Workbook
Name \0: #REF!
Name _1: #REF!
Name _2: #REF!
Name _A655555: #REF!
Name _CFR1: #REF!
Name _cia1: #REF!
Name _XL250: #REF!
Name A: #REF!
Name ADM: [1]!ADM
Name ADM: [1]!ADM
Name ADM: [1]!ADM
Name ADM: [1]!ADM
Name ADM: [1]!ADM
Name ADM_: [1]!ADM
Name ADM_: [1]!ADM
Name ADM_: [1]!ADM
Name ADM_: [1]!ADM
Name ADM_: [1]!ADM
Name AI: #REF!
Name Air: #REF!
Name AP: '[2]TARIFA no aforos'!$C$12
Name Bancos: [3]Fx!$C$1:$C$23
Name CBL: #REF!
Name CCS: #REF!
Name CDT_p: [4]CDT!$C$3
Name CFR: #REF!
Name cia: #REF!
Name COM: #REF!
Name CRT: #REF!
Name CRT___CTEp___CDTp___CMRv: #REF!
Name CRT_aislados: '[4]COSTOS AJUSTADOS'!$C$13
Name CRT_costas: #REF!
Name CTE_p: [4]CTE!$C$5
Name Denominador: #REF!
Name dg: [1]!ADM
Name dg: [1]!ADM
Name dg: [1]!ADM
Name dg: [1]!ADM
Name dg: [1]!ADM
Name DIAS: [5]CONTRA!#REF!
Name Fmerc: #REF!
Name FPS: #REF!
Name InformacionGeneral: [1]!InformacionGeneral
Name InformacionGeneral: [1]!InformacionGeneral
Name InformacionGeneral: [1]!InformacionGeneral
Name InformacionGeneral: [1]!InformacionGeneral
Name InformacionGeneral: [1]!InformacionGeneral
Name INTFIN: #REF!
Name INV: [1]!INV
Name INV: [1]!INV
Name INV: [1]!INV
Name INV: [1]!INV
Name INV: [1]!INV
Name K: #REF!
Name N: '[4]COSTOS AJUSTADOS'!#REF!
Name Na: '[2]TARIFA no aforos'!$C$39
Name nfc: '[4]COSTOS AJUSTADOS'!#REF!
Name OYM: [1]!OYM
Name OYM: [1]!OYM
Name OYM: [1]!OYM

Sheet Recaudo EAAB Reciprocidad
B2: OPORTUNO | C2: ASE | D2: VALOR 1° Q | E2: NUMERO REG. 1°Q | F2: VALOR 2° Q | G2: NUMERO REG. 2°Q
C3: 1 | D3: 0 | E3: 0 | F3: 0 | G3: 0
C4: 2 | D4: 0 | E4: 0 | F4: 24173030 | G4: 330
C5: 3 | D5: 0 | E5: 0 | F5: 0 | G5: 0
C6: 4 | D6: 0 | E6: 0 | F6: 15822520 | G6: 133
C7: 5 | D7: 0 | E7: 0 | F7: 0 | G7: 0
C8: X
D9: 0 | E9: 0 | F9: 39995550 | G9: 463
C11: ASE | D11: VALOR 1° Q | E11: NUMERO REG. 1°Q | F11: VALOR 2° Q | G11: NUMERO REG. 2°Q
B12: EXTEMP. | C12: 1 | D12: 0 | E12: 0 | F12: 0 | G12: 0
C13: 2 | D13: 0 | E13: 0 | F13: 58730 | G13: 1
C14: 3 | D14: 0 | E14: 0 | F14: 0 | G14: 0
C15: 4 | D15: 0 | E15: 0 | F15: 63120 | G15: 1
C16: 5 | D16: 0 | E16: 0 | F16: 0 | G16: 0
C17: X
D18: 0 | E18: 0 | F18: 121850 | G18: 2
C20: ASE | D20: VALOR 1° Q | E20: NUMERO REG. 1°Q | F20: VALOR 2° Q | G20: NUMERO REG. 2°Q | I20: VALOR TOTAL MES | J20: NUMERO REGISTROS MES
B21: TOTAL | C21: 1 | D21: 0 | E21: 0 | F21: 0 | G21: 0 | I21: 0 | J21: 0
C22: 2 | D22: 0 | E22: 0 | F22: 24231760 | G22: 331 | I22: 0 | J22: 0
C23: 3 | D23: 0 | E23: 0 | F23: 0 | G23: 0 | I23: 0 | J23: 0
C24: 4 | D24: 0 | E24: 0 | F24: 15885640 | G24: 134 | I24: 0 | J24: 0
C25: 5 | D25: 0 | E25: 0 | F25: 0 | G25: 0 | I25: 0 | J25: 0
C26: X | I26: 0 | J26: 0
D27: 0 | E27: 0 | F27: 40117400 | G27: 465 | I27: 0 | J27: 0
B31: OPORTUNO | D31: =D9=SUM(D3:D8) -> TRUE | E31: =E9=SUM(E3:E8) -> TRUE | F31: =F9=SUM(F3:F8) -> TRUE | G31: =G9=SUM(G3:G8) -> TRUE
B33: EXTEMP. | D33: =D18=SUM(D12:D17) -> TRUE | E33: =E18=SUM(E12:E17) -> TRUE | F33: =F18=SUM(F12:F17) -> TRUE | G33: =G18=SUM(G12:G17) -> TRUE
B35: TOTAL | D35: =D27=SUM(D21:D26) -> TRUE | E35: =E27=SUM(E21:E26) -> TRUE | F35: =F27=SUM(F21:F26) -> TRUE | G35: =G27=SUM(G21:G26) -> TRUE | I35: =I27=SUM(I21:I26) -> TRUE | J35: =J27=SUM(J21:J26) -> TRUE
E69: =C69-G17 -> 0

Sheet Recaudo ENEL
B2: OPORTUNO | C2: ASE | D2: VALOR 1° Q | E2: NUMERO REG. 1°Q | F2: VALOR 2° Q | G2: NUMERO REG. 2°Q
C3: 1 | D3: 0 | E3: 0 | F3: 16467129562 | G3: 273797
C4: 2 | D4: 0 | E4: 0 | F4: 19037496395 | G4: 406215
C5: 3 | D5: 0 | E5: 0 | F5: 13952517350 | G5: 269668
C6: 4 | D6: 0 | E6: 0 | F6: 6579568126 | G6: 120492
C7: 5 | D7: 0 | E7: 0 | F7: 11684535987 | G7: 242618
C8: X
D9: 0 | E9: 0 | F9: 67721247420 | G9: 1312790
C11: ASE | D11: VALOR 1° Q | E11: NUMERO REG. 1°Q | F11: VALOR 2° Q | G11: NUMERO REG. 2°Q
B12: EXTEMP. | C12: 1 | D12: 0 | E12: 0 | F12: 193558629 | G12: 3299
C13: 2 | D13: 0 | E13: 0 | F13: 53213747 | G13: 918
C14: 3 | D14: 0 | E14: 0 | F14: 74684472 | G14: 1206
C15: 4 | D15: 0 | E15: 0 | F15: 60823284 | G15: 1331
C16: 5 | D16: 0 | E16: 0 | F16: 41090640 | G16: 830
C17: X
D18: 0 | E18: 0 | F18: 423370772 | G18: 7584
C20: ASE | D20: VALOR 1° Q | E20: NUMERO REG. 1°Q | F20: VALOR 2° Q | G20: NUMERO REG. 2°Q | I20: VALOR TOTAL MES | J20: NUMERO REGISTROS MES
B21: TOTAL | C21: 1 | D21: 0 | E21: 0 | F21: 16660688191 | G21: 277096 | I21: 0 | J21: 0
C22: 2 | D22: 0 | E22: 0 | F22: 19090710142 | G22: 407133 | I22: 0 | J22: 0
C23: 3 | D23: 0 | E23: 0 | F23: 14027201822 | G23: 270874 | I23: 0 | J23: 0
C24: 4 | D24: 0 | E24: 0 | F24: 6640391410 | G24: 121823 | I24: 0 | J24: 0
C25: 5 | D25: 0 | E25: 0 | F25: 11725626627 | G25: 243448 | I25: 0 | J25: 0
C26: X | I26: 0 | J26: 0
D27: 0 | E27: 0 | F27: 68144618192 | G27: 1320374 | I27: 0 | J27: 0
B31: OPORTUNO | D31: =D9=SUM(D3:D8) -> TRUE | E31: =E9=SUM(E3:E8) -> TRUE | F31: =F9=SUM(F3:F8) -> TRUE | G31: =G9=SUM(G3:G8) -> TRUE
B33: EXTEMP. | D33: =D18=SUM(D12:D17) -> TRUE | E33: =E18=SUM(E12:E17) -> TRUE | F33: =F18=SUM(F12:F17) -> TRUE | G33: =G18=SUM(G12:G17) -> TRUE
B35: TOTAL | D35: =D27=SUM(D21:D26) -> TRUE | E35: =E27=SUM(E21:E26) -> TRUE | F35: =F27=SUM(F21:F26) -> TRUE | G35: =G27=SUM(G21:G26) -> TRUE | I35: =I27=SUM(I21:I26) -> TRUE | J35: =J27=SUM(J21:J26) -> TRUE
E69: =C69-G17 -> 0

Sheet Recaudo ENERBIT
B2: OPORTUNO | C2: ASE | D2: VALOR 1° Q | E2: NUMERO REG. 1°Q | F2: VALOR 2° Q | G2: NUMERO REG. 2°Q
C3: 1 | D3: 0 | E3: 0 | F3: 0 | G3: 0
C4: 2 | D4: 0 | E4: 0 | F4: 0 | G4: 0
C5: 3 | D5: 0 | E5: 0 | F5: 0 | G5: 0
C6: 4 | D6: 0 | E6: 0 | F6: 0 | G6: 0
C7: 5 | D7: 0 | E7: 0 | F7: 28645323 | G7: 545
C8: X
D9: 0 | E9: 0 | F9: 28645323 | G9: 545
C11: ASE | D11: VALOR 1° Q | E11: NUMERO REG. 1°Q | F11: VALOR 2° Q | G11: NUMERO REG. 2°Q
B12: EXTEMP. | C12: 1 | D12: 0 | E12: 0 | F12: 0 | G12: 0
C13: 2 | D13: 0 | E13: 0 | F13: 0 | G13: 0
C14: 3 | D14: 0 | E14: 0 | F14: 0 | G14: 0
C15: 4 | D15: 0 | E15: 0 | F15: 0 | G15: 0
C16: 5 | D16: 0 | E16: 0 | F16: 0 | G16: 0
C17: X
D18: 0 | E18: 0 | F18: 0 | G18: 0
C20: ASE | D20: VALOR 1° Q | E20: NUMERO REG. 1°Q | F20: VALOR 2° Q | G20: NUMERO REG. 2°Q | I20: VALOR TOTAL MES | J20: NUMERO REGISTROS MES
B21: TOTAL | C21: 1 | D21: 0 | E21: 0 | F21: 0 | G21: 0 | I21: 0 | J21: 0
C22: 2 | D22: 0 | E22: 0 | F22: 0 | G22: 0 | I22: 0 | J22: 0
C23: 3 | D23: 0 | E23: 0 | F23: 0 | G23: 0 | I23: 0 | J23: 0
C24: 4 | D24: 0 | E24: 0 | F24: 0 | G24: 0 | I24: 0 | J24: 0
C25: 5 | D25: 0 | E25: 0 | F25: 28645323 | G25: 545 | I25: 0 | J25: 0
C26: X | I26: 0 | J26: 0
D27: 0 | E27: 0 | F27: 28645323 | G27: 545 | I27: 0 | J27: 0
B31: OPORTUNO | D31: =D9=SUM(D3:D8) -> TRUE | E31: =E9=SUM(E3:E8) -> TRUE | F31: =F9=SUM(F3:F8) -> TRUE | G31: =G9=SUM(G3:G8) -> TRUE
B33: EXTEMP. | D33: =D18=SUM(D12:D17) -> TRUE | E33: =E18=SUM(E12:E17) -> TRUE | F33: =F18=SUM(F12:F17) -> TRUE | G33: =G18=SUM(G12:G17) -> TRUE
B35: TOTAL | D35: =D27=SUM(D21:D26) -> TRUE | E35: =E27=SUM(E21:E26) -> TRUE | F35: =F27=SUM(F21:F26) -> TRUE | G35: =G27=SUM(G21:G26) -> TRUE | I35: =I27=SUM(I21:I26) -> TRUE | J35: =J27=SUM(J21:J26) -> TRUE
E69: =C69-G17 -> 0

Sheet Recaudo EAAB + Ciud Limp
B2: Ciudad Limpia - Prestador | C2: ASE | D2: VALOR 1° Q | E2: NUMERO REG. 1°Q | F2: VALOR 2° Q | G2: NUMERO REG. 2°Q
C3: 1 | D3: 0 | E3: 0 | F3: 0 | G3: 0
C4: 2 | D4: 0 | E4: 0 | F4: 0 | G4: 0
C5: 3 | D5: 0 | E5: 0 | F5: 0 | G5: 0
C6: 4 | D6: 0 | E6: 0 | F6: 0 | G6: 0
C7: 5 | D7: 0 | E7: 0 | F7: 0 | G7: 0
C8: X
D9: 0 | E9: 0 | F9: 0 | G9: 0
C11: ASE | D11: VALOR 1° Q | E11: NUMERO REG. 1°Q | F11: VALOR 2° Q | G11: NUMERO REG. 2°Q
B12: EAAB - Prestador | C12: 1 | D12: 0 | E12: 0 | F12: 0 | G12: 0
C13: 2 | D13: 0 | E13: 0 | F13: 0 | G13: 0
C14: 3 | D14: 0 | E14: 0 | F14: 0 | G14: 0
C15: 4 | D15: 0 | E15: 0 | F15: 0 | G15: 0
C16: 5 | D16: 0 | E16: 0 | F16: 0 | G16: 0
C17: X
D18: 0 | E18: 0 | F18: 0 | G18: 0
C20: ASE | D20: VALOR 1° Q | E20: NUMERO REG. 1°Q | F20: VALOR 2° Q | G20: NUMERO REG. 2°Q | I20: VALOR TOTAL MES | J20: NUMERO REGISTROS MES
B21: TOTAL | C21: 1 | D21: 0 | E21: 0 | F21: 0 | G21: 0 | I21: 0 | J21: 0
C22: 2 | D22: 0 | E22: 0 | F22: 0 | G22: 0 | I22: 0 | J22: 0
C23: 3 | D23: 0 | E23: 0 | F23: 0 | G23: 0 | I23: 0 | J23: 0
C24: 4 | D24: 0 | E24: 0 | F24: 0 | G24: 0 | I24: 0 | J24: 0
C25: 5 | D25: 0 | E25: 0 | F25: 0 | G25: 0 | I25: 0 | J25: 0
C26: X | I26: 0 | J26: 0
D27: 0 | E27: 0 | F27: 0 | G27: 0 | I27: 0 | J27: 0
B31: OPORTUNO | D31: =D9=SUM(D3:D8) -> TRUE | E31: =E9=SUM(E3:E8) -> TRUE | F31: =F9=SUM(F3:F8) -> TRUE | G31: =G9=SUM(G3:G8) -> TRUE
B33: EXTEMP. | D33: =D18=SUM(D12:D17) -> TRUE | E33: =E18=SUM(E12:E17) -> TRUE | F33: =F18=SUM(F12:F17) -> TRUE | G33: =G18=SUM(G12:G17) -> TRUE
B35: TOTAL | D35: =D27=SUM(D21:D26) -> TRUE | E35: =E27=SUM(E21:E26) -> TRUE | F35: =F27=SUM(F21:F26) -> TRUE | G35: =G27=SUM(G21:G26) -> TRUE | I35: =I27=SUM(I21:I26) -> TRUE | J35: =J27=SUM(J21:J26) -> TRUE

Sheet Recaudo Directa Occidente
B2: OPORTUNO | C2: ASE | D2: VALOR 1° Q | E2: NUMERO REG. 1°Q | F2: VALOR 2° Q | G2: NUMERO REG. 2°Q
C3: 1 | D3: 0 | E3: 0 | F3: 644977472 | G3: 2386
C4: 2 | D4: 0 | E4: 0 | F4: 1127716979 | G4: 9079
C5: 3 | D5: 0 | E5: 0 | F5: 858037220 | G5: 2287
C6: 4 | D6: 0 | E6: 0 | F6: 362907055 | G6: 2213
C7: 5 | D7: 0 | E7: 0 | F7: 271576031 | G7: 1257
C8: X | D8: 0 | E8: 0 | F8: 0 | G8: 0
D9: 0 | E9: 0 | F9: 3265214757 | G9: 17222
C11: ASE | D11: VALOR 1° Q | E11: NUMERO REG. 1°Q | F11: VALOR 2° Q | G11: NUMERO REG. 2°Q
B12: EXTEMP. | C12: 1 | D12: 0 | E12: 0 | F12: 160336245 | G12: 481
C13: 2 | D13: 0 | E13: 0 | F13: 298229199 | G13: 665
C14: 3 | D14: 0 | E14: 0 | F14: 387133299 | G14: 251
C15: 4 | D15: 0 | E15: 0 | F15: 123732462 | G15: 270
C16: 5 | D16: 0 | E16: 0 | F16: 49923090 | G16: 176
C17: X | D17: 0 | E17: 0 | F17: 0 | G17: 0
D18: 0 | E18: 0 | F18: 1019354295 | G18: 1843
C20: ASE | D20: VALOR 1° Q | E20: NUMERO REG. 1°Q | F20: VALOR 2° Q | G20: NUMERO REG. 2°Q | I20: VALOR TOTAL MES | J20: NUMERO REGISTROS MES
B21: TOTAL | C21: 1 | D21: 0 | E21: 0 | F21: 805313717 | G21: 2867 | I21: 0 | J21: 0
C22: 2 | D22: 0 | E22: 0 | F22: 1425946178 | G22: 9744 | I22: 0 | J22: 0
C23: 3 | D23: 0 | E23: 0 | F23: 1245170519 | G23: 2538 | I23: 0 | J23: 0
C24: 4 | D24: 0 | E24: 0 | F24: 486639517 | G24: 2483 | I24: 0 | J24: 0
C25: 5 | D25: 0 | E25: 0 | F25: 321499121 | G25: 1433 | I25: 0 | J25: 0
C26: X | D26: 0 | E26: 0 | F26: 0 | G26: 0 | I26: 0 | J26: 0
D27: 0 | E27: 0 | F27: 4284569052 | G27: 19065 | I27: 0 | J27: 0
B31: OPORTUNO | D31: =D9=SUM(D3:D8) -> TRUE | E31: =E9=SUM(E3:E8) -> TRUE | F31: =F9=SUM(F3:F8) -> TRUE | G31: =G9=SUM(G3:G8) -> TRUE
B33: EXTEMP. | D33: =D18=SUM(D12:D17) -> TRUE | E33: =E18=SUM(E12:E17) -> TRUE | F33: =F18=SUM(F12:F17) -> TRUE | G33: =G18=SUM(G12:G17) -> TRUE
B35: TOTAL | D35: =D27=SUM(D21:D26) -> TRUE | E35: =E27=SUM(E21:E26) -> TRUE | F35: =F27=SUM(F21:F26) -> TRUE | G35: =G27=SUM(G21:G26) -> TRUE | I35: =I27=SUM(I21:I26) -> TRUE | J35: =J27=SUM(J21:J26) -> TRUE
E69: =C69-G17 -> 0

Sheet REPORTE RECAUDO x BANCO
C1: ENEL | D1: CIUDAD LIMPIA | E1: EAB | F1: NUEVO ESQUEMA | G1: ENERBIT | H1: OCCIDENTE | I1: Total
B2: 1-APLICADOS A FACTURACION | C2: =C13+C23+C32+C41+C51 -> 6.7949268e+10 | D2: =D13+D23+D32+D41+D51 -> 0 | E2: =E13+E23+E32+E41+E51 -> 0 | F2: =F13+F23+F32+F41+F51 -> 17028090 | G2: =G13+G23+G32+G41+G51 -> 26864220 | H2: =H13+H23+H32+H41+H51 -> 4.1068552e+09 | I2: =SUM(C2:H2) -> 7.2100015e+10
B3: 2-SALDOS A FAVOR GENERADOS | C3: =C14+C24+C33+C42+C52 -> 2.3671717e+08 | D3: =D14+D24+D33+D42+D52 -> 0 | E3: =E14+E24+E33+E42+E52 -> 0 | F3: =F14+F24+F33+F42+F52 -> 23089310 | G3: =G14+G24+G33+G42+G52 -> 1781103 | H3: =H14+H24+H33+H42+H52 -> 1.3687274e+08 | I3: =SUM(C3:H3) -> 3.9846032e+08
B4: 3-APLICADOS A FINANCIACIONES NUEVAS | C4: =C15+C25+C34+C43+C53 -> 0 | D4: =D15+D25+D34+D43+D53 -> 0 | E4: =E15+E25+E34+E43+E53 -> 0 | F4: =F15+F25+F34+F43+F53 -> 0 | G4: =G15+G25+G34+G43+G53 -> 0 | H4: =H15+H25+H34+H43+H53 -> 40841134 | I4: =SUM(C4:H4) -> 40841134
B5: 7-APLICADOS A RECIBOS SERVICIOS ESPECIALES | C5: =C16+C26+C35+C44+C54 -> 0 | D5: =D16+D26+D35+D44+D54 -> 0 | E5: =E16+E26+E35+E44+E54 -> 0 | F5: =F16+F26+F35+F44+F54 -> 0 | G5: =G16+G26+G35+G44+G54 -> 0 | H5: =H16+H26+H35+H44+H54 -> 0 | I5: =SUM(C5:H5) -> 0
B6: Total | C6: =SUM(C2:C5) -> 68185984867 | D6: =SUM(D2:D5) -> 0 | E6: =SUM(E2:E5) -> 0 | F6: =SUM(F2:F5) -> 40117400 | G6: =SUM(G2:G5) -> 28645323 | H6: =SUM(H2:H5) -> 4.2845691e+09 | I6: =SUM(I2:I5) -> 7.2539317e+10
C7: =C6=(C17+C27+C36+C45+C55) -> TRUE | D7: =D6=(D17+D27+D36+D45+D55) -> TRUE | E7: =E6=(E17+E27+E36+E45+E55) -> TRUE | F7: =F6=(F17+F27+F36+F45+F55) -> TRUE | H7: =H6=(H17+H27+H36+H45+H55) -> TRUE | I7: =I6=(I17+I27+I36+I45+I55) -> TRUE
B10: ASE 1
B11: Resumen Recaudo Aplicado Por Servicio
C12: ENEL | D12: CIUDAD LIMPIA | E12: EAB | F12: NUEVO ESQUEMA | G12: ENERBIT | H12: OCCIDENTE | I12: Total
B13: 1-APLICADOS A FACTURACION | C13: 1.6577116e+10 | D13: 0 | E13: 0 | F13: 0 | G13: 0 | H13: 7.7622223e+08 | I13: =SUM(C13:H13) -> 1.7353338e+10 | J13: =SUM(C13:H13)=I13 -> TRUE
B14: 2-SALDOS A FAVOR GENERADOS | C14: 83572548 | D14: 0 | E14: 0 | F14: 0 | G14: 0 | H14: 17358484 | I14: =SUM(C14:H14) -> 1.0093103e+08 | J14: =SUM(C14:H14)=I14 -> TRUE
B15: 3-APLICADOS A FINANCIACIONES NUEVAS | C15: 0 | D15: 0 | E15: 0 | F15: 0 | G15: 0 | H15: 11733000 | I15: =SUM(C15:H15) -> 11733000 | J15: =SUM(C15:H15)=I15 -> TRUE
B16: 7-APLICADOS A RECIBOS SERVICIOS ESPECIALES | C16: 0 | D16: 0 | E16: 0 | F16: 0 | G16: 0 | H16: 0 | I16: =SUM(C16:H16) -> 0 | J16: =SUM(C16:H16)=I16 -> TRUE
B17: Total | C17: =SUM(C13:C16) -> 16660688191 | D17: =SUM(D13:D16) -> 0 | E17: =SUM(E13:E16) -> 0 | F17: =SUM(F13:F16) -> 0 | G17: =SUM(G13:G16) -> 0 | H17: =SUM(H13:H16) -> 805313717 | I17: =SUM(I13:I16) -> 17466001908 | J17: =SUM(C17:H17)=I17 -> TRUE
B20: ASE 2
B21: Resumen Recaudo Aplicado Por Servicio
C22: ENEL | D22: CIUDAD LIMPIA | E22: EAB | F22: NUEVO ESQUEMA | G22: ENERBIT | H22: OCCIDENTE | I22: Total
B23: 1-APLICADOS A FACTURACION | C23: 19047798453 | D23: 0 | E23: 0 | F23: 11411240 | G23: 0 | H23: 1346513069 | I23: =SUM(C23:H23) -> 20405722762 | J23: =SUM(C23:H23)=I23 -> TRUE
B24: 2-SALDOS A FAVOR GENERADOS | C24: 44281124 | D24: 0 | E24: 0 | F24: 12820520 | G24: 0 | H24: 79433109 | I24: =SUM(C24:H24) -> 136534753 | J24: =SUM(C24:H24)=I24 -> TRUE
B25: 3-APLICADOS A FINANCIACIONES NUEVAS | C25: 0 | D25: 0 | E25: 0 | F25: 0 | G25: 0 | H25: 0 | I25: =SUM(C25:H25) -> 0 | J25: =SUM(C25:H25)=I25 -> TRUE
B26: 7-APLICADOS A RECIBOS SERVICIOS ESPECIALES | C26: 0 | D26: 0 | E26: 0 | F26: 0 | G26: 0 | H26: 0 | I26: =SUM(C26:H26) -> 0 | J26: =SUM(C26:H26)=I26 -> TRUE
B27: Total | C27: =SUM(C23:C26) -> 19092079577 | D27: =SUM(D23:D26) -> 0 | E27: =SUM(E23:E26) -> 0 | F27: =SUM(F23:F26) -> 24231760 | G27: =SUM(G23:G26) -> 0 | H27: =SUM(H23:H26) -> 1425946178 | I27: =SUM(I23:I26) -> 20542257515 | J27: =SUM(C27:H27)=I27 -> TRUE
B29: ASE 3
B30: Resumen Recaudo Aplicado Por Servicio
C31: ENEL | D31: CIUDAD LIMPIA | E31: EAB | F31: NUEVO ESQUEMA | G31: ENERBIT | H31: OCCIDENTE | I31: Total
B32: 1-APLICADOS A FACTURACION | C32: 14010202412 | D32: 0 | E32: 0 | F32: 0 | G32: 0 | H32: 1.2278438e+09 | I32: =SUM(C32:H32) -> 1.5238046e+10 | J32: =SUM(C32:H32)=I32 -> TRUE
B33: 2-SALDOS A FAVOR GENERADOS | C33: 44039530 | D33: 0 | E33: 0 | F33: 0 | G33: 0 | H33: 14844503 | I33: =SUM(C33:H33) -> 58884033 | J33: =SUM(C33:H33)=I33 -> TRUE
B34: 3-APLICADOS A FINANCIACIONES NUEVAS | C34: 0 | D34: 0 | E34: 0 | F34: 0 | G34: 0 | H34: 2482198.7 | I34: =SUM(C34:H34) -> 2482198.7 | J34: =SUM(C34:H34)=I34 -> TRUE
B35: 7-APLICADOS A RECIBOS SERVICIOS ESPECIALES | C35: 0 | D35: 0 | E35: 0 | F35: 0 | G35: 0 | H35: 0 | I35: =SUM(C35:H35) -> 0 | J35: =SUM(C35:H35)=I35 -> TRUE
B36: Total | C36: =SUM(C32:C35) -> 14054241942 | D36: =SUM(D32:D35) -> 0 | E36: =SUM(E32:E35) -> 0 | F36: =SUM(F32:F35) -> 0 | G36: =SUM(G32:G35) -> 0 | H36: =SUM(H32:H35) -> 1245170519 | I36: =SUM(I32:I35) -> 15299412461 | J36: =SUM(C36:H36)=I36 -> TRUE
B38: ASE 4
B39: Resumen Recaudo Aplicado Por Servicio
C40: ENEL | D40: CIUDAD LIMPIA | E40: EAB | F40: NUEVO ESQUEMA | G40: ENERBIT | H40: OCCIDENTE | I40: Total
B41: 1-APLICADOS A FACTURACION | C41: 6603996268 | D41: 0 | E41: 0 | F41: 5616850 | G41: 0 | H41: 4.4604021e+08 | I41: =SUM(C41:H41) -> 7.0556533e+09 | J41: =SUM(C41:H41)=I41 -> TRUE
B42: 2-SALDOS A FAVOR GENERADOS | C42: 48826052 | D42: 0 | E42: 0 | F42: 10268790 | G42: 0 | H42: 14631795 | I42: =SUM(C42:H42) -> 73726637 | J42: =SUM(C42:H42)=I42 -> TRUE
B43: 3-APLICADOS A FINANCIACIONES NUEVAS | C43: 0 | D43: 0 | E43: 0 | F43: 0 | G43: 0 | H43: 25967508 | I43: =SUM(C43:H43) -> 25967508 | J43: =SUM(C43:H43)=I43 -> TRUE
B44: 7-APLICADOS A RECIBOS SERVICIOS ESPECIALES | C44: 0 | D44: 0 | E44: 0 | F44: 0 | G44: 0 | H44: 0 | I44: =SUM(C44:H44) -> 0 | J44: =SUM(C44:H44)=I44 -> TRUE
B45: Total | C45: =SUM(C41:C44) -> 6652822320 | D45: =SUM(D41:D44) -> 0 | E45: =SUM(E41:E44) -> 0 | F45: =SUM(F41:F44) -> 15885640 | G45: =SUM(G41:G44) -> 0 | H45: =SUM(H41:H44) -> 4.8663952e+08 | I45: =SUM(I41:I44) -> 7155347477 | J45: =SUM(C45:H45)=I45 -> TRUE
B48: ASE 5
B49: Resumen Recaudo Aplicado Por Servicio
C50: ENEL | D50: CIUDAD LIMPIA | E50: EAB | F50: NUEVO ESQUEMA | G50: ENERBIT | H50: OCCIDENTE | I50: Total
B51: 1-APLICADOS A FACTURACION | C51: 11710154922 | D51: 0 | E51: 0 | F51: 0 | G51: 26864220 | H51: 3.1023585e+08 | I51: =SUM(C51:H51) -> 1.2047255e+10 | J51: =SUM(C51:H51)=I51 -> TRUE
B52: 2-SALDOS A FAVOR GENERADOS | C52: 15997915 | D52: 0 | E52: 0 | F52: 0 | G52: 1781103 | H52: 10604848 | I52: =SUM(C52:H52) -> 28383866 | J52: =SUM(C52:H52)=I52 -> TRUE
B53: 3-APLICADOS A FINANCIACIONES NUEVAS | C53: 0 | D53: 0 | E53: 0 | F53: 0 | G53: 0 | H53: 658426.44 | I53: =SUM(C53:H53) -> 658426.44 | J53: =SUM(C53:H53)=I53 -> TRUE
B54: 7-APLICADOS A RECIBOS SERVICIOS ESPECIALES | C54: 0 | D54: 0 | E54: 0 | F54: 0 | G54: 0 | H54: 0 | I54: =SUM(C54:H54) -> 0 | J54: =SUM(C54:H54)=I54 -> TRUE
B55: Total | C55: =SUM(C51:C54) -> 11726152837 | D55: =SUM(D51:D54) -> 0 | E55: =SUM(E51:E54) -> 0 | F55: =SUM(F51:F54) -> 0 | G55: =SUM(G51:G54) -> 28645323 | H55: =SUM(H51:H54) -> 321499121 | I55: =SUM(I51:I54) -> 12076297281 | J55: =SUM(C55:H55)=I55 -> TRUE
B59: QUINCENA | C59: 2 | D59: OJO/// DILIGENCIAR
B62: Recaudo ENEL - ASE 1 | C62: =IF($C$59=1,'Recaudo ENEL'!D21,'Recaudo ENEL'!F21) -> 16660688191 | D62: =C17=C62 -> TRUE | E62: =C17-C62 -> 0
B63: Recaudo ENERBIT - ASE 1 | C63: =IF($C$59=1,'Recaudo ENERBIT'!D21,'Recaudo ENERBIT'!F21) -> 0 | D63: =G17=C63 -> TRUE | E63: =G17-C63 -> 0
B64: Recaudo Reciprocidad EAAB - ASE 2 | C64: =IF($C$59=1,'Recaudo EAAB Reciprocidad'!D22,'Recaudo EAAB Reciprocidad'!F22) -> 24231760 | D64: =F27=C64 -> TRUE | E64: =F27-C64 -> 0
B65: Recaudo ENEL - ASE 2 | C65: =IF($C$59=1,'Recaudo ENEL'!D22,'Recaudo ENEL'!F22) -> 19090710142 | D65: =C27=C65 -> FALSE | E65: =C27-C65 -> 1369435
B66: Recaudo ENERBIT - ASE 2 | C66: =IF($C$59=1,'Recaudo ENERBIT'!D22,'Recaudo ENERBIT'!F22) -> 0 | D66: =G27=C66 -> TRUE | E66: =G27-C66 -> 0
B67: Recaudo ENEL - ASE 3 | C67: =IF($C$59=1,'Recaudo ENEL'!D23,'Recaudo ENEL'!F23) -> 14027201822 | D67: =C36=C67 -> FALSE | E67: =C36-C67 -> 27040120
B68: Recaudo ENERBIT - ASE 3 | C68: =IF($C$59=1,'Recaudo ENERBIT'!D23,'Recaudo ENERBIT'!F23) -> 0 | D68: =G36=C68 -> TRUE | E68: =G36-C68 -> 0
B69: Recaudo Reciprocidad EAAB - ASE 4 | C69: =IF($C$59=1,'Recaudo EAAB Reciprocidad'!D24,'Recaudo EAAB Reciprocidad'!F24) -> 15885640 | D69: =F45=C69 -> TRUE | E69: =F45-C69 -> 0
B70: Recaudo ENEL - ASE 4 | C70: =IF($C$59=1,'Recaudo ENEL'!D24,'Recaudo ENEL'!F24) -> 6640391410 | D70: =C45=C70 -> FALSE | E70: =C45-C70 -> 12430910
B71: Recaudo ENERBIT - ASE 4 | C71: =IF($C$59=1,'Recaudo ENERBIT'!D24,'Recaudo ENERBIT'!F24) -> 0 | D71: =G45=C71 -> TRUE | E71: =G45-C71 -> 0
B72: Recaudo ENEL - ASE 5 | C72: =IF($C$59=1,'Recaudo ENEL'!D25,'Recaudo ENEL'!F25) -> 11725626627 | D72: =C55=C72 -> FALSE | E72: =C55-C72 -> 526210
B73: Recaudo ENERBIT - ASE 5 | C73: =IF($C$59=1,'Recaudo ENERBIT'!D25,'Recaudo ENERBIT'!F25) -> 28645323 | D73: =G55=C73 -> TRUE | E73: =G55-C73 -> 0
B75: Recaudo Banco Occidente ASE 1 | C75: =IF($C$59=1,'Recaudo Directa Occidente'!D21,'Recaudo Directa Occidente'!F21) -> 805313717 | D75: =C75=H17 -> TRUE | E75: =C75-H17 -> 0
B76: Recaudo Banco Occidente ASE 2 | C76: =IF($C$59=1,'Recaudo Directa Occidente'!D22,'Recaudo Directa Occidente'!F22) -> 1425946178 | D76: =C76=H27 -> TRUE | E76: =C76-H27 -> 0
B77: Recaudo Banco Occidente ASE 3 | C77: =IF($C$59=1,'Recaudo Directa Occidente'!D23,'Recaudo Directa Occidente'!F23) -> 1245170519 | D77: =C77=H36 -> TRUE | E77: =C77-H36 -> 0
B78: Recaudo Banco Occidente ASE 4 | C78: =IF($C$59=1,'Recaudo Directa Occidente'!D24,'Recaudo Directa Occidente'!F24) -> 486639517 | D78: =C78=H45 -> TRUE | E78: =C78-H45 -> 0
B79: Recaudo Banco Occidente ASE 5 | C79: =IF($C$59=1,'Recaudo Directa Occidente'!D25,'Recaudo Directa Occidente'!F25) -> 321499121 | D79: =C79=H55 -> TRUE | E79: =C79-H55 -> 0

Sheet ANT EXT-REV
C1: ASE 1 | E1: ASE 2 | G1: ASE 3 | I1: ASE 4 | K1: ASE 5 | M1: TOTAL
C2: REPORTE 3 | D2: REPORTE 4 | E2: REPORTE 3 | F2: REPORTE 4 | G2: REPORTE 3 | H2: REPORTE 4 | I2: REPORTE 3 | J2: REPORTE 4 | K2: REPORTE 3 | L2: REPORTE 4 | M2: REPORTE 3 | N2: REPORTE 4
B3: APLICADO | C3: =C11+C19+C27+C35+C43 -> 0 | D3: =D11+D19+D27+D35+D43 -> 0 | E3: =E11+E19+E27+E35+E43 -> 0 | F3: =F11+F19+F27+F35+F43 -> 0 | G3: =G11+G19+G27+G35+G43 -> 0 | H3: =H11+H19+H27+H35+H43 -> 0 | I3: =I11+I19+I27+I35+I43 -> 0 | J3: =J11+J19+J27+J35+J43 -> 0 | ... L3: =L11+L19+L27+L35+L43 -> 0 | M3: =C3+E3+G3+I3+K3 -> 0 | N3: =D3+F3+H3+J3+L3 -> 0 | P3: =N3=(-VALIDACION_TOTAL!M9) -> FALSE
B4: ANTICIPOS | C4: =C12+C20+C28+C36+C44 -> 0 | D4: =D12+D20+D28+D36+D44 -> 0 | E4: =E12+E20+E28+E36+E44 -> 0 | F4: =F12+F20+F28+F36+F44 -> 0 | G4: =G12+G20+G28+G36+G44 -> 0 | H4: =H12+H20+H28+H36+H44 -> 0 | I4: =I12+I20+I28+I36+I44 -> 0 | J4: =J12+J20+J28+J36+J44 -> 0 | ... L4: =L12+L20+L28+L36+L44 -> 0 | M4: =C4+E4+G4+I4+K4 -> 0 | N4: =D4+F4+H4+J4+L4 -> 0 | P4: =N4=(-'CONSOLIDADO_TOTAL RECAUDO'!L131) -> TRUE
B5: TOTAL | C5: =SUM(C3:C4) -> 0 | D5: =SUM(D3:D4) -> 0 | E5: =SUM(E3:E4) -> 0 | F5: =SUM(F3:F4) -> 0 | G5: =SUM(G3:G4) -> 0 | H5: =SUM(H3:H4) -> 0 | I5: =SUM(I3:I4) -> 0 | J5: =SUM(J3:J4) -> 0 | ... N5: =SUM(N3:N4) -> 0
C6: =C5=(C13+C21+C29+C37+C45) -> TRUE | D6: =D5=(D13+D21+D29+D37+D45) -> TRUE | E6: =E5=(E13+E21+E29+E37+E45) -> TRUE | F6: =F5=(F13+F21+F29+F37+F45) -> TRUE | G6: =G5=(G13+G21+G29+G37+G45) -> TRUE | H6: =H5=(H13+H21+H29+H37+H45) -> TRUE | I6: =I5=(I13+I21+I29+I37+I45) -> TRUE | J6: =J5=(J13+J21+J29+J37+J45) -> TRUE | ... N6: =N5=(N13+N21+N29+N37+N45) -> TRUE
B8: BANCO DE OCCIDENTE
C9: ASE 1 | E9: ASE 2 | G9: ASE 3 | I9: ASE 4 | K9: ASE 5 | M9: TOTAL
C10: REPORTE 3 | D10: REPORTE 4 | E10: REPORTE 3 | F10: REPORTE 4 | G10: REPORTE 3 | H10: REPORTE 4 | I10: REPORTE 3 | J10: REPORTE 4 | K10: REPORTE 3 | L10: REPORTE 4 | M10: REPORTE 3 | N10: REPORTE 4
B11: APLICADO | C11: 0 | D11: 0 | E11: 0 | F11: 0 | G11: 0 | H11: 0 | I11: 0 | J11: 0 | K11: 0 | L11: 0 | M11: =C11+E11+G11+I11+K11 -> 0 | N11: =D11+F11+H11+J11+L11 -> 0
B12: ANTICIPOS | C12: 0 | D12: 0 | E12: 0 | F12: 0 | G12: 0 | H12: 0 | I12: 0 | J12: 0 | K12: 0 | L12: 0 | M12: =C12+E12+G12+I12+K12 -> 0 | N12: =D12+F12+H12+J12+L12 -> 0
B13: TOTAL | C13: =SUM(C11:C12) -> 0 | D13: =SUM(D11:D12) -> 0 | E13: =SUM(E11:E12) -> 0 | F13: =SUM(F11:F12) -> 0 | G13: =SUM(G11:G12) -> 0 | H13: =SUM(H11:H12) -> 0 | I13: =SUM(I11:I12) -> 0 | J13: =SUM(J11:J12) -> 0 | ... N13: =SUM(N11:N12) -> 0
B16: EAAB RECIPROCIDAD
C17: ASE 1 | E17: ASE 2 | G17: ASE 3 | I17: ASE 4 | K17: ASE 5 | M17: TOTAL
C18: REPORTE 3 | D18: REPORTE 4 | E18: REPORTE 3 | F18: REPORTE 4 | G18: REPORTE 3 | H18: REPORTE 4 | I18: REPORTE 3 | J18: REPORTE 4 | K18: REPORTE 3 | L18: REPORTE 4 | M18: REPORTE 3 | N18: REPORTE 4
B19: APLICADO | C19: 0 | D19: 0 | E19: 0 | F19: 0 | G19: 0 | H19: 0 | I19: 0 | J19: 0 | K19: 0 | L19: 0 | M19: =C19+E19+G19+I19+K19 -> 0 | N19: =D19+F19+H19+J19+L19 -> 0
B20: ANTICIPOS | C20: 0 | D20: 0 | E20: 0 | F20: 0 | G20: 0 | H20: 0 | I20: 0 | J20: 0 | K20: 0 | L20: 0 | M20: =C20+E20+G20+I20+K20 -> 0 | N20: =D20+F20+H20+J20+L20 -> 0
B21: TOTAL | C21: =SUM(C19:C20) -> 0 | D21: =SUM(D19:D20) -> 0 | E21: =SUM(E19:E20) -> 0 | F21: =SUM(F19:F20) -> 0 | G21: =SUM(G19:G20) -> 0 | H21: =SUM(H19:H20) -> 0 | I21: =SUM(I19:I20) -> 0 | J21: =SUM(J19:J20) -> 0 | ... L21: =SUM(L19:L20) -> 0 | M21: =C21+E21+G21+I21+K21 -> 0 | N21: =SUM(N19:N20) -> 0
B24: EAAB CIUDAD LIMPIA
C25: ASE 1 | E25: ASE 2 | G25: ASE 3 | I25: ASE 4 | K25: ASE 5 | M25: TOTAL
C26: REPORTE 3 | D26: REPORTE 4 | E26: REPORTE 3 | F26: REPORTE 4 | G26: REPORTE 3 | H26: REPORTE 4 | I26: REPORTE 3 | J26: REPORTE 4 | K26: REPORTE 3 | L26: REPORTE 4 | M26: REPORTE 3 | N26: REPORTE 4
B27: APLICADO | C27: 0 | D27: 0 | E27: 0 | F27: 0 | G27: 0 | H27: 0 | I27: 0 | J27: 0 | K27: 0 | L27: 0 | M27: =C27+E27+G27+I27+K27 -> 0 | N27: =D27+F27+H27+J27+L27 -> 0
B28: ANTICIPOS | C28: 0 | D28: 0 | E28: 0 | F28: 0 | G28: 0 | H28: 0 | I28: 0 | J28: 0 | K28: 0 | L28: 0 | M28: =C28+E28+G28+I28+K28 -> 0 | N28: =D28+F28+H28+J28+L28 -> 0
B29: TOTAL | C29: =SUM(C27:C28) -> 0 | D29: =SUM(D27:D28) -> 0 | E29: =SUM(E27:E28) -> 0 | F29: =SUM(F27:F28) -> 0 | G29: =SUM(G27:G28) -> 0 | H29: =SUM(H27:H28) -> 0 | I29: =SUM(I27:I28) -> 0 | J29: =SUM(J27:J28) -> 0 | ... N29: =SUM(N27:N28) -> 0
B32: ENEL
C33: ASE 1 | E33: ASE 2 | G33: ASE 3 | I33: ASE 4 | K33: ASE 5 | M33: TOTAL
C34: REPORTE 3 | D34: REPORTE 4 | E34: REPORTE 3 | F34: REPORTE 4 | G34: REPORTE 3 | H34: REPORTE 4 | I34: REPORTE 3 | J34: REPORTE 4 | K34: REPORTE 3 | L34: REPORTE 4 | M34: REPORTE 3 | N34: REPORTE 4
B35: APLICADO | C35: 0 | D35: 0 | E35: 0 | F35: 0 | G35: 0 | H35: 0 | I35: 0 | J35: 0 | K35: 0 | L35: 0 | M35: =C35+E35+G35+I35+K35 -> 0 | N35: =D35+F35+H35+J35+L35 -> 0
B36: ANTICIPOS | C36: 0 | D36: 0 | E36: 0 | F36: 0 | G36: 0 | H36: 0 | I36: 0 | J36: 0 | K36: 0 | L36: 0 | M36: =C36+E36+G36+I36+K36 -> 0 | N36: =D36+F36+H36+J36+L36 -> 0
B37: TOTAL | C37: =SUM(C35:C36) -> 0 | D37: =SUM(D35:D36) -> 0 | E37: =SUM(E35:E36) -> 0 | F37: =SUM(F35:F36) -> 0 | G37: =SUM(G35:G36) -> 0 | H37: =SUM(H35:H36) -> 0 | I37: =SUM(I35:I36) -> 0 | J37: =SUM(J35:J36) -> 0 | ... N37: =SUM(N35:N36) -> 0
B40: ENERBIT
C41: ASE 1 | E41: ASE 2 | G41: ASE 3 | I41: ASE 4 | K41: ASE 5 | M41: TOTAL
C42: REPORTE 3 | D42: REPORTE 4 | E42: REPORTE 3 | F42: REPORTE 4 | G42: REPORTE 3 | H42: REPORTE 4 | I42: REPORTE 3 | J42: REPORTE 4 | K42: REPORTE 3 | L42: REPORTE 4 | M42: REPORTE 3 | N42: REPORTE 4
B43: APLICADO | C43: 0 | D43: 0 | E43: 0 | F43: 0 | G43: 0 | H43: 0 | I43: 0 | J43: 0 | K43: 0 | L43: 0 | M43: =C43+E43+G43+I43+K43 -> 0 | N43: =D43+F43+H43+J43+L43 -> 0
B44: ANTICIPOS | C44: 0 | D44: 0 | E44: 0 | F44: 0 | G44: 0 | H44: 0 | I44: 0 | J44: 0 | K44: 0 | L44: 0 | M44: =C44+E44+G44+I44+K44 -> 0 | N44: =D44+F44+H44+J44+L44 -> 0
B45: TOTAL | C45: =SUM(C43:C44) -> 0 | D45: =SUM(D43:D44) -> 0 | E45: =SUM(E43:E44) -> 0 | F45: =SUM(F43:F44) -> 0 | G45: =SUM(G43:G44) -> 0 | H45: =SUM(H43:H44) -> 0 | I45: =SUM(I43:I44) -> 0 | J45: =SUM(J43:J44) -> 0 | ... N45: =SUM(N43:N44) -> 0

Sheet ANTICIPOS USUARIOS
B1: TOTAL | E1: RECIPRCIDAD | H1: ENEL | K1: ENERBIT | N1: OCCIDENTE | Q1: EAAB-CIUDADLIMPIA
B2: ASE | C2: ANTICIPOS GENERADOS POR PAGO | E2: ASE | F2: ANTICIPOS GENERADOS POR PAGO | H2: ASE | I2: ANTICIPOS GENERADOS POR PAGO | K2: ASE | L2: ANTICIPOS GENERADOS POR PAGO | N2: ASE | O2: ANTICIPOS GENERADOS POR PAGO | Q2: ASE | R2: ANTICIPOS GENERADOS POR PAGO | T2: Anticipos generados por pago
B3: 1 | C3: ='REPORTE RECAUDO x BANCO'!I14 -> 1.0093103e+08 | E3: 1 | F3: ='REPORTE RECAUDO x BANCO'!F14 -> 0 | H3: 1 | I3: ='REPORTE RECAUDO x BANCO'!C14 -> 83572548 | K3: 1 | L3: ='REPORTE RECAUDO x BANCO'!G14 -> 0 | N3: 1 | O3: ='REPORTE RECAUDO x BANCO'!H14 -> 17358484 | Q3: 1 | R3: ='REPORTE RECAUDO x BANCO'!D14+'REPORTE RECAUDO x BANCO'!E14 -> 0 | T3: Sale del reporte Recaudo por Bancos.
B4: 2 | C4: ='REPORTE RECAUDO x BANCO'!I24 -> 136534753 | E4: 2 | F4: ='REPORTE RECAUDO x BANCO'!F24 -> 12820520 | H4: 2 | I4: ='REPORTE RECAUDO x BANCO'!C24 -> 44281124 | K4: 2 | L4: ='REPORTE RECAUDO x BANCO'!G24 -> 0 | N4: 2 | O4: ='REPORTE RECAUDO x BANCO'!H24 -> 79433109 | Q4: 2 | R4: ='REPORTE RECAUDO x BANCO'!D24+'REPORTE RECAUDO x BANCO'!E24 -> 0
B5: 3 | C5: ='REPORTE RECAUDO x BANCO'!I33 -> 58884033 | E5: 3 | F5: ='REPORTE RECAUDO x BANCO'!F33 -> 0 | H5: 3 | I5: ='REPORTE RECAUDO x BANCO'!C33 -> 44039530 | K5: 3 | L5: ='REPORTE RECAUDO x BANCO'!G33 -> 0 | N5: 3 | O5: ='REPORTE RECAUDO x BANCO'!H33 -> 14844503 | Q5: 3 | R5: ='REPORTE RECAUDO x BANCO'!D33+'REPORTE RECAUDO x BANCO'!E33 -> 0
B6: 4 | C6: ='REPORTE RECAUDO x BANCO'!I42 -> 73726637 | E6: 4 | F6: ='REPORTE RECAUDO x BANCO'!F42 -> 10268790 | H6: 4 | I6: ='REPORTE RECAUDO x BANCO'!C42 -> 48826052 | K6: 4 | L6: ='REPORTE RECAUDO x BANCO'!G42 -> 0 | N6: 4 | O6: ='REPORTE RECAUDO x BANCO'!H42 -> 14631795 | Q6: 4 | R6: ='REPORTE RECAUDO x BANCO'!D42+'REPORTE RECAUDO x BANCO'!E42 -> 0
B7: 5 | C7: ='REPORTE RECAUDO x BANCO'!I52 -> 28383866 | E7: 5 | F7: ='REPORTE RECAUDO x BANCO'!F52 -> 0 | H7: 5 | I7: ='REPORTE RECAUDO x BANCO'!C52 -> 15997915 | K7: 5 | L7: ='REPORTE RECAUDO x BANCO'!G52 -> 1781103 | N7: 5 | O7: ='REPORTE RECAUDO x BANCO'!H52 -> 10604848 | Q7: 5 | R7: ='REPORTE RECAUDO x BANCO'!D52+'REPORTE RECAUDO x BANCO'!E52 -> 0
C8: =SUM(C3:C7) -> 3.9846032e+08 | F8: =SUM(F3:F7) -> 23089310 | I8: =SUM(I3:I7) -> 2.3671717e+08 | L8: =SUM(L3:L7) -> 1781103 | O8: =SUM(O3:O7) -> 1.3687274e+08 | R8: =SUM(R3:R7) -> 0
C9: =C8='REPORTE RECAUDO x BANCO'!I3 -> TRUE | F9: =F8='REPORTE RECAUDO x BANCO'!F3 -> TRUE | I9: =I8='REPORTE RECAUDO x BANCO'!C3 -> TRUE | L9: =L8='REPORTE RECAUDO x BANCO'!G3 -> TRUE | O9: =O8='REPORTE RECAUDO x BANCO'!H3 -> TRUE | R9: =R8='REPORTE RECAUDO x BANCO'!D3+'REPORTE RECAUDO x BANCO'!E3 -> TRUE
B11: ASE | C11: ANTICIPOS GENERADOS POR EXTEMPORANEOS | E11: ASE | F11: ANTICIPOS GENERADOS POR EXTEMPORANEOS | H11: ASE | I11: ANTICIPOS GENERADOS POR EXTEMPORANEOS | K11: ASE | L11: ANTICIPOS GENERADOS POR EXTEMPORANEOS | N11: ASE | O11: ANTICIPOS GENERADOS POR EXTEMPORANEOS | Q11: ASE | R11: ANTICIPOS GENERADOS POR EXTEMPORANEOS | T11: Anticipos generados por pagos aplicados de reversiones
B12: 1 | C12: ='ANT EXT-REV'!C4 -> 0 | E12: 1 | F12: ='ANT EXT-REV'!C20 -> 0 | H12: 1 | I12: ='ANT EXT-REV'!C36 -> 0 | K12: 1 | L12: ='ANT EXT-REV'!C44 -> 0 | N12: 1 | O12: ='ANT EXT-REV'!C12 -> 0 | Q12: 1 | R12: ='ANT EXT-REV'!C28 -> 0 | T12: Sale del reporte Recaudo reversado
B13: 2 | C13: ='ANT EXT-REV'!E4 -> 0 | E13: 2 | F13: ='ANT EXT-REV'!E20 -> 0 | H13: 2 | I13: ='ANT EXT-REV'!E36 -> 0 | K13: 2 | L13: ='ANT EXT-REV'!E44 -> 0 | N13: 2 | O13: ='ANT EXT-REV'!E12 -> 0 | Q13: 2 | R13: ='ANT EXT-REV'!E28 -> 0
B14: 3 | C14: ='ANT EXT-REV'!G4 -> 0 | E14: 3 | F14: ='ANT EXT-REV'!G20 -> 0 | H14: 3 | I14: ='ANT EXT-REV'!G36 -> 0 | K14: 3 | L14: ='ANT EXT-REV'!G44 -> 0 | N14: 3 | O14: ='ANT EXT-REV'!G12 -> 0 | Q14: 3 | R14: ='ANT EXT-REV'!G28 -> 0
B15: 4 | C15: ='ANT EXT-REV'!I4 -> 0 | E15: 4 | F15: ='ANT EXT-REV'!I20 -> 0 | H15: 4 | I15: ='ANT EXT-REV'!I36 -> 0 | K15: 4 | L15: ='ANT EXT-REV'!I44 -> 0 | N15: 4 | O15: ='ANT EXT-REV'!I12 -> 0 | Q15: 4 | R15: ='ANT EXT-REV'!I28 -> 0
B16: 5 | C16: ='ANT EXT-REV'!K4 -> 0 | E16: 5 | F16: ='ANT EXT-REV'!K20 -> 0 | H16: 5 | I16: ='ANT EXT-REV'!K36 -> 0 | K16: 5 | L16: ='ANT EXT-REV'!K44 -> 0 | N16: 5 | O16: ='ANT EXT-REV'!K12 -> 0 | Q16: 5 | R16: ='ANT EXT-REV'!K28 -> 0
C17: =SUM(C12:C16) -> 0 | F17: =SUM(F12:F16) -> 0 | I17: =SUM(I12:I16) -> 0 | L17: =SUM(L12:L16) -> 0 | O17: =SUM(O12:O16) -> 0 | R17: =SUM(R12:R16) -> 0
C18: =C17='ANT EXT-REV'!M4 -> TRUE | F18: =F17='ANT EXT-REV'!M20 -> TRUE | I18: =I17='ANT EXT-REV'!M36 -> TRUE | L18: =L17='ANT EXT-REV'!M44 -> TRUE | O18: =O17='ANT EXT-REV'!M12 -> TRUE | R18: =R17='ANT EXT-REV'!M28 -> TRUE
B20: ASE | C20: ANTICIPOS QUE CARGAN POR REVERSIONES | E20: ASE | F20: ANTICIPOS QUE CARGAN POR REVERSIONES | H20: ASE | I20: ANTICIPOS QUE CARGAN POR REVERSIONES | K20: ASE | L20: ANTICIPOS QUE CARGAN POR REVERSIONES | N20: ASE | O20: ANTICIPOS QUE CARGAN POR REVERSIONES | Q20: ASE | R20: ANTICIPOS QUE CARGAN POR REVERSIONES | T20: Anticipos que cargan de reversiones
B21: 1 | C21: ='ANT EXT-REV'!D4 -> 0 | E21: 1 | F21: ='ANT EXT-REV'!D20 -> 0 | H21: 1 | I21: ='ANT EXT-REV'!D36 -> 0 | K21: 1 | L21: ='ANT EXT-REV'!D44 -> 0 | N21: 1 | O21: ='ANT EXT-REV'!D12 -> 0 | Q21: 1 | R21: ='ANT EXT-REV'!D28 -> 0 | T21: Sale del reporte Recaudo reversado
B22: 2 | C22: ='ANT EXT-REV'!F4 -> 0 | E22: 2 | F22: ='ANT EXT-REV'!F20 -> 0 | H22: 2 | I22: ='ANT EXT-REV'!F36 -> 0 | K22: 2 | L22: ='ANT EXT-REV'!F44 -> 0 | N22: 2 | O22: ='ANT EXT-REV'!F12 -> 0 | Q22: 2 | R22: ='ANT EXT-REV'!F28 -> 0
B23: 3 | C23: ='ANT EXT-REV'!H4 -> 0 | E23: 3 | F23: ='ANT EXT-REV'!H20 -> 0 | H23: 3 | I23: ='ANT EXT-REV'!H36 -> 0 | K23: 3 | L23: ='ANT EXT-REV'!H44 -> 0 | N23: 3 | O23: ='ANT EXT-REV'!H12 -> 0 | Q23: 3 | R23: ='ANT EXT-REV'!H28 -> 0
B24: 4 | C24: ='ANT EXT-REV'!J4 -> 0 | E24: 4 | F24: ='ANT EXT-REV'!J20 -> 0 | H24: 4 | I24: ='ANT EXT-REV'!J36 -> 0 | K24: 4 | L24: ='ANT EXT-REV'!J44 -> 0 | N24: 4 | O24: ='ANT EXT-REV'!J12 -> 0 | Q24: 4 | R24: ='ANT EXT-REV'!J28 -> 0
B25: 5 | C25: ='ANT EXT-REV'!L4 -> 0 | E25: 5 | F25: ='ANT EXT-REV'!L20 -> 0 | H25: 5 | I25: ='ANT EXT-REV'!L36 -> 0 | K25: 5 | L25: ='ANT EXT-REV'!L44 -> 0 | N25: 5 | O25: ='ANT EXT-REV'!L12 -> 0 | Q25: 5 | R25: ='ANT EXT-REV'!L28 -> 0
C26: =SUM(C21:C25) -> 0 | F26: =SUM(F21:F25) -> 0 | I26: =SUM(I21:I25) -> 0 | L26: =SUM(L21:L25) -> 0 | O26: =SUM(O21:O25) -> 0 | R26: =SUM(R21:R25) -> 0
C27: =C26='ANT EXT-REV'!N4 -> TRUE | F27: =F26='ANT EXT-REV'!N20 -> TRUE | I27: =I26='ANT EXT-REV'!N36 -> TRUE | L27: =L26='ANT EXT-REV'!N44 -> TRUE | O27: =O26='ANT EXT-REV'!N12 -> TRUE | R27: =R26='ANT EXT-REV'!N28 -> TRUE

Sheet BCE SC POR FACT.
C2: ASE | D2: SUBSIDIO | E2: CONTRIBUCION | F2: TOTAL BSC | H2: SISTEMA
C3: 1 | D3: -6.0415123e+09 | E3: 2.4520577e+09 | F3: =D3+E3 -> -3.5894547e+09 | H3: =DetRetri2026072!J9 -> -3589454666 | I3: =F3-H3 -> 0.45000029
C4: 2 | D4: -5.5026723e+09 | E4: 2.2614785e+09 | F4: =D4+E4 -> -3.2411937e+09 | H4: =DetRetri2026072!J10 -> -3241193714 | I4: =F4-H4 -> -0.11000013
C5: 3 | D5: -2.1159662e+09 | E5: 1.2627217e+09 | F5: =D5+E5 -> -8.5324456e+08 | H5: =DetRetri2026072!J11 -> -853244565 | I5: =F5-H5 -> 0.49000001
C6: 4 | D6: -2.4678057e+09 | E6: 1.767923e+09 | F6: =D6+E6 -> -6.9988271e+08 | H6: =DetRetri2026072!J12 -> -699882713 | I6: =F6-H6 -> -0.37000012
C7: 5 | D7: -1.1386507e+09 | E7: 1.0556917e+09 | F7: =D7+E7 -> -82959024 | H7: =DetRetri2026072!J13 -> -82959024 | I7: =F7-H7 -> 0.33999991
F9: =SUM(F3:F7) -> -8.4667347e+09 | H9: =SUM(H3:H7) -> -8466734682 | I9: =F9-H9 -> 0.80000019
H10: =H9=DetRetri2026072!J14 -> TRUE
D11: =SUM(D3:D7) -> -1.7266607e+10 | E11: =SUM(E3:E7) -> 8.7998726e+09 | F11: =SUM(D3:E7) -> -8.4667347e+09
F12: =ROUND(F11,2)=ROUND(F9,2) -> TRUE
F13: =ROUND(F11,2)-ROUND(F9,2) -> 0
D18: ASE | E18: REMUN TOTAL | F18: VALIDA 1 | G18: VALIDA 2 | H18: DIFERENCIA VALIDA 2
D19: 1 | E19: ='CONSOLIDADO_TOTAL RECAUDO'!J104 -> -3.5894547e+09 | F19: =E19=F3 -> TRUE | G19: =E19=H3 -> FALSE | H19: =E19-H3 -> 0.45000029
D20: 2 | E20: ='CONSOLIDADO_TOTAL RECAUDO'!J105 -> -3.2411937e+09 | F20: =E20=F4 -> TRUE | G20: =E20=H4 -> FALSE | H20: =E20-H4 -> -0.11000013
D21: 3 | E21: ='CONSOLIDADO_TOTAL RECAUDO'!J106 -> -8.5324456e+08 | F21: =E21=F5 -> TRUE | G21: =E21=H5 -> FALSE | H21: =E21-H5 -> 0.49000001
D22: 4 | E22: ='CONSOLIDADO_TOTAL RECAUDO'!J107 -> -6.9988271e+08 | F22: =E22=F6 -> TRUE | G22: =E22=H6 -> FALSE | H22: =E22-H6 -> -0.37000012
D23: 5 | E23: ='CONSOLIDADO_TOTAL RECAUDO'!J108 -> -82959024 | F23: =E23=F7 -> TRUE | G23: =E23=H7 -> FALSE | H23: =E23-H7 -> 0.33999991
E24: =SUM(E19:E23) -> -8.4667347e+09 | F24: =E24=F9 -> TRUE | G24: =E24=H9 -> FALSE | H24: =E24-H9 -> 0.80000019

Sheet Reporte Componentes R1
B4: PROMOAMBIENTAL
F5: Total | G5: Componente TDF | H5: Componente TTL | I5: Componente TVIAT | J5: Aprovechamiento | K5: CCSA Prest.Aprov. | L5: SERVICIO ESPECIALES | M5: Componente TCS | N5: Componente TLU | O5: Componente TBL | P5: Componente TRT | Q5: CCSA Prest. No Aprov. | R5: Ajuste Decena | S5: Ajuste Recargo Aseo | T5: Intereses Cte Financiac. Aseo | U5: Exonera-Recargo Aseo | V5: Exonera-Ajuste Decena Aseo | W5: Exonera-Recargo Aseo | X5: Exonera-Recargo Aseo | Y5: Intereses Cte Financiac. Aseo | Z5: Rec.Intereses
E6: Vlr Servicio | F6: -7108.82 | G6: -502.98 | H6: -213.69 | I6: -93.3 | J6: -1231.48 | K6: -79.57 | L6: 0 | M6: -698.02 | N6: -584.17 | O6: -2331.79 | P6: -1243.99 | Q6: -129.83 | R6: 0 | S6: 0 | T6: 0 | U6: 0 | V6: 0 | W6: 0 | X6: 0 | Y6: 0 | Z6: 0
D7: E | E7: Total | F7: -7108.82 | G7: -502.98 | H7: -213.69 | I7: -93.3 | J7: -1231.48 | K7: -79.57 | L7: 0 | M7: -698.02 | N7: -584.17 | O7: -2331.79 | P7: -1243.99 | Q7: -129.83 | R7: 0 | S7: 0 | T7: 0 | U7: 0 | V7: 0 | W7: 0 | X7: 0 | Y7: 0 | Z7: 0
C8: ENEL | D8: Total | F8: -7108.82 | G8: -502.98 | H8: -213.69 | I8: -93.3 | J8: -1231.48 | K8: -79.57 | L8: 0 | M8: -698.02 | N8: -584.17 | O8: -2331.79 | P8: -1243.99 | Q8: -129.83 | R8: 0 | S8: 0 | T8: 0 | U8: 0 | V8: 0 | W8: 0 | X8: 0 | Y8: 0 | Z8: 0
E9: Vlr Servicio | F9: 0 | G9: 0 | H9: 0 | I9: 0 | J9: 0 | K9: 0 | L9: 0 | M9: 0 | N9: 0 | O9: 0 | P9: 0 | Q9: 0 | R9: 0 | S9: 0 | T9: 0 | U9: 0 | V9: 0 | W9: 0 | X9: 0 | Y9: 0 | Z9: 0
D10: H | E10: Total | F10: 0 | G10: 0 | H10: 0 | I10: 0 | J10: 0 | K10: 0 | L10: 0 | M10: 0 | N10: 0 | O10: 0 | P10: 0 | Q10: 0 | R10: 0 | S10: 0 | T10: 0 | U10: 0 | V10: 0 | W10: 0 | X10: 0 | Y10: 0 | Z10: 0
E11: Vlr Servicio | F11: -4108.55 | G11: -263.4 | H11: -111.9 | I11: -48.87 | J11: -738.89 | K11: -47.75 | L11: 0 | M11: -418.8 | N11: -350.5 | O11: -1399.09 | P11: -651.44 | Q11: -77.91 | R11: 0 | S11: 0 | T11: 0 | U11: 0 | V11: 0 | W11: 0 | X11: 0 | Y11: 0 | Z11: 0
D12: O | E12: Total | F12: -4108.55 | G12: -263.4 | H12: -111.9 | I12: -48.87 | J12: -738.89 | K12: -47.75 | L12: 0 | M12: -418.8 | N12: -350.5 | O12: -1399.09 | P12: -651.44 | Q12: -77.91 | R12: 0 | S12: 0 | T12: 0 | U12: 0 | V12: 0 | W12: 0 | X12: 0 | Y12: 0 | Z12: 0
E13: Vlr Servicio | F13: 0 | G13: 0 | H13: 0 | I13: 0 | J13: 0 | K13: 0 | L13: 0 | M13: 0 | N13: 0 | O13: 0 | P13: 0 | Q13: 0 | R13: 0 | S13: 0 | T13: 0 | U13: 0 | V13: 0 | W13: 0 | X13: 0 | Y13: 0 | Z13: 0
D14: T | E14: Total | F14: 0 | G14: 0 | H14: 0 | I14: 0 | J14: 0 | K14: 0 | L14: 0 | M14: 0 | N14: 0 | O14: 0 | P14: 0 | Q14: 0 | R14: 0 | S14: 0 | T14: 0 | U14: 0 | V14: 0 | W14: 0 | X14: 0 | Y14: 0 | Z14: 0
C15: OCCIDENTE | D15: Total | F15: -4108.55 | G15: -263.4 | H15: -111.9 | I15: -48.87 | J15: -738.89 | K15: -47.75 | L15: 0 | M15: -418.8 | N15: -350.5 | O15: -1399.09 | P15: -651.44 | Q15: -77.91 | R15: 0 | S15: 0 | T15: 0 | U15: 0 | V15: 0 | W15: 0 | X15: 0 | Y15: 0 | Z15: 0
B16: Mes | C16: Total | F16: -11217.37 | G16: -766.38 | H16: -325.59 | I16: -142.17 | J16: -1970.37 | K16: -127.32 | L16: 0 | M16: -1116.82 | N16: -934.67 | O16: -3730.88 | P16: -1895.43 | Q16: -207.74 | R16: 0 | S16: 0 | T16: 0 | U16: 0 | V16: 0 | W16: 0 | X16: 0 | Y16: 0 | Z16: 0
A17: AFaseo | B17: Total | F17: -11217.37 | G17: -766.38 | H17: -325.59 | I17: -142.17 | J17: -1970.37 | K17: -127.32 | L17: 0 | M17: -1116.82 | N17: -934.67 | O17: -3730.88 | P17: -1895.43 | Q17: -207.74 | R17: 0 | S17: 0 | T17: 0 | U17: 0 | V17: 0 | W17: 0 | X17: 0 | Y17: 0 | Z17: 0
E18: Vlr Servicio | F18: 9215.69 | G18: 2007.44 | H18: 1133.38 | I18: 594.88 | J18: 0 | K18: 0 | L18: 0 | M18: 0 | N18: 0 | O18: 0 | P18: 5482.6 | Q18: 0 | R18: -2.61 | S18: 0 | T18: 0 | U18: 0 | V18: 0 | W18: 0 | X18: 0 | Y18: 0 | Z18: 0
E19: Vlr Intereses | F19: 0 | G19: 0 | H19: 0 | I19: 0 | J19: 0 | K19: 0 | L19: 0 | M19: 0 | N19: 0 | O19: 0 | P19: 0 | Q19: 0 | R19: 0 | S19: 0 | T19: 0 | U19: 0 | V19: 0 | W19: 0 | X19: 0 | Y19: 0 | Z19: 0
D20: E | E20: Total | F20: 9215.69 | G20: 2007.44 | H20: 1133.38 | I20: 594.88 | J20: 0 | K20: 0 | L20: 0 | M20: 0 | N20: 0 | O20: 0 | P20: 5482.6 | Q20: 0 | R20: -2.61 | S20: 0 | T20: 0 | U20: 0 | V20: 0 | W20: 0 | X20: 0 | Y20: 0 | Z20: 0
C21: ENEL | D21: Total | F21: 9215.69 | G21: 2007.44 | H21: 1133.38 | I21: 594.88 | J21: 0 | K21: 0 | L21: 0 | M21: 0 | N21: 0 | O21: 0 | P21: 5482.6 | Q21: 0 | R21: -2.61 | S21: 0 | T21: 0 | U21: 0 | V21: 0 | W21: 0 | X21: 0 | Y21: 0 | Z21: 0
E22: Vlr Servicio | F22: 0 | G22: 0 | H22: 0 | I22: 0 | J22: 0 | K22: 0 | L22: 0 | M22: 0 | N22: 0 | O22: 0 | P22: 0 | Q22: 0 | R22: 0 | S22: 0 | T22: 0 | U22: 0 | V22: 0 | W22: 0 | X22: 0 | Y22: 0 | Z22: 0
E23: Vlr Intereses | F23: 0 | G23: 0 | H23: 0 | I23: 0 | J23: 0 | K23: 0 | L23: 0 | M23: 0 | N23: 0 | O23: 0 | P23: 0 | Q23: 0 | R23: 0 | S23: 0 | T23: 0 | U23: 0 | V23: 0 | W23: 0 | X23: 0 | Y23: 0 | Z23: 0
D24: E | E24: Total | F24: 0 | G24: 0 | H24: 0 | I24: 0 | J24: 0 | K24: 0 | L24: 0 | M24: 0 | N24: 0 | O24: 0 | P24: 0 | Q24: 0 | R24: 0 | S24: 0 | T24: 0 | U24: 0 | V24: 0 | W24: 0 | X24: 0 | Y24: 0 | Z24: 0
C25: ENERBIT | D25: Total | F25: 0 | G25: 0 | H25: 0 | I25: 0 | J25: 0 | K25: 0 | L25: 0 | M25: 0 | N25: 0 | O25: 0 | P25: 0 | Q25: 0 | R25: 0 | S25: 0 | T25: 0 | U25: 0 | V25: 0 | W25: 0 | X25: 0 | Y25: 0 | Z25: 0
E26: Vlr Servicio | F26: 0 | G26: 0 | H26: 0 | I26: 0 | J26: 0 | K26: 0 | L26: 0 | M26: 0 | N26: 0 | O26: 0 | P26: 0 | Q26: 370.08 | R26: -1.95 | S26: 0 | T26: 0 | U26: 0 | V26: 0 | W26: 0 | X26: 0 | Y26: 0 | Z26: 0
E27: Vlr Intereses | F27: 0 | G27: 0 | H27: 0 | I27: 0 | J27: 0 | K27: 0 | L27: 0 | M27: 0 | N27: 0 | O27: 0 | P27: 0 | Q27: 0.07 | R27: 0 | S27: 0 | T27: 0 | U27: 0 | V27: 0 | W27: 0 | X27: 0 | Y27: 0 | Z27: 0
D28: H | E28: Total | F28: 0 | G28: 0 | H28: 0 | I28: 0 | J28: 0 | K28: 0 | L28: 0 | M28: 0 | N28: 0 | O28: 0 | P28: 0 | Q28: 370.15 | R28: -1.95 | S28: 0 | T28: 0 | U28: 0 | V28: 0 | W28: 0 | X28: 0 | Y28: 0 | Z28: 0
E29: Vlr Servicio | F29: 0 | G29: 0 | H29: 0 | I29: 0 | J29: 0 | K29: 0 | L29: 0 | M29: 0 | N29: 0 | O29: 0 | P29: 0 | Q29: 370.08 | R29: -1.95 | S29: 0 | T29: 0 | U29: 0 | V29: 0 | W29: 0 | X29: 0 | Y29: 0 | Z29: 0
E30: Vlr Intereses | F30: 0 | G30: 0 | H30: 0 | I30: 0 | J30: 0 | K30: 0 | L30: 0 | M30: 0 | N30: 0 | O30: 0 | P30: 0 | Q30: 0.07 | R30: 0 | S30: 0 | T30: 0 | U30: 0 | V30: 0 | W30: 0 | X30: 0 | Y30: 0 | Z30: 0
D31: O | E31: Total | F31: 0 | G31: 0 | H31: 0 | I31: 0 | J31: 0 | K31: 0 | L31: 0 | M31: 0 | N31: 0 | O31: 0 | P31: 0 | Q31: 370.15 | R31: -1.95 | S31: 0 | T31: 0 | U31: 0 | V31: 0 | W31: 0 | X31: 0 | Y31: 0 | Z31: 0
E32: Vlr Servicio | F32: 0 | G32: 0 | H32: 0 | I32: 0 | J32: 0 | K32: 0 | L32: 0 | M32: 0 | N32: 0 | O32: 0 | P32: 0 | Q32: 0 | R32: 0 | S32: 0 | T32: 0 | U32: 0 | V32: 0 | W32: 0 | X32: 0 | Y32: 0 | Z32: 0
E33: Vlr Intereses | F33: 0 | G33: 0 | H33: 0 | I33: 0 | J33: 0 | K33: 0 | L33: 0 | M33: 0 | N33: 0 | O33: 0 | P33: 0 | Q33: 0 | R33: 0 | S33: 0 | T33: 0 | U33: 0 | V33: 0 | W33: 0 | X33: 0 | Y33: 0 | Z33: 0
D34: T | E34: Total | F34: 0 | G34: 0 | H34: 0 | I34: 0 | J34: 0 | K34: 0 | L34: 0 | M34: 0 | N34: 0 | O34: 0 | P34: 0 | Q34: 0 | R34: 0 | S34: 0 | T34: 0 | U34: 0 | V34: 0 | W34: 0 | X34: 0 | Y34: 0 | Z34: 0
C35: OCCIDENTE | D35: Total | F35: 0 | G35: 0 | H35: 0 | I35: 0 | J35: 0 | K35: 0 | L35: 0 | M35: 0 | N35: 0 | O35: 0 | P35: 0 | Q35: 0 | R35: 0 | S35: 0 | T35: 0 | U35: 0 | V35: 0 | W35: 0 | X35: 0 | Y35: 0 | Z35: 0
B36: Aplicacion nuevos x reversion | C36: Total | F36: 9215.69 | G36: 2007.44 | H36: 1133.38 | I36: 594.88 | J36: 0 | K36: 0 | L36: 0 | M36: 0 | N36: 0 | O36: 0 | P36: 5482.6 | Q36: 0 | R36: -2.61 | S36: 0 | T36: 0 | U36: 0 | V36: 0 | W36: 0 | X36: 0 | Y36: 0 | Z36: 0
E37: Vlr Servicio | F37: 1.5311909e+10 | G37: 8.013638e+08 | H37: 4.5218165e+08 | I37: 2.375767e+08 | J37: 3.7426033e+09 | K37: 1.3187246e+08 | L37: 16515976 | M37: 1.1602294e+09 | N37: 1.1131782e+09 | O37: 5.2698556e+09 | P37: 2.1713711e+09 | Q37: 2.1517844e+08 | R37: -17072.68 | S37: 0 | T37: 0 | U37: 0 | V37: 0 | W37: 0 | X37: 0 | Y37: 0 | Z37: 0
E38: Vlr Intereses | F38: 4090440.9 | G38: 281733.24 | H38: 147454.73 | I38: 76550.04 | J38: 796420.04 | K38: 36830.11 | L38: 516.31 | M38: 325736.63 | N38: 292484.52 | O38: 1313250.7 | P38: 758517.98 | Q38: 60116.44 | R38: 308.42 | S38: 0 | T38: 521.8 | U38: 0 | V38: 0 | W38: 0 | X38: 0 | Y38: 0 | Z38: -0.03
D39: E | E39: Total | F39: 1.5316e+10 | G39: 8.0164553e+08 | H39: 4.5232911e+08 | I39: 2.3765325e+08 | J39: 3.7433997e+09 | K39: 1.3190929e+08 | L39: 16516492 | M39: 1.1605551e+09 | N39: 1.1134707e+09 | O39: 5.2711688e+09 | P39: 2.1721296e+09 | Q39: 2.1523856e+08 | R39: -16764.26 | S39: 0 | T39: 521.8 | U39: 0 | V39: 0 | W39: 0 | X39: 0 | Y39: 0 | Z39: -0.03
C40: ENEL | D40: Total | F40: 1.5316e+10 | G40: 8.0164553e+08 | H40: 4.5232911e+08 | I40: 2.3765325e+08 | J40: 3.7433997e+09 | K40: 1.3190929e+08 | L40: 16516492 | M40: 1.1605551e+09 | N40: 1.1134707e+09 | O40: 5.2711688e+09 | P40: 2.1721296e+09 | Q40: 2.1523856e+08 | R40: -16764.26 | S40: 0 | T40: 521.8 | U40: 0 | V40: 0 | W40: 0 | X40: 0 | Y40: 0 | Z40: -0.03
E41: Vlr Servicio | F41: 0 | G41: 0 | H41: 0 | I41: 0 | J41: 0 | K41: 0 | L41: 0 | M41: 0 | N41: 0 | O41: 0 | P41: 0 | Q41: 0 | R41: 0 | S41: 0 | T41: 0 | U41: 0 | V41: 0 | W41: 0 | X41: 0 | Y41: 0 | Z41: 0
E42: Vlr Intereses | F42: 0 | G42: 0 | H42: 0 | I42: 0 | J42: 0 | K42: 0 | L42: 0 | M42: 0 | N42: 0 | O42: 0 | P42: 0 | Q42: 0 | R42: 0 | S42: 0 | T42: 0 | U42: 0 | V42: 0 | W42: 0 | X42: 0 | Y42: 0 | Z42: 0
D43: E | E43: Total | F43: 0 | G43: 0 | H43: 0 | I43: 0 | J43: 0 | K43: 0 | L43: 0 | M43: 0 | N43: 0 | O43: 0 | P43: 0 | Q43: 0 | R43: 0 | S43: 0 | T43: 0 | U43: 0 | V43: 0 | W43: 0 | X43: 0 | Y43: 0 | Z43: 0
C44: ENERBIT | D44: Total | F44: 0 | G44: 0 | H44: 0 | I44: 0 | J44: 0 | K44: 0 | L44: 0 | M44: 0 | N44: 0 | O44: 0 | P44: 0 | Q44: 0 | R44: 0 | S44: 0 | T44: 0 | U44: 0 | V44: 0 | W44: 0 | X44: 0 | Y44: 0 | Z44: 0
E45: Vlr Servicio | F45: 32531853 | G45: 2591273.9 | H45: 1444146.4 | I45: 758108.3 | J45: 6042578.8 | K45: 205824.68 | L45: 0 | M45: 1805861.6 | N45: 2163115.5 | O45: 10120980 | P45: 7063994.1 | Q45: 335853.33 | R45: 116.52 | S45: 0 | T45: 0 | U45: 0 | V45: 0 | W45: 0 | X45: 0 | Y45: 0 | Z45: 0
E46: Vlr Intereses | F46: 70410.78 | G46: 4075.34 | H46: 2009.42 | I46: 1036.19 | J46: 14956.08 | K46: 634.42 | L46: 0 | M46: 5556.36 | N46: 5429.24 | O46: 24704.76 | P46: 10925.02 | Q46: 1033.93 | R46: 49.75 | S46: 0 | T46: 0.27 | U46: 0 | V46: 0 | W46: 0 | X46: 0 | Y46: 0 | Z46: 0
D47: H | E47: Total | F47: 32602264 | G47: 2595349.2 | H47: 1446155.9 | I47: 759144.49 | J47: 6057534.9 | K47: 206459.1 | L47: 0 | M47: 1811418 | N47: 2168544.8 | O47: 10145685 | P47: 7074919.1 | Q47: 336887.26 | R47: 166.27 | S47: 0 | T47: 0.27 | U47: 0 | V47: 0 | W47: 0 | X47: 0 | Y47: 0 | Z47: 0
E48: Vlr Servicio | F48: 1.4271862e+08 | G48: 16226923 | H48: 8978685.1 | I48: 4682686.1 | J48: 17356716 | K48: 717148.94 | L48: 4122672 | M48: 6303944.3 | N48: 6897057 | O48: 32134628 | P48: 44127364 | Q48: 1171009.8 | R48: -218.38 | S48: 0 | T48: 0 | U48: 0 | V48: 0 | W48: 0 | X48: 0 | Y48: 0 | Z48: 0
E49: Vlr Intereses | F49: 700269.72 | G49: 40116.7 | H49: 19139.89 | I49: 10101.16 | J49: 153132.53 | K49: 7303.27 | L49: 0 | M49: 64029.13 | N49: 56965.87 | O49: 230260.01 | P49: 107283.27 | Q49: 11912.73 | R49: 27.3 | S49: -2.32 | T49: 0.18 | U49: 0 | V49: 0 | W49: 0 | X49: 0 | Y49: 0 | Z49: 0
D50: O | E50: Total | F50: 1.4341889e+08 | G50: 16267039 | H50: 8997825 | I50: 4692787.3 | J50: 17509848 | K50: 724452.21 | L50: 4122672 | M50: 6367973.5 | N50: 6954022.9 | O50: 32364888 | P50: 44234647 | Q50: 1182922.5 | R50: -191.08 | S50: -2.32 | T50: 0.18 | U50: 0 | V50: 0 | W50: 0 | X50: 0 | Y50: 0 | Z50: 0
E51: Vlr Servicio | F51: 4.4329992e+08 | G51: 77621929 | H51: 43739697 | I51: 23002911 | J51: 27531678 | K51: 700778.07 | L51: 4638006 | M51: 6178734.5 | N51: 8275304.8 | O51: 38410844 | P51: 2.1205741e+08 | Q51: 1143387.7 | R51: -766.24 | S51: 0 | T51: 0 | U51: 0 | V51: 0 | W51: 0 | X51: 0 | Y51: 0 | Z51: 0
E52: Vlr Intereses | F52: 613877.45 | G52: 94058.21 | H52: 48331.99 | I52: 26441.83 | J52: 61251.38 | K52: 1855.3 | L52: 146.01 | M52: 16384.73 | N52: 20507.08 | O52: 89016.81 | P52: 254956.79 | Q52: 3029.72 | R52: 10.11 | S52: -2112.51 | T52: 0 | U52: 0 | V52: 0 | W52: 0 | X52: 0 | Y52: 0 | Z52: 0
D53: T | E53: Total | F53: 4.4391379e+08 | G53: 77715987 | H53: 43788029 | I53: 23029353 | J53: 27592930 | K53: 702633.37 | L53: 4638152 | M53: 6195119.2 | N53: 8295811.8 | O53: 38499861 | P53: 2.1231237e+08 | Q53: 1146417.4 | R53: -756.13 | S53: -2112.51 | T53: 0 | U53: 0 | V53: 0 | W53: 0 | X53: 0 | Y53: 0 | Z53: 0
C54: OCCIDENTE | D54: Total | F54: 6.1993494e+08 | G54: 96578376 | H54: 54232009 | I54: 28481285 | J54: 51160313 | K54: 1633544.7 | L54: 8760824 | M54: 14374511 | N54: 17418380 | O54: 81010433 | P54: 2.6362194e+08 | Q54: 2666227.1 | R54: -780.94 | S54: -2114.83 | T54: 0.45 | U54: 0 | V54: 0 | W54: 0 | X54: 0 | Y54: 0 | Z54: 0
B55: Mes | C55: Total | F55: 1.5935935e+10 | G55: 8.9822391e+08 | H55: 5.0656112e+08 | I55: 2.6613453e+08 | J55: 3.79456e+09 | K55: 1.3354283e+08 | L55: 25277316 | M55: 1.1749296e+09 | N55: 1.130889e+09 | O55: 5.3521793e+09 | P55: 2.4357515e+09 | Q55: 2.1790479e+08 | R55: -17545.2 | S55: -2114.83 | T55: 522.25 | U55: 0 | V55: 0 | W55: 0 | X55: 0 | Y55: 0 | Z55: -0.03
A56: Componente | B56: Total | F56: 1.5935944e+10 | G56: 8.9822592e+08 | H56: 5.0656225e+08 | I56: 2.6613513e+08 | J56: 3.79456e+09 | K56: 1.3354283e+08 | L56: 25277316 | M56: 1.1749296e+09 | N56: 1.130889e+09 | O56: 5.3521793e+09 | P56: 2.435757e+09 | Q56: 2.1790479e+08 | R56: -17547.81 | S56: -2114.83 | T56: 522.25 | U56: 0 | V56: 0 | W56: 0 | X56: 0 | Y56: 0 | Z56: -0.03
E57: Subsidio(-)/Contribucion(+) | F57: 40364.31 | G57: 1974.08 | H57: 1114.56 | I57: 585 | J57: 9457.65 | K57: 361.03 | L57: 0 | M57: 3166.94 | N57: 3091.65 | O57: 14632.85 | P57: 5391.5 | Q57: 589.05 | R57: 0 | S57: 0 | T57: 0 | U57: 0 | V57: 0 | W57: 0 | X57: 0 | Y57: 0 | Z57: 0
D58: E | E58: Total | F58: 40364.31 | G58: 1974.08 | H58: 1114.56 | I58: 585 | J58: 9457.65 | K58: 361.03 | L58: 0 | M58: 3166.94 | N58: 3091.65 | O58: 14632.85 | P58: 5391.5 | Q58: 589.05 | R58: 0 | S58: 0 | T58: 0 | U58: 0 | V58: 0 | W58: 0 | X58: 0 | Y58: 0 | Z58: 0
C59: ENEL | D59: Total | F59: 40364.31 | G59: 1974.08 | H59: 1114.56 | I59: 585 | J59: 9457.65 | K59: 361.03 | L59: 0 | M59: 3166.94 | N59: 3091.65 | O59: 14632.85 | P59: 5391.5 | Q59: 589.05 | R59: 0 | S59: 0 | T59: 0 | U59: 0 | V59: 0 | W59: 0 | X59: 0 | Y59: 0 | Z59: 0
E60: Subsidio(-)/Contribucion(+) | F60: 0 | G60: 0 | H60: 0 | I60: 0 | J60: 0 | K60: 0 | L60: 0 | M60: 0 | N60: 0 | O60: 0 | P60: 0 | Q60: 0 | R60: 0 | S60: 0 | T60: 0 | U60: 0 | V60: 0 | W60: 0 | X60: 0 | Y60: 0 | Z60: 0
D61: E | E61: Total | F61: 0 | G61: 0 | H61: 0 | I61: 0 | J61: 0 | K61: 0 | L61: 0 | M61: 0 | N61: 0 | O61: 0 | P61: 0 | Q61: 0 | R61: 0 | S61: 0 | T61: 0 | U61: 0 | V61: 0 | W61: 0 | X61: 0 | Y61: 0 | Z61: 0
C62: ENERBIT | D62: Total | F62: 0 | G62: 0 | H62: 0 | I62: 0 | J62: 0 | K62: 0 | L62: 0 | M62: 0 | N62: 0 | O62: 0 | P62: 0 | Q62: 0 | R62: 0 | S62: 0 | T62: 0 | U62: 0 | V62: 0 | W62: 0 | X62: 0 | Y62: 0 | Z62: 0
E63: Subsidio(-)/Contribucion(+) | F63: 0 | G63: 0 | H63: 0 | I63: 0 | J63: 0 | K63: 0 | L63: 0 | M63: 0 | N63: 0 | O63: 0 | P63: 0 | Q63: 0 | R63: 0 | S63: 0 | T63: 0 | U63: 0 | V63: 0 | W63: 0 | X63: 0 | Y63: 0 | Z63: 0
D64: H | E64: Total | F64: 0 | G64: 0 | H64: 0 | I64: 0 | J64: 0 | K64: 0 | L64: 0 | M64: 0 | N64: 0 | O64: 0 | P64: 0 | Q64: 0 | R64: 0 | S64: 0 | T64: 0 | U64: 0 | V64: 0 | W64: 0 | X64: 0 | Y64: 0 | Z64: 0
E65: Subsidio(-)/Contribucion(+) | F65: 0 | G65: 0 | H65: 0 | I65: 0 | J65: 0 | K65: 0 | L65: 0 | M65: 0 | N65: 0 | O65: 0 | P65: 0 | Q65: 0 | R65: 0 | S65: 0 | T65: 0 | U65: 0 | V65: 0 | W65: 0 | X65: 0 | Y65: 0 | Z65: 0
D66: O | E66: Total | F66: 0 | G66: 0 | H66: 0 | I66: 0 | J66: 0 | K66: 0 | L66: 0 | M66: 0 | N66: 0 | O66: 0 | P66: 0 | Q66: 0 | R66: 0 | S66: 0 | T66: 0 | U66: 0 | V66: 0 | W66: 0 | X66: 0 | Y66: 0 | Z66: 0
E67: Subsidio(-)/Contribucion(+) | F67: 0 | G67: 0 | H67: 0 | I67: 0 | J67: 0 | K67: 0 | L67: 0 | M67: 0 | N67: 0 | O67: 0 | P67: 0 | Q67: 0 | R67: 0 | S67: 0 | T67: 0 | U67: 0 | V67: 0 | W67: 0 | X67: 0 | Y67: 0 | Z67: 0
D68: T | E68: Total | F68: 0 | G68: 0 | H68: 0 | I68: 0 | J68: 0 | K68: 0 | L68: 0 | M68: 0 | N68: 0 | O68: 0 | P68: 0 | Q68: 0 | R68: 0 | S68: 0 | T68: 0 | U68: 0 | V68: 0 | W68: 0 | X68: 0 | Y68: 0 | Z68: 0
C69: OCCIDENTE | D69: Total | F69: 0 | G69: 0 | H69: 0 | I69: 0 | J69: 0 | K69: 0 | L69: 0 | M69: 0 | N69: 0 | O69: 0 | P69: 0 | Q69: 0 | R69: 0 | S69: 0 | T69: 0 | U69: 0 | V69: 0 | W69: 0 | X69: 0 | Y69: 0 | Z69: 0
B70: Aplicacion nuevos x reversion | C70: Total | F70: 40364.31 | G70: 1974.08 | H70: 1114.56 | I70: 585 | J70: 9457.65 | K70: 361.03 | L70: 0 | M70: 3166.94 | N70: 3091.65 | O70: 14632.85 | P70: 5391.5 | Q70: 589.05 | R70: 0 | S70: 0 | T70: 0 | U70: 0 | V70: 0 | W70: 0 | X70: 0 | Y70: 0 | Z70: 0
E71: Subsidio(-)/Contribucion(+) | F71: 1.2611229e+09 | G71: 1.4501764e+08 | H71: 81882192 | I71: 42987613 | J71: 1.8128397e+08 | K71: 6932108.8 | L71: 0 | M71: 59431480 | N71: 58073053 | O71: 2.7486104e+08 | P71: 3.9934319e+08 | Q71: 11310606 | R71: 0 | S71: 0 | T71: 0 | U71: 0 | V71: 0 | W71: 0 | X71: 0 | Y71: 0 | Z71: 0
D72: E | E72: Total | F72: 1.2611229e+09 | G72: 1.4501764e+08 | H72: 81882192 | I72: 42987613 | J72: 1.8128397e+08 | K72: 6932108.8 | L72: 0 | M72: 59431480 | N72: 58073053 | O72: 2.7486104e+08 | P72: 3.9934319e+08 | Q72: 11310606 | R72: 0 | S72: 0 | T72: 0 | U72: 0 | V72: 0 | W72: 0 | X72: 0 | Y72: 0 | Z72: 0
C73: ENEL | D73: Total | F73: 1.2611229e+09 | G73: 1.4501764e+08 | H73: 81882192 | I73: 42987613 | J73: 1.8128397e+08 | K73: 6932108.8 | L73: 0 | M73: 59431480 | N73: 58073053 | O73: 2.7486104e+08 | P73: 3.9934319e+08 | Q73: 11310606 | R73: 0 | S73: 0 | T73: 0 | U73: 0 | V73: 0 | W73: 0 | X73: 0 | Y73: 0 | Z73: 0
E74: Subsidio(-)/Contribucion(+) | F74: 0 | G74: 0 | H74: 0 | I74: 0 | J74: 0 | K74: 0 | L74: 0 | M74: 0 | N74: 0 | O74: 0 | P74: 0 | Q74: 0 | R74: 0 | S74: 0 | T74: 0 | U74: 0 | V74: 0 | W74: 0 | X74: 0 | Y74: 0 | Z74: 0
D75: E | E75: Total | F75: 0 | G75: 0 | H75: 0 | I75: 0 | J75: 0 | K75: 0 | L75: 0 | M75: 0 | N75: 0 | O75: 0 | P75: 0 | Q75: 0 | R75: 0 | S75: 0 | T75: 0 | U75: 0 | V75: 0 | W75: 0 | X75: 0 | Y75: 0 | Z75: 0
C76: ENERBIT | D76: Total | F76: 0 | G76: 0 | H76: 0 | I76: 0 | J76: 0 | K76: 0 | L76: 0 | M76: 0 | N76: 0 | O76: 0 | P76: 0 | Q76: 0 | R76: 0 | S76: 0 | T76: 0 | U76: 0 | V76: 0 | W76: 0 | X76: 0 | Y76: 0 | Z76: 0
E77: Subsidio(-)/Contribucion(+) | F77: 6082566.2 | G77: 1209162.8 | H77: 679361.72 | I77: 354481.28 | J77: 358187.27 | K77: -4705.56 | L77: 0 | M77: -42042.77 | N77: 41264.06 | O77: 193736.04 | P77: 3300638.3 | Q77: -7516.97 | R77: 0 | S77: 0 | T77: 0 | U77: 0 | V77: 0 | W77: 0 | X77: 0 | Y77: 0 | Z77: 0
D78: H | E78: Total | F78: 6082566.2 | G78: 1209162.8 | H78: 679361.72 | I78: 354481.28 | J78: 358187.27 | K78: -4705.56 | L78: 0 | M78: -42042.77 | N78: 41264.06 | O78: 193736.04 | P78: 3300638.3 | Q78: -7516.97 | R78: 0 | S78: 0 | T78: 0 | U78: 0 | V78: 0 | W78: 0 | X78: 0 | Y78: 0 | Z78: 0
E79: Subsidio(-)/Contribucion(+) | F79: 29193363 | G79: 5503604.9 | H79: 3036599.6 | I79: 1564692.2 | J79: 1181412.5 | K79: 26083.53 | L79: 0 | M79: 217934.27 | N79: 473929.76 | O79: 2182082.5 | P79: 14964294 | Q79: 42729.77 | R79: 0 | S79: 0 | T79: 0 | U79: 0 | V79: 0 | W79: 0 | X79: 0 | Y79: 0 | Z79: 0
D80: O | E80: Total | F80: 29193363 | G80: 5503604.9 | H80: 3036599.6 | I80: 1564692.2 | J80: 1181412.5 | K80: 26083.53 | L80: 0 | M80: 217934.27 | N80: 473929.76 | O80: 2182082.5 | P80: 14964294 | Q80: 42729.77 | R80: 0 | S80: 0 | T80: 0 | U80: 0 | V80: 0 | W80: 0 | X80: 0 | Y80: 0 | Z80: 0
E81: Subsidio(-)/Contribucion(+) | F81: 1.3274847e+08 | G81: 23581040 | H81: 13134900 | I81: 6932118 | J81: 8421230.3 | K81: 204893.95 | L81: 0 | M81: 1822856.4 | N81: 2503084.3 | O81: 11686632 | P81: 64127780 | Q81: 333934.56 | R81: 0 | S81: 0 | T81: 0 | U81: 0 | V81: 0 | W81: 0 | X81: 0 | Y81: 0 | Z81: 0
D82: T | E82: Total | F82: 1.3274847e+08 | G82: 23581040 | H82: 13134900 | I82: 6932118 | J82: 8421230.3 | K82: 204893.95 | L82: 0 | M82: 1822856.4 | N82: 2503084.3 | O82: 11686632 | P82: 64127780 | Q82: 333934.56 | R82: 0 | S82: 0 | T82: 0 | U82: 0 | V82: 0 | W82: 0 | X82: 0 | Y82: 0 | Z82: 0
C83: OCCIDENTE | D83: Total | F83: 1.680244e+08 | G83: 30293808 | H83: 16850862 | I83: 8851291.5 | J83: 9960830.1 | K83: 226271.92 | L83: 0 | M83: 1998747.9 | N83: 3018278.1 | O83: 14062451 | P83: 82392712 | Q83: 369147.36 | R83: 0 | S83: 0 | T83: 0 | U83: 0 | V83: 0 | W83: 0 | X83: 0 | Y83: 0 | Z83: 0
B84: Mes | C84: Total | F84: 1.4291473e+09 | G84: 1.7531145e+08 | H84: 98733053 | I84: 51838904 | J84: 1.912448e+08 | K84: 7158380.7 | L84: 0 | M84: 61430227 | N84: 61091331 | O84: 2.8892349e+08 | P84: 4.8173591e+08 | Q84: 11679754 | R84: 0 | S84: 0 | T84: 0 | U84: 0 | V84: 0 | W84: 0 | X84: 0 | Y84: 0 | Z84: 0
A85: Subs/Cont | B85: Total | F85: 1.4291877e+09 | G85: 1.7531342e+08 | H85: 98734168 | I85: 51839489 | J85: 1.9125425e+08 | K85: 7158741.7 | L85: 0 | M85: 61433394 | N85: 61094422 | O85: 2.8893812e+08 | P85: 4.817413e+08 | Q85: 11680343 | R85: 0 | S85: 0 | T85: 0 | U85: 0 | V85: 0 | W85: 0 | X85: 0 | Y85: 0 | Z85: 0
A86: Total | F86: 1.736512e+10 | G86: 1.0735386e+09 | H86: 6.0529609e+08 | I86: 3.1797447e+08 | J86: 3.9858123e+09 | K86: 1.4070145e+08 | L86: 25277316 | M86: 1.2363619e+09 | N86: 1.1919825e+09 | O86: 5.6411136e+09 | P86: 2.9174964e+09 | Q86: 2.2958492e+08 | R86: -17547.81 | S86: -2114.83 | T86: 522.25 | U86: 0 | V86: 0 | W86: 0 | X86: 0 | Y86: 0 | Z86: -0.03
C89: TOTAL | D89: OPORTUNO | E89: Total | F89: =F55+F84+F16-L16-L55 -> 1.7339794e+10 | G89: =G55+G16 -> 8.9822314e+08 | H89: =H55+H16 -> 5.0656079e+08 | I89: =I55+I16 -> 2.6613439e+08 | J89: =J55+J16 -> 3.794558e+09 | K89: =K55+K16 -> 1.335427e+08 | L89: =L55+L16 -> 25277316 | M89: =M55+M16 -> 1.1749285e+09 | N89: =N55+N16 -> 1.1308881e+09 | ... AP89: =AP55+AP16 -> 0
E90: Subsidio(-)/Contribucion(+) | F90: =F84 -> 1.4291473e+09
D91: EXTEMPORANEO | E91: Total | F91: =F70+F36-L36 -> 49580 | G91: =G36 -> 2007.44 | H91: =H36 -> 1133.38 | I91: =I36 -> 594.88 | J91: =J36 -> 0 | K91: =K36 -> 0 | L91: =L36 -> 0 | M91: =M36 -> 0 | N91: =N36 -> 0 | ... AP91: =AP36 -> 0
E92: Subsidio(-)/Contribucion(+) | F92: =F70 -> 40364.31
C94: RECIPROCIDAD | D94: OPORTUNO | E94: Total | F94: 0 | G94: 0 | H94: 0 | I94: 0 | J94: 0 | K94: 0 | L94: 0 | M94: 0 | N94: 0 | O94: 0 | P94: 0 | Q94: 0 | R94: 0 | S94: 0 | T94: 0 | U94: 0 | V94: 0 | W94: 0 | X94: 0 | Y94: 0 | Z94: 0 | AA94: 0 | AB94: 0 | AC94: 0 | AD94: 0 | AE94: 0 | AF94: 0 | AG94: 0 | AH94: 0 | AI94: 0 | AJ94: 0 | AK94: 0 | AL94: 0 | AM94: 0 | AN94: 0 | AO94: 0 | AP94: 0
E95: Subsidio(-)/Contribucion(+) | F95: 0
D96: EXTEMPORANEO | E96: Total | F96: 0 | G96: 0 | H96: 0 | I96: 0 | J96: 0 | K96: 0 | L96: 0 | M96: 0 | N96: 0 | O96: 0 | P96: 0 | Q96: 0 | R96: 0 | S96: 0 | T96: 0 | U96: 0 | V96: 0 | W96: 0 | X96: 0 | Y96: 0 | Z96: 0 | AA96: 0 | AB96: 0 | AC96: 0 | AD96: 0 | AE96: 0 | AF96: 0 | AG96: 0 | AH96: 0 | AI96: 0 | AJ96: 0 | AK96: 0 | AL96: 0 | AM96: 0 | AN96: 0 | AO96: 0 | AP96: 0
E97: Subsidio(-)/Contribucion(+) | F97: 0
C99: ENEL | D99: OPORTUNO | E99: Total | F99: =F73+F40+F8-L8-L40 -> 1.6560599e+10 | G99: =G40+G8 -> 8.0164503e+08 | H99: =H40+H8 -> 4.5232889e+08 | I99: =I40+I8 -> 2.3765315e+08 | J99: =J40+J8 -> 3.7433985e+09 | K99: =K40+K8 -> 1.3190921e+08 | L99: =L40+L8 -> 16516492 | M99: =M40+M8 -> 1.1605544e+09 | N99: =N40+N8 -> 1.1134701e+09 | ... AP99: =AP40+AP8 -> 0
E100: Subsidio(-)/Contribucion(+) | F100: =F73 -> 1.2611229e+09
D101: EXTEMPORANEO | E101: Total | F101: =F59+F21-L21 -> 49580 | G101: =G21 -> 2007.44 | H101: =H21 -> 1133.38 | I101: =I21 -> 594.88 | J101: =J21 -> 0 | K101: =K21 -> 0 | L101: =L21 -> 0 | M101: =M21 -> 0 | N101: =N21 -> 0 | ... AP101: =AP21 -> 0
E102: Subsidio(-)/Contribucion(+) | F102: =F59 -> 40364.31
C104: ENERBIT | D104: OPORTUNO | E104: Total | F104: =F76+F44-L44 -> 0 | G104: =G44 -> 0 | H104: =H44 -> 0 | I104: =I44 -> 0 | J104: =J44 -> 0 | K104: =K44 -> 0 | L104: =L44 -> 0 | M104: =M44 -> 0 | N104: =N44 -> 0 | ... AO104: =AO44 -> 0
E105: Subsidio(-)/Contribucion(+) | F105: =F76 -> 0
D106: EXTEMPORANEO | E106: Total | F106: =F62+F25-L25 -> 0 | G106: =G25 -> 0 | H106: =H25 -> 0 | I106: =I25 -> 0 | J106: =J25 -> 0 | K106: =K25 -> 0 | L106: =L25 -> 0 | M106: =M25 -> 0 | N106: =N25 -> 0 | ... AO106: =AO25 -> 0
E107: Subsidio(-)/Contribucion(+) | F107: =F62 -> 0
C109: OCCIDENTE | D109: OPORTUNO | E109: Total | F109: =F83+F54+F15-L15-L54 -> 7.7919441e+08 | G109: =G54+G15 -> 96578113 | H109: =H54+H15 -> 54231898 | I109: =I54+I15 -> 28481236 | J109: =J54+J15 -> 51159574 | K109: =K54+K15 -> 1633496.9 | L109: =L54+L15 -> 8760824 | M109: =M54+M15 -> 14374092 | N109: =N54+N15 -> 17418029 | ... AP109: =AP54+AP15 -> 0
...

Sheet Rem. Anticipos R2
B1: PROMOAMBIENTAL
E2: Total | F2: Componente TDF | G2: Componente TTL | H2: Componente TVIAT | I2: Aprovechamiento | J2: CCSA Prest.Aprov. | K2: Especiales | L2: Componente TCS | M2: Componente TLU | N2: Componente TBL | O2: Componente TRT | P2: CCSA Prest. No Aprov. | Q2: Deb/Cred | R2: Deb/Cred-otros
D3: Vlr Servicio | E3: 0 | F3: 0 | G3: 0 | H3: 0 | I3: 0 | J3: 0 | K3: 0 | L3: 0 | M3: 0 | N3: 0 | O3: 0 | P3: 0 | Q3: 0 | R3: 0
D4: Vlr Intereses | E4: 0 | F4: 0 | G4: 0 | H4: 0 | I4: 0 | J4: 0 | K4: 0 | L4: 0 | M4: 0 | N4: 0 | O4: 0 | P4: 0 | Q4: 0 | R4: 0
C5: A | D5: Total | E5: 0 | F5: 0 | G5: 0 | H5: 0 | I5: 0 | J5: 0 | K5: 0 | L5: 0 | M5: 0 | N5: 0 | O5: 0 | P5: 0 | Q5: 0 | R5: 0
B6: EAB | C6: Total | E6: 0 | F6: 0 | G6: 0 | H6: 0 | I6: 0 | J6: 0 | K6: 0 | L6: 0 | M6: 0 | N6: 0 | O6: 0 | P6: 0 | Q6: 0 | R6: 0
D7: Vlr Servicio | E7: 1.0475463e+08 | F7: 6975298.7 | G7: 3988878.1 | H7: 1891710.5 | I7: 21813833 | J7: 885097.78 | K7: 0 | L7: 8065770.6 | M7: 7536469.1 | N7: 33213004 | O7: 19115514 | P7: 1269059.6 | Q7: -0.63 | R7: 0
D8: Vlr Intereses | E8: 15816.77 | F8: 1163.38 | G8: 642.32 | H8: 341.55 | I8: 3027.69 | J8: 126.06 | K8: 0 | L8: 1110.61 | M8: 1054.19 | N8: 4963.73 | O8: 3181.55 | P8: 205.61 | Q8: 0.08 | R8: 0
C9: E | D9: Total | E9: 1.0477045e+08 | F9: 6976462.1 | G9: 3989520.4 | H9: 1892052 | I9: 21816861 | J9: 885223.84 | K9: 0 | L9: 8066881.2 | M9: 7537523.3 | N9: 33217967 | O9: 19118696 | P9: 1269265.2 | Q9: -0.55 | R9: 0
B10: ENEL | C10: Total | E10: 1.0477045e+08 | F10: 6976462.1 | G10: 3989520.4 | H10: 1892052 | I10: 21816861 | J10: 885223.84 | K10: 0 | L10: 8066881.2 | M10: 7537523.3 | N10: 33217967 | O10: 19118696 | P10: 1269265.2 | Q10: -0.55 | R10: 0
D11: Vlr Servicio | E11: 0 | F11: 0 | G11: 0 | H11: 0 | I11: 0 | J11: 0 | K11: 0 | L11: 0 | M11: 0 | N11: 0 | O11: 0 | P11: 0 | Q11: 0 | R11: 0
D12: Vlr Intereses | E12: 0 | F12: 0 | G12: 0 | H12: 0 | I12: 0 | J12: 0 | K12: 0 | L12: 0 | M12: 0 | N12: 0 | O12: 0 | P12: 0 | Q12: 0 | R12: 0
C13: E | D13: Total | E13: 0 | F13: 0 | G13: 0 | H13: 0 | I13: 0 | J13: 0 | K13: 0 | L13: 0 | M13: 0 | N13: 0 | O13: 0 | P13: 0 | Q13: 0 | R13: 0
B14: ENERBIT | C14: Total | E14: 0 | F14: 0 | G14: 0 | H14: 0 | I14: 0 | J14: 0 | K14: 0 | L14: 0 | M14: 0 | N14: 0 | O14: 0 | P14: 0 | Q14: 0 | R14: 0
D15: Vlr Servicio | E15: 2066328.1 | F15: 95509.13 | G15: 53786.6 | H15: 25807.38 | I15: 498516.51 | J15: 14869.65 | K15: 0 | L15: 154839.34 | M15: 178346.64 | N15: 760377.7 | O15: 261105.9 | P15: 23181.14 | Q15: -11.84 | R15: 0
D16: Vlr Intereses | E16: 53.09 | F16: 2.2 | G16: 1.21 | H16: 0.66 | I16: 13.81 | J16: 0.47 | K16: 0 | L16: 4.11 | M16: 4.2 | N16: 19.61 | O16: 6.05 | P16: 0.77 | Q16: 0 | R16: 0
C17: H | D17: Total | E17: 2066381.2 | F17: 95511.33 | G17: 53787.81 | H17: 25808.04 | I17: 498530.32 | J17: 14870.12 | K17: 0 | L17: 154843.45 | M17: 178350.84 | N17: 760397.31 | O17: 261111.95 | P17: 23181.91 | Q17: -11.84 | R17: 0
D18: Vlr Servicio | E18: 1667705.3 | F18: 94831.21 | G18: 53653.37 | H18: 23974.41 | I18: 360931.98 | J18: 13656.23 | K18: 0 | L18: 118901.31 | M18: 135021.65 | N18: 589240.87 | O18: 258802.75 | P18: 18683.4 | Q18: 8.11 | R18: 0
D19: Vlr Intereses | E19: 534.46 | F19: 31.52 | G19: 17.83 | H19: 9.34 | I19: 118.64 | J19: 4.45 | K19: 0 | L19: 39.04 | M19: 38.33 | N19: 181.9 | O19: 86.11 | P19: 7.3 | Q19: 0 | R19: 0
C20: O | D20: Total | E20: 1668239.8 | F20: 94862.73 | G20: 53671.2 | H20: 23983.75 | I20: 361050.62 | J20: 13660.68 | K20: 0 | L20: 118940.35 | M20: 135059.98 | N20: 589422.77 | O20: 258888.86 | P20: 18690.7 | Q20: 8.11 | R20: 0
D21: Vlr Servicio | E21: 18251249 | F21: 2466979.3 | G21: 1389961.4 | H21: 841642.79 | I21: 1865966 | J21: 51082.32 | K21: 0 | L21: 482981.31 | M21: 671717.75 | N21: 3043351.3 | O21: 7354815.6 | P21: 82820.66 | Q21: -69.46 | R21: 0
D22: Vlr Intereses | E22: 35670.7 | F22: 6587.48 | G22: 3721.93 | H22: 1963.44 | I22: 1660.15 | J22: 49.7 | K22: 0 | L22: 436.97 | M22: 541.21 | N22: 2526.1 | O22: 18102.54 | P22: 81.19 | Q22: -0.01 | R22: 0
C23: T | D23: Total | E23: 18286920 | F23: 2473566.8 | G23: 1393683.3 | H23: 843606.23 | I23: 1867626.2 | J23: 51132.02 | K23: 0 | L23: 483418.28 | M23: 672258.96 | N23: 3045877.4 | O23: 7372918.2 | P23: 82901.85 | Q23: -69.47 | R23: 0
B24: OCCIDENTE | C24: Total | E24: 22021541 | F24: 2663940.8 | G24: 1501142.3 | H24: 893398.02 | I24: 2727207.1 | J24: 79662.82 | K24: 0 | L24: 757202.08 | M24: 985669.78 | N24: 4395697.5 | O24: 7892919 | P24: 124774.46 | Q24: -73.2 | R24: 0
A25: Componente | B25: Total | E25: 1.2679199e+08 | F25: 9640402.9 | G25: 5490662.7 | H25: 2785450 | I25: 24544068 | J25: 964886.66 | K25: 0 | L25: 8824083.3 | M25: 8523193.1 | N25: 37613665 | O25: 27011615 | P25: 1394039.6 | Q25: -73.75 | R25: 0
D26: Subsidio(-)/Contribucion(+) | E26: 0 | F26: 0 | G26: 0 | H26: 0 | I26: 0 | J26: 0 | K26: 0 | L26: 0 | M26: 0 | N26: 0 | O26: 0 | P26: 0 | Q26: 0 | R26: 0
C27: A | D27: Total | E27: 0 | F27: 0 | G27: 0 | H27: 0 | I27: 0 | J27: 0 | K27: 0 | L27: 0 | M27: 0 | N27: 0 | O27: 0 | P27: 0 | Q27: 0 | R27: 0
B28: EAB | C28: Total | E28: 0 | F28: 0 | G28: 0 | H28: 0 | I28: 0 | J28: 0 | K28: 0 | L28: 0 | M28: 0 | N28: 0 | O28: 0 | P28: 0 | Q28: 0 | R28: 0
D29: Subsidio(-)/Contribucion(+) | E29: -7679309.2 | F29: 637875.65 | G29: 341985.27 | H29: 179997 | I29: -2784147.3 | J29: -136924.32 | K29: 0 | L29: -1201987.1 | M29: -1088414.8 | N29: -5141699 | O29: 1734349.6 | P29: -220344.15 | Q29: 0 | R29: 0
C30: E | D30: Total | E30: -7679309.2 | F30: 637875.65 | G30: 341985.27 | H30: 179997 | I30: -2784147.3 | J30: -136924.32 | K30: 0 | L30: -1201987.1 | M30: -1088414.8 | N30: -5141699 | O30: 1734349.6 | P30: -220344.15 | Q30: 0 | R30: 0
B31: ENEL | C31: Total | E31: -7679309.2 | F31: 637875.65 | G31: 341985.27 | H31: 179997 | I31: -2784147.3 | J31: -136924.32 | K31: 0 | L31: -1201987.1 | M31: -1088414.8 | N31: -5141699 | O31: 1734349.6 | P31: -220344.15 | Q31: 0 | R31: 0
D32: Subsidio(-)/Contribucion(+) | E32: 0 | F32: 0 | G32: 0 | H32: 0 | I32: 0 | J32: 0 | K32: 0 | L32: 0 | M32: 0 | N32: 0 | O32: 0 | P32: 0 | Q32: 0 | R32: 0
C33: E | D33: Total | E33: 0 | F33: 0 | G33: 0 | H33: 0 | I33: 0 | J33: 0 | K33: 0 | L33: 0 | M33: 0 | N33: 0 | O33: 0 | P33: 0 | Q33: 0 | R33: 0
B34: ENERBIT | C34: Total | E34: 0 | F34: 0 | G34: 0 | H34: 0 | I34: 0 | J34: 0 | K34: 0 | L34: 0 | M34: 0 | N34: 0 | O34: 0 | P34: 0 | Q34: 0 | R34: 0
D35: Subsidio(-)/Contribucion(+) | E35: -50554.72 | F35: 4736.11 | G35: 2674.07 | H35: 345.4 | I35: -23429.04 | J35: -1776.06 | K35: 0 | L35: -14634.19 | M35: -5072.07 | N35: -23919.85 | O35: 13249.96 | P35: -2729.05 | Q35: 0 | R35: 0
C36: H | D36: Total | E36: -50554.72 | F36: 4736.11 | G36: 2674.07 | H36: 345.4 | I36: -23429.04 | J36: -1776.06 | K36: 0 | L36: -14634.19 | M36: -5072.07 | N36: -23919.85 | O36: 13249.96 | P36: -2729.05 | Q36: 0 | R36: 0
D37: Subsidio(-)/Contribucion(+) | E37: -41372.31 | F37: 12793.71 | G37: 7223.37 | H37: 821.96 | I37: -13378.5 | J37: -1510.5 | K37: 0 | L37: -12344.21 | M37: -12400.64 | N37: -55249.52 | O37: 35136.41 | P37: -2464.39 | Q37: 0 | R37: 0
C38: O | D38: Total | E38: -41372.31 | F38: 12793.71 | G38: 7223.37 | H38: 821.96 | I38: -13378.5 | J38: -1510.5 | K38: 0 | L38: -12344.21 | M38: -12400.64 | N38: -55249.52 | O38: 35136.41 | P38: -2464.39 | Q38: 0 | R38: 0
D39: Subsidio(-)/Contribucion(+) | E39: 6927796.9 | F39: 1130170.6 | G39: 623361.6 | H39: 304609.91 | I39: 533203.52 | J39: 13692.34 | K39: 0 | L39: 126469.3 | M39: 172463.37 | N39: 810419.93 | O39: 3191349.9 | P39: 22056.36 | Q39: 0 | R39: 0
C40: T | D40: Total | E40: 6927796.9 | F40: 1130170.6 | G40: 623361.6 | H40: 304609.91 | I40: 533203.52 | J40: 13692.34 | K40: 0 | L40: 126469.3 | M40: 172463.37 | N40: 810419.93 | O40: 3191349.9 | P40: 22056.36 | Q40: 0 | R40: 0
B41: OCCIDENTE | C41: Total | E41: 6835869.9 | F41: 1147700.5 | G41: 633259.04 | H41: 305777.27 | I41: 496395.98 | J41: 10405.78 | K41: 0 | L41: 99490.9 | M41: 154990.66 | N41: 731250.56 | O41: 3239736.3 | P41: 16862.92 | Q41: 0 | R41: 0
A42: Subs/Cont | B42: Total | E42: -843439.3 | F42: 1785576.1 | G42: 975244.31 | H42: 485774.27 | I42: -2287751.4 | J42: -126518.54 | K42: 0 | L42: -1102496.2 | M42: -933424.09 | N42: -4410448.5 | O42: 4974085.9 | P42: -203481.23 | Q42: 0 | R42: 0
A43: Total | E43: 1.2594855e+08 | F43: 11425979 | G43: 6465907 | H43: 3271224.3 | I43: 22256317 | J43: 838368.12 | K43: 0 | L43: 7721587.1 | M43: 7589769 | N43: 33203216 | O43: 31985701 | P43: 1190558.4 | Q43: -73.75 | R43: 0
B57: TOTAL | C57: OPORTUNO | D57: Total | E57: =E25+E42-K25 -> 1.2594855e+08 | F57: =F25 -> 9640402.9 | G57: =G25 -> 5490662.7 | H57: =H25 -> 2785450 | I57: =I25 -> 24544068 | J57: =J25 -> 964886.66 | K57: =K25 -> 0 | L57: =L25 -> 8824083.3 | M57: =M25 -> 8523193.1 | ... S57: =S25 -> 0
D58: Subsidio(-)/Contribucion(+) | E58: =E42 -> -843439.3
B60: RECIPROCIDAD | C60: OPORTUNO | D60: Total | E60: 0 | F60: 0 | G60: 0 | H60: 0 | I60: 0 | J60: 0 | K60: 0 | L60: 0 | M60: 0 | N60: 0 | O60: 0 | P60: 0 | Q60: 0 | R60: 0 | S60: 0
D61: Subsidio(-)/Contribucion(+) | E61: 0
B63: ENEL | C63: OPORTUNO | D63: Total | E63: =E31+E28+E10+E6-K6-K10 -> 97091143 | F63: =F10+F6 -> 6976462.1 | G63: =G10+G6 -> 3989520.4 | H63: =H10+H6 -> 1892052 | I63: =I10+I6 -> 21816861 | J63: =J10+J6 -> 885223.84 | K63: =K10+K6 -> 0 | L63: =L10+L6 -> 8066881.2 | M63: =M10+M6 -> 7537523.3 | ... S63: =S10+S6 -> 0
D64: Subsidio(-)/Contribucion(+) | E64: =E31+E28 -> -7679309.2
B66: ENERBIT | C66: OPORTUNO | D66: Total | E66: =E34+E14-K14 -> 0 | F66: =F14 -> 0 | G66: 0 | H66: 0 | I66: 0 | J66: 0 | K66: 0 | L66: 0 | M66: 0 | N66: 0 | O66: 0 | P66: 0 | Q66: 0 | R66: 0
D67: Subsidio(-)/Contribucion(+) | E67: =E34 -> 0
B69: OCCIDENTE | C69: OPORTUNO | D69: Total | E69: =E24+E41-K24 -> 28857411 | F69: =F24 -> 2663940.8 | G69: =G24 -> 1501142.3 | H69: =H24 -> 893398.02 | I69: =I24 -> 2727207.1 | J69: =J24 -> 79662.82 | K69: =K24 -> 0 | L69: =L24 -> 757202.08 | M69: =M24 -> 985669.78 | ... S69: =S24 -> 0
D70: Subsidio(-)/Contribucion(+) | E70: =E41 -> 6835869.9
B72: CIUDAD LIMPIA-ACUEDUCTO | C72: OPORTUNO | D72: Total | E72: 0 | F72: 0 | G72: 0 | H72: 0 | I72: 0 | J72: 0 | K72: 0 | L72: 0 | M72: 0 | N72: 0 | O72: 0 | P72: 0 | Q72: 0 | R72: 0 | S72: 0
D73: Subsidio(-)/Contribucion(+) | E73: 0
B75: LIME
E76: Total | F76: Componente TDF | G76: Componente TTL | H76: Componente TVIAT | I76: Aprovechamiento | J76: CCSA Prest.Aprov. | K76: Especiales | L76: Componente TCS | M76: Componente TLU | N76: Componente TBL | O76: Componente TRT | P76: CCSA Prest. No Aprov. | Q76: Deb/Cred | R76: Deb/Cred-otros
D77: Vlr Servicio | E77: 0 | F77: 0 | G77: 0 | H77: 0 | I77: 0 | J77: 0 | K77: 0 | L77: 0 | M77: 0 | N77: 0 | O77: 0 | P77: 0 | Q77: 0 | R77: 0
D78: Vlr Intereses | E78: 0 | F78: 0 | G78: 0 | H78: 0 | I78: 0 | J78: 0 | K78: 0 | L78: 0 | M78: 0 | N78: 0 | O78: 0 | P78: 0 | Q78: 0 | R78: 0
C79: A | D79: Total | E79: 0 | F79: 0 | G79: 0 | H79: 0 | I79: 0 | J79: 0 | K79: 0 | L79: 0 | M79: 0 | N79: 0 | O79: 0 | P79: 0 | Q79: 0 | R79: 0
B80: EAB | C80: Total | E80: 0 | F80: 0 | G80: 0 | H80: 0 | I80: 0 | J80: 0 | K80: 0 | L80: 0 | M80: 0 | N80: 0 | O80: 0 | P80: 0 | Q80: 0 | R80: 0
D81: Vlr Servicio | E81: 71702409 | F81: 4119196.9 | G81: 2445784.3 | H81: 988499.28 | I81: 18958221 | J81: 632942.16 | K81: 0 | L81: 5923929.5 | M81: 5752498 | N81: 23264099 | O81: 8731555.6 | P81: 885560.39 | Q81: 122.44 | R81: 0
D82: Vlr Intereses | E82: 95038.85 | F82: 9024.33 | G82: 4730.41 | H82: 2571.82 | I82: 19131.48 | J82: 648.99 | K82: 0 | L82: 5659.74 | M82: 6117.92 | N82: 28047 | O82: 18026.08 | P82: 1059.27 | Q82: 21.81 | R82: 0
C83: E | D83: Total | E83: 71797448 | F83: 4128221.2 | G83: 2450514.8 | H83: 991071.1 | I83: 18977353 | J83: 633591.15 | K83: 0 | L83: 5929589.2 | M83: 5758616 | N83: 23292146 | O83: 8749581.6 | P83: 886619.66 | Q83: 144.25 | R83: 0
B84: ENEL | C84: Total | E84: 71797448 | F84: 4128221.2 | G84: 2450514.8 | H84: 991071.1 | I84: 18977353 | J84: 633591.15 | K84: 0 | L84: 5929589.2 | M84: 5758616 | N84: 23292146 | O84: 8749581.6 | P84: 886619.66 | Q84: 144.25 | R84: 0
D85: Vlr Servicio | E85: 22093259 | F85: 1421141.7 | G85: 778144.37 | H85: 342749 | I85: 6034872.3 | J85: 158457.39 | K85: 0 | L85: 1458906.2 | M85: 1770857 | N85: 5515356 | O85: 4418000.6 | P85: 194910.48 | Q85: -136.28 | R85: 0
D86: Vlr Intereses | E86: 17021.45 | F86: 1413.33 | G86: 751.77 | H86: 431.98 | I86: 3886.9 | J86: 91.78 | K86: 0 | L86: 805.04 | M86: 1177.57 | N86: 5500.97 | O86: 2812.31 | P86: 149.78 | Q86: 0.02 | R86: 0
C87: 1 | D87: Total | E87: 22110280 | F87: 1422555.1 | G87: 778896.14 | H87: 343180.98 | I87: 6038759.2 | J87: 158549.17 | K87: 0 | L87: 1459711.3 | M87: 1772034.6 | N87: 5520857 | O87: 4420812.9 | P87: 195060.26 | Q87: -136.26 | R87: 0
D88: Vlr Servicio | E88: 1616173.6 | F88: 90529.5 | G88: 47826.83 | H88: 24108.87 | I88: 433611.64 | J88: 13309 | K88: 0 | L88: 100420.03 | M88: 121133.57 | N88: 423371.69 | O88: 346736.28 | P88: 15115.46 | Q88: 10.76 | R88: 0
D89: Vlr Intereses | E89: 406.42 | F89: 41.47 | G89: 21.23 | H89: 12.67 | I89: 83.96 | J89: 1.95 | K89: 0 | L89: 17.12 | M89: 25.02 | N89: 117.24 | O89: 82.58 | P89: 3.19 | Q89: -0.01 | R89: 0
C90: 2 | D90: Total | E90: 1616580.1 | F90: 90570.97 | G90: 47848.06 | H90: 24121.54 | I90: 433695.6 | J90: 13310.95 | K90: 0 | L90: 100437.15 | M90: 121158.59 | N90: 423488.93 | O90: 346818.86 | P90: 15118.65 | Q90: 10.75 | R90: 0
D91: Vlr Servicio | E91: 0 | F91: 0 | G91: 0 | H91: 0 | I91: 0 | J91: 0 | K91: 0 | L91: 0 | M91: 0 | N91: 0 | O91: 0 | P91: 0 | Q91: 0 | R91: 0
D92: Vlr Intereses | E92: 0 | F92: 0 | G92: 0 | H92: 0 | I92: 0 | J92: 0 | K92: 0 | L92: 0 | M92: 0 | N92: 0 | O92: 0 | P92: 0 | Q92: 0 | R92: 0
C93: 3 | D93: Total | E93: 0 | F93: 0 | G93: 0 | H93: 0 | I93: 0 | J93: 0 | K93: 0 | L93: 0 | M93: 0 | N93: 0 | O93: 0 | P93: 0 | Q93: 0 | R93: 0
D94: Vlr Servicio | E94: 0 | F94: 0 | G94: 0 | H94: 0 | I94: 0 | J94: 0 | K94: 0 | L94: 0 | M94: 0 | N94: 0 | O94: 0 | P94: 0 | Q94: 0 | R94: 0
D95: Vlr Intereses | E95: 0 | F95: 0 | G95: 0 | H95: 0 | I95: 0 | J95: 0 | K95: 0 | L95: 0 | M95: 0 | N95: 0 | O95: 0 | P95: 0 | Q95: 0 | R95: 0
C96: 4 | D96: Total | E96: 0 | F96: 0 | G96: 0 | H96: 0 | I96: 0 | J96: 0 | K96: 0 | L96: 0 | M96: 0 | N96: 0 | O96: 0 | P96: 0 | Q96: 0 | R96: 0
D97: Vlr Servicio | E97: 27690465 | F97: 1701572.3 | G97: 971553.65 | H97: 405189.21 | I97: 7839404.6 | J97: 234550.49 | K97: 0 | L97: 2072653.2 | M97: 2236560 | N97: 8259845.4 | O97: 3677240.6 | P97: 291796.3 | Q97: 99.64 | R97: 0
D98: Vlr Intereses | E98: 220606.32 | F98: 2079.3 | G98: 1101.6 | H98: 634.08 | I98: 4056.19 | J98: 100.05 | K98: 0 | L98: 31497.06 | M98: 39422.95 | N98: 118658.47 | O98: 22893.4 | P98: 163.27 | Q98: -0.05 | R98: 0
C99: 5 | D99: Total | E99: 27911072 | F99: 1703651.6 | G99: 972655.25 | H99: 405823.29 | I99: 7843460.8 | J99: 234650.54 | K99: 0 | L99: 2104150.3 | M99: 2275982.9 | N99: 8378503.9 | O99: 3700134 | P99: 291959.57 | Q99: 99.59 | R99: 0
D100: Vlr Servicio | E100: 0 | F100: 0 | G100: 0 | H100: 0 | I100: 0 | J100: 0 | K100: 0 | L100: 0 | M100: 0 | N100: 0 | O100: 0 | P100: 0 | Q100: 0 | R100: 0
D101: Vlr Intereses | E101: 0 | F101: 0 | G101: 0 | H101: 0 | I101: 0 | J101: 0 | K101: 0 | L101: 0 | M101: 0 | N101: 0 | O101: 0 | P101: 0 | Q101: 0 | R101: 0
C102: 6 | D102: Total | E102: 0 | F102: 0 | G102: 0 | H102: 0 | I102: 0 | J102: 0 | K102: 0 | L102: 0 | M102: 0 | N102: 0 | O102: 0 | P102: 0 | Q102: 0 | R102: 0
D103: Vlr Servicio | E103: 831919.29 | F103: 0 | G103: 0 | H103: 0 | I103: 0 | J103: 0 | K103: 0 | L103: 4321.14 | M103: 6126.52 | N103: 6629.52 | O103: 814845.14 | P103: 0 | Q103: -3.03 | R103: 0
D104: Vlr Intereses | E104: 0 | F104: 0 | G104: 0 | H104: 0 | I104: 0 | J104: 0 | K104: 0 | L104: 0 | M104: 0 | N104: 0 | O104: 0 | P104: 0 | Q104: 0 | R104: 0
C105: 9 | D105: Total | E105: 831919.29 | F105: 0 | G105: 0 | H105: 0 | I105: 0 | J105: 0 | K105: 0 | L105: 4321.14 | M105: 6126.52 | N105: 6629.52 | O105: 814845.14 | P105: 0 | Q105: -3.03 | R105: 0
B106: NUEVO ESQUEMA | C106: Total | E106: 52469851 | F106: 3216777.6 | G106: 1799399.4 | H106: 773125.81 | I106: 14315916 | J106: 406510.66 | K106: 0 | L106: 3668619.8 | M106: 4175302.6 | N106: 14329479 | O106: 9282610.9 | P106: 502138.48 | Q106: -28.95 | R106: 0
D107: Vlr Servicio | E107: 11075335 | F107: 821378.55 | G107: 465927.35 | H107: 215214.87 | I107: 2963943.3 | J107: 82515.34 | K107: 0 | L107: 658290.51 | M107: 834824.5 | N107: 3348380.9 | O107: 1591238.4 | P107: 93600.37 | Q107: 20.46 | R107: 0
D108: Vlr Intereses | E108: 20136.06 | F108: 2455.33 | G108: 1132.97 | H108: 675.49 | I108: 3924.78 | J108: 92.44 | K108: 0 | L108: 810.75 | M108: 1058.05 | N108: 4906.98 | O108: 4928.45 | P108: 150.8 | Q108: 0.02 | R108: 0
C109: H | D109: Total | E109: 11095471 | F109: 823833.88 | G109: 467060.32 | H109: 215890.36 | I109: 2967868 | J109: 82607.78 | K109: 0 | L109: 659101.26 | M109: 835882.55 | N109: 3353287.9 | O109: 1596166.8 | P109: 93751.17 | Q109: 20.48 | R109: 0
D110: Vlr Servicio | E110: 38346937 | F110: 3218428.2 | G110: 1802927.9 | H110: 864947.8 | I110: 8956303.6 | J110: 272835.85 | K110: 0 | L110: 2439524.5 | M110: 2783253.1 | N110: 10966064 | O110: 6668396.5 | P110: 374240.28 | Q110: 15.41 | R110: 0
D111: Vlr Intereses | E111: 435116.55 | F111: 47759.13 | G111: 22622.8 | H111: 11464.99 | I111: 86745.59 | J111: 2665.2 | K111: 0 | L111: 22811.78 | M111: 28601.42 | N111: 113175.65 | O111: 94916.98 | P111: 4352.25 | Q111: 0.76 | R111: 0
C112: O | D112: Total | E112: 38782054 | F112: 3266187.3 | G112: 1825550.7 | H112: 876412.79 | I112: 9043049.2 | J112: 275501.05 | K112: 0 | L112: 2462336.3 | M112: 2811854.5 | N112: 11079240 | O112: 6763313.5 | P112: 378592.53 | Q112: 16.17 | R112: 0
D113: Vlr Servicio | E113: 42498049 | F113: 5756619.9 | G113: 3216233.5 | H113: 1817946.3 | I113: 1910670.2 | J113: 53108.69 | K113: 0 | L113: 473073.31 | M113: 611269.16 | N113: 2270384.9 | O113: 26329366 | P113: 59347.07 | Q113: 29.67 | R113: 0
D114: Vlr Intereses | E114: 9526.39 | F114: 1485.4 | G114: 831.8 | H114: 440.06 | I114: 1225.21 | J114: 39.88 | K114: 0 | L114: 349.95 | M114: 378.78 | N114: 1754.01 | O114: 2956.22 | P114: 65.09 | Q114: -0.01 | R114: 0
C115: T | D115: Total | E115: 42507575 | F115: 5758105.3 | G115: 3217065.3 | H115: 1818386.4 | I115: 1911895.4 | J115: 53148.57 | K115: 0 | L115: 473423.26 | M115: 611647.94 | N115: 2272138.9 | O115: 26332322 | P115: 59412.16 | Q115: 29.66 | R115: 0
B116: OCCIDENTE | C116: Total | E116: 92385100 | F116: 9848126.5 | G116: 5509676.3 | H116: 2910689.5 | I116: 13922813 | J116: 411257.4 | K116: 0 | L116: 3594860.9 | M116: 4259385 | N116: 16704667 | O116: 34691803 | P116: 531755.86 | Q116: 66.31 | R116: 0
A117: Componente | B117: Total | E117: 2.166524e+08 | F117: 17193125 | G117: 9759590.5 | H117: 4674886.5 | I117: 47216081 | J117: 1451359.2 | K117: 0 | L117: 13193070 | M117: 14193304 | N117: 54326292 | O117: 52723995 | P117: 1920514 | Q117: 181.61 | R117: 0
D118: Subsidio(-)/Contribucion(+) | E118: 0 | F118: 0 | G118: 0 | H118: 0 | I118: 0 | J118: 0 | K118: 0 | L118: 0 | M118: 0 | N118: 0 | O118: 0 | P118: 0 | Q118: 0 | R118: 0
C119: A | D119: Total | E119: 0 | F119: 0 | G119: 0 | H119: 0 | I119: 0 | J119: 0 | K119: 0 | L119: 0 | M119: 0 | N119: 0 | O119: 0 | P119: 0 | Q119: 0 | R119: 0
...

Sheet Reversion Pagos R4
B1: PROMOAMBIENTAL
D2: Total | E2: Componente TDF | F2: Componente TTL | G2: Componente TVIAT | H2: Aprovechamiento | I2: CCSA Prest.Aprov. | J2: Componente TCS | K2: Componente TLU | L2: Componente TBL | M2: Componente TRT | N2: CCSA Prest. No Aprov. | O2: Ajuste Decena | P2: SERVICIO ESPECIALES | Q2: Ajuste Recargo Aseo | R2: Otros
C3: Vlr Servicio | D3: -15794348 | E3: -792653.97 | F3: -443520.95 | G3: -235150.45 | H3: -3808729.7 | I3: -139986.99 | J3: -1241530.6 | K3: -1202003.5 | L3: -5520144.8 | M3: -2181286.4 | N3: -229451.13 | O3: 110.22 | P3: 0 | Q3: 0 | R3: 0
C4: Vlr Intereses | D4: -23575 | E4: -1070.04 | F4: -517.3 | G4: -287.09 | H4: -5416.02 | I4: -247.11 | J4: -2165.7 | K4: -1867.54 | L4: -8699.17 | M4: -2902.92 | N4: -402.93 | O4: 0.82 | P4: 0 | Q4: 0 | R4: 0
B5: Componente | C5: Total | D5: -15817923 | E5: -793724.01 | F5: -444038.25 | G5: -235437.54 | H5: -3814145.7 | I5: -140234.1 | J5: -1243696.3 | K5: -1203871 | L5: -5528844 | M5: -2184189.4 | N5: -229854.06 | O5: 111.04 | P5: 0 | Q5: 0 | R5: 0
C6: Subsidio(-)/Contribucion(+) | D6: 283961.51 | E6: -50016.63 | F6: -28439.29 | G6: -8473.6 | H6: 123071.72 | I6: 6856.23 | J6: 57818.27 | K6: 55412.62 | L6: 258242.83 | M6: -141530 | N6: 11019.36 | O6: 0 | P6: 0 | Q6: 0 | R6: 0
B7: Subs/Cont | C7: Total | D7: 283961.51 | E7: -50016.63 | F7: -28439.29 | G7: -8473.6 | H7: 123071.72 | I7: 6856.23 | J7: 57818.27 | K7: 55412.62 | L7: 258242.83 | M7: -141530 | N7: 11019.36 | O7: 0 | P7: 0 | Q7: 0 | R7: 0
A8: ENEL | B8: Total | D8: -15533962 | E8: -843740.64 | F8: -472477.54 | G8: -243911.14 | H8: -3691074 | I8: -133377.87 | J8: -1185878 | K8: -1148458.4 | L8: -5270601.2 | M8: -2325719.4 | N8: -218834.7 | O8: 111.04 | P8: 0 | Q8: 0 | R8: 0
C9: Vlr Servicio | D9: 0 | E9: 0 | F9: 0 | G9: 0 | H9: 0 | I9: 0 | J9: 0 | K9: 0 | L9: 0 | M9: 0 | N9: 0 | O9: 0 | P9: 0 | Q9: 0 | R9: 0
C10: Vlr Intereses | D10: 0 | E10: 0 | F10: 0 | G10: 0 | H10: 0 | I10: 0 | J10: 0 | K10: 0 | L10: 0 | M10: 0 | N10: 0 | O10: 0 | P10: 0 | Q10: 0 | R10: 0
B11: Componente | C11: Total | D11: 0 | E11: 0 | F11: 0 | G11: 0 | H11: 0 | I11: 0 | J11: 0 | K11: 0 | L11: 0 | M11: 0 | N11: 0 | O11: 0 | P11: 0 | Q11: 0 | R11: 0
C12: Subsidio(-)/Contribucion(+) | D12: 0 | E12: 0 | F12: 0 | G12: 0 | H12: 0 | I12: 0 | J12: 0 | K12: 0 | L12: 0 | M12: 0 | N12: 0 | O12: 0 | P12: 0 | Q12: 0 | R12: 0
B13: Subs/Cont | C13: Total | D13: 0 | E13: 0 | F13: 0 | G13: 0 | H13: 0 | I13: 0 | J13: 0 | K13: 0 | L13: 0 | M13: 0 | N13: 0 | O13: 0 | P13: 0 | Q13: 0 | R13: 0
A14: ENERBIT | B14: Total | D14: 0 | E14: 0 | F14: 0 | G14: 0 | H14: 0 | I14: 0 | J14: 0 | K14: 0 | L14: 0 | M14: 0 | N14: 0 | O14: 0 | P14: 0 | Q14: 0 | R14: 0
C15: Vlr Servicio | D15: -762167.27 | E15: -48309.04 | F15: -26455.25 | G15: -13891.43 | H15: -192277.47 | I15: -4768.85 | J15: -58119.3 | K15: -51919.38 | L15: -246558.5 | M15: -112077.14 | N15: -7780.61 | O15: -10.3 | P15: 0 | Q15: 0 | R15: 0
C16: Vlr Intereses | D16: -177.06 | E16: -11.22 | F16: -6.34 | G16: -3.35 | H16: -43.6 | I16: -1.05 | J16: -9.24 | K16: -12.57 | L16: -57.05 | M16: -30.93 | N16: -1.71 | O16: 0 | P16: 0 | Q16: 0 | R16: 0
B17: Componente | C17: Total | D17: -762344.33 | E17: -48320.26 | F17: -26461.59 | G17: -13894.78 | H17: -192321.07 | I17: -4769.9 | J17: -58128.54 | K17: -51931.95 | L17: -246615.55 | M17: -112108.07 | N17: -7782.32 | O17: -10.3 | P17: 0 | Q17: 0 | R17: 0
C18: Subsidio(-)/Contribucion(+) | D18: -240407.06 | E18: -14057.56 | F18: -7937.89 | G18: -4170.17 | H18: -58249.85 | I18: -1605.37 | J18: -14082 | K18: -17535.88 | L18: -81716.35 | M18: -38432.73 | N18: -2619.26 | O18: 0 | P18: 0 | Q18: 0 | R18: 0
B19: Subs/Cont | C19: Total | D19: -240407.06 | E19: -14057.56 | F19: -7937.89 | G19: -4170.17 | H19: -58249.85 | I19: -1605.37 | J19: -14082 | K19: -17535.88 | L19: -81716.35 | M19: -38432.73 | N19: -2619.26 | O19: 0 | P19: 0 | Q19: 0 | R19: 0
A20: OCCIDENTE | B20: Total | D20: -1002751.4 | E20: -62377.82 | F20: -34399.48 | G20: -18064.95 | H20: -250570.92 | I20: -6375.27 | J20: -72210.54 | K20: -69467.83 | L20: -328331.9 | M20: -150540.8 | N20: -10401.58 | O20: -10.3 | P20: 0 | Q20: 0 | R20: 0
A21: Total | D21: -16536713 | E21: -906118.46 | F21: -506877.02 | G21: -261976.09 | H21: -3941644.9 | I21: -139753.14 | J21: -1258088.5 | K21: -1217926.2 | L21: -5598933.1 | M21: -2476260.1 | N21: -229236.28 | O21: 100.74 | P21: 0 | Q21: 0 | R21: 0
A79: TOTAL | B79: OPORTUNO | C79: Total | D79: =D21-P21 -> -16536713 | E79: =E5+E17 -> -842044.27 | F79: =F5+F17 -> -470499.84 | G79: =G5+G17 -> -249332.32 | H79: =H5+H17 -> -4006466.8 | I79: =I5+I17 -> -145004 | J79: =J5+J17 -> -1301824.8 | K79: =K5+K17 -> -1255802.9 | L79: =L5+L17 -> -5775459.5 | ... R79: =R5+R17 -> 0
C80: Subsidio(-)/Contribucion(+) | D80: =D7+D19 -> 43554.45
A82: RECIPROCIDAD | B82: OPORTUNO | C82: Total | D82: 0 | E82: 0 | F82: 0 | G82: 0 | H82: 0 | I82: 0 | J82: 0 | K82: 0 | L82: 0 | M82: 0 | N82: 0 | O82: 0 | P82: 0 | Q82: 0 | R82: 0
C83: Subsidio(-)/Contribucion(+) | D83: 0
A85: ENEL | B85: OPORTUNO | C85: Total | D85: =D8-P8 -> -15533962 | E85: =E5 -> -793724.01 | F85: =F5 -> -444038.25 | G85: =G5 -> -235437.54 | H85: =H5 -> -3814145.7 | I85: =I5 -> -140234.1 | J85: =J5 -> -1243696.3 | K85: =K5 -> -1203871 | L85: =L5 -> -5528844 | ... R85: =R5 -> 0
C86: Subsidio(-)/Contribucion(+) | D86: =D7 -> 283961.51
A88: ENERBIT | B88: OPORTUNO | C88: Total | D88: =D14-P14 -> 0 | E88: =E11 -> 0 | F88: =F11 -> 0 | G88: =G11 -> 0 | H88: =H11 -> 0 | I88: =I11 -> 0 | J88: =J11 -> 0 | K88: =K11 -> 0 | L88: =L11 -> 0 | ... R88: =R11 -> 0
C89: Subsidio(-)/Contribucion(+) | D89: =D13 -> 0
A91: OCCIDENTE | B91: OPORTUNO | C91: Total | D91: =D20-P20 -> -1002751.4 | E91: =E17 -> -48320.26 | F91: =F17 -> -26461.59 | G91: =G17 -> -13894.78 | H91: =H17 -> -192321.07 | I91: =I17 -> -4769.9 | J91: =J17 -> -58128.54 | K91: =K17 -> -51931.95 | L91: =L17 -> -246615.55 | ... R91: =R17 -> 0
C92: Subsidio(-)/Contribucion(+) | D92: =D19 -> -240407.06
A94: CIUDAD LIMPIA-ACUEDUCTO | B94: OPORTUNO | C94: Total | D94: 0 | E94: 0 | F94: 0 | G94: 0 | H94: 0 | I94: 0 | J94: 0 | K94: 0 | L94: 0 | M94: 0 | N94: 0 | O94: 0 | P94: 0 | Q94: 0 | R94: 0
C95: Subsidio(-)/Contribucion(+) | D95: 0
B97: LIME
D98: Total | E98: Componente TDF | F98: Componente TTL | G98: Componente TVIAT | H98: Aprovechamiento | I98: CCSA Prest.Aprov. | J98: Componente TCS | K98: Componente TLU | L98: Componente TBL | M98: Componente TRT | N98: CCSA Prest. No Aprov. | O98: Ajuste Decena | P98: SERVICIO ESPECIALES | Q98: Ajuste Recargo Aseo | R98: Otros
C99: Vlr Servicio | D99: -53998016 | E99: -11667185 | F99: -5414703.5 | G99: -2951482.2 | H99: -3201477.2 | I99: -115838.75 | J99: -1017620.8 | K99: -1016768.4 | L99: -4764304 | M99: -23659661 | N99: -188999.83 | O99: 24.58 | P99: 0 | Q99: 0 | R99: 0
C100: Vlr Intereses | D100: -15789582 | E100: -4170790.8 | F100: -1943304.3 | G100: -1075258 | H100: -52026.8 | I100: -1440.2 | J100: -12737.8 | K100: -15000.59 | L100: -66290.83 | M100: -8450381.3 | N100: -2350.38 | O100: -0.84 | P100: 0 | Q100: 0 | R100: 0
B101: Componente | C101: Total | D101: -69787598 | E101: -15837976 | F101: -7358007.8 | G101: -4026740.1 | H101: -3253504 | I101: -117278.95 | J101: -1030358.6 | K101: -1031769 | L101: -4830594.8 | M101: -32110042 | N101: -191350.21 | O101: 23.74 | P101: 0 | Q101: 0 | R101: 0
C102: Subsidio(-)/Contribucion(+) | D102: -991410.96 | E102: -916794.52 | F102: -399784.58 | G102: -225583.16 | H102: 753139.3 | I102: 27321.94 | J102: 241143.71 | K102: 238753.51 | L102: 1113806.2 | M102: -1867991.1 | N102: 44577.73 | O102: 0 | P102: 0 | Q102: 0 | R102: 0
B103: Subs/Cont | C103: Total | D103: -991410.96 | E103: -916794.52 | F103: -399784.58 | G103: -225583.16 | H103: 753139.3 | I103: 27321.94 | J103: 241143.71 | K103: 238753.51 | L103: 1113806.2 | M103: -1867991.1 | N103: 44577.73 | O103: 0 | P103: 0 | Q103: 0 | R103: 0
A104: ENEL | B104: Total | D104: -70779009 | E104: -16754771 | F104: -7757792.4 | G104: -4252323.3 | H104: -2500364.7 | I104: -89957.01 | J104: -789214.84 | K104: -793015.48 | L104: -3716788.6 | M104: -33978033 | N104: -146772.48 | O104: 23.74 | P104: 0 | Q104: 0 | R104: 0
C105: Vlr Servicio | D105: 0 | E105: 0 | F105: 0 | G105: 0 | H105: 0 | I105: 0 | J105: 0 | K105: 0 | L105: 0 | M105: 0 | N105: 0 | O105: 0 | P105: 0 | Q105: 0 | R105: 0
C106: Vlr Intereses | D106: 0 | E106: 0 | F106: 0 | G106: 0 | H106: 0 | I106: 0 | J106: 0 | K106: 0 | L106: 0 | M106: 0 | N106: 0 | O106: 0 | P106: 0 | Q106: 0 | R106: 0
B107: Componente | C107: Total | D107: 0 | E107: 0 | F107: 0 | G107: 0 | H107: 0 | I107: 0 | J107: 0 | K107: 0 | L107: 0 | M107: 0 | N107: 0 | O107: 0 | P107: 0 | Q107: 0 | R107: 0
C108: Subsidio(-)/Contribucion(+) | D108: 0 | E108: 0 | F108: 0 | G108: 0 | H108: 0 | I108: 0 | J108: 0 | K108: 0 | L108: 0 | M108: 0 | N108: 0 | O108: 0 | P108: 0 | Q108: 0 | R108: 0
B109: Subs/Cont | C109: Total | D109: 0 | E109: 0 | F109: 0 | G109: 0 | H109: 0 | I109: 0 | J109: 0 | K109: 0 | L109: 0 | M109: 0 | N109: 0 | O109: 0 | P109: 0 | Q109: 0 | R109: 0
A110: NUEVO ESQUEMA | B110: Total | D110: 0 | E110: 0 | F110: 0 | G110: 0 | H110: 0 | I110: 0 | J110: 0 | K110: 0 | L110: 0 | M110: 0 | N110: 0 | O110: 0 | P110: 0 | Q110: 0 | R110: 0
C111: Vlr Servicio | D111: -377166.8 | E111: -43251.45 | F111: -24151.06 | G111: -13029.67 | H111: -77002.42 | I111: -2284.76 | J111: -20041.71 | K111: -20313.51 | L111: -87724.06 | M111: -86066.71 | N111: -3305.91 | O111: 4.46 | P111: 0 | Q111: 0 | R111: 0
C112: Vlr Intereses | D112: -9054.66 | E112: -491.84 | F112: -219.75 | G112: -125.76 | H112: -2696.53 | I112: -61.76 | J112: -541.98 | K112: -671.69 | L112: -3161.57 | M112: -983.04 | N112: -100.83 | O112: 0.09 | P112: 0 | Q112: 0 | R112: 0
B113: Componente | C113: Total | D113: -386221.46 | E113: -43743.29 | F113: -24370.81 | G113: -13155.43 | H113: -79698.95 | I113: -2346.52 | J113: -20583.69 | K113: -20985.2 | L113: -90885.63 | M113: -87049.75 | N113: -3406.74 | O113: 4.55 | P113: 0 | Q113: 0 | R113: 0
C114: Subsidio(-)/Contribucion(+) | D114: 95471.46 | E114: 4869.41 | F114: 2653.99 | G114: 1418.22 | H114: 24431.4 | I114: 804.56 | J114: 7057.6 | K114: 7551.54 | L114: 35697.19 | M114: 9674.81 | N114: 1312.74 | O114: 0 | P114: 0 | Q114: 0 | R114: 0
B115: Subs/Cont | C115: Total | D115: 95471.46 | E115: 4869.41 | F115: 2653.99 | G115: 1418.22 | H115: 24431.4 | I115: 804.56 | J115: 7057.6 | K115: 7551.54 | L115: 35697.19 | M115: 9674.81 | N115: 1312.74 | O115: 0 | P115: 0 | Q115: 0 | R115: 0
A116: OCCIDENTE | B116: Total | D116: -290750 | E116: -38873.88 | F116: -21716.82 | G116: -11737.21 | H116: -55267.55 | I116: -1541.96 | J116: -13526.09 | K116: -13433.66 | L116: -55188.44 | M116: -77374.94 | N116: -2094 | O116: 4.55 | P116: 0 | Q116: 0 | R116: 0
A117: Total | D117: -71069759 | E117: -16793644 | F117: -7779509.2 | G117: -4264060.5 | H117: -2555632.3 | I117: -91498.97 | J117: -802740.93 | K117: -806449.14 | L117: -3771977 | M117: -34055408 | N117: -148866.48 | O117: 28.29 | P117: 0 | Q117: 0 | R117: 0
A180: TOTAL | B180: OPORTUNO | C180: Total | D180: =D117-P117 -> -71069759 | E180: =E101+E107+E113 -> -15881719 | F180: =F101+F107+F113 -> -7382378.6 | G180: =G101+G107+G113 -> -4039895.6 | H180: =H101+H107+H113 -> -3333203 | I180: =I101+I107+I113 -> -119625.47 | J180: =J101+J107+J113 -> -1050942.2 | K180: =K101+K107+K113 -> -1052754.2 | L180: =L101+L107+L113 -> -4921480.5 | ... R180: =R101+R107+R113 -> 0
C181: Subsidio(-)/Contribucion(+) | D181: =D103+D109+D115 -> -895939.5
A183: RECIPROCIDAD | B183: OPORTUNO | C183: Total | D183: =D110-P110 -> 0 | E183: =E107 -> 0 | F183: =F107 -> 0 | G183: =G107 -> 0 | H183: =H107 -> 0 | I183: =I107 -> 0 | J183: =J107 -> 0 | K183: =K107 -> 0 | L183: =L107 -> 0 | ... R183: =R107 -> 0
C184: Subsidio(-)/Contribucion(+) | D184: =D109 -> 0
A186: ENEL | B186: OPORTUNO | C186: Total | D186: =D104-P104 -> -70779009 | E186: =E101 -> -15837976 | F186: =F101 -> -7358007.8 | G186: =G101 -> -4026740.1 | H186: =H101 -> -3253504 | I186: =I101 -> -117278.95 | J186: =J101 -> -1030358.6 | K186: =K101 -> -1031769 | L186: =L101 -> -4830594.8 | ... R186: =R101 -> 0
C187: Subsidio(-)/Contribucion(+) | D187: =D103 -> -991410.96
A189: ENERBIT | B189: OPORTUNO | C189: Total | D189: 0 | E189: 0 | F189: 0 | G189: 0 | H189: 0 | I189: 0 | J189: 0 | K189: 0 | L189: 0 | M189: 0 | N189: 0 | O189: 0 | P189: 0 | Q189: 0 | R189: 0
C190: Subsidio(-)/Contribucion(+) | D190: 0
A192: OCCIDENTE | B192: OPORTUNO | C192: Total | D192: =D116-P116 -> -290750 | E192: =E113 -> -43743.29 | F192: =F113 -> -24370.81 | G192: =G113 -> -13155.43 | H192: =H113 -> -79698.95 | I192: =I113 -> -2346.52 | J192: =J113 -> -20583.69 | K192: =K113 -> -20985.2 | L192: =L113 -> -90885.63 | ... R192: =R113 -> 0
C193: Subsidio(-)/Contribucion(+) | D193: =D115 -> 95471.46
A195: CIUDAD LIMPIA-ACUEDUCTO | B195: OPORTUNO | C195: Total | D195: 0 | E195: 0 | F195: 0 | G195: 0 | H195: 0 | I195: 0 | J195: 0 | K195: 0 | L195: 0 | M195: 0 | N195: 0 | O195: 0 | P195: 0 | Q195: 0 | R195: 0
C196: Subsidio(-)/Contribucion(+) | D196: 0
B198: CIUDAD LIMPIA
D199: Total | E199: Componente TDF | F199: Componente TTL | G199: Componente TVIAT | H199: Aprovechamiento | I199: CCSA Prest.Aprov. | J199: Componente TCS | K199: Componente TLU | L199: Componente TBL | M199: Componente TRT | N199: CCSA Prest. No Aprov. | O199: Ajuste Decena | P199: SERVICIO ESPECIALES | Q199: Ajuste Recargo Aseo | R199: Otros
C200: Vlr Servicio | D200: -27227799 | E200: -2315528.5 | F200: -1284217.6 | G200: -681382.92 | H200: -5451652.2 | I200: -202328.82 | J200: -1782592.4 | K200: -1715323.7 | L200: -8067276.3 | M200: -5394689.7 | N200: -332680.61 | O200: -126.11 | P200: 0 | Q200: 0 | R200: 0
C201: Vlr Intereses | D201: -345928.04 | E201: -25008.84 | F201: -12602.88 | G201: -7036.43 | H201: -80348.21 | I201: -2983.37 | J201: -25907.02 | K201: -22627.65 | L201: -105993.62 | M201: -58451.89 | N201: -4966.27 | O201: -1.86 | P201: 0 | Q201: 0 | R201: 0
B202: Componente | C202: Total | D202: -27573727 | E202: -2340537.3 | F202: -1296820.5 | G202: -688419.35 | H202: -5532000.4 | I202: -205312.19 | J202: -1808499.4 | K202: -1737951.4 | L202: -8173269.9 | M202: -5453141.6 | N202: -337646.88 | O202: -127.97 | P202: 0 | Q202: 0 | R202: 0
C203: Subsidio(-)/Contribucion(+) | D203: -4430593.2 | E203: -1063182.6 | F203: -614089.04 | G203: -323946.96 | H203: -38852 | I203: -204.27 | J203: 8451.79 | K203: 15720.47 | L203: 51334.92 | M203: -2466098.4 | N203: 272.9 | O203: 0 | P203: 0 | Q203: 0 | R203: 0
B204: Subs/Cont | C204: Total | D204: -4430593.2 | E204: -1063182.6 | F204: -614089.04 | G204: -323946.96 | H204: -38852 | I204: -204.27 | J204: 8451.79 | K204: 15720.47 | L204: 51334.92 | M204: -2466098.4 | N204: 272.9 | O204: 0 | P204: 0 | Q204: 0 | R204: 0
A205: ENEL | B205: Total | D205: -32004320 | E205: -3403720 | F205: -1910909.5 | G205: -1012366.3 | H205: -5570852.4 | I205: -205516.46 | J205: -1800047.6 | K205: -1722230.9 | L205: -8121935 | M205: -7919240 | N205: -337373.98 | O205: -127.97 | P205: 0 | Q205: 0 | R205: 0
C206: Vlr Servicio | D206: -397050.36 | E206: -18659.83 | F206: -10362.45 | G206: -4678.66 | H206: -109695.93 | I206: -3357.59 | J206: -29452.65 | K206: -33114.32 | L206: -139136.36 | M206: -43529.99 | N206: -5062.02 | O206: -0.56 | P206: 0 | Q206: 0 | R206: 0
C207: Vlr Intereses | D207: -785.24 | E207: -33.72 | F207: -17.4 | G207: -10.35 | H207: -222.64 | I207: -7.01 | J207: -61.61 | K207: -60.33 | L207: -281.65 | M207: -79.05 | N207: -11.44 | O207: -0.04 | P207: 0 | Q207: 0 | R207: 0
B208: Componente | C208: Total | D208: -397835.6 | E208: -18693.55 | F208: -10379.85 | G208: -4689.01 | H208: -109918.57 | I208: -3364.6 | J208: -29514.26 | K208: -33174.65 | L208: -139418.01 | M208: -43609.04 | N208: -5073.46 | O208: -0.6 | P208: 0 | Q208: 0 | R208: 0
C209: Subsidio(-)/Contribucion(+) | D209: 91175.8 | E209: 4274.38 | F209: 2344.18 | G209: 1290.14 | H209: 24141.72 | I209: 835.82 | J209: 7331.65 | K209: 6999.36 | L209: 32593.77 | M209: 10001.11 | N209: 1363.67 | O209: 0 | P209: 0 | Q209: 0 | R209: 0
B210: Subs/Cont | C210: Total | D210: 91175.8 | E210: 4274.38 | F210: 2344.18 | G210: 1290.14 | H210: 24141.72 | I210: 835.82 | J210: 7331.65 | K210: 6999.36 | L210: 32593.77 | M210: 10001.11 | N210: 1363.67 | O210: 0 | P210: 0 | Q210: 0 | R210: 0
A211: OCCIDENTE | B211: Total | D211: -306659.8 | E211: -14419.17 | F211: -8035.67 | G211: -3398.87 | H211: -85776.85 | I211: -2528.78 | J211: -22182.61 | K211: -26175.29 | L211: -106824.24 | M211: -33607.93 | N211: -3709.79 | O211: -0.6 | P211: 0 | Q211: 0 | R211: 0
A212: Total | D212: -32310980 | E212: -3418139.1 | F212: -1918945.2 | G212: -1015765.2 | H212: -5656629.2 | I212: -208045.24 | J212: -1822230.2 | K212: -1748406.2 | L212: -8228759.2 | M212: -7952847.9 | N212: -341083.77 | O212: -128.57 | P212: 0 | Q212: 0 | R212: 0
A217: TOTAL | B217: OPORTUNO | C217: Total | D217: =D212-P212 -> -32310980 | E217: =E202+E208 -> -2359230.9 | F217: =F202+F208 -> -1307200.3 | G217: =G202+G208 -> -693108.36 | H217: =H202+H208 -> -5641919 | I217: =I202+I208 -> -208676.79 | J217: =J202+J208 -> -1838013.6 | K217: =K202+K208 -> -1771126 | L217: =L202+L208 -> -8312687.9 | ... R217: =R202+R208 -> 0
C218: Subsidio(-)/Contribucion(+) | D218: =D204+D210 -> -4339417.4
A220: RECIPROCIDAD | B220: OPORTUNO | C220: Total | D220: 0 | E220: 0 | F220: 0 | G220: 0 | H220: 0 | I220: 0 | J220: 0 | K220: 0 | L220: 0 | M220: 0 | N220: 0 | O220: 0 | P220: 0 | Q220: 0 | R220: 0
C221: Subsidio(-)/Contribucion(+) | D221: 0
A223: ENEL | B223: OPORTUNO | C223: Total | D223: =D205-P205 -> -32004320 | E223: =E202 -> -2340537.3 | F223: =F202 -> -1296820.5 | G223: =G202 -> -688419.35 | H223: =H202 -> -5532000.4 | I223: =I202 -> -205312.19 | J223: =J202 -> -1808499.4 | K223: =K202 -> -1737951.4 | L223: =L202 -> -8173269.9 | ... R223: =R202 -> 0
C224: Subsidio(-)/Contribucion(+) | D224: =D204 -> -4430593.2
A226: ENERBIT | B226: OPORTUNO | C226: Total | D226: 0 | E226: 0 | F226: 0 | G226: 0 | H226: 0 | I226: 0 | J226: 0 | K226: 0 | L226: 0 | M226: 0 | N226: 0 | O226: 0 | P226: 0 | Q226: 0 | R226: 0
C227: Subsidio(-)/Contribucion(+) | D227: 0
A229: OCCIDENTE | B229: OPORTUNO | C229: Total | D229: =D211-P211 -> -306659.8 | E229: =E208 -> -18693.55 | F229: =F208 -> -10379.85 | G229: =G208 -> -4689.01 | H229: =H208 -> -109918.57 | I229: =I208 -> -3364.6 | J229: =J208 -> -29514.26 | K229: =K208 -> -33174.65 | L229: =L208 -> -139418.01 | ... R229: =R208 -> 0
C230: Subsidio(-)/Contribucion(+) | D230: =D210 -> 91175.8
A232: CIUDAD LIMPIA-ACUEDUCTO | B232: OPORTUNO | C232: Total | D232: 0 | E232: 0 | F232: 0 | G232: 0 | H232: 0 | I232: 0 | J232: 0 | K232: 0 | L232: 0 | M232: 0 | N232: 0 | O232: 0 | P232: 0 | Q232: 0 | R232: 0
C233: Subsidio(-)/Contribucion(+) | D233: 0
B235: BOGOTA LIMPIA
D236: Total | E236: Componente TDF | F236: Componente TTL | G236: Componente TVIAT | H236: Aprovechamiento | I236: CCSA Prest.Aprov. | J236: Componente TCS | K236: Componente TLU | L236: Componente TBL | M236: Componente TRT | N236: CCSA Prest. No Aprov. | O236: Ajuste Decena | P236: SERVICIO ESPECIALES | Q236: Ajuste Recargo Aseo | R236: Otros
C237: Vlr Servicio | D237: -21566863 | E237: -1602733.6 | F237: -896891.02 | G237: -475692.34 | H237: -4329801.2 | I237: -156115.79 | J237: -1354111 | K237: -1357517.4 | L237: -6863140.8 | M237: -4276100.4 | N237: -254729.55 | O237: -30.13 | P237: 0 | Q237: 0 | R237: 0
C238: Vlr Intereses | D238: -10375865 | E238: -1376999.4 | F238: -590233.5 | G238: -209963.97 | H238: -1412012.6 | I238: -55947.15 | J238: -490779.37 | K238: -582672.58 | L238: -1966419 | M238: -3599557 | N238: -91288.76 | O238: 8.34 | P238: 0 | Q238: 0 | R238: -0.29
B239: Componente | C239: Total | D239: -31942729 | E239: -2979733 | F239: -1487124.5 | G239: -685656.31 | H239: -5741813.8 | I239: -212062.94 | J239: -1844890.4 | K239: -1940190 | L239: -8829559.8 | M239: -7875657.5 | N239: -346018.31 | O239: -21.79 | P239: 0 | Q239: 0 | R239: -0.29
C240: Subsidio(-)/Contribucion(+) | D240: 2174082.8 | E240: 22089.07 | F240: 10938.57 | G240: 6096.13 | H240: 636523.27 | I240: 22219.55 | J240: 194912.33 | K240: 197393.84 | L240: 989072.18 | M240: 58583.97 | N240: 36253.89 | O240: 0 | P240: 0 | Q240: 0 | R240: 0
B241: Subs/Cont | C241: Total | D241: 2174082.8 | E241: 22089.07 | F241: 10938.57 | G241: 6096.13 | H241: 636523.27 | I241: 22219.55 | J241: 194912.33 | K241: 197393.84 | L241: 989072.18 | M241: 58583.97 | N241: 36253.89 | O241: 0 | P241: 0 | Q241: 0 | R241: 0
...

Sheet SALDOS POR NOTA
B1: PROMOAMBIENTAL
C2: Total | D2: Componente TDF | E2: Componente TTL | F2: Componente TVIAT | G2: Aprovechamiento | H2: CCSA Prest.Aprov. | I2: Especiales | J2: Componente TCS | K2: Componente TLU | L2: Componente TBL | M2: Componente TRT | N2: CCSA Prest. No Aprov. | O2: Deb/Cred
B3: Vlr Servicio | C3: 796773.47 | D3: 65524.22 | E3: 36995.02 | F3: 19417.65 | G3: 156624.35 | H3: 5557.5 | I3: 0 | J3: 52109.79 | K3: 47607.03 | L3: 225441.17 | M3: 178429.31 | N3: 9067.43 | O3: 0
B4: Vlr Intereses | C4: 0 | D4: 0 | E4: 0 | F4: 0 | G4: 0 | H4: 0 | I4: 0 | J4: 0 | K4: 0 | L4: 0 | M4: 0 | N4: 0 | O4: 0
A5: Componente | B5: Total | C5: 796773.47 | D5: 65524.22 | E5: 36995.02 | F5: 19417.65 | G5: 156624.35 | H5: 5557.5 | I5: 0 | J5: 52109.79 | K5: 47607.03 | L5: 225441.17 | M5: 178429.31 | N5: 9067.43 | O5: 0
B6: Subsidio(-)/Contribucion(+) | C6: 176919.99 | D6: 32442.78 | E6: 18317.24 | F6: 9614.21 | G6: 9543.57 | H6: 280.5 | I6: 0 | J6: 1116.45 | K6: 2883.45 | L6: 13655.06 | M6: 88609.08 | N6: 457.65 | O6: 0
A7: Subs/Cont | B7: Total | C7: 176919.99 | D7: 32442.78 | E7: 18317.24 | F7: 9614.21 | G7: 9543.57 | H7: 280.5 | I7: 0 | J7: 1116.45 | K7: 2883.45 | L7: 13655.06 | M7: 88609.08 | N7: 457.65 | O7: 0
A8: Total | C8: 973693.46 | D8: 97967 | E8: 55312.26 | F8: 29031.86 | G8: 166167.92 | H8: 5838 | I8: 0 | J8: 53226.24 | K8: 50490.48 | L8: 239096.23 | M8: 267038.39 | N8: 9525.08 | O8: 0
B10: Total | C10: =C8-I8 -> 973693.46 | D10: =D5 -> 65524.22 | E10: =E5 -> 36995.02 | F10: =F5 -> 19417.65 | G10: =G5 -> 156624.35 | H10: =H5 -> 5557.5 | I10: =I5 -> 0 | J10: =J5 -> 52109.79 | K10: =K5 -> 47607.03 | ... P10: =P5 -> 0
B11: Subsidio(-)/Contribucion(+) | C11: =C7 -> 176919.99
B14: LIME
C15: Total | D15: Componente TDF | E15: Componente TTL | F15: Componente TVIAT | G15: Aprovechamiento | H15: CCSA Prest.Aprov. | I15: Especiales | J15: Componente TCS | K15: Componente TLU | L15: Componente TBL | M15: Componente TRT | N15: CCSA Prest. No Aprov. | O15: Deb/Cred
B16: Vlr Servicio | C16: 448371.28 | D16: 31889 | E16: 18568.04 | F16: 8864.59 | G16: 92916.35 | H16: 3882.28 | I16: 0 | J16: 61344.03 | K16: 33520.25 | L16: 127751.61 | M16: 64498.2 | N16: 5137.3 | O16: -0.37
B17: Vlr Intereses | C17: 172.61 | D17: 8.62 | E17: 4.87 | F17: 2.55 | G17: 43.14 | H17: 1.6 | I17: 0 | J17: 14.06 | K17: 13.76 | L17: 64.26 | M17: 17.12 | N17: 2.62 | O17: 0.01
A18: Componente | B18: Total | C18: 448543.89 | D18: 31897.62 | E18: 18572.91 | F18: 8867.14 | G18: 92959.49 | H18: 3883.88 | I18: 0 | J18: 61358.09 | K18: 33534.01 | L18: 127815.87 | M18: 64515.32 | N18: 5139.92 | O18: -0.36
B19: Subsidio(-)/Contribucion(+) | C19: -232518.12 | D19: -15692.52 | E19: -8860.02 | F19: -4649.05 | G19: -48588.46 | H19: -1735.35 | I19: 0 | J19: -35751.35 | K19: -14884.94 | L19: -70344.96 | M19: -29180.14 | N19: -2831.33 | O19: 0
A20: Subs/Cont | B20: Total | C20: -232518.12 | D20: -15692.52 | E20: -8860.02 | F20: -4649.05 | G20: -48588.46 | H20: -1735.35 | I20: 0 | J20: -35751.35 | K20: -14884.94 | L20: -70344.96 | M20: -29180.14 | N20: -2831.33 | O20: 0
A21: Total | C21: 216025.77 | D21: 16205.1 | E21: 9712.89 | F21: 4218.09 | G21: 44371.03 | H21: 2148.53 | I21: 0 | J21: 25606.74 | K21: 18649.07 | L21: 57470.91 | M21: 35335.18 | N21: 2308.59 | O21: -0.36
B23: Total | C23: =C21-I21 -> 216025.77 | D23: =D18 -> 31897.62 | E23: =E18 -> 18572.91 | F23: =F18 -> 8867.14 | G23: =G18 -> 92959.49 | H23: =H18 -> 3883.88 | I23: =I18 -> 0 | J23: =J18 -> 61358.09 | K23: =K18 -> 33534.01 | ... P23: =P18 -> 0
B24: Subsidio(-)/Contribucion(+) | C24: =C20 -> -232518.12
B27: CIUDAD LIMPIA
C28: Total | D28: Componente TDF | E28: Componente TTL | F28: Componente TVIAT | G28: Aprovechamiento | H28: CCSA Prest.Aprov. | I28: Especiales | J28: Componente TCS | K28: Componente TLU | L28: Componente TBL | M28: Componente TRT | N28: CCSA Prest. No Aprov. | O28: Deb/Cred
B29: Vlr Servicio | C29: 93864.95 | D29: 6620.63 | E29: 3738.02 | F29: 1961.98 | G29: 20927.5 | H29: 743.08 | I29: 0 | J29: 6518.28 | K29: 6410.86 | L29: 30349.1 | M29: 15383.1 | N29: 1212.4 | O29: 0
B30: Vlr Intereses | C30: 0 | D30: 0 | E30: 0 | F30: 0 | G30: 0 | H30: 0 | I30: 0 | J30: 0 | K30: 0 | L30: 0 | M30: 0 | N30: 0 | O30: 0
A31: Componente | B31: Total | C31: 93864.95 | D31: 6620.63 | E31: 3738.02 | F31: 1961.98 | G31: 20927.5 | H31: 743.08 | I31: 0 | J31: 6518.28 | K31: 6410.86 | L31: 30349.1 | M31: 15383.1 | N31: 1212.4 | O31: 0
B32: Subsidio(-)/Contribucion(+) | C32: 10366.88 | D32: 1686.92 | E32: 952.43 | F32: 499.9 | G32: 1046.38 | H32: 37.15 | I32: 0 | J32: 325.91 | K32: 320.55 | L32: 1517.46 | M32: 3919.56 | N32: 60.62 | O32: 0
A33: Subs/Cont | B33: Total | C33: 10366.88 | D33: 1686.92 | E33: 952.43 | F33: 499.9 | G33: 1046.38 | H33: 37.15 | I33: 0 | J33: 325.91 | K33: 320.55 | L33: 1517.46 | M33: 3919.56 | N33: 60.62 | O33: 0
A34: Total | C34: 104231.83 | D34: 8307.55 | E34: 4690.45 | F34: 2461.88 | G34: 21973.88 | H34: 780.23 | I34: 0 | J34: 6844.19 | K34: 6731.41 | L34: 31866.56 | M34: 19302.66 | N34: 1273.02 | O34: 0
B36: Total | C36: =C34-I34 -> 104231.83 | D36: =D31 -> 6620.63 | E36: =E31 -> 3738.02 | F36: =F31 -> 1961.98 | G36: =G31 -> 20927.5 | H36: =H31 -> 743.08 | I36: =I31 -> 0 | J36: =J31 -> 6518.28 | K36: =K31 -> 6410.86 | ... P36: =P31 -> 0
B37: Subsidio(-)/Contribucion(+) | C37: =C33 -> 10366.88
B40: BOGOTA LIMPIA
C41: Total | D41: Componente TDF | E41: Componente TTL | F41: Componente TVIAT | G41: Aprovechamiento | H41: CCSA Prest.Aprov. | I41: Especiales | J41: Componente TCS | K41: Componente TLU | L41: Componente TBL | M41: Componente TRT | N41: CCSA Prest. No Aprov. | O41: Deb/Cred
B42: Vlr Servicio | C42: 43025.12 | D42: 1890.6 | E42: 1067.43 | F42: 560.27 | G42: 10800.02 | H42: 371.66 | I42: 0 | J42: 3260.18 | K42: 3149.08 | L42: 16313.73 | M42: 5005.76 | N42: 606.39 | O42: 0
B43: Vlr Intereses | C43: -616.92 | D43: 0 | E43: 0 | F43: 0 | G43: 0 | H43: 0 | I43: 0 | J43: 0 | K43: 0 | L43: -616.92 | M43: 0 | N43: 0 | O43: 0
A44: Componente | B44: Total | C44: 42408.2 | D44: 1890.6 | E44: 1067.43 | F44: 560.27 | G44: 10800.02 | H44: 371.66 | I44: 0 | J44: 3260.18 | K44: 3149.08 | L44: 15696.81 | M44: 5005.76 | N44: 606.39 | O44: 0
B45: Subsidio(-)/Contribucion(+) | C45: -6453.76 | D45: -283.59 | E45: -160.11 | F45: -84.04 | G45: -1620 | H45: -55.75 | I45: 0 | J45: -489.03 | K45: -472.36 | L45: -2447.06 | M45: -750.86 | N45: -90.96 | O45: 0
A46: Subs/Cont | B46: Total | C46: -6453.76 | D46: -283.59 | E46: -160.11 | F46: -84.04 | G46: -1620 | H46: -55.75 | I46: 0 | J46: -489.03 | K46: -472.36 | L46: -2447.06 | M46: -750.86 | N46: -90.96 | O46: 0
A47: Total | C47: 35954.44 | D47: 1607.01 | E47: 907.32 | F47: 476.23 | G47: 9180.02 | H47: 315.91 | I47: 0 | J47: 2771.15 | K47: 2676.72 | L47: 13249.75 | M47: 4254.9 | N47: 515.43 | O47: 0
B49: Total | C49: =C47-I47 -> 35954.44 | D49: =D44 -> 1890.6 | E49: =E44 -> 1067.43 | F49: =F44 -> 560.27 | G49: =G44 -> 10800.02 | H49: =H44 -> 371.66 | I49: =I44 -> 0 | J49: =J44 -> 3260.18 | K49: =K44 -> 3149.08 | ... P49: =P44 -> 0
B50: Subsidio(-)/Contribucion(+) | C50: =C46 -> -6453.76
B53: AREA LIMPIA
C54: Total | D54: Componente TDF | E54: Componente TTL | F54: Componente TVIAT | G54: Aprovechamiento | H54: CCSA Prest.Aprov. | I54: Especiales | J54: Componente TCS | K54: Componente TLU | L54: Componente TBL | M54: Componente TRT | N54: CCSA Prest. No Aprov. | O54: Deb/Cred
B55: Vlr Servicio | C55: 0 | D55: 0 | E55: 0 | F55: 0 | G55: 0 | H55: 0 | I55: 0 | J55: 0 | K55: 0 | L55: 0 | M55: 0 | N55: 0 | O55: 0
B56: Vlr Intereses | C56: 0 | D56: 0 | E56: 0 | F56: 0 | G56: 0 | H56: 0 | I56: 0 | J56: 0 | K56: 0 | L56: 0 | M56: 0 | N56: 0 | O56: 0
A57: Componente | B57: Total | C57: 0 | D57: 0 | E57: 0 | F57: 0 | G57: 0 | H57: 0 | I57: 0 | J57: 0 | K57: 0 | L57: 0 | M57: 0 | N57: 0 | O57: 0
B58: Subsidio(-)/Contribucion(+) | C58: 0 | D58: 0 | E58: 0 | F58: 0 | G58: 0 | H58: 0 | I58: 0 | J58: 0 | K58: 0 | L58: 0 | M58: 0 | N58: 0 | O58: 0
A59: Subs/Cont | B59: Total | C59: 0 | D59: 0 | E59: 0 | F59: 0 | G59: 0 | H59: 0 | I59: 0 | J59: 0 | K59: 0 | L59: 0 | M59: 0 | N59: 0 | O59: 0
A60: Total | C60: 0 | D60: 0 | E60: 0 | F60: 0 | G60: 0 | H60: 0 | I60: 0 | J60: 0 | K60: 0 | L60: 0 | M60: 0 | N60: 0 | O60: 0
B62: Total | C62: =C60-I60 -> 0 | D62: =D57 -> 0 | E62: =E57 -> 0 | F62: =F57 -> 0 | G62: =G57 -> 0 | H62: =H57 -> 0 | I62: =I57 -> 0 | J62: =J57 -> 0 | K62: =K57 -> 0 | ... P62: =P57 -> 0
B63: Subsidio(-)/Contribucion(+) | C63: =C59 -> 0

Sheet RETRIBUCION NEGATIVA
B1: PROMOAMBIENTAL
C2: Total | D2: Componente TDF | E2: Componente TTL | F2: Componente TVIAT | G2: Aprovechamiento | H2: CCSA Prest.Aprov. | I2: Especiales | J2: Componente TCS | K2: Componente TLU | L2: Componente TBL | M2: Componente TRT | N2: CCSA Prest. No Aprov. | O2: Deb/Cred
B3: Vlr Intereses | C3: 0 | D3: 0 | E3: 0 | F3: 0 | G3: 0 | H3: 0 | I3: 0 | J3: 0 | K3: 0 | L3: 0 | M3: 0 | N3: 0 | O3: 0
B4: Vlr Servicio | C4: 0 | D4: 0 | E4: 0 | F4: 0 | G4: 0 | H4: 0 | I4: 0 | J4: 0 | K4: 0 | L4: 0 | M4: 0 | N4: 0 | O4: 0
A5: Componente | B5: Total | C5: 0 | D5: 0 | E5: 0 | F5: 0 | G5: 0 | H5: 0 | I5: 0 | J5: 0 | K5: 0 | L5: 0 | M5: 0 | N5: 0 | O5: 0
B6: Subsidio(-)/Contribucion(+) | C6: 0 | D6: 0 | E6: 0 | F6: 0 | G6: 0 | H6: 0 | I6: 0 | J6: 0 | K6: 0 | L6: 0 | M6: 0 | N6: 0 | O6: 0
A7: Subs/Cont | B7: Total | C7: 0 | D7: 0 | E7: 0 | F7: 0 | G7: 0 | H7: 0 | I7: 0 | J7: 0 | K7: 0 | L7: 0 | M7: 0 | N7: 0 | O7: 0
A8: Total | C8: 0 | D8: 0 | E8: 0 | F8: 0 | G8: 0 | H8: 0 | I8: 0 | J8: 0 | K8: 0 | L8: 0 | M8: 0 | N8: 0 | O8: 0
B10: Total | C10: =C8-I8 -> 0 | D10: =D5 -> 0 | E10: =E5 -> 0 | F10: =F5 -> 0 | G10: =G5 -> 0 | H10: =H5 -> 0 | I10: =I5 -> 0 | J10: =J5 -> 0 | K10: =K5 -> 0 | ... O10: =O5 -> 0
B11: Subsidio(-)/Contribucion(+) | C11: =C7 -> 0
B14: LIME
C15: Total | D15: Componente TDF | E15: Componente TTL | F15: Componente TVIAT | G15: Aprovechamiento | H15: CCSA Prest.Aprov. | I15: Especiales | J15: Componente TCS | K15: Componente TLU | L15: Componente TBL | M15: Componente TRT | N15: CCSA Prest. No Aprov. | O15: Deb/Cred
B16: Vlr Intereses | C16: 0 | D16: 0 | E16: 0 | F16: 0 | G16: 0 | H16: 0 | I16: 0 | J16: 0 | K16: 0 | L16: 0 | M16: 0 | N16: 0 | O16: 0
B17: Vlr Servicio | C17: 0 | D17: 0 | E17: 0 | F17: 0 | G17: 0 | H17: 0 | I17: 0 | J17: 0 | K17: 0 | L17: 0 | M17: 0 | N17: 0 | O17: 0
A18: Componente | B18: Total | C18: 0 | D18: 0 | E18: 0 | F18: 0 | G18: 0 | H18: 0 | I18: 0 | J18: 0 | K18: 0 | L18: 0 | M18: 0 | N18: 0 | O18: 0
B19: Subsidio(-)/Contribucion(+) | C19: 0 | D19: 0 | E19: 0 | F19: 0 | G19: 0 | H19: 0 | I19: 0 | J19: 0 | K19: 0 | L19: 0 | M19: 0 | N19: 0 | O19: 0
A20: Subs/Cont | B20: Total | C20: 0 | D20: 0 | E20: 0 | F20: 0 | G20: 0 | H20: 0 | I20: 0 | J20: 0 | K20: 0 | L20: 0 | M20: 0 | N20: 0 | O20: 0
A21: Total | C21: 0 | D21: 0 | E21: 0 | F21: 0 | G21: 0 | H21: 0 | I21: 0 | J21: 0 | K21: 0 | L21: 0 | M21: 0 | N21: 0 | O21: 0
B23: Total | C23: =C21-I21 -> 0 | D23: =D18 -> 0 | E23: =E18 -> 0 | F23: =F18 -> 0 | G23: =G18 -> 0 | H23: =H18 -> 0 | I23: =I18 -> 0 | J23: =J18 -> 0 | K23: =K18 -> 0 | ... O23: =O18 -> 0
B24: Subsidio(-)/Contribucion(+) | C24: =C20 -> 0
B27: CIUDAD LIMPIA
C28: Total | D28: Componente TDF | E28: Componente TTL | F28: Componente TVIAT | G28: Aprovechamiento | H28: CCSA Prest.Aprov. | I28: Especiales | J28: Componente TCS | K28: Componente TLU | L28: Componente TBL | M28: Componente TRT | N28: CCSA Prest. No Aprov. | O28: Deb/Cred
B29: Vlr Intereses | C29: 0 | D29: 0 | E29: 0 | F29: 0 | G29: 0 | H29: 0 | I29: 0 | J29: 0 | K29: 0 | L29: 0 | M29: 0 | N29: 0 | O29: 0
B30: Vlr Servicio | C30: 0 | D30: 0 | E30: 0 | F30: 0 | G30: 0 | H30: 0 | I30: 0 | J30: 0 | K30: 0 | L30: 0 | M30: 0 | N30: 0 | O30: 0
A31: Componente | B31: Total | C31: 0 | D31: 0 | E31: 0 | F31: 0 | G31: 0 | H31: 0 | I31: 0 | J31: 0 | K31: 0 | L31: 0 | M31: 0 | N31: 0 | O31: 0
B32: Subsidio(-)/Contribucion(+) | C32: 0 | D32: 0 | E32: 0 | F32: 0 | G32: 0 | H32: 0 | I32: 0 | J32: 0 | K32: 0 | L32: 0 | M32: 0 | N32: 0 | O32: 0
A33: Subs/Cont | B33: Total | C33: 0 | D33: 0 | E33: 0 | F33: 0 | G33: 0 | H33: 0 | I33: 0 | J33: 0 | K33: 0 | L33: 0 | M33: 0 | N33: 0 | O33: 0
A34: Total | C34: 0 | D34: 0 | E34: 0 | F34: 0 | G34: 0 | H34: 0 | I34: 0 | J34: 0 | K34: 0 | L34: 0 | M34: 0 | N34: 0 | O34: 0
B36: Total | C36: =C34-I34 -> 0 | D36: =D31 -> 0 | E36: =E31 -> 0 | F36: =F31 -> 0 | G36: =G31 -> 0 | H36: =H31 -> 0 | I36: =I31 -> 0 | J36: =J31 -> 0 | K36: =K31 -> 0 | ... O36: =O31 -> 0
B37: Subsidio(-)/Contribucion(+) | C37: =C33 -> 0
B40: BOGOTA LIMPIA
C41: Total | D41: Componente TDF | E41: Componente TTL | F41: Componente TVIAT | G41: Aprovechamiento | H41: CCSA Prest.Aprov. | I41: Especiales | J41: Componente TCS | K41: Componente TLU | L41: Componente TBL | M41: Componente TRT | N41: CCSA Prest. No Aprov. | O41: Deb/Cred
B42: Vlr Intereses | C42: 0 | D42: 0 | E42: 0 | F42: 0 | G42: 0 | H42: 0 | I42: 0 | J42: 0 | K42: 0 | L42: 0 | M42: 0 | N42: 0 | O42: 0
B43: Vlr Servicio | C43: 0 | D43: 0 | E43: 0 | F43: 0 | G43: 0 | H43: 0 | I43: 0 | J43: 0 | K43: 0 | L43: 0 | M43: 0 | N43: 0 | O43: 0
A44: Componente | B44: Total | C44: 0 | D44: 0 | E44: 0 | F44: 0 | G44: 0 | H44: 0 | I44: 0 | J44: 0 | K44: 0 | L44: 0 | M44: 0 | N44: 0 | O44: 0
B45: Subsidio(-)/Contribucion(+) | C45: 0 | D45: 0 | E45: 0 | F45: 0 | G45: 0 | H45: 0 | I45: 0 | J45: 0 | K45: 0 | L45: 0 | M45: 0 | N45: 0 | O45: 0
A46: Subs/Cont | B46: Total | C46: 0 | D46: 0 | E46: 0 | F46: 0 | G46: 0 | H46: 0 | I46: 0 | J46: 0 | K46: 0 | L46: 0 | M46: 0 | N46: 0 | O46: 0
A47: Total | C47: 0 | D47: 0 | E47: 0 | F47: 0 | G47: 0 | H47: 0 | I47: 0 | J47: 0 | K47: 0 | L47: 0 | M47: 0 | N47: 0 | O47: 0
B49: Total | C49: =C47-I47 -> 0 | D49: =D44 -> 0 | E49: =E44 -> 0 | F49: =F44 -> 0 | G49: =G44 -> 0 | H49: =H44 -> 0 | I49: =I44 -> 0 | J49: =J44 -> 0 | K49: =K44 -> 0 | ... O49: =O44 -> 0
B50: Subsidio(-)/Contribucion(+) | C50: =C46 -> 0
B53: AREA LIMPIA
C54: Total | D54: Componente TDF | E54: Componente TTL | F54: Componente TVIAT | G54: Aprovechamiento | H54: CCSA Prest.Aprov. | I54: Especiales | J54: Componente TCS | K54: Componente TLU | L54: Componente TBL | M54: Componente TRT | N54: CCSA Prest. No Aprov. | O54: Deb/Cred
B55: Vlr Intereses | C55: 0 | D55: 0 | E55: 0 | F55: 0 | G55: 0 | H55: 0 | I55: 0 | J55: 0 | K55: 0 | L55: 0 | M55: 0 | N55: 0 | O55: 0
B56: Vlr Servicio | C56: 0 | D56: 0 | E56: 0 | F56: 0 | G56: 0 | H56: 0 | I56: 0 | J56: 0 | K56: 0 | L56: 0 | M56: 0 | N56: 0 | O56: 0
A57: Componente | B57: Total | C57: 0 | D57: 0 | E57: 0 | F57: 0 | G57: 0 | H57: 0 | I57: 0 | J57: 0 | K57: 0 | L57: 0 | M57: 0 | N57: 0 | O57: 0
B58: Subsidio(-)/Contribucion(+) | C58: 0 | D58: 0 | E58: 0 | F58: 0 | G58: 0 | H58: 0 | I58: 0 | J58: 0 | K58: 0 | L58: 0 | M58: 0 | N58: 0 | O58: 0
A59: Subs/Cont | B59: Total | C59: 0 | D59: 0 | E59: 0 | F59: 0 | G59: 0 | H59: 0 | I59: 0 | J59: 0 | K59: 0 | L59: 0 | M59: 0 | N59: 0 | O59: 0
A60: Total | C60: 0 | D60: 0 | E60: 0 | F60: 0 | G60: 0 | H60: 0 | I60: 0 | J60: 0 | K60: 0 | L60: 0 | M60: 0 | N60: 0 | O60: 0
B62: Total | C62: =C60-I60 -> 0 | D62: =D57 -> 0 | E62: =E57 -> 0 | F62: =F57 -> 0 | G62: =G57 -> 0 | H62: =H57 -> 0 | I62: =I57 -> 0 | J62: =J57 -> 0 | K62: =K57 -> 0 | ... O62: =O57 -> 0
B63: Subsidio(-)/Contribucion(+) | C63: =C59 -> 0

Sheet AJUSTES - SF-T
F3: PROCERASEO S.A.S. | I3: NIT: 901 153 639 - 0 | M3: Codigo Remuneración: | N3: ='CONSOLIDADO_TOTAL RECAUDO'!N3 -> 2026072 | U3: PROCERASEO S.A.S. | W3: NIT: 901 153 639 - 0 | AA3: Codigo Remuneración: | AC3: =N3 -> 2026072
F4: 3. ESQUEMA FINANCIERO DEL SERVICIO PUBLICO DE ASEO | U4: 3. ESQUEMA FINANCIERO DEL SERVICIO PUBLICO DE ASEO
F5: Resoluciòn UAESP Número 27 de 2018 | U5: Resoluciòn UAESP Número 27 de 2018
C6: Fecha de Proceso: | D6: ='CONSOLIDADO_TOTAL RECAUDO'!D6 -> 46297 | F6: SALDOS A FAVOR POR NOTA | U6: =+F6 -> SALDOS A FAVOR POR NOTA
C7: Hora: | D7: ='CONSOLIDADO_TOTAL RECAUDO'!D7 -> 0.58333333 | F7: Fecha Desde: | H7: ='CONSOLIDADO_TOTAL RECAUDO'!G7 -> 46219 | J7: Feha Hasta: | K7: ='CONSOLIDADO_TOTAL RECAUDO'!K7 -> 46234 | U7: =F7 -> Fecha Desde: | V7: =H7 -> 46219 | X7: =J7 -> Feha Hasta: | Y7: =K7 -> 46234
B8: ASE | C8: Concesionarios | D8: Recaudo Total | E8: Recaudo por disposicion final | F8: Recaudo por tratamiento de lixiviados | G8: Recaudo por Componente VIAT ( Decreto 2412/2018) | H8: Recaudo por aprovechamiento | I8: Recaudo del componente de comercializacion para Aprovechamiento (11,4%) | J8: Balance de subsidio o contribuciones | K8: RECAUDO BASE DE REMUNERACION | L8: Costo de la Interventoría | M8: REMUNERACION FINAL | N8: Conceptos especiales | O8: REMUNERACION FINAL MAS CONCEPTOS ESPECIALES | S8: ASE | T8: Concesionarios | U8: Tarifa de Comercialización del Servicio. ( TCS) | V8: Tarifa de Limpieza Urbana del Servicio. ( TLU) | W8: Tarifa de Barrido y Limpieza del Servicio. ( TBL) | X8: Tarifa de Recolección y Transporte del Servicio. (TRT) | Y8: Recaudo del componente de comercializacion para Aprovechamiento (18,6%) | Z8: Costo de la Interventoría | AA8: Ajuste a la decena | AB8: Conceptos especiales | AC8: Diferencial Balance S / C (Fac vs Rec) | AD8: Balance S / C Con Baase en (Recaudo) | AE8: REMUNERACION FINAL MAS CONCEPTOS ESPECIALES
B9: 1 | C9: PROMOAMBIENTAL DISTRITO S.A.S. ESP. | D9: ='SALDOS POR NOTA'!C10 -> 973693.46 | E9: ='SALDOS POR NOTA'!D10 -> 65524.22 | F9: ='SALDOS POR NOTA'!E10 -> 36995.02 | G9: ='SALDOS POR NOTA'!F10 -> 19417.65 | H9: ='SALDOS POR NOTA'!G10 -> 156624.35 | I9: ='SALDOS POR NOTA'!H10 -> 5557.5 | J9: 0 | K9: =D9-E9-F9-G9-H9-I9-J9 -> 689574.72 | L9: 0 | M9: =K9-L9 -> 689574.72 | N9: ='SALDOS POR NOTA'!I10 -> 0 | O9: =M9+N9 -> 689574.72 | S9: 1 | T9: PROMOAMBIENTAL DISTRITO S.A.S. ESP. | U9: ='SALDOS POR NOTA'!J10 -> 52109.79 | V9: ='SALDOS POR NOTA'!K10 -> 47607.03 | W9: ='SALDOS POR NOTA'!L10 -> 225441.17 | X9: ='SALDOS POR NOTA'!M10 -> 178429.31 | Y9: ='SALDOS POR NOTA'!N10 -> 9067.43 | Z9: =L9*-1 -> 0 | AA9: ='SALDOS POR NOTA'!O10 -> 0 | AB9: =N9 -> 0 | AC9: =-J9+AD9 -> 176919.99 | AD9: ='SALDOS POR NOTA'!C11 -> 176919.99 | AE9: =SUM(U9:AC9) -> 689574.72 | AF9: =(AE9-O9) -> 0 | AG9: =AF9=0 -> TRUE
B10: 2 | C10: LIMPIEZA METROPOLITANA S.A. ESP. | D10: ='SALDOS POR NOTA'!C23 -> 216025.77 | E10: ='SALDOS POR NOTA'!D23 -> 31897.62 | F10: ='SALDOS POR NOTA'!E23 -> 18572.91 | G10: ='SALDOS POR NOTA'!F23 -> 8867.14 | H10: ='SALDOS POR NOTA'!G23 -> 92959.49 | I10: ='SALDOS POR NOTA'!H23 -> 3883.88 | J10: 0 | K10: =D10-E10-F10-G10-H10-I10-J10 -> 59844.73 | L10: 0 | M10: =K10-L10 -> 59844.73 | N10: ='SALDOS POR NOTA'!I23 -> 0 | O10: =M10+N10 -> 59844.73 | S10: 2 | T10: LIMPIEZA METROPOLITANA S.A. ESP. | U10: ='SALDOS POR NOTA'!J23 -> 61358.09 | V10: ='SALDOS POR NOTA'!K23 -> 33534.01 | W10: ='SALDOS POR NOTA'!L23 -> 127815.87 | X10: ='SALDOS POR NOTA'!M23 -> 64515.32 | Y10: ='SALDOS POR NOTA'!N23 -> 5139.92 | Z10: =L10*-1 -> 0 | AA10: ='SALDOS POR NOTA'!O23 -> -0.36 | AB10: =N10 -> 0 | AC10: =-J10+AD10 -> -232518.12 | AD10: ='SALDOS POR NOTA'!C24 -> -232518.12 | AE10: =SUM(U10:AC10) -> 59844.73 | AF10: =(AE10-O10) -> 7.2759576e-12 | AG10: =AF10=0 -> FALSE
B11: 3 | C11: CIUDAD LIMPIA BOGOTA S.A. ESP. | D11: ='SALDOS POR NOTA'!C36 -> 104231.83 | E11: ='SALDOS POR NOTA'!D36 -> 6620.63 | F11: ='SALDOS POR NOTA'!E36 -> 3738.02 | G11: ='SALDOS POR NOTA'!F36 -> 1961.98 | H11: ='SALDOS POR NOTA'!G36 -> 20927.5 | I11: ='SALDOS POR NOTA'!H36 -> 743.08 | J11: 0 | K11: =D11-E11-F11-G11-H11-I11-J11 -> 70240.62 | L11: 0 | M11: =K11-L11 -> 70240.62 | N11: ='SALDOS POR NOTA'!I36 -> 0 | O11: =M11+N11 -> 70240.62 | S11: 3 | T11: CIUDAD LIMPIA BOGOTA S.A. ESP. | U11: ='SALDOS POR NOTA'!J36 -> 6518.28 | V11: ='SALDOS POR NOTA'!K36 -> 6410.86 | W11: ='SALDOS POR NOTA'!L36 -> 30349.1 | X11: ='SALDOS POR NOTA'!M36 -> 15383.1 | Y11: ='SALDOS POR NOTA'!N36 -> 1212.4 | Z11: =L11*-1 -> 0 | AA11: ='SALDOS POR NOTA'!O36 -> 0 | AB11: =N11 -> 0 | AC11: =-J11+AD11 -> 10366.88 | AD11: ='SALDOS POR NOTA'!C37 -> 10366.88 | AE11: =SUM(U11:AC11) -> 70240.62 | AF11: =(AE11-O11) -> 0 | AG11: =AF11=0 -> TRUE
B12: 4 | C12: BOGOTA LIMPIA S.A.S. ESP. | D12: ='SALDOS POR NOTA'!C49 -> 35954.44 | E12: ='SALDOS POR NOTA'!D49 -> 1890.6 | F12: ='SALDOS POR NOTA'!E49 -> 1067.43 | G12: ='SALDOS POR NOTA'!F49 -> 560.27 | H12: ='SALDOS POR NOTA'!G49 -> 10800.02 | I12: ='SALDOS POR NOTA'!H49 -> 371.66 | J12: 0 | K12: =D12-E12-F12-G12-H12-I12-J12 -> 21264.46 | L12: 0 | M12: =K12-L12 -> 21264.46 | N12: ='SALDOS POR NOTA'!I49 -> 0 | O12: =M12+N12 -> 21264.46 | S12: 4 | T12: BOGOTA LIMPIA S.A.S. ESP. | U12: ='SALDOS POR NOTA'!J49 -> 3260.18 | V12: ='SALDOS POR NOTA'!K49 -> 3149.08 | W12: ='SALDOS POR NOTA'!L49 -> 15696.81 | X12: ='SALDOS POR NOTA'!M49 -> 5005.76 | Y12: ='SALDOS POR NOTA'!N49 -> 606.39 | Z12: =L12*-1 -> 0 | AA12: ='SALDOS POR NOTA'!O49 -> 0 | AB12: =N12 -> 0 | AC12: =-J12+AD12 -> -6453.76 | AD12: ='SALDOS POR NOTA'!C50 -> -6453.76 | AE12: =SUM(U12:AC12) -> 21264.46 | AF12: =(AE12-O12) -> -3.6379788e-12 | AG12: =AF12=0 -> FALSE
B13: 5 | C13: AREA LIMPIA DISTRITO CAPITAL S.A.S. ESP. | D13: ='SALDOS POR NOTA'!C62 -> 0 | E13: ='SALDOS POR NOTA'!D62 -> 0 | F13: ='SALDOS POR NOTA'!E62 -> 0 | G13: ='SALDOS POR NOTA'!F62 -> 0 | H13: ='SALDOS POR NOTA'!G62 -> 0 | I13: ='SALDOS POR NOTA'!H62 -> 0 | J13: 0 | K13: =D13-E13-F13-G13-H13-I13-J13 -> 0 | L13: 0 | M13: =K13-L13 -> 0 | N13: ='SALDOS POR NOTA'!I62 -> 0 | O13: =M13+N13 -> 0 | S13: 5 | T13: AREA LIMPIA DISTRITO CAPITAL S.A.S. ESP. | U13: ='SALDOS POR NOTA'!J62 -> 0 | V13: ='SALDOS POR NOTA'!K62 -> 0 | W13: ='SALDOS POR NOTA'!L62 -> 0 | X13: ='SALDOS POR NOTA'!M62 -> 0 | Y13: ='SALDOS POR NOTA'!N62 -> 0 | Z13: =L13*-1 -> 0 | AA13: ='SALDOS POR NOTA'!O62 -> 0 | AB13: =N13 -> 0 | AC13: =-J13+AD13 -> 0 | AD13: ='SALDOS POR NOTA'!C63 -> 0 | AE13: =SUM(U13:AC13) -> 0 | AF13: =(AE13-O13) -> 0 | AG13: =AF13=0 -> TRUE
C14: TOTAL | D14: =SUM(D9:D13) -> 1329905.5 | E14: =SUM(E9:E13) -> 105933.07 | F14: =SUM(F9:F13) -> 60373.38 | G14: =SUM(G9:G13) -> 30807.04 | H14: =SUM(H9:H13) -> 281311.36 | I14: =SUM(I9:I13) -> 10556.12 | J14: =SUM(J9:J13) -> 0 | K14: =SUM(K9:K13) -> 840924.53 | ... O14: =SUM(O9:O13) -> 840924.53 | T14: TOTAL | U14: =SUM(U9:U13) -> 123246.34 | V14: =SUM(V9:V13) -> 90700.98 | W14: =SUM(W9:W13) -> 399302.95 | X14: =SUM(X9:X13) -> 263333.49 | Y14: =SUM(Y9:Y13) -> 16026.14 | Z14: =SUM(Z9:Z13) -> 0 | AA14: =SUM(AA9:AA13) -> -0.36 | AB14: =SUM(AB9:AB13) -> 0 | ... AF14: =SUM(AF9:AF13) -> 3.6379788e-12 | AG14: =AF14=0 -> FALSE
Y16: =SUM(U14:Y14) -> 892609.9
F18: Firma autorizada
F22: PROCERASEO S.A.S. | I22: NIT: 901 153 639 - 0 | M22: Codigo Remuneración: | N22: =N3 -> 2026072 | U22: PROCERASEO S.A.S. | W22: NIT: 901 153 639 - 0 | AA22: Codigo Remuneración: | AC22: =N22 -> 2026072
F23: 3. ESQUEMA FINANCIERO DEL SERVICIO PUBLICO DE ASEO | U23: 3. ESQUEMA FINANCIERO DEL SERVICIO PUBLICO DE ASEO
F24: Resoluciòn UAESP Número 27 de 2018 | U24: Resoluciòn UAESP Número 27 de 2018
C25: Fecha de Proceso: | D25: =D6 -> 46297 | F25: RETRIBUCION NEGATIVA | U25: =+F25 -> RETRIBUCION NEGATIVA
C26: Hora: | D26: =D7 -> 0.58333333 | F26: Fecha Desde: | H26: =H7 -> 46219 | J26: Feha Hasta: | K26: =K7 -> 46234 | U26: =F26 -> Fecha Desde: | V26: =H26 -> 46219 | X26: =J26 -> Feha Hasta: | Y26: =K26 -> 46234
B27: ASE | C27: Concesionarios | D27: Recaudo Total | E27: Recaudo por disposicion final | F27: Recaudo por tratamiento de lixiviados | G27: Recaudo por Componente VIAT ( Decreto 2412/2018) | H27: Recaudo por aprovechamiento | I27: Recaudo del componente de comercializacion para Aprovechamiento (11,4%) | J27: Balance de subsidio o contribuciones | K27: RECAUDO BASE DE REMUNERACION | L27: Costo de la Interventoría | M27: REMUNERACION FINAL | N27: Conceptos especiales | O27: REMUNERACION FINAL MAS CONCEPTOS ESPECIALES | S27: ASE | T27: Concesionarios | U27: Tarifa de Comercialización del Servicio. ( TCS) | V27: Tarifa de Limpieza Urbana del Servicio. ( TLU) | W27: Tarifa de Barrido y Limpieza del Servicio. ( TBL) | X27: Tarifa de Recolección y Transporte del Servicio. (TRT) | Y27: Recaudo del componente de comercializacion para Aprovechamiento (18,6%) | Z27: Costo de la Interventoría | AA27: Ajuste a la decena | AB27: Conceptos especiales | AC27: Diferencial Balance S / C (Fac vs Rec) | AD27: Balance S / C Con Baase en (Recaudo) | AE27: REMUNERACION FINAL MAS CONCEPTOS ESPECIALES
B28: 1 | C28: PROMOAMBIENTAL DISTRITO S.A.S. ESP. | D28: ='RETRIBUCION NEGATIVA'!C10 -> 0 | E28: ='RETRIBUCION NEGATIVA'!D10 -> 0 | F28: ='RETRIBUCION NEGATIVA'!E10 -> 0 | G28: ='RETRIBUCION NEGATIVA'!F10 -> 0 | H28: ='RETRIBUCION NEGATIVA'!G10 -> 0 | I28: ='RETRIBUCION NEGATIVA'!H10 -> 0 | J28: 0 | K28: =D28-E28-F28-H28-I28-J28-G28 -> 0 | L28: 0 | M28: =K28-L28 -> 0 | N28: ='RETRIBUCION NEGATIVA'!I10 -> 0 | O28: =M28+N28 -> 0 | S28: 1 | T28: PROMOAMBIENTAL DISTRITO S.A.S. ESP. | U28: ='RETRIBUCION NEGATIVA'!J10 -> 0 | V28: ='RETRIBUCION NEGATIVA'!K10 -> 0 | W28: ='RETRIBUCION NEGATIVA'!L10 -> 0 | X28: ='RETRIBUCION NEGATIVA'!M10 -> 0 | Y28: ='RETRIBUCION NEGATIVA'!N10 -> 0 | Z28: =L28*-1 -> 0 | AA28: ='RETRIBUCION NEGATIVA'!O10 -> 0 | AB28: =N28 -> 0 | AC28: =-J28+AD28 -> 0 | AD28: ='RETRIBUCION NEGATIVA'!C11 -> 0 | AE28: =SUM(U28:AC28) -> 0 | AF28: =(AE28-O28) -> 0 | AG28: =AF28=0 -> TRUE
B29: 2 | C29: LIMPIEZA METROPOLITANA S.A. ESP. | D29: ='RETRIBUCION NEGATIVA'!C23 -> 0 | E29: ='RETRIBUCION NEGATIVA'!D23 -> 0 | F29: ='RETRIBUCION NEGATIVA'!E23 -> 0 | G29: ='RETRIBUCION NEGATIVA'!F23 -> 0 | H29: ='RETRIBUCION NEGATIVA'!G23 -> 0 | I29: ='RETRIBUCION NEGATIVA'!H23 -> 0 | J29: 0 | K29: =D29-E29-F29-H29-I29-J29-G29 -> 0 | L29: 0 | M29: =K29-L29 -> 0 | N29: ='RETRIBUCION NEGATIVA'!I23 -> 0 | O29: =M29+N29 -> 0 | S29: 2 | T29: LIMPIEZA METROPOLITANA S.A. ESP. | U29: ='RETRIBUCION NEGATIVA'!J23 -> 0 | V29: ='RETRIBUCION NEGATIVA'!K23 -> 0 | W29: ='RETRIBUCION NEGATIVA'!L23 -> 0 | X29: ='RETRIBUCION NEGATIVA'!M23 -> 0 | Y29: ='RETRIBUCION NEGATIVA'!N23 -> 0 | Z29: =L29*-1 -> 0 | AA29: ='RETRIBUCION NEGATIVA'!O23 -> 0 | AB29: =N29 -> 0 | AC29: =-J29+AD29 -> 0 | AD29: ='RETRIBUCION NEGATIVA'!C24 -> 0 | AE29: =SUM(U29:AC29) -> 0 | AF29: =(AE29-O29) -> 0 | AG29: =AF29=0 -> TRUE
B30: 3 | C30: CIUDAD LIMPIA BOGOTA S.A. ESP. | D30: ='RETRIBUCION NEGATIVA'!C36 -> 0 | E30: ='RETRIBUCION NEGATIVA'!D36 -> 0 | F30: ='RETRIBUCION NEGATIVA'!E36 -> 0 | G30: ='RETRIBUCION NEGATIVA'!F36 -> 0 | H30: ='RETRIBUCION NEGATIVA'!G36 -> 0 | I30: ='RETRIBUCION NEGATIVA'!H36 -> 0 | J30: 0 | K30: =D30-E30-F30-H30-I30-J30-G30 -> 0 | L30: 0 | M30: =K30-L30 -> 0 | N30: ='RETRIBUCION NEGATIVA'!I36 -> 0 | O30: =M30+N30 -> 0 | S30: 3 | T30: CIUDAD LIMPIA BOGOTA S.A. ESP. | U30: ='RETRIBUCION NEGATIVA'!J36 -> 0 | V30: ='RETRIBUCION NEGATIVA'!K36 -> 0 | W30: ='RETRIBUCION NEGATIVA'!L36 -> 0 | X30: ='RETRIBUCION NEGATIVA'!M36 -> 0 | Y30: ='RETRIBUCION NEGATIVA'!N36 -> 0 | Z30: =L30*-1 -> 0 | AA30: ='RETRIBUCION NEGATIVA'!O36 -> 0 | AB30: =N30 -> 0 | AC30: =-J30+AD30 -> 0 | AD30: ='RETRIBUCION NEGATIVA'!C37 -> 0 | AE30: =SUM(U30:AC30) -> 0 | AF30: =(AE30-O30) -> 0 | AG30: =AF30=0 -> TRUE
B31: 4 | C31: BOGOTA LIMPIA S.A.S. ESP. | D31: ='RETRIBUCION NEGATIVA'!C49 -> 0 | E31: ='RETRIBUCION NEGATIVA'!D49 -> 0 | F31: ='RETRIBUCION NEGATIVA'!E49 -> 0 | G31: ='RETRIBUCION NEGATIVA'!F49 -> 0 | H31: ='RETRIBUCION NEGATIVA'!G49 -> 0 | I31: ='RETRIBUCION NEGATIVA'!H49 -> 0 | J31: 0 | K31: =D31-E31-F31-H31-I31-J31-G31 -> 0 | L31: 0 | M31: =K31-L31 -> 0 | N31: ='RETRIBUCION NEGATIVA'!I49 -> 0 | O31: =M31+N31 -> 0 | S31: 4 | T31: BOGOTA LIMPIA S.A.S. ESP. | U31: ='RETRIBUCION NEGATIVA'!J49 -> 0 | V31: ='RETRIBUCION NEGATIVA'!K49 -> 0 | W31: ='RETRIBUCION NEGATIVA'!L49 -> 0 | X31: ='RETRIBUCION NEGATIVA'!M49 -> 0 | Y31: ='RETRIBUCION NEGATIVA'!N49 -> 0 | Z31: =L31*-1 -> 0 | AA31: ='RETRIBUCION NEGATIVA'!O49 -> 0 | AB31: =N31 -> 0 | AC31: =-J31+AD31 -> 0 | AD31: ='RETRIBUCION NEGATIVA'!C50 -> 0 | AE31: =SUM(U31:AC31) -> 0 | AF31: =(AE31-O31) -> 0 | AG31: =AF31=0 -> TRUE
B32: 5 | C32: AREA LIMPIA DISTRITO CAPITAL S.A.S. ESP. | D32: ='RETRIBUCION NEGATIVA'!C62 -> 0 | E32: ='RETRIBUCION NEGATIVA'!D62 -> 0 | F32: ='RETRIBUCION NEGATIVA'!E62 -> 0 | G32: ='RETRIBUCION NEGATIVA'!F62 -> 0 | H32: ='RETRIBUCION NEGATIVA'!G62 -> 0 | I32: ='RETRIBUCION NEGATIVA'!H62 -> 0 | J32: 0 | K32: =D32-E32-F32-H32-I32-J32-G32 -> 0 | L32: 0 | M32: =K32-L32 -> 0 | N32: ='RETRIBUCION NEGATIVA'!I62 -> 0 | O32: =M32+N32 -> 0 | S32: 5 | T32: AREA LIMPIA DISTRITO CAPITAL S.A.S. ESP. | U32: ='RETRIBUCION NEGATIVA'!J62 -> 0 | V32: ='RETRIBUCION NEGATIVA'!K62 -> 0 | W32: ='RETRIBUCION NEGATIVA'!L62 -> 0 | X32: ='RETRIBUCION NEGATIVA'!M62 -> 0 | Y32: ='RETRIBUCION NEGATIVA'!N62 -> 0 | Z32: =L32*-1 -> 0 | AA32: ='RETRIBUCION NEGATIVA'!O62 -> 0 | AB32: =N32 -> 0 | AC32: =-J32+AD32 -> 0 | AD32: ='RETRIBUCION NEGATIVA'!C63 -> 0 | AE32: =SUM(U32:AC32) -> 0 | AF32: =(AE32-O32) -> 0 | AG32: =AF32=0 -> TRUE
C33: TOTAL | D33: =SUM(D28:D32) -> 0 | E33: =SUM(E28:E32) -> 0 | F33: =SUM(F28:F32) -> 0 | G33: =SUM(G28:G32) -> 0 | H33: =SUM(H28:H32) -> 0 | I33: =SUM(I28:I32) -> 0 | J33: =SUM(J28:J32) -> 0 | K33: =SUM(K28:K32) -> 0 | ... O33: =SUM(O28:O32) -> 0 | T33: TOTAL | U33: =SUM(U28:U32) -> 0 | V33: =SUM(V28:V32) -> 0 | W33: =SUM(W28:W32) -> 0 | X33: =SUM(X28:X32) -> 0 | Y33: =SUM(Y28:Y32) -> 0 | Z33: =SUM(Z28:Z32) -> 0 | AA33: =SUM(AA28:AA32) -> 0 | AB33: =SUM(AB28:AB32) -> 0 | ... AF33: =SUM(AF28:AF32) -> 0 | AG33: =AF33=0 -> TRUE
J35: VALIDADOR DE POSTIVIOS EN REMUNERACION NEGATIVA | M35: =IF(MAX(D28:O32,U28:AE32)>0.9,"ERROR",TRUE) -> TRUE | Y35: =SUM(U33:Y33) -> 0
F37: Firma autorizada
F41: PROCERASEO S.A.S. | I41: NIT: 901 153 639 - 0 | M41: Codigo Remuneración: | N41: =N3 -> 2026072 | U41: PROCERASEO S.A.S. | W41: NIT: 901 153 639 - 0 | AA41: Codigo Remuneración: | AC41: =N41 -> 2026072
F42: 3. ESQUEMA FINANCIERO DEL SERVICIO PUBLICO DE ASEO | U42: 3. ESQUEMA FINANCIERO DEL SERVICIO PUBLICO DE ASEO
F43: Resoluciòn UAESP Número 27 de 2018 | U43: Resoluciòn UAESP Número 27 de 2018
C44: Fecha de Proceso: | D44: =D6 -> 46297 | F44: CONSOLIDADO SALDOS A FAVOR | U44: =+F44 -> CONSOLIDADO SALDOS A FAVOR
C45: Hora: | D45: =D7 -> 0.58333333 | F45: Fecha Desde: | H45: =H7 -> 46219 | J45: Feha Hasta: | K45: =K7 -> 46234 | U45: =F45 -> Fecha Desde: | V45: =H45 -> 46219 | X45: =J45 -> Feha Hasta: | Y45: =K45 -> 46234
B46: ASE | C46: Concesionarios | D46: Recaudo Total | E46: Recaudo por disposicion final | F46: Recaudo por tratamiento de lixiviados | G46: Recaudo por Componente VIAT ( Decreto 2412/2018) | H46: Recaudo por aprovechamiento | I46: Recaudo del componente de comercializacion para Aprovechamiento (11,4%) | J46: Balance de subsidio o contribuciones | K46: RECAUDO BASE DE REMUNERACION | L46: Costo de la Interventoría | M46: REMUNERACION FINAL | N46: Conceptos especiales | O46: REMUNERACION FINAL MAS CONCEPTOS ESPECIALES | S46: ASE | T46: Concesionarios | U46: Tarifa de Comercialización del Servicio. ( TCS) | V46: Tarifa de Limpieza Urbana del Servicio. ( TLU) | W46: Tarifa de Barrido y Limpieza del Servicio. ( TBL) | X46: Tarifa de Recolección y Transporte del Servicio. (TRT) | Y46: Recaudo del componente de comercializacion para Aprovechamiento (18,6%) | Z46: Costo de la Interventoría | AA46: Ajuste a la decena | AB46: Conceptos especiales | AC46: Diferencial Balance S / C (Fac vs Rec) | AD46: Balance S / C Con Baase en (Recaudo) | AE46: REMUNERACION FINAL MAS CONCEPTOS ESPECIALES
B47: 1 | C47: PROMOAMBIENTAL DISTRITO S.A.S. ESP. | D47: =D9+D28 -> 973693.46 | E47: =E9+E28 -> 65524.22 | F47: =F9+F28 -> 36995.02 | G47: =G9+G28 -> 19417.65 | H47: =H9+H28 -> 156624.35 | I47: =I9+I28 -> 5557.5 | J47: =J9+J28 -> 0 | K47: =D47-E47-F47-G47-H47-I47-J47 -> 689574.72 | L47: 0 | M47: =K47-L47 -> 689574.72 | N47: =N9+N28 -> 0 | O47: =M47+N47 -> 689574.72 | S47: 1 | T47: PROMOAMBIENTAL DISTRITO S.A.S. ESP. | U47: =U9+U28 -> 52109.79 | V47: =V9+V28 -> 47607.03 | W47: =W9+W28 -> 225441.17 | X47: =X9+X28 -> 178429.31 | Y47: =Y9+Y28 -> 9067.43 | Z47: =-L47 -> 0 | AA47: =AA9+AA28 -> 0 | AB47: =AB9+AB28 -> 0 | AC47: =AC9+AC28 -> 176919.99 | AD47: =AD9+AD28 -> 176919.99 | AE47: =SUM(U47:AC47) -> 689574.72 | AF47: =(AE47-O47) -> 0 | AG47: =AF47=0 -> TRUE
B48: 2 | C48: LIMPIEZA METROPOLITANA S.A. ESP. | D48: =D10+D29 -> 216025.77 | E48: =E10+E29 -> 31897.62 | F48: =F10+F29 -> 18572.91 | G48: =G10+G29 -> 8867.14 | H48: =H10+H29 -> 92959.49 | I48: =I10+I29 -> 3883.88 | J48: =J10+J29 -> 0 | K48: =D48-E48-F48-G48-H48-I48-J48 -> 59844.73 | L48: 0 | M48: =K48-L48 -> 59844.73 | N48: =N10+N29 -> 0 | O48: =M48+N48 -> 59844.73 | S48: 2 | T48: LIMPIEZA METROPOLITANA S.A. ESP. | U48: =U10+U29 -> 61358.09 | V48: =V10+V29 -> 33534.01 | W48: =W10+W29 -> 127815.87 | X48: =X10+X29 -> 64515.32 | Y48: =Y10+Y29 -> 5139.92 | Z48: =-L48 -> 0 | AA48: =AA10+AA29 -> -0.36 | AB48: =AB10+AB29 -> 0 | AC48: =AC10+AC29 -> -232518.12 | AD48: =AD10+AD29 -> -232518.12 | AE48: =SUM(U48:AC48) -> 59844.73 | AF48: =(AE48-O48) -> 7.2759576e-12 | AG48: =AF48=0 -> FALSE
B49: 3 | C49: CIUDAD LIMPIA BOGOTA S.A. ESP. | D49: =D11+D30 -> 104231.83 | E49: =E11+E30 -> 6620.63 | F49: =F11+F30 -> 3738.02 | G49: =G11+G30 -> 1961.98 | H49: =H11+H30 -> 20927.5 | I49: =I11+I30 -> 743.08 | J49: =J11+J30 -> 0 | K49: =D49-E49-F49-G49-H49-I49-J49 -> 70240.62 | L49: 0 | M49: =K49-L49 -> 70240.62 | N49: =N11+N30 -> 0 | O49: =M49+N49 -> 70240.62 | S49: 3 | T49: CIUDAD LIMPIA BOGOTA S.A. ESP. | U49: =U11+U30 -> 6518.28 | V49: =V11+V30 -> 6410.86 | W49: =W11+W30 -> 30349.1 | X49: =X11+X30 -> 15383.1 | Y49: =Y11+Y30 -> 1212.4 | Z49: =-L49 -> 0 | AA49: =AA11+AA30 -> 0 | AB49: =AB11+AB30 -> 0 | AC49: =AC11+AC30 -> 10366.88 | AD49: =AD11+AD30 -> 10366.88 | AE49: =SUM(U49:AC49) -> 70240.62 | AF49: =(AE49-O49) -> 0 | AG49: =AF49=0 -> TRUE
B50: 4 | C50: BOGOTA LIMPIA S.A.S. ESP. | D50: =D12+D31 -> 35954.44 | E50: =E12+E31 -> 1890.6 | F50: =F12+F31 -> 1067.43 | G50: =G12+G31 -> 560.27 | H50: =H12+H31 -> 10800.02 | I50: =I12+I31 -> 371.66 | J50: =J12+J31 -> 0 | K50: =D50-E50-F50-G50-H50-I50-J50 -> 21264.46 | L50: 0 | M50: =K50-L50 -> 21264.46 | N50: =N12+N31 -> 0 | O50: =M50+N50 -> 21264.46 | S50: 4 | T50: BOGOTA LIMPIA S.A.S. ESP. | U50: =U12+U31 -> 3260.18 | V50: =V12+V31 -> 3149.08 | W50: =W12+W31 -> 15696.81 | X50: =X12+X31 -> 5005.76 | Y50: =Y12+Y31 -> 606.39 | Z50: =-L50 -> 0 | AA50: =AA12+AA31 -> 0 | AB50: =AB12+AB31 -> 0 | AC50: =AC12+AC31 -> -6453.76 | AD50: =AD12+AD31 -> -6453.76 | AE50: =SUM(U50:AC50) -> 21264.46 | AF50: =(AE50-O50) -> -3.6379788e-12 | AG50: =AF50=0 -> FALSE
B51: 5 | C51: AREA LIMPIA DISTRITO CAPITAL S.A.S. ESP. | D51: =D13+D32 -> 0 | E51: =E13+E32 -> 0 | F51: =F13+F32 -> 0 | G51: =G13+G32 -> 0 | H51: =H13+H32 -> 0 | I51: =I13+I32 -> 0 | J51: =J13+J32 -> 0 | K51: =D51-E51-F51-G51-H51-I51-J51 -> 0 | L51: 0 | M51: =K51-L51 -> 0 | N51: =N13+N32 -> 0 | O51: =M51+N51 -> 0 | S51: 5 | T51: AREA LIMPIA DISTRITO CAPITAL S.A.S. ESP. | U51: =U13+U32 -> 0 | V51: =V13+V32 -> 0 | W51: =W13+W32 -> 0 | X51: =X13+X32 -> 0 | Y51: =Y13+Y32 -> 0 | Z51: =-L51 -> 0 | AA51: =AA13+AA32 -> 0 | AB51: =AB13+AB32 -> 0 | AC51: =AC13+AC32 -> 0 | AD51: =AD13+AD32 -> 0 | AE51: =SUM(U51:AC51) -> 0 | AF51: =(AE51-O51) -> 0 | AG51: =AF51=0 -> TRUE
C52: TOTAL | D52: =SUM(D47:D51) -> 1329905.5 | E52: =SUM(E47:E51) -> 105933.07 | F52: =SUM(F47:F51) -> 60373.38 | G52: =SUM(G47:G51) -> 30807.04 | H52: =SUM(H47:H51) -> 281311.36 | I52: =SUM(I47:I51) -> 10556.12 | J52: =SUM(J47:J51) -> 0 | K52: =SUM(K47:K51) -> 840924.53 | ... O52: =SUM(O47:O51) -> 840924.53 | T52: TOTAL | U52: =SUM(U47:U51) -> 123246.34 | V52: =SUM(V47:V51) -> 90700.98 | W52: =SUM(W47:W51) -> 399302.95 | X52: =SUM(X47:X51) -> 263333.49 | Y52: =SUM(Y47:Y51) -> 16026.14 | Z52: =SUM(Z47:Z51) -> 0 | AA52: =SUM(AA47:AA51) -> -0.36 | AB52: =SUM(AB47:AB51) -> 0 | ... AF52: =SUM(AF47:AF51) -> 3.6379788e-12 | AG52: =AF52=0 -> FALSE
Y54: =SUM(U52:Y52) -> 892609.9
F56: Firma autorizada

Sheet INTERVENTORIA
F2: 2026 01 2 | G2: 2026 02 1 | H2: 2026 02 2 | I2: 2026 03 1 | J2: 2026 03 2 | K2: 2026 04 1 | L2: 2026 04 2 | M2: 2026 05 1 | N2: 2026 05 2 | O2: 2026 06 1 | P2: 2026 06 2 | Q2: 2026 07 1
B3: VALOR MES | C3: ASE | D3: Concesionarios | E3: % | F3: MITAD 1 // ENERO -26 | G3: MITAD 2 // ENERO -26 | H3: MITAD 1 // FEBRERO -26 | I3: MITAD 2 // FEBRERO -26 | J3: MITAD 1 // MARZO -26 | K3: MITAD 2 // MARZO -26 | L3: MITAD 1 // ABRIL -26 | M3: MITAD 2 // ABRIL -26 | N3: MITAD 1 // MAYO -26 | O3: MITAD 2 // MAYO -26 | P3: MITAD 1 // JUNIO -26 | Q3: MITAD 2 // JUNIO -26
B4: 378371975 | C4: 1 | D4: PROMOAMBIENTAL DISTRITO S.A.S. ESP. | E4: 0.22 | F4: 189185988 | G4: 189185987 | H4: 189185988 | I4: 189185987 | J4: 189185988 | K4: 189185987 | L4: 189185988 | M4: 189185987 | N4: 189185988 | O4: 189185987 | P4: 189185988 | Q4: 189185987
B5: 533160511 | C5: 2 | D5: LIMPIEZA METROPOLITANA S.A. ESP. | E5: 0.31 | F5: 266580256 | G5: 266580255 | H5: 266580256 | I5: 266580255 | J5: 266580256 | K5: 266580255 | L5: 266580256 | M5: 266580255 | N5: 266580256 | O5: 266580255 | P5: 266580256 | Q5: 266580255
B6: 309577071 | C6: 3 | D6: CIUDAD LIMPIA BOGOTA S.A. ESP. | E6: 0.18 | F6: 154788536 | G6: 154788535 | H6: 154788536 | I6: 154788535 | J6: 154788536 | K6: 154788535 | L6: 154788536 | M6: 154788535 | N6: 154788536 | O6: 154788535 | P6: 154788536 | Q6: 154788535
B7: 240782166 | C7: 4 | D7: BOGOTA LIMPIA S.A.S. ESP. | E7: 0.14 | F7: 120391083 | G7: 120391083 | H7: 120391083 | I7: 120391083 | J7: 120391083 | K7: 120391083 | L7: 120391083 | M7: 120391083 | N7: 120391083 | O7: 120391083 | P7: 120391083 | Q7: 120391083
B8: 257980891 | C8: 5 | D8: AREA LIMPIA DISTRITO CAPITAL S.A.S. ESP. | E8: 0.15 | F8: 128990446 | G8: 128990445 | H8: 128990446 | I8: 128990445 | J8: 128990446 | K8: 128990445 | L8: 128990446 | M8: 128990445 | N8: 128990446 | O8: 128990445 | P8: 128990446 | Q8: 128990445
B9: 1719872614 | D9: TOTAL | E9: 1 | F9: 859936309 | G9: 859936305 | H9: 859936309 | I9: 859936305 | J9: 859936309 | K9: 859936305 | L9: 859936309 | M9: 859936305 | N9: 859936309 | O9: 859936305 | P9: 859936309 | Q9: 859936305
F10: =SUM(F9:G9) -> 1719872614 | H10: =SUM(H9:I9) -> 1719872614 | J10: =SUM(J9:K9) -> 1719872614 | L10: =SUM(L9:M9) -> 1719872614 | N10: =SUM(N9:O9) -> 1719872614 | P10: =SUM(P9:Q9) -> 1719872614
F13: 2026 07 2 | G13: 2026 08 1 | H13: 2026 08 2 | I13: 2026 09 1 | J13: 2026 09 2 | K13: 2026 10 1 | L13: 2026 10 2 | M13: 2026 11 1 | N13: 2026 11 2 | O13: 2026 12 1 | P13: 2026 12 2 | Q13: 2027 01 1
C14: ASE | D14: Concesionarios | E14: % | F14: MITAD 1 // JULIO -26 | G14: MITAD 2 // JULIO -26 | H14: MITAD 1 // AGOSTO -26 | I14: MITAD 2 // AGOSTO -26 | J14: MITAD 1 // SEPTIEMBRE -26 | K14: MITAD 2 // SEPTIEMBRE -26 | L14: MITAD 1 // OCTUBRE -26 | M14: MITAD 2 // OCTUBRE -26 | N14: MITAD 1 // NOVIEMBRE -26 | O14: MITAD 2 // NOVIEMBRE -26 | P14: MITAD 1 // DICIEMBRE -26 | Q14: MITAD 2 // DICIEMBRE -26
C15: 1 | D15: PROMOAMBIENTAL DISTRITO S.A.S. ESP. | E15: 0.22 | F15: 189185988 | G15: 189185987 | H15: 189185988 | I15: 189185987 | J15: 189185988 | K15: 189185987 | L15: 189185988 | M15: 189185987 | N15: 189185988 | O15: 189185987 | P15: 189185988 | Q15: 189185987
C16: 2 | D16: LIMPIEZA METROPOLITANA S.A. ESP. | E16: 0.31 | F16: 266580256 | G16: 266580255 | H16: 266580256 | I16: 266580255 | J16: 266580256 | K16: 266580255 | L16: 266580256 | M16: 266580255 | N16: 266580256 | O16: 266580255 | P16: 266580256 | Q16: 266580255
C17: 3 | D17: CIUDAD LIMPIA BOGOTA S.A. ESP. | E17: 0.18 | F17: 154788536 | G17: 154788535 | H17: 154788536 | I17: 154788535 | J17: 154788536 | K17: 154788535 | L17: 154788536 | M17: 154788535 | N17: 154788536 | O17: 154788535 | P17: 154788536 | Q17: 154788535
C18: 4 | D18: BOGOTA LIMPIA S.A.S. ESP. | E18: 0.14 | F18: 120391083 | G18: 120391083 | H18: 120391083 | I18: 120391083 | J18: 120391083 | K18: 120391083 | L18: 120391083 | M18: 120391083 | N18: 120391083 | O18: 120391083 | P18: 120391083 | Q18: 120391083
C19: 5 | D19: AREA LIMPIA DISTRITO CAPITAL S.A.S. ESP. | E19: 0.15 | F19: 128990446 | G19: 128990445 | H19: 128990446 | I19: 128990445 | J19: 128990446 | K19: 128990445 | L19: 128990446 | M19: 128990445 | N19: 128990446 | O19: 128990445 | P19: 128990446 | Q19: 128990445
D20: TOTAL | E20: 1 | F20: 859936309 | G20: 859936305 | H20: 859936309 | I20: 859936305 | J20: 859936309 | K20: 859936305 | L20: 859936309 | M20: 859936305 | N20: 859936309 | O20: 859936305 | P20: 859936309 | Q20: 859936305
F21: =SUM(F20:G20) -> 1719872614 | G21: 1191383498 | H21: =SUM(H20:I20) -> 1719872614 | I21: 1191383498 | J21: =SUM(J20:K20) -> 1719872614 | K21: 1191383498 | L21: =SUM(L20:M20) -> 1719872614 | M21: 1191383498 | N21: =SUM(N20:O20) -> 1719872614 | O21: 1191383498 | P21: =SUM(P20:Q20) -> 1719872614 | Q21: 1191383498
K25: VALOR OFICIAL MES | L25: ASE | M25: Segunda quincena | N25: Primera quincena | R25: VALIDACION
K26: 378371975 | L26: 1 | M26: 189185988 | N26: 189185987 | O26: =M26=R26 -> TRUE | Q26: ='CONSOLIDADO_TOTAL RECAUDO'!L104 -> 189185988 | R26: =J15 -> 189185988 | S26: =Q26=R26 -> TRUE
K27: 533160511 | L27: 2 | M27: 266580256 | N27: 266580255 | O27: =M27=R27 -> TRUE | Q27: ='CONSOLIDADO_TOTAL RECAUDO'!L105 -> 266580256 | R27: =J16 -> 266580256 | S27: =Q27=R27 -> TRUE
K28: 309577071 | L28: 3 | M28: 154788536 | N28: 154788535 | O28: =M28=R28 -> TRUE | Q28: ='CONSOLIDADO_TOTAL RECAUDO'!L106 -> 154788536 | R28: =J17 -> 154788536 | S28: =Q28=R28 -> TRUE
K29: 240782166 | L29: 4 | M29: 120391083 | N29: 120391083 | O29: =M29=R29 -> TRUE | Q29: ='CONSOLIDADO_TOTAL RECAUDO'!L107 -> 120391083 | R29: =J18 -> 120391083 | S29: =Q29=R29 -> TRUE
K30: 257980891 | L30: 5 | M30: 128990446 | N30: 128990445 | O30: =M30=R30 -> TRUE | Q30: ='CONSOLIDADO_TOTAL RECAUDO'!L108 -> 128990446 | R30: =J19 -> 128990446 | S30: =Q30=R30 -> TRUE
K31: =SUM(K26:K30) -> 1719872614 | M31: =SUM(M26:M30) -> 859936309 | N31: =SUM(N26:N30) -> 859936305 | O31: =M31=R31 -> TRUE | Q31: ='CONSOLIDADO_TOTAL RECAUDO'!L109 -> 859936309 | R31: =J20 -> 859936309 | S31: =Q31=R31 -> TRUE
K32: =SUM(M31:N31) -> 1719872614

Sheet Informe AFaseo Recaudo 202607-2
D5: PROCERASEO S.A.S. | I5: NIT: 901 153 639 - 0 | P5: PROCERASEO S.A.S. | T5: NIT: 901 153 639 - 0
D6: INFORME Afaseo // RECAUDO | P6: INFORME AFaseo
D7: BENEFICIO TRANSITORIO ALIVIO SOBRE EL VALOR DE LA FACTURA | P7: BENEFICIO TRANSITORIO ALIVIO SOBRE EL VALOR DE LA FACTURA
D8: Según Resoluciòn UAESP Número 273 de 2.020 | P8: Según Resoluciòn UAESP Número 273 de 2.020
E10: Fecha Desde: | F10: ='CONSOLIDADO_TOTAL RECAUDO'!G102 -> 46219 | H10: Feha Hasta: | I10: ='CONSOLIDADO_TOTAL RECAUDO'!K102 -> 46234
B11: ASE | C11: Concesionarios | D11: Valor Afaseo | E11: Afaseo por disposicion final | F11: Afaseo por tratamiento de lixiviados | G11: Afaseo por Componente VIAT ( Decreto 2412/2018) | H11: Afaseo por aprovechamiento | I11: Afaseo del componente de comercializacion para Aprovechamiento (11,4%) | J11: Afaseo RBL | N11: ASE | O11: Concesionarios | P11: Tarifa de Comercialización del Servicio. ( TCS) | Q11: Tarifa de Limpieza Urbana del Servicio. ( TLU) | R11: Tarifa de Barrido y Limpieza del Servicio. ( TBL) | S11: Tarifa de Recolección y Transporte del Servicio. (TRT) | T11: Componente de comercialización para Aprovechamiento (18,6%) | U11: Afaseo RBL
B12: 1 | C12: PROMOAMBIENTAL DISTRITO S.A.S. ESP. | D12: ='Reporte Componentes R1'!F119*$D$24 -> 11217.37 | E12: ='Reporte Componentes R1'!G119*$D$24 -> 766.38 | F12: ='Reporte Componentes R1'!H119*$D$24 -> 325.59 | G12: ='Reporte Componentes R1'!I119*$D$24 -> 142.17 | H12: ='Reporte Componentes R1'!J119*$D$24 -> 1970.37 | I12: ='Reporte Componentes R1'!K119*$D$24 -> 127.32 | J12: =D12-E12-F12-G12-H12-I12 -> 7885.54 | N12: 1 | O12: PROMOAMBIENTAL DISTRITO S.A.S. ESP. | P12: ='Reporte Componentes R1'!M119*$P$24 -> 1116.82 | Q12: ='Reporte Componentes R1'!N119*$P$24 -> 934.67 | R12: ='Reporte Componentes R1'!O119*$P$24 -> 3730.88 | S12: ='Reporte Componentes R1'!P119*$P$24 -> 1895.43 | T12: ='Reporte Componentes R1'!Q119*$P$24 -> 207.74 | U12: =SUM(P12:T12) -> 7885.54 | V12: =J12-U12 -> 0 | W12: =V12=0 -> TRUE
B13: 2 | C13: LIMPIEZA METROPOLITANA S.A. ESP. | D13: ='Reporte Componentes R1'!F353*$D$24 -> 405906.75 | E13: ='Reporte Componentes R1'!G353*$D$24 -> 36253.24 | F13: ='Reporte Componentes R1'!H353*$D$24 -> 15401.35 | G13: ='Reporte Componentes R1'!I353*$D$24 -> 6725.8 | H13: ='Reporte Componentes R1'!J353*$D$24 -> 80022.36 | I13: ='Reporte Componentes R1'!K353*$D$24 -> 3364.46 | J13: =D13-E13-F13-G13-H13-I13 -> 264139.54 | N13: 2 | O13: LIMPIEZA METROPOLITANA S.A. ESP. | P13: ='Reporte Componentes R1'!M353*$P$24 -> 29514 | Q13: ='Reporte Componentes R1'!N353*$P$24 -> 36987.9 | R13: ='Reporte Componentes R1'!O353*$P$24 -> 124266.63 | S13: ='Reporte Componentes R1'!P353*$P$24 -> 67881.4 | T13: ='Reporte Componentes R1'!Q353*$P$24 -> 5489.61 | U13: =SUM(P13:T13) -> 264139.54 | V13: =J13-U13 -> 0 | W13: =V13=0 -> TRUE
B14: 3 | C14: CIUDAD LIMPIA BOGOTA S.A. ESP. | D14: ='Reporte Componentes R1'!F514*$D$24 -> 16458.46 | E14: ='Reporte Componentes R1'!G514*$D$24 -> 1490.88 | F14: ='Reporte Componentes R1'!H514*$D$24 -> 633.39 | G14: ='Reporte Componentes R1'!I514*$D$24 -> 276.6 | H14: ='Reporte Componentes R1'!J514*$D$24 -> 3142.56 | I14: ='Reporte Componentes R1'!K514*$D$24 -> 129.48 | J14: =D14-E14-F14-G14-H14-I14 -> 10785.55 | N14: 3 | O14: CIUDAD LIMPIA BOGOTA S.A. ESP. | P14: ='Reporte Componentes R1'!M514*$P$24 -> 1135.68 | Q14: ='Reporte Componentes R1'!N514*$P$24 -> 1423.48 | R14: ='Reporte Componentes R1'!O514*$P$24 -> 4781.43 | S14: ='Reporte Componentes R1'!P514*$P$24 -> 3233.73 | T14: ='Reporte Componentes R1'!Q514*$P$24 -> 211.23 | U14: =SUM(P14:T14) -> 10785.55 | V14: =J14-U14 -> 0 | W14: =V14=0 -> TRUE
B15: 4 | C15: BOGOTA LIMPIA S.A.S. ESP. | D15: ='Reporte Componentes R1'!F722*$D$24 -> 439956.52 | E15: ='Reporte Componentes R1'!G722*$D$24 -> 35444.41 | F15: ='Reporte Componentes R1'!H722*$D$24 -> 15058.04 | G15: ='Reporte Componentes R1'!I722*$D$24 -> 6575.73 | H15: ='Reporte Componentes R1'!J722*$D$24 -> 81642.18 | I15: ='Reporte Componentes R1'!K722*$D$24 -> 3324.84 | J15: =D15-E15-F15-G15-H15-I15 -> 297911.32 | N15: 4 | O15: BOGOTA LIMPIA S.A.S. ESP. | P15: ='Reporte Componentes R1'!M722*$P$24 -> 29164.3 | Q15: ='Reporte Componentes R1'!N722*$P$24 -> 37085.49 | R15: ='Reporte Componentes R1'!O722*$P$24 -> 136171.69 | S15: ='Reporte Componentes R1'!P722*$P$24 -> 90064.99 | T15: ='Reporte Componentes R1'!Q722*$P$24 -> 5424.85 | U15: =SUM(P15:T15) -> 297911.32 | V15: =J15-U15 -> 0 | W15: =V15=0 -> TRUE
B16: 5 | C16: AREA LIMPIA DISTRITO CAPITAL S.A.S. ESP. | D16: ='Reporte Componentes R1'!F841*$D$24 -> 0 | E16: ='Reporte Componentes R1'!G841*$D$24 -> 0 | F16: ='Reporte Componentes R1'!H841*$D$24 -> 0 | G16: ='Reporte Componentes R1'!I841*$D$24 -> 0 | H16: ='Reporte Componentes R1'!J841*$D$24 -> 0 | I16: ='Reporte Componentes R1'!K841*$D$24 -> 0 | J16: =D16-E16-F16-G16-H16-I16 -> 0 | N16: 5 | O16: AREA LIMPIA DISTRITO CAPITAL S.A.S. ESP. | P16: ='Reporte Componentes R1'!M841*$P$24 -> 0 | Q16: ='Reporte Componentes R1'!N841*$P$24 -> 0 | R16: ='Reporte Componentes R1'!O841*$P$24 -> 0 | S16: ='Reporte Componentes R1'!P841*$P$24 -> 0 | T16: ='Reporte Componentes R1'!Q841*$P$24 -> 0 | U16: =SUM(P16:T16) -> 0 | V16: =J16-U16 -> 0 | W16: =V16=0 -> TRUE
C17: TOTAL | D17: =SUM(D12:D16) -> 873539.1 | E17: =SUM(E12:E16) -> 73954.91 | F17: =SUM(F12:F16) -> 31418.37 | G17: =SUM(G12:G16) -> 13720.3 | H17: =SUM(H12:H16) -> 166777.47 | I17: =SUM(I12:I16) -> 6946.1 | J17: =SUM(J12:J16) -> 580721.95 | O17: TOTAL | P17: =SUM(P12:P16) -> 60930.8 | Q17: =SUM(Q12:Q16) -> 76431.54 | R17: =SUM(R12:R16) -> 268950.63 | S17: =SUM(S12:S16) -> 163075.55 | T17: =SUM(T12:T16) -> 11333.43 | U17: =SUM(U12:U16) -> 580721.95 | V17: =SUM(V12:V16) -> 0 | W17: =V17=0 -> TRUE
T19: =SUM(P17:T17) -> 580721.95
J20: =+IF(MAX(J12:J17)>500000,"VALIDAR",TRUE) -> VALIDAR
F21: Firma autorizada
D24: -1 | P24: -1

Sheet CONSOLIDADO_TOTAL RECAUDO
F3: PROCERASEO S.A.S. | I3: NIT: 901 153 639 - 0 | M3: Codigo Remuneración: | N3: 2026072 | U3: PROCERASEO S.A.S. | W3: NIT: 901 153 639 - 0 | AA3: Codigo Remuneración: | AD3: =N3 -> 2026072
F4: 3. ESQUEMA FINANCIERO DEL SERVICIO PUBLICO DE ASEO | U4: 3. ESQUEMA FINANCIERO DEL SERVICIO PUBLICO DE ASEO
F5: Resoluciòn UAESP Número 27 de 2018 | U5: Resoluciòn UAESP Número 27 de 2018
C6: Fecha de Proceso: | D6: 46297 | F6: R1 - RECAUDO OPORTUNO | U6: R1 - RECAUDO OPORTUNO
C7: Hora: | D7: 0.58333333 | F7: Fecha Desde: | G7: 46219 | J7: Feha Hasta: | K7: 46234 | U7: =F7 -> Fecha Desde: | V7: =G7 -> 46219 | X7: =J7 -> Feha Hasta: | Y7: =K7 -> 46234
B8: ASE | C8: Concesionarios | D8: Recaudo Total | E8: Recaudo por disposicion final | F8: Recaudo por tratamiento de lixiviados | G8: Recaudo por Componente VIAT ( Decreto 2412/2018) | H8: Recaudo por aprovechamiento | I8: Recaudo del componente de comercializacion para Aprovechamiento (11,4%) | J8: Balance de subsidio o contribuciones | K8: RECAUDO BASE DE REMUNERACION | L8: Costo de la Interventoría | M8: REMUNERACION FINAL | N8: Conceptos especiales | O8: REMUNERACION FINAL MAS CONCEPTOS ESPECIALES | S8: ASE | T8: Concesionarios | U8: Tarifa de Comercialización del Servicio. ( TCS) | V8: Tarifa de Limpieza Urbana del Servicio. ( TLU) | W8: Tarifa de Barrido y Limpieza del Servicio. ( TBL) | X8: Tarifa de Recolección y Transporte del Servicio. (TRT) | Y8: Recaudo del componente de comercializacion para Aprovechamiento (18,6%) | Z8: Costo de la Interventoría | AA8: Ajuste a la decena | AB8: Conceptos especiales | AC8: Otros | AD8: Diferencial Balance S / C (Fac vs Rec) | AE8: Balance S / C Con Base en (Recaudo) | AF8: REMUNERACION FINAL MAS CONCEPTOS ESPECIALES
B9: 1 | C9: PROMOAMBIENTAL DISTRITO S.A.S. ESP. | D9: ='Reporte Componentes R1'!F89 -> 1.7339794e+10 | E9: ='Reporte Componentes R1'!G89 -> 8.9822314e+08 | F9: ='Reporte Componentes R1'!H89 -> 5.0656079e+08 | G9: ='Reporte Componentes R1'!I89 -> 2.6613439e+08 | H9: ='Reporte Componentes R1'!J89 -> 3.794558e+09 | I9: ='Reporte Componentes R1'!K89 -> 1.335427e+08 | J9: ='BCE SC POR FACT.'!F3 -> -3.5894547e+09 | K9: =D9-E9-F9-G9-H9-I9-J9 -> 1.5330229e+10 | L9: =INTERVENTORIA!M26 -> 189185988 | M9: =K9-L9 -> 1.5141043e+10 | N9: ='Reporte Componentes R1'!L89 -> 25277316 | O9: =M9+N9 -> 1.516632e+10 | S9: 1 | T9: PROMOAMBIENTAL DISTRITO S.A.S. ESP. | U9: ='Reporte Componentes R1'!M89 -> 1.1749285e+09 | V9: ='Reporte Componentes R1'!N89 -> 1.1308881e+09 | W9: ='Reporte Componentes R1'!O89 -> 5.3521755e+09 | X9: ='Reporte Componentes R1'!P89 -> 2.4357496e+09 | Y9: ='Reporte Componentes R1'!Q89 -> 2.1790458e+08 | Z9: =L9*-1 -> -189185988 | AA9: ='Reporte Componentes R1'!R89+'Reporte Componentes R1'!U89+'Reporte Componentes R1'!V89 -> -17545.2 | AB9: =N9 -> 25277316 | AC9: ='Reporte Componentes R1'!T89+'Reporte Componentes R1'!W89+'Reporte Componentes R1'!X89+'Reporte Componentes R1'!Y89+'Reporte Componentes R1'!Z89+'Reporte Componentes R1'!S89 -> -1592.61 | AD9: =-J9+AE9 -> 5.018602e+09 | AE9: ='Reporte Componentes R1'!F90 -> 1.4291473e+09 | AF9: =SUM(U9:AD9) -> 1.516632e+10 | AG9: =(AF9-O9) -> -1.9073486e-06 | AH9: =INT(AG9)=0 -> FALSE
B10: 2 | C10: LIMPIEZA METROPOLITANA S.A. ESP. | D10: ='Reporte Componentes R1'!F323 -> 2.0352269e+10 | E10: ='Reporte Componentes R1'!G323 -> 1.5751276e+09 | F10: ='Reporte Componentes R1'!H323 -> 8.8334416e+08 | G10: ='Reporte Componentes R1'!I323 -> 4.6365748e+08 | H10: ='Reporte Componentes R1'!J323 -> 5.7709398e+09 | I10: ='Reporte Componentes R1'!K323 -> 2.210878e+08 | J10: ='BCE SC POR FACT.'!F4 -> -3.2411937e+09 | K10: =D10-E10-F10-G10-H10-I10-J10 -> 1.4679305e+10 | L10: =INTERVENTORIA!M27 -> 266580256 | M10: =K10-L10 -> 1.4412725e+10 | N10: ='Reporte Componentes R1'!L323 -> 53454221 | O10: =M10+N10 -> 1.4466179e+10 | S10: 2 | T10: LIMPIEZA METROPOLITANA S.A. ESP. | U10: ='Reporte Componentes R1'!M323 -> 1.9376362e+09 | V10: ='Reporte Componentes R1'!N323 -> 1.932409e+09 | W10: ='Reporte Componentes R1'!O323 -> 9.1061021e+09 | X10: ='Reporte Componentes R1'!P323 -> 3.1061417e+09 | Y10: ='Reporte Componentes R1'!Q323 -> 3.6126402e+08 | Z10: =L10*-1 -> -266580256 | AA10: ='Reporte Componentes R1'!R323+'Reporte Componentes R1'!U323+'Reporte Componentes R1'!V323 -> 86691.03 | AB10: =N10 -> 53454221 | AC10: ='Reporte Componentes R1'!T323+'Reporte Componentes R1'!W323+'Reporte Componentes R1'!X323+'Reporte Componentes R1'!Y323+'Reporte Componentes R1'!Z323+'Reporte Componentes R1'!S323 -> -123.21 | AD10: =-J10+AE10 -> -1.7643341e+09 | AE10: ='Reporte Componentes R1'!F324 -> -5.0055278e+09 | AF10: =SUM(U10:AD10) -> 1.4466179e+10 | AG10: =(AF10-O10) -> 5.7220459e-06 | AH10: =INT(AG10)=0 -> TRUE
B11: 3 | C11: CIUDAD LIMPIA BOGOTA S.A. ESP. | D11: ='Reporte Componentes R1'!F484 -> 1.5226209e+10 | E11: ='Reporte Componentes R1'!G484 -> 1.1543525e+09 | F11: ='Reporte Componentes R1'!H484 -> 6.5077046e+08 | G11: ='Reporte Componentes R1'!I484 -> 3.4205619e+08 | H11: ='Reporte Componentes R1'!J484 -> 3.4214088e+09 | I11: ='Reporte Componentes R1'!K484 -> 1.2577956e+08 | J11: ='BCE SC POR FACT.'!F5 -> -8.5324456e+08 | K11: =D11-E11-F11-G11-H11-I11-J11 -> 1.0385086e+10 | L11: =INTERVENTORIA!M28 -> 154788536 | M11: =K11-L11 -> 1.0230298e+10 | N11: ='Reporte Componentes R1'!L484 -> 14319221 | O11: =M11+N11 -> 1.0244617e+10 | S11: 3 | T11: CIUDAD LIMPIA BOGOTA S.A. ESP. | U11: ='Reporte Componentes R1'!M484 -> 1.1030915e+09 | V11: ='Reporte Componentes R1'!N484 -> 1.086972e+09 | W11: ='Reporte Componentes R1'!O484 -> 5.1439124e+09 | X11: ='Reporte Componentes R1'!P484 -> 2.6844228e+09 | Y11: ='Reporte Componentes R1'!Q484 -> 2.0532074e+08 | Z11: =L11*-1 -> -154788536 | AA11: ='Reporte Componentes R1'!R484+'Reporte Componentes R1'!U484+'Reporte Componentes R1'!V484 -> 246494.88 | AB11: =N11 -> 14319221 | AC11: ='Reporte Componentes R1'!T484+'Reporte Componentes R1'!W484+'Reporte Componentes R1'!X484+'Reporte Componentes R1'!Y484+'Reporte Componentes R1'!Z484+'Reporte Componentes R1'!S484 -> -11886.32 | AD11: =-J11+AE11 -> 1.6113214e+08 | AE11: ='Reporte Componentes R1'!F485 -> -6.9211242e+08 | AF11: =SUM(U11:AD11) -> 1.0244617e+10 | AG11: =(AF11-O11) -> -1.9073486e-06 | AH11: =INT(AG11)=0 -> FALSE
B12: 4 | C12: BOGOTA LIMPIA S.A.S. ESP. | D12: ='Reporte Componentes R1'!F692 -> 7.0474925e+09 | E12: ='Reporte Componentes R1'!G692 -> 4.6047444e+08 | F12: ='Reporte Componentes R1'!H692 -> 2.5701337e+08 | G12: ='Reporte Componentes R1'!I692 -> 1.3430593e+08 | H12: ='Reporte Componentes R1'!J692 -> 1.5789239e+09 | I12: ='Reporte Componentes R1'!K692 -> 61673075 | J12: ='BCE SC POR FACT.'!F6 -> -6.9988271e+08 | K12: =D12-E12-F12-G12-H12-I12-J12 -> 5.2549845e+09 | L12: =INTERVENTORIA!M29 -> 120391083 | M12: =K12-L12 -> 5.1345934e+09 | N12: ='Reporte Componentes R1'!L692 -> 34128345 | O12: =M12+N12 -> 5.1687217e+09 | S12: 4 | T12: BOGOTA LIMPIA S.A.S. ESP. | U12: ='Reporte Componentes R1'!M692 -> 5.4155502e+08 | V12: ='Reporte Componentes R1'!N692 -> 5.4004565e+08 | W12: ='Reporte Componentes R1'!O692 -> 2.7618559e+09 | X12: ='Reporte Componentes R1'!P692 -> 1.2186725e+09 | Y12: ='Reporte Componentes R1'!Q692 -> 1.0084121e+08 | Z12: =L12*-1 -> -120391083 | AA12: ='Reporte Componentes R1'!R692+'Reporte Componentes R1'!U692+'Reporte Componentes R1'!V692 -> -16277.43 | AB12: =N12 -> 34128345 | AC12: ='Reporte Componentes R1'!T692+'Reporte Componentes R1'!W692+'Reporte Componentes R1'!X692+'Reporte Componentes R1'!Y692+'Reporte Componentes R1'!Z692+'Reporte Componentes R1'!S692 -> -440.07 | AD12: =-J12+AE12 -> 92030892 | AE12: ='Reporte Componentes R1'!F693 -> -6.0785182e+08 | AF12: =SUM(U12:AD12) -> 5.1687217e+09 | AG12: =(AF12-O12) -> 1.9073486e-06 | AH12: =INT(AG12)=0 -> TRUE
B13: 5 | C13: AREA LIMPIA DISTRITO CAPITAL S.A.S. ESP. | D13: ='Reporte Componentes R1'!F811 -> 1.2033012e+10 | E13: ='Reporte Componentes R1'!G811 -> 7.2881764e+08 | F13: ='Reporte Componentes R1'!H811 -> 4.1084319e+08 | G13: ='Reporte Componentes R1'!I811 -> 2.1546417e+08 | H13: ='Reporte Componentes R1'!J811 -> 2.7646495e+09 | I13: ='Reporte Componentes R1'!K811 -> 1.0563604e+08 | J13: ='BCE SC POR FACT.'!F7 -> -82959024 | K13: =D13-E13-F13-G13-H13-I13-J13 -> 7.8905601e+09 | L13: =INTERVENTORIA!M30 -> 128990446 | M13: =K13-L13 -> 7.7615697e+09 | N13: ='Reporte Componentes R1'!L811 -> 14901729 | O13: =M13+N13 -> 7.7764714e+09 | S13: 5 | T13: AREA LIMPIA DISTRITO CAPITAL S.A.S. ESP. | U13: ='Reporte Componentes R1'!M811 -> 9.2615879e+08 | V13: ='Reporte Componentes R1'!N811 -> 9.0889738e+08 | W13: ='Reporte Componentes R1'!O811 -> 4.6714789e+09 | X13: ='Reporte Componentes R1'!P811 -> 2.1651157e+09 | Y13: ='Reporte Componentes R1'!Q811 -> 1.7241858e+08 | Z13: =L13*-1 -> -128990446 | AA13: ='Reporte Componentes R1'!R811+'Reporte Componentes R1'!U811+'Reporte Componentes R1'!V811 -> -147734.33 | AB13: =N13 -> 14901729 | AC13: ='Reporte Componentes R1'!T811+'Reporte Componentes R1'!W811+'Reporte Componentes R1'!X811+'Reporte Componentes R1'!Y811+'Reporte Componentes R1'!Z811+'Reporte Componentes R1'!S811 -> -32.98 | AD13: =-J13+AE13 -> -9.533615e+08 | AE13: ='Reporte Componentes R1'!F812 -> -1.0363205e+09 | AF13: =SUM(U13:AD13) -> 7.7764714e+09 | AG13: =(AF13-O13) -> -9.5367432e-07 | AH13: =INT(AG13)=0 -> FALSE
C14: TOTAL | D14: =SUM(D9:D13) -> 7.1998775e+10 | E14: =SUM(E9:E13) -> 4.8169953e+09 | F14: =SUM(F9:F13) -> 2.708532e+09 | G14: =SUM(G9:G13) -> 1.4216182e+09 | H14: =SUM(H9:H13) -> 1.733048e+10 | I14: =SUM(I9:I13) -> 6.4771917e+08 | J14: =SUM(J9:J13) -> -8.4667347e+09 | K14: =SUM(K9:K13) -> 5.3540165e+10 | ... O14: =SUM(O9:O13) -> 5.282231e+10 | T14: TOTAL | U14: =SUM(U9:U13) -> 5.68337e+09 | V14: =SUM(V9:V13) -> 5.5992122e+09 | W14: =SUM(W9:W13) -> 2.7035525e+10 | X14: =SUM(X9:X13) -> 1.1610102e+10 | Y14: =SUM(Y9:Y13) -> 1.0577491e+09 | Z14: =SUM(Z9:Z13) -> -859936309 | AA14: =SUM(AA9:AA13) -> 151628.95 | AB14: =SUM(AB9:AB13) -> 1.4208083e+08 | ... AG14: =SUM(AG9:AG13) -> 2.8610229e-06 | AH14: =INT(AG14)=0 -> TRUE
Y16: =SUM(U14:Y14) -> 5.0985959e+10
F18: Firma autorizada
F22: PROCERASEO S.A.S. | I22: NIT: 901 153 639 - 0 | M22: Codigo Remuneración: | N22: =N3 -> 2026072 | U22: PROCERASEO S.A.S. | W22: NIT: 901 153 639 - 0 | AA22: Codigo Remuneración: | AD22: =N22 -> 2026072
F23: 3. ESQUEMA FINANCIERO DEL SERVICIO PUBLICO DE ASEO | U23: 3. ESQUEMA FINANCIERO DEL SERVICIO PUBLICO DE ASEO
F24: Resoluciòn UAESP Número 27 de 2018 | U24: Resoluciòn UAESP Número 27 de 2018
C25: Fecha de Proceso: | D25: =D6 -> 46297 | F25: R2 - ANTICIPOS A USUARIOS | U25: R2 - ANTICIPOS A USUARIOS
C26: Hora: | D26: =D7 -> 0.58333333 | F26: Fecha Desde: | G26: =G7 -> 46219 | J26: Feha Hasta: | K26: =K7 -> 46234 | U26: =F26 -> Fecha Desde: | V26: =G26 -> 46219 | X26: =J26 -> Feha Hasta: | Y26: =K26 -> 46234
B27: ASE | C27: Concesionarios | D27: Recaudo Total | E27: Recaudo por disposicion final | F27: Recaudo por tratamiento de lixiviados | G27: Recaudo por Componente VIAT ( Decreto 2412/2018) | H27: Recaudo por aprovechamiento | I27: Recaudo del componente de comercializacion para Aprovechamiento (11,4%) | J27: Balance de subsidio o contribuciones | K27: RECAUDO BASE DE REMUNERACION | L27: Costo de la Interventoría | M27: REMUNERACION FINAL | N27: Conceptos especiales | O27: REMUNERACION FINAL MAS CONCEPTOS ESPECIALES | S27: ASE | T27: Concesionarios | U27: Tarifa de Comercialización del Servicio. ( TCS) | V27: Tarifa de Limpieza Urbana del Servicio. ( TLU) | W27: Tarifa de Barrido y Limpieza del Servicio. ( TBL) | X27: Tarifa de Recolección y Transporte del Servicio. (TRT) | Y27: Recaudo del componente de comercializacion para Aprovechamiento (18,6%) | Z27: Costo de la Interventoría | AA27: Ajuste a la decena | AB27: Conceptos especiales | AC27: Otros | AD27: Diferencial Balance S / C (Fac vs Rec) | AE27: Balance S / C Con Base en (Recaudo) | AF27: REMUNERACION FINAL MAS CONCEPTOS ESPECIALES
B28: 1 | C28: PROMOAMBIENTAL DISTRITO S.A.S. ESP. | D28: ='Rem. Anticipos R2'!E57 -> 1.2594855e+08 | E28: ='Rem. Anticipos R2'!F57 -> 9640402.9 | F28: ='Rem. Anticipos R2'!G57 -> 5490662.7 | G28: ='Rem. Anticipos R2'!H57 -> 2785450 | H28: ='Rem. Anticipos R2'!I57 -> 24544068 | I28: ='Rem. Anticipos R2'!J57 -> 964886.66 | J28: 0 | K28: =D28-E28-F28-G28-H28-I28-J28 -> 82523083 | L28: 0 | M28: =K28-L28 -> 82523083 | N28: ='Rem. Anticipos R2'!K57 -> 0 | O28: =M28+N28 -> 82523083 | S28: 1 | T28: PROMOAMBIENTAL DISTRITO S.A.S. ESP. | U28: ='Rem. Anticipos R2'!L57 -> 8824083.3 | V28: ='Rem. Anticipos R2'!M57 -> 8523193.1 | W28: ='Rem. Anticipos R2'!N57 -> 37613665 | X28: ='Rem. Anticipos R2'!O57 -> 27011615 | Y28: ='Rem. Anticipos R2'!P57 -> 1394039.6 | Z28: =L28*-1 -> 0 | AA28: ='Rem. Anticipos R2'!Q57 -> -73.75 | AB28: =N28 -> 0 | AC28: ='Rem. Anticipos R2'!R57 -> 0 | AD28: =-J28+AE28 -> -843439.3 | AE28: ='Rem. Anticipos R2'!E58 -> -843439.3 | AF28: =SUM(U28:AD28) -> 82523083 | AG28: =(AF28-O28) -> 0 | AH28: =INT(AG28)=0 -> TRUE
B29: 2 | C29: LIMPIEZA METROPOLITANA S.A. ESP. | D29: ='Rem. Anticipos R2'!E178 -> 1.7853909e+08 | E29: ='Rem. Anticipos R2'!F178 -> 17193125 | F29: ='Rem. Anticipos R2'!G178 -> 9759590.5 | G29: ='Rem. Anticipos R2'!H178 -> 4674886.5 | H29: ='Rem. Anticipos R2'!I178 -> 47216081 | I29: ='Rem. Anticipos R2'!J178 -> 1451359.2 | J29: 0 | K29: =D29-E29-F29-G29-H29-I29-J29 -> 98244049 | L29: 0 | M29: =K29-L29 -> 98244049 | N29: ='Rem. Anticipos R2'!K178 -> 0 | O29: =M29+N29 -> 98244049 | S29: 2 | T29: LIMPIEZA METROPOLITANA S.A. ESP. | U29: ='Rem. Anticipos R2'!L178 -> 13193070 | V29: ='Rem. Anticipos R2'!M178 -> 14193304 | W29: ='Rem. Anticipos R2'!N178 -> 54326292 | X29: ='Rem. Anticipos R2'!O178 -> 52723995 | Y29: ='Rem. Anticipos R2'!P178 -> 1920514 | Z29: =L29*-1 -> 0 | AA29: ='Rem. Anticipos R2'!Q178 -> 181.61 | AB29: =N29 -> 0 | AC29: ='Rem. Anticipos R2'!R178 -> 0 | AD29: =-J29+AE29 -> -38113307 | AE29: ='Rem. Anticipos R2'!E179 -> -38113307 | AF29: =SUM(U29:AD29) -> 98244049 | AG29: =(AF29-O29) -> 1.4901161e-08 | AH29: =INT(AG29)=0 -> TRUE
B30: 3 | C30: CIUDAD LIMPIA BOGOTA S.A. ESP. | D30: ='Rem. Anticipos R2'!E299 -> 26586328 | E30: ='Rem. Anticipos R2'!F299 -> 2669416 | F30: ='Rem. Anticipos R2'!G299 -> 1115118.9 | G30: ='Rem. Anticipos R2'!H299 -> 766590.87 | H30: ='Rem. Anticipos R2'!I299 -> 3649866.3 | I30: ='Rem. Anticipos R2'!J299 -> 117977.5 | J30: 0 | K30: =D30-E30-F30-G30-H30-I30-J30 -> 18267359 | L30: 0 | M30: =K30-L30 -> 18267359 | N30: ='Rem. Anticipos R2'!K299 -> 22742.37 | O30: =M30+N30 -> 18290101 | S30: 3 | T30: CIUDAD LIMPIA BOGOTA S.A. ESP. | U30: ='Rem. Anticipos R2'!L299 -> 1069586.7 | V30: ='Rem. Anticipos R2'!M299 -> 1249645.9 | W30: ='Rem. Anticipos R2'!N299 -> 6297254.5 | X30: ='Rem. Anticipos R2'!O299 -> 6569127.8 | Y30: ='Rem. Anticipos R2'!P299 -> 179885.12 | Z30: =L30*-1 -> 0 | AA30: ='Rem. Anticipos R2'!Q299 -> 46.22 | AB30: =N30 -> 22742.37 | AC30: ='Rem. Anticipos R2'!R299 -> 0 | AD30: =-J30+AE30 -> 2901812.5 | AE30: ='Rem. Anticipos R2'!E300 -> 2901812.5 | AF30: =SUM(U30:AD30) -> 18290101 | AG30: =(AF30-O30) -> 0 | AH30: =INT(AG30)=0 -> TRUE
B31: 4 | C31: BOGOTA LIMPIA S.A.S. ESP. | D31: ='Rem. Anticipos R2'!E423 -> 1.6146195e+08 | E31: ='Rem. Anticipos R2'!F423 -> 16099105 | F31: ='Rem. Anticipos R2'!G423 -> 9061043.2 | G31: ='Rem. Anticipos R2'!H423 -> 2852946.1 | H31: ='Rem. Anticipos R2'!I423 -> 32340246 | I31: ='Rem. Anticipos R2'!J423 -> 1124253 | J31: 0 | K31: =D31-E31-F31-G31-H31-I31-J31 -> 99984356 | L31: 0 | M31: =K31-L31 -> 99984356 | N31: ='Rem. Anticipos R2'!K423 -> 0 | O31: =M31+N31 -> 99984356 | S31: 4 | T31: BOGOTA LIMPIA S.A.S. ESP. | U31: ='Rem. Anticipos R2'!L423 -> 9787993.9 | V31: ='Rem. Anticipos R2'!M423 -> 10109598 | W31: ='Rem. Anticipos R2'!N423 -> 46326513 | X31: ='Rem. Anticipos R2'!O423 -> 43710042 | Y31: ='Rem. Anticipos R2'!P423 -> 1759287.8 | Z31: =L31*-1 -> 0 | AA31: ='Rem. Anticipos R2'!Q423 -> 4.56 | AB31: =N31 -> 0 | AC31: ='Rem. Anticipos R2'!R423 -> 0 | AD31: =-J31+AE31 -> -11709083 | AE31: ='Rem. Anticipos R2'!E424 -> -11709083 | AF31: =SUM(U31:AD31) -> 99984356 | AG31: =(AF31-O31) -> -2.9802322e-08 | AH31: =INT(AG31)=0 -> FALSE
B32: 5 | C32: AREA LIMPIA DISTRITO CAPITAL S.A.S. ESP. | D32: ='Rem. Anticipos R2'!E510 -> 42983502 | E32: ='Rem. Anticipos R2'!F510 -> 3046795 | F32: ='Rem. Anticipos R2'!G510 -> 1737546.6 | G32: ='Rem. Anticipos R2'!H510 -> 808529.7 | H32: ='Rem. Anticipos R2'!I510 -> 7182406.2 | I32: ='Rem. Anticipos R2'!J510 -> 249175.55 | J32: 0 | K32: =D32-E32-F32-G32-H32-I32-J32 -> 29959049 | L32: 0 | M32: =K32-L32 -> 29959049 | N32: ='Rem. Anticipos R2'!K510 -> 990006.55 | O32: =M32+N32 -> 30949056 | S32: 5 | T32: AREA LIMPIA DISTRITO CAPITAL S.A.S. ESP. | U32: ='Rem. Anticipos R2'!L510 -> 2265402.9 | V32: ='Rem. Anticipos R2'!M510 -> 2501140.3 | W32: ='Rem. Anticipos R2'!N510 -> 10769603 | X32: ='Rem. Anticipos R2'!O510 -> 9260216.2 | Y32: ='Rem. Anticipos R2'!P510 -> 352055.57 | Z32: =L32*-1 -> 0 | AA32: ='Rem. Anticipos R2'!Q510 -> -10.37 | AB32: =N32 -> 990006.55 | AC32: ='Rem. Anticipos R2'!R510 -> 0 | AD32: =-J32+AE32 -> 4810642.2 | AE32: ='Rem. Anticipos R2'!E511 -> 4810642.2 | AF32: =SUM(U32:AD32) -> 30949056 | AG32: =(AF32-O32) -> 7.4505806e-09 | AH32: =INT(AG32)=0 -> TRUE
C33: TOTAL | D33: =SUM(D28:D32) -> 5.3551943e+08 | E33: =SUM(E28:E32) -> 48648844 | F33: =SUM(F28:F32) -> 27163962 | G33: =SUM(G28:G32) -> 11888403 | H33: =SUM(H28:H32) -> 1.1493267e+08 | I33: =SUM(I28:I32) -> 3907652 | J33: =SUM(J28:J32) -> 0 | K33: =SUM(K28:K32) -> 3.289779e+08 | ... O33: =SUM(O28:O32) -> 3.2999065e+08 | T33: TOTAL | U33: =SUM(U28:U32) -> 35140137 | V33: =SUM(V28:V32) -> 36576881 | W33: =SUM(W28:W32) -> 1.5533333e+08 | X33: =SUM(X28:X32) -> 1.39275e+08 | Y33: =SUM(Y28:Y32) -> 5605782.1 | Z33: =SUM(Z28:Z32) -> 0 | AA33: =SUM(AA28:AA32) -> 148.27 | AB33: =SUM(AB28:AB32) -> 1012748.9 | ... AG33: =SUM(AG28:AG32) -> -7.4505806e-09 | AH33: =INT(AG33)=0 -> FALSE
Y35: =SUM(U33:Y33) -> 3.7193112e+08
F37: Firma autorizada
F41: PROCERASEO S.A.S. | I41: NIT: 901 153 639 - 0 | M41: Codigo Remuneración: | N41: =N3 -> 2026072 | U41: PROCERASEO S.A.S. | W41: NIT: 901 153 639 - 0 | AA41: Codigo Remuneración: | AD41: =N41 -> 2026072
F42: 3. ESQUEMA FINANCIERO DEL SERVICIO PUBLICO DE ASEO | U42: 3. ESQUEMA FINANCIERO DEL SERVICIO PUBLICO DE ASEO
F43: Resoluciòn UAESP Número 27 de 2018 | U43: Resoluciòn UAESP Número 27 de 2018
C44: Fecha de Proceso: | D44: =D6 -> 46297 | F44: R3 - RECAUDO EXTEMPORANEO | U44: R3 - RECAUDO EXTEMPORANEO
C45: Hora: | D45: =D7 -> 0.58333333 | F45: Fecha Desde: | G45: =G7 -> 46219 | J45: Feha Hasta: | K45: =K7 -> 46234 | U45: =F45 -> Fecha Desde: | V45: =G45 -> 46219 | X45: =J45 -> Feha Hasta: | Y45: =K45 -> 46234
B46: ASE | C46: Concesionarios | D46: Recaudo Total | E46: Recaudo por disposicion final | F46: Recaudo por tratamiento de lixiviados | G46: Recaudo por Componente VIAT ( Decreto 2412/2018) | H46: Recaudo por aprovechamiento | I46: Recaudo del componente de comercializacion para Aprovechamiento (11,4%) | J46: Balance de subsidio o contribuciones | K46: RECAUDO BASE DE REMUNERACION | L46: Costo de la Interventoría | M46: REMUNERACION FINAL | N46: Conceptos especiales | O46: REMUNERACION FINAL MAS CONCEPTOS ESPECIALES | S46: ASE | T46: Concesionarios | U46: Tarifa de Comercialización del Servicio. ( TCS) | V46: Tarifa de Limpieza Urbana del Servicio. ( TLU) | W46: Tarifa de Barrido y Limpieza del Servicio. ( TBL) | X46: Tarifa de Recolección y Transporte del Servicio. (TRT) | Y46: Recaudo del componente de comercializacion para Aprovechamiento (18,6%) | Z46: Costo de la Interventoría | AA46: Ajuste a la decena | AB46: Conceptos especiales | AC46: Otros | AD46: Diferencial Balance S / C (Fac vs Rec) | AE46: Balance S / C Con Base en (Recaudo) | AF46: REMUNERACION FINAL MAS CONCEPTOS ESPECIALES
B47: 1 | C47: PROMOAMBIENTAL DISTRITO S.A.S. ESP. | D47: ='Reporte Componentes R1'!F91 -> 49580 | E47: ='Reporte Componentes R1'!G91 -> 2007.44 | F47: ='Reporte Componentes R1'!H91 -> 1133.38 | G47: ='Reporte Componentes R1'!I91 -> 594.88 | H47: ='Reporte Componentes R1'!J91 -> 0 | I47: ='Reporte Componentes R1'!K91 -> 0 | J47: 0 | K47: =D47-E47-F47-G47-H47-I47-J47 -> 45844.3 | L47: 0 | M47: =K47-L47 -> 45844.3 | N47: ='Reporte Componentes R1'!L91 -> 0 | O47: =M47+N47 -> 45844.3 | S47: 1 | T47: PROMOAMBIENTAL DISTRITO S.A.S. ESP. | U47: ='Reporte Componentes R1'!M91 -> 0 | V47: ='Reporte Componentes R1'!N91 -> 0 | W47: ='Reporte Componentes R1'!O91 -> 0 | X47: ='Reporte Componentes R1'!P91 -> 5482.6 | Y47: ='Reporte Componentes R1'!Q91 -> 0 | Z47: =-L47 -> 0 | AA47: ='Reporte Componentes R1'!R91+'Reporte Componentes R1'!V91+'Reporte Componentes R1'!U91 -> -2.61 | AB47: =N47 -> 0 | AC47: ='Reporte Componentes R1'!T91+'Reporte Componentes R1'!W91+'Reporte Componentes R1'!X91+'Reporte Componentes R1'!Y91+'Reporte Componentes R1'!Z91+'Reporte Componentes R1'!S91 -> 0 | AD47: =-J47+AE47 -> 40364.31 | AE47: ='Reporte Componentes R1'!F92 -> 40364.31 | AF47: =SUM(U47:AD47) -> 45844.3 | AG47: =(AF47-O47) -> -7.2759576e-12 | AH47: =INT(AG47)=0 -> FALSE
B48: 2 | C48: LIMPIEZA METROPOLITANA S.A. ESP. | D48: ='Reporte Componentes R1'!F325 -> 56190070 | E48: ='Reporte Componentes R1'!G325 -> 7708934.9 | F48: ='Reporte Componentes R1'!H325 -> 4358213 | G48: ='Reporte Componentes R1'!I325 -> 2310135.7 | H48: ='Reporte Componentes R1'!J325 -> 173927.38 | I48: ='Reporte Componentes R1'!K325 -> 5311.09 | J48: 0 | K48: =D48-E48-F48-G48-H48-I48-J48 -> 41633548 | L48: 0 | M48: =K48-L48 -> 41633548 | N48: ='Reporte Componentes R1'!L325 -> 0 | O48: =M48+N48 -> 41633548 | S48: 2 | T48: LIMPIEZA METROPOLITANA S.A. ESP. | U48: ='Reporte Componentes R1'!M325 -> 46588.43 | V48: ='Reporte Componentes R1'!N325 -> 53938.06 | W48: ='Reporte Componentes R1'!O325 -> 251431.52 | X48: ='Reporte Componentes R1'!P325 -> 15476286 | Y48: ='Reporte Componentes R1'!Q325 -> 8665.45 | Z48: =-L48 -> 0 | AA48: ='Reporte Componentes R1'!R325+'Reporte Componentes R1'!V325+'Reporte Componentes R1'!U325 -> -0.41 | AB48: =N48 -> 0 | AC48: ='Reporte Componentes R1'!T325+'Reporte Componentes R1'!W325+'Reporte Componentes R1'!X325+'Reporte Componentes R1'!Y325+'Reporte Componentes R1'!Z325+'Reporte Componentes R1'!S325 -> 0 | AD48: =-J48+AE48 -> 25796638 | AE48: ='Reporte Componentes R1'!F326 -> 25796638 | AF48: =SUM(U48:AD48) -> 41633548 | AG48: =(AF48-O48) -> 0 | AH48: =INT(AG48)=0 -> TRUE
B49: 3 | C49: CIUDAD LIMPIA BOGOTA S.A. ESP. | D49: ='Reporte Componentes R1'!F486 -> 1307680 | E49: ='Reporte Componentes R1'!G486 -> 147598.38 | F49: ='Reporte Componentes R1'!H486 -> 66140.96 | G49: ='Reporte Componentes R1'!I486 -> 37291.57 | H49: ='Reporte Componentes R1'!J486 -> 33572.08 | I49: ='Reporte Componentes R1'!K486 -> 682.45 | J49: 0 | K49: =D49-E49-F49-G49-H49-I49-J49 -> 1022394.6 | L49: 0 | M49: =K49-L49 -> 1022394.6 | N49: ='Reporte Componentes R1'!L486 -> 0 | O49: =M49+N49 -> 1022394.6 | S49: 3 | T49: CIUDAD LIMPIA BOGOTA S.A. ESP. | U49: ='Reporte Componentes R1'!M486 -> 5991.23 | V49: ='Reporte Componentes R1'!N486 -> 7293.25 | W49: ='Reporte Componentes R1'!O486 -> 33919.09 | X49: ='Reporte Componentes R1'!P486 -> 346942.9 | Y49: ='Reporte Componentes R1'!Q486 -> 1113.37 | Z49: =-L49 -> 0 | AA49: ='Reporte Componentes R1'!R486+'Reporte Componentes R1'!V486+'Reporte Componentes R1'!U486 -> -7.95 | AB49: =N49 -> 0 | AC49: ='Reporte Componentes R1'!T486+'Reporte Componentes R1'!W486+'Reporte Componentes R1'!X486+'Reporte Componentes R1'!Y486+'Reporte Componentes R1'!Z486+'Reporte Componentes R1'!S486 -> 0.7 | AD49: =-J49+AE49 -> 627141.97 | AE49: ='Reporte Componentes R1'!F487 -> 627141.97 | AF49: =SUM(U49:AD49) -> 1022394.6 | AG49: =(AF49-O49) -> -1.1641532e-10 | AH49: =INT(AG49)=0 -> FALSE
B50: 4 | C50: BOGOTA LIMPIA S.A.S. ESP. | D50: ='Reporte Componentes R1'!F694 -> 4343101 | E50: ='Reporte Componentes R1'!G694 -> 311438.06 | F50: ='Reporte Componentes R1'!H694 -> 174745.19 | G50: ='Reporte Componentes R1'!I694 -> 94552.57 | H50: ='Reporte Componentes R1'!J694 -> 971475.94 | I50: ='Reporte Componentes R1'!K694 -> 31532.52 | J50: 0 | K50: =D50-E50-F50-G50-H50-I50-J50 -> 2759356.7 | L50: 0 | M50: =K50-L50 -> 2759356.7 | N50: ='Reporte Componentes R1'!L694 -> 0 | O50: =M50+N50 -> 2759356.7 | S50: 4 | T50: BOGOTA LIMPIA S.A.S. ESP. | U50: ='Reporte Componentes R1'!M694 -> 280120.46 | V50: ='Reporte Componentes R1'!N694 -> 309903.63 | W50: ='Reporte Componentes R1'!O694 -> 1543098.8 | X50: ='Reporte Componentes R1'!P694 -> 830464.64 | Y50: ='Reporte Componentes R1'!Q694 -> 53321.16 | Z50: =-L50 -> 0 | AA50: ='Reporte Componentes R1'!R694+'Reporte Componentes R1'!V694+'Reporte Componentes R1'!U694 -> 10.98 | AB50: =N50 -> 0 | AC50: ='Reporte Componentes R1'!T694+'Reporte Componentes R1'!W694+'Reporte Componentes R1'!X694+'Reporte Componentes R1'!Y694+'Reporte Componentes R1'!Z694+'Reporte Componentes R1'!S694 -> -88.74 | AD50: =-J50+AE50 -> -257474.16 | AE50: ='Reporte Componentes R1'!F695 -> -257474.16 | AF50: =SUM(U50:AD50) -> 2759356.7 | AG50: =(AF50-O50) -> -4.6566129e-10 | AH50: =INT(AG50)=0 -> FALSE
B51: 5 | C51: AREA LIMPIA DISTRITO CAPITAL S.A.S. ESP. | D51: ='Reporte Componentes R1'!F813 -> 441849 | E51: ='Reporte Componentes R1'!G813 -> 26657.43 | F51: ='Reporte Componentes R1'!H813 -> 14138.02 | G51: ='Reporte Componentes R1'!I813 -> 7723.27 | H51: ='Reporte Componentes R1'!J813 -> 93911.73 | I51: ='Reporte Componentes R1'!K813 -> 2290.29 | J51: 0 | K51: =D51-E51-F51-G51-H51-I51-J51 -> 297128.26 | L51: 0 | M51: =K51-L51 -> 297128.26 | N51: ='Reporte Componentes R1'!L813 -> 0 | O51: =M51+N51 -> 297128.26 | S51: 5 | T51: AREA LIMPIA DISTRITO CAPITAL S.A.S. ESP. | U51: ='Reporte Componentes R1'!M813 -> 20089.34 | V51: ='Reporte Componentes R1'!N813 -> 28092.36 | W51: ='Reporte Componentes R1'!O813 -> 141333 | X51: ='Reporte Componentes R1'!P813 -> 79544.79 | Y51: ='Reporte Componentes R1'!Q813 -> 3736.7 | Z51: =-L51 -> 0 | AA51: ='Reporte Componentes R1'!R813+'Reporte Componentes R1'!V813+'Reporte Componentes R1'!U813 -> 2.69 | AB51: =N51 -> 0 | AC51: ='Reporte Componentes R1'!T813+'Reporte Componentes R1'!W813+'Reporte Componentes R1'!X813+'Reporte Componentes R1'!Y813+'Reporte Componentes R1'!Z813+'Reporte Componentes R1'!S813 -> 0 | AD51: =-J51+AE51 -> 24329.38 | AE51: ='Reporte Componentes R1'!F814 -> 24329.38 | AF51: =SUM(U51:AD51) -> 297128.26 | AG51: =(AF51-O51) -> 0 | AH51: =INT(AG51)=0 -> TRUE
C52: TOTAL | D52: =SUM(D47:D51) -> 62332280 | E52: =SUM(E47:E51) -> 8196636.2 | F52: =SUM(F47:F51) -> 4614370.6 | G52: =SUM(G47:G51) -> 2450298 | H52: =SUM(H47:H51) -> 1272887.1 | I52: =SUM(I47:I51) -> 39816.35 | J52: =SUM(J47:J51) -> 0 | K52: =SUM(K47:K51) -> 45758272 | ... O52: =SUM(O47:O51) -> 45758272 | T52: TOTAL | U52: =SUM(U47:U51) -> 352789.46 | V52: =SUM(V47:V51) -> 399227.3 | W52: =SUM(W47:W51) -> 1969782.4 | X52: =SUM(X47:X51) -> 16738721 | Y52: =SUM(Y47:Y51) -> 66836.68 | Z52: =SUM(Z47:Z51) -> 0 | AA52: =SUM(AA47:AA51) -> 2.7 | AB52: =SUM(AB47:AB51) -> 0 | ... AG52: =SUM(AG47:AG51) -> -5.8935257e-10 | AH52: =INT(AG52)=0 -> FALSE
Y54: =SUM(U52:Y52) -> 19527357
F56: Firma autorizada
F60: PROCERASEO S.A.S. | I60: NIT: 901 153 639 - 0 | M60: Codigo Remuneración: | N60: =N3 -> 2026072 | U60: PROCERASEO S.A.S. | W60: NIT: 901 153 639 - 0 | AA60: Codigo Remuneración: | AD60: =N60 -> 2026072
F61: 3. ESQUEMA FINANCIERO DEL SERVICIO PUBLICO DE ASEO | U61: 3. ESQUEMA FINANCIERO DEL SERVICIO PUBLICO DE ASEO
F62: Resoluciòn UAESP Número 27 de 2018 | U62: Resoluciòn UAESP Número 27 de 2018
C63: Fecha de Proceso: | D63: =D6 -> 46297 | F63: R4 - REVERSIÓN DE PAGOS | U63: R4 - REVERSIÓN DE PAGOS
C64: Hora: | D64: =D7 -> 0.58333333 | F64: Fecha Desde: | G64: =G7 -> 46219 | J64: Feha Hasta: | K64: =K7 -> 46234 | U64: =F64 -> Fecha Desde: | V64: =G64 -> 46219 | X64: =J64 -> Feha Hasta: | Y64: =K64 -> 46234
B65: ASE | C65: Concesionarios | D65: Recaudo Total | E65: Recaudo por disposicion final | F65: Recaudo por tratamiento de lixiviados | G65: Recaudo por Componente VIAT ( Decreto 2412/2018) | H65: Recaudo por aprovechamiento | I65: Recaudo del componente de comercializacion para Aprovechamiento (11,4%) | J65: Balance de subsidio o contribuciones | K65: RECAUDO BASE DE REMUNERACION | L65: Costo de la Interventoría | M65: REMUNERACION FINAL | N65: Conceptos especiales | O65: REMUNERACION FINAL MAS CONCEPTOS ESPECIALES | S65: ASE | T65: Concesionarios | U65: Tarifa de Comercialización del Servicio. ( TCS) | V65: Tarifa de Limpieza Urbana del Servicio. ( TLU) | W65: Tarifa de Barrido y Limpieza del Servicio. ( TBL) | X65: Tarifa de Recolección y Transporte del Servicio. (TRT) | Y65: Recaudo del componente de comercializacion para Aprovechamiento (18,6%) | Z65: Costo de la Interventoría | AA65: Ajuste a la decena | AB65: Conceptos especiales | AC65: Otros | AD65: Diferencial Balance S / C (Fac vs Rec) | AE65: Balance S / C Con Base en (Recaudo) | AF65: REMUNERACION FINAL MAS CONCEPTOS ESPECIALES
B66: 1 | C66: PROMOAMBIENTAL DISTRITO S.A.S. ESP. | D66: ='Reversion Pagos R4'!D79 -> -16536713 | E66: ='Reversion Pagos R4'!E79 -> -842044.27 | F66: ='Reversion Pagos R4'!F79 -> -470499.84 | G66: ='Reversion Pagos R4'!G79 -> -249332.32 | H66: ='Reversion Pagos R4'!H79 -> -4006466.8 | I66: ='Reversion Pagos R4'!I79 -> -145004 | J66: 0 | K66: =D66-E66-F66-G66-H66-I66-J66 -> -10823366 | L66: 0 | M66: =K66-L66 -> -10823366 | N66: ='Reversion Pagos R4'!P79 -> 0 | O66: =M66+N66 -> -10823366 | S66: 1 | T66: PROMOAMBIENTAL DISTRITO S.A.S. ESP. | U66: ='Reversion Pagos R4'!J79 -> -1301824.8 | V66: ='Reversion Pagos R4'!K79 -> -1255802.9 | W66: ='Reversion Pagos R4'!L79 -> -5775459.5 | X66: ='Reversion Pagos R4'!M79 -> -2296297.4 | Y66: ='Reversion Pagos R4'!N79 -> -237636.38 | Z66: =-L66 -> 0 | AA66: ='Reversion Pagos R4'!O79 -> 100.74 | AB66: =N66 -> 0 | AC66: =+'Reversion Pagos R4'!Q79+'Reversion Pagos R4'!R79 -> 0 | AD66: =-J66+AE66 -> 43554.45 | AE66: ='Reversion Pagos R4'!D80 -> 43554.45 | AF66: =SUM(U66:AD66) -> -10823366 | AG66: =(AF66-O66) -> 0 | AH66: =INT(AG66)=0 -> TRUE
B67: 2 | C67: LIMPIEZA METROPOLITANA S.A. ESP. | D67: ='Reversion Pagos R4'!D180 -> -71069759 | E67: ='Reversion Pagos R4'!E180 -> -15881719 | F67: ='Reversion Pagos R4'!F180 -> -7382378.6 | G67: ='Reversion Pagos R4'!G180 -> -4039895.6 | H67: ='Reversion Pagos R4'!H180 -> -3333203 | I67: ='Reversion Pagos R4'!I180 -> -119625.47 | J67: 0 | K67: =D67-E67-F67-G67-H67-I67-J67 -> -40312937 | L67: 0 | M67: =K67-L67 -> -40312937 | N67: ='Reversion Pagos R4'!P180 -> 0 | O67: =M67+N67 -> -40312937 | S67: 2 | T67: LIMPIEZA METROPOLITANA S.A. ESP. | U67: ='Reversion Pagos R4'!J180 -> -1050942.2 | V67: ='Reversion Pagos R4'!K180 -> -1052754.2 | W67: ='Reversion Pagos R4'!L180 -> -4921480.5 | X67: ='Reversion Pagos R4'!M180 -> -32197092 | Y67: ='Reversion Pagos R4'!N180 -> -194756.95 | Z67: =-L67 -> 0 | AA67: ='Reversion Pagos R4'!O180 -> 28.29 | AB67: =N67 -> 0 | AC67: =+'Reversion Pagos R4'!Q180+'Reversion Pagos R4'!R180 -> 0 | AD67: =-J67+AE67 -> -895939.5 | AE67: ='Reversion Pagos R4'!D181 -> -895939.5 | AF67: =SUM(U67:AD67) -> -40312937 | AG67: =(AF67-O67) -> -1.4901161e-08 | AH67: =INT(AG67)=0 -> FALSE
B68: 3 | C68: CIUDAD LIMPIA BOGOTA S.A. ESP. | D68: ='Reversion Pagos R4'!D217 -> -32310980 | E68: ='Reversion Pagos R4'!E217 -> -2359230.9 | F68: ='Reversion Pagos R4'!F217 -> -1307200.3 | G68: ='Reversion Pagos R4'!G217 -> -693108.36 | H68: ='Reversion Pagos R4'!H217 -> -5641919 | I68: ='Reversion Pagos R4'!I217 -> -208676.79 | J68: 0 | K68: =D68-E68-F68-G68-H68-I68-J68 -> -22100844 | L68: 0 | M68: =K68-L68 -> -22100844 | N68: ='Reversion Pagos R4'!P217 -> 0 | O68: =M68+N68 -> -22100844 | S68: 3 | T68: CIUDAD LIMPIA BOGOTA S.A. ESP. | U68: ='Reversion Pagos R4'!J217 -> -1838013.6 | V68: ='Reversion Pagos R4'!K217 -> -1771126 | W68: ='Reversion Pagos R4'!L217 -> -8312687.9 | X68: ='Reversion Pagos R4'!M217 -> -5496750.7 | Y68: ='Reversion Pagos R4'!N217 -> -342720.34 | Z68: =-L68 -> 0 | AA68: ='Reversion Pagos R4'!O217 -> -128.57 | AB68: =N68 -> 0 | AC68: =+'Reversion Pagos R4'!Q217+'Reversion Pagos R4'!R217 -> 0 | AD68: =-J68+AE68 -> -4339417.4 | AE68: ='Reversion Pagos R4'!D218 -> -4339417.4 | AF68: =SUM(U68:AD68) -> -22100844 | AG68: =(AF68-O68) -> 0 | AH68: =INT(AG68)=0 -> TRUE
B69: 4 | C69: BOGOTA LIMPIA S.A.S. ESP. | D69: ='Reversion Pagos R4'!D332 -> -33738104 | E69: ='Reversion Pagos R4'!E332 -> -3280830.1 | F69: ='Reversion Pagos R4'!F332 -> -1653570.3 | G69: ='Reversion Pagos R4'!G332 -> -772414.51 | H69: ='Reversion Pagos R4'!H332 -> -6809335.5 | I69: ='Reversion Pagos R4'!I332 -> -246830.89 | J69: 0 | K69: =D69-E69-F69-G69-H69-I69-J69 -> -20975123 | L69: 0 | M69: =K69-L69 -> -20975123 | N69: ='Reversion Pagos R4'!P332 -> 0 | O69: =M69+N69 -> -20975123 | S69: 4 | T69: BOGOTA LIMPIA S.A.S. ESP. | U69: ='Reversion Pagos R4'!J332 -> -2175989.7 | V69: ='Reversion Pagos R4'!K332 -> -2281434.7 | W69: ='Reversion Pagos R4'!L332 -> -10508486 | X69: ='Reversion Pagos R4'!M332 -> -8690898.3 | Y69: ='Reversion Pagos R4'!N332 -> -404523.79 | Z69: =-L69 -> 0 | AA69: ='Reversion Pagos R4'!O332 -> -1.3 | AB69: =N69 -> 0 | AC69: =+'Reversion Pagos R4'!Q332+'Reversion Pagos R4'!R332 -> -0.29 | AD69: =-J69+AE69 -> 3086211.4 | AE69: ='Reversion Pagos R4'!D333 -> 3086211.4 | AF69: =SUM(U69:AD69) -> -20975123 | AG69: =(AF69-O69) -> 0 | AH69: =INT(AG69)=0 -> TRUE
B70: 5 | C70: AREA LIMPIA DISTRITO CAPITAL S.A.S. ESP. | D70: ='Reversion Pagos R4'!D373 -> -3092375.5 | E70: ='Reversion Pagos R4'!E373 -> -204651.35 | F70: ='Reversion Pagos R4'!F373 -> -114062.66 | G70: ='Reversion Pagos R4'!G373 -> -59426.1 | H70: ='Reversion Pagos R4'!H373 -> -755065.42 | I70: ='Reversion Pagos R4'!I373 -> -27250.92 | J70: 0 | K70: =D70-E70-F70-G70-H70-I70-J70 -> -1931919.1 | L70: 0 | M70: =K70-L70 -> -1931919.1 | N70: ='Reversion Pagos R4'!P373 -> 0 | O70: =M70+N70 -> -1931919.1 | S70: 5 | T70: AREA LIMPIA DISTRITO CAPITAL S.A.S. ESP. | U70: ='Reversion Pagos R4'!J373 -> -239043.97 | V70: ='Reversion Pagos R4'!K373 -> -246114.56 | W70: ='Reversion Pagos R4'!L373 -> -1258305.7 | X70: ='Reversion Pagos R4'!M373 -> -604168.66 | Y70: ='Reversion Pagos R4'!N373 -> -44461.78 | Z70: =-L70 -> 0 | AA70: ='Reversion Pagos R4'!O373 -> -2.56 | AB70: =N70 -> 0 | AC70: =+'Reversion Pagos R4'!Q373+'Reversion Pagos R4'!R373 -> 0 | AD70: =-J70+AE70 -> 460178.15 | AE70: ='Reversion Pagos R4'!D374 -> 460178.15 | AF70: =SUM(U70:AD70) -> -1931919.1 | AG70: =(AF70-O70) -> -4.6566129e-10 | AH70: =INT(AG70)=0 -> FALSE
C71: TOTAL | D71: =SUM(D66:D70) -> -1.5674793e+08 | E71: =SUM(E66:E70) -> -22568476 | F71: =SUM(F66:F70) -> -10927712 | G71: =SUM(G66:G70) -> -5814176.8 | H71: =SUM(H66:H70) -> -20545990 | I71: =SUM(I66:I70) -> -747388.07 | J71: =SUM(J66:J70) -> 0 | K71: =SUM(K66:K70) -> -96144189 | ... O71: =SUM(O66:O70) -> -96144189 | T71: TOTAL | U71: =SUM(U66:U70) -> -6605814.4 | V71: =SUM(V66:V70) -> -6607232.4 | W71: =SUM(W66:W70) -> -30776420 | X71: =SUM(X66:X70) -> -49285207 | Y71: =SUM(Y66:Y70) -> -1224099.2 | Z71: =SUM(Z66:Z70) -> 0 | AA71: =SUM(AA66:AA70) -> -3.4 | AB71: =SUM(AB66:AB70) -> 0 | ... AG71: =SUM(AG66:AG70) -> -1.5366822e-08 | AH71: =INT(AG71)=0 -> FALSE
Y73: =SUM(U71:Y71) -> -94498773
F75: Firma autorizada
F79: PROCERASEO S.A.S. | I79: NIT: 901 153 639 - 0 | M79: Codigo Remuneración: | N79: =N3 -> 2026072 | U79: PROCERASEO S.A.S. | W79: NIT: 901 153 639 - 0 | AA79: Codigo Remuneración: | AD79: =N79 -> 2026072
F80: 3. ESQUEMA FINANCIERO DEL SERVICIO PUBLICO DE ASEO | U80: 3. ESQUEMA FINANCIERO DEL SERVICIO PUBLICO DE ASEO
F81: Resoluciòn UAESP Número 27 de 2018 | U81: Resoluciòn UAESP Número 27 de 2018
C82: Fecha de Proceso: | D82: =D6 -> 46297 | F82: R5 - REMUNERACIÓN SALDOS A FAVOR POR NOTA | U82: =F82 -> R5 - REMUNERACIÓN SALDOS A FAVOR POR NOTA
C83: Hora: | D83: =D7 -> 0.58333333 | F83: Fecha Desde: | G83: =G7 -> 46219 | J83: Feha Hasta: | K83: =K7 -> 46234 | U83: =F83 -> Fecha Desde: | V83: =G83 -> 46219 | X83: =J83 -> Feha Hasta: | Y83: =K83 -> 46234
B84: ASE | C84: Concesionarios | D84: Recaudo Total | E84: Recaudo por disposicion final | F84: Recaudo por tratamiento de lixiviados | G84: Recaudo por Componente VIAT ( Decreto 2412/2018) | H84: Recaudo por aprovechamiento | I84: Recaudo del componente de comercializacion para Aprovechamiento (11,4%) | J84: Balance de subsidio o contribuciones | K84: RECAUDO BASE DE REMUNERACION | L84: Costo de la Interventoría | M84: REMUNERACION FINAL | N84: Conceptos especiales | O84: REMUNERACION FINAL MAS CONCEPTOS ESPECIALES | S84: ASE | T84: Concesionarios | U84: Tarifa de Comercialización del Servicio. ( TCS) | V84: Tarifa de Limpieza Urbana del Servicio. ( TLU) | W84: Tarifa de Barrido y Limpieza del Servicio. ( TBL) | X84: Tarifa de Recolección y Transporte del Servicio. (TRT) | Y84: Recaudo del componente de comercializacion para Aprovechamiento (18,6%) | Z84: Costo de la Interventoría | AA84: Ajuste a la decena | AB84: Conceptos especiales | AC84: Otros | AD84: Diferencial Balance Subsidio y Contribución (Fac vs Rec) | AE84: Balance de subsidio o contribuciones (Recaudo) | AF84: REMUNERACION FINAL MAS CONCEPTOS ESPECIALES
B85: 1 | C85: PROMOAMBIENTAL DISTRITO S.A.S. ESP. | D85: ='AJUSTES - SF-T'!D47 -> 973693.46 | E85: ='AJUSTES - SF-T'!E47 -> 65524.22 | F85: ='AJUSTES - SF-T'!F47 -> 36995.02 | G85: ='AJUSTES - SF-T'!G47 -> 19417.65 | H85: ='AJUSTES - SF-T'!H47 -> 156624.35 | I85: ='AJUSTES - SF-T'!I47 -> 5557.5 | J85: ='AJUSTES - SF-T'!J47 -> 0 | K85: =D85-E85-F85-G85-H85-I85-J85 -> 689574.72 | L85: 0 | M85: =K85-L85 -> 689574.72 | N85: ='AJUSTES - SF-T'!N47 -> 0 | O85: =M85+N85 -> 689574.72 | S85: 1 | T85: PROMOAMBIENTAL DISTRITO S.A.S. ESP. | U85: ='AJUSTES - SF-T'!U47 -> 52109.79 | V85: ='AJUSTES - SF-T'!V47 -> 47607.03 | W85: ='AJUSTES - SF-T'!W47 -> 225441.17 | X85: ='AJUSTES - SF-T'!X47 -> 178429.31 | Y85: ='AJUSTES - SF-T'!Y47 -> 9067.43 | Z85: =-L85 -> 0 | AA85: ='AJUSTES - SF-T'!AA47 -> 0 | AB85: =N85 -> 0 | AC85: 0 | AD85: =-J85+AE85 -> 176919.99 | AE85: ='AJUSTES - SF-T'!AD47 -> 176919.99 | AF85: =SUM(U85:AD85) -> 689574.72 | AG85: =AF85-O85 -> 0 | AH85: =INT(AG85)=0 -> TRUE
B86: 2 | C86: LIMPIEZA METROPOLITANA S.A. ESP. | D86: ='AJUSTES - SF-T'!D48 -> 216025.77 | E86: ='AJUSTES - SF-T'!E48 -> 31897.62 | F86: ='AJUSTES - SF-T'!F48 -> 18572.91 | G86: ='AJUSTES - SF-T'!G48 -> 8867.14 | H86: ='AJUSTES - SF-T'!H48 -> 92959.49 | I86: ='AJUSTES - SF-T'!I48 -> 3883.88 | J86: ='AJUSTES - SF-T'!J48 -> 0 | K86: =D86-E86-F86-G86-H86-I86-J86 -> 59844.73 | L86: 0 | M86: =K86-L86 -> 59844.73 | N86: ='AJUSTES - SF-T'!N48 -> 0 | O86: =M86+N86 -> 59844.73 | S86: 2 | T86: LIMPIEZA METROPOLITANA S.A. ESP. | U86: ='AJUSTES - SF-T'!U48 -> 61358.09 | V86: ='AJUSTES - SF-T'!V48 -> 33534.01 | W86: ='AJUSTES - SF-T'!W48 -> 127815.87 | X86: ='AJUSTES - SF-T'!X48 -> 64515.32 | Y86: ='AJUSTES - SF-T'!Y48 -> 5139.92 | Z86: =-L86 -> 0 | AA86: ='AJUSTES - SF-T'!AA48 -> -0.36 | AB86: =N86 -> 0 | AC86: 0 | AD86: =-J86+AE86 -> -232518.12 | AE86: ='AJUSTES - SF-T'!AD48 -> -232518.12 | AF86: =SUM(U86:AD86) -> 59844.73 | AG86: =AF86-O86 -> 0 | AH86: =INT(AG86)=0 -> TRUE
B87: 3 | C87: CIUDAD LIMPIA BOGOTA S.A. ESP. | D87: ='AJUSTES - SF-T'!D49 -> 104231.83 | E87: ='AJUSTES - SF-T'!E49 -> 6620.63 | F87: ='AJUSTES - SF-T'!F49 -> 3738.02 | G87: ='AJUSTES - SF-T'!G49 -> 1961.98 | H87: ='AJUSTES - SF-T'!H49 -> 20927.5 | I87: ='AJUSTES - SF-T'!I49 -> 743.08 | J87: ='AJUSTES - SF-T'!J49 -> 0 | K87: =D87-E87-F87-G87-H87-I87-J87 -> 70240.62 | L87: 0 | M87: =K87-L87 -> 70240.62 | N87: ='AJUSTES - SF-T'!N49 -> 0 | O87: =M87+N87 -> 70240.62 | S87: 3 | T87: CIUDAD LIMPIA BOGOTA S.A. ESP. | U87: ='AJUSTES - SF-T'!U49 -> 6518.28 | V87: ='AJUSTES - SF-T'!V49 -> 6410.86 | W87: ='AJUSTES - SF-T'!W49 -> 30349.1 | X87: ='AJUSTES - SF-T'!X49 -> 15383.1 | Y87: ='AJUSTES - SF-T'!Y49 -> 1212.4 | Z87: =-L87 -> 0 | AA87: ='AJUSTES - SF-T'!AA49 -> 0 | AB87: =N87 -> 0 | AC87: 0 | AD87: =-J87+AE87 -> 10366.88 | AE87: ='AJUSTES - SF-T'!AD49 -> 10366.88 | AF87: =SUM(U87:AD87) -> 70240.62 | AG87: =AF87-O87 -> 0 | AH87: =INT(AG87)=0 -> TRUE
B88: 4 | C88: BOGOTA LIMPIA S.A.S. ESP. | D88: ='AJUSTES - SF-T'!D50 -> 35954.44 | E88: ='AJUSTES - SF-T'!E50 -> 1890.6 | F88: ='AJUSTES - SF-T'!F50 -> 1067.43 | G88: ='AJUSTES - SF-T'!G50 -> 560.27 | H88: ='AJUSTES - SF-T'!H50 -> 10800.02 | I88: ='AJUSTES - SF-T'!I50 -> 371.66 | J88: ='AJUSTES - SF-T'!J50 -> 0 | K88: =D88-E88-F88-G88-H88-I88-J88 -> 21264.46 | L88: 0 | M88: =K88-L88 -> 21264.46 | N88: ='AJUSTES - SF-T'!N50 -> 0 | O88: =M88+N88 -> 21264.46 | S88: 4 | T88: BOGOTA LIMPIA S.A.S. ESP. | U88: ='AJUSTES - SF-T'!U50 -> 3260.18 | V88: ='AJUSTES - SF-T'!V50 -> 3149.08 | W88: ='AJUSTES - SF-T'!W50 -> 15696.81 | X88: ='AJUSTES - SF-T'!X50 -> 5005.76 | Y88: ='AJUSTES - SF-T'!Y50 -> 606.39 | Z88: =-L88 -> 0 | AA88: ='AJUSTES - SF-T'!AA50 -> 0 | AB88: =N88 -> 0 | AC88: 0 | AD88: =-J88+AE88 -> -6453.76 | AE88: ='AJUSTES - SF-T'!AD50 -> -6453.76 | AF88: =SUM(U88:AD88) -> 21264.46 | AG88: =AF88-O88 -> 0 | AH88: =INT(AG88)=0 -> TRUE
B89: 5 | C89: AREA LIMPIA DISTRITO CAPITAL S.A.S. ESP. | D89: ='AJUSTES - SF-T'!D51 -> 0 | E89: ='AJUSTES - SF-T'!E51 -> 0 | F89: ='AJUSTES - SF-T'!F51 -> 0 | G89: ='AJUSTES - SF-T'!G51 -> 0 | H89: ='AJUSTES - SF-T'!H51 -> 0 | I89: ='AJUSTES - SF-T'!I51 -> 0 | J89: ='AJUSTES - SF-T'!J51 -> 0 | K89: =D89-E89-F89-G89-H89-I89-J89 -> 0 | L89: 0 | M89: =K89-L89 -> 0 | N89: ='AJUSTES - SF-T'!N51 -> 0 | O89: =M89+N89 -> 0 | S89: 5 | T89: AREA LIMPIA DISTRITO CAPITAL S.A.S. ESP. | U89: ='AJUSTES - SF-T'!U51 -> 0 | V89: ='AJUSTES - SF-T'!V51 -> 0 | W89: ='AJUSTES - SF-T'!W51 -> 0 | X89: ='AJUSTES - SF-T'!X51 -> 0 | Y89: ='AJUSTES - SF-T'!Y51 -> 0 | Z89: =-L89 -> 0 | AA89: ='AJUSTES - SF-T'!AA51 -> 0 | AB89: =N89 -> 0 | AC89: 0 | AD89: =-J89+AE89 -> 0 | AE89: ='AJUSTES - SF-T'!AD51 -> 0 | AF89: =SUM(U89:AD89) -> 0 | AG89: =AF89-O89 -> 0 | AH89: =INT(AG89)=0 -> TRUE
C90: TOTAL | D90: =SUM(D85:D89) -> 1329905.5 | E90: =SUM(E85:E89) -> 105933.07 | F90: =SUM(F85:F89) -> 60373.38 | G90: =SUM(G85:G89) -> 30807.04 | H90: =SUM(H85:H89) -> 281311.36 | I90: =SUM(I85:I89) -> 10556.12 | J90: =SUM(J85:J89) -> 0 | K90: =SUM(K85:K89) -> 840924.53 | ... O90: =SUM(O85:O89) -> 840924.53 | T90: TOTAL | U90: =SUM(U85:U89) -> 123246.34 | V90: =SUM(V85:V89) -> 90700.98 | W90: =SUM(W85:W89) -> 399302.95 | X90: =SUM(X85:X89) -> 263333.49 | Y90: =SUM(Y85:Y89) -> 16026.14 | Z90: =SUM(Z85:Z89) -> 0 | AA90: =SUM(AA85:AA89) -> -0.36 | AB90: =SUM(AB85:AB89) -> 0 | ... AG90: =SUM(AG85:AG89) -> 0 | AH90: =INT(AG90)=0 -> TRUE
Y92: =SUM(U90:Y90) -> 892609.9
F94: Firma autorizada
F98: PROCERASEO S.A.S. | I98: NIT: 901 153 639 - 0 | M98: Codigo Remuneración: | N98: =N3 -> 2026072 | U98: PROCERASEO S.A.S. | W98: NIT: 901 153 639 - 0 | AA98: Codigo Remuneración: | AD98: =N98 -> 2026072
F99: 3. ESQUEMA FINANCIERO DEL SERVICIO PUBLICO DE ASEO | U99: 3. ESQUEMA FINANCIERO DEL SERVICIO PUBLICO DE ASEO
F100: Resoluciòn UAESP Número 27 de 2018 | U100: Resoluciòn UAESP Número 27 de 2018
C101: Fecha de Proceso: | D101: =D6 -> 46297 | F101: REPORTE CONSOLIDADO TOTAL DE RECAUDO | U101: REPORTE DETALLADO SUBBOLSA RBL DISCRIMINADO POR ACTIVIDADES
C102: Hora: | D102: =D7 -> 0.58333333 | F102: Fecha Desde: | G102: =G7 -> 46219 | J102: Feha Hasta: | K102: =K7 -> 46234 | U102: =F102 -> Fecha Desde: | V102: =G102 -> 46219 | X102: =J102 -> Feha Hasta: | Y102: =K102 -> 46234
B103: ASE | C103: Concesionarios | D103: Recaudo Total | E103: Recaudo por disposicion final | F103: Recaudo por tratamiento de lixiviados | G103: Recaudo por Componente VIAT ( Decreto 2412/2018) | H103: Recaudo por aprovechamiento | I103: Recaudo del componente de comercializacion para Aprovechamiento (11,4%) | J103: Balance de subsidio o contribuciones | K103: RECAUDO BASE DE REMUNERACION | L103: Costo de la Interventoría | M103: REMUNERACION FINAL | N103: Conceptos especiales | O103: REMUNERACION FINAL MAS CONCEPTOS ESPECIALES | S103: ASE | T103: Concesionarios | U103: Tarifa de Comercialización del Servicio. ( TCS) | V103: Tarifa de Limpieza Urbana del Servicio. ( TLU) | W103: Tarifa de Barrido y Limpieza del Servicio. ( TBL) | X103: Tarifa de Recolección y Transporte del Servicio. (TRT) | Y103: Recaudo del componente de comercializacion para Aprovechamiento (18,6%) | Z103: Costo de la Interventoría | AA103: Ajuste a la decena | AB103: Conceptos especiales | AC103: Otros | AD103: Diferencial Balance Subsidio y Contribución (Fac vs Rec) | AE103: Balance de subsidio o contribuciones (Recaudo) | AF103: REMUNERACION FINAL MAS CONCEPTOS ESPECIALES
B104: 1 | C104: PROMOAMBIENTAL DISTRITO S.A.S. ESP. | D104: =D9+D28+D47+D66+D85 -> 1.7450229e+10 | E104: =E9+E28+E47+E66+E85 -> 9.0708903e+08 | F104: =F9+F28+F47+F66+F85 -> 5.1161908e+08 | G104: =G9+G28+G47+G66+G85 -> 2.6869052e+08 | H104: =H9+H28+H47+H66+H85 -> 3.8152523e+09 | I104: =I9+I28+I47+I66+I85 -> 1.3436814e+08 | J104: =J9+J28+J47+J66+J85 -> -3.5894547e+09 | K104: =D104-E104-F104-G104-H104-I104-J104 -> 1.5402664e+10 | L104: =L9+L28+L47+L66+L85 -> 189185988 | M104: =K104-L104 -> 1.5213478e+10 | N104: =N9+N28+N47+N66+N85 -> 25277316 | O104: =M104+N104 -> 1.5238756e+10 | S104: 1 | T104: PROMOAMBIENTAL DISTRITO S.A.S. ESP. | U104: =U9+U28+U47+U66+U85 -> 1.1825029e+09 | V104: =V9+V28+V47+V66+V85 -> 1.1382031e+09 | W104: =W9+W28+W47+W66+W85 -> 5.3842392e+09 | X104: =X9+X28+X47+X66+X85 -> 2.4606489e+09 | Y104: =Y9+Y28+Y47+Y66+Y85 -> 2.1907005e+08 | Z104: =Z9+Z28+Z47+Z66+Z85 -> -189185988 | AA104: =AA9+AA28+AA47+AA66+AA85 -> -17520.82 | AB104: =AB9+AB28+AB47+AB66+AB85 -> 25277316 | AC104: =AC9+AC28+AC47+AC66+AC85 -> -1592.61 | AD104: =-J104+AE104 -> 5.0180194e+09 | AE104: =AE9+AE28+AE47+AE66+AE85 -> 1.4285647e+09 | AF104: =SUM(U104:AD104) -> 1.5238756e+10 | AG104: =AF104-O104 -> 0 | AH104: =INT(AG104)=0 -> TRUE
B105: 2 | C105: LIMPIEZA METROPOLITANA S.A. ESP. | D105: =D10+D29+D48+D67+D86 -> 2.0516144e+10 | E105: =E10+E29+E48+E67+E86 -> 1.5841798e+09 | F105: =F10+F29+F48+F67+F86 -> 8.9009816e+08 | G105: =G10+G29+G48+G67+G86 -> 4.6661147e+08 | H105: =H10+H29+H48+H67+H86 -> 5.8150895e+09 | I105: =I10+I29+I48+I67+I86 -> 2.2242873e+08 | J105: =J10+J29+J48+J67+J86 -> -3.2411937e+09 | K105: =D105-E105-F105-G105-H105-I105-J105 -> 1.477893e+10 | L105: =L10+L29+L48+L67+L86 -> 266580256 | M105: =K105-L105 -> 1.451235e+10 | N105: =N10+N29+N48+N67+N86 -> 53454221 | O105: =M105+N105 -> 1.4565804e+10 | S105: 2 | T105: LIMPIEZA METROPOLITANA S.A. ESP. | U105: =U10+U29+U48+U67+U86 -> 1.9498863e+09 | V105: =V10+V29+V48+V67+V86 -> 1.945637e+09 | W105: =W10+W29+W48+W67+W86 -> 9.1558861e+09 | X105: =X10+X29+X48+X67+X86 -> 3.1422094e+09 | Y105: =Y10+Y29+Y48+Y67+Y86 -> 3.6300358e+08 | Z105: =Z10+Z29+Z48+Z67+Z86 -> -266580256 | AA105: =AA10+AA29+AA48+AA67+AA86 -> 86900.16 | AB105: =AB10+AB29+AB48+AB67+AB86 -> 53454221 | AC105: =AC10+AC29+AC48+AC67+AC86 -> -123.21 | AD105: =-J105+AE105 -> -1.7777792e+09 | AE105: =AE10+AE29+AE48+AE67+AE86 -> -5.018973e+09 | AF105: =SUM(U105:AD105) -> 1.4565804e+10 | AG105: =AF105-O105 -> 0 | AH105: =INT(AG105)=0 -> TRUE
B106: 3 | C106: CIUDAD LIMPIA BOGOTA S.A. ESP. | D106: =D11+D30+D49+D68+D87 -> 1.5221896e+10 | E106: =E11+E30+E49+E68+E87 -> 1.1548169e+09 | F106: =F11+F30+F49+F68+F87 -> 6.5064826e+08 | G106: =G11+G30+G49+G68+G87 -> 3.4216893e+08 | H106: =H11+H30+H49+H68+H87 -> 3.4194713e+09 | I106: =I11+I30+I49+I68+I87 -> 1.2569028e+08 | J106: =J11+J30+J49+J68+J87 -> -8.5324456e+08 | K106: =D106-E106-F106-G106-H106-I106-J106 -> 1.0382345e+10 | L106: =L11+L30+L49+L68+L87 -> 154788536 | M106: =K106-L106 -> 1.0227557e+10 | N106: =N11+N30+N49+N68+N87 -> 14341963 | O106: =M106+N106 -> 1.0241899e+10 | S106: 3 | T106: CIUDAD LIMPIA BOGOTA S.A. ESP. | U106: =U11+U30+U49+U68+U87 -> 1.1023356e+09 | V106: =V11+V30+V49+V68+V87 -> 1.0864642e+09 | W106: =W11+W30+W49+W68+W87 -> 5.1419612e+09 | X106: =X11+X30+X49+X68+X87 -> 2.6858575e+09 | Y106: =Y11+Y30+Y49+Y68+Y87 -> 2.0516023e+08 | Z106: =Z11+Z30+Z49+Z68+Z87 -> -154788536 | AA106: =AA11+AA30+AA49+AA68+AA87 -> 246404.58 | AB106: =AB11+AB30+AB49+AB68+AB87 -> 14341963 | AC106: =AC11+AC30+AC49+AC68+AC87 -> -11885.62 | AD106: =-J106+AE106 -> 1.6033205e+08 | AE106: =AE11+AE30+AE49+AE68+AE87 -> -6.9291252e+08 | AF106: =SUM(U106:AD106) -> 1.0241899e+10 | AG106: =AF106-O106 -> 0 | AH106: =INT(AG106)=0 -> TRUE
B107: 4 | C107: BOGOTA LIMPIA S.A.S. ESP. | D107: =D12+D31+D50+D69+D88 -> 7.1795954e+09 | E107: =E12+E31+E50+E69+E88 -> 4.7360604e+08 | F107: =F12+F31+F50+F69+F88 -> 2.6459666e+08 | G107: =G12+G31+G50+G69+G88 -> 1.3648158e+08 | H107: =H12+H31+H50+H69+H88 -> 1.6054371e+09 | I107: =I12+I31+I50+I69+I88 -> 62582402 | J107: =J12+J31+J50+J69+J88 -> -6.9988271e+08 | K107: =D107-E107-F107-G107-H107-I107-J107 -> 5.3367743e+09 | L107: =L12+L31+L50+L69+L88 -> 120391083 | M107: =K107-L107 -> 5.2163833e+09 | N107: =N12+N31+N50+N69+N88 -> 34128345 | O107: =M107+N107 -> 5.2505116e+09 | S107: 4 | T107: BOGOTA LIMPIA S.A.S. ESP. | U107: =U12+U31+U50+U69+U88 -> 5.4945041e+08 | V107: =V12+V31+V50+V69+V88 -> 5.4818687e+08 | W107: =W12+W31+W50+W69+W88 -> 2.7992328e+09 | X107: =X12+X31+X50+X69+X88 -> 1.2545271e+09 | Y107: =Y12+Y31+Y50+Y69+Y88 -> 1.022499e+08 | Z107: =Z12+Z31+Z50+Z69+Z88 -> -120391083 | AA107: =AA12+AA31+AA50+AA69+AA88 -> -16263.19 | AB107: =AB12+AB31+AB50+AB69+AB88 -> 34128345 | AC107: =AC12+AC31+AC50+AC69+AC88 -> -529.1 | AD107: =-J107+AE107 -> 83144093 | AE107: =AE12+AE31+AE50+AE69+AE88 -> -6.1673862e+08 | AF107: =SUM(U107:AD107) -> 5.2505116e+09 | AG107: =AF107-O107 -> 0 | AH107: =INT(AG107)=0 -> TRUE
B108: 5 | C108: AREA LIMPIA DISTRITO CAPITAL S.A.S. ESP. | D108: =D13+D32+D51+D70+D89 -> 1.2073345e+10 | E108: =E13+E32+E51+E70+E89 -> 7.3168644e+08 | F108: =F13+F32+F51+F70+F89 -> 4.1248082e+08 | G108: =G13+G32+G51+G70+G89 -> 2.16221e+08 | H108: =H13+H32+H51+H70+H89 -> 2.7711708e+09 | I108: =I13+I32+I51+I70+I89 -> 1.0586025e+08 | J108: =J13+J32+J51+J70+J89 -> -82959024 | K108: =D108-E108-F108-G108-H108-I108-J108 -> 7.9188844e+09 | L108: =L13+L32+L51+L70+L89 -> 128990446 | M108: =K108-L108 -> 7.7898939e+09 | N108: =N13+N32+N51+N70+N89 -> 15891736 | O108: =M108+N108 -> 7.8057857e+09 | S108: 5 | T108: AREA LIMPIA DISTRITO CAPITAL S.A.S. ESP. | U108: =U13+U32+U51+U70+U89 -> 9.2820524e+08 | V108: =V13+V32+V51+V70+V89 -> 9.111805e+08 | W108: =W13+W32+W51+W70+W89 -> 4.6811316e+09 | X108: =X13+X32+X51+X70+X89 -> 2.1738513e+09 | Y108: =Y13+Y32+Y51+Y70+Y89 -> 1.7272991e+08 | Z108: =Z13+Z32+Z51+Z70+Z89 -> -128990446 | AA108: =AA13+AA32+AA51+AA70+AA89 -> -147744.57 | AB108: =AB13+AB32+AB51+AB70+AB89 -> 15891736 | AC108: =AC13+AC32+AC51+AC70+AC89 -> -32.98 | AD108: =-J108+AE108 -> -9.4806635e+08 | AE108: =AE13+AE32+AE51+AE70+AE89 -> -1.0310254e+09 | AF108: =SUM(U108:AD108) -> 7.8057857e+09 | AG108: =AF108-O108 -> 0 | AH108: =INT(AG108)=0 -> TRUE
C109: TOTAL | D109: =SUM(D104:D108) -> 7.2441209e+10 | E109: =SUM(E104:E108) -> 4.8513783e+09 | F109: =SUM(F104:F108) -> 2.729443e+09 | G109: =SUM(G104:G108) -> 1.4301735e+09 | H109: =SUM(H104:H108) -> 1.7426421e+10 | I109: =SUM(I104:I108) -> 6.5092981e+08 | J109: =SUM(J104:J108) -> -8.4667347e+09 | K109: =SUM(K104:K108) -> 5.3819598e+10 | ... O109: =SUM(O104:O108) -> 5.3102756e+10 | T109: TOTAL | U109: =SUM(U104:U108) -> 5.7123804e+09 | V109: =SUM(V104:V108) -> 5.6296717e+09 | W109: =SUM(W104:W108) -> 2.7162451e+10 | X109: =SUM(X104:X108) -> 1.1717094e+10 | Y109: =SUM(Y104:Y108) -> 1.0622137e+09 | Z109: =SUM(Z104:Z108) -> -859936309 | AA109: =SUM(AA104:AA108) -> 151776.16 | AB109: =SUM(AB104:AB108) -> 1.4309358e+08 | ... AG109: =SUM(AG104:AG108) -> 0 | AH109: =INT(AG109)=0 -> TRUE
Y111: =SUM(U109:Y109) -> 5.1283811e+10
F113: Firma autorizada | V113: Firma autorizada
F117: PROCERASEO S.A.S. | I117: NIT: 901 153 639 - 0 | L117: Codigo Remuneración: | M117: =N3 -> 2026072
F118: 3. ESQUEMA FINANCIERO DEL SERVICIO PUBLICO DE ASEO
F119: Resoluciòn UAESP Número 27 de 2018
F121: REPORTE CONSOLIDADO DE ANTICIPOS
F122: Fecha Desde: | G122: =G7 -> 46219 | J122: Feha Hasta: | K122: =K7 -> 46234
