Workbook
Name \0: #REF!
Name _1: #REF!
Name _2: #REF!
Name _A655555: #REF!
Name _CFR1: #REF!
Name _cia1: #REF!
Name _XL250: #REF!
Name A: #REF!
Name ADM: [1]!ADM
Name ADM: [1]!ADM
Name ADM: [1]!ADM
Name ADM: [1]!ADM
Name ADM: [1]!ADM
Name ADM_: [1]!ADM
Name ADM_: [1]!ADM
Name ADM_: [1]!ADM
Name ADM_: [1]!ADM
Name ADM_: [1]!ADM
Name AI: #REF!
Name Air: #REF!
Name AP: '[2]TARIFA no aforos'!$C$12
Name Bancos: [3]Fx!$C$1:$C$23
Name CBL: #REF!
Name CCS: #REF!
Name CDT_p: [4]CDT!$C$3
Name CFR: #REF!
Name cia: #REF!
Name COM: #REF!
Name CRT: #REF!
Name CRT___CTEp___CDTp___CMRv: #REF!
Name CRT_aislados: '[4]COSTOS AJUSTADOS'!$C$13
Name CRT_costas: #REF!
Name CTE_p: [4]CTE!$C$5
Name Denominador: #REF!
Name dg: [1]!ADM
Name dg: [1]!ADM
Name dg: [1]!ADM
Name dg: [1]!ADM
Name dg: [1]!ADM
Name DIAS: [5]CONTRA!#REF!
Name Fmerc: #REF!
Name FPS: #REF!
Name InformacionGeneral: [1]!InformacionGeneral
Name InformacionGeneral: [1]!InformacionGeneral
Name InformacionGeneral: [1]!InformacionGeneral
Name InformacionGeneral: [1]!InformacionGeneral
Name InformacionGeneral: [1]!InformacionGeneral
Name INTFIN: #REF!
Name INV: [1]!INV
Name INV: [1]!INV
Name INV: [1]!INV
Name INV: [1]!INV
Name INV: [1]!INV
Name K: #REF!
Name N: '[4]COSTOS AJUSTADOS'!#REF!
Name Na: '[2]TARIFA no aforos'!$C$39
Name nfc: '[4]COSTOS AJUSTADOS'!#REF!
Name OYM: [1]!OYM
Name OYM: [1]!OYM
Name OYM: [1]!OYM

Sheet Recaudo EAAB Reciprocidad
B2: OPORTUNO | C2: ASE | D2: VALOR 1° Q | E2: NUMERO REG. 1°Q | F2: VALOR 2° Q | G2: NUMERO REG. 2°Q
C3: 1 | D3: 0 | E3: 0 | F3: 0 | G3: 0
C4: 2 | D4: 11627730 | E4: 116 | F4: 4390091 | G4: 56
C5: 3 | D5: 0 | E5: 0 | F5: 0 | G5: 0
C6: 4 | D6: 7382710 | E6: 66 | F6: 1814000 | G6: 24
C7: 5 | D7: 0 | E7: 0 | F7: 0 | G7: 0
C8: X
D9: 19010440 | E9: 182 | F9: 6204091 | G9: 80
C11: ASE | D11: VALOR 1° Q | E11: NUMERO REG. 1°Q | F11: VALOR 2° Q | G11: NUMERO REG. 2°Q
B12: EXTEMP. | C12: 1 | D12: 0 | E12: 0 | F12: 0 | G12: 0
C13: 2 | D13: 0 | E13: 0 | F13: 0 | G13: 0
C14: 3 | D14: 0 | E14: 0 | F14: 0 | G14: 0
C15: 4 | D15: 0 | E15: 0 | F15: 0 | G15: 0
C16: 5 | D16: 0 | E16: 0 | F16: 0 | G16: 0
C17: X
D18: 0 | E18: 0 | F18: 0 | G18: 0
C20: ASE | D20: VALOR 1° Q | E20: NUMERO REG. 1°Q | F20: VALOR 2° Q | G20: NUMERO REG. 2°Q | I20: VALOR TOTAL MES | J20: NUMERO REGISTROS MES
B21: TOTAL | C21: 1 | D21: 0 | E21: 0 | F21: 0 | G21: 0 | I21: 0 | J21: 0
C22: 2 | D22: 11627730 | E22: 116 | F22: 4390091 | G22: 56 | I22: 16017821 | J22: 172
C23: 3 | D23: 0 | E23: 0 | F23: 0 | G23: 0 | I23: 0 | J23: 0
C24: 4 | D24: 7382710 | E24: 66 | F24: 1814000 | G24: 24 | I24: 9196710 | J24: 90
C25: 5 | D25: 0 | E25: 0 | F25: 0 | G25: 0 | I25: 0 | J25: 0
C26: X | I26: 0 | J26: 0
D27: 19010440 | E27: 182 | F27: 6204091 | G27: 80 | I27: 25214531 | J27: 262
B31: OPORTUNO | D31: =D9=SUM(D3:D8) -> TRUE | E31: =E9=SUM(E3:E8) -> TRUE | F31: =F9=SUM(F3:F8) -> TRUE | G31: =G9=SUM(G3:G8) -> TRUE
B33: EXTEMP. | D33: =D18=SUM(D12:D17) -> TRUE | E33: =E18=SUM(E12:E17) -> TRUE | F33: =F18=SUM(F12:F17) -> TRUE | G33: =G18=SUM(G12:G17) -> TRUE
B35: TOTAL | D35: =D27=SUM(D21:D26) -> TRUE | E35: =E27=SUM(E21:E26) -> TRUE | F35: =F27=SUM(F21:F26) -> TRUE | G35: =G27=SUM(G21:G26) -> TRUE | I35: =I27=SUM(I21:I26) -> TRUE | J35: =J27=SUM(J21:J26) -> TRUE
E69: =C69-G17 -> 0

Sheet Recaudo ENEL
B2: OPORTUNO | C2: ASE | D2: VALOR 1° Q | E2: NUMERO REG. 1°Q | F2: VALOR 2° Q | G2: NUMERO REG. 2°Q
C3: 1 | D3: 16745673525 | E3: 356945 | F3: 15131451516 | G3: 257196
C4: 2 | D4: 12677941411 | E4: 247628 | F4: 20191843481 | G4: 415819
C5: 3 | D5: 10157711962 | E5: 233934 | F5: 13824429136 | G5: 269019
C6: 4 | D6: 10972037248 | E6: 193770 | F6: 6638974137 | G6: 116956
C7: 5 | D7: 8639656940 | E7: 172542 | F7: 12022816376 | G7: 242887
C8: X
D9: 59193021086 | E9: 1204819 | F9: 67809514646 | G9: 1301877
C11: ASE | D11: VALOR 1° Q | E11: NUMERO REG. 1°Q | F11: VALOR 2° Q | G11: NUMERO REG. 2°Q
B12: EXTEMP. | C12: 1 | D12: 202711553 | E12: 2558 | F12: 175327928 | G12: 2824
C13: 2 | D13: 73096641 | E13: 1473 | F13: 49072267 | G13: 722
C14: 3 | D14: 51248640 | E14: 963 | F14: 67822789 | G14: 1184
C15: 4 | D15: 62236830 | E15: 857 | F15: 72481595 | G15: 1595
C16: 5 | D16: 158575115 | E16: 2854 | F16: 25848890 | G16: 515
C17: X
D18: 547868779 | E18: 8705 | F18: 390553469 | G18: 6840
C20: ASE | D20: VALOR 1° Q | E20: NUMERO REG. 1°Q | F20: VALOR 2° Q | G20: NUMERO REG. 2°Q | I20: VALOR TOTAL MES | J20: NUMERO REGISTROS MES
B21: TOTAL | C21: 1 | D21: 16948385078 | E21: 359503 | F21: 15306779444 | G21: 260020 | I21: 32255164522 | J21: 619523
C22: 2 | D22: 12751038052 | E22: 249101 | F22: 20240915748 | G22: 416541 | I22: 32991953800 | J22: 665642
C23: 3 | D23: 10208960602 | E23: 234897 | F23: 13892251925 | G23: 270203 | I23: 24101212527 | J23: 505100
C24: 4 | D24: 11034274078 | E24: 194627 | F24: 6711455732 | G24: 118551 | I24: 17745729810 | J24: 313178
C25: 5 | D25: 8798232055 | E25: 175396 | F25: 12048665266 | G25: 243402 | I25: 20846897321 | J25: 418798
C26: X | I26: 0 | J26: 0
D27: 59740889865 | E27: 1213524 | F27: 68200068115 | G27: 1308717 | I27: 127940957980 | J27: 2522241
B31: OPORTUNO | D31: =D9=SUM(D3:D8) -> TRUE | E31: =E9=SUM(E3:E8) -> TRUE | F31: =F9=SUM(F3:F8) -> TRUE | G31: =G9=SUM(G3:G8) -> TRUE
B33: EXTEMP. | D33: =D18=SUM(D12:D17) -> TRUE | E33: =E18=SUM(E12:E17) -> TRUE | F33: =F18=SUM(F12:F17) -> TRUE | G33: =G18=SUM(G12:G17) -> TRUE
B35: TOTAL | D35: =D27=SUM(D21:D26) -> TRUE | E35: =E27=SUM(E21:E26) -> TRUE | F35: =F27=SUM(F21:F26) -> TRUE | G35: =G27=SUM(G21:G26) -> TRUE | I35: =I27=SUM(I21:I26) -> TRUE | J35: =J27=SUM(J21:J26) -> TRUE
E69: =C69-G17 -> 0

Sheet Recaudo ENERBIT
B2: OPORTUNO | C2: ASE | D2: VALOR 1° Q | E2: NUMERO REG. 1°Q | F2: VALOR 2° Q | G2: NUMERO REG. 2°Q
C3: 1 | D3: 0 | E3: 0 | F3: 0 | G3: 0
C4: 2 | D4: 0 | E4: 0 | F4: 0 | G4: 0
C5: 3 | D5: 0 | E5: 0 | F5: 0 | G5: 0
C6: 4 | D6: 0 | E6: 0 | F6: 0 | G6: 0
C7: 5 | D7: 137371512 | E7: 3020 | F7: 33627704 | G7: 521
C8: X
D9: 137371512 | E9: 3020 | F9: 33627704 | G9: 521
C11: ASE | D11: VALOR 1° Q | E11: NUMERO REG. 1°Q | F11: VALOR 2° Q | G11: NUMERO REG. 2°Q
B12: EXTEMP. | C12: 1 | D12: 0 | E12: 0 | F12: 0 | G12: 0
C13: 2 | D13: 0 | E13: 0 | F13: 0 | G13: 0
C14: 3 | D14: 0 | E14: 0 | F14: 0 | G14: 0
C15: 4 | D15: 0 | E15: 0 | F15: 0 | G15: 0
C16: 5 | D16: 1179300 | E16: 6 | F16: 5242682 | G16: 76
C17: X
D18: 1179300 | E18: 6 | F18: 5242682 | G18: 76
C20: ASE | D20: VALOR 1° Q | E20: NUMERO REG. 1°Q | F20: VALOR 2° Q | G20: NUMERO REG. 2°Q | I20: VALOR TOTAL MES | J20: NUMERO REGISTROS MES
B21: TOTAL | C21: 1 | D21: 0 | E21: 0 | F21: 0 | G21: 0 | I21: 0 | J21: 0
C22: 2 | D22: 0 | E22: 0 | F22: 0 | G22: 0 | I22: 0 | J22: 0
C23: 3 | D23: 0 | E23: 0 | F23: 0 | G23: 0 | I23: 0 | J23: 0
C24: 4 | D24: 0 | E24: 0 | F24: 0 | G24: 0 | I24: 0 | J24: 0
C25: 5 | D25: 138550812 | E25: 3026 | F25: 38870386 | G25: 597 | I25: 177421198 | J25: 3623
C26: X | I26: 0 | J26: 0
D27: 138550812 | E27: 3026 | F27: 38870386 | G27: 597 | I27: 177421198 | J27: 3623
B31: OPORTUNO | D31: =D9=SUM(D3:D8) -> TRUE | E31: =E9=SUM(E3:E8) -> TRUE | F31: =F9=SUM(F3:F8) -> TRUE | G31: =G9=SUM(G3:G8) -> TRUE
B33: EXTEMP. | D33: =D18=SUM(D12:D17) -> TRUE | E33: =E18=SUM(E12:E17) -> TRUE | F33: =F18=SUM(F12:F17) -> TRUE | G33: =G18=SUM(G12:G17) -> TRUE
B35: TOTAL | D35: =D27=SUM(D21:D26) -> TRUE | E35: =E27=SUM(E21:E26) -> TRUE | F35: =F27=SUM(F21:F26) -> TRUE | G35: =G27=SUM(G21:G26) -> TRUE | I35: =I27=SUM(I21:I26) -> TRUE | J35: =J27=SUM(J21:J26) -> TRUE
E69: =C69-G17 -> 0

Sheet Recaudo EAAB + Ciud Limp
B2: Ciudad Limpia - Prestador | C2: ASE | D2: VALOR 1° Q | E2: NUMERO REG. 1°Q | F2: VALOR 2° Q | G2: NUMERO REG. 2°Q
C3: 1 | D3: 0 | E3: 0 | F3: 0 | G3: 0
C4: 2 | D4: 0 | E4: 0 | F4: 0 | G4: 0
C5: 3 | D5: 0 | E5: 0 | F5: 0 | G5: 0
C6: 4 | D6: 0 | E6: 0 | F6: 0 | G6: 0
C7: 5 | D7: 0 | E7: 0 | F7: 0 | G7: 0
C8: X
D9: 0 | E9: 0 | F9: 0 | G9: 0
C11: ASE | D11: VALOR 1° Q | E11: NUMERO REG. 1°Q | F11: VALOR 2° Q | G11: NUMERO REG. 2°Q
B12: EAAB - Prestador | C12: 1 | D12: 0 | E12: 0 | F12: 0 | G12: 0
C13: 2 | D13: 0 | E13: 0 | F13: 0 | G13: 0
C14: 3 | D14: 0 | E14: 0 | F14: 0 | G14: 0
C15: 4 | D15: 0 | E15: 0 | F15: 0 | G15: 0
C16: 5 | D16: 0 | E16: 0 | F16: 0 | G16: 0
C17: X
D18: 0 | E18: 0 | F18: 0 | G18: 0
C20: ASE | D20: VALOR 1° Q | E20: NUMERO REG. 1°Q | F20: VALOR 2° Q | G20: NUMERO REG. 2°Q | I20: VALOR TOTAL MES | J20: NUMERO REGISTROS MES
B21: TOTAL | C21: 1 | D21: 0 | E21: 0 | F21: 0 | G21: 0 | I21: 0 | J21: 0
C22: 2 | D22: 0 | E22: 0 | F22: 0 | G22: 0 | I22: 0 | J22: 0
C23: 3 | D23: 0 | E23: 0 | F23: 0 | G23: 0 | I23: 0 | J23: 0
C24: 4 | D24: 0 | E24: 0 | F24: 0 | G24: 0 | I24: 0 | J24: 0
C25: 5 | D25: 0 | E25: 0 | F25: 0 | G25: 0 | I25: 0 | J25: 0
C26: X | I26: 0 | J26: 0
D27: 0 | E27: 0 | F27: 0 | G27: 0 | I27: 0 | J27: 0
B31: OPORTUNO | D31: =D9=SUM(D3:D8) -> TRUE | E31: =E9=SUM(E3:E8) -> TRUE | F31: =F9=SUM(F3:F8) -> TRUE | G31: =G9=SUM(G3:G8) -> TRUE
B33: EXTEMP. | D33: =D18=SUM(D12:D17) -> TRUE | E33: =E18=SUM(E12:E17) -> TRUE | F33: =F18=SUM(F12:F17) -> TRUE | G33: =G18=SUM(G12:G17) -> TRUE
B35: TOTAL | D35: =D27=SUM(D21:D26) -> TRUE | E35: =E27=SUM(E21:E26) -> TRUE | F35: =F27=SUM(F21:F26) -> TRUE | G35: =G27=SUM(G21:G26) -> TRUE | I35: =I27=SUM(I21:I26) -> TRUE | J35: =J27=SUM(J21:J26) -> TRUE

Sheet Recaudo Directa Occidente
B2: OPORTUNO | C2: ASE | D2: VALOR 1° Q | E2: NUMERO REG. 1°Q | F2: VALOR 2° Q | G2: NUMERO REG. 2°Q
C3: 1 | D3: 510782327 | E3: 2083 | F3: 659215777 | G3: 2359
C4: 2 | D4: 1360190364 | E4: 4795 | F4: 1939956060 | G4: 8702
C5: 3 | D5: 650826874 | E5: 1469 | F5: 1048706515 | G5: 1996
C6: 4 | D6: 515587332 | E6: 3012 | F6: 920907421 | G6: 4189
C7: 5 | D7: 224557157 | E7: 1221 | F7: 278031281 | G7: 1447
C8: X | D8: 0 | E8: 0 | F8: 437900 | G8: 1
D9: 3261944054 | E9: 12580 | F9: 4847254954 | G9: 18694
C11: ASE | D11: VALOR 1° Q | E11: NUMERO REG. 1°Q | F11: VALOR 2° Q | G11: NUMERO REG. 2°Q
B12: EXTEMP. | C12: 1 | D12: 23795111 | E12: 50 | F12: 118038698 | G12: 431
C13: 2 | D13: 62759499 | E13: 134 | F13: 234466650 | G13: 488
C14: 3 | D14: 48196023 | E14: 55 | F14: 422530889 | G14: 69
C15: 4 | D15: 5014320 | E15: 32 | F15: 111430406 | G15: 150
C16: 5 | D16: 14004529 | E16: 30 | F16: 2852410 | G16: 32
C17: X | D17: 0 | E17: 0 | F17: 0 | G17: 0
D18: 153769482 | E18: 301 | F18: 889319053 | G18: 1170
C20: ASE | D20: VALOR 1° Q | E20: NUMERO REG. 1°Q | F20: VALOR 2° Q | G20: NUMERO REG. 2°Q | I20: VALOR TOTAL MES | J20: NUMERO REGISTROS MES
B21: TOTAL | C21: 1 | D21: 534577438 | E21: 2133 | F21: 777254475 | G21: 2790 | I21: 1311831913 | J21: 4923
C22: 2 | D22: 1422949863 | E22: 4929 | F22: 2174422710 | G22: 9190 | I22: 3597372573 | J22: 14119
C23: 3 | D23: 699022897 | E23: 1524 | F23: 1471237404 | G23: 2065 | I23: 2170260301 | J23: 3589
C24: 4 | D24: 520601652 | E24: 3044 | F24: 1032337827 | G24: 4339 | I24: 1552939479 | J24: 7383
C25: 5 | D25: 238561686 | E25: 1251 | F25: 280883691 | G25: 1479 | I25: 519445377 | J25: 2730
C26: X | D26: 0 | E26: 0 | F26: 437900 | G26: 1 | I26: 437900 | J26: 1
D27: 3415713536 | E27: 12881 | F27: 5736574007 | G27: 19864 | I27: 9152287543 | J27: 32745
B31: OPORTUNO | D31: =D9=SUM(D3:D8) -> TRUE | E31: =E9=SUM(E3:E8) -> TRUE | F31: =F9=SUM(F3:F8) -> TRUE | G31: =G9=SUM(G3:G8) -> TRUE
B33: EXTEMP. | D33: =D18=SUM(D12:D17) -> TRUE | E33: =E18=SUM(E12:E17) -> TRUE | F33: =F18=SUM(F12:F17) -> TRUE | G33: =G18=SUM(G12:G17) -> TRUE
B35: TOTAL | D35: =D27=SUM(D21:D26) -> TRUE | E35: =E27=SUM(E21:E26) -> TRUE | F35: =F27=SUM(F21:F26) -> TRUE | G35: =G27=SUM(G21:G26) -> TRUE | I35: =I27=SUM(I21:I26) -> TRUE | J35: =J27=SUM(J21:J26) -> TRUE
E69: =C69-G17 -> 0

Sheet REPORTE RECAUDO x BANCO
C1: ENEL | D1: CIUDAD LIMPIA | E1: EAB | F1: NUEVO ESQUEMA | G1: ENERBIT | H1: OCCIDENTE | I1: Total
B2: 1-APLICADOS A FACTURACION | C2: =C13+C23+C32+C41+C51 -> 68070277487 | D2: =D13+D23+D32+D41+D51 -> 0 | E2: =E13+E23+E32+E41+E51 -> 0 | F2: =F13+F23+F32+F41+F51 -> 2329750 | G2: =G13+G23+G32+G41+G51 -> 34785208 | H2: =H13+H23+H32+H41+H51 -> 5.3054052e+09 | I2: =SUM(C2:H2) -> 7.3412798e+10
B3: 2-SALDOS A FAVOR GENERADOS | C3: =C14+C24+C33+C42+C52 -> 135065158 | D3: =D14+D24+D33+D42+D52 -> 0 | E3: =E14+E24+E33+E42+E52 -> 0 | F3: =F14+F24+F33+F42+F52 -> 3874341 | G3: =G14+G24+G33+G42+G52 -> 4085178 | H3: =H14+H24+H33+H42+H52 -> 3.811974e+08 | I3: =SUM(C3:H3) -> 5.2422208e+08
B4: 3-APLICADOS A FINANCIACIONES NUEVAS | C4: =C15+C25+C34+C43+C53 -> 0 | D4: =D15+D25+D34+D43+D53 -> 0 | E4: =E15+E25+E34+E43+E53 -> 0 | F4: =F15+F25+F34+F43+F53 -> 0 | G4: =G15+G25+G34+G43+G53 -> 0 | H4: =H15+H25+H34+H43+H53 -> 49533469 | I4: =SUM(C4:H4) -> 49533469
B5: 7-APLICADOS A RECIBOS SERVICIOS ESPECIALES | C5: =C16+C26+C35+C44+C54 -> 0 | D5: =D16+D26+D35+D44+D54 -> 0 | E5: =E16+E26+E35+E44+E54 -> 0 | F5: =F16+F26+F35+F44+F54 -> 0 | G5: =G16+G26+G35+G44+G54 -> 0 | H5: =H16+H26+H35+H44+H54 -> 0 | I5: =SUM(C5:H5) -> 0
B6: Total | C6: =SUM(C2:C5) -> 68205342645 | D6: =SUM(D2:D5) -> 0 | E6: =SUM(E2:E5) -> 0 | F6: =SUM(F2:F5) -> 6204091 | G6: =SUM(G2:G5) -> 38870386 | H6: =SUM(H2:H5) -> 5.7361361e+09 | I6: =SUM(I2:I5) -> 73986553229
C7: =C6=(C17+C27+C36+C45+C55) -> TRUE | D7: =D6=(D17+D27+D36+D45+D55) -> TRUE | E7: =E6=(E17+E27+E36+E45+E55) -> TRUE | F7: =F6=(F17+F27+F36+F45+F55) -> TRUE | H7: =H6=(H17+H27+H36+H45+H55) -> TRUE | I7: =I6=(I17+I27+I36+I45+I55) -> TRUE
B10: ASE 1
B11: Resumen Recaudo Aplicado Por Servicio
C12: ENEL | D12: CIUDAD LIMPIA | E12: EAB | F12: NUEVO ESQUEMA | G12: ENERBIT | H12: OCCIDENTE | I12: Total
B13: 1-APLICADOS A FACTURACION | C13: 15275852337 | H13: 7.2951372e+08 | I13: =SUM(C13:H13) -> 1.6005366e+10 | J13: =SUM(C13:H13)=I13 -> TRUE
B14: 2-SALDOS A FAVOR GENERADOS | C14: 30927107 | H14: 34356276 | I14: =SUM(C14:H14) -> 65283383 | J14: =SUM(C14:H14)=I14 -> TRUE
B15: 3-APLICADOS A FINANCIACIONES NUEVAS | C15: 0 | H15: 13384481 | I15: =SUM(C15:H15) -> 13384481 | J15: =SUM(C15:H15)=I15 -> TRUE
B16: 7-APLICADOS A RECIBOS SERVICIOS ESPECIALES | C16: 0 | I16: =SUM(C16:H16) -> 0 | J16: =SUM(C16:H16)=I16 -> TRUE
B17: Total | C17: =SUM(C13:C16) -> 15306779444 | D17: =SUM(D13:D16) -> 0 | E17: =SUM(E13:E16) -> 0 | F17: =SUM(F13:F16) -> 0 | G17: =SUM(G13:G16) -> 0 | H17: =SUM(H13:H16) -> 7.7725448e+08 | I17: =SUM(I13:I16) -> 1.6084034e+10 | J17: =SUM(C17:H17)=I17 -> TRUE
B20: ASE 2
B21: Resumen Recaudo Aplicado Por Servicio
C22: ENEL | D22: CIUDAD LIMPIA | E22: EAB | F22: NUEVO ESQUEMA | G22: ENERBIT | H22: OCCIDENTE | I22: Total
B23: 1-APLICADOS A FACTURACION | C23: 20206354631 | E23: 0 | F23: 1778140 | H23: 2.049434e+09 | I23: =SUM(C23:H23) -> 2.2257567e+10 | J23: =SUM(C23:H23)=I23 -> TRUE
B24: 2-SALDOS A FAVOR GENERADOS | C24: 37168207 | E24: 0 | F24: 2611951 | H24: 1.1706611e+08 | I24: =SUM(C24:H24) -> 1.5684627e+08 | J24: =SUM(C24:H24)=I24 -> TRUE
B25: 3-APLICADOS A FINANCIACIONES NUEVAS | C25: 0 | E25: 0 | F25: 0 | H25: 7922640.9 | I25: =SUM(C25:H25) -> 7922640.9 | J25: =SUM(C25:H25)=I25 -> TRUE
B26: 7-APLICADOS A RECIBOS SERVICIOS ESPECIALES | F26: 0 | H26: 0 | I26: =SUM(C26:H26) -> 0 | J26: =SUM(C26:H26)=I26 -> TRUE
B27: Total | C27: =SUM(C23:C26) -> 20243522838 | D27: =SUM(D23:D26) -> 0 | E27: =SUM(E23:E26) -> 0 | F27: =SUM(F23:F26) -> 4390091 | G27: =SUM(G23:G26) -> 0 | H27: =SUM(H23:H26) -> 2174422710 | I27: =SUM(I23:I26) -> 2.2422336e+10 | J27: =SUM(C27:H27)=I27 -> TRUE
B29: ASE 3
B30: Resumen Recaudo Aplicado Por Servicio
C31: ENEL | D31: CIUDAD LIMPIA | E31: EAB | F31: NUEVO ESQUEMA | G31: ENERBIT | H31: OCCIDENTE | I31: Total
B32: 1-APLICADOS A FACTURACION | C32: 13883027309 | F32: 0 | H32: 1.2760545e+09 | I32: =SUM(C32:H32) -> 1.5159082e+10 | J32: =SUM(C32:H32)=I32 -> TRUE
B33: 2-SALDOS A FAVOR GENERADOS | C33: 10762026 | F33: 0 | H33: 1.9018313e+08 | I33: =SUM(C33:H33) -> 2.0094516e+08 | J33: =SUM(C33:H33)=I33 -> TRUE
B34: 3-APLICADOS A FINANCIACIONES NUEVAS | C34: 0 | F34: 0 | H34: 4999782.5 | I34: =SUM(C34:H34) -> 4999782.5 | J34: =SUM(C34:H34)=I34 -> TRUE
B35: 7-APLICADOS A RECIBOS SERVICIOS ESPECIALES | C35: 0 | F35: 0 | I35: =SUM(C35:H35) -> 0 | J35: =SUM(C35:H35)=I35 -> TRUE
B36: Total | C36: =SUM(C32:C35) -> 13893789335 | D36: =SUM(D32:D35) -> 0 | E36: =SUM(E32:E35) -> 0 | F36: =SUM(F32:F35) -> 0 | G36: =SUM(G32:G35) -> 0 | H36: =SUM(H32:H35) -> 1471237404 | I36: =SUM(I32:I35) -> 1.5365027e+10 | J36: =SUM(C36:H36)=I36 -> TRUE
B38: ASE 4
B39: Resumen Recaudo Aplicado Por Servicio
C40: ENEL | D40: CIUDAD LIMPIA | E40: EAB | F40: NUEVO ESQUEMA | G40: ENERBIT | H40: OCCIDENTE | I40: Total
B41: 1-APLICADOS A FACTURACION | C41: 6664014596 | E41: 0 | F41: 551610 | H41: 9.857407e+08 | I41: =SUM(C41:H41) -> 7.6503069e+09 | J41: =SUM(C41:H41)=I41 -> TRUE
B42: 2-SALDOS A FAVOR GENERADOS | C42: 48073886 | E42: 0 | F42: 1262390 | H42: 24854028 | I42: =SUM(C42:H42) -> 74190304 | J42: =SUM(C42:H42)=I42 -> TRUE
B43: 3-APLICADOS A FINANCIACIONES NUEVAS | C43: 0 | E43: 0 | F43: 0 | H43: 21743103 | I43: =SUM(C43:H43) -> 21743103 | J43: =SUM(C43:H43)=I43 -> TRUE
B44: 7-APLICADOS A RECIBOS SERVICIOS ESPECIALES | I44: =SUM(C44:H44) -> 0 | J44: =SUM(C44:H44)=I44 -> TRUE
B45: Total | C45: =SUM(C41:C44) -> 6712088482 | D45: =SUM(D41:D44) -> 0 | E45: =SUM(E41:E44) -> 0 | F45: =SUM(F41:F44) -> 1814000 | G45: =SUM(G41:G44) -> 0 | H45: =SUM(H41:H44) -> 1032337827 | I45: =SUM(I41:I44) -> 7.7462403e+09 | J45: =SUM(C45:H45)=I45 -> TRUE
B48: ASE 5
B49: Resumen Recaudo Aplicado Por Servicio
C50: ENEL | D50: CIUDAD LIMPIA | E50: EAB | F50: NUEVO ESQUEMA | G50: ENERBIT | H50: OCCIDENTE | I50: Total
B51: 1-APLICADOS A FACTURACION | C51: 12041028614 | G51: 34785208 | H51: 2.6466237e+08 | I51: =SUM(C51:H51) -> 1.2340476e+10 | J51: =SUM(C51:H51)=I51 -> TRUE
B52: 2-SALDOS A FAVOR GENERADOS | C52: 8133932 | G52: 4085178 | H52: 14737858 | I52: =SUM(C52:H52) -> 26956968 | J52: =SUM(C52:H52)=I52 -> TRUE
B53: 3-APLICADOS A FINANCIACIONES NUEVAS | C53: 0 | G53: 0 | H53: 1483461.3 | I53: =SUM(C53:H53) -> 1483461.3 | J53: =SUM(C53:H53)=I53 -> TRUE
B54: 7-APLICADOS A RECIBOS SERVICIOS ESPECIALES | C54: 0 | I54: =SUM(C54:H54) -> 0 | J54: =SUM(C54:H54)=I54 -> TRUE
B55: Total | C55: =SUM(C51:C54) -> 12049162546 | D55: =SUM(D51:D54) -> 0 | E55: =SUM(E51:E54) -> 0 | F55: =SUM(F51:F54) -> 0 | G55: =SUM(G51:G54) -> 38870386 | H55: =SUM(H51:H54) -> 280883691 | I55: =SUM(I51:I54) -> 12368916623 | J55: =SUM(C55:H55)=I55 -> TRUE
B59: QUINCENA | C59: 2 | D59: OJO/// DILIGENCIAR
B62: Recaudo ENEL - ASE 1 | C62: =IF($C$59=1,'Recaudo ENEL'!D21,'Recaudo ENEL'!F21) -> 15306779444 | D62: =C17=C62 -> TRUE | E62: =C17-C62 -> 0
B63: Recaudo ENERBIT - ASE 1 | C63: =IF($C$59=1,'Recaudo ENERBIT'!D21,'Recaudo ENERBIT'!F21) -> 0 | D63: =G17=C63 -> TRUE | E63: =G17-C63 -> 0
B64: Recaudo Reciprocidad EAAB - ASE 2 | C64: =IF($C$59=1,'Recaudo EAAB Reciprocidad'!D22,'Recaudo EAAB Reciprocidad'!F22) -> 4390091 | D64: =F27=C64 -> TRUE | E64: =F27-C64 -> 0
B65: Recaudo ENEL - ASE 2 | C65: =IF($C$59=1,'Recaudo ENEL'!D22,'Recaudo ENEL'!F22) -> 20240915748 | D65: =C27=C65 -> FALSE | E65: =C27-C65 -> 2607090 | F65: OK
B66: Recaudo ENERBIT - ASE 2 | C66: =IF($C$59=1,'Recaudo ENERBIT'!D22,'Recaudo ENERBIT'!F22) -> 0 | D66: =G27=C66 -> TRUE | E66: =G27-C66 -> 0
B67: Recaudo ENEL - ASE 3 | C67: =IF($C$59=1,'Recaudo ENEL'!D23,'Recaudo ENEL'!F23) -> 13892251925 | D67: =C36=C67 -> FALSE | E67: =C36-C67 -> 1537410 | F67: OK
B68: Recaudo ENERBIT - ASE 3 | C68: =IF($C$59=1,'Recaudo ENERBIT'!D23,'Recaudo ENERBIT'!F23) -> 0 | D68: =G36=C68 -> TRUE | E68: =G36-C68 -> 0
B69: Recaudo Reciprocidad EAAB - ASE 4 | C69: =IF($C$59=1,'Recaudo EAAB Reciprocidad'!D24,'Recaudo EAAB Reciprocidad'!F24) -> 1814000 | D69: =F45=C69 -> TRUE | E69: =F45-C69 -> 0
B70: Recaudo ENEL - ASE 4 | C70: =IF($C$59=1,'Recaudo ENEL'!D24,'Recaudo ENEL'!F24) -> 6711455732 | D70: =C45=C70 -> FALSE | E70: =C45-C70 -> 632750 | F70: OK
B71: Recaudo ENERBIT - ASE 4 | C71: =IF($C$59=1,'Recaudo ENERBIT'!D24,'Recaudo ENERBIT'!F24) -> 0 | D71: =G45=C71 -> TRUE | E71: =G45-C71 -> 0
B72: Recaudo ENEL - ASE 5 | C72: =IF($C$59=1,'Recaudo ENEL'!D25,'Recaudo ENEL'!F25) -> 12048665266 | D72: =C55=C72 -> FALSE | E72: =C55-C72 -> 497280 | F72: OK
B73: Recaudo ENERBIT - ASE 5 | C73: =IF($C$59=1,'Recaudo ENERBIT'!D25,'Recaudo ENERBIT'!F25) -> 38870386 | D73: =G55=C73 -> TRUE | E73: =G55-C73 -> 0
B75: Recaudo Banco Occidente ASE 1 | C75: =IF($C$59=1,'Recaudo Directa Occidente'!D21,'Recaudo Directa Occidente'!F21) -> 777254475 | D75: =C75=H17 -> TRUE | E75: =C75-H17 -> 0
B76: Recaudo Banco Occidente ASE 2 | C76: =IF($C$59=1,'Recaudo Directa Occidente'!D22,'Recaudo Directa Occidente'!F22) -> 2174422710 | D76: =C76=H27 -> TRUE | E76: =C76-H27 -> 0
B77: Recaudo Banco Occidente ASE 3 | C77: =IF($C$59=1,'Recaudo Directa Occidente'!D23,'Recaudo Directa Occidente'!F23) -> 1471237404 | D77: =C77=H36 -> TRUE | E77: =C77-H36 -> 0
B78: Recaudo Banco Occidente ASE 4 | C78: =IF($C$59=1,'Recaudo Directa Occidente'!D24,'Recaudo Directa Occidente'!F24) -> 1032337827 | D78: =C78=H45 -> TRUE | E78: =C78-H45 -> 0
B79: Recaudo Banco Occidente ASE 5 | C79: =IF($C$59=1,'Recaudo Directa Occidente'!D25,'Recaudo Directa Occidente'!F25) -> 280883691 | D79: =C79=H55 -> TRUE | E79: =C79-H55 -> 0

Sheet ANT EXT-REV
C1: ASE 1 | E1: ASE 2 | G1: ASE 3 | I1: ASE 4 | K1: ASE 5 | M1: TOTAL
C2: REPORTE 3 | D2: REPORTE 4 | E2: REPORTE 3 | F2: REPORTE 4 | G2: REPORTE 3 | H2: REPORTE 4 | I2: REPORTE 3 | J2: REPORTE 4 | K2: REPORTE 3 | L2: REPORTE 4 | M2: REPORTE 3 | N2: REPORTE 4
B3: APLICADO | C3: =C11+C19+C27+C35+C43 -> 40070 | D3: =D11+D19+D27+D35+D43 -> -1285060 | E3: =E11+E19+E27+E35+E43 -> 18014168 | F3: =F11+F19+F27+F35+F43 -> -45230052 | G3: =G11+G19+G27+G35+G43 -> 388550 | H3: =H11+H19+H27+H35+H43 -> -7715664 | I3: =I11+I19+I27+I35+I43 -> 83364801 | J3: =J11+J19+J27+J35+J43 -> -1.7861971e+08 | ... L3: =L11+L19+L27+L35+L43 -> -4790099 | M3: =C3+E3+G3+I3+K3 -> 1.0180759e+08 | N3: =D3+F3+H3+J3+L3 -> -2.3764058e+08 | P3: =N3=(-VALIDACION_TOTAL!M9) -> TRUE
B4: ANTICIPOS | C4: =C12+C20+C28+C36+C44 -> 691640 | D4: =D12+D20+D28+D36+D44 -> -137440 | E4: =E12+E20+E28+E36+E44 -> 12142859 | F4: =F12+F20+F28+F36+F44 -> -139792 | G4: =G12+G20+G28+G36+G44 -> 1272990 | H4: =H12+H20+H28+H36+H44 -> -541790 | I4: =I12+I20+I28+I36+I44 -> 91642042 | J4: =J12+J20+J28+J36+J44 -> -780507.47 | ... L4: =L12+L20+L28+L36+L44 -> 0 | M4: =C4+E4+G4+I4+K4 -> 1.0574953e+08 | N4: =D4+F4+H4+J4+L4 -> -1599529.5 | P4: =N4=(-'CONSOLIDADO_TOTAL RECAUDO'!L131) -> TRUE
B5: TOTAL | C5: =SUM(C3:C4) -> 731710 | D5: =SUM(D3:D4) -> -1422500 | E5: =SUM(E3:E4) -> 30157027 | F5: =SUM(F3:F4) -> -45369844 | G5: =SUM(G3:G4) -> 1661540 | H5: =SUM(H3:H4) -> -8257454 | I5: =SUM(I3:I4) -> 175006843 | J5: =SUM(J3:J4) -> -179400217 | ... N5: =SUM(N3:N4) -> -239240114
C6: =C5=(C13+C21+C29+C37+C45) -> TRUE | D6: =D5=(D13+D21+D29+D37+D45) -> TRUE | E6: =E5=(E13+E21+E29+E37+E45) -> TRUE | F6: =F5=(F13+F21+F29+F37+F45) -> TRUE | G6: =G5=(G13+G21+G29+G37+G45) -> TRUE | H6: =H5=(H13+H21+H29+H37+H45) -> TRUE | I6: =I5=(I13+I21+I29+I37+I45) -> TRUE | J6: =J5=(J13+J21+J29+J37+J45) -> TRUE | ... N6: =N5=(N13+N21+N29+N37+N45) -> TRUE
B8: BANCO DE OCCIDENTE
C9: ASE 1 | E9: ASE 2 | G9: ASE 3 | I9: ASE 4 | K9: ASE 5 | M9: TOTAL
C10: REPORTE 3 | D10: REPORTE 4 | E10: REPORTE 3 | F10: REPORTE 4 | G10: REPORTE 3 | H10: REPORTE 4 | I10: REPORTE 3 | J10: REPORTE 4 | K10: REPORTE 3 | L10: REPORTE 4 | M10: REPORTE 3 | N10: REPORTE 4
B11: APLICADO | C11: 40070 | D11: -40070 | E11: 1003966 | F11: -3643056 | G11: 0 | H11: 0 | I11: 5075866 | J11: -9398936.9 | K11: 0 | L11: 0 | M11: =C11+E11+G11+I11+K11 -> 6119902 | N11: =D11+F11+H11+J11+L11 -> -13082063
B12: ANTICIPOS | C12: 0 | D12: 0 | E12: 2673592 | F12: -34502 | G12: 0 | H12: 0 | I12: 4396815 | J12: -73744.13 | K12: 0 | L12: 0 | M12: =C12+E12+G12+I12+K12 -> 7070407 | N12: =D12+F12+H12+J12+L12 -> -108246.13
B13: TOTAL | C13: =SUM(C11:C12) -> 40070 | D13: =SUM(D11:D12) -> -40070 | E13: =SUM(E11:E12) -> 3677558 | F13: =SUM(F11:F12) -> -3677558 | G13: =SUM(G11:G12) -> 0 | H13: =SUM(H11:H12) -> 0 | I13: =SUM(I11:I12) -> 9472681 | J13: =SUM(J11:J12) -> -9472681 | ... N13: =SUM(N11:N12) -> -13190309
B16: EAAB RECIPROCIDAD
C17: ASE 1 | E17: ASE 2 | G17: ASE 3 | I17: ASE 4 | K17: ASE 5 | M17: TOTAL
C18: REPORTE 3 | D18: REPORTE 4 | E18: REPORTE 3 | F18: REPORTE 4 | G18: REPORTE 3 | H18: REPORTE 4 | I18: REPORTE 3 | J18: REPORTE 4 | K18: REPORTE 3 | L18: REPORTE 4 | M18: REPORTE 3 | N18: REPORTE 4
B19: APLICADO | C19: 0 | D19: 0 | E19: 0 | F19: -46130 | G19: 0 | H19: 0 | I19: 477310 | J19: -1564160 | K19: 0 | L19: 0 | M19: =C19+E19+G19+I19+K19 -> 477310 | N19: =D19+F19+H19+J19+L19 -> -1610290
B20: ANTICIPOS | C20: 0 | D20: 0 | E20: 46130 | F20: 0 | G20: 0 | H20: 0 | I20: 1086850 | K20: 0 | L20: 0 | M20: =C20+E20+G20+I20+K20 -> 1132980 | N20: =D20+F20+H20+J20+L20 -> 0
B21: TOTAL | C21: =SUM(C19:C20) -> 0 | D21: =SUM(D19:D20) -> 0 | E21: =SUM(E19:E20) -> 46130 | F21: =SUM(F19:F20) -> -46130 | G21: =SUM(G19:G20) -> 0 | H21: =SUM(H19:H20) -> 0 | I21: =SUM(I19:I20) -> 1564160 | J21: =SUM(J19:J20) -> -1564160 | ... L21: =SUM(L19:L20) -> 0 | M21: =C21+E21+G21+I21+K21 -> 1610290 | N21: =SUM(N19:N20) -> -1610290
B24: EAAB CIUDAD LIMPIA
C25: ASE 1 | E25: ASE 2 | G25: ASE 3 | I25: ASE 4 | K25: ASE 5 | M25: TOTAL
C26: REPORTE 3 | D26: REPORTE 4 | E26: REPORTE 3 | F26: REPORTE 4 | G26: REPORTE 3 | H26: REPORTE 4 | I26: REPORTE 3 | J26: REPORTE 4 | K26: REPORTE 3 | L26: REPORTE 4 | M26: REPORTE 3 | N26: REPORTE 4
B27: APLICADO | C27: 0 | D27: 0 | E27: 0 | F27: 0 | G27: 0 | H27: 0 | I27: 0 | J27: 0 | K27: 0 | L27: 0 | M27: =C27+E27+G27+I27+K27 -> 0 | N27: =D27+F27+H27+J27+L27 -> 0
B28: ANTICIPOS | C28: 0 | D28: 0 | E28: 0 | F28: 0 | G28: 0 | H28: 0 | I28: 0 | J28: 0 | K28: 0 | L28: 0 | M28: =C28+E28+G28+I28+K28 -> 0 | N28: =D28+F28+H28+J28+L28 -> 0
B29: TOTAL | C29: =SUM(C27:C28) -> 0 | D29: =SUM(D27:D28) -> 0 | E29: =SUM(E27:E28) -> 0 | F29: =SUM(F27:F28) -> 0 | G29: =SUM(G27:G28) -> 0 | H29: =SUM(H27:H28) -> 0 | I29: =SUM(I27:I28) -> 0 | J29: =SUM(J27:J28) -> 0 | ... N29: =SUM(N27:N28) -> 0
B32: ENEL
C33: ASE 1 | E33: ASE 2 | G33: ASE 3 | I33: ASE 4 | K33: ASE 5 | M33: TOTAL
C34: REPORTE 3 | D34: REPORTE 4 | E34: REPORTE 3 | F34: REPORTE 4 | G34: REPORTE 3 | H34: REPORTE 4 | I34: REPORTE 3 | J34: REPORTE 4 | K34: REPORTE 3 | L34: REPORTE 4 | M34: REPORTE 3 | N34: REPORTE 4
B35: APLICADO | C35: 0 | D35: -1244990 | E35: 17010202 | F35: -41540866 | G35: 388550 | H35: -7715664 | I35: 77811625 | J35: -1.6765661e+08 | K35: 0 | L35: -4790099 | M35: =C35+E35+G35+I35+K35 -> 95210377 | N35: =D35+F35+H35+J35+L35 -> -2.2294823e+08
B36: ANTICIPOS | C36: 691640 | D36: -137440 | E36: 9423137 | F36: -105290 | G36: 1272990 | H36: -541790 | I36: 86158377 | J36: -706763.34 | K36: 0 | L36: 0 | M36: =C36+E36+G36+I36+K36 -> 97546144 | N36: =D36+F36+H36+J36+L36 -> -1491283.3
B37: TOTAL | C37: =SUM(C35:C36) -> 691640 | D37: =SUM(D35:D36) -> -1382430 | E37: =SUM(E35:E36) -> 26433339 | F37: =SUM(F35:F36) -> -41646156 | G37: =SUM(G35:G36) -> 1661540 | H37: =SUM(H35:H36) -> -8257454 | I37: =SUM(I35:I36) -> 163970002 | J37: =SUM(J35:J36) -> -168363376 | ... N37: =SUM(N35:N36) -> -224439515
B40: ENERBIT
C41: ASE 1 | E41: ASE 2 | G41: ASE 3 | I41: ASE 4 | K41: ASE 5 | M41: TOTAL
C42: REPORTE 3 | D42: REPORTE 4 | E42: REPORTE 3 | F42: REPORTE 4 | G42: REPORTE 3 | H42: REPORTE 4 | I42: REPORTE 3 | J42: REPORTE 4 | K42: REPORTE 3 | L42: REPORTE 4 | M42: REPORTE 3 | N42: REPORTE 4
B43: APLICADO | C43: 0 | D43: 0 | E43: 0 | F43: 0 | G43: 0 | H43: 0 | I43: 0 | J43: 0 | K43: 0 | L43: 0 | M43: =C43+E43+G43+I43+K43 -> 0 | N43: =D43+F43+H43+J43+L43 -> 0
B44: ANTICIPOS | C44: 0 | D44: 0 | E44: 0 | F44: 0 | G44: 0 | H44: 0 | I44: 0 | J44: 0 | K44: 0 | L44: 0 | M44: =C44+E44+G44+I44+K44 -> 0 | N44: =D44+F44+H44+J44+L44 -> 0
B45: TOTAL | C45: =SUM(C43:C44) -> 0 | D45: =SUM(D43:D44) -> 0 | E45: =SUM(E43:E44) -> 0 | F45: =SUM(F43:F44) -> 0 | G45: =SUM(G43:G44) -> 0 | H45: =SUM(H43:H44) -> 0 | I45: =SUM(I43:I44) -> 0 | J45: =SUM(J43:J44) -> 0 | ... N45: =SUM(N43:N44) -> 0

Sheet ANTICIPOS USUARIOS
B1: TOTAL | E1: RECIPRCIDAD | H1: ENEL | K1: ENERBIT | N1: OCCIDENTE | Q1: EAAB-CIUDADLIMPIA
B2: ASE | C2: ANTICIPOS GENERADOS POR PAGO | E2: ASE | F2: ANTICIPOS GENERADOS POR PAGO | H2: ASE | I2: ANTICIPOS GENERADOS POR PAGO | K2: ASE | L2: ANTICIPOS GENERADOS POR PAGO | N2: ASE | O2: ANTICIPOS GENERADOS POR PAGO | Q2: ASE | R2: ANTICIPOS GENERADOS POR PAGO | T2: Anticipos generados por pago
B3: 1 | C3: ='REPORTE RECAUDO x BANCO'!I14 -> 65283383 | E3: 1 | F3: ='REPORTE RECAUDO x BANCO'!F14 -> 0 | H3: 1 | I3: ='REPORTE RECAUDO x BANCO'!C14 -> 30927107 | K3: 1 | L3: ='REPORTE RECAUDO x BANCO'!G14 -> 0 | N3: 1 | O3: ='REPORTE RECAUDO x BANCO'!H14 -> 34356276 | Q3: 1 | R3: ='REPORTE RECAUDO x BANCO'!D14+'REPORTE RECAUDO x BANCO'!E14 -> 0 | T3: Sale del reporte Recaudo por Bancos.
B4: 2 | C4: ='REPORTE RECAUDO x BANCO'!I24 -> 1.5684627e+08 | E4: 2 | F4: ='REPORTE RECAUDO x BANCO'!F24 -> 2611951 | H4: 2 | I4: ='REPORTE RECAUDO x BANCO'!C24 -> 37168207 | K4: 2 | L4: ='REPORTE RECAUDO x BANCO'!G24 -> 0 | N4: 2 | O4: ='REPORTE RECAUDO x BANCO'!H24 -> 1.1706611e+08 | Q4: 2 | R4: ='REPORTE RECAUDO x BANCO'!D24+'REPORTE RECAUDO x BANCO'!E24 -> 0
B5: 3 | C5: ='REPORTE RECAUDO x BANCO'!I33 -> 2.0094516e+08 | E5: 3 | F5: ='REPORTE RECAUDO x BANCO'!F33 -> 0 | H5: 3 | I5: ='REPORTE RECAUDO x BANCO'!C33 -> 10762026 | K5: 3 | L5: ='REPORTE RECAUDO x BANCO'!G33 -> 0 | N5: 3 | O5: ='REPORTE RECAUDO x BANCO'!H33 -> 1.9018313e+08 | Q5: 3 | R5: ='REPORTE RECAUDO x BANCO'!D33+'REPORTE RECAUDO x BANCO'!E33 -> 0
B6: 4 | C6: ='REPORTE RECAUDO x BANCO'!I42 -> 74190304 | E6: 4 | F6: ='REPORTE RECAUDO x BANCO'!F42 -> 1262390 | H6: 4 | I6: ='REPORTE RECAUDO x BANCO'!C42 -> 48073886 | K6: 4 | L6: ='REPORTE RECAUDO x BANCO'!G42 -> 0 | N6: 4 | O6: ='REPORTE RECAUDO x BANCO'!H42 -> 24854028 | Q6: 4 | R6: ='REPORTE RECAUDO x BANCO'!D42+'REPORTE RECAUDO x BANCO'!E42 -> 0
B7: 5 | C7: ='REPORTE RECAUDO x BANCO'!I52 -> 26956968 | E7: 5 | F7: ='REPORTE RECAUDO x BANCO'!F52 -> 0 | H7: 5 | I7: ='REPORTE RECAUDO x BANCO'!C52 -> 8133932 | K7: 5 | L7: ='REPORTE RECAUDO x BANCO'!G52 -> 4085178 | N7: 5 | O7: ='REPORTE RECAUDO x BANCO'!H52 -> 14737858 | Q7: 5 | R7: ='REPORTE RECAUDO x BANCO'!D52+'REPORTE RECAUDO x BANCO'!E52 -> 0
C8: =SUM(C3:C7) -> 5.2422208e+08 | F8: =SUM(F3:F7) -> 3874341 | I8: =SUM(I3:I7) -> 135065158 | L8: =SUM(L3:L7) -> 4085178 | O8: =SUM(O3:O7) -> 3.811974e+08 | R8: =SUM(R3:R7) -> 0
C9: =C8='REPORTE RECAUDO x BANCO'!I3 -> TRUE | F9: =F8='REPORTE RECAUDO x BANCO'!F3 -> TRUE | I9: =I8='REPORTE RECAUDO x BANCO'!C3 -> TRUE | L9: =L8='REPORTE RECAUDO x BANCO'!G3 -> TRUE | O9: =O8='REPORTE RECAUDO x BANCO'!H3 -> TRUE | R9: =R8='REPORTE RECAUDO x BANCO'!D3+'REPORTE RECAUDO x BANCO'!E3 -> TRUE
B11: ASE | C11: ANTICIPOS GENERADOS POR EXTEMPORANEOS | E11: ASE | F11: ANTICIPOS GENERADOS POR EXTEMPORANEOS | H11: ASE | I11: ANTICIPOS GENERADOS POR EXTEMPORANEOS | K11: ASE | L11: ANTICIPOS GENERADOS POR EXTEMPORANEOS | N11: ASE | O11: ANTICIPOS GENERADOS POR EXTEMPORANEOS | Q11: ASE | R11: ANTICIPOS GENERADOS POR EXTEMPORANEOS | T11: Anticipos generados por pagos aplicados de reversiones
B12: 1 | C12: ='ANT EXT-REV'!C4 -> 691640 | E12: 1 | F12: ='ANT EXT-REV'!C20 -> 0 | H12: 1 | I12: ='ANT EXT-REV'!C36 -> 691640 | K12: 1 | L12: ='ANT EXT-REV'!C44 -> 0 | N12: 1 | O12: ='ANT EXT-REV'!C12 -> 0 | Q12: 1 | R12: ='ANT EXT-REV'!C28 -> 0 | T12: Sale del reporte Recaudo reversado
B13: 2 | C13: ='ANT EXT-REV'!E4 -> 12142859 | E13: 2 | F13: ='ANT EXT-REV'!E20 -> 46130 | H13: 2 | I13: ='ANT EXT-REV'!E36 -> 9423137 | K13: 2 | L13: ='ANT EXT-REV'!E44 -> 0 | N13: 2 | O13: ='ANT EXT-REV'!E12 -> 2673592 | Q13: 2 | R13: ='ANT EXT-REV'!E28 -> 0
B14: 3 | C14: ='ANT EXT-REV'!G4 -> 1272990 | E14: 3 | F14: ='ANT EXT-REV'!G20 -> 0 | H14: 3 | I14: ='ANT EXT-REV'!G36 -> 1272990 | K14: 3 | L14: ='ANT EXT-REV'!G44 -> 0 | N14: 3 | O14: ='ANT EXT-REV'!G12 -> 0 | Q14: 3 | R14: ='ANT EXT-REV'!G28 -> 0
B15: 4 | C15: ='ANT EXT-REV'!I4 -> 91642042 | E15: 4 | F15: ='ANT EXT-REV'!I20 -> 1086850 | H15: 4 | I15: ='ANT EXT-REV'!I36 -> 86158377 | K15: 4 | L15: ='ANT EXT-REV'!I44 -> 0 | N15: 4 | O15: ='ANT EXT-REV'!I12 -> 4396815 | Q15: 4 | R15: ='ANT EXT-REV'!I28 -> 0
B16: 5 | C16: ='ANT EXT-REV'!K4 -> 0 | E16: 5 | F16: ='ANT EXT-REV'!K20 -> 0 | H16: 5 | I16: ='ANT EXT-REV'!K36 -> 0 | K16: 5 | L16: ='ANT EXT-REV'!K44 -> 0 | N16: 5 | O16: ='ANT EXT-REV'!K12 -> 0 | Q16: 5 | R16: ='ANT EXT-REV'!K28 -> 0
C17: =SUM(C12:C16) -> 1.0574953e+08 | F17: =SUM(F12:F16) -> 1132980 | I17: =SUM(I12:I16) -> 97546144 | L17: =SUM(L12:L16) -> 0 | O17: =SUM(O12:O16) -> 7070407 | R17: =SUM(R12:R16) -> 0
C18: =C17='ANT EXT-REV'!M4 -> TRUE | F18: =F17='ANT EXT-REV'!M20 -> TRUE | I18: =I17='ANT EXT-REV'!M36 -> TRUE | L18: =L17='ANT EXT-REV'!M44 -> TRUE | O18: =O17='ANT EXT-REV'!M12 -> TRUE | R18: =R17='ANT EXT-REV'!M28 -> TRUE
B20: ASE | C20: ANTICIPOS QUE CARGAN POR REVERSIONES | E20: ASE | F20: ANTICIPOS QUE CARGAN POR REVERSIONES | H20: ASE | I20: ANTICIPOS QUE CARGAN POR REVERSIONES | K20: ASE | L20: ANTICIPOS QUE CARGAN POR REVERSIONES | N20: ASE | O20: ANTICIPOS QUE CARGAN POR REVERSIONES | Q20: ASE | R20: ANTICIPOS QUE CARGAN POR REVERSIONES | T20: Anticipos que cargan de reversiones
B21: 1 | C21: ='ANT EXT-REV'!D4 -> -137440 | E21: 1 | F21: ='ANT EXT-REV'!D20 -> 0 | H21: 1 | I21: ='ANT EXT-REV'!D36 -> -137440 | K21: 1 | L21: ='ANT EXT-REV'!D44 -> 0 | N21: 1 | O21: ='ANT EXT-REV'!D12 -> 0 | Q21: 1 | R21: ='ANT EXT-REV'!D28 -> 0 | T21: Sale del reporte Recaudo reversado
B22: 2 | C22: ='ANT EXT-REV'!F4 -> -139792 | E22: 2 | F22: ='ANT EXT-REV'!F20 -> 0 | H22: 2 | I22: ='ANT EXT-REV'!F36 -> -105290 | K22: 2 | L22: ='ANT EXT-REV'!F44 -> 0 | N22: 2 | O22: ='ANT EXT-REV'!F12 -> -34502 | Q22: 2 | R22: ='ANT EXT-REV'!F28 -> 0
B23: 3 | C23: ='ANT EXT-REV'!H4 -> -541790 | E23: 3 | F23: ='ANT EXT-REV'!H20 -> 0 | H23: 3 | I23: ='ANT EXT-REV'!H36 -> -541790 | K23: 3 | L23: ='ANT EXT-REV'!H44 -> 0 | N23: 3 | O23: ='ANT EXT-REV'!H12 -> 0 | Q23: 3 | R23: ='ANT EXT-REV'!H28 -> 0
B24: 4 | C24: ='ANT EXT-REV'!J4 -> -780507.47 | E24: 4 | F24: ='ANT EXT-REV'!J20 -> 0 | H24: 4 | I24: ='ANT EXT-REV'!J36 -> -706763.34 | K24: 4 | L24: ='ANT EXT-REV'!J44 -> 0 | N24: 4 | O24: ='ANT EXT-REV'!J12 -> -73744.13 | Q24: 4 | R24: ='ANT EXT-REV'!J28 -> 0
B25: 5 | C25: ='ANT EXT-REV'!L4 -> 0 | E25: 5 | F25: ='ANT EXT-REV'!L20 -> 0 | H25: 5 | I25: ='ANT EXT-REV'!L36 -> 0 | K25: 5 | L25: ='ANT EXT-REV'!L44 -> 0 | N25: 5 | O25: ='ANT EXT-REV'!L12 -> 0 | Q25: 5 | R25: ='ANT EXT-REV'!L28 -> 0
C26: =SUM(C21:C25) -> -1599529.5 | F26: =SUM(F21:F25) -> 0 | I26: =SUM(I21:I25) -> -1491283.3 | L26: =SUM(L21:L25) -> 0 | O26: =SUM(O21:O25) -> -108246.13 | R26: =SUM(R21:R25) -> 0
C27: =C26='ANT EXT-REV'!N4 -> TRUE | F27: =F26='ANT EXT-REV'!N20 -> TRUE | I27: =I26='ANT EXT-REV'!N36 -> TRUE | L27: =L26='ANT EXT-REV'!N44 -> TRUE | O27: =O26='ANT EXT-REV'!N12 -> TRUE | R27: =R26='ANT EXT-REV'!N28 -> TRUE

Sheet BCE SC POR FACT.
C2: ASE | D2: SUBSIDIO | E2: CONTRIBUCION | F2: TOTAL BSC | H2: SISTEMA
C3: 1 | D3: -6.6055391e+09 | E3: 2.1040376e+09 | F3: =D3+E3 -> -4.5015016e+09 | H3: =DetRetri2026092!J9 -> -4501501560 | I3: =F3-H3 -> -0.34999943
C4: 2 | D4: -5.5089379e+09 | E4: 1.95863e+09 | F4: =D4+E4 -> -3.5503079e+09 | H4: =DetRetri2026092!J10 -> -3550307908 | I4: =F4-H4 -> -0.4800005
C5: 3 | D5: -2.0642657e+09 | E5: 1.313676e+09 | F5: =D5+E5 -> -7.5058976e+08 | H5: =DetRetri2026092!J11 -> -750589760 | I5: =F5-H5 -> 0.4000001
C6: 4 | D6: -2.5882756e+09 | E6: 1.8741347e+09 | F6: =D6+E6 -> -7.1414094e+08 | H6: =DetRetri2026092!J12 -> -714140939 | I6: =F6-H6 -> -0.3599999
C7: 5 | D7: -1.2358747e+09 | E7: 1.1376358e+09 | F7: =D7+E7 -> -98238892 | H7: =DetRetri2026092!J13 -> -98238892 | I7: =F7-H7 -> 0.059999943
F9: =SUM(F3:F7) -> -9.6147791e+09 | H9: =SUM(H3:H7) -> -9614779059 | I9: =F9-H9 -> -0.73000145
H10: =H9=DetRetri2026092!J14 -> TRUE
D11: =SUM(D3:D7) -> -1.8002893e+10 | E11: =SUM(E3:E7) -> 8.388114e+09 | F11: =SUM(D3:E7) -> -9.6147791e+09
F12: =ROUND(F11,2)=ROUND(F9,2) -> TRUE
F13: =ROUND(F11,2)-ROUND(F9,2) -> 0
D18: ASE | E18: REMUN TOTAL | F18: VALIDA 1 | G18: VALIDA 2 | H18: DIFERENCIA VALIDA 2
D19: 1 | E19: ='CONSOLIDADO_TOTAL RECAUDO'!J104 -> -4.5015016e+09 | F19: =E19=F3 -> TRUE | G19: =E19=H3 -> FALSE | H19: =E19-H3 -> -0.34999943
D20: 2 | E20: ='CONSOLIDADO_TOTAL RECAUDO'!J105 -> -3.5503079e+09 | F20: =E20=F4 -> TRUE | G20: =E20=H4 -> FALSE | H20: =E20-H4 -> -0.4800005
D21: 3 | E21: ='CONSOLIDADO_TOTAL RECAUDO'!J106 -> -7.5058976e+08 | F21: =E21=F5 -> TRUE | G21: =E21=H5 -> FALSE | H21: =E21-H5 -> 0.4000001
D22: 4 | E22: ='CONSOLIDADO_TOTAL RECAUDO'!J107 -> -7.1414094e+08 | F22: =E22=F6 -> TRUE | G22: =E22=H6 -> FALSE | H22: =E22-H6 -> -0.3599999
D23: 5 | E23: ='CONSOLIDADO_TOTAL RECAUDO'!J108 -> -98238892 | F23: =E23=F7 -> TRUE | G23: =E23=H7 -> FALSE | H23: =E23-H7 -> 0.059999943
E24: =SUM(E19:E23) -> -9.6147791e+09 | F24: =E24=F9 -> TRUE | G24: =E24=H9 -> FALSE | H24: =E24-H9 -> -0.73000145

Sheet Reporte Componentes R1
B4: PROMOAMBIENTAL
F5: Total | G5: Componente TDF | H5: Componente TTL | I5: Componente TVIAT | J5: Aprovechamiento | K5: CCSA Prest.Aprov. | L5: SERVICIO ESPECIALES | M5: Componente TCS | N5: Componente TLU | O5: Componente TBL | P5: Componente TRT | Q5: CCSA Prest. No Aprov. | R5: Ajuste Decena | S5: Ajuste Recargo Aseo | T5: Intereses Cte Financiac. Aseo | U5: Exonera-Recargo Aseo | V5: Exonera-Ajuste Decena Aseo | W5: Exonera-Recargo Aseo | X5: Exonera-Recargo Aseo | Y5: Intereses Cte Financiac. Aseo | Z5: Rec.Intereses
E6: Vlr Servicio | F6: -17225.21 | G6: -1127.52 | H6: -479 | I6: -209.2 | J6: -3072.3 | K6: -198.78 | L6: 0 | M6: -1743.38 | N6: -1458.17 | O6: -5823.96 | P6: -2788.6 | Q6: -324.3 | R6: 0 | S6: 0 | T6: 0 | U6: 0 | V6: 0 | W6: 0 | X6: 0 | Y6: 0 | Z6: 0
D7: O | E7: Total | F7: -17225.21 | G7: -1127.52 | H7: -479 | I7: -209.2 | J7: -3072.3 | K7: -198.78 | L7: 0 | M7: -1743.38 | N7: -1458.17 | O7: -5823.96 | P7: -2788.6 | Q7: -324.3 | R7: 0 | S7: 0 | T7: 0 | U7: 0 | V7: 0 | W7: 0 | X7: 0 | Y7: 0 | Z7: 0
C8: OCCIDENTE | D8: Total | F8: -17225.21 | G8: -1127.52 | H8: -479 | I8: -209.2 | J8: -3072.3 | K8: -198.78 | L8: 0 | M8: -1743.38 | N8: -1458.17 | O8: -5823.96 | P8: -2788.6 | Q8: -324.3 | R8: 0 | S8: 0 | T8: 0 | U8: 0 | V8: 0 | W8: 0 | X8: 0 | Y8: 0 | Z8: 0
B9: Mes | C9: Total | F9: -17225.21 | G9: -1127.52 | H9: -479 | I9: -209.2 | J9: -3072.3 | K9: -198.78 | L9: 0 | M9: -1743.38 | N9: -1458.17 | O9: -5823.96 | P9: -2788.6 | Q9: -324.3 | R9: 0 | S9: 0 | T9: 0 | U9: 0 | V9: 0 | W9: 0 | X9: 0 | Y9: 0 | Z9: 0
A10: AFaseo | B10: Total | F10: -17225.21 | G10: -1127.52 | H10: -479 | I10: -209.2 | J10: -3072.3 | K10: -198.78 | L10: 0 | M10: -1743.38 | N10: -1458.17 | O10: -5823.96 | P10: -2788.6 | Q10: -324.3 | R10: 0 | S10: 0 | T10: 0 | U10: 0 | V10: 0 | W10: 0 | X10: 0 | Y10: 0 | Z10: 0
E11: Vlr Servicio | F11: 40070 | G11: 1956.64 | H11: 1090.23 | I11: 579.83 | J11: 9781.04 | K11: 359.68 | L11: 0 | M11: 3155.11 | N11: 3024.18 | O11: 14196.18 | P11: 5344.07 | Q11: 586.85 | R11: -3.81 | S11: 0 | T11: 0 | U11: 0 | V11: 0 | W11: 0 | X11: 0 | Y11: 0 | Z11: 0
D12: T | E12: Total | F12: 40070 | G12: 1956.64 | H12: 1090.23 | I12: 579.83 | J12: 9781.04 | K12: 359.68 | L12: 0 | M12: 3155.11 | N12: 3024.18 | O12: 14196.18 | P12: 5344.07 | Q12: 586.85 | R12: -3.81 | S12: 0 | T12: 0 | U12: 0 | V12: 0 | W12: 0 | X12: 0 | Y12: 0 | Z12: 0
C13: OCCIDENTE | D13: Total | F13: 40070 | G13: 1956.64 | H13: 1090.23 | I13: 579.83 | J13: 9781.04 | K13: 359.68 | L13: 0 | M13: 3155.11 | N13: 3024.18 | O13: 14196.18 | P13: 5344.07 | Q13: 586.85 | R13: -3.81 | S13: 0 | T13: 0 | U13: 0 | V13: 0 | W13: 0 | X13: 0 | Y13: 0 | Z13: 0
B14: Aplicacion nuevos x reversion | C14: Total | F14: 40070 | G14: 1956.64 | H14: 1090.23 | I14: 579.83 | J14: 9781.04 | K14: 359.68 | L14: 0 | M14: 3155.11 | N14: 3024.18 | O14: 14196.18 | P14: 5344.07 | Q14: 586.85 | R14: -3.81 | S14: 0 | T14: 0 | U14: 0 | V14: 0 | W14: 0 | X14: 0 | Y14: 0 | Z14: 0
E15: Vlr Servicio | F15: 1.3820608e+10 | G15: 7.2609079e+08 | H15: 4.0461759e+08 | I15: 2.1507678e+08 | J15: 3.251669e+09 | K15: 1.2220472e+08 | L15: 8899784.6 | M15: 1.075307e+09 | N15: 1.0244595e+09 | O15: 4.8175803e+09 | P15: 1.9751857e+09 | Q15: 1.9940879e+08 | R15: 108332.55 | S15: 0 | T15: 0 | U15: 0 | V15: 0 | W15: 0 | X15: 0 | Y15: 0 | Z15: 0
E16: Vlr Intereses | F16: 2775510.5 | G16: 173184.52 | H16: 90025.64 | I16: 45834.86 | J16: 593178.71 | K16: 25683.52 | L16: 1137.27 | M16: 223805.96 | N16: 203715.02 | O16: 915969.2 | P16: 460731.85 | Q16: 41886.91 | R16: 287.49 | S16: 0 | T16: 69.57 | U16: 0 | V16: 0 | W16: 0 | X16: 0 | Y16: 0 | Z16: 0
D17: E | E17: Total | F17: 1.3823384e+10 | G17: 7.2626397e+08 | H17: 4.0470762e+08 | I17: 2.1512261e+08 | J17: 3.2522621e+09 | K17: 1.222304e+08 | L17: 8900921.8 | M17: 1.0755308e+09 | N17: 1.0246632e+09 | O17: 4.8184963e+09 | P17: 1.9756465e+09 | Q17: 1.9945067e+08 | R17: 108620.04 | S17: 0 | T17: 69.57 | U17: 0 | V17: 0 | W17: 0 | X17: 0 | Y17: 0 | Z17: 0
C18: ENEL | D18: Total | F18: 1.3823384e+10 | G18: 7.2626397e+08 | H18: 4.0470762e+08 | I18: 2.1512261e+08 | J18: 3.2522621e+09 | K18: 1.222304e+08 | L18: 8900921.8 | M18: 1.0755308e+09 | N18: 1.0246632e+09 | O18: 4.8184963e+09 | P18: 1.9756465e+09 | Q18: 1.9945067e+08 | R18: 108620.04 | S18: 0 | T18: 69.57 | U18: 0 | V18: 0 | W18: 0 | X18: 0 | Y18: 0 | Z18: 0
E19: Vlr Servicio | F19: 32423892 | G19: 2094905.1 | H19: 1163712.2 | I19: 616207.45 | J19: 6735190.8 | K19: 225631.74 | L19: 0 | M19: 1960612.4 | N19: 2382394.7 | O19: 11164316 | P19: 5712544.2 | Q19: 368628.92 | R19: -251.29 | S19: 0 | T19: 0 | U19: 0 | V19: 0 | W19: 0 | X19: 0 | Y19: 0 | Z19: 0
E20: Vlr Intereses | F20: 103289.61 | G20: 6294.04 | H20: 3163.57 | I20: 1714.05 | J20: 22356.07 | K20: 784.39 | L20: 0 | M20: 6905.15 | N20: 7794.49 | O20: 35934.39 | P20: 17009.19 | Q20: 1280.21 | R20: 53.94 | S20: 0 | T20: 0.12 | U20: 0 | V20: 0 | W20: 0 | X20: 0 | Y20: 0 | Z20: 0
D21: H | E21: Total | F21: 32527182 | G21: 2101199.1 | H21: 1166875.8 | I21: 617921.5 | J21: 6757546.8 | K21: 226416.13 | L21: 0 | M21: 1967517.6 | N21: 2390189.2 | O21: 11200250 | P21: 5729553.4 | Q21: 369909.13 | R21: -197.35 | S21: 0 | T21: 0.12 | U21: 0 | V21: 0 | W21: 0 | X21: 0 | Y21: 0 | Z21: 0
E22: Vlr Servicio | F22: 95497576 | G22: 11573781 | H22: 6315699.4 | I22: 3344369 | J22: 11196862 | K22: 506065.73 | L22: 135643.06 | M22: 4492396.4 | N22: 4604644.3 | O22: 20948918 | P22: 31553963 | Q22: 825687.23 | R22: -452.16 | S22: 0 | T22: 0 | U22: 0 | V22: 0 | W22: 0 | X22: 0 | Y22: 0 | Z22: 0
E23: Vlr Intereses | F23: 165198.17 | G23: 9910.54 | H23: 4898.7 | I23: 2681.95 | J23: 31220.87 | K23: 1643.89 | L23: 0 | M23: 14419.27 | N23: 13134.82 | O23: 57844.58 | P23: 26763.02 | Q23: 2681.01 | R23: -0.59 | S23: 0 | T23: 0.11 | U23: 0 | V23: 0 | W23: 0 | X23: 0 | Y23: 0 | Z23: 0
D24: O | E24: Total | F24: 95662775 | G24: 11583691 | H24: 6320598.1 | I24: 3347050.9 | J24: 11228083 | K24: 507709.62 | L24: 135643.06 | M24: 4506815.7 | N24: 4617779.1 | O24: 21006763 | P24: 31580726 | Q24: 828368.24 | R24: -452.75 | S24: 0 | T24: 0.11 | U24: 0 | V24: 0 | W24: 0 | X24: 0 | Y24: 0 | Z24: 0
E25: Vlr Servicio | F25: 4.5899942e+08 | G25: 72781452 | H25: 40662720 | I25: 21480324 | J25: 34870261 | K25: 898680.48 | L25: 19324973 | M25: 7870315.9 | N25: 10737963 | O25: 50379165 | P25: 1.9852882e+08 | Q25: 1466127.9 | R25: -1383.76 | S25: 0 | T25: 0 | U25: 0 | V25: 0 | W25: 0 | X25: 0 | Y25: 0 | Z25: 0
E26: Vlr Intereses | F26: 882023.55 | G26: 103988.24 | H26: 56003.01 | I26: 29383.84 | J26: 116356.97 | K26: 3816.91 | L26: 48754.08 | M26: 33492.66 | N26: 37349.61 | O26: 164534.39 | P26: 282106.88 | Q26: 6236.98 | R26: -0.08 | S26: 0.03 | T26: 0.03 | U26: 0 | V26: 0 | W26: 0 | X26: 0 | Y26: 0 | Z26: 0
D27: T | E27: Total | F27: 4.5988144e+08 | G27: 72885440 | H27: 40718723 | I27: 21509708 | J27: 34986618 | K27: 902497.39 | L27: 19373727 | M27: 7903808.5 | N27: 10775312 | O27: 50543700 | P27: 1.9881092e+08 | Q27: 1472364.9 | R27: -1383.84 | S27: 0.03 | T27: 0.03 | U27: 0 | V27: 0 | W27: 0 | X27: 0 | Y27: 0 | Z27: 0
C28: OCCIDENTE | D28: Total | F28: 5.880714e+08 | G28: 86570330 | H28: 48206196 | I28: 25474680 | J28: 52972247 | K28: 1636623.1 | L28: 19509370 | M28: 14378142 | N28: 17783281 | O28: 82750712 | P28: 2.361212e+08 | Q28: 2670642.2 | R28: -2033.94 | S28: 0.03 | T28: 0.26 | U28: 0 | V28: 0 | W28: 0 | X28: 0 | Y28: 0 | Z28: 0
B29: Mes | C29: Total | F29: 1.4411455e+10 | G29: 8.128343e+08 | H29: 4.5291382e+08 | I29: 2.4059729e+08 | J29: 3.3052344e+09 | K29: 1.2386702e+08 | L29: 28410292 | M29: 1.0899089e+09 | N29: 1.0424465e+09 | O29: 4.901247e+09 | P29: 2.2117677e+09 | Q29: 2.0212131e+08 | R29: 106586.1 | S29: 0.03 | T29: 69.83 | U29: 0 | V29: 0 | W29: 0 | X29: 0 | Y29: 0 | Z29: 0
A30: Componente | B30: Total | F30: 1.4411495e+10 | G30: 8.1283626e+08 | H30: 4.5291491e+08 | I30: 2.4059787e+08 | J30: 3.3052442e+09 | K30: 1.2386738e+08 | L30: 28410292 | M30: 1089912064 | N30: 1.0424495e+09 | O30: 4.9012612e+09 | P30: 2.211773e+09 | Q30: 2.021219e+08 | R30: 106582.29 | S30: 0.03 | T30: 69.83 | U30: 0 | V30: 0 | W30: 0 | X30: 0 | Y30: 0 | Z30: 0
E31: Subsidio(-)/Contribucion(+) | F31: 1.4524686e+09 | G31: 1.4297322e+08 | H31: 79654038 | I31: 42355359 | J31: 2.4241903e+08 | K31: 9336364.5 | L31: 0 | M31: 80865229 | N31: 78214633 | O31: 3.6849954e+08 | P31: 3.9291835e+08 | Q31: 15232879 | R31: 0 | S31: 0 | T31: 0 | U31: 0 | V31: 0 | W31: 0 | X31: 0 | Y31: 0 | Z31: 0
D32: E | E32: Total | F32: 1.4524686e+09 | G32: 1.4297322e+08 | H32: 79654038 | I32: 42355359 | J32: 2.4241903e+08 | K32: 9336364.5 | L32: 0 | M32: 80865229 | N32: 78214633 | O32: 3.6849954e+08 | P32: 3.9291835e+08 | Q32: 15232879 | R32: 0 | S32: 0 | T32: 0 | U32: 0 | V32: 0 | W32: 0 | X32: 0 | Y32: 0 | Z32: 0
C33: ENEL | D33: Total | F33: 1.4524686e+09 | G33: 1.4297322e+08 | H33: 79654038 | I33: 42355359 | J33: 2.4241903e+08 | K33: 9336364.5 | L33: 0 | M33: 80865229 | N33: 78214633 | O33: 3.6849954e+08 | P33: 3.9291835e+08 | Q33: 15232879 | R33: 0 | S33: 0 | T33: 0 | U33: 0 | V33: 0 | W33: 0 | X33: 0 | Y33: 0 | Z33: 0
E34: Subsidio(-)/Contribucion(+) | F34: 5898418.4 | G34: 881999.26 | H34: 489087.28 | I34: 260611.8 | J34: 636049.85 | K34: 10462.68 | L34: 0 | M34: 91956.29 | N34: 193499.75 | O34: 909344.29 | P34: 2408335.8 | Q34: 17071.35 | R34: 0 | S34: 0 | T34: 0 | U34: 0 | V34: 0 | W34: 0 | X34: 0 | Y34: 0 | Z34: 0
D35: H | E35: Total | F35: 5898418.4 | G35: 881999.26 | H35: 489087.28 | I35: 260611.8 | J35: 636049.85 | K35: 10462.68 | L35: 0 | M35: 91956.29 | N35: 193499.75 | O35: 909344.29 | P35: 2408335.8 | Q35: 17071.35 | R35: 0 | S35: 0 | T35: 0 | U35: 0 | V35: 0 | W35: 0 | X35: 0 | Y35: 0 | Z35: 0
E36: Subsidio(-)/Contribucion(+) | F36: 13098226 | G36: 2940924 | H36: 1605818.6 | I36: 857242.56 | J36: -362631.74 | K36: -26684.44 | L36: 0 | M36: -237386.59 | N36: 21203.47 | O36: 315579.15 | P36: 8027696.6 | Q36: -43535.67 | R36: 0 | S36: 0 | T36: 0 | U36: 0 | V36: 0 | W36: 0 | X36: 0 | Y36: 0 | Z36: 0
D37: O | E37: Total | F37: 13098226 | G37: 2940924 | H37: 1605818.6 | I37: 857242.56 | J37: -362631.74 | K37: -26684.44 | L37: 0 | M37: -237386.59 | N37: 21203.47 | O37: 315579.15 | P37: 8027696.6 | Q37: -43535.67 | R37: 0 | S37: 0 | T37: 0 | U37: 0 | V37: 0 | W37: 0 | X37: 0 | Y37: 0 | Z37: 0
E38: Subsidio(-)/Contribucion(+) | F38: 1.3584738e+08 | G38: 23857697 | H38: 13350084 | I38: 7071037.8 | J38: 8488542.9 | K38: 229087.23 | L38: 0 | M38: 2009970.9 | N38: 2694316.7 | O38: 12601163 | P38: 65171708 | Q38: 373777.59 | R38: 0 | S38: 0 | T38: 0 | U38: 0 | V38: 0 | W38: 0 | X38: 0 | Y38: 0 | Z38: 0
D39: T | E39: Total | F39: 1.3584738e+08 | G39: 23857697 | H39: 13350084 | I39: 7071037.8 | J39: 8488542.9 | K39: 229087.23 | L39: 0 | M39: 2009970.9 | N39: 2694316.7 | O39: 12601163 | P39: 65171708 | Q39: 373777.59 | R39: 0 | S39: 0 | T39: 0 | U39: 0 | V39: 0 | W39: 0 | X39: 0 | Y39: 0 | Z39: 0
C40: OCCIDENTE | D40: Total | F40: 1.5484403e+08 | G40: 27680620 | H40: 15444990 | I40: 8188892.2 | J40: 8761961 | K40: 212865.47 | L40: 0 | M40: 1864540.6 | N40: 2909020 | O40: 13826086 | P40: 75607740 | Q40: 347313.27 | R40: 0 | S40: 0 | T40: 0 | U40: 0 | V40: 0 | W40: 0 | X40: 0 | Y40: 0 | Z40: 0
B41: Mes | C41: Total | F41: 1.6073127e+09 | G41: 1.7065384e+08 | H41: 95099028 | I41: 50544251 | J41: 2.5118099e+08 | K41: 9549230 | L41: 0 | M41: 82729770 | N41: 81123653 | O41: 3.8232563e+08 | P41: 4.6852609e+08 | Q41: 15580192 | R41: 0 | S41: 0 | T41: 0 | U41: 0 | V41: 0 | W41: 0 | X41: 0 | Y41: 0 | Z41: 0
A42: Subs/Cont | B42: Total | F42: 1.6073127e+09 | G42: 1.7065384e+08 | H42: 95099028 | I42: 50544251 | J42: 2.5118099e+08 | K42: 9549230 | L42: 0 | M42: 82729770 | N42: 81123653 | O42: 3.8232563e+08 | P42: 4.6852609e+08 | Q42: 15580192 | R42: 0 | S42: 0 | T42: 0 | U42: 0 | V42: 0 | W42: 0 | X42: 0 | Y42: 0 | Z42: 0
A43: Total | F43: 1.6018791e+10 | G43: 9.8348897e+08 | H43: 5.4801346e+08 | I43: 2.9114192e+08 | J43: 3.5564221e+09 | K43: 1.3341642e+08 | L43: 28410292 | M43: 1.1726401e+09 | N43: 1.1235717e+09 | O43: 5.283581e+09 | P43: 2.6802963e+09 | Q43: 2.1770177e+08 | R43: 106582.29 | S43: 0.03 | T43: 69.83 | U43: 0 | V43: 0 | W43: 0 | X43: 0 | Y43: 0 | Z43: 0
C46: TOTAL | D46: OPORTUNO | E46: Total | F46: =F29+F41+F9-L9-L29 -> 1.599034e+10 | G46: =G29+G9 -> 8.1283317e+08 | H46: =H29+H9 -> 4.5291334e+08 | I46: =I29+I9 -> 2.4059708e+08 | J46: =J29+J9 -> 3.3052313e+09 | K46: =K29+K9 -> 1.2386683e+08 | L46: =L29+L9 -> 28410292 | M46: =M29+M9 -> 1.0899072e+09 | N46: =N29+N9 -> 1.042445e+09 | ... AP46: =AP29+AP9 -> 0
E47: Subsidio(-)/Contribucion(+) | F47: =F41 -> 1.6073127e+09
D48: EXTEMPORANEO | E48: Total | F48: =F14-L14 -> 40070 | G48: =G14 -> 1956.64 | H48: =H14 -> 1090.23 | I48: =I14 -> 579.83 | J48: =J14 -> 9781.04 | K48: =K14 -> 359.68 | L48: =L14 -> 0 | M48: =M14 -> 3155.11 | N48: =N14 -> 3024.18 | ... AP48: =AP14 -> 0
E49: Subsidio(-)/Contribucion(+) | F49: 0
C51: RECIPROCIDAD | D51: OPORTUNO | E51: Total | F51: 0 | G51: 0 | H51: 0 | I51: 0 | J51: 0 | K51: 0 | L51: 0 | M51: 0 | N51: 0 | O51: 0 | P51: 0 | Q51: 0 | R51: 0 | S51: 0 | T51: 0 | U51: 0 | V51: 0 | W51: 0 | X51: 0 | Y51: 0 | Z51: 0 | AA51: 0 | AB51: 0 | AC51: 0 | AD51: 0 | AE51: 0 | AF51: 0 | AG51: 0 | AH51: 0 | AI51: 0 | AJ51: 0 | AK51: 0 | AL51: 0 | AM51: 0 | AN51: 0 | AO51: 0 | AP51: 0
E52: Subsidio(-)/Contribucion(+) | F52: 0
D53: EXTEMPORANEO | E53: Total | F53: 0 | G53: 0 | H53: 0 | I53: 0 | J53: 0 | K53: 0 | L53: 0 | M53: 0 | N53: 0 | O53: 0 | P53: 0 | Q53: 0 | R53: 0 | S53: 0 | T53: 0 | U53: 0 | V53: 0 | W53: 0 | X53: 0 | Y53: 0 | Z53: 0 | AA53: 0 | AB53: 0 | AC53: 0 | AD53: 0 | AE53: 0 | AF53: 0 | AG53: 0 | AH53: 0 | AI53: 0 | AJ53: 0 | AK53: 0 | AL53: 0 | AM53: 0 | AN53: 0 | AO53: 0 | AP53: 0
E54: Subsidio(-)/Contribucion(+) | F54: 0
C56: ENEL | D56: OPORTUNO | E56: Total | F56: =F33+F18-L18 -> 1.5266951e+10 | G56: =G18 -> 7.2626397e+08 | H56: =H18 -> 4.0470762e+08 | I56: =I18 -> 2.1512261e+08 | J56: =J18 -> 3.2522621e+09 | K56: =K18 -> 1.222304e+08 | L56: =L18 -> 8900921.8 | M56: =M18 -> 1.0755308e+09 | N56: =N18 -> 1.0246632e+09 | ... AP56: =AP18 -> 0
E57: Subsidio(-)/Contribucion(+) | F57: =F33 -> 1.4524686e+09
D58: EXTEMPORANEO | E58: Total | F58: 0 | G58: 0 | H58: 0 | I58: 0 | J58: 0 | K58: 0 | L58: 0 | M58: 0 | N58: 0 | O58: 0 | P58: 0 | Q58: 0 | R58: 0 | S58: 0 | T58: 0 | U58: 0 | V58: 0 | W58: 0 | X58: 0 | Y58: 0 | Z58: 0 | AA58: 0 | AB58: 0 | AC58: 0 | AD58: 0 | AE58: 0 | AF58: 0 | AG58: 0 | AH58: 0 | AI58: 0 | AJ58: 0 | AK58: 0 | AL58: 0 | AM58: 0 | AN58: 0 | AO58: 0 | AP58: 0
E59: Subsidio(-)/Contribucion(+) | F59: 0
C61: ENERBIT | D61: OPORTUNO | E61: Total | F61: 0 | G61: 0 | H61: 0 | I61: 0 | J61: 0 | K61: 0 | L61: 0 | M61: 0 | N61: 0 | O61: 0 | P61: 0 | Q61: 0 | R61: 0 | S61: 0 | T61: 0 | U61: 0 | V61: 0 | W61: 0 | X61: 0 | Y61: 0 | Z61: 0 | AA61: 0 | AB61: 0 | AC61: 0 | AD61: 0 | AE61: 0 | AF61: 0 | AG61: 0 | AH61: 0 | AI61: 0 | AJ61: 0 | AK61: 0 | AL61: 0 | AM61: 0 | AN61: 0 | AO61: 0
E62: Subsidio(-)/Contribucion(+) | F62: 0
D63: EXTEMPORANEO | E63: Total | F63: 0 | G63: 0 | H63: 0 | I63: 0 | J63: 0 | K63: 0 | L63: 0 | M63: 0 | N63: 0 | O63: 0 | P63: 0 | Q63: 0 | R63: 0 | S63: 0 | T63: 0 | U63: 0 | V63: 0 | W63: 0 | X63: 0 | Y63: 0 | Z63: 0 | AA63: 0 | AB63: 0 | AC63: 0 | AD63: 0 | AE63: 0 | AF63: 0 | AG63: 0 | AH63: 0 | AI63: 0 | AJ63: 0 | AK63: 0 | AL63: 0 | AM63: 0 | AN63: 0 | AO63: 0
E64: Subsidio(-)/Contribucion(+) | F64: 0
C66: OCCIDENTE | D66: OPORTUNO | E66: Total | F66: =F40+F28+F8-L8-L28 -> 7.2338883e+08 | G66: =G28+G8 -> 86569203 | H66: =H28+H8 -> 48205717 | I66: =I28+I8 -> 25474471 | J66: =J28+J8 -> 52969175 | K66: =K28+K8 -> 1636424.4 | L66: =L28+L8 -> 19509370 | M66: =M28+M8 -> 14376398 | N66: =N28+N8 -> 17781822 | ... AP66: =AP28+AP8 -> 0
E67: Subsidio(-)/Contribucion(+) | F67: =F40 -> 1.5484403e+08
D68: EXTEMPORANEO | E68: Total | F68: =F13-L13 -> 40070 | G68: =G13 -> 1956.64 | H68: =H13 -> 1090.23 | I68: =I13 -> 579.83 | J68: =J13 -> 9781.04 | K68: =K13 -> 359.68 | L68: =L13 -> 0 | M68: =M13 -> 3155.11 | N68: =N13 -> 3024.18 | ... AP68: =AP13 -> 0
E69: Subsidio(-)/Contribucion(+) | F69: 0
C71: CIUDAD LIMPIA-ACUEDUCTO | D71: OPORTUNO | E71: Total | F71: 0 | G71: 0 | H71: 0 | I71: 0 | J71: 0 | K71: 0 | L71: 0 | M71: 0 | N71: 0 | O71: 0 | P71: 0 | Q71: 0 | R71: 0 | S71: 0 | T71: 0 | U71: 0 | V71: 0 | W71: 0 | X71: 0 | Y71: 0 | Z71: 0 | AA71: 0 | AB71: 0 | AC71: 0 | AD71: 0 | AE71: 0 | AF71: 0 | AG71: 0 | AH71: 0 | AI71: 0 | AJ71: 0 | AK71: 0 | AL71: 0 | AM71: 0 | AN71: 0 | AO71: 0 | AP71: 0
E72: Subsidio(-)/Contribucion(+) | F72: 0
D73: EXTEMPORANEO | E73: Total | F73: 0 | G73: 0 | H73: 0 | I73: 0 | J73: 0 | K73: 0 | L73: 0 | M73: 0 | N73: 0 | O73: 0 | P73: 0 | Q73: 0 | R73: 0 | S73: 0 | T73: 0 | U73: 0 | V73: 0 | W73: 0 | X73: 0 | Y73: 0 | Z73: 0 | AA73: 0 | AB73: 0 | AC73: 0 | AD73: 0 | AE73: 0 | AF73: 0 | AG73: 0 | AH73: 0 | AI73: 0 | AJ73: 0 | AK73: 0 | AL73: 0 | AM73: 0 | AN73: 0 | AO73: 0 | AP73: 0
E74: Subsidio(-)/Contribucion(+) | F74: 0
D76: AFaseo | E76: Total | F76: =F10 -> -17225.21 | G76: =G10 -> -1127.52 | H76: =H10 -> -479 | I76: =I10 -> -209.2 | J76: =J10 -> -3072.3 | K76: =K10 -> -198.78 | L76: =L10 -> 0 | M76: =M10 -> -1743.38 | ... AP76: =AP10 -> 0
B79: LIME
F80: Total | G80: Componente TDF | H80: Componente TTL | I80: Componente TVIAT | J80: Aprovechamiento | K80: CCSA Prest.Aprov. | L80: SERVICIO ESPECIALES | M80: Componente TCS | N80: Componente TLU | O80: Componente TBL | P80: Componente TRT | Q80: CCSA Prest. No Aprov. | R80: Ajuste Decena | S80: Ajuste Recargo Aseo | T80: Intereses Cte Financiac. Aseo | U80: Exonera-Recargo Aseo | V80: Exonera-Ajuste Decena Aseo | W80: Exonera-Recargo Aseo | X80: Exonera-Recargo Aseo | Y80: Intereses Cte Financiac. Aseo | Z80: Rec.Intereses
E81: Vlr Servicio | F81: -959960.05 | G81: -83596.03 | H81: -35513.93 | I81: -15509.04 | J81: -193649.93 | K81: -8005.36 | L81: 0 | M81: -70404.88 | N81: -88042.57 | O81: -295676.04 | P81: -156499.38 | Q81: -13062.89 | R81: 0 | S81: 0 | T81: 0 | U81: 0 | V81: 0 | W81: 0 | X81: 0 | Y81: 0 | Z81: 0
D82: E | E82: Total | F82: -959960.05 | G82: -83596.03 | H82: -35513.93 | I82: -15509.04 | J82: -193649.93 | K82: -8005.36 | L82: 0 | M82: -70404.88 | N82: -88042.57 | O82: -295676.04 | P82: -156499.38 | Q82: -13062.89 | R82: 0 | S82: 0 | T82: 0 | U82: 0 | V82: 0 | W82: 0 | X82: 0 | Y82: 0 | Z82: 0
C83: ENEL | D83: Total | F83: -959960.05 | G83: -83596.03 | H83: -35513.93 | I83: -15509.04 | J83: -193649.93 | K83: -8005.36 | L83: 0 | M83: -70404.88 | N83: -88042.57 | O83: -295676.04 | P83: -156499.38 | Q83: -13062.89 | R83: 0 | S83: 0 | T83: 0 | U83: 0 | V83: 0 | W83: 0 | X83: 0 | Y83: 0 | Z83: 0
E84: Vlr Servicio | F84: -7651.9 | G84: -673.86 | H84: -286.29 | I84: -125.01 | J84: -1539.2 | K84: -63.42 | L84: 0 | M84: -556.32 | N84: -697.37 | O84: -2342.4 | P84: -1264.56 | Q84: -103.47 | R84: 0 | S84: 0 | T84: 0 | U84: 0 | V84: 0 | W84: 0 | X84: 0 | Y84: 0 | Z84: 0
D85: H | E85: Total | F85: -7651.9 | G85: -673.86 | H85: -286.29 | I85: -125.01 | J85: -1539.2 | K85: -63.42 | L85: 0 | M85: -556.32 | N85: -697.37 | O85: -2342.4 | P85: -1264.56 | Q85: -103.47 | R85: 0 | S85: 0 | T85: 0 | U85: 0 | V85: 0 | W85: 0 | X85: 0 | Y85: 0 | Z85: 0
E86: Vlr Servicio | F86: -25906.78 | G86: -2297.68 | H86: -976.11 | I86: -426.3 | J86: -5194.83 | K86: -214.04 | L86: 0 | M86: -1877.6 | N86: -2353.6 | O86: -7905.6 | P86: -4311.78 | Q86: -349.24 | R86: 0 | S86: 0 | T86: 0 | U86: 0 | V86: 0 | W86: 0 | X86: 0 | Y86: 0 | Z86: 0
D87: O | E87: Total | F87: -25906.78 | G87: -2297.68 | H87: -976.11 | I87: -426.3 | J87: -5194.83 | K87: -214.04 | L87: 0 | M87: -1877.6 | N87: -2353.6 | O87: -7905.6 | P87: -4311.78 | Q87: -349.24 | R87: 0 | S87: 0 | T87: 0 | U87: 0 | V87: 0 | W87: 0 | X87: 0 | Y87: 0 | Z87: 0
C88: OCCIDENTE | D88: Total | F88: -33558.68 | G88: -2971.54 | H88: -1262.4 | I88: -551.31 | J88: -6734.03 | K88: -277.46 | L88: 0 | M88: -2433.92 | N88: -3050.97 | O88: -10248 | P88: -5576.34 | Q88: -452.71 | R88: 0 | S88: 0 | T88: 0 | U88: 0 | V88: 0 | W88: 0 | X88: 0 | Y88: 0 | Z88: 0
B89: Mes | C89: Total | F89: -993518.73 | G89: -86567.57 | H89: -36776.33 | I89: -16060.35 | J89: -200383.96 | K89: -8282.82 | L89: 0 | M89: -72838.8 | N89: -91093.54 | O89: -305924.04 | P89: -162075.72 | Q89: -13515.6 | R89: 0 | S89: 0 | T89: 0 | U89: 0 | V89: 0 | W89: 0 | X89: 0 | Y89: 0 | Z89: 0
A90: AFaseo | B90: Total | F90: -993518.73 | G90: -86567.57 | H90: -36776.33 | I90: -16060.35 | J90: -200383.96 | K90: -8282.82 | L90: 0 | M90: -72838.8 | N90: -91093.54 | O90: -305924.04 | P90: -162075.72 | Q90: -13515.6 | R90: 0 | S90: 0 | T90: 0 | U90: 0 | V90: 0 | W90: 0 | X90: 0 | Y90: 0 | Z90: 0
E91: Vlr Servicio | F91: 20283554 | G91: 1111927.3 | H91: 624122.92 | I91: 331325.92 | J91: 5227826.4 | K91: 136781.71 | L91: 0 | M91: 1200936.3 | N91: 1600252.6 | O91: 7637862.9 | P91: 2189262.9 | Q91: 223377.17 | R91: -122.09 | S91: 0 | T91: 0 | U91: 0 | V91: 0 | W91: 0 | X91: 0 | Y91: 0 | Z91: 0
E92: Vlr Intereses | F92: 526203.15 | G92: 45415.85 | H92: 24830.95 | I92: 13349.41 | J92: 116506.52 | K92: 2879.8 | L92: 0 | M92: 25262.63 | N92: 35551.81 | O92: 166823.52 | P92: 90885.25 | Q92: 4698.7 | R92: -1.29 | S92: 0 | T92: 0 | U92: 0 | V92: 0 | W92: 0 | X92: 0 | Y92: 0 | Z92: 0
D93: E | E93: Total | F93: 20809757 | G93: 1157343.2 | H93: 648953.87 | I93: 344675.33 | J93: 5344332.9 | K93: 139661.51 | L93: 0 | M93: 1226198.9 | N93: 1635804.4 | O93: 7804686.4 | P93: 2280148.2 | Q93: 228075.87 | R93: -123.38 | S93: 0 | T93: 0 | U93: 0 | V93: 0 | W93: 0 | X93: 0 | Y93: 0 | Z93: 0
C94: ENEL | D94: Total | F94: 20809757 | G94: 1157343.2 | H94: 648953.87 | I94: 344675.33 | J94: 5344332.9 | K94: 139661.51 | L94: 0 | M94: 1226198.9 | N94: 1635804.4 | O94: 7804686.4 | P94: 2280148.2 | Q94: 228075.87 | R94: -123.38 | S94: 0 | T94: 0 | U94: 0 | V94: 0 | W94: 0 | X94: 0 | Y94: 0 | Z94: 0
E95: Vlr Servicio | F95: 535407.43 | G95: 24186.79 | H95: 13571.57 | I95: 7188.58 | J95: 127199.44 | K95: 4331.32 | L95: 0 | M95: 37993.92 | N95: 38162.29 | O95: 227538.79 | P95: 48172.01 | Q95: 7066.9 | R95: -4.18 | S95: 0 | T95: 0 | U95: 0 | V95: 0 | W95: 0 | X95: 0 | Y95: 0 | Z95: 0
D96: H | E96: Total | F96: 535407.43 | G96: 24186.79 | H96: 13571.57 | I96: 7188.58 | J96: 127199.44 | K96: 4331.32 | L96: 0 | M96: 37993.92 | N96: 38162.29 | O96: 227538.79 | P96: 48172.01 | Q96: 7066.9 | R96: -4.18 | S96: 0 | T96: 0 | U96: 0 | V96: 0 | W96: 0 | X96: 0 | Y96: 0 | Z96: 0
E97: Vlr Servicio | F97: 807630.46 | G97: 42543.54 | H97: 24154.99 | I97: 16130.43 | J97: 196483.81 | K97: 6280.06 | L97: 0 | M97: 46445.85 | N97: 57673.1 | O97: 315970.56 | P97: 92573.74 | Q97: 9352.13 | R97: 22.25 | S97: 0 | T97: 0 | U97: 0 | V97: 0 | W97: 0 | X97: 0 | Y97: 0 | Z97: 0
E98: Vlr Intereses | F98: -3314.17 | G98: -505.6 | H98: -284.11 | I98: -149.05 | J98: -401.57 | K98: -7.96 | L98: 0 | M98: -70.24 | N98: -146.01 | O98: -735.95 | P98: -1000.68 | Q98: -13.1 | R98: 0.04 | S98: 0.06 | T98: 0 | U98: 0 | V98: 0 | W98: 0 | X98: 0 | Y98: 0 | Z98: 0
D99: O | E99: Total | F99: 804316.29 | G99: 42037.94 | H99: 23870.88 | I99: 15981.38 | J99: 196082.24 | K99: 6272.1 | L99: 0 | M99: 46375.61 | N99: 57527.09 | O99: 315234.61 | P99: 91573.06 | Q99: 9339.03 | R99: 22.29 | S99: 0.06 | T99: 0 | U99: 0 | V99: 0 | W99: 0 | X99: 0 | Y99: 0 | Z99: 0
C100: OCCIDENTE | D100: Total | F100: 1339723.7 | G100: 66224.73 | H100: 37442.45 | I100: 23169.96 | J100: 323281.68 | K100: 10603.42 | L100: 0 | M100: 84369.53 | N100: 95689.38 | O100: 542773.4 | P100: 139745.07 | Q100: 16405.93 | R100: 18.11 | S100: 0.06 | T100: 0 | U100: 0 | V100: 0 | W100: 0 | X100: 0 | Y100: 0 | Z100: 0
B101: Aplicacion nuevos x reversion | C101: Total | F101: 22149481 | G101: 1223567.9 | H101: 686396.32 | I101: 367845.29 | J101: 5667614.6 | K101: 150264.93 | L101: 0 | M101: 1310568.5 | N101: 1731493.8 | O101: 8347459.8 | P101: 2419893.2 | Q101: 244481.8 | R101: -105.27 | S101: 0.06 | T101: 0 | U101: 0 | V101: 0 | W101: 0 | X101: 0 | Y101: 0 | Z101: 0
E102: Vlr Servicio | F102: 2.5851948e+10 | G102: 1.4367824e+09 | H102: 7.9546324e+08 | I102: 4.2145414e+08 | J102: 6.4994387e+09 | K102: 2.2970079e+08 | L102: 23565663 | M102: 2.0128714e+09 | N102: 1.9716262e+09 | O102: 9.258863e+09 | P102: 2.8268781e+09 | Q102: 3.7514734e+08 | R102: 157224.15 | S102: 0 | T102: 0 | U102: 0 | V102: 0 | W102: 0 | X102: 0 | Y102: 0 | Z102: 0
E103: Vlr Intereses | F103: 99110271 | G103: 11931368 | H103: 5570660.5 | I103: 2431228.6 | J103: 18080591 | K103: 634164.61 | L103: 17997.02 | M103: 5560988.8 | N103: 6623487.2 | O103: 23793880 | P103: 23428727 | Q103: 1034817.9 | R103: 2403.55 | S103: -39.87 | T103: 0.46 | U103: 0 | V103: 0 | W103: 0 | X103: 0 | Y103: 0 | Z103: -2.54
D104: E | E104: Total | F104: 2.5951058e+10 | G104: 1.4487137e+09 | H104: 8.010339e+08 | I104: 4.2388536e+08 | J104: 6.5175193e+09 | K104: 2.3033495e+08 | L104: 23583660 | M104: 2.0184324e+09 | N104: 1.9782497e+09 | O104: 9.2826568e+09 | P104: 2.8503068e+09 | Q104: 3.7618216e+08 | R104: 159627.7 | S104: -39.87 | T104: 0.46 | U104: 0 | V104: 0 | W104: 0 | X104: 0 | Y104: 0 | Z104: -2.54
C105: ENEL | D105: Total | F105: 2.5951058e+10 | G105: 1.4487137e+09 | H105: 8.010339e+08 | I105: 4.2388536e+08 | J105: 6.5175193e+09 | K105: 2.3033495e+08 | L105: 23583660 | M105: 2.0184324e+09 | N105: 1.9782497e+09 | O105: 9.2826568e+09 | P105: 2.8503068e+09 | Q105: 3.7618216e+08 | R105: 159627.7 | S105: -39.87 | T105: 0.46 | U105: 0 | V105: 0 | W105: 0 | X105: 0 | Y105: 0 | Z105: -2.54
E106: Vlr Servicio | F106: 107199.99 | G106: 3814.07 | H106: 2013.23 | I106: 1075.31 | J106: 31633.35 | K106: 963.04 | L106: 0 | M106: 8447.81 | N106: 8872.4 | O106: 41178.56 | P106: 7627.22 | Q106: 1571.3 | R106: 3.7 | S106: 0 | T106: 0 | U106: 0 | V106: 0 | W106: 0 | X106: 0 | Y106: 0 | Z106: 0
E107: Vlr Intereses | F107: 54.32 | G107: 1.66 | H107: 0.84 | I107: 0.45 | J107: 16.67 | K107: 0.48 | L107: 0 | M107: 4.2 | N107: 4.63 | O107: 21.26 | P107: 3.35 | Q107: 0.78 | R107: 0 | S107: 0 | T107: 0 | U107: 0 | V107: 0 | W107: 0 | X107: 0 | Y107: 0 | Z107: 0
D108: 1 | E108: Total | F108: 107254.31 | G108: 3815.73 | H108: 2014.07 | I108: 1075.76 | J108: 31650.02 | K108: 963.52 | L108: 0 | M108: 8452.01 | N108: 8877.03 | O108: 41199.82 | P108: 7630.57 | Q108: 1572.08 | R108: 3.7 | S108: 0 | T108: 0 | U108: 0 | V108: 0 | W108: 0 | X108: 0 | Y108: 0 | Z108: 0
E109: Vlr Servicio | F109: 127520.62 | G109: 12427.88 | H109: 6940.45 | I109: 3682.61 | J109: 25758.06 | K109: 896.24 | L109: 0 | M109: 7861.73 | N109: 7686.33 | O109: 36125.75 | P109: 24674.37 | Q109: 1462.28 | R109: 4.92 | S109: 0 | T109: 0 | U109: 0 | V109: 0 | W109: 0 | X109: 0 | Y109: 0 | Z109: 0
E110: Vlr Intereses | F110: 801.46 | G110: 76.94 | H110: 43.44 | I110: 22.8 | J110: 170.64 | K110: 5.56 | L110: 0 | M110: 48.79 | N110: 47.34 | O110: 224.13 | P110: 152.75 | Q110: 9.07 | R110: 0 | S110: 0 | T110: 0 | U110: 0 | V110: 0 | W110: 0 | X110: 0 | Y110: 0 | Z110: 0
D111: 2 | E111: Total | F111: 128322.08 | G111: 12504.82 | H111: 6983.89 | I111: 3705.41 | J111: 25928.7 | K111: 901.8 | L111: 0 | M111: 7910.52 | N111: 7733.67 | O111: 36349.88 | P111: 24827.12 | Q111: 1471.35 | R111: 4.92 | S111: 0 | T111: 0 | U111: 0 | V111: 0 | W111: 0 | X111: 0 | Y111: 0 | Z111: 0
E112: Vlr Servicio | F112: 2484432.4 | G112: 117509.34 | H112: 65623.65 | I112: 35147.19 | J112: 651490.81 | K112: 23203.85 | L112: 0 | M112: 195200.05 | N112: 196745.88 | O112: 931730.47 | P112: 231035.27 | Q112: 36732.97 | R112: 12.92 | S112: 0 | T112: 0 | U112: 0 | V112: 0 | W112: 0 | X112: 0 | Y112: 0 | Z112: 0
E113: Vlr Intereses | F113: 3226.7 | G113: 166.13 | H113: 93.91 | I113: 48.63 | J113: 856.89 | K113: 21.56 | L113: 0 | M113: 195.95 | N113: 262.5 | O113: 1212.37 | P113: 333.63 | Q113: 35.19 | R113: -0.06 | S113: 0 | T113: 0 | U113: 0 | V113: 0 | W113: 0 | X113: 0 | Y113: 0 | Z113: 0
...

Sheet Rem. Anticipos R2
B1: PROMOAMBIENTAL
E2: Total | F2: Componente TDF | G2: Componente TTL | H2: Componente TVIAT | I2: Aprovechamiento | J2: CCSA Prest.Aprov. | K2: Especiales | L2: Componente TCS | M2: Componente TLU | N2: Componente TBL | O2: Componente TRT | P2: CCSA Prest. No Aprov. | Q2: Deb/Cred | R2: Deb/Cred-otros
D3: Vlr Servicio | E3: 55834234 | F3: 3094647.4 | G3: 1682765.2 | H3: 530662.91 | I3: 14660029 | J3: 506485.61 | K3: 0 | L3: 5081668.9 | M3: 4157674.5 | N3: 16968786 | O3: 8430869 | P3: 720682.78 | Q3: -37.03 | R3: 0
D4: Vlr Intereses | E4: 3707.99 | F4: 156.46 | G4: 86.98 | H4: 46.44 | I4: 813.79 | J4: 38.21 | K4: 0 | L4: 335.01 | M4: 322.78 | N4: 1416.95 | O4: 429 | P4: 62.35 | Q4: 0.02 | R4: 0
C5: E | D5: Total | E5: 55837942 | F5: 3094803.9 | G5: 1682852.2 | H5: 530709.35 | I5: 14660843 | J5: 506523.82 | K5: 0 | L5: 5082003.9 | M5: 4157997.2 | N5: 16970203 | O5: 8431298 | P5: 720745.13 | Q5: -37.01 | R5: 0
B6: ENEL | C6: Total | E6: 55837942 | F6: 3094803.9 | G6: 1682852.2 | H6: 530709.35 | I6: 14660843 | J6: 506523.82 | K6: 0 | L6: 5082003.9 | M6: 4157997.2 | N6: 16970203 | O6: 8431298 | P6: 720745.13 | Q6: -37.01 | R6: 0
D7: Vlr Servicio | E7: 2493179.1 | F7: 105458.8 | G7: 60546.26 | H7: 25821.53 | I7: 658727.02 | J7: 20098.4 | K7: 0 | L7: 179573.87 | M7: 217698.78 | N7: 900619.58 | O7: 296715.15 | P7: 27929.76 | Q7: -10 | R7: 0
D8: Vlr Intereses | E8: 732.75 | F8: 36.24 | G8: 18.73 | H8: 10.23 | I8: 195.31 | J8: 4.71 | K8: 0 | L8: 41.31 | M8: 56.94 | N8: 262.11 | O8: 99.47 | P8: 7.68 | Q8: 0.02 | R8: 0
C9: H | D9: Total | E9: 2493911.9 | F9: 105495.04 | G9: 60564.99 | H9: 25831.76 | I9: 658922.33 | J9: 20103.11 | K9: 0 | L9: 179615.18 | M9: 217755.72 | N9: 900881.69 | O9: 296814.62 | P9: 27937.44 | Q9: -9.98 | R9: 0
D10: Vlr Servicio | E10: 2223198.6 | F10: 147874.33 | G10: 83270.12 | H10: 44538.96 | I10: 324582.72 | J10: 14764.44 | K10: 0 | L10: 134454.14 | M10: 151788.8 | N10: 653436.37 | O10: 644060.97 | P10: 24424.93 | Q10: 2.78 | R10: 0
D11: Vlr Intereses | E11: 676.52 | F11: 18.42 | G11: 9.52 | H11: 5.19 | I11: 108.14 | J11: 12.59 | K11: 0 | L11: 109.25 | M11: 100.54 | N11: 242.05 | O11: 50.3 | P11: 20.52 | Q11: 0 | R11: 0
C12: O | D12: Total | E12: 2223875.1 | F12: 147892.75 | G12: 83279.64 | H12: 44544.15 | I12: 324690.86 | J12: 14777.03 | K12: 0 | L12: 134563.39 | M12: 151889.34 | N12: 653678.42 | O12: 644111.27 | P12: 24445.45 | Q12: 2.78 | R12: 0
D13: Vlr Servicio | E13: 20285169 | F13: 2616611 | G13: 1450507.4 | H13: 764170.91 | I13: 2505995.4 | J13: 57900.44 | K13: 1030668 | L13: 683264.29 | M13: 755299.62 | N13: 2961183 | O13: 7368849.4 | P13: 90741.67 | Q13: -22.49 | R13: 0
D14: Vlr Intereses | E14: 22217.37 | F14: 1381.19 | G14: 639.86 | H14: 371.8 | I14: 5346.65 | J14: 194.18 | K14: 0 | L14: 1703.91 | M14: 1518.67 | N14: 6962.94 | O14: 3781.33 | P14: 316.83 | Q14: 0.01 | R14: 0
C15: T | D15: Total | E15: 20307386 | F15: 2617992.2 | G15: 1451147.2 | H15: 764542.71 | I15: 2511342.1 | J15: 58094.62 | K15: 1030668 | L15: 684968.2 | M15: 756818.29 | N15: 2968145.9 | O15: 7372630.7 | P15: 91058.5 | Q15: -22.48 | R15: 0
B16: OCCIDENTE | C16: Total | E16: 25025173 | F16: 2871380 | G16: 1594991.9 | H16: 834918.62 | I16: 3494955.2 | J16: 92974.76 | K16: 1030668 | L16: 999146.77 | M16: 1126463.4 | N16: 4522706 | O16: 8313556.6 | P16: 143441.39 | Q16: -29.68 | R16: 0
A17: Componente | B17: Total | E17: 80863115 | F17: 5966183.8 | G17: 3277844.1 | H17: 1365628 | I17: 18155798 | J17: 599498.58 | K17: 1030668 | L17: 6081150.7 | M17: 5284460.6 | N17: 21492909 | O17: 16744855 | P17: 864186.52 | Q17: -66.69 | R17: 0
D18: Subsidio(-)/Contribucion(+) | E18: -19207014 | F18: -617716.24 | G18: -328873.02 | H18: -172186.54 | I18: -5306584.7 | J18: -192729.4 | K18: 0 | L18: -1649344.1 | M18: -1543787.5 | N18: -7413085.7 | O18: -1667377.9 | P18: -315328.54 | Q18: 0 | R18: 0
C19: E | D19: Total | E19: -19207014 | F19: -617716.24 | G19: -328873.02 | H19: -172186.54 | I19: -5306584.7 | J19: -192729.4 | K19: 0 | L19: -1649344.1 | M19: -1543787.5 | N19: -7413085.7 | O19: -1667377.9 | P19: -315328.54 | Q19: 0 | R19: 0
B20: ENEL | C20: Total | E20: -19207014 | F20: -617716.24 | G20: -328873.02 | H20: -172186.54 | I20: -5306584.7 | J20: -192729.4 | K20: 0 | L20: -1649344.1 | M20: -1543787.5 | N20: -7413085.7 | O20: -1667377.9 | P20: -315328.54 | Q20: 0 | R20: 0
D21: Subsidio(-)/Contribucion(+) | E21: -372078.25 | F21: -10720.26 | G21: -5973.28 | H21: -4443.92 | I21: -103772.07 | J21: -4179.18 | K21: 0 | L21: -33851.55 | M21: -33425.82 | N21: -139613.89 | O21: -29279.68 | P21: -6818.6 | Q21: 0 | R21: 0
C22: H | D22: Total | E22: -372078.25 | F22: -10720.26 | G22: -5973.28 | H22: -4443.92 | I22: -103772.07 | J22: -4179.18 | K22: 0 | L22: -33851.55 | M22: -33425.82 | N22: -139613.89 | O22: -29279.68 | P22: -6818.6 | Q22: 0 | R22: 0
D23: Subsidio(-)/Contribucion(+) | E23: 561663.57 | F23: 85215.3 | G23: 47452.88 | H23: 25221.76 | I23: 57091.22 | J23: 1115.44 | K23: 0 | L23: 8666.79 | M23: 16123.86 | N23: 85989.95 | O23: 232941.23 | P23: 1845.14 | Q23: 0 | R23: 0
C24: O | D24: Total | E24: 561663.57 | F24: 85215.3 | G24: 47452.88 | H24: 25221.76 | I24: 57091.22 | J24: 1115.44 | K24: 0 | L24: 8666.79 | M24: 16123.86 | N24: 85989.95 | O24: 232941.23 | P24: 1845.14 | Q24: 0 | R24: 0
D25: Subsidio(-)/Contribucion(+) | E25: 6792970.1 | F25: 1198577.8 | G25: 647576.97 | H25: 267551.01 | I25: 336837.22 | J25: 10835.7 | K25: 0 | L25: 130771.96 | M25: 148376.47 | N25: 751931.64 | O25: 3281949.7 | P25: 18561.61 | Q25: 0 | R25: 0
C26: T | D26: Total | E26: 6792970.1 | F26: 1198577.8 | G26: 647576.97 | H26: 267551.01 | I26: 336837.22 | J26: 10835.7 | K26: 0 | L26: 130771.96 | M26: 148376.47 | N26: 751931.64 | O26: 3281949.7 | P26: 18561.61 | Q26: 0 | R26: 0
B27: OCCIDENTE | C27: Total | E27: 6982555.4 | F27: 1273072.8 | G27: 689056.57 | H27: 288328.85 | I27: 290156.37 | J27: 7771.96 | K27: 0 | L27: 105587.2 | M27: 131074.51 | N27: 698307.7 | O27: 3485611.3 | P27: 13588.15 | Q27: 0 | R27: 0
A28: Subs/Cont | B28: Total | E28: -12224458 | F28: 655356.59 | G28: 360183.55 | H28: 116142.31 | I28: -5016428.3 | J28: -184957.44 | K28: 0 | L28: -1543756.9 | M28: -1412712.9 | N28: -6714778 | O28: 1818233.4 | P28: -301740.39 | Q28: 0 | R28: 0
A29: Total | E29: 68638657 | F29: 6621540.4 | G29: 3638027.6 | H29: 1481770.3 | I29: 13139370 | J29: 414541.14 | K29: 1030668 | L29: 4537393.8 | M29: 3871747.6 | N29: 14778131 | O29: 18563088 | P29: 562446.13 | Q29: -66.69 | R29: 0
B43: TOTAL | C43: OPORTUNO | D43: Total | E43: =E17+E28-K17 -> 67607989 | F43: =F17 -> 5966183.8 | G43: =G17 -> 3277844.1 | H43: =H17 -> 1365628 | I43: =I17 -> 18155798 | J43: =J17 -> 599498.58 | K43: =K17 -> 1030668 | L43: =L17 -> 6081150.7 | M43: =M17 -> 5284460.6 | ... S43: =S17 -> 0
D44: Subsidio(-)/Contribucion(+) | E44: =E28 -> -12224458
B46: RECIPROCIDAD | C46: OPORTUNO | D46: Total | E46: 0 | F46: 0 | G46: 0 | H46: 0 | I46: 0 | J46: 0 | K46: 0 | L46: 0 | M46: 0 | N46: 0 | O46: 0 | P46: 0 | Q46: 0 | R46: 0 | S46: 0
D47: Subsidio(-)/Contribucion(+) | E47: 0
B49: ENEL | C49: OPORTUNO | D49: Total | E49: =E20+E6-K6 -> 36630929 | F49: =F6 -> 3094803.9 | G49: =G6 -> 1682852.2 | H49: =H6 -> 530709.35 | I49: =I6 -> 14660843 | J49: =J6 -> 506523.82 | K49: =K6 -> 0 | L49: =L6 -> 5082003.9 | M49: =M6 -> 4157997.2 | ... S49: =S6 -> 0
D50: Subsidio(-)/Contribucion(+) | E50: =E20 -> -19207014
B52: ENERBIT | C52: OPORTUNO | D52: Total | E52: 0 | F52: 0 | G52: 0 | H52: 0 | I52: 0 | J52: 0 | K52: 0 | L52: 0 | M52: 0 | N52: 0 | O52: 0 | P52: 0 | Q52: 0 | R52: 0
D53: Subsidio(-)/Contribucion(+) | E53: 0
B55: OCCIDENTE | C55: OPORTUNO | D55: Total | E55: =E16+E27-K16 -> 30977060 | F55: =F16 -> 2871380 | G55: =G16 -> 1594991.9 | H55: =H16 -> 834918.62 | I55: =I16 -> 3494955.2 | J55: =J16 -> 92974.76 | K55: =K16 -> 1030668 | L55: =L16 -> 999146.77 | M55: =M16 -> 1126463.4 | ... S55: =S16 -> 0
D56: Subsidio(-)/Contribucion(+) | E56: =E27 -> 6982555.4
B58: CIUDAD LIMPIA-ACUEDUCTO | C58: OPORTUNO | D58: Total | E58: 0 | F58: 0 | G58: 0 | H58: 0 | I58: 0 | J58: 0 | K58: 0 | L58: 0 | M58: 0 | N58: 0 | O58: 0 | P58: 0 | Q58: 0 | R58: 0 | S58: 0
D59: Subsidio(-)/Contribucion(+) | E59: 0
B61: LIME
E62: Total | F62: Componente TDF | G62: Componente TTL | H62: Componente TVIAT | I62: Aprovechamiento | J62: CCSA Prest.Aprov. | K62: Especiales | L62: Componente TCS | M62: Componente TLU | N62: Componente TBL | O62: Componente TRT | P62: CCSA Prest. No Aprov. | Q62: Deb/Cred | R62: Deb/Cred-otros
D63: Vlr Servicio | E63: 28225718 | F63: 1523009.5 | G63: 856635.8 | H63: 368666.94 | I63: 7399643.2 | J63: 281341.88 | K63: 0 | L63: 2447043.9 | M63: 2235081.8 | N63: 9487154.7 | O63: 3223971 | P63: 403174.67 | Q63: -5.12 | R63: 0
D64: Vlr Intereses | E64: 29203.02 | F64: 2472.94 | G64: 1390.25 | H64: 736.34 | I64: 6081.52 | J64: 220.48 | K64: 0 | L64: 1927.94 | M64: 1958.92 | N64: 9161.85 | O64: 4893.03 | P64: 359.83 | Q64: -0.08 | R64: 0
C65: E | D65: Total | E65: 28254921 | F65: 1525482.4 | G65: 858026.05 | H65: 369403.28 | I65: 7405724.7 | J65: 281562.36 | K65: 0 | L65: 2448971.8 | M65: 2237040.7 | N65: 9496316.5 | O65: 3228864 | P65: 403534.5 | Q65: -5.2 | R65: 0
B66: ENEL | C66: Total | E66: 28254921 | F66: 1525482.4 | G66: 858026.05 | H66: 369403.28 | I66: 7405724.7 | J66: 281562.36 | K66: 0 | L66: 2448971.8 | M66: 2237040.7 | N66: 9496316.5 | O66: 3228864 | P66: 403534.5 | Q66: -5.2 | R66: 0
D67: Vlr Servicio | E67: 4760792.9 | F67: 288724.81 | G67: 147272.85 | H67: 68470.77 | I67: 1185854.2 | J67: 38000.33 | K67: 0 | L67: 338950.86 | M67: 397158.13 | N67: 1672085.9 | O67: 564784.72 | P67: 59478.02 | Q67: 12.35 | R67: 0
D68: Vlr Intereses | E68: 1273.85 | F68: 57.57 | G68: 31.73 | H68: 17.29 | I68: 328.43 | J68: 10.77 | K68: 0 | L68: 94.4 | M68: 105.7 | N68: 489.16 | O68: 121.19 | P68: 17.54 | Q68: 0.07 | R68: 0
C69: 1 | D69: Total | E69: 4762066.7 | F69: 288782.38 | G69: 147304.58 | H69: 68488.06 | I69: 1186182.6 | J69: 38011.1 | K69: 0 | L69: 339045.26 | M69: 397263.83 | N69: 1672575 | O69: 564905.91 | P69: 59495.56 | Q69: 12.42 | R69: 0
D70: Vlr Servicio | E70: 1297078.9 | F70: 82842.16 | G70: 44279.79 | H70: 17659.15 | I70: 374931.03 | J70: 10152.12 | K70: 0 | L70: 101140.81 | M70: 102043.75 | N70: 389699.31 | O70: 162492.81 | P70: 11838.7 | Q70: -0.76 | R70: 0
C71: 2 | D71: Total | E71: 1297078.9 | F71: 82842.16 | G71: 44279.79 | H71: 17659.15 | I71: 374931.03 | J71: 10152.12 | K71: 0 | L71: 101140.81 | M71: 102043.75 | N71: 389699.31 | O71: 162492.81 | P71: 11838.7 | Q71: -0.76 | R71: 0
D72: Vlr Servicio | E72: 12436550 | F72: 747251 | G72: 415550.99 | H72: 136961.03 | I72: 3490640 | J72: 121618.81 | K72: 0 | L72: 1058162.9 | M72: 963885.06 | N72: 3891234.4 | O72: 1454466.6 | P72: 156806.02 | Q72: -26.52 | R72: 0
D73: Vlr Intereses | E73: 1943.21 | F73: 127.65 | G73: 68.95 | H73: 37.92 | I73: 491.88 | J73: 12.97 | K73: 0 | L73: 113.86 | M73: 145.35 | N73: 675.45 | O73: 247.87 | P73: 21.19 | Q73: 0.12 | R73: 0
C74: 5 | D74: Total | E74: 12438494 | F74: 747378.65 | G74: 415619.94 | H74: 136998.95 | I74: 3491131.9 | J74: 121631.78 | K74: 0 | L74: 1058276.8 | M74: 964030.41 | N74: 3891909.9 | O74: 1454714.4 | P74: 156827.21 | Q74: -26.4 | R74: 0
B75: NUEVO ESQUEMA | C75: Total | E75: 18497639 | F75: 1119003.2 | G75: 607204.31 | H75: 223146.16 | I75: 5052245.6 | J75: 169795 | K75: 0 | L75: 1498462.8 | M75: 1463338 | N75: 5954184.2 | O75: 2182113.2 | P75: 228161.47 | Q75: -14.74 | R75: 0
D76: Vlr Servicio | E76: 11228659 | F76: 627548.19 | G76: 345070.03 | H76: 150190.6 | I76: 3094084.6 | J76: 82036.02 | K76: 0 | L76: 744009.01 | M76: 843104.93 | N76: 3956025.2 | O76: 1253497.5 | P76: 133159.91 | Q76: -66.83 | R76: 0
D77: Vlr Intereses | E77: 11721.9 | F77: 1152.27 | G77: 593.19 | H77: 336.21 | I77: 2440.1 | J77: 71.24 | K77: 0 | L77: 625.01 | M77: 723.16 | N77: 3359.71 | O77: 2304.85 | P77: 116.27 | Q77: -0.11 | R77: 0
C78: H | D78: Total | E78: 11240381 | F78: 628700.46 | G78: 345663.22 | H78: 150526.81 | I78: 3096524.7 | J78: 82107.26 | K78: 0 | L78: 744634.02 | M78: 843828.09 | N78: 3959385 | O78: 1255802.3 | P78: 133276.18 | Q78: -66.94 | R78: 0
D79: Vlr Servicio | E79: 41530971 | F79: 3446223.9 | G79: 1837407 | H79: 839836.39 | I79: 10048658 | J79: 294477.08 | K79: 0 | L79: 2560741.1 | M79: 2844892.5 | N79: 12464433 | O79: 6734618.4 | P79: 459737.13 | Q79: -53.9 | R79: 0
D80: Vlr Intereses | E80: 838272.78 | F80: 158907.47 | G80: 77095.07 | H80: 35087.2 | I80: 85486.28 | J80: 2763.9 | K80: 0 | L80: 24264.38 | M80: 29986.1 | N80: 110461.52 | O80: 309708.84 | P80: 4508.85 | Q80: 3.17 | R80: 0
C81: O | D81: Total | E81: 42369243 | F81: 3605131.4 | G81: 1914502.1 | H81: 874923.59 | I81: 10134144 | J81: 297240.98 | K81: 0 | L81: 2585005.5 | M81: 2874878.5 | N81: 12574894 | O81: 7044327.3 | P81: 464245.98 | Q81: -50.73 | R81: 0
D82: Vlr Servicio | E82: 70333717 | F82: 14300186 | G82: 7461392.8 | H82: 3919492.2 | I82: 4692682.5 | J82: 110418.13 | K82: 219000 | L82: 937656.42 | M82: 1233594.2 | N82: 5715904.7 | O82: 31568840 | P82: 174575.03 | Q82: -25.07 | R82: 0
D83: Vlr Intereses | E83: 2597.82 | F83: 534.71 | G83: 300.32 | H83: 158.46 | I83: 184.7 | J83: 5.14 | K83: 0 | L83: 45.12 | M83: 52.17 | N83: 247.23 | O83: 1061.6 | P83: 8.38 | Q83: -0.01 | R83: 0
C84: T | D84: Total | E84: 70336315 | F84: 14300720 | G84: 7461693.2 | H84: 3919650.7 | I84: 4692867.2 | J84: 110423.27 | K84: 219000 | L84: 937701.54 | M84: 1233646.4 | N84: 5716152 | O84: 31569902 | P84: 174583.41 | Q84: -25.08 | R84: 0
B85: OCCIDENTE | C85: Total | E85: 1.2394594e+08 | F85: 18534552 | G85: 9721858.4 | H85: 4945101.1 | I85: 17923536 | J85: 489771.51 | K85: 219000 | L85: 4267341 | M85: 4952353 | N85: 22250431 | O85: 39870031 | P85: 772105.57 | Q85: -142.75 | R85: 0
A86: Componente | B86: Total | E86: 1.706985e+08 | F86: 21179038 | G86: 11187089 | H86: 5537650.5 | I86: 30381507 | J86: 941128.87 | K86: 219000 | L86: 8214775.6 | M86: 8652731.7 | N86: 37700932 | O86: 45281009 | P86: 1403801.5 | Q86: -162.69 | R86: 0
D87: Subsidio(-)/Contribucion(+) | E87: -7717840.7 | F87: -223244.82 | G87: -129355.59 | H87: -75143.33 | I87: -2015008.8 | J87: -82434.13 | K87: 0 | L87: -715732.9 | M87: -685682.04 | N87: -3229430.7 | O87: -428639.54 | P87: -133168.79 | Q87: 0 | R87: 0
C88: E | D88: Total | E88: -7717840.7 | F88: -223244.82 | G88: -129355.59 | H88: -75143.33 | I88: -2015008.8 | J88: -82434.13 | K88: 0 | L88: -715732.9 | M88: -685682.04 | N88: -3229430.7 | O88: -428639.54 | P88: -133168.79 | Q88: 0 | R88: 0
B89: ENEL | C89: Total | E89: -7717840.7 | F89: -223244.82 | G89: -129355.59 | H89: -75143.33 | I89: -2015008.8 | J89: -82434.13 | K89: 0 | L89: -715732.9 | M89: -685682.04 | N89: -3229430.7 | O89: -428639.54 | P89: -133168.79 | Q89: 0 | R89: 0
D90: Subsidio(-)/Contribucion(+) | E90: -1727591.8 | F90: -66699.01 | G90: -37718.2 | H90: -21366.1 | I90: -470847.92 | J90: -14108.12 | K90: 0 | L90: -121593.44 | M90: -145997.1 | N90: -696216.07 | O90: -130027.11 | P90: -23018.7 | Q90: 0 | R90: 0
C91: 1 | D91: Total | E91: -1727591.8 | F91: -66699.01 | G91: -37718.2 | H91: -21366.1 | I91: -470847.92 | J91: -14108.12 | K91: 0 | L91: -121593.44 | M91: -145997.1 | N91: -696216.07 | O91: -130027.11 | P91: -23018.7 | Q91: 0 | R91: 0
D92: Subsidio(-)/Contribucion(+) | E92: -451067.07 | F92: -14827.04 | G92: -8309.25 | H92: -5522 | I92: -130344.19 | J92: -3806.48 | K92: 0 | L92: -33390.01 | M92: -38655.21 | N92: -181383.9 | O92: -28618.4 | P92: -6210.59 | Q92: 0 | R92: 0
C93: 2 | D93: Total | E93: -451067.07 | F93: -14827.04 | G93: -8309.25 | H93: -5522 | I93: -130344.19 | J93: -3806.48 | K93: 0 | L93: -33390.01 | M93: -38655.21 | N93: -181383.9 | O93: -28618.4 | P93: -6210.59 | Q93: 0 | R93: 0
D94: Subsidio(-)/Contribucion(+) | E94: -4663033.9 | F94: -168863.63 | G94: -100236.26 | H94: -51045.95 | I94: -1292045.4 | J94: -43838.41 | K94: 0 | L94: -384070.02 | M94: -387480.88 | N94: -1833929.9 | O94: -329765.11 | P94: -71758.34 | Q94: 0 | R94: 0
C95: 5 | D95: Total | E95: -4663033.9 | F95: -168863.63 | G95: -100236.26 | H95: -51045.95 | I95: -1292045.4 | J95: -43838.41 | K95: 0 | L95: -384070.02 | M95: -387480.88 | N95: -1833929.9 | O95: -329765.11 | P95: -71758.34 | Q95: 0 | R95: 0
B96: NUEVO ESQUEMA | C96: Total | E96: -6841692.7 | F96: -250389.68 | G96: -146263.71 | H96: -77934.05 | I96: -1893237.5 | J96: -61753.01 | K96: 0 | L96: -539053.47 | M96: -572133.19 | N96: -2711529.8 | O96: -488410.62 | P96: -100987.63 | Q96: 0 | R96: 0
D97: Subsidio(-)/Contribucion(+) | E97: -2917701.6 | F97: -111832.49 | G97: -64149.93 | H97: -36385.65 | I97: -814075.83 | J97: -23223.91 | K97: 0 | L97: -196498.78 | M97: -246815.7 | N97: -1170171.5 | O97: -217199.08 | P97: -37348.73 | Q97: 0 | R97: 0
C98: H | D98: Total | E98: -2917701.6 | F98: -111832.49 | G98: -64149.93 | H98: -36385.65 | I98: -814075.83 | J98: -23223.91 | K98: 0 | L98: -196498.78 | M98: -246815.7 | N98: -1170171.5 | O98: -217199.08 | P98: -37348.73 | Q98: 0 | R98: 0
D99: Subsidio(-)/Contribucion(+) | E99: -8597088.7 | F99: -139068.15 | G99: -98790.42 | H99: -53095.25 | I99: -3452478.2 | J99: -97001.85 | K99: 0 | L99: -752144.38 | M99: -919143.38 | N99: -4438605.9 | O99: 1510906.9 | P99: -157668.06 | Q99: 0 | R99: 0
C100: O | D100: Total | E100: -8597088.7 | F100: -139068.15 | G100: -98790.42 | H100: -53095.25 | I100: -3452478.2 | J100: -97001.85 | K100: 0 | L100: -752144.38 | M100: -919143.38 | N100: -4438605.9 | O100: 1510906.9 | P100: -157668.06 | Q100: 0 | R100: 0
D101: Subsidio(-)/Contribucion(+) | E101: 11344979 | F101: 2875483 | G101: 1478938.9 | H101: 732213.35 | I101: 194987.48 | J101: 4069.58 | K101: 0 | L101: 44417.39 | M101: 56222.39 | N101: 242951.8 | O101: 5709057.7 | P101: 6637.87 | Q101: 0 | R101: 0
C102: T | D102: Total | E102: 11344979 | F102: 2875483 | G102: 1478938.9 | H102: 732213.35 | I102: 194987.48 | J102: 4069.58 | K102: 0 | L102: 44417.39 | M102: 56222.39 | N102: 242951.8 | O102: 5709057.7 | P102: 6637.87 | Q102: 0 | R102: 0
B103: OCCIDENTE | C103: Total | E103: -169810.84 | F103: 2624582.3 | G103: 1315998.6 | H103: 642732.45 | I103: -4071566.5 | J103: -116156.18 | K103: 0 | L103: -904225.77 | M103: -1109736.7 | N103: -5365825.6 | O103: 7002765.5 | P103: -188378.92 | Q103: 0 | R103: 0
A104: Subs/Cont | B104: Total | E104: -14729344 | F104: 2150947.8 | G104: 1040379.3 | H104: 489655.07 | I104: -7979812.9 | J104: -260343.32 | K104: 0 | L104: -2159012.1 | M104: -2367551.9 | N104: -11306786 | O104: 6085715.4 | P104: -422535.34 | Q104: 0 | R104: 0
A105: Total | E105: 1.5596916e+08 | F105: 23329986 | G105: 12227468 | H105: 6027305.6 | I105: 22401694 | J105: 680785.55 | K105: 219000 | L105: 6055763.5 | M105: 6285179.8 | N105: 26394146 | O105: 51366724 | P105: 981266.2 | Q105: -162.69 | R105: 0
B136: TOTAL | C136: OPORTUNO | D136: Total | E136: =E86+E104-K86 -> 1.5575016e+08 | F136: =F86 -> 21179038 | G136: =G86 -> 11187089 | H136: =H86 -> 5537650.5 | I136: =I86 -> 30381507 | J136: =J86 -> 941128.87 | K136: =K86 -> 219000 | L136: =L86 -> 8214775.6 | M136: =M86 -> 8652731.7 | ... R136: =R86 -> 0
D137: Subsidio(-)/Contribucion(+) | E137: =E104 -> -14729344
B139: RECIPROCIDAD | C139: OPORTUNO | D139: Total | E139: =E96+E75-K75 -> 11655946 | F139: =F75 -> 1119003.2 | G139: =G75 -> 607204.31 | H139: =H75 -> 223146.16 | I139: =I75 -> 5052245.6 | J139: =J75 -> 169795 | K139: =K75 -> 0 | L139: =L75 -> 1498462.8 | M139: =M75 -> 1463338 | ... R139: =R75 -> 0
D140: Subsidio(-)/Contribucion(+) | E140: =E96 -> -6841692.7
B142: ENEL | C142: OPORTUNO | D142: Total | E142: =E89+E66-K66 -> 20537081 | F142: =F66 -> 1525482.4 | G142: =G66 -> 858026.05 | H142: =H66 -> 369403.28 | I142: =I66 -> 7405724.7 | J142: =J66 -> 281562.36 | K142: =K66 -> 0 | L142: =L66 -> 2448971.8 | M142: =M66 -> 2237040.7 | ... R142: =R66 -> 0
D143: Subsidio(-)/Contribucion(+) | E143: =E89 -> -7717840.7
B145: ENERBIT | C145: OPORTUNO | D145: Total | E145: 0 | F145: 0 | G145: 0 | H145: 0 | I145: 0 | J145: 0 | K145: 0 | L145: 0 | M145: 0 | N145: 0 | O145: 0 | P145: 0 | Q145: 0 | R145: 0
D146: Subsidio(-)/Contribucion(+) | E146: 0
B148: OCCIDENTE | C148: OPORTUNO | D148: Total | E148: =E85+E103-K85 -> 1.2355713e+08 | F148: =F85 -> 18534552 | G148: =G85 -> 9721858.4 | H148: =H85 -> 4945101.1 | I148: =I85 -> 17923536 | J148: =J85 -> 489771.51 | K148: =K85 -> 219000 | L148: =L85 -> 4267341 | M148: =M85 -> 4952353 | ... R148: =R85 -> 0
D149: Subsidio(-)/Contribucion(+) | E149: =E103 -> -169810.84
B151: CIUDAD LIMPIA-ACUEDUCTO | C151: OPORTUNO | D151: Total | E151: 0 | F151: 0 | G151: 0 | H151: 0 | I151: 0 | J151: 0 | K151: 0 | L151: 0 | M151: 0 | N151: 0 | O151: 0 | P151: 0 | Q151: 0 | R151: 0
D152: Subsidio(-)/Contribucion(+) | E152: 0
B154: CIUDAD LIMPIA
E155: Total | F155: Componente TDF | G155: Componente TTL | H155: Componente TVIAT | I155: Aprovechamiento | J155: CCSA Prest.Aprov. | K155: Especiales | L155: Componente TCS | M155: Componente TLU | N155: Componente TBL | O155: Componente TRT | P155: CCSA Prest. No Aprov. | Q155: Deb/Cred | R155: Deb/Cred-otros
...

Sheet Reversion Pagos R4
B1: PROMOAMBIENTAL
D2: Total | E2: Componente TDF | F2: Componente TTL | G2: Componente TVIAT | H2: Aprovechamiento | I2: CCSA Prest.Aprov. | J2: Componente TCS | K2: Componente TLU | L2: Componente TBL | M2: Componente TRT | N2: CCSA Prest. No Aprov. | O2: Ajuste Decena | P2: SERVICIO ESPECIALES | Q2: Ajuste Recargo Aseo | R2: Otros
C3: Vlr Servicio | D3: -902656.46 | E3: -50786.1 | F3: -28687.84 | G3: -15112.67 | H3: -214829.29 | I3: -7567.12 | J3: -66377.88 | K3: -64591.46 | L3: -303450.84 | M3: -138897.31 | N3: -12346.16 | O3: -9.79 | P3: 0 | Q3: 0 | R3: 0
C4: Vlr Intereses | D4: -84.31 | E4: -4.65 | F4: -2.63 | G4: -1.39 | H4: -20.46 | I4: -0.71 | J4: -6.2 | K4: -6.14 | L4: -28.19 | M4: -12.78 | N4: -1.15 | O4: -0.01 | P4: 0 | Q4: 0 | R4: 0
B5: Componente | C5: Total | D5: -902740.77 | E5: -50790.75 | F5: -28690.47 | G5: -15114.06 | H5: -214849.75 | I5: -7567.83 | J5: -66384.08 | K5: -64597.6 | L5: -303479.03 | M5: -138910.09 | N5: -12347.31 | O5: -9.8 | P5: 0 | Q5: 0 | R5: 0
C6: Subsidio(-)/Contribucion(+) | D6: -342249.23 | E6: -20012.25 | F6: -11305.96 | G6: -5961.84 | H6: -80024.59 | I6: -2832.43 | J6: -24845.71 | K6: -24218.43 | L6: -113481.59 | M6: -54945.16 | N6: -4621.27 | O6: 0 | P6: 0 | Q6: 0 | R6: 0
B7: Subs/Cont | C7: Total | D7: -342249.23 | E7: -20012.25 | F7: -11305.96 | G7: -5961.84 | H7: -80024.59 | I7: -2832.43 | J7: -24845.71 | K7: -24218.43 | L7: -113481.59 | M7: -54945.16 | N7: -4621.27 | O7: 0 | P7: 0 | Q7: 0 | R7: 0
A8: ENEL | B8: Total | D8: -1244990 | E8: -70803 | F8: -39996.43 | G8: -21075.9 | H8: -294874.34 | I8: -10400.26 | J8: -91229.79 | K8: -88816.03 | L8: -416960.62 | M8: -193855.25 | N8: -16968.58 | O8: -9.8 | P8: 0 | Q8: 0 | R8: 0
C9: Vlr Servicio | D9: -40070 | E9: -2042.17 | F9: -1153.02 | G9: -605.19 | H9: -10019.35 | I9: -249.19 | J9: -2185.89 | K9: -3113.99 | L9: -14745.86 | M9: -5553.38 | N9: -406.58 | O9: 4.62 | P9: 0 | Q9: 0 | R9: 0
B10: Componente | C10: Total | D10: -40070 | E10: -2042.17 | F10: -1153.02 | G10: -605.19 | H10: -10019.35 | I10: -249.19 | J10: -2185.89 | K10: -3113.99 | L10: -14745.86 | M10: -5553.38 | N10: -406.58 | O10: 4.62 | P10: 0 | Q10: 0 | R10: 0
A11: OCCIDENTE | B11: Total | D11: -40070 | E11: -2042.17 | F11: -1153.02 | G11: -605.19 | H11: -10019.35 | I11: -249.19 | J11: -2185.89 | K11: -3113.99 | L11: -14745.86 | M11: -5553.38 | N11: -406.58 | O11: 4.62 | P11: 0 | Q11: 0 | R11: 0
A12: Total | D12: -1285060 | E12: -72845.17 | F12: -41149.45 | G12: -21681.09 | H12: -304893.69 | I12: -10649.45 | J12: -93415.68 | K12: -91930.02 | L12: -431706.48 | M12: -199408.63 | N12: -17375.16 | O12: -5.18 | P12: 0 | Q12: 0 | R12: 0
A70: TOTAL | B70: OPORTUNO | C70: Total | D70: =D12-P12 -> -1285060 | E70: =E5+E10 -> -52832.92 | F70: =F5+F10 -> -29843.49 | G70: =G5+G10 -> -15719.25 | H70: =H5+H10 -> -224869.1 | I70: =I5+I10 -> -7817.02 | J70: =J5+J10 -> -68569.97 | K70: =K5+K10 -> -67711.59 | L70: =L5+L10 -> -318224.89 | ... R70: =R5+R10 -> 0
C71: Subsidio(-)/Contribucion(+) | D71: =D7 -> -342249.23
A73: RECIPROCIDAD | B73: OPORTUNO | C73: Total | D73: 0 | E73: 0 | F73: 0 | G73: 0 | H73: 0 | I73: 0 | J73: 0 | K73: 0 | L73: 0 | M73: 0 | N73: 0 | O73: 0 | P73: 0 | Q73: 0 | R73: 0
C74: Subsidio(-)/Contribucion(+) | D74: 0
A76: ENEL | B76: OPORTUNO | C76: Total | D76: =D8-P8 -> -1244990 | E76: =E5 -> -50790.75 | F76: =F5 -> -28690.47 | G76: =G5 -> -15114.06 | H76: =H5 -> -214849.75 | I76: =I5 -> -7567.83 | J76: =J5 -> -66384.08 | K76: =K5 -> -64597.6 | L76: =L5 -> -303479.03 | ... R76: =R5 -> 0
C77: Subsidio(-)/Contribucion(+) | D77: =D7 -> -342249.23
A79: ENERBIT | B79: OPORTUNO | C79: Total | D79: 0 | E79: 0 | F79: 0 | G79: 0 | H79: 0 | I79: 0 | J79: 0 | K79: 0 | L79: 0 | M79: 0 | N79: 0 | O79: 0 | P79: 0 | Q79: 0 | R79: 0
C80: Subsidio(-)/Contribucion(+) | D80: 0
A82: OCCIDENTE | B82: OPORTUNO | C82: Total | D82: =D11-P11 -> -40070 | E82: =E10 -> -2042.17 | F82: =F10 -> -1153.02 | G82: =G10 -> -605.19 | H82: =H10 -> -10019.35 | I82: =I10 -> -249.19 | J82: =J10 -> -2185.89 | K82: =K10 -> -3113.99 | L82: =L10 -> -14745.86 | ... R82: =R10 -> 0
C83: Subsidio(-)/Contribucion(+) | D83: 0
A85: CIUDAD LIMPIA-ACUEDUCTO | B85: OPORTUNO | C85: Total | D85: 0 | E85: 0 | F85: 0 | G85: 0 | H85: 0 | I85: 0 | J85: 0 | K85: 0 | L85: 0 | M85: 0 | N85: 0 | O85: 0 | P85: 0 | Q85: 0 | R85: 0
C86: Subsidio(-)/Contribucion(+) | D86: 0
B88: LIME
D89: Total | E89: Componente TDF | F89: Componente TTL | G89: Componente TVIAT | H89: Aprovechamiento | I89: CCSA Prest.Aprov. | J89: Componente TCS | K89: Componente TLU | L89: Componente TBL | M89: Componente TRT | N89: CCSA Prest. No Aprov. | O89: Ajuste Decena | P89: SERVICIO ESPECIALES | Q89: Ajuste Recargo Aseo | R89: Otros
C90: Vlr Servicio | D90: -50598099 | E90: -3020381.9 | F90: -1629949.6 | G90: -850506.71 | H90: -12343961 | I90: -436345.15 | J90: -3854743.4 | K90: -3881901.3 | L90: -17844917 | M90: -6019284.2 | N90: -716097.95 | O90: -10.88 | P90: 0 | Q90: 0 | R90: 0
C91: Vlr Intereses | D91: -863642.25 | E91: -86868.6 | F91: -40393.28 | G91: -20594.22 | H91: -182194.3 | I91: -5497.81 | J91: -48405.41 | K91: -58042.26 | L91: -238361.58 | M91: -174296.88 | N91: -8984.88 | O91: -3.29 | P91: 0 | Q91: 0.26 | R91: 0
B92: Componente | C92: Total | D92: -51461741 | E92: -3107250.5 | F92: -1670342.9 | G92: -871100.93 | H92: -12526155 | I92: -441842.96 | J92: -3903148.8 | K92: -3939943.5 | L92: -18083278 | M92: -6193581.1 | N92: -725082.83 | O92: -14.17 | P92: 0 | Q92: 0.26 | R92: 0
C93: Subsidio(-)/Contribucion(+) | D93: 9920875 | E93: 303875.69 | F93: 150290.09 | G93: 72257.8 | H93: 2865204.2 | I93: 96655.6 | J93: 848909.8 | K93: 888082.75 | L93: 3956095.5 | M93: 581803.98 | N93: 157699.54 | O93: 0 | P93: 0 | Q93: 0 | R93: 0
B94: Subs/Cont | C94: Total | D94: 9920875 | E94: 303875.69 | F94: 150290.09 | G94: 72257.8 | H94: 2865204.2 | I94: 96655.6 | J94: 848909.8 | K94: 888082.75 | L94: 3956095.5 | M94: 581803.98 | N94: 157699.54 | O94: 0 | P94: 0 | Q94: 0 | R94: 0
A95: ENEL | B95: Total | D95: -41540866 | E95: -2803374.8 | F95: -1520052.8 | G95: -798843.13 | H95: -9660951 | I95: -345187.36 | J95: -3054239 | K95: -3051860.8 | L95: -14127183 | M95: -5611777.1 | N95: -567383.29 | O95: -14.17 | P95: 0 | Q95: 0.26 | R95: 0
C96: Vlr Servicio | D96: -76886.16 | E96: -3878.52 | F96: -2172.78 | G96: -1192.62 | H96: -20529.3 | I96: -491.85 | J96: -4314.5 | K96: -6347.49 | L96: -29323.18 | M96: -7837.65 | N96: -802.5 | O96: 4.23 | P96: 0 | Q96: 0 | R96: 0
B97: Componente | C97: Total | D97: -76886.16 | E97: -3878.52 | F97: -2172.78 | G97: -1192.62 | H97: -20529.3 | I97: -491.85 | J97: -4314.5 | K97: -6347.49 | L97: -29323.18 | M97: -7837.65 | N97: -802.5 | O97: 4.23 | P97: 0 | Q97: 0 | R97: 0
C98: Subsidio(-)/Contribucion(+) | D98: 30756.16 | E98: 1551.4 | F98: 869.11 | G98: 477.04 | H98: 8211.72 | I98: 196.73 | J98: 1725.81 | K98: 2539 | L98: 11729.28 | M98: 3135.07 | N98: 321 | O98: 0 | P98: 0 | Q98: 0 | R98: 0
B99: Subs/Cont | C99: Total | D99: 30756.16 | E99: 1551.4 | F99: 869.11 | G99: 477.04 | H99: 8211.72 | I99: 196.73 | J99: 1725.81 | K99: 2539 | L99: 11729.28 | M99: 3135.07 | N99: 321 | O99: 0 | P99: 0 | Q99: 0 | R99: 0
A100: NUEVO ESQUEMA | B100: Total | D100: -46130 | E100: -2327.12 | F100: -1303.67 | G100: -715.58 | H100: -12317.58 | I100: -295.12 | J100: -2588.69 | K100: -3808.49 | L100: -17593.9 | M100: -4702.58 | N100: -481.5 | O100: 4.23 | P100: 0 | Q100: 0 | R100: 0
C101: Vlr Servicio | D101: -6896431.4 | E101: -457444.01 | F101: -239394.76 | G101: -121915.4 | H101: -1704835.5 | I101: -52568.96 | J101: -464698 | K101: -563915.35 | L101: -2331911.5 | M101: -875007.12 | N101: -84792.49 | O101: 51.65 | P101: 0 | Q101: 0 | R101: 0
C102: Vlr Intereses | D102: -436148.07 | E102: -65575.05 | F102: -28205.75 | G102: -9888.85 | H102: -63469.4 | I102: -2533.87 | J102: -22226.6 | K102: -23823.17 | L102: -89035.29 | M102: -127548.68 | N102: -4134.18 | O102: 14 | P102: 0 | Q102: -10.42 | R102: 289.19
B103: Componente | C103: Total | D103: -7332579.5 | E103: -523019.06 | F103: -267600.51 | G103: -131804.25 | H103: -1768304.9 | I103: -55102.83 | J103: -486924.6 | K103: -587738.52 | L103: -2420946.8 | M103: -1002555.8 | N103: -88926.67 | O103: 65.65 | P103: 0 | Q103: -10.42 | R103: 289.19
C104: Subsidio(-)/Contribucion(+) | D104: 3689523.5 | E104: 196445.95 | F104: 97024.73 | G104: 47913.53 | H104: 980845.01 | I104: 31030.31 | J104: 272193.56 | K104: 321126.58 | L104: 1303205.1 | M104: 389110.69 | N104: 50628.1 | O104: 0 | P104: 0 | Q104: 0 | R104: 0
B105: Subs/Cont | C105: Total | D105: 3689523.5 | E105: 196445.95 | F105: 97024.73 | G105: 47913.53 | H105: 980845.01 | I105: 31030.31 | J105: 272193.56 | K105: 321126.58 | L105: 1303205.1 | M105: 389110.69 | N105: 50628.1 | O105: 0 | P105: 0 | Q105: 0 | R105: 0
A106: OCCIDENTE | B106: Total | D106: -3643056 | E106: -326573.11 | F106: -170575.78 | G106: -83890.72 | H106: -787459.92 | I106: -24072.52 | J106: -214731.04 | K106: -266611.94 | L106: -1117741.7 | M106: -613445.11 | N106: -38298.57 | O106: 65.65 | P106: 0 | Q106: -10.42 | R106: 289.19
A107: Total | D107: -45230052 | E107: -3132275.1 | F107: -1691932.2 | G107: -883449.43 | H107: -10460728 | I107: -369555 | J107: -3271558.7 | K107: -3322281.2 | L107: -15262518 | M107: -6229924.8 | N107: -606163.36 | O107: 55.71 | P107: 0 | Q107: -10.16 | R107: 289.19
A170: TOTAL | B170: OPORTUNO | C170: Total | D170: =D107-P107 -> -45230052 | E170: =E92+E97+E103 -> -3634148.1 | F170: =F92+F97+F103 -> -1940116.2 | G170: =G92+G97+G103 -> -1004097.8 | H170: =H92+H97+H103 -> -14314989 | I170: =I92+I97+I103 -> -497437.64 | J170: =J92+J97+J103 -> -4394387.9 | K170: =K92+K97+K103 -> -4534029.6 | L170: =L92+L97+L103 -> -20533548 | ... R170: =R92+R97+R103 -> 289.19
C171: Subsidio(-)/Contribucion(+) | D171: =D94+D99+D105 -> 13641155
A173: RECIPROCIDAD | B173: OPORTUNO | C173: Total | D173: =D100-P100 -> -46130 | E173: =E97 -> -3878.52 | F173: =F97 -> -2172.78 | G173: =G97 -> -1192.62 | H173: =H97 -> -20529.3 | I173: =I97 -> -491.85 | J173: =J97 -> -4314.5 | K173: =K97 -> -6347.49 | L173: =L97 -> -29323.18 | ... R173: =R97 -> 0
C174: Subsidio(-)/Contribucion(+) | D174: =D99 -> 30756.16
A176: ENEL | B176: OPORTUNO | C176: Total | D176: =D95-P95 -> -41540866 | E176: =E92 -> -3107250.5 | F176: =F92 -> -1670342.9 | G176: =G92 -> -871100.93 | H176: =H92 -> -12526155 | I176: =I92 -> -441842.96 | J176: =J92 -> -3903148.8 | K176: =K92 -> -3939943.5 | L176: =L92 -> -18083278 | ... R176: =R92 -> 0
C177: Subsidio(-)/Contribucion(+) | D177: =D94 -> 9920875
A179: ENERBIT | B179: OPORTUNO | C179: Total | D179: 0 | E179: 0 | F179: 0 | G179: 0 | H179: 0 | I179: 0 | J179: 0 | K179: 0 | L179: 0 | M179: 0 | N179: 0 | O179: 0 | P179: 0 | Q179: 0 | R179: 0
C180: Subsidio(-)/Contribucion(+) | D180: 0
A182: OCCIDENTE | B182: OPORTUNO | C182: Total | D182: =D106-P106 -> -3643056 | E182: =E103 -> -523019.06 | F182: =F103 -> -267600.51 | G182: =G103 -> -131804.25 | H182: =H103 -> -1768304.9 | I182: =I103 -> -55102.83 | J182: =J103 -> -486924.6 | K182: =K103 -> -587738.52 | L182: =L103 -> -2420946.8 | ... R182: =R103 -> 289.19
C183: Subsidio(-)/Contribucion(+) | D183: =D105 -> 3689523.5
A185: CIUDAD LIMPIA-ACUEDUCTO | B185: OPORTUNO | C185: Total | D185: 0 | E185: 0 | F185: 0 | G185: 0 | H185: 0 | I185: 0 | J185: 0 | K185: 0 | L185: 0 | M185: 0 | N185: 0 | O185: 0 | P185: 0 | Q185: 0 | R185: 0
C186: Subsidio(-)/Contribucion(+) | D186: 0
B188: CIUDAD LIMPIA
D189: Total | E189: Componente TDF | F189: Componente TTL | G189: Componente TVIAT | H189: Aprovechamiento | I189: CCSA Prest.Aprov. | J189: Componente TCS | K189: Componente TLU | L189: Componente TBL | M189: Componente TRT | N189: CCSA Prest. No Aprov. | O189: Ajuste Decena | P189: SERVICIO ESPECIALES | Q189: Ajuste Recargo Aseo | R189: Otros
C190: Vlr Servicio | D190: -7273359.1 | E190: -515292.55 | F190: -289983.7 | G190: -152857.65 | H190: -1791444.1 | I190: -54888.34 | J190: -481479.26 | K190: -469276.25 | L190: -2213791.1 | M190: -1214658.7 | N190: -89555.13 | O190: -132.36 | P190: 0 | Q190: 0 | R190: 0
C191: Vlr Intereses | D191: -3288.33 | E191: -359.82 | F191: -203.26 | G191: -107.06 | H191: -573.45 | I191: -19.83 | J191: -173.94 | K191: -170.76 | L191: -807.72 | M191: -840.06 | N191: -32.37 | O191: -0.06 | P191: 0 | Q191: 0 | R191: 0
B192: Componente | C192: Total | D192: -7276647.5 | E192: -515652.37 | F192: -290186.96 | G192: -152964.71 | H192: -1792017.6 | I192: -54908.17 | J192: -481653.2 | K192: -469447.01 | L192: -2214598.8 | M192: -1215498.8 | N192: -89587.5 | O192: -132.42 | P192: 0 | Q192: 0 | R192: 0
C193: Subsidio(-)/Contribucion(+) | D193: -439016.54 | E193: -190403.28 | F193: -107378.28 | G193: -56563.26 | H193: 140225.3 | I193: 3676.03 | J193: 32245.56 | K193: 31345.12 | L193: 148908.02 | M193: -447069.41 | N193: 5997.66 | O193: 0 | P193: 0 | Q193: 0 | R193: 0
B194: Subs/Cont | C194: Total | D194: -439016.54 | E194: -190403.28 | F194: -107378.28 | G194: -56563.26 | H194: 140225.3 | I194: 3676.03 | J194: 32245.56 | K194: 31345.12 | L194: 148908.02 | M194: -447069.41 | N194: 5997.66 | O194: 0 | P194: 0 | Q194: 0 | R194: 0
A195: ENEL | B195: Total | D195: -7715664 | E195: -706055.65 | F195: -397565.24 | G195: -209527.97 | H195: -1651792.3 | I195: -51232.14 | J195: -449407.64 | K195: -438101.89 | L195: -2065690.8 | M195: -1662568.2 | N195: -83589.84 | O195: -132.42 | P195: 0 | Q195: 0 | R195: 0
A196: Total | D196: -7715664 | E196: -706055.65 | F196: -397565.24 | G196: -209527.97 | H196: -1651792.3 | I196: -51232.14 | J196: -449407.64 | K196: -438101.89 | L196: -2065690.8 | M196: -1662568.2 | N196: -83589.84 | O196: -132.42 | P196: 0 | Q196: 0 | R196: 0
A201: TOTAL | B201: OPORTUNO | C201: Total | D201: =D196-P196 -> -7715664 | E201: =E192 -> -515652.37 | F201: =F192 -> -290186.96 | G201: =G192 -> -152964.71 | H201: =H192 -> -1792017.6 | I201: =I192 -> -54908.17 | J201: =J192 -> -481653.2 | K201: =K192 -> -469447.01 | L201: =L192 -> -2214598.8 | ... R201: =R192 -> 0
C202: Subsidio(-)/Contribucion(+) | D202: =D194 -> -439016.54
A204: RECIPROCIDAD | B204: OPORTUNO | C204: Total | D204: 0 | E204: 0 | F204: 0 | G204: 0 | H204: 0 | I204: 0 | J204: 0 | K204: 0 | L204: 0 | M204: 0 | N204: 0 | O204: 0 | P204: 0 | Q204: 0 | R204: 0
C205: Subsidio(-)/Contribucion(+) | D205: 0
A207: ENEL | B207: OPORTUNO | C207: Total | D207: =D195-P195 -> -7715664 | E207: =E192 -> -515652.37 | F207: =F192 -> -290186.96 | G207: =G192 -> -152964.71 | H207: =H192 -> -1792017.6 | I207: =I192 -> -54908.17 | J207: =J192 -> -481653.2 | K207: =K192 -> -469447.01 | L207: =L192 -> -2214598.8 | ... R207: =R192 -> 0
C208: Subsidio(-)/Contribucion(+) | D208: =D194 -> -439016.54
A210: ENERBIT | B210: OPORTUNO | C210: Total | D210: 0 | E210: 0 | F210: 0 | G210: 0 | H210: 0 | I210: 0 | J210: 0 | K210: 0 | L210: 0 | M210: 0 | N210: 0 | O210: 0 | P210: 0 | Q210: 0 | R210: 0
C211: Subsidio(-)/Contribucion(+) | D211: 0
A213: OCCIDENTE | B213: OPORTUNO | C213: Total | D213: 0 | E213: 0 | F213: 0 | G213: 0 | H213: 0 | I213: 0 | J213: 0 | K213: 0 | L213: 0 | M213: 0 | N213: 0 | O213: 0 | P213: 0 | Q213: 0 | R213: 0
C214: Subsidio(-)/Contribucion(+) | D214: 0
A216: CIUDAD LIMPIA-ACUEDUCTO | B216: OPORTUNO | C216: Total | D216: 0 | E216: 0 | F216: 0 | G216: 0 | H216: 0 | I216: 0 | J216: 0 | K216: 0 | L216: 0 | M216: 0 | N216: 0 | O216: 0 | P216: 0 | Q216: 0 | R216: 0
C217: Subsidio(-)/Contribucion(+) | D217: 0
B219: BOGOTA LIMPIA
D220: Total | E220: Componente TDF | F220: Componente TTL | G220: Componente TVIAT | H220: Aprovechamiento | I220: CCSA Prest.Aprov. | J220: Componente TCS | K220: Componente TLU | L220: Componente TBL | M220: Componente TRT | N220: CCSA Prest. No Aprov. | O220: Ajuste Decena | P220: SERVICIO ESPECIALES | Q220: Ajuste Recargo Aseo | R220: Otros
C221: Vlr Servicio | D221: -1.5732745e+08 | E221: -9430397.4 | F221: -5276977.2 | G221: -2791564.2 | H221: -34817384 | I221: -1247425.2 | J221: -10847623 | K221: -10796411 | L221: -54839371 | M221: -25201521 | N221: -2032323.2 | O221: 44.06 | P221: -46500 | Q221: 0 | R221: 0
C222: Vlr Intereses | D222: -8144814 | E222: -951923.77 | F222: -375514.63 | G222: -129613.08 | H222: -1189171 | I222: -52721.89 | J222: -463859.24 | K222: -525049.74 | L222: -1738654.5 | M222: -2632481.2 | N222: -86041.09 | O222: 23.23 | P222: 0 | Q222: 0 | R222: 192.99
B223: Componente | C223: Total | D223: -1.6547227e+08 | E223: -10382321 | F223: -5652491.8 | G223: -2921177.3 | H223: -36006555 | I223: -1300147.1 | J223: -11311482 | K223: -11321460 | L223: -56578026 | M223: -27834002 | N223: -2118364.3 | O223: 67.29 | P223: -46500 | Q223: 0 | R223: 192.99
C224: Subsidio(-)/Contribucion(+) | D224: -2184344.9 | E224: -1160936.6 | F224: -658002.48 | G224: -348496.64 | H224: 1038703.4 | I224: 30026.19 | J224: 266241.69 | K224: 289895.02 | L224: 1391094.3 | M224: -3081846.4 | N224: 48976.7 | O224: 0 | P224: 0 | Q224: 0 | R224: 0
B225: Subs/Cont | C225: Total | D225: -2184344.9 | E225: -1160936.6 | F225: -658002.48 | G225: -348496.64 | H225: 1038703.4 | I225: 30026.19 | J225: 266241.69 | K225: 289895.02 | L225: 1391094.3 | M225: -3081846.4 | N225: 48976.7 | O225: 0 | P225: 0 | Q225: 0 | R225: 0
A226: ENEL | B226: Total | D226: -1.6765661e+08 | E226: -11543258 | F226: -6310494.3 | G226: -3269674 | H226: -34967852 | I226: -1270120.9 | J226: -11045241 | K226: -11031565 | L226: -55186932 | M226: -30915849 | N226: -2069387.6 | O226: 67.29 | P226: -46500 | Q226: 0 | R226: 192.99
C227: Vlr Servicio | D227: -1724959.4 | E227: -91259.53 | F227: -48435.24 | G227: -27909.76 | H227: -408389.88 | I227: -10429.99 | J227: -91492.5 | K227: -129303.36 | L227: -657960.06 | M227: -242752.42 | N227: -17017.52 | O227: -9.13 | P227: 0 | Q227: 0 | R227: 0
C228: Vlr Intereses | D228: -337.76 | E228: -15.23 | F228: -6.99 | G228: -3.86 | H228: -94.08 | I228: -2.32 | J228: -20.26 | K228: -25.24 | L228: -124.85 | M228: -41.16 | N228: -3.77 | O228: 0 | P228: 0 | Q228: 0 | R228: 0
B229: Componente | C229: Total | D229: -1725297.1 | E229: -91274.76 | F229: -48442.23 | G229: -27913.62 | H229: -408483.96 | I229: -10432.31 | J229: -91512.76 | K229: -129328.6 | L229: -658084.91 | M229: -242793.58 | N229: -17021.29 | O229: -9.13 | P229: 0 | Q229: 0 | R229: 0
C230: Subsidio(-)/Contribucion(+) | D230: 161137.15 | E230: 3670.4 | F230: 2105.69 | G230: 1208.53 | H230: 43532.95 | I230: 1149.26 | J230: 10081.39 | K230: 14348.69 | L230: 73395.61 | M230: 9769.58 | N230: 1875.05 | O230: 0 | P230: 0 | Q230: 0 | R230: 0
B231: Subs/Cont | C231: Total | D231: 161137.15 | E231: 3670.4 | F231: 2105.69 | G231: 1208.53 | H231: 43532.95 | I231: 1149.26 | J231: 10081.39 | K231: 14348.69 | L231: 73395.61 | M231: 9769.58 | N231: 1875.05 | O231: 0 | P231: 0 | Q231: 0 | R231: 0
A232: NUEVO ESQUEMA | B232: Total | D232: -1564160 | E232: -87604.36 | F232: -46336.54 | G232: -26705.09 | H232: -364951.01 | I232: -9283.05 | J232: -81431.37 | K232: -114979.91 | L232: -584689.3 | M232: -233024 | N232: -15146.24 | O232: -9.13 | P232: 0 | Q232: 0 | R232: 0
C233: Vlr Servicio | D233: -10100250 | E233: -607294.85 | F233: -326671.62 | G233: -172683.09 | H233: -2111900.8 | I233: -70330.78 | J233: -637400.48 | K233: -763863.09 | L233: -3673670.2 | M233: -1615156.6 | N233: -117847.03 | O233: -30.9 | P233: -3400.44 | Q233: 0 | R233: 0
C234: Vlr Intereses | D234: -397350.61 | E234: -33893.04 | F234: -16136.18 | G234: -6879.74 | H234: -82482.34 | I234: -2952.82 | J234: -25776.6 | K234: -32756.7 | L234: -104055.6 | M234: -87594.34 | N234: -4823.72 | O234: 0.71 | P234: 0 | Q234: 0 | R234: -0.24
B235: Componente | C235: Total | D235: -10497600 | E235: -641187.89 | F235: -342807.8 | G235: -179562.83 | H235: -2194383.1 | I235: -73283.6 | J235: -663177.08 | K235: -796619.79 | L235: -3777725.8 | M235: -1702750.9 | N235: -122670.75 | O235: -30.19 | P235: -3400.44 | Q235: 0 | R235: -0.24
C236: Subsidio(-)/Contribucion(+) | D236: 1098663.6 | E236: 30030.42 | F236: 18785.99 | G236: 9703.94 | H236: 301708.72 | I236: 10087.81 | J236: 88465.97 | K236: 90031.21 | L236: 452691.34 | M236: 80706.35 | N236: 16451.83 | O236: 0 | P236: 0 | Q236: 0 | R236: 0
B237: Subs/Cont | C237: Total | D237: 1098663.6 | E237: 30030.42 | F237: 18785.99 | G237: 9703.94 | H237: 301708.72 | I237: 10087.81 | J237: 88465.97 | K237: 90031.21 | L237: 452691.34 | M237: 80706.35 | N237: 16451.83 | O237: 0 | P237: 0 | Q237: 0 | R237: 0
A238: OCCIDENTE | B238: Total | D238: -9398936.9 | E238: -611157.47 | F238: -324021.81 | G238: -169858.89 | H238: -1892674.4 | I238: -63195.79 | J238: -574711.11 | K238: -706588.58 | L238: -3325034.5 | M238: -1622044.6 | N238: -106218.92 | O238: -30.19 | P238: -3400.44 | Q238: 0 | R238: -0.24
A239: Total | D239: -1.7861971e+08 | E239: -12242020 | F239: -6680852.6 | G239: -3466237.9 | H239: -37225477 | I239: -1342599.8 | J239: -11701383 | K239: -11853134 | L239: -59096655 | M239: -32770917 | N239: -2190752.8 | O239: 27.97 | P239: -49900.44 | Q239: 0 | R239: 192.75
A316: TOTAL | B316: OPORTUNO | C316: Total | D316: =D239-P239 -> -1.7856981e+08 | E316: =E235+E229+E223 -> -11114784 | F316: =F235+F229+F223 -> -6043741.8 | G316: =G235+G229+G223 -> -3128653.8 | H316: =H235+H229+H223 -> -38609422 | I316: =I235+I229+I223 -> -1383863 | J316: =J235+J229+J223 -> -12066172 | K316: =K235+K229+K223 -> -12247409 | L316: =L235+L229+L223 -> -61013837 | ... R316: =R235+R229+R223 -> 192.75
C317: Subsidio(-)/Contribucion(+) | D317: =D237+D231+D225 -> -924544.12
...

Sheet SALDOS POR NOTA
B1: PROMOAMBIENTAL
C2: Total | D2: Componente TDF | E2: Componente TTL | F2: Componente TVIAT | G2: Aprovechamiento | H2: CCSA Prest.Aprov. | I2: Especiales | J2: Componente TCS | K2: Componente TLU | L2: Componente TBL | M2: Componente TRT | N2: CCSA Prest. No Aprov. | O2: Deb/Cred
B3: Vlr Servicio | C3: 610474.63 | D3: 31457.17 | E3: 17527.74 | F3: 8747.16 | G3: 161245.56 | H3: 5296.18 | I3: 0 | J3: 49817.24 | K3: 43798.38 | L3: 198669.66 | M3: 85917.24 | N3: 7999.99 | O3: -1.69
A4: Componente | B4: Total | C4: 610474.63 | D4: 31457.17 | E4: 17527.74 | F4: 8747.16 | G4: 161245.56 | H4: 5296.18 | I4: 0 | J4: 49817.24 | K4: 43798.38 | L4: 198669.66 | M4: 85917.24 | N4: 7999.99 | O4: -1.69
B5: Subsidio(-)/Contribucion(+) | C5: -21467.71 | D5: 1021.25 | E5: 569.02 | F5: 302.68 | G5: -11805.23 | H5: -273.34 | I5: 0 | J5: -3741.84 | K5: -1666.65 | L5: -8216.89 | M5: 2789.29 | N5: -446 | O5: 0
A6: Subs/Cont | B6: Total | C6: -21467.71 | D6: 1021.25 | E6: 569.02 | F6: 302.68 | G6: -11805.23 | H6: -273.34 | I6: 0 | J6: -3741.84 | K6: -1666.65 | L6: -8216.89 | M6: 2789.29 | N6: -446 | O6: 0
A7: Total | C7: 589006.92 | D7: 32478.42 | E7: 18096.76 | F7: 9049.84 | G7: 149440.33 | H7: 5022.84 | I7: 0 | J7: 46075.4 | K7: 42131.73 | L7: 190452.77 | M7: 88706.53 | N7: 7553.99 | O7: -1.69
B9: Total | C9: =C7-I7 -> 589006.92 | D9: =D4 -> 31457.17 | E9: =E4 -> 17527.74 | F9: =F4 -> 8747.16 | G9: =G4 -> 161245.56 | H9: =H4 -> 5296.18 | I9: =I4 -> 0 | J9: =J4 -> 49817.24 | K9: =K4 -> 43798.38 | ... P9: =P4 -> 0
B10: Subsidio(-)/Contribucion(+) | C10: =C6 -> -21467.71
B13: LIME
C14: Total | D14: Componente TDF | E14: Componente TTL | F14: Componente TVIAT | G14: Aprovechamiento | H14: CCSA Prest.Aprov. | I14: Especiales | J14: Componente TCS | K14: Componente TLU | L14: Componente TBL | M14: Componente TRT | N14: CCSA Prest. No Aprov. | O14: Deb/Cred
B15: Vlr Servicio | C15: 1892491.9 | D15: 163064.18 | E15: 104049.98 | F15: 29276.94 | G15: 518383.42 | H15: 16747.23 | I15: 0 | J15: 129955.32 | K15: 129030.3 | L15: 466888.64 | M15: 319038.69 | N15: 16066.11 | O15: -8.88
B16: Vlr Intereses | C16: 3621.15 | D16: 345.13 | E16: 194.86 | F16: 102.27 | G16: 783.49 | H16: 25.09 | I16: 0 | J16: 220.11 | K16: 213.42 | L16: 1010.61 | M16: 685.23 | N16: 40.94 | O16: 0
A17: Componente | B17: Total | C17: 1896113.1 | D17: 163409.31 | E17: 104244.84 | F17: 29379.21 | G17: 519166.91 | H17: 16772.32 | I17: 0 | J17: 130175.43 | K17: 129243.72 | L17: 467899.25 | M17: 319723.92 | N17: 16107.05 | O17: -8.88
B18: Subsidio(-)/Contribucion(+) | C18: -640396.29 | D18: -32142.69 | E18: -15328.96 | F18: -9507.47 | G18: -164746.93 | H18: -5636 | I18: 0 | J18: -68052.5 | K18: -49800.77 | L18: -222045.88 | M18: -64569.3 | N18: -8565.79 | O18: 0
A19: Subs/Cont | B19: Total | C19: -640396.29 | D19: -32142.69 | E19: -15328.96 | F19: -9507.47 | G19: -164746.93 | H19: -5636 | I19: 0 | J19: -68052.5 | K19: -49800.77 | L19: -222045.88 | M19: -64569.3 | N19: -8565.79 | O19: 0
A20: Total | C20: 1255716.8 | D20: 131266.62 | E20: 88915.88 | F20: 19871.74 | G20: 354419.98 | H20: 11136.32 | I20: 0 | J20: 62122.93 | K20: 79442.95 | L20: 245853.37 | M20: 255154.62 | N20: 7541.26 | O20: -8.88
B22: Total | C22: =C20-I20 -> 1255716.8 | D22: =D17 -> 163409.31 | E22: =E17 -> 104244.84 | F22: =F17 -> 29379.21 | G22: =G17 -> 519166.91 | H22: =H17 -> 16772.32 | I22: =I17 -> 0 | J22: =J17 -> 130175.43 | K22: =K17 -> 129243.72 | ... P22: =P17 -> 0
B23: Subsidio(-)/Contribucion(+) | C23: =C19 -> -640396.29
B26: CIUDAD LIMPIA
C27: Total | D27: Componente TDF | E27: Componente TTL | F27: Componente TVIAT | G27: Aprovechamiento | H27: CCSA Prest.Aprov. | I27: Especiales | J27: Componente TCS | K27: Componente TLU | L27: Componente TBL | M27: Componente TRT | N27: CCSA Prest. No Aprov. | O27: Deb/Cred
B28: Vlr Servicio | C28: 92308.17 | D28: 6267.13 | E28: 3492.01 | F28: 1857.22 | G28: 21047.14 | H28: 743.08 | I28: 0 | J28: 6518.28 | K28: 6377.76 | L28: 29933.14 | M28: 14860.01 | N28: 1212.4 | O28: 0
A29: Componente | B29: Total | C29: 92308.17 | D29: 6267.13 | E29: 3492.01 | F29: 1857.22 | G29: 21047.14 | H29: 743.08 | I29: 0 | J29: 6518.28 | K29: 6377.76 | L29: 29933.14 | M29: 14860.01 | N29: 1212.4 | O29: 0
B30: Subsidio(-)/Contribucion(+) | C30: 10027.54 | D30: 1594.44 | E30: 888.42 | F30: 472.5 | G30: 1052.36 | H30: 37.15 | I30: 0 | J30: 325.91 | K30: 318.89 | L30: 1496.66 | M30: 3780.59 | N30: 60.62 | O30: 0
A31: Subs/Cont | B31: Total | C31: 10027.54 | D31: 1594.44 | E31: 888.42 | F31: 472.5 | G31: 1052.36 | H31: 37.15 | I31: 0 | J31: 325.91 | K31: 318.89 | L31: 1496.66 | M31: 3780.59 | N31: 60.62 | O31: 0
A32: Total | C32: 102335.71 | D32: 7861.57 | E32: 4380.43 | F32: 2329.72 | G32: 22099.5 | H32: 780.23 | I32: 0 | J32: 6844.19 | K32: 6696.65 | L32: 31429.8 | M32: 18640.6 | N32: 1273.02 | O32: 0
B34: Total | C34: =C32-I32 -> 102335.71 | D34: =D29 -> 6267.13 | E34: =E29 -> 3492.01 | F34: =F29 -> 1857.22 | G34: =G29 -> 21047.14 | H34: =H29 -> 743.08 | I34: =I29 -> 0 | J34: =J29 -> 6518.28 | K34: =K29 -> 6377.76 | ... P34: =P29 -> 0
B35: Subsidio(-)/Contribucion(+) | C35: =C31 -> 10027.54
B38: BOGOTA LIMPIA
C39: Total | D39: Componente TDF | E39: Componente TTL | F39: Componente TVIAT | G39: Aprovechamiento | H39: CCSA Prest.Aprov. | I39: Especiales | J39: Componente TCS | K39: Componente TLU | L39: Componente TBL | M39: Componente TRT | N39: CCSA Prest. No Aprov. | O39: Deb/Cred
B40: Vlr Servicio | C40: 384704.1 | D40: 35792.41 | E40: 20194.46 | F40: 2067.44 | G40: 112556.14 | H40: 2826.23 | I40: 0 | J40: 27571.69 | K40: 34487.27 | L40: 48317.47 | M40: 96285.04 | N40: 4611.27 | O40: -5.32
B41: Vlr Intereses | C41: -1393.04 | D41: 0 | E41: 0 | F41: 0 | G41: 0 | H41: 0 | I41: 0 | J41: 0 | K41: 0 | L41: -1393.07 | M41: 0 | N41: 0 | O41: 0.03
A42: Componente | B42: Total | C42: 383311.06 | D42: 35792.41 | E42: 20194.46 | F42: 2067.44 | G42: 112556.14 | H42: 2826.23 | I42: 0 | J42: 27571.69 | K42: 34487.27 | L42: 46924.4 | M42: 96285.04 | N42: 4611.27 | O42: -5.29
B43: Subsidio(-)/Contribucion(+) | C43: -43651.25 | D43: -2153.83 | E43: -1213.99 | F43: -638.29 | G43: -10771.77 | H43: -277.32 | I43: 0 | J43: -2432.76 | K43: -3291.62 | L43: -16717.82 | M43: -5701.37 | N43: -452.48 | O43: 0
A44: Subs/Cont | B44: Total | C44: -43651.25 | D44: -2153.83 | E44: -1213.99 | F44: -638.29 | G44: -10771.77 | H44: -277.32 | I44: 0 | J44: -2432.76 | K44: -3291.62 | L44: -16717.82 | M44: -5701.37 | N44: -452.48 | O44: 0
A45: Total | C45: 339659.81 | D45: 33638.58 | E45: 18980.47 | F45: 1429.15 | G45: 101784.37 | H45: 2548.91 | I45: 0 | J45: 25138.93 | K45: 31195.65 | L45: 30206.58 | M45: 90583.67 | N45: 4158.79 | O45: -5.29
B47: Total | C47: =C45-I45 -> 339659.81 | D47: =D42 -> 35792.41 | E47: =E42 -> 20194.46 | F47: =F42 -> 2067.44 | G47: =G42 -> 112556.14 | H47: =H42 -> 2826.23 | I47: =I42 -> 0 | J47: =J42 -> 27571.69 | K47: =K42 -> 34487.27 | ... P47: =P42 -> 0
B48: Subsidio(-)/Contribucion(+) | C48: =C44 -> -43651.25
B51: AREA LIMPIA
C52: Total | D52: Componente TDF | E52: Componente TTL | F52: Componente TVIAT | G52: Aprovechamiento | H52: CCSA Prest.Aprov. | I52: Especiales | J52: Componente TCS | K52: Componente TLU | L52: Componente TBL | M52: Componente TRT | N52: CCSA Prest. No Aprov. | O52: Deb/Cred
B53: Vlr Servicio | C53: 0 | D53: 0 | E53: 0 | F53: 0 | G53: 0 | H53: 0 | I53: 0 | J53: 0 | K53: 0 | L53: 0 | M53: 0 | N53: 0 | O53: 0
B54: Vlr Intereses | C54: 0 | D54: 0 | E54: 0 | F54: 0 | G54: 0 | H54: 0 | I54: 0 | J54: 0 | K54: 0 | L54: 0 | M54: 0 | N54: 0 | O54: 0
A55: Componente | B55: Total | C55: 0 | D55: 0 | E55: 0 | F55: 0 | G55: 0 | H55: 0 | I55: 0 | J55: 0 | K55: 0 | L55: 0 | M55: 0 | N55: 0 | O55: 0
B56: Subsidio(-)/Contribucion(+) | C56: 0 | D56: 0 | E56: 0 | F56: 0 | G56: 0 | H56: 0 | I56: 0 | J56: 0 | K56: 0 | L56: 0 | M56: 0 | N56: 0 | O56: 0
A57: Subs/Cont | B57: Total | C57: 0 | D57: 0 | E57: 0 | F57: 0 | G57: 0 | H57: 0 | I57: 0 | J57: 0 | K57: 0 | L57: 0 | M57: 0 | N57: 0 | O57: 0
A58: Total | C58: 0 | D58: 0 | E58: 0 | F58: 0 | G58: 0 | H58: 0 | I58: 0 | J58: 0 | K58: 0 | L58: 0 | M58: 0 | N58: 0 | O58: 0
B60: Total | C60: =C58-I58 -> 0 | D60: =D55 -> 0 | E60: =E55 -> 0 | F60: =F55 -> 0 | G60: =G55 -> 0 | H60: =H55 -> 0 | I60: =I55 -> 0 | J60: =J55 -> 0 | K60: =K55 -> 0 | ... P60: =P55 -> 0
B61: Subsidio(-)/Contribucion(+) | C61: =C57 -> 0

Sheet RETRIBUCION NEGATIVA
B1: PROMOAMBIENTAL
C2: Total | D2: Componente TDF | E2: Componente TTL | F2: Componente TVIAT | G2: Aprovechamiento | H2: CCSA Prest.Aprov. | I2: Especiales | J2: Componente TCS | K2: Componente TLU | L2: Componente TBL | M2: Componente TRT | N2: CCSA Prest. No Aprov. | O2: Deb/Cred
B3: Vlr Intereses | C3: 0 | D3: 0 | E3: 0 | F3: 0 | G3: 0 | H3: 0 | I3: 0 | J3: 0 | K3: 0 | L3: 0 | M3: 0 | N3: 0 | O3: 0
B4: Vlr Servicio | C4: 0 | D4: 0 | E4: 0 | F4: 0 | G4: 0 | H4: 0 | I4: 0 | J4: 0 | K4: 0 | L4: 0 | M4: 0 | N4: 0 | O4: 0
A5: Componente | B5: Total | C5: 0 | D5: 0 | E5: 0 | F5: 0 | G5: 0 | H5: 0 | I5: 0 | J5: 0 | K5: 0 | L5: 0 | M5: 0 | N5: 0 | O5: 0
B6: Subsidio(-)/Contribucion(+) | C6: 0 | D6: 0 | E6: 0 | F6: 0 | G6: 0 | H6: 0 | I6: 0 | J6: 0 | K6: 0 | L6: 0 | M6: 0 | N6: 0 | O6: 0
A7: Subs/Cont | B7: Total | C7: 0 | D7: 0 | E7: 0 | F7: 0 | G7: 0 | H7: 0 | I7: 0 | J7: 0 | K7: 0 | L7: 0 | M7: 0 | N7: 0 | O7: 0
A8: Total | C8: 0 | D8: 0 | E8: 0 | F8: 0 | G8: 0 | H8: 0 | I8: 0 | J8: 0 | K8: 0 | L8: 0 | M8: 0 | N8: 0 | O8: 0
B10: Total | C10: =C8-I8 -> 0 | D10: =D5 -> 0 | E10: =E5 -> 0 | F10: =F5 -> 0 | G10: =G5 -> 0 | H10: =H5 -> 0 | I10: =I5 -> 0 | J10: =J5 -> 0 | K10: =K5 -> 0 | ... O10: =O5 -> 0
B11: Subsidio(-)/Contribucion(+) | C11: =C7 -> 0
B14: LIME
C15: Total | D15: Componente TDF | E15: Componente TTL | F15: Componente TVIAT | G15: Aprovechamiento | H15: CCSA Prest.Aprov. | I15: Especiales | J15: Componente TCS | K15: Componente TLU | L15: Componente TBL | M15: Componente TRT | N15: CCSA Prest. No Aprov. | O15: Deb/Cred
B16: Vlr Intereses | C16: 0 | D16: 0 | E16: 0 | F16: 0 | G16: 0 | H16: 0 | I16: 0 | J16: 0 | K16: 0 | L16: 0 | M16: 0 | N16: 0 | O16: 0
B17: Vlr Servicio | C17: 0 | D17: 0 | E17: 0 | F17: 0 | G17: 0 | H17: 0 | I17: 0 | J17: 0 | K17: 0 | L17: 0 | M17: 0 | N17: 0 | O17: 0
A18: Componente | B18: Total | C18: 0 | D18: 0 | E18: 0 | F18: 0 | G18: 0 | H18: 0 | I18: 0 | J18: 0 | K18: 0 | L18: 0 | M18: 0 | N18: 0 | O18: 0
B19: Subsidio(-)/Contribucion(+) | C19: 0 | D19: 0 | E19: 0 | F19: 0 | G19: 0 | H19: 0 | I19: 0 | J19: 0 | K19: 0 | L19: 0 | M19: 0 | N19: 0 | O19: 0
A20: Subs/Cont | B20: Total | C20: 0 | D20: 0 | E20: 0 | F20: 0 | G20: 0 | H20: 0 | I20: 0 | J20: 0 | K20: 0 | L20: 0 | M20: 0 | N20: 0 | O20: 0
A21: Total | C21: 0 | D21: 0 | E21: 0 | F21: 0 | G21: 0 | H21: 0 | I21: 0 | J21: 0 | K21: 0 | L21: 0 | M21: 0 | N21: 0 | O21: 0
B23: Total | C23: =C21-I21 -> 0 | D23: =D18 -> 0 | E23: =E18 -> 0 | F23: =F18 -> 0 | G23: =G18 -> 0 | H23: =H18 -> 0 | I23: =I18 -> 0 | J23: =J18 -> 0 | K23: =K18 -> 0 | ... O23: =O18 -> 0
B24: Subsidio(-)/Contribucion(+) | C24: =C20 -> 0
B27: CIUDAD LIMPIA
C28: Total | D28: Componente TDF | E28: Componente TTL | F28: Componente TVIAT | G28: Aprovechamiento | H28: CCSA Prest.Aprov. | I28: Especiales | J28: Componente TCS | K28: Componente TLU | L28: Componente TBL | M28: Componente TRT | N28: CCSA Prest. No Aprov. | O28: Deb/Cred
B29: Vlr Intereses | C29: 0 | D29: 0 | E29: 0 | F29: 0 | G29: 0 | H29: 0 | I29: 0 | J29: 0 | K29: 0 | L29: 0 | M29: 0 | N29: 0 | O29: 0
B30: Vlr Servicio | C30: 0 | D30: 0 | E30: 0 | F30: 0 | G30: 0 | H30: 0 | I30: 0 | J30: 0 | K30: 0 | L30: 0 | M30: 0 | N30: 0 | O30: 0
A31: Componente | B31: Total | C31: 0 | D31: 0 | E31: 0 | F31: 0 | G31: 0 | H31: 0 | I31: 0 | J31: 0 | K31: 0 | L31: 0 | M31: 0 | N31: 0 | O31: 0
B32: Subsidio(-)/Contribucion(+) | C32: 0 | D32: 0 | E32: 0 | F32: 0 | G32: 0 | H32: 0 | I32: 0 | J32: 0 | K32: 0 | L32: 0 | M32: 0 | N32: 0 | O32: 0
A33: Subs/Cont | B33: Total | C33: 0 | D33: 0 | E33: 0 | F33: 0 | G33: 0 | H33: 0 | I33: 0 | J33: 0 | K33: 0 | L33: 0 | M33: 0 | N33: 0 | O33: 0
A34: Total | C34: 0 | D34: 0 | E34: 0 | F34: 0 | G34: 0 | H34: 0 | I34: 0 | J34: 0 | K34: 0 | L34: 0 | M34: 0 | N34: 0 | O34: 0
B36: Total | C36: =C34-I34 -> 0 | D36: =D31 -> 0 | E36: =E31 -> 0 | F36: =F31 -> 0 | G36: =G31 -> 0 | H36: =H31 -> 0 | I36: =I31 -> 0 | J36: =J31 -> 0 | K36: =K31 -> 0 | ... O36: =O31 -> 0
B37: Subsidio(-)/Contribucion(+) | C37: =C33 -> 0
B40: BOGOTA LIMPIA
C41: Total | D41: Componente TDF | E41: Componente TTL | F41: Componente TVIAT | G41: Aprovechamiento | H41: CCSA Prest.Aprov. | I41: Especiales | J41: Componente TCS | K41: Componente TLU | L41: Componente TBL | M41: Componente TRT | N41: CCSA Prest. No Aprov. | O41: Deb/Cred
B42: Vlr Intereses | C42: 0 | D42: 0 | E42: 0 | F42: 0 | G42: 0 | H42: 0 | I42: 0 | J42: 0 | K42: 0 | L42: 0 | M42: 0 | N42: 0 | O42: 0
B43: Vlr Servicio | C43: 0 | D43: 0 | E43: 0 | F43: 0 | G43: 0 | H43: 0 | I43: 0 | J43: 0 | K43: 0 | L43: 0 | M43: 0 | N43: 0 | O43: 0
A44: Componente | B44: Total | C44: 0 | D44: 0 | E44: 0 | F44: 0 | G44: 0 | H44: 0 | I44: 0 | J44: 0 | K44: 0 | L44: 0 | M44: 0 | N44: 0 | O44: 0
B45: Subsidio(-)/Contribucion(+) | C45: 0 | D45: 0 | E45: 0 | F45: 0 | G45: 0 | H45: 0 | I45: 0 | J45: 0 | K45: 0 | L45: 0 | M45: 0 | N45: 0 | O45: 0
A46: Subs/Cont | B46: Total | C46: 0 | D46: 0 | E46: 0 | F46: 0 | G46: 0 | H46: 0 | I46: 0 | J46: 0 | K46: 0 | L46: 0 | M46: 0 | N46: 0 | O46: 0
A47: Total | C47: 0 | D47: 0 | E47: 0 | F47: 0 | G47: 0 | H47: 0 | I47: 0 | J47: 0 | K47: 0 | L47: 0 | M47: 0 | N47: 0 | O47: 0
B49: Total | C49: =C47-I47 -> 0 | D49: =D44 -> 0 | E49: =E44 -> 0 | F49: =F44 -> 0 | G49: =G44 -> 0 | H49: =H44 -> 0 | I49: =I44 -> 0 | J49: =J44 -> 0 | K49: =K44 -> 0 | ... O49: =O44 -> 0
B50: Subsidio(-)/Contribucion(+) | C50: =C46 -> 0
B53: AREA LIMPIA
C54: Total | D54: Componente TDF | E54: Componente TTL | F54: Componente TVIAT | G54: Aprovechamiento | H54: CCSA Prest.Aprov. | I54: Especiales | J54: Componente TCS | K54: Componente TLU | L54: Componente TBL | M54: Componente TRT | N54: CCSA Prest. No Aprov. | O54: Deb/Cred
B55: Vlr Servicio | C55: 0 | D55: 0 | E55: 0 | F55: 0 | G55: 0 | H55: 0 | I55: 0 | J55: 0 | K55: 0 | L55: 0 | M55: 0 | N55: 0 | O55: 0
A56: Componente | B56: Total | C56: 0 | D56: 0 | E56: 0 | F56: 0 | G56: 0 | H56: 0 | I56: 0 | J56: 0 | K56: 0 | L56: 0 | M56: 0 | N56: 0 | O56: 0
B57: Subsidio(-)/Contribucion(+) | C57: 0 | D57: 0 | E57: 0 | F57: 0 | G57: 0 | H57: 0 | I57: 0 | J57: 0 | K57: 0 | L57: 0 | M57: 0 | N57: 0 | O57: 0
A58: Subs/Cont | B58: Total | C58: 0 | D58: 0 | E58: 0 | F58: 0 | G58: 0 | H58: 0 | I58: 0 | J58: 0 | K58: 0 | L58: 0 | M58: 0 | N58: 0 | O58: 0
A59: Total | C59: 0 | D59: 0 | E59: 0 | F59: 0 | G59: 0 | H59: 0 | I59: 0 | J59: 0 | K59: 0 | L59: 0 | M59: 0 | N59: 0 | O59: 0
B61: Total | C61: =C59-I59 -> 0 | D61: =D56 -> 0 | E61: =E56 -> 0 | F61: =F56 -> 0 | G61: =G56 -> 0 | H61: =H56 -> 0 | I61: =I56 -> 0 | J61: =J56 -> 0 | K61: =K56 -> 0 | ... O61: =O56 -> 0
B62: Subsidio(-)/Contribucion(+) | C62: =C58 -> 0

Sheet AJUSTES - SF-T
F3: PROCERASEO S.A.S. | I3: NIT: 901 153 639 - 0 | M3: Codigo Remuneración: | N3: ='CONSOLIDADO_TOTAL RECAUDO'!N3 -> 2026092 | U3: PROCERASEO S.A.S. | W3: NIT: 901 153 639 - 0 | AA3: Codigo Remuneración: | AC3: =N3 -> 2026092
F4: 3. ESQUEMA FINANCIERO DEL SERVICIO PUBLICO DE ASEO | U4: 3. ESQUEMA FINANCIERO DEL SERVICIO PUBLICO DE ASEO
F5: Resoluciòn UAESP Número 27 de 2018 | U5: Resoluciòn UAESP Número 27 de 2018
C6: Fecha de Proceso: | D6: ='CONSOLIDADO_TOTAL RECAUDO'!D6 -> 46297 | F6: SALDOS A FAVOR POR NOTA | U6: =+F6 -> SALDOS A FAVOR POR NOTA
C7: Hora: | D7: ='CONSOLIDADO_TOTAL RECAUDO'!D7 -> 0.58333333 | F7: Fecha Desde: | H7: ='CONSOLIDADO_TOTAL RECAUDO'!G7 -> 46281 | J7: Feha Hasta: | K7: ='CONSOLIDADO_TOTAL RECAUDO'!K7 -> 46295 | U7: =F7 -> Fecha Desde: | V7: =H7 -> 46281 | X7: =J7 -> Feha Hasta: | Y7: =K7 -> 46295
B8: ASE | C8: Concesionarios | D8: Recaudo Total | E8: Recaudo por disposicion final | F8: Recaudo por tratamiento de lixiviados | G8: Recaudo por Componente VIAT ( Decreto 2412/2018) | H8: Recaudo por aprovechamiento | I8: Recaudo del componente de comercializacion para Aprovechamiento (11,4%) | J8: Balance de subsidio o contribuciones | K8: RECAUDO BASE DE REMUNERACION | L8: Costo de la Interventoría | M8: REMUNERACION FINAL | N8: Conceptos especiales | O8: REMUNERACION FINAL MAS CONCEPTOS ESPECIALES | S8: ASE | T8: Concesionarios | U8: Tarifa de Comercialización del Servicio. ( TCS) | V8: Tarifa de Limpieza Urbana del Servicio. ( TLU) | W8: Tarifa de Barrido y Limpieza del Servicio. ( TBL) | X8: Tarifa de Recolección y Transporte del Servicio. (TRT) | Y8: Recaudo del componente de comercializacion para Aprovechamiento (18,6%) | Z8: Costo de la Interventoría | AA8: Ajuste a la decena | AB8: Conceptos especiales | AC8: Diferencial Balance S / C (Fac vs Rec) | AD8: Balance S / C Con Baase en (Recaudo) | AE8: REMUNERACION FINAL MAS CONCEPTOS ESPECIALES
B9: 1 | C9: PROMOAMBIENTAL DISTRITO S.A.S. ESP. | D9: ='SALDOS POR NOTA'!C9 -> 589006.92 | E9: ='SALDOS POR NOTA'!D9 -> 31457.17 | F9: ='SALDOS POR NOTA'!E9 -> 17527.74 | G9: ='SALDOS POR NOTA'!F9 -> 8747.16 | H9: ='SALDOS POR NOTA'!G9 -> 161245.56 | I9: ='SALDOS POR NOTA'!H9 -> 5296.18 | J9: 0 | K9: =D9-E9-F9-G9-H9-I9-J9 -> 364733.11 | L9: 0 | M9: =K9-L9 -> 364733.11 | N9: ='SALDOS POR NOTA'!I9 -> 0 | O9: =M9+N9 -> 364733.11 | S9: 1 | T9: PROMOAMBIENTAL DISTRITO S.A.S. ESP. | U9: ='SALDOS POR NOTA'!J9 -> 49817.24 | V9: ='SALDOS POR NOTA'!K9 -> 43798.38 | W9: ='SALDOS POR NOTA'!L9 -> 198669.66 | X9: ='SALDOS POR NOTA'!M9 -> 85917.24 | Y9: ='SALDOS POR NOTA'!N9 -> 7999.99 | Z9: =L9*-1 -> 0 | AA9: ='SALDOS POR NOTA'!O9 -> -1.69 | AB9: =N9 -> 0 | AC9: =-J9+AD9 -> -21467.71 | AD9: ='SALDOS POR NOTA'!C10 -> -21467.71 | AE9: =SUM(U9:AC9) -> 364733.11 | AF9: =(AE9-O9) -> 0 | AG9: =AF9=0 -> TRUE
B10: 2 | C10: LIMPIEZA METROPOLITANA S.A. ESP. | D10: ='SALDOS POR NOTA'!C22 -> 1255716.8 | E10: ='SALDOS POR NOTA'!D22 -> 163409.31 | F10: ='SALDOS POR NOTA'!E22 -> 104244.84 | G10: ='SALDOS POR NOTA'!F22 -> 29379.21 | H10: ='SALDOS POR NOTA'!G22 -> 519166.91 | I10: ='SALDOS POR NOTA'!H22 -> 16772.32 | J10: 0 | K10: =D10-E10-F10-G10-H10-I10-J10 -> 422744.2 | L10: 0 | M10: =K10-L10 -> 422744.2 | N10: ='SALDOS POR NOTA'!I22 -> 0 | O10: =M10+N10 -> 422744.2 | S10: 2 | T10: LIMPIEZA METROPOLITANA S.A. ESP. | U10: ='SALDOS POR NOTA'!J22 -> 130175.43 | V10: ='SALDOS POR NOTA'!K22 -> 129243.72 | W10: ='SALDOS POR NOTA'!L22 -> 467899.25 | X10: ='SALDOS POR NOTA'!M22 -> 319723.92 | Y10: ='SALDOS POR NOTA'!N22 -> 16107.05 | Z10: =L10*-1 -> 0 | AA10: ='SALDOS POR NOTA'!O22 -> -8.88 | AB10: =N10 -> 0 | AC10: =-J10+AD10 -> -640396.29 | AD10: ='SALDOS POR NOTA'!C23 -> -640396.29 | AE10: =SUM(U10:AC10) -> 422744.2 | AF10: =(AE10-O10) -> 1.1641532e-10 | AG10: =AF10=0 -> FALSE
B11: 3 | C11: CIUDAD LIMPIA BOGOTA S.A. ESP. | D11: ='SALDOS POR NOTA'!C34 -> 102335.71 | E11: ='SALDOS POR NOTA'!D34 -> 6267.13 | F11: ='SALDOS POR NOTA'!E34 -> 3492.01 | G11: ='SALDOS POR NOTA'!F34 -> 1857.22 | H11: ='SALDOS POR NOTA'!G34 -> 21047.14 | I11: ='SALDOS POR NOTA'!H34 -> 743.08 | J11: 0 | K11: =D11-E11-F11-G11-H11-I11-J11 -> 68929.13 | L11: 0 | M11: =K11-L11 -> 68929.13 | N11: ='SALDOS POR NOTA'!I34 -> 0 | O11: =M11+N11 -> 68929.13 | S11: 3 | T11: CIUDAD LIMPIA BOGOTA S.A. ESP. | U11: ='SALDOS POR NOTA'!J34 -> 6518.28 | V11: ='SALDOS POR NOTA'!K34 -> 6377.76 | W11: ='SALDOS POR NOTA'!L34 -> 29933.14 | X11: ='SALDOS POR NOTA'!M34 -> 14860.01 | Y11: ='SALDOS POR NOTA'!N34 -> 1212.4 | Z11: =L11*-1 -> 0 | AA11: ='SALDOS POR NOTA'!O34 -> 0 | AB11: =N11 -> 0 | AC11: =-J11+AD11 -> 10027.54 | AD11: ='SALDOS POR NOTA'!C35 -> 10027.54 | AE11: =SUM(U11:AC11) -> 68929.13 | AF11: =(AE11-O11) -> 0 | AG11: =AF11=0 -> TRUE
B12: 4 | C12: BOGOTA LIMPIA S.A.S. ESP. | D12: ='SALDOS POR NOTA'!C47 -> 339659.81 | E12: ='SALDOS POR NOTA'!D47 -> 35792.41 | F12: ='SALDOS POR NOTA'!E47 -> 20194.46 | G12: ='SALDOS POR NOTA'!F47 -> 2067.44 | H12: ='SALDOS POR NOTA'!G47 -> 112556.14 | I12: ='SALDOS POR NOTA'!H47 -> 2826.23 | J12: 0 | K12: =D12-E12-F12-G12-H12-I12-J12 -> 166223.13 | L12: 0 | M12: =K12-L12 -> 166223.13 | N12: ='SALDOS POR NOTA'!I47 -> 0 | O12: =M12+N12 -> 166223.13 | S12: 4 | T12: BOGOTA LIMPIA S.A.S. ESP. | U12: ='SALDOS POR NOTA'!J47 -> 27571.69 | V12: ='SALDOS POR NOTA'!K47 -> 34487.27 | W12: ='SALDOS POR NOTA'!L47 -> 46924.4 | X12: ='SALDOS POR NOTA'!M47 -> 96285.04 | Y12: ='SALDOS POR NOTA'!N47 -> 4611.27 | Z12: =L12*-1 -> 0 | AA12: ='SALDOS POR NOTA'!O47 -> -5.29 | AB12: =N12 -> 0 | AC12: =-J12+AD12 -> -43651.25 | AD12: ='SALDOS POR NOTA'!C48 -> -43651.25 | AE12: =SUM(U12:AC12) -> 166223.13 | AF12: =(AE12-O12) -> -2.910383e-11 | AG12: =AF12=0 -> FALSE
B13: 5 | C13: AREA LIMPIA DISTRITO CAPITAL S.A.S. ESP. | D13: ='SALDOS POR NOTA'!C60 -> 0 | E13: ='SALDOS POR NOTA'!D60 -> 0 | F13: ='SALDOS POR NOTA'!E60 -> 0 | G13: ='SALDOS POR NOTA'!F60 -> 0 | H13: ='SALDOS POR NOTA'!G60 -> 0 | I13: ='SALDOS POR NOTA'!H60 -> 0 | J13: 0 | K13: =D13-E13-F13-G13-H13-I13-J13 -> 0 | L13: 0 | M13: =K13-L13 -> 0 | N13: ='SALDOS POR NOTA'!I60 -> 0 | O13: =M13+N13 -> 0 | S13: 5 | T13: AREA LIMPIA DISTRITO CAPITAL S.A.S. ESP. | U13: ='SALDOS POR NOTA'!J60 -> 0 | V13: ='SALDOS POR NOTA'!K60 -> 0 | W13: ='SALDOS POR NOTA'!L60 -> 0 | X13: ='SALDOS POR NOTA'!M60 -> 0 | Y13: ='SALDOS POR NOTA'!N60 -> 0 | Z13: =L13*-1 -> 0 | AA13: ='SALDOS POR NOTA'!O60 -> 0 | AB13: =N13 -> 0 | AC13: =-J13+AD13 -> 0 | AD13: ='SALDOS POR NOTA'!C61 -> 0 | AE13: =SUM(U13:AC13) -> 0 | AF13: =(AE13-O13) -> 0 | AG13: =AF13=0 -> TRUE
C14: TOTAL | D14: =SUM(D9:D13) -> 2286719.2 | E14: =SUM(E9:E13) -> 236926.02 | F14: =SUM(F9:F13) -> 145459.05 | G14: =SUM(G9:G13) -> 42051.03 | H14: =SUM(H9:H13) -> 814015.75 | I14: =SUM(I9:I13) -> 25637.81 | J14: =SUM(J9:J13) -> 0 | K14: =SUM(K9:K13) -> 1022629.6 | ... O14: =SUM(O9:O13) -> 1022629.6 | T14: TOTAL | U14: =SUM(U9:U13) -> 214082.64 | V14: =SUM(V9:V13) -> 213907.13 | W14: =SUM(W9:W13) -> 743426.45 | X14: =SUM(X9:X13) -> 516786.21 | Y14: =SUM(Y9:Y13) -> 29930.71 | Z14: =SUM(Z9:Z13) -> 0 | AA14: =SUM(AA9:AA13) -> -15.86 | AB14: =SUM(AB9:AB13) -> 0 | ... AF14: =SUM(AF9:AF13) -> 8.7311491e-11 | AG14: =AF14=0 -> FALSE
Y16: =SUM(U14:Y14) -> 1718133.1
F18: Firma autorizada
F22: PROCERASEO S.A.S. | I22: NIT: 901 153 639 - 0 | M22: Codigo Remuneración: | N22: =N3 -> 2026092 | U22: PROCERASEO S.A.S. | W22: NIT: 901 153 639 - 0 | AA22: Codigo Remuneración: | AC22: =N22 -> 2026092
F23: 3. ESQUEMA FINANCIERO DEL SERVICIO PUBLICO DE ASEO | U23: 3. ESQUEMA FINANCIERO DEL SERVICIO PUBLICO DE ASEO
F24: Resoluciòn UAESP Número 27 de 2018 | U24: Resoluciòn UAESP Número 27 de 2018
C25: Fecha de Proceso: | D25: =D6 -> 46297 | F25: RETRIBUCION NEGATIVA | U25: =+F25 -> RETRIBUCION NEGATIVA
C26: Hora: | D26: =D7 -> 0.58333333 | F26: Fecha Desde: | H26: =H7 -> 46281 | J26: Feha Hasta: | K26: =K7 -> 46295 | U26: =F26 -> Fecha Desde: | V26: =H26 -> 46281 | X26: =J26 -> Feha Hasta: | Y26: =K26 -> 46295
B27: ASE | C27: Concesionarios | D27: Recaudo Total | E27: Recaudo por disposicion final | F27: Recaudo por tratamiento de lixiviados | G27: Recaudo por Componente VIAT ( Decreto 2412/2018) | H27: Recaudo por aprovechamiento | I27: Recaudo del componente de comercializacion para Aprovechamiento (11,4%) | J27: Balance de subsidio o contribuciones | K27: RECAUDO BASE DE REMUNERACION | L27: Costo de la Interventoría | M27: REMUNERACION FINAL | N27: Conceptos especiales | O27: REMUNERACION FINAL MAS CONCEPTOS ESPECIALES | S27: ASE | T27: Concesionarios | U27: Tarifa de Comercialización del Servicio. ( TCS) | V27: Tarifa de Limpieza Urbana del Servicio. ( TLU) | W27: Tarifa de Barrido y Limpieza del Servicio. ( TBL) | X27: Tarifa de Recolección y Transporte del Servicio. (TRT) | Y27: Recaudo del componente de comercializacion para Aprovechamiento (18,6%) | Z27: Costo de la Interventoría | AA27: Ajuste a la decena | AB27: Conceptos especiales | AC27: Diferencial Balance S / C (Fac vs Rec) | AD27: Balance S / C Con Baase en (Recaudo) | AE27: REMUNERACION FINAL MAS CONCEPTOS ESPECIALES
B28: 1 | C28: PROMOAMBIENTAL DISTRITO S.A.S. ESP. | D28: ='RETRIBUCION NEGATIVA'!C10 -> 0 | E28: ='RETRIBUCION NEGATIVA'!D10 -> 0 | F28: ='RETRIBUCION NEGATIVA'!E10 -> 0 | G28: ='RETRIBUCION NEGATIVA'!F10 -> 0 | H28: ='RETRIBUCION NEGATIVA'!G10 -> 0 | I28: ='RETRIBUCION NEGATIVA'!H10 -> 0 | J28: 0 | K28: =D28-E28-F28-H28-I28-J28-G28 -> 0 | L28: 0 | M28: =K28-L28 -> 0 | N28: ='RETRIBUCION NEGATIVA'!I10 -> 0 | O28: =M28+N28 -> 0 | S28: 1 | T28: PROMOAMBIENTAL DISTRITO S.A.S. ESP. | U28: ='RETRIBUCION NEGATIVA'!J10 -> 0 | V28: ='RETRIBUCION NEGATIVA'!K10 -> 0 | W28: ='RETRIBUCION NEGATIVA'!L10 -> 0 | X28: ='RETRIBUCION NEGATIVA'!M10 -> 0 | Y28: ='RETRIBUCION NEGATIVA'!N10 -> 0 | Z28: =L28*-1 -> 0 | AA28: ='RETRIBUCION NEGATIVA'!O10 -> 0 | AB28: =N28 -> 0 | AC28: =-J28+AD28 -> 0 | AD28: ='RETRIBUCION NEGATIVA'!C11 -> 0 | AE28: =SUM(U28:AC28) -> 0 | AF28: =(AE28-O28) -> 0 | AG28: =AF28=0 -> TRUE
B29: 2 | C29: LIMPIEZA METROPOLITANA S.A. ESP. | D29: ='RETRIBUCION NEGATIVA'!C23 -> 0 | E29: ='RETRIBUCION NEGATIVA'!D23 -> 0 | F29: ='RETRIBUCION NEGATIVA'!E23 -> 0 | G29: ='RETRIBUCION NEGATIVA'!F23 -> 0 | H29: ='RETRIBUCION NEGATIVA'!G23 -> 0 | I29: ='RETRIBUCION NEGATIVA'!H23 -> 0 | J29: 0 | K29: =D29-E29-F29-H29-I29-J29-G29 -> 0 | L29: 0 | M29: =K29-L29 -> 0 | N29: ='RETRIBUCION NEGATIVA'!I23 -> 0 | O29: =M29+N29 -> 0 | S29: 2 | T29: LIMPIEZA METROPOLITANA S.A. ESP. | U29: ='RETRIBUCION NEGATIVA'!J23 -> 0 | V29: ='RETRIBUCION NEGATIVA'!K23 -> 0 | W29: ='RETRIBUCION NEGATIVA'!L23 -> 0 | X29: ='RETRIBUCION NEGATIVA'!M23 -> 0 | Y29: ='RETRIBUCION NEGATIVA'!N23 -> 0 | Z29: =L29*-1 -> 0 | AA29: ='RETRIBUCION NEGATIVA'!O23 -> 0 | AB29: =N29 -> 0 | AC29: =-J29+AD29 -> 0 | AD29: ='RETRIBUCION NEGATIVA'!C24 -> 0 | AE29: =SUM(U29:AC29) -> 0 | AF29: =(AE29-O29) -> 0 | AG29: =AF29=0 -> TRUE
B30: 3 | C30: CIUDAD LIMPIA BOGOTA S.A. ESP. | D30: ='RETRIBUCION NEGATIVA'!C36 -> 0 | E30: ='RETRIBUCION NEGATIVA'!D36 -> 0 | F30: ='RETRIBUCION NEGATIVA'!E36 -> 0 | G30: ='RETRIBUCION NEGATIVA'!F36 -> 0 | H30: ='RETRIBUCION NEGATIVA'!G36 -> 0 | I30: ='RETRIBUCION NEGATIVA'!H36 -> 0 | J30: 0 | K30: =D30-E30-F30-H30-I30-J30-G30 -> 0 | L30: 0 | M30: =K30-L30 -> 0 | N30: ='RETRIBUCION NEGATIVA'!I36 -> 0 | O30: =M30+N30 -> 0 | S30: 3 | T30: CIUDAD LIMPIA BOGOTA S.A. ESP. | U30: ='RETRIBUCION NEGATIVA'!J36 -> 0 | V30: ='RETRIBUCION NEGATIVA'!K36 -> 0 | W30: ='RETRIBUCION NEGATIVA'!L36 -> 0 | X30: ='RETRIBUCION NEGATIVA'!M36 -> 0 | Y30: ='RETRIBUCION NEGATIVA'!N36 -> 0 | Z30: =L30*-1 -> 0 | AA30: ='RETRIBUCION NEGATIVA'!O36 -> 0 | AB30: =N30 -> 0 | AC30: =-J30+AD30 -> 0 | AD30: ='RETRIBUCION NEGATIVA'!C37 -> 0 | AE30: =SUM(U30:AC30) -> 0 | AF30: =(AE30-O30) -> 0 | AG30: =AF30=0 -> TRUE
B31: 4 | C31: BOGOTA LIMPIA S.A.S. ESP. | D31: ='RETRIBUCION NEGATIVA'!C49 -> 0 | E31: ='RETRIBUCION NEGATIVA'!D49 -> 0 | F31: ='RETRIBUCION NEGATIVA'!E49 -> 0 | G31: ='RETRIBUCION NEGATIVA'!F49 -> 0 | H31: ='RETRIBUCION NEGATIVA'!G49 -> 0 | I31: ='RETRIBUCION NEGATIVA'!H49 -> 0 | J31: 0 | K31: =D31-E31-F31-H31-I31-J31-G31 -> 0 | L31: 0 | M31: =K31-L31 -> 0 | N31: ='RETRIBUCION NEGATIVA'!I49 -> 0 | O31: =M31+N31 -> 0 | S31: 4 | T31: BOGOTA LIMPIA S.A.S. ESP. | U31: ='RETRIBUCION NEGATIVA'!J49 -> 0 | V31: ='RETRIBUCION NEGATIVA'!K49 -> 0 | W31: ='RETRIBUCION NEGATIVA'!L49 -> 0 | X31: ='RETRIBUCION NEGATIVA'!M49 -> 0 | Y31: ='RETRIBUCION NEGATIVA'!N49 -> 0 | Z31: =L31*-1 -> 0 | AA31: ='RETRIBUCION NEGATIVA'!O49 -> 0 | AB31: =N31 -> 0 | AC31: =-J31+AD31 -> 0 | AD31: ='RETRIBUCION NEGATIVA'!C50 -> 0 | AE31: =SUM(U31:AC31) -> 0 | AF31: =(AE31-O31) -> 0 | AG31: =AF31=0 -> TRUE
B32: 5 | C32: AREA LIMPIA DISTRITO CAPITAL S.A.S. ESP. | D32: ='RETRIBUCION NEGATIVA'!C61 -> 0 | E32: ='RETRIBUCION NEGATIVA'!D61 -> 0 | F32: ='RETRIBUCION NEGATIVA'!E61 -> 0 | G32: ='RETRIBUCION NEGATIVA'!F61 -> 0 | H32: ='RETRIBUCION NEGATIVA'!G61 -> 0 | I32: ='RETRIBUCION NEGATIVA'!H61 -> 0 | J32: 0 | K32: =D32-E32-F32-H32-I32-J32-G32 -> 0 | L32: 0 | M32: =K32-L32 -> 0 | N32: ='RETRIBUCION NEGATIVA'!I61 -> 0 | O32: =M32+N32 -> 0 | S32: 5 | T32: AREA LIMPIA DISTRITO CAPITAL S.A.S. ESP. | U32: ='RETRIBUCION NEGATIVA'!J61 -> 0 | V32: ='RETRIBUCION NEGATIVA'!K61 -> 0 | W32: ='RETRIBUCION NEGATIVA'!L61 -> 0 | X32: ='RETRIBUCION NEGATIVA'!M61 -> 0 | Y32: ='RETRIBUCION NEGATIVA'!N61 -> 0 | Z32: =L32*-1 -> 0 | AA32: ='RETRIBUCION NEGATIVA'!O61 -> 0 | AB32: =N32 -> 0 | AC32: =-J32+AD32 -> 0 | AD32: ='RETRIBUCION NEGATIVA'!C62 -> 0 | AE32: =SUM(U32:AC32) -> 0 | AF32: =(AE32-O32) -> 0 | AG32: =AF32=0 -> TRUE
C33: TOTAL | D33: =SUM(D28:D32) -> 0 | E33: =SUM(E28:E32) -> 0 | F33: =SUM(F28:F32) -> 0 | G33: =SUM(G28:G32) -> 0 | H33: =SUM(H28:H32) -> 0 | I33: =SUM(I28:I32) -> 0 | J33: =SUM(J28:J32) -> 0 | K33: =SUM(K28:K32) -> 0 | ... O33: =SUM(O28:O32) -> 0 | T33: TOTAL | U33: =SUM(U28:U32) -> 0 | V33: =SUM(V28:V32) -> 0 | W33: =SUM(W28:W32) -> 0 | X33: =SUM(X28:X32) -> 0 | Y33: =SUM(Y28:Y32) -> 0 | Z33: =SUM(Z28:Z32) -> 0 | AA33: =SUM(AA28:AA32) -> 0 | AB33: =SUM(AB28:AB32) -> 0 | ... AF33: =SUM(AF28:AF32) -> 0 | AG33: =AF33=0 -> TRUE
J35: VALIDADOR DE POSTIVIOS EN REMUNERACION NEGATIVA | M35: =IF(MAX(D28:O32,U28:AE32)>0.9,"ERROR",TRUE) -> TRUE | Y35: =SUM(U33:Y33) -> 0
F37: Firma autorizada
F41: PROCERASEO S.A.S. | I41: NIT: 901 153 639 - 0 | M41: Codigo Remuneración: | N41: =N3 -> 2026092 | U41: PROCERASEO S.A.S. | W41: NIT: 901 153 639 - 0 | AA41: Codigo Remuneración: | AC41: =N41 -> 2026092
F42: 3. ESQUEMA FINANCIERO DEL SERVICIO PUBLICO DE ASEO | U42: 3. ESQUEMA FINANCIERO DEL SERVICIO PUBLICO DE ASEO
F43: Resoluciòn UAESP Número 27 de 2018 | U43: Resoluciòn UAESP Número 27 de 2018
C44: Fecha de Proceso: | D44: =D6 -> 46297 | F44: CONSOLIDADO SALDOS A FAVOR | U44: =+F44 -> CONSOLIDADO SALDOS A FAVOR
C45: Hora: | D45: =D7 -> 0.58333333 | F45: Fecha Desde: | H45: =H7 -> 46281 | J45: Feha Hasta: | K45: =K7 -> 46295 | U45: =F45 -> Fecha Desde: | V45: =H45 -> 46281 | X45: =J45 -> Feha Hasta: | Y45: =K45 -> 46295
B46: ASE | C46: Concesionarios | D46: Recaudo Total | E46: Recaudo por disposicion final | F46: Recaudo por tratamiento de lixiviados | G46: Recaudo por Componente VIAT ( Decreto 2412/2018) | H46: Recaudo por aprovechamiento | I46: Recaudo del componente de comercializacion para Aprovechamiento (11,4%) | J46: Balance de subsidio o contribuciones | K46: RECAUDO BASE DE REMUNERACION | L46: Costo de la Interventoría | M46: REMUNERACION FINAL | N46: Conceptos especiales | O46: REMUNERACION FINAL MAS CONCEPTOS ESPECIALES | S46: ASE | T46: Concesionarios | U46: Tarifa de Comercialización del Servicio. ( TCS) | V46: Tarifa de Limpieza Urbana del Servicio. ( TLU) | W46: Tarifa de Barrido y Limpieza del Servicio. ( TBL) | X46: Tarifa de Recolección y Transporte del Servicio. (TRT) | Y46: Recaudo del componente de comercializacion para Aprovechamiento (18,6%) | Z46: Costo de la Interventoría | AA46: Ajuste a la decena | AB46: Conceptos especiales | AC46: Diferencial Balance S / C (Fac vs Rec) | AD46: Balance S / C Con Baase en (Recaudo) | AE46: REMUNERACION FINAL MAS CONCEPTOS ESPECIALES
B47: 1 | C47: PROMOAMBIENTAL DISTRITO S.A.S. ESP. | D47: =D9+D28 -> 589006.92 | E47: =E9+E28 -> 31457.17 | F47: =F9+F28 -> 17527.74 | G47: =G9+G28 -> 8747.16 | H47: =H9+H28 -> 161245.56 | I47: =I9+I28 -> 5296.18 | J47: =J9+J28 -> 0 | K47: =D47-E47-F47-G47-H47-I47-J47 -> 364733.11 | L47: 0 | M47: =K47-L47 -> 364733.11 | N47: =N9+N28 -> 0 | O47: =M47+N47 -> 364733.11 | S47: 1 | T47: PROMOAMBIENTAL DISTRITO S.A.S. ESP. | U47: =U9+U28 -> 49817.24 | V47: =V9+V28 -> 43798.38 | W47: =W9+W28 -> 198669.66 | X47: =X9+X28 -> 85917.24 | Y47: =Y9+Y28 -> 7999.99 | Z47: =-L47 -> 0 | AA47: =AA9+AA28 -> -1.69 | AB47: =AB9+AB28 -> 0 | AC47: =AC9+AC28 -> -21467.71 | AD47: =AD9+AD28 -> -21467.71 | AE47: =SUM(U47:AC47) -> 364733.11 | AF47: =(AE47-O47) -> 0 | AG47: =AF47=0 -> TRUE
B48: 2 | C48: LIMPIEZA METROPOLITANA S.A. ESP. | D48: =D10+D29 -> 1255716.8 | E48: =E10+E29 -> 163409.31 | F48: =F10+F29 -> 104244.84 | G48: =G10+G29 -> 29379.21 | H48: =H10+H29 -> 519166.91 | I48: =I10+I29 -> 16772.32 | J48: =J10+J29 -> 0 | K48: =D48-E48-F48-G48-H48-I48-J48 -> 422744.2 | L48: 0 | M48: =K48-L48 -> 422744.2 | N48: =N10+N29 -> 0 | O48: =M48+N48 -> 422744.2 | S48: 2 | T48: LIMPIEZA METROPOLITANA S.A. ESP. | U48: =U10+U29 -> 130175.43 | V48: =V10+V29 -> 129243.72 | W48: =W10+W29 -> 467899.25 | X48: =X10+X29 -> 319723.92 | Y48: =Y10+Y29 -> 16107.05 | Z48: =-L48 -> 0 | AA48: =AA10+AA29 -> -8.88 | AB48: =AB10+AB29 -> 0 | AC48: =AC10+AC29 -> -640396.29 | AD48: =AD10+AD29 -> -640396.29 | AE48: =SUM(U48:AC48) -> 422744.2 | AF48: =(AE48-O48) -> 1.1641532e-10 | AG48: =AF48=0 -> FALSE
B49: 3 | C49: CIUDAD LIMPIA BOGOTA S.A. ESP. | D49: =D11+D30 -> 102335.71 | E49: =E11+E30 -> 6267.13 | F49: =F11+F30 -> 3492.01 | G49: =G11+G30 -> 1857.22 | H49: =H11+H30 -> 21047.14 | I49: =I11+I30 -> 743.08 | J49: =J11+J30 -> 0 | K49: =D49-E49-F49-G49-H49-I49-J49 -> 68929.13 | L49: 0 | M49: =K49-L49 -> 68929.13 | N49: =N11+N30 -> 0 | O49: =M49+N49 -> 68929.13 | S49: 3 | T49: CIUDAD LIMPIA BOGOTA S.A. ESP. | U49: =U11+U30 -> 6518.28 | V49: =V11+V30 -> 6377.76 | W49: =W11+W30 -> 29933.14 | X49: =X11+X30 -> 14860.01 | Y49: =Y11+Y30 -> 1212.4 | Z49: =-L49 -> 0 | AA49: =AA11+AA30 -> 0 | AB49: =AB11+AB30 -> 0 | AC49: =AC11+AC30 -> 10027.54 | AD49: =AD11+AD30 -> 10027.54 | AE49: =SUM(U49:AC49) -> 68929.13 | AF49: =(AE49-O49) -> 0 | AG49: =AF49=0 -> TRUE
B50: 4 | C50: BOGOTA LIMPIA S.A.S. ESP. | D50: =D12+D31 -> 339659.81 | E50: =E12+E31 -> 35792.41 | F50: =F12+F31 -> 20194.46 | G50: =G12+G31 -> 2067.44 | H50: =H12+H31 -> 112556.14 | I50: =I12+I31 -> 2826.23 | J50: =J12+J31 -> 0 | K50: =D50-E50-F50-G50-H50-I50-J50 -> 166223.13 | L50: 0 | M50: =K50-L50 -> 166223.13 | N50: =N12+N31 -> 0 | O50: =M50+N50 -> 166223.13 | S50: 4 | T50: BOGOTA LIMPIA S.A.S. ESP. | U50: =U12+U31 -> 27571.69 | V50: =V12+V31 -> 34487.27 | W50: =W12+W31 -> 46924.4 | X50: =X12+X31 -> 96285.04 | Y50: =Y12+Y31 -> 4611.27 | Z50: =-L50 -> 0 | AA50: =AA12+AA31 -> -5.29 | AB50: =AB12+AB31 -> 0 | AC50: =AC12+AC31 -> -43651.25 | AD50: =AD12+AD31 -> -43651.25 | AE50: =SUM(U50:AC50) -> 166223.13 | AF50: =(AE50-O50) -> -2.910383e-11 | AG50: =AF50=0 -> FALSE
B51: 5 | C51: AREA LIMPIA DISTRITO CAPITAL S.A.S. ESP. | D51: =D13+D32 -> 0 | E51: =E13+E32 -> 0 | F51: =F13+F32 -> 0 | G51: =G13+G32 -> 0 | H51: =H13+H32 -> 0 | I51: =I13+I32 -> 0 | J51: =J13+J32 -> 0 | K51: =D51-E51-F51-G51-H51-I51-J51 -> 0 | L51: 0 | M51: =K51-L51 -> 0 | N51: =N13+N32 -> 0 | O51: =M51+N51 -> 0 | S51: 5 | T51: AREA LIMPIA DISTRITO CAPITAL S.A.S. ESP. | U51: =U13+U32 -> 0 | V51: =V13+V32 -> 0 | W51: =W13+W32 -> 0 | X51: =X13+X32 -> 0 | Y51: =Y13+Y32 -> 0 | Z51: =-L51 -> 0 | AA51: =AA13+AA32 -> 0 | AB51: =AB13+AB32 -> 0 | AC51: =AC13+AC32 -> 0 | AD51: =AD13+AD32 -> 0 | AE51: =SUM(U51:AC51) -> 0 | AF51: =(AE51-O51) -> 0 | AG51: =AF51=0 -> TRUE
C52: TOTAL | D52: =SUM(D47:D51) -> 2286719.2 | E52: =SUM(E47:E51) -> 236926.02 | F52: =SUM(F47:F51) -> 145459.05 | G52: =SUM(G47:G51) -> 42051.03 | H52: =SUM(H47:H51) -> 814015.75 | I52: =SUM(I47:I51) -> 25637.81 | J52: =SUM(J47:J51) -> 0 | K52: =SUM(K47:K51) -> 1022629.6 | ... O52: =SUM(O47:O51) -> 1022629.6 | T52: TOTAL | U52: =SUM(U47:U51) -> 214082.64 | V52: =SUM(V47:V51) -> 213907.13 | W52: =SUM(W47:W51) -> 743426.45 | X52: =SUM(X47:X51) -> 516786.21 | Y52: =SUM(Y47:Y51) -> 29930.71 | Z52: =SUM(Z47:Z51) -> 0 | AA52: =SUM(AA47:AA51) -> -15.86 | AB52: =SUM(AB47:AB51) -> 0 | ... AF52: =SUM(AF47:AF51) -> 8.7311491e-11 | AG52: =AF52=0 -> FALSE
Y54: =SUM(U52:Y52) -> 1718133.1
F56: Firma autorizada

Sheet INTERVENTORIA
F2: 2026 01 2 | G2: 2026 02 1 | H2: 2026 02 2 | I2: 2026 03 1 | J2: 2026 03 2 | K2: 2026 04 1 | L2: 2026 04 2 | M2: 2026 05 1 | N2: 2026 05 2 | O2: 2026 06 1 | P2: 2026 06 2 | Q2: 2026 07 1
B3: VALOR MES | C3: ASE | D3: Concesionarios | E3: % | F3: MITAD 1 // ENERO -26 | G3: MITAD 2 // ENERO -26 | H3: MITAD 1 // FEBRERO -26 | I3: MITAD 2 // FEBRERO -26 | J3: MITAD 1 // MARZO -26 | K3: MITAD 2 // MARZO -26 | L3: MITAD 1 // ABRIL -26 | M3: MITAD 2 // ABRIL -26 | N3: MITAD 1 // MAYO -26 | O3: MITAD 2 // MAYO -26 | P3: MITAD 1 // JUNIO -26 | Q3: MITAD 2 // JUNIO -26
B4: 378371975 | C4: 1 | D4: PROMOAMBIENTAL DISTRITO S.A.S. ESP. | E4: 0.22 | F4: 189185988 | G4: 189185987 | H4: 189185988 | I4: 189185987 | J4: 189185988 | K4: 189185987 | L4: 189185988 | M4: 189185987 | N4: 189185988 | O4: 189185987 | P4: 189185988 | Q4: 189185987
B5: 533160511 | C5: 2 | D5: LIMPIEZA METROPOLITANA S.A. ESP. | E5: 0.31 | F5: 266580256 | G5: 266580255 | H5: 266580256 | I5: 266580255 | J5: 266580256 | K5: 266580255 | L5: 266580256 | M5: 266580255 | N5: 266580256 | O5: 266580255 | P5: 266580256 | Q5: 266580255
B6: 309577071 | C6: 3 | D6: CIUDAD LIMPIA BOGOTA S.A. ESP. | E6: 0.18 | F6: 154788536 | G6: 154788535 | H6: 154788536 | I6: 154788535 | J6: 154788536 | K6: 154788535 | L6: 154788536 | M6: 154788535 | N6: 154788536 | O6: 154788535 | P6: 154788536 | Q6: 154788535
B7: 240782166 | C7: 4 | D7: BOGOTA LIMPIA S.A.S. ESP. | E7: 0.14 | F7: 120391083 | G7: 120391083 | H7: 120391083 | I7: 120391083 | J7: 120391083 | K7: 120391083 | L7: 120391083 | M7: 120391083 | N7: 120391083 | O7: 120391083 | P7: 120391083 | Q7: 120391083
B8: 257980891 | C8: 5 | D8: AREA LIMPIA DISTRITO CAPITAL S.A.S. ESP. | E8: 0.15 | F8: 128990446 | G8: 128990445 | H8: 128990446 | I8: 128990445 | J8: 128990446 | K8: 128990445 | L8: 128990446 | M8: 128990445 | N8: 128990446 | O8: 128990445 | P8: 128990446 | Q8: 128990445
B9: 1719872614 | D9: TOTAL | E9: 1 | F9: 859936309 | G9: 859936305 | H9: 859936309 | I9: 859936305 | J9: 859936309 | K9: 859936305 | L9: 859936309 | M9: 859936305 | N9: 859936309 | O9: 859936305 | P9: 859936309 | Q9: 859936305
F10: =SUM(F9:G9) -> 1719872614 | H10: =SUM(H9:I9) -> 1719872614 | J10: =SUM(J9:K9) -> 1719872614 | L10: =SUM(L9:M9) -> 1719872614 | N10: =SUM(N9:O9) -> 1719872614 | P10: =SUM(P9:Q9) -> 1719872614
F13: 2026 07 2 | G13: 2026 08 1 | H13: 2026 08 2 | I13: 2026 09 1 | J13: 2026 09 2 | K13: 2026 10 1 | L13: 2026 10 2 | M13: 2026 11 1 | N13: 2026 11 2 | O13: 2026 12 1 | P13: 2026 12 2 | Q13: 2027 01 1
C14: ASE | D14: Concesionarios | E14: % | F14: MITAD 1 // JULIO -26 | G14: MITAD 2 // JULIO -26 | H14: MITAD 1 // AGOSTO -26 | I14: MITAD 2 // AGOSTO -26 | J14: MITAD 1 // SEPTIEMBRE -26 | K14: MITAD 2 // SEPTIEMBRE -26 | L14: MITAD 1 // OCTUBRE -26 | M14: MITAD 2 // OCTUBRE -26 | N14: MITAD 1 // NOVIEMBRE -26 | O14: MITAD 2 // NOVIEMBRE -26 | P14: MITAD 1 // DICIEMBRE -26 | Q14: MITAD 2 // DICIEMBRE -26
C15: 1 | D15: PROMOAMBIENTAL DISTRITO S.A.S. ESP. | E15: 0.22 | F15: 189185988 | G15: 189185987 | H15: 189185988 | I15: 189185987 | J15: 189185988 | K15: 189185987 | L15: 189185988 | M15: 189185987 | N15: 189185988 | O15: 189185987 | P15: 189185988 | Q15: 189185987
C16: 2 | D16: LIMPIEZA METROPOLITANA S.A. ESP. | E16: 0.31 | F16: 266580256 | G16: 266580255 | H16: 266580256 | I16: 266580255 | J16: 266580256 | K16: 266580255 | L16: 266580256 | M16: 266580255 | N16: 266580256 | O16: 266580255 | P16: 266580256 | Q16: 266580255
C17: 3 | D17: CIUDAD LIMPIA BOGOTA S.A. ESP. | E17: 0.18 | F17: 154788536 | G17: 154788535 | H17: 154788536 | I17: 154788535 | J17: 154788536 | K17: 154788535 | L17: 154788536 | M17: 154788535 | N17: 154788536 | O17: 154788535 | P17: 154788536 | Q17: 154788535
C18: 4 | D18: BOGOTA LIMPIA S.A.S. ESP. | E18: 0.14 | F18: 120391083 | G18: 120391083 | H18: 120391083 | I18: 120391083 | J18: 120391083 | K18: 120391083 | L18: 120391083 | M18: 120391083 | N18: 120391083 | O18: 120391083 | P18: 120391083 | Q18: 120391083
C19: 5 | D19: AREA LIMPIA DISTRITO CAPITAL S.A.S. ESP. | E19: 0.15 | F19: 128990446 | G19: 128990445 | H19: 128990446 | I19: 128990445 | J19: 128990446 | K19: 128990445 | L19: 128990446 | M19: 128990445 | N19: 128990446 | O19: 128990445 | P19: 128990446 | Q19: 128990445
D20: TOTAL | E20: 1 | F20: 859936309 | G20: 859936305 | H20: 859936309 | I20: 859936305 | J20: 859936309 | K20: 859936305 | L20: 859936309 | M20: 859936305 | N20: 859936309 | O20: 859936305 | P20: 859936309 | Q20: 859936305
F21: =SUM(F20:G20) -> 1719872614 | G21: 1191383498 | H21: =SUM(H20:I20) -> 1719872614 | I21: 1191383498 | J21: =SUM(J20:K20) -> 1719872614 | K21: 1191383498 | L21: =SUM(L20:M20) -> 1719872614 | M21: 1191383498 | N21: =SUM(N20:O20) -> 1719872614 | O21: 1191383498 | P21: =SUM(P20:Q20) -> 1719872614 | Q21: 1191383498
K25: VALOR OFICIAL MES | L25: ASE | M25: Segunda quincena | N25: Primera quincena | R25: VALIDACION
K26: 378371975 | L26: 1 | M26: 189185988 | N26: 189185987 | O26: =M26=R26 -> TRUE | Q26: ='CONSOLIDADO_TOTAL RECAUDO'!L104 -> 189185988 | R26: =J15 -> 189185988 | S26: =Q26=R26 -> TRUE
K27: 533160511 | L27: 2 | M27: 266580256 | N27: 266580255 | O27: =M27=R27 -> TRUE | Q27: ='CONSOLIDADO_TOTAL RECAUDO'!L105 -> 266580256 | R27: =J16 -> 266580256 | S27: =Q27=R27 -> TRUE
K28: 309577071 | L28: 3 | M28: 154788536 | N28: 154788535 | O28: =M28=R28 -> TRUE | Q28: ='CONSOLIDADO_TOTAL RECAUDO'!L106 -> 154788536 | R28: =J17 -> 154788536 | S28: =Q28=R28 -> TRUE
K29: 240782166 | L29: 4 | M29: 120391083 | N29: 120391083 | O29: =M29=R29 -> TRUE | Q29: ='CONSOLIDADO_TOTAL RECAUDO'!L107 -> 120391083 | R29: =J18 -> 120391083 | S29: =Q29=R29 -> TRUE
K30: 257980891 | L30: 5 | M30: 128990446 | N30: 128990445 | O30: =M30=R30 -> TRUE | Q30: ='CONSOLIDADO_TOTAL RECAUDO'!L108 -> 128990446 | R30: =J19 -> 128990446 | S30: =Q30=R30 -> TRUE
K31: =SUM(K26:K30) -> 1719872614 | M31: =SUM(M26:M30) -> 859936309 | N31: =SUM(N26:N30) -> 859936305 | O31: =M31=R31 -> TRUE | Q31: ='CONSOLIDADO_TOTAL RECAUDO'!L109 -> 859936309 | R31: =J20 -> 859936309 | S31: =Q31=R31 -> TRUE
K32: =SUM(M31:N31) -> 1719872614

Sheet Informe AFaseo Recaudo 202609-2
D5: PROCERASEO S.A.S. | I5: NIT: 901 153 639 - 0 | P5: PROCERASEO S.A.S. | T5: NIT: 901 153 639 - 0
D6: INFORME Afaseo // RECAUDO | P6: INFORME AFaseo
D7: BENEFICIO TRANSITORIO ALIVIO SOBRE EL VALOR DE LA FACTURA | P7: BENEFICIO TRANSITORIO ALIVIO SOBRE EL VALOR DE LA FACTURA
D8: Según Resoluciòn UAESP Número 273 de 2.020 | P8: Según Resoluciòn UAESP Número 273 de 2.020
E10: Fecha Desde: | F10: ='CONSOLIDADO_TOTAL RECAUDO'!G102 -> 46281 | H10: Feha Hasta: | I10: ='CONSOLIDADO_TOTAL RECAUDO'!K102 -> 46295
B11: ASE | C11: Concesionarios | D11: Valor Afaseo | E11: Afaseo por disposicion final | F11: Afaseo por tratamiento de lixiviados | G11: Afaseo por Componente VIAT ( Decreto 2412/2018) | H11: Afaseo por aprovechamiento | I11: Afaseo del componente de comercializacion para Aprovechamiento (11,4%) | J11: Afaseo RBL | N11: ASE | O11: Concesionarios | P11: Tarifa de Comercialización del Servicio. ( TCS) | Q11: Tarifa de Limpieza Urbana del Servicio. ( TLU) | R11: Tarifa de Barrido y Limpieza del Servicio. ( TBL) | S11: Tarifa de Recolección y Transporte del Servicio. (TRT) | T11: Componente de comercialización para Aprovechamiento (18,6%) | U11: Afaseo RBL
B12: 1 | C12: PROMOAMBIENTAL DISTRITO S.A.S. ESP. | D12: ='Reporte Componentes R1'!F76*$D$24 -> 17225.21 | E12: ='Reporte Componentes R1'!G76*$D$24 -> 1127.52 | F12: ='Reporte Componentes R1'!H76*$D$24 -> 479 | G12: ='Reporte Componentes R1'!I76*$D$24 -> 209.2 | H12: ='Reporte Componentes R1'!J76*$D$24 -> 3072.3 | I12: ='Reporte Componentes R1'!K76*$D$24 -> 198.78 | J12: =D12-E12-F12-G12-H12-I12 -> 12138.41 | N12: 1 | O12: PROMOAMBIENTAL DISTRITO S.A.S. ESP. | P12: ='Reporte Componentes R1'!M76*$P$24 -> 1743.38 | Q12: ='Reporte Componentes R1'!N76*$P$24 -> 1458.17 | R12: ='Reporte Componentes R1'!O76*$P$24 -> 5823.96 | S12: ='Reporte Componentes R1'!P76*$P$24 -> 2788.6 | T12: ='Reporte Componentes R1'!Q76*$P$24 -> 324.3 | U12: =SUM(P12:T12) -> 12138.41 | V12: =J12-U12 -> 0 | W12: =V12=0 -> TRUE
B13: 2 | C13: LIMPIEZA METROPOLITANA S.A. ESP. | D13: ='Reporte Componentes R1'!F230*$D$24 -> 993518.73 | E13: ='Reporte Componentes R1'!G230*$D$24 -> 86567.57 | F13: ='Reporte Componentes R1'!H230*$D$24 -> 36776.33 | G13: ='Reporte Componentes R1'!I230*$D$24 -> 16060.35 | H13: ='Reporte Componentes R1'!J230*$D$24 -> 200383.96 | I13: ='Reporte Componentes R1'!K230*$D$24 -> 8282.82 | J13: =D13-E13-F13-G13-H13-I13 -> 645447.7 | N13: 2 | O13: LIMPIEZA METROPOLITANA S.A. ESP. | P13: ='Reporte Componentes R1'!M230*$P$24 -> 72838.8 | Q13: ='Reporte Componentes R1'!N230*$P$24 -> 91093.54 | R13: ='Reporte Componentes R1'!O230*$P$24 -> 305924.04 | S13: ='Reporte Componentes R1'!P230*$P$24 -> 162075.72 | T13: ='Reporte Componentes R1'!Q230*$P$24 -> 13515.6 | U13: =SUM(P13:T13) -> 645447.7 | V13: =J13-U13 -> 0 | W13: =V13=0 -> TRUE
B14: 3 | C14: CIUDAD LIMPIA BOGOTA S.A. ESP. | D14: ='Reporte Componentes R1'!F369*$D$24 -> 7866.61 | E14: ='Reporte Componentes R1'!G369*$D$24 -> 678.72 | F14: ='Reporte Componentes R1'!H369*$D$24 -> 288.36 | G14: ='Reporte Componentes R1'!I369*$D$24 -> 125.91 | H14: ='Reporte Componentes R1'!J369*$D$24 -> 1539.2 | I14: ='Reporte Componentes R1'!K369*$D$24 -> 63.42 | J14: =D14-E14-F14-G14-H14-I14 -> 5171 | N14: 3 | O14: CIUDAD LIMPIA BOGOTA S.A. ESP. | P14: ='Reporte Componentes R1'!M369*$P$24 -> 556.25 | Q14: ='Reporte Componentes R1'!N369*$P$24 -> 697.22 | R14: ='Reporte Componentes R1'!O369*$P$24 -> 2341.94 | S14: ='Reporte Componentes R1'!P369*$P$24 -> 1472.13 | T14: ='Reporte Componentes R1'!Q369*$P$24 -> 103.46 | U14: =SUM(P14:T14) -> 5171 | V14: =J14-U14 -> 0 | W14: =V14=0 -> TRUE
B15: 4 | C15: BOGOTA LIMPIA S.A.S. ESP. | D15: ='Reporte Componentes R1'!F502*$D$24 -> 28294.15 | E15: ='Reporte Componentes R1'!G502*$D$24 -> 2288.4 | F15: ='Reporte Componentes R1'!H502*$D$24 -> 972.18 | G15: ='Reporte Componentes R1'!I502*$D$24 -> 424.56 | H15: ='Reporte Componentes R1'!J502*$D$24 -> 5258.96 | I15: ='Reporte Componentes R1'!K502*$D$24 -> 214.2 | J15: =D15-E15-F15-G15-H15-I15 -> 19135.85 | N15: 4 | O15: BOGOTA LIMPIA S.A.S. ESP. | P15: ='Reporte Componentes R1'!M502*$P$24 -> 1878.6 | Q15: ='Reporte Componentes R1'!N502*$P$24 -> 2388.84 | R15: ='Reporte Componentes R1'!O502*$P$24 -> 8771.52 | S15: ='Reporte Componentes R1'!P502*$P$24 -> 5747.39 | T15: ='Reporte Componentes R1'!Q502*$P$24 -> 349.5 | U15: =SUM(P15:T15) -> 19135.85 | V15: =J15-U15 -> 0 | W15: =V15=0 -> TRUE
B16: 5 | C16: AREA LIMPIA DISTRITO CAPITAL S.A.S. ESP. | D16: ='Reporte Componentes R1'!F581*$D$24 -> 9919.7 | E16: ='Reporte Componentes R1'!G581*$D$24 -> 794.89 | F16: ='Reporte Componentes R1'!H581*$D$24 -> 337.68 | G16: ='Reporte Componentes R1'!I581*$D$24 -> 147.47 | H16: ='Reporte Componentes R1'!J581*$D$24 -> 1690.49 | I16: ='Reporte Componentes R1'!K581*$D$24 -> 104.34 | J16: =D16-E16-F16-G16-H16-I16 -> 6844.83 | N16: 5 | O16: AREA LIMPIA DISTRITO CAPITAL S.A.S. ESP. | P16: ='Reporte Componentes R1'!M581*$P$24 -> 915.1 | Q16: ='Reporte Componentes R1'!N581*$P$24 -> 767.16 | R16: ='Reporte Componentes R1'!O581*$P$24 -> 2803.42 | S16: ='Reporte Componentes R1'!P581*$P$24 -> 2188.93 | T16: ='Reporte Componentes R1'!Q581*$P$24 -> 170.22 | U16: =SUM(P16:T16) -> 6844.83 | V16: =J16-U16 -> 0 | W16: =V16=0 -> TRUE
C17: TOTAL | D17: =SUM(D12:D16) -> 1056824.4 | E17: =SUM(E12:E16) -> 91457.1 | F17: =SUM(F12:F16) -> 38853.55 | G17: =SUM(G12:G16) -> 16967.49 | H17: =SUM(H12:H16) -> 211944.91 | I17: =SUM(I12:I16) -> 8863.56 | J17: =SUM(J12:J16) -> 688737.79 | O17: TOTAL | P17: =SUM(P12:P16) -> 77932.13 | Q17: =SUM(Q12:Q16) -> 96404.93 | R17: =SUM(R12:R16) -> 325664.88 | S17: =SUM(S12:S16) -> 174272.77 | T17: =SUM(T12:T16) -> 14463.08 | U17: =SUM(U12:U16) -> 688737.79 | V17: =SUM(V12:V16) -> 0 | W17: =V17=0 -> TRUE
T19: =SUM(P17:T17) -> 688737.79
J20: =+IF(MAX(J12:J17)>500000,"VALIDAR",TRUE) -> VALIDAR
F21: Firma autorizada
D24: -1 | P24: -1

Sheet CONSOLIDADO_TOTAL RECAUDO
F3: PROCERASEO S.A.S. | I3: NIT: 901 153 639 - 0 | M3: Codigo Remuneración: | N3: 2026092 | U3: PROCERASEO S.A.S. | W3: NIT: 901 153 639 - 0 | AA3: Codigo Remuneración: | AD3: =N3 -> 2026092
F4: 3. ESQUEMA FINANCIERO DEL SERVICIO PUBLICO DE ASEO | U4: 3. ESQUEMA FINANCIERO DEL SERVICIO PUBLICO DE ASEO
F5: Resoluciòn UAESP Número 27 de 2018 | U5: Resoluciòn UAESP Número 27 de 2018
C6: Fecha de Proceso: | D6: 46297 | F6: R1 - RECAUDO OPORTUNO | U6: R1 - RECAUDO OPORTUNO
C7: Hora: | D7: 0.58333333 | F7: Fecha Desde: | G7: 46281 | J7: Feha Hasta: | K7: 46295 | U7: =F7 -> Fecha Desde: | V7: =G7 -> 46281 | X7: =J7 -> Feha Hasta: | Y7: =K7 -> 46295
B8: ASE | C8: Concesionarios | D8: Recaudo Total | E8: Recaudo por disposicion final | F8: Recaudo por tratamiento de lixiviados | G8: Recaudo por Componente VIAT ( Decreto 2412/2018) | H8: Recaudo por aprovechamiento | I8: Recaudo del componente de comercializacion para Aprovechamiento (11,4%) | J8: Balance de subsidio o contribuciones | K8: RECAUDO BASE DE REMUNERACION | L8: Costo de la Interventoría | M8: REMUNERACION FINAL | N8: Conceptos especiales | O8: REMUNERACION FINAL MAS CONCEPTOS ESPECIALES | S8: ASE | T8: Concesionarios | U8: Tarifa de Comercialización del Servicio. ( TCS) | V8: Tarifa de Limpieza Urbana del Servicio. ( TLU) | W8: Tarifa de Barrido y Limpieza del Servicio. ( TBL) | X8: Tarifa de Recolección y Transporte del Servicio. (TRT) | Y8: Recaudo del componente de comercializacion para Aprovechamiento (18,6%) | Z8: Costo de la Interventoría | AA8: Ajuste a la decena | AB8: Conceptos especiales | AC8: Otros | AD8: Diferencial Balance S / C (Fac vs Rec) | AE8: Balance S / C Con Base en (Recaudo) | AF8: REMUNERACION FINAL MAS CONCEPTOS ESPECIALES
B9: 1 | C9: PROMOAMBIENTAL DISTRITO S.A.S. ESP. | D9: ='Reporte Componentes R1'!F46 -> 1.599034e+10 | E9: ='Reporte Componentes R1'!G46 -> 8.1283317e+08 | F9: ='Reporte Componentes R1'!H46 -> 4.5291334e+08 | G9: ='Reporte Componentes R1'!I46 -> 2.4059708e+08 | H9: ='Reporte Componentes R1'!J46 -> 3.3052313e+09 | I9: ='Reporte Componentes R1'!K46 -> 1.2386683e+08 | J9: ='BCE SC POR FACT.'!F3 -> -4.5015016e+09 | K9: =D9-E9-F9-G9-H9-I9-J9 -> 1.55564e+10 | L9: =INTERVENTORIA!J15 -> 189185988 | M9: =K9-L9 -> 1.5367214e+10 | N9: ='Reporte Componentes R1'!L46 -> 28410292 | O9: =M9+N9 -> 1.5395624e+10 | S9: 1 | T9: PROMOAMBIENTAL DISTRITO S.A.S. ESP. | U9: ='Reporte Componentes R1'!M46 -> 1.0899072e+09 | V9: ='Reporte Componentes R1'!N46 -> 1.042445e+09 | W9: ='Reporte Componentes R1'!O46 -> 4.9012412e+09 | X9: ='Reporte Componentes R1'!P46 -> 2.2117649e+09 | Y9: ='Reporte Componentes R1'!Q46 -> 2.0212099e+08 | Z9: =L9*-1 -> -189185988 | AA9: ='Reporte Componentes R1'!R46+'Reporte Componentes R1'!U46+'Reporte Componentes R1'!V46 -> 106586.1 | AB9: =N9 -> 28410292 | AC9: ='Reporte Componentes R1'!T46+'Reporte Componentes R1'!W46+'Reporte Componentes R1'!X46+'Reporte Componentes R1'!Y46+'Reporte Componentes R1'!Z46+'Reporte Componentes R1'!S46 -> 69.86 | AD9: =-J9+AE9 -> 6.1088142e+09 | AE9: ='Reporte Componentes R1'!F47 -> 1.6073127e+09 | AF9: =SUM(U9:AD9) -> 1.5395624e+10 | AG9: =(AF9-O9) -> 0 | AH9: =INT(AG9)=0 -> TRUE
B10: 2 | C10: LIMPIEZA METROPOLITANA S.A. ESP. | D10: ='Reporte Componentes R1'!F200 -> 2.2191562e+10 | E10: ='Reporte Componentes R1'!G200 -> 1.6848302e+09 | F10: ='Reporte Componentes R1'!H200 -> 9.3345561e+08 | G10: ='Reporte Componentes R1'!I200 -> 4.9351245e+08 | H10: ='Reporte Componentes R1'!J200 -> 6.8212161e+09 | I10: ='Reporte Componentes R1'!K200 -> 2.3801118e+08 | J10: ='BCE SC POR FACT.'!F4 -> -3.5503079e+09 | K10: =D10-E10-F10-G10-H10-I10-J10 -> 1.5570844e+10 | L10: =INTERVENTORIA!J16 -> 266580256 | M10: =K10-L10 -> 1.5304264e+10 | N10: ='Reporte Componentes R1'!L200 -> 73927483 | O10: =M10+N10 -> 1.5378191e+10 | S10: 2 | T10: LIMPIEZA METROPOLITANA S.A. ESP. | U10: ='Reporte Componentes R1'!M200 -> 2.0856929e+09 | V10: ='Reporte Componentes R1'!N200 -> 2.070916e+09 | W10: ='Reporte Componentes R1'!O200 -> 9.7283154e+09 | X10: ='Reporte Componentes R1'!P200 -> 3.3114109e+09 | Y10: ='Reporte Componentes R1'!Q200 -> 3.8878799e+08 | Z10: =L10*-1 -> -266580256 | AA10: ='Reporte Componentes R1'!R200+'Reporte Componentes R1'!U200+'Reporte Componentes R1'!V200 -> 157355.9 | AB10: =N10 -> 73927483 | AC10: ='Reporte Componentes R1'!T200+'Reporte Componentes R1'!W200+'Reporte Componentes R1'!X200+'Reporte Componentes R1'!Y200+'Reporte Componentes R1'!Z200+'Reporte Componentes R1'!S200 -> -24.05 | AD10: =-J10+AE10 -> -2.0144363e+09 | AE10: ='Reporte Componentes R1'!F201 -> -5.5647442e+09 | AF10: =SUM(U10:AD10) -> 1.5378191e+10 | AG10: =(AF10-O10) -> 5.7220459e-06 | AH10: =INT(AG10)=0 -> TRUE
B11: 3 | C11: CIUDAD LIMPIA BOGOTA S.A. ESP. | D11: ='Reporte Componentes R1'!F339 -> 1.5126945e+10 | E11: ='Reporte Componentes R1'!G339 -> 1.1263262e+09 | F11: ='Reporte Componentes R1'!H339 -> 6.2687264e+08 | G11: ='Reporte Componentes R1'!I339 -> 3.3309403e+08 | H11: ='Reporte Componentes R1'!J339 -> 3.4794876e+09 | I11: ='Reporte Componentes R1'!K339 -> 1.2652841e+08 | J11: ='BCE SC POR FACT.'!F5 -> -7.5058976e+08 | K11: =D11-E11-F11-G11-H11-I11-J11 -> 1.0185226e+10 | L11: =INTERVENTORIA!J17 -> 154788536 | M11: =K11-L11 -> 1.0030437e+10 | N11: ='Reporte Componentes R1'!L339 -> 37136885 | O11: =M11+N11 -> 1.0067574e+10 | S11: 3 | T11: CIUDAD LIMPIA BOGOTA S.A. ESP. | U11: ='Reporte Componentes R1'!M339 -> 1.1096532e+09 | V11: ='Reporte Componentes R1'!N339 -> 1.0842074e+09 | W11: ='Reporte Componentes R1'!O339 -> 5.0954962e+09 | X11: ='Reporte Componentes R1'!P339 -> 2.6672301e+09 | Y11: ='Reporte Componentes R1'!Q339 -> 2.0650797e+08 | Z11: =L11*-1 -> -154788536 | AA11: ='Reporte Componentes R1'!R339+'Reporte Componentes R1'!U339+'Reporte Componentes R1'!V339 -> -129436.44 | AB11: =N11 -> 37136885 | AC11: ='Reporte Componentes R1'!T339+'Reporte Componentes R1'!W339+'Reporte Componentes R1'!X339+'Reporte Componentes R1'!Y339+'Reporte Componentes R1'!Z339+'Reporte Componentes R1'!S339 -> 1.45 | AD11: =-J11+AE11 -> 22260227 | AE11: ='Reporte Componentes R1'!F340 -> -7.2832953e+08 | AF11: =SUM(U11:AD11) -> 1.0067574e+10 | AG11: =(AF11-O11) -> 1.9073486e-06 | AH11: =INT(AG11)=0 -> TRUE
B12: 4 | C12: BOGOTA LIMPIA S.A.S. ESP. | D12: ='Reporte Componentes R1'!F472 -> 7.6619869e+09 | E12: ='Reporte Componentes R1'!G472 -> 4.7237275e+08 | F12: ='Reporte Componentes R1'!H472 -> 2.6225158e+08 | G12: ='Reporte Componentes R1'!I472 -> 1.39261e+08 | H12: ='Reporte Componentes R1'!J472 -> 1.7763613e+09 | I12: ='Reporte Componentes R1'!K472 -> 61161137 | J12: ='BCE SC POR FACT.'!F6 -> -7.1414094e+08 | K12: =D12-E12-F12-G12-H12-I12-J12 -> 5.6647201e+09 | L12: =INTERVENTORIA!J18 -> 120391083 | M12: =K12-L12 -> 5.544329e+09 | N12: ='Reporte Componentes R1'!L472 -> 10063122 | O12: =M12+N12 -> 5.5543921e+09 | S12: 4 | T12: BOGOTA LIMPIA S.A.S. ESP. | U12: ='Reporte Componentes R1'!M472 -> 5.35211e+08 | V12: ='Reporte Componentes R1'!N472 -> 5.3324223e+08 | W12: ='Reporte Componentes R1'!O472 -> 2.7309061e+09 | X12: ='Reporte Componentes R1'!P472 -> 1.2504897e+09 | Y12: ='Reporte Componentes R1'!Q472 -> 99941706 | Z12: =L12*-1 -> -120391083 | AA12: ='Reporte Componentes R1'!R472+'Reporte Componentes R1'!U472+'Reporte Componentes R1'!V472 -> 2887.41 | AB12: =N12 -> 10063122 | AC12: ='Reporte Componentes R1'!T472+'Reporte Componentes R1'!W472+'Reporte Componentes R1'!X472+'Reporte Componentes R1'!Y472+'Reporte Componentes R1'!Z472+'Reporte Componentes R1'!S472 -> 70.57 | AD12: =-J12+AE12 -> 5.1492636e+08 | AE12: ='Reporte Componentes R1'!F473 -> -1.9921458e+08 | AF12: =SUM(U12:AD12) -> 5.5543921e+09 | AG12: =(AF12-O12) -> -9.5367432e-07 | AH12: =INT(AG12)=0 -> FALSE
B13: 5 | C13: AREA LIMPIA DISTRITO CAPITAL S.A.S. ESP. | D13: ='Reporte Componentes R1'!F551 -> 1.2329805e+10 | E13: ='Reporte Componentes R1'!G551 -> 6.9748276e+08 | F13: ='Reporte Componentes R1'!H551 -> 3.8825929e+08 | G13: ='Reporte Componentes R1'!I551 -> 2.0645375e+08 | H13: ='Reporte Componentes R1'!J551 -> 3.2569316e+09 | I13: ='Reporte Componentes R1'!K551 -> 1.0608962e+08 | J13: ='BCE SC POR FACT.'!F7 -> -98238892 | K13: =D13-E13-F13-G13-H13-I13-J13 -> 7.7728273e+09 | L13: =INTERVENTORIA!J19 -> 128990446 | M13: =K13-L13 -> 7.6438369e+09 | N13: ='Reporte Componentes R1'!L551 -> 12154251 | O13: =M13+N13 -> 7.6559911e+09 | S13: 5 | T13: AREA LIMPIA DISTRITO CAPITAL S.A.S. ESP. | U13: ='Reporte Componentes R1'!M551 -> 9.3050688e+08 | V13: ='Reporte Componentes R1'!N551 -> 9.0384402e+08 | W13: ='Reporte Componentes R1'!O551 -> 4.6122014e+09 | X13: ='Reporte Componentes R1'!P551 -> 2.0729118e+09 | Y13: ='Reporte Componentes R1'!Q551 -> 1.7312155e+08 | Z13: =L13*-1 -> -128990446 | AA13: ='Reporte Componentes R1'!R551+'Reporte Componentes R1'!U551+'Reporte Componentes R1'!V551 -> -177200.85 | AB13: =N13 -> 12154251 | AC13: ='Reporte Componentes R1'!T551+'Reporte Componentes R1'!W551+'Reporte Componentes R1'!X551+'Reporte Componentes R1'!Y551+'Reporte Componentes R1'!Z551+'Reporte Componentes R1'!S551 -> -23.52 | AD13: =-J13+AE13 -> -9.1958107e+08 | AE13: ='Reporte Componentes R1'!F552 -> -1.01782e+09 | AF13: =SUM(U13:AD13) -> 7.6559911e+09 | AG13: =(AF13-O13) -> -1.9073486e-06 | AH13: =INT(AG13)=0 -> FALSE
C14: TOTAL | D14: =SUM(D9:D13) -> 7.3300639e+10 | E14: =SUM(E9:E13) -> 4.7938451e+09 | F14: =SUM(F9:F13) -> 2.6637525e+09 | G14: =SUM(G9:G13) -> 1.4129183e+09 | H14: =SUM(H9:H13) -> 1.8639228e+10 | I14: =SUM(I9:I13) -> 6.5565717e+08 | J14: =SUM(J9:J13) -> -9.6147791e+09 | K14: =SUM(K9:K13) -> 5.4750017e+10 | ... O14: =SUM(O9:O13) -> 5.4051773e+10 | T14: TOTAL | U14: =SUM(U9:U13) -> 5.7509712e+09 | V14: =SUM(V9:V13) -> 5.6346547e+09 | W14: =SUM(W9:W13) -> 2.706816e+10 | X14: =SUM(X9:X13) -> 1.1513807e+10 | Y14: =SUM(Y9:Y13) -> 1.0704802e+09 | Z14: =SUM(Z9:Z13) -> -859936309 | AA14: =SUM(AA9:AA13) -> -39807.88 | AB14: =SUM(AB9:AB13) -> 1.6169203e+08 | ... AG14: =SUM(AG9:AG13) -> 4.7683716e-06 | AH14: =INT(AG14)=0 -> TRUE
Y16: =SUM(U14:Y14) -> 5.1038074e+10
F18: Firma autorizada
F22: PROCERASEO S.A.S. | I22: NIT: 901 153 639 - 0 | M22: Codigo Remuneración: | N22: =N3 -> 2026092 | U22: PROCERASEO S.A.S. | W22: NIT: 901 153 639 - 0 | AA22: Codigo Remuneración: | AD22: =N22 -> 2026092
F23: 3. ESQUEMA FINANCIERO DEL SERVICIO PUBLICO DE ASEO | U23: 3. ESQUEMA FINANCIERO DEL SERVICIO PUBLICO DE ASEO
F24: Resoluciòn UAESP Número 27 de 2018 | U24: Resoluciòn UAESP Número 27 de 2018
C25: Fecha de Proceso: | D25: =D6 -> 46297 | F25: R2 - ANTICIPOS A USUARIOS | U25: R2 - ANTICIPOS A USUARIOS
C26: Hora: | D26: =D7 -> 0.58333333 | F26: Fecha Desde: | G26: =G7 -> 46281 | J26: Feha Hasta: | K26: =K7 -> 46295 | U26: =F26 -> Fecha Desde: | V26: =G26 -> 46281 | X26: =J26 -> Feha Hasta: | Y26: =K26 -> 46295
B27: ASE | C27: Concesionarios | D27: Recaudo Total | E27: Recaudo por disposicion final | F27: Recaudo por tratamiento de lixiviados | G27: Recaudo por Componente VIAT ( Decreto 2412/2018) | H27: Recaudo por aprovechamiento | I27: Recaudo del componente de comercializacion para Aprovechamiento (11,4%) | J27: Balance de subsidio o contribuciones | K27: RECAUDO BASE DE REMUNERACION | L27: Costo de la Interventoría | M27: REMUNERACION FINAL | N27: Conceptos especiales | O27: REMUNERACION FINAL MAS CONCEPTOS ESPECIALES | S27: ASE | T27: Concesionarios | U27: Tarifa de Comercialización del Servicio. ( TCS) | V27: Tarifa de Limpieza Urbana del Servicio. ( TLU) | W27: Tarifa de Barrido y Limpieza del Servicio. ( TBL) | X27: Tarifa de Recolección y Transporte del Servicio. (TRT) | Y27: Recaudo del componente de comercializacion para Aprovechamiento (18,6%) | Z27: Costo de la Interventoría | AA27: Ajuste a la decena | AB27: Conceptos especiales | AC27: Otros | AD27: Diferencial Balance S / C (Fac vs Rec) | AE27: Balance S / C Con Base en (Recaudo) | AF27: REMUNERACION FINAL MAS CONCEPTOS ESPECIALES
B28: 1 | C28: PROMOAMBIENTAL DISTRITO S.A.S. ESP. | D28: ='Rem. Anticipos R2'!E43 -> 67607989 | E28: ='Rem. Anticipos R2'!F43 -> 5966183.8 | F28: ='Rem. Anticipos R2'!G43 -> 3277844.1 | G28: ='Rem. Anticipos R2'!H43 -> 1365628 | H28: ='Rem. Anticipos R2'!I43 -> 18155798 | I28: ='Rem. Anticipos R2'!J43 -> 599498.58 | J28: 0 | K28: =D28-E28-F28-G28-H28-I28-J28 -> 38243036 | L28: 0 | M28: =K28-L28 -> 38243036 | N28: ='Rem. Anticipos R2'!K43 -> 1030668 | O28: =M28+N28 -> 39273704 | S28: 1 | T28: PROMOAMBIENTAL DISTRITO S.A.S. ESP. | U28: ='Rem. Anticipos R2'!L43 -> 6081150.7 | V28: ='Rem. Anticipos R2'!M43 -> 5284460.6 | W28: ='Rem. Anticipos R2'!N43 -> 21492909 | X28: ='Rem. Anticipos R2'!O43 -> 16744855 | Y28: ='Rem. Anticipos R2'!P43 -> 864186.52 | Z28: =L28*-1 -> 0 | AA28: ='Rem. Anticipos R2'!Q43 -> -66.69 | AB28: =N28 -> 1030668 | AC28: ='Rem. Anticipos R2'!R43 -> 0 | AD28: =-J28+AE28 -> -12224458 | AE28: ='Rem. Anticipos R2'!E44 -> -12224458 | AF28: =SUM(U28:AD28) -> 39273704 | AG28: =(AF28-O28) -> 7.4505806e-09 | AH28: =INT(AG28)=0 -> TRUE
B29: 2 | C29: LIMPIEZA METROPOLITANA S.A. ESP. | D29: ='Rem. Anticipos R2'!E136 -> 1.5575016e+08 | E29: ='Rem. Anticipos R2'!F136 -> 21179038 | F29: ='Rem. Anticipos R2'!G136 -> 11187089 | G29: ='Rem. Anticipos R2'!H136 -> 5537650.5 | H29: ='Rem. Anticipos R2'!I136 -> 30381507 | I29: ='Rem. Anticipos R2'!J136 -> 941128.87 | J29: 0 | K29: =D29-E29-F29-G29-H29-I29-J29 -> 86523743 | L29: 0 | M29: =K29-L29 -> 86523743 | N29: ='Rem. Anticipos R2'!K136 -> 219000 | O29: =M29+N29 -> 86742743 | S29: 2 | T29: LIMPIEZA METROPOLITANA S.A. ESP. | U29: ='Rem. Anticipos R2'!L136 -> 8214775.6 | V29: ='Rem. Anticipos R2'!M136 -> 8652731.7 | W29: ='Rem. Anticipos R2'!N136 -> 37700932 | X29: ='Rem. Anticipos R2'!O136 -> 45281009 | Y29: ='Rem. Anticipos R2'!P136 -> 1403801.5 | Z29: =L29*-1 -> 0 | AA29: ='Rem. Anticipos R2'!Q136 -> -162.69 | AB29: =N29 -> 219000 | AC29: ='Rem. Anticipos R2'!R136 -> 0 | AD29: =-J29+AE29 -> -14729344 | AE29: ='Rem. Anticipos R2'!E137 -> -14729344 | AF29: =SUM(U29:AD29) -> 86742743 | AG29: =(AF29-O29) -> 1.4901161e-08 | AH29: =INT(AG29)=0 -> TRUE
B30: 3 | C30: CIUDAD LIMPIA BOGOTA S.A. ESP. | D30: ='Rem. Anticipos R2'!E253 -> 1.1304844e+08 | E30: ='Rem. Anticipos R2'!F253 -> 12979986 | F30: ='Rem. Anticipos R2'!G253 -> 7286379.7 | G30: ='Rem. Anticipos R2'!H253 -> 3842632.8 | H30: ='Rem. Anticipos R2'!I253 -> 5668174.7 | I30: ='Rem. Anticipos R2'!J253 -> 236252.61 | J30: 0 | K30: =D30-E30-F30-G30-H30-I30-J30 -> 83035014 | L30: 0 | M30: =K30-L30 -> 83035014 | N30: ='Rem. Anticipos R2'!K253 -> 34149.98 | O30: =M30+N30 -> 83069164 | S30: 3 | T30: CIUDAD LIMPIA BOGOTA S.A. ESP. | U30: ='Rem. Anticipos R2'!L253 -> 1131854.3 | V30: ='Rem. Anticipos R2'!M253 -> 1377651.4 | W30: ='Rem. Anticipos R2'!N253 -> 6105100.7 | X30: ='Rem. Anticipos R2'!O253 -> 32123713 | Y30: ='Rem. Anticipos R2'!P253 -> 238348.94 | Z30: =L30*-1 -> 0 | AA30: ='Rem. Anticipos R2'!Q253 -> -320.32 | AB30: =N30 -> 34149.98 | AC30: ='Rem. Anticipos R2'!R253 -> 0 | AD30: =-J30+AE30 -> 42058665 | AE30: ='Rem. Anticipos R2'!E254 -> 42058665 | AF30: =SUM(U30:AD30) -> 83069164 | AG30: =(AF30-O30) -> 0 | AH30: =INT(AG30)=0 -> TRUE
B31: 4 | C31: BOGOTA LIMPIA S.A.S. ESP. | D31: ='Rem. Anticipos R2'!E352 -> 1.0824612e+08 | E31: ='Rem. Anticipos R2'!F352 -> 9725918.4 | F31: ='Rem. Anticipos R2'!G352 -> 5452154 | G31: ='Rem. Anticipos R2'!H352 -> 2672799.7 | H31: ='Rem. Anticipos R2'!I352 -> 22573568 | I31: ='Rem. Anticipos R2'!J352 -> 844332.2 | J31: 0 | K31: =D31-E31-F31-G31-H31-I31-J31 -> 66977348 | L31: 0 | M31: =K31-L31 -> 66977348 | N31: ='Rem. Anticipos R2'!K352 -> 858314.69 | O31: =M31+N31 -> 67835662 | S31: 4 | T31: BOGOTA LIMPIA S.A.S. ESP. | U31: ='Rem. Anticipos R2'!L352 -> 7377605.4 | V31: ='Rem. Anticipos R2'!M352 -> 7810341.8 | W31: ='Rem. Anticipos R2'!N352 -> 34685436 | X31: ='Rem. Anticipos R2'!O352 -> 26142247 | Y31: ='Rem. Anticipos R2'!P352 -> 1125289.9 | Z31: =L31*-1 -> 0 | AA31: ='Rem. Anticipos R2'!Q352 -> 237.3 | AB31: =N31 -> 858314.69 | AC31: ='Rem. Anticipos R2'!R352 -> 0 | AD31: =-J31+AE31 -> -10163810 | AE31: ='Rem. Anticipos R2'!E353 -> -10163810 | AF31: =SUM(U31:AD31) -> 67835662 | AG31: =(AF31-O31) -> 0 | AH31: =INT(AG31)=0 -> TRUE
B32: 5 | C32: AREA LIMPIA DISTRITO CAPITAL S.A.S. ESP. | D32: ='Rem. Anticipos R2'!E432 -> 29429174 | E32: ='Rem. Anticipos R2'!F432 -> 2356482.7 | F32: ='Rem. Anticipos R2'!G432 -> 1326761.9 | G32: ='Rem. Anticipos R2'!H432 -> 654859.67 | H32: ='Rem. Anticipos R2'!I432 -> 6005028.4 | I32: ='Rem. Anticipos R2'!J432 -> 194109.12 | J32: 0 | K32: =D32-E32-F32-G32-H32-I32-J32 -> 18891933 | L32: 0 | M32: =K32-L32 -> 18891933 | N32: ='Rem. Anticipos R2'!K432 -> 575000 | O32: =M32+N32 -> 19466933 | S32: 5 | T32: AREA LIMPIA DISTRITO CAPITAL S.A.S. ESP. | U32: ='Rem. Anticipos R2'!L432 -> 1456800.1 | V32: ='Rem. Anticipos R2'!M432 -> 1682011.8 | W32: ='Rem. Anticipos R2'!N432 -> 6682528.6 | X32: ='Rem. Anticipos R2'!O432 -> 7067100.7 | Y32: ='Rem. Anticipos R2'!P432 -> 312064.72 | Z32: =L32*-1 -> 0 | AA32: ='Rem. Anticipos R2'!Q432 -> 79.87 | AB32: =N32 -> 575000 | AC32: ='Rem. Anticipos R2'!R432 -> 0 | AD32: =-J32+AE32 -> 1691346.7 | AE32: ='Rem. Anticipos R2'!E433 -> 1691346.7 | AF32: =SUM(U32:AD32) -> 19466933 | AG32: =(AF32-O32) -> 0 | AH32: =INT(AG32)=0 -> TRUE
C33: TOTAL | D33: =SUM(D28:D32) -> 4.7408188e+08 | E33: =SUM(E28:E32) -> 52207609 | F33: =SUM(F28:F32) -> 28530229 | G33: =SUM(G28:G32) -> 14073571 | H33: =SUM(H28:H32) -> 82784076 | I33: =SUM(I28:I32) -> 2815321.4 | J33: =SUM(J28:J32) -> 0 | K33: =SUM(K28:K32) -> 2.9367107e+08 | ... O33: =SUM(O28:O32) -> 2.9638821e+08 | T33: TOTAL | U33: =SUM(U28:U32) -> 24262186 | V33: =SUM(V28:V32) -> 24807197 | W33: =SUM(W28:W32) -> 1.0666691e+08 | X33: =SUM(X28:X32) -> 1.2735892e+08 | Y33: =SUM(Y28:Y32) -> 3943691.6 | Z33: =SUM(Z28:Z32) -> 0 | AA33: =SUM(AA28:AA32) -> -232.53 | AB33: =SUM(AB28:AB32) -> 2717132.7 | ... AG33: =SUM(AG28:AG32) -> 2.2351742e-08 | AH33: =INT(AG33)=0 -> TRUE
Y35: =SUM(U33:Y33) -> 2.8703891e+08
F37: Firma autorizada
F41: PROCERASEO S.A.S. | I41: NIT: 901 153 639 - 0 | M41: Codigo Remuneración: | N41: =N3 -> 2026092 | U41: PROCERASEO S.A.S. | W41: NIT: 901 153 639 - 0 | AA41: Codigo Remuneración: | AD41: =N41 -> 2026092
F42: 3. ESQUEMA FINANCIERO DEL SERVICIO PUBLICO DE ASEO | U42: 3. ESQUEMA FINANCIERO DEL SERVICIO PUBLICO DE ASEO
F43: Resoluciòn UAESP Número 27 de 2018 | U43: Resoluciòn UAESP Número 27 de 2018
C44: Fecha de Proceso: | D44: =D6 -> 46297 | F44: R3 - RECAUDO EXTEMPORANEO | U44: R3 - RECAUDO EXTEMPORANEO
C45: Hora: | D45: =D7 -> 0.58333333 | F45: Fecha Desde: | G45: =G7 -> 46281 | J45: Feha Hasta: | K45: =K7 -> 46295 | U45: =F45 -> Fecha Desde: | V45: =G45 -> 46281 | X45: =J45 -> Feha Hasta: | Y45: =K45 -> 46295
B46: ASE | C46: Concesionarios | D46: Recaudo Total | E46: Recaudo por disposicion final | F46: Recaudo por tratamiento de lixiviados | G46: Recaudo por Componente VIAT ( Decreto 2412/2018) | H46: Recaudo por aprovechamiento | I46: Recaudo del componente de comercializacion para Aprovechamiento (11,4%) | J46: Balance de subsidio o contribuciones | K46: RECAUDO BASE DE REMUNERACION | L46: Costo de la Interventoría | M46: REMUNERACION FINAL | N46: Conceptos especiales | O46: REMUNERACION FINAL MAS CONCEPTOS ESPECIALES | S46: ASE | T46: Concesionarios | U46: Tarifa de Comercialización del Servicio. ( TCS) | V46: Tarifa de Limpieza Urbana del Servicio. ( TLU) | W46: Tarifa de Barrido y Limpieza del Servicio. ( TBL) | X46: Tarifa de Recolección y Transporte del Servicio. (TRT) | Y46: Recaudo del componente de comercializacion para Aprovechamiento (18,6%) | Z46: Costo de la Interventoría | AA46: Ajuste a la decena | AB46: Conceptos especiales | AC46: Otros | AD46: Diferencial Balance S / C (Fac vs Rec) | AE46: Balance S / C Con Base en (Recaudo) | AF46: REMUNERACION FINAL MAS CONCEPTOS ESPECIALES
B47: 1 | C47: PROMOAMBIENTAL DISTRITO S.A.S. ESP. | D47: ='Reporte Componentes R1'!F48 -> 40070 | E47: ='Reporte Componentes R1'!G48 -> 1956.64 | F47: ='Reporte Componentes R1'!H48 -> 1090.23 | G47: ='Reporte Componentes R1'!I48 -> 579.83 | H47: ='Reporte Componentes R1'!J48 -> 9781.04 | I47: ='Reporte Componentes R1'!K48 -> 359.68 | J47: 0 | K47: =D47-E47-F47-G47-H47-I47-J47 -> 26302.58 | L47: 0 | M47: =K47-L47 -> 26302.58 | N47: ='Reporte Componentes R1'!L48 -> 0 | O47: =M47+N47 -> 26302.58 | S47: 1 | T47: PROMOAMBIENTAL DISTRITO S.A.S. ESP. | U47: ='Reporte Componentes R1'!M48 -> 3155.11 | V47: ='Reporte Componentes R1'!N48 -> 3024.18 | W47: ='Reporte Componentes R1'!O48 -> 14196.18 | X47: ='Reporte Componentes R1'!P48 -> 5344.07 | Y47: ='Reporte Componentes R1'!Q48 -> 586.85 | Z47: =-L47 -> 0 | AA47: ='Reporte Componentes R1'!R48+'Reporte Componentes R1'!V48+'Reporte Componentes R1'!U48 -> -3.81 | AB47: =N47 -> 0 | AC47: ='Reporte Componentes R1'!T48+'Reporte Componentes R1'!W48+'Reporte Componentes R1'!X48+'Reporte Componentes R1'!Y48+'Reporte Componentes R1'!Z48+'Reporte Componentes R1'!S48 -> 0 | AD47: =-J47+AE47 -> 0 | AE47: ='Reporte Componentes R1'!F49 -> 0 | AF47: =SUM(U47:AD47) -> 26302.58 | AG47: =(AF47-O47) -> 3.6379788e-12 | AH47: =INT(AG47)=0 -> TRUE
B48: 2 | C48: LIMPIEZA METROPOLITANA S.A. ESP. | D48: ='Reporte Componentes R1'!F202 -> 18014168 | E48: ='Reporte Componentes R1'!G202 -> 1223567.9 | F48: ='Reporte Componentes R1'!H202 -> 686396.32 | G48: ='Reporte Componentes R1'!I202 -> 367845.29 | H48: ='Reporte Componentes R1'!J202 -> 5667614.6 | I48: ='Reporte Componentes R1'!K202 -> 150264.93 | J48: 0 | K48: =D48-E48-F48-G48-H48-I48-J48 -> 9918479 | L48: 0 | M48: =K48-L48 -> 9918479 | N48: ='Reporte Componentes R1'!L202 -> 0 | O48: =M48+N48 -> 9918479 | S48: 2 | T48: LIMPIEZA METROPOLITANA S.A. ESP. | U48: ='Reporte Componentes R1'!M202 -> 1310568.5 | V48: ='Reporte Componentes R1'!N202 -> 1731493.8 | W48: ='Reporte Componentes R1'!O202 -> 8347459.8 | X48: ='Reporte Componentes R1'!P202 -> 2419893.2 | Y48: ='Reporte Componentes R1'!Q202 -> 244481.8 | Z48: =-L48 -> 0 | AA48: ='Reporte Componentes R1'!R202+'Reporte Componentes R1'!V202+'Reporte Componentes R1'!U202 -> -105.27 | AB48: =N48 -> 0 | AC48: ='Reporte Componentes R1'!T202+'Reporte Componentes R1'!W202+'Reporte Componentes R1'!X202+'Reporte Componentes R1'!Y202+'Reporte Componentes R1'!Z202+'Reporte Componentes R1'!S202 -> 0.06 | AD48: =-J48+AE48 -> -4135313 | AE48: ='Reporte Componentes R1'!F203 -> -4135313 | AF48: =SUM(U48:AD48) -> 9918479 | AG48: =(AF48-O48) -> 3.7252903e-09 | AH48: =INT(AG48)=0 -> TRUE
B49: 3 | C49: CIUDAD LIMPIA BOGOTA S.A. ESP. | D49: ='Reporte Componentes R1'!F341 -> 388550 | E49: ='Reporte Componentes R1'!G341 -> 40467.76 | F49: ='Reporte Componentes R1'!H341 -> 22548.38 | G49: ='Reporte Componentes R1'!I341 -> 11992.34 | H49: ='Reporte Componentes R1'!J341 -> 10672.75 | I49: ='Reporte Componentes R1'!K341 -> 385.44 | J49: 0 | K49: =D49-E49-F49-G49-H49-I49-J49 -> 302483.33 | L49: 0 | M49: =K49-L49 -> 302483.33 | N49: ='Reporte Componentes R1'!L341 -> 0 | O49: =M49+N49 -> 302483.33 | S49: 3 | T49: CIUDAD LIMPIA BOGOTA S.A. ESP. | U49: ='Reporte Componentes R1'!M341 -> 3380.99 | V49: ='Reporte Componentes R1'!N341 -> 3214.74 | W49: ='Reporte Componentes R1'!O341 -> 15256.24 | X49: ='Reporte Componentes R1'!P341 -> 95953.3 | Y49: ='Reporte Componentes R1'!Q341 -> 628.86 | Z49: =-L49 -> 0 | AA49: ='Reporte Componentes R1'!R341+'Reporte Componentes R1'!V341+'Reporte Componentes R1'!U341 -> -1.51 | AB49: =N49 -> 0 | AC49: ='Reporte Componentes R1'!T341+'Reporte Componentes R1'!W341+'Reporte Componentes R1'!X341+'Reporte Componentes R1'!Y341+'Reporte Componentes R1'!Z341+'Reporte Componentes R1'!S341 -> 0 | AD49: =-J49+AE49 -> 184050.71 | AE49: ='Reporte Componentes R1'!F342 -> 184050.71 | AF49: =SUM(U49:AD49) -> 302483.33 | AG49: =(AF49-O49) -> 5.8207661e-11 | AH49: =INT(AG49)=0 -> TRUE
B50: 4 | C50: BOGOTA LIMPIA S.A.S. ESP. | D50: ='Reporte Componentes R1'!F474 -> 83359647 | E50: ='Reporte Componentes R1'!G474 -> 6075269.3 | F50: ='Reporte Componentes R1'!H474 -> 3380450 | G50: ='Reporte Componentes R1'!I474 -> 1783357.2 | H50: ='Reporte Componentes R1'!J474 -> 16603425 | I50: ='Reporte Componentes R1'!K474 -> 514853.18 | J50: 0 | K50: =D50-E50-F50-G50-H50-I50-J50 -> 55002293 | L50: 0 | M50: =K50-L50 -> 55002293 | N50: ='Reporte Componentes R1'!L474 -> 5153.85 | O50: =M50+N50 -> 55007447 | S50: 4 | T50: BOGOTA LIMPIA S.A.S. ESP. | U50: ='Reporte Componentes R1'!M474 -> 4479556.2 | V50: ='Reporte Componentes R1'!N474 -> 5391190.3 | W50: ='Reporte Componentes R1'!O474 -> 27410403 | X50: ='Reporte Componentes R1'!P474 -> 16085765 | Y50: ='Reporte Componentes R1'!Q474 -> 843874.77 | Z50: =-L50 -> 0 | AA50: ='Reporte Componentes R1'!R474+'Reporte Componentes R1'!V474+'Reporte Componentes R1'!U474 -> -83.41 | AB50: =N50 -> 5153.85 | AC50: ='Reporte Componentes R1'!T474+'Reporte Componentes R1'!W474+'Reporte Componentes R1'!X474+'Reporte Componentes R1'!Y474+'Reporte Componentes R1'!Z474+'Reporte Componentes R1'!S474 -> 0.93 | AD50: =-J50+AE50 -> 791585.72 | AE50: ='Reporte Componentes R1'!F475 -> 791585.72 | AF50: =SUM(U50:AD50) -> 55007447 | AG50: =(AF50-O50) -> 7.4505806e-09 | AH50: =INT(AG50)=0 -> TRUE
B51: 5 | C51: AREA LIMPIA DISTRITO CAPITAL S.A.S. ESP. | D51: ='Reporte Componentes R1'!F553 -> 0 | E51: ='Reporte Componentes R1'!G553 -> 0 | F51: ='Reporte Componentes R1'!H553 -> 0 | G51: ='Reporte Componentes R1'!I553 -> 0 | H51: ='Reporte Componentes R1'!J553 -> 0 | I51: ='Reporte Componentes R1'!K553 -> 0 | J51: 0 | K51: =D51-E51-F51-G51-H51-I51-J51 -> 0 | L51: 0 | M51: =K51-L51 -> 0 | N51: ='Reporte Componentes R1'!L553 -> 0 | O51: =M51+N51 -> 0 | S51: 5 | T51: AREA LIMPIA DISTRITO CAPITAL S.A.S. ESP. | U51: ='Reporte Componentes R1'!M553 -> 0 | V51: ='Reporte Componentes R1'!N553 -> 0 | W51: ='Reporte Componentes R1'!O553 -> 0 | X51: ='Reporte Componentes R1'!P553 -> 0 | Y51: ='Reporte Componentes R1'!Q553 -> 0 | Z51: =-L51 -> 0 | AA51: ='Reporte Componentes R1'!R553+'Reporte Componentes R1'!V553+'Reporte Componentes R1'!U553 -> 0 | AB51: =N51 -> 0 | AC51: ='Reporte Componentes R1'!T553+'Reporte Componentes R1'!W553+'Reporte Componentes R1'!X553+'Reporte Componentes R1'!Y553+'Reporte Componentes R1'!Z553+'Reporte Componentes R1'!S553 -> 0 | AD51: =-J51+AE51 -> 0 | AE51: ='Reporte Componentes R1'!F554 -> 0 | AF51: =SUM(U51:AD51) -> 0 | AG51: =(AF51-O51) -> 0 | AH51: =INT(AG51)=0 -> TRUE
C52: TOTAL | D52: =SUM(D47:D51) -> 1.0180244e+08 | E52: =SUM(E47:E51) -> 7341261.7 | F52: =SUM(F47:F51) -> 4090485 | G52: =SUM(G47:G51) -> 2163774.6 | H52: =SUM(H47:H51) -> 22291493 | I52: =SUM(I47:I51) -> 665863.23 | J52: =SUM(J47:J51) -> 0 | K52: =SUM(K47:K51) -> 65249558 | ... O52: =SUM(O47:O51) -> 65254712 | T52: TOTAL | U52: =SUM(U47:U51) -> 5796660.7 | V52: =SUM(V47:V51) -> 7128923.1 | W52: =SUM(W47:W51) -> 35787315 | X52: =SUM(X47:X51) -> 18606956 | Y52: =SUM(Y47:Y51) -> 1089572.3 | Z52: =SUM(Z47:Z51) -> 0 | AA52: =SUM(AA47:AA51) -> -194 | AB52: =SUM(AB47:AB51) -> 5153.85 | ... AG52: =SUM(AG47:AG51) -> 1.1237717e-08 | AH52: =INT(AG52)=0 -> TRUE
Y54: =SUM(U52:Y52) -> 68409427
F56: Firma autorizada
F60: PROCERASEO S.A.S. | I60: NIT: 901 153 639 - 0 | M60: Codigo Remuneración: | N60: =N3 -> 2026092 | U60: PROCERASEO S.A.S. | W60: NIT: 901 153 639 - 0 | AA60: Codigo Remuneración: | AD60: =N60 -> 2026092
F61: 3. ESQUEMA FINANCIERO DEL SERVICIO PUBLICO DE ASEO | U61: 3. ESQUEMA FINANCIERO DEL SERVICIO PUBLICO DE ASEO
F62: Resoluciòn UAESP Número 27 de 2018 | U62: Resoluciòn UAESP Número 27 de 2018
C63: Fecha de Proceso: | D63: =D6 -> 46297 | F63: R4 - REVERSIÓN DE PAGOS | U63: R4 - REVERSIÓN DE PAGOS
C64: Hora: | D64: =D7 -> 0.58333333 | F64: Fecha Desde: | G64: =G7 -> 46281 | J64: Feha Hasta: | K64: =K7 -> 46295 | U64: =F64 -> Fecha Desde: | V64: =G64 -> 46281 | X64: =J64 -> Feha Hasta: | Y64: =K64 -> 46295
B65: ASE | C65: Concesionarios | D65: Recaudo Total | E65: Recaudo por disposicion final | F65: Recaudo por tratamiento de lixiviados | G65: Recaudo por Componente VIAT ( Decreto 2412/2018) | H65: Recaudo por aprovechamiento | I65: Recaudo del componente de comercializacion para Aprovechamiento (11,4%) | J65: Balance de subsidio o contribuciones | K65: RECAUDO BASE DE REMUNERACION | L65: Costo de la Interventoría | M65: REMUNERACION FINAL | N65: Conceptos especiales | O65: REMUNERACION FINAL MAS CONCEPTOS ESPECIALES | S65: ASE | T65: Concesionarios | U65: Tarifa de Comercialización del Servicio. ( TCS) | V65: Tarifa de Limpieza Urbana del Servicio. ( TLU) | W65: Tarifa de Barrido y Limpieza del Servicio. ( TBL) | X65: Tarifa de Recolección y Transporte del Servicio. (TRT) | Y65: Recaudo del componente de comercializacion para Aprovechamiento (18,6%) | Z65: Costo de la Interventoría | AA65: Ajuste a la decena | AB65: Conceptos especiales | AC65: Otros | AD65: Diferencial Balance S / C (Fac vs Rec) | AE65: Balance S / C Con Base en (Recaudo) | AF65: REMUNERACION FINAL MAS CONCEPTOS ESPECIALES
B66: 1 | C66: PROMOAMBIENTAL DISTRITO S.A.S. ESP. | D66: ='Reversion Pagos R4'!D70 -> -1285060 | E66: ='Reversion Pagos R4'!E70 -> -52832.92 | F66: ='Reversion Pagos R4'!F70 -> -29843.49 | G66: ='Reversion Pagos R4'!G70 -> -15719.25 | H66: ='Reversion Pagos R4'!H70 -> -224869.1 | I66: ='Reversion Pagos R4'!I70 -> -7817.02 | J66: 0 | K66: =D66-E66-F66-G66-H66-I66-J66 -> -953978.22 | L66: 0 | M66: =K66-L66 -> -953978.22 | N66: ='Reversion Pagos R4'!P70 -> 0 | O66: =M66+N66 -> -953978.22 | S66: 1 | T66: PROMOAMBIENTAL DISTRITO S.A.S. ESP. | U66: ='Reversion Pagos R4'!J70 -> -68569.97 | V66: ='Reversion Pagos R4'!K70 -> -67711.59 | W66: ='Reversion Pagos R4'!L70 -> -318224.89 | X66: ='Reversion Pagos R4'!M70 -> -144463.47 | Y66: ='Reversion Pagos R4'!N70 -> -12753.89 | Z66: =-L66 -> 0 | AA66: ='Reversion Pagos R4'!O70 -> -5.18 | AB66: =N66 -> 0 | AC66: =+'Reversion Pagos R4'!Q70+'Reversion Pagos R4'!R70 -> 0 | AD66: =-J66+AE66 -> -342249.23 | AE66: ='Reversion Pagos R4'!D71 -> -342249.23 | AF66: =SUM(U66:AD66) -> -953978.22 | AG66: =(AF66-O66) -> 0 | AH66: =INT(AG66)=0 -> TRUE
B67: 2 | C67: LIMPIEZA METROPOLITANA S.A. ESP. | D67: ='Reversion Pagos R4'!D170 -> -45230052 | E67: ='Reversion Pagos R4'!E170 -> -3634148.1 | F67: ='Reversion Pagos R4'!F170 -> -1940116.2 | G67: ='Reversion Pagos R4'!G170 -> -1004097.8 | H67: ='Reversion Pagos R4'!H170 -> -14314989 | I67: ='Reversion Pagos R4'!I170 -> -497437.64 | J67: 0 | K67: =D67-E67-F67-G67-H67-I67-J67 -> -23839263 | L67: 0 | M67: =K67-L67 -> -23839263 | N67: ='Reversion Pagos R4'!P170 -> 0 | O67: =M67+N67 -> -23839263 | S67: 2 | T67: LIMPIEZA METROPOLITANA S.A. ESP. | U67: ='Reversion Pagos R4'!J170 -> -4394387.9 | V67: ='Reversion Pagos R4'!K170 -> -4534029.6 | W67: ='Reversion Pagos R4'!L170 -> -20533548 | X67: ='Reversion Pagos R4'!M170 -> -7203974.5 | Y67: ='Reversion Pagos R4'!N170 -> -814812 | Z67: =-L67 -> 0 | AA67: ='Reversion Pagos R4'!O170 -> 55.71 | AB67: =N67 -> 0 | AC67: =+'Reversion Pagos R4'!Q170+'Reversion Pagos R4'!R170 -> 279.03 | AD67: =-J67+AE67 -> 13641155 | AE67: ='Reversion Pagos R4'!D171 -> 13641155 | AF67: =SUM(U67:AD67) -> -23839263 | AG67: =(AF67-O67) -> 3.7252903e-09 | AH67: =INT(AG67)=0 -> TRUE
B68: 3 | C68: CIUDAD LIMPIA BOGOTA S.A. ESP. | D68: ='Reversion Pagos R4'!D201 -> -7715664 | E68: ='Reversion Pagos R4'!E201 -> -515652.37 | F68: ='Reversion Pagos R4'!F201 -> -290186.96 | G68: ='Reversion Pagos R4'!G201 -> -152964.71 | H68: ='Reversion Pagos R4'!H201 -> -1792017.6 | I68: ='Reversion Pagos R4'!I201 -> -54908.17 | J68: 0 | K68: =D68-E68-F68-G68-H68-I68-J68 -> -4909934.2 | L68: 0 | M68: =K68-L68 -> -4909934.2 | N68: ='Reversion Pagos R4'!P201 -> 0 | O68: =M68+N68 -> -4909934.2 | S68: 3 | T68: CIUDAD LIMPIA BOGOTA S.A. ESP. | U68: ='Reversion Pagos R4'!J201 -> -481653.2 | V68: ='Reversion Pagos R4'!K201 -> -469447.01 | W68: ='Reversion Pagos R4'!L201 -> -2214598.8 | X68: ='Reversion Pagos R4'!M201 -> -1215498.8 | Y68: ='Reversion Pagos R4'!N201 -> -89587.5 | Z68: =-L68 -> 0 | AA68: ='Reversion Pagos R4'!O201 -> -132.42 | AB68: =N68 -> 0 | AC68: =+'Reversion Pagos R4'!Q201+'Reversion Pagos R4'!R201 -> 0 | AD68: =-J68+AE68 -> -439016.54 | AE68: ='Reversion Pagos R4'!D202 -> -439016.54 | AF68: =SUM(U68:AD68) -> -4909934.2 | AG68: =(AF68-O68) -> 0 | AH68: =INT(AG68)=0 -> TRUE
B69: 4 | C69: BOGOTA LIMPIA S.A.S. ESP. | D69: ='Reversion Pagos R4'!D316 -> -1.7856981e+08 | E69: ='Reversion Pagos R4'!E316 -> -11114784 | F69: ='Reversion Pagos R4'!F316 -> -6043741.8 | G69: ='Reversion Pagos R4'!G316 -> -3128653.8 | H69: ='Reversion Pagos R4'!H316 -> -38609422 | I69: ='Reversion Pagos R4'!I316 -> -1383863 | J69: 0 | K69: =D69-E69-F69-G69-H69-I69-J69 -> -1.1828934e+08 | L69: 0 | M69: =K69-L69 -> -1.1828934e+08 | N69: ='Reversion Pagos R4'!P316 -> -49900.44 | O69: =M69+N69 -> -1.1833924e+08 | S69: 4 | T69: BOGOTA LIMPIA S.A.S. ESP. | U69: ='Reversion Pagos R4'!J316 -> -12066172 | V69: ='Reversion Pagos R4'!K316 -> -12247409 | W69: ='Reversion Pagos R4'!L316 -> -61013837 | X69: ='Reversion Pagos R4'!M316 -> -29779547 | Y69: ='Reversion Pagos R4'!N316 -> -2258056.3 | Z69: =-L69 -> 0 | AA69: ='Reversion Pagos R4'!O316 -> 27.97 | AB69: =N69 -> -49900.44 | AC69: =+'Reversion Pagos R4'!Q316+'Reversion Pagos R4'!R316 -> 192.75 | AD69: =-J69+AE69 -> -924544.12 | AE69: ='Reversion Pagos R4'!D317 -> -924544.12 | AF69: =SUM(U69:AD69) -> -1.1833924e+08 | AG69: =(AF69-O69) -> -1.4901161e-08 | AH69: =INT(AG69)=0 -> FALSE
B70: 5 | C70: AREA LIMPIA DISTRITO CAPITAL S.A.S. ESP. | D70: ='Reversion Pagos R4'!D345 -> -4790099 | E70: ='Reversion Pagos R4'!E345 -> -288872.47 | F70: ='Reversion Pagos R4'!F345 -> -159348.35 | G70: ='Reversion Pagos R4'!G345 -> -81360.21 | H70: ='Reversion Pagos R4'!H345 -> -1166766.3 | I70: ='Reversion Pagos R4'!I345 -> -56965.58 | J70: 0 | K70: =D70-E70-F70-G70-H70-I70-J70 -> -3036786.1 | L70: 0 | M70: =K70-L70 -> -3036786.1 | N70: ='Reversion Pagos R4'!P345 -> 0 | O70: =M70+N70 -> -3036786.1 | S70: 5 | T70: AREA LIMPIA DISTRITO CAPITAL S.A.S. ESP. | U70: ='Reversion Pagos R4'!J345 -> -498401.42 | V70: ='Reversion Pagos R4'!K345 -> -466788.11 | W70: ='Reversion Pagos R4'!L345 -> -2254795.1 | X70: ='Reversion Pagos R4'!M345 -> -858640.26 | Y70: ='Reversion Pagos R4'!N345 -> -92941.78 | Z70: =-L70 -> 0 | AA70: ='Reversion Pagos R4'!O345 -> 41.97 | AB70: =N70 -> 0 | AC70: =+'Reversion Pagos R4'!Q345+'Reversion Pagos R4'!R345 -> -0.09 | AD70: =-J70+AE70 -> 1134738.7 | AE70: ='Reversion Pagos R4'!D346 -> 1134738.7 | AF70: =SUM(U70:AD70) -> -3036786.1 | AG70: =(AF70-O70) -> 1.3969839e-09 | AH70: =INT(AG70)=0 -> TRUE
C71: TOTAL | D71: =SUM(D66:D70) -> -2.3759068e+08 | E71: =SUM(E66:E70) -> -15606290 | F71: =SUM(F66:F70) -> -8463236.8 | G71: =SUM(G66:G70) -> -4382795.7 | H71: =SUM(H66:H70) -> -56108065 | I71: =SUM(I66:I70) -> -2000991.5 | J71: =SUM(J66:J70) -> 0 | K71: =SUM(K66:K70) -> -1.5102931e+08 | ... O71: =SUM(O66:O70) -> -1.5107921e+08 | T71: TOTAL | U71: =SUM(U66:U70) -> -17509185 | V71: =SUM(V66:V70) -> -17785385 | W71: =SUM(W66:W70) -> -86335004 | X71: =SUM(X66:X70) -> -39202124 | Y71: =SUM(Y66:Y70) -> -3268151.5 | Z71: =SUM(Z66:Z70) -> 0 | AA71: =SUM(AA66:AA70) -> -11.95 | AB71: =SUM(AB66:AB70) -> -49900.44 | ... AG71: =SUM(AG66:AG70) -> -9.778887e-09 | AH71: =INT(AG71)=0 -> FALSE
Y73: =SUM(U71:Y71) -> -1.6409985e+08
F75: Firma autorizada
F79: PROCERASEO S.A.S. | I79: NIT: 901 153 639 - 0 | M79: Codigo Remuneración: | N79: =N3 -> 2026092 | U79: PROCERASEO S.A.S. | W79: NIT: 901 153 639 - 0 | AA79: Codigo Remuneración: | AD79: =N79 -> 2026092
F80: 3. ESQUEMA FINANCIERO DEL SERVICIO PUBLICO DE ASEO | U80: 3. ESQUEMA FINANCIERO DEL SERVICIO PUBLICO DE ASEO
F81: Resoluciòn UAESP Número 27 de 2018 | U81: Resoluciòn UAESP Número 27 de 2018
C82: Fecha de Proceso: | D82: =D6 -> 46297 | F82: R5 - REMUNERACIÓN SALDOS A FAVOR POR NOTA | U82: =F82 -> R5 - REMUNERACIÓN SALDOS A FAVOR POR NOTA
C83: Hora: | D83: =D7 -> 0.58333333 | F83: Fecha Desde: | G83: =G7 -> 46281 | J83: Feha Hasta: | K83: =K7 -> 46295 | U83: =F83 -> Fecha Desde: | V83: =G83 -> 46281 | X83: =J83 -> Feha Hasta: | Y83: =K83 -> 46295
B84: ASE | C84: Concesionarios | D84: Recaudo Total | E84: Recaudo por disposicion final | F84: Recaudo por tratamiento de lixiviados | G84: Recaudo por Componente VIAT ( Decreto 2412/2018) | H84: Recaudo por aprovechamiento | I84: Recaudo del componente de comercializacion para Aprovechamiento (11,4%) | J84: Balance de subsidio o contribuciones | K84: RECAUDO BASE DE REMUNERACION | L84: Costo de la Interventoría | M84: REMUNERACION FINAL | N84: Conceptos especiales | O84: REMUNERACION FINAL MAS CONCEPTOS ESPECIALES | S84: ASE | T84: Concesionarios | U84: Tarifa de Comercialización del Servicio. ( TCS) | V84: Tarifa de Limpieza Urbana del Servicio. ( TLU) | W84: Tarifa de Barrido y Limpieza del Servicio. ( TBL) | X84: Tarifa de Recolección y Transporte del Servicio. (TRT) | Y84: Recaudo del componente de comercializacion para Aprovechamiento (18,6%) | Z84: Costo de la Interventoría | AA84: Ajuste a la decena | AB84: Conceptos especiales | AC84: Otros | AD84: Diferencial Balance Subsidio y Contribución (Fac vs Rec) | AE84: Balance de subsidio o contribuciones (Recaudo) | AF84: REMUNERACION FINAL MAS CONCEPTOS ESPECIALES
B85: 1 | C85: PROMOAMBIENTAL DISTRITO S.A.S. ESP. | D85: ='AJUSTES - SF-T'!D47 -> 589006.92 | E85: ='AJUSTES - SF-T'!E47 -> 31457.17 | F85: ='AJUSTES - SF-T'!F47 -> 17527.74 | G85: ='AJUSTES - SF-T'!G47 -> 8747.16 | H85: ='AJUSTES - SF-T'!H47 -> 161245.56 | I85: ='AJUSTES - SF-T'!I47 -> 5296.18 | J85: ='AJUSTES - SF-T'!J47 -> 0 | K85: =D85-E85-F85-G85-H85-I85-J85 -> 364733.11 | L85: 0 | M85: =K85-L85 -> 364733.11 | N85: ='AJUSTES - SF-T'!N47 -> 0 | O85: =M85+N85 -> 364733.11 | S85: 1 | T85: PROMOAMBIENTAL DISTRITO S.A.S. ESP. | U85: ='AJUSTES - SF-T'!U47 -> 49817.24 | V85: ='AJUSTES - SF-T'!V47 -> 43798.38 | W85: ='AJUSTES - SF-T'!W47 -> 198669.66 | X85: ='AJUSTES - SF-T'!X47 -> 85917.24 | Y85: ='AJUSTES - SF-T'!Y47 -> 7999.99 | Z85: =-L85 -> 0 | AA85: ='AJUSTES - SF-T'!AA47 -> -1.69 | AB85: =N85 -> 0 | AC85: 0 | AD85: =-J85+AE85 -> -21467.71 | AE85: ='AJUSTES - SF-T'!AD47 -> -21467.71 | AF85: =SUM(U85:AD85) -> 364733.11 | AG85: =AF85-O85 -> 0 | AH85: =INT(AG85)=0 -> TRUE
B86: 2 | C86: LIMPIEZA METROPOLITANA S.A. ESP. | D86: ='AJUSTES - SF-T'!D48 -> 1255716.8 | E86: ='AJUSTES - SF-T'!E48 -> 163409.31 | F86: ='AJUSTES - SF-T'!F48 -> 104244.84 | G86: ='AJUSTES - SF-T'!G48 -> 29379.21 | H86: ='AJUSTES - SF-T'!H48 -> 519166.91 | I86: ='AJUSTES - SF-T'!I48 -> 16772.32 | J86: ='AJUSTES - SF-T'!J48 -> 0 | K86: =D86-E86-F86-G86-H86-I86-J86 -> 422744.2 | L86: 0 | M86: =K86-L86 -> 422744.2 | N86: ='AJUSTES - SF-T'!N48 -> 0 | O86: =M86+N86 -> 422744.2 | S86: 2 | T86: LIMPIEZA METROPOLITANA S.A. ESP. | U86: ='AJUSTES - SF-T'!U48 -> 130175.43 | V86: ='AJUSTES - SF-T'!V48 -> 129243.72 | W86: ='AJUSTES - SF-T'!W48 -> 467899.25 | X86: ='AJUSTES - SF-T'!X48 -> 319723.92 | Y86: ='AJUSTES - SF-T'!Y48 -> 16107.05 | Z86: =-L86 -> 0 | AA86: ='AJUSTES - SF-T'!AA48 -> -8.88 | AB86: =N86 -> 0 | AC86: 0 | AD86: =-J86+AE86 -> -640396.29 | AE86: ='AJUSTES - SF-T'!AD48 -> -640396.29 | AF86: =SUM(U86:AD86) -> 422744.2 | AG86: =AF86-O86 -> 0 | AH86: =INT(AG86)=0 -> TRUE
B87: 3 | C87: CIUDAD LIMPIA BOGOTA S.A. ESP. | D87: ='AJUSTES - SF-T'!D49 -> 102335.71 | E87: ='AJUSTES - SF-T'!E49 -> 6267.13 | F87: ='AJUSTES - SF-T'!F49 -> 3492.01 | G87: ='AJUSTES - SF-T'!G49 -> 1857.22 | H87: ='AJUSTES - SF-T'!H49 -> 21047.14 | I87: ='AJUSTES - SF-T'!I49 -> 743.08 | J87: ='AJUSTES - SF-T'!J49 -> 0 | K87: =D87-E87-F87-G87-H87-I87-J87 -> 68929.13 | L87: 0 | M87: =K87-L87 -> 68929.13 | N87: ='AJUSTES - SF-T'!N49 -> 0 | O87: =M87+N87 -> 68929.13 | S87: 3 | T87: CIUDAD LIMPIA BOGOTA S.A. ESP. | U87: ='AJUSTES - SF-T'!U49 -> 6518.28 | V87: ='AJUSTES - SF-T'!V49 -> 6377.76 | W87: ='AJUSTES - SF-T'!W49 -> 29933.14 | X87: ='AJUSTES - SF-T'!X49 -> 14860.01 | Y87: ='AJUSTES - SF-T'!Y49 -> 1212.4 | Z87: =-L87 -> 0 | AA87: ='AJUSTES - SF-T'!AA49 -> 0 | AB87: =N87 -> 0 | AC87: 0 | AD87: =-J87+AE87 -> 10027.54 | AE87: ='AJUSTES - SF-T'!AD49 -> 10027.54 | AF87: =SUM(U87:AD87) -> 68929.13 | AG87: =AF87-O87 -> 0 | AH87: =INT(AG87)=0 -> TRUE
B88: 4 | C88: BOGOTA LIMPIA S.A.S. ESP. | D88: ='AJUSTES - SF-T'!D50 -> 339659.81 | E88: ='AJUSTES - SF-T'!E50 -> 35792.41 | F88: ='AJUSTES - SF-T'!F50 -> 20194.46 | G88: ='AJUSTES - SF-T'!G50 -> 2067.44 | H88: ='AJUSTES - SF-T'!H50 -> 112556.14 | I88: ='AJUSTES - SF-T'!I50 -> 2826.23 | J88: ='AJUSTES - SF-T'!J50 -> 0 | K88: =D88-E88-F88-G88-H88-I88-J88 -> 166223.13 | L88: 0 | M88: =K88-L88 -> 166223.13 | N88: ='AJUSTES - SF-T'!N50 -> 0 | O88: =M88+N88 -> 166223.13 | S88: 4 | T88: BOGOTA LIMPIA S.A.S. ESP. | U88: ='AJUSTES - SF-T'!U50 -> 27571.69 | V88: ='AJUSTES - SF-T'!V50 -> 34487.27 | W88: ='AJUSTES - SF-T'!W50 -> 46924.4 | X88: ='AJUSTES - SF-T'!X50 -> 96285.04 | Y88: ='AJUSTES - SF-T'!Y50 -> 4611.27 | Z88: =-L88 -> 0 | AA88: ='AJUSTES - SF-T'!AA50 -> -5.29 | AB88: =N88 -> 0 | AC88: 0 | AD88: =-J88+AE88 -> -43651.25 | AE88: ='AJUSTES - SF-T'!AD50 -> -43651.25 | AF88: =SUM(U88:AD88) -> 166223.13 | AG88: =AF88-O88 -> 0 | AH88: =INT(AG88)=0 -> TRUE
B89: 5 | C89: AREA LIMPIA DISTRITO CAPITAL S.A.S. ESP. | D89: ='AJUSTES - SF-T'!D51 -> 0 | E89: ='AJUSTES - SF-T'!E51 -> 0 | F89: ='AJUSTES - SF-T'!F51 -> 0 | G89: ='AJUSTES - SF-T'!G51 -> 0 | H89: ='AJUSTES - SF-T'!H51 -> 0 | I89: ='AJUSTES - SF-T'!I51 -> 0 | J89: ='AJUSTES - SF-T'!J51 -> 0 | K89: =D89-E89-F89-G89-H89-I89-J89 -> 0 | L89: 0 | M89: =K89-L89 -> 0 | N89: ='AJUSTES - SF-T'!N51 -> 0 | O89: =M89+N89 -> 0 | S89: 5 | T89: AREA LIMPIA DISTRITO CAPITAL S.A.S. ESP. | U89: ='AJUSTES - SF-T'!U51 -> 0 | V89: ='AJUSTES - SF-T'!V51 -> 0 | W89: ='AJUSTES - SF-T'!W51 -> 0 | X89: ='AJUSTES - SF-T'!X51 -> 0 | Y89: ='AJUSTES - SF-T'!Y51 -> 0 | Z89: =-L89 -> 0 | AA89: ='AJUSTES - SF-T'!AA51 -> 0 | AB89: =N89 -> 0 | AC89: 0 | AD89: =-J89+AE89 -> 0 | AE89: ='AJUSTES - SF-T'!AD51 -> 0 | AF89: =SUM(U89:AD89) -> 0 | AG89: =AF89-O89 -> 0 | AH89: =INT(AG89)=0 -> TRUE
C90: TOTAL | D90: =SUM(D85:D89) -> 2286719.2 | E90: =SUM(E85:E89) -> 236926.02 | F90: =SUM(F85:F89) -> 145459.05 | G90: =SUM(G85:G89) -> 42051.03 | H90: =SUM(H85:H89) -> 814015.75 | I90: =SUM(I85:I89) -> 25637.81 | J90: =SUM(J85:J89) -> 0 | K90: =SUM(K85:K89) -> 1022629.6 | ... O90: =SUM(O85:O89) -> 1022629.6 | T90: TOTAL | U90: =SUM(U85:U89) -> 214082.64 | V90: =SUM(V85:V89) -> 213907.13 | W90: =SUM(W85:W89) -> 743426.45 | X90: =SUM(X85:X89) -> 516786.21 | Y90: =SUM(Y85:Y89) -> 29930.71 | Z90: =SUM(Z85:Z89) -> 0 | AA90: =SUM(AA85:AA89) -> -15.86 | AB90: =SUM(AB85:AB89) -> 0 | ... AG90: =SUM(AG85:AG89) -> 0 | AH90: =INT(AG90)=0 -> TRUE
Y92: =SUM(U90:Y90) -> 1718133.1
F94: Firma autorizada
F98: PROCERASEO S.A.S. | I98: NIT: 901 153 639 - 0 | M98: Codigo Remuneración: | N98: =N3 -> 2026092 | U98: PROCERASEO S.A.S. | W98: NIT: 901 153 639 - 0 | AA98: Codigo Remuneración: | AD98: =N98 -> 2026092
F99: 3. ESQUEMA FINANCIERO DEL SERVICIO PUBLICO DE ASEO | U99: 3. ESQUEMA FINANCIERO DEL SERVICIO PUBLICO DE ASEO
F100: Resoluciòn UAESP Número 27 de 2018 | U100: Resoluciòn UAESP Número 27 de 2018
C101: Fecha de Proceso: | D101: =D6 -> 46297 | F101: REPORTE CONSOLIDADO TOTAL DE RECAUDO | U101: REPORTE DETALLADO SUBBOLSA RBL DISCRIMINADO POR ACTIVIDADES
C102: Hora: | D102: =D7 -> 0.58333333 | F102: Fecha Desde: | G102: =G7 -> 46281 | J102: Feha Hasta: | K102: =K7 -> 46295 | U102: =F102 -> Fecha Desde: | V102: =G102 -> 46281 | X102: =J102 -> Feha Hasta: | Y102: =K102 -> 46295
B103: ASE | C103: Concesionarios | D103: Recaudo Total | E103: Recaudo por disposicion final | F103: Recaudo por tratamiento de lixiviados | G103: Recaudo por Componente VIAT ( Decreto 2412/2018) | H103: Recaudo por aprovechamiento | I103: Recaudo del componente de comercializacion para Aprovechamiento (11,4%) | J103: Balance de subsidio o contribuciones | K103: RECAUDO BASE DE REMUNERACION | L103: Costo de la Interventoría | M103: REMUNERACION FINAL | N103: Conceptos especiales | O103: REMUNERACION FINAL MAS CONCEPTOS ESPECIALES | S103: ASE | T103: Concesionarios | U103: Tarifa de Comercialización del Servicio. ( TCS) | V103: Tarifa de Limpieza Urbana del Servicio. ( TLU) | W103: Tarifa de Barrido y Limpieza del Servicio. ( TBL) | X103: Tarifa de Recolección y Transporte del Servicio. (TRT) | Y103: Recaudo del componente de comercializacion para Aprovechamiento (18,6%) | Z103: Costo de la Interventoría | AA103: Ajuste a la decena | AB103: Conceptos especiales | AC103: Otros | AD103: Diferencial Balance Subsidio y Contribución (Fac vs Rec) | AE103: Balance de subsidio o contribuciones (Recaudo) | AF103: REMUNERACION FINAL MAS CONCEPTOS ESPECIALES
