Workbook
Name \0: #REF!
Name _1: #REF!
Name _2: #REF!
Name _A655555: #REF!
Name _CFR1: #REF!
Name _cia1: #REF!
Name _XL250: #REF!
Name A: #REF!
Name ADM: [1]!ADM
Name ADM: [1]!ADM
Name ADM: [1]!ADM
Name ADM: [1]!ADM
Name ADM: [1]!ADM
Name ADM_: [1]!ADM
Name ADM_: [1]!ADM
Name ADM_: [1]!ADM
Name ADM_: [1]!ADM
Name ADM_: [1]!ADM
Name AI: #REF!
Name Air: #REF!
Name AP: '[2]TARIFA no aforos'!$C$12
Name Bancos: [3]Fx!$C$1:$C$23
Name CBL: #REF!
Name CCS: #REF!
Name CDT_p: [4]CDT!$C$3
Name CFR: #REF!
Name cia: #REF!
Name COM: #REF!
Name CRT: #REF!
Name CRT___CTEp___CDTp___CMRv: #REF!
Name CRT_aislados: '[4]COSTOS AJUSTADOS'!$C$13
Name CRT_costas: #REF!
Name CTE_p: [4]CTE!$C$5
Name Denominador: #REF!
Name dg: [1]!ADM
Name dg: [1]!ADM
Name dg: [1]!ADM
Name dg: [1]!ADM
Name dg: [1]!ADM
Name DIAS: [5]CONTRA!#REF!
Name Fmerc: #REF!
Name FPS: #REF!
Name InformacionGeneral: [1]!InformacionGeneral
Name InformacionGeneral: [1]!InformacionGeneral
Name InformacionGeneral: [1]!InformacionGeneral
Name InformacionGeneral: [1]!InformacionGeneral
Name InformacionGeneral: [1]!InformacionGeneral
Name INTFIN: #REF!
Name INV: [1]!INV
Name INV: [1]!INV
Name INV: [1]!INV
Name INV: [1]!INV
Name INV: [1]!INV
Name K: #REF!
Name N: '[4]COSTOS AJUSTADOS'!#REF!
Name Na: '[2]TARIFA no aforos'!$C$39
Name nfc: '[4]COSTOS AJUSTADOS'!#REF!
Name OYM: [1]!OYM
Name OYM: [1]!OYM
Name OYM: [1]!OYM

Sheet Recaudo EAAB Reciprocidad
B2: OPORTUNO | C2: ASE | D2: VALOR 1° Q | E2: NUMERO REG. 1°Q | F2: VALOR 2° Q | G2: NUMERO REG. 2°Q
C3: 1 | D3: 0 | E3: 0 | F3: 0 | G3: 0
C4: 2 | D4: 0 | E4: 0 | F4: 0 | G4: 0
C5: 3 | D5: 0 | E5: 0 | F5: 0 | G5: 0
C6: 4 | D6: 0 | E6: 0 | F6: 0 | G6: 0
C7: 5 | D7: 0 | E7: 0 | F7: 0 | G7: 0
C8: X
D9: 0 | E9: 0 | F9: 0 | G9: 0
C11: ASE | D11: VALOR 1° Q | E11: NUMERO REG. 1°Q | F11: VALOR 2° Q | G11: NUMERO REG. 2°Q
B12: EXTEMP. | C12: 1 | D12: 0 | E12: 0 | F12: 0 | G12: 0
C13: 2 | D13: 0 | E13: 0 | F13: 0 | G13: 0
C14: 3 | D14: 0 | E14: 0 | F14: 0 | G14: 0
C15: 4 | D15: 0 | E15: 0 | F15: 0 | G15: 0
C16: 5 | D16: 0 | E16: 0 | F16: 0 | G16: 0
C17: X
D18: 0 | E18: 0 | F18: 0 | G18: 0
C20: ASE | D20: VALOR 1° Q | E20: NUMERO REG. 1°Q | F20: VALOR 2° Q | G20: NUMERO REG. 2°Q | I20: VALOR TOTAL MES | J20: NUMERO REGISTROS MES
B21: TOTAL | C21: 1 | D21: 0 | E21: 0 | F21: 0 | G21: 0 | I21: 0 | J21: 0
C22: 2 | D22: 0 | E22: 0 | F22: 0 | G22: 0 | I22: 0 | J22: 0
C23: 3 | D23: 0 | E23: 0 | F23: 0 | G23: 0 | I23: 0 | J23: 0
C24: 4 | D24: 0 | E24: 0 | F24: 0 | G24: 0 | I24: 0 | J24: 0
C25: 5 | D25: 0 | E25: 0 | F25: 0 | G25: 0 | I25: 0 | J25: 0
C26: X | I26: 0 | J26: 0
D27: 0 | E27: 0 | F27: 0 | G27: 0 | I27: 0 | J27: 0
B31: OPORTUNO | D31: =D9=SUM(D3:D8) -> TRUE | E31: =E9=SUM(E3:E8) -> TRUE | F31: =F9=SUM(F3:F8) -> TRUE | G31: =G9=SUM(G3:G8) -> TRUE
B33: EXTEMP. | D33: =D18=SUM(D12:D17) -> TRUE | E33: =E18=SUM(E12:E17) -> TRUE | F33: =F18=SUM(F12:F17) -> TRUE | G33: =G18=SUM(G12:G17) -> TRUE
B35: TOTAL | D35: =D27=SUM(D21:D26) -> TRUE | E35: =E27=SUM(E21:E26) -> TRUE | F35: =F27=SUM(F21:F26) -> TRUE | G35: =G27=SUM(G21:G26) -> TRUE | I35: =I27=SUM(I21:I26) -> TRUE | J35: =J27=SUM(J21:J26) -> TRUE
E69: =C69-G17 -> 0

Sheet Recaudo ENEL
B2: OPORTUNO | C2: ASE | D2: VALOR 1° Q | E2: NUMERO REG. 1°Q | F2: VALOR 2° Q | G2: NUMERO REG. 2°Q
C3: 1 | D3: 14382259562 | E3: 305702 | F3: 0 | G3: 0
C4: 2 | D4: 10247752463 | E4: 198695 | F4: 0 | G4: 0
C5: 3 | D5: 8348318512 | E5: 195122 | F5: 0 | G5: 0
C6: 4 | D6: 9859647946 | E6: 172571 | F6: 0 | G6: 0
C7: 5 | D7: 7125653520 | E7: 137028 | F7: 0 | G7: 0
C8: X
D9: 49963632003 | E9: 1009118 | F9: 0 | G9: 0
C11: ASE | D11: VALOR 1° Q | E11: NUMERO REG. 1°Q | F11: VALOR 2° Q | G11: NUMERO REG. 2°Q
B12: EXTEMP. | C12: 1 | D12: 128684600 | E12: 2090 | F12: 0 | G12: 0
C13: 2 | D13: 60162560 | E13: 1233 | F13: 0 | G13: 0
C14: 3 | D14: 58639078 | E14: 1146 | F14: 0 | G14: 0
C15: 4 | D15: 72782190 | E15: 1190 | F15: 0 | G15: 0
C16: 5 | D16: 122557965 | E16: 2207 | F16: 0 | G16: 0
C17: X
D18: 442826393 | E18: 7866 | F18: 0 | G18: 0
C20: ASE | D20: VALOR 1° Q | E20: NUMERO REG. 1°Q | F20: VALOR 2° Q | G20: NUMERO REG. 2°Q | I20: VALOR TOTAL MES | J20: NUMERO REGISTROS MES
B21: TOTAL | C21: 1 | D21: 14510944162 | E21: 307792 | F21: 0 | G21: 0 | I21: 0 | J21: 0
C22: 2 | D22: 10307915023 | E22: 199928 | F22: 0 | G22: 0 | I22: 0 | J22: 0
C23: 3 | D23: 8406957590 | E23: 196268 | F23: 0 | G23: 0 | I23: 0 | J23: 0
C24: 4 | D24: 9932430136 | E24: 173761 | F24: 0 | G24: 0 | I24: 0 | J24: 0
C25: 5 | D25: 7248211485 | E25: 139235 | F25: 0 | G25: 0 | I25: 0 | J25: 0
C26: X | I26: 0 | J26: 0
D27: 50406458396 | E27: 1016984 | F27: 0 | G27: 0 | I27: 0 | J27: 0
B31: OPORTUNO | D31: =D9=SUM(D3:D8) -> TRUE | E31: =E9=SUM(E3:E8) -> TRUE | F31: =F9=SUM(F3:F8) -> TRUE | G31: =G9=SUM(G3:G8) -> TRUE
B33: EXTEMP. | D33: =D18=SUM(D12:D17) -> TRUE | E33: =E18=SUM(E12:E17) -> TRUE | F33: =F18=SUM(F12:F17) -> TRUE | G33: =G18=SUM(G12:G17) -> TRUE
B35: TOTAL | D35: =D27=SUM(D21:D26) -> TRUE | E35: =E27=SUM(E21:E26) -> TRUE | F35: =F27=SUM(F21:F26) -> TRUE | G35: =G27=SUM(G21:G26) -> TRUE | I35: =I27=SUM(I21:I26) -> TRUE | J35: =J27=SUM(J21:J26) -> TRUE
E69: =C69-G17 -> 0

Sheet Recaudo ENERBIT
B2: OPORTUNO | C2: ASE | D2: VALOR 1° Q | E2: NUMERO REG. 1°Q | F2: VALOR 2° Q | G2: NUMERO REG. 2°Q
C3: 1 | D3: 0 | E3: 0 | F3: 0 | G3: 0
C4: 2 | D4: 0 | E4: 0 | F4: 0 | G4: 0
C5: 3 | D5: 0 | E5: 0 | F5: 0 | G5: 0
C6: 4 | D6: 0 | E6: 0 | F6: 0 | G6: 0
C7: 5 | D7: 140424760 | E7: 2998 | F7: 0 | G7: 0
C8: X
D9: 140424760 | E9: 2998 | F9: 0 | G9: 0
C11: ASE | D11: VALOR 1° Q | E11: NUMERO REG. 1°Q | F11: VALOR 2° Q | G11: NUMERO REG. 2°Q
B12: EXTEMP. | C12: 1 | D12: 0 | E12: 0 | F12: 0 | G12: 0
C13: 2 | D13: 0 | E13: 0 | F13: 0 | G13: 0
C14: 3 | D14: 0 | E14: 0 | F14: 0 | G14: 0
C15: 4 | D15: 0 | E15: 0 | F15: 0 | G15: 0
C16: 5 | D16: 0 | E16: 0 | F16: 0 | G16: 0
C17: X
D18: 0 | E18: 0 | F18: 0 | G18: 0
C20: ASE | D20: VALOR 1° Q | E20: NUMERO REG. 1°Q | F20: VALOR 2° Q | G20: NUMERO REG. 2°Q | I20: VALOR TOTAL MES | J20: NUMERO REGISTROS MES
B21: TOTAL | C21: 1 | D21: 0 | E21: 0 | F21: 0 | G21: 0 | I21: 0 | J21: 0
C22: 2 | D22: 0 | E22: 0 | F22: 0 | G22: 0 | I22: 0 | J22: 0
C23: 3 | D23: 0 | E23: 0 | F23: 0 | G23: 0 | I23: 0 | J23: 0
C24: 4 | D24: 0 | E24: 0 | F24: 0 | G24: 0 | I24: 0 | J24: 0
C25: 5 | D25: 140424760 | E25: 2998 | F25: 0 | G25: 0 | I25: 0 | J25: 0
C26: X | I26: 0 | J26: 0
D27: 140424760 | E27: 2998 | F27: 0 | G27: 0 | I27: 0 | J27: 0
B31: OPORTUNO | D31: =D9=SUM(D3:D8) -> TRUE | E31: =E9=SUM(E3:E8) -> TRUE | F31: =F9=SUM(F3:F8) -> TRUE | G31: =G9=SUM(G3:G8) -> TRUE
B33: EXTEMP. | D33: =D18=SUM(D12:D17) -> TRUE | E33: =E18=SUM(E12:E17) -> TRUE | F33: =F18=SUM(F12:F17) -> TRUE | G33: =G18=SUM(G12:G17) -> TRUE
B35: TOTAL | D35: =D27=SUM(D21:D26) -> TRUE | E35: =E27=SUM(E21:E26) -> TRUE | F35: =F27=SUM(F21:F26) -> TRUE | G35: =G27=SUM(G21:G26) -> TRUE | I35: =I27=SUM(I21:I26) -> TRUE | J35: =J27=SUM(J21:J26) -> TRUE
E69: =C69-G17 -> 0

Sheet Recaudo EAAB + Ciud Limp
B2: Ciudad Limpia - Prestador | C2: ASE | D2: VALOR 1° Q | E2: NUMERO REG. 1°Q | F2: VALOR 2° Q | G2: NUMERO REG. 2°Q
C3: 1 | D3: 0 | E3: 0 | F3: 0 | G3: 0
C4: 2 | D4: 0 | E4: 0 | F4: 0 | G4: 0
C5: 3 | D5: 0 | E5: 0 | F5: 0 | G5: 0
C6: 4 | D6: 0 | E6: 0 | F6: 0 | G6: 0
C7: 5 | D7: 0 | E7: 0 | F7: 0 | G7: 0
C8: X
D9: 0 | E9: 0 | F9: 0 | G9: 0
C11: ASE | D11: VALOR 1° Q | E11: NUMERO REG. 1°Q | F11: VALOR 2° Q | G11: NUMERO REG. 2°Q
B12: EAAB - Prestador | C12: 1 | D12: 0 | E12: 0 | F12: 0 | G12: 0
C13: 2 | D13: 0 | E13: 0 | F13: 0 | G13: 0
C14: 3 | D14: 0 | E14: 0 | F14: 0 | G14: 0
C15: 4 | D15: 0 | E15: 0 | F15: 0 | G15: 0
C16: 5 | D16: 0 | E16: 0 | F16: 0 | G16: 0
C17: X
D18: 0 | E18: 0 | F18: 0 | G18: 0
C20: ASE | D20: VALOR 1° Q | E20: NUMERO REG. 1°Q | F20: VALOR 2° Q | G20: NUMERO REG. 2°Q | I20: VALOR TOTAL MES | J20: NUMERO REGISTROS MES
B21: TOTAL | C21: 1 | D21: 0 | E21: 0 | F21: 0 | G21: 0 | I21: 0 | J21: 0
C22: 2 | D22: 0 | E22: 0 | F22: 0 | G22: 0 | I22: 0 | J22: 0
C23: 3 | D23: 0 | E23: 0 | F23: 0 | G23: 0 | I23: 0 | J23: 0
C24: 4 | D24: 0 | E24: 0 | F24: 0 | G24: 0 | I24: 0 | J24: 0
C25: 5 | D25: 0 | E25: 0 | F25: 0 | G25: 0 | I25: 0 | J25: 0
C26: X | I26: 0 | J26: 0
D27: 0 | E27: 0 | F27: 0 | G27: 0 | I27: 0 | J27: 0
B31: OPORTUNO | D31: =D9=SUM(D3:D8) -> TRUE | E31: =E9=SUM(E3:E8) -> TRUE | F31: =F9=SUM(F3:F8) -> TRUE | G31: =G9=SUM(G3:G8) -> TRUE
B33: EXTEMP. | D33: =D18=SUM(D12:D17) -> TRUE | E33: =E18=SUM(E12:E17) -> TRUE | F33: =F18=SUM(F12:F17) -> TRUE | G33: =G18=SUM(G12:G17) -> TRUE
B35: TOTAL | D35: =D27=SUM(D21:D26) -> TRUE | E35: =E27=SUM(E21:E26) -> TRUE | F35: =F27=SUM(F21:F26) -> TRUE | G35: =G27=SUM(G21:G26) -> TRUE | I35: =I27=SUM(I21:I26) -> TRUE | J35: =J27=SUM(J21:J26) -> TRUE

Sheet Recaudo Directa Occidente
B2: OPORTUNO | C2: ASE | D2: VALOR 1° Q | E2: NUMERO REG. 1°Q | F2: VALOR 2° Q | G2: NUMERO REG. 2°Q
C3: 1 | D3: 322739090 | E3: 1616 | F3: 0 | G3: 0
C4: 2 | D4: 839789795 | E4: 3964 | F4: 0 | G4: 0
C5: 3 | D5: 417500887 | E5: 1376 | F5: 0 | G5: 0
C6: 4 | D6: 481464262 | E6: 2591 | F6: 0 | G6: 0
C7: 5 | D7: 168793421 | E7: 1160 | F7: 0 | G7: 0
C8: X | D8: 0 | E8: 0 | F8: 0 | G8: 0
D9: 2230287455 | E9: 10707 | F9: 0 | G9: 0
C11: ASE | D11: VALOR 1° Q | E11: NUMERO REG. 1°Q | F11: VALOR 2° Q | G11: NUMERO REG. 2°Q
B12: EXTEMP. | C12: 1 | D12: 48127653 | E12: 73 | F12: 0 | G12: 0
C13: 2 | D13: 132160935 | E13: 54 | F13: 0 | G13: 0
C14: 3 | D14: 19609348 | E14: 11 | F14: 0 | G14: 0
C15: 4 | D15: 118198907 | E15: 9 | F15: 0 | G15: 0
C16: 5 | D16: 7112332 | E16: 27 | F16: 0 | G16: 0
C17: X | D17: 0 | E17: 0 | F17: 0 | G17: 0
D18: 325209175 | E18: 174 | F18: 0 | G18: 0
C20: ASE | D20: VALOR 1° Q | E20: NUMERO REG. 1°Q | F20: VALOR 2° Q | G20: NUMERO REG. 2°Q | I20: VALOR TOTAL MES | J20: NUMERO REGISTROS MES
B21: TOTAL | C21: 1 | D21: 370866743 | E21: 1689 | F21: 0 | G21: 0 | I21: 0 | J21: 0
C22: 2 | D22: 971950730 | E22: 4018 | F22: 0 | G22: 0 | I22: 0 | J22: 0
C23: 3 | D23: 437110235 | E23: 1387 | F23: 0 | G23: 0 | I23: 0 | J23: 0
C24: 4 | D24: 599663169 | E24: 2600 | F24: 0 | G24: 0 | I24: 0 | J24: 0
C25: 5 | D25: 175905753 | E25: 1187 | F25: 0 | G25: 0 | I25: 0 | J25: 0
C26: X | D26: 0 | E26: 0 | F26: 0 | G26: 0 | I26: 0 | J26: 0
D27: 2555496630 | E27: 10881 | F27: 0 | G27: 0 | I27: 0 | J27: 0
B31: OPORTUNO | D31: =D9=SUM(D3:D8) -> TRUE | E31: =E9=SUM(E3:E8) -> TRUE | F31: =F9=SUM(F3:F8) -> TRUE | G31: =G9=SUM(G3:G8) -> TRUE
B33: EXTEMP. | D33: =D18=SUM(D12:D17) -> TRUE | E33: =E18=SUM(E12:E17) -> TRUE | F33: =F18=SUM(F12:F17) -> TRUE | G33: =G18=SUM(G12:G17) -> TRUE
B35: TOTAL | D35: =D27=SUM(D21:D26) -> TRUE | E35: =E27=SUM(E21:E26) -> TRUE | F35: =F27=SUM(F21:F26) -> TRUE | G35: =G27=SUM(G21:G26) -> TRUE | I35: =I27=SUM(I21:I26) -> TRUE | J35: =J27=SUM(J21:J26) -> TRUE
E69: =C69-G17 -> 0

Sheet REPORTE RECAUDO x BANCO
C1: ENEL | D1: CIUDAD LIMPIA | E1: EAB | F1: NUEVO ESQUEMA | G1: ENERBIT | H1: OCCIDENTE | I1: Total
B2: 1-APLICADOS A FACTURACION | C2: =C13+C23+C32+C41+C51 -> 5.0300863e+10 | D2: =D13+D23+D32+D41+D51 -> 0 | E2: =E13+E23+E32+E41+E51 -> 0 | F2: =F13+F23+F32+F41+F51 -> 0 | G2: =G13+G23+G32+G41+G51 -> 139510580 | H2: =H13+H23+H32+H41+H51 -> 2.4480562e+09 | I2: =SUM(C2:H2) -> 5.288843e+10
B3: 2-SALDOS A FAVOR GENERADOS | C3: =C14+C24+C33+C42+C52 -> 1.0831116e+08 | D3: =D14+D24+D33+D42+D52 -> 0 | E3: =E14+E24+E33+E42+E52 -> 0 | F3: =F14+F24+F33+F42+F52 -> 0 | G3: =G14+G24+G33+G42+G52 -> 914180 | H3: =H14+H24+H33+H42+H52 -> 61958868 | I3: =SUM(C3:H3) -> 1.7118421e+08
B4: 3-APLICADOS A FINANCIACIONES NUEVAS | C4: =C15+C25+C34+C43+C53 -> 0 | D4: =D15+D25+D34+D43+D53 -> 0 | E4: =E15+E25+E34+E43+E53 -> 0 | F4: =F15+F25+F34+F43+F53 -> 0 | G4: =G15+G25+G34+G43+G53 -> 0 | H4: =H15+H25+H34+H43+H53 -> 45481533 | I4: =SUM(C4:H4) -> 45481533
B5: 7-APLICADOS A RECIBOS SERVICIOS ESPECIALES | C5: =C16+C26+C35+C44+C54 -> 0 | D5: =D16+D26+D35+D44+D54 -> 0 | E5: =E16+E26+E35+E44+E54 -> 0 | F5: =F16+F26+F35+F44+F54 -> 0 | G5: =G16+G26+G35+G44+G54 -> 0 | H5: =H16+H26+H35+H44+H54 -> 0 | I5: =SUM(C5:H5) -> 0
B6: Total | C6: =SUM(C2:C5) -> 50409174172 | D6: =SUM(D2:D5) -> 0 | E6: =SUM(E2:E5) -> 0 | F6: =SUM(F2:F5) -> 0 | G6: =SUM(G2:G5) -> 140424760 | H6: =SUM(H2:H5) -> 2.5554966e+09 | I6: =SUM(I2:I5) -> 5.3105096e+10
C7: =C6=(C17+C27+C36+C45+C55) -> TRUE | D7: =D6=(D17+D27+D36+D45+D55) -> TRUE | E7: =E6=(E17+E27+E36+E45+E55) -> TRUE | F7: =F6=(F17+F27+F36+F45+F55) -> TRUE | H7: =H6=(H17+H27+H36+H45+H55) -> TRUE | I7: =I6=(I17+I27+I36+I45+I55) -> TRUE
B10: ASE 1
B11: Resumen Recaudo Aplicado Por Servicio
C12: ENEL | D12: CIUDAD LIMPIA | E12: EAB | F12: NUEVO ESQUEMA | G12: ENERBIT | H12: OCCIDENTE | I12: Total
B13: 1-APLICADOS A FACTURACION | C13: 14481337615 | D13: 0 | E13: 0 | F13: 0 | G13: 0 | H13: 3.5146605e+08 | I13: =SUM(C13:H13) -> 1.4832804e+10 | J13: =SUM(C13:H13)=I13 -> TRUE
B14: 2-SALDOS A FAVOR GENERADOS | C14: 29606547 | D14: 0 | E14: 0 | F14: 0 | G14: 0 | H14: 17250690 | I14: =SUM(C14:H14) -> 46857237 | J14: =SUM(C14:H14)=I14 -> TRUE
B15: 3-APLICADOS A FINANCIACIONES NUEVAS | C15: 0 | D15: 0 | E15: 0 | F15: 0 | G15: 0 | H15: 2150000 | I15: =SUM(C15:H15) -> 2150000 | J15: =SUM(C15:H15)=I15 -> TRUE
B16: 7-APLICADOS A RECIBOS SERVICIOS ESPECIALES | C16: 0 | D16: 0 | E16: 0 | F16: 0 | G16: 0 | H16: 0 | I16: =SUM(C16:H16) -> 0 | J16: =SUM(C16:H16)=I16 -> TRUE
B17: Total | C17: =SUM(C13:C16) -> 14510944162 | D17: =SUM(D13:D16) -> 0 | E17: =SUM(E13:E16) -> 0 | F17: =SUM(F13:F16) -> 0 | G17: =SUM(G13:G16) -> 0 | H17: =SUM(H13:H16) -> 370866743 | I17: =SUM(I13:I16) -> 14881810905 | J17: =SUM(C17:H17)=I17 -> TRUE
B20: ASE 2
B21: Resumen Recaudo Aplicado Por Servicio
C22: ENEL | D22: CIUDAD LIMPIA | E22: EAB | F22: NUEVO ESQUEMA | G22: ENERBIT | H22: OCCIDENTE | I22: Total
B23: 1-APLICADOS A FACTURACION | C23: 1.0286935e+10 | D23: 0 | E23: 0 | F23: 0 | G23: 0 | H23: 9.240376e+08 | I23: =SUM(C23:H23) -> 1.1210973e+10 | J23: =SUM(C23:H23)=I23 -> TRUE
B24: 2-SALDOS A FAVOR GENERADOS | C24: 22325147 | D24: 0 | E24: 0 | F24: 0 | G24: 0 | H24: 29950515 | I24: =SUM(C24:H24) -> 52275662 | J24: =SUM(C24:H24)=I24 -> TRUE
B25: 3-APLICADOS A FINANCIACIONES NUEVAS | C25: 0 | D25: 0 | E25: 0 | F25: 0 | G25: 0 | H25: 17962612 | I25: =SUM(C25:H25) -> 17962612 | J25: =SUM(C25:H25)=I25 -> TRUE
B26: 7-APLICADOS A RECIBOS SERVICIOS ESPECIALES | C26: 0 | D26: 0 | E26: 0 | F26: 0 | G26: 0 | H26: 0 | I26: =SUM(C26:H26) -> 0 | J26: =SUM(C26:H26)=I26 -> TRUE
B27: Total | C27: =SUM(C23:C26) -> 10309260573 | D27: =SUM(D23:D26) -> 0 | E27: =SUM(E23:E26) -> 0 | F27: =SUM(F23:F26) -> 0 | G27: =SUM(G23:G26) -> 0 | H27: =SUM(H23:H26) -> 971950730 | I27: =SUM(I23:I26) -> 11281211303 | J27: =SUM(C27:H27)=I27 -> TRUE
B29: ASE 3
B30: Resumen Recaudo Aplicado Por Servicio
C31: ENEL | D31: CIUDAD LIMPIA | E31: EAB | F31: NUEVO ESQUEMA | G31: ENERBIT | H31: OCCIDENTE | I31: Total
B32: 1-APLICADOS A FACTURACION | C32: 8398576932 | D32: 0 | E32: 0 | F32: 0 | G32: 0 | H32: 4.3152163e+08 | I32: =SUM(C32:H32) -> 8.8300986e+09 | J32: =SUM(C32:H32)=I32 -> TRUE
B33: 2-SALDOS A FAVOR GENERADOS | C33: 8845080 | D33: 0 | E33: 0 | F33: 0 | G33: 0 | H33: 4909289 | I33: =SUM(C33:H33) -> 13754369 | J33: =SUM(C33:H33)=I33 -> TRUE
B34: 3-APLICADOS A FINANCIACIONES NUEVAS | C34: 0 | D34: 0 | E34: 0 | F34: 0 | G34: 0 | H34: 679320.71 | I34: =SUM(C34:H34) -> 679320.71 | J34: =SUM(C34:H34)=I34 -> TRUE
B35: 7-APLICADOS A RECIBOS SERVICIOS ESPECIALES | C35: 0 | D35: 0 | E35: 0 | F35: 0 | G35: 0 | H35: 0 | I35: =SUM(C35:H35) -> 0 | J35: =SUM(C35:H35)=I35 -> TRUE
B36: Total | C36: =SUM(C32:C35) -> 8407422012 | D36: =SUM(D32:D35) -> 0 | E36: =SUM(E32:E35) -> 0 | F36: =SUM(F32:F35) -> 0 | G36: =SUM(G32:G35) -> 0 | H36: =SUM(H32:H35) -> 437110235 | I36: =SUM(I32:I35) -> 8844532247 | J36: =SUM(C36:H36)=I36 -> TRUE
B38: ASE 4
B39: Resumen Recaudo Aplicado Por Servicio
C40: ENEL | D40: CIUDAD LIMPIA | E40: EAB | F40: NUEVO ESQUEMA | G40: ENERBIT | H40: OCCIDENTE | I40: Total
B41: 1-APLICADOS A FACTURACION | C41: 9890363914 | D41: 0 | E41: 0 | F41: 0 | G41: 0 | H41: 5.6767788e+08 | I41: =SUM(C41:H41) -> 1.0458042e+10 | J41: =SUM(C41:H41)=I41 -> TRUE
B42: 2-SALDOS A FAVOR GENERADOS | C42: 42284806 | D42: 0 | E42: 0 | F42: 0 | G42: 0 | H42: 7416134 | I42: =SUM(C42:H42) -> 49700940 | J42: =SUM(C42:H42)=I42 -> TRUE
B43: 3-APLICADOS A FINANCIACIONES NUEVAS | C43: 0 | D43: 0 | E43: 0 | F43: 0 | G43: 0 | H43: 24569155 | I43: =SUM(C43:H43) -> 24569155 | J43: =SUM(C43:H43)=I43 -> TRUE
B44: 7-APLICADOS A RECIBOS SERVICIOS ESPECIALES | C44: 0 | D44: 0 | E44: 0 | F44: 0 | G44: 0 | H44: 0 | I44: =SUM(C44:H44) -> 0 | J44: =SUM(C44:H44)=I44 -> TRUE
B45: Total | C45: =SUM(C41:C44) -> 9932648720 | D45: =SUM(D41:D44) -> 0 | E45: =SUM(E41:E44) -> 0 | F45: =SUM(F41:F44) -> 0 | G45: =SUM(G41:G44) -> 0 | H45: =SUM(H41:H44) -> 599663169 | I45: =SUM(I41:I44) -> 10532311889 | J45: =SUM(C45:H45)=I45 -> TRUE
B48: ASE 5
B49: Resumen Recaudo Aplicado Por Servicio
C50: ENEL | D50: CIUDAD LIMPIA | E50: EAB | F50: NUEVO ESQUEMA | G50: ENERBIT | H50: OCCIDENTE | I50: Total
B51: 1-APLICADOS A FACTURACION | C51: 7243649125 | D51: 0 | E51: 0 | F51: 0 | G51: 139510580 | H51: 1.7335307e+08 | I51: =SUM(C51:H51) -> 7.5565128e+09 | J51: =SUM(C51:H51)=I51 -> TRUE
B52: 2-SALDOS A FAVOR GENERADOS | C52: 5249580 | D52: 0 | E52: 0 | F52: 0 | G52: 914180 | H52: 2432240 | I52: =SUM(C52:H52) -> 8596000 | J52: =SUM(C52:H52)=I52 -> TRUE
B53: 3-APLICADOS A FINANCIACIONES NUEVAS | C53: 0 | D53: 0 | E53: 0 | F53: 0 | G53: 0 | H53: 120445.76 | I53: =SUM(C53:H53) -> 120445.76 | J53: =SUM(C53:H53)=I53 -> TRUE
B54: 7-APLICADOS A RECIBOS SERVICIOS ESPECIALES | C54: 0 | D54: 0 | E54: 0 | F54: 0 | G54: 0 | H54: 0 | I54: =SUM(C54:H54) -> 0 | J54: =SUM(C54:H54)=I54 -> TRUE
B55: Total | C55: =SUM(C51:C54) -> 7248898705 | D55: =SUM(D51:D54) -> 0 | E55: =SUM(E51:E54) -> 0 | F55: =SUM(F51:F54) -> 0 | G55: =SUM(G51:G54) -> 140424760 | H55: =SUM(H51:H54) -> 175905753 | I55: =SUM(I51:I54) -> 7565229218 | J55: =SUM(C55:H55)=I55 -> TRUE
B59: QUINCENA | C59: 1 | D59: OJO/// DILIGENCIAR
B62: Recaudo ENEL - ASE 1 | C62: =IF($C$59=1,'Recaudo ENEL'!D21,'Recaudo ENEL'!F21) -> 14510944162 | D62: =C17=C62 -> TRUE | E62: =C17-C62 -> 0
B63: Recaudo ENERBIT - ASE 1 | C63: =IF($C$59=1,'Recaudo ENERBIT'!D21,'Recaudo ENERBIT'!F21) -> 0 | D63: =G17=C63 -> TRUE | E63: =G17-C63 -> 0
B64: Recaudo Reciprocidad EAAB - ASE 2 | C64: =IF($C$59=1,'Recaudo EAAB Reciprocidad'!D22,'Recaudo EAAB Reciprocidad'!F22) -> 0 | D64: =F27=C64 -> TRUE | E64: =F27-C64 -> 0
B65: Recaudo ENEL - ASE 2 | C65: =IF($C$59=1,'Recaudo ENEL'!D22,'Recaudo ENEL'!F22) -> 10307915023 | D65: =C27=C65 -> FALSE | E65: =C27-C65 -> 1345550
B66: Recaudo ENERBIT - ASE 2 | C66: =IF($C$59=1,'Recaudo ENERBIT'!D22,'Recaudo ENERBIT'!F22) -> 0 | D66: =G27=C66 -> TRUE | E66: =G27-C66 -> 0
B67: Recaudo ENEL - ASE 3 | C67: =IF($C$59=1,'Recaudo ENEL'!D23,'Recaudo ENEL'!F23) -> 8406957590 | D67: =C36=C67 -> FALSE | E67: =C36-C67 -> 464422
B68: Recaudo ENERBIT - ASE 3 | C68: =IF($C$59=1,'Recaudo ENERBIT'!D23,'Recaudo ENERBIT'!F23) -> 0 | D68: =G36=C68 -> TRUE | E68: =G36-C68 -> 0
B69: Recaudo Reciprocidad EAAB - ASE 4 | C69: =IF($C$59=1,'Recaudo EAAB Reciprocidad'!D24,'Recaudo EAAB Reciprocidad'!F24) -> 0 | D69: =F45=C69 -> TRUE | E69: =F45-C69 -> 0
B70: Recaudo ENEL - ASE 4 | C70: =IF($C$59=1,'Recaudo ENEL'!D24,'Recaudo ENEL'!F24) -> 9932430136 | D70: =C45=C70 -> FALSE | E70: =C45-C70 -> 218584
B71: Recaudo ENERBIT - ASE 4 | C71: =IF($C$59=1,'Recaudo ENERBIT'!D24,'Recaudo ENERBIT'!F24) -> 0 | D71: =G45=C71 -> TRUE | E71: =G45-C71 -> 0
B72: Recaudo ENEL - ASE 5 | C72: =IF($C$59=1,'Recaudo ENEL'!D25,'Recaudo ENEL'!F25) -> 7248211485 | D72: =C55=C72 -> FALSE | E72: =C55-C72 -> 687220
B73: Recaudo ENERBIT - ASE 5 | C73: =IF($C$59=1,'Recaudo ENERBIT'!D25,'Recaudo ENERBIT'!F25) -> 140424760 | D73: =G55=C73 -> TRUE | E73: =G55-C73 -> 0
B75: Recaudo Banco Occidente ASE 1 | C75: =IF($C$59=1,'Recaudo Directa Occidente'!D21,'Recaudo Directa Occidente'!F21) -> 370866743 | D75: =C75=H17 -> TRUE | E75: =C75-H17 -> 0
B76: Recaudo Banco Occidente ASE 2 | C76: =IF($C$59=1,'Recaudo Directa Occidente'!D22,'Recaudo Directa Occidente'!F22) -> 971950730 | D76: =C76=H27 -> TRUE | E76: =C76-H27 -> 0
B77: Recaudo Banco Occidente ASE 3 | C77: =IF($C$59=1,'Recaudo Directa Occidente'!D23,'Recaudo Directa Occidente'!F23) -> 437110235 | D77: =C77=H36 -> TRUE | E77: =C77-H36 -> 0
B78: Recaudo Banco Occidente ASE 4 | C78: =IF($C$59=1,'Recaudo Directa Occidente'!D24,'Recaudo Directa Occidente'!F24) -> 599663169 | D78: =C78=H45 -> TRUE | E78: =C78-H45 -> 0
B79: Recaudo Banco Occidente ASE 5 | C79: =IF($C$59=1,'Recaudo Directa Occidente'!D25,'Recaudo Directa Occidente'!F25) -> 175905753 | D79: =C79=H55 -> TRUE | E79: =C79-H55 -> 0

Sheet ANT EXT-REV
C1: ASE 1 | E1: ASE 2 | G1: ASE 3 | I1: ASE 4 | K1: ASE 5 | M1: TOTAL
C2: REPORTE 3 | D2: REPORTE 4 | E2: REPORTE 3 | F2: REPORTE 4 | G2: REPORTE 3 | H2: REPORTE 4 | I2: REPORTE 3 | J2: REPORTE 4 | K2: REPORTE 3 | L2: REPORTE 4 | M2: REPORTE 3 | N2: REPORTE 4
B3: APLICADO | C3: =C11+C19+C27+C35+C43 -> 0 | D3: =D11+D19+D27+D35+D43 -> 0 | E3: =E11+E19+E27+E35+E43 -> 0 | F3: =F11+F19+F27+F35+F43 -> 0 | G3: =G11+G19+G27+G35+G43 -> 0 | H3: =H11+H19+H27+H35+H43 -> 0 | I3: =I11+I19+I27+I35+I43 -> 0 | J3: =J11+J19+J27+J35+J43 -> 0 | ... L3: =L11+L19+L27+L35+L43 -> 0 | M3: =C3+E3+G3+I3+K3 -> 0 | N3: =D3+F3+H3+J3+L3 -> 0 | P3: =N3=(-VALIDACION_TOTAL!M9) -> FALSE
B4: ANTICIPOS | C4: =C12+C20+C28+C36+C44 -> 0 | D4: =D12+D20+D28+D36+D44 -> 0 | E4: =E12+E20+E28+E36+E44 -> 0 | F4: =F12+F20+F28+F36+F44 -> 0 | G4: =G12+G20+G28+G36+G44 -> 0 | H4: =H12+H20+H28+H36+H44 -> 0 | I4: =I12+I20+I28+I36+I44 -> 0 | J4: =J12+J20+J28+J36+J44 -> 0 | ... L4: =L12+L20+L28+L36+L44 -> 0 | M4: =C4+E4+G4+I4+K4 -> 0 | N4: =D4+F4+H4+J4+L4 -> 0 | P4: =N4=(-'CONSOLIDADO_TOTAL RECAUDO'!L131) -> TRUE
B5: TOTAL | C5: =SUM(C3:C4) -> 0 | D5: =SUM(D3:D4) -> 0 | E5: =SUM(E3:E4) -> 0 | F5: =SUM(F3:F4) -> 0 | G5: =SUM(G3:G4) -> 0 | H5: =SUM(H3:H4) -> 0 | I5: =SUM(I3:I4) -> 0 | J5: =SUM(J3:J4) -> 0 | ... N5: =SUM(N3:N4) -> 0
C6: =C5=(C13+C21+C29+C37+C45) -> TRUE | D6: =D5=(D13+D21+D29+D37+D45) -> TRUE | E6: =E5=(E13+E21+E29+E37+E45) -> TRUE | F6: =F5=(F13+F21+F29+F37+F45) -> TRUE | G6: =G5=(G13+G21+G29+G37+G45) -> TRUE | H6: =H5=(H13+H21+H29+H37+H45) -> TRUE | I6: =I5=(I13+I21+I29+I37+I45) -> TRUE | J6: =J5=(J13+J21+J29+J37+J45) -> TRUE | ... N6: =N5=(N13+N21+N29+N37+N45) -> TRUE
B8: BANCO DE OCCIDENTE
C9: ASE 1 | E9: ASE 2 | G9: ASE 3 | I9: ASE 4 | K9: ASE 5 | M9: TOTAL
C10: REPORTE 3 | D10: REPORTE 4 | E10: REPORTE 3 | F10: REPORTE 4 | G10: REPORTE 3 | H10: REPORTE 4 | I10: REPORTE 3 | J10: REPORTE 4 | K10: REPORTE 3 | L10: REPORTE 4 | M10: REPORTE 3 | N10: REPORTE 4
B11: APLICADO | C11: 0 | D11: 0 | E11: 0 | F11: 0 | G11: 0 | H11: 0 | I11: 0 | J11: 0 | K11: 0 | L11: 0 | M11: =C11+E11+G11+I11+K11 -> 0 | N11: =D11+F11+H11+J11+L11 -> 0
B12: ANTICIPOS | C12: 0 | D12: 0 | E12: 0 | F12: 0 | G12: 0 | H12: 0 | I12: 0 | J12: 0 | K12: 0 | L12: 0 | M12: =C12+E12+G12+I12+K12 -> 0 | N12: =D12+F12+H12+J12+L12 -> 0
B13: TOTAL | C13: =SUM(C11:C12) -> 0 | D13: =SUM(D11:D12) -> 0 | E13: =SUM(E11:E12) -> 0 | F13: =SUM(F11:F12) -> 0 | G13: =SUM(G11:G12) -> 0 | H13: =SUM(H11:H12) -> 0 | I13: =SUM(I11:I12) -> 0 | J13: =SUM(J11:J12) -> 0 | ... N13: =SUM(N11:N12) -> 0
B16: EAAB RECIPROCIDAD
C17: ASE 1 | E17: ASE 2 | G17: ASE 3 | I17: ASE 4 | K17: ASE 5 | M17: TOTAL
C18: REPORTE 3 | D18: REPORTE 4 | E18: REPORTE 3 | F18: REPORTE 4 | G18: REPORTE 3 | H18: REPORTE 4 | I18: REPORTE 3 | J18: REPORTE 4 | K18: REPORTE 3 | L18: REPORTE 4 | M18: REPORTE 3 | N18: REPORTE 4
B19: APLICADO | C19: 0 | D19: 0 | E19: 0 | F19: 0 | G19: 0 | H19: 0 | I19: 0 | J19: 0 | K19: 0 | L19: 0 | M19: =C19+E19+G19+I19+K19 -> 0 | N19: =D19+F19+H19+J19+L19 -> 0
B20: ANTICIPOS | C20: 0 | D20: 0 | E20: 0 | F20: 0 | G20: 0 | H20: 0 | I20: 0 | J20: 0 | K20: 0 | L20: 0 | M20: =C20+E20+G20+I20+K20 -> 0 | N20: =D20+F20+H20+J20+L20 -> 0
B21: TOTAL | C21: =SUM(C19:C20) -> 0 | D21: =SUM(D19:D20) -> 0 | E21: =SUM(E19:E20) -> 0 | F21: =SUM(F19:F20) -> 0 | G21: =SUM(G19:G20) -> 0 | H21: =SUM(H19:H20) -> 0 | I21: =SUM(I19:I20) -> 0 | J21: =SUM(J19:J20) -> 0 | ... L21: =SUM(L19:L20) -> 0 | M21: =C21+E21+G21+I21+K21 -> 0 | N21: =SUM(N19:N20) -> 0
B24: EAAB CIUDAD LIMPIA
C25: ASE 1 | E25: ASE 2 | G25: ASE 3 | I25: ASE 4 | K25: ASE 5 | M25: TOTAL
C26: REPORTE 3 | D26: REPORTE 4 | E26: REPORTE 3 | F26: REPORTE 4 | G26: REPORTE 3 | H26: REPORTE 4 | I26: REPORTE 3 | J26: REPORTE 4 | K26: REPORTE 3 | L26: REPORTE 4 | M26: REPORTE 3 | N26: REPORTE 4
B27: APLICADO | C27: 0 | D27: 0 | E27: 0 | F27: 0 | G27: 0 | H27: 0 | I27: 0 | J27: 0 | K27: 0 | L27: 0 | M27: =C27+E27+G27+I27+K27 -> 0 | N27: =D27+F27+H27+J27+L27 -> 0
B28: ANTICIPOS | C28: 0 | D28: 0 | E28: 0 | F28: 0 | G28: 0 | H28: 0 | I28: 0 | J28: 0 | K28: 0 | L28: 0 | M28: =C28+E28+G28+I28+K28 -> 0 | N28: =D28+F28+H28+J28+L28 -> 0
B29: TOTAL | C29: =SUM(C27:C28) -> 0 | D29: =SUM(D27:D28) -> 0 | E29: =SUM(E27:E28) -> 0 | F29: =SUM(F27:F28) -> 0 | G29: =SUM(G27:G28) -> 0 | H29: =SUM(H27:H28) -> 0 | I29: =SUM(I27:I28) -> 0 | J29: =SUM(J27:J28) -> 0 | ... N29: =SUM(N27:N28) -> 0
B32: ENEL
C33: ASE 1 | E33: ASE 2 | G33: ASE 3 | I33: ASE 4 | K33: ASE 5 | M33: TOTAL
C34: REPORTE 3 | D34: REPORTE 4 | E34: REPORTE 3 | F34: REPORTE 4 | G34: REPORTE 3 | H34: REPORTE 4 | I34: REPORTE 3 | J34: REPORTE 4 | K34: REPORTE 3 | L34: REPORTE 4 | M34: REPORTE 3 | N34: REPORTE 4
B35: APLICADO | C35: 0 | D35: 0 | E35: 0 | F35: 0 | G35: 0 | H35: 0 | I35: 0 | J35: 0 | K35: 0 | L35: 0 | M35: =C35+E35+G35+I35+K35 -> 0 | N35: =D35+F35+H35+J35+L35 -> 0
B36: ANTICIPOS | C36: 0 | D36: 0 | E36: 0 | F36: 0 | G36: 0 | H36: 0 | I36: 0 | J36: 0 | K36: 0 | L36: 0 | M36: =C36+E36+G36+I36+K36 -> 0 | N36: =D36+F36+H36+J36+L36 -> 0
B37: TOTAL | C37: =SUM(C35:C36) -> 0 | D37: =SUM(D35:D36) -> 0 | E37: =SUM(E35:E36) -> 0 | F37: =SUM(F35:F36) -> 0 | G37: =SUM(G35:G36) -> 0 | H37: =SUM(H35:H36) -> 0 | I37: =SUM(I35:I36) -> 0 | J37: =SUM(J35:J36) -> 0 | ... N37: =SUM(N35:N36) -> 0
B40: ENERBIT
C41: ASE 1 | E41: ASE 2 | G41: ASE 3 | I41: ASE 4 | K41: ASE 5 | M41: TOTAL
C42: REPORTE 3 | D42: REPORTE 4 | E42: REPORTE 3 | F42: REPORTE 4 | G42: REPORTE 3 | H42: REPORTE 4 | I42: REPORTE 3 | J42: REPORTE 4 | K42: REPORTE 3 | L42: REPORTE 4 | M42: REPORTE 3 | N42: REPORTE 4
B43: APLICADO | C43: 0 | D43: 0 | E43: 0 | F43: 0 | G43: 0 | H43: 0 | I43: 0 | J43: 0 | K43: 0 | L43: 0 | M43: =C43+E43+G43+I43+K43 -> 0 | N43: =D43+F43+H43+J43+L43 -> 0
B44: ANTICIPOS | C44: 0 | D44: 0 | E44: 0 | F44: 0 | G44: 0 | H44: 0 | I44: 0 | J44: 0 | K44: 0 | L44: 0 | M44: =C44+E44+G44+I44+K44 -> 0 | N44: =D44+F44+H44+J44+L44 -> 0
B45: TOTAL | C45: =SUM(C43:C44) -> 0 | D45: =SUM(D43:D44) -> 0 | E45: =SUM(E43:E44) -> 0 | F45: =SUM(F43:F44) -> 0 | G45: =SUM(G43:G44) -> 0 | H45: =SUM(H43:H44) -> 0 | I45: =SUM(I43:I44) -> 0 | J45: =SUM(J43:J44) -> 0 | ... N45: =SUM(N43:N44) -> 0

Sheet ANTICIPOS USUARIOS
B1: TOTAL | E1: RECIPRCIDAD | H1: ENEL | K1: ENERBIT | N1: OCCIDENTE | Q1: EAAB-CIUDADLIMPIA
B2: ASE | C2: ANTICIPOS GENERADOS POR PAGO | E2: ASE | F2: ANTICIPOS GENERADOS POR PAGO | H2: ASE | I2: ANTICIPOS GENERADOS POR PAGO | K2: ASE | L2: ANTICIPOS GENERADOS POR PAGO | N2: ASE | O2: ANTICIPOS GENERADOS POR PAGO | Q2: ASE | R2: ANTICIPOS GENERADOS POR PAGO | T2: Anticipos generados por pago
B3: 1 | C3: ='REPORTE RECAUDO x BANCO'!I14 -> 46857237 | E3: 1 | F3: ='REPORTE RECAUDO x BANCO'!F14 -> 0 | H3: 1 | I3: ='REPORTE RECAUDO x BANCO'!C14 -> 29606547 | K3: 1 | L3: ='REPORTE RECAUDO x BANCO'!G14 -> 0 | N3: 1 | O3: ='REPORTE RECAUDO x BANCO'!H14 -> 17250690 | Q3: 1 | R3: ='REPORTE RECAUDO x BANCO'!D14+'REPORTE RECAUDO x BANCO'!E14 -> 0 | T3: Sale del reporte Recaudo por Bancos.
B4: 2 | C4: ='REPORTE RECAUDO x BANCO'!I24 -> 52275662 | E4: 2 | F4: ='REPORTE RECAUDO x BANCO'!F24 -> 0 | H4: 2 | I4: ='REPORTE RECAUDO x BANCO'!C24 -> 22325147 | K4: 2 | L4: ='REPORTE RECAUDO x BANCO'!G24 -> 0 | N4: 2 | O4: ='REPORTE RECAUDO x BANCO'!H24 -> 29950515 | Q4: 2 | R4: ='REPORTE RECAUDO x BANCO'!D24+'REPORTE RECAUDO x BANCO'!E24 -> 0
B5: 3 | C5: ='REPORTE RECAUDO x BANCO'!I33 -> 13754369 | E5: 3 | F5: ='REPORTE RECAUDO x BANCO'!F33 -> 0 | H5: 3 | I5: ='REPORTE RECAUDO x BANCO'!C33 -> 8845080 | K5: 3 | L5: ='REPORTE RECAUDO x BANCO'!G33 -> 0 | N5: 3 | O5: ='REPORTE RECAUDO x BANCO'!H33 -> 4909289 | Q5: 3 | R5: ='REPORTE RECAUDO x BANCO'!D33+'REPORTE RECAUDO x BANCO'!E33 -> 0
B6: 4 | C6: ='REPORTE RECAUDO x BANCO'!I42 -> 49700940 | E6: 4 | F6: ='REPORTE RECAUDO x BANCO'!F42 -> 0 | H6: 4 | I6: ='REPORTE RECAUDO x BANCO'!C42 -> 42284806 | K6: 4 | L6: ='REPORTE RECAUDO x BANCO'!G42 -> 0 | N6: 4 | O6: ='REPORTE RECAUDO x BANCO'!H42 -> 7416134 | Q6: 4 | R6: ='REPORTE RECAUDO x BANCO'!D42+'REPORTE RECAUDO x BANCO'!E42 -> 0
B7: 5 | C7: ='REPORTE RECAUDO x BANCO'!I52 -> 8596000 | E7: 5 | F7: ='REPORTE RECAUDO x BANCO'!F52 -> 0 | H7: 5 | I7: ='REPORTE RECAUDO x BANCO'!C52 -> 5249580 | K7: 5 | L7: ='REPORTE RECAUDO x BANCO'!G52 -> 914180 | N7: 5 | O7: ='REPORTE RECAUDO x BANCO'!H52 -> 2432240 | Q7: 5 | R7: ='REPORTE RECAUDO x BANCO'!D52+'REPORTE RECAUDO x BANCO'!E52 -> 0
C8: =SUM(C3:C7) -> 1.7118421e+08 | F8: =SUM(F3:F7) -> 0 | I8: =SUM(I3:I7) -> 1.0831116e+08 | L8: =SUM(L3:L7) -> 914180 | O8: =SUM(O3:O7) -> 61958868 | R8: =SUM(R3:R7) -> 0
C9: =C8='REPORTE RECAUDO x BANCO'!I3 -> TRUE | F9: =F8='REPORTE RECAUDO x BANCO'!F3 -> TRUE | I9: =I8='REPORTE RECAUDO x BANCO'!C3 -> TRUE | L9: =L8='REPORTE RECAUDO x BANCO'!G3 -> TRUE | O9: =O8='REPORTE RECAUDO x BANCO'!H3 -> TRUE | R9: =R8='REPORTE RECAUDO x BANCO'!D3+'REPORTE RECAUDO x BANCO'!E3 -> TRUE
B11: ASE | C11: ANTICIPOS GENERADOS POR EXTEMPORANEOS | E11: ASE | F11: ANTICIPOS GENERADOS POR EXTEMPORANEOS | H11: ASE | I11: ANTICIPOS GENERADOS POR EXTEMPORANEOS | K11: ASE | L11: ANTICIPOS GENERADOS POR EXTEMPORANEOS | N11: ASE | O11: ANTICIPOS GENERADOS POR EXTEMPORANEOS | Q11: ASE | R11: ANTICIPOS GENERADOS POR EXTEMPORANEOS | T11: Anticipos generados por pagos aplicados de reversiones
B12: 1 | C12: ='ANT EXT-REV'!C4 -> 0 | E12: 1 | F12: ='ANT EXT-REV'!C20 -> 0 | H12: 1 | I12: ='ANT EXT-REV'!C36 -> 0 | K12: 1 | L12: ='ANT EXT-REV'!C44 -> 0 | N12: 1 | O12: ='ANT EXT-REV'!C12 -> 0 | Q12: 1 | R12: ='ANT EXT-REV'!C28 -> 0 | T12: Sale del reporte Recaudo reversado
B13: 2 | C13: ='ANT EXT-REV'!E4 -> 0 | E13: 2 | F13: ='ANT EXT-REV'!E20 -> 0 | H13: 2 | I13: ='ANT EXT-REV'!E36 -> 0 | K13: 2 | L13: ='ANT EXT-REV'!E44 -> 0 | N13: 2 | O13: ='ANT EXT-REV'!E12 -> 0 | Q13: 2 | R13: ='ANT EXT-REV'!E28 -> 0
B14: 3 | C14: ='ANT EXT-REV'!G4 -> 0 | E14: 3 | F14: ='ANT EXT-REV'!G20 -> 0 | H14: 3 | I14: ='ANT EXT-REV'!G36 -> 0 | K14: 3 | L14: ='ANT EXT-REV'!G44 -> 0 | N14: 3 | O14: ='ANT EXT-REV'!G12 -> 0 | Q14: 3 | R14: ='ANT EXT-REV'!G28 -> 0
B15: 4 | C15: ='ANT EXT-REV'!I4 -> 0 | E15: 4 | F15: ='ANT EXT-REV'!I20 -> 0 | H15: 4 | I15: ='ANT EXT-REV'!I36 -> 0 | K15: 4 | L15: ='ANT EXT-REV'!I44 -> 0 | N15: 4 | O15: ='ANT EXT-REV'!I12 -> 0 | Q15: 4 | R15: ='ANT EXT-REV'!I28 -> 0
B16: 5 | C16: ='ANT EXT-REV'!K4 -> 0 | E16: 5 | F16: ='ANT EXT-REV'!K20 -> 0 | H16: 5 | I16: ='ANT EXT-REV'!K36 -> 0 | K16: 5 | L16: ='ANT EXT-REV'!K44 -> 0 | N16: 5 | O16: ='ANT EXT-REV'!K12 -> 0 | Q16: 5 | R16: ='ANT EXT-REV'!K28 -> 0
C17: =SUM(C12:C16) -> 0 | F17: =SUM(F12:F16) -> 0 | I17: =SUM(I12:I16) -> 0 | L17: =SUM(L12:L16) -> 0 | O17: =SUM(O12:O16) -> 0 | R17: =SUM(R12:R16) -> 0
C18: =C17='ANT EXT-REV'!M4 -> TRUE | F18: =F17='ANT EXT-REV'!M20 -> TRUE | I18: =I17='ANT EXT-REV'!M36 -> TRUE | L18: =L17='ANT EXT-REV'!M44 -> TRUE | O18: =O17='ANT EXT-REV'!M12 -> TRUE | R18: =R17='ANT EXT-REV'!M28 -> TRUE
B20: ASE | C20: ANTICIPOS QUE CARGAN POR REVERSIONES | E20: ASE | F20: ANTICIPOS QUE CARGAN POR REVERSIONES | H20: ASE | I20: ANTICIPOS QUE CARGAN POR REVERSIONES | K20: ASE | L20: ANTICIPOS QUE CARGAN POR REVERSIONES | N20: ASE | O20: ANTICIPOS QUE CARGAN POR REVERSIONES | Q20: ASE | R20: ANTICIPOS QUE CARGAN POR REVERSIONES | T20: Anticipos que cargan de reversiones
B21: 1 | C21: ='ANT EXT-REV'!D4 -> 0 | E21: 1 | F21: ='ANT EXT-REV'!D20 -> 0 | H21: 1 | I21: ='ANT EXT-REV'!D36 -> 0 | K21: 1 | L21: ='ANT EXT-REV'!D44 -> 0 | N21: 1 | O21: ='ANT EXT-REV'!D12 -> 0 | Q21: 1 | R21: ='ANT EXT-REV'!D28 -> 0 | T21: Sale del reporte Recaudo reversado
B22: 2 | C22: ='ANT EXT-REV'!F4 -> 0 | E22: 2 | F22: ='ANT EXT-REV'!F20 -> 0 | H22: 2 | I22: ='ANT EXT-REV'!F36 -> 0 | K22: 2 | L22: ='ANT EXT-REV'!F44 -> 0 | N22: 2 | O22: ='ANT EXT-REV'!F12 -> 0 | Q22: 2 | R22: ='ANT EXT-REV'!F28 -> 0
B23: 3 | C23: ='ANT EXT-REV'!H4 -> 0 | E23: 3 | F23: ='ANT EXT-REV'!H20 -> 0 | H23: 3 | I23: ='ANT EXT-REV'!H36 -> 0 | K23: 3 | L23: ='ANT EXT-REV'!H44 -> 0 | N23: 3 | O23: ='ANT EXT-REV'!H12 -> 0 | Q23: 3 | R23: ='ANT EXT-REV'!H28 -> 0
B24: 4 | C24: ='ANT EXT-REV'!J4 -> 0 | E24: 4 | F24: ='ANT EXT-REV'!J20 -> 0 | H24: 4 | I24: ='ANT EXT-REV'!J36 -> 0 | K24: 4 | L24: ='ANT EXT-REV'!J44 -> 0 | N24: 4 | O24: ='ANT EXT-REV'!J12 -> 0 | Q24: 4 | R24: ='ANT EXT-REV'!J28 -> 0
B25: 5 | C25: ='ANT EXT-REV'!L4 -> 0 | E25: 5 | F25: ='ANT EXT-REV'!L20 -> 0 | H25: 5 | I25: ='ANT EXT-REV'!L36 -> 0 | K25: 5 | L25: ='ANT EXT-REV'!L44 -> 0 | N25: 5 | O25: ='ANT EXT-REV'!L12 -> 0 | Q25: 5 | R25: ='ANT EXT-REV'!L28 -> 0
C26: =SUM(C21:C25) -> 0 | F26: =SUM(F21:F25) -> 0 | I26: =SUM(I21:I25) -> 0 | L26: =SUM(L21:L25) -> 0 | O26: =SUM(O21:O25) -> 0 | R26: =SUM(R21:R25) -> 0
C27: =C26='ANT EXT-REV'!N4 -> TRUE | F27: =F26='ANT EXT-REV'!N20 -> TRUE | I27: =I26='ANT EXT-REV'!N36 -> TRUE | L27: =L26='ANT EXT-REV'!N44 -> TRUE | O27: =O26='ANT EXT-REV'!N12 -> TRUE | R27: =R26='ANT EXT-REV'!N28 -> TRUE

Sheet BCE SC POR FACT.
C2: ASE | D2: SUBSIDIO | E2: CONTRIBUCION | F2: TOTAL BSC | H2: SISTEMA
C3: 1 | D3: -1.3280729e+09 | E3: 3.4820238e+09 | F3: =D3+E3 -> 2.1539508e+09 | H3: =DetRetri2026101!J9 -> 0 | I3: =F3-H3 -> 2.1539508e+09
C4: 2 | D4: -6.051832e+09 | E4: 1.8346864e+09 | F4: =D4+E4 -> -4.2171455e+09 | H4: =DetRetri2026101!J10 -> 0 | I4: =F4-H4 -> -4.2171455e+09
C5: 3 | D5: -3.1050034e+09 | E5: 1.816197e+09 | F5: =D5+E5 -> -1.2888063e+09 | H5: =DetRetri2026101!J11 -> 0 | I5: =F5-H5 -> -1.2888063e+09
C6: 4 | D6: -3.693256e+08 | E6: 4.3085756e+08 | F6: =D6+E6 -> 61531954 | H6: =DetRetri2026101!J12 -> 0 | I6: =F6-H6 -> 61531954
C7: 5 | D7: -2.3876069e+09 | E7: 1.1411338e+09 | F7: =D7+E7 -> -1.2464731e+09 | H7: =DetRetri2026101!J13 -> 0 | I7: =F7-H7 -> -1.2464731e+09
F9: =SUM(F3:F7) -> -4.5369422e+09 | H9: =SUM(H3:H7) -> 0 | I9: =F9-H9 -> -4.5369422e+09
H10: =H9=DetRetri2026101!J14 -> TRUE
D11: =SUM(D3:D7) -> -1.3241841e+10 | E11: =SUM(E3:E7) -> 8.7048987e+09 | F11: =SUM(D3:E7) -> -4.5369422e+09
F12: =ROUND(F11,2)=ROUND(F9,2) -> TRUE
F13: =ROUND(F11,2)-ROUND(F9,2) -> 0
D18: ASE | E18: REMUN TOTAL | F18: VALIDA 1 | G18: VALIDA 2 | H18: DIFERENCIA VALIDA 2
D19: 1 | E19: ='CONSOLIDADO_TOTAL RECAUDO'!J104 -> 2.1539508e+09 | F19: =E19=F3 -> TRUE | G19: =E19=H3 -> FALSE | H19: =E19-H3 -> 2.1539508e+09
D20: 2 | E20: ='CONSOLIDADO_TOTAL RECAUDO'!J105 -> -4.2171455e+09 | F20: =E20=F4 -> TRUE | G20: =E20=H4 -> FALSE | H20: =E20-H4 -> -4.2171455e+09
D21: 3 | E21: ='CONSOLIDADO_TOTAL RECAUDO'!J106 -> -1.2888063e+09 | F21: =E21=F5 -> TRUE | G21: =E21=H5 -> FALSE | H21: =E21-H5 -> -1.2888063e+09
D22: 4 | E22: ='CONSOLIDADO_TOTAL RECAUDO'!J107 -> 61531954 | F22: =E22=F6 -> TRUE | G22: =E22=H6 -> FALSE | H22: =E22-H6 -> 61531954
D23: 5 | E23: ='CONSOLIDADO_TOTAL RECAUDO'!J108 -> -1.2464731e+09 | F23: =E23=F7 -> TRUE | G23: =E23=H7 -> FALSE | H23: =E23-H7 -> -1.2464731e+09
E24: =SUM(E19:E23) -> -4.5369422e+09 | F24: =E24=F9 -> TRUE | G24: =E24=H9 -> FALSE | H24: =E24-H9 -> -4.5369422e+09

Sheet Reporte Componentes R1
B4: PROMOAMBIENTAL
F5: Total | G5: Componente TDF | H5: Componente TTL | I5: Componente TVIAT | J5: Aprovechamiento | K5: CCSA Prest.Aprov. | L5: SERVICIO ESPECIALES | M5: Componente TCS | N5: Componente TLU | O5: Componente TBL | P5: Componente TRT | Q5: CCSA Prest. No Aprov. | R5: Ajuste Decena | S5: Ajuste Recargo Aseo | T5: Intereses Cte Financiac. Aseo | U5: Exonera-Recargo Aseo | V5: Exonera-Ajuste Decena Aseo | W5: Exonera-Recargo Aseo | X5: Exonera-Recargo Aseo | Y5: Intereses Cte Financiac. Aseo | Z5: Rec.Intereses
E6: Vlr Servicio | F6: -2015.07 | G6: -122.1 | H6: -51.87 | I6: -22.65 | J6: -369.44 | K6: -23.88 | L6: 0 | M6: -209.4 | N6: -175.25 | O6: -699.55 | P6: -301.98 | Q6: -38.95 | R6: 0 | S6: 0 | T6: 0 | U6: 0 | V6: 0 | W6: 0 | X6: 0 | Y6: 0 | Z6: 0
D7: E | E7: Total | F7: -2015.07 | G7: -122.1 | H7: -51.87 | I7: -22.65 | J7: -369.44 | K7: -23.88 | L7: 0 | M7: -209.4 | N7: -175.25 | O7: -699.55 | P7: -301.98 | Q7: -38.95 | R7: 0 | S7: 0 | T7: 0 | U7: 0 | V7: 0 | W7: 0 | X7: 0 | Y7: 0 | Z7: 0
C8: ENEL | D8: Total | F8: -2015.07 | G8: -122.1 | H8: -51.87 | I8: -22.65 | J8: -369.44 | K8: -23.88 | L8: 0 | M8: -209.4 | N8: -175.25 | O8: -699.55 | P8: -301.98 | Q8: -38.95 | R8: 0 | S8: 0 | T8: 0 | U8: 0 | V8: 0 | W8: 0 | X8: 0 | Y8: 0 | Z8: 0
E9: Vlr Servicio | F9: 0 | G9: 0 | H9: 0 | I9: 0 | J9: 0 | K9: 0 | L9: 0 | M9: 0 | N9: 0 | O9: 0 | P9: 0 | Q9: 0 | R9: 0 | S9: 0 | T9: 0 | U9: 0 | V9: 0 | W9: 0 | X9: 0 | Y9: 0 | Z9: 0
D10: H | E10: Total | F10: 0 | G10: 0 | H10: 0 | I10: 0 | J10: 0 | K10: 0 | L10: 0 | M10: 0 | N10: 0 | O10: 0 | P10: 0 | Q10: 0 | R10: 0 | S10: 0 | T10: 0 | U10: 0 | V10: 0 | W10: 0 | X10: 0 | Y10: 0 | Z10: 0
E11: Vlr Servicio | F11: 0 | G11: 0 | H11: 0 | I11: 0 | J11: 0 | K11: 0 | L11: 0 | M11: 0 | N11: 0 | O11: 0 | P11: 0 | Q11: 0 | R11: 0 | S11: 0 | T11: 0 | U11: 0 | V11: 0 | W11: 0 | X11: 0 | Y11: 0 | Z11: 0
D12: O | E12: Total | F12: 0 | G12: 0 | H12: 0 | I12: 0 | J12: 0 | K12: 0 | L12: 0 | M12: 0 | N12: 0 | O12: 0 | P12: 0 | Q12: 0 | R12: 0 | S12: 0 | T12: 0 | U12: 0 | V12: 0 | W12: 0 | X12: 0 | Y12: 0 | Z12: 0
E13: Vlr Servicio | F13: 0 | G13: 0 | H13: 0 | I13: 0 | J13: 0 | K13: 0 | L13: 0 | M13: 0 | N13: 0 | O13: 0 | P13: 0 | Q13: 0 | R13: 0 | S13: 0 | T13: 0 | U13: 0 | V13: 0 | W13: 0 | X13: 0 | Y13: 0 | Z13: 0
D14: T | E14: Total | F14: 0 | G14: 0 | H14: 0 | I14: 0 | J14: 0 | K14: 0 | L14: 0 | M14: 0 | N14: 0 | O14: 0 | P14: 0 | Q14: 0 | R14: 0 | S14: 0 | T14: 0 | U14: 0 | V14: 0 | W14: 0 | X14: 0 | Y14: 0 | Z14: 0
C15: OCCIDENTE | D15: Total | F15: 0 | G15: 0 | H15: 0 | I15: 0 | J15: 0 | K15: 0 | L15: 0 | M15: 0 | N15: 0 | O15: 0 | P15: 0 | Q15: 0 | R15: 0 | S15: 0 | T15: 0 | U15: 0 | V15: 0 | W15: 0 | X15: 0 | Y15: 0 | Z15: 0
B16: Mes | C16: Total | F16: -2015.07 | G16: -122.1 | H16: -51.87 | I16: -22.65 | J16: -369.44 | K16: -23.88 | L16: 0 | M16: -209.4 | N16: -175.25 | O16: -699.55 | P16: -301.98 | Q16: -38.95 | R16: 0 | S16: 0 | T16: 0 | U16: 0 | V16: 0 | W16: 0 | X16: 0 | Y16: 0 | Z16: 0
A17: AFaseo | B17: Total | F17: -2015.07 | G17: -122.1 | H17: -51.87 | I17: -22.65 | J17: -369.44 | K17: -23.88 | L17: 0 | M17: -209.4 | N17: -175.25 | O17: -699.55 | P17: -301.98 | Q17: -38.95 | R17: 0 | S17: 0 | T17: 0 | U17: 0 | V17: 0 | W17: 0 | X17: 0 | Y17: 0 | Z17: 0
E18: Vlr Servicio | F18: 543996.54 | G18: 23503.13 | H18: 13266.51 | I18: 6965.01 | J18: 119922.22 | K18: 5285.43 | L18: 0 | M18: 46363.01 | N18: 44625.42 | O18: 211250.82 | P18: 64191.45 | Q18: 8623.46 | R18: 0.08 | S18: 0 | T18: 0 | U18: 0 | V18: 0 | W18: 0 | X18: 0 | Y18: 0 | Z18: 0
E19: Vlr Intereses | F19: 2063.1 | G19: 86.78 | H19: 48.91 | I19: 25.71 | J19: 441.75 | K19: 20.42 | L19: 0 | M19: 179.53 | N19: 172.72 | O19: 816.93 | P19: 236.94 | Q19: 33.41 | R19: 0 | S19: 0 | T19: 0 | U19: 0 | V19: 0 | W19: 0 | X19: 0 | Y19: 0 | Z19: 0
D20: E | E20: Total | F20: 546059.64 | G20: 23589.91 | H20: 13315.42 | I20: 6990.72 | J20: 120363.97 | K20: 5305.85 | L20: 0 | M20: 46542.54 | N20: 44798.14 | O20: 212067.75 | P20: 64428.39 | Q20: 8656.87 | R20: 0.08 | S20: 0 | T20: 0 | U20: 0 | V20: 0 | W20: 0 | X20: 0 | Y20: 0 | Z20: 0
C21: ENEL | D21: Total | F21: 546059.64 | G21: 23589.91 | H21: 13315.42 | I21: 6990.72 | J21: 120363.97 | K21: 5305.85 | L21: 0 | M21: 46542.54 | N21: 44798.14 | O21: 212067.75 | P21: 64428.39 | Q21: 8656.87 | R21: 0.08 | S21: 0 | T21: 0 | U21: 0 | V21: 0 | W21: 0 | X21: 0 | Y21: 0 | Z21: 0
E22: Vlr Servicio | F22: 0 | G22: 0 | H22: 0 | I22: 0 | J22: 0 | K22: 0 | L22: 0 | M22: 0 | N22: 0 | O22: 0 | P22: 0 | Q22: 0 | R22: 0 | S22: 0 | T22: 0 | U22: 0 | V22: 0 | W22: 0 | X22: 0 | Y22: 0 | Z22: 0
E23: Vlr Intereses | F23: 0 | G23: 0 | H23: 0 | I23: 0 | J23: 0 | K23: 0 | L23: 0 | M23: 0 | N23: 0 | O23: 0 | P23: 0 | Q23: 0 | R23: 0 | S23: 0 | T23: 0 | U23: 0 | V23: 0 | W23: 0 | X23: 0 | Y23: 0 | Z23: 0
D24: E | E24: Total | F24: 0 | G24: 0 | H24: 0 | I24: 0 | J24: 0 | K24: 0 | L24: 0 | M24: 0 | N24: 0 | O24: 0 | P24: 0 | Q24: 0 | R24: 0 | S24: 0 | T24: 0 | U24: 0 | V24: 0 | W24: 0 | X24: 0 | Y24: 0 | Z24: 0
C25: ENERBIT | D25: Total | F25: 0 | G25: 0 | H25: 0 | I25: 0 | J25: 0 | K25: 0 | L25: 0 | M25: 0 | N25: 0 | O25: 0 | P25: 0 | Q25: 0 | R25: 0 | S25: 0 | T25: 0 | U25: 0 | V25: 0 | W25: 0 | X25: 0 | Y25: 0 | Z25: 0
E26: Vlr Servicio | F26: 0 | G26: 0 | H26: 0 | I26: 0 | J26: 0 | K26: 0 | L26: 0 | M26: 0 | N26: 0 | O26: 0 | P26: 0 | Q26: 370.08 | R26: -1.95 | S26: 0 | T26: 0 | U26: 0 | V26: 0 | W26: 0 | X26: 0 | Y26: 0 | Z26: 0
E27: Vlr Intereses | F27: 0 | G27: 0 | H27: 0 | I27: 0 | J27: 0 | K27: 0 | L27: 0 | M27: 0 | N27: 0 | O27: 0 | P27: 0 | Q27: 0.07 | R27: 0 | S27: 0 | T27: 0 | U27: 0 | V27: 0 | W27: 0 | X27: 0 | Y27: 0 | Z27: 0
D28: H | E28: Total | F28: 0 | G28: 0 | H28: 0 | I28: 0 | J28: 0 | K28: 0 | L28: 0 | M28: 0 | N28: 0 | O28: 0 | P28: 0 | Q28: 370.15 | R28: -1.95 | S28: 0 | T28: 0 | U28: 0 | V28: 0 | W28: 0 | X28: 0 | Y28: 0 | Z28: 0
E29: Vlr Servicio | F29: 0 | G29: 0 | H29: 0 | I29: 0 | J29: 0 | K29: 0 | L29: 0 | M29: 0 | N29: 0 | O29: 0 | P29: 0 | Q29: 370.08 | R29: -1.95 | S29: 0 | T29: 0 | U29: 0 | V29: 0 | W29: 0 | X29: 0 | Y29: 0 | Z29: 0
E30: Vlr Intereses | F30: 0 | G30: 0 | H30: 0 | I30: 0 | J30: 0 | K30: 0 | L30: 0 | M30: 0 | N30: 0 | O30: 0 | P30: 0 | Q30: 0.07 | R30: 0 | S30: 0 | T30: 0 | U30: 0 | V30: 0 | W30: 0 | X30: 0 | Y30: 0 | Z30: 0
D31: O | E31: Total | F31: 0 | G31: 0 | H31: 0 | I31: 0 | J31: 0 | K31: 0 | L31: 0 | M31: 0 | N31: 0 | O31: 0 | P31: 0 | Q31: 370.15 | R31: -1.95 | S31: 0 | T31: 0 | U31: 0 | V31: 0 | W31: 0 | X31: 0 | Y31: 0 | Z31: 0
E32: Vlr Servicio | F32: 89870.51 | G32: 5626.37 | H32: 3138.96 | I32: 1667.33 | J32: 21034.12 | K32: 519.02 | L32: 0 | M32: 4552.92 | N32: 6472.07 | O32: 30640.84 | P32: 15366.98 | Q32: 846.86 | R32: 5.04 | S32: 0 | T32: 0 | U32: 0 | V32: 0 | W32: 0 | X32: 0 | Y32: 0 | Z32: 0
E33: Vlr Intereses | F33: 116.92 | G33: 7.31 | H33: 4.09 | I33: 2.17 | J33: 27.38 | K33: 0.67 | L33: 0 | M33: 5.91 | N33: 8.47 | O33: 39.84 | P33: 19.98 | Q33: 1.1 | R33: 0 | S33: 0 | T33: 0 | U33: 0 | V33: 0 | W33: 0 | X33: 0 | Y33: 0 | Z33: 0
D34: T | E34: Total | F34: 89987.43 | G34: 5633.68 | H34: 3143.05 | I34: 1669.5 | J34: 21061.5 | K34: 519.69 | L34: 0 | M34: 4558.83 | N34: 6480.54 | O34: 30680.68 | P34: 15386.96 | Q34: 847.96 | R34: 5.04 | S34: 0 | T34: 0 | U34: 0 | V34: 0 | W34: 0 | X34: 0 | Y34: 0 | Z34: 0
C35: OCCIDENTE | D35: Total | F35: 89987.43 | G35: 5633.68 | H35: 3143.05 | I35: 1669.5 | J35: 21061.5 | K35: 519.69 | L35: 0 | M35: 4558.83 | N35: 6480.54 | O35: 30680.68 | P35: 15386.96 | Q35: 847.96 | R35: 5.04 | S35: 0 | T35: 0 | U35: 0 | V35: 0 | W35: 0 | X35: 0 | Y35: 0 | Z35: 0
B36: Aplicacion nuevos x reversion | C36: Total | F36: 636047.07 | G36: 29223.59 | H36: 16458.47 | I36: 8660.22 | J36: 141425.47 | K36: 5825.54 | L36: 0 | M36: 51101.37 | N36: 51278.68 | O36: 242748.43 | P36: 79815.35 | Q36: 9504.83 | R36: 5.12 | S36: 0 | T36: 0 | U36: 0 | V36: 0 | W36: 0 | X36: 0 | Y36: 0 | Z36: 0
E37: Vlr Servicio | F37: 1.7732826e+10 | G37: 8.0811608e+08 | H37: 4.5018145e+08 | I37: 2.396397e+08 | J37: 4.7172894e+09 | K37: 1.5731653e+08 | L37: 9937432.2 | M37: 1.3814111e+09 | N37: 1.3028635e+09 | O37: 6.2103431e+09 | P37: 2.1989365e+09 | Q37: 2.5681561e+08 | R37: -24243.8 | S37: 0 | T37: 0 | U37: 0 | V37: 0 | W37: 0 | X37: 0 | Y37: 0 | Z37: 0
E38: Vlr Intereses | F38: 2121030.6 | G38: 114429.04 | H38: 59031.07 | I38: 30884.79 | J38: 467332.66 | K38: 20333.36 | L38: 491.86 | M38: 178752.52 | N38: 163509.31 | O38: 744605.58 | P38: 308414.05 | Q38: 33078.85 | R38: 18.46 | S38: 19.47 | T38: 236.47 | U38: 0 | V38: 0 | W38: 0 | X38: 0 | Y38: 0 | Z38: -106.9
D39: E | E39: Total | F39: 1.7734947e+10 | G39: 8.0823051e+08 | H39: 4.5024048e+08 | I39: 2.3967059e+08 | J39: 4.7177568e+09 | K39: 1.5733686e+08 | L39: 9937924.1 | M39: 1.3815898e+09 | N39: 1.303027e+09 | O39: 6.2110877e+09 | P39: 2.1992449e+09 | Q39: 2.5684868e+08 | R39: -24225.34 | S39: 19.47 | T39: 236.47 | U39: 0 | V39: 0 | W39: 0 | X39: 0 | Y39: 0 | Z39: -106.9
C40: ENEL | D40: Total | F40: 1.7734947e+10 | G40: 8.0823051e+08 | H40: 4.5024048e+08 | I40: 2.3967059e+08 | J40: 4.7177568e+09 | K40: 1.5733686e+08 | L40: 9937924.1 | M40: 1.3815898e+09 | N40: 1.303027e+09 | O40: 6.2110877e+09 | P40: 2.1992449e+09 | Q40: 2.5684868e+08 | R40: -24225.34 | S40: 19.47 | T40: 236.47 | U40: 0 | V40: 0 | W40: 0 | X40: 0 | Y40: 0 | Z40: -106.9
E41: Vlr Servicio | F41: 0 | G41: 0 | H41: 0 | I41: 0 | J41: 0 | K41: 0 | L41: 0 | M41: 0 | N41: 0 | O41: 0 | P41: 0 | Q41: 0 | R41: 0 | S41: 0 | T41: 0 | U41: 0 | V41: 0 | W41: 0 | X41: 0 | Y41: 0 | Z41: 0
E42: Vlr Intereses | F42: 0 | G42: 0 | H42: 0 | I42: 0 | J42: 0 | K42: 0 | L42: 0 | M42: 0 | N42: 0 | O42: 0 | P42: 0 | Q42: 0 | R42: 0 | S42: 0 | T42: 0 | U42: 0 | V42: 0 | W42: 0 | X42: 0 | Y42: 0 | Z42: 0
D43: E | E43: Total | F43: 0 | G43: 0 | H43: 0 | I43: 0 | J43: 0 | K43: 0 | L43: 0 | M43: 0 | N43: 0 | O43: 0 | P43: 0 | Q43: 0 | R43: 0 | S43: 0 | T43: 0 | U43: 0 | V43: 0 | W43: 0 | X43: 0 | Y43: 0 | Z43: 0
C44: ENERBIT | D44: Total | F44: 0 | G44: 0 | H44: 0 | I44: 0 | J44: 0 | K44: 0 | L44: 0 | M44: 0 | N44: 0 | O44: 0 | P44: 0 | Q44: 0 | R44: 0 | S44: 0 | T44: 0 | U44: 0 | V44: 0 | W44: 0 | X44: 0 | Y44: 0 | Z44: 0
E45: Vlr Servicio | F45: 27812534 | G45: 3127682.6 | H45: 1787750.6 | I45: 994482.9 | J45: 3900132.4 | K45: 128394.64 | L45: 65261.43 | M45: 1108739.3 | N45: 1377785.4 | O45: 6585392.2 | P45: 8526230.1 | Q45: 210777.87 | R45: -95.43 | S45: 0 | T45: 0 | U45: 0 | V45: 0 | W45: 0 | X45: 0 | Y45: 0 | Z45: 0
E46: Vlr Intereses | F46: 52627 | G46: 3905.72 | H46: 2108.89 | I46: 1129.02 | J46: 9194.6 | K46: 397.89 | L46: 0 | M46: 3497.21 | N46: 3710.89 | O46: 17365.58 | P46: 10667.02 | Q46: 649.71 | R46: 0.42 | S46: -0.01 | T46: 0.06 | U46: 0 | V46: 0 | W46: 0 | X46: 0 | Y46: 0 | Z46: 0
D47: H | E47: Total | F47: 27865161 | G47: 3131588.3 | H47: 1789859.5 | I47: 995611.92 | J47: 3909327 | K47: 128792.53 | L47: 65261.43 | M47: 1112236.5 | N47: 1381496.3 | O47: 6602757.8 | P47: 8536897.1 | Q47: 211427.58 | R47: -95.01 | S47: -0.01 | T47: 0.06 | U47: 0 | V47: 0 | W47: 0 | X47: 0 | Y47: 0 | Z47: 0
E48: Vlr Servicio | F48: 38733807 | G48: 3039800.2 | H48: 1655044.1 | I48: 884056.68 | J48: 6291646.5 | K48: 298351.07 | L48: 43507.62 | M48: 2623588.8 | N48: 2661210.6 | O48: 12473941 | P48: 8276274 | Q48: 486783.55 | R48: -397.6 | S48: 0 | T48: 0 | U48: 0 | V48: 0 | W48: 0 | X48: 0 | Y48: 0 | Z48: 0
E49: Vlr Intereses | F49: 103423.02 | G49: 5231.83 | H49: 2620.78 | I49: 1432.53 | J49: 22089.08 | K49: 1012.15 | L49: 0 | M49: 8840.42 | N49: 8284.39 | O49: 37991.28 | P49: 14270.12 | Q49: 1651.75 | R49: -1.34 | S49: 0 | T49: 0.03 | U49: 0 | V49: 0 | W49: 0 | X49: 0 | Y49: 0 | Z49: 0
D50: O | E50: Total | F50: 38837230 | G50: 3045032.1 | H50: 1657664.9 | I50: 885489.21 | J50: 6313735.6 | K50: 299363.22 | L50: 43507.62 | M50: 2632429.2 | N50: 2669495 | O50: 12511933 | P50: 8290544.1 | Q50: 488435.3 | R50: -398.94 | S50: 0 | T50: 0.03 | U50: 0 | V50: 0 | W50: 0 | X50: 0 | Y50: 0 | Z50: 0
E51: Vlr Servicio | F51: 2.2289166e+08 | G51: 27345007 | H51: 15201201 | I51: 8089797.9 | J51: 28735246 | K51: 729515.15 | L51: 9878361.2 | M51: 6370953.3 | N51: 8839869.6 | O51: 41844064 | P51: 74669973 | Q51: 1190722.6 | R51: -3045.97 | S51: 0 | T51: 0 | U51: 0 | V51: 0 | W51: 0 | X51: 0 | Y51: 0 | Z51: 0
E52: Vlr Intereses | F52: 650065.1 | G52: 54025.13 | H52: 28815.72 | I52: 15452.4 | J52: 131416.37 | K52: 3462.06 | L52: 6638.64 | M52: 30369.24 | N52: 40871.66 | O52: 186410.2 | P52: 147007.48 | Q52: 5632.59 | R52: -36.4 | S52: 0.01 | T52: 0 | U52: 0 | V52: 0 | W52: 0 | X52: 0 | Y52: 0 | Z52: 0
D53: T | E53: Total | F53: 2.2354173e+08 | G53: 27399032 | H53: 15230017 | I53: 8105250.3 | J53: 28866662 | K53: 732977.21 | L53: 9884999.9 | M53: 6401322.6 | N53: 8880741.2 | O53: 42030474 | P53: 74816980 | Q53: 1196355.2 | R53: -3082.37 | S53: 0.01 | T53: 0 | U53: 0 | V53: 0 | W53: 0 | X53: 0 | Y53: 0 | Z53: 0
C54: OCCIDENTE | D54: Total | F54: 2.9024412e+08 | G54: 33575652 | H54: 18677541 | I54: 9986351.4 | J54: 39089725 | K54: 1161133 | L54: 9993768.9 | M54: 10145988 | N54: 12931733 | O54: 61145165 | P54: 91644422 | Q54: 1896218.1 | R54: -3576.32 | S54: 0 | T54: 0.09 | U54: 0 | V54: 0 | W54: 0 | X54: 0 | Y54: 0 | Z54: 0
B55: Mes | C55: Total | F55: 1.8025191e+10 | G55: 8.4180616e+08 | H55: 4.6891802e+08 | I55: 2.4965694e+08 | J55: 4.7568465e+09 | K55: 1.58498e+08 | L55: 19931693 | M55: 1.3917358e+09 | N55: 1.3159588e+09 | O55: 6.2722329e+09 | P55: 2.2908894e+09 | Q55: 2.587449e+08 | R55: -27801.66 | S55: 19.47 | T55: 236.56 | U55: 0 | V55: 0 | W55: 0 | X55: 0 | Y55: 0 | Z55: -106.9
A56: Componente | B56: Total | F56: 1.8025827e+10 | G56: 8.4183538e+08 | H56: 4.6893448e+08 | I56: 2.496656e+08 | J56: 4.7569879e+09 | K56: 1.5850382e+08 | L56: 19931693 | M56: 1391786912 | N56: 1.3160101e+09 | O56: 6.2724756e+09 | P56: 2.2909692e+09 | Q56: 2.5875441e+08 | R56: -27796.54 | S56: 19.47 | T56: 236.56 | U56: 0 | V56: 0 | W56: 0 | X56: 0 | Y56: 0 | Z56: -106.9
E57: Subsidio(-)/Contribucion(+) | F57: -32099.64 | G57: -1182.8 | H57: -661.02 | I57: -350.52 | J57: -6245.62 | K57: -344.7 | L57: 0 | M57: -3023.82 | N57: -2892.68 | O57: -13605.48 | P57: -3230.56 | Q57: -562.44 | R57: 0 | S57: 0 | T57: 0 | U57: 0 | V57: 0 | W57: 0 | X57: 0 | Y57: 0 | Z57: 0
D58: E | E58: Total | F58: -32099.64 | G58: -1182.8 | H58: -661.02 | I58: -350.52 | J58: -6245.62 | K58: -344.7 | L58: 0 | M58: -3023.82 | N58: -2892.68 | O58: -13605.48 | P58: -3230.56 | Q58: -562.44 | R58: 0 | S58: 0 | T58: 0 | U58: 0 | V58: 0 | W58: 0 | X58: 0 | Y58: 0 | Z58: 0
C59: ENEL | D59: Total | F59: -32099.64 | G59: -1182.8 | H59: -661.02 | I59: -350.52 | J59: -6245.62 | K59: -344.7 | L59: 0 | M59: -3023.82 | N59: -2892.68 | O59: -13605.48 | P59: -3230.56 | Q59: -562.44 | R59: 0 | S59: 0 | T59: 0 | U59: 0 | V59: 0 | W59: 0 | X59: 0 | Y59: 0 | Z59: 0
E60: Subsidio(-)/Contribucion(+) | F60: 0 | G60: 0 | H60: 0 | I60: 0 | J60: 0 | K60: 0 | L60: 0 | M60: 0 | N60: 0 | O60: 0 | P60: 0 | Q60: 0 | R60: 0 | S60: 0 | T60: 0 | U60: 0 | V60: 0 | W60: 0 | X60: 0 | Y60: 0 | Z60: 0
D61: E | E61: Total | F61: 0 | G61: 0 | H61: 0 | I61: 0 | J61: 0 | K61: 0 | L61: 0 | M61: 0 | N61: 0 | O61: 0 | P61: 0 | Q61: 0 | R61: 0 | S61: 0 | T61: 0 | U61: 0 | V61: 0 | W61: 0 | X61: 0 | Y61: 0 | Z61: 0
C62: ENERBIT | D62: Total | F62: 0 | G62: 0 | H62: 0 | I62: 0 | J62: 0 | K62: 0 | L62: 0 | M62: 0 | N62: 0 | O62: 0 | P62: 0 | Q62: 0 | R62: 0 | S62: 0 | T62: 0 | U62: 0 | V62: 0 | W62: 0 | X62: 0 | Y62: 0 | Z62: 0
E63: Subsidio(-)/Contribucion(+) | F63: 0 | G63: 0 | H63: 0 | I63: 0 | J63: 0 | K63: 0 | L63: 0 | M63: 0 | N63: 0 | O63: 0 | P63: 0 | Q63: 0 | R63: 0 | S63: 0 | T63: 0 | U63: 0 | V63: 0 | W63: 0 | X63: 0 | Y63: 0 | Z63: 0
D64: H | E64: Total | F64: 0 | G64: 0 | H64: 0 | I64: 0 | J64: 0 | K64: 0 | L64: 0 | M64: 0 | N64: 0 | O64: 0 | P64: 0 | Q64: 0 | R64: 0 | S64: 0 | T64: 0 | U64: 0 | V64: 0 | W64: 0 | X64: 0 | Y64: 0 | Z64: 0
E65: Subsidio(-)/Contribucion(+) | F65: 0 | G65: 0 | H65: 0 | I65: 0 | J65: 0 | K65: 0 | L65: 0 | M65: 0 | N65: 0 | O65: 0 | P65: 0 | Q65: 0 | R65: 0 | S65: 0 | T65: 0 | U65: 0 | V65: 0 | W65: 0 | X65: 0 | Y65: 0 | Z65: 0
D66: O | E66: Total | F66: 0 | G66: 0 | H66: 0 | I66: 0 | J66: 0 | K66: 0 | L66: 0 | M66: 0 | N66: 0 | O66: 0 | P66: 0 | Q66: 0 | R66: 0 | S66: 0 | T66: 0 | U66: 0 | V66: 0 | W66: 0 | X66: 0 | Y66: 0 | Z66: 0
E67: Subsidio(-)/Contribucion(+) | F67: 44922.57 | G67: 2812.56 | H67: 1569.13 | I67: 833.5 | J67: 10514.48 | K67: 259.46 | L67: 0 | M67: 2275.96 | N67: 3235.33 | O67: 15317.02 | P67: 7681.79 | Q67: 423.34 | R67: 0 | S67: 0 | T67: 0 | U67: 0 | V67: 0 | W67: 0 | X67: 0 | Y67: 0 | Z67: 0
D68: T | E68: Total | F68: 44922.57 | G68: 2812.56 | H68: 1569.13 | I68: 833.5 | J68: 10514.48 | K68: 259.46 | L68: 0 | M68: 2275.96 | N68: 3235.33 | O68: 15317.02 | P68: 7681.79 | Q68: 423.34 | R68: 0 | S68: 0 | T68: 0 | U68: 0 | V68: 0 | W68: 0 | X68: 0 | Y68: 0 | Z68: 0
C69: OCCIDENTE | D69: Total | F69: 44922.57 | G69: 2812.56 | H69: 1569.13 | I69: 833.5 | J69: 10514.48 | K69: 259.46 | L69: 0 | M69: 2275.96 | N69: 3235.33 | O69: 15317.02 | P69: 7681.79 | Q69: 423.34 | R69: 0 | S69: 0 | T69: 0 | U69: 0 | V69: 0 | W69: 0 | X69: 0 | Y69: 0 | Z69: 0
B70: Aplicacion nuevos x reversion | C70: Total | F70: 12822.93 | G70: 1629.76 | H70: 908.11 | I70: 482.98 | J70: 4268.86 | K70: -85.24 | L70: 0 | M70: -747.86 | N70: 342.65 | O70: 1711.54 | P70: 4451.23 | Q70: -139.1 | R70: 0 | S70: 0 | T70: 0 | U70: 0 | V70: 0 | W70: 0 | X70: 0 | Y70: 0 | Z70: 0
E71: Subsidio(-)/Contribucion(+) | F71: -3.2536076e+09 | G71: -91345711 | H71: -50905404 | I71: -27078429 | J71: -9.643413e+08 | K71: -31681533 | L71: 0 | M71: -2.7807169e+08 | N71: -2.6199779e+08 | O71: -1.2502637e+09 | P71: -2.4623216e+08 | Q71: -51689935 | R71: 0 | S71: 0 | T71: 0 | U71: 0 | V71: 0 | W71: 0 | X71: 0 | Y71: 0 | Z71: 0
D72: E | E72: Total | F72: -3.2536076e+09 | G72: -91345711 | H72: -50905404 | I72: -27078429 | J72: -9.643413e+08 | K72: -31681533 | L72: 0 | M72: -2.7807169e+08 | N72: -2.6199779e+08 | O72: -1.2502637e+09 | P72: -2.4623216e+08 | Q72: -51689935 | R72: 0 | S72: 0 | T72: 0 | U72: 0 | V72: 0 | W72: 0 | X72: 0 | Y72: 0 | Z72: 0
C73: ENEL | D73: Total | F73: -3.2536076e+09 | G73: -91345711 | H73: -50905404 | I73: -27078429 | J73: -9.643413e+08 | K73: -31681533 | L73: 0 | M73: -2.7807169e+08 | N73: -2.6199779e+08 | O73: -1.2502637e+09 | P73: -2.4623216e+08 | Q73: -51689935 | R73: 0 | S73: 0 | T73: 0 | U73: 0 | V73: 0 | W73: 0 | X73: 0 | Y73: 0 | Z73: 0
E74: Subsidio(-)/Contribucion(+) | F74: 0 | G74: 0 | H74: 0 | I74: 0 | J74: 0 | K74: 0 | L74: 0 | M74: 0 | N74: 0 | O74: 0 | P74: 0 | Q74: 0 | R74: 0 | S74: 0 | T74: 0 | U74: 0 | V74: 0 | W74: 0 | X74: 0 | Y74: 0 | Z74: 0
D75: E | E75: Total | F75: 0 | G75: 0 | H75: 0 | I75: 0 | J75: 0 | K75: 0 | L75: 0 | M75: 0 | N75: 0 | O75: 0 | P75: 0 | Q75: 0 | R75: 0 | S75: 0 | T75: 0 | U75: 0 | V75: 0 | W75: 0 | X75: 0 | Y75: 0 | Z75: 0
C76: ENERBIT | D76: Total | F76: 0 | G76: 0 | H76: 0 | I76: 0 | J76: 0 | K76: 0 | L76: 0 | M76: 0 | N76: 0 | O76: 0 | P76: 0 | Q76: 0 | R76: 0 | S76: 0 | T76: 0 | U76: 0 | V76: 0 | W76: 0 | X76: 0 | Y76: 0 | Z76: 0
E77: Subsidio(-)/Contribucion(+) | F77: 13423599 | G77: 2490552.8 | H77: 1387405.4 | I77: 737634.79 | J77: 631013.34 | K77: 16984.56 | L77: 0 | M77: 150899.5 | N77: 207661.14 | O77: 966790.95 | P77: 6806944.6 | Q77: 27712.01 | R77: 0 | S77: 0 | T77: 0 | U77: 0 | V77: 0 | W77: 0 | X77: 0 | Y77: 0 | Z77: 0
D78: H | E78: Total | F78: 13423599 | G78: 2490552.8 | H78: 1387405.4 | I78: 737634.79 | J78: 631013.34 | K78: 16984.56 | L78: 0 | M78: 150899.5 | N78: 207661.14 | O78: 966790.95 | P78: 6806944.6 | Q78: 27712.01 | R78: 0 | S78: 0 | T78: 0 | U78: 0 | V78: 0 | W78: 0 | X78: 0 | Y78: 0 | Z78: 0
E79: Subsidio(-)/Contribucion(+) | F79: -325150.37 | G79: 488590.2 | H79: 270618.04 | I79: 137804.15 | J79: -905950.9 | K79: -31107.48 | L79: 0 | M79: -273355.91 | N79: -212055.38 | O79: -1075614 | P79: 1326676.2 | Q79: -50755.33 | R79: 0 | S79: 0 | T79: 0 | U79: 0 | V79: 0 | W79: 0 | X79: 0 | Y79: 0 | Z79: 0
D80: O | E80: Total | F80: -325150.37 | G80: 488590.2 | H80: 270618.04 | I80: 137804.15 | J80: -905950.9 | K80: -31107.48 | L80: 0 | M80: -273355.91 | N80: -212055.38 | O80: -1075614 | P80: 1326676.2 | Q80: -50755.33 | R80: 0 | S80: 0 | T80: 0 | U80: 0 | V80: 0 | W80: 0 | X80: 0 | Y80: 0 | Z80: 0
E81: Subsidio(-)/Contribucion(+) | F81: 50273483 | G81: 8795896.6 | H81: 4922970.6 | I81: 2633606.2 | J81: 2971274.2 | K81: 89779.5 | L81: 0 | M81: 777804.41 | N81: 1027778.3 | O81: 4888775.7 | P81: 24019519 | Q81: 146078.4 | R81: 0 | S81: 0 | T81: 0 | U81: 0 | V81: 0 | W81: 0 | X81: 0 | Y81: 0 | Z81: 0
D82: T | E82: Total | F82: 50273483 | G82: 8795896.6 | H82: 4922970.6 | I82: 2633606.2 | J82: 2971274.2 | K82: 89779.5 | L82: 0 | M82: 777804.41 | N82: 1027778.3 | O82: 4888775.7 | P82: 24019519 | Q82: 146078.4 | R82: 0 | S82: 0 | T82: 0 | U82: 0 | V82: 0 | W82: 0 | X82: 0 | Y82: 0 | Z82: 0
C83: OCCIDENTE | D83: Total | F83: 63371932 | G83: 11775040 | H83: 6580994 | I83: 3509045.2 | J83: 2696336.7 | K83: 75656.58 | L83: 0 | M83: 655348 | N83: 1023384 | O83: 4779952.6 | P83: 32153140 | Q83: 123035.08 | R83: 0 | S83: 0 | T83: 0 | U83: 0 | V83: 0 | W83: 0 | X83: 0 | Y83: 0 | Z83: 0
B84: Mes | C84: Total | F84: -3.1902357e+09 | G84: -79570672 | H84: -44324410 | I84: -23569383 | J84: -9.6164497e+08 | K84: -31605876 | L84: 0 | M84: -2.7741635e+08 | N84: -2.6097441e+08 | O84: -1.2454837e+09 | P84: -2.1407902e+08 | Q84: -51566900 | R84: 0 | S84: 0 | T84: 0 | U84: 0 | V84: 0 | W84: 0 | X84: 0 | Y84: 0 | Z84: 0
A85: Subs/Cont | B85: Total | F85: -3.1902229e+09 | G85: -79569042 | H85: -44323502 | I85: -23568900 | J85: -9.616407e+08 | K85: -31605962 | L85: 0 | M85: -2.7741709e+08 | N85: -2.6097407e+08 | O85: -1.245482e+09 | P85: -2.1407457e+08 | Q85: -51567039 | R85: 0 | S85: 0 | T85: 0 | U85: 0 | V85: 0 | W85: 0 | X85: 0 | Y85: 0 | Z85: 0
A86: Total | F86: 1.4835603e+10 | G86: 7.6226622e+08 | H86: 4.2461093e+08 | I86: 2.2609668e+08 | J86: 3.7953468e+09 | K86: 1.2689784e+08 | L86: 19931693 | M86: 1.1143696e+09 | N86: 1.0550358e+09 | O86: 5.0269929e+09 | P86: 2.0768943e+09 | Q86: 2.0718733e+08 | R86: -27796.54 | S86: 19.47 | T86: 236.56 | U86: 0 | V86: 0 | W86: 0 | X86: 0 | Y86: 0 | Z86: -106.9
C89: TOTAL | D89: OPORTUNO | E89: Total | F89: =F55+F84+F16-L16-L55 -> 1.4815022e+10 | G89: =G55+G16 -> 8.4180604e+08 | H89: =H55+H16 -> 4.6891797e+08 | I89: =I55+I16 -> 2.4965692e+08 | J89: =J55+J16 -> 4.7568461e+09 | K89: =K55+K16 -> 1.5849797e+08 | L89: =L55+L16 -> 19931693 | M89: =M55+M16 -> 1.3917356e+09 | N89: =N55+N16 -> 1.3159586e+09 | ... AP89: =AP55+AP16 -> 0
E90: Subsidio(-)/Contribucion(+) | F90: =F84 -> -3.1902357e+09
D91: EXTEMPORANEO | E91: Total | F91: =F70+F36-L36 -> 648870 | G91: =G36 -> 29223.59 | H91: =H36 -> 16458.47 | I91: =I36 -> 8660.22 | J91: =J36 -> 141425.47 | K91: =K36 -> 5825.54 | L91: =L36 -> 0 | M91: =M36 -> 51101.37 | N91: =N36 -> 51278.68 | ... AP91: =AP36 -> 0
E92: Subsidio(-)/Contribucion(+) | F92: =F70 -> 12822.93
C94: RECIPROCIDAD | D94: OPORTUNO | E94: Total | F94: 0 | G94: 0 | H94: 0 | I94: 0 | J94: 0 | K94: 0 | L94: 0 | M94: 0 | N94: 0 | O94: 0 | P94: 0 | Q94: 0 | R94: 0 | S94: 0 | T94: 0 | U94: 0 | V94: 0 | W94: 0 | X94: 0 | Y94: 0 | Z94: 0 | AA94: 0 | AB94: 0 | AC94: 0 | AD94: 0 | AE94: 0 | AF94: 0 | AG94: 0 | AH94: 0 | AI94: 0 | AJ94: 0 | AK94: 0 | AL94: 0 | AM94: 0 | AN94: 0 | AO94: 0 | AP94: 0
E95: Subsidio(-)/Contribucion(+) | F95: 0
D96: EXTEMPORANEO | E96: Total | F96: 0 | G96: 0 | H96: 0 | I96: 0 | J96: 0 | K96: 0 | L96: 0 | M96: 0 | N96: 0 | O96: 0 | P96: 0 | Q96: 0 | R96: 0 | S96: 0 | T96: 0 | U96: 0 | V96: 0 | W96: 0 | X96: 0 | Y96: 0 | Z96: 0 | AA96: 0 | AB96: 0 | AC96: 0 | AD96: 0 | AE96: 0 | AF96: 0 | AG96: 0 | AH96: 0 | AI96: 0 | AJ96: 0 | AK96: 0 | AL96: 0 | AM96: 0 | AN96: 0 | AO96: 0 | AP96: 0
E97: Subsidio(-)/Contribucion(+) | F97: 0
C99: ENEL | D99: OPORTUNO | E99: Total | F99: =F73+F40+F8-L8-L40 -> 1.44714e+10 | G99: =G40+G8 -> 8.0823038e+08 | H99: =H40+H8 -> 4.5024043e+08 | I99: =I40+I8 -> 2.3967057e+08 | J99: =J40+J8 -> 4.7177564e+09 | K99: =K40+K8 -> 1.5733684e+08 | L99: =L40+L8 -> 9937924.1 | M99: =M40+M8 -> 1.3815896e+09 | N99: =N40+N8 -> 1.3030269e+09 | ... AP99: =AP40+AP8 -> 0
E100: Subsidio(-)/Contribucion(+) | F100: =F73 -> -3.2536076e+09
D101: EXTEMPORANEO | E101: Total | F101: =F59+F21-L21 -> 513960 | G101: =G21 -> 23589.91 | H101: =H21 -> 13315.42 | I101: =I21 -> 6990.72 | J101: =J21 -> 120363.97 | K101: =K21 -> 5305.85 | L101: =L21 -> 0 | M101: =M21 -> 46542.54 | N101: =N21 -> 44798.14 | ... AP101: =AP21 -> 0
E102: Subsidio(-)/Contribucion(+) | F102: =F59 -> -32099.64
C104: ENERBIT | D104: OPORTUNO | E104: Total | F104: =F76+F44-L44 -> 0 | G104: =G44 -> 0 | H104: =H44 -> 0 | I104: =I44 -> 0 | J104: =J44 -> 0 | K104: =K44 -> 0 | L104: =L44 -> 0 | M104: =M44 -> 0 | N104: =N44 -> 0 | ... AO104: =AO44 -> 0
E105: Subsidio(-)/Contribucion(+) | F105: =F76 -> 0
D106: EXTEMPORANEO | E106: Total | F106: =F62+F25-L25 -> 0 | G106: =G25 -> 0 | H106: =H25 -> 0 | I106: =I25 -> 0 | J106: =J25 -> 0 | K106: =K25 -> 0 | L106: =L25 -> 0 | M106: =M25 -> 0 | N106: =N25 -> 0 | ... AO106: =AO25 -> 0
E107: Subsidio(-)/Contribucion(+) | F107: =F62 -> 0
C109: OCCIDENTE | D109: OPORTUNO | E109: Total | F109: =F83+F54+F15-L15-L54 -> 3.4362228e+08 | G109: =G54+G15 -> 33575652 | H109: =H54+H15 -> 18677541 | I109: =I54+I15 -> 9986351.4 | J109: =J54+J15 -> 39089725 | K109: =K54+K15 -> 1161133 | L109: =L54+L15 -> 9993768.9 | M109: =M54+M15 -> 10145988 | N109: =N54+N15 -> 12931733 | ... AP109: =AP54+AP15 -> 0
...

Sheet Rem. Anticipos R2
B1: PROMOAMBIENTAL
E2: Total | F2: Componente TDF | G2: Componente TTL | H2: Componente TVIAT | I2: Aprovechamiento | J2: CCSA Prest.Aprov. | K2: Especiales | L2: Componente TCS | M2: Componente TLU | N2: Componente TBL | O2: Componente TRT | P2: CCSA Prest. No Aprov. | Q2: Deb/Cred | R2: Deb/Cred-otros
D3: Vlr Servicio | E3: 0 | F3: 0 | G3: 0 | H3: 0 | I3: 0 | J3: 0 | K3: 0 | L3: 0 | M3: 0 | N3: 0 | O3: 0 | P3: 0 | Q3: 0 | R3: 0
D4: Vlr Intereses | E4: 0 | F4: 0 | G4: 0 | H4: 0 | I4: 0 | J4: 0 | K4: 0 | L4: 0 | M4: 0 | N4: 0 | O4: 0 | P4: 0 | Q4: 0 | R4: 0
C5: A | D5: Total | E5: 0 | F5: 0 | G5: 0 | H5: 0 | I5: 0 | J5: 0 | K5: 0 | L5: 0 | M5: 0 | N5: 0 | O5: 0 | P5: 0 | Q5: 0 | R5: 0
B6: EAB | C6: Total | E6: 0 | F6: 0 | G6: 0 | H6: 0 | I6: 0 | J6: 0 | K6: 0 | L6: 0 | M6: 0 | N6: 0 | O6: 0 | P6: 0 | Q6: 0 | R6: 0
D7: Vlr Servicio | E7: 0 | F7: 0 | G7: 0 | H7: 0 | I7: 0 | J7: 0 | K7: 0 | L7: 0 | M7: 0 | N7: 0 | O7: 0 | P7: 0 | Q7: 0 | R7: 0
D8: Vlr Intereses | E8: 0 | F8: 0 | G8: 0 | H8: 0 | I8: 0 | J8: 0 | K8: 0 | L8: 0 | M8: 0 | N8: 0 | O8: 0 | P8: 0 | Q8: 0 | R8: 0
C9: E | D9: Total | E9: 0 | F9: 0 | G9: 0 | H9: 0 | I9: 0 | J9: 0 | K9: 0 | L9: 0 | M9: 0 | N9: 0 | O9: 0 | P9: 0 | Q9: 0 | R9: 0
B10: ENEL | C10: Total | E10: 28281219 | F10: 0 | G10: 0 | H10: 0 | I10: 0 | J10: 0 | K10: 0 | L10: 0 | M10: 0 | N10: 0 | O10: 0 | P10: 0 | Q10: 0 | R10: 0
D11: Vlr Servicio | E11: 0 | F11: 0 | G11: 0 | H11: 0 | I11: 0 | J11: 0 | K11: 0 | L11: 0 | M11: 0 | N11: 0 | O11: 0 | P11: 0 | Q11: 0 | R11: 0
D12: Vlr Intereses | E12: 0 | F12: 0 | G12: 0 | H12: 0 | I12: 0 | J12: 0 | K12: 0 | L12: 0 | M12: 0 | N12: 0 | O12: 0 | P12: 0 | Q12: 0 | R12: 0
C13: E | D13: Total | E13: 0 | F13: 0 | G13: 0 | H13: 0 | I13: 0 | J13: 0 | K13: 0 | L13: 0 | M13: 0 | N13: 0 | O13: 0 | P13: 0 | Q13: 0 | R13: 0
B14: ENERBIT | C14: Total | E14: 0 | F14: 0 | G14: 0 | H14: 0 | I14: 0 | J14: 0 | K14: 0 | L14: 0 | M14: 0 | N14: 0 | O14: 0 | P14: 0 | Q14: 0 | R14: 0
D15: Vlr Servicio | E15: 0 | F15: 0 | G15: 0 | H15: 0 | I15: 0 | J15: 0 | K15: 0 | L15: 0 | M15: 0 | N15: 0 | O15: 0 | P15: 0 | Q15: 0 | R15: 0
D16: Vlr Intereses | E16: 0 | F16: 0 | G16: 0 | H16: 0 | I16: 0 | J16: 0 | K16: 0 | L16: 0 | M16: 0 | N16: 0 | O16: 0 | P16: 0 | Q16: 0 | R16: 0
C17: H | D17: Total | E17: 0 | F17: 0 | G17: 0 | H17: 0 | I17: 0 | J17: 0 | K17: 0 | L17: 0 | M17: 0 | N17: 0 | O17: 0 | P17: 0 | Q17: 0 | R17: 0
D18: Vlr Servicio | E18: 0 | F18: 0 | G18: 0 | H18: 0 | I18: 0 | J18: 0 | K18: 0 | L18: 0 | M18: 0 | N18: 0 | O18: 0 | P18: 0 | Q18: 0 | R18: 0
D19: Vlr Intereses | E19: 0 | F19: 0 | G19: 0 | H19: 0 | I19: 0 | J19: 0 | K19: 0 | L19: 0 | M19: 0 | N19: 0 | O19: 0 | P19: 0 | Q19: 0 | R19: 0
C20: O | D20: Total | E20: 0 | F20: 0 | G20: 0 | H20: 0 | I20: 0 | J20: 0 | K20: 0 | L20: 0 | M20: 0 | N20: 0 | O20: 0 | P20: 0 | Q20: 0 | R20: 0
D21: Vlr Servicio | E21: 0 | F21: 0 | G21: 0 | H21: 0 | I21: 0 | J21: 0 | K21: 0 | L21: 0 | M21: 0 | N21: 0 | O21: 0 | P21: 0 | Q21: 0 | R21: 0
D22: Vlr Intereses | E22: 0 | F22: 0 | G22: 0 | H22: 0 | I22: 0 | J22: 0 | K22: 0 | L22: 0 | M22: 0 | N22: 0 | O22: 0 | P22: 0 | Q22: 0 | R22: 0
C23: T | D23: Total | E23: 0 | F23: 0 | G23: 0 | H23: 0 | I23: 0 | J23: 0 | K23: 0 | L23: 0 | M23: 0 | N23: 0 | O23: 0 | P23: 0 | Q23: 0 | R23: 0
B24: OCCIDENTE | C24: Total | E24: 2995523.6 | F24: 0 | G24: 0 | H24: 0 | I24: 0 | J24: 0 | K24: 0 | L24: 0 | M24: 0 | N24: 0 | O24: 0 | P24: 0 | Q24: 0 | R24: 0
A25: Componente | B25: Total | E25: 31276742 | F25: 0 | G25: 0 | H25: 0 | I25: 0 | J25: 0 | K25: 0 | L25: 0 | M25: 0 | N25: 0 | O25: 0 | P25: 0 | Q25: 0 | R25: 0
D26: Subsidio(-)/Contribucion(+) | E26: 0 | F26: 0 | G26: 0 | H26: 0 | I26: 0 | J26: 0 | K26: 0 | L26: 0 | M26: 0 | N26: 0 | O26: 0 | P26: 0 | Q26: 0 | R26: 0
C27: A | D27: Total | E27: 0 | F27: 0 | G27: 0 | H27: 0 | I27: 0 | J27: 0 | K27: 0 | L27: 0 | M27: 0 | N27: 0 | O27: 0 | P27: 0 | Q27: 0 | R27: 0
B28: EAB | C28: Total | E28: 0 | F28: 0 | G28: 0 | H28: 0 | I28: 0 | J28: 0 | K28: 0 | L28: 0 | M28: 0 | N28: 0 | O28: 0 | P28: 0 | Q28: 0 | R28: 0
D29: Subsidio(-)/Contribucion(+) | E29: 0 | F29: 0 | G29: 0 | H29: 0 | I29: 0 | J29: 0 | K29: 0 | L29: 0 | M29: 0 | N29: 0 | O29: 0 | P29: 0 | Q29: 0 | R29: 0
C30: E | D30: Total | E30: 0 | F30: 0 | G30: 0 | H30: 0 | I30: 0 | J30: 0 | K30: 0 | L30: 0 | M30: 0 | N30: 0 | O30: 0 | P30: 0 | Q30: 0 | R30: 0
B31: ENEL | C31: Total | E31: -1549869.4 | F31: 0 | G31: 0 | H31: 0 | I31: 0 | J31: 0 | K31: 0 | L31: 0 | M31: 0 | N31: 0 | O31: 0 | P31: 0 | Q31: 0 | R31: 0
D32: Subsidio(-)/Contribucion(+) | E32: 0 | F32: 0 | G32: 0 | H32: 0 | I32: 0 | J32: 0 | K32: 0 | L32: 0 | M32: 0 | N32: 0 | O32: 0 | P32: 0 | Q32: 0 | R32: 0
C33: E | D33: Total | E33: 0 | F33: 0 | G33: 0 | H33: 0 | I33: 0 | J33: 0 | K33: 0 | L33: 0 | M33: 0 | N33: 0 | O33: 0 | P33: 0 | Q33: 0 | R33: 0
B34: ENERBIT | C34: Total | E34: 0 | F34: 0 | G34: 0 | H34: 0 | I34: 0 | J34: 0 | K34: 0 | L34: 0 | M34: 0 | N34: 0 | O34: 0 | P34: 0 | Q34: 0 | R34: 0
D35: Subsidio(-)/Contribucion(+) | E35: 0 | F35: 0 | G35: 0 | H35: 0 | I35: 0 | J35: 0 | K35: 0 | L35: 0 | M35: 0 | N35: 0 | O35: 0 | P35: 0 | Q35: 0 | R35: 0
C36: H | D36: Total | E36: 0 | F36: 0 | G36: 0 | H36: 0 | I36: 0 | J36: 0 | K36: 0 | L36: 0 | M36: 0 | N36: 0 | O36: 0 | P36: 0 | Q36: 0 | R36: 0
D37: Subsidio(-)/Contribucion(+) | E37: 0 | F37: 0 | G37: 0 | H37: 0 | I37: 0 | J37: 0 | K37: 0 | L37: 0 | M37: 0 | N37: 0 | O37: 0 | P37: 0 | Q37: 0 | R37: 0
C38: O | D38: Total | E38: 0 | F38: 0 | G38: 0 | H38: 0 | I38: 0 | J38: 0 | K38: 0 | L38: 0 | M38: 0 | N38: 0 | O38: 0 | P38: 0 | Q38: 0 | R38: 0
D39: Subsidio(-)/Contribucion(+) | E39: 0 | F39: 0 | G39: 0 | H39: 0 | I39: 0 | J39: 0 | K39: 0 | L39: 0 | M39: 0 | N39: 0 | O39: 0 | P39: 0 | Q39: 0 | R39: 0
C40: T | D40: Total | E40: 0 | F40: 0 | G40: 0 | H40: 0 | I40: 0 | J40: 0 | K40: 0 | L40: 0 | M40: 0 | N40: 0 | O40: 0 | P40: 0 | Q40: 0 | R40: 0
B41: OCCIDENTE | C41: Total | E41: 861197.98 | F41: 0 | G41: 0 | H41: 0 | I41: 0 | J41: 0 | K41: 0 | L41: 0 | M41: 0 | N41: 0 | O41: 0 | P41: 0 | Q41: 0 | R41: 0
A42: Subs/Cont | B42: Total | E42: -688671.4 | F42: 0 | G42: 0 | H42: 0 | I42: 0 | J42: 0 | K42: 0 | L42: 0 | M42: 0 | N42: 0 | O42: 0 | P42: 0 | Q42: 0 | R42: 0
A43: Total | E43: 0 | F43: 0 | G43: 0 | H43: 0 | I43: 0 | J43: 0 | K43: 0 | L43: 0 | M43: 0 | N43: 0 | O43: 0 | P43: 0 | Q43: 0 | R43: 0
B57: TOTAL | C57: OPORTUNO | D57: Total | E57: =E25+E42-K25 -> 30588071 | F57: =F25 -> 0 | G57: =G25 -> 0 | H57: =H25 -> 0 | I57: =I25 -> 0 | J57: =J25 -> 0 | K57: =K25 -> 0 | L57: =L25 -> 0 | M57: =M25 -> 0 | ... S57: =S25 -> 0
D58: Subsidio(-)/Contribucion(+) | E58: =E42 -> -688671.4
B60: RECIPROCIDAD | C60: OPORTUNO | D60: Total | E60: 0 | F60: 0 | G60: 0 | H60: 0 | I60: 0 | J60: 0 | K60: 0 | L60: 0 | M60: 0 | N60: 0 | O60: 0 | P60: 0 | Q60: 0 | R60: 0 | S60: 0
D61: Subsidio(-)/Contribucion(+) | E61: 0
B63: ENEL | C63: OPORTUNO | D63: Total | E63: =E31+E28+E10+E6-K6-K10 -> 26731349 | F63: =F10+F6 -> 0 | G63: =G10+G6 -> 0 | H63: =H10+H6 -> 0 | I63: =I10+I6 -> 0 | J63: =J10+J6 -> 0 | K63: =K10+K6 -> 0 | L63: =L10+L6 -> 0 | M63: =M10+M6 -> 0 | ... S63: =S10+S6 -> 0
D64: Subsidio(-)/Contribucion(+) | E64: =E31+E28 -> -1549869.4
B66: ENERBIT | C66: OPORTUNO | D66: Total | E66: =E34+E14-K14 -> 0 | F66: =F14 -> 0 | G66: 0 | H66: 0 | I66: 0 | J66: 0 | K66: 0 | L66: 0 | M66: 0 | N66: 0 | O66: 0 | P66: 0 | Q66: 0 | R66: 0
D67: Subsidio(-)/Contribucion(+) | E67: =E34 -> 0
B69: OCCIDENTE | C69: OPORTUNO | D69: Total | E69: =E24+E41-K24 -> 3856721.6 | F69: =F24 -> 0 | G69: =G24 -> 0 | H69: =H24 -> 0 | I69: =I24 -> 0 | J69: =J24 -> 0 | K69: =K24 -> 0 | L69: =L24 -> 0 | M69: =M24 -> 0 | ... S69: =S24 -> 0
D70: Subsidio(-)/Contribucion(+) | E70: =E41 -> 861197.98
B72: CIUDAD LIMPIA-ACUEDUCTO | C72: OPORTUNO | D72: Total | E72: 0 | F72: 0 | G72: 0 | H72: 0 | I72: 0 | J72: 0 | K72: 0 | L72: 0 | M72: 0 | N72: 0 | O72: 0 | P72: 0 | Q72: 0 | R72: 0 | S72: 0
D73: Subsidio(-)/Contribucion(+) | E73: 0
B75: LIME
E76: Total | F76: Componente TDF | G76: Componente TTL | H76: Componente TVIAT | I76: Aprovechamiento | J76: CCSA Prest.Aprov. | K76: Especiales | L76: Componente TCS | M76: Componente TLU | N76: Componente TBL | O76: Componente TRT | P76: CCSA Prest. No Aprov. | Q76: Deb/Cred | R76: Deb/Cred-otros
D77: Vlr Servicio | E77: 0 | F77: 0 | G77: 0 | H77: 0 | I77: 0 | J77: 0 | K77: 0 | L77: 0 | M77: 0 | N77: 0 | O77: 0 | P77: 0 | Q77: 0 | R77: 0
D78: Vlr Intereses | E78: 0 | F78: 0 | G78: 0 | H78: 0 | I78: 0 | J78: 0 | K78: 0 | L78: 0 | M78: 0 | N78: 0 | O78: 0 | P78: 0 | Q78: 0 | R78: 0
C79: A | D79: Total | E79: 0 | F79: 0 | G79: 0 | H79: 0 | I79: 0 | J79: 0 | K79: 0 | L79: 0 | M79: 0 | N79: 0 | O79: 0 | P79: 0 | Q79: 0 | R79: 0
B80: EAB | C80: Total | E80: 149137.87 | F80: 0 | G80: 0 | H80: 0 | I80: 0 | J80: 0 | K80: 0 | L80: 0 | M80: 0 | N80: 0 | O80: 0 | P80: 0 | Q80: 0 | R80: 0
D81: Vlr Servicio | E81: 0 | F81: 0 | G81: 0 | H81: 0 | I81: 0 | J81: 0 | K81: 0 | L81: 0 | M81: 0 | N81: 0 | O81: 0 | P81: 0 | Q81: 0 | R81: 0
D82: Vlr Intereses | E82: 0 | F82: 0 | G82: 0 | H82: 0 | I82: 0 | J82: 0 | K82: 0 | L82: 0 | M82: 0 | N82: 0 | O82: 0 | P82: 0 | Q82: 0 | R82: 0
C83: E | D83: Total | E83: 0 | F83: 0 | G83: 0 | H83: 0 | I83: 0 | J83: 0 | K83: 0 | L83: 0 | M83: 0 | N83: 0 | O83: 0 | P83: 0 | Q83: 0 | R83: 0
B84: ENEL | C84: Total | E84: 58544042 | F84: 0 | G84: 0 | H84: 0 | I84: 0 | J84: 0 | K84: 70736.95 | L84: 0 | M84: 0 | N84: 0 | O84: 0 | P84: 0 | Q84: 0 | R84: 0
D85: Vlr Servicio | E85: 0 | F85: 0 | G85: 0 | H85: 0 | I85: 0 | J85: 0 | K85: 0 | L85: 0 | M85: 0 | N85: 0 | O85: 0 | P85: 0 | Q85: 0 | R85: 0
D86: Vlr Intereses | E86: 0 | F86: 0 | G86: 0 | H86: 0 | I86: 0 | J86: 0 | K86: 0 | L86: 0 | M86: 0 | N86: 0 | O86: 0 | P86: 0 | Q86: 0 | R86: 0
C87: 1 | D87: Total | E87: 0 | F87: 0 | G87: 0 | H87: 0 | I87: 0 | J87: 0 | K87: 0 | L87: 0 | M87: 0 | N87: 0 | O87: 0 | P87: 0 | Q87: 0 | R87: 0
D88: Vlr Servicio | E88: 0 | F88: 0 | G88: 0 | H88: 0 | I88: 0 | J88: 0 | K88: 0 | L88: 0 | M88: 0 | N88: 0 | O88: 0 | P88: 0 | Q88: 0 | R88: 0
D89: Vlr Intereses | E89: 0 | F89: 0 | G89: 0 | H89: 0 | I89: 0 | J89: 0 | K89: 0 | L89: 0 | M89: 0 | N89: 0 | O89: 0 | P89: 0 | Q89: 0 | R89: 0
C90: 2 | D90: Total | E90: 0 | F90: 0 | G90: 0 | H90: 0 | I90: 0 | J90: 0 | K90: 0 | L90: 0 | M90: 0 | N90: 0 | O90: 0 | P90: 0 | Q90: 0 | R90: 0
D91: Vlr Servicio | E91: 0 | F91: 0 | G91: 0 | H91: 0 | I91: 0 | J91: 0 | K91: 0 | L91: 0 | M91: 0 | N91: 0 | O91: 0 | P91: 0 | Q91: 0 | R91: 0
D92: Vlr Intereses | E92: 0 | F92: 0 | G92: 0 | H92: 0 | I92: 0 | J92: 0 | K92: 0 | L92: 0 | M92: 0 | N92: 0 | O92: 0 | P92: 0 | Q92: 0 | R92: 0
C93: 3 | D93: Total | E93: 0 | F93: 0 | G93: 0 | H93: 0 | I93: 0 | J93: 0 | K93: 0 | L93: 0 | M93: 0 | N93: 0 | O93: 0 | P93: 0 | Q93: 0 | R93: 0
D94: Vlr Servicio | E94: 0 | F94: 0 | G94: 0 | H94: 0 | I94: 0 | J94: 0 | K94: 0 | L94: 0 | M94: 0 | N94: 0 | O94: 0 | P94: 0 | Q94: 0 | R94: 0
D95: Vlr Intereses | E95: 0 | F95: 0 | G95: 0 | H95: 0 | I95: 0 | J95: 0 | K95: 0 | L95: 0 | M95: 0 | N95: 0 | O95: 0 | P95: 0 | Q95: 0 | R95: 0
C96: 4 | D96: Total | E96: 0 | F96: 0 | G96: 0 | H96: 0 | I96: 0 | J96: 0 | K96: 0 | L96: 0 | M96: 0 | N96: 0 | O96: 0 | P96: 0 | Q96: 0 | R96: 0
D97: Vlr Servicio | E97: 0 | F97: 0 | G97: 0 | H97: 0 | I97: 0 | J97: 0 | K97: 0 | L97: 0 | M97: 0 | N97: 0 | O97: 0 | P97: 0 | Q97: 0 | R97: 0
D98: Vlr Intereses | E98: 0 | F98: 0 | G98: 0 | H98: 0 | I98: 0 | J98: 0 | K98: 0 | L98: 0 | M98: 0 | N98: 0 | O98: 0 | P98: 0 | Q98: 0 | R98: 0
C99: 5 | D99: Total | E99: 0 | F99: 0 | G99: 0 | H99: 0 | I99: 0 | J99: 0 | K99: 0 | L99: 0 | M99: 0 | N99: 0 | O99: 0 | P99: 0 | Q99: 0 | R99: 0
D100: Vlr Servicio | E100: 0 | F100: 0 | G100: 0 | H100: 0 | I100: 0 | J100: 0 | K100: 0 | L100: 0 | M100: 0 | N100: 0 | O100: 0 | P100: 0 | Q100: 0 | R100: 0
D101: Vlr Intereses | E101: 0 | F101: 0 | G101: 0 | H101: 0 | I101: 0 | J101: 0 | K101: 0 | L101: 0 | M101: 0 | N101: 0 | O101: 0 | P101: 0 | Q101: 0 | R101: 0
C102: 6 | D102: Total | E102: 0 | F102: 0 | G102: 0 | H102: 0 | I102: 0 | J102: 0 | K102: 0 | L102: 0 | M102: 0 | N102: 0 | O102: 0 | P102: 0 | Q102: 0 | R102: 0
D103: Vlr Servicio | E103: 0 | F103: 0 | G103: 0 | H103: 0 | I103: 0 | J103: 0 | K103: 0 | L103: 0 | M103: 0 | N103: 0 | O103: 0 | P103: 0 | Q103: 0 | R103: 0
D104: Vlr Intereses | E104: 0 | F104: 0 | G104: 0 | H104: 0 | I104: 0 | J104: 0 | K104: 0 | L104: 0 | M104: 0 | N104: 0 | O104: 0 | P104: 0 | Q104: 0 | R104: 0
C105: 9 | D105: Total | E105: 0 | F105: 0 | G105: 0 | H105: 0 | I105: 0 | J105: 0 | K105: 0 | L105: 0 | M105: 0 | N105: 0 | O105: 0 | P105: 0 | Q105: 0 | R105: 0
B106: NUEVO ESQUEMA | C106: Total | E106: 16015077 | F106: 0 | G106: 0 | H106: 0 | I106: 0 | J106: 0 | K106: 0 | L106: 0 | M106: 0 | N106: 0 | O106: 0 | P106: 0 | Q106: 0 | R106: 0
D107: Vlr Servicio | E107: 0 | F107: 0 | G107: 0 | H107: 0 | I107: 0 | J107: 0 | K107: 0 | L107: 0 | M107: 0 | N107: 0 | O107: 0 | P107: 0 | Q107: 0 | R107: 0
D108: Vlr Intereses | E108: 0 | F108: 0 | G108: 0 | H108: 0 | I108: 0 | J108: 0 | K108: 0 | L108: 0 | M108: 0 | N108: 0 | O108: 0 | P108: 0 | Q108: 0 | R108: 0
C109: H | D109: Total | E109: 0 | F109: 0 | G109: 0 | H109: 0 | I109: 0 | J109: 0 | K109: 0 | L109: 0 | M109: 0 | N109: 0 | O109: 0 | P109: 0 | Q109: 0 | R109: 0
D110: Vlr Servicio | E110: 0 | F110: 0 | G110: 0 | H110: 0 | I110: 0 | J110: 0 | K110: 0 | L110: 0 | M110: 0 | N110: 0 | O110: 0 | P110: 0 | Q110: 0 | R110: 0
D111: Vlr Intereses | E111: 0 | F111: 0 | G111: 0 | H111: 0 | I111: 0 | J111: 0 | K111: 0 | L111: 0 | M111: 0 | N111: 0 | O111: 0 | P111: 0 | Q111: 0 | R111: 0
C112: O | D112: Total | E112: 0 | F112: 0 | G112: 0 | H112: 0 | I112: 0 | J112: 0 | K112: 0 | L112: 0 | M112: 0 | N112: 0 | O112: 0 | P112: 0 | Q112: 0 | R112: 0
D113: Vlr Servicio | E113: 0 | F113: 0 | G113: 0 | H113: 0 | I113: 0 | J113: 0 | K113: 0 | L113: 0 | M113: 0 | N113: 0 | O113: 0 | P113: 0 | Q113: 0 | R113: 0
D114: Vlr Intereses | E114: 0 | F114: 0 | G114: 0 | H114: 0 | I114: 0 | J114: 0 | K114: 0 | L114: 0 | M114: 0 | N114: 0 | O114: 0 | P114: 0 | Q114: 0 | R114: 0
C115: T | D115: Total | E115: 0 | F115: 0 | G115: 0 | H115: 0 | I115: 0 | J115: 0 | K115: 0 | L115: 0 | M115: 0 | N115: 0 | O115: 0 | P115: 0 | Q115: 0 | R115: 0
B116: OCCIDENTE | C116: Total | E116: 41702164 | F116: 0 | G116: 0 | H116: 0 | I116: 0 | J116: 0 | K116: 0 | L116: 0 | M116: 0 | N116: 0 | O116: 0 | P116: 0 | Q116: 0 | R116: 0
A117: Componente | B117: Total | E117: 1.1641042e+08 | F117: 0 | G117: 0 | H117: 0 | I117: 0 | J117: 0 | K117: 70736.95 | L117: 0 | M117: 0 | N117: 0 | O117: 0 | P117: 0 | Q117: 0 | R117: 0
D118: Subsidio(-)/Contribucion(+) | E118: 0 | F118: 0 | G118: 0 | H118: 0 | I118: 0 | J118: 0 | K118: 0 | L118: 0 | M118: 0 | N118: 0 | O118: 0 | P118: 0 | Q118: 0 | R118: 0
C119: A | D119: Total | E119: 0 | F119: 0 | G119: 0 | H119: 0 | I119: 0 | J119: 0 | K119: 0 | L119: 0 | M119: 0 | N119: 0 | O119: 0 | P119: 0 | Q119: 0 | R119: 0
...

Sheet Reversion Pagos R4
B1: PROMOAMBIENTAL
D2: Total | E2: Componente TDF | F2: Componente TTL | G2: Componente TVIAT | H2: Aprovechamiento | I2: CCSA Prest.Aprov. | J2: Componente TCS | K2: Componente TLU | L2: Componente TBL | M2: Componente TRT | N2: CCSA Prest. No Aprov. | O2: Ajuste Decena | P2: SERVICIO ESPECIALES | Q2: Ajuste Recargo Aseo | R2: Otros
C3: Vlr Servicio | D3: 0 | E3: 0 | F3: 0 | G3: 0 | H3: 0 | I3: 0 | J3: 0 | K3: 0 | L3: 0 | M3: 0 | N3: 0 | O3: 0 | P3: 0 | Q3: 0 | R3: 0
C4: Vlr Intereses | D4: 0 | E4: 0 | F4: 0 | G4: 0 | H4: 0 | I4: 0 | J4: 0 | K4: 0 | L4: 0 | M4: 0 | N4: 0 | O4: 0 | P4: 0 | Q4: 0 | R4: 0
B5: Componente | C5: Total | D5: 0 | E5: 0 | F5: 0 | G5: 0 | H5: 0 | I5: 0 | J5: 0 | K5: 0 | L5: 0 | M5: 0 | N5: 0 | O5: 0 | P5: 0 | Q5: 0 | R5: 0
C6: Subsidio(-)/Contribucion(+) | D6: 0 | E6: 0 | F6: 0 | G6: 0 | H6: 0 | I6: 0 | J6: 0 | K6: 0 | L6: 0 | M6: 0 | N6: 0 | O6: 0 | P6: 0 | Q6: 0 | R6: 0
B7: Subs/Cont | C7: Total | D7: 0 | E7: 0 | F7: 0 | G7: 0 | H7: 0 | I7: 0 | J7: 0 | K7: 0 | L7: 0 | M7: 0 | N7: 0 | O7: 0 | P7: 0 | Q7: 0 | R7: 0
A8: ENEL | B8: Total | D8: -3698870 | E8: 0 | F8: 0 | G8: 0 | H8: 0 | I8: 0 | J8: 0 | K8: 0 | L8: 0 | M8: 0 | N8: 0 | O8: 0 | P8: 0 | Q8: 0 | R8: 0
C9: Vlr Servicio | D9: 0 | E9: 0 | F9: 0 | G9: 0 | H9: 0 | I9: 0 | J9: 0 | K9: 0 | L9: 0 | M9: 0 | N9: 0 | O9: 0 | P9: 0 | Q9: 0 | R9: 0
C10: Vlr Intereses | D10: 0 | E10: 0 | F10: 0 | G10: 0 | H10: 0 | I10: 0 | J10: 0 | K10: 0 | L10: 0 | M10: 0 | N10: 0 | O10: 0 | P10: 0 | Q10: 0 | R10: 0
B11: Componente | C11: Total | D11: 0 | E11: 0 | F11: 0 | G11: 0 | H11: 0 | I11: 0 | J11: 0 | K11: 0 | L11: 0 | M11: 0 | N11: 0 | O11: 0 | P11: 0 | Q11: 0 | R11: 0
C12: Subsidio(-)/Contribucion(+) | D12: 0 | E12: 0 | F12: 0 | G12: 0 | H12: 0 | I12: 0 | J12: 0 | K12: 0 | L12: 0 | M12: 0 | N12: 0 | O12: 0 | P12: 0 | Q12: 0 | R12: 0
B13: Subs/Cont | C13: Total | D13: 0 | E13: 0 | F13: 0 | G13: 0 | H13: 0 | I13: 0 | J13: 0 | K13: 0 | L13: 0 | M13: 0 | N13: 0 | O13: 0 | P13: 0 | Q13: 0 | R13: 0
A14: ENERBIT | B14: Total | D14: 0 | E14: 0 | F14: 0 | G14: 0 | H14: 0 | I14: 0 | J14: 0 | K14: 0 | L14: 0 | M14: 0 | N14: 0 | O14: 0 | P14: 0 | Q14: 0 | R14: 0
C15: Vlr Servicio | D15: 0 | E15: 0 | F15: 0 | G15: 0 | H15: 0 | I15: 0 | J15: 0 | K15: 0 | L15: 0 | M15: 0 | N15: 0 | O15: 0 | P15: 0 | Q15: 0 | R15: 0
C16: Vlr Intereses | D16: 0 | E16: 0 | F16: 0 | G16: 0 | H16: 0 | I16: 0 | J16: 0 | K16: 0 | L16: 0 | M16: 0 | N16: 0 | O16: 0 | P16: 0 | Q16: 0 | R16: 0
B17: Componente | C17: Total | D17: 0 | E17: 0 | F17: 0 | G17: 0 | H17: 0 | I17: 0 | J17: 0 | K17: 0 | L17: 0 | M17: 0 | N17: 0 | O17: 0 | P17: 0 | Q17: 0 | R17: 0
C18: Subsidio(-)/Contribucion(+) | D18: 0 | E18: 0 | F18: 0 | G18: 0 | H18: 0 | I18: 0 | J18: 0 | K18: 0 | L18: 0 | M18: 0 | N18: 0 | O18: 0 | P18: 0 | Q18: 0 | R18: 0
B19: Subs/Cont | C19: Total | D19: 0 | E19: 0 | F19: 0 | G19: 0 | H19: 0 | I19: 0 | J19: 0 | K19: 0 | L19: 0 | M19: 0 | N19: 0 | O19: 0 | P19: 0 | Q19: 0 | R19: 0
A20: OCCIDENTE | B20: Total | D20: -134910 | E20: 0 | F20: 0 | G20: 0 | H20: 0 | I20: 0 | J20: 0 | K20: 0 | L20: 0 | M20: 0 | N20: 0 | O20: 0 | P20: 0 | Q20: 0 | R20: 0
A21: Total | D21: -3833780 | E21: 0 | F21: 0 | G21: 0 | H21: 0 | I21: 0 | J21: 0 | K21: 0 | L21: 0 | M21: 0 | N21: 0 | O21: 0 | P21: 0 | Q21: 0 | R21: 0
A79: TOTAL | B79: OPORTUNO | C79: Total | D79: =D21-P21 -> -3833780 | E79: =E5+E17 -> 0 | F79: =F5+F17 -> 0 | G79: =G5+G17 -> 0 | H79: =H5+H17 -> 0 | I79: =I5+I17 -> 0 | J79: =J5+J17 -> 0 | K79: =K5+K17 -> 0 | L79: =L5+L17 -> 0 | ... R79: =R5+R17 -> 0
C80: Subsidio(-)/Contribucion(+) | D80: =D7+D19 -> 0
A82: RECIPROCIDAD | B82: OPORTUNO | C82: Total | D82: 0 | E82: 0 | F82: 0 | G82: 0 | H82: 0 | I82: 0 | J82: 0 | K82: 0 | L82: 0 | M82: 0 | N82: 0 | O82: 0 | P82: 0 | Q82: 0 | R82: 0
C83: Subsidio(-)/Contribucion(+) | D83: 0
A85: ENEL | B85: OPORTUNO | C85: Total | D85: =D8-P8 -> -3698870 | E85: =E5 -> 0 | F85: =F5 -> 0 | G85: =G5 -> 0 | H85: =H5 -> 0 | I85: =I5 -> 0 | J85: =J5 -> 0 | K85: =K5 -> 0 | L85: =L5 -> 0 | ... R85: =R5 -> 0
C86: Subsidio(-)/Contribucion(+) | D86: =D7 -> 0
A88: ENERBIT | B88: OPORTUNO | C88: Total | D88: =D14-P14 -> 0 | E88: =E11 -> 0 | F88: =F11 -> 0 | G88: =G11 -> 0 | H88: =H11 -> 0 | I88: =I11 -> 0 | J88: =J11 -> 0 | K88: =K11 -> 0 | L88: =L11 -> 0 | ... R88: =R11 -> 0
C89: Subsidio(-)/Contribucion(+) | D89: =D13 -> 0
A91: OCCIDENTE | B91: OPORTUNO | C91: Total | D91: =D20-P20 -> -134910 | E91: =E17 -> 0 | F91: =F17 -> 0 | G91: =G17 -> 0 | H91: =H17 -> 0 | I91: =I17 -> 0 | J91: =J17 -> 0 | K91: =K17 -> 0 | L91: =L17 -> 0 | ... R91: =R17 -> 0
C92: Subsidio(-)/Contribucion(+) | D92: =D19 -> 0
A94: CIUDAD LIMPIA-ACUEDUCTO | B94: OPORTUNO | C94: Total | D94: 0 | E94: 0 | F94: 0 | G94: 0 | H94: 0 | I94: 0 | J94: 0 | K94: 0 | L94: 0 | M94: 0 | N94: 0 | O94: 0 | P94: 0 | Q94: 0 | R94: 0
C95: Subsidio(-)/Contribucion(+) | D95: 0
B97: LIME
D98: Total | E98: Componente TDF | F98: Componente TTL | G98: Componente TVIAT | H98: Aprovechamiento | I98: CCSA Prest.Aprov. | J98: Componente TCS | K98: Componente TLU | L98: Componente TBL | M98: Componente TRT | N98: CCSA Prest. No Aprov. | O98: Ajuste Decena | P98: SERVICIO ESPECIALES | Q98: Ajuste Recargo Aseo | R98: Otros
C99: Vlr Servicio | D99: 0 | E99: 0 | F99: 0 | G99: 0 | H99: 0 | I99: 0 | J99: 0 | K99: 0 | L99: 0 | M99: 0 | N99: 0 | O99: 0 | P99: 0 | Q99: 0 | R99: 0
C100: Vlr Intereses | D100: 0 | E100: 0 | F100: 0 | G100: 0 | H100: 0 | I100: 0 | J100: 0 | K100: 0 | L100: 0 | M100: 0 | N100: 0 | O100: 0 | P100: 0 | Q100: 0 | R100: 0
B101: Componente | C101: Total | D101: 0 | E101: 0 | F101: 0 | G101: 0 | H101: 0 | I101: 0 | J101: 0 | K101: 0 | L101: 0 | M101: 0 | N101: 0 | O101: 0 | P101: 0 | Q101: 0 | R101: 0
C102: Subsidio(-)/Contribucion(+) | D102: 0 | E102: 0 | F102: 0 | G102: 0 | H102: 0 | I102: 0 | J102: 0 | K102: 0 | L102: 0 | M102: 0 | N102: 0 | O102: 0 | P102: 0 | Q102: 0 | R102: 0
B103: Subs/Cont | C103: Total | D103: 0 | E103: 0 | F103: 0 | G103: 0 | H103: 0 | I103: 0 | J103: 0 | K103: 0 | L103: 0 | M103: 0 | N103: 0 | O103: 0 | P103: 0 | Q103: 0 | R103: 0
A104: ENEL | B104: Total | D104: -20858585 | E104: 0 | F104: 0 | G104: 0 | H104: 0 | I104: 0 | J104: 0 | K104: 0 | L104: 0 | M104: 0 | N104: 0 | O104: 0 | P104: 0 | Q104: 0 | R104: 0
C105: Vlr Servicio | D105: 0 | E105: 0 | F105: 0 | G105: 0 | H105: 0 | I105: 0 | J105: 0 | K105: 0 | L105: 0 | M105: 0 | N105: 0 | O105: 0 | P105: 0 | Q105: 0 | R105: 0
C106: Vlr Intereses | D106: 0 | E106: 0 | F106: 0 | G106: 0 | H106: 0 | I106: 0 | J106: 0 | K106: 0 | L106: 0 | M106: 0 | N106: 0 | O106: 0 | P106: 0 | Q106: 0 | R106: 0
B107: Componente | C107: Total | D107: 0 | E107: 0 | F107: 0 | G107: 0 | H107: 0 | I107: 0 | J107: 0 | K107: 0 | L107: 0 | M107: 0 | N107: 0 | O107: 0 | P107: 0 | Q107: 0 | R107: 0
C108: Subsidio(-)/Contribucion(+) | D108: 0 | E108: 0 | F108: 0 | G108: 0 | H108: 0 | I108: 0 | J108: 0 | K108: 0 | L108: 0 | M108: 0 | N108: 0 | O108: 0 | P108: 0 | Q108: 0 | R108: 0
B109: Subs/Cont | C109: Total | D109: 0 | E109: 0 | F109: 0 | G109: 0 | H109: 0 | I109: 0 | J109: 0 | K109: 0 | L109: 0 | M109: 0 | N109: 0 | O109: 0 | P109: 0 | Q109: 0 | R109: 0
A110: NUEVO ESQUEMA | B110: Total | D110: 0 | E110: 0 | F110: 0 | G110: 0 | H110: 0 | I110: 0 | J110: 0 | K110: 0 | L110: 0 | M110: 0 | N110: 0 | O110: 0 | P110: 0 | Q110: 0 | R110: 0
C111: Vlr Servicio | D111: 0 | E111: 0 | F111: 0 | G111: 0 | H111: 0 | I111: 0 | J111: 0 | K111: 0 | L111: 0 | M111: 0 | N111: 0 | O111: 0 | P111: 0 | Q111: 0 | R111: 0
C112: Vlr Intereses | D112: 0 | E112: 0 | F112: 0 | G112: 0 | H112: 0 | I112: 0 | J112: 0 | K112: 0 | L112: 0 | M112: 0 | N112: 0 | O112: 0 | P112: 0 | Q112: 0 | R112: 0
B113: Componente | C113: Total | D113: 0 | E113: 0 | F113: 0 | G113: 0 | H113: 0 | I113: 0 | J113: 0 | K113: 0 | L113: 0 | M113: 0 | N113: 0 | O113: 0 | P113: 0 | Q113: 0 | R113: 0
C114: Subsidio(-)/Contribucion(+) | D114: 0 | E114: 0 | F114: 0 | G114: 0 | H114: 0 | I114: 0 | J114: 0 | K114: 0 | L114: 0 | M114: 0 | N114: 0 | O114: 0 | P114: 0 | Q114: 0 | R114: 0
B115: Subs/Cont | C115: Total | D115: 0 | E115: 0 | F115: 0 | G115: 0 | H115: 0 | I115: 0 | J115: 0 | K115: 0 | L115: 0 | M115: 0 | N115: 0 | O115: 0 | P115: 0 | Q115: 0 | R115: 0
A116: OCCIDENTE | B116: Total | D116: -945063 | E116: 0 | F116: 0 | G116: 0 | H116: 0 | I116: 0 | J116: 0 | K116: 0 | L116: 0 | M116: 0 | N116: 0 | O116: 0 | P116: 0 | Q116: 0 | R116: 0
A117: Total | D117: -21803648 | E117: 0 | F117: 0 | G117: 0 | H117: 0 | I117: 0 | J117: 0 | K117: 0 | L117: 0 | M117: 0 | N117: 0 | O117: 0 | P117: 0 | Q117: 0 | R117: 0
A180: TOTAL | B180: OPORTUNO | C180: Total | D180: =D117-P117 -> -21803648 | E180: =E101+E107+E113 -> 0 | F180: =F101+F107+F113 -> 0 | G180: =G101+G107+G113 -> 0 | H180: =H101+H107+H113 -> 0 | I180: =I101+I107+I113 -> 0 | J180: =J101+J107+J113 -> 0 | K180: =K101+K107+K113 -> 0 | L180: =L101+L107+L113 -> 0 | ... R180: =R101+R107+R113 -> 0
C181: Subsidio(-)/Contribucion(+) | D181: =D103+D109+D115 -> 0
A183: RECIPROCIDAD | B183: OPORTUNO | C183: Total | D183: =D110-P110 -> 0 | E183: =E107 -> 0 | F183: =F107 -> 0 | G183: =G107 -> 0 | H183: =H107 -> 0 | I183: =I107 -> 0 | J183: =J107 -> 0 | K183: =K107 -> 0 | L183: =L107 -> 0 | ... R183: =R107 -> 0
C184: Subsidio(-)/Contribucion(+) | D184: =D109 -> 0
A186: ENEL | B186: OPORTUNO | C186: Total | D186: =D104-P104 -> -20858585 | E186: =E101 -> 0 | F186: =F101 -> 0 | G186: =G101 -> 0 | H186: =H101 -> 0 | I186: =I101 -> 0 | J186: =J101 -> 0 | K186: =K101 -> 0 | L186: =L101 -> 0 | ... R186: =R101 -> 0
C187: Subsidio(-)/Contribucion(+) | D187: =D103 -> 0
A189: ENERBIT | B189: OPORTUNO | C189: Total | D189: 0 | E189: 0 | F189: 0 | G189: 0 | H189: 0 | I189: 0 | J189: 0 | K189: 0 | L189: 0 | M189: 0 | N189: 0 | O189: 0 | P189: 0 | Q189: 0 | R189: 0
C190: Subsidio(-)/Contribucion(+) | D190: 0
A192: OCCIDENTE | B192: OPORTUNO | C192: Total | D192: =D116-P116 -> -945063 | E192: =E113 -> 0 | F192: =F113 -> 0 | G192: =G113 -> 0 | H192: =H113 -> 0 | I192: =I113 -> 0 | J192: =J113 -> 0 | K192: =K113 -> 0 | L192: =L113 -> 0 | ... R192: =R113 -> 0
C193: Subsidio(-)/Contribucion(+) | D193: =D115 -> 0
A195: CIUDAD LIMPIA-ACUEDUCTO | B195: OPORTUNO | C195: Total | D195: 0 | E195: 0 | F195: 0 | G195: 0 | H195: 0 | I195: 0 | J195: 0 | K195: 0 | L195: 0 | M195: 0 | N195: 0 | O195: 0 | P195: 0 | Q195: 0 | R195: 0
C196: Subsidio(-)/Contribucion(+) | D196: 0
B198: CIUDAD LIMPIA
D199: Total | E199: Componente TDF | F199: Componente TTL | G199: Componente TVIAT | H199: Aprovechamiento | I199: CCSA Prest.Aprov. | J199: Componente TCS | K199: Componente TLU | L199: Componente TBL | M199: Componente TRT | N199: CCSA Prest. No Aprov. | O199: Ajuste Decena | P199: SERVICIO ESPECIALES | Q199: Ajuste Recargo Aseo | R199: Otros
C200: Vlr Servicio | D200: 0 | E200: 0 | F200: 0 | G200: 0 | H200: 0 | I200: 0 | J200: 0 | K200: 0 | L200: 0 | M200: 0 | N200: 0 | O200: 0 | P200: 0 | Q200: 0 | R200: 0
C201: Vlr Intereses | D201: 0 | E201: 0 | F201: 0 | G201: 0 | H201: 0 | I201: 0 | J201: 0 | K201: 0 | L201: 0 | M201: 0 | N201: 0 | O201: 0 | P201: 0 | Q201: 0 | R201: 0
B202: Componente | C202: Total | D202: 0 | E202: 0 | F202: 0 | G202: 0 | H202: 0 | I202: 0 | J202: 0 | K202: 0 | L202: 0 | M202: 0 | N202: 0 | O202: 0 | P202: 0 | Q202: 0 | R202: 0
C203: Subsidio(-)/Contribucion(+) | D203: 0 | E203: 0 | F203: 0 | G203: 0 | H203: 0 | I203: 0 | J203: 0 | K203: 0 | L203: 0 | M203: 0 | N203: 0 | O203: 0 | P203: 0 | Q203: 0 | R203: 0
B204: Subs/Cont | C204: Total | D204: 0 | E204: 0 | F204: 0 | G204: 0 | H204: 0 | I204: 0 | J204: 0 | K204: 0 | L204: 0 | M204: 0 | N204: 0 | O204: 0 | P204: 0 | Q204: 0 | R204: 0
A205: ENEL | B205: Total | D205: -2259272 | E205: 0 | F205: 0 | G205: 0 | H205: 0 | I205: 0 | J205: 0 | K205: 0 | L205: 0 | M205: 0 | N205: 0 | O205: 0 | P205: 0 | Q205: 0 | R205: 0
C206: Vlr Servicio | D206: 0 | E206: 0 | F206: 0 | G206: 0 | H206: 0 | I206: 0 | J206: 0 | K206: 0 | L206: 0 | M206: 0 | N206: 0 | O206: 0 | P206: 0 | Q206: 0 | R206: 0
C207: Vlr Intereses | D207: 0 | E207: 0 | F207: 0 | G207: 0 | H207: 0 | I207: 0 | J207: 0 | K207: 0 | L207: 0 | M207: 0 | N207: 0 | O207: 0 | P207: 0 | Q207: 0 | R207: 0
B208: Componente | C208: Total | D208: 0 | E208: 0 | F208: 0 | G208: 0 | H208: 0 | I208: 0 | J208: 0 | K208: 0 | L208: 0 | M208: 0 | N208: 0 | O208: 0 | P208: 0 | Q208: 0 | R208: 0
C209: Subsidio(-)/Contribucion(+) | D209: 0 | E209: 0 | F209: 0 | G209: 0 | H209: 0 | I209: 0 | J209: 0 | K209: 0 | L209: 0 | M209: 0 | N209: 0 | O209: 0 | P209: 0 | Q209: 0 | R209: 0
B210: Subs/Cont | C210: Total | D210: 0 | E210: 0 | F210: 0 | G210: 0 | H210: 0 | I210: 0 | J210: 0 | K210: 0 | L210: 0 | M210: 0 | N210: 0 | O210: 0 | P210: 0 | Q210: 0 | R210: 0
A211: OCCIDENTE | B211: Total | D211: 0 | E211: 0 | F211: 0 | G211: 0 | H211: 0 | I211: 0 | J211: 0 | K211: 0 | L211: 0 | M211: 0 | N211: 0 | O211: 0 | P211: 0 | Q211: 0 | R211: 0
A212: Total | D212: -2259272 | E212: 0 | F212: 0 | G212: 0 | H212: 0 | I212: 0 | J212: 0 | K212: 0 | L212: 0 | M212: 0 | N212: 0 | O212: 0 | P212: 0 | Q212: 0 | R212: 0
A217: TOTAL | B217: OPORTUNO | C217: Total | D217: =D212-P212 -> -2259272 | E217: =E202+E208 -> 0 | F217: =F202+F208 -> 0 | G217: =G202+G208 -> 0 | H217: =H202+H208 -> 0 | I217: =I202+I208 -> 0 | J217: =J202+J208 -> 0 | K217: =K202+K208 -> 0 | L217: =L202+L208 -> 0 | ... R217: =R202+R208 -> 0
C218: Subsidio(-)/Contribucion(+) | D218: =D204+D210 -> 0
A220: RECIPROCIDAD | B220: OPORTUNO | C220: Total | D220: 0 | E220: 0 | F220: 0 | G220: 0 | H220: 0 | I220: 0 | J220: 0 | K220: 0 | L220: 0 | M220: 0 | N220: 0 | O220: 0 | P220: 0 | Q220: 0 | R220: 0
C221: Subsidio(-)/Contribucion(+) | D221: 0
A223: ENEL | B223: OPORTUNO | C223: Total | D223: =D205-P205 -> -2259272 | E223: =E202 -> 0 | F223: =F202 -> 0 | G223: =G202 -> 0 | H223: =H202 -> 0 | I223: =I202 -> 0 | J223: =J202 -> 0 | K223: =K202 -> 0 | L223: =L202 -> 0 | ... R223: =R202 -> 0
C224: Subsidio(-)/Contribucion(+) | D224: =D204 -> 0
A226: ENERBIT | B226: OPORTUNO | C226: Total | D226: 0 | E226: 0 | F226: 0 | G226: 0 | H226: 0 | I226: 0 | J226: 0 | K226: 0 | L226: 0 | M226: 0 | N226: 0 | O226: 0 | P226: 0 | Q226: 0 | R226: 0
C227: Subsidio(-)/Contribucion(+) | D227: 0
A229: OCCIDENTE | B229: OPORTUNO | C229: Total | D229: =D211-P211 -> 0 | E229: =E208 -> 0 | F229: =F208 -> 0 | G229: =G208 -> 0 | H229: =H208 -> 0 | I229: =I208 -> 0 | J229: =J208 -> 0 | K229: =K208 -> 0 | L229: =L208 -> 0 | ... R229: =R208 -> 0
C230: Subsidio(-)/Contribucion(+) | D230: =D210 -> 0
A232: CIUDAD LIMPIA-ACUEDUCTO | B232: OPORTUNO | C232: Total | D232: 0 | E232: 0 | F232: 0 | G232: 0 | H232: 0 | I232: 0 | J232: 0 | K232: 0 | L232: 0 | M232: 0 | N232: 0 | O232: 0 | P232: 0 | Q232: 0 | R232: 0
C233: Subsidio(-)/Contribucion(+) | D233: 0
B235: BOGOTA LIMPIA
D236: Total | E236: Componente TDF | F236: Componente TTL | G236: Componente TVIAT | H236: Aprovechamiento | I236: CCSA Prest.Aprov. | J236: Componente TCS | K236: Componente TLU | L236: Componente TBL | M236: Componente TRT | N236: CCSA Prest. No Aprov. | O236: Ajuste Decena | P236: SERVICIO ESPECIALES | Q236: Ajuste Recargo Aseo | R236: Otros
C237: Vlr Servicio | D237: 0 | E237: 0 | F237: 0 | G237: 0 | H237: 0 | I237: 0 | J237: 0 | K237: 0 | L237: 0 | M237: 0 | N237: 0 | O237: 0 | P237: 0 | Q237: 0 | R237: 0
C238: Vlr Intereses | D238: 0 | E238: 0 | F238: 0 | G238: 0 | H238: 0 | I238: 0 | J238: 0 | K238: 0 | L238: 0 | M238: 0 | N238: 0 | O238: 0 | P238: 0 | Q238: 0 | R238: 0
B239: Componente | C239: Total | D239: 0 | E239: 0 | F239: 0 | G239: 0 | H239: 0 | I239: 0 | J239: 0 | K239: 0 | L239: 0 | M239: 0 | N239: 0 | O239: 0 | P239: 0 | Q239: 0 | R239: 0
C240: Subsidio(-)/Contribucion(+) | D240: 0 | E240: 0 | F240: 0 | G240: 0 | H240: 0 | I240: 0 | J240: 0 | K240: 0 | L240: 0 | M240: 0 | N240: 0 | O240: 0 | P240: 0 | Q240: 0 | R240: 0
B241: Subs/Cont | C241: Total | D241: 0 | E241: 0 | F241: 0 | G241: 0 | H241: 0 | I241: 0 | J241: 0 | K241: 0 | L241: 0 | M241: 0 | N241: 0 | O241: 0 | P241: 0 | Q241: 0 | R241: 0
...

Sheet SALDOS POR NOTA
B1: PROMOAMBIENTAL
C2: Total | D2: Componente TDF | E2: Componente TTL | F2: Componente TVIAT | G2: Aprovechamiento | H2: CCSA Prest.Aprov. | I2: Especiales | J2: Componente TCS | K2: Componente TLU | L2: Componente TBL | M2: Componente TRT | N2: CCSA Prest. No Aprov. | O2: Deb/Cred
B3: Vlr Servicio | C3: 0 | D3: 0 | E3: 0 | F3: 0 | G3: 0 | H3: 0 | I3: 0 | J3: 0 | K3: 0 | L3: 0 | M3: 0 | N3: 0 | O3: 0
B4: Vlr Intereses | C4: 0 | D4: 0 | E4: 0 | F4: 0 | G4: 0 | H4: 0 | I4: 0 | J4: 0 | K4: 0 | L4: 0 | M4: 0 | N4: 0 | O4: 0
A5: Componente | B5: Total | C5: 0 | D5: 0 | E5: 0 | F5: 0 | G5: 0 | H5: 0 | I5: 0 | J5: 0 | K5: 0 | L5: 0 | M5: 0 | N5: 0 | O5: 0
B6: Subsidio(-)/Contribucion(+) | C6: 0 | D6: 0 | E6: 0 | F6: 0 | G6: 0 | H6: 0 | I6: 0 | J6: 0 | K6: 0 | L6: 0 | M6: 0 | N6: 0 | O6: 0
A7: Subs/Cont | B7: Total | C7: 0 | D7: 0 | E7: 0 | F7: 0 | G7: 0 | H7: 0 | I7: 0 | J7: 0 | K7: 0 | L7: 0 | M7: 0 | N7: 0 | O7: 0
A8: Total | C8: 0 | D8: 0 | E8: 0 | F8: 0 | G8: 0 | H8: 0 | I8: 0 | J8: 0 | K8: 0 | L8: 0 | M8: 0 | N8: 0 | O8: 0
B10: Total | C10: =C8-I8 -> 0 | D10: =D5 -> 0 | E10: =E5 -> 0 | F10: =F5 -> 0 | G10: =G5 -> 0 | H10: =H5 -> 0 | I10: =I5 -> 0 | J10: =J5 -> 0 | K10: =K5 -> 0 | ... P10: =P5 -> 0
B11: Subsidio(-)/Contribucion(+) | C11: =C7 -> 0
B14: LIME
C15: Total | D15: Componente TDF | E15: Componente TTL | F15: Componente TVIAT | G15: Aprovechamiento | H15: CCSA Prest.Aprov. | I15: Especiales | J15: Componente TCS | K15: Componente TLU | L15: Componente TBL | M15: Componente TRT | N15: CCSA Prest. No Aprov. | O15: Deb/Cred
B16: Vlr Servicio | C16: 0 | D16: 0 | E16: 0 | F16: 0 | G16: 0 | H16: 0 | I16: 0 | J16: 0 | K16: 0 | L16: 0 | M16: 0 | N16: 0 | O16: 0
B17: Vlr Intereses | C17: 0 | D17: 0 | E17: 0 | F17: 0 | G17: 0 | H17: 0 | I17: 0 | J17: 0 | K17: 0 | L17: 0 | M17: 0 | N17: 0 | O17: 0
A18: Componente | B18: Total | C18: 0 | D18: 0 | E18: 0 | F18: 0 | G18: 0 | H18: 0 | I18: 0 | J18: 0 | K18: 0 | L18: 0 | M18: 0 | N18: 0 | O18: 0
B19: Subsidio(-)/Contribucion(+) | C19: 0 | D19: 0 | E19: 0 | F19: 0 | G19: 0 | H19: 0 | I19: 0 | J19: 0 | K19: 0 | L19: 0 | M19: 0 | N19: 0 | O19: 0
A20: Subs/Cont | B20: Total | C20: 0 | D20: 0 | E20: 0 | F20: 0 | G20: 0 | H20: 0 | I20: 0 | J20: 0 | K20: 0 | L20: 0 | M20: 0 | N20: 0 | O20: 0
A21: Total | C21: 0 | D21: 0 | E21: 0 | F21: 0 | G21: 0 | H21: 0 | I21: 0 | J21: 0 | K21: 0 | L21: 0 | M21: 0 | N21: 0 | O21: 0
B23: Total | C23: =C21-I21 -> 0 | D23: =D18 -> 0 | E23: =E18 -> 0 | F23: =F18 -> 0 | G23: =G18 -> 0 | H23: =H18 -> 0 | I23: =I18 -> 0 | J23: =J18 -> 0 | K23: =K18 -> 0 | ... P23: =P18 -> 0
B24: Subsidio(-)/Contribucion(+) | C24: =C20 -> 0
B27: CIUDAD LIMPIA
C28: Total | D28: Componente TDF | E28: Componente TTL | F28: Componente TVIAT | G28: Aprovechamiento | H28: CCSA Prest.Aprov. | I28: Especiales | J28: Componente TCS | K28: Componente TLU | L28: Componente TBL | M28: Componente TRT | N28: CCSA Prest. No Aprov. | O28: Deb/Cred
B29: Vlr Servicio | C29: 0 | D29: 0 | E29: 0 | F29: 0 | G29: 0 | H29: 0 | I29: 0 | J29: 0 | K29: 0 | L29: 0 | M29: 0 | N29: 0 | O29: 0
B30: Vlr Intereses | C30: 0 | D30: 0 | E30: 0 | F30: 0 | G30: 0 | H30: 0 | I30: 0 | J30: 0 | K30: 0 | L30: 0 | M30: 0 | N30: 0 | O30: 0
A31: Componente | B31: Total | C31: 0 | D31: 0 | E31: 0 | F31: 0 | G31: 0 | H31: 0 | I31: 0 | J31: 0 | K31: 0 | L31: 0 | M31: 0 | N31: 0 | O31: 0
B32: Subsidio(-)/Contribucion(+) | C32: 0 | D32: 0 | E32: 0 | F32: 0 | G32: 0 | H32: 0 | I32: 0 | J32: 0 | K32: 0 | L32: 0 | M32: 0 | N32: 0 | O32: 0
A33: Subs/Cont | B33: Total | C33: 0 | D33: 0 | E33: 0 | F33: 0 | G33: 0 | H33: 0 | I33: 0 | J33: 0 | K33: 0 | L33: 0 | M33: 0 | N33: 0 | O33: 0
A34: Total | C34: 0 | D34: 0 | E34: 0 | F34: 0 | G34: 0 | H34: 0 | I34: 0 | J34: 0 | K34: 0 | L34: 0 | M34: 0 | N34: 0 | O34: 0
B36: Total | C36: =C34-I34 -> 0 | D36: =D31 -> 0 | E36: =E31 -> 0 | F36: =F31 -> 0 | G36: =G31 -> 0 | H36: =H31 -> 0 | I36: =I31 -> 0 | J36: =J31 -> 0 | K36: =K31 -> 0 | ... P36: =P31 -> 0
B37: Subsidio(-)/Contribucion(+) | C37: =C33 -> 0
B40: BOGOTA LIMPIA
C41: Total | D41: Componente TDF | E41: Componente TTL | F41: Componente TVIAT | G41: Aprovechamiento | H41: CCSA Prest.Aprov. | I41: Especiales | J41: Componente TCS | K41: Componente TLU | L41: Componente TBL | M41: Componente TRT | N41: CCSA Prest. No Aprov. | O41: Deb/Cred
B42: Vlr Servicio | C42: 0 | D42: 0 | E42: 0 | F42: 0 | G42: 0 | H42: 0 | I42: 0 | J42: 0 | K42: 0 | L42: 0 | M42: 0 | N42: 0 | O42: 0
B43: Vlr Intereses | C43: 0 | D43: 0 | E43: 0 | F43: 0 | G43: 0 | H43: 0 | I43: 0 | J43: 0 | K43: 0 | L43: 0 | M43: 0 | N43: 0 | O43: 0
A44: Componente | B44: Total | C44: 0 | D44: 0 | E44: 0 | F44: 0 | G44: 0 | H44: 0 | I44: 0 | J44: 0 | K44: 0 | L44: 0 | M44: 0 | N44: 0 | O44: 0
B45: Subsidio(-)/Contribucion(+) | C45: 0 | D45: 0 | E45: 0 | F45: 0 | G45: 0 | H45: 0 | I45: 0 | J45: 0 | K45: 0 | L45: 0 | M45: 0 | N45: 0 | O45: 0
A46: Subs/Cont | B46: Total | C46: 0 | D46: 0 | E46: 0 | F46: 0 | G46: 0 | H46: 0 | I46: 0 | J46: 0 | K46: 0 | L46: 0 | M46: 0 | N46: 0 | O46: 0
A47: Total | C47: 0 | D47: 0 | E47: 0 | F47: 0 | G47: 0 | H47: 0 | I47: 0 | J47: 0 | K47: 0 | L47: 0 | M47: 0 | N47: 0 | O47: 0
B49: Total | C49: =C47-I47 -> 0 | D49: =D44 -> 0 | E49: =E44 -> 0 | F49: =F44 -> 0 | G49: =G44 -> 0 | H49: =H44 -> 0 | I49: =I44 -> 0 | J49: =J44 -> 0 | K49: =K44 -> 0 | ... P49: =P44 -> 0
B50: Subsidio(-)/Contribucion(+) | C50: =C46 -> 0
B53: AREA LIMPIA
C54: Total | D54: Componente TDF | E54: Componente TTL | F54: Componente TVIAT | G54: Aprovechamiento | H54: CCSA Prest.Aprov. | I54: Especiales | J54: Componente TCS | K54: Componente TLU | L54: Componente TBL | M54: Componente TRT | N54: CCSA Prest. No Aprov. | O54: Deb/Cred
B55: Vlr Servicio | C55: 0 | D55: 0 | E55: 0 | F55: 0 | G55: 0 | H55: 0 | I55: 0 | J55: 0 | K55: 0 | L55: 0 | M55: 0 | N55: 0 | O55: 0
B56: Vlr Intereses | C56: 0 | D56: 0 | E56: 0 | F56: 0 | G56: 0 | H56: 0 | I56: 0 | J56: 0 | K56: 0 | L56: 0 | M56: 0 | N56: 0 | O56: 0
A57: Componente | B57: Total | C57: 0 | D57: 0 | E57: 0 | F57: 0 | G57: 0 | H57: 0 | I57: 0 | J57: 0 | K57: 0 | L57: 0 | M57: 0 | N57: 0 | O57: 0
B58: Subsidio(-)/Contribucion(+) | C58: 0 | D58: 0 | E58: 0 | F58: 0 | G58: 0 | H58: 0 | I58: 0 | J58: 0 | K58: 0 | L58: 0 | M58: 0 | N58: 0 | O58: 0
A59: Subs/Cont | B59: Total | C59: 0 | D59: 0 | E59: 0 | F59: 0 | G59: 0 | H59: 0 | I59: 0 | J59: 0 | K59: 0 | L59: 0 | M59: 0 | N59: 0 | O59: 0
A60: Total | C60: 0 | D60: 0 | E60: 0 | F60: 0 | G60: 0 | H60: 0 | I60: 0 | J60: 0 | K60: 0 | L60: 0 | M60: 0 | N60: 0 | O60: 0
B62: Total | C62: =C60-I60 -> 0 | D62: =D57 -> 0 | E62: =E57 -> 0 | F62: =F57 -> 0 | G62: =G57 -> 0 | H62: =H57 -> 0 | I62: =I57 -> 0 | J62: =J57 -> 0 | K62: =K57 -> 0 | ... P62: =P57 -> 0
B63: Subsidio(-)/Contribucion(+) | C63: =C59 -> 0

Sheet RETRIBUCION NEGATIVA
B1: PROMOAMBIENTAL
C2: Total | D2: Componente TDF | E2: Componente TTL | F2: Componente TVIAT | G2: Aprovechamiento | H2: CCSA Prest.Aprov. | I2: Especiales | J2: Componente TCS | K2: Componente TLU | L2: Componente TBL | M2: Componente TRT | N2: CCSA Prest. No Aprov. | O2: Deb/Cred
B3: Vlr Intereses | C3: 0 | D3: 0 | E3: 0 | F3: 0 | G3: 0 | H3: 0 | I3: 0 | J3: 0 | K3: 0 | L3: 0 | M3: 0 | N3: 0 | O3: 0
B4: Vlr Servicio | C4: 0 | D4: 0 | E4: 0 | F4: 0 | G4: 0 | H4: 0 | I4: 0 | J4: 0 | K4: 0 | L4: 0 | M4: 0 | N4: 0 | O4: 0
A5: Componente | B5: Total | C5: 0 | D5: 0 | E5: 0 | F5: 0 | G5: 0 | H5: 0 | I5: 0 | J5: 0 | K5: 0 | L5: 0 | M5: 0 | N5: 0 | O5: 0
B6: Subsidio(-)/Contribucion(+) | C6: 0 | D6: 0 | E6: 0 | F6: 0 | G6: 0 | H6: 0 | I6: 0 | J6: 0 | K6: 0 | L6: 0 | M6: 0 | N6: 0 | O6: 0
A7: Subs/Cont | B7: Total | C7: 0 | D7: 0 | E7: 0 | F7: 0 | G7: 0 | H7: 0 | I7: 0 | J7: 0 | K7: 0 | L7: 0 | M7: 0 | N7: 0 | O7: 0
A8: Total | C8: 0 | D8: 0 | E8: 0 | F8: 0 | G8: 0 | H8: 0 | I8: 0 | J8: 0 | K8: 0 | L8: 0 | M8: 0 | N8: 0 | O8: 0
B10: Total | C10: =C8-I8 -> 0 | D10: =D5 -> 0 | E10: =E5 -> 0 | F10: =F5 -> 0 | G10: =G5 -> 0 | H10: =H5 -> 0 | I10: =I5 -> 0 | J10: =J5 -> 0 | K10: =K5 -> 0 | ... O10: =O5 -> 0
B11: Subsidio(-)/Contribucion(+) | C11: =C7 -> 0
B14: LIME
C15: Total | D15: Componente TDF | E15: Componente TTL | F15: Componente TVIAT | G15: Aprovechamiento | H15: CCSA Prest.Aprov. | I15: Especiales | J15: Componente TCS | K15: Componente TLU | L15: Componente TBL | M15: Componente TRT | N15: CCSA Prest. No Aprov. | O15: Deb/Cred
B16: Vlr Intereses | C16: 0 | D16: 0 | E16: 0 | F16: 0 | G16: 0 | H16: 0 | I16: 0 | J16: 0 | K16: 0 | L16: 0 | M16: 0 | N16: 0 | O16: 0
B17: Vlr Servicio | C17: 0 | D17: 0 | E17: 0 | F17: 0 | G17: 0 | H17: 0 | I17: 0 | J17: 0 | K17: 0 | L17: 0 | M17: 0 | N17: 0 | O17: 0
A18: Componente | B18: Total | C18: 0 | D18: 0 | E18: 0 | F18: 0 | G18: 0 | H18: 0 | I18: 0 | J18: 0 | K18: 0 | L18: 0 | M18: 0 | N18: 0 | O18: 0
B19: Subsidio(-)/Contribucion(+) | C19: 0 | D19: 0 | E19: 0 | F19: 0 | G19: 0 | H19: 0 | I19: 0 | J19: 0 | K19: 0 | L19: 0 | M19: 0 | N19: 0 | O19: 0
A20: Subs/Cont | B20: Total | C20: 0 | D20: 0 | E20: 0 | F20: 0 | G20: 0 | H20: 0 | I20: 0 | J20: 0 | K20: 0 | L20: 0 | M20: 0 | N20: 0 | O20: 0
A21: Total | C21: 0 | D21: 0 | E21: 0 | F21: 0 | G21: 0 | H21: 0 | I21: 0 | J21: 0 | K21: 0 | L21: 0 | M21: 0 | N21: 0 | O21: 0
B23: Total | C23: =C21-I21 -> 0 | D23: =D18 -> 0 | E23: =E18 -> 0 | F23: =F18 -> 0 | G23: =G18 -> 0 | H23: =H18 -> 0 | I23: =I18 -> 0 | J23: =J18 -> 0 | K23: =K18 -> 0 | ... O23: =O18 -> 0
B24: Subsidio(-)/Contribucion(+) | C24: =C20 -> 0
B27: CIUDAD LIMPIA
C28: Total | D28: Componente TDF | E28: Componente TTL | F28: Componente TVIAT | G28: Aprovechamiento | H28: CCSA Prest.Aprov. | I28: Especiales | J28: Componente TCS | K28: Componente TLU | L28: Componente TBL | M28: Componente TRT | N28: CCSA Prest. No Aprov. | O28: Deb/Cred
B29: Vlr Intereses | C29: 0 | D29: 0 | E29: 0 | F29: 0 | G29: 0 | H29: 0 | I29: 0 | J29: 0 | K29: 0 | L29: 0 | M29: 0 | N29: 0 | O29: 0
B30: Vlr Servicio | C30: 0 | D30: 0 | E30: 0 | F30: 0 | G30: 0 | H30: 0 | I30: 0 | J30: 0 | K30: 0 | L30: 0 | M30: 0 | N30: 0 | O30: 0
A31: Componente | B31: Total | C31: 0 | D31: 0 | E31: 0 | F31: 0 | G31: 0 | H31: 0 | I31: 0 | J31: 0 | K31: 0 | L31: 0 | M31: 0 | N31: 0 | O31: 0
B32: Subsidio(-)/Contribucion(+) | C32: 0 | D32: 0 | E32: 0 | F32: 0 | G32: 0 | H32: 0 | I32: 0 | J32: 0 | K32: 0 | L32: 0 | M32: 0 | N32: 0 | O32: 0
A33: Subs/Cont | B33: Total | C33: 0 | D33: 0 | E33: 0 | F33: 0 | G33: 0 | H33: 0 | I33: 0 | J33: 0 | K33: 0 | L33: 0 | M33: 0 | N33: 0 | O33: 0
A34: Total | C34: 0 | D34: 0 | E34: 0 | F34: 0 | G34: 0 | H34: 0 | I34: 0 | J34: 0 | K34: 0 | L34: 0 | M34: 0 | N34: 0 | O34: 0
B36: Total | C36: =C34-I34 -> 0 | D36: =D31 -> 0 | E36: =E31 -> 0 | F36: =F31 -> 0 | G36: =G31 -> 0 | H36: =H31 -> 0 | I36: =I31 -> 0 | J36: =J31 -> 0 | K36: =K31 -> 0 | ... O36: =O31 -> 0
B37: Subsidio(-)/Contribucion(+) | C37: =C33 -> 0
B40: BOGOTA LIMPIA
C41: Total | D41: Componente TDF | E41: Componente TTL | F41: Componente TVIAT | G41: Aprovechamiento | H41: CCSA Prest.Aprov. | I41: Especiales | J41: Componente TCS | K41: Componente TLU | L41: Componente TBL | M41: Componente TRT | N41: CCSA Prest. No Aprov. | O41: Deb/Cred
B42: Vlr Intereses | C42: 0 | D42: 0 | E42: 0 | F42: 0 | G42: 0 | H42: 0 | I42: 0 | J42: 0 | K42: 0 | L42: 0 | M42: 0 | N42: 0 | O42: 0
B43: Vlr Servicio | C43: 0 | D43: 0 | E43: 0 | F43: 0 | G43: 0 | H43: 0 | I43: 0 | J43: 0 | K43: 0 | L43: 0 | M43: 0 | N43: 0 | O43: 0
A44: Componente | B44: Total | C44: 0 | D44: 0 | E44: 0 | F44: 0 | G44: 0 | H44: 0 | I44: 0 | J44: 0 | K44: 0 | L44: 0 | M44: 0 | N44: 0 | O44: 0
B45: Subsidio(-)/Contribucion(+) | C45: 0 | D45: 0 | E45: 0 | F45: 0 | G45: 0 | H45: 0 | I45: 0 | J45: 0 | K45: 0 | L45: 0 | M45: 0 | N45: 0 | O45: 0
A46: Subs/Cont | B46: Total | C46: 0 | D46: 0 | E46: 0 | F46: 0 | G46: 0 | H46: 0 | I46: 0 | J46: 0 | K46: 0 | L46: 0 | M46: 0 | N46: 0 | O46: 0
A47: Total | C47: 0 | D47: 0 | E47: 0 | F47: 0 | G47: 0 | H47: 0 | I47: 0 | J47: 0 | K47: 0 | L47: 0 | M47: 0 | N47: 0 | O47: 0
B49: Total | C49: =C47-I47 -> 0 | D49: =D44 -> 0 | E49: =E44 -> 0 | F49: =F44 -> 0 | G49: =G44 -> 0 | H49: =H44 -> 0 | I49: =I44 -> 0 | J49: =J44 -> 0 | K49: =K44 -> 0 | ... O49: =O44 -> 0
B50: Subsidio(-)/Contribucion(+) | C50: =C46 -> 0
B53: AREA LIMPIA
C54: Total | D54: Componente TDF | E54: Componente TTL | F54: Componente TVIAT | G54: Aprovechamiento | H54: CCSA Prest.Aprov. | I54: Especiales | J54: Componente TCS | K54: Componente TLU | L54: Componente TBL | M54: Componente TRT | N54: CCSA Prest. No Aprov. | O54: Deb/Cred
B55: Vlr Intereses | C55: 0 | D55: 0 | E55: 0 | F55: 0 | G55: 0 | H55: 0 | I55: 0 | J55: 0 | K55: 0 | L55: 0 | M55: 0 | N55: 0 | O55: 0
B56: Vlr Servicio | C56: 0 | D56: 0 | E56: 0 | F56: 0 | G56: 0 | H56: 0 | I56: 0 | J56: 0 | K56: 0 | L56: 0 | M56: 0 | N56: 0 | O56: 0
A57: Componente | B57: Total | C57: 0 | D57: 0 | E57: 0 | F57: 0 | G57: 0 | H57: 0 | I57: 0 | J57: 0 | K57: 0 | L57: 0 | M57: 0 | N57: 0 | O57: 0
B58: Subsidio(-)/Contribucion(+) | C58: 0 | D58: 0 | E58: 0 | F58: 0 | G58: 0 | H58: 0 | I58: 0 | J58: 0 | K58: 0 | L58: 0 | M58: 0 | N58: 0 | O58: 0
A59: Subs/Cont | B59: Total | C59: 0 | D59: 0 | E59: 0 | F59: 0 | G59: 0 | H59: 0 | I59: 0 | J59: 0 | K59: 0 | L59: 0 | M59: 0 | N59: 0 | O59: 0
A60: Total | C60: 0 | D60: 0 | E60: 0 | F60: 0 | G60: 0 | H60: 0 | I60: 0 | J60: 0 | K60: 0 | L60: 0 | M60: 0 | N60: 0 | O60: 0
B62: Total | C62: =C60-I60 -> 0 | D62: =D57 -> 0 | E62: =E57 -> 0 | F62: =F57 -> 0 | G62: =G57 -> 0 | H62: =H57 -> 0 | I62: =I57 -> 0 | J62: =J57 -> 0 | K62: =K57 -> 0 | ... O62: =O57 -> 0
B63: Subsidio(-)/Contribucion(+) | C63: =C59 -> 0

Sheet AJUSTES - SF-T
F3: PROCERASEO S.A.S. | I3: NIT: 901 153 639 - 0 | M3: Codigo Remuneración: | N3: ='CONSOLIDADO_TOTAL RECAUDO'!N3 -> 2026101 | U3: PROCERASEO S.A.S. | W3: NIT: 901 153 639 - 0 | AA3: Codigo Remuneración: | AC3: =N3 -> 2026101
F4: 3. ESQUEMA FINANCIERO DEL SERVICIO PUBLICO DE ASEO | U4: 3. ESQUEMA FINANCIERO DEL SERVICIO PUBLICO DE ASEO
F5: Resoluciòn UAESP Número 27 de 2018 | U5: Resoluciòn UAESP Número 27 de 2018
C6: Fecha de Proceso: | D6: ='CONSOLIDADO_TOTAL RECAUDO'!D6 -> 46297 | F6: SALDOS A FAVOR POR NOTA | U6: =+F6 -> SALDOS A FAVOR POR NOTA
C7: Hora: | D7: ='CONSOLIDADO_TOTAL RECAUDO'!D7 -> 0.58333333 | F7: Fecha Desde: | H7: ='CONSOLIDADO_TOTAL RECAUDO'!G7 -> 46296 | J7: Feha Hasta: | K7: ='CONSOLIDADO_TOTAL RECAUDO'!K7 -> 46310 | U7: =F7 -> Fecha Desde: | V7: =H7 -> 46296 | X7: =J7 -> Feha Hasta: | Y7: =K7 -> 46310
B8: ASE | C8: Concesionarios | D8: Recaudo Total | E8: Recaudo por disposicion final | F8: Recaudo por tratamiento de lixiviados | G8: Recaudo por Componente VIAT ( Decreto 2412/2018) | H8: Recaudo por aprovechamiento | I8: Recaudo del componente de comercializacion para Aprovechamiento (11,4%) | J8: Balance de subsidio o contribuciones | K8: RECAUDO BASE DE REMUNERACION | L8: Costo de la Interventoría | M8: REMUNERACION FINAL | N8: Conceptos especiales | O8: REMUNERACION FINAL MAS CONCEPTOS ESPECIALES | S8: ASE | T8: Concesionarios | U8: Tarifa de Comercialización del Servicio. ( TCS) | V8: Tarifa de Limpieza Urbana del Servicio. ( TLU) | W8: Tarifa de Barrido y Limpieza del Servicio. ( TBL) | X8: Tarifa de Recolección y Transporte del Servicio. (TRT) | Y8: Recaudo del componente de comercializacion para Aprovechamiento (18,6%) | Z8: Costo de la Interventoría | AA8: Ajuste a la decena | AB8: Conceptos especiales | AC8: Diferencial Balance S / C (Fac vs Rec) | AD8: Balance S / C Con Baase en (Recaudo) | AE8: REMUNERACION FINAL MAS CONCEPTOS ESPECIALES
B9: 1 | C9: PROMOAMBIENTAL DISTRITO S.A.S. ESP. | D9: ='SALDOS POR NOTA'!C10 -> 0 | E9: ='SALDOS POR NOTA'!D10 -> 0 | F9: ='SALDOS POR NOTA'!E10 -> 0 | G9: ='SALDOS POR NOTA'!F10 -> 0 | H9: ='SALDOS POR NOTA'!G10 -> 0 | I9: ='SALDOS POR NOTA'!H10 -> 0 | J9: 0 | K9: =D9-E9-F9-G9-H9-I9-J9 -> 0 | L9: 0 | M9: =K9-L9 -> 0 | N9: ='SALDOS POR NOTA'!I10 -> 0 | O9: =M9+N9 -> 0 | S9: 1 | T9: PROMOAMBIENTAL DISTRITO S.A.S. ESP. | U9: ='SALDOS POR NOTA'!J10 -> 0 | V9: ='SALDOS POR NOTA'!K10 -> 0 | W9: ='SALDOS POR NOTA'!L10 -> 0 | X9: ='SALDOS POR NOTA'!M10 -> 0 | Y9: ='SALDOS POR NOTA'!N10 -> 0 | Z9: =L9*-1 -> 0 | AA9: ='SALDOS POR NOTA'!O10 -> 0 | AB9: =N9 -> 0 | AC9: =-J9+AD9 -> 0 | AD9: ='SALDOS POR NOTA'!C11 -> 0 | AE9: =SUM(U9:AC9) -> 0 | AF9: =(AE9-O9) -> 0 | AG9: =AF9=0 -> TRUE
B10: 2 | C10: LIMPIEZA METROPOLITANA S.A. ESP. | D10: ='SALDOS POR NOTA'!C23 -> 0 | E10: ='SALDOS POR NOTA'!D23 -> 0 | F10: ='SALDOS POR NOTA'!E23 -> 0 | G10: ='SALDOS POR NOTA'!F23 -> 0 | H10: ='SALDOS POR NOTA'!G23 -> 0 | I10: ='SALDOS POR NOTA'!H23 -> 0 | J10: 0 | K10: =D10-E10-F10-G10-H10-I10-J10 -> 0 | L10: 0 | M10: =K10-L10 -> 0 | N10: ='SALDOS POR NOTA'!I23 -> 0 | O10: =M10+N10 -> 0 | S10: 2 | T10: LIMPIEZA METROPOLITANA S.A. ESP. | U10: ='SALDOS POR NOTA'!J23 -> 0 | V10: ='SALDOS POR NOTA'!K23 -> 0 | W10: ='SALDOS POR NOTA'!L23 -> 0 | X10: ='SALDOS POR NOTA'!M23 -> 0 | Y10: ='SALDOS POR NOTA'!N23 -> 0 | Z10: =L10*-1 -> 0 | AA10: ='SALDOS POR NOTA'!O23 -> 0 | AB10: =N10 -> 0 | AC10: =-J10+AD10 -> 0 | AD10: ='SALDOS POR NOTA'!C24 -> 0 | AE10: =SUM(U10:AC10) -> 0 | AF10: =(AE10-O10) -> 0 | AG10: =AF10=0 -> TRUE
B11: 3 | C11: CIUDAD LIMPIA BOGOTA S.A. ESP. | D11: ='SALDOS POR NOTA'!C36 -> 0 | E11: ='SALDOS POR NOTA'!D36 -> 0 | F11: ='SALDOS POR NOTA'!E36 -> 0 | G11: ='SALDOS POR NOTA'!F36 -> 0 | H11: ='SALDOS POR NOTA'!G36 -> 0 | I11: ='SALDOS POR NOTA'!H36 -> 0 | J11: 0 | K11: =D11-E11-F11-G11-H11-I11-J11 -> 0 | L11: 0 | M11: =K11-L11 -> 0 | N11: ='SALDOS POR NOTA'!I36 -> 0 | O11: =M11+N11 -> 0 | S11: 3 | T11: CIUDAD LIMPIA BOGOTA S.A. ESP. | U11: ='SALDOS POR NOTA'!J36 -> 0 | V11: ='SALDOS POR NOTA'!K36 -> 0 | W11: ='SALDOS POR NOTA'!L36 -> 0 | X11: ='SALDOS POR NOTA'!M36 -> 0 | Y11: ='SALDOS POR NOTA'!N36 -> 0 | Z11: =L11*-1 -> 0 | AA11: ='SALDOS POR NOTA'!O36 -> 0 | AB11: =N11 -> 0 | AC11: =-J11+AD11 -> 0 | AD11: ='SALDOS POR NOTA'!C37 -> 0 | AE11: =SUM(U11:AC11) -> 0 | AF11: =(AE11-O11) -> 0 | AG11: =AF11=0 -> TRUE
B12: 4 | C12: BOGOTA LIMPIA S.A.S. ESP. | D12: ='SALDOS POR NOTA'!C49 -> 0 | E12: ='SALDOS POR NOTA'!D49 -> 0 | F12: ='SALDOS POR NOTA'!E49 -> 0 | G12: ='SALDOS POR NOTA'!F49 -> 0 | H12: ='SALDOS POR NOTA'!G49 -> 0 | I12: ='SALDOS POR NOTA'!H49 -> 0 | J12: 0 | K12: =D12-E12-F12-G12-H12-I12-J12 -> 0 | L12: 0 | M12: =K12-L12 -> 0 | N12: ='SALDOS POR NOTA'!I49 -> 0 | O12: =M12+N12 -> 0 | S12: 4 | T12: BOGOTA LIMPIA S.A.S. ESP. | U12: ='SALDOS POR NOTA'!J49 -> 0 | V12: ='SALDOS POR NOTA'!K49 -> 0 | W12: ='SALDOS POR NOTA'!L49 -> 0 | X12: ='SALDOS POR NOTA'!M49 -> 0 | Y12: ='SALDOS POR NOTA'!N49 -> 0 | Z12: =L12*-1 -> 0 | AA12: ='SALDOS POR NOTA'!O49 -> 0 | AB12: =N12 -> 0 | AC12: =-J12+AD12 -> 0 | AD12: ='SALDOS POR NOTA'!C50 -> 0 | AE12: =SUM(U12:AC12) -> 0 | AF12: =(AE12-O12) -> 0 | AG12: =AF12=0 -> TRUE
B13: 5 | C13: AREA LIMPIA DISTRITO CAPITAL S.A.S. ESP. | D13: ='SALDOS POR NOTA'!C62 -> 0 | E13: ='SALDOS POR NOTA'!D62 -> 0 | F13: ='SALDOS POR NOTA'!E62 -> 0 | G13: ='SALDOS POR NOTA'!F62 -> 0 | H13: ='SALDOS POR NOTA'!G62 -> 0 | I13: ='SALDOS POR NOTA'!H62 -> 0 | J13: 0 | K13: =D13-E13-F13-G13-H13-I13-J13 -> 0 | L13: 0 | M13: =K13-L13 -> 0 | N13: ='SALDOS POR NOTA'!I62 -> 0 | O13: =M13+N13 -> 0 | S13: 5 | T13: AREA LIMPIA DISTRITO CAPITAL S.A.S. ESP. | U13: ='SALDOS POR NOTA'!J62 -> 0 | V13: ='SALDOS POR NOTA'!K62 -> 0 | W13: ='SALDOS POR NOTA'!L62 -> 0 | X13: ='SALDOS POR NOTA'!M62 -> 0 | Y13: ='SALDOS POR NOTA'!N62 -> 0 | Z13: =L13*-1 -> 0 | AA13: ='SALDOS POR NOTA'!O62 -> 0 | AB13: =N13 -> 0 | AC13: =-J13+AD13 -> 0 | AD13: ='SALDOS POR NOTA'!C63 -> 0 | AE13: =SUM(U13:AC13) -> 0 | AF13: =(AE13-O13) -> 0 | AG13: =AF13=0 -> TRUE
C14: TOTAL | D14: =SUM(D9:D13) -> 0 | E14: =SUM(E9:E13) -> 0 | F14: =SUM(F9:F13) -> 0 | G14: =SUM(G9:G13) -> 0 | H14: =SUM(H9:H13) -> 0 | I14: =SUM(I9:I13) -> 0 | J14: =SUM(J9:J13) -> 0 | K14: =SUM(K9:K13) -> 0 | ... O14: =SUM(O9:O13) -> 0 | T14: TOTAL | U14: =SUM(U9:U13) -> 0 | V14: =SUM(V9:V13) -> 0 | W14: =SUM(W9:W13) -> 0 | X14: =SUM(X9:X13) -> 0 | Y14: =SUM(Y9:Y13) -> 0 | Z14: =SUM(Z9:Z13) -> 0 | AA14: =SUM(AA9:AA13) -> 0 | AB14: =SUM(AB9:AB13) -> 0 | ... AF14: =SUM(AF9:AF13) -> 0 | AG14: =AF14=0 -> TRUE
Y16: =SUM(U14:Y14) -> 0
F18: Firma autorizada
F22: PROCERASEO S.A.S. | I22: NIT: 901 153 639 - 0 | M22: Codigo Remuneración: | N22: =N3 -> 2026101 | U22: PROCERASEO S.A.S. | W22: NIT: 901 153 639 - 0 | AA22: Codigo Remuneración: | AC22: =N22 -> 2026101
F23: 3. ESQUEMA FINANCIERO DEL SERVICIO PUBLICO DE ASEO | U23: 3. ESQUEMA FINANCIERO DEL SERVICIO PUBLICO DE ASEO
F24: Resoluciòn UAESP Número 27 de 2018 | U24: Resoluciòn UAESP Número 27 de 2018
C25: Fecha de Proceso: | D25: =D6 -> 46297 | F25: RETRIBUCION NEGATIVA | U25: =+F25 -> RETRIBUCION NEGATIVA
C26: Hora: | D26: =D7 -> 0.58333333 | F26: Fecha Desde: | H26: =H7 -> 46296 | J26: Feha Hasta: | K26: =K7 -> 46310 | U26: =F26 -> Fecha Desde: | V26: =H26 -> 46296 | X26: =J26 -> Feha Hasta: | Y26: =K26 -> 46310
B27: ASE | C27: Concesionarios | D27: Recaudo Total | E27: Recaudo por disposicion final | F27: Recaudo por tratamiento de lixiviados | G27: Recaudo por Componente VIAT ( Decreto 2412/2018) | H27: Recaudo por aprovechamiento | I27: Recaudo del componente de comercializacion para Aprovechamiento (11,4%) | J27: Balance de subsidio o contribuciones | K27: RECAUDO BASE DE REMUNERACION | L27: Costo de la Interventoría | M27: REMUNERACION FINAL | N27: Conceptos especiales | O27: REMUNERACION FINAL MAS CONCEPTOS ESPECIALES | S27: ASE | T27: Concesionarios | U27: Tarifa de Comercialización del Servicio. ( TCS) | V27: Tarifa de Limpieza Urbana del Servicio. ( TLU) | W27: Tarifa de Barrido y Limpieza del Servicio. ( TBL) | X27: Tarifa de Recolección y Transporte del Servicio. (TRT) | Y27: Recaudo del componente de comercializacion para Aprovechamiento (18,6%) | Z27: Costo de la Interventoría | AA27: Ajuste a la decena | AB27: Conceptos especiales | AC27: Diferencial Balance S / C (Fac vs Rec) | AD27: Balance S / C Con Baase en (Recaudo) | AE27: REMUNERACION FINAL MAS CONCEPTOS ESPECIALES
B28: 1 | C28: PROMOAMBIENTAL DISTRITO S.A.S. ESP. | D28: ='RETRIBUCION NEGATIVA'!C10 -> 0 | E28: ='RETRIBUCION NEGATIVA'!D10 -> 0 | F28: ='RETRIBUCION NEGATIVA'!E10 -> 0 | G28: ='RETRIBUCION NEGATIVA'!F10 -> 0 | H28: ='RETRIBUCION NEGATIVA'!G10 -> 0 | I28: ='RETRIBUCION NEGATIVA'!H10 -> 0 | J28: 0 | K28: =D28-E28-F28-H28-I28-J28-G28 -> 0 | L28: 0 | M28: =K28-L28 -> 0 | N28: ='RETRIBUCION NEGATIVA'!I10 -> 0 | O28: =M28+N28 -> 0 | S28: 1 | T28: PROMOAMBIENTAL DISTRITO S.A.S. ESP. | U28: ='RETRIBUCION NEGATIVA'!J10 -> 0 | V28: ='RETRIBUCION NEGATIVA'!K10 -> 0 | W28: ='RETRIBUCION NEGATIVA'!L10 -> 0 | X28: ='RETRIBUCION NEGATIVA'!M10 -> 0 | Y28: ='RETRIBUCION NEGATIVA'!N10 -> 0 | Z28: =L28*-1 -> 0 | AA28: ='RETRIBUCION NEGATIVA'!O10 -> 0 | AB28: =N28 -> 0 | AC28: =-J28+AD28 -> 0 | AD28: ='RETRIBUCION NEGATIVA'!C11 -> 0 | AE28: =SUM(U28:AC28) -> 0 | AF28: =(AE28-O28) -> 0 | AG28: =AF28=0 -> TRUE
B29: 2 | C29: LIMPIEZA METROPOLITANA S.A. ESP. | D29: ='RETRIBUCION NEGATIVA'!C23 -> 0 | E29: ='RETRIBUCION NEGATIVA'!D23 -> 0 | F29: ='RETRIBUCION NEGATIVA'!E23 -> 0 | G29: ='RETRIBUCION NEGATIVA'!F23 -> 0 | H29: ='RETRIBUCION NEGATIVA'!G23 -> 0 | I29: ='RETRIBUCION NEGATIVA'!H23 -> 0 | J29: 0 | K29: =D29-E29-F29-H29-I29-J29-G29 -> 0 | L29: 0 | M29: =K29-L29 -> 0 | N29: ='RETRIBUCION NEGATIVA'!I23 -> 0 | O29: =M29+N29 -> 0 | S29: 2 | T29: LIMPIEZA METROPOLITANA S.A. ESP. | U29: ='RETRIBUCION NEGATIVA'!J23 -> 0 | V29: ='RETRIBUCION NEGATIVA'!K23 -> 0 | W29: ='RETRIBUCION NEGATIVA'!L23 -> 0 | X29: ='RETRIBUCION NEGATIVA'!M23 -> 0 | Y29: ='RETRIBUCION NEGATIVA'!N23 -> 0 | Z29: =L29*-1 -> 0 | AA29: ='RETRIBUCION NEGATIVA'!O23 -> 0 | AB29: =N29 -> 0 | AC29: =-J29+AD29 -> 0 | AD29: ='RETRIBUCION NEGATIVA'!C24 -> 0 | AE29: =SUM(U29:AC29) -> 0 | AF29: =(AE29-O29) -> 0 | AG29: =AF29=0 -> TRUE
B30: 3 | C30: CIUDAD LIMPIA BOGOTA S.A. ESP. | D30: ='RETRIBUCION NEGATIVA'!C36 -> 0 | E30: ='RETRIBUCION NEGATIVA'!D36 -> 0 | F30: ='RETRIBUCION NEGATIVA'!E36 -> 0 | G30: ='RETRIBUCION NEGATIVA'!F36 -> 0 | H30: ='RETRIBUCION NEGATIVA'!G36 -> 0 | I30: ='RETRIBUCION NEGATIVA'!H36 -> 0 | J30: 0 | K30: =D30-E30-F30-H30-I30-J30-G30 -> 0 | L30: 0 | M30: =K30-L30 -> 0 | N30: ='RETRIBUCION NEGATIVA'!I36 -> 0 | O30: =M30+N30 -> 0 | S30: 3 | T30: CIUDAD LIMPIA BOGOTA S.A. ESP. | U30: ='RETRIBUCION NEGATIVA'!J36 -> 0 | V30: ='RETRIBUCION NEGATIVA'!K36 -> 0 | W30: ='RETRIBUCION NEGATIVA'!L36 -> 0 | X30: ='RETRIBUCION NEGATIVA'!M36 -> 0 | Y30: ='RETRIBUCION NEGATIVA'!N36 -> 0 | Z30: =L30*-1 -> 0 | AA30: ='RETRIBUCION NEGATIVA'!O36 -> 0 | AB30: =N30 -> 0 | AC30: =-J30+AD30 -> 0 | AD30: ='RETRIBUCION NEGATIVA'!C37 -> 0 | AE30: =SUM(U30:AC30) -> 0 | AF30: =(AE30-O30) -> 0 | AG30: =AF30=0 -> TRUE
B31: 4 | C31: BOGOTA LIMPIA S.A.S. ESP. | D31: ='RETRIBUCION NEGATIVA'!C49 -> 0 | E31: ='RETRIBUCION NEGATIVA'!D49 -> 0 | F31: ='RETRIBUCION NEGATIVA'!E49 -> 0 | G31: ='RETRIBUCION NEGATIVA'!F49 -> 0 | H31: ='RETRIBUCION NEGATIVA'!G49 -> 0 | I31: ='RETRIBUCION NEGATIVA'!H49 -> 0 | J31: 0 | K31: =D31-E31-F31-H31-I31-J31-G31 -> 0 | L31: 0 | M31: =K31-L31 -> 0 | N31: ='RETRIBUCION NEGATIVA'!I49 -> 0 | O31: =M31+N31 -> 0 | S31: 4 | T31: BOGOTA LIMPIA S.A.S. ESP. | U31: ='RETRIBUCION NEGATIVA'!J49 -> 0 | V31: ='RETRIBUCION NEGATIVA'!K49 -> 0 | W31: ='RETRIBUCION NEGATIVA'!L49 -> 0 | X31: ='RETRIBUCION NEGATIVA'!M49 -> 0 | Y31: ='RETRIBUCION NEGATIVA'!N49 -> 0 | Z31: =L31*-1 -> 0 | AA31: ='RETRIBUCION NEGATIVA'!O49 -> 0 | AB31: =N31 -> 0 | AC31: =-J31+AD31 -> 0 | AD31: ='RETRIBUCION NEGATIVA'!C50 -> 0 | AE31: =SUM(U31:AC31) -> 0 | AF31: =(AE31-O31) -> 0 | AG31: =AF31=0 -> TRUE
B32: 5 | C32: AREA LIMPIA DISTRITO CAPITAL S.A.S. ESP. | D32: ='RETRIBUCION NEGATIVA'!C62 -> 0 | E32: ='RETRIBUCION NEGATIVA'!D62 -> 0 | F32: ='RETRIBUCION NEGATIVA'!E62 -> 0 | G32: ='RETRIBUCION NEGATIVA'!F62 -> 0 | H32: ='RETRIBUCION NEGATIVA'!G62 -> 0 | I32: ='RETRIBUCION NEGATIVA'!H62 -> 0 | J32: 0 | K32: =D32-E32-F32-H32-I32-J32-G32 -> 0 | L32: 0 | M32: =K32-L32 -> 0 | N32: ='RETRIBUCION NEGATIVA'!I62 -> 0 | O32: =M32+N32 -> 0 | S32: 5 | T32: AREA LIMPIA DISTRITO CAPITAL S.A.S. ESP. | U32: ='RETRIBUCION NEGATIVA'!J62 -> 0 | V32: ='RETRIBUCION NEGATIVA'!K62 -> 0 | W32: ='RETRIBUCION NEGATIVA'!L62 -> 0 | X32: ='RETRIBUCION NEGATIVA'!M62 -> 0 | Y32: ='RETRIBUCION NEGATIVA'!N62 -> 0 | Z32: =L32*-1 -> 0 | AA32: ='RETRIBUCION NEGATIVA'!O62 -> 0 | AB32: =N32 -> 0 | AC32: =-J32+AD32 -> 0 | AD32: ='RETRIBUCION NEGATIVA'!C63 -> 0 | AE32: =SUM(U32:AC32) -> 0 | AF32: =(AE32-O32) -> 0 | AG32: =AF32=0 -> TRUE
C33: TOTAL | D33: =SUM(D28:D32) -> 0 | E33: =SUM(E28:E32) -> 0 | F33: =SUM(F28:F32) -> 0 | G33: =SUM(G28:G32) -> 0 | H33: =SUM(H28:H32) -> 0 | I33: =SUM(I28:I32) -> 0 | J33: =SUM(J28:J32) -> 0 | K33: =SUM(K28:K32) -> 0 | ... O33: =SUM(O28:O32) -> 0 | T33: TOTAL | U33: =SUM(U28:U32) -> 0 | V33: =SUM(V28:V32) -> 0 | W33: =SUM(W28:W32) -> 0 | X33: =SUM(X28:X32) -> 0 | Y33: =SUM(Y28:Y32) -> 0 | Z33: =SUM(Z28:Z32) -> 0 | AA33: =SUM(AA28:AA32) -> 0 | AB33: =SUM(AB28:AB32) -> 0 | ... AF33: =SUM(AF28:AF32) -> 0 | AG33: =AF33=0 -> TRUE
J35: VALIDADOR DE POSTIVIOS EN REMUNERACION NEGATIVA | M35: =IF(MAX(D28:O32,U28:AE32)>0.9,"ERROR",TRUE) -> TRUE | Y35: =SUM(U33:Y33) -> 0
F37: Firma autorizada
F41: PROCERASEO S.A.S. | I41: NIT: 901 153 639 - 0 | M41: Codigo Remuneración: | N41: =N3 -> 2026101 | U41: PROCERASEO S.A.S. | W41: NIT: 901 153 639 - 0 | AA41: Codigo Remuneración: | AC41: =N41 -> 2026101
F42: 3. ESQUEMA FINANCIERO DEL SERVICIO PUBLICO DE ASEO | U42: 3. ESQUEMA FINANCIERO DEL SERVICIO PUBLICO DE ASEO
F43: Resoluciòn UAESP Número 27 de 2018 | U43: Resoluciòn UAESP Número 27 de 2018
C44: Fecha de Proceso: | D44: =D6 -> 46297 | F44: CONSOLIDADO SALDOS A FAVOR | U44: =+F44 -> CONSOLIDADO SALDOS A FAVOR
C45: Hora: | D45: =D7 -> 0.58333333 | F45: Fecha Desde: | H45: =H7 -> 46296 | J45: Feha Hasta: | K45: =K7 -> 46310 | U45: =F45 -> Fecha Desde: | V45: =H45 -> 46296 | X45: =J45 -> Feha Hasta: | Y45: =K45 -> 46310
B46: ASE | C46: Concesionarios | D46: Recaudo Total | E46: Recaudo por disposicion final | F46: Recaudo por tratamiento de lixiviados | G46: Recaudo por Componente VIAT ( Decreto 2412/2018) | H46: Recaudo por aprovechamiento | I46: Recaudo del componente de comercializacion para Aprovechamiento (11,4%) | J46: Balance de subsidio o contribuciones | K46: RECAUDO BASE DE REMUNERACION | L46: Costo de la Interventoría | M46: REMUNERACION FINAL | N46: Conceptos especiales | O46: REMUNERACION FINAL MAS CONCEPTOS ESPECIALES | S46: ASE | T46: Concesionarios | U46: Tarifa de Comercialización del Servicio. ( TCS) | V46: Tarifa de Limpieza Urbana del Servicio. ( TLU) | W46: Tarifa de Barrido y Limpieza del Servicio. ( TBL) | X46: Tarifa de Recolección y Transporte del Servicio. (TRT) | Y46: Recaudo del componente de comercializacion para Aprovechamiento (18,6%) | Z46: Costo de la Interventoría | AA46: Ajuste a la decena | AB46: Conceptos especiales | AC46: Diferencial Balance S / C (Fac vs Rec) | AD46: Balance S / C Con Baase en (Recaudo) | AE46: REMUNERACION FINAL MAS CONCEPTOS ESPECIALES
B47: 1 | C47: PROMOAMBIENTAL DISTRITO S.A.S. ESP. | D47: =D9+D28 -> 0 | E47: =E9+E28 -> 0 | F47: =F9+F28 -> 0 | G47: =G9+G28 -> 0 | H47: =H9+H28 -> 0 | I47: =I9+I28 -> 0 | J47: =J9+J28 -> 0 | K47: =D47-E47-F47-G47-H47-I47-J47 -> 0 | L47: 0 | M47: =K47-L47 -> 0 | N47: =N9+N28 -> 0 | O47: =M47+N47 -> 0 | S47: 1 | T47: PROMOAMBIENTAL DISTRITO S.A.S. ESP. | U47: =U9+U28 -> 0 | V47: =V9+V28 -> 0 | W47: =W9+W28 -> 0 | X47: =X9+X28 -> 0 | Y47: =Y9+Y28 -> 0 | Z47: =-L47 -> 0 | AA47: =AA9+AA28 -> 0 | AB47: =AB9+AB28 -> 0 | AC47: =AC9+AC28 -> 0 | AD47: =AD9+AD28 -> 0 | AE47: =SUM(U47:AC47) -> 0 | AF47: =(AE47-O47) -> 0 | AG47: =AF47=0 -> TRUE
B48: 2 | C48: LIMPIEZA METROPOLITANA S.A. ESP. | D48: =D10+D29 -> 0 | E48: =E10+E29 -> 0 | F48: =F10+F29 -> 0 | G48: =G10+G29 -> 0 | H48: =H10+H29 -> 0 | I48: =I10+I29 -> 0 | J48: =J10+J29 -> 0 | K48: =D48-E48-F48-G48-H48-I48-J48 -> 0 | L48: 0 | M48: =K48-L48 -> 0 | N48: =N10+N29 -> 0 | O48: =M48+N48 -> 0 | S48: 2 | T48: LIMPIEZA METROPOLITANA S.A. ESP. | U48: =U10+U29 -> 0 | V48: =V10+V29 -> 0 | W48: =W10+W29 -> 0 | X48: =X10+X29 -> 0 | Y48: =Y10+Y29 -> 0 | Z48: =-L48 -> 0 | AA48: =AA10+AA29 -> 0 | AB48: =AB10+AB29 -> 0 | AC48: =AC10+AC29 -> 0 | AD48: =AD10+AD29 -> 0 | AE48: =SUM(U48:AC48) -> 0 | AF48: =(AE48-O48) -> 0 | AG48: =AF48=0 -> TRUE
B49: 3 | C49: CIUDAD LIMPIA BOGOTA S.A. ESP. | D49: =D11+D30 -> 0 | E49: =E11+E30 -> 0 | F49: =F11+F30 -> 0 | G49: =G11+G30 -> 0 | H49: =H11+H30 -> 0 | I49: =I11+I30 -> 0 | J49: =J11+J30 -> 0 | K49: =D49-E49-F49-G49-H49-I49-J49 -> 0 | L49: 0 | M49: =K49-L49 -> 0 | N49: =N11+N30 -> 0 | O49: =M49+N49 -> 0 | S49: 3 | T49: CIUDAD LIMPIA BOGOTA S.A. ESP. | U49: =U11+U30 -> 0 | V49: =V11+V30 -> 0 | W49: =W11+W30 -> 0 | X49: =X11+X30 -> 0 | Y49: =Y11+Y30 -> 0 | Z49: =-L49 -> 0 | AA49: =AA11+AA30 -> 0 | AB49: =AB11+AB30 -> 0 | AC49: =AC11+AC30 -> 0 | AD49: =AD11+AD30 -> 0 | AE49: =SUM(U49:AC49) -> 0 | AF49: =(AE49-O49) -> 0 | AG49: =AF49=0 -> TRUE
B50: 4 | C50: BOGOTA LIMPIA S.A.S. ESP. | D50: =D12+D31 -> 0 | E50: =E12+E31 -> 0 | F50: =F12+F31 -> 0 | G50: =G12+G31 -> 0 | H50: =H12+H31 -> 0 | I50: =I12+I31 -> 0 | J50: =J12+J31 -> 0 | K50: =D50-E50-F50-G50-H50-I50-J50 -> 0 | L50: 0 | M50: =K50-L50 -> 0 | N50: =N12+N31 -> 0 | O50: =M50+N50 -> 0 | S50: 4 | T50: BOGOTA LIMPIA S.A.S. ESP. | U50: =U12+U31 -> 0 | V50: =V12+V31 -> 0 | W50: =W12+W31 -> 0 | X50: =X12+X31 -> 0 | Y50: =Y12+Y31 -> 0 | Z50: =-L50 -> 0 | AA50: =AA12+AA31 -> 0 | AB50: =AB12+AB31 -> 0 | AC50: =AC12+AC31 -> 0 | AD50: =AD12+AD31 -> 0 | AE50: =SUM(U50:AC50) -> 0 | AF50: =(AE50-O50) -> 0 | AG50: =AF50=0 -> TRUE
B51: 5 | C51: AREA LIMPIA DISTRITO CAPITAL S.A.S. ESP. | D51: =D13+D32 -> 0 | E51: =E13+E32 -> 0 | F51: =F13+F32 -> 0 | G51: =G13+G32 -> 0 | H51: =H13+H32 -> 0 | I51: =I13+I32 -> 0 | J51: =J13+J32 -> 0 | K51: =D51-E51-F51-G51-H51-I51-J51 -> 0 | L51: 0 | M51: =K51-L51 -> 0 | N51: =N13+N32 -> 0 | O51: =M51+N51 -> 0 | S51: 5 | T51: AREA LIMPIA DISTRITO CAPITAL S.A.S. ESP. | U51: =U13+U32 -> 0 | V51: =V13+V32 -> 0 | W51: =W13+W32 -> 0 | X51: =X13+X32 -> 0 | Y51: =Y13+Y32 -> 0 | Z51: =-L51 -> 0 | AA51: =AA13+AA32 -> 0 | AB51: =AB13+AB32 -> 0 | AC51: =AC13+AC32 -> 0 | AD51: =AD13+AD32 -> 0 | AE51: =SUM(U51:AC51) -> 0 | AF51: =(AE51-O51) -> 0 | AG51: =AF51=0 -> TRUE
C52: TOTAL | D52: =SUM(D47:D51) -> 0 | E52: =SUM(E47:E51) -> 0 | F52: =SUM(F47:F51) -> 0 | G52: =SUM(G47:G51) -> 0 | H52: =SUM(H47:H51) -> 0 | I52: =SUM(I47:I51) -> 0 | J52: =SUM(J47:J51) -> 0 | K52: =SUM(K47:K51) -> 0 | ... O52: =SUM(O47:O51) -> 0 | T52: TOTAL | U52: =SUM(U47:U51) -> 0 | V52: =SUM(V47:V51) -> 0 | W52: =SUM(W47:W51) -> 0 | X52: =SUM(X47:X51) -> 0 | Y52: =SUM(Y47:Y51) -> 0 | Z52: =SUM(Z47:Z51) -> 0 | AA52: =SUM(AA47:AA51) -> 0 | AB52: =SUM(AB47:AB51) -> 0 | ... AF52: =SUM(AF47:AF51) -> 0 | AG52: =AF52=0 -> TRUE
Y54: =SUM(U52:Y52) -> 0
F56: Firma autorizada

Sheet INTERVENTORIA
F2: 2026 01 2 | G2: 2026 02 1 | H2: 2026 02 2 | I2: 2026 03 1 | J2: 2026 03 2 | K2: 2026 04 1 | L2: 2026 04 2 | M2: 2026 05 1 | N2: 2026 05 2 | O2: 2026 06 1 | P2: 2026 06 2 | Q2: 2026 07 1
B3: VALOR MES | C3: ASE | D3: Concesionarios | E3: % | F3: MITAD 1 // ENERO -26 | G3: MITAD 2 // ENERO -26 | H3: MITAD 1 // FEBRERO -26 | I3: MITAD 2 // FEBRERO -26 | J3: MITAD 1 // MARZO -26 | K3: MITAD 2 // MARZO -26 | L3: MITAD 1 // ABRIL -26 | M3: MITAD 2 // ABRIL -26 | N3: MITAD 1 // MAYO -26 | O3: MITAD 2 // MAYO -26 | P3: MITAD 1 // JUNIO -26 | Q3: MITAD 2 // JUNIO -26
B4: 378371975 | C4: 1 | D4: PROMOAMBIENTAL DISTRITO S.A.S. ESP. | E4: 0.22 | F4: 189185988 | G4: 189185987 | H4: 189185988 | I4: 189185987 | J4: 189185988 | K4: 189185987 | L4: 189185988 | M4: 189185987 | N4: 189185988 | O4: 189185987 | P4: 189185988 | Q4: 189185987
B5: 533160511 | C5: 2 | D5: LIMPIEZA METROPOLITANA S.A. ESP. | E5: 0.31 | F5: 266580256 | G5: 266580255 | H5: 266580256 | I5: 266580255 | J5: 266580256 | K5: 266580255 | L5: 266580256 | M5: 266580255 | N5: 266580256 | O5: 266580255 | P5: 266580256 | Q5: 266580255
B6: 309577071 | C6: 3 | D6: CIUDAD LIMPIA BOGOTA S.A. ESP. | E6: 0.18 | F6: 154788536 | G6: 154788535 | H6: 154788536 | I6: 154788535 | J6: 154788536 | K6: 154788535 | L6: 154788536 | M6: 154788535 | N6: 154788536 | O6: 154788535 | P6: 154788536 | Q6: 154788535
B7: 240782166 | C7: 4 | D7: BOGOTA LIMPIA S.A.S. ESP. | E7: 0.14 | F7: 120391083 | G7: 120391083 | H7: 120391083 | I7: 120391083 | J7: 120391083 | K7: 120391083 | L7: 120391083 | M7: 120391083 | N7: 120391083 | O7: 120391083 | P7: 120391083 | Q7: 120391083
B8: 257980891 | C8: 5 | D8: AREA LIMPIA DISTRITO CAPITAL S.A.S. ESP. | E8: 0.15 | F8: 128990446 | G8: 128990445 | H8: 128990446 | I8: 128990445 | J8: 128990446 | K8: 128990445 | L8: 128990446 | M8: 128990445 | N8: 128990446 | O8: 128990445 | P8: 128990446 | Q8: 128990445
B9: 1719872614 | D9: TOTAL | E9: 1 | F9: 859936309 | G9: 859936305 | H9: 859936309 | I9: 859936305 | J9: 859936309 | K9: 859936305 | L9: 859936309 | M9: 859936305 | N9: 859936309 | O9: 859936305 | P9: 859936309 | Q9: 859936305
F10: =SUM(F9:G9) -> 1719872614 | H10: =SUM(H9:I9) -> 1719872614 | J10: =SUM(J9:K9) -> 1719872614 | L10: =SUM(L9:M9) -> 1719872614 | N10: =SUM(N9:O9) -> 1719872614 | P10: =SUM(P9:Q9) -> 1719872614
F13: 2026 07 2 | G13: 2026 08 1 | H13: 2026 08 2 | I13: 2026 09 1 | J13: 2026 09 2 | K13: 2026 10 1 | L13: 2026 10 2 | M13: 2026 11 1 | N13: 2026 11 2 | O13: 2026 12 1 | P13: 2026 12 2 | Q13: 2027 01 1
C14: ASE | D14: Concesionarios | E14: % | F14: MITAD 1 // JULIO -26 | G14: MITAD 2 // JULIO -26 | H14: MITAD 1 // AGOSTO -26 | I14: MITAD 2 // AGOSTO -26 | J14: MITAD 1 // SEPTIEMBRE -26 | K14: MITAD 2 // SEPTIEMBRE -26 | L14: MITAD 1 // OCTUBRE -26 | M14: MITAD 2 // OCTUBRE -26 | N14: MITAD 1 // NOVIEMBRE -26 | O14: MITAD 2 // NOVIEMBRE -26 | P14: MITAD 1 // DICIEMBRE -26 | Q14: MITAD 2 // DICIEMBRE -26
C15: 1 | D15: PROMOAMBIENTAL DISTRITO S.A.S. ESP. | E15: 0.22 | F15: 189185988 | G15: 189185987 | H15: 189185988 | I15: 189185987 | J15: 189185988 | K15: 189185987 | L15: 189185988 | M15: 189185987 | N15: 189185988 | O15: 189185987 | P15: 189185988 | Q15: 189185987
C16: 2 | D16: LIMPIEZA METROPOLITANA S.A. ESP. | E16: 0.31 | F16: 266580256 | G16: 266580255 | H16: 266580256 | I16: 266580255 | J16: 266580256 | K16: 266580255 | L16: 266580256 | M16: 266580255 | N16: 266580256 | O16: 266580255 | P16: 266580256 | Q16: 266580255
C17: 3 | D17: CIUDAD LIMPIA BOGOTA S.A. ESP. | E17: 0.18 | F17: 154788536 | G17: 154788535 | H17: 154788536 | I17: 154788535 | J17: 154788536 | K17: 154788535 | L17: 154788536 | M17: 154788535 | N17: 154788536 | O17: 154788535 | P17: 154788536 | Q17: 154788535
C18: 4 | D18: BOGOTA LIMPIA S.A.S. ESP. | E18: 0.14 | F18: 120391083 | G18: 120391083 | H18: 120391083 | I18: 120391083 | J18: 120391083 | K18: 120391083 | L18: 120391083 | M18: 120391083 | N18: 120391083 | O18: 120391083 | P18: 120391083 | Q18: 120391083
C19: 5 | D19: AREA LIMPIA DISTRITO CAPITAL S.A.S. ESP. | E19: 0.15 | F19: 128990446 | G19: 128990445 | H19: 128990446 | I19: 128990445 | J19: 128990446 | K19: 128990445 | L19: 128990446 | M19: 128990445 | N19: 128990446 | O19: 128990445 | P19: 128990446 | Q19: 128990445
D20: TOTAL | E20: 1 | F20: 859936309 | G20: 859936305 | H20: 859936309 | I20: 859936305 | J20: 859936309 | K20: 859936305 | L20: 859936309 | M20: 859936305 | N20: 859936309 | O20: 859936305 | P20: 859936309 | Q20: 859936305
F21: =SUM(F20:G20) -> 1719872614 | G21: 1191383498 | H21: =SUM(H20:I20) -> 1719872614 | I21: 1191383498 | J21: =SUM(J20:K20) -> 1719872614 | K21: 1191383498 | L21: =SUM(L20:M20) -> 1719872614 | M21: 1191383498 | N21: =SUM(N20:O20) -> 1719872614 | O21: 1191383498 | P21: =SUM(P20:Q20) -> 1719872614 | Q21: 1191383498
K25: VALOR OFICIAL MES | L25: ASE | M25: Segunda quincena | N25: Primera quincena | R25: VALIDACION
K26: 378371975 | L26: 1 | M26: 189185988 | N26: 189185987 | O26: =M26=R26 -> FALSE | Q26: ='CONSOLIDADO_TOTAL RECAUDO'!L104 -> 189185987 | R26: =N26 -> 189185987 | S26: =Q26=R26 -> TRUE
K27: 533160511 | L27: 2 | M27: 266580256 | N27: 266580255 | O27: =M27=R27 -> FALSE | Q27: ='CONSOLIDADO_TOTAL RECAUDO'!L105 -> 266580255 | R27: =N27 -> 266580255 | S27: =Q27=R27 -> TRUE
K28: 309577071 | L28: 3 | M28: 154788536 | N28: 154788535 | O28: =M28=R28 -> FALSE | Q28: ='CONSOLIDADO_TOTAL RECAUDO'!L106 -> 154788535 | R28: =N28 -> 154788535 | S28: =Q28=R28 -> TRUE
K29: 240782166 | L29: 4 | M29: 120391083 | N29: 120391083 | O29: =M29=R29 -> TRUE | Q29: ='CONSOLIDADO_TOTAL RECAUDO'!L107 -> 120391083 | R29: =N29 -> 120391083 | S29: =Q29=R29 -> TRUE
K30: 257980891 | L30: 5 | M30: 128990446 | N30: 128990445 | O30: =M30=R30 -> FALSE | Q30: ='CONSOLIDADO_TOTAL RECAUDO'!L108 -> 128990445 | R30: =N30 -> 128990445 | S30: =Q30=R30 -> TRUE
K31: =SUM(K26:K30) -> 1719872614 | M31: =SUM(M26:M30) -> 859936309 | N31: =SUM(N26:N30) -> 859936305 | O31: =M31=R31 -> FALSE | Q31: ='CONSOLIDADO_TOTAL RECAUDO'!L109 -> 859936305 | R31: =N31 -> 859936305 | S31: =Q31=R31 -> TRUE
K32: =SUM(M31:N31) -> 1719872614

Sheet Informe AFaseo Recaudo 202610-1
D5: PROCERASEO S.A.S. | I5: NIT: 901 153 639 - 0 | P5: PROCERASEO S.A.S. | T5: NIT: 901 153 639 - 0
D6: INFORME Afaseo // RECAUDO | P6: INFORME AFaseo
D7: BENEFICIO TRANSITORIO ALIVIO SOBRE EL VALOR DE LA FACTURA | P7: BENEFICIO TRANSITORIO ALIVIO SOBRE EL VALOR DE LA FACTURA
D8: Según Resoluciòn UAESP Número 273 de 2.020 | P8: Según Resoluciòn UAESP Número 273 de 2.020
E10: Fecha Desde: | F10: ='CONSOLIDADO_TOTAL RECAUDO'!G102 -> 46296 | H10: Feha Hasta: | I10: ='CONSOLIDADO_TOTAL RECAUDO'!K102 -> 46310
B11: ASE | C11: Concesionarios | D11: Valor Afaseo | E11: Afaseo por disposicion final | F11: Afaseo por tratamiento de lixiviados | G11: Afaseo por Componente VIAT ( Decreto 2412/2018) | H11: Afaseo por aprovechamiento | I11: Afaseo del componente de comercializacion para Aprovechamiento (11,4%) | J11: Afaseo RBL | N11: ASE | O11: Concesionarios | P11: Tarifa de Comercialización del Servicio. ( TCS) | Q11: Tarifa de Limpieza Urbana del Servicio. ( TLU) | R11: Tarifa de Barrido y Limpieza del Servicio. ( TBL) | S11: Tarifa de Recolección y Transporte del Servicio. (TRT) | T11: Componente de comercialización para Aprovechamiento (18,6%) | U11: Afaseo RBL
B12: 1 | C12: PROMOAMBIENTAL DISTRITO S.A.S. ESP. | D12: ='Reporte Componentes R1'!F119*$D$24 -> 2015.07 | E12: ='Reporte Componentes R1'!G119*$D$24 -> 122.1 | F12: ='Reporte Componentes R1'!H119*$D$24 -> 51.87 | G12: ='Reporte Componentes R1'!I119*$D$24 -> 22.65 | H12: ='Reporte Componentes R1'!J119*$D$24 -> 369.44 | I12: ='Reporte Componentes R1'!K119*$D$24 -> 23.88 | J12: =D12-E12-F12-G12-H12-I12 -> 1425.13 | N12: 1 | O12: PROMOAMBIENTAL DISTRITO S.A.S. ESP. | P12: ='Reporte Componentes R1'!M119*$P$24 -> 209.4 | Q12: ='Reporte Componentes R1'!N119*$P$24 -> 175.25 | R12: ='Reporte Componentes R1'!O119*$P$24 -> 699.55 | S12: ='Reporte Componentes R1'!P119*$P$24 -> 301.98 | T12: ='Reporte Componentes R1'!Q119*$P$24 -> 38.95 | U12: =SUM(P12:T12) -> 1425.13 | V12: =J12-U12 -> 0 | W12: =V12=0 -> TRUE
B13: 2 | C13: LIMPIEZA METROPOLITANA S.A. ESP. | D13: ='Reporte Componentes R1'!F353*$D$24 -> 243714.65 | E13: ='Reporte Componentes R1'!G353*$D$24 -> 20951.02 | F13: ='Reporte Componentes R1'!H353*$D$24 -> 8900.5 | G13: ='Reporte Componentes R1'!I353*$D$24 -> 3886.81 | H13: ='Reporte Componentes R1'!J353*$D$24 -> 48437.8 | I13: ='Reporte Componentes R1'!K353*$D$24 -> 2062.98 | J13: =D13-E13-F13-G13-H13-I13 -> 159475.54 | N13: 2 | O13: LIMPIEZA METROPOLITANA S.A. ESP. | P13: ='Reporte Componentes R1'!M353*$P$24 -> 18096.09 | Q13: ='Reporte Componentes R1'!N353*$P$24 -> 22688.82 | R13: ='Reporte Componentes R1'!O353*$P$24 -> 76193.1 | S13: ='Reporte Componentes R1'!P353*$P$24 -> 39131.24 | T13: ='Reporte Componentes R1'!Q353*$P$24 -> 3366.29 | U13: =SUM(P13:T13) -> 159475.54 | V13: =J13-U13 -> 0 | W13: =V13=0 -> TRUE
B14: 3 | C14: CIUDAD LIMPIA BOGOTA S.A. ESP. | D14: ='Reporte Componentes R1'!F514*$D$24 -> 558.05 | E14: ='Reporte Componentes R1'!G514*$D$24 -> 36.43 | F14: ='Reporte Componentes R1'!H514*$D$24 -> 15.48 | G14: ='Reporte Componentes R1'!I514*$D$24 -> 6.76 | H14: ='Reporte Componentes R1'!J514*$D$24 -> 123.14 | I14: ='Reporte Componentes R1'!K514*$D$24 -> 4.99 | J14: =D14-E14-F14-G14-H14-I14 -> 371.25 | N14: 3 | O14: CIUDAD LIMPIA BOGOTA S.A. ESP. | P14: ='Reporte Componentes R1'!M514*$P$24 -> 43.78 | Q14: ='Reporte Componentes R1'!N514*$P$24 -> 55.99 | R14: ='Reporte Componentes R1'!O514*$P$24 -> 184.32 | S14: ='Reporte Componentes R1'!P514*$P$24 -> 79.02 | T14: ='Reporte Componentes R1'!Q514*$P$24 -> 8.14 | U14: =SUM(P14:T14) -> 371.25 | V14: =J14-U14 -> 0 | W14: =V14=0 -> TRUE
B15: 4 | C15: BOGOTA LIMPIA S.A.S. ESP. | D15: ='Reporte Componentes R1'!F722*$D$24 -> 30180.94 | E15: ='Reporte Componentes R1'!G722*$D$24 -> 2445.45 | F15: ='Reporte Componentes R1'!H722*$D$24 -> 1038.91 | G15: ='Reporte Componentes R1'!I722*$D$24 -> 453.69 | H15: ='Reporte Componentes R1'!J722*$D$24 -> 5579.62 | I15: ='Reporte Componentes R1'!K722*$D$24 -> 227.22 | J15: =D15-E15-F15-G15-H15-I15 -> 20436.05 | N15: 4 | O15: BOGOTA LIMPIA S.A.S. ESP. | P15: ='Reporte Componentes R1'!M722*$P$24 -> 1993.18 | Q15: ='Reporte Componentes R1'!N722*$P$24 -> 2534.52 | R15: ='Reporte Componentes R1'!O722*$P$24 -> 9306.3 | S15: ='Reporte Componentes R1'!P722*$P$24 -> 6231.3 | T15: ='Reporte Componentes R1'!Q722*$P$24 -> 370.75 | U15: =SUM(P15:T15) -> 20436.05 | V15: =J15-U15 -> 0 | W15: =V15=0 -> TRUE
B16: 5 | C16: AREA LIMPIA DISTRITO CAPITAL S.A.S. ESP. | D16: ='Reporte Componentes R1'!F841*$D$24 -> 0 | E16: ='Reporte Componentes R1'!G841*$D$24 -> 0 | F16: ='Reporte Componentes R1'!H841*$D$24 -> 0 | G16: ='Reporte Componentes R1'!I841*$D$24 -> 0 | H16: ='Reporte Componentes R1'!J841*$D$24 -> 0 | I16: ='Reporte Componentes R1'!K841*$D$24 -> 0 | J16: =D16-E16-F16-G16-H16-I16 -> 0 | N16: 5 | O16: AREA LIMPIA DISTRITO CAPITAL S.A.S. ESP. | P16: ='Reporte Componentes R1'!M841*$P$24 -> 0 | Q16: ='Reporte Componentes R1'!N841*$P$24 -> 0 | R16: ='Reporte Componentes R1'!O841*$P$24 -> 0 | S16: ='Reporte Componentes R1'!P841*$P$24 -> 0 | T16: ='Reporte Componentes R1'!Q841*$P$24 -> 0 | U16: =SUM(P16:T16) -> 0 | V16: =J16-U16 -> 0 | W16: =V16=0 -> TRUE
C17: TOTAL | D17: =SUM(D12:D16) -> 276468.71 | E17: =SUM(E12:E16) -> 23555 | F17: =SUM(F12:F16) -> 10006.76 | G17: =SUM(G12:G16) -> 4369.91 | H17: =SUM(H12:H16) -> 54510 | I17: =SUM(I12:I16) -> 2319.07 | J17: =SUM(J12:J16) -> 181707.97 | O17: TOTAL | P17: =SUM(P12:P16) -> 20342.45 | Q17: =SUM(Q12:Q16) -> 25454.58 | R17: =SUM(R12:R16) -> 86383.27 | S17: =SUM(S12:S16) -> 45743.54 | T17: =SUM(T12:T16) -> 3784.13 | U17: =SUM(U12:U16) -> 181707.97 | V17: =SUM(V12:V16) -> 0 | W17: =V17=0 -> TRUE
T19: =SUM(P17:T17) -> 181707.97
J20: =+IF(MAX(J12:J17)>500000,"VALIDAR",TRUE) -> TRUE
F21: Firma autorizada
D24: -1 | P24: -1

Sheet CONSOLIDADO_TOTAL RECAUDO
F3: PROCERASEO S.A.S. | I3: NIT: 901 153 639 - 0 | M3: Codigo Remuneración: | N3: 2026101 | U3: PROCERASEO S.A.S. | W3: NIT: 901 153 639 - 0 | AA3: Codigo Remuneración: | AD3: =N3 -> 2026101
F4: 3. ESQUEMA FINANCIERO DEL SERVICIO PUBLICO DE ASEO | U4: 3. ESQUEMA FINANCIERO DEL SERVICIO PUBLICO DE ASEO
F5: Resoluciòn UAESP Número 27 de 2018 | U5: Resoluciòn UAESP Número 27 de 2018
C6: Fecha de Proceso: | D6: 46297 | F6: R1 - RECAUDO OPORTUNO | U6: R1 - RECAUDO OPORTUNO
C7: Hora: | D7: 0.58333333 | F7: Fecha Desde: | G7: 46296 | J7: Feha Hasta: | K7: 46310 | U7: =F7 -> Fecha Desde: | V7: =G7 -> 46296 | X7: =J7 -> Feha Hasta: | Y7: =K7 -> 46310
B8: ASE | C8: Concesionarios | D8: Recaudo Total | E8: Recaudo por disposicion final | F8: Recaudo por tratamiento de lixiviados | G8: Recaudo por Componente VIAT ( Decreto 2412/2018) | H8: Recaudo por aprovechamiento | I8: Recaudo del componente de comercializacion para Aprovechamiento (11,4%) | J8: Balance de subsidio o contribuciones | K8: RECAUDO BASE DE REMUNERACION | L8: Costo de la Interventoría | M8: REMUNERACION FINAL | N8: Conceptos especiales | O8: REMUNERACION FINAL MAS CONCEPTOS ESPECIALES | S8: ASE | T8: Concesionarios | U8: Tarifa de Comercialización del Servicio. ( TCS) | V8: Tarifa de Limpieza Urbana del Servicio. ( TLU) | W8: Tarifa de Barrido y Limpieza del Servicio. ( TBL) | X8: Tarifa de Recolección y Transporte del Servicio. (TRT) | Y8: Recaudo del componente de comercializacion para Aprovechamiento (18,6%) | Z8: Costo de la Interventoría | AA8: Ajuste a la decena | AB8: Conceptos especiales | AC8: Otros | AD8: Diferencial Balance S / C (Fac vs Rec) | AE8: Balance S / C Con Base en (Recaudo) | AF8: REMUNERACION FINAL MAS CONCEPTOS ESPECIALES
B9: 1 | C9: PROMOAMBIENTAL DISTRITO S.A.S. ESP. | D9: ='Reporte Componentes R1'!F89 -> 1.4815022e+10 | E9: ='Reporte Componentes R1'!G89 -> 8.4180604e+08 | F9: ='Reporte Componentes R1'!H89 -> 4.6891797e+08 | G9: ='Reporte Componentes R1'!I89 -> 2.4965692e+08 | H9: ='Reporte Componentes R1'!J89 -> 4.7568461e+09 | I9: ='Reporte Componentes R1'!K89 -> 1.5849797e+08 | J9: ='BCE SC POR FACT.'!F3 -> 2.1539508e+09 | K9: =D9-E9-F9-G9-H9-I9-J9 -> 6.1853461e+09 | L9: =INTERVENTORIA!N26 -> 189185987 | M9: =K9-L9 -> 5.9961602e+09 | N9: ='Reporte Componentes R1'!L89 -> 19931693 | O9: =M9+N9 -> 6.0160918e+09 | S9: 1 | T9: PROMOAMBIENTAL DISTRITO S.A.S. ESP. | U9: ='Reporte Componentes R1'!M89 -> 1.3917356e+09 | V9: ='Reporte Componentes R1'!N89 -> 1.3159586e+09 | W9: ='Reporte Componentes R1'!O89 -> 6.2722322e+09 | X9: ='Reporte Componentes R1'!P89 -> 2.2908891e+09 | Y9: ='Reporte Componentes R1'!Q89 -> 2.5874486e+08 | Z9: =L9*-1 -> -189185987 | AA9: ='Reporte Componentes R1'!R89+'Reporte Componentes R1'!U89+'Reporte Componentes R1'!V89 -> -27801.66 | AB9: =N9 -> 19931693 | AC9: ='Reporte Componentes R1'!T89+'Reporte Componentes R1'!W89+'Reporte Componentes R1'!X89+'Reporte Componentes R1'!Y89+'Reporte Componentes R1'!Z89+'Reporte Componentes R1'!S89 -> 149.13 | AD9: =-J9+AE9 -> -5.3441865e+09 | AE9: ='Reporte Componentes R1'!F90 -> -3.1902357e+09 | AF9: =SUM(U9:AD9) -> 6.0160918e+09 | AG9: =(AF9-O9) -> 4.7683716e-06 | AH9: =INT(AG9)=0 -> TRUE
B10: 2 | C10: LIMPIEZA METROPOLITANA S.A. ESP. | D10: ='Reporte Componentes R1'!F323 -> 1.1219101e+10 | E10: ='Reporte Componentes R1'!G323 -> 8.7325431e+08 | F10: ='Reporte Componentes R1'!H323 -> 4.8346293e+08 | G10: ='Reporte Componentes R1'!I323 -> 2.5630965e+08 | H10: ='Reporte Componentes R1'!J323 -> 3.5736206e+09 | I10: ='Reporte Componentes R1'!K323 -> 1.2662777e+08 | J10: ='BCE SC POR FACT.'!F4 -> -4.2171455e+09 | K10: =D10-E10-F10-G10-H10-I10-J10 -> 1.0122972e+10 | L10: =INTERVENTORIA!N27 -> 266580255 | M10: =K10-L10 -> 9.8563914e+09 | N10: ='Reporte Componentes R1'!L323 -> 9834335.8 | O10: =M10+N10 -> 9.8662257e+09 | S10: 2 | T10: LIMPIEZA METROPOLITANA S.A. ESP. | U10: ='Reporte Componentes R1'!M323 -> 1.1109993e+09 | V10: ='Reporte Componentes R1'!N323 -> 1.0681559e+09 | W10: ='Reporte Componentes R1'!O323 -> 5.074672e+09 | X10: ='Reporte Componentes R1'!P323 -> 1.712803e+09 | Y10: ='Reporte Componentes R1'!Q323 -> 2.0676196e+08 | Z10: =L10*-1 -> -266580255 | AA10: ='Reporte Componentes R1'!R323+'Reporte Componentes R1'!U323+'Reporte Componentes R1'!V323 -> -14204.66 | AB10: =N10 -> 9834335.8 | AC10: ='Reporte Componentes R1'!T323+'Reporte Componentes R1'!W323+'Reporte Componentes R1'!X323+'Reporte Componentes R1'!Y323+'Reporte Componentes R1'!Z323+'Reporte Componentes R1'!S323 -> -56307.81 | AD10: =-J10+AE10 -> 9.4964996e+08 | AE10: ='Reporte Componentes R1'!F324 -> -3.2674956e+09 | AF10: =SUM(U10:AD10) -> 9.8662257e+09 | AG10: =(AF10-O10) -> 1.9073486e-06 | AH10: =INT(AG10)=0 -> TRUE
B11: 3 | C11: CIUDAD LIMPIA BOGOTA S.A. ESP. | D11: ='Reporte Componentes R1'!F484 -> 8.8114722e+09 | E11: ='Reporte Componentes R1'!G484 -> 5.6904906e+08 | F11: ='Reporte Componentes R1'!H484 -> 3.1726749e+08 | G11: ='Reporte Componentes R1'!I484 -> 1.685178e+08 | H11: ='Reporte Componentes R1'!J484 -> 2.4290215e+09 | I11: ='Reporte Componentes R1'!K484 -> 86984011 | J11: ='BCE SC POR FACT.'!F5 -> -1.2888063e+09 | K11: =D11-E11-F11-G11-H11-I11-J11 -> 6.5294386e+09 | L11: =INTERVENTORIA!N28 -> 154788535 | M11: =K11-L11 -> 6.3746501e+09 | N11: ='Reporte Componentes R1'!L484 -> 19305718 | O11: =M11+N11 -> 6.3939558e+09 | S11: 3 | T11: CIUDAD LIMPIA BOGOTA S.A. ESP. | U11: ='Reporte Componentes R1'!M484 -> 7.636827e+08 | V11: ='Reporte Componentes R1'!N484 -> 7.2501882e+08 | W11: ='Reporte Componentes R1'!O484 -> 3.4442559e+09 | X11: ='Reporte Componentes R1'!P484 -> 1.3479162e+09 | Y11: ='Reporte Componentes R1'!Q484 -> 1.4202598e+08 | Z11: =L11*-1 -> -154788535 | AA11: ='Reporte Componentes R1'!R484+'Reporte Componentes R1'!U484+'Reporte Componentes R1'!V484 -> -81704.87 | AB11: =N11 -> 19305718 | AC11: ='Reporte Componentes R1'!T484+'Reporte Componentes R1'!W484+'Reporte Componentes R1'!X484+'Reporte Componentes R1'!Y484+'Reporte Componentes R1'!Z484+'Reporte Componentes R1'!S484 -> -41619.9 | AD11: =-J11+AE11 -> 1.0666238e+08 | AE11: ='Reporte Componentes R1'!F485 -> -1.182144e+09 | AF11: =SUM(U11:AD11) -> 6.3939558e+09 | AG11: =(AF11-O11) -> 0 | AH11: =INT(AG11)=0 -> TRUE
B12: 4 | C12: BOGOTA LIMPIA S.A.S. ESP. | D12: ='Reporte Componentes R1'!F692 -> 1.0473968e+10 | E12: ='Reporte Componentes R1'!G692 -> 6.0467e+08 | F12: ='Reporte Componentes R1'!H692 -> 3.3517547e+08 | G12: ='Reporte Componentes R1'!I692 -> 1.7872296e+08 | H12: ='Reporte Componentes R1'!J692 -> 2.3961854e+09 | I12: ='Reporte Componentes R1'!K692 -> 89652486 | J12: ='BCE SC POR FACT.'!F6 -> 61531954 | K12: =D12-E12-F12-G12-H12-I12-J12 -> 6.8080295e+09 | L12: =INTERVENTORIA!N29 -> 120391083 | M12: =K12-L12 -> 6.6876384e+09 | N12: ='Reporte Componentes R1'!L692 -> 8643135.6 | O12: =M12+N12 -> 6.6962816e+09 | S12: 4 | T12: BOGOTA LIMPIA S.A.S. ESP. | U12: ='Reporte Componentes R1'!M692 -> 7.8581447e+08 | V12: ='Reporte Componentes R1'!N692 -> 7.4992426e+08 | W12: ='Reporte Componentes R1'!O692 -> 3.8805462e+09 | X12: ='Reporte Componentes R1'!P692 -> 1.600708e+09 | Y12: ='Reporte Componentes R1'!Q692 -> 1.4652791e+08 | Z12: =L12*-1 -> -120391083 | AA12: ='Reporte Componentes R1'!R692+'Reporte Componentes R1'!U692+'Reporte Componentes R1'!V692 -> 31942.35 | AB12: =N12 -> 8643135.6 | AC12: ='Reporte Componentes R1'!T692+'Reporte Componentes R1'!W692+'Reporte Componentes R1'!X692+'Reporte Componentes R1'!Y692+'Reporte Componentes R1'!Z692+'Reporte Componentes R1'!S692 -> 189.43 | AD12: =-J12+AE12 -> -3.5552347e+08 | AE12: ='Reporte Componentes R1'!F693 -> -2.9399152e+08 | AF12: =SUM(U12:AD12) -> 6.6962816e+09 | AG12: =(AF12-O12) -> 1.9073486e-06 | AH12: =INT(AG12)=0 -> TRUE
B13: 5 | C13: AREA LIMPIA DISTRITO CAPITAL S.A.S. ESP. | D13: ='Reporte Componentes R1'!F811 -> 7.5442533e+09 | E13: ='Reporte Componentes R1'!G811 -> 4.0814547e+08 | F13: ='Reporte Componentes R1'!H811 -> 2.2711804e+08 | G13: ='Reporte Componentes R1'!I811 -> 1.2084103e+08 | H13: ='Reporte Componentes R1'!J811 -> 1.8642679e+09 | I13: ='Reporte Componentes R1'!K811 -> 62073127 | J13: ='BCE SC POR FACT.'!F7 -> -1.2464731e+09 | K13: =D13-E13-F13-G13-H13-I13-J13 -> 6.1082808e+09 | L13: =INTERVENTORIA!N30 -> 128990445 | M13: =K13-L13 -> 5.9792904e+09 | N13: ='Reporte Componentes R1'!L811 -> 12379938 | O13: =M13+N13 -> 5.9916703e+09 | S13: 5 | T13: AREA LIMPIA DISTRITO CAPITAL S.A.S. ESP. | U13: ='Reporte Componentes R1'!M811 -> 5.4468434e+08 | V13: ='Reporte Componentes R1'!N811 -> 5.1295881e+08 | W13: ='Reporte Componentes R1'!O811 -> 2.6405604e+09 | X13: ='Reporte Componentes R1'!P811 -> 1.2146777e+09 | Y13: ='Reporte Componentes R1'!Q811 -> 101292451 | Z13: =L13*-1 -> -128990445 | AA13: ='Reporte Componentes R1'!R811+'Reporte Componentes R1'!U811+'Reporte Componentes R1'!V811 -> 10679.52 | AB13: =N13 -> 12379938 | AC13: ='Reporte Componentes R1'!T811+'Reporte Componentes R1'!W811+'Reporte Componentes R1'!X811+'Reporte Componentes R1'!Y811+'Reporte Componentes R1'!Z811+'Reporte Componentes R1'!S811 -> 4.86 | AD13: =-J13+AE13 -> 1.0940964e+09 | AE13: ='Reporte Componentes R1'!F812 -> -152376731 | AF13: =SUM(U13:AD13) -> 5.9916703e+09 | AG13: =(AF13-O13) -> 0 | AH13: =INT(AG13)=0 -> TRUE
C14: TOTAL | D14: =SUM(D9:D13) -> 5.2863817e+10 | E14: =SUM(E9:E13) -> 3.2969249e+09 | F14: =SUM(F9:F13) -> 1.8319419e+09 | G14: =SUM(G9:G13) -> 9.7404836e+08 | H14: =SUM(H9:H13) -> 1.5019942e+10 | I14: =SUM(I9:I13) -> 5.2383536e+08 | J14: =SUM(J9:J13) -> -4.5369422e+09 | K14: =SUM(K9:K13) -> 3.5754067e+10 | ... O14: =SUM(O9:O13) -> 3.4964225e+10 | T14: TOTAL | U14: =SUM(U9:U13) -> 4.5969164e+09 | V14: =SUM(V9:V13) -> 4.3720164e+09 | W14: =SUM(W9:W13) -> 2.1312267e+10 | X14: =SUM(X9:X13) -> 8.1669939e+09 | Y14: =SUM(Y9:Y13) -> 8.5535316e+08 | Z14: =SUM(Z9:Z13) -> -859936305 | AA14: =SUM(AA9:AA13) -> -81089.32 | AB14: =SUM(AB9:AB13) -> 70094820 | ... AG14: =SUM(AG9:AG13) -> 8.5830688e-06 | AH14: =INT(AG14)=0 -> TRUE
Y16: =SUM(U14:Y14) -> 3.9303547e+10
F18: Firma autorizada
F22: PROCERASEO S.A.S. | I22: NIT: 901 153 639 - 0 | M22: Codigo Remuneración: | N22: =N3 -> 2026101 | U22: PROCERASEO S.A.S. | W22: NIT: 901 153 639 - 0 | AA22: Codigo Remuneración: | AD22: =N22 -> 2026101
F23: 3. ESQUEMA FINANCIERO DEL SERVICIO PUBLICO DE ASEO | U23: 3. ESQUEMA FINANCIERO DEL SERVICIO PUBLICO DE ASEO
F24: Resoluciòn UAESP Número 27 de 2018 | U24: Resoluciòn UAESP Número 27 de 2018
C25: Fecha de Proceso: | D25: =D6 -> 46297 | F25: R2 - ANTICIPOS A USUARIOS | U25: R2 - ANTICIPOS A USUARIOS
C26: Hora: | D26: =D7 -> 0.58333333 | F26: Fecha Desde: | G26: =G7 -> 46296 | J26: Feha Hasta: | K26: =K7 -> 46310 | U26: =F26 -> Fecha Desde: | V26: =G26 -> 46296 | X26: =J26 -> Feha Hasta: | Y26: =K26 -> 46310
B27: ASE | C27: Concesionarios | D27: Recaudo Total | E27: Recaudo por disposicion final | F27: Recaudo por tratamiento de lixiviados | G27: Recaudo por Componente VIAT ( Decreto 2412/2018) | H27: Recaudo por aprovechamiento | I27: Recaudo del componente de comercializacion para Aprovechamiento (11,4%) | J27: Balance de subsidio o contribuciones | K27: RECAUDO BASE DE REMUNERACION | L27: Costo de la Interventoría | M27: REMUNERACION FINAL | N27: Conceptos especiales | O27: REMUNERACION FINAL MAS CONCEPTOS ESPECIALES | S27: ASE | T27: Concesionarios | U27: Tarifa de Comercialización del Servicio. ( TCS) | V27: Tarifa de Limpieza Urbana del Servicio. ( TLU) | W27: Tarifa de Barrido y Limpieza del Servicio. ( TBL) | X27: Tarifa de Recolección y Transporte del Servicio. (TRT) | Y27: Recaudo del componente de comercializacion para Aprovechamiento (18,6%) | Z27: Costo de la Interventoría | AA27: Ajuste a la decena | AB27: Conceptos especiales | AC27: Otros | AD27: Diferencial Balance S / C (Fac vs Rec) | AE27: Balance S / C Con Base en (Recaudo) | AF27: REMUNERACION FINAL MAS CONCEPTOS ESPECIALES
B28: 1 | C28: PROMOAMBIENTAL DISTRITO S.A.S. ESP. | D28: ='Rem. Anticipos R2'!E57 -> 30588071 | E28: ='Rem. Anticipos R2'!F57 -> 0 | F28: ='Rem. Anticipos R2'!G57 -> 0 | G28: ='Rem. Anticipos R2'!H57 -> 0 | H28: ='Rem. Anticipos R2'!I57 -> 0 | I28: ='Rem. Anticipos R2'!J57 -> 0 | J28: 0 | K28: =D28-E28-F28-G28-H28-I28-J28 -> 30588071 | L28: 0 | M28: =K28-L28 -> 30588071 | N28: ='Rem. Anticipos R2'!K57 -> 0 | O28: =M28+N28 -> 30588071 | S28: 1 | T28: PROMOAMBIENTAL DISTRITO S.A.S. ESP. | U28: ='Rem. Anticipos R2'!L57 -> 0 | V28: ='Rem. Anticipos R2'!M57 -> 0 | W28: ='Rem. Anticipos R2'!N57 -> 0 | X28: ='Rem. Anticipos R2'!O57 -> 0 | Y28: ='Rem. Anticipos R2'!P57 -> 0 | Z28: =L28*-1 -> 0 | AA28: ='Rem. Anticipos R2'!Q57 -> 0 | AB28: =N28 -> 0 | AC28: ='Rem. Anticipos R2'!R57 -> 0 | AD28: =-J28+AE28 -> -688671.4 | AE28: ='Rem. Anticipos R2'!E58 -> -688671.4 | AF28: =SUM(U28:AD28) -> -688671.4 | AG28: =(AF28-O28) -> -31276742 | AH28: =INT(AG28)=0 -> FALSE
B29: 2 | C29: LIMPIEZA METROPOLITANA S.A. ESP. | D29: ='Rem. Anticipos R2'!E178 -> 95634974 | E29: ='Rem. Anticipos R2'!F178 -> 0 | F29: ='Rem. Anticipos R2'!G178 -> 0 | G29: ='Rem. Anticipos R2'!H178 -> 0 | H29: ='Rem. Anticipos R2'!I178 -> 0 | I29: ='Rem. Anticipos R2'!J178 -> 0 | J29: 0 | K29: =D29-E29-F29-G29-H29-I29-J29 -> 95634974 | L29: 0 | M29: =K29-L29 -> 95634974 | N29: ='Rem. Anticipos R2'!K178 -> 70736.95 | O29: =M29+N29 -> 95705711 | S29: 2 | T29: LIMPIEZA METROPOLITANA S.A. ESP. | U29: ='Rem. Anticipos R2'!L178 -> 0 | V29: ='Rem. Anticipos R2'!M178 -> 0 | W29: ='Rem. Anticipos R2'!N178 -> 0 | X29: ='Rem. Anticipos R2'!O178 -> 0 | Y29: ='Rem. Anticipos R2'!P178 -> 0 | Z29: =L29*-1 -> 0 | AA29: ='Rem. Anticipos R2'!Q178 -> 0 | AB29: =N29 -> 70736.95 | AC29: ='Rem. Anticipos R2'!R178 -> 0 | AD29: =-J29+AE29 -> -20704709 | AE29: ='Rem. Anticipos R2'!E179 -> -20704709 | AF29: =SUM(U29:AD29) -> -20633972 | AG29: =(AF29-O29) -> -1.1633968e+08 | AH29: =INT(AG29)=0 -> FALSE
B30: 3 | C30: CIUDAD LIMPIA BOGOTA S.A. ESP. | D30: ='Rem. Anticipos R2'!E299 -> 14574412 | E30: ='Rem. Anticipos R2'!F299 -> 0 | F30: ='Rem. Anticipos R2'!G299 -> 0 | G30: ='Rem. Anticipos R2'!H299 -> 0 | H30: ='Rem. Anticipos R2'!I299 -> 0 | I30: ='Rem. Anticipos R2'!J299 -> 0 | J30: 0 | K30: =D30-E30-F30-G30-H30-I30-J30 -> 14574412 | L30: 0 | M30: =K30-L30 -> 14574412 | N30: ='Rem. Anticipos R2'!K299 -> 16082.29 | O30: =M30+N30 -> 14590494 | S30: 3 | T30: CIUDAD LIMPIA BOGOTA S.A. ESP. | U30: ='Rem. Anticipos R2'!L299 -> 0 | V30: ='Rem. Anticipos R2'!M299 -> 0 | W30: ='Rem. Anticipos R2'!N299 -> 0 | X30: ='Rem. Anticipos R2'!O299 -> 0 | Y30: ='Rem. Anticipos R2'!P299 -> 0 | Z30: =L30*-1 -> 0 | AA30: ='Rem. Anticipos R2'!Q299 -> 0 | AB30: =N30 -> 16082.29 | AC30: ='Rem. Anticipos R2'!R299 -> 0 | AD30: =-J30+AE30 -> -3867345.8 | AE30: ='Rem. Anticipos R2'!E300 -> -3867345.8 | AF30: =SUM(U30:AD30) -> -3851263.5 | AG30: =(AF30-O30) -> -18441758 | AH30: =INT(AG30)=0 -> FALSE
B31: 4 | C31: BOGOTA LIMPIA S.A.S. ESP. | D31: ='Rem. Anticipos R2'!E423 -> 29206357 | E31: ='Rem. Anticipos R2'!F423 -> 0 | F31: ='Rem. Anticipos R2'!G423 -> 0 | G31: ='Rem. Anticipos R2'!H423 -> 0 | H31: ='Rem. Anticipos R2'!I423 -> 0 | I31: ='Rem. Anticipos R2'!J423 -> 0 | J31: 0 | K31: =D31-E31-F31-G31-H31-I31-J31 -> 29206357 | L31: 0 | M31: =K31-L31 -> 29206357 | N31: ='Rem. Anticipos R2'!K423 -> 0 | O31: =M31+N31 -> 29206357 | S31: 4 | T31: BOGOTA LIMPIA S.A.S. ESP. | U31: ='Rem. Anticipos R2'!L423 -> 0 | V31: ='Rem. Anticipos R2'!M423 -> 0 | W31: ='Rem. Anticipos R2'!N423 -> 0 | X31: ='Rem. Anticipos R2'!O423 -> 0 | Y31: ='Rem. Anticipos R2'!P423 -> 0 | Z31: =L31*-1 -> 0 | AA31: ='Rem. Anticipos R2'!Q423 -> 0 | AB31: =N31 -> 0 | AC31: ='Rem. Anticipos R2'!R423 -> 0 | AD31: =-J31+AE31 -> 382600.2 | AE31: ='Rem. Anticipos R2'!E424 -> 382600.2 | AF31: =SUM(U31:AD31) -> 382600.2 | AG31: =(AF31-O31) -> -28823757 | AH31: =INT(AG31)=0 -> FALSE
B32: 5 | C32: AREA LIMPIA DISTRITO CAPITAL S.A.S. ESP. | D32: ='Rem. Anticipos R2'!E510 -> 10379542 | E32: ='Rem. Anticipos R2'!F510 -> 0 | F32: ='Rem. Anticipos R2'!G510 -> 0 | G32: ='Rem. Anticipos R2'!H510 -> 0 | H32: ='Rem. Anticipos R2'!I510 -> 0 | I32: ='Rem. Anticipos R2'!J510 -> 0 | J32: 0 | K32: =D32-E32-F32-G32-H32-I32-J32 -> 10379542 | L32: 0 | M32: =K32-L32 -> 10379542 | N32: ='Rem. Anticipos R2'!K510 -> 0 | O32: =M32+N32 -> 10379542 | S32: 5 | T32: AREA LIMPIA DISTRITO CAPITAL S.A.S. ESP. | U32: ='Rem. Anticipos R2'!L510 -> 0 | V32: ='Rem. Anticipos R2'!M510 -> 0 | W32: ='Rem. Anticipos R2'!N510 -> 0 | X32: ='Rem. Anticipos R2'!O510 -> 0 | Y32: ='Rem. Anticipos R2'!P510 -> 0 | Z32: =L32*-1 -> 0 | AA32: ='Rem. Anticipos R2'!Q510 -> 0 | AB32: =N32 -> 0 | AC32: ='Rem. Anticipos R2'!R510 -> 0 | AD32: =-J32+AE32 -> -33324.08 | AE32: ='Rem. Anticipos R2'!E511 -> -33324.08 | AF32: =SUM(U32:AD32) -> -33324.08 | AG32: =(AF32-O32) -> -10412866 | AH32: =INT(AG32)=0 -> FALSE
C33: TOTAL | D33: =SUM(D28:D32) -> 1.8038336e+08 | E33: =SUM(E28:E32) -> 0 | F33: =SUM(F28:F32) -> 0 | G33: =SUM(G28:G32) -> 0 | H33: =SUM(H28:H32) -> 0 | I33: =SUM(I28:I32) -> 0 | J33: =SUM(J28:J32) -> 0 | K33: =SUM(K28:K32) -> 1.8038336e+08 | ... O33: =SUM(O28:O32) -> 1.8047018e+08 | T33: TOTAL | U33: =SUM(U28:U32) -> 0 | V33: =SUM(V28:V32) -> 0 | W33: =SUM(W28:W32) -> 0 | X33: =SUM(X28:X32) -> 0 | Y33: =SUM(Y28:Y32) -> 0 | Z33: =SUM(Z28:Z32) -> 0 | AA33: =SUM(AA28:AA32) -> 0 | AB33: =SUM(AB28:AB32) -> 86819.24 | ... AG33: =SUM(AG28:AG32) -> -2.0529481e+08 | AH33: =INT(AG33)=0 -> FALSE
Y35: =SUM(U33:Y33) -> 0
F37: Firma autorizada
F41: PROCERASEO S.A.S. | I41: NIT: 901 153 639 - 0 | M41: Codigo Remuneración: | N41: =N3 -> 2026101 | U41: PROCERASEO S.A.S. | W41: NIT: 901 153 639 - 0 | AA41: Codigo Remuneración: | AD41: =N41 -> 2026101
F42: 3. ESQUEMA FINANCIERO DEL SERVICIO PUBLICO DE ASEO | U42: 3. ESQUEMA FINANCIERO DEL SERVICIO PUBLICO DE ASEO
F43: Resoluciòn UAESP Número 27 de 2018 | U43: Resoluciòn UAESP Número 27 de 2018
C44: Fecha de Proceso: | D44: =D6 -> 46297 | F44: R3 - RECAUDO EXTEMPORANEO | U44: R3 - RECAUDO EXTEMPORANEO
C45: Hora: | D45: =D7 -> 0.58333333 | F45: Fecha Desde: | G45: =G7 -> 46296 | J45: Feha Hasta: | K45: =K7 -> 46310 | U45: =F45 -> Fecha Desde: | V45: =G45 -> 46296 | X45: =J45 -> Feha Hasta: | Y45: =K45 -> 46310
B46: ASE | C46: Concesionarios | D46: Recaudo Total | E46: Recaudo por disposicion final | F46: Recaudo por tratamiento de lixiviados | G46: Recaudo por Componente VIAT ( Decreto 2412/2018) | H46: Recaudo por aprovechamiento | I46: Recaudo del componente de comercializacion para Aprovechamiento (11,4%) | J46: Balance de subsidio o contribuciones | K46: RECAUDO BASE DE REMUNERACION | L46: Costo de la Interventoría | M46: REMUNERACION FINAL | N46: Conceptos especiales | O46: REMUNERACION FINAL MAS CONCEPTOS ESPECIALES | S46: ASE | T46: Concesionarios | U46: Tarifa de Comercialización del Servicio. ( TCS) | V46: Tarifa de Limpieza Urbana del Servicio. ( TLU) | W46: Tarifa de Barrido y Limpieza del Servicio. ( TBL) | X46: Tarifa de Recolección y Transporte del Servicio. (TRT) | Y46: Recaudo del componente de comercializacion para Aprovechamiento (18,6%) | Z46: Costo de la Interventoría | AA46: Ajuste a la decena | AB46: Conceptos especiales | AC46: Otros | AD46: Diferencial Balance S / C (Fac vs Rec) | AE46: Balance S / C Con Base en (Recaudo) | AF46: REMUNERACION FINAL MAS CONCEPTOS ESPECIALES
B47: 1 | C47: PROMOAMBIENTAL DISTRITO S.A.S. ESP. | D47: ='Reporte Componentes R1'!F91 -> 648870 | E47: ='Reporte Componentes R1'!G91 -> 29223.59 | F47: ='Reporte Componentes R1'!H91 -> 16458.47 | G47: ='Reporte Componentes R1'!I91 -> 8660.22 | H47: ='Reporte Componentes R1'!J91 -> 141425.47 | I47: ='Reporte Componentes R1'!K91 -> 5825.54 | J47: 0 | K47: =D47-E47-F47-G47-H47-I47-J47 -> 447276.71 | L47: 0 | M47: =K47-L47 -> 447276.71 | N47: ='Reporte Componentes R1'!L91 -> 0 | O47: =M47+N47 -> 447276.71 | S47: 1 | T47: PROMOAMBIENTAL DISTRITO S.A.S. ESP. | U47: ='Reporte Componentes R1'!M91 -> 51101.37 | V47: ='Reporte Componentes R1'!N91 -> 51278.68 | W47: ='Reporte Componentes R1'!O91 -> 242748.43 | X47: ='Reporte Componentes R1'!P91 -> 79815.35 | Y47: ='Reporte Componentes R1'!Q91 -> 9504.83 | Z47: =-L47 -> 0 | AA47: ='Reporte Componentes R1'!R91+'Reporte Componentes R1'!V91+'Reporte Componentes R1'!U91 -> 5.12 | AB47: =N47 -> 0 | AC47: ='Reporte Componentes R1'!T91+'Reporte Componentes R1'!W91+'Reporte Componentes R1'!X91+'Reporte Componentes R1'!Y91+'Reporte Componentes R1'!Z91+'Reporte Componentes R1'!S91 -> 0 | AD47: =-J47+AE47 -> 12822.93 | AE47: ='Reporte Componentes R1'!F92 -> 12822.93 | AF47: =SUM(U47:AD47) -> 447276.71 | AG47: =(AF47-O47) -> -1.7462298e-10 | AH47: =INT(AG47)=0 -> FALSE
B48: 2 | C48: LIMPIEZA METROPOLITANA S.A. ESP. | D48: ='Reporte Componentes R1'!F325 -> 9704974 | E48: ='Reporte Componentes R1'!G325 -> 651837.25 | F48: ='Reporte Componentes R1'!H325 -> 367261.1 | G48: ='Reporte Componentes R1'!I325 -> 196265.14 | H48: ='Reporte Componentes R1'!J325 -> 2936066.5 | I48: ='Reporte Componentes R1'!K325 -> 79272.71 | J48: 0 | K48: =D48-E48-F48-G48-H48-I48-J48 -> 5474271.3 | L48: 0 | M48: =K48-L48 -> 5474271.3 | N48: ='Reporte Componentes R1'!L325 -> 0 | O48: =M48+N48 -> 5474271.3 | S48: 2 | T48: LIMPIEZA METROPOLITANA S.A. ESP. | U48: ='Reporte Componentes R1'!M325 -> 695375.41 | V48: ='Reporte Componentes R1'!N325 -> 925873.97 | W48: ='Reporte Componentes R1'!O325 -> 4476434.6 | X48: ='Reporte Componentes R1'!P325 -> 1295216.9 | Y48: ='Reporte Componentes R1'!Q325 -> 130580.61 | Z48: =-L48 -> 0 | AA48: ='Reporte Componentes R1'!R325+'Reporte Componentes R1'!V325+'Reporte Componentes R1'!U325 -> -101.63 | AB48: =N48 -> 0 | AC48: ='Reporte Componentes R1'!T325+'Reporte Componentes R1'!W325+'Reporte Componentes R1'!X325+'Reporte Componentes R1'!Y325+'Reporte Componentes R1'!Z325+'Reporte Componentes R1'!S325 -> 0.04 | AD48: =-J48+AE48 -> -2049108.6 | AE48: ='Reporte Componentes R1'!F326 -> -2049108.6 | AF48: =SUM(U48:AD48) -> 5474271.3 | AG48: =(AF48-O48) -> 0 | AH48: =INT(AG48)=0 -> TRUE
B49: 3 | C49: CIUDAD LIMPIA BOGOTA S.A. ESP. | D49: ='Reporte Componentes R1'!F486 -> 0 | E49: ='Reporte Componentes R1'!G486 -> 0 | F49: ='Reporte Componentes R1'!H486 -> 0 | G49: ='Reporte Componentes R1'!I486 -> 0 | H49: ='Reporte Componentes R1'!J486 -> 0 | I49: ='Reporte Componentes R1'!K486 -> 0 | J49: 0 | K49: =D49-E49-F49-G49-H49-I49-J49 -> 0 | L49: 0 | M49: =K49-L49 -> 0 | N49: ='Reporte Componentes R1'!L486 -> 0 | O49: =M49+N49 -> 0 | S49: 3 | T49: CIUDAD LIMPIA BOGOTA S.A. ESP. | U49: ='Reporte Componentes R1'!M486 -> 0 | V49: ='Reporte Componentes R1'!N486 -> 0 | W49: ='Reporte Componentes R1'!O486 -> 0 | X49: ='Reporte Componentes R1'!P486 -> 0 | Y49: ='Reporte Componentes R1'!Q486 -> 0 | Z49: =-L49 -> 0 | AA49: ='Reporte Componentes R1'!R486+'Reporte Componentes R1'!V486+'Reporte Componentes R1'!U486 -> 0 | AB49: =N49 -> 0 | AC49: ='Reporte Componentes R1'!T486+'Reporte Componentes R1'!W486+'Reporte Componentes R1'!X486+'Reporte Componentes R1'!Y486+'Reporte Componentes R1'!Z486+'Reporte Componentes R1'!S486 -> 0 | AD49: =-J49+AE49 -> 0 | AE49: ='Reporte Componentes R1'!F487 -> 0 | AF49: =SUM(U49:AD49) -> 0 | AG49: =(AF49-O49) -> 0 | AH49: =INT(AG49)=0 -> TRUE
B50: 4 | C50: BOGOTA LIMPIA S.A.S. ESP. | D50: ='Reporte Componentes R1'!F694 -> 21557177 | E50: ='Reporte Componentes R1'!G694 -> 1278757.6 | F50: ='Reporte Componentes R1'!H694 -> 719798.43 | G50: ='Reporte Componentes R1'!I694 -> 385650.58 | H50: ='Reporte Componentes R1'!J694 -> 5181365.2 | I50: ='Reporte Componentes R1'!K694 -> 155526.08 | J50: 0 | K50: =D50-E50-F50-G50-H50-I50-J50 -> 13836079 | L50: 0 | M50: =K50-L50 -> 13836079 | N50: ='Reporte Componentes R1'!L694 -> 0 | O50: =M50+N50 -> 13836079 | S50: 4 | T50: BOGOTA LIMPIA S.A.S. ESP. | U50: ='Reporte Componentes R1'!M694 -> 1351292.3 | V50: ='Reporte Componentes R1'!N694 -> 1669548.6 | W50: ='Reporte Componentes R1'!O694 -> 8617443.9 | X50: ='Reporte Componentes R1'!P694 -> 3417030.9 | Y50: ='Reporte Componentes R1'!Q694 -> 255177.82 | Z50: =-L50 -> 0 | AA50: ='Reporte Componentes R1'!R694+'Reporte Componentes R1'!V694+'Reporte Componentes R1'!U694 -> -9.05 | AB50: =N50 -> 0 | AC50: ='Reporte Componentes R1'!T694+'Reporte Componentes R1'!W694+'Reporte Componentes R1'!X694+'Reporte Componentes R1'!Y694+'Reporte Componentes R1'!Z694+'Reporte Componentes R1'!S694 -> 0 | AD50: =-J50+AE50 -> -1474405.3 | AE50: ='Reporte Componentes R1'!F695 -> -1474405.3 | AF50: =SUM(U50:AD50) -> 13836079 | AG50: =(AF50-O50) -> -1.8626451e-09 | AH50: =INT(AG50)=0 -> FALSE
B51: 5 | C51: AREA LIMPIA DISTRITO CAPITAL S.A.S. ESP. | D51: ='Reporte Componentes R1'!F813 -> 0 | E51: ='Reporte Componentes R1'!G813 -> 0 | F51: ='Reporte Componentes R1'!H813 -> 0 | G51: ='Reporte Componentes R1'!I813 -> 0 | H51: ='Reporte Componentes R1'!J813 -> 0 | I51: ='Reporte Componentes R1'!K813 -> 0 | J51: 0 | K51: =D51-E51-F51-G51-H51-I51-J51 -> 0 | L51: 0 | M51: =K51-L51 -> 0 | N51: ='Reporte Componentes R1'!L813 -> 0 | O51: =M51+N51 -> 0 | S51: 5 | T51: AREA LIMPIA DISTRITO CAPITAL S.A.S. ESP. | U51: ='Reporte Componentes R1'!M813 -> 0 | V51: ='Reporte Componentes R1'!N813 -> 0 | W51: ='Reporte Componentes R1'!O813 -> 0 | X51: ='Reporte Componentes R1'!P813 -> 0 | Y51: ='Reporte Componentes R1'!Q813 -> 0 | Z51: =-L51 -> 0 | AA51: ='Reporte Componentes R1'!R813+'Reporte Componentes R1'!V813+'Reporte Componentes R1'!U813 -> 0 | AB51: =N51 -> 0 | AC51: ='Reporte Componentes R1'!T813+'Reporte Componentes R1'!W813+'Reporte Componentes R1'!X813+'Reporte Componentes R1'!Y813+'Reporte Componentes R1'!Z813+'Reporte Componentes R1'!S813 -> 0 | AD51: =-J51+AE51 -> 0 | AE51: ='Reporte Componentes R1'!F814 -> 0 | AF51: =SUM(U51:AD51) -> 0 | AG51: =(AF51-O51) -> 0 | AH51: =INT(AG51)=0 -> TRUE
C52: TOTAL | D52: =SUM(D47:D51) -> 31911021 | E52: =SUM(E47:E51) -> 1959818.5 | F52: =SUM(F47:F51) -> 1103518 | G52: =SUM(G47:G51) -> 590575.94 | H52: =SUM(H47:H51) -> 8258857.1 | I52: =SUM(I47:I51) -> 240624.33 | J52: =SUM(J47:J51) -> 0 | K52: =SUM(K47:K51) -> 19757627 | ... O52: =SUM(O47:O51) -> 19757627 | T52: TOTAL | U52: =SUM(U47:U51) -> 2097769.1 | V52: =SUM(V47:V51) -> 2646701.2 | W52: =SUM(W47:W51) -> 13336627 | X52: =SUM(X47:X51) -> 4792063.2 | Y52: =SUM(Y47:Y51) -> 395263.26 | Z52: =SUM(Z47:Z51) -> 0 | AA52: =SUM(AA47:AA51) -> -105.56 | AB52: =SUM(AB47:AB51) -> 0 | ... AG52: =SUM(AG47:AG51) -> -2.0372681e-09 | AH52: =INT(AG52)=0 -> FALSE
Y54: =SUM(U52:Y52) -> 23268424
F56: Firma autorizada
F60: PROCERASEO S.A.S. | I60: NIT: 901 153 639 - 0 | M60: Codigo Remuneración: | N60: =N3 -> 2026101 | U60: PROCERASEO S.A.S. | W60: NIT: 901 153 639 - 0 | AA60: Codigo Remuneración: | AD60: =N60 -> 2026101
F61: 3. ESQUEMA FINANCIERO DEL SERVICIO PUBLICO DE ASEO | U61: 3. ESQUEMA FINANCIERO DEL SERVICIO PUBLICO DE ASEO
F62: Resoluciòn UAESP Número 27 de 2018 | U62: Resoluciòn UAESP Número 27 de 2018
C63: Fecha de Proceso: | D63: =D6 -> 46297 | F63: R4 - REVERSIÓN DE PAGOS | U63: R4 - REVERSIÓN DE PAGOS
C64: Hora: | D64: =D7 -> 0.58333333 | F64: Fecha Desde: | G64: =G7 -> 46296 | J64: Feha Hasta: | K64: =K7 -> 46310 | U64: =F64 -> Fecha Desde: | V64: =G64 -> 46296 | X64: =J64 -> Feha Hasta: | Y64: =K64 -> 46310
B65: ASE | C65: Concesionarios | D65: Recaudo Total | E65: Recaudo por disposicion final | F65: Recaudo por tratamiento de lixiviados | G65: Recaudo por Componente VIAT ( Decreto 2412/2018) | H65: Recaudo por aprovechamiento | I65: Recaudo del componente de comercializacion para Aprovechamiento (11,4%) | J65: Balance de subsidio o contribuciones | K65: RECAUDO BASE DE REMUNERACION | L65: Costo de la Interventoría | M65: REMUNERACION FINAL | N65: Conceptos especiales | O65: REMUNERACION FINAL MAS CONCEPTOS ESPECIALES | S65: ASE | T65: Concesionarios | U65: Tarifa de Comercialización del Servicio. ( TCS) | V65: Tarifa de Limpieza Urbana del Servicio. ( TLU) | W65: Tarifa de Barrido y Limpieza del Servicio. ( TBL) | X65: Tarifa de Recolección y Transporte del Servicio. (TRT) | Y65: Recaudo del componente de comercializacion para Aprovechamiento (18,6%) | Z65: Costo de la Interventoría | AA65: Ajuste a la decena | AB65: Conceptos especiales | AC65: Otros | AD65: Diferencial Balance S / C (Fac vs Rec) | AE65: Balance S / C Con Base en (Recaudo) | AF65: REMUNERACION FINAL MAS CONCEPTOS ESPECIALES
B66: 1 | C66: PROMOAMBIENTAL DISTRITO S.A.S. ESP. | D66: ='Reversion Pagos R4'!D79 -> -3833780 | E66: ='Reversion Pagos R4'!E79 -> 0 | F66: ='Reversion Pagos R4'!F79 -> 0 | G66: ='Reversion Pagos R4'!G79 -> 0 | H66: ='Reversion Pagos R4'!H79 -> 0 | I66: ='Reversion Pagos R4'!I79 -> 0 | J66: 0 | K66: =D66-E66-F66-G66-H66-I66-J66 -> -3833780 | L66: 0 | M66: =K66-L66 -> -3833780 | N66: ='Reversion Pagos R4'!P79 -> 0 | O66: =M66+N66 -> -3833780 | S66: 1 | T66: PROMOAMBIENTAL DISTRITO S.A.S. ESP. | U66: ='Reversion Pagos R4'!J79 -> 0 | V66: ='Reversion Pagos R4'!K79 -> 0 | W66: ='Reversion Pagos R4'!L79 -> 0 | X66: ='Reversion Pagos R4'!M79 -> 0 | Y66: ='Reversion Pagos R4'!N79 -> 0 | Z66: =-L66 -> 0 | AA66: ='Reversion Pagos R4'!O79 -> 0 | AB66: =N66 -> 0 | AC66: =+'Reversion Pagos R4'!Q79+'Reversion Pagos R4'!R79 -> 0 | AD66: =-J66+AE66 -> 0 | AE66: ='Reversion Pagos R4'!D80 -> 0 | AF66: =SUM(U66:AD66) -> 0 | AG66: =(AF66-O66) -> 3833780 | AH66: =INT(AG66)=0 -> FALSE
B67: 2 | C67: LIMPIEZA METROPOLITANA S.A. ESP. | D67: ='Reversion Pagos R4'!D180 -> -21803648 | E67: ='Reversion Pagos R4'!E180 -> 0 | F67: ='Reversion Pagos R4'!F180 -> 0 | G67: ='Reversion Pagos R4'!G180 -> 0 | H67: ='Reversion Pagos R4'!H180 -> 0 | I67: ='Reversion Pagos R4'!I180 -> 0 | J67: 0 | K67: =D67-E67-F67-G67-H67-I67-J67 -> -21803648 | L67: 0 | M67: =K67-L67 -> -21803648 | N67: ='Reversion Pagos R4'!P180 -> 0 | O67: =M67+N67 -> -21803648 | S67: 2 | T67: LIMPIEZA METROPOLITANA S.A. ESP. | U67: ='Reversion Pagos R4'!J180 -> 0 | V67: ='Reversion Pagos R4'!K180 -> 0 | W67: ='Reversion Pagos R4'!L180 -> 0 | X67: ='Reversion Pagos R4'!M180 -> 0 | Y67: ='Reversion Pagos R4'!N180 -> 0 | Z67: =-L67 -> 0 | AA67: ='Reversion Pagos R4'!O180 -> 0 | AB67: =N67 -> 0 | AC67: =+'Reversion Pagos R4'!Q180+'Reversion Pagos R4'!R180 -> 0 | AD67: =-J67+AE67 -> 0 | AE67: ='Reversion Pagos R4'!D181 -> 0 | AF67: =SUM(U67:AD67) -> 0 | AG67: =(AF67-O67) -> 21803648 | AH67: =INT(AG67)=0 -> FALSE
B68: 3 | C68: CIUDAD LIMPIA BOGOTA S.A. ESP. | D68: ='Reversion Pagos R4'!D217 -> -2259272 | E68: ='Reversion Pagos R4'!E217 -> 0 | F68: ='Reversion Pagos R4'!F217 -> 0 | G68: ='Reversion Pagos R4'!G217 -> 0 | H68: ='Reversion Pagos R4'!H217 -> 0 | I68: ='Reversion Pagos R4'!I217 -> 0 | J68: 0 | K68: =D68-E68-F68-G68-H68-I68-J68 -> -2259272 | L68: 0 | M68: =K68-L68 -> -2259272 | N68: ='Reversion Pagos R4'!P217 -> 0 | O68: =M68+N68 -> -2259272 | S68: 3 | T68: CIUDAD LIMPIA BOGOTA S.A. ESP. | U68: ='Reversion Pagos R4'!J217 -> 0 | V68: ='Reversion Pagos R4'!K217 -> 0 | W68: ='Reversion Pagos R4'!L217 -> 0 | X68: ='Reversion Pagos R4'!M217 -> 0 | Y68: ='Reversion Pagos R4'!N217 -> 0 | Z68: =-L68 -> 0 | AA68: ='Reversion Pagos R4'!O217 -> 0 | AB68: =N68 -> 0 | AC68: =+'Reversion Pagos R4'!Q217+'Reversion Pagos R4'!R217 -> 0 | AD68: =-J68+AE68 -> 0 | AE68: ='Reversion Pagos R4'!D218 -> 0 | AF68: =SUM(U68:AD68) -> 0 | AG68: =(AF68-O68) -> 2259272 | AH68: =INT(AG68)=0 -> FALSE
B69: 4 | C69: BOGOTA LIMPIA S.A.S. ESP. | D69: ='Reversion Pagos R4'!D332 -> -41558585 | E69: ='Reversion Pagos R4'!E332 -> 0 | F69: ='Reversion Pagos R4'!F332 -> 0 | G69: ='Reversion Pagos R4'!G332 -> 0 | H69: ='Reversion Pagos R4'!H332 -> 0 | I69: ='Reversion Pagos R4'!I332 -> 0 | J69: 0 | K69: =D69-E69-F69-G69-H69-I69-J69 -> -41558585 | L69: 0 | M69: =K69-L69 -> -41558585 | N69: ='Reversion Pagos R4'!P332 -> 0 | O69: =M69+N69 -> -41558585 | S69: 4 | T69: BOGOTA LIMPIA S.A.S. ESP. | U69: ='Reversion Pagos R4'!J332 -> 0 | V69: ='Reversion Pagos R4'!K332 -> 0 | W69: ='Reversion Pagos R4'!L332 -> 0 | X69: ='Reversion Pagos R4'!M332 -> 0 | Y69: ='Reversion Pagos R4'!N332 -> 0 | Z69: =-L69 -> 0 | AA69: ='Reversion Pagos R4'!O332 -> 0 | AB69: =N69 -> 0 | AC69: =+'Reversion Pagos R4'!Q332+'Reversion Pagos R4'!R332 -> 0 | AD69: =-J69+AE69 -> 0 | AE69: ='Reversion Pagos R4'!D333 -> 0 | AF69: =SUM(U69:AD69) -> 0 | AG69: =(AF69-O69) -> 41558585 | AH69: =INT(AG69)=0 -> FALSE
B70: 5 | C70: AREA LIMPIA DISTRITO CAPITAL S.A.S. ESP. | D70: ='Reversion Pagos R4'!D373 -> -3964157 | E70: ='Reversion Pagos R4'!E373 -> 0 | F70: ='Reversion Pagos R4'!F373 -> 0 | G70: ='Reversion Pagos R4'!G373 -> 0 | H70: ='Reversion Pagos R4'!H373 -> 0 | I70: ='Reversion Pagos R4'!I373 -> 0 | J70: 0 | K70: =D70-E70-F70-G70-H70-I70-J70 -> -3964157 | L70: 0 | M70: =K70-L70 -> -3964157 | N70: ='Reversion Pagos R4'!P373 -> 0 | O70: =M70+N70 -> -3964157 | S70: 5 | T70: AREA LIMPIA DISTRITO CAPITAL S.A.S. ESP. | U70: ='Reversion Pagos R4'!J373 -> 0 | V70: ='Reversion Pagos R4'!K373 -> 0 | W70: ='Reversion Pagos R4'!L373 -> 0 | X70: ='Reversion Pagos R4'!M373 -> 0 | Y70: ='Reversion Pagos R4'!N373 -> 0 | Z70: =-L70 -> 0 | AA70: ='Reversion Pagos R4'!O373 -> 0 | AB70: =N70 -> 0 | AC70: =+'Reversion Pagos R4'!Q373+'Reversion Pagos R4'!R373 -> 0 | AD70: =-J70+AE70 -> 0 | AE70: ='Reversion Pagos R4'!D374 -> 0 | AF70: =SUM(U70:AD70) -> 0 | AG70: =(AF70-O70) -> 3964157 | AH70: =INT(AG70)=0 -> FALSE
C71: TOTAL | D71: =SUM(D66:D70) -> -73419443 | E71: =SUM(E66:E70) -> 0 | F71: =SUM(F66:F70) -> 0 | G71: =SUM(G66:G70) -> 0 | H71: =SUM(H66:H70) -> 0 | I71: =SUM(I66:I70) -> 0 | J71: =SUM(J66:J70) -> 0 | K71: =SUM(K66:K70) -> -73419443 | ... O71: =SUM(O66:O70) -> -73419443 | T71: TOTAL | U71: =SUM(U66:U70) -> 0 | V71: =SUM(V66:V70) -> 0 | W71: =SUM(W66:W70) -> 0 | X71: =SUM(X66:X70) -> 0 | Y71: =SUM(Y66:Y70) -> 0 | Z71: =SUM(Z66:Z70) -> 0 | AA71: =SUM(AA66:AA70) -> 0 | AB71: =SUM(AB66:AB70) -> 0 | ... AG71: =SUM(AG66:AG70) -> 73419443 | AH71: =INT(AG71)=0 -> FALSE
Y73: =SUM(U71:Y71) -> 0
F75: Firma autorizada
F79: PROCERASEO S.A.S. | I79: NIT: 901 153 639 - 0 | M79: Codigo Remuneración: | N79: =N3 -> 2026101 | U79: PROCERASEO S.A.S. | W79: NIT: 901 153 639 - 0 | AA79: Codigo Remuneración: | AD79: =N79 -> 2026101
F80: 3. ESQUEMA FINANCIERO DEL SERVICIO PUBLICO DE ASEO | U80: 3. ESQUEMA FINANCIERO DEL SERVICIO PUBLICO DE ASEO
F81: Resoluciòn UAESP Número 27 de 2018 | U81: Resoluciòn UAESP Número 27 de 2018
C82: Fecha de Proceso: | D82: =D6 -> 46297 | F82: R5 - REMUNERACIÓN SALDOS A FAVOR POR NOTA | U82: =F82 -> R5 - REMUNERACIÓN SALDOS A FAVOR POR NOTA
C83: Hora: | D83: =D7 -> 0.58333333 | F83: Fecha Desde: | G83: =G7 -> 46296 | J83: Feha Hasta: | K83: =K7 -> 46310 | U83: =F83 -> Fecha Desde: | V83: =G83 -> 46296 | X83: =J83 -> Feha Hasta: | Y83: =K83 -> 46310
B84: ASE | C84: Concesionarios | D84: Recaudo Total | E84: Recaudo por disposicion final | F84: Recaudo por tratamiento de lixiviados | G84: Recaudo por Componente VIAT ( Decreto 2412/2018) | H84: Recaudo por aprovechamiento | I84: Recaudo del componente de comercializacion para Aprovechamiento (11,4%) | J84: Balance de subsidio o contribuciones | K84: RECAUDO BASE DE REMUNERACION | L84: Costo de la Interventoría | M84: REMUNERACION FINAL | N84: Conceptos especiales | O84: REMUNERACION FINAL MAS CONCEPTOS ESPECIALES | S84: ASE | T84: Concesionarios | U84: Tarifa de Comercialización del Servicio. ( TCS) | V84: Tarifa de Limpieza Urbana del Servicio. ( TLU) | W84: Tarifa de Barrido y Limpieza del Servicio. ( TBL) | X84: Tarifa de Recolección y Transporte del Servicio. (TRT) | Y84: Recaudo del componente de comercializacion para Aprovechamiento (18,6%) | Z84: Costo de la Interventoría | AA84: Ajuste a la decena | AB84: Conceptos especiales | AC84: Otros | AD84: Diferencial Balance Subsidio y Contribución (Fac vs Rec) | AE84: Balance de subsidio o contribuciones (Recaudo) | AF84: REMUNERACION FINAL MAS CONCEPTOS ESPECIALES
B85: 1 | C85: PROMOAMBIENTAL DISTRITO S.A.S. ESP. | D85: ='AJUSTES - SF-T'!D47 -> 0 | E85: ='AJUSTES - SF-T'!E47 -> 0 | F85: ='AJUSTES - SF-T'!F47 -> 0 | G85: ='AJUSTES - SF-T'!G47 -> 0 | H85: ='AJUSTES - SF-T'!H47 -> 0 | I85: ='AJUSTES - SF-T'!I47 -> 0 | J85: ='AJUSTES - SF-T'!J47 -> 0 | K85: =D85-E85-F85-G85-H85-I85-J85 -> 0 | L85: 0 | M85: =K85-L85 -> 0 | N85: ='AJUSTES - SF-T'!N47 -> 0 | O85: =M85+N85 -> 0 | S85: 1 | T85: PROMOAMBIENTAL DISTRITO S.A.S. ESP. | U85: ='AJUSTES - SF-T'!U47 -> 0 | V85: ='AJUSTES - SF-T'!V47 -> 0 | W85: ='AJUSTES - SF-T'!W47 -> 0 | X85: ='AJUSTES - SF-T'!X47 -> 0 | Y85: ='AJUSTES - SF-T'!Y47 -> 0 | Z85: =-L85 -> 0 | AA85: ='AJUSTES - SF-T'!AA47 -> 0 | AB85: =N85 -> 0 | AC85: 0 | AD85: =-J85+AE85 -> 0 | AE85: ='AJUSTES - SF-T'!AD47 -> 0 | AF85: =SUM(U85:AD85) -> 0 | AG85: =AF85-O85 -> 0 | AH85: =INT(AG85)=0 -> TRUE
B86: 2 | C86: LIMPIEZA METROPOLITANA S.A. ESP. | D86: ='AJUSTES - SF-T'!D48 -> 0 | E86: ='AJUSTES - SF-T'!E48 -> 0 | F86: ='AJUSTES - SF-T'!F48 -> 0 | G86: ='AJUSTES - SF-T'!G48 -> 0 | H86: ='AJUSTES - SF-T'!H48 -> 0 | I86: ='AJUSTES - SF-T'!I48 -> 0 | J86: ='AJUSTES - SF-T'!J48 -> 0 | K86: =D86-E86-F86-G86-H86-I86-J86 -> 0 | L86: 0 | M86: =K86-L86 -> 0 | N86: ='AJUSTES - SF-T'!N48 -> 0 | O86: =M86+N86 -> 0 | S86: 2 | T86: LIMPIEZA METROPOLITANA S.A. ESP. | U86: ='AJUSTES - SF-T'!U48 -> 0 | V86: ='AJUSTES - SF-T'!V48 -> 0 | W86: ='AJUSTES - SF-T'!W48 -> 0 | X86: ='AJUSTES - SF-T'!X48 -> 0 | Y86: ='AJUSTES - SF-T'!Y48 -> 0 | Z86: =-L86 -> 0 | AA86: ='AJUSTES - SF-T'!AA48 -> 0 | AB86: =N86 -> 0 | AC86: 0 | AD86: =-J86+AE86 -> 0 | AE86: ='AJUSTES - SF-T'!AD48 -> 0 | AF86: =SUM(U86:AD86) -> 0 | AG86: =AF86-O86 -> 0 | AH86: =INT(AG86)=0 -> TRUE
B87: 3 | C87: CIUDAD LIMPIA BOGOTA S.A. ESP. | D87: ='AJUSTES - SF-T'!D49 -> 0 | E87: ='AJUSTES - SF-T'!E49 -> 0 | F87: ='AJUSTES - SF-T'!F49 -> 0 | G87: ='AJUSTES - SF-T'!G49 -> 0 | H87: ='AJUSTES - SF-T'!H49 -> 0 | I87: ='AJUSTES - SF-T'!I49 -> 0 | J87: ='AJUSTES - SF-T'!J49 -> 0 | K87: =D87-E87-F87-G87-H87-I87-J87 -> 0 | L87: 0 | M87: =K87-L87 -> 0 | N87: ='AJUSTES - SF-T'!N49 -> 0 | O87: =M87+N87 -> 0 | S87: 3 | T87: CIUDAD LIMPIA BOGOTA S.A. ESP. | U87: ='AJUSTES - SF-T'!U49 -> 0 | V87: ='AJUSTES - SF-T'!V49 -> 0 | W87: ='AJUSTES - SF-T'!W49 -> 0 | X87: ='AJUSTES - SF-T'!X49 -> 0 | Y87: ='AJUSTES - SF-T'!Y49 -> 0 | Z87: =-L87 -> 0 | AA87: ='AJUSTES - SF-T'!AA49 -> 0 | AB87: =N87 -> 0 | AC87: 0 | AD87: =-J87+AE87 -> 0 | AE87: ='AJUSTES - SF-T'!AD49 -> 0 | AF87: =SUM(U87:AD87) -> 0 | AG87: =AF87-O87 -> 0 | AH87: =INT(AG87)=0 -> TRUE
B88: 4 | C88: BOGOTA LIMPIA S.A.S. ESP. | D88: ='AJUSTES - SF-T'!D50 -> 0 | E88: ='AJUSTES - SF-T'!E50 -> 0 | F88: ='AJUSTES - SF-T'!F50 -> 0 | G88: ='AJUSTES - SF-T'!G50 -> 0 | H88: ='AJUSTES - SF-T'!H50 -> 0 | I88: ='AJUSTES - SF-T'!I50 -> 0 | J88: ='AJUSTES - SF-T'!J50 -> 0 | K88: =D88-E88-F88-G88-H88-I88-J88 -> 0 | L88: 0 | M88: =K88-L88 -> 0 | N88: ='AJUSTES - SF-T'!N50 -> 0 | O88: =M88+N88 -> 0 | S88: 4 | T88: BOGOTA LIMPIA S.A.S. ESP. | U88: ='AJUSTES - SF-T'!U50 -> 0 | V88: ='AJUSTES - SF-T'!V50 -> 0 | W88: ='AJUSTES - SF-T'!W50 -> 0 | X88: ='AJUSTES - SF-T'!X50 -> 0 | Y88: ='AJUSTES - SF-T'!Y50 -> 0 | Z88: =-L88 -> 0 | AA88: ='AJUSTES - SF-T'!AA50 -> 0 | AB88: =N88 -> 0 | AC88: 0 | AD88: =-J88+AE88 -> 0 | AE88: ='AJUSTES - SF-T'!AD50 -> 0 | AF88: =SUM(U88:AD88) -> 0 | AG88: =AF88-O88 -> 0 | AH88: =INT(AG88)=0 -> TRUE
B89: 5 | C89: AREA LIMPIA DISTRITO CAPITAL S.A.S. ESP. | D89: ='AJUSTES - SF-T'!D51 -> 0 | E89: ='AJUSTES - SF-T'!E51 -> 0 | F89: ='AJUSTES - SF-T'!F51 -> 0 | G89: ='AJUSTES - SF-T'!G51 -> 0 | H89: ='AJUSTES - SF-T'!H51 -> 0 | I89: ='AJUSTES - SF-T'!I51 -> 0 | J89: ='AJUSTES - SF-T'!J51 -> 0 | K89: =D89-E89-F89-G89-H89-I89-J89 -> 0 | L89: 0 | M89: =K89-L89 -> 0 | N89: ='AJUSTES - SF-T'!N51 -> 0 | O89: =M89+N89 -> 0 | S89: 5 | T89: AREA LIMPIA DISTRITO CAPITAL S.A.S. ESP. | U89: ='AJUSTES - SF-T'!U51 -> 0 | V89: ='AJUSTES - SF-T'!V51 -> 0 | W89: ='AJUSTES - SF-T'!W51 -> 0 | X89: ='AJUSTES - SF-T'!X51 -> 0 | Y89: ='AJUSTES - SF-T'!Y51 -> 0 | Z89: =-L89 -> 0 | AA89: ='AJUSTES - SF-T'!AA51 -> 0 | AB89: =N89 -> 0 | AC89: 0 | AD89: =-J89+AE89 -> 0 | AE89: ='AJUSTES - SF-T'!AD51 -> 0 | AF89: =SUM(U89:AD89) -> 0 | AG89: =AF89-O89 -> 0 | AH89: =INT(AG89)=0 -> TRUE
C90: TOTAL | D90: =SUM(D85:D89) -> 0 | E90: =SUM(E85:E89) -> 0 | F90: =SUM(F85:F89) -> 0 | G90: =SUM(G85:G89) -> 0 | H90: =SUM(H85:H89) -> 0 | I90: =SUM(I85:I89) -> 0 | J90: =SUM(J85:J89) -> 0 | K90: =SUM(K85:K89) -> 0 | ... O90: =SUM(O85:O89) -> 0 | T90: TOTAL | U90: =SUM(U85:U89) -> 0 | V90: =SUM(V85:V89) -> 0 | W90: =SUM(W85:W89) -> 0 | X90: =SUM(X85:X89) -> 0 | Y90: =SUM(Y85:Y89) -> 0 | Z90: =SUM(Z85:Z89) -> 0 | AA90: =SUM(AA85:AA89) -> 0 | AB90: =SUM(AB85:AB89) -> 0 | ... AG90: =SUM(AG85:AG89) -> 0 | AH90: =INT(AG90)=0 -> TRUE
Y92: =SUM(U90:Y90) -> 0
F94: Firma autorizada
F98: PROCERASEO S.A.S. | I98: NIT: 901 153 639 - 0 | M98: Codigo Remuneración: | N98: =N3 -> 2026101 | U98: PROCERASEO S.A.S. | W98: NIT: 901 153 639 - 0 | AA98: Codigo Remuneración: | AD98: =N98 -> 2026101
F99: 3. ESQUEMA FINANCIERO DEL SERVICIO PUBLICO DE ASEO | U99: 3. ESQUEMA FINANCIERO DEL SERVICIO PUBLICO DE ASEO
F100: Resoluciòn UAESP Número 27 de 2018 | U100: Resoluciòn UAESP Número 27 de 2018
C101: Fecha de Proceso: | D101: =D6 -> 46297 | F101: REPORTE CONSOLIDADO TOTAL DE RECAUDO | U101: REPORTE DETALLADO SUBBOLSA RBL DISCRIMINADO POR ACTIVIDADES
C102: Hora: | D102: =D7 -> 0.58333333 | F102: Fecha Desde: | G102: =G7 -> 46296 | J102: Feha Hasta: | K102: =K7 -> 46310 | U102: =F102 -> Fecha Desde: | V102: =G102 -> 46296 | X102: =J102 -> Feha Hasta: | Y102: =K102 -> 46310
B103: ASE | C103: Concesionarios | D103: Recaudo Total | E103: Recaudo por disposicion final | F103: Recaudo por tratamiento de lixiviados | G103: Recaudo por Componente VIAT ( Decreto 2412/2018) | H103: Recaudo por aprovechamiento | I103: Recaudo del componente de comercializacion para Aprovechamiento (11,4%) | J103: Balance de subsidio o contribuciones | K103: RECAUDO BASE DE REMUNERACION | L103: Costo de la Interventoría | M103: REMUNERACION FINAL | N103: Conceptos especiales | O103: REMUNERACION FINAL MAS CONCEPTOS ESPECIALES | S103: ASE | T103: Concesionarios | U103: Tarifa de Comercialización del Servicio. ( TCS) | V103: Tarifa de Limpieza Urbana del Servicio. ( TLU) | W103: Tarifa de Barrido y Limpieza del Servicio. ( TBL) | X103: Tarifa de Recolección y Transporte del Servicio. (TRT) | Y103: Recaudo del componente de comercializacion para Aprovechamiento (18,6%) | Z103: Costo de la Interventoría | AA103: Ajuste a la decena | AB103: Conceptos especiales | AC103: Otros | AD103: Diferencial Balance Subsidio y Contribución (Fac vs Rec) | AE103: Balance de subsidio o contribuciones (Recaudo) | AF103: REMUNERACION FINAL MAS CONCEPTOS ESPECIALES
B104: 1 | C104: PROMOAMBIENTAL DISTRITO S.A.S. ESP. | D104: =D9+D28+D47+D66+D85 -> 1.4842425e+10 | E104: =E9+E28+E47+E66+E85 -> 8.4183526e+08 | F104: =F9+F28+F47+F66+F85 -> 4.6893443e+08 | G104: =G9+G28+G47+G66+G85 -> 2.4966558e+08 | H104: =H9+H28+H47+H66+H85 -> 4.7569875e+09 | I104: =I9+I28+I47+I66+I85 -> 1.585038e+08 | J104: =J9+J28+J47+J66+J85 -> 2.1539508e+09 | K104: =D104-E104-F104-G104-H104-I104-J104 -> 6.2125477e+09 | L104: =L9+L28+L47+L66+L85 -> 189185987 | M104: =K104-L104 -> 6.0233617e+09 | N104: =N9+N28+N47+N66+N85 -> 19931693 | O104: =M104+N104 -> 6.0432934e+09 | S104: 1 | T104: PROMOAMBIENTAL DISTRITO S.A.S. ESP. | U104: =U9+U28+U47+U66+U85 -> 1.3917867e+09 | V104: =V9+V28+V47+V66+V85 -> 1.3160099e+09 | W104: =W9+W28+W47+W66+W85 -> 6.2724749e+09 | X104: =X9+X28+X47+X66+X85 -> 2.2909689e+09 | Y104: =Y9+Y28+Y47+Y66+Y85 -> 2.5875437e+08 | Z104: =Z9+Z28+Z47+Z66+Z85 -> -189185987 | AA104: =AA9+AA28+AA47+AA66+AA85 -> -27796.54 | AB104: =AB9+AB28+AB47+AB66+AB85 -> 19931693 | AC104: =AC9+AC28+AC47+AC66+AC85 -> 149.13 | AD104: =-J104+AE104 -> -5.3448624e+09 | AE104: =AE9+AE28+AE47+AE66+AE85 -> -3.1909116e+09 | AF104: =SUM(U104:AD104) -> 6.0158505e+09 | AG104: =AF104-O104 -> -27442962 | AH104: =INT(AG104)=0 -> FALSE
B105: 2 | C105: LIMPIEZA METROPOLITANA S.A. ESP. | D105: =D10+D29+D48+D67+D86 -> 1.1302638e+10 | E105: =E10+E29+E48+E67+E86 -> 8.7390614e+08 | F105: =F10+F29+F48+F67+F86 -> 4.8383019e+08 | G105: =G10+G29+G48+G67+G86 -> 2.5650592e+08 | H105: =H10+H29+H48+H67+H86 -> 3.5765566e+09 | I105: =I10+I29+I48+I67+I86 -> 1.2670704e+08 | J105: =J10+J29+J48+J67+J86 -> -4.2171455e+09 | K105: =D105-E105-F105-G105-H105-I105-J105 -> 1.0202277e+10 | L105: =L10+L29+L48+L67+L86 -> 266580255 | M105: =K105-L105 -> 9.935697e+09 | N105: =N10+N29+N48+N67+N86 -> 9905072.8 | O105: =M105+N105 -> 9.945602e+09 | S105: 2 | T105: LIMPIEZA METROPOLITANA S.A. ESP. | U105: =U10+U29+U48+U67+U86 -> 1.1116947e+09 | V105: =V10+V29+V48+V67+V86 -> 1.0690818e+09 | W105: =W10+W29+W48+W67+W86 -> 5.0791484e+09 | X105: =X10+X29+X48+X67+X86 -> 1.7140982e+09 | Y105: =Y10+Y29+Y48+Y67+Y86 -> 2.0689254e+08 | Z105: =Z10+Z29+Z48+Z67+Z86 -> -266580255 | AA105: =AA10+AA29+AA48+AA67+AA86 -> -14306.29 | AB105: =AB10+AB29+AB48+AB67+AB86 -> 9905072.8 | AC105: =AC10+AC29+AC48+AC67+AC86 -> -56307.77 | AD105: =-J105+AE105 -> 9.2689614e+08 | AE105: =AE10+AE29+AE48+AE67+AE86 -> -3.2902494e+09 | AF105: =SUM(U105:AD105) -> 9.851066e+09 | AG105: =AF105-O105 -> -94536035 | AH105: =INT(AG105)=0 -> FALSE
B106: 3 | C106: CIUDAD LIMPIA BOGOTA S.A. ESP. | D106: =D11+D30+D49+D68+D87 -> 8.8237873e+09 | E106: =E11+E30+E49+E68+E87 -> 5.6904906e+08 | F106: =F11+F30+F49+F68+F87 -> 3.1726749e+08 | G106: =G11+G30+G49+G68+G87 -> 1.685178e+08 | H106: =H11+H30+H49+H68+H87 -> 2.4290215e+09 | I106: =I11+I30+I49+I68+I87 -> 86984011 | J106: =J11+J30+J49+J68+J87 -> -1.2888063e+09 | K106: =D106-E106-F106-G106-H106-I106-J106 -> 6.5417537e+09 | L106: =L11+L30+L49+L68+L87 -> 154788535 | M106: =K106-L106 -> 6.3869652e+09 | N106: =N11+N30+N49+N68+N87 -> 19321800 | O106: =M106+N106 -> 6.406287e+09 | S106: 3 | T106: CIUDAD LIMPIA BOGOTA S.A. ESP. | U106: =U11+U30+U49+U68+U87 -> 7.636827e+08 | V106: =V11+V30+V49+V68+V87 -> 7.2501882e+08 | W106: =W11+W30+W49+W68+W87 -> 3.4442559e+09 | X106: =X11+X30+X49+X68+X87 -> 1.3479162e+09 | Y106: =Y11+Y30+Y49+Y68+Y87 -> 1.4202598e+08 | Z106: =Z11+Z30+Z49+Z68+Z87 -> -154788535 | AA106: =AA11+AA30+AA49+AA68+AA87 -> -81704.87 | AB106: =AB11+AB30+AB49+AB68+AB87 -> 19321800 | AC106: =AC11+AC30+AC49+AC68+AC87 -> -41619.9 | AD106: =-J106+AE106 -> 1.0279504e+08 | AE106: =AE11+AE30+AE49+AE68+AE87 -> -1.1860113e+09 | AF106: =SUM(U106:AD106) -> 6.3901045e+09 | AG106: =AF106-O106 -> -16182486 | AH106: =INT(AG106)=0 -> FALSE
B107: 4 | C107: BOGOTA LIMPIA S.A.S. ESP. | D107: =D12+D31+D50+D69+D88 -> 1.0483173e+10 | E107: =E12+E31+E50+E69+E88 -> 6.0594876e+08 | F107: =F12+F31+F50+F69+F88 -> 3.3589527e+08 | G107: =G12+G31+G50+G69+G88 -> 1.7910861e+08 | H107: =H12+H31+H50+H69+H88 -> 2.4013668e+09 | I107: =I12+I31+I50+I69+I88 -> 89808012 | J107: =J12+J31+J50+J69+J88 -> 61531954 | K107: =D107-E107-F107-G107-H107-I107-J107 -> 6.8095134e+09 | L107: =L12+L31+L50+L69+L88 -> 120391083 | M107: =K107-L107 -> 6.6891223e+09 | N107: =N12+N31+N50+N69+N88 -> 8643135.6 | O107: =M107+N107 -> 6.6977654e+09 | S107: 4 | T107: BOGOTA LIMPIA S.A.S. ESP. | U107: =U12+U31+U50+U69+U88 -> 7.8716576e+08 | V107: =V12+V31+V50+V69+V88 -> 7.5159381e+08 | W107: =W12+W31+W50+W69+W88 -> 3.8891637e+09 | X107: =X12+X31+X50+X69+X88 -> 1.604125e+09 | Y107: =Y12+Y31+Y50+Y69+Y88 -> 1.4678308e+08 | Z107: =Z12+Z31+Z50+Z69+Z88 -> -120391083 | AA107: =AA12+AA31+AA50+AA69+AA88 -> 31933.3 | AB107: =AB12+AB31+AB50+AB69+AB88 -> 8643135.6 | AC107: =AC12+AC31+AC50+AC69+AC88 -> 189.43 | AD107: =-J107+AE107 -> -3.5661528e+08 | AE107: =AE12+AE31+AE50+AE69+AE88 -> -2.9508333e+08 | AF107: =SUM(U107:AD107) -> 6.7105002e+09 | AG107: =AF107-O107 -> 12734829 | AH107: =INT(AG107)=0 -> FALSE
B108: 5 | C108: AREA LIMPIA DISTRITO CAPITAL S.A.S. ESP. | D108: =D13+D32+D51+D70+D89 -> 7.5506687e+09 | E108: =E13+E32+E51+E70+E89 -> 4.0814547e+08 | F108: =F13+F32+F51+F70+F89 -> 2.2711804e+08 | G108: =G13+G32+G51+G70+G89 -> 1.2084103e+08 | H108: =H13+H32+H51+H70+H89 -> 1.8642679e+09 | I108: =I13+I32+I51+I70+I89 -> 62073127 | J108: =J13+J32+J51+J70+J89 -> -1.2464731e+09 | K108: =D108-E108-F108-G108-H108-I108-J108 -> 6.1146962e+09 | L108: =L13+L32+L51+L70+L89 -> 128990445 | M108: =K108-L108 -> 5.9857058e+09 | N108: =N13+N32+N51+N70+N89 -> 12379938 | O108: =M108+N108 -> 5.9980857e+09 | S108: 5 | T108: AREA LIMPIA DISTRITO CAPITAL S.A.S. ESP. | U108: =U13+U32+U51+U70+U89 -> 5.4468434e+08 | V108: =V13+V32+V51+V70+V89 -> 5.1295881e+08 | W108: =W13+W32+W51+W70+W89 -> 2.6405604e+09 | X108: =X13+X32+X51+X70+X89 -> 1.2146777e+09 | Y108: =Y13+Y32+Y51+Y70+Y89 -> 101292451 | Z108: =Z13+Z32+Z51+Z70+Z89 -> -128990445 | AA108: =AA13+AA32+AA51+AA70+AA89 -> 10679.52 | AB108: =AB13+AB32+AB51+AB70+AB89 -> 12379938 | AC108: =AC13+AC32+AC51+AC70+AC89 -> 4.86 | AD108: =-J108+AE108 -> 1.094063e+09 | AE108: =AE13+AE32+AE51+AE70+AE89 -> -1.5241006e+08 | AF108: =SUM(U108:AD108) -> 5.991637e+09 | AG108: =AF108-O108 -> -6448709.1 | AH108: =INT(AG108)=0 -> FALSE
C109: TOTAL | D109: =SUM(D104:D108) -> 5.3002691e+10 | E109: =SUM(E104:E108) -> 3.2988847e+09 | F109: =SUM(F104:F108) -> 1.8330454e+09 | G109: =SUM(G104:G108) -> 9.7463894e+08 | H109: =SUM(H104:H108) -> 1.50282e+10 | I109: =SUM(I104:I108) -> 5.2407599e+08 | J109: =SUM(J104:J108) -> -4.5369422e+09 | K109: =SUM(K104:K108) -> 3.5880788e+10 | ... O109: =SUM(O104:O108) -> 3.5091034e+10 | T109: TOTAL | U109: =SUM(U104:U108) -> 4.5990142e+09 | V109: =SUM(V104:V108) -> 4.3746631e+09 | W109: =SUM(W104:W108) -> 2.1325603e+10 | X109: =SUM(X104:X108) -> 8.171786e+09 | Y109: =SUM(Y104:Y108) -> 8.5574842e+08 | Z109: =SUM(Z104:Z108) -> -859936305 | AA109: =SUM(AA104:AA108) -> -81194.88 | AB109: =SUM(AB104:AB108) -> 70181639 | ... AG109: =SUM(AG104:AG108) -> -1.3187536e+08 | AH109: =INT(AG109)=0 -> FALSE
Y111: =SUM(U109:Y109) -> 3.9326815e+10
F113: Firma autorizada | V113: Firma autorizada
F117: PROCERASEO S.A.S. | I117: NIT: 901 153 639 - 0 | L117: Codigo Remuneración: | M117: =N3 -> 2026101
F118: 3. ESQUEMA FINANCIERO DEL SERVICIO PUBLICO DE ASEO
F119: Resoluciòn UAESP Número 27 de 2018
F121: REPORTE CONSOLIDADO DE ANTICIPOS
F122: Fecha Desde: | G122: =G7 -> 46296 | J122: Feha Hasta: | K122: =K7 -> 46310
B124: ASE | C124: Concesionarios | D124: ANTICIPOS GENERADOS | E124: PAGOS PENDIENTES POR APLICAR | G124: RECAUDO APLICADO PERIODOS ANTERIORES | H124: ANTICIPOS QUE DESCARGAN | I124: SALDOS A FAVOR POR NOTA | J124: REVERSIÓN DE PAGOS | K124: SALDOS A FAVOR GENERADOS RECAUDO EXTEMPORANEO | L124: SALDOS A FAVOR QUE DESCARGAN POR REVERSIONES
B125: 1 | C125: PROMOAMBIENTAL DISTRITO S.A.S. ESP. | D125: ='ANTICIPOS USUARIOS'!C3 -> 46857237 | E125: 0 | G125: =D47+N47 -> 648870 | H125: =D28+N28 -> 30588071 | I125: =D85+N85 -> 0 | J125: =D66+N66 -> -3833780 | K125: ='ANTICIPOS USUARIOS'!C12 -> 0 | L125: =-'ANTICIPOS USUARIOS'!C21 -> 0
B126: 2 | C126: LIMPIEZA METROPOLITANA S.A. ESP. | D126: ='ANTICIPOS USUARIOS'!C4 -> 52275662 | E126: 0 | G126: =D48+N48 -> 9704974 | H126: =D29+N29 -> 95705711 | I126: =D86+N86 -> 0 | J126: =D67+N67 -> -21803648 | K126: ='ANTICIPOS USUARIOS'!C13 -> 0 | L126: =-'ANTICIPOS USUARIOS'!C22 -> 0
B127: 3 | C127: CIUDAD LIMPIA BOGOTA S.A. ESP. | D127: ='ANTICIPOS USUARIOS'!C5 -> 13754369 | E127: 0 | G127: =D49+N49 -> 0 | H127: =D30+N30 -> 14590494 | I127: =D87+N87 -> 0 | J127: =D68+N68 -> -2259272 | K127: ='ANTICIPOS USUARIOS'!C14 -> 0 | L127: =-'ANTICIPOS USUARIOS'!C23 -> 0
B128: 4 | C128: BOGOTA LIMPIA S.A.S. ESP. | D128: ='ANTICIPOS USUARIOS'!C6 -> 49700940 | E128: 0 | G128: =D50+N50 -> 21557177 | H128: =D31+N31 -> 29206357 | I128: =D88+N88 -> 0 | J128: =D69+N69 -> -41558585 | K128: ='ANTICIPOS USUARIOS'!C15 -> 0 | L128: =-'ANTICIPOS USUARIOS'!C24 -> 0
B129: 5 | C129: AREA LIMPIA DISTRITO CAPITAL S.A.S. ESP. | D129: ='ANTICIPOS USUARIOS'!C7 -> 8596000 | E129: 0 | G129: =D51+N51 -> 0 | H129: =D32+N32 -> 10379542 | I129: =D89+N89 -> 0 | J129: =D70+N70 -> -3964157 | K129: ='ANTICIPOS USUARIOS'!C16 -> 0 | L129: =-'ANTICIPOS USUARIOS'!C25 -> 0
B130: X | C130: PENDIENTE POR APLICAR | E130: ='Recaudo Directa Occidente'!F26 -> 0
C131: TOTAL | D131: =SUM(D125:D130) -> 1.7118421e+08 | E131: =SUM(E125:E130) -> 0 | G131: =SUM(G125:G129) -> 31911021 | H131: =SUM(H125:H130) -> 1.8047018e+08 | I131: =SUM(I125:I130) -> 0 | J131: =SUM(J125:J130) -> -73419443 | K131: =SUM(K125:K130) -> 0 | L131: =SUM(L125:L130) -> 0
F135: PROCERASEO SAS
C138: VALIDACION DEL RECAUDO VERSUS REMUNERACION
B141: ASE | C141: Concesionarios | D141: Recaudo REMUNERADO | E141: RECAUDO RECIBIDO | F141: R2 - ANTICIPOS A USUARIOS | G141: R4 - REVERSION DE PAGOS | H141: R5 - SALDOS A FAVOR POR NOTA | I141: RECAUDO PENDIENTE POR REVERSAR | J141: RECAUDO APLICADO PERIODOS ANTERIORES | K141: RECAUDO APLICADO ANTICIPOS
...

Sheet VALIDACION_TOTAL
B2: ASE | C2: TOTAL RECAUDO RECIBIDO | D2: RECAUDO PERIODOS ANTERIORES | E2: (REMUNERACION) ANTICIPOS QUE DESCARGAN | F2: RECAUDO POR REVERSAR | G2: SALDOS A FAVOR POR NOTA | H2: TOTAL RECAUDO | I2: REMUNERACION RECAUDO TOTAL | J2: REMUNERACION CONCEPTOS ESPECIALES | K2: REMUNERACION ANTICIPOS GENERADOS | L2: REMUNERACION PAGOS PENDIENTES POR APLICAR | M2: REVERSION DE PAGOS | N2: TOTAL REMUNERACION
B3: 1 | C3: ='Recaudo EAAB Reciprocidad'!D21+'Recaudo EAAB + Ciud Limp'!D21+'Recaudo Directa Occidente'!D21+'Recaudo ENEL'!D21+'Recaudo ENERBIT'!D21 -> 14881810905 | D3: ='CONSOLIDADO_TOTAL RECAUDO'!G125 -> 648870 | E3: ='CONSOLIDADO_TOTAL RECAUDO'!D28+'CONSOLIDADO_TOTAL RECAUDO'!N28 -> 30588071 | F3: ='CONSOLIDADO_TOTAL RECAUDO'!I142 -> 0 | G3: ='CONSOLIDADO_TOTAL RECAUDO'!H142 -> 0 | H3: =SUM(C3:G3) -> 1.4913048e+10 | I3: ='CONSOLIDADO_TOTAL RECAUDO'!D104 -> 1.4842425e+10 | J3: ='CONSOLIDADO_TOTAL RECAUDO'!N104 -> 19931693 | K3: ='CONSOLIDADO_TOTAL RECAUDO'!D125 -> 46857237 | L3: ='CONSOLIDADO_TOTAL RECAUDO'!E125 -> 0 | M3: =-'CONSOLIDADO_TOTAL RECAUDO'!D66-'CONSOLIDADO_TOTAL RECAUDO'!N66 -> 3833780 | N3: =SUM(I3:M3) -> 1.4913048e+10 | O3: =H3-N3 -> 0 | P3: =INT(O3)=0 -> TRUE
B4: 2 | C4: ='Recaudo EAAB Reciprocidad'!D22+'Recaudo EAAB + Ciud Limp'!D22+'Recaudo Directa Occidente'!D22+'Recaudo ENEL'!D22+'Recaudo ENERBIT'!D22 -> 11279865753 | D4: ='CONSOLIDADO_TOTAL RECAUDO'!G126 -> 9704974 | E4: ='CONSOLIDADO_TOTAL RECAUDO'!D29+'CONSOLIDADO_TOTAL RECAUDO'!N29 -> 95705711 | F4: ='CONSOLIDADO_TOTAL RECAUDO'!I143 -> 1345550 | G4: ='CONSOLIDADO_TOTAL RECAUDO'!H143 -> 0 | H4: =SUM(C4:G4) -> 1.1386622e+10 | I4: ='CONSOLIDADO_TOTAL RECAUDO'!D105 -> 1.1302638e+10 | J4: ='CONSOLIDADO_TOTAL RECAUDO'!N105 -> 9905072.8 | K4: ='CONSOLIDADO_TOTAL RECAUDO'!D126 -> 52275662 | L4: ='CONSOLIDADO_TOTAL RECAUDO'!E126 -> 0 | M4: =-'CONSOLIDADO_TOTAL RECAUDO'!D67-'CONSOLIDADO_TOTAL RECAUDO'!N67 -> 21803648 | N4: =SUM(I4:M4) -> 1.1386622e+10 | O4: =H4-N4 -> 0 | P4: =INT(O4)=0 -> TRUE
B5: 3 | C5: ='Recaudo EAAB Reciprocidad'!D23+'Recaudo EAAB + Ciud Limp'!D23+'Recaudo Directa Occidente'!D23+'Recaudo ENEL'!D23+'Recaudo ENERBIT'!D23 -> 8844067825 | D5: ='CONSOLIDADO_TOTAL RECAUDO'!G127 -> 0 | E5: ='CONSOLIDADO_TOTAL RECAUDO'!D30+'CONSOLIDADO_TOTAL RECAUDO'!N30 -> 14590494 | F5: ='CONSOLIDADO_TOTAL RECAUDO'!I144 -> 464422 | G5: ='CONSOLIDADO_TOTAL RECAUDO'!H144 -> 0 | H5: =SUM(C5:G5) -> 8.8591227e+09 | I5: ='CONSOLIDADO_TOTAL RECAUDO'!D106 -> 8.8237873e+09 | J5: ='CONSOLIDADO_TOTAL RECAUDO'!N106 -> 19321800 | K5: ='CONSOLIDADO_TOTAL RECAUDO'!D127 -> 13754369 | L5: ='CONSOLIDADO_TOTAL RECAUDO'!E127 -> 0 | M5: =-'CONSOLIDADO_TOTAL RECAUDO'!D68-'CONSOLIDADO_TOTAL RECAUDO'!N68 -> 2259272 | N5: =SUM(I5:M5) -> 8.8591227e+09 | O5: =H5-N5 -> 0 | P5: =INT(O5)=0 -> TRUE
B6: 4 | C6: ='Recaudo EAAB Reciprocidad'!D24+'Recaudo EAAB + Ciud Limp'!D24+'Recaudo Directa Occidente'!D24+'Recaudo ENEL'!D24+'Recaudo ENERBIT'!D24 -> 10532093305 | D6: ='CONSOLIDADO_TOTAL RECAUDO'!G128 -> 21557177 | E6: ='CONSOLIDADO_TOTAL RECAUDO'!D31+'CONSOLIDADO_TOTAL RECAUDO'!N31 -> 29206357 | F6: ='CONSOLIDADO_TOTAL RECAUDO'!I145 -> 218584 | G6: ='CONSOLIDADO_TOTAL RECAUDO'!H145 -> 0 | H6: =SUM(C6:G6) -> 1.0583075e+10 | I6: ='CONSOLIDADO_TOTAL RECAUDO'!D107 -> 1.0483173e+10 | J6: ='CONSOLIDADO_TOTAL RECAUDO'!N107 -> 8643135.6 | K6: ='CONSOLIDADO_TOTAL RECAUDO'!D128 -> 49700940 | L6: ='CONSOLIDADO_TOTAL RECAUDO'!E128 -> 0 | M6: =-'CONSOLIDADO_TOTAL RECAUDO'!D69-'CONSOLIDADO_TOTAL RECAUDO'!N69 -> 41558585 | N6: =SUM(I6:M6) -> 1.0583075e+10 | O6: =H6-N6 -> 0 | P6: =INT(O6)=0 -> TRUE
B7: 5 | C7: ='Recaudo EAAB Reciprocidad'!D25+'Recaudo EAAB + Ciud Limp'!D25+'Recaudo Directa Occidente'!D25+'Recaudo ENEL'!D25+'Recaudo ENERBIT'!D25 -> 7564541998 | D7: ='CONSOLIDADO_TOTAL RECAUDO'!G129 -> 0 | E7: ='CONSOLIDADO_TOTAL RECAUDO'!D32+'CONSOLIDADO_TOTAL RECAUDO'!N32 -> 10379542 | F7: ='CONSOLIDADO_TOTAL RECAUDO'!I146 -> 687220 | G7: ='CONSOLIDADO_TOTAL RECAUDO'!H146 -> 0 | H7: =SUM(C7:G7) -> 7.5756088e+09 | I7: ='CONSOLIDADO_TOTAL RECAUDO'!D108 -> 7.5506687e+09 | J7: ='CONSOLIDADO_TOTAL RECAUDO'!N108 -> 12379938 | K7: ='CONSOLIDADO_TOTAL RECAUDO'!D129 -> 8596000 | L7: ='CONSOLIDADO_TOTAL RECAUDO'!E129 -> 0 | M7: =-'CONSOLIDADO_TOTAL RECAUDO'!D70-'CONSOLIDADO_TOTAL RECAUDO'!N70 -> 3964157 | N7: =SUM(I7:M7) -> 7.5756088e+09 | O7: =H7-N7 -> 0 | P7: =INT(O7)=0 -> TRUE
B8: X | C8: ='Recaudo EAAB Reciprocidad'!D26+'Recaudo EAAB + Ciud Limp'!D26+'Recaudo Directa Occidente'!D26+'Recaudo ENEL'!D26+'Recaudo ENERBIT'!D26 -> 0 | D8: 0 | E8: 0 | F8: 0 | G8: 0 | H8: =SUM(C8:G8) -> 0 | I8: 0 | J8: 0 | K8: 0 | L8: ='CONSOLIDADO_TOTAL RECAUDO'!E130 -> 0 | M8: 0 | N8: =SUM(I8:L8)-M8 -> 0 | O8: =H8-N8 -> 0 | P8: =INT(O8)=0 -> TRUE
C9: =SUM(C3:C8) -> 53102379786 | D9: =SUM(D3:D8) -> 31911021 | E9: =SUM(E3:E8) -> 1.8047018e+08 | F9: =SUM(F3:F8) -> 2715776 | G9: =SUM(G3:G8) -> 0 | H9: =SUM(H3:H8) -> 5.3317477e+10 | I9: =SUM(I3:I8) -> 5.3002691e+10 | J9: =SUM(J3:J8) -> 70181639 | ... O9: =SUM(O3:O8) -> 0 | P9: =INT(O9)=0 -> TRUE
B11: X | C11: Recaudo pendiente de identificar
C14: ='Valida - Control Recaudo'!F10 -> 53102379786
C15: =C14=C9 -> TRUE
D18: CONCILIACIÓN CAJA
D19: TOTAL RECAUDO RECIBIDO | E19: RECAUDO PERIODOS ANTERIORES | F19: (REMUNERACION) ANTICIPOS QUE DESCARGAN | G19: RECAUDO POR REVERSAR | H19: SALDOS A FAVOR POR NOTA | I19: TOTAL RECAUDO | J19: REMUNERACION RECAUDO TOTAL | K19: REMUNERACION CONCEPTOS ESPECIALES | L19: REMUNERACION ANTICIPOS GENERADOS | M19: REMUNERACION PAGOS PENDIENTES POR APLICAR | N19: REVERSION DE PAGOS | O19: TOTAL REMUNERACION
C20: EAAB | D20: =VALIDACION_RECIP!C9 -> 0 | E20: =VALIDACION_RECIP!D9 -> 309350 | F20: =VALIDACION_RECIP!E9 -> 13851565 | G20: =VALIDACION_RECIP!F9 -> 0 | H20: =VALIDACION_RECIP!G9 -> 0 | I20: =VALIDACION_RECIP!H9 -> 14160915 | J20: =VALIDACION_RECIP!I9 -> 13606835 | K20: =VALIDACION_RECIP!J9 -> 0 | ... O20: =VALIDACION_RECIP!N9 -> 14160915
C21: ENEL | D21: =VALIDACION_ENEL!C9 -> 50406458396 | E21: =VALIDACION_ENEL!D9 -> 30151870 | F21: =VALIDACION_ENEL!E9 -> 1.1146515e+08 | G21: =VALIDACION_ENEL!F9 -> 2715776 | H21: =VALIDACION_ENEL!G9 -> 0 | I21: =VALIDACION_ENEL!H9 -> 5.0550791e+10 | J21: =VALIDACION_ENEL!I9 -> 5.0322381e+10 | K21: =VALIDACION_ENEL!J9 -> 49684982 | ... O21: =VALIDACION_ENEL!N9 -> 5.0550791e+10
C22: ENERBIT | D22: =VALIDACION_ENERBIT!C9 -> 140424760 | E22: =VALIDACION_ENERBIT!D9 -> 0 | F22: =VALIDACION_ENERBIT!E9 -> 0 | G22: =VALIDACION_ENERBIT!F9 -> 0 | H22: =VALIDACION_ENERBIT!G9 -> 0 | I22: =VALIDACION_ENERBIT!H9 -> 140424760 | J22: =VALIDACION_ENERBIT!I9 -> 139510580 | K22: =VALIDACION_ENERBIT!J9 -> 0 | ... O22: =VALIDACION_ENERBIT!N9 -> 140424760
C23: OCCIDENTE | D23: =VALIDACION_OCCIDENTE!C9 -> 2555496630 | E23: =VALIDACION_OCCIDENTE!D9 -> 1449801 | F23: =VALIDACION_OCCIDENTE!E9 -> 55153463 | G23: =VALIDACION_OCCIDENTE!F9 -> 0 | H23: =VALIDACION_OCCIDENTE!G9 -> 0 | I23: =VALIDACION_OCCIDENTE!H9 -> 2.6120999e+09 | J23: =VALIDACION_OCCIDENTE!I9 -> 2.5271931e+09 | K23: =VALIDACION_OCCIDENTE!J9 -> 20496657 | ... O23: =VALIDACION_OCCIDENTE!N9 -> 2.6120999e+09
D24: =SUM(D20:D23) -> 53102379786 | E24: =SUM(E20:E23) -> 31911021 | F24: =SUM(F20:F23) -> 1.8047018e+08 | G24: =SUM(G20:G23) -> 2715776 | H24: =SUM(H20:H23) -> 0 | I24: =SUM(I20:I23) -> 5.3317477e+10 | J24: =SUM(J20:J23) -> 5.3002691e+10 | K24: =SUM(K20:K23) -> 70181639 | ... O24: =SUM(O20:O23) -> 5.3317477e+10
D25: =D24=C9 -> TRUE | E25: =E24=D9 -> TRUE | F25: =F24=E9 -> TRUE | G25: =G24=F9 -> TRUE | H25: =H24=G9 -> TRUE | I25: =I24=H9 -> TRUE | J25: =J24=I9 -> TRUE | K25: =K24=J9 -> TRUE | ... O25: =O24=N9 -> TRUE
D27: CONCILIACIÓN _ REMUNERACIÓN
D28: Recaudo Total | E28: Conceptos especiales | F28: TOTAL RECAUDO + CONCP ESP | G28: DIFERENCIA | I28: ANTICIPOS GENERADOS | J28: PxI | K28: RECAUDO APLICADO PERIODOS ANTERIORES | L28: ANTICIPOS QUE DESCARGAN | M28: SALDOS A FAVOR POR NOTA+REMUNERA NEGATIVA | N28: REVERSIÓN DE PAGOS | O28: RECAUDO POR REVERSAR | P28: DIFERENCIA | Q28: VALIDACIÓN
C29: EAAB | D29: ='REMUNERACION Reciprocidad EAAB'!D109 -> 13606835 | E29: ='REMUNERACION Reciprocidad EAAB'!N109 -> 0 | F29: =D29+E29 -> 13606835 | G29: =D20-F29 -> -13606835 | I29: ='REMUNERACION Reciprocidad EAAB'!D131 -> 0 | K29: ='REMUNERACION Reciprocidad EAAB'!G131 -> 309350 | L29: ='REMUNERACION Reciprocidad EAAB'!H131 -> 13851565 | M29: ='REMUNERACION Reciprocidad EAAB'!I131 -> 0 | N29: =+'REMUNERACION Reciprocidad EAAB'!J131 -> -554080 | O29: ='REMUNERACION Reciprocidad EAAB'!I147 -> 0 | P29: =I29+J29-K29-L29-M29-N29-O29 -> -13606835 | Q29: =G29-P29 -> 0
C30: ENEL | D30: =REMUNERACION_ENEL!D109 -> 5.0322381e+10 | E30: =REMUNERACION_ENEL!N109 -> 49684982 | F30: =D30+E30 -> 5.0372066e+10 | G30: =D21-F30 -> 34392504 | I30: =REMUNERACION_ENEL!D131 -> 1.0831116e+08 | K30: =REMUNERACION_ENEL!G131 -> 30151870 | L30: =REMUNERACION_ENEL!H131 -> 1.1146515e+08 | M30: =REMUNERACION_ENEL!I131 -> 0 | N30: =REMUNERACION_ENEL!J131 -> -70414138 | O30: =REMUNERACION_ENEL!I147 -> 2715776 | P30: =I30+J30-K30-L30-M30-N30-O30 -> 34392504 | Q30: =G30-P30 -> 0
C31: ENERBIT | D31: =REMUNERACION_ENERBIT!D109 -> 139510580 | E31: =REMUNERACION_ENERBIT!N109 -> 0 | F31: =D31+E31 -> 139510580 | G31: =D22-F31 -> 914180 | I31: =REMUNERACION_ENERBIT!D131 -> 914180 | K31: =REMUNERACION_ENERBIT!G131 -> 0 | L31: =REMUNERACION_ENERBIT!H131 -> 0 | M31: =REMUNERACION_ENERBIT!I131 -> 0 | N31: =REMUNERACION_ENERBIT!J131 -> 0 | O31: =REMUNERACION_ENERBIT!K131 -> 0 | P31: =I31+J31-K31-L31-M31-N31-O31 -> 914180 | Q31: =G31-P31 -> 0
C32: OCCIDENTE | D32: ='REMUNERACION_OCCIDENTE_ Directa'!D109 -> 2.5271931e+09 | E32: ='REMUNERACION_OCCIDENTE_ Directa'!N109 -> 20496657 | F32: =D32+E32 -> 2.5476898e+09 | G32: =D23-F32 -> 7806828.8 | I32: ='REMUNERACION_OCCIDENTE_ Directa'!D131 -> 61958868 | J32: ='CONSOLIDADO_TOTAL RECAUDO'!E131 -> 0 | K32: ='REMUNERACION_OCCIDENTE_ Directa'!G131 -> 1449801 | L32: ='REMUNERACION_OCCIDENTE_ Directa'!H131 -> 55153463 | M32: ='REMUNERACION_OCCIDENTE_ Directa'!I131 -> 0 | N32: ='REMUNERACION_OCCIDENTE_ Directa'!J131 -> -2451225 | O32: ='REMUNERACION_OCCIDENTE_ Directa'!I147 -> 0 | P32: =I32+J32-K32-L32-M32-N32-O32 -> 7806828.8 | Q32: =G32-P32 -> -7.5250864e-07
D33: =SUM(D29:D32) -> 5.3002691e+10 | E33: =SUM(E29:E32) -> 70181639 | F33: =SUM(F29:F32) -> 5.3072873e+10 | G33: =D24-F33 -> 29506678 | I33: =SUM(I29:I32) -> 1.7118421e+08 | J33: =SUM(J29:J32) -> 0 | K33: =SUM(K29:K32) -> 31911021 | L33: =SUM(L29:L32) -> 1.8047018e+08 | M33: =SUM(M29:M32) -> 0 | N33: =SUM(N29:N32) -> -73419443 | O33: =SUM(O29:O32) -> 2715776 | P33: =SUM(P29:P32) -> 29506678 | Q33: =SUM(Q29:Q32) -> -7.5250864e-07
D34: =D33='CONSOLIDADO_TOTAL RECAUDO'!D109 -> TRUE | E34: =E33='CONSOLIDADO_TOTAL RECAUDO'!N109 -> TRUE | F34: =F33='CONSOLIDADO_TOTAL RECAUDO'!D109+'CONSOLIDADO_TOTAL RECAUDO'!N109 -> TRUE
P35: =P33-G33 -> -2.4661422e-06

Sheet GERENTES_TOTAL
