Workbook
Name \0: #REF!
Name _1: #REF!
Name _2: #REF!
Name _A655555: #REF!
Name _CFR1: #REF!
Name _cia1: #REF!
Name _XL250: #REF!
Name A: #REF!
Name ADM: [1]!ADM
Name ADM: [1]!ADM
Name ADM: [1]!ADM
Name ADM: [1]!ADM
Name ADM: [1]!ADM
Name ADM_: [1]!ADM
Name ADM_: [1]!ADM
Name ADM_: [1]!ADM
Name ADM_: [1]!ADM
Name ADM_: [1]!ADM
Name AI: #REF!
Name Air: #REF!
Name AP: '[2]TARIFA no aforos'!$C$12
Name Bancos: [3]Fx!$C$1:$C$23
Name CBL: #REF!
Name CCS: #REF!
Name CDT_p: [4]CDT!$C$3
Name CFR: #REF!
Name cia: #REF!
Name COM: #REF!
Name CRT: #REF!
Name CRT___CTEp___CDTp___CMRv: #REF!
Name CRT_aislados: '[4]COSTOS AJUSTADOS'!$C$13
Name CRT_costas: #REF!
Name CTE_p: [4]CTE!$C$5
Name Denominador: #REF!
Name dg: [1]!ADM
Name dg: [1]!ADM
Name dg: [1]!ADM
Name dg: [1]!ADM
Name dg: [1]!ADM
Name DIAS: [5]CONTRA!#REF!
Name Fmerc: #REF!
Name FPS: #REF!
Name InformacionGeneral: [1]!InformacionGeneral
Name InformacionGeneral: [1]!InformacionGeneral
Name InformacionGeneral: [1]!InformacionGeneral
Name InformacionGeneral: [1]!InformacionGeneral
Name InformacionGeneral: [1]!InformacionGeneral
Name INTFIN: #REF!
Name INV: [1]!INV
Name INV: [1]!INV
Name INV: [1]!INV
Name INV: [1]!INV
Name INV: [1]!INV
Name K: #REF!
Name N: '[4]COSTOS AJUSTADOS'!#REF!
Name Na: '[2]TARIFA no aforos'!$C$39
Name nfc: '[4]COSTOS AJUSTADOS'!#REF!
Name OYM: [1]!OYM
Name OYM: [1]!OYM
Name OYM: [1]!OYM

Sheet Recaudo EAAB Reciprocidad
B2: OPORTUNO | C2: ASE | D2: VALOR 1° Q | E2: NUMERO REG. 1°Q | F2: VALOR 2° Q | G2: NUMERO REG. 2°Q
C3: 1 | D3: 0 | E3: 0 | F3: 0 | G3: 0
C4: 2 | D4: 11627730 | E4: 116 | F4: 0 | G4: 0
C5: 3 | D5: 0 | E5: 0 | F5: 0 | G5: 0
C6: 4 | D6: 7382710 | E6: 66 | F6: 0 | G6: 0
C7: 5 | D7: 0 | E7: 0 | F7: 0 | G7: 0
C8: X
D9: 19010440 | E9: 182 | F9: 0 | G9: 0
C11: ASE | D11: VALOR 1° Q | E11: NUMERO REG. 1°Q | F11: VALOR 2° Q | G11: NUMERO REG. 2°Q
B12: EXTEMP. | C12: 1 | D12: 0 | E12: 0 | F12: 0 | G12: 0
C13: 2 | D13: 0 | E13: 0 | F13: 0 | G13: 0
C14: 3 | D14: 0 | E14: 0 | F14: 0 | G14: 0
C15: 4 | D15: 0 | E15: 0 | F15: 0 | G15: 0
C16: 5 | D16: 0 | E16: 0 | F16: 0 | G16: 0
C17: X
D18: 0 | E18: 0 | F18: 0 | G18: 0
C20: ASE | D20: VALOR 1° Q | E20: NUMERO REG. 1°Q | F20: VALOR 2° Q | G20: NUMERO REG. 2°Q | I20: VALOR TOTAL MES | J20: NUMERO REGISTROS MES
B21: TOTAL | C21: 1 | D21: 0 | E21: 0 | F21: 0 | G21: 0 | I21: 0 | J21: 0
C22: 2 | D22: 11627730 | E22: 116 | F22: 0 | G22: 0 | I22: 0 | J22: 0
C23: 3 | D23: 0 | E23: 0 | F23: 0 | G23: 0 | I23: 0 | J23: 0
C24: 4 | D24: 7382710 | E24: 66 | F24: 0 | G24: 0 | I24: 0 | J24: 0
C25: 5 | D25: 0 | E25: 0 | F25: 0 | G25: 0 | I25: 0 | J25: 0
C26: X | I26: 0 | J26: 0
D27: 19010440 | E27: 182 | F27: 0 | G27: 0 | I27: 0 | J27: 0
B31: OPORTUNO | D31: =D9=SUM(D3:D8) -> TRUE | E31: =E9=SUM(E3:E8) -> TRUE | F31: =F9=SUM(F3:F8) -> TRUE | G31: =G9=SUM(G3:G8) -> TRUE
B33: EXTEMP. | D33: =D18=SUM(D12:D17) -> TRUE | E33: =E18=SUM(E12:E17) -> TRUE | F33: =F18=SUM(F12:F17) -> TRUE | G33: =G18=SUM(G12:G17) -> TRUE
B35: TOTAL | D35: =D27=SUM(D21:D26) -> TRUE | E35: =E27=SUM(E21:E26) -> TRUE | F35: =F27=SUM(F21:F26) -> TRUE | G35: =G27=SUM(G21:G26) -> TRUE | I35: =I27=SUM(I21:I26) -> TRUE | J35: =J27=SUM(J21:J26) -> TRUE
E69: =C69-G17 -> 0

Sheet Recaudo ENEL
B2: OPORTUNO | C2: ASE | D2: VALOR 1° Q | E2: NUMERO REG. 1°Q | F2: VALOR 2° Q | G2: NUMERO REG. 2°Q
C3: 1 | D3: 16745673525 | E3: 356945 | F3: 0 | G3: 0
C4: 2 | D4: 12677941411 | E4: 247628 | F4: 0 | G4: 0
C5: 3 | D5: 10157711962 | E5: 233934 | F5: 0 | G5: 0
C6: 4 | D6: 10972037248 | E6: 193770 | F6: 0 | G6: 0
C7: 5 | D7: 8639656940 | E7: 172542 | F7: 0 | G7: 0
C8: X
D9: 59193021086 | E9: 1204819 | F9: 0 | G9: 0
C11: ASE | D11: VALOR 1° Q | E11: NUMERO REG. 1°Q | F11: VALOR 2° Q | G11: NUMERO REG. 2°Q
B12: EXTEMP. | C12: 1 | D12: 202711553 | E12: 2558 | F12: 0 | G12: 0
C13: 2 | D13: 73096641 | E13: 1473 | F13: 0 | G13: 0
C14: 3 | D14: 51248640 | E14: 963 | F14: 0 | G14: 0
C15: 4 | D15: 62236830 | E15: 857 | F15: 0 | G15: 0
C16: 5 | D16: 158575115 | E16: 2854 | F16: 0 | G16: 0
C17: X
D18: 547868779 | E18: 8705 | F18: 0 | G18: 0
C20: ASE | D20: VALOR 1° Q | E20: NUMERO REG. 1°Q | F20: VALOR 2° Q | G20: NUMERO REG. 2°Q | I20: VALOR TOTAL MES | J20: NUMERO REGISTROS MES
B21: TOTAL | C21: 1 | D21: 16948385078 | E21: 359503 | F21: 0 | G21: 0 | I21: 0 | J21: 0
C22: 2 | D22: 12751038052 | E22: 249101 | F22: 0 | G22: 0 | I22: 0 | J22: 0
C23: 3 | D23: 10208960602 | E23: 234897 | F23: 0 | G23: 0 | I23: 0 | J23: 0
C24: 4 | D24: 11034274078 | E24: 194627 | F24: 0 | G24: 0 | I24: 0 | J24: 0
C25: 5 | D25: 8798232055 | E25: 175396 | F25: 0 | G25: 0 | I25: 0 | J25: 0
C26: X | I26: 0 | J26: 0
D27: 59740889865 | E27: 1213524 | F27: 0 | G27: 0 | I27: 0 | J27: 0
B31: OPORTUNO | D31: =D9=SUM(D3:D8) -> TRUE | E31: =E9=SUM(E3:E8) -> TRUE | F31: =F9=SUM(F3:F8) -> TRUE | G31: =G9=SUM(G3:G8) -> TRUE
B33: EXTEMP. | D33: =D18=SUM(D12:D17) -> TRUE | E33: =E18=SUM(E12:E17) -> TRUE | F33: =F18=SUM(F12:F17) -> TRUE | G33: =G18=SUM(G12:G17) -> TRUE
B35: TOTAL | D35: =D27=SUM(D21:D26) -> TRUE | E35: =E27=SUM(E21:E26) -> TRUE | F35: =F27=SUM(F21:F26) -> TRUE | G35: =G27=SUM(G21:G26) -> TRUE | I35: =I27=SUM(I21:I26) -> TRUE | J35: =J27=SUM(J21:J26) -> TRUE
E69: =C69-G17 -> 0

Sheet Recaudo ENERBIT
B2: OPORTUNO | C2: ASE | D2: VALOR 1° Q | E2: NUMERO REG. 1°Q | F2: VALOR 2° Q | G2: NUMERO REG. 2°Q
C3: 1 | D3: 0 | E3: 0 | F3: 0 | G3: 0
C4: 2 | D4: 0 | E4: 0 | F4: 0 | G4: 0
C5: 3 | D5: 0 | E5: 0 | F5: 0 | G5: 0
C6: 4 | D6: 0 | E6: 0 | F6: 0 | G6: 0
C7: 5 | D7: 137371512 | E7: 3020 | F7: 0 | G7: 0
C8: X
D9: 137371512 | E9: 3020 | F9: 0 | G9: 0
C11: ASE | D11: VALOR 1° Q | E11: NUMERO REG. 1°Q | F11: VALOR 2° Q | G11: NUMERO REG. 2°Q
B12: EXTEMP. | C12: 1 | D12: 0 | E12: 0 | F12: 0 | G12: 0
C13: 2 | D13: 0 | E13: 0 | F13: 0 | G13: 0
C14: 3 | D14: 0 | E14: 0 | F14: 0 | G14: 0
C15: 4 | D15: 0 | E15: 0 | F15: 0 | G15: 0
C16: 5 | D16: 1179300 | E16: 6 | F16: 0 | G16: 0
C17: X
D18: 1179300 | E18: 6 | F18: 0 | G18: 0
C20: ASE | D20: VALOR 1° Q | E20: NUMERO REG. 1°Q | F20: VALOR 2° Q | G20: NUMERO REG. 2°Q | I20: VALOR TOTAL MES | J20: NUMERO REGISTROS MES
B21: TOTAL | C21: 1 | D21: 0 | E21: 0 | F21: 0 | G21: 0 | I21: 0 | J21: 0
C22: 2 | D22: 0 | E22: 0 | F22: 0 | G22: 0 | I22: 0 | J22: 0
C23: 3 | D23: 0 | E23: 0 | F23: 0 | G23: 0 | I23: 0 | J23: 0
C24: 4 | D24: 0 | E24: 0 | F24: 0 | G24: 0 | I24: 0 | J24: 0
C25: 5 | D25: 138550812 | E25: 3026 | F25: 0 | G25: 0 | I25: 0 | J25: 0
C26: X | I26: 0 | J26: 0
D27: 138550812 | E27: 3026 | F27: 0 | G27: 0 | I27: 0 | J27: 0
B31: OPORTUNO | D31: =D9=SUM(D3:D8) -> TRUE | E31: =E9=SUM(E3:E8) -> TRUE | F31: =F9=SUM(F3:F8) -> TRUE | G31: =G9=SUM(G3:G8) -> TRUE
B33: EXTEMP. | D33: =D18=SUM(D12:D17) -> TRUE | E33: =E18=SUM(E12:E17) -> TRUE | F33: =F18=SUM(F12:F17) -> TRUE | G33: =G18=SUM(G12:G17) -> TRUE
B35: TOTAL | D35: =D27=SUM(D21:D26) -> TRUE | E35: =E27=SUM(E21:E26) -> TRUE | F35: =F27=SUM(F21:F26) -> TRUE | G35: =G27=SUM(G21:G26) -> TRUE | I35: =I27=SUM(I21:I26) -> TRUE | J35: =J27=SUM(J21:J26) -> TRUE
E69: =C69-G17 -> 0

Sheet Recaudo EAAB + Ciud Limp
B2: Ciudad Limpia - Prestador | C2: ASE | D2: VALOR 1° Q | E2: NUMERO REG. 1°Q | F2: VALOR 2° Q | G2: NUMERO REG. 2°Q
C3: 1 | D3: 0 | E3: 0 | F3: 0 | G3: 0
C4: 2 | D4: 0 | E4: 0 | F4: 0 | G4: 0
C5: 3 | D5: 0 | E5: 0 | F5: 0 | G5: 0
C6: 4 | D6: 0 | E6: 0 | F6: 0 | G6: 0
C7: 5 | D7: 0 | E7: 0 | F7: 0 | G7: 0
C8: X
D9: 0 | E9: 0 | F9: 0 | G9: 0
C11: ASE | D11: VALOR 1° Q | E11: NUMERO REG. 1°Q | F11: VALOR 2° Q | G11: NUMERO REG. 2°Q
B12: EAAB - Prestador | C12: 1 | D12: 0 | E12: 0 | F12: 0 | G12: 0
C13: 2 | D13: 0 | E13: 0 | F13: 0 | G13: 0
C14: 3 | D14: 0 | E14: 0 | F14: 0 | G14: 0
C15: 4 | D15: 0 | E15: 0 | F15: 0 | G15: 0
C16: 5 | D16: 0 | E16: 0 | F16: 0 | G16: 0
C17: X
D18: 0 | E18: 0 | F18: 0 | G18: 0
C20: ASE | D20: VALOR 1° Q | E20: NUMERO REG. 1°Q | F20: VALOR 2° Q | G20: NUMERO REG. 2°Q | I20: VALOR TOTAL MES | J20: NUMERO REGISTROS MES
B21: TOTAL | C21: 1 | D21: 0 | E21: 0 | F21: 0 | G21: 0 | I21: 0 | J21: 0
C22: 2 | D22: 0 | E22: 0 | F22: 0 | G22: 0 | I22: 0 | J22: 0
C23: 3 | D23: 0 | E23: 0 | F23: 0 | G23: 0 | I23: 0 | J23: 0
C24: 4 | D24: 0 | E24: 0 | F24: 0 | G24: 0 | I24: 0 | J24: 0
C25: 5 | D25: 0 | E25: 0 | F25: 0 | G25: 0 | I25: 0 | J25: 0
C26: X | I26: 0 | J26: 0
D27: 0 | E27: 0 | F27: 0 | G27: 0 | I27: 0 | J27: 0
B31: OPORTUNO | D31: =D9=SUM(D3:D8) -> TRUE | E31: =E9=SUM(E3:E8) -> TRUE | F31: =F9=SUM(F3:F8) -> TRUE | G31: =G9=SUM(G3:G8) -> TRUE
B33: EXTEMP. | D33: =D18=SUM(D12:D17) -> TRUE | E33: =E18=SUM(E12:E17) -> TRUE | F33: =F18=SUM(F12:F17) -> TRUE | G33: =G18=SUM(G12:G17) -> TRUE
B35: TOTAL | D35: =D27=SUM(D21:D26) -> TRUE | E35: =E27=SUM(E21:E26) -> TRUE | F35: =F27=SUM(F21:F26) -> TRUE | G35: =G27=SUM(G21:G26) -> TRUE | I35: =I27=SUM(I21:I26) -> TRUE | J35: =J27=SUM(J21:J26) -> TRUE

Sheet Recaudo Directa Occidente
B2: OPORTUNO | C2: ASE | D2: VALOR 1° Q | E2: NUMERO REG. 1°Q | F2: VALOR 2° Q | G2: NUMERO REG. 2°Q
C3: 1 | D3: 510782327 | E3: 2083 | F3: 0 | G3: 0
C4: 2 | D4: 1360190364 | E4: 4795 | F4: 0 | G4: 0
C5: 3 | D5: 650826874 | E5: 1469 | F5: 0 | G5: 0
C6: 4 | D6: 515587332 | E6: 3012 | F6: 0 | G6: 0
C7: 5 | D7: 224557157 | E7: 1221 | F7: 0 | G7: 0
C8: X | D8: 0 | E8: 0 | F8: 0 | G8: 0
D9: 3261944054 | E9: 12580 | F9: 0 | G9: 0
C11: ASE | D11: VALOR 1° Q | E11: NUMERO REG. 1°Q | F11: VALOR 2° Q | G11: NUMERO REG. 2°Q
B12: EXTEMP. | C12: 1 | D12: 23795111 | E12: 50 | F12: 0 | G12: 0
C13: 2 | D13: 62759499 | E13: 134 | F13: 0 | G13: 0
C14: 3 | D14: 48196023 | E14: 55 | F14: 0 | G14: 0
C15: 4 | D15: 5014320 | E15: 32 | F15: 0 | G15: 0
C16: 5 | D16: 14004529 | E16: 30 | F16: 0 | G16: 0
C17: X | D17: 0 | E17: 0 | F17: 0 | G17: 0
D18: 153769482 | E18: 301 | F18: 0 | G18: 0
C20: ASE | D20: VALOR 1° Q | E20: NUMERO REG. 1°Q | F20: VALOR 2° Q | G20: NUMERO REG. 2°Q | I20: VALOR TOTAL MES | J20: NUMERO REGISTROS MES
B21: TOTAL | C21: 1 | D21: 534577438 | E21: 2133 | F21: 0 | G21: 0 | I21: 0 | J21: 0
C22: 2 | D22: 1422949863 | E22: 4929 | F22: 0 | G22: 0 | I22: 0 | J22: 0
C23: 3 | D23: 699022897 | E23: 1524 | F23: 0 | G23: 0 | I23: 0 | J23: 0
C24: 4 | D24: 520601652 | E24: 3044 | F24: 0 | G24: 0 | I24: 0 | J24: 0
C25: 5 | D25: 238561686 | E25: 1251 | F25: 0 | G25: 0 | I25: 0 | J25: 0
C26: X | D26: 0 | E26: 0 | F26: 0 | G26: 0 | I26: 0 | J26: 0
D27: 3415713536 | E27: 12881 | F27: 0 | G27: 0 | I27: 0 | J27: 0
B31: OPORTUNO | D31: =D9=SUM(D3:D8) -> TRUE | E31: =E9=SUM(E3:E8) -> TRUE | F31: =F9=SUM(F3:F8) -> TRUE | G31: =G9=SUM(G3:G8) -> TRUE
B33: EXTEMP. | D33: =D18=SUM(D12:D17) -> TRUE | E33: =E18=SUM(E12:E17) -> TRUE | F33: =F18=SUM(F12:F17) -> TRUE | G33: =G18=SUM(G12:G17) -> TRUE
B35: TOTAL | D35: =D27=SUM(D21:D26) -> TRUE | E35: =E27=SUM(E21:E26) -> TRUE | F35: =F27=SUM(F21:F26) -> TRUE | G35: =G27=SUM(G21:G26) -> TRUE | I35: =I27=SUM(I21:I26) -> TRUE | J35: =J27=SUM(J21:J26) -> TRUE
E69: =C69-G17 -> 0

Sheet REPORTE RECAUDO x BANCO
C1: ENEL | D1: CIUDAD LIMPIA | E1: EAB | F1: NUEVO ESQUEMA | G1: ENERBIT | H1: OCCIDENTE | I1: Total
B2: 1-APLICADOS A FACTURACION | C2: =C13+C23+C32+C41+C51 -> 59646927181 | D2: =D13+D23+D32+D41+D51 -> 0 | E2: =E13+E23+E32+E41+E51 -> 0 | F2: =F13+F23+F32+F41+F51 -> 5603210 | G2: =G13+G23+G32+G41+G51 -> 137170902 | H2: =H13+H23+H32+H41+H51 -> 3.2507019e+09 | I2: =SUM(C2:H2) -> 6.3040403e+10
B3: 2-SALDOS A FAVOR GENERADOS | C3: =C14+C24+C33+C42+C52 -> 95923744 | D3: =D14+D24+D33+D42+D52 -> 0 | E3: =E14+E24+E33+E42+E52 -> 0 | F3: =F14+F24+F33+F42+F52 -> 13407230 | G3: =G14+G24+G33+G42+G52 -> 1379910 | H3: =H14+H24+H33+H42+H52 -> 75193898 | I3: =SUM(C3:H3) -> 1.8590478e+08
B4: 3-APLICADOS A FINANCIACIONES NUEVAS | C4: =C15+C25+C34+C43+C53 -> 0 | D4: =D15+D25+D34+D43+D53 -> 0 | E4: =E15+E25+E34+E43+E53 -> 0 | F4: =F15+F25+F34+F43+F53 -> 0 | G4: =G15+G25+G34+G43+G53 -> 0 | H4: =H15+H25+H34+H43+H53 -> 89817711 | I4: =SUM(C4:H4) -> 89817711
B5: 7-APLICADOS A RECIBOS SERVICIOS ESPECIALES | C5: =C16+C26+C35+C44+C54 -> 0 | D5: =D16+D26+D35+D44+D54 -> 0 | E5: =E16+E26+E35+E44+E54 -> 0 | F5: =F16+F26+F35+F44+F54 -> 0 | G5: =G16+G26+G35+G44+G54 -> 0 | H5: =H16+H26+H35+H44+H54 -> 0 | I5: =SUM(C5:H5) -> 0
B6: Total | C6: =SUM(C2:C5) -> 59742850925 | D6: =SUM(D2:D5) -> 0 | E6: =SUM(E2:E5) -> 0 | F6: =SUM(F2:F5) -> 19010440 | G6: =SUM(G2:G5) -> 138550812 | H6: =SUM(H2:H5) -> 3.4157135e+09 | I6: =SUM(I2:I5) -> 63316125713
C7: =C6=(C17+C27+C36+C45+C55) -> TRUE | D7: =D6=(D17+D27+D36+D45+D55) -> TRUE | E7: =E6=(E17+E27+E36+E45+E55) -> TRUE | F7: =F6=(F17+F27+F36+F45+F55) -> TRUE | H7: =H6=(H17+H27+H36+H45+H55) -> TRUE | I7: =I6=(I17+I27+I36+I45+I55) -> TRUE
B10: ASE 1
B11: Resumen Recaudo Aplicado Por Servicio
C12: ENEL | D12: CIUDAD LIMPIA | E12: EAB | F12: NUEVO ESQUEMA | G12: ENERBIT | H12: OCCIDENTE | I12: Total
B13: 1-APLICADOS A FACTURACION | C13: 16922955923 | D13: 0 | E13: 0 | F13: 0 | G13: 0 | H13: 5.2128716e+08 | I13: =SUM(C13:H13) -> 1.7444243e+10 | J13: =SUM(C13:H13)=I13 -> TRUE
B14: 2-SALDOS A FAVOR GENERADOS | C14: 25429155 | D14: 0 | E14: 0 | F14: 0 | G14: 0 | H14: 7990275.5 | I14: =SUM(C14:H14) -> 33419430 | J14: =SUM(C14:H14)=I14 -> TRUE
B15: 3-APLICADOS A FINANCIACIONES NUEVAS | C15: 0 | D15: 0 | E15: 0 | F15: 0 | G15: 0 | H15: 5300003 | I15: =SUM(C15:H15) -> 5300003 | J15: =SUM(C15:H15)=I15 -> TRUE
B16: 7-APLICADOS A RECIBOS SERVICIOS ESPECIALES | C16: 0 | D16: 0 | E16: 0 | F16: 0 | G16: 0 | H16: 0 | I16: =SUM(C16:H16) -> 0 | J16: =SUM(C16:H16)=I16 -> TRUE
B17: Total | C17: =SUM(C13:C16) -> 16948385078 | D17: =SUM(D13:D16) -> 0 | E17: =SUM(E13:E16) -> 0 | F17: =SUM(F13:F16) -> 0 | G17: =SUM(G13:G16) -> 0 | H17: =SUM(H13:H16) -> 534577438 | I17: =SUM(I13:I16) -> 17482962516 | J17: =SUM(C17:H17)=I17 -> TRUE
B20: ASE 2
B21: Resumen Recaudo Aplicado Por Servicio
C22: ENEL | D22: CIUDAD LIMPIA | E22: EAB | F22: NUEVO ESQUEMA | G22: ENERBIT | H22: OCCIDENTE | I22: Total
B23: 1-APLICADOS A FACTURACION | C23: 12724393063 | D23: 0 | E23: 0 | F23: 3445900 | G23: 0 | H23: 1.3616741e+09 | I23: =SUM(C23:H23) -> 1.4089513e+10 | J23: =SUM(C23:H23)=I23 -> TRUE
B24: 2-SALDOS A FAVOR GENERADOS | C24: 27050219 | D24: 0 | E24: 0 | F24: 8181830 | G24: 0 | H24: 52788865 | I24: =SUM(C24:H24) -> 88020914 | J24: =SUM(C24:H24)=I24 -> TRUE
B25: 3-APLICADOS A FINANCIACIONES NUEVAS | C25: 0 | D25: 0 | E25: 0 | F25: 0 | G25: 0 | H25: 8486848.6 | I25: =SUM(C25:H25) -> 8486848.6 | J25: =SUM(C25:H25)=I25 -> TRUE
B26: 7-APLICADOS A RECIBOS SERVICIOS ESPECIALES | C26: 0 | D26: 0 | E26: 0 | F26: 0 | G26: 0 | H26: 0 | I26: =SUM(C26:H26) -> 0 | J26: =SUM(C26:H26)=I26 -> TRUE
B27: Total | C27: =SUM(C23:C26) -> 12751443282 | D27: =SUM(D23:D26) -> 0 | E27: =SUM(E23:E26) -> 0 | F27: =SUM(F23:F26) -> 11627730 | G27: =SUM(G23:G26) -> 0 | H27: =SUM(H23:H26) -> 1422949863 | I27: =SUM(I23:I26) -> 1.4186021e+10 | J27: =SUM(C27:H27)=I27 -> TRUE
B29: ASE 3
B30: Resumen Recaudo Aplicado Por Servicio
C31: ENEL | D31: CIUDAD LIMPIA | E31: EAB | F31: NUEVO ESQUEMA | G31: ENERBIT | H31: OCCIDENTE | I31: Total
B32: 1-APLICADOS A FACTURACION | C32: 10203127061 | D32: 0 | E32: 0 | F32: 0 | G32: 0 | H32: 6.9348502e+08 | I32: =SUM(C32:H32) -> 1.0896612e+10 | J32: =SUM(C32:H32)=I32 -> TRUE
B33: 2-SALDOS A FAVOR GENERADOS | C33: 6025131 | D33: 0 | E33: 0 | F33: 0 | G33: 0 | H33: 2921040 | I33: =SUM(C33:H33) -> 8946171 | J33: =SUM(C33:H33)=I33 -> TRUE
B34: 3-APLICADOS A FINANCIACIONES NUEVAS | C34: 0 | D34: 0 | E34: 0 | F34: 0 | G34: 0 | H34: 2616838.9 | I34: =SUM(C34:H34) -> 2616838.9 | J34: =SUM(C34:H34)=I34 -> TRUE
B35: 7-APLICADOS A RECIBOS SERVICIOS ESPECIALES | C35: 0 | D35: 0 | E35: 0 | F35: 0 | G35: 0 | H35: 0 | I35: =SUM(C35:H35) -> 0 | J35: =SUM(C35:H35)=I35 -> TRUE
B36: Total | C36: =SUM(C32:C35) -> 10209152192 | D36: =SUM(D32:D35) -> 0 | E36: =SUM(E32:E35) -> 0 | F36: =SUM(F32:F35) -> 0 | G36: =SUM(G32:G35) -> 0 | H36: =SUM(H32:H35) -> 699022897 | I36: =SUM(I32:I35) -> 10908175089 | J36: =SUM(C36:H36)=I36 -> TRUE
B38: ASE 4
B39: Resumen Recaudo Aplicado Por Servicio
C40: ENEL | D40: CIUDAD LIMPIA | E40: EAB | F40: NUEVO ESQUEMA | G40: ENERBIT | H40: OCCIDENTE | I40: Total
B41: 1-APLICADOS A FACTURACION | C41: 11007626472 | D41: 0 | E41: 0 | F41: 2157310 | G41: 0 | H41: 4.4153236e+08 | I41: =SUM(C41:H41) -> 1.1451316e+10 | J41: =SUM(C41:H41)=I41 -> TRUE
B42: 2-SALDOS A FAVOR GENERADOS | C42: 27660196 | D42: 0 | E42: 0 | F42: 5225400 | G42: 0 | H42: 8186683.7 | I42: =SUM(C42:H42) -> 41072280 | J42: =SUM(C42:H42)=I42 -> TRUE
B43: 3-APLICADOS A FINANCIACIONES NUEVAS | C43: 0 | D43: 0 | E43: 0 | F43: 0 | G43: 0 | H43: 70882609 | I43: =SUM(C43:H43) -> 70882609 | J43: =SUM(C43:H43)=I43 -> TRUE
B44: 7-APLICADOS A RECIBOS SERVICIOS ESPECIALES | C44: 0 | D44: 0 | E44: 0 | F44: 0 | G44: 0 | H44: 0 | I44: =SUM(C44:H44) -> 0 | J44: =SUM(C44:H44)=I44 -> TRUE
B45: Total | C45: =SUM(C41:C44) -> 11035286668 | D45: =SUM(D41:D44) -> 0 | E45: =SUM(E41:E44) -> 0 | F45: =SUM(F41:F44) -> 7382710 | G45: =SUM(G41:G44) -> 0 | H45: =SUM(H41:H44) -> 5.2060165e+08 | I45: =SUM(I41:I44) -> 11563271030 | J45: =SUM(C45:H45)=I45 -> TRUE
B48: ASE 5
B49: Resumen Recaudo Aplicado Por Servicio
C50: ENEL | D50: CIUDAD LIMPIA | E50: EAB | F50: NUEVO ESQUEMA | G50: ENERBIT | H50: OCCIDENTE | I50: Total
B51: 1-APLICADOS A FACTURACION | C51: 8788824662 | D51: 0 | E51: 0 | F51: 0 | G51: 137170902 | H51: 2.3272324e+08 | I51: =SUM(C51:H51) -> 9.1587188e+09 | J51: =SUM(C51:H51)=I51 -> TRUE
B52: 2-SALDOS A FAVOR GENERADOS | C52: 9759043 | D52: 0 | E52: 0 | F52: 0 | G52: 1379910 | H52: 3307034 | I52: =SUM(C52:H52) -> 14445987 | J52: =SUM(C52:H52)=I52 -> TRUE
B53: 3-APLICADOS A FINANCIACIONES NUEVAS | C53: 0 | D53: 0 | E53: 0 | F53: 0 | G53: 0 | H53: 2531411 | I53: =SUM(C53:H53) -> 2531411 | J53: =SUM(C53:H53)=I53 -> TRUE
B54: 7-APLICADOS A RECIBOS SERVICIOS ESPECIALES | C54: 0 | D54: 0 | E54: 0 | F54: 0 | G54: 0 | H54: 0 | I54: =SUM(C54:H54) -> 0 | J54: =SUM(C54:H54)=I54 -> TRUE
B55: Total | C55: =SUM(C51:C54) -> 8798583705 | D55: =SUM(D51:D54) -> 0 | E55: =SUM(E51:E54) -> 0 | F55: =SUM(F51:F54) -> 0 | G55: =SUM(G51:G54) -> 138550812 | H55: =SUM(H51:H54) -> 238561686 | I55: =SUM(I51:I54) -> 9175696203 | J55: =SUM(C55:H55)=I55 -> TRUE
B59: QUINCENA | C59: 1 | D59: OJO/// DILIGENCIAR
B62: Recaudo ENEL - ASE 1 | C62: =IF($C$59=1,'Recaudo ENEL'!D21,'Recaudo ENEL'!F21) -> 16948385078 | D62: =C17=C62 -> TRUE | E62: =C17-C62 -> 0
B63: Recaudo ENERBIT - ASE 1 | C63: =IF($C$59=1,'Recaudo ENERBIT'!D21,'Recaudo ENERBIT'!F21) -> 0 | D63: =G17=C63 -> TRUE | E63: =G17-C63 -> 0
B64: Recaudo Reciprocidad EAAB - ASE 2 | C64: =IF($C$59=1,'Recaudo EAAB Reciprocidad'!D22,'Recaudo EAAB Reciprocidad'!F22) -> 11627730 | D64: =F27=C64 -> TRUE | E64: =F27-C64 -> 0
B65: Recaudo ENEL - ASE 2 | C65: =IF($C$59=1,'Recaudo ENEL'!D22,'Recaudo ENEL'!F22) -> 12751038052 | D65: =C27=C65 -> FALSE | E65: =C27-C65 -> 405230
B66: Recaudo ENERBIT - ASE 2 | C66: =IF($C$59=1,'Recaudo ENERBIT'!D22,'Recaudo ENERBIT'!F22) -> 0 | D66: =G27=C66 -> TRUE | E66: =G27-C66 -> 0
B67: Recaudo ENEL - ASE 3 | C67: =IF($C$59=1,'Recaudo ENEL'!D23,'Recaudo ENEL'!F23) -> 10208960602 | D67: =C36=C67 -> FALSE | E67: =C36-C67 -> 191590
B68: Recaudo ENERBIT - ASE 3 | C68: =IF($C$59=1,'Recaudo ENERBIT'!D23,'Recaudo ENERBIT'!F23) -> 0 | D68: =G36=C68 -> TRUE | E68: =G36-C68 -> 0
B69: Recaudo Reciprocidad EAAB - ASE 4 | C69: =IF($C$59=1,'Recaudo EAAB Reciprocidad'!D24,'Recaudo EAAB Reciprocidad'!F24) -> 7382710 | D69: =F45=C69 -> TRUE | E69: =F45-C69 -> 0
B70: Recaudo ENEL - ASE 4 | C70: =IF($C$59=1,'Recaudo ENEL'!D24,'Recaudo ENEL'!F24) -> 11034274078 | D70: =C45=C70 -> FALSE | E70: =C45-C70 -> 1012590
B71: Recaudo ENERBIT - ASE 4 | C71: =IF($C$59=1,'Recaudo ENERBIT'!D24,'Recaudo ENERBIT'!F24) -> 0 | D71: =G45=C71 -> TRUE | E71: =G45-C71 -> 0
B72: Recaudo ENEL - ASE 5 | C72: =IF($C$59=1,'Recaudo ENEL'!D25,'Recaudo ENEL'!F25) -> 8798232055 | D72: =C55=C72 -> FALSE | E72: =C55-C72 -> 351650
B73: Recaudo ENERBIT - ASE 5 | C73: =IF($C$59=1,'Recaudo ENERBIT'!D25,'Recaudo ENERBIT'!F25) -> 138550812 | D73: =G55=C73 -> TRUE | E73: =G55-C73 -> 0
B75: Recaudo Banco Occidente ASE 1 | C75: =IF($C$59=1,'Recaudo Directa Occidente'!D21,'Recaudo Directa Occidente'!F21) -> 534577438 | D75: =C75=H17 -> TRUE | E75: =C75-H17 -> 0
B76: Recaudo Banco Occidente ASE 2 | C76: =IF($C$59=1,'Recaudo Directa Occidente'!D22,'Recaudo Directa Occidente'!F22) -> 1422949863 | D76: =C76=H27 -> TRUE | E76: =C76-H27 -> 0
B77: Recaudo Banco Occidente ASE 3 | C77: =IF($C$59=1,'Recaudo Directa Occidente'!D23,'Recaudo Directa Occidente'!F23) -> 699022897 | D77: =C77=H36 -> TRUE | E77: =C77-H36 -> 0
B78: Recaudo Banco Occidente ASE 4 | C78: =IF($C$59=1,'Recaudo Directa Occidente'!D24,'Recaudo Directa Occidente'!F24) -> 520601652 | D78: =C78=H45 -> TRUE | E78: =C78-H45 -> 0
B79: Recaudo Banco Occidente ASE 5 | C79: =IF($C$59=1,'Recaudo Directa Occidente'!D25,'Recaudo Directa Occidente'!F25) -> 238561686 | D79: =C79=H55 -> TRUE | E79: =C79-H55 -> 0

Sheet ANT EXT-REV
C1: ASE 1 | E1: ASE 2 | G1: ASE 3 | I1: ASE 4 | K1: ASE 5 | M1: TOTAL
C2: REPORTE 3 | D2: REPORTE 4 | E2: REPORTE 3 | F2: REPORTE 4 | G2: REPORTE 3 | H2: REPORTE 4 | I2: REPORTE 3 | J2: REPORTE 4 | K2: REPORTE 3 | L2: REPORTE 4 | M2: REPORTE 3 | N2: REPORTE 4
B3: APLICADO | C3: =C11+C19+C27+C35+C43 -> 0 | D3: =D11+D19+D27+D35+D43 -> 0 | E3: =E11+E19+E27+E35+E43 -> 0 | F3: =F11+F19+F27+F35+F43 -> 0 | G3: =G11+G19+G27+G35+G43 -> 0 | H3: =H11+H19+H27+H35+H43 -> 0 | I3: =I11+I19+I27+I35+I43 -> 0 | J3: =J11+J19+J27+J35+J43 -> 0 | ... L3: =L11+L19+L27+L35+L43 -> 0 | M3: =C3+E3+G3+I3+K3 -> 0 | N3: =D3+F3+H3+J3+L3 -> 0 | P3: =N3=(-VALIDACION_TOTAL!M9) -> FALSE
B4: ANTICIPOS | C4: =C12+C20+C28+C36+C44 -> 0 | D4: =D12+D20+D28+D36+D44 -> 0 | E4: =E12+E20+E28+E36+E44 -> 0 | F4: =F12+F20+F28+F36+F44 -> 0 | G4: =G12+G20+G28+G36+G44 -> 0 | H4: =H12+H20+H28+H36+H44 -> 0 | I4: =I12+I20+I28+I36+I44 -> 0 | J4: =J12+J20+J28+J36+J44 -> 0 | ... L4: =L12+L20+L28+L36+L44 -> 0 | M4: =C4+E4+G4+I4+K4 -> 0 | N4: =D4+F4+H4+J4+L4 -> 0 | P4: =N4=(-'CONSOLIDADO_TOTAL RECAUDO'!L131) -> TRUE
B5: TOTAL | C5: =SUM(C3:C4) -> 0 | D5: =SUM(D3:D4) -> 0 | E5: =SUM(E3:E4) -> 0 | F5: =SUM(F3:F4) -> 0 | G5: =SUM(G3:G4) -> 0 | H5: =SUM(H3:H4) -> 0 | I5: =SUM(I3:I4) -> 0 | J5: =SUM(J3:J4) -> 0 | ... N5: =SUM(N3:N4) -> 0
C6: =C5=(C13+C21+C29+C37+C45) -> TRUE | D6: =D5=(D13+D21+D29+D37+D45) -> TRUE | E6: =E5=(E13+E21+E29+E37+E45) -> TRUE | F6: =F5=(F13+F21+F29+F37+F45) -> TRUE | G6: =G5=(G13+G21+G29+G37+G45) -> TRUE | H6: =H5=(H13+H21+H29+H37+H45) -> TRUE | I6: =I5=(I13+I21+I29+I37+I45) -> TRUE | J6: =J5=(J13+J21+J29+J37+J45) -> TRUE | ... N6: =N5=(N13+N21+N29+N37+N45) -> TRUE
B8: BANCO DE OCCIDENTE
C9: ASE 1 | E9: ASE 2 | G9: ASE 3 | I9: ASE 4 | K9: ASE 5 | M9: TOTAL
C10: REPORTE 3 | D10: REPORTE 4 | E10: REPORTE 3 | F10: REPORTE 4 | G10: REPORTE 3 | H10: REPORTE 4 | I10: REPORTE 3 | J10: REPORTE 4 | K10: REPORTE 3 | L10: REPORTE 4 | M10: REPORTE 3 | N10: REPORTE 4
B11: APLICADO | C11: 0 | D11: 0 | E11: 0 | F11: 0 | G11: 0 | H11: 0 | I11: 0 | J11: 0 | K11: 0 | L11: 0 | M11: =C11+E11+G11+I11+K11 -> 0 | N11: =D11+F11+H11+J11+L11 -> 0
B12: ANTICIPOS | C12: 0 | D12: 0 | E12: 0 | F12: 0 | G12: 0 | H12: 0 | I12: 0 | J12: 0 | K12: 0 | L12: 0 | M12: =C12+E12+G12+I12+K12 -> 0 | N12: =D12+F12+H12+J12+L12 -> 0
B13: TOTAL | C13: =SUM(C11:C12) -> 0 | D13: =SUM(D11:D12) -> 0 | E13: =SUM(E11:E12) -> 0 | F13: =SUM(F11:F12) -> 0 | G13: =SUM(G11:G12) -> 0 | H13: =SUM(H11:H12) -> 0 | I13: =SUM(I11:I12) -> 0 | J13: =SUM(J11:J12) -> 0 | ... N13: =SUM(N11:N12) -> 0
B16: EAAB RECIPROCIDAD
C17: ASE 1 | E17: ASE 2 | G17: ASE 3 | I17: ASE 4 | K17: ASE 5 | M17: TOTAL
C18: REPORTE 3 | D18: REPORTE 4 | E18: REPORTE 3 | F18: REPORTE 4 | G18: REPORTE 3 | H18: REPORTE 4 | I18: REPORTE 3 | J18: REPORTE 4 | K18: REPORTE 3 | L18: REPORTE 4 | M18: REPORTE 3 | N18: REPORTE 4
B19: APLICADO | C19: 0 | D19: 0 | E19: 0 | F19: 0 | G19: 0 | H19: 0 | I19: 0 | J19: 0 | K19: 0 | L19: 0 | M19: =C19+E19+G19+I19+K19 -> 0 | N19: =D19+F19+H19+J19+L19 -> 0
B20: ANTICIPOS | C20: 0 | D20: 0 | E20: 0 | F20: 0 | G20: 0 | H20: 0 | I20: 0 | J20: 0 | K20: 0 | L20: 0 | M20: =C20+E20+G20+I20+K20 -> 0 | N20: =D20+F20+H20+J20+L20 -> 0
B21: TOTAL | C21: =SUM(C19:C20) -> 0 | D21: =SUM(D19:D20) -> 0 | E21: =SUM(E19:E20) -> 0 | F21: =SUM(F19:F20) -> 0 | G21: =SUM(G19:G20) -> 0 | H21: =SUM(H19:H20) -> 0 | I21: =SUM(I19:I20) -> 0 | J21: =SUM(J19:J20) -> 0 | ... L21: =SUM(L19:L20) -> 0 | M21: =C21+E21+G21+I21+K21 -> 0 | N21: =SUM(N19:N20) -> 0
B24: EAAB CIUDAD LIMPIA
C25: ASE 1 | E25: ASE 2 | G25: ASE 3 | I25: ASE 4 | K25: ASE 5 | M25: TOTAL
C26: REPORTE 3 | D26: REPORTE 4 | E26: REPORTE 3 | F26: REPORTE 4 | G26: REPORTE 3 | H26: REPORTE 4 | I26: REPORTE 3 | J26: REPORTE 4 | K26: REPORTE 3 | L26: REPORTE 4 | M26: REPORTE 3 | N26: REPORTE 4
B27: APLICADO | C27: 0 | D27: 0 | E27: 0 | F27: 0 | G27: 0 | H27: 0 | I27: 0 | J27: 0 | K27: 0 | L27: 0 | M27: =C27+E27+G27+I27+K27 -> 0 | N27: =D27+F27+H27+J27+L27 -> 0
B28: ANTICIPOS | C28: 0 | D28: 0 | E28: 0 | F28: 0 | G28: 0 | H28: 0 | I28: 0 | J28: 0 | K28: 0 | L28: 0 | M28: =C28+E28+G28+I28+K28 -> 0 | N28: =D28+F28+H28+J28+L28 -> 0
B29: TOTAL | C29: =SUM(C27:C28) -> 0 | D29: =SUM(D27:D28) -> 0 | E29: =SUM(E27:E28) -> 0 | F29: =SUM(F27:F28) -> 0 | G29: =SUM(G27:G28) -> 0 | H29: =SUM(H27:H28) -> 0 | I29: =SUM(I27:I28) -> 0 | J29: =SUM(J27:J28) -> 0 | ... N29: =SUM(N27:N28) -> 0
B32: ENEL
C33: ASE 1 | E33: ASE 2 | G33: ASE 3 | I33: ASE 4 | K33: ASE 5 | M33: TOTAL
C34: REPORTE 3 | D34: REPORTE 4 | E34: REPORTE 3 | F34: REPORTE 4 | G34: REPORTE 3 | H34: REPORTE 4 | I34: REPORTE 3 | J34: REPORTE 4 | K34: REPORTE 3 | L34: REPORTE 4 | M34: REPORTE 3 | N34: REPORTE 4
B35: APLICADO | C35: 0 | D35: 0 | E35: 0 | F35: 0 | G35: 0 | H35: 0 | I35: 0 | J35: 0 | K35: 0 | L35: 0 | M35: =C35+E35+G35+I35+K35 -> 0 | N35: =D35+F35+H35+J35+L35 -> 0
B36: ANTICIPOS | C36: 0 | D36: 0 | E36: 0 | F36: 0 | G36: 0 | H36: 0 | I36: 0 | J36: 0 | K36: 0 | L36: 0 | M36: =C36+E36+G36+I36+K36 -> 0 | N36: =D36+F36+H36+J36+L36 -> 0
B37: TOTAL | C37: =SUM(C35:C36) -> 0 | D37: =SUM(D35:D36) -> 0 | E37: =SUM(E35:E36) -> 0 | F37: =SUM(F35:F36) -> 0 | G37: =SUM(G35:G36) -> 0 | H37: =SUM(H35:H36) -> 0 | I37: =SUM(I35:I36) -> 0 | J37: =SUM(J35:J36) -> 0 | ... N37: =SUM(N35:N36) -> 0
B40: ENERBIT
C41: ASE 1 | E41: ASE 2 | G41: ASE 3 | I41: ASE 4 | K41: ASE 5 | M41: TOTAL
C42: REPORTE 3 | D42: REPORTE 4 | E42: REPORTE 3 | F42: REPORTE 4 | G42: REPORTE 3 | H42: REPORTE 4 | I42: REPORTE 3 | J42: REPORTE 4 | K42: REPORTE 3 | L42: REPORTE 4 | M42: REPORTE 3 | N42: REPORTE 4
B43: APLICADO | C43: 0 | D43: 0 | E43: 0 | F43: 0 | G43: 0 | H43: 0 | I43: 0 | J43: 0 | K43: 0 | L43: 0 | M43: =C43+E43+G43+I43+K43 -> 0 | N43: =D43+F43+H43+J43+L43 -> 0
B44: ANTICIPOS | C44: 0 | D44: 0 | E44: 0 | F44: 0 | G44: 0 | H44: 0 | I44: 0 | J44: 0 | K44: 0 | L44: 0 | M44: =C44+E44+G44+I44+K44 -> 0 | N44: =D44+F44+H44+J44+L44 -> 0
B45: TOTAL | C45: =SUM(C43:C44) -> 0 | D45: =SUM(D43:D44) -> 0 | E45: =SUM(E43:E44) -> 0 | F45: =SUM(F43:F44) -> 0 | G45: =SUM(G43:G44) -> 0 | H45: =SUM(H43:H44) -> 0 | I45: =SUM(I43:I44) -> 0 | J45: =SUM(J43:J44) -> 0 | ... N45: =SUM(N43:N44) -> 0

Sheet ANTICIPOS USUARIOS
B1: TOTAL | E1: RECIPRCIDAD | H1: ENEL | K1: ENERBIT | N1: OCCIDENTE | Q1: EAAB-CIUDADLIMPIA
B2: ASE | C2: ANTICIPOS GENERADOS POR PAGO | E2: ASE | F2: ANTICIPOS GENERADOS POR PAGO | H2: ASE | I2: ANTICIPOS GENERADOS POR PAGO | K2: ASE | L2: ANTICIPOS GENERADOS POR PAGO | N2: ASE | O2: ANTICIPOS GENERADOS POR PAGO | Q2: ASE | R2: ANTICIPOS GENERADOS POR PAGO | T2: Anticipos generados por pago
B3: 1 | C3: ='REPORTE RECAUDO x BANCO'!I14 -> 33419430 | E3: 1 | F3: ='REPORTE RECAUDO x BANCO'!F14 -> 0 | H3: 1 | I3: ='REPORTE RECAUDO x BANCO'!C14 -> 25429155 | K3: 1 | L3: ='REPORTE RECAUDO x BANCO'!G14 -> 0 | N3: 1 | O3: ='REPORTE RECAUDO x BANCO'!H14 -> 7990275.5 | Q3: 1 | R3: ='REPORTE RECAUDO x BANCO'!D14+'REPORTE RECAUDO x BANCO'!E14 -> 0 | T3: Sale del reporte Recaudo por Bancos.
B4: 2 | C4: ='REPORTE RECAUDO x BANCO'!I24 -> 88020914 | E4: 2 | F4: ='REPORTE RECAUDO x BANCO'!F24 -> 8181830 | H4: 2 | I4: ='REPORTE RECAUDO x BANCO'!C24 -> 27050219 | K4: 2 | L4: ='REPORTE RECAUDO x BANCO'!G24 -> 0 | N4: 2 | O4: ='REPORTE RECAUDO x BANCO'!H24 -> 52788865 | Q4: 2 | R4: ='REPORTE RECAUDO x BANCO'!D24+'REPORTE RECAUDO x BANCO'!E24 -> 0
B5: 3 | C5: ='REPORTE RECAUDO x BANCO'!I33 -> 8946171 | E5: 3 | F5: ='REPORTE RECAUDO x BANCO'!F33 -> 0 | H5: 3 | I5: ='REPORTE RECAUDO x BANCO'!C33 -> 6025131 | K5: 3 | L5: ='REPORTE RECAUDO x BANCO'!G33 -> 0 | N5: 3 | O5: ='REPORTE RECAUDO x BANCO'!H33 -> 2921040 | Q5: 3 | R5: ='REPORTE RECAUDO x BANCO'!D33+'REPORTE RECAUDO x BANCO'!E33 -> 0
B6: 4 | C6: ='REPORTE RECAUDO x BANCO'!I42 -> 41072280 | E6: 4 | F6: ='REPORTE RECAUDO x BANCO'!F42 -> 5225400 | H6: 4 | I6: ='REPORTE RECAUDO x BANCO'!C42 -> 27660196 | K6: 4 | L6: ='REPORTE RECAUDO x BANCO'!G42 -> 0 | N6: 4 | O6: ='REPORTE RECAUDO x BANCO'!H42 -> 8186683.7 | Q6: 4 | R6: ='REPORTE RECAUDO x BANCO'!D42+'REPORTE RECAUDO x BANCO'!E42 -> 0
B7: 5 | C7: ='REPORTE RECAUDO x BANCO'!I52 -> 14445987 | E7: 5 | F7: ='REPORTE RECAUDO x BANCO'!F52 -> 0 | H7: 5 | I7: ='REPORTE RECAUDO x BANCO'!C52 -> 9759043 | K7: 5 | L7: ='REPORTE RECAUDO x BANCO'!G52 -> 1379910 | N7: 5 | O7: ='REPORTE RECAUDO x BANCO'!H52 -> 3307034 | Q7: 5 | R7: ='REPORTE RECAUDO x BANCO'!D52+'REPORTE RECAUDO x BANCO'!E52 -> 0
C8: =SUM(C3:C7) -> 1.8590478e+08 | F8: =SUM(F3:F7) -> 13407230 | I8: =SUM(I3:I7) -> 95923744 | L8: =SUM(L3:L7) -> 1379910 | O8: =SUM(O3:O7) -> 75193898 | R8: =SUM(R3:R7) -> 0
C9: =C8='REPORTE RECAUDO x BANCO'!I3 -> TRUE | F9: =F8='REPORTE RECAUDO x BANCO'!F3 -> TRUE | I9: =I8='REPORTE RECAUDO x BANCO'!C3 -> TRUE | L9: =L8='REPORTE RECAUDO x BANCO'!G3 -> TRUE | O9: =O8='REPORTE RECAUDO x BANCO'!H3 -> TRUE | R9: =R8='REPORTE RECAUDO x BANCO'!D3+'REPORTE RECAUDO x BANCO'!E3 -> TRUE
B11: ASE | C11: ANTICIPOS GENERADOS POR EXTEMPORANEOS | E11: ASE | F11: ANTICIPOS GENERADOS POR EXTEMPORANEOS | H11: ASE | I11: ANTICIPOS GENERADOS POR EXTEMPORANEOS | K11: ASE | L11: ANTICIPOS GENERADOS POR EXTEMPORANEOS | N11: ASE | O11: ANTICIPOS GENERADOS POR EXTEMPORANEOS | Q11: ASE | R11: ANTICIPOS GENERADOS POR EXTEMPORANEOS | T11: Anticipos generados por pagos aplicados de reversiones
B12: 1 | C12: ='ANT EXT-REV'!C4 -> 0 | E12: 1 | F12: ='ANT EXT-REV'!C20 -> 0 | H12: 1 | I12: ='ANT EXT-REV'!C36 -> 0 | K12: 1 | L12: ='ANT EXT-REV'!C44 -> 0 | N12: 1 | O12: ='ANT EXT-REV'!C12 -> 0 | Q12: 1 | R12: ='ANT EXT-REV'!C28 -> 0 | T12: Sale del reporte Recaudo reversado
B13: 2 | C13: ='ANT EXT-REV'!E4 -> 0 | E13: 2 | F13: ='ANT EXT-REV'!E20 -> 0 | H13: 2 | I13: ='ANT EXT-REV'!E36 -> 0 | K13: 2 | L13: ='ANT EXT-REV'!E44 -> 0 | N13: 2 | O13: ='ANT EXT-REV'!E12 -> 0 | Q13: 2 | R13: ='ANT EXT-REV'!E28 -> 0
B14: 3 | C14: ='ANT EXT-REV'!G4 -> 0 | E14: 3 | F14: ='ANT EXT-REV'!G20 -> 0 | H14: 3 | I14: ='ANT EXT-REV'!G36 -> 0 | K14: 3 | L14: ='ANT EXT-REV'!G44 -> 0 | N14: 3 | O14: ='ANT EXT-REV'!G12 -> 0 | Q14: 3 | R14: ='ANT EXT-REV'!G28 -> 0
B15: 4 | C15: ='ANT EXT-REV'!I4 -> 0 | E15: 4 | F15: ='ANT EXT-REV'!I20 -> 0 | H15: 4 | I15: ='ANT EXT-REV'!I36 -> 0 | K15: 4 | L15: ='ANT EXT-REV'!I44 -> 0 | N15: 4 | O15: ='ANT EXT-REV'!I12 -> 0 | Q15: 4 | R15: ='ANT EXT-REV'!I28 -> 0
B16: 5 | C16: ='ANT EXT-REV'!K4 -> 0 | E16: 5 | F16: ='ANT EXT-REV'!K20 -> 0 | H16: 5 | I16: ='ANT EXT-REV'!K36 -> 0 | K16: 5 | L16: ='ANT EXT-REV'!K44 -> 0 | N16: 5 | O16: ='ANT EXT-REV'!K12 -> 0 | Q16: 5 | R16: ='ANT EXT-REV'!K28 -> 0
C17: =SUM(C12:C16) -> 0 | F17: =SUM(F12:F16) -> 0 | I17: =SUM(I12:I16) -> 0 | L17: =SUM(L12:L16) -> 0 | O17: =SUM(O12:O16) -> 0 | R17: =SUM(R12:R16) -> 0
C18: =C17='ANT EXT-REV'!M4 -> TRUE | F18: =F17='ANT EXT-REV'!M20 -> TRUE | I18: =I17='ANT EXT-REV'!M36 -> TRUE | L18: =L17='ANT EXT-REV'!M44 -> TRUE | O18: =O17='ANT EXT-REV'!M12 -> TRUE | R18: =R17='ANT EXT-REV'!M28 -> TRUE
B20: ASE | C20: ANTICIPOS QUE CARGAN POR REVERSIONES | E20: ASE | F20: ANTICIPOS QUE CARGAN POR REVERSIONES | H20: ASE | I20: ANTICIPOS QUE CARGAN POR REVERSIONES | K20: ASE | L20: ANTICIPOS QUE CARGAN POR REVERSIONES | N20: ASE | O20: ANTICIPOS QUE CARGAN POR REVERSIONES | Q20: ASE | R20: ANTICIPOS QUE CARGAN POR REVERSIONES | T20: Anticipos que cargan de reversiones
B21: 1 | C21: ='ANT EXT-REV'!D4 -> 0 | E21: 1 | F21: ='ANT EXT-REV'!D20 -> 0 | H21: 1 | I21: ='ANT EXT-REV'!D36 -> 0 | K21: 1 | L21: ='ANT EXT-REV'!D44 -> 0 | N21: 1 | O21: ='ANT EXT-REV'!D12 -> 0 | Q21: 1 | R21: ='ANT EXT-REV'!D28 -> 0 | T21: Sale del reporte Recaudo reversado
B22: 2 | C22: ='ANT EXT-REV'!F4 -> 0 | E22: 2 | F22: ='ANT EXT-REV'!F20 -> 0 | H22: 2 | I22: ='ANT EXT-REV'!F36 -> 0 | K22: 2 | L22: ='ANT EXT-REV'!F44 -> 0 | N22: 2 | O22: ='ANT EXT-REV'!F12 -> 0 | Q22: 2 | R22: ='ANT EXT-REV'!F28 -> 0
B23: 3 | C23: ='ANT EXT-REV'!H4 -> 0 | E23: 3 | F23: ='ANT EXT-REV'!H20 -> 0 | H23: 3 | I23: ='ANT EXT-REV'!H36 -> 0 | K23: 3 | L23: ='ANT EXT-REV'!H44 -> 0 | N23: 3 | O23: ='ANT EXT-REV'!H12 -> 0 | Q23: 3 | R23: ='ANT EXT-REV'!H28 -> 0
B24: 4 | C24: ='ANT EXT-REV'!J4 -> 0 | E24: 4 | F24: ='ANT EXT-REV'!J20 -> 0 | H24: 4 | I24: ='ANT EXT-REV'!J36 -> 0 | K24: 4 | L24: ='ANT EXT-REV'!J44 -> 0 | N24: 4 | O24: ='ANT EXT-REV'!J12 -> 0 | Q24: 4 | R24: ='ANT EXT-REV'!J28 -> 0
B25: 5 | C25: ='ANT EXT-REV'!L4 -> 0 | E25: 5 | F25: ='ANT EXT-REV'!L20 -> 0 | H25: 5 | I25: ='ANT EXT-REV'!L36 -> 0 | K25: 5 | L25: ='ANT EXT-REV'!L44 -> 0 | N25: 5 | O25: ='ANT EXT-REV'!L12 -> 0 | Q25: 5 | R25: ='ANT EXT-REV'!L28 -> 0
C26: =SUM(C21:C25) -> 0 | F26: =SUM(F21:F25) -> 0 | I26: =SUM(I21:I25) -> 0 | L26: =SUM(L21:L25) -> 0 | O26: =SUM(O21:O25) -> 0 | R26: =SUM(R21:R25) -> 0
C27: =C26='ANT EXT-REV'!N4 -> TRUE | F27: =F26='ANT EXT-REV'!N20 -> TRUE | I27: =I26='ANT EXT-REV'!N36 -> TRUE | L27: =L26='ANT EXT-REV'!N44 -> TRUE | O27: =O26='ANT EXT-REV'!N12 -> TRUE | R27: =R26='ANT EXT-REV'!N28 -> TRUE

Sheet BCE SC POR FACT.
C2: ASE | D2: SUBSIDIO | E2: CONTRIBUCION | F2: TOTAL BSC | H2: SISTEMA
C3: 1 | D3: -1.2144311e+09 | E3: 3.8037668e+09 | F3: =D3+E3 -> 2.5893357e+09 | H3: =DetRetri2026091!J9 -> 2589335717 | I3: =F3-H3 -> -0.46000004
C4: 2 | D4: -7.0202293e+09 | E4: 1.9269695e+09 | F4: =D4+E4 -> -5.0932598e+09 | H4: =DetRetri2026091!J10 -> -5093259797 | I4: =F4-H4 -> -0.21999931
C5: 3 | D5: -3.1336986e+09 | E5: 1.9033016e+09 | F5: =D5+E5 -> -1.230397e+09 | H5: =DetRetri2026091!J11 -> -1230396998 | I5: =F5-H5 -> -0.43999982
C6: 4 | D6: -4.4790574e+08 | E6: 4.8603964e+08 | F6: =D6+E6 -> 38133906 | H6: =DetRetri2026091!J12 -> 38133906 | I6: =F6-H6 -> -0.19999999
C7: 5 | D7: -2.5354614e+09 | E7: 1.3113607e+09 | F7: =D7+E7 -> -1.2241007e+09 | H7: =DetRetri2026091!J13 -> -1224100690 | I7: =F7-H7 -> -0.46000028
F9: =SUM(F3:F7) -> -4.9202879e+09 | H9: =SUM(H3:H7) -> -4920287862 | I9: =F9-H9 -> -1.7799988
H10: =H9=DetRetri2026091!J14 -> TRUE
D11: =SUM(D3:D7) -> -1.4351726e+10 | E11: =SUM(E3:E7) -> 9.4314383e+09 | F11: =SUM(D3:E7) -> -4.9202879e+09
F12: =ROUND(F11,2)=ROUND(F9,2) -> TRUE
F13: =ROUND(F11,2)-ROUND(F9,2) -> 0
D18: ASE | E18: REMUN TOTAL | F18: VALIDA 1 | G18: VALIDA 2 | H18: DIFERENCIA VALIDA 2
D19: 1 | E19: ='CONSOLIDADO_TOTAL RECAUDO'!J104 -> 2.5893357e+09 | F19: =E19=F3 -> TRUE | G19: =E19=H3 -> FALSE | H19: =E19-H3 -> -0.46000004
D20: 2 | E20: ='CONSOLIDADO_TOTAL RECAUDO'!J105 -> -5.0932598e+09 | F20: =E20=F4 -> TRUE | G20: =E20=H4 -> FALSE | H20: =E20-H4 -> -0.21999931
D21: 3 | E21: ='CONSOLIDADO_TOTAL RECAUDO'!J106 -> -1.230397e+09 | F21: =E21=F5 -> TRUE | G21: =E21=H5 -> FALSE | H21: =E21-H5 -> -0.43999982
D22: 4 | E22: ='CONSOLIDADO_TOTAL RECAUDO'!J107 -> 38133906 | F22: =E22=F6 -> TRUE | G22: =E22=H6 -> FALSE | H22: =E22-H6 -> -0.19999999
D23: 5 | E23: ='CONSOLIDADO_TOTAL RECAUDO'!J108 -> -1.2241007e+09 | F23: =E23=F7 -> TRUE | G23: =E23=H7 -> FALSE | H23: =E23-H7 -> -0.46000028
E24: =SUM(E19:E23) -> -4.9202879e+09 | F24: =E24=F9 -> TRUE | G24: =E24=H9 -> FALSE | H24: =E24-H9 -> -1.7799988

Sheet Reporte Componentes R1
B4: PROMOAMBIENTAL
F5: Total | G5: Componente TDF | H5: Componente TTL | I5: Componente TVIAT | J5: Aprovechamiento | K5: CCSA Prest.Aprov. | L5: SERVICIO ESPECIALES | M5: Componente TCS | N5: Componente TLU | O5: Componente TBL | P5: Componente TRT | Q5: CCSA Prest. No Aprov. | R5: Ajuste Decena | S5: Ajuste Recargo Aseo | T5: Intereses Cte Financiac. Aseo | U5: Exonera-Recargo Aseo | V5: Exonera-Ajuste Decena Aseo | W5: Exonera-Recargo Aseo | X5: Exonera-Recargo Aseo | Y5: Intereses Cte Financiac. Aseo | Z5: Rec.Intereses
E6: Vlr Servicio | F6: -7108.83 | G6: -502.98 | H6: -213.69 | I6: -93.3 | J6: -1231.48 | K6: -79.58 | L6: 0 | M6: -698.02 | N6: -584.16 | O6: -2331.79 | P6: -1243.99 | Q6: -129.84 | R6: 0 | S6: 0 | T6: 0 | U6: 0 | V6: 0 | W6: 0 | X6: 0 | Y6: 0 | Z6: 0
D7: E | E7: Total | F7: -7108.83 | G7: -502.98 | H7: -213.69 | I7: -93.3 | J7: -1231.48 | K7: -79.58 | L7: 0 | M7: -698.02 | N7: -584.16 | O7: -2331.79 | P7: -1243.99 | Q7: -129.84 | R7: 0 | S7: 0 | T7: 0 | U7: 0 | V7: 0 | W7: 0 | X7: 0 | Y7: 0 | Z7: 0
C8: ENEL | D8: Total | F8: -7108.83 | G8: -502.98 | H8: -213.69 | I8: -93.3 | J8: -1231.48 | K8: -79.58 | L8: 0 | M8: -698.02 | N8: -584.16 | O8: -2331.79 | P8: -1243.99 | Q8: -129.84 | R8: 0 | S8: 0 | T8: 0 | U8: 0 | V8: 0 | W8: 0 | X8: 0 | Y8: 0 | Z8: 0
E9: Vlr Servicio | F9: 0 | G9: 0 | H9: 0 | I9: 0 | J9: 0 | K9: 0 | L9: 0 | M9: 0 | N9: 0 | O9: 0 | P9: 0 | Q9: 0 | R9: 0 | S9: 0 | T9: 0 | U9: 0 | V9: 0 | W9: 0 | X9: 0 | Y9: 0 | Z9: 0
D10: H | E10: Total | F10: 0 | G10: 0 | H10: 0 | I10: 0 | J10: 0 | K10: 0 | L10: 0 | M10: 0 | N10: 0 | O10: 0 | P10: 0 | Q10: 0 | R10: 0 | S10: 0 | T10: 0 | U10: 0 | V10: 0 | W10: 0 | X10: 0 | Y10: 0 | Z10: 0
E11: Vlr Servicio | F11: 0 | G11: 0 | H11: 0 | I11: 0 | J11: 0 | K11: 0 | L11: 0 | M11: 0 | N11: 0 | O11: 0 | P11: 0 | Q11: 0 | R11: 0 | S11: 0 | T11: 0 | U11: 0 | V11: 0 | W11: 0 | X11: 0 | Y11: 0 | Z11: 0
D12: O | E12: Total | F12: 0 | G12: 0 | H12: 0 | I12: 0 | J12: 0 | K12: 0 | L12: 0 | M12: 0 | N12: 0 | O12: 0 | P12: 0 | Q12: 0 | R12: 0 | S12: 0 | T12: 0 | U12: 0 | V12: 0 | W12: 0 | X12: 0 | Y12: 0 | Z12: 0
E13: Vlr Servicio | F13: 0 | G13: 0 | H13: 0 | I13: 0 | J13: 0 | K13: 0 | L13: 0 | M13: 0 | N13: 0 | O13: 0 | P13: 0 | Q13: 0 | R13: 0 | S13: 0 | T13: 0 | U13: 0 | V13: 0 | W13: 0 | X13: 0 | Y13: 0 | Z13: 0
D14: T | E14: Total | F14: 0 | G14: 0 | H14: 0 | I14: 0 | J14: 0 | K14: 0 | L14: 0 | M14: 0 | N14: 0 | O14: 0 | P14: 0 | Q14: 0 | R14: 0 | S14: 0 | T14: 0 | U14: 0 | V14: 0 | W14: 0 | X14: 0 | Y14: 0 | Z14: 0
C15: OCCIDENTE | D15: Total | F15: 0 | G15: 0 | H15: 0 | I15: 0 | J15: 0 | K15: 0 | L15: 0 | M15: 0 | N15: 0 | O15: 0 | P15: 0 | Q15: 0 | R15: 0 | S15: 0 | T15: 0 | U15: 0 | V15: 0 | W15: 0 | X15: 0 | Y15: 0 | Z15: 0
B16: Mes | C16: Total | F16: -7108.83 | G16: -502.98 | H16: -213.69 | I16: -93.3 | J16: -1231.48 | K16: -79.58 | L16: 0 | M16: -698.02 | N16: -584.16 | O16: -2331.79 | P16: -1243.99 | Q16: -129.84 | R16: 0 | S16: 0 | T16: 0 | U16: 0 | V16: 0 | W16: 0 | X16: 0 | Y16: 0 | Z16: 0
A17: AFaseo | B17: Total | F17: -7108.83 | G17: -502.98 | H17: -213.69 | I17: -93.3 | J17: -1231.48 | K17: -79.58 | L17: 0 | M17: -698.02 | N17: -584.16 | O17: -2331.79 | P17: -1243.99 | Q17: -129.84 | R17: 0 | S17: 0 | T17: 0 | U17: 0 | V17: 0 | W17: 0 | X17: 0 | Y17: 0 | Z17: 0
E18: Vlr Servicio | F18: 0 | G18: 0 | H18: 0 | I18: 0 | J18: 0 | K18: 0 | L18: 0 | M18: 0 | N18: 0 | O18: 0 | P18: 0 | Q18: 0 | R18: 0 | S18: 0 | T18: 0 | U18: 0 | V18: 0 | W18: 0 | X18: 0 | Y18: 0 | Z18: 0
E19: Vlr Intereses | F19: 0 | G19: 0 | H19: 0 | I19: 0 | J19: 0 | K19: 0 | L19: 0 | M19: 0 | N19: 0 | O19: 0 | P19: 0 | Q19: 0 | R19: 0 | S19: 0 | T19: 0 | U19: 0 | V19: 0 | W19: 0 | X19: 0 | Y19: 0 | Z19: 0
D20: E | E20: Total | F20: 0 | G20: 0 | H20: 0 | I20: 0 | J20: 0 | K20: 0 | L20: 0 | M20: 0 | N20: 0 | O20: 0 | P20: 0 | Q20: 0 | R20: 0 | S20: 0 | T20: 0 | U20: 0 | V20: 0 | W20: 0 | X20: 0 | Y20: 0 | Z20: 0
C21: ENEL | D21: Total | F21: 0 | G21: 0 | H21: 0 | I21: 0 | J21: 0 | K21: 0 | L21: 0 | M21: 0 | N21: 0 | O21: 0 | P21: 0 | Q21: 0 | R21: 0 | S21: 0 | T21: 0 | U21: 0 | V21: 0 | W21: 0 | X21: 0 | Y21: 0 | Z21: 0
E22: Vlr Servicio | F22: 0 | G22: 0 | H22: 0 | I22: 0 | J22: 0 | K22: 0 | L22: 0 | M22: 0 | N22: 0 | O22: 0 | P22: 0 | Q22: 0 | R22: 0 | S22: 0 | T22: 0 | U22: 0 | V22: 0 | W22: 0 | X22: 0 | Y22: 0 | Z22: 0
E23: Vlr Intereses | F23: 0 | G23: 0 | H23: 0 | I23: 0 | J23: 0 | K23: 0 | L23: 0 | M23: 0 | N23: 0 | O23: 0 | P23: 0 | Q23: 0 | R23: 0 | S23: 0 | T23: 0 | U23: 0 | V23: 0 | W23: 0 | X23: 0 | Y23: 0 | Z23: 0
D24: E | E24: Total | F24: 0 | G24: 0 | H24: 0 | I24: 0 | J24: 0 | K24: 0 | L24: 0 | M24: 0 | N24: 0 | O24: 0 | P24: 0 | Q24: 0 | R24: 0 | S24: 0 | T24: 0 | U24: 0 | V24: 0 | W24: 0 | X24: 0 | Y24: 0 | Z24: 0
C25: ENERBIT | D25: Total | F25: 0 | G25: 0 | H25: 0 | I25: 0 | J25: 0 | K25: 0 | L25: 0 | M25: 0 | N25: 0 | O25: 0 | P25: 0 | Q25: 0 | R25: 0 | S25: 0 | T25: 0 | U25: 0 | V25: 0 | W25: 0 | X25: 0 | Y25: 0 | Z25: 0
E26: Vlr Servicio | F26: 0 | G26: 0 | H26: 0 | I26: 0 | J26: 0 | K26: 0 | L26: 0 | M26: 0 | N26: 0 | O26: 0 | P26: 0 | Q26: 370.08 | R26: -1.95 | S26: 0 | T26: 0 | U26: 0 | V26: 0 | W26: 0 | X26: 0 | Y26: 0 | Z26: 0
E27: Vlr Intereses | F27: 0 | G27: 0 | H27: 0 | I27: 0 | J27: 0 | K27: 0 | L27: 0 | M27: 0 | N27: 0 | O27: 0 | P27: 0 | Q27: 0.07 | R27: 0 | S27: 0 | T27: 0 | U27: 0 | V27: 0 | W27: 0 | X27: 0 | Y27: 0 | Z27: 0
D28: H | E28: Total | F28: 0 | G28: 0 | H28: 0 | I28: 0 | J28: 0 | K28: 0 | L28: 0 | M28: 0 | N28: 0 | O28: 0 | P28: 0 | Q28: 370.15 | R28: -1.95 | S28: 0 | T28: 0 | U28: 0 | V28: 0 | W28: 0 | X28: 0 | Y28: 0 | Z28: 0
E29: Vlr Servicio | F29: 0 | G29: 0 | H29: 0 | I29: 0 | J29: 0 | K29: 0 | L29: 0 | M29: 0 | N29: 0 | O29: 0 | P29: 0 | Q29: 370.08 | R29: -1.95 | S29: 0 | T29: 0 | U29: 0 | V29: 0 | W29: 0 | X29: 0 | Y29: 0 | Z29: 0
E30: Vlr Intereses | F30: 0 | G30: 0 | H30: 0 | I30: 0 | J30: 0 | K30: 0 | L30: 0 | M30: 0 | N30: 0 | O30: 0 | P30: 0 | Q30: 0.07 | R30: 0 | S30: 0 | T30: 0 | U30: 0 | V30: 0 | W30: 0 | X30: 0 | Y30: 0 | Z30: 0
D31: O | E31: Total | F31: 0 | G31: 0 | H31: 0 | I31: 0 | J31: 0 | K31: 0 | L31: 0 | M31: 0 | N31: 0 | O31: 0 | P31: 0 | Q31: 370.15 | R31: -1.95 | S31: 0 | T31: 0 | U31: 0 | V31: 0 | W31: 0 | X31: 0 | Y31: 0 | Z31: 0
E32: Vlr Servicio | F32: 42672.75 | G32: 2083.59 | H32: 1160.96 | I32: 617.46 | J32: 10415.64 | K32: 383.02 | L32: 0 | M32: 3359.81 | N32: 3220.39 | O32: 15117.23 | P32: 5690.79 | Q32: 624.92 | R32: -1.06 | S32: 0 | T32: 0 | U32: 0 | V32: 0 | W32: 0 | X32: 0 | Y32: 0 | Z32: 0
E33: Vlr Intereses | F33: 7.25 | G33: 0.35 | H33: 0.2 | I33: 0.1 | J33: 1.77 | K33: 0.07 | L33: 0 | M33: 0.57 | N33: 0.54 | O33: 2.57 | P33: 0.97 | Q33: 0.11 | R33: 0 | S33: 0 | T33: 0 | U33: 0 | V33: 0 | W33: 0 | X33: 0 | Y33: 0 | Z33: 0
D34: T | E34: Total | F34: 42680 | G34: 2083.94 | H34: 1161.16 | I34: 617.56 | J34: 10417.41 | K34: 383.09 | L34: 0 | M34: 3360.38 | N34: 3220.93 | O34: 15119.8 | P34: 5691.76 | Q34: 625.03 | R34: -1.06 | S34: 0 | T34: 0 | U34: 0 | V34: 0 | W34: 0 | X34: 0 | Y34: 0 | Z34: 0
C35: OCCIDENTE | D35: Total | F35: 42680 | G35: 2083.94 | H35: 1161.16 | I35: 617.56 | J35: 10417.41 | K35: 383.09 | L35: 0 | M35: 3360.38 | N35: 3220.93 | O35: 15119.8 | P35: 5691.76 | Q35: 625.03 | R35: -1.06 | S35: 0 | T35: 0 | U35: 0 | V35: 0 | W35: 0 | X35: 0 | Y35: 0 | Z35: 0
B36: Aplicacion nuevos x reversion | C36: Total | F36: 42680 | G36: 2083.94 | H36: 1161.16 | I36: 617.56 | J36: 10417.41 | K36: 383.09 | L36: 0 | M36: 3360.38 | N36: 3220.93 | O36: 15119.8 | P36: 5691.76 | Q36: 625.03 | R36: -1.06 | S36: 0 | T36: 0 | U36: 0 | V36: 0 | W36: 0 | X36: 0 | Y36: 0 | Z36: 0
E37: Vlr Servicio | F37: 1.9865858e+10 | G37: 9.4982754e+08 | H37: 5.3058782e+08 | I37: 2.8117925e+08 | J37: 4.8115398e+09 | K37: 1.8047125e+08 | L37: 28843603 | M37: 1.5840574e+09 | N37: 1.5109569e+09 | O37: 7.108873e+09 | P37: 2.585077e+09 | Q37: 2.9449051e+08 | R37: -46186.47 | S37: 0 | T37: 0 | U37: 0 | V37: 0 | W37: 0 | X37: 0 | Y37: 0 | Z37: 0
E38: Vlr Intereses | F38: 3221187.2 | G38: 191257.04 | H38: 96240.8 | I38: 48070.33 | J38: 691627.43 | K38: 30779.35 | L38: 1888.23 | M38: 270442.29 | N38: 245214.4 | O38: 1082415 | P38: 513014.61 | Q38: 50206.13 | R38: -5.69 | S38: 0 | T38: 53.13 | U38: 0 | V38: 0 | W38: 0 | X38: 0 | Y38: 0 | Z38: -15.86
D39: E | E39: Total | F39: 1.9869079e+10 | G39: 9.500188e+08 | H39: 5.3068406e+08 | I39: 2.8122732e+08 | J39: 4.8122314e+09 | K39: 1.8050203e+08 | L39: 28845491 | M39: 1.5843279e+09 | N39: 1.5112021e+09 | O39: 7.1099554e+09 | P39: 2.58559e+09 | Q39: 2.9454072e+08 | R39: -46192.16 | S39: 0 | T39: 53.13 | U39: 0 | V39: 0 | W39: 0 | X39: 0 | Y39: 0 | Z39: -15.86
C40: ENEL | D40: Total | F40: 1.9869079e+10 | G40: 9.500188e+08 | H40: 5.3068406e+08 | I40: 2.8122732e+08 | J40: 4.8122314e+09 | K40: 1.8050203e+08 | L40: 28845491 | M40: 1.5843279e+09 | N40: 1.5112021e+09 | O40: 7.1099554e+09 | P40: 2.58559e+09 | Q40: 2.9454072e+08 | R40: -46192.16 | S40: 0 | T40: 53.13 | U40: 0 | V40: 0 | W40: 0 | X40: 0 | Y40: 0 | Z40: -15.86
E41: Vlr Servicio | F41: 0 | G41: 0 | H41: 0 | I41: 0 | J41: 0 | K41: 0 | L41: 0 | M41: 0 | N41: 0 | O41: 0 | P41: 0 | Q41: 0 | R41: 0 | S41: 0 | T41: 0 | U41: 0 | V41: 0 | W41: 0 | X41: 0 | Y41: 0 | Z41: 0
E42: Vlr Intereses | F42: 0 | G42: 0 | H42: 0 | I42: 0 | J42: 0 | K42: 0 | L42: 0 | M42: 0 | N42: 0 | O42: 0 | P42: 0 | Q42: 0 | R42: 0 | S42: 0 | T42: 0 | U42: 0 | V42: 0 | W42: 0 | X42: 0 | Y42: 0 | Z42: 0
D43: E | E43: Total | F43: 0 | G43: 0 | H43: 0 | I43: 0 | J43: 0 | K43: 0 | L43: 0 | M43: 0 | N43: 0 | O43: 0 | P43: 0 | Q43: 0 | R43: 0 | S43: 0 | T43: 0 | U43: 0 | V43: 0 | W43: 0 | X43: 0 | Y43: 0 | Z43: 0
C44: ENERBIT | D44: Total | F44: 0 | G44: 0 | H44: 0 | I44: 0 | J44: 0 | K44: 0 | L44: 0 | M44: 0 | N44: 0 | O44: 0 | P44: 0 | Q44: 0 | R44: 0 | S44: 0 | T44: 0 | U44: 0 | V44: 0 | W44: 0 | X44: 0 | Y44: 0 | Z44: 0
E45: Vlr Servicio | F45: 34834776 | G45: 3050420.4 | H45: 1694569.4 | I45: 901684.59 | J45: 6258963.8 | K45: 206736.51 | L45: 0 | M45: 1810170.8 | N45: 2156347.4 | O45: 10098959 | P45: 8319284.7 | Q45: 337911.22 | R45: -271.21 | S45: 0 | T45: 0 | U45: 0 | V45: 0 | W45: 0 | X45: 0 | Y45: 0 | Z45: 0
E46: Vlr Intereses | F46: 73612.43 | G46: 3963.92 | H46: 2089.52 | I46: 1132.4 | J46: 18172.87 | K46: 548.71 | L46: 0 | M46: 4821.44 | N46: 5503.49 | O46: 25681.1 | P46: 10802.17 | Q46: 897.07 | R46: -0.3 | S46: 0 | T46: 0.04 | U46: 0 | V46: 0 | W46: 0 | X46: 0 | Y46: 0 | Z46: 0
D47: H | E47: Total | F47: 34908389 | G47: 3054384.4 | H47: 1696658.9 | I47: 902816.99 | J47: 6277136.7 | K47: 207285.22 | L47: 0 | M47: 1814992.3 | N47: 2161850.9 | O47: 10124640 | P47: 8330086.8 | Q47: 338808.29 | R47: -271.51 | S47: 0 | T47: 0.04 | U47: 0 | V47: 0 | W47: 0 | X47: 0 | Y47: 0 | Z47: 0
E48: Vlr Servicio | F48: 99460670 | G48: 8743467.5 | H48: 4501924.5 | I48: 2257268.8 | J48: 15226576 | K48: 720340.83 | L48: 71191.32 | M48: 6347720.1 | N48: 6458242.7 | O48: 29949150 | P48: 24008686 | Q48: 1175914.7 | R48: 186.99 | S48: 0 | T48: 0 | U48: 0 | V48: 0 | W48: 0 | X48: 0 | Y48: 0 | Z48: 0
E49: Vlr Intereses | F49: 8554576 | G49: 822696.95 | H49: 248641.09 | I49: 50902.54 | J49: 1306165.8 | K49: 80047.98 | L49: 0 | M49: 702034.32 | N49: 586868.46 | O49: 2182750.4 | P49: 2443333.5 | Q49: 130594.62 | R49: 184.84 | S49: 0 | T49: 355.38 | U49: 0 | V49: 0 | W49: 0 | X49: 0 | Y49: 0 | Z49: 0
D50: O | E50: Total | F50: 1.0801525e+08 | G50: 9566164.5 | H50: 4750565.5 | I50: 2308171.3 | J50: 16532742 | K50: 800388.81 | L50: 71191.32 | M50: 7049754.4 | N50: 7045111.2 | O50: 32131901 | P50: 26452020 | Q50: 1306509.3 | R50: 371.83 | S50: 0 | T50: 355.38 | U50: 0 | V50: 0 | W50: 0 | X50: 0 | Y50: 0 | Z50: 0
E51: Vlr Servicio | F51: 2.3738431e+08 | G51: 38284622 | H51: 21414097 | I51: 11342632 | J51: 19779058 | K51: 508140.34 | L51: 1717780 | M51: 4440916.8 | N51: 6082873.5 | O51: 28426345 | P51: 1.0455968e+08 | Q51: 828965.34 | R51: -796.43 | S51: 0 | T51: 0 | U51: 0 | V51: 0 | W51: 0 | X51: 0 | Y51: 0 | Z51: 0
E52: Vlr Intereses | F52: 1223054.1 | G52: 158799.91 | H52: 78943.63 | I52: 38013.15 | J52: 162199.93 | K52: 5653.98 | L52: 1207.03 | M52: 49618.45 | N52: 61442.74 | O52: 241587.84 | P52: 416341.81 | Q52: 9230.55 | R52: 15.01 | S52: -0.06 | T52: 0.11 | U52: 0 | V52: 0 | W52: 0 | X52: 0 | Y52: 0 | Z52: 0
D53: T | E53: Total | F53: 2.3860737e+08 | G53: 38443422 | H53: 21493041 | I53: 11380645 | J53: 19941258 | K53: 513794.32 | L53: 1718987 | M53: 4490535.3 | N53: 6144316.2 | O53: 28667933 | P53: 1.0497602e+08 | Q53: 838195.89 | R53: -781.42 | S53: -0.06 | T53: 0.11 | U53: 0 | V53: 0 | W53: 0 | X53: 0 | Y53: 0 | Z53: 0
C54: OCCIDENTE | D54: Total | F54: 3.81531e+08 | G54: 51063971 | H54: 27940265 | I54: 14591634 | J54: 42751137 | K54: 1521468.4 | L54: 1790178.4 | M54: 13355282 | N54: 15351278 | O54: 70924473 | P54: 1.3975813e+08 | Q54: 2483513.5 | R54: -681.1 | S54: -0.06 | T54: 355.53 | U54: 0 | V54: 0 | W54: 0 | X54: 0 | Y54: 0 | Z54: 0
B55: Mes | C55: Total | F55: 2.025061e+10 | G55: 1.0010828e+09 | H55: 5.5862433e+08 | I55: 2.9581895e+08 | J55: 4.8549825e+09 | K55: 1.820235e+08 | L55: 30635670 | M55: 1.5976832e+09 | N55: 1.5265534e+09 | O55: 7.1808799e+09 | P55: 2.7253481e+09 | Q55: 2.9702423e+08 | R55: -46873.26 | S55: -0.06 | T55: 408.66 | U55: 0 | V55: 0 | W55: 0 | X55: 0 | Y55: 0 | Z55: -15.86
A56: Componente | B56: Total | F56: 2.0250653e+10 | G56: 1.0010849e+09 | H56: 5.5862549e+08 | I56: 2.9581957e+08 | J56: 4.8549929e+09 | K56: 1.8202388e+08 | L56: 30635670 | M56: 1.5976865e+09 | N56: 1.5265566e+09 | O56: 7.180895e+09 | P56: 2.7253538e+09 | Q56: 2.9702486e+08 | R56: -46874.32 | S56: -0.06 | T56: 408.66 | U56: 0 | V56: 0 | W56: 0 | X56: 0 | Y56: 0 | Z56: -15.86
E57: Subsidio(-)/Contribucion(+) | F57: 0 | G57: 0 | H57: 0 | I57: 0 | J57: 0 | K57: 0 | L57: 0 | M57: 0 | N57: 0 | O57: 0 | P57: 0 | Q57: 0 | R57: 0 | S57: 0 | T57: 0 | U57: 0 | V57: 0 | W57: 0 | X57: 0 | Y57: 0 | Z57: 0
D58: E | E58: Total | F58: 0 | G58: 0 | H58: 0 | I58: 0 | J58: 0 | K58: 0 | L58: 0 | M58: 0 | N58: 0 | O58: 0 | P58: 0 | Q58: 0 | R58: 0 | S58: 0 | T58: 0 | U58: 0 | V58: 0 | W58: 0 | X58: 0 | Y58: 0 | Z58: 0
C59: ENEL | D59: Total | F59: 0 | G59: 0 | H59: 0 | I59: 0 | J59: 0 | K59: 0 | L59: 0 | M59: 0 | N59: 0 | O59: 0 | P59: 0 | Q59: 0 | R59: 0 | S59: 0 | T59: 0 | U59: 0 | V59: 0 | W59: 0 | X59: 0 | Y59: 0 | Z59: 0
E60: Subsidio(-)/Contribucion(+) | F60: 0 | G60: 0 | H60: 0 | I60: 0 | J60: 0 | K60: 0 | L60: 0 | M60: 0 | N60: 0 | O60: 0 | P60: 0 | Q60: 0 | R60: 0 | S60: 0 | T60: 0 | U60: 0 | V60: 0 | W60: 0 | X60: 0 | Y60: 0 | Z60: 0
D61: E | E61: Total | F61: 0 | G61: 0 | H61: 0 | I61: 0 | J61: 0 | K61: 0 | L61: 0 | M61: 0 | N61: 0 | O61: 0 | P61: 0 | Q61: 0 | R61: 0 | S61: 0 | T61: 0 | U61: 0 | V61: 0 | W61: 0 | X61: 0 | Y61: 0 | Z61: 0
C62: ENERBIT | D62: Total | F62: 0 | G62: 0 | H62: 0 | I62: 0 | J62: 0 | K62: 0 | L62: 0 | M62: 0 | N62: 0 | O62: 0 | P62: 0 | Q62: 0 | R62: 0 | S62: 0 | T62: 0 | U62: 0 | V62: 0 | W62: 0 | X62: 0 | Y62: 0 | Z62: 0
E63: Subsidio(-)/Contribucion(+) | F63: 0 | G63: 0 | H63: 0 | I63: 0 | J63: 0 | K63: 0 | L63: 0 | M63: 0 | N63: 0 | O63: 0 | P63: 0 | Q63: 0 | R63: 0 | S63: 0 | T63: 0 | U63: 0 | V63: 0 | W63: 0 | X63: 0 | Y63: 0 | Z63: 0
D64: H | E64: Total | F64: 0 | G64: 0 | H64: 0 | I64: 0 | J64: 0 | K64: 0 | L64: 0 | M64: 0 | N64: 0 | O64: 0 | P64: 0 | Q64: 0 | R64: 0 | S64: 0 | T64: 0 | U64: 0 | V64: 0 | W64: 0 | X64: 0 | Y64: 0 | Z64: 0
E65: Subsidio(-)/Contribucion(+) | F65: 0 | G65: 0 | H65: 0 | I65: 0 | J65: 0 | K65: 0 | L65: 0 | M65: 0 | N65: 0 | O65: 0 | P65: 0 | Q65: 0 | R65: 0 | S65: 0 | T65: 0 | U65: 0 | V65: 0 | W65: 0 | X65: 0 | Y65: 0 | Z65: 0
D66: O | E66: Total | F66: 0 | G66: 0 | H66: 0 | I66: 0 | J66: 0 | K66: 0 | L66: 0 | M66: 0 | N66: 0 | O66: 0 | P66: 0 | Q66: 0 | R66: 0 | S66: 0 | T66: 0 | U66: 0 | V66: 0 | W66: 0 | X66: 0 | Y66: 0 | Z66: 0
E67: Subsidio(-)/Contribucion(+) | F67: 0 | G67: 0 | H67: 0 | I67: 0 | J67: 0 | K67: 0 | L67: 0 | M67: 0 | N67: 0 | O67: 0 | P67: 0 | Q67: 0 | R67: 0 | S67: 0 | T67: 0 | U67: 0 | V67: 0 | W67: 0 | X67: 0 | Y67: 0 | Z67: 0
D68: T | E68: Total | F68: 0 | G68: 0 | H68: 0 | I68: 0 | J68: 0 | K68: 0 | L68: 0 | M68: 0 | N68: 0 | O68: 0 | P68: 0 | Q68: 0 | R68: 0 | S68: 0 | T68: 0 | U68: 0 | V68: 0 | W68: 0 | X68: 0 | Y68: 0 | Z68: 0
C69: OCCIDENTE | D69: Total | F69: 0 | G69: 0 | H69: 0 | I69: 0 | J69: 0 | K69: 0 | L69: 0 | M69: 0 | N69: 0 | O69: 0 | P69: 0 | Q69: 0 | R69: 0 | S69: 0 | T69: 0 | U69: 0 | V69: 0 | W69: 0 | X69: 0 | Y69: 0 | Z69: 0
B70: Aplicacion nuevos x reversion | C70: Total | F70: 0 | G70: 0 | H70: 0 | I70: 0 | J70: 0 | K70: 0 | L70: 0 | M70: 0 | N70: 0 | O70: 0 | P70: 0 | Q70: 0 | R70: 0 | S70: 0 | T70: 0 | U70: 0 | V70: 0 | W70: 0 | X70: 0 | Y70: 0 | Z70: 0
E71: Subsidio(-)/Contribucion(+) | F71: -2.946116e+09 | G71: -66231005 | H71: -36832734 | I71: -19652614 | J71: -8.2718576e+08 | K71: -30673428 | L71: 0 | M71: -2.6937726e+08 | N71: -2.5777835e+08 | O71: -1.2109156e+09 | P71: -1.7742294e+08 | Q71: -50046274 | R71: 0 | S71: 0 | T71: 0 | U71: 0 | V71: 0 | W71: 0 | X71: 0 | Y71: 0 | Z71: 0
D72: E | E72: Total | F72: -2.946116e+09 | G72: -66231005 | H72: -36832734 | I72: -19652614 | J72: -8.2718576e+08 | K72: -30673428 | L72: 0 | M72: -2.6937726e+08 | N72: -2.5777835e+08 | O72: -1.2109156e+09 | P72: -1.7742294e+08 | Q72: -50046274 | R72: 0 | S72: 0 | T72: 0 | U72: 0 | V72: 0 | W72: 0 | X72: 0 | Y72: 0 | Z72: 0
C73: ENEL | D73: Total | F73: -2.946116e+09 | G73: -66231005 | H73: -36832734 | I73: -19652614 | J73: -8.2718576e+08 | K73: -30673428 | L73: 0 | M73: -2.6937726e+08 | N73: -2.5777835e+08 | O73: -1.2109156e+09 | P73: -1.7742294e+08 | Q73: -50046274 | R73: 0 | S73: 0 | T73: 0 | U73: 0 | V73: 0 | W73: 0 | X73: 0 | Y73: 0 | Z73: 0
E74: Subsidio(-)/Contribucion(+) | F74: 0 | G74: 0 | H74: 0 | I74: 0 | J74: 0 | K74: 0 | L74: 0 | M74: 0 | N74: 0 | O74: 0 | P74: 0 | Q74: 0 | R74: 0 | S74: 0 | T74: 0 | U74: 0 | V74: 0 | W74: 0 | X74: 0 | Y74: 0 | Z74: 0
D75: E | E75: Total | F75: 0 | G75: 0 | H75: 0 | I75: 0 | J75: 0 | K75: 0 | L75: 0 | M75: 0 | N75: 0 | O75: 0 | P75: 0 | Q75: 0 | R75: 0 | S75: 0 | T75: 0 | U75: 0 | V75: 0 | W75: 0 | X75: 0 | Y75: 0 | Z75: 0
C76: ENERBIT | D76: Total | F76: 0 | G76: 0 | H76: 0 | I76: 0 | J76: 0 | K76: 0 | L76: 0 | M76: 0 | N76: 0 | O76: 0 | P76: 0 | Q76: 0 | R76: 0 | S76: 0 | T76: 0 | U76: 0 | V76: 0 | W76: 0 | X76: 0 | Y76: 0 | Z76: 0
E77: Subsidio(-)/Contribucion(+) | F77: 6948561.3 | G77: 1410581.2 | H77: 792768.83 | I77: 419896.52 | J77: 180596.23 | K77: -3882.3 | L77: 0 | M77: -34057.21 | N77: 57414.32 | O77: 271593.35 | P77: 3859983.6 | Q77: -6333.32 | R77: 0 | S77: 0 | T77: 0 | U77: 0 | V77: 0 | W77: 0 | X77: 0 | Y77: 0 | Z77: 0
D78: H | E78: Total | F78: 6948561.3 | G78: 1410581.2 | H78: 792768.83 | I78: 419896.52 | J78: 180596.23 | K78: -3882.3 | L78: 0 | M78: -34057.21 | N78: 57414.32 | O78: 271593.35 | P78: 3859983.6 | Q78: -6333.32 | R78: 0 | S78: 0 | T78: 0 | U78: 0 | V78: 0 | W78: 0 | X78: 0 | Y78: 0 | Z78: 0
E79: Subsidio(-)/Contribucion(+) | F79: 18379766 | G79: 3896523 | H79: 1932685.5 | I79: 904936.27 | J79: 174866.47 | K79: -4332.57 | L79: 0 | M79: -47024.58 | N79: 133689.19 | O79: 548414.37 | P79: 10847077 | Q79: -7068.65 | R79: 0 | S79: 0 | T79: 0 | U79: 0 | V79: 0 | W79: 0 | X79: 0 | Y79: 0 | Z79: 0
D80: O | E80: Total | F80: 18379766 | G80: 3896523 | H80: 1932685.5 | I80: 904936.27 | J80: 174866.47 | K80: -4332.57 | L80: 0 | M80: -47024.58 | N80: 133689.19 | O80: 548414.37 | P80: 10847077 | Q80: -7068.65 | R80: 0 | S80: 0 | T80: 0 | U80: 0 | V80: 0 | W80: 0 | X80: 0 | Y80: 0 | Z80: 0
E81: Subsidio(-)/Contribucion(+) | F81: 1.1972783e+08 | G81: 21174918 | H81: 11896575 | I81: 6266740.5 | J81: 7356037.8 | K81: 191531.36 | L81: 0 | M81: 1677524.2 | N81: 2303267 | O81: 10782216 | P81: 57766394 | Q81: 312627.59 | R81: 0 | S81: 0 | T81: 0 | U81: 0 | V81: 0 | W81: 0 | X81: 0 | Y81: 0 | Z81: 0
D82: T | E82: Total | F82: 1.1972783e+08 | G82: 21174918 | H82: 11896575 | I82: 6266740.5 | J82: 7356037.8 | K82: 191531.36 | L82: 0 | M82: 1677524.2 | N82: 2303267 | O82: 10782216 | P82: 57766394 | Q82: 312627.59 | R82: 0 | S82: 0 | T82: 0 | U82: 0 | V82: 0 | W82: 0 | X82: 0 | Y82: 0 | Z82: 0
C83: OCCIDENTE | D83: Total | F83: 1.4505616e+08 | G83: 26482022 | H83: 14622030 | I83: 7591573.3 | J83: 7711500.5 | K83: 183316.49 | L83: 0 | M83: 1596442.5 | N83: 2494370.5 | O83: 11602224 | P83: 72473455 | Q83: 299225.62 | R83: 0 | S83: 0 | T83: 0 | U83: 0 | V83: 0 | W83: 0 | X83: 0 | Y83: 0 | Z83: 0
B84: Mes | C84: Total | F84: -2.8010598e+09 | G84: -39748983 | H84: -22210705 | I84: -12061041 | J84: -8.1947426e+08 | K84: -30490112 | L84: 0 | M84: -2.6778081e+08 | N84: -2.5528398e+08 | O84: -1.1993134e+09 | P84: -1.0494949e+08 | Q84: -49747048 | R84: 0 | S84: 0 | T84: 0 | U84: 0 | V84: 0 | W84: 0 | X84: 0 | Y84: 0 | Z84: 0
A85: Subs/Cont | B85: Total | F85: -2.8010598e+09 | G85: -39748983 | H85: -22210705 | I85: -12061041 | J85: -8.1947426e+08 | K85: -30490112 | L85: 0 | M85: -2.6778081e+08 | N85: -2.5528398e+08 | O85: -1.1993134e+09 | P85: -1.0494949e+08 | Q85: -49747048 | R85: 0 | S85: 0 | T85: 0 | U85: 0 | V85: 0 | W85: 0 | X85: 0 | Y85: 0 | Z85: 0
A86: Total | F86: 1.7449586e+10 | G86: 9.6133536e+08 | H86: 5.3641457e+08 | I86: 2.8375844e+08 | J86: 4.0355174e+09 | K86: 1.5153369e+08 | L86: 30635670 | M86: 1.329905e+09 | N86: 1.271272e+09 | O86: 5.9815793e+09 | P86: 2.6204031e+09 | Q86: 2.4727768e+08 | R86: -46874.32 | S86: -0.06 | T86: 408.66 | U86: 0 | V86: 0 | W86: 0 | X86: 0 | Y86: 0 | Z86: -15.86
C89: TOTAL | D89: OPORTUNO | E89: Total | F89: =F55+F84+F16-L16-L55 -> 1.7418907e+10 | G89: =G55+G16 -> 1.0010823e+09 | H89: =H55+H16 -> 5.5862411e+08 | I89: =I55+I16 -> 2.9581886e+08 | J89: =J55+J16 -> 4.8549813e+09 | K89: =K55+K16 -> 1.8202342e+08 | L89: =L55+L16 -> 30635670 | M89: =M55+M16 -> 1.5976825e+09 | N89: =N55+N16 -> 1.5265528e+09 | ... AP89: =AP55+AP16 -> 0
E90: Subsidio(-)/Contribucion(+) | F90: =F84 -> -2.8010598e+09
D91: EXTEMPORANEO | E91: Total | F91: =F70+F36-L36 -> 42680 | G91: =G36 -> 2083.94 | H91: =H36 -> 1161.16 | I91: =I36 -> 617.56 | J91: =J36 -> 10417.41 | K91: =K36 -> 383.09 | L91: =L36 -> 0 | M91: =M36 -> 3360.38 | N91: =N36 -> 3220.93 | ... AP91: =AP36 -> 0
E92: Subsidio(-)/Contribucion(+) | F92: =F70 -> 0
C94: RECIPROCIDAD | D94: OPORTUNO | E94: Total | F94: 0 | G94: 0 | H94: 0 | I94: 0 | J94: 0 | K94: 0 | L94: 0 | M94: 0 | N94: 0 | O94: 0 | P94: 0 | Q94: 0 | R94: 0 | S94: 0 | T94: 0 | U94: 0 | V94: 0 | W94: 0 | X94: 0 | Y94: 0 | Z94: 0 | AA94: 0 | AB94: 0 | AC94: 0 | AD94: 0 | AE94: 0 | AF94: 0 | AG94: 0 | AH94: 0 | AI94: 0 | AJ94: 0 | AK94: 0 | AL94: 0 | AM94: 0 | AN94: 0 | AO94: 0 | AP94: 0
E95: Subsidio(-)/Contribucion(+) | F95: 0
D96: EXTEMPORANEO | E96: Total | F96: 0 | G96: 0 | H96: 0 | I96: 0 | J96: 0 | K96: 0 | L96: 0 | M96: 0 | N96: 0 | O96: 0 | P96: 0 | Q96: 0 | R96: 0 | S96: 0 | T96: 0 | U96: 0 | V96: 0 | W96: 0 | X96: 0 | Y96: 0 | Z96: 0 | AA96: 0 | AB96: 0 | AC96: 0 | AD96: 0 | AE96: 0 | AF96: 0 | AG96: 0 | AH96: 0 | AI96: 0 | AJ96: 0 | AK96: 0 | AL96: 0 | AM96: 0 | AN96: 0 | AO96: 0 | AP96: 0
E97: Subsidio(-)/Contribucion(+) | F97: 0
C99: ENEL | D99: OPORTUNO | E99: Total | F99: =F73+F40+F8-L8-L40 -> 1.689411e+10 | G99: =G40+G8 -> 9.5001829e+08 | H99: =H40+H8 -> 5.3068385e+08 | I99: =I40+I8 -> 2.8122723e+08 | J99: =J40+J8 -> 4.8122301e+09 | K99: =K40+K8 -> 1.8050195e+08 | L99: =L40+L8 -> 28845491 | M99: =M40+M8 -> 1.5843272e+09 | N99: =N40+N8 -> 1.5112015e+09 | ... AP99: =AP40+AP8 -> 0
E100: Subsidio(-)/Contribucion(+) | F100: =F73 -> -2.946116e+09
D101: EXTEMPORANEO | E101: Total | F101: =F59+F21-L21 -> 0 | G101: =G21 -> 0 | H101: =H21 -> 0 | I101: =I21 -> 0 | J101: =J21 -> 0 | K101: =K21 -> 0 | L101: =L21 -> 0 | M101: =M21 -> 0 | N101: =N21 -> 0 | ... AP101: =AP21 -> 0
E102: Subsidio(-)/Contribucion(+) | F102: =F59 -> 0
C104: ENERBIT | D104: OPORTUNO | E104: Total | F104: =F76+F44-L44 -> 0 | G104: =G44 -> 0 | H104: =H44 -> 0 | I104: =I44 -> 0 | J104: =J44 -> 0 | K104: =K44 -> 0 | L104: =L44 -> 0 | M104: =M44 -> 0 | N104: =N44 -> 0 | ... AO104: =AO44 -> 0
E105: Subsidio(-)/Contribucion(+) | F105: =F76 -> 0
D106: EXTEMPORANEO | E106: Total | F106: =F62+F25-L25 -> 0 | G106: =G25 -> 0 | H106: =H25 -> 0 | I106: =I25 -> 0 | J106: =J25 -> 0 | K106: =K25 -> 0 | L106: =L25 -> 0 | M106: =M25 -> 0 | N106: =N25 -> 0 | ... AO106: =AO25 -> 0
E107: Subsidio(-)/Contribucion(+) | F107: =F62 -> 0
C109: OCCIDENTE | D109: OPORTUNO | E109: Total | F109: =F83+F54+F15-L15-L54 -> 5.2479698e+08 | G109: =G54+G15 -> 51063971 | H109: =H54+H15 -> 27940265 | I109: =I54+I15 -> 14591634 | J109: =J54+J15 -> 42751137 | K109: =K54+K15 -> 1521468.4 | L109: =L54+L15 -> 1790178.4 | M109: =M54+M15 -> 13355282 | N109: =N54+N15 -> 15351278 | ... AP109: =AP54+AP15 -> 0
...

Sheet Rem. Anticipos R2
B1: PROMOAMBIENTAL
E2: Total | F2: Componente TDF | G2: Componente TTL | H2: Componente TVIAT | I2: Aprovechamiento | J2: CCSA Prest.Aprov. | K2: Especiales | L2: Componente TCS | M2: Componente TLU | N2: Componente TBL | O2: Componente TRT | P2: CCSA Prest. No Aprov. | Q2: Deb/Cred | R2: Deb/Cred-otros
D3: Vlr Servicio | E3: 0 | F3: 0 | G3: 0 | H3: 0 | I3: 0 | J3: 0 | K3: 0 | L3: 0 | M3: 0 | N3: 0 | O3: 0 | P3: 0 | Q3: 0 | R3: 0
D4: Vlr Intereses | E4: 0 | F4: 0 | G4: 0 | H4: 0 | I4: 0 | J4: 0 | K4: 0 | L4: 0 | M4: 0 | N4: 0 | O4: 0 | P4: 0 | Q4: 0 | R4: 0
C5: A | D5: Total | E5: 0 | F5: 0 | G5: 0 | H5: 0 | I5: 0 | J5: 0 | K5: 0 | L5: 0 | M5: 0 | N5: 0 | O5: 0 | P5: 0 | Q5: 0 | R5: 0
B6: EAB | C6: Total | E6: 0 | F6: 0 | G6: 0 | H6: 0 | I6: 0 | J6: 0 | K6: 0 | L6: 0 | M6: 0 | N6: 0 | O6: 0 | P6: 0 | Q6: 0 | R6: 0
D7: Vlr Servicio | E7: 29113116 | F7: 1628607.2 | G7: 888839.63 | H7: 520100 | I7: 4494462.8 | J7: 206660.7 | K7: 0 | L7: 2285816.4 | M7: 2318036.2 | N7: 11916210 | O7: 4523138.8 | P7: 331271.2 | Q7: -26.69 | R7: 0
D8: Vlr Intereses | E8: 1903.01 | F8: 73.46 | G8: 40.2 | H8: 21.55 | I8: 326.7 | J8: 21.37 | K8: 0 | L8: 192.26 | M8: 174.97 | N8: 818.31 | O8: 199.3 | P8: 34.85 | Q8: 0.04 | R8: 0
C9: E | D9: Total | E9: 29115019 | F9: 1628680.7 | G9: 888879.83 | H9: 520121.55 | I9: 4494789.5 | J9: 206682.07 | K9: 0 | L9: 2286008.7 | M9: 2318211.1 | N9: 11917028 | O9: 4523338.1 | P9: 331306.05 | Q9: -26.65 | R9: 0
B10: ENEL | C10: Total | E10: 29115019 | F10: 1628680.7 | G10: 888879.83 | H10: 520121.55 | I10: 4494789.5 | J10: 206682.07 | K10: 0 | L10: 2286008.7 | M10: 2318211.1 | N10: 11917028 | O10: 4523338.1 | P10: 331306.05 | Q10: -26.65 | R10: 0
D11: Vlr Servicio | E11: 0 | F11: 0 | G11: 0 | H11: 0 | I11: 0 | J11: 0 | K11: 0 | L11: 0 | M11: 0 | N11: 0 | O11: 0 | P11: 0 | Q11: 0 | R11: 0
D12: Vlr Intereses | E12: 0 | F12: 0 | G12: 0 | H12: 0 | I12: 0 | J12: 0 | K12: 0 | L12: 0 | M12: 0 | N12: 0 | O12: 0 | P12: 0 | Q12: 0 | R12: 0
C13: E | D13: Total | E13: 0 | F13: 0 | G13: 0 | H13: 0 | I13: 0 | J13: 0 | K13: 0 | L13: 0 | M13: 0 | N13: 0 | O13: 0 | P13: 0 | Q13: 0 | R13: 0
B14: ENERBIT | C14: Total | E14: 0 | F14: 0 | G14: 0 | H14: 0 | I14: 0 | J14: 0 | K14: 0 | L14: 0 | M14: 0 | N14: 0 | O14: 0 | P14: 0 | Q14: 0 | R14: 0
D15: Vlr Servicio | E15: 793692.13 | F15: 30716.86 | G15: 16909.04 | H15: 9688.4 | I15: 151298.66 | J15: 7470.71 | K15: 0 | L15: 68892.29 | M15: 68745.87 | N15: 346268.88 | O15: 81506.79 | P15: 12188.93 | Q15: 5.7 | R15: 0
D16: Vlr Intereses | E16: 390.56 | F16: 13.47 | G16: 6.62 | H16: 4.12 | I16: 56.72 | J16: 4.51 | K16: 0 | L16: 39.61 | M16: 38.85 | N16: 182.43 | O16: 36.86 | P16: 7.36 | Q16: 0.01 | R16: 0
C17: H | D17: Total | E17: 794082.69 | F17: 30730.33 | G17: 16915.66 | H17: 9692.52 | I17: 151355.38 | J17: 7475.22 | K17: 0 | L17: 68931.9 | M17: 68784.72 | N17: 346451.31 | O17: 81543.65 | P17: 12196.29 | Q17: 5.71 | R17: 0
D18: Vlr Servicio | E18: 462871.22 | F18: 17750.61 | G18: 9935.12 | H18: 5797.01 | I18: 63590.58 | J18: 4697.55 | K18: 0 | L18: 43276.6 | M18: 42645.09 | N18: 218816.26 | O18: 48699.89 | P18: 7664.33 | Q18: -1.82 | R18: 0
D19: Vlr Intereses | E19: 0 | F19: 0 | G19: 0 | H19: 0 | I19: 0 | J19: 0 | K19: 0 | L19: 0 | M19: 0 | N19: 0 | O19: 0 | P19: 0 | Q19: 0 | R19: 0
C20: O | D20: Total | E20: 462871.22 | F20: 17750.61 | G20: 9935.12 | H20: 5797.01 | I20: 63590.58 | J20: 4697.55 | K20: 0 | L20: 43276.6 | M20: 42645.09 | N20: 218816.26 | O20: 48699.89 | P20: 7664.33 | Q20: -1.82 | R20: 0
D21: Vlr Servicio | E21: 2198318.9 | F21: 188049.69 | G21: 89756.71 | H21: 48201.07 | I21: 310657.06 | J21: 11520.24 | K21: 0 | L21: 108962.88 | M21: 96743.8 | N21: 469156.33 | O21: 856474.39 | P21: 18795.96 | Q21: 0.79 | R21: 0
D22: Vlr Intereses | E22: 0 | F22: 0 | G22: 0 | H22: 0 | I22: 0 | J22: 0 | K22: 0 | L22: 0 | M22: 0 | N22: 0 | O22: 0 | P22: 0 | Q22: 0 | R22: 0
C23: T | D23: Total | E23: 2198318.9 | F23: 188049.69 | G23: 89756.71 | H23: 48201.07 | I23: 310657.06 | J23: 11520.24 | K23: 0 | L23: 108962.88 | M23: 96743.8 | N23: 469156.33 | O23: 856474.39 | P23: 18795.96 | Q23: 0.79 | R23: 0
B24: OCCIDENTE | C24: Total | E24: 3455272.8 | F24: 236530.63 | G24: 116607.49 | H24: 63690.6 | I24: 525603.02 | J24: 23693.01 | K24: 0 | L24: 221171.38 | M24: 208173.61 | N24: 1034423.9 | O24: 986717.93 | P24: 38656.58 | Q24: 4.68 | R24: 0
A25: Componente | B25: Total | E25: 32570292 | F25: 1865211.3 | G25: 1005487.3 | H25: 583812.15 | I25: 5020392.6 | J25: 230375.08 | K25: 0 | L25: 2507180.1 | M25: 2526384.8 | N25: 12951452 | O25: 5510056 | P25: 369962.63 | Q25: -21.97 | R25: 0
D26: Subsidio(-)/Contribucion(+) | E26: 0 | F26: 0 | G26: 0 | H26: 0 | I26: 0 | J26: 0 | K26: 0 | L26: 0 | M26: 0 | N26: 0 | O26: 0 | P26: 0 | Q26: 0 | R26: 0
C27: A | D27: Total | E27: 0 | F27: 0 | G27: 0 | H27: 0 | I27: 0 | J27: 0 | K27: 0 | L27: 0 | M27: 0 | N27: 0 | O27: 0 | P27: 0 | Q27: 0 | R27: 0
B28: EAB | C28: Total | E28: 0 | F28: 0 | G28: 0 | H28: 0 | I28: 0 | J28: 0 | K28: 0 | L28: 0 | M28: 0 | N28: 0 | O28: 0 | P28: 0 | Q28: 0 | R28: 0
D29: Subsidio(-)/Contribucion(+) | E29: 1139503.2 | F29: 264067.13 | G29: 147039.05 | H29: 72868.6 | I29: -136480.3 | J29: 3896.46 | K29: 0 | L29: -61838.04 | M29: -5695.54 | N29: 107985.49 | O29: 741490.48 | P29: 6169.9 | Q29: 0 | R29: 0
C30: E | D30: Total | E30: 1139503.2 | F30: 264067.13 | G30: 147039.05 | H30: 72868.6 | I30: -136480.3 | J30: 3896.46 | K30: 0 | L30: -61838.04 | M30: -5695.54 | N30: 107985.49 | O30: 741490.48 | P30: 6169.9 | Q30: 0 | R30: 0
B31: ENEL | C31: Total | E31: 1139503.2 | F31: 264067.13 | G31: 147039.05 | H31: 72868.6 | I31: -136480.3 | J31: 3896.46 | K31: 0 | L31: -61838.04 | M31: -5695.54 | N31: 107985.49 | O31: 741490.48 | P31: 6169.9 | Q31: 0 | R31: 0
D32: Subsidio(-)/Contribucion(+) | E32: 0 | F32: 0 | G32: 0 | H32: 0 | I32: 0 | J32: 0 | K32: 0 | L32: 0 | M32: 0 | N32: 0 | O32: 0 | P32: 0 | Q32: 0 | R32: 0
C33: E | D33: Total | E33: 0 | F33: 0 | G33: 0 | H33: 0 | I33: 0 | J33: 0 | K33: 0 | L33: 0 | M33: 0 | N33: 0 | O33: 0 | P33: 0 | Q33: 0 | R33: 0
B34: ENERBIT | C34: Total | E34: 0 | F34: 0 | G34: 0 | H34: 0 | I34: 0 | J34: 0 | K34: 0 | L34: 0 | M34: 0 | N34: 0 | O34: 0 | P34: 0 | Q34: 0 | R34: 0
D35: Subsidio(-)/Contribucion(+) | E35: 124917.68 | F35: 5425.49 | G35: 3470.55 | H35: 2025.09 | I35: 30214.16 | J35: 1088.11 | K35: 0 | L35: 9544.97 | M35: 9235.05 | N35: 43751.21 | O35: 18387.71 | P35: 1775.34 | Q35: 0 | R35: 0
C36: H | D36: Total | E36: 124917.68 | F36: 5425.49 | G36: 3470.55 | H36: 2025.09 | I36: 30214.16 | J36: 1088.11 | K36: 0 | L36: 9544.97 | M36: 9235.05 | N36: 43751.21 | O36: 18387.71 | P36: 1775.34 | Q36: 0 | R36: 0
D37: Subsidio(-)/Contribucion(+) | E37: 166291.05 | F37: 8434.38 | G37: 4699.6 | H37: 2499.5 | I37: 29821.33 | J37: 1737.19 | K37: 0 | L37: 13525.99 | M37: 12946.73 | N37: 66755.66 | O37: 23036.36 | P37: 2834.31 | Q37: 0 | R37: 0
C38: O | D38: Total | E38: 166291.05 | F38: 8434.38 | G38: 4699.6 | H38: 2499.5 | I38: 29821.33 | J38: 1737.19 | K38: 0 | L38: 13525.99 | M38: 12946.73 | N38: 66755.66 | O38: 23036.36 | P38: 2834.31 | Q38: 0 | R38: 0
D39: Subsidio(-)/Contribucion(+) | E39: 843950.15 | F39: 106181.23 | G39: 59113.51 | H39: 30954.51 | I39: 107753.85 | J39: 4247.21 | K39: 0 | L39: 35494.18 | M39: 35638.24 | N39: 167630.68 | O39: 290007.18 | P39: 6929.56 | Q39: 0 | R39: 0
C40: T | D40: Total | E40: 843950.15 | F40: 106181.23 | G40: 59113.51 | H40: 30954.51 | I40: 107753.85 | J40: 4247.21 | K40: 0 | L40: 35494.18 | M40: 35638.24 | N40: 167630.68 | O40: 290007.18 | P40: 6929.56 | Q40: 0 | R40: 0
B41: OCCIDENTE | C41: Total | E41: 1135158.9 | F41: 120041.1 | G41: 67283.66 | H41: 35479.1 | I41: 167789.34 | J41: 7072.51 | K41: 0 | L41: 58565.14 | M41: 57820.02 | N41: 278137.55 | O41: 331431.25 | P41: 11539.21 | Q41: 0 | R41: 0
A42: Subs/Cont | B42: Total | E42: 2274662.1 | F42: 384108.23 | G42: 214322.71 | H42: 108347.7 | I42: 31309.04 | J42: 10968.97 | K42: 0 | L42: -3272.9 | M42: 52124.48 | N42: 386123.04 | O42: 1072921.7 | P42: 17709.11 | Q42: 0 | R42: 0
A43: Total | E43: 34844954 | F43: 2249319.5 | G43: 1219810 | H43: 692159.85 | I43: 5051701.6 | J43: 241344.05 | K43: 0 | L43: 2503907.2 | M43: 2578509.2 | N43: 13337575 | O43: 6582977.7 | P43: 387671.74 | Q43: -21.97 | R43: 0
B57: TOTAL | C57: OPORTUNO | D57: Total | E57: =E25+E42-K25 -> 34844954 | F57: =F25 -> 1865211.3 | G57: =G25 -> 1005487.3 | H57: =H25 -> 583812.15 | I57: =I25 -> 5020392.6 | J57: =J25 -> 230375.08 | K57: =K25 -> 0 | L57: =L25 -> 2507180.1 | M57: =M25 -> 2526384.8 | ... S57: =S25 -> 0
D58: Subsidio(-)/Contribucion(+) | E58: =E42 -> 2274662.1
B60: RECIPROCIDAD | C60: OPORTUNO | D60: Total | E60: 0 | F60: 0 | G60: 0 | H60: 0 | I60: 0 | J60: 0 | K60: 0 | L60: 0 | M60: 0 | N60: 0 | O60: 0 | P60: 0 | Q60: 0 | R60: 0 | S60: 0
D61: Subsidio(-)/Contribucion(+) | E61: 0
B63: ENEL | C63: OPORTUNO | D63: Total | E63: =E31+E28+E10+E6-K6-K10 -> 30254522 | F63: =F10+F6 -> 1628680.7 | G63: =G10+G6 -> 888879.83 | H63: =H10+H6 -> 520121.55 | I63: =I10+I6 -> 4494789.5 | J63: =J10+J6 -> 206682.07 | K63: =K10+K6 -> 0 | L63: =L10+L6 -> 2286008.7 | M63: =M10+M6 -> 2318211.1 | ... S63: =S10+S6 -> 0
D64: Subsidio(-)/Contribucion(+) | E64: =E31+E28 -> 1139503.2
B66: ENERBIT | C66: OPORTUNO | D66: Total | E66: =E34+E14-K14 -> 0 | F66: =F14 -> 0 | G66: 0 | H66: 0 | I66: 0 | J66: 0 | K66: 0 | L66: 0 | M66: 0 | N66: 0 | O66: 0 | P66: 0 | Q66: 0 | R66: 0
D67: Subsidio(-)/Contribucion(+) | E67: =E34 -> 0
B69: OCCIDENTE | C69: OPORTUNO | D69: Total | E69: =E24+E41-K24 -> 4590431.7 | F69: =F24 -> 236530.63 | G69: =G24 -> 116607.49 | H69: =H24 -> 63690.6 | I69: =I24 -> 525603.02 | J69: =J24 -> 23693.01 | K69: =K24 -> 0 | L69: =L24 -> 221171.38 | M69: =M24 -> 208173.61 | ... S69: =S24 -> 0
D70: Subsidio(-)/Contribucion(+) | E70: =E41 -> 1135158.9
B72: CIUDAD LIMPIA-ACUEDUCTO | C72: OPORTUNO | D72: Total | E72: 0 | F72: 0 | G72: 0 | H72: 0 | I72: 0 | J72: 0 | K72: 0 | L72: 0 | M72: 0 | N72: 0 | O72: 0 | P72: 0 | Q72: 0 | R72: 0 | S72: 0
D73: Subsidio(-)/Contribucion(+) | E73: 0
B75: LIME
E76: Total | F76: Componente TDF | G76: Componente TTL | H76: Componente TVIAT | I76: Aprovechamiento | J76: CCSA Prest.Aprov. | K76: Especiales | L76: Componente TCS | M76: Componente TLU | N76: Componente TBL | O76: Componente TRT | P76: CCSA Prest. No Aprov. | Q76: Deb/Cred | R76: Deb/Cred-otros
D77: Vlr Servicio | E77: 0 | F77: 0 | G77: 0 | H77: 0 | I77: 0 | J77: 0 | K77: 0 | L77: 0 | M77: 0 | N77: 0 | O77: 0 | P77: 0 | Q77: 0 | R77: 0
D78: Vlr Intereses | E78: 0 | F78: 0 | G78: 0 | H78: 0 | I78: 0 | J78: 0 | K78: 0 | L78: 0 | M78: 0 | N78: 0 | O78: 0 | P78: 0 | Q78: 0 | R78: 0
C79: A | D79: Total | E79: 0 | F79: 0 | G79: 0 | H79: 0 | I79: 0 | J79: 0 | K79: 0 | L79: 0 | M79: 0 | N79: 0 | O79: 0 | P79: 0 | Q79: 0 | R79: 0
B80: EAB | C80: Total | E80: 0 | F80: 0 | G80: 0 | H80: 0 | I80: 0 | J80: 0 | K80: 0 | L80: 0 | M80: 0 | N80: 0 | O80: 0 | P80: 0 | Q80: 0 | R80: 0
D81: Vlr Servicio | E81: 76172813 | F81: 4284667.4 | G81: 2478920 | H81: 894079.85 | I81: 19165035 | J81: 613033.04 | K81: 51372.12 | L81: 6695698 | M81: 6139885.2 | N81: 26107831 | O81: 8845683.5 | P81: 896338.13 | Q81: 269.69 | R81: 0
D82: Vlr Intereses | E82: 405301.06 | F82: 45882.1 | G82: 21905.35 | H82: 6058.48 | I82: 53792.9 | J82: 1687.15 | K82: 0 | L82: 24878.6 | M82: 29440.99 | N82: 127695.47 | O82: 91205.49 | P82: 2753.1 | Q82: 1.43 | R82: 0
C83: E | D83: Total | E83: 76578114 | F83: 4330549.5 | G83: 2500825.3 | H83: 900138.33 | I83: 19218828 | J83: 614720.19 | K83: 51372.12 | L83: 6720576.6 | M83: 6169326.2 | N83: 26235526 | O83: 8936889 | P83: 899091.23 | Q83: 271.12 | R83: 0
B84: ENEL | C84: Total | E84: 76578114 | F84: 4330549.5 | G84: 2500825.3 | H84: 900138.33 | I84: 19218828 | J84: 614720.19 | K84: 51372.12 | L84: 6720576.6 | M84: 6169326.2 | N84: 26235526 | O84: 8936889 | P84: 899091.23 | Q84: 271.12 | R84: 0
D85: Vlr Servicio | E85: 3697205.2 | F85: 224587.06 | G85: 131985.45 | H85: 46899.61 | I85: 1009958.8 | J85: 32320.93 | K85: 0 | L85: 324307.81 | M85: 265069.78 | N85: 1170089.6 | O85: 450797.77 | P85: 41194.89 | Q85: -6.51 | R85: 0
D86: Vlr Intereses | E86: 438.11 | F86: 43.19 | G86: 22.78 | H86: 12.09 | I86: 96.81 | J86: 2.8 | K86: 0 | L86: 24.54 | M86: 25.59 | N86: 119.35 | O86: 86.42 | P86: 4.57 | Q86: -0.03 | R86: 0
C87: 1 | D87: Total | E87: 3697643.3 | F87: 224630.25 | G87: 132008.23 | H87: 46911.7 | I87: 1010055.6 | J87: 32323.73 | K87: 0 | L87: 324332.35 | M87: 265095.37 | N87: 1170209 | O87: 450884.19 | P87: 41199.46 | Q87: -6.54 | R87: 0
D88: Vlr Servicio | E88: 985683.46 | F88: 69109.02 | G88: 36538.01 | H88: 13453.14 | I88: 287582.83 | J88: 9153.37 | K88: 0 | L88: 82037.98 | M88: 69059.03 | N88: 274803.2 | O88: 134412.31 | P88: 9540.6 | Q88: -6.03 | R88: 0
D89: Vlr Intereses | E89: 0 | F89: 0 | G89: 0 | H89: 0 | I89: 0 | J89: 0 | K89: 0 | L89: 0 | M89: 0 | N89: 0 | O89: 0 | P89: 0 | Q89: 0 | R89: 0
C90: 2 | D90: Total | E90: 985683.46 | F90: 69109.02 | G90: 36538.01 | H90: 13453.14 | I90: 287582.83 | J90: 9153.37 | K90: 0 | L90: 82037.98 | M90: 69059.03 | N90: 274803.2 | O90: 134412.31 | P90: 9540.6 | Q90: -6.03 | R90: 0
D91: Vlr Servicio | E91: 0 | F91: 0 | G91: 0 | H91: 0 | I91: 0 | J91: 0 | K91: 0 | L91: 0 | M91: 0 | N91: 0 | O91: 0 | P91: 0 | Q91: 0 | R91: 0
D92: Vlr Intereses | E92: 0 | F92: 0 | G92: 0 | H92: 0 | I92: 0 | J92: 0 | K92: 0 | L92: 0 | M92: 0 | N92: 0 | O92: 0 | P92: 0 | Q92: 0 | R92: 0
C93: 3 | D93: Total | E93: 0 | F93: 0 | G93: 0 | H93: 0 | I93: 0 | J93: 0 | K93: 0 | L93: 0 | M93: 0 | N93: 0 | O93: 0 | P93: 0 | Q93: 0 | R93: 0
D94: Vlr Servicio | E94: 0 | F94: 0 | G94: 0 | H94: 0 | I94: 0 | J94: 0 | K94: 0 | L94: 0 | M94: 0 | N94: 0 | O94: 0 | P94: 0 | Q94: 0 | R94: 0
D95: Vlr Intereses | E95: 0 | F95: 0 | G95: 0 | H95: 0 | I95: 0 | J95: 0 | K95: 0 | L95: 0 | M95: 0 | N95: 0 | O95: 0 | P95: 0 | Q95: 0 | R95: 0
C96: 4 | D96: Total | E96: 0 | F96: 0 | G96: 0 | H96: 0 | I96: 0 | J96: 0 | K96: 0 | L96: 0 | M96: 0 | N96: 0 | O96: 0 | P96: 0 | Q96: 0 | R96: 0
D97: Vlr Servicio | E97: 18762806 | F97: 1069718.5 | G97: 652346.13 | H97: 178774.19 | I97: 5624013.3 | J97: 166253.39 | K97: 0 | L97: 1667800.4 | M97: 1432331.3 | N97: 5647380.5 | O97: 2150226.7 | P97: 173791.57 | Q97: 169.78 | R97: 0
D98: Vlr Intereses | E98: 1557.48 | F98: 105.97 | G98: 58.29 | H98: 31.24 | I98: 365.86 | J98: 12.42 | K98: 0 | L98: 109 | M98: 112.67 | N98: 531.07 | O98: 210.73 | P98: 20.27 | Q98: -0.04 | R98: 0
C99: 5 | D99: Total | E99: 18764363 | F99: 1069824.4 | G99: 652404.42 | H99: 178805.43 | I99: 5624379.2 | J99: 166265.81 | K99: 0 | L99: 1667909.4 | M99: 1432444 | N99: 5647911.5 | O99: 2150437.5 | P99: 173811.84 | Q99: 169.74 | R99: 0
D100: Vlr Servicio | E100: 0 | F100: 0 | G100: 0 | H100: 0 | I100: 0 | J100: 0 | K100: 0 | L100: 0 | M100: 0 | N100: 0 | O100: 0 | P100: 0 | Q100: 0 | R100: 0
D101: Vlr Intereses | E101: 0 | F101: 0 | G101: 0 | H101: 0 | I101: 0 | J101: 0 | K101: 0 | L101: 0 | M101: 0 | N101: 0 | O101: 0 | P101: 0 | Q101: 0 | R101: 0
C102: 6 | D102: Total | E102: 0 | F102: 0 | G102: 0 | H102: 0 | I102: 0 | J102: 0 | K102: 0 | L102: 0 | M102: 0 | N102: 0 | O102: 0 | P102: 0 | Q102: 0 | R102: 0
D103: Vlr Servicio | E103: 0 | F103: 0 | G103: 0 | H103: 0 | I103: 0 | J103: 0 | K103: 0 | L103: 0 | M103: 0 | N103: 0 | O103: 0 | P103: 0 | Q103: 0 | R103: 0
D104: Vlr Intereses | E104: 0 | F104: 0 | G104: 0 | H104: 0 | I104: 0 | J104: 0 | K104: 0 | L104: 0 | M104: 0 | N104: 0 | O104: 0 | P104: 0 | Q104: 0 | R104: 0
C105: 9 | D105: Total | E105: 0 | F105: 0 | G105: 0 | H105: 0 | I105: 0 | J105: 0 | K105: 0 | L105: 0 | M105: 0 | N105: 0 | O105: 0 | P105: 0 | Q105: 0 | R105: 0
B106: NUEVO ESQUEMA | C106: Total | E106: 23447690 | F106: 1363563.7 | G106: 820950.66 | H106: 239170.27 | I106: 6922017.7 | J106: 207742.91 | K106: 0 | L106: 2074279.7 | M106: 1766598.4 | N106: 7092923.7 | O106: 2735734 | P106: 224551.9 | Q106: 157.17 | R106: 0
D107: Vlr Servicio | E107: 3424363.4 | F107: 193904.51 | G107: 105926.68 | H107: 44650.24 | I107: 871174.9 | J107: 28634.07 | K107: 0 | L107: 280560.08 | M107: 271116.53 | N107: 1194088 | O107: 396460.66 | P107: 37858.56 | Q107: -10.77 | R107: 0
D108: Vlr Intereses | E108: 9177.03 | F108: 847.38 | G108: 479.07 | H108: 253.95 | I108: 1842.43 | J108: 67 | K108: 0 | L108: 587.73 | M108: 577.57 | N108: 2703.44 | O108: 1709.06 | P108: 109.33 | Q108: 0.07 | R108: 0
C109: H | D109: Total | E109: 3433540.5 | F109: 194751.89 | G109: 106405.75 | H109: 44904.19 | I109: 873017.33 | J109: 28701.07 | K109: 0 | L109: 281147.81 | M109: 271694.1 | N109: 1196791.4 | O109: 398169.72 | P109: 37967.89 | Q109: -10.7 | R109: 0
D110: Vlr Servicio | E110: 21026339 | F110: 2447720.8 | G110: 1370734.8 | H110: 666552.07 | I110: 3536069 | J110: 136948.11 | K110: 0 | L110: 1395691.4 | M110: 1241864.2 | N110: 5125598.2 | O110: 4911373.5 | P110: 193726.12 | Q110: 61.33 | R110: 0
D111: Vlr Intereses | E111: 1143672.6 | F111: 164527.55 | G111: 76426.08 | H111: 30595.99 | I111: 168828.35 | J111: 6886.01 | K111: 0 | L111: 60313.09 | M111: 71428.55 | N111: 229600.44 | O111: 323815.18 | P111: 11246.94 | Q111: 4.4 | R111: 0
C112: O | D112: Total | E112: 22170012 | F112: 2612248.3 | G112: 1447160.9 | H112: 697148.06 | I112: 3704897.3 | J112: 143834.12 | K112: 0 | L112: 1456004.5 | M112: 1313292.8 | N112: 5355198.7 | O112: 5235188.7 | P112: 204973.06 | Q112: 65.73 | R112: 0
D113: Vlr Servicio | E113: 1247383.2 | F113: 104470.27 | G113: 61589.36 | H113: 22988.66 | I113: 272684.1 | J113: 8354.34 | K113: 0 | L113: 111652.21 | M113: 93795.87 | N113: 322239.45 | O113: 236861.37 | P113: 12733.53 | Q113: 14.06 | R113: 0
D114: Vlr Intereses | E114: 112.94 | F114: 8.95 | G114: 5.05 | H114: 2.65 | I114: 31.41 | J114: 0.88 | K114: 0 | L114: 7.77 | M114: 8.75 | N114: 26.93 | O114: 17.76 | P114: 2.77 | Q114: 0.02 | R114: 0
C115: T | D115: Total | E115: 1247496.2 | F115: 104479.22 | G115: 61594.41 | H115: 22991.31 | I115: 272715.51 | J115: 8355.22 | K115: 0 | L115: 111659.98 | M115: 93804.62 | N115: 322266.38 | O115: 236879.13 | P115: 12736.3 | Q115: 14.08 | R115: 0
B116: OCCIDENTE | C116: Total | E116: 26851049 | F116: 2911479.5 | G116: 1615161 | H116: 765043.56 | I116: 4850630.2 | J116: 180890.41 | K116: 0 | L116: 1848812.3 | M116: 1678791.5 | N116: 6874256.4 | O116: 5870237.5 | P116: 255677.25 | Q116: 69.11 | R116: 0
A117: Componente | B117: Total | E117: 1.2687685e+08 | F117: 8605592.6 | G117: 4936937 | H117: 1904352.2 | I117: 30991476 | J117: 1003353.5 | K117: 51372.12 | L117: 10643669 | M117: 9614716.1 | N117: 40202706 | O117: 17542860 | P117: 1379320.4 | Q117: 497.4 | R117: 0
D118: Subsidio(-)/Contribucion(+) | E118: 0 | F118: 0 | G118: 0 | H118: 0 | I118: 0 | J118: 0 | K118: 0 | L118: 0 | M118: 0 | N118: 0 | O118: 0 | P118: 0 | Q118: 0 | R118: 0
C119: A | D119: Total | E119: 0 | F119: 0 | G119: 0 | H119: 0 | I119: 0 | J119: 0 | K119: 0 | L119: 0 | M119: 0 | N119: 0 | O119: 0 | P119: 0 | Q119: 0 | R119: 0
...

Sheet Reversion Pagos R4
B1: PROMOAMBIENTAL
D2: Total | E2: Componente TDF | F2: Componente TTL | G2: Componente TVIAT | H2: Aprovechamiento | I2: CCSA Prest.Aprov. | J2: Componente TCS | K2: Componente TLU | L2: Componente TBL | M2: Componente TRT | N2: CCSA Prest. No Aprov. | O2: Ajuste Decena | P2: SERVICIO ESPECIALES | Q2: Ajuste Recargo Aseo | R2: Otros
C3: Vlr Servicio | D3: -4753329.9 | E3: -214159.07 | F3: -114902.14 | G3: -61576.43 | H3: -1165948.6 | I3: -45063.11 | J3: -395289.43 | K3: -369526.83 | L3: -1753828.5 | M3: -560155.38 | N3: -72898.32 | O3: 17.99 | P3: 0 | Q3: 0 | R3: 0
C4: Vlr Intereses | D4: -12501.61 | E4: -542.19 | F4: -246.5 | G4: -140.42 | H4: -2800.13 | I4: -138.59 | J4: -1215.05 | K4: -1024.58 | L4: -4838.23 | M4: -1328.64 | N4: -227.04 | O4: -0.24 | P4: 0 | Q4: 0 | R4: 0
B5: Componente | C5: Total | D5: -4765831.5 | E5: -214701.26 | F5: -115148.64 | G5: -61716.85 | H5: -1168748.8 | I5: -45201.7 | J5: -396504.48 | K5: -370551.41 | L5: -1758666.8 | M5: -561484.02 | N5: -73125.36 | O5: 17.75 | P5: 0 | Q5: 0 | R5: 0
C6: Subsidio(-)/Contribucion(+) | D6: 1304634.2 | E6: 54873.86 | F6: 28576.76 | G6: 15506.07 | H6: 320570.26 | I6: 12973.15 | J6: 113799.96 | K6: 105110.1 | L6: 491550.49 | M6: 140506.71 | N6: 21166.82 | O6: 0 | P6: 0 | Q6: 0 | R6: 0
B7: Subs/Cont | C7: Total | D7: 1304634.2 | E7: 54873.86 | F7: 28576.76 | G7: 15506.07 | H7: 320570.26 | I7: 12973.15 | J7: 113799.96 | K7: 105110.1 | L7: 491550.49 | M7: 140506.71 | N7: 21166.82 | O7: 0 | P7: 0 | Q7: 0 | R7: 0
A8: ENEL | B8: Total | D8: -3461197.3 | E8: -159827.4 | F8: -86571.88 | G8: -46210.78 | H8: -848178.49 | I8: -32228.55 | J8: -282704.52 | K8: -265441.31 | L8: -1267116.3 | M8: -420977.31 | N8: -51958.54 | O8: 17.75 | P8: 0 | Q8: 0 | R8: 0
C9: Vlr Servicio | D9: 0 | E9: 0 | F9: 0 | G9: 0 | H9: 0 | I9: 0 | J9: 0 | K9: 0 | L9: 0 | M9: 0 | N9: 0 | O9: 0 | P9: 0 | Q9: 0 | R9: 0
C10: Vlr Intereses | D10: 0 | E10: 0 | F10: 0 | G10: 0 | H10: 0 | I10: 0 | J10: 0 | K10: 0 | L10: 0 | M10: 0 | N10: 0 | O10: 0 | P10: 0 | Q10: 0 | R10: 0
B11: Componente | C11: Total | D11: 0 | E11: 0 | F11: 0 | G11: 0 | H11: 0 | I11: 0 | J11: 0 | K11: 0 | L11: 0 | M11: 0 | N11: 0 | O11: 0 | P11: 0 | Q11: 0 | R11: 0
C12: Subsidio(-)/Contribucion(+) | D12: 0 | E12: 0 | F12: 0 | G12: 0 | H12: 0 | I12: 0 | J12: 0 | K12: 0 | L12: 0 | M12: 0 | N12: 0 | O12: 0 | P12: 0 | Q12: 0 | R12: 0
B13: Subs/Cont | C13: Total | D13: 0 | E13: 0 | F13: 0 | G13: 0 | H13: 0 | I13: 0 | J13: 0 | K13: 0 | L13: 0 | M13: 0 | N13: 0 | O13: 0 | P13: 0 | Q13: 0 | R13: 0
A14: ENERBIT | B14: Total | D14: 0 | E14: 0 | F14: 0 | G14: 0 | H14: 0 | I14: 0 | J14: 0 | K14: 0 | L14: 0 | M14: 0 | N14: 0 | O14: 0 | P14: 0 | Q14: 0 | R14: 0
C15: Vlr Servicio | D15: -83090.08 | E15: -4319.28 | F15: -2439.7 | G15: -1284.52 | H15: -21380.91 | I15: -495.68 | J15: -4348.01 | K15: -6438.31 | L15: -29729.3 | M15: -11838.57 | N15: -808.72 | O15: -7.08 | P15: 0 | Q15: 0 | R15: 0
C16: Vlr Intereses | D16: -219.92 | E16: -11.38 | F16: -6.42 | G16: -3.38 | H16: -57.73 | I16: -1.29 | J16: -11.47 | K16: -16.98 | L16: -77.95 | M16: -31.19 | N16: -2.12 | O16: -0.01 | P16: 0 | Q16: 0 | R16: 0
B17: Componente | C17: Total | D17: -83310 | E17: -4330.66 | F17: -2446.12 | G17: -1287.9 | H17: -21438.64 | I17: -496.97 | J17: -4359.48 | K17: -6455.29 | L17: -29807.25 | M17: -11869.76 | N17: -810.84 | O17: -7.09 | P17: 0 | Q17: 0 | R17: 0
C18: Subsidio(-)/Contribucion(+) | D18: 0 | E18: 0 | F18: 0 | G18: 0 | H18: 0 | I18: 0 | J18: 0 | K18: 0 | L18: 0 | M18: 0 | N18: 0 | O18: 0 | P18: 0 | Q18: 0 | R18: 0
B19: Subs/Cont | C19: Total | D19: 0 | E19: 0 | F19: 0 | G19: 0 | H19: 0 | I19: 0 | J19: 0 | K19: 0 | L19: 0 | M19: 0 | N19: 0 | O19: 0 | P19: 0 | Q19: 0 | R19: 0
A20: OCCIDENTE | B20: Total | D20: -83310 | E20: -4330.66 | F20: -2446.12 | G20: -1287.9 | H20: -21438.64 | I20: -496.97 | J20: -4359.48 | K20: -6455.29 | L20: -29807.25 | M20: -11869.76 | N20: -810.84 | O20: -7.09 | P20: 0 | Q20: 0 | R20: 0
A21: Total | D21: -3544507.3 | E21: -164158.06 | F21: -89018 | G21: -47498.68 | H21: -869617.13 | I21: -32725.52 | J21: -287064 | K21: -271896.6 | L21: -1296923.5 | M21: -432847.07 | N21: -52769.38 | O21: 10.66 | P21: 0 | Q21: 0 | R21: 0
A79: TOTAL | B79: OPORTUNO | C79: Total | D79: =D21-P21 -> -3544507.3 | E79: =E5+E17 -> -219031.92 | F79: =F5+F17 -> -117594.76 | G79: =G5+G17 -> -63004.75 | H79: =H5+H17 -> -1190187.4 | I79: =I5+I17 -> -45698.67 | J79: =J5+J17 -> -400863.96 | K79: =K5+K17 -> -377006.7 | L79: =L5+L17 -> -1788474 | ... R79: =R5+R17 -> 0
C80: Subsidio(-)/Contribucion(+) | D80: =D7+D19 -> 1304634.2
A82: RECIPROCIDAD | B82: OPORTUNO | C82: Total | D82: 0 | E82: 0 | F82: 0 | G82: 0 | H82: 0 | I82: 0 | J82: 0 | K82: 0 | L82: 0 | M82: 0 | N82: 0 | O82: 0 | P82: 0 | Q82: 0 | R82: 0
C83: Subsidio(-)/Contribucion(+) | D83: 0
A85: ENEL | B85: OPORTUNO | C85: Total | D85: =D8-P8 -> -3461197.3 | E85: =E5 -> -214701.26 | F85: =F5 -> -115148.64 | G85: =G5 -> -61716.85 | H85: =H5 -> -1168748.8 | I85: =I5 -> -45201.7 | J85: =J5 -> -396504.48 | K85: =K5 -> -370551.41 | L85: =L5 -> -1758666.8 | ... R85: =R5 -> 0
C86: Subsidio(-)/Contribucion(+) | D86: =D7 -> 1304634.2
A88: ENERBIT | B88: OPORTUNO | C88: Total | D88: =D14-P14 -> 0 | E88: =E11 -> 0 | F88: =F11 -> 0 | G88: =G11 -> 0 | H88: =H11 -> 0 | I88: =I11 -> 0 | J88: =J11 -> 0 | K88: =K11 -> 0 | L88: =L11 -> 0 | ... R88: =R11 -> 0
C89: Subsidio(-)/Contribucion(+) | D89: =D13 -> 0
A91: OCCIDENTE | B91: OPORTUNO | C91: Total | D91: =D20-P20 -> -83310 | E91: =E17 -> -4330.66 | F91: =F17 -> -2446.12 | G91: =G17 -> -1287.9 | H91: =H17 -> -21438.64 | I91: =I17 -> -496.97 | J91: =J17 -> -4359.48 | K91: =K17 -> -6455.29 | L91: =L17 -> -29807.25 | ... R91: =R17 -> 0
C92: Subsidio(-)/Contribucion(+) | D92: =D19 -> 0
A94: CIUDAD LIMPIA-ACUEDUCTO | B94: OPORTUNO | C94: Total | D94: 0 | E94: 0 | F94: 0 | G94: 0 | H94: 0 | I94: 0 | J94: 0 | K94: 0 | L94: 0 | M94: 0 | N94: 0 | O94: 0 | P94: 0 | Q94: 0 | R94: 0
C95: Subsidio(-)/Contribucion(+) | D95: 0
B97: LIME
D98: Total | E98: Componente TDF | F98: Componente TTL | G98: Componente TVIAT | H98: Aprovechamiento | I98: CCSA Prest.Aprov. | J98: Componente TCS | K98: Componente TLU | L98: Componente TBL | M98: Componente TRT | N98: CCSA Prest. No Aprov. | O98: Ajuste Decena | P98: SERVICIO ESPECIALES | Q98: Ajuste Recargo Aseo | R98: Otros
C99: Vlr Servicio | D99: -10237443 | E99: -563399.38 | F99: -316917.62 | G99: -166722.74 | H99: -2628414.2 | I99: -89684.05 | J99: -786699.09 | K99: -766969.55 | L99: -3636763.4 | M99: -1109050.8 | N99: -146326.35 | O99: 4.57 | P99: -26500 | Q99: 0 | R99: 0
C100: Vlr Intereses | D100: -49535.64 | E100: -2812.32 | F100: -1322.36 | G100: -716.51 | H100: -13748.88 | I100: -368.55 | J100: -3233.3 | K100: -3852.97 | L100: -17279.39 | M100: -5599.52 | N100: -601.36 | O100: -0.48 | P100: 0 | Q100: 0 | R100: 0
B101: Componente | C101: Total | D101: -10286978 | E101: -566211.7 | F101: -318239.98 | G101: -167439.25 | H101: -2642163 | I101: -90052.6 | J101: -789932.39 | K101: -770822.52 | L101: -3654042.8 | M101: -1114650.3 | N101: -146927.71 | O101: 4.09 | P101: -26500 | Q101: 0 | R101: 0
C102: Subsidio(-)/Contribucion(+) | D102: 1547375.8 | E102: 29312.92 | F102: 16341.6 | G102: 8648.05 | H102: 470464.34 | I102: 15992.12 | J102: 140279.81 | K102: 136965.6 | L102: 646070.43 | M102: 57208.93 | N102: 26092.04 | O102: 0 | P102: 0 | Q102: 0 | R102: 0
B103: Subs/Cont | C103: Total | D103: 1547375.8 | E103: 29312.92 | F103: 16341.6 | G103: 8648.05 | H103: 470464.34 | I103: 15992.12 | J103: 140279.81 | K103: 136965.6 | L103: 646070.43 | M103: 57208.93 | N103: 26092.04 | O103: 0 | P103: 0 | Q103: 0 | R103: 0
A104: ENEL | B104: Total | D104: -8739602.4 | E104: -536898.78 | F104: -301898.38 | G104: -158791.2 | H104: -2171698.7 | I104: -74060.48 | J104: -649652.58 | K104: -633856.92 | L104: -3007972.4 | M104: -1057441.4 | N104: -120835.67 | O104: 4.09 | P104: -26500 | Q104: 0 | R104: 0
C105: Vlr Servicio | D105: 0 | E105: 0 | F105: 0 | G105: 0 | H105: 0 | I105: 0 | J105: 0 | K105: 0 | L105: 0 | M105: 0 | N105: 0 | O105: 0 | P105: 0 | Q105: 0 | R105: 0
C106: Vlr Intereses | D106: 0 | E106: 0 | F106: 0 | G106: 0 | H106: 0 | I106: 0 | J106: 0 | K106: 0 | L106: 0 | M106: 0 | N106: 0 | O106: 0 | P106: 0 | Q106: 0 | R106: 0
B107: Componente | C107: Total | D107: 0 | E107: 0 | F107: 0 | G107: 0 | H107: 0 | I107: 0 | J107: 0 | K107: 0 | L107: 0 | M107: 0 | N107: 0 | O107: 0 | P107: 0 | Q107: 0 | R107: 0
C108: Subsidio(-)/Contribucion(+) | D108: 0 | E108: 0 | F108: 0 | G108: 0 | H108: 0 | I108: 0 | J108: 0 | K108: 0 | L108: 0 | M108: 0 | N108: 0 | O108: 0 | P108: 0 | Q108: 0 | R108: 0
B109: Subs/Cont | C109: Total | D109: 0 | E109: 0 | F109: 0 | G109: 0 | H109: 0 | I109: 0 | J109: 0 | K109: 0 | L109: 0 | M109: 0 | N109: 0 | O109: 0 | P109: 0 | Q109: 0 | R109: 0
A110: NUEVO ESQUEMA | B110: Total | D110: 0 | E110: 0 | F110: 0 | G110: 0 | H110: 0 | I110: 0 | J110: 0 | K110: 0 | L110: 0 | M110: 0 | N110: 0 | O110: 0 | P110: 0 | Q110: 0 | R110: 0
C111: Vlr Servicio | D111: 0 | E111: 0 | F111: 0 | G111: 0 | H111: 0 | I111: 0 | J111: 0 | K111: 0 | L111: 0 | M111: 0 | N111: 0 | O111: 0 | P111: 0 | Q111: 0 | R111: 0
C112: Vlr Intereses | D112: 0 | E112: 0 | F112: 0 | G112: 0 | H112: 0 | I112: 0 | J112: 0 | K112: 0 | L112: 0 | M112: 0 | N112: 0 | O112: 0 | P112: 0 | Q112: 0 | R112: 0
B113: Componente | C113: Total | D113: 0 | E113: 0 | F113: 0 | G113: 0 | H113: 0 | I113: 0 | J113: 0 | K113: 0 | L113: 0 | M113: 0 | N113: 0 | O113: 0 | P113: 0 | Q113: 0 | R113: 0
C114: Subsidio(-)/Contribucion(+) | D114: 0 | E114: 0 | F114: 0 | G114: 0 | H114: 0 | I114: 0 | J114: 0 | K114: 0 | L114: 0 | M114: 0 | N114: 0 | O114: 0 | P114: 0 | Q114: 0 | R114: 0
B115: Subs/Cont | C115: Total | D115: 0 | E115: 0 | F115: 0 | G115: 0 | H115: 0 | I115: 0 | J115: 0 | K115: 0 | L115: 0 | M115: 0 | N115: 0 | O115: 0 | P115: 0 | Q115: 0 | R115: 0
A116: OCCIDENTE | B116: Total | D116: 0 | E116: 0 | F116: 0 | G116: 0 | H116: 0 | I116: 0 | J116: 0 | K116: 0 | L116: 0 | M116: 0 | N116: 0 | O116: 0 | P116: 0 | Q116: 0 | R116: 0
A117: Total | D117: -8739602.4 | E117: -536898.78 | F117: -301898.38 | G117: -158791.2 | H117: -2171698.7 | I117: -74060.48 | J117: -649652.58 | K117: -633856.92 | L117: -3007972.4 | M117: -1057441.4 | N117: -120835.67 | O117: 4.09 | P117: -26500 | Q117: 0 | R117: 0
A180: TOTAL | B180: OPORTUNO | C180: Total | D180: =D117-P117 -> -8713102.4 | E180: =E101+E107+E113 -> -566211.7 | F180: =F101+F107+F113 -> -318239.98 | G180: =G101+G107+G113 -> -167439.25 | H180: =H101+H107+H113 -> -2642163 | I180: =I101+I107+I113 -> -90052.6 | J180: =J101+J107+J113 -> -789932.39 | K180: =K101+K107+K113 -> -770822.52 | L180: =L101+L107+L113 -> -3654042.8 | ... R180: =R101+R107+R113 -> 0
C181: Subsidio(-)/Contribucion(+) | D181: =D103+D109+D115 -> 1547375.8
A183: RECIPROCIDAD | B183: OPORTUNO | C183: Total | D183: =D110-P110 -> 0 | E183: =E107 -> 0 | F183: =F107 -> 0 | G183: =G107 -> 0 | H183: =H107 -> 0 | I183: =I107 -> 0 | J183: =J107 -> 0 | K183: =K107 -> 0 | L183: =L107 -> 0 | ... R183: =R107 -> 0
C184: Subsidio(-)/Contribucion(+) | D184: =D109 -> 0
A186: ENEL | B186: OPORTUNO | C186: Total | D186: =D104-P104 -> -8713102.4 | E186: =E101 -> -566211.7 | F186: =F101 -> -318239.98 | G186: =G101 -> -167439.25 | H186: =H101 -> -2642163 | I186: =I101 -> -90052.6 | J186: =J101 -> -789932.39 | K186: =K101 -> -770822.52 | L186: =L101 -> -3654042.8 | ... R186: =R101 -> 0
C187: Subsidio(-)/Contribucion(+) | D187: =D103 -> 1547375.8
A189: ENERBIT | B189: OPORTUNO | C189: Total | D189: 0 | E189: 0 | F189: 0 | G189: 0 | H189: 0 | I189: 0 | J189: 0 | K189: 0 | L189: 0 | M189: 0 | N189: 0 | O189: 0 | P189: 0 | Q189: 0 | R189: 0
C190: Subsidio(-)/Contribucion(+) | D190: 0
A192: OCCIDENTE | B192: OPORTUNO | C192: Total | D192: =D116-P116 -> 0 | E192: =E113 -> 0 | F192: =F113 -> 0 | G192: =G113 -> 0 | H192: =H113 -> 0 | I192: =I113 -> 0 | J192: =J113 -> 0 | K192: =K113 -> 0 | L192: =L113 -> 0 | ... R192: =R113 -> 0
C193: Subsidio(-)/Contribucion(+) | D193: =D115 -> 0
A195: CIUDAD LIMPIA-ACUEDUCTO | B195: OPORTUNO | C195: Total | D195: 0 | E195: 0 | F195: 0 | G195: 0 | H195: 0 | I195: 0 | J195: 0 | K195: 0 | L195: 0 | M195: 0 | N195: 0 | O195: 0 | P195: 0 | Q195: 0 | R195: 0
C196: Subsidio(-)/Contribucion(+) | D196: 0
B198: CIUDAD LIMPIA
D199: Total | E199: Componente TDF | F199: Componente TTL | G199: Componente TVIAT | H199: Aprovechamiento | I199: CCSA Prest.Aprov. | J199: Componente TCS | K199: Componente TLU | L199: Componente TBL | M199: Componente TRT | N199: CCSA Prest. No Aprov. | O199: Ajuste Decena | P199: SERVICIO ESPECIALES | Q199: Ajuste Recargo Aseo | R199: Otros
C200: Vlr Servicio | D200: -6968154.2 | E200: -329081.64 | F200: -185597.2 | G200: -97672.38 | H200: -2008331.1 | I200: -59494.92 | J200: -518628.97 | K200: -504844.61 | L200: -2391600.7 | M200: -775803.2 | N200: -97071.22 | O200: -28.2 | P200: 0 | Q200: 0 | R200: 0
C201: Vlr Intereses | D201: -1954.21 | E201: -129.5 | F201: -73.1 | G201: -38.35 | H201: -455.19 | I201: -15.73 | J201: -138.23 | K201: -135.61 | L201: -641.52 | M201: -301.27 | N201: -25.73 | O201: 0.02 | P201: 0 | Q201: 0 | R201: 0
B202: Componente | C202: Total | D202: -6970108.4 | E202: -329211.14 | F202: -185670.3 | G202: -97710.73 | H202: -2008786.3 | I202: -59510.65 | J202: -518767.2 | K202: -504980.22 | L202: -2392242.2 | M202: -776104.47 | N202: -97096.95 | O202: -28.18 | P202: 0 | Q202: 0 | R202: 0
C203: Subsidio(-)/Contribucion(+) | D203: 878534.48 | E203: 23290.01 | F203: 13131.96 | G203: 6902.39 | H203: 294747.35 | I203: 8059.48 | J203: 70696.62 | K203: 68683.76 | L203: 324708.43 | M203: 55164.96 | N203: 13149.52 | O203: 0 | P203: 0 | Q203: 0 | R203: 0
B204: Subs/Cont | C204: Total | D204: 878534.48 | E204: 23290.01 | F204: 13131.96 | G204: 6902.39 | H204: 294747.35 | I204: 8059.48 | J204: 70696.62 | K204: 68683.76 | L204: 324708.43 | M204: 55164.96 | N204: 13149.52 | O204: 0 | P204: 0 | Q204: 0 | R204: 0
A205: ENEL | B205: Total | D205: -6091573.9 | E205: -305921.13 | F205: -172538.34 | G205: -90808.34 | H205: -1714039 | I205: -51451.17 | J205: -448070.58 | K205: -436296.46 | L205: -2067533.8 | M205: -720939.51 | N205: -83947.43 | O205: -28.18 | P205: 0 | Q205: 0 | R205: 0
C206: Vlr Servicio | D206: -40482.2 | E206: -1930.6 | F206: -1090.02 | G206: -572.11 | H206: -10651 | I206: -255.08 | J206: -2237.53 | K206: -3286.56 | L206: -15556.53 | M206: -4485.76 | N206: -416.18 | O206: -0.83 | P206: 0 | Q206: 0 | R206: 0
C207: Vlr Intereses | D207: 0 | E207: 0 | F207: 0 | G207: 0 | H207: 0 | I207: 0 | J207: 0 | K207: 0 | L207: 0 | M207: 0 | N207: 0 | O207: 0 | P207: 0 | Q207: 0 | R207: 0
B208: Componente | C208: Total | D208: -40482.2 | E208: -1930.6 | F208: -1090.02 | G208: -572.11 | H208: -10651 | I208: -255.08 | J208: -2237.53 | K208: -3286.56 | L208: -15556.53 | M208: -4485.76 | N208: -416.18 | O208: -0.83 | P208: 0 | Q208: 0 | R208: 0
C209: Subsidio(-)/Contribucion(+) | D209: 6072.2 | E209: 289.59 | F209: 163.5 | G209: 85.81 | H209: 1597.65 | I209: 38.26 | J209: 335.63 | K209: 492.99 | L209: 2333.48 | M209: 672.86 | N209: 62.43 | O209: 0 | P209: 0 | Q209: 0 | R209: 0
B210: Subs/Cont | C210: Total | D210: 6072.2 | E210: 289.59 | F210: 163.5 | G210: 85.81 | H210: 1597.65 | I210: 38.26 | J210: 335.63 | K210: 492.99 | L210: 2333.48 | M210: 672.86 | N210: 62.43 | O210: 0 | P210: 0 | Q210: 0 | R210: 0
A211: OCCIDENTE | B211: Total | D211: -34410 | E211: -1641.01 | F211: -926.52 | G211: -486.3 | H211: -9053.35 | I211: -216.82 | J211: -1901.9 | K211: -2793.57 | L211: -13223.05 | M211: -3812.9 | N211: -353.75 | O211: -0.83 | P211: 0 | Q211: 0 | R211: 0
A212: Total | D212: -6125983.9 | E212: -307562.14 | F212: -173464.86 | G212: -91294.64 | H212: -1723092.3 | I212: -51667.99 | J212: -449972.48 | K212: -439090.03 | L212: -2080756.8 | M212: -724752.41 | N212: -84301.18 | O212: -29.01 | P212: 0 | Q212: 0 | R212: 0
A217: TOTAL | B217: OPORTUNO | C217: Total | D217: =D212-P212 -> -6125983.9 | E217: =E202+E208 -> -331141.74 | F217: =F202+F208 -> -186760.32 | G217: =G202+G208 -> -98282.84 | H217: =H202+H208 -> -2019437.3 | I217: =I202+I208 -> -59765.73 | J217: =J202+J208 -> -521004.73 | K217: =K202+K208 -> -508266.78 | L217: =L202+L208 -> -2407798.7 | ... R217: =R202+R208 -> 0
C218: Subsidio(-)/Contribucion(+) | D218: =D204+D210 -> 884606.68
A220: RECIPROCIDAD | B220: OPORTUNO | C220: Total | D220: 0 | E220: 0 | F220: 0 | G220: 0 | H220: 0 | I220: 0 | J220: 0 | K220: 0 | L220: 0 | M220: 0 | N220: 0 | O220: 0 | P220: 0 | Q220: 0 | R220: 0
C221: Subsidio(-)/Contribucion(+) | D221: 0
A223: ENEL | B223: OPORTUNO | C223: Total | D223: =D205-P205 -> -6091573.9 | E223: =E202 -> -329211.14 | F223: =F202 -> -185670.3 | G223: =G202 -> -97710.73 | H223: =H202 -> -2008786.3 | I223: =I202 -> -59510.65 | J223: =J202 -> -518767.2 | K223: =K202 -> -504980.22 | L223: =L202 -> -2392242.2 | ... R223: =R202 -> 0
C224: Subsidio(-)/Contribucion(+) | D224: =D204 -> 878534.48
A226: ENERBIT | B226: OPORTUNO | C226: Total | D226: 0 | E226: 0 | F226: 0 | G226: 0 | H226: 0 | I226: 0 | J226: 0 | K226: 0 | L226: 0 | M226: 0 | N226: 0 | O226: 0 | P226: 0 | Q226: 0 | R226: 0
C227: Subsidio(-)/Contribucion(+) | D227: 0
A229: OCCIDENTE | B229: OPORTUNO | C229: Total | D229: =D211-P211 -> -34410 | E229: =E208 -> -1930.6 | F229: =F208 -> -1090.02 | G229: =G208 -> -572.11 | H229: =H208 -> -10651 | I229: =I208 -> -255.08 | J229: =J208 -> -2237.53 | K229: =K208 -> -3286.56 | L229: =L208 -> -15556.53 | ... R229: =R208 -> 0
C230: Subsidio(-)/Contribucion(+) | D230: =D210 -> 6072.2
A232: CIUDAD LIMPIA-ACUEDUCTO | B232: OPORTUNO | C232: Total | D232: 0 | E232: 0 | F232: 0 | G232: 0 | H232: 0 | I232: 0 | J232: 0 | K232: 0 | L232: 0 | M232: 0 | N232: 0 | O232: 0 | P232: 0 | Q232: 0 | R232: 0
C233: Subsidio(-)/Contribucion(+) | D233: 0
B235: BOGOTA LIMPIA
D236: Total | E236: Componente TDF | F236: Componente TTL | G236: Componente TVIAT | H236: Aprovechamiento | I236: CCSA Prest.Aprov. | J236: Componente TCS | K236: Componente TLU | L236: Componente TBL | M236: Componente TRT | N236: CCSA Prest. No Aprov. | O236: Ajuste Decena | P236: SERVICIO ESPECIALES | Q236: Ajuste Recargo Aseo | R236: Otros
C237: Vlr Servicio | D237: -20867961 | E237: -1183575.9 | F237: -660785.56 | G237: -360417.26 | H237: -4675852.3 | I237: -165970.21 | J237: -1465578.8 | K237: -1450674.8 | L237: -7405960.4 | M237: -3230098.4 | N237: -269110.48 | O237: 62.73 | P237: 0 | Q237: 0 | R237: 0
C238: Vlr Intereses | D238: -70844.04 | E238: -12872.38 | F238: -3618.8 | G238: -466.49 | H238: -10077.28 | I238: -549.6 | J238: -4821.86 | K238: -4702.86 | L238: 6554.19 | M238: -39396.22 | N238: -896.75 | O238: 4.01 | P238: 0 | Q238: 0 | R238: 0
B239: Componente | C239: Total | D239: -20938805 | E239: -1196448.3 | F239: -664404.36 | G239: -360883.75 | H239: -4685929.5 | I239: -166519.81 | J239: -1470400.6 | K239: -1455377.7 | L239: -7399406.2 | M239: -3269494.6 | N239: -270007.23 | O239: 66.74 | P239: 0 | Q239: 0 | R239: 0
C240: Subsidio(-)/Contribucion(+) | D240: 693280.58 | E240: -60645.51 | F240: -33250.49 | G240: -18054.75 | H240: 283080.41 | I240: 10777.75 | J240: 94543.45 | K240: 92360.66 | L240: 468946.29 | M240: -162062.32 | N240: 17585.09 | O240: 0 | P240: 0 | Q240: 0 | R240: 0
B241: Subs/Cont | C241: Total | D241: 693280.58 | E241: -60645.51 | F241: -33250.49 | G241: -18054.75 | H241: 283080.41 | I241: 10777.75 | J241: 94543.45 | K241: 92360.66 | L241: 468946.29 | M241: -162062.32 | N241: 17585.09 | O241: 0 | P241: 0 | Q241: 0 | R241: 0
...

Sheet SALDOS POR NOTA
B1: PROMOAMBIENTAL
C2: Total | D2: Componente TDF | E2: Componente TTL | F2: Componente TVIAT | G2: Aprovechamiento | H2: CCSA Prest.Aprov. | I2: Especiales | J2: Componente TCS | K2: Componente TLU | L2: Componente TBL | M2: Componente TRT | N2: CCSA Prest. No Aprov. | O2: Deb/Cred
B3: Vlr Servicio | C3: 0 | D3: 0 | E3: 0 | F3: 0 | G3: 0 | H3: 0 | I3: 0 | J3: 0 | K3: 0 | L3: 0 | M3: 0 | N3: 0 | O3: 0
B4: Vlr Intereses | C4: 0 | D4: 0 | E4: 0 | F4: 0 | G4: 0 | H4: 0 | I4: 0 | J4: 0 | K4: 0 | L4: 0 | M4: 0 | N4: 0 | O4: 0
A5: Componente | B5: Total | C5: 0 | D5: 0 | E5: 0 | F5: 0 | G5: 0 | H5: 0 | I5: 0 | J5: 0 | K5: 0 | L5: 0 | M5: 0 | N5: 0 | O5: 0
B6: Subsidio(-)/Contribucion(+) | C6: 0 | D6: 0 | E6: 0 | F6: 0 | G6: 0 | H6: 0 | I6: 0 | J6: 0 | K6: 0 | L6: 0 | M6: 0 | N6: 0 | O6: 0
A7: Subs/Cont | B7: Total | C7: 0 | D7: 0 | E7: 0 | F7: 0 | G7: 0 | H7: 0 | I7: 0 | J7: 0 | K7: 0 | L7: 0 | M7: 0 | N7: 0 | O7: 0
A8: Total | C8: 0 | D8: 0 | E8: 0 | F8: 0 | G8: 0 | H8: 0 | I8: 0 | J8: 0 | K8: 0 | L8: 0 | M8: 0 | N8: 0 | O8: 0
B10: Total | C10: =C8-I8 -> 0 | D10: =D5 -> 0 | E10: =E5 -> 0 | F10: =F5 -> 0 | G10: =G5 -> 0 | H10: =H5 -> 0 | I10: =I5 -> 0 | J10: =J5 -> 0 | K10: =K5 -> 0 | ... P10: =P5 -> 0
B11: Subsidio(-)/Contribucion(+) | C11: =C7 -> 0
B14: LIME
C15: Total | D15: Componente TDF | E15: Componente TTL | F15: Componente TVIAT | G15: Aprovechamiento | H15: CCSA Prest.Aprov. | I15: Especiales | J15: Componente TCS | K15: Componente TLU | L15: Componente TBL | M15: Componente TRT | N15: CCSA Prest. No Aprov. | O15: Deb/Cred
B16: Vlr Servicio | C16: 0 | D16: 0 | E16: 0 | F16: 0 | G16: 0 | H16: 0 | I16: 0 | J16: 0 | K16: 0 | L16: 0 | M16: 0 | N16: 0 | O16: 0
B17: Vlr Intereses | C17: 0 | D17: 0 | E17: 0 | F17: 0 | G17: 0 | H17: 0 | I17: 0 | J17: 0 | K17: 0 | L17: 0 | M17: 0 | N17: 0 | O17: 0
A18: Componente | B18: Total | C18: 0 | D18: 0 | E18: 0 | F18: 0 | G18: 0 | H18: 0 | I18: 0 | J18: 0 | K18: 0 | L18: 0 | M18: 0 | N18: 0 | O18: 0
B19: Subsidio(-)/Contribucion(+) | C19: 0 | D19: 0 | E19: 0 | F19: 0 | G19: 0 | H19: 0 | I19: 0 | J19: 0 | K19: 0 | L19: 0 | M19: 0 | N19: 0 | O19: 0
A20: Subs/Cont | B20: Total | C20: 0 | D20: 0 | E20: 0 | F20: 0 | G20: 0 | H20: 0 | I20: 0 | J20: 0 | K20: 0 | L20: 0 | M20: 0 | N20: 0 | O20: 0
A21: Total | C21: 0 | D21: 0 | E21: 0 | F21: 0 | G21: 0 | H21: 0 | I21: 0 | J21: 0 | K21: 0 | L21: 0 | M21: 0 | N21: 0 | O21: 0
B23: Total | C23: =C21-I21 -> 0 | D23: =D18 -> 0 | E23: =E18 -> 0 | F23: =F18 -> 0 | G23: =G18 -> 0 | H23: =H18 -> 0 | I23: =I18 -> 0 | J23: =J18 -> 0 | K23: =K18 -> 0 | ... P23: =P18 -> 0
B24: Subsidio(-)/Contribucion(+) | C24: =C20 -> 0
B27: CIUDAD LIMPIA
C28: Total | D28: Componente TDF | E28: Componente TTL | F28: Componente TVIAT | G28: Aprovechamiento | H28: CCSA Prest.Aprov. | I28: Especiales | J28: Componente TCS | K28: Componente TLU | L28: Componente TBL | M28: Componente TRT | N28: CCSA Prest. No Aprov. | O28: Deb/Cred
B29: Vlr Servicio | C29: 0 | D29: 0 | E29: 0 | F29: 0 | G29: 0 | H29: 0 | I29: 0 | J29: 0 | K29: 0 | L29: 0 | M29: 0 | N29: 0 | O29: 0
B30: Vlr Intereses | C30: 0 | D30: 0 | E30: 0 | F30: 0 | G30: 0 | H30: 0 | I30: 0 | J30: 0 | K30: 0 | L30: 0 | M30: 0 | N30: 0 | O30: 0
A31: Componente | B31: Total | C31: 0 | D31: 0 | E31: 0 | F31: 0 | G31: 0 | H31: 0 | I31: 0 | J31: 0 | K31: 0 | L31: 0 | M31: 0 | N31: 0 | O31: 0
B32: Subsidio(-)/Contribucion(+) | C32: 0 | D32: 0 | E32: 0 | F32: 0 | G32: 0 | H32: 0 | I32: 0 | J32: 0 | K32: 0 | L32: 0 | M32: 0 | N32: 0 | O32: 0
A33: Subs/Cont | B33: Total | C33: 0 | D33: 0 | E33: 0 | F33: 0 | G33: 0 | H33: 0 | I33: 0 | J33: 0 | K33: 0 | L33: 0 | M33: 0 | N33: 0 | O33: 0
A34: Total | C34: 0 | D34: 0 | E34: 0 | F34: 0 | G34: 0 | H34: 0 | I34: 0 | J34: 0 | K34: 0 | L34: 0 | M34: 0 | N34: 0 | O34: 0
B36: Total | C36: =C34-I34 -> 0 | D36: =D31 -> 0 | E36: =E31 -> 0 | F36: =F31 -> 0 | G36: =G31 -> 0 | H36: =H31 -> 0 | I36: =I31 -> 0 | J36: =J31 -> 0 | K36: =K31 -> 0 | ... P36: =P31 -> 0
B37: Subsidio(-)/Contribucion(+) | C37: =C33 -> 0
B40: BOGOTA LIMPIA
C41: Total | D41: Componente TDF | E41: Componente TTL | F41: Componente TVIAT | G41: Aprovechamiento | H41: CCSA Prest.Aprov. | I41: Especiales | J41: Componente TCS | K41: Componente TLU | L41: Componente TBL | M41: Componente TRT | N41: CCSA Prest. No Aprov. | O41: Deb/Cred
B42: Vlr Servicio | C42: 0 | D42: 0 | E42: 0 | F42: 0 | G42: 0 | H42: 0 | I42: 0 | J42: 0 | K42: 0 | L42: 0 | M42: 0 | N42: 0 | O42: 0
B43: Vlr Intereses | C43: 0 | D43: 0 | E43: 0 | F43: 0 | G43: 0 | H43: 0 | I43: 0 | J43: 0 | K43: 0 | L43: 0 | M43: 0 | N43: 0 | O43: 0
A44: Componente | B44: Total | C44: 0 | D44: 0 | E44: 0 | F44: 0 | G44: 0 | H44: 0 | I44: 0 | J44: 0 | K44: 0 | L44: 0 | M44: 0 | N44: 0 | O44: 0
B45: Subsidio(-)/Contribucion(+) | C45: 0 | D45: 0 | E45: 0 | F45: 0 | G45: 0 | H45: 0 | I45: 0 | J45: 0 | K45: 0 | L45: 0 | M45: 0 | N45: 0 | O45: 0
A46: Subs/Cont | B46: Total | C46: 0 | D46: 0 | E46: 0 | F46: 0 | G46: 0 | H46: 0 | I46: 0 | J46: 0 | K46: 0 | L46: 0 | M46: 0 | N46: 0 | O46: 0
A47: Total | C47: 0 | D47: 0 | E47: 0 | F47: 0 | G47: 0 | H47: 0 | I47: 0 | J47: 0 | K47: 0 | L47: 0 | M47: 0 | N47: 0 | O47: 0
B49: Total | C49: =C47-I47 -> 0 | D49: =D44 -> 0 | E49: =E44 -> 0 | F49: =F44 -> 0 | G49: =G44 -> 0 | H49: =H44 -> 0 | I49: =I44 -> 0 | J49: =J44 -> 0 | K49: =K44 -> 0 | ... P49: =P44 -> 0
B50: Subsidio(-)/Contribucion(+) | C50: =C46 -> 0
B53: AREA LIMPIA
C54: Total | D54: Componente TDF | E54: Componente TTL | F54: Componente TVIAT | G54: Aprovechamiento | H54: CCSA Prest.Aprov. | I54: Especiales | J54: Componente TCS | K54: Componente TLU | L54: Componente TBL | M54: Componente TRT | N54: CCSA Prest. No Aprov. | O54: Deb/Cred
B55: Vlr Servicio | C55: 0 | D55: 0 | E55: 0 | F55: 0 | G55: 0 | H55: 0 | I55: 0 | J55: 0 | K55: 0 | L55: 0 | M55: 0 | N55: 0 | O55: 0
B56: Vlr Intereses | C56: 0 | D56: 0 | E56: 0 | F56: 0 | G56: 0 | H56: 0 | I56: 0 | J56: 0 | K56: 0 | L56: 0 | M56: 0 | N56: 0 | O56: 0
A57: Componente | B57: Total | C57: 0 | D57: 0 | E57: 0 | F57: 0 | G57: 0 | H57: 0 | I57: 0 | J57: 0 | K57: 0 | L57: 0 | M57: 0 | N57: 0 | O57: 0
B58: Subsidio(-)/Contribucion(+) | C58: 0 | D58: 0 | E58: 0 | F58: 0 | G58: 0 | H58: 0 | I58: 0 | J58: 0 | K58: 0 | L58: 0 | M58: 0 | N58: 0 | O58: 0
A59: Subs/Cont | B59: Total | C59: 0 | D59: 0 | E59: 0 | F59: 0 | G59: 0 | H59: 0 | I59: 0 | J59: 0 | K59: 0 | L59: 0 | M59: 0 | N59: 0 | O59: 0
A60: Total | C60: 0 | D60: 0 | E60: 0 | F60: 0 | G60: 0 | H60: 0 | I60: 0 | J60: 0 | K60: 0 | L60: 0 | M60: 0 | N60: 0 | O60: 0
B62: Total | C62: =C60-I60 -> 0 | D62: =D57 -> 0 | E62: =E57 -> 0 | F62: =F57 -> 0 | G62: =G57 -> 0 | H62: =H57 -> 0 | I62: =I57 -> 0 | J62: =J57 -> 0 | K62: =K57 -> 0 | ... P62: =P57 -> 0
B63: Subsidio(-)/Contribucion(+) | C63: =C59 -> 0

Sheet RETRIBUCION NEGATIVA
B1: PROMOAMBIENTAL
C2: Total | D2: Componente TDF | E2: Componente TTL | F2: Componente TVIAT | G2: Aprovechamiento | H2: CCSA Prest.Aprov. | I2: Especiales | J2: Componente TCS | K2: Componente TLU | L2: Componente TBL | M2: Componente TRT | N2: CCSA Prest. No Aprov. | O2: Deb/Cred
B3: Vlr Intereses | C3: 0 | D3: 0 | E3: 0 | F3: 0 | G3: 0 | H3: 0 | I3: 0 | J3: 0 | K3: 0 | L3: 0 | M3: 0 | N3: 0 | O3: 0
B4: Vlr Servicio | C4: 0 | D4: 0 | E4: 0 | F4: 0 | G4: 0 | H4: 0 | I4: 0 | J4: 0 | K4: 0 | L4: 0 | M4: 0 | N4: 0 | O4: 0
A5: Componente | B5: Total | C5: 0 | D5: 0 | E5: 0 | F5: 0 | G5: 0 | H5: 0 | I5: 0 | J5: 0 | K5: 0 | L5: 0 | M5: 0 | N5: 0 | O5: 0
B6: Subsidio(-)/Contribucion(+) | C6: 0 | D6: 0 | E6: 0 | F6: 0 | G6: 0 | H6: 0 | I6: 0 | J6: 0 | K6: 0 | L6: 0 | M6: 0 | N6: 0 | O6: 0
A7: Subs/Cont | B7: Total | C7: 0 | D7: 0 | E7: 0 | F7: 0 | G7: 0 | H7: 0 | I7: 0 | J7: 0 | K7: 0 | L7: 0 | M7: 0 | N7: 0 | O7: 0
A8: Total | C8: 0 | D8: 0 | E8: 0 | F8: 0 | G8: 0 | H8: 0 | I8: 0 | J8: 0 | K8: 0 | L8: 0 | M8: 0 | N8: 0 | O8: 0
B10: Total | C10: =C8-I8 -> 0 | D10: =D5 -> 0 | E10: =E5 -> 0 | F10: =F5 -> 0 | G10: =G5 -> 0 | H10: =H5 -> 0 | I10: =I5 -> 0 | J10: =J5 -> 0 | K10: =K5 -> 0 | ... O10: =O5 -> 0
B11: Subsidio(-)/Contribucion(+) | C11: =C7 -> 0
B14: LIME
C15: Total | D15: Componente TDF | E15: Componente TTL | F15: Componente TVIAT | G15: Aprovechamiento | H15: CCSA Prest.Aprov. | I15: Especiales | J15: Componente TCS | K15: Componente TLU | L15: Componente TBL | M15: Componente TRT | N15: CCSA Prest. No Aprov. | O15: Deb/Cred
B16: Vlr Intereses | C16: 0 | D16: 0 | E16: 0 | F16: 0 | G16: 0 | H16: 0 | I16: 0 | J16: 0 | K16: 0 | L16: 0 | M16: 0 | N16: 0 | O16: 0
B17: Vlr Servicio | C17: 0 | D17: 0 | E17: 0 | F17: 0 | G17: 0 | H17: 0 | I17: 0 | J17: 0 | K17: 0 | L17: 0 | M17: 0 | N17: 0 | O17: 0
A18: Componente | B18: Total | C18: 0 | D18: 0 | E18: 0 | F18: 0 | G18: 0 | H18: 0 | I18: 0 | J18: 0 | K18: 0 | L18: 0 | M18: 0 | N18: 0 | O18: 0
B19: Subsidio(-)/Contribucion(+) | C19: 0 | D19: 0 | E19: 0 | F19: 0 | G19: 0 | H19: 0 | I19: 0 | J19: 0 | K19: 0 | L19: 0 | M19: 0 | N19: 0 | O19: 0
A20: Subs/Cont | B20: Total | C20: 0 | D20: 0 | E20: 0 | F20: 0 | G20: 0 | H20: 0 | I20: 0 | J20: 0 | K20: 0 | L20: 0 | M20: 0 | N20: 0 | O20: 0
A21: Total | C21: 0 | D21: 0 | E21: 0 | F21: 0 | G21: 0 | H21: 0 | I21: 0 | J21: 0 | K21: 0 | L21: 0 | M21: 0 | N21: 0 | O21: 0
B23: Total | C23: =C21-I21 -> 0 | D23: =D18 -> 0 | E23: =E18 -> 0 | F23: =F18 -> 0 | G23: =G18 -> 0 | H23: =H18 -> 0 | I23: =I18 -> 0 | J23: =J18 -> 0 | K23: =K18 -> 0 | ... O23: =O18 -> 0
B24: Subsidio(-)/Contribucion(+) | C24: =C20 -> 0
B27: CIUDAD LIMPIA
C28: Total | D28: Componente TDF | E28: Componente TTL | F28: Componente TVIAT | G28: Aprovechamiento | H28: CCSA Prest.Aprov. | I28: Especiales | J28: Componente TCS | K28: Componente TLU | L28: Componente TBL | M28: Componente TRT | N28: CCSA Prest. No Aprov. | O28: Deb/Cred
B29: Vlr Intereses | C29: 0 | D29: 0 | E29: 0 | F29: 0 | G29: 0 | H29: 0 | I29: 0 | J29: 0 | K29: 0 | L29: 0 | M29: 0 | N29: 0 | O29: 0
B30: Vlr Servicio | C30: 0 | D30: 0 | E30: 0 | F30: 0 | G30: 0 | H30: 0 | I30: 0 | J30: 0 | K30: 0 | L30: 0 | M30: 0 | N30: 0 | O30: 0
A31: Componente | B31: Total | C31: 0 | D31: 0 | E31: 0 | F31: 0 | G31: 0 | H31: 0 | I31: 0 | J31: 0 | K31: 0 | L31: 0 | M31: 0 | N31: 0 | O31: 0
B32: Subsidio(-)/Contribucion(+) | C32: 0 | D32: 0 | E32: 0 | F32: 0 | G32: 0 | H32: 0 | I32: 0 | J32: 0 | K32: 0 | L32: 0 | M32: 0 | N32: 0 | O32: 0
A33: Subs/Cont | B33: Total | C33: 0 | D33: 0 | E33: 0 | F33: 0 | G33: 0 | H33: 0 | I33: 0 | J33: 0 | K33: 0 | L33: 0 | M33: 0 | N33: 0 | O33: 0
A34: Total | C34: 0 | D34: 0 | E34: 0 | F34: 0 | G34: 0 | H34: 0 | I34: 0 | J34: 0 | K34: 0 | L34: 0 | M34: 0 | N34: 0 | O34: 0
B36: Total | C36: =C34-I34 -> 0 | D36: =D31 -> 0 | E36: =E31 -> 0 | F36: =F31 -> 0 | G36: =G31 -> 0 | H36: =H31 -> 0 | I36: =I31 -> 0 | J36: =J31 -> 0 | K36: =K31 -> 0 | ... O36: =O31 -> 0
B37: Subsidio(-)/Contribucion(+) | C37: =C33 -> 0
B40: BOGOTA LIMPIA
C41: Total | D41: Componente TDF | E41: Componente TTL | F41: Componente TVIAT | G41: Aprovechamiento | H41: CCSA Prest.Aprov. | I41: Especiales | J41: Componente TCS | K41: Componente TLU | L41: Componente TBL | M41: Componente TRT | N41: CCSA Prest. No Aprov. | O41: Deb/Cred
B42: Vlr Intereses | C42: 0 | D42: 0 | E42: 0 | F42: 0 | G42: 0 | H42: 0 | I42: 0 | J42: 0 | K42: 0 | L42: 0 | M42: 0 | N42: 0 | O42: 0
B43: Vlr Servicio | C43: 0 | D43: 0 | E43: 0 | F43: 0 | G43: 0 | H43: 0 | I43: 0 | J43: 0 | K43: 0 | L43: 0 | M43: 0 | N43: 0 | O43: 0
A44: Componente | B44: Total | C44: 0 | D44: 0 | E44: 0 | F44: 0 | G44: 0 | H44: 0 | I44: 0 | J44: 0 | K44: 0 | L44: 0 | M44: 0 | N44: 0 | O44: 0
B45: Subsidio(-)/Contribucion(+) | C45: 0 | D45: 0 | E45: 0 | F45: 0 | G45: 0 | H45: 0 | I45: 0 | J45: 0 | K45: 0 | L45: 0 | M45: 0 | N45: 0 | O45: 0
A46: Subs/Cont | B46: Total | C46: 0 | D46: 0 | E46: 0 | F46: 0 | G46: 0 | H46: 0 | I46: 0 | J46: 0 | K46: 0 | L46: 0 | M46: 0 | N46: 0 | O46: 0
A47: Total | C47: 0 | D47: 0 | E47: 0 | F47: 0 | G47: 0 | H47: 0 | I47: 0 | J47: 0 | K47: 0 | L47: 0 | M47: 0 | N47: 0 | O47: 0
B49: Total | C49: =C47-I47 -> 0 | D49: =D44 -> 0 | E49: =E44 -> 0 | F49: =F44 -> 0 | G49: =G44 -> 0 | H49: =H44 -> 0 | I49: =I44 -> 0 | J49: =J44 -> 0 | K49: =K44 -> 0 | ... O49: =O44 -> 0
B50: Subsidio(-)/Contribucion(+) | C50: =C46 -> 0
B53: AREA LIMPIA
C54: Total | D54: Componente TDF | E54: Componente TTL | F54: Componente TVIAT | G54: Aprovechamiento | H54: CCSA Prest.Aprov. | I54: Especiales | J54: Componente TCS | K54: Componente TLU | L54: Componente TBL | M54: Componente TRT | N54: CCSA Prest. No Aprov. | O54: Deb/Cred
B55: Vlr Intereses | C55: 0 | D55: 0 | E55: 0 | F55: 0 | G55: 0 | H55: 0 | I55: 0 | J55: 0 | K55: 0 | L55: 0 | M55: 0 | N55: 0 | O55: 0
B56: Vlr Servicio | C56: 0 | D56: 0 | E56: 0 | F56: 0 | G56: 0 | H56: 0 | I56: 0 | J56: 0 | K56: 0 | L56: 0 | M56: 0 | N56: 0 | O56: 0
A57: Componente | B57: Total | C57: 0 | D57: 0 | E57: 0 | F57: 0 | G57: 0 | H57: 0 | I57: 0 | J57: 0 | K57: 0 | L57: 0 | M57: 0 | N57: 0 | O57: 0
B58: Subsidio(-)/Contribucion(+) | C58: 0 | D58: 0 | E58: 0 | F58: 0 | G58: 0 | H58: 0 | I58: 0 | J58: 0 | K58: 0 | L58: 0 | M58: 0 | N58: 0 | O58: 0
A59: Subs/Cont | B59: Total | C59: 0 | D59: 0 | E59: 0 | F59: 0 | G59: 0 | H59: 0 | I59: 0 | J59: 0 | K59: 0 | L59: 0 | M59: 0 | N59: 0 | O59: 0
A60: Total | C60: 0 | D60: 0 | E60: 0 | F60: 0 | G60: 0 | H60: 0 | I60: 0 | J60: 0 | K60: 0 | L60: 0 | M60: 0 | N60: 0 | O60: 0
B62: Total | C62: =C60-I60 -> 0 | D62: =D57 -> 0 | E62: =E57 -> 0 | F62: =F57 -> 0 | G62: =G57 -> 0 | H62: =H57 -> 0 | I62: =I57 -> 0 | J62: =J57 -> 0 | K62: =K57 -> 0 | ... O62: =O57 -> 0
B63: Subsidio(-)/Contribucion(+) | C63: =C59 -> 0

Sheet AJUSTES - SF-T
F3: PROCERASEO S.A.S. | I3: NIT: 901 153 639 - 0 | M3: Codigo Remuneración: | N3: ='CONSOLIDADO_TOTAL RECAUDO'!N3 -> 2026091 | U3: PROCERASEO S.A.S. | W3: NIT: 901 153 639 - 0 | AA3: Codigo Remuneración: | AC3: =N3 -> 2026091
F4: 3. ESQUEMA FINANCIERO DEL SERVICIO PUBLICO DE ASEO | U4: 3. ESQUEMA FINANCIERO DEL SERVICIO PUBLICO DE ASEO
F5: Resoluciòn UAESP Número 27 de 2018 | U5: Resoluciòn UAESP Número 27 de 2018
C6: Fecha de Proceso: | D6: ='CONSOLIDADO_TOTAL RECAUDO'!D6 -> 46297 | F6: SALDOS A FAVOR POR NOTA | U6: =+F6 -> SALDOS A FAVOR POR NOTA
C7: Hora: | D7: ='CONSOLIDADO_TOTAL RECAUDO'!D7 -> 0.58333333 | F7: Fecha Desde: | H7: ='CONSOLIDADO_TOTAL RECAUDO'!G7 -> 46266 | J7: Feha Hasta: | K7: ='CONSOLIDADO_TOTAL RECAUDO'!K7 -> 46280 | U7: =F7 -> Fecha Desde: | V7: =H7 -> 46266 | X7: =J7 -> Feha Hasta: | Y7: =K7 -> 46280
B8: ASE | C8: Concesionarios | D8: Recaudo Total | E8: Recaudo por disposicion final | F8: Recaudo por tratamiento de lixiviados | G8: Recaudo por Componente VIAT ( Decreto 2412/2018) | H8: Recaudo por aprovechamiento | I8: Recaudo del componente de comercializacion para Aprovechamiento (11,4%) | J8: Balance de subsidio o contribuciones | K8: RECAUDO BASE DE REMUNERACION | L8: Costo de la Interventoría | M8: REMUNERACION FINAL | N8: Conceptos especiales | O8: REMUNERACION FINAL MAS CONCEPTOS ESPECIALES | S8: ASE | T8: Concesionarios | U8: Tarifa de Comercialización del Servicio. ( TCS) | V8: Tarifa de Limpieza Urbana del Servicio. ( TLU) | W8: Tarifa de Barrido y Limpieza del Servicio. ( TBL) | X8: Tarifa de Recolección y Transporte del Servicio. (TRT) | Y8: Recaudo del componente de comercializacion para Aprovechamiento (18,6%) | Z8: Costo de la Interventoría | AA8: Ajuste a la decena | AB8: Conceptos especiales | AC8: Diferencial Balance S / C (Fac vs Rec) | AD8: Balance S / C Con Baase en (Recaudo) | AE8: REMUNERACION FINAL MAS CONCEPTOS ESPECIALES
B9: 1 | C9: PROMOAMBIENTAL DISTRITO S.A.S. ESP. | D9: ='SALDOS POR NOTA'!C10 -> 0 | E9: ='SALDOS POR NOTA'!D10 -> 0 | F9: ='SALDOS POR NOTA'!E10 -> 0 | G9: ='SALDOS POR NOTA'!F10 -> 0 | H9: ='SALDOS POR NOTA'!G10 -> 0 | I9: ='SALDOS POR NOTA'!H10 -> 0 | J9: 0 | K9: =D9-E9-F9-G9-H9-I9-J9 -> 0 | L9: 0 | M9: =K9-L9 -> 0 | N9: ='SALDOS POR NOTA'!I10 -> 0 | O9: =M9+N9 -> 0 | S9: 1 | T9: PROMOAMBIENTAL DISTRITO S.A.S. ESP. | U9: ='SALDOS POR NOTA'!J10 -> 0 | V9: ='SALDOS POR NOTA'!K10 -> 0 | W9: ='SALDOS POR NOTA'!L10 -> 0 | X9: ='SALDOS POR NOTA'!M10 -> 0 | Y9: ='SALDOS POR NOTA'!N10 -> 0 | Z9: =L9*-1 -> 0 | AA9: ='SALDOS POR NOTA'!O10 -> 0 | AB9: =N9 -> 0 | AC9: =-J9+AD9 -> 0 | AD9: ='SALDOS POR NOTA'!C11 -> 0 | AE9: =SUM(U9:AC9) -> 0 | AF9: =(AE9-O9) -> 0 | AG9: =AF9=0 -> TRUE
B10: 2 | C10: LIMPIEZA METROPOLITANA S.A. ESP. | D10: ='SALDOS POR NOTA'!C23 -> 0 | E10: ='SALDOS POR NOTA'!D23 -> 0 | F10: ='SALDOS POR NOTA'!E23 -> 0 | G10: ='SALDOS POR NOTA'!F23 -> 0 | H10: ='SALDOS POR NOTA'!G23 -> 0 | I10: ='SALDOS POR NOTA'!H23 -> 0 | J10: 0 | K10: =D10-E10-F10-G10-H10-I10-J10 -> 0 | L10: 0 | M10: =K10-L10 -> 0 | N10: ='SALDOS POR NOTA'!I23 -> 0 | O10: =M10+N10 -> 0 | S10: 2 | T10: LIMPIEZA METROPOLITANA S.A. ESP. | U10: ='SALDOS POR NOTA'!J23 -> 0 | V10: ='SALDOS POR NOTA'!K23 -> 0 | W10: ='SALDOS POR NOTA'!L23 -> 0 | X10: ='SALDOS POR NOTA'!M23 -> 0 | Y10: ='SALDOS POR NOTA'!N23 -> 0 | Z10: =L10*-1 -> 0 | AA10: ='SALDOS POR NOTA'!O23 -> 0 | AB10: =N10 -> 0 | AC10: =-J10+AD10 -> 0 | AD10: ='SALDOS POR NOTA'!C24 -> 0 | AE10: =SUM(U10:AC10) -> 0 | AF10: =(AE10-O10) -> 0 | AG10: =AF10=0 -> TRUE
B11: 3 | C11: CIUDAD LIMPIA BOGOTA S.A. ESP. | D11: ='SALDOS POR NOTA'!C36 -> 0 | E11: ='SALDOS POR NOTA'!D36 -> 0 | F11: ='SALDOS POR NOTA'!E36 -> 0 | G11: ='SALDOS POR NOTA'!F36 -> 0 | H11: ='SALDOS POR NOTA'!G36 -> 0 | I11: ='SALDOS POR NOTA'!H36 -> 0 | J11: 0 | K11: =D11-E11-F11-G11-H11-I11-J11 -> 0 | L11: 0 | M11: =K11-L11 -> 0 | N11: ='SALDOS POR NOTA'!I36 -> 0 | O11: =M11+N11 -> 0 | S11: 3 | T11: CIUDAD LIMPIA BOGOTA S.A. ESP. | U11: ='SALDOS POR NOTA'!J36 -> 0 | V11: ='SALDOS POR NOTA'!K36 -> 0 | W11: ='SALDOS POR NOTA'!L36 -> 0 | X11: ='SALDOS POR NOTA'!M36 -> 0 | Y11: ='SALDOS POR NOTA'!N36 -> 0 | Z11: =L11*-1 -> 0 | AA11: ='SALDOS POR NOTA'!O36 -> 0 | AB11: =N11 -> 0 | AC11: =-J11+AD11 -> 0 | AD11: ='SALDOS POR NOTA'!C37 -> 0 | AE11: =SUM(U11:AC11) -> 0 | AF11: =(AE11-O11) -> 0 | AG11: =AF11=0 -> TRUE
B12: 4 | C12: BOGOTA LIMPIA S.A.S. ESP. | D12: ='SALDOS POR NOTA'!C49 -> 0 | E12: ='SALDOS POR NOTA'!D49 -> 0 | F12: ='SALDOS POR NOTA'!E49 -> 0 | G12: ='SALDOS POR NOTA'!F49 -> 0 | H12: ='SALDOS POR NOTA'!G49 -> 0 | I12: ='SALDOS POR NOTA'!H49 -> 0 | J12: 0 | K12: =D12-E12-F12-G12-H12-I12-J12 -> 0 | L12: 0 | M12: =K12-L12 -> 0 | N12: ='SALDOS POR NOTA'!I49 -> 0 | O12: =M12+N12 -> 0 | S12: 4 | T12: BOGOTA LIMPIA S.A.S. ESP. | U12: ='SALDOS POR NOTA'!J49 -> 0 | V12: ='SALDOS POR NOTA'!K49 -> 0 | W12: ='SALDOS POR NOTA'!L49 -> 0 | X12: ='SALDOS POR NOTA'!M49 -> 0 | Y12: ='SALDOS POR NOTA'!N49 -> 0 | Z12: =L12*-1 -> 0 | AA12: ='SALDOS POR NOTA'!O49 -> 0 | AB12: =N12 -> 0 | AC12: =-J12+AD12 -> 0 | AD12: ='SALDOS POR NOTA'!C50 -> 0 | AE12: =SUM(U12:AC12) -> 0 | AF12: =(AE12-O12) -> 0 | AG12: =AF12=0 -> TRUE
B13: 5 | C13: AREA LIMPIA DISTRITO CAPITAL S.A.S. ESP. | D13: ='SALDOS POR NOTA'!C62 -> 0 | E13: ='SALDOS POR NOTA'!D62 -> 0 | F13: ='SALDOS POR NOTA'!E62 -> 0 | G13: ='SALDOS POR NOTA'!F62 -> 0 | H13: ='SALDOS POR NOTA'!G62 -> 0 | I13: ='SALDOS POR NOTA'!H62 -> 0 | J13: 0 | K13: =D13-E13-F13-G13-H13-I13-J13 -> 0 | L13: 0 | M13: =K13-L13 -> 0 | N13: ='SALDOS POR NOTA'!I62 -> 0 | O13: =M13+N13 -> 0 | S13: 5 | T13: AREA LIMPIA DISTRITO CAPITAL S.A.S. ESP. | U13: ='SALDOS POR NOTA'!J62 -> 0 | V13: ='SALDOS POR NOTA'!K62 -> 0 | W13: ='SALDOS POR NOTA'!L62 -> 0 | X13: ='SALDOS POR NOTA'!M62 -> 0 | Y13: ='SALDOS POR NOTA'!N62 -> 0 | Z13: =L13*-1 -> 0 | AA13: ='SALDOS POR NOTA'!O62 -> 0 | AB13: =N13 -> 0 | AC13: =-J13+AD13 -> 0 | AD13: ='SALDOS POR NOTA'!C63 -> 0 | AE13: =SUM(U13:AC13) -> 0 | AF13: =(AE13-O13) -> 0 | AG13: =AF13=0 -> TRUE
C14: TOTAL | D14: =SUM(D9:D13) -> 0 | E14: =SUM(E9:E13) -> 0 | F14: =SUM(F9:F13) -> 0 | G14: =SUM(G9:G13) -> 0 | H14: =SUM(H9:H13) -> 0 | I14: =SUM(I9:I13) -> 0 | J14: =SUM(J9:J13) -> 0 | K14: =SUM(K9:K13) -> 0 | ... O14: =SUM(O9:O13) -> 0 | T14: TOTAL | U14: =SUM(U9:U13) -> 0 | V14: =SUM(V9:V13) -> 0 | W14: =SUM(W9:W13) -> 0 | X14: =SUM(X9:X13) -> 0 | Y14: =SUM(Y9:Y13) -> 0 | Z14: =SUM(Z9:Z13) -> 0 | AA14: =SUM(AA9:AA13) -> 0 | AB14: =SUM(AB9:AB13) -> 0 | ... AF14: =SUM(AF9:AF13) -> 0 | AG14: =AF14=0 -> TRUE
Y16: =SUM(U14:Y14) -> 0
F18: Firma autorizada
F22: PROCERASEO S.A.S. | I22: NIT: 901 153 639 - 0 | M22: Codigo Remuneración: | N22: =N3 -> 2026091 | U22: PROCERASEO S.A.S. | W22: NIT: 901 153 639 - 0 | AA22: Codigo Remuneración: | AC22: =N22 -> 2026091
F23: 3. ESQUEMA FINANCIERO DEL SERVICIO PUBLICO DE ASEO | U23: 3. ESQUEMA FINANCIERO DEL SERVICIO PUBLICO DE ASEO
F24: Resoluciòn UAESP Número 27 de 2018 | U24: Resoluciòn UAESP Número 27 de 2018
C25: Fecha de Proceso: | D25: =D6 -> 46297 | F25: RETRIBUCION NEGATIVA | U25: =+F25 -> RETRIBUCION NEGATIVA
C26: Hora: | D26: =D7 -> 0.58333333 | F26: Fecha Desde: | H26: =H7 -> 46266 | J26: Feha Hasta: | K26: =K7 -> 46280 | U26: =F26 -> Fecha Desde: | V26: =H26 -> 46266 | X26: =J26 -> Feha Hasta: | Y26: =K26 -> 46280
B27: ASE | C27: Concesionarios | D27: Recaudo Total | E27: Recaudo por disposicion final | F27: Recaudo por tratamiento de lixiviados | G27: Recaudo por Componente VIAT ( Decreto 2412/2018) | H27: Recaudo por aprovechamiento | I27: Recaudo del componente de comercializacion para Aprovechamiento (11,4%) | J27: Balance de subsidio o contribuciones | K27: RECAUDO BASE DE REMUNERACION | L27: Costo de la Interventoría | M27: REMUNERACION FINAL | N27: Conceptos especiales | O27: REMUNERACION FINAL MAS CONCEPTOS ESPECIALES | S27: ASE | T27: Concesionarios | U27: Tarifa de Comercialización del Servicio. ( TCS) | V27: Tarifa de Limpieza Urbana del Servicio. ( TLU) | W27: Tarifa de Barrido y Limpieza del Servicio. ( TBL) | X27: Tarifa de Recolección y Transporte del Servicio. (TRT) | Y27: Recaudo del componente de comercializacion para Aprovechamiento (18,6%) | Z27: Costo de la Interventoría | AA27: Ajuste a la decena | AB27: Conceptos especiales | AC27: Diferencial Balance S / C (Fac vs Rec) | AD27: Balance S / C Con Baase en (Recaudo) | AE27: REMUNERACION FINAL MAS CONCEPTOS ESPECIALES
B28: 1 | C28: PROMOAMBIENTAL DISTRITO S.A.S. ESP. | D28: ='RETRIBUCION NEGATIVA'!C10 -> 0 | E28: ='RETRIBUCION NEGATIVA'!D10 -> 0 | F28: ='RETRIBUCION NEGATIVA'!E10 -> 0 | G28: ='RETRIBUCION NEGATIVA'!F10 -> 0 | H28: ='RETRIBUCION NEGATIVA'!G10 -> 0 | I28: ='RETRIBUCION NEGATIVA'!H10 -> 0 | J28: 0 | K28: =D28-E28-F28-H28-I28-J28-G28 -> 0 | L28: 0 | M28: =K28-L28 -> 0 | N28: ='RETRIBUCION NEGATIVA'!I10 -> 0 | O28: =M28+N28 -> 0 | S28: 1 | T28: PROMOAMBIENTAL DISTRITO S.A.S. ESP. | U28: ='RETRIBUCION NEGATIVA'!J10 -> 0 | V28: ='RETRIBUCION NEGATIVA'!K10 -> 0 | W28: ='RETRIBUCION NEGATIVA'!L10 -> 0 | X28: ='RETRIBUCION NEGATIVA'!M10 -> 0 | Y28: ='RETRIBUCION NEGATIVA'!N10 -> 0 | Z28: =L28*-1 -> 0 | AA28: ='RETRIBUCION NEGATIVA'!O10 -> 0 | AB28: =N28 -> 0 | AC28: =-J28+AD28 -> 0 | AD28: ='RETRIBUCION NEGATIVA'!C11 -> 0 | AE28: =SUM(U28:AC28) -> 0 | AF28: =(AE28-O28) -> 0 | AG28: =AF28=0 -> TRUE
B29: 2 | C29: LIMPIEZA METROPOLITANA S.A. ESP. | D29: ='RETRIBUCION NEGATIVA'!C23 -> 0 | E29: ='RETRIBUCION NEGATIVA'!D23 -> 0 | F29: ='RETRIBUCION NEGATIVA'!E23 -> 0 | G29: ='RETRIBUCION NEGATIVA'!F23 -> 0 | H29: ='RETRIBUCION NEGATIVA'!G23 -> 0 | I29: ='RETRIBUCION NEGATIVA'!H23 -> 0 | J29: 0 | K29: =D29-E29-F29-H29-I29-J29-G29 -> 0 | L29: 0 | M29: =K29-L29 -> 0 | N29: ='RETRIBUCION NEGATIVA'!I23 -> 0 | O29: =M29+N29 -> 0 | S29: 2 | T29: LIMPIEZA METROPOLITANA S.A. ESP. | U29: ='RETRIBUCION NEGATIVA'!J23 -> 0 | V29: ='RETRIBUCION NEGATIVA'!K23 -> 0 | W29: ='RETRIBUCION NEGATIVA'!L23 -> 0 | X29: ='RETRIBUCION NEGATIVA'!M23 -> 0 | Y29: ='RETRIBUCION NEGATIVA'!N23 -> 0 | Z29: =L29*-1 -> 0 | AA29: ='RETRIBUCION NEGATIVA'!O23 -> 0 | AB29: =N29 -> 0 | AC29: =-J29+AD29 -> 0 | AD29: ='RETRIBUCION NEGATIVA'!C24 -> 0 | AE29: =SUM(U29:AC29) -> 0 | AF29: =(AE29-O29) -> 0 | AG29: =AF29=0 -> TRUE
B30: 3 | C30: CIUDAD LIMPIA BOGOTA S.A. ESP. | D30: ='RETRIBUCION NEGATIVA'!C36 -> 0 | E30: ='RETRIBUCION NEGATIVA'!D36 -> 0 | F30: ='RETRIBUCION NEGATIVA'!E36 -> 0 | G30: ='RETRIBUCION NEGATIVA'!F36 -> 0 | H30: ='RETRIBUCION NEGATIVA'!G36 -> 0 | I30: ='RETRIBUCION NEGATIVA'!H36 -> 0 | J30: 0 | K30: =D30-E30-F30-H30-I30-J30-G30 -> 0 | L30: 0 | M30: =K30-L30 -> 0 | N30: ='RETRIBUCION NEGATIVA'!I36 -> 0 | O30: =M30+N30 -> 0 | S30: 3 | T30: CIUDAD LIMPIA BOGOTA S.A. ESP. | U30: ='RETRIBUCION NEGATIVA'!J36 -> 0 | V30: ='RETRIBUCION NEGATIVA'!K36 -> 0 | W30: ='RETRIBUCION NEGATIVA'!L36 -> 0 | X30: ='RETRIBUCION NEGATIVA'!M36 -> 0 | Y30: ='RETRIBUCION NEGATIVA'!N36 -> 0 | Z30: =L30*-1 -> 0 | AA30: ='RETRIBUCION NEGATIVA'!O36 -> 0 | AB30: =N30 -> 0 | AC30: =-J30+AD30 -> 0 | AD30: ='RETRIBUCION NEGATIVA'!C37 -> 0 | AE30: =SUM(U30:AC30) -> 0 | AF30: =(AE30-O30) -> 0 | AG30: =AF30=0 -> TRUE
B31: 4 | C31: BOGOTA LIMPIA S.A.S. ESP. | D31: ='RETRIBUCION NEGATIVA'!C49 -> 0 | E31: ='RETRIBUCION NEGATIVA'!D49 -> 0 | F31: ='RETRIBUCION NEGATIVA'!E49 -> 0 | G31: ='RETRIBUCION NEGATIVA'!F49 -> 0 | H31: ='RETRIBUCION NEGATIVA'!G49 -> 0 | I31: ='RETRIBUCION NEGATIVA'!H49 -> 0 | J31: 0 | K31: =D31-E31-F31-H31-I31-J31-G31 -> 0 | L31: 0 | M31: =K31-L31 -> 0 | N31: ='RETRIBUCION NEGATIVA'!I49 -> 0 | O31: =M31+N31 -> 0 | S31: 4 | T31: BOGOTA LIMPIA S.A.S. ESP. | U31: ='RETRIBUCION NEGATIVA'!J49 -> 0 | V31: ='RETRIBUCION NEGATIVA'!K49 -> 0 | W31: ='RETRIBUCION NEGATIVA'!L49 -> 0 | X31: ='RETRIBUCION NEGATIVA'!M49 -> 0 | Y31: ='RETRIBUCION NEGATIVA'!N49 -> 0 | Z31: =L31*-1 -> 0 | AA31: ='RETRIBUCION NEGATIVA'!O49 -> 0 | AB31: =N31 -> 0 | AC31: =-J31+AD31 -> 0 | AD31: ='RETRIBUCION NEGATIVA'!C50 -> 0 | AE31: =SUM(U31:AC31) -> 0 | AF31: =(AE31-O31) -> 0 | AG31: =AF31=0 -> TRUE
B32: 5 | C32: AREA LIMPIA DISTRITO CAPITAL S.A.S. ESP. | D32: ='RETRIBUCION NEGATIVA'!C62 -> 0 | E32: ='RETRIBUCION NEGATIVA'!D62 -> 0 | F32: ='RETRIBUCION NEGATIVA'!E62 -> 0 | G32: ='RETRIBUCION NEGATIVA'!F62 -> 0 | H32: ='RETRIBUCION NEGATIVA'!G62 -> 0 | I32: ='RETRIBUCION NEGATIVA'!H62 -> 0 | J32: 0 | K32: =D32-E32-F32-H32-I32-J32-G32 -> 0 | L32: 0 | M32: =K32-L32 -> 0 | N32: ='RETRIBUCION NEGATIVA'!I62 -> 0 | O32: =M32+N32 -> 0 | S32: 5 | T32: AREA LIMPIA DISTRITO CAPITAL S.A.S. ESP. | U32: ='RETRIBUCION NEGATIVA'!J62 -> 0 | V32: ='RETRIBUCION NEGATIVA'!K62 -> 0 | W32: ='RETRIBUCION NEGATIVA'!L62 -> 0 | X32: ='RETRIBUCION NEGATIVA'!M62 -> 0 | Y32: ='RETRIBUCION NEGATIVA'!N62 -> 0 | Z32: =L32*-1 -> 0 | AA32: ='RETRIBUCION NEGATIVA'!O62 -> 0 | AB32: =N32 -> 0 | AC32: =-J32+AD32 -> 0 | AD32: ='RETRIBUCION NEGATIVA'!C63 -> 0 | AE32: =SUM(U32:AC32) -> 0 | AF32: =(AE32-O32) -> 0 | AG32: =AF32=0 -> TRUE
C33: TOTAL | D33: =SUM(D28:D32) -> 0 | E33: =SUM(E28:E32) -> 0 | F33: =SUM(F28:F32) -> 0 | G33: =SUM(G28:G32) -> 0 | H33: =SUM(H28:H32) -> 0 | I33: =SUM(I28:I32) -> 0 | J33: =SUM(J28:J32) -> 0 | K33: =SUM(K28:K32) -> 0 | ... O33: =SUM(O28:O32) -> 0 | T33: TOTAL | U33: =SUM(U28:U32) -> 0 | V33: =SUM(V28:V32) -> 0 | W33: =SUM(W28:W32) -> 0 | X33: =SUM(X28:X32) -> 0 | Y33: =SUM(Y28:Y32) -> 0 | Z33: =SUM(Z28:Z32) -> 0 | AA33: =SUM(AA28:AA32) -> 0 | AB33: =SUM(AB28:AB32) -> 0 | ... AF33: =SUM(AF28:AF32) -> 0 | AG33: =AF33=0 -> TRUE
J35: VALIDADOR DE POSTIVIOS EN REMUNERACION NEGATIVA | M35: =IF(MAX(D28:O32,U28:AE32)>0.9,"ERROR",TRUE) -> TRUE | Y35: =SUM(U33:Y33) -> 0
F37: Firma autorizada
F41: PROCERASEO S.A.S. | I41: NIT: 901 153 639 - 0 | M41: Codigo Remuneración: | N41: =N3 -> 2026091 | U41: PROCERASEO S.A.S. | W41: NIT: 901 153 639 - 0 | AA41: Codigo Remuneración: | AC41: =N41 -> 2026091
F42: 3. ESQUEMA FINANCIERO DEL SERVICIO PUBLICO DE ASEO | U42: 3. ESQUEMA FINANCIERO DEL SERVICIO PUBLICO DE ASEO
F43: Resoluciòn UAESP Número 27 de 2018 | U43: Resoluciòn UAESP Número 27 de 2018
C44: Fecha de Proceso: | D44: =D6 -> 46297 | F44: CONSOLIDADO SALDOS A FAVOR | U44: =+F44 -> CONSOLIDADO SALDOS A FAVOR
C45: Hora: | D45: =D7 -> 0.58333333 | F45: Fecha Desde: | H45: =H7 -> 46266 | J45: Feha Hasta: | K45: =K7 -> 46280 | U45: =F45 -> Fecha Desde: | V45: =H45 -> 46266 | X45: =J45 -> Feha Hasta: | Y45: =K45 -> 46280
B46: ASE | C46: Concesionarios | D46: Recaudo Total | E46: Recaudo por disposicion final | F46: Recaudo por tratamiento de lixiviados | G46: Recaudo por Componente VIAT ( Decreto 2412/2018) | H46: Recaudo por aprovechamiento | I46: Recaudo del componente de comercializacion para Aprovechamiento (11,4%) | J46: Balance de subsidio o contribuciones | K46: RECAUDO BASE DE REMUNERACION | L46: Costo de la Interventoría | M46: REMUNERACION FINAL | N46: Conceptos especiales | O46: REMUNERACION FINAL MAS CONCEPTOS ESPECIALES | S46: ASE | T46: Concesionarios | U46: Tarifa de Comercialización del Servicio. ( TCS) | V46: Tarifa de Limpieza Urbana del Servicio. ( TLU) | W46: Tarifa de Barrido y Limpieza del Servicio. ( TBL) | X46: Tarifa de Recolección y Transporte del Servicio. (TRT) | Y46: Recaudo del componente de comercializacion para Aprovechamiento (18,6%) | Z46: Costo de la Interventoría | AA46: Ajuste a la decena | AB46: Conceptos especiales | AC46: Diferencial Balance S / C (Fac vs Rec) | AD46: Balance S / C Con Baase en (Recaudo) | AE46: REMUNERACION FINAL MAS CONCEPTOS ESPECIALES
B47: 1 | C47: PROMOAMBIENTAL DISTRITO S.A.S. ESP. | D47: =D9+D28 -> 0 | E47: =E9+E28 -> 0 | F47: =F9+F28 -> 0 | G47: =G9+G28 -> 0 | H47: =H9+H28 -> 0 | I47: =I9+I28 -> 0 | J47: =J9+J28 -> 0 | K47: =D47-E47-F47-G47-H47-I47-J47 -> 0 | L47: 0 | M47: =K47-L47 -> 0 | N47: =N9+N28 -> 0 | O47: =M47+N47 -> 0 | S47: 1 | T47: PROMOAMBIENTAL DISTRITO S.A.S. ESP. | U47: =U9+U28 -> 0 | V47: =V9+V28 -> 0 | W47: =W9+W28 -> 0 | X47: =X9+X28 -> 0 | Y47: =Y9+Y28 -> 0 | Z47: =-L47 -> 0 | AA47: =AA9+AA28 -> 0 | AB47: =AB9+AB28 -> 0 | AC47: =AC9+AC28 -> 0 | AD47: =AD9+AD28 -> 0 | AE47: =SUM(U47:AC47) -> 0 | AF47: =(AE47-O47) -> 0 | AG47: =AF47=0 -> TRUE
B48: 2 | C48: LIMPIEZA METROPOLITANA S.A. ESP. | D48: =D10+D29 -> 0 | E48: =E10+E29 -> 0 | F48: =F10+F29 -> 0 | G48: =G10+G29 -> 0 | H48: =H10+H29 -> 0 | I48: =I10+I29 -> 0 | J48: =J10+J29 -> 0 | K48: =D48-E48-F48-G48-H48-I48-J48 -> 0 | L48: 0 | M48: =K48-L48 -> 0 | N48: =N10+N29 -> 0 | O48: =M48+N48 -> 0 | S48: 2 | T48: LIMPIEZA METROPOLITANA S.A. ESP. | U48: =U10+U29 -> 0 | V48: =V10+V29 -> 0 | W48: =W10+W29 -> 0 | X48: =X10+X29 -> 0 | Y48: =Y10+Y29 -> 0 | Z48: =-L48 -> 0 | AA48: =AA10+AA29 -> 0 | AB48: =AB10+AB29 -> 0 | AC48: =AC10+AC29 -> 0 | AD48: =AD10+AD29 -> 0 | AE48: =SUM(U48:AC48) -> 0 | AF48: =(AE48-O48) -> 0 | AG48: =AF48=0 -> TRUE
B49: 3 | C49: CIUDAD LIMPIA BOGOTA S.A. ESP. | D49: =D11+D30 -> 0 | E49: =E11+E30 -> 0 | F49: =F11+F30 -> 0 | G49: =G11+G30 -> 0 | H49: =H11+H30 -> 0 | I49: =I11+I30 -> 0 | J49: =J11+J30 -> 0 | K49: =D49-E49-F49-G49-H49-I49-J49 -> 0 | L49: 0 | M49: =K49-L49 -> 0 | N49: =N11+N30 -> 0 | O49: =M49+N49 -> 0 | S49: 3 | T49: CIUDAD LIMPIA BOGOTA S.A. ESP. | U49: =U11+U30 -> 0 | V49: =V11+V30 -> 0 | W49: =W11+W30 -> 0 | X49: =X11+X30 -> 0 | Y49: =Y11+Y30 -> 0 | Z49: =-L49 -> 0 | AA49: =AA11+AA30 -> 0 | AB49: =AB11+AB30 -> 0 | AC49: =AC11+AC30 -> 0 | AD49: =AD11+AD30 -> 0 | AE49: =SUM(U49:AC49) -> 0 | AF49: =(AE49-O49) -> 0 | AG49: =AF49=0 -> TRUE
B50: 4 | C50: BOGOTA LIMPIA S.A.S. ESP. | D50: =D12+D31 -> 0 | E50: =E12+E31 -> 0 | F50: =F12+F31 -> 0 | G50: =G12+G31 -> 0 | H50: =H12+H31 -> 0 | I50: =I12+I31 -> 0 | J50: =J12+J31 -> 0 | K50: =D50-E50-F50-G50-H50-I50-J50 -> 0 | L50: 0 | M50: =K50-L50 -> 0 | N50: =N12+N31 -> 0 | O50: =M50+N50 -> 0 | S50: 4 | T50: BOGOTA LIMPIA S.A.S. ESP. | U50: =U12+U31 -> 0 | V50: =V12+V31 -> 0 | W50: =W12+W31 -> 0 | X50: =X12+X31 -> 0 | Y50: =Y12+Y31 -> 0 | Z50: =-L50 -> 0 | AA50: =AA12+AA31 -> 0 | AB50: =AB12+AB31 -> 0 | AC50: =AC12+AC31 -> 0 | AD50: =AD12+AD31 -> 0 | AE50: =SUM(U50:AC50) -> 0 | AF50: =(AE50-O50) -> 0 | AG50: =AF50=0 -> TRUE
B51: 5 | C51: AREA LIMPIA DISTRITO CAPITAL S.A.S. ESP. | D51: =D13+D32 -> 0 | E51: =E13+E32 -> 0 | F51: =F13+F32 -> 0 | G51: =G13+G32 -> 0 | H51: =H13+H32 -> 0 | I51: =I13+I32 -> 0 | J51: =J13+J32 -> 0 | K51: =D51-E51-F51-G51-H51-I51-J51 -> 0 | L51: 0 | M51: =K51-L51 -> 0 | N51: =N13+N32 -> 0 | O51: =M51+N51 -> 0 | S51: 5 | T51: AREA LIMPIA DISTRITO CAPITAL S.A.S. ESP. | U51: =U13+U32 -> 0 | V51: =V13+V32 -> 0 | W51: =W13+W32 -> 0 | X51: =X13+X32 -> 0 | Y51: =Y13+Y32 -> 0 | Z51: =-L51 -> 0 | AA51: =AA13+AA32 -> 0 | AB51: =AB13+AB32 -> 0 | AC51: =AC13+AC32 -> 0 | AD51: =AD13+AD32 -> 0 | AE51: =SUM(U51:AC51) -> 0 | AF51: =(AE51-O51) -> 0 | AG51: =AF51=0 -> TRUE
C52: TOTAL | D52: =SUM(D47:D51) -> 0 | E52: =SUM(E47:E51) -> 0 | F52: =SUM(F47:F51) -> 0 | G52: =SUM(G47:G51) -> 0 | H52: =SUM(H47:H51) -> 0 | I52: =SUM(I47:I51) -> 0 | J52: =SUM(J47:J51) -> 0 | K52: =SUM(K47:K51) -> 0 | ... O52: =SUM(O47:O51) -> 0 | T52: TOTAL | U52: =SUM(U47:U51) -> 0 | V52: =SUM(V47:V51) -> 0 | W52: =SUM(W47:W51) -> 0 | X52: =SUM(X47:X51) -> 0 | Y52: =SUM(Y47:Y51) -> 0 | Z52: =SUM(Z47:Z51) -> 0 | AA52: =SUM(AA47:AA51) -> 0 | AB52: =SUM(AB47:AB51) -> 0 | ... AF52: =SUM(AF47:AF51) -> 0 | AG52: =AF52=0 -> TRUE
Y54: =SUM(U52:Y52) -> 0
F56: Firma autorizada

Sheet INTERVENTORIA
F2: 2026 01 2 | G2: 2026 02 1 | H2: 2026 02 2 | I2: 2026 03 1 | J2: 2026 03 2 | K2: 2026 04 1 | L2: 2026 04 2 | M2: 2026 05 1 | N2: 2026 05 2 | O2: 2026 06 1 | P2: 2026 06 2 | Q2: 2026 07 1
B3: VALOR MES | C3: ASE | D3: Concesionarios | E3: % | F3: MITAD 1 // ENERO -26 | G3: MITAD 2 // ENERO -26 | H3: MITAD 1 // FEBRERO -26 | I3: MITAD 2 // FEBRERO -26 | J3: MITAD 1 // MARZO -26 | K3: MITAD 2 // MARZO -26 | L3: MITAD 1 // ABRIL -26 | M3: MITAD 2 // ABRIL -26 | N3: MITAD 1 // MAYO -26 | O3: MITAD 2 // MAYO -26 | P3: MITAD 1 // JUNIO -26 | Q3: MITAD 2 // JUNIO -26
B4: 378371975 | C4: 1 | D4: PROMOAMBIENTAL DISTRITO S.A.S. ESP. | E4: 0.22 | F4: 189185988 | G4: 189185987 | H4: 189185988 | I4: 189185987 | J4: 189185988 | K4: 189185987 | L4: 189185988 | M4: 189185987 | N4: 189185988 | O4: 189185987 | P4: 189185988 | Q4: 189185987
B5: 533160511 | C5: 2 | D5: LIMPIEZA METROPOLITANA S.A. ESP. | E5: 0.31 | F5: 266580256 | G5: 266580255 | H5: 266580256 | I5: 266580255 | J5: 266580256 | K5: 266580255 | L5: 266580256 | M5: 266580255 | N5: 266580256 | O5: 266580255 | P5: 266580256 | Q5: 266580255
B6: 309577071 | C6: 3 | D6: CIUDAD LIMPIA BOGOTA S.A. ESP. | E6: 0.18 | F6: 154788536 | G6: 154788535 | H6: 154788536 | I6: 154788535 | J6: 154788536 | K6: 154788535 | L6: 154788536 | M6: 154788535 | N6: 154788536 | O6: 154788535 | P6: 154788536 | Q6: 154788535
B7: 240782166 | C7: 4 | D7: BOGOTA LIMPIA S.A.S. ESP. | E7: 0.14 | F7: 120391083 | G7: 120391083 | H7: 120391083 | I7: 120391083 | J7: 120391083 | K7: 120391083 | L7: 120391083 | M7: 120391083 | N7: 120391083 | O7: 120391083 | P7: 120391083 | Q7: 120391083
B8: 257980891 | C8: 5 | D8: AREA LIMPIA DISTRITO CAPITAL S.A.S. ESP. | E8: 0.15 | F8: 128990446 | G8: 128990445 | H8: 128990446 | I8: 128990445 | J8: 128990446 | K8: 128990445 | L8: 128990446 | M8: 128990445 | N8: 128990446 | O8: 128990445 | P8: 128990446 | Q8: 128990445
B9: 1719872614 | D9: TOTAL | E9: 1 | F9: 859936309 | G9: 859936305 | H9: 859936309 | I9: 859936305 | J9: 859936309 | K9: 859936305 | L9: 859936309 | M9: 859936305 | N9: 859936309 | O9: 859936305 | P9: 859936309 | Q9: 859936305
F10: =SUM(F9:G9) -> 1719872614 | H10: =SUM(H9:I9) -> 1719872614 | J10: =SUM(J9:K9) -> 1719872614 | L10: =SUM(L9:M9) -> 1719872614 | N10: =SUM(N9:O9) -> 1719872614 | P10: =SUM(P9:Q9) -> 1719872614
F13: 2026 07 2 | G13: 2026 08 1 | H13: 2026 08 2 | I13: 2026 09 1 | J13: 2026 09 2 | K13: 2026 10 1 | L13: 2026 10 2 | M13: 2026 11 1 | N13: 2026 11 2 | O13: 2026 12 1 | P13: 2026 12 2 | Q13: 2027 01 1
C14: ASE | D14: Concesionarios | E14: % | F14: MITAD 1 // JULIO -26 | G14: MITAD 2 // JULIO -26 | H14: MITAD 1 // AGOSTO -26 | I14: MITAD 2 // AGOSTO -26 | J14: MITAD 1 // SEPTIEMBRE -26 | K14: MITAD 2 // SEPTIEMBRE -26 | L14: MITAD 1 // OCTUBRE -26 | M14: MITAD 2 // OCTUBRE -26 | N14: MITAD 1 // NOVIEMBRE -26 | O14: MITAD 2 // NOVIEMBRE -26 | P14: MITAD 1 // DICIEMBRE -26 | Q14: MITAD 2 // DICIEMBRE -26
C15: 1 | D15: PROMOAMBIENTAL DISTRITO S.A.S. ESP. | E15: 0.22 | F15: 189185988 | G15: 189185987 | H15: 189185988 | I15: 189185987 | J15: 189185988 | K15: 189185987 | L15: 189185988 | M15: 189185987 | N15: 189185988 | O15: 189185987 | P15: 189185988 | Q15: 189185987
C16: 2 | D16: LIMPIEZA METROPOLITANA S.A. ESP. | E16: 0.31 | F16: 266580256 | G16: 266580255 | H16: 266580256 | I16: 266580255 | J16: 266580256 | K16: 266580255 | L16: 266580256 | M16: 266580255 | N16: 266580256 | O16: 266580255 | P16: 266580256 | Q16: 266580255
C17: 3 | D17: CIUDAD LIMPIA BOGOTA S.A. ESP. | E17: 0.18 | F17: 154788536 | G17: 154788535 | H17: 154788536 | I17: 154788535 | J17: 154788536 | K17: 154788535 | L17: 154788536 | M17: 154788535 | N17: 154788536 | O17: 154788535 | P17: 154788536 | Q17: 154788535
C18: 4 | D18: BOGOTA LIMPIA S.A.S. ESP. | E18: 0.14 | F18: 120391083 | G18: 120391083 | H18: 120391083 | I18: 120391083 | J18: 120391083 | K18: 120391083 | L18: 120391083 | M18: 120391083 | N18: 120391083 | O18: 120391083 | P18: 120391083 | Q18: 120391083
C19: 5 | D19: AREA LIMPIA DISTRITO CAPITAL S.A.S. ESP. | E19: 0.15 | F19: 128990446 | G19: 128990445 | H19: 128990446 | I19: 128990445 | J19: 128990446 | K19: 128990445 | L19: 128990446 | M19: 128990445 | N19: 128990446 | O19: 128990445 | P19: 128990446 | Q19: 128990445
D20: TOTAL | E20: 1 | F20: 859936309 | G20: 859936305 | H20: 859936309 | I20: 859936305 | J20: 859936309 | K20: 859936305 | L20: 859936309 | M20: 859936305 | N20: 859936309 | O20: 859936305 | P20: 859936309 | Q20: 859936305
F21: =SUM(F20:G20) -> 1719872614 | G21: 1191383498 | H21: =SUM(H20:I20) -> 1719872614 | I21: 1191383498 | J21: =SUM(J20:K20) -> 1719872614 | K21: 1191383498 | L21: =SUM(L20:M20) -> 1719872614 | M21: 1191383498 | N21: =SUM(N20:O20) -> 1719872614 | O21: 1191383498 | P21: =SUM(P20:Q20) -> 1719872614 | Q21: 1191383498
K25: VALOR OFICIAL MES | L25: ASE | M25: Segunda quincena | N25: Primera quincena | R25: VALIDACION
K26: 378371975 | L26: 1 | M26: 189185988 | N26: 189185987 | O26: =M26=R26 -> FALSE | Q26: ='CONSOLIDADO_TOTAL RECAUDO'!L104 -> 189185987 | R26: =N26 -> 189185987 | S26: =Q26=R26 -> TRUE
K27: 533160511 | L27: 2 | M27: 266580256 | N27: 266580255 | O27: =M27=R27 -> FALSE | Q27: ='CONSOLIDADO_TOTAL RECAUDO'!L105 -> 266580255 | R27: =N27 -> 266580255 | S27: =Q27=R27 -> TRUE
K28: 309577071 | L28: 3 | M28: 154788536 | N28: 154788535 | O28: =M28=R28 -> FALSE | Q28: ='CONSOLIDADO_TOTAL RECAUDO'!L106 -> 154788535 | R28: =N28 -> 154788535 | S28: =Q28=R28 -> TRUE
K29: 240782166 | L29: 4 | M29: 120391083 | N29: 120391083 | O29: =M29=R29 -> TRUE | Q29: ='CONSOLIDADO_TOTAL RECAUDO'!L107 -> 120391083 | R29: =N29 -> 120391083 | S29: =Q29=R29 -> TRUE
K30: 257980891 | L30: 5 | M30: 128990446 | N30: 128990445 | O30: =M30=R30 -> FALSE | Q30: ='CONSOLIDADO_TOTAL RECAUDO'!L108 -> 128990445 | R30: =N30 -> 128990445 | S30: =Q30=R30 -> TRUE
K31: =SUM(K26:K30) -> 1719872614 | M31: =SUM(M26:M30) -> 859936309 | N31: =SUM(N26:N30) -> 859936305 | O31: =M31=R31 -> FALSE | Q31: ='CONSOLIDADO_TOTAL RECAUDO'!L109 -> 859936305 | R31: =N31 -> 859936305 | S31: =Q31=R31 -> TRUE
K32: =SUM(M31:N31) -> 1719872614

Sheet Informe AFaseo Recaudo 202609-1
D5: PROCERASEO S.A.S. | I5: NIT: 901 153 639 - 0 | P5: PROCERASEO S.A.S. | T5: NIT: 901 153 639 - 0
D6: INFORME Afaseo // RECAUDO | P6: INFORME AFaseo
D7: BENEFICIO TRANSITORIO ALIVIO SOBRE EL VALOR DE LA FACTURA | P7: BENEFICIO TRANSITORIO ALIVIO SOBRE EL VALOR DE LA FACTURA
D8: Según Resoluciòn UAESP Número 273 de 2.020 | P8: Según Resoluciòn UAESP Número 273 de 2.020
E10: Fecha Desde: | F10: ='CONSOLIDADO_TOTAL RECAUDO'!G102 -> 46266 | H10: Feha Hasta: | I10: ='CONSOLIDADO_TOTAL RECAUDO'!K102 -> 46280
B11: ASE | C11: Concesionarios | D11: Valor Afaseo | E11: Afaseo por disposicion final | F11: Afaseo por tratamiento de lixiviados | G11: Afaseo por Componente VIAT ( Decreto 2412/2018) | H11: Afaseo por aprovechamiento | I11: Afaseo del componente de comercializacion para Aprovechamiento (11,4%) | J11: Afaseo RBL | N11: ASE | O11: Concesionarios | P11: Tarifa de Comercialización del Servicio. ( TCS) | Q11: Tarifa de Limpieza Urbana del Servicio. ( TLU) | R11: Tarifa de Barrido y Limpieza del Servicio. ( TBL) | S11: Tarifa de Recolección y Transporte del Servicio. (TRT) | T11: Componente de comercialización para Aprovechamiento (18,6%) | U11: Afaseo RBL
B12: 1 | C12: PROMOAMBIENTAL DISTRITO S.A.S. ESP. | D12: ='Reporte Componentes R1'!F119*$D$24 -> 7108.83 | E12: ='Reporte Componentes R1'!G119*$D$24 -> 502.98 | F12: ='Reporte Componentes R1'!H119*$D$24 -> 213.69 | G12: ='Reporte Componentes R1'!I119*$D$24 -> 93.3 | H12: ='Reporte Componentes R1'!J119*$D$24 -> 1231.48 | I12: ='Reporte Componentes R1'!K119*$D$24 -> 79.58 | J12: =D12-E12-F12-G12-H12-I12 -> 4987.8 | N12: 1 | O12: PROMOAMBIENTAL DISTRITO S.A.S. ESP. | P12: ='Reporte Componentes R1'!M119*$P$24 -> 698.02 | Q12: ='Reporte Componentes R1'!N119*$P$24 -> 584.16 | R12: ='Reporte Componentes R1'!O119*$P$24 -> 2331.79 | S12: ='Reporte Componentes R1'!P119*$P$24 -> 1243.99 | T12: ='Reporte Componentes R1'!Q119*$P$24 -> 129.84 | U12: =SUM(P12:T12) -> 4987.8 | V12: =J12-U12 -> 0 | W12: =V12=0 -> TRUE
B13: 2 | C13: LIMPIEZA METROPOLITANA S.A. ESP. | D13: ='Reporte Componentes R1'!F353*$D$24 -> 274771.41 | E13: ='Reporte Componentes R1'!G353*$D$24 -> 24590.67 | F13: ='Reporte Componentes R1'!H353*$D$24 -> 10446.86 | G13: ='Reporte Componentes R1'!I353*$D$24 -> 4562.18 | H13: ='Reporte Componentes R1'!J353*$D$24 -> 54962.58 | I13: ='Reporte Componentes R1'!K353*$D$24 -> 2264.61 | J13: =D13-E13-F13-G13-H13-I13 -> 177944.51 | N13: 2 | O13: LIMPIEZA METROPOLITANA S.A. ESP. | P13: ='Reporte Componentes R1'!M353*$P$24 -> 19865.54 | Q13: ='Reporte Componentes R1'!N353*$P$24 -> 24901.75 | R13: ='Reporte Componentes R1'!O353*$P$24 -> 83643.2 | S13: ='Reporte Componentes R1'!P353*$P$24 -> 45838.96 | T13: ='Reporte Componentes R1'!Q353*$P$24 -> 3695.06 | U13: =SUM(P13:T13) -> 177944.51 | V13: =J13-U13 -> 0 | W13: =V13=0 -> TRUE
B14: 3 | C14: CIUDAD LIMPIA BOGOTA S.A. ESP. | D14: ='Reporte Componentes R1'!F514*$D$24 -> 5649.87 | E14: ='Reporte Componentes R1'!G514*$D$24 -> 501.3 | F14: ='Reporte Componentes R1'!H514*$D$24 -> 212.97 | G14: ='Reporte Componentes R1'!I514*$D$24 -> 93 | H14: ='Reporte Componentes R1'!J514*$D$24 -> 1090.28 | I14: ='Reporte Componentes R1'!K514*$D$24 -> 44.92 | J14: =D14-E14-F14-G14-H14-I14 -> 3707.4 | N14: 3 | O14: CIUDAD LIMPIA BOGOTA S.A. ESP. | P14: ='Reporte Componentes R1'!M514*$P$24 -> 394.01 | Q14: ='Reporte Componentes R1'!N514*$P$24 -> 493.87 | R14: ='Reporte Componentes R1'!O514*$P$24 -> 1658.87 | S14: ='Reporte Componentes R1'!P514*$P$24 -> 1087.36 | T14: ='Reporte Componentes R1'!Q514*$P$24 -> 73.29 | U14: =SUM(P14:T14) -> 3707.4 | V14: =J14-U14 -> 0 | W14: =V14=0 -> TRUE
B15: 4 | C15: BOGOTA LIMPIA S.A.S. ESP. | D15: ='Reporte Componentes R1'!F722*$D$24 -> 45650 | E15: ='Reporte Componentes R1'!G722*$D$24 -> 3731.55 | F15: ='Reporte Componentes R1'!H722*$D$24 -> 1585.29 | G15: ='Reporte Componentes R1'!I722*$D$24 -> 692.31 | H15: ='Reporte Componentes R1'!J722*$D$24 -> 8401.52 | I15: ='Reporte Componentes R1'!K722*$D$24 -> 342.15 | J15: =D15-E15-F15-G15-H15-I15 -> 30897.18 | N15: 4 | O15: BOGOTA LIMPIA S.A.S. ESP. | P15: ='Reporte Componentes R1'!M722*$P$24 -> 3001.2 | Q15: ='Reporte Componentes R1'!N722*$P$24 -> 3816.34 | R15: ='Reporte Componentes R1'!O722*$P$24 -> 14012.94 | S15: ='Reporte Componentes R1'!P722*$P$24 -> 9508.44 | T15: ='Reporte Componentes R1'!Q722*$P$24 -> 558.26 | U15: =SUM(P15:T15) -> 30897.18 | V15: =J15-U15 -> 0 | W15: =V15=0 -> TRUE
B16: 5 | C16: AREA LIMPIA DISTRITO CAPITAL S.A.S. ESP. | D16: ='Reporte Componentes R1'!F841*$D$24 -> 29681.86 | E16: ='Reporte Componentes R1'!G841*$D$24 -> 2042.55 | F16: ='Reporte Componentes R1'!H841*$D$24 -> 867.73 | G16: ='Reporte Componentes R1'!I841*$D$24 -> 378.94 | H16: ='Reporte Componentes R1'!J841*$D$24 -> 5515.52 | I16: ='Reporte Componentes R1'!K841*$D$24 -> 317.57 | J16: =D16-E16-F16-G16-H16-I16 -> 20559.55 | N16: 5 | O16: AREA LIMPIA DISTRITO CAPITAL S.A.S. ESP. | P16: ='Reporte Componentes R1'!M841*$P$24 -> 2785.77 | Q16: ='Reporte Componentes R1'!N841*$P$24 -> 2498.45 | R16: ='Reporte Componentes R1'!O841*$P$24 -> 9132.41 | S16: ='Reporte Componentes R1'!P841*$P$24 -> 5624.76 | T16: ='Reporte Componentes R1'!Q841*$P$24 -> 518.16 | U16: =SUM(P16:T16) -> 20559.55 | V16: =J16-U16 -> 0 | W16: =V16=0 -> TRUE
C17: TOTAL | D17: =SUM(D12:D16) -> 362861.97 | E17: =SUM(E12:E16) -> 31369.05 | F17: =SUM(F12:F16) -> 13326.54 | G17: =SUM(G12:G16) -> 5819.73 | H17: =SUM(H12:H16) -> 71201.38 | I17: =SUM(I12:I16) -> 3048.83 | J17: =SUM(J12:J16) -> 238096.44 | O17: TOTAL | P17: =SUM(P12:P16) -> 26744.54 | Q17: =SUM(Q12:Q16) -> 32294.57 | R17: =SUM(R12:R16) -> 110779.21 | S17: =SUM(S12:S16) -> 63303.51 | T17: =SUM(T12:T16) -> 4974.61 | U17: =SUM(U12:U16) -> 238096.44 | V17: =SUM(V12:V16) -> 0 | W17: =V17=0 -> TRUE
T19: =SUM(P17:T17) -> 238096.44
J20: =+IF(MAX(J12:J17)>500000,"VALIDAR",TRUE) -> TRUE
F21: Firma autorizada
D24: -1 | P24: -1

Sheet CONSOLIDADO_TOTAL RECAUDO
F3: PROCERASEO S.A.S. | I3: NIT: 901 153 639 - 0 | M3: Codigo Remuneración: | N3: 2026091 | U3: PROCERASEO S.A.S. | W3: NIT: 901 153 639 - 0 | AA3: Codigo Remuneración: | AD3: =N3 -> 2026091
F4: 3. ESQUEMA FINANCIERO DEL SERVICIO PUBLICO DE ASEO | U4: 3. ESQUEMA FINANCIERO DEL SERVICIO PUBLICO DE ASEO
F5: Resoluciòn UAESP Número 27 de 2018 | U5: Resoluciòn UAESP Número 27 de 2018
C6: Fecha de Proceso: | D6: 46297 | F6: R1 - RECAUDO OPORTUNO | U6: R1 - RECAUDO OPORTUNO
C7: Hora: | D7: 0.58333333 | F7: Fecha Desde: | G7: 46266 | J7: Feha Hasta: | K7: 46280 | U7: =F7 -> Fecha Desde: | V7: =G7 -> 46266 | X7: =J7 -> Feha Hasta: | Y7: =K7 -> 46280
B8: ASE | C8: Concesionarios | D8: Recaudo Total | E8: Recaudo por disposicion final | F8: Recaudo por tratamiento de lixiviados | G8: Recaudo por Componente VIAT ( Decreto 2412/2018) | H8: Recaudo por aprovechamiento | I8: Recaudo del componente de comercializacion para Aprovechamiento (11,4%) | J8: Balance de subsidio o contribuciones | K8: RECAUDO BASE DE REMUNERACION | L8: Costo de la Interventoría | M8: REMUNERACION FINAL | N8: Conceptos especiales | O8: REMUNERACION FINAL MAS CONCEPTOS ESPECIALES | S8: ASE | T8: Concesionarios | U8: Tarifa de Comercialización del Servicio. ( TCS) | V8: Tarifa de Limpieza Urbana del Servicio. ( TLU) | W8: Tarifa de Barrido y Limpieza del Servicio. ( TBL) | X8: Tarifa de Recolección y Transporte del Servicio. (TRT) | Y8: Recaudo del componente de comercializacion para Aprovechamiento (18,6%) | Z8: Costo de la Interventoría | AA8: Ajuste a la decena | AB8: Conceptos especiales | AC8: Otros | AD8: Diferencial Balance S / C (Fac vs Rec) | AE8: Balance S / C Con Base en (Recaudo) | AF8: REMUNERACION FINAL MAS CONCEPTOS ESPECIALES
B9: 1 | C9: PROMOAMBIENTAL DISTRITO S.A.S. ESP. | D9: ='Reporte Componentes R1'!F89 -> 1.7418907e+10 | E9: ='Reporte Componentes R1'!G89 -> 1.0010823e+09 | F9: ='Reporte Componentes R1'!H89 -> 5.5862411e+08 | G9: ='Reporte Componentes R1'!I89 -> 2.9581886e+08 | H9: ='Reporte Componentes R1'!J89 -> 4.8549813e+09 | I9: ='Reporte Componentes R1'!K89 -> 1.8202342e+08 | J9: ='BCE SC POR FACT.'!F3 -> 2.5893357e+09 | K9: =D9-E9-F9-G9-H9-I9-J9 -> 7.9370418e+09 | L9: =INTERVENTORIA!N26 -> 189185987 | M9: =K9-L9 -> 7.7478558e+09 | N9: ='Reporte Componentes R1'!L89 -> 30635670 | O9: =M9+N9 -> 7.7784914e+09 | S9: 1 | T9: PROMOAMBIENTAL DISTRITO S.A.S. ESP. | U9: ='Reporte Componentes R1'!M89 -> 1.5976825e+09 | V9: ='Reporte Componentes R1'!N89 -> 1.5265528e+09 | W9: ='Reporte Componentes R1'!O89 -> 7.1808775e+09 | X9: ='Reporte Componentes R1'!P89 -> 2.7253469e+09 | Y9: ='Reporte Componentes R1'!Q89 -> 2.970241e+08 | Z9: =L9*-1 -> -189185987 | AA9: ='Reporte Componentes R1'!R89+'Reporte Componentes R1'!U89+'Reporte Componentes R1'!V89 -> -46873.26 | AB9: =N9 -> 30635670 | AC9: ='Reporte Componentes R1'!T89+'Reporte Componentes R1'!W89+'Reporte Componentes R1'!X89+'Reporte Componentes R1'!Y89+'Reporte Componentes R1'!Z89+'Reporte Componentes R1'!S89 -> 392.74 | AD9: =-J9+AE9 -> -5.3903955e+09 | AE9: ='Reporte Componentes R1'!F90 -> -2.8010598e+09 | AF9: =SUM(U9:AD9) -> 7.7784914e+09 | AG9: =(AF9-O9) -> 6.6757202e-06 | AH9: =INT(AG9)=0 -> TRUE
B10: 2 | C10: LIMPIEZA METROPOLITANA S.A. ESP. | D10: ='Reporte Componentes R1'!F323 -> 1.4054409e+10 | E10: ='Reporte Componentes R1'!G323 -> 1.0882025e+09 | F10: ='Reporte Componentes R1'!H323 -> 6.0306981e+08 | G10: ='Reporte Componentes R1'!I323 -> 3.1900917e+08 | H10: ='Reporte Componentes R1'!J323 -> 4.4578076e+09 | I10: ='Reporte Componentes R1'!K323 -> 1.5158627e+08 | J10: ='BCE SC POR FACT.'!F4 -> -5.0932598e+09 | K10: =D10-E10-F10-G10-H10-I10-J10 -> 1.2527993e+10 | L10: =INTERVENTORIA!N27 -> 266580255 | M10: =K10-L10 -> 1.2261413e+10 | N10: ='Reporte Componentes R1'!L323 -> 43591202 | O10: =M10+N10 -> 1.2305004e+10 | S10: 2 | T10: LIMPIEZA METROPOLITANA S.A. ESP. | U10: ='Reporte Componentes R1'!M323 -> 1.3288221e+09 | V10: ='Reporte Componentes R1'!N323 -> 1.3172024e+09 | W10: ='Reporte Componentes R1'!O323 -> 6.1783747e+09 | X10: ='Reporte Componentes R1'!P323 -> 2.1380791e+09 | Y10: ='Reporte Componentes R1'!Q323 -> 2.4778521e+08 | Z10: =L10*-1 -> -266580255 | AA10: ='Reporte Componentes R1'!R323+'Reporte Componentes R1'!U323+'Reporte Componentes R1'!V323 -> 60921.93 | AB10: =N10 -> 43591202 | AC10: ='Reporte Componentes R1'!T323+'Reporte Componentes R1'!W323+'Reporte Componentes R1'!X323+'Reporte Componentes R1'!Y323+'Reporte Componentes R1'!Z323+'Reporte Componentes R1'!S323 -> -56807.54 | AD10: =-J10+AE10 -> 1.3177255e+09 | AE10: ='Reporte Componentes R1'!F324 -> -3.7755343e+09 | AF10: =SUM(U10:AD10) -> 1.2305004e+10 | AG10: =(AF10-O10) -> -1.9073486e-06 | AH10: =INT(AG10)=0 -> FALSE
B11: 3 | C11: CIUDAD LIMPIA BOGOTA S.A. ESP. | D11: ='Reporte Componentes R1'!F484 -> 1.0873712e+10 | E11: ='Reporte Componentes R1'!G484 -> 7.094801e+08 | F11: ='Reporte Componentes R1'!H484 -> 3.9679768e+08 | G11: ='Reporte Componentes R1'!I484 -> 2.1007236e+08 | H11: ='Reporte Componentes R1'!J484 -> 3.0860385e+09 | I11: ='Reporte Componentes R1'!K484 -> 1.0245381e+08 | J11: ='BCE SC POR FACT.'!F5 -> -1.230397e+09 | K11: =D11-E11-F11-G11-H11-I11-J11 -> 7.5992662e+09 | L11: =INTERVENTORIA!N28 -> 154788535 | M11: =K11-L11 -> 7.4444777e+09 | N11: ='Reporte Componentes R1'!L484 -> 25517242 | O11: =M11+N11 -> 7.4699949e+09 | S11: 3 | T11: CIUDAD LIMPIA BOGOTA S.A. ESP. | U11: ='Reporte Componentes R1'!M484 -> 8.9876063e+08 | V11: ='Reporte Componentes R1'!N484 -> 8.790698e+08 | W11: ='Reporte Componentes R1'!O484 -> 4.1378283e+09 | X11: ='Reporte Componentes R1'!P484 -> 1.6799445e+09 | Y11: ='Reporte Componentes R1'!Q484 -> 1.6723142e+08 | Z11: =L11*-1 -> -154788535 | AA11: ='Reporte Componentes R1'!R484+'Reporte Componentes R1'!U484+'Reporte Componentes R1'!V484 -> 46878 | AB11: =N11 -> 25517242 | AC11: ='Reporte Componentes R1'!T484+'Reporte Componentes R1'!W484+'Reporte Componentes R1'!X484+'Reporte Componentes R1'!Y484+'Reporte Componentes R1'!Z484+'Reporte Componentes R1'!S484 -> 5.57 | AD11: =-J11+AE11 -> -1.6361542e+08 | AE11: ='Reporte Componentes R1'!F485 -> -1.3940124e+09 | AF11: =SUM(U11:AD11) -> 7.4699949e+09 | AG11: =(AF11-O11) -> 0.099998474 | AH11: =INT(AG11)=0 -> TRUE
B12: 4 | C12: BOGOTA LIMPIA S.A.S. ESP. | D12: ='Reporte Componentes R1'!F692 -> 1.1499013e+10 | E12: ='Reporte Componentes R1'!G692 -> 6.509964e+08 | F12: ='Reporte Componentes R1'!H692 -> 3.6166457e+08 | G12: ='Reporte Componentes R1'!I692 -> 1.913117e+08 | H12: ='Reporte Componentes R1'!J692 -> 2.8484436e+09 | I12: ='Reporte Componentes R1'!K692 -> 98370577 | J12: ='BCE SC POR FACT.'!F6 -> 38133906 | K12: =D12-E12-F12-G12-H12-I12-J12 -> 7.3100926e+09 | L12: =INTERVENTORIA!N29 -> 120391083 | M12: =K12-L12 -> 7.1897015e+09 | N12: ='Reporte Componentes R1'!L692 -> 23185408 | O12: =M12+N12 -> 7.2128869e+09 | S12: 4 | T12: BOGOTA LIMPIA S.A.S. ESP. | U12: ='Reporte Componentes R1'!M692 -> 8.6252558e+08 | V12: ='Reporte Componentes R1'!N692 -> 8.5027888e+08 | W12: ='Reporte Componentes R1'!O692 -> 4.3346851e+09 | X12: ='Reporte Componentes R1'!P692 -> 1.7232123e+09 | Y12: ='Reporte Componentes R1'!Q692 -> 1.608079e+08 | Z12: =L12*-1 -> -120391083 | AA12: ='Reporte Componentes R1'!R692+'Reporte Componentes R1'!U692+'Reporte Componentes R1'!V692 -> -64274.34 | AB12: =N12 -> 23185408 | AC12: ='Reporte Componentes R1'!T692+'Reporte Componentes R1'!W692+'Reporte Componentes R1'!X692+'Reporte Componentes R1'!Y692+'Reporte Componentes R1'!Z692+'Reporte Componentes R1'!S692 -> 181.07 | AD12: =-J12+AE12 -> -6.2135311e+08 | AE12: ='Reporte Componentes R1'!F693 -> -5.832192e+08 | AF12: =SUM(U12:AD12) -> 7.2128869e+09 | AG12: =(AF12-O12) -> -1.9073486e-06 | AH12: =INT(AG12)=0 -> FALSE
B13: 5 | C13: AREA LIMPIA DISTRITO CAPITAL S.A.S. ESP. | D13: ='Reporte Componentes R1'!F811 -> 9.1286743e+09 | E13: ='Reporte Componentes R1'!G811 -> 4.9999386e+08 | F13: ='Reporte Componentes R1'!H811 -> 2.7929527e+08 | G13: ='Reporte Componentes R1'!I811 -> 1.4792873e+08 | H13: ='Reporte Componentes R1'!J811 -> 2.0955676e+09 | I13: ='Reporte Componentes R1'!K811 -> 75251314 | J13: ='BCE SC POR FACT.'!F7 -> -1.2241007e+09 | K13: =D13-E13-F13-G13-H13-I13-J13 -> 7.2547382e+09 | L13: =INTERVENTORIA!N30 -> 128990445 | M13: =K13-L13 -> 7.1257478e+09 | N13: ='Reporte Componentes R1'!L811 -> 32575938 | O13: =M13+N13 -> 7.1583237e+09 | S13: 5 | T13: AREA LIMPIA DISTRITO CAPITAL S.A.S. ESP. | U13: ='Reporte Componentes R1'!M811 -> 6.6045214e+08 | V13: ='Reporte Componentes R1'!N811 -> 6.4266044e+08 | W13: ='Reporte Componentes R1'!O811 -> 3.2982859e+09 | X13: ='Reporte Componentes R1'!P811 -> 1.4970148e+09 | Y13: ='Reporte Componentes R1'!Q811 -> 1.2287348e+08 | Z13: =L13*-1 -> -128990445 | AA13: ='Reporte Componentes R1'!R811+'Reporte Componentes R1'!U811+'Reporte Componentes R1'!V811 -> -16285.89 | AB13: =N13 -> 32575938 | AC13: ='Reporte Componentes R1'!T811+'Reporte Componentes R1'!W811+'Reporte Componentes R1'!X811+'Reporte Componentes R1'!Y811+'Reporte Componentes R1'!Z811+'Reporte Componentes R1'!S811 -> -105.68 | AD13: =-J13+AE13 -> 1.0334679e+09 | AE13: ='Reporte Componentes R1'!F812 -> -1.9063282e+08 | AF13: =SUM(U13:AD13) -> 7.1583237e+09 | AG13: =(AF13-O13) -> -9.5367432e-07 | AH13: =INT(AG13)=0 -> FALSE
C14: TOTAL | D14: =SUM(D9:D13) -> 6.2974715e+10 | E14: =SUM(E9:E13) -> 3.9497551e+09 | F14: =SUM(F9:F13) -> 2.1994514e+09 | G14: =SUM(G9:G13) -> 1.1641408e+09 | H14: =SUM(H9:H13) -> 1.7342839e+10 | I14: =SUM(I9:I13) -> 6.0968539e+08 | J14: =SUM(J9:J13) -> -4.9202879e+09 | K14: =SUM(K9:K13) -> 4.2629132e+10 | ... O14: =SUM(O9:O13) -> 4.1924701e+10 | T14: TOTAL | U14: =SUM(U9:U13) -> 5.348243e+09 | V14: =SUM(V9:V13) -> 5.2157643e+09 | W14: =SUM(W9:W13) -> 2.5130052e+10 | X14: =SUM(X9:X13) -> 9.7635977e+09 | Y14: =SUM(Y9:Y13) -> 9.9572211e+08 | Z14: =SUM(Z9:Z13) -> -859936305 | AA14: =SUM(AA9:AA13) -> -19633.56 | AB14: =SUM(AB9:AB13) -> 1.5550546e+08 | ... AG14: =SUM(AG9:AG13) -> 0.10000038 | AH14: =INT(AG14)=0 -> TRUE
Y16: =SUM(U14:Y14) -> 4.6453379e+10
F18: Firma autorizada
F22: PROCERASEO S.A.S. | I22: NIT: 901 153 639 - 0 | M22: Codigo Remuneración: | N22: =N3 -> 2026091 | U22: PROCERASEO S.A.S. | W22: NIT: 901 153 639 - 0 | AA22: Codigo Remuneración: | AD22: =N22 -> 2026091
F23: 3. ESQUEMA FINANCIERO DEL SERVICIO PUBLICO DE ASEO | U23: 3. ESQUEMA FINANCIERO DEL SERVICIO PUBLICO DE ASEO
F24: Resoluciòn UAESP Número 27 de 2018 | U24: Resoluciòn UAESP Número 27 de 2018
C25: Fecha de Proceso: | D25: =D6 -> 46297 | F25: R2 - ANTICIPOS A USUARIOS | U25: R2 - ANTICIPOS A USUARIOS
C26: Hora: | D26: =D7 -> 0.58333333 | F26: Fecha Desde: | G26: =G7 -> 46266 | J26: Feha Hasta: | K26: =K7 -> 46280 | U26: =F26 -> Fecha Desde: | V26: =G26 -> 46266 | X26: =J26 -> Feha Hasta: | Y26: =K26 -> 46280
B27: ASE | C27: Concesionarios | D27: Recaudo Total | E27: Recaudo por disposicion final | F27: Recaudo por tratamiento de lixiviados | G27: Recaudo por Componente VIAT ( Decreto 2412/2018) | H27: Recaudo por aprovechamiento | I27: Recaudo del componente de comercializacion para Aprovechamiento (11,4%) | J27: Balance de subsidio o contribuciones | K27: RECAUDO BASE DE REMUNERACION | L27: Costo de la Interventoría | M27: REMUNERACION FINAL | N27: Conceptos especiales | O27: REMUNERACION FINAL MAS CONCEPTOS ESPECIALES | S27: ASE | T27: Concesionarios | U27: Tarifa de Comercialización del Servicio. ( TCS) | V27: Tarifa de Limpieza Urbana del Servicio. ( TLU) | W27: Tarifa de Barrido y Limpieza del Servicio. ( TBL) | X27: Tarifa de Recolección y Transporte del Servicio. (TRT) | Y27: Recaudo del componente de comercializacion para Aprovechamiento (18,6%) | Z27: Costo de la Interventoría | AA27: Ajuste a la decena | AB27: Conceptos especiales | AC27: Otros | AD27: Diferencial Balance S / C (Fac vs Rec) | AE27: Balance S / C Con Base en (Recaudo) | AF27: REMUNERACION FINAL MAS CONCEPTOS ESPECIALES
B28: 1 | C28: PROMOAMBIENTAL DISTRITO S.A.S. ESP. | D28: ='Rem. Anticipos R2'!E57 -> 34844954 | E28: ='Rem. Anticipos R2'!F57 -> 1865211.3 | F28: ='Rem. Anticipos R2'!G57 -> 1005487.3 | G28: ='Rem. Anticipos R2'!H57 -> 583812.15 | H28: ='Rem. Anticipos R2'!I57 -> 5020392.6 | I28: ='Rem. Anticipos R2'!J57 -> 230375.08 | J28: 0 | K28: =D28-E28-F28-G28-H28-I28-J28 -> 26139676 | L28: 0 | M28: =K28-L28 -> 26139676 | N28: ='Rem. Anticipos R2'!K57 -> 0 | O28: =M28+N28 -> 26139676 | S28: 1 | T28: PROMOAMBIENTAL DISTRITO S.A.S. ESP. | U28: ='Rem. Anticipos R2'!L57 -> 2507180.1 | V28: ='Rem. Anticipos R2'!M57 -> 2526384.8 | W28: ='Rem. Anticipos R2'!N57 -> 12951452 | X28: ='Rem. Anticipos R2'!O57 -> 5510056 | Y28: ='Rem. Anticipos R2'!P57 -> 369962.63 | Z28: =L28*-1 -> 0 | AA28: ='Rem. Anticipos R2'!Q57 -> -21.97 | AB28: =N28 -> 0 | AC28: ='Rem. Anticipos R2'!R57 -> 0 | AD28: =-J28+AE28 -> 2274662.1 | AE28: ='Rem. Anticipos R2'!E58 -> 2274662.1 | AF28: =SUM(U28:AD28) -> 26139676 | AG28: =(AF28-O28) -> -7.4505806e-09 | AH28: =INT(AG28)=0 -> FALSE
B29: 2 | C29: LIMPIEZA METROPOLITANA S.A. ESP. | D29: ='Rem. Anticipos R2'!E178 -> 1.016621e+08 | E29: ='Rem. Anticipos R2'!F178 -> 8605592.6 | F29: ='Rem. Anticipos R2'!G178 -> 4936937 | G29: ='Rem. Anticipos R2'!H178 -> 1904352.2 | H29: ='Rem. Anticipos R2'!I178 -> 30991476 | I29: ='Rem. Anticipos R2'!J178 -> 1003353.5 | J29: 0 | K29: =D29-E29-F29-G29-H29-I29-J29 -> 54220387 | L29: 0 | M29: =K29-L29 -> 54220387 | N29: ='Rem. Anticipos R2'!K178 -> 51372.12 | O29: =M29+N29 -> 54271759 | S29: 2 | T29: LIMPIEZA METROPOLITANA S.A. ESP. | U29: ='Rem. Anticipos R2'!L178 -> 10643669 | V29: ='Rem. Anticipos R2'!M178 -> 9614716.1 | W29: ='Rem. Anticipos R2'!N178 -> 40202706 | X29: ='Rem. Anticipos R2'!O178 -> 17542860 | Y29: ='Rem. Anticipos R2'!P178 -> 1379320.4 | Z29: =L29*-1 -> 0 | AA29: ='Rem. Anticipos R2'!Q178 -> 497.4 | AB29: =N29 -> 51372.12 | AC29: ='Rem. Anticipos R2'!R178 -> 0 | AD29: =-J29+AE29 -> -25163382 | AE29: ='Rem. Anticipos R2'!E179 -> -25163382 | AF29: =SUM(U29:AD29) -> 54271759 | AG29: =(AF29-O29) -> 1.4901161e-08 | AH29: =INT(AG29)=0 -> TRUE
B30: 3 | C30: CIUDAD LIMPIA BOGOTA S.A. ESP. | D30: ='Rem. Anticipos R2'!E299 -> 23583927 | E30: ='Rem. Anticipos R2'!F299 -> 1547938 | F30: ='Rem. Anticipos R2'!G299 -> 861396.51 | G30: ='Rem. Anticipos R2'!H299 -> 389140.56 | H30: ='Rem. Anticipos R2'!I299 -> 5713748.3 | I30: ='Rem. Anticipos R2'!J299 -> 195637.95 | J30: 0 | K30: =D30-E30-F30-G30-H30-I30-J30 -> 14876066 | L30: 0 | M30: =K30-L30 -> 14876066 | N30: ='Rem. Anticipos R2'!K299 -> 45286.42 | O30: =M30+N30 -> 14921353 | S30: 3 | T30: CIUDAD LIMPIA BOGOTA S.A. ESP. | U30: ='Rem. Anticipos R2'!L299 -> 2152729 | V30: ='Rem. Anticipos R2'!M299 -> 1674276.1 | W30: ='Rem. Anticipos R2'!N299 -> 7520400.5 | X30: ='Rem. Anticipos R2'!O299 -> 4675829.6 | Y30: ='Rem. Anticipos R2'!P299 -> 285203.72 | Z30: =L30*-1 -> 0 | AA30: ='Rem. Anticipos R2'!Q299 -> -187.1 | AB30: =N30 -> 45286.42 | AC30: ='Rem. Anticipos R2'!R299 -> 0 | AD30: =-J30+AE30 -> -1432185.7 | AE30: ='Rem. Anticipos R2'!E300 -> -1432185.7 | AF30: =SUM(U30:AD30) -> 14921353 | AG30: =(AF30-O30) -> 3.7252903e-09 | AH30: =INT(AG30)=0 -> TRUE
B31: 4 | C31: BOGOTA LIMPIA S.A.S. ESP. | D31: ='Rem. Anticipos R2'!E423 -> 23548210 | E31: ='Rem. Anticipos R2'!F423 -> 1470007.4 | F31: ='Rem. Anticipos R2'!G423 -> 836215.45 | G31: ='Rem. Anticipos R2'!H423 -> 336141.94 | H31: ='Rem. Anticipos R2'!I423 -> 5278546.5 | I31: ='Rem. Anticipos R2'!J423 -> 193637.28 | J31: 0 | K31: =D31-E31-F31-G31-H31-I31-J31 -> 15433662 | L31: 0 | M31: =K31-L31 -> 15433662 | N31: ='Rem. Anticipos R2'!K423 -> 0 | O31: =M31+N31 -> 15433662 | S31: 4 | T31: BOGOTA LIMPIA S.A.S. ESP. | U31: ='Rem. Anticipos R2'!L423 -> 2124229.1 | V31: ='Rem. Anticipos R2'!M423 -> 1645599 | W31: ='Rem. Anticipos R2'!N423 -> 7267809.3 | X31: ='Rem. Anticipos R2'!O423 -> 4237012.9 | Y31: ='Rem. Anticipos R2'!P423 -> 279286.86 | Z31: =L31*-1 -> 0 | AA31: ='Rem. Anticipos R2'!Q423 -> -108.3 | AB31: =N31 -> 0 | AC31: ='Rem. Anticipos R2'!R423 -> 0 | AD31: =-J31+AE31 -> -120167.08 | AE31: ='Rem. Anticipos R2'!E424 -> -120167.08 | AF31: =SUM(U31:AD31) -> 15433662 | AG31: =(AF31-O31) -> -3.7252903e-09 | AH31: =INT(AG31)=0 -> FALSE
B32: 5 | C32: AREA LIMPIA DISTRITO CAPITAL S.A.S. ESP. | D32: ='Rem. Anticipos R2'!E510 -> 27520061 | E32: ='Rem. Anticipos R2'!F510 -> 1572950.5 | F32: ='Rem. Anticipos R2'!G510 -> 893114.93 | G32: ='Rem. Anticipos R2'!H510 -> 439698.34 | H32: ='Rem. Anticipos R2'!I510 -> 6421366.7 | I32: ='Rem. Anticipos R2'!J510 -> 208412.06 | J32: 0 | K32: =D32-E32-F32-G32-H32-I32-J32 -> 17984518 | L32: 0 | M32: =K32-L32 -> 17984518 | N32: ='Rem. Anticipos R2'!K510 -> 0 | O32: =M32+N32 -> 17984518 | S32: 5 | T32: AREA LIMPIA DISTRITO CAPITAL S.A.S. ESP. | U32: ='Rem. Anticipos R2'!L510 -> 1987677.6 | V32: ='Rem. Anticipos R2'!M510 -> 1803263.4 | W32: ='Rem. Anticipos R2'!N510 -> 8986120.5 | X32: ='Rem. Anticipos R2'!O510 -> 4947370 | Y32: ='Rem. Anticipos R2'!P510 -> 335190.24 | Z32: =L32*-1 -> 0 | AA32: ='Rem. Anticipos R2'!Q510 -> -244.14 | AB32: =N32 -> 0 | AC32: ='Rem. Anticipos R2'!R510 -> 0 | AD32: =-J32+AE32 -> -74859.4 | AE32: ='Rem. Anticipos R2'!E511 -> -74859.4 | AF32: =SUM(U32:AD32) -> 17984518 | AG32: =(AF32-O32) -> -3.7252903e-09 | AH32: =INT(AG32)=0 -> FALSE
C33: TOTAL | D33: =SUM(D28:D32) -> 2.1115925e+08 | E33: =SUM(E28:E32) -> 15061700 | F33: =SUM(F28:F32) -> 8533151.2 | G33: =SUM(G28:G32) -> 3653145.1 | H33: =SUM(H28:H32) -> 53425530 | I33: =SUM(I28:I32) -> 1831415.9 | J33: =SUM(J28:J32) -> 0 | K33: =SUM(K28:K32) -> 1.2865431e+08 | ... O33: =SUM(O28:O32) -> 1.2875097e+08 | T33: TOTAL | U33: =SUM(U28:U32) -> 19415484 | V33: =SUM(V28:V32) -> 17264239 | W33: =SUM(W28:W32) -> 76928489 | X33: =SUM(X28:X32) -> 36913129 | Y33: =SUM(Y28:Y32) -> 2648963.8 | Z33: =SUM(Z28:Z32) -> 0 | AA33: =SUM(AA28:AA32) -> -64.11 | AB33: =SUM(AB28:AB32) -> 96658.54 | ... AG33: =SUM(AG28:AG32) -> 3.7252903e-09 | AH33: =INT(AG33)=0 -> TRUE
Y35: =SUM(U33:Y33) -> 1.5317031e+08
F37: Firma autorizada
F41: PROCERASEO S.A.S. | I41: NIT: 901 153 639 - 0 | M41: Codigo Remuneración: | N41: =N3 -> 2026091 | U41: PROCERASEO S.A.S. | W41: NIT: 901 153 639 - 0 | AA41: Codigo Remuneración: | AD41: =N41 -> 2026091
F42: 3. ESQUEMA FINANCIERO DEL SERVICIO PUBLICO DE ASEO | U42: 3. ESQUEMA FINANCIERO DEL SERVICIO PUBLICO DE ASEO
F43: Resoluciòn UAESP Número 27 de 2018 | U43: Resoluciòn UAESP Número 27 de 2018
C44: Fecha de Proceso: | D44: =D6 -> 46297 | F44: R3 - RECAUDO EXTEMPORANEO | U44: R3 - RECAUDO EXTEMPORANEO
C45: Hora: | D45: =D7 -> 0.58333333 | F45: Fecha Desde: | G45: =G7 -> 46266 | J45: Feha Hasta: | K45: =K7 -> 46280 | U45: =F45 -> Fecha Desde: | V45: =G45 -> 46266 | X45: =J45 -> Feha Hasta: | Y45: =K45 -> 46280
B46: ASE | C46: Concesionarios | D46: Recaudo Total | E46: Recaudo por disposicion final | F46: Recaudo por tratamiento de lixiviados | G46: Recaudo por Componente VIAT ( Decreto 2412/2018) | H46: Recaudo por aprovechamiento | I46: Recaudo del componente de comercializacion para Aprovechamiento (11,4%) | J46: Balance de subsidio o contribuciones | K46: RECAUDO BASE DE REMUNERACION | L46: Costo de la Interventoría | M46: REMUNERACION FINAL | N46: Conceptos especiales | O46: REMUNERACION FINAL MAS CONCEPTOS ESPECIALES | S46: ASE | T46: Concesionarios | U46: Tarifa de Comercialización del Servicio. ( TCS) | V46: Tarifa de Limpieza Urbana del Servicio. ( TLU) | W46: Tarifa de Barrido y Limpieza del Servicio. ( TBL) | X46: Tarifa de Recolección y Transporte del Servicio. (TRT) | Y46: Recaudo del componente de comercializacion para Aprovechamiento (18,6%) | Z46: Costo de la Interventoría | AA46: Ajuste a la decena | AB46: Conceptos especiales | AC46: Otros | AD46: Diferencial Balance S / C (Fac vs Rec) | AE46: Balance S / C Con Base en (Recaudo) | AF46: REMUNERACION FINAL MAS CONCEPTOS ESPECIALES
B47: 1 | C47: PROMOAMBIENTAL DISTRITO S.A.S. ESP. | D47: ='Reporte Componentes R1'!F91 -> 42680 | E47: ='Reporte Componentes R1'!G91 -> 2083.94 | F47: ='Reporte Componentes R1'!H91 -> 1161.16 | G47: ='Reporte Componentes R1'!I91 -> 617.56 | H47: ='Reporte Componentes R1'!J91 -> 10417.41 | I47: ='Reporte Componentes R1'!K91 -> 383.09 | J47: 0 | K47: =D47-E47-F47-G47-H47-I47-J47 -> 28016.84 | L47: 0 | M47: =K47-L47 -> 28016.84 | N47: ='Reporte Componentes R1'!L91 -> 0 | O47: =M47+N47 -> 28016.84 | S47: 1 | T47: PROMOAMBIENTAL DISTRITO S.A.S. ESP. | U47: ='Reporte Componentes R1'!M91 -> 3360.38 | V47: ='Reporte Componentes R1'!N91 -> 3220.93 | W47: ='Reporte Componentes R1'!O91 -> 15119.8 | X47: ='Reporte Componentes R1'!P91 -> 5691.76 | Y47: ='Reporte Componentes R1'!Q91 -> 625.03 | Z47: =-L47 -> 0 | AA47: ='Reporte Componentes R1'!R91+'Reporte Componentes R1'!V91+'Reporte Componentes R1'!U91 -> -1.06 | AB47: =N47 -> 0 | AC47: ='Reporte Componentes R1'!T91+'Reporte Componentes R1'!W91+'Reporte Componentes R1'!X91+'Reporte Componentes R1'!Y91+'Reporte Componentes R1'!Z91+'Reporte Componentes R1'!S91 -> 0 | AD47: =-J47+AE47 -> 0 | AE47: ='Reporte Componentes R1'!F92 -> 0 | AF47: =SUM(U47:AD47) -> 28016.84 | AG47: =(AF47-O47) -> 3.6379788e-12 | AH47: =INT(AG47)=0 -> TRUE
B48: 2 | C48: LIMPIEZA METROPOLITANA S.A. ESP. | D48: ='Reporte Componentes R1'!F325 -> 0 | E48: ='Reporte Componentes R1'!G325 -> 0 | F48: ='Reporte Componentes R1'!H325 -> 0 | G48: ='Reporte Componentes R1'!I325 -> 0 | H48: ='Reporte Componentes R1'!J325 -> 0 | I48: ='Reporte Componentes R1'!K325 -> 0 | J48: 0 | K48: =D48-E48-F48-G48-H48-I48-J48 -> 0 | L48: 0 | M48: =K48-L48 -> 0 | N48: ='Reporte Componentes R1'!L325 -> 0 | O48: =M48+N48 -> 0 | S48: 2 | T48: LIMPIEZA METROPOLITANA S.A. ESP. | U48: ='Reporte Componentes R1'!M325 -> 0 | V48: ='Reporte Componentes R1'!N325 -> 0 | W48: ='Reporte Componentes R1'!O325 -> 0 | X48: ='Reporte Componentes R1'!P325 -> 0 | Y48: ='Reporte Componentes R1'!Q325 -> 0 | Z48: =-L48 -> 0 | AA48: ='Reporte Componentes R1'!R325+'Reporte Componentes R1'!V325+'Reporte Componentes R1'!U325 -> 0 | AB48: =N48 -> 0 | AC48: ='Reporte Componentes R1'!T325+'Reporte Componentes R1'!W325+'Reporte Componentes R1'!X325+'Reporte Componentes R1'!Y325+'Reporte Componentes R1'!Z325+'Reporte Componentes R1'!S325 -> 0 | AD48: =-J48+AE48 -> 0 | AE48: ='Reporte Componentes R1'!F326 -> 0 | AF48: =SUM(U48:AD48) -> 0 | AG48: =(AF48-O48) -> 0 | AH48: =INT(AG48)=0 -> TRUE
B49: 3 | C49: CIUDAD LIMPIA BOGOTA S.A. ESP. | D49: ='Reporte Componentes R1'!F486 -> 169120 | E49: ='Reporte Componentes R1'!G486 -> 9182.42 | F49: ='Reporte Componentes R1'!H486 -> 5162.64 | G49: ='Reporte Componentes R1'!I486 -> 2721.2 | H49: ='Reporte Componentes R1'!J486 -> 52890.57 | I49: ='Reporte Componentes R1'!K486 -> 1377.07 | J49: 0 | K49: =D49-E49-F49-G49-H49-I49-J49 -> 97786.1 | L49: 0 | M49: =K49-L49 -> 97786.1 | N49: ='Reporte Componentes R1'!L486 -> 0 | O49: =M49+N49 -> 97786.1 | S49: 3 | T49: CIUDAD LIMPIA BOGOTA S.A. ESP. | U49: ='Reporte Componentes R1'!M486 -> 12079.7 | V49: ='Reporte Componentes R1'!N486 -> 16023.47 | W49: ='Reporte Componentes R1'!O486 -> 75525.46 | X49: ='Reporte Componentes R1'!P486 -> 21576.6 | Y49: ='Reporte Componentes R1'!Q486 -> 2246.83 | Z49: =-L49 -> 0 | AA49: ='Reporte Componentes R1'!R486+'Reporte Componentes R1'!V486+'Reporte Componentes R1'!U486 -> -4.89 | AB49: =N49 -> 0 | AC49: ='Reporte Componentes R1'!T486+'Reporte Componentes R1'!W486+'Reporte Componentes R1'!X486+'Reporte Componentes R1'!Y486+'Reporte Componentes R1'!Z486+'Reporte Componentes R1'!S486 -> 0 | AD49: =-J49+AE49 -> -29661.07 | AE49: ='Reporte Componentes R1'!F487 -> -29661.07 | AF49: =SUM(U49:AD49) -> 97786.1 | AG49: =(AF49-O49) -> 5.8207661e-11 | AH49: =INT(AG49)=0 -> TRUE
B50: 4 | C50: BOGOTA LIMPIA S.A.S. ESP. | D50: ='Reporte Componentes R1'!F694 -> 8635714 | E50: ='Reporte Componentes R1'!G694 -> 521617.57 | F50: ='Reporte Componentes R1'!H694 -> 295276.31 | G50: ='Reporte Componentes R1'!I694 -> 158970.97 | H50: ='Reporte Componentes R1'!J694 -> 1910496.6 | I50: ='Reporte Componentes R1'!K694 -> 53118.02 | J50: 0 | K50: =D50-E50-F50-G50-H50-I50-J50 -> 5696234.5 | L50: 0 | M50: =K50-L50 -> 5696234.5 | N50: ='Reporte Componentes R1'!L694 -> 0 | O50: =M50+N50 -> 5696234.5 | S50: 4 | T50: BOGOTA LIMPIA S.A.S. ESP. | U50: ='Reporte Componentes R1'!M694 -> 465949.63 | V50: ='Reporte Componentes R1'!N694 -> 593731.16 | W50: ='Reporte Componentes R1'!O694 -> 3012620.8 | X50: ='Reporte Componentes R1'!P694 -> 1391475 | Y50: ='Reporte Componentes R1'!Q694 -> 87879.79 | Z50: =-L50 -> 0 | AA50: ='Reporte Componentes R1'!R694+'Reporte Componentes R1'!V694+'Reporte Componentes R1'!U694 -> -15.83 | AB50: =N50 -> 0 | AC50: ='Reporte Componentes R1'!T694+'Reporte Componentes R1'!W694+'Reporte Componentes R1'!X694+'Reporte Componentes R1'!Y694+'Reporte Componentes R1'!Z694+'Reporte Componentes R1'!S694 -> 0 | AD50: =-J50+AE50 -> 144593.98 | AE50: ='Reporte Componentes R1'!F695 -> 144593.98 | AF50: =SUM(U50:AD50) -> 5696234.5 | AG50: =(AF50-O50) -> 0 | AH50: =INT(AG50)=0 -> TRUE
B51: 5 | C51: AREA LIMPIA DISTRITO CAPITAL S.A.S. ESP. | D51: ='Reporte Componentes R1'!F813 -> 61140 | E51: ='Reporte Componentes R1'!G813 -> 2566.43 | F51: ='Reporte Componentes R1'!H813 -> 1430.01 | G51: ='Reporte Componentes R1'!I813 -> 760.56 | H51: ='Reporte Componentes R1'!J813 -> 11744.12 | I51: ='Reporte Componentes R1'!K813 -> 584.9 | J51: 0 | K51: =D51-E51-F51-G51-H51-I51-J51 -> 44053.98 | L51: 0 | M51: =K51-L51 -> 44053.98 | N51: ='Reporte Componentes R1'!L813 -> 0 | O51: =M51+N51 -> 44053.98 | S51: 5 | T51: AREA LIMPIA DISTRITO CAPITAL S.A.S. ESP. | U51: ='Reporte Componentes R1'!M813 -> 5130.67 | V51: ='Reporte Componentes R1'!N813 -> 5018.9 | W51: ='Reporte Componentes R1'!O813 -> 25484.97 | X51: ='Reporte Componentes R1'!P813 -> 7649.02 | Y51: ='Reporte Componentes R1'!Q813 -> 954.31 | Z51: =-L51 -> 0 | AA51: ='Reporte Componentes R1'!R813+'Reporte Componentes R1'!V813+'Reporte Componentes R1'!U813 -> -4.74 | AB51: =N51 -> 0 | AC51: ='Reporte Componentes R1'!T813+'Reporte Componentes R1'!W813+'Reporte Componentes R1'!X813+'Reporte Componentes R1'!Y813+'Reporte Componentes R1'!Z813+'Reporte Componentes R1'!S813 -> 0 | AD51: =-J51+AE51 -> -179.15 | AE51: ='Reporte Componentes R1'!F814 -> -179.15 | AF51: =SUM(U51:AD51) -> 44053.98 | AG51: =(AF51-O51) -> 0 | AH51: =INT(AG51)=0 -> TRUE
C52: TOTAL | D52: =SUM(D47:D51) -> 8908654 | E52: =SUM(E47:E51) -> 535450.36 | F52: =SUM(F47:F51) -> 303030.12 | G52: =SUM(G47:G51) -> 163070.29 | H52: =SUM(H47:H51) -> 1985548.7 | I52: =SUM(I47:I51) -> 55463.08 | J52: =SUM(J47:J51) -> 0 | K52: =SUM(K47:K51) -> 5866091.4 | ... O52: =SUM(O47:O51) -> 5866091.4 | T52: TOTAL | U52: =SUM(U47:U51) -> 486520.38 | V52: =SUM(V47:V51) -> 617994.46 | W52: =SUM(W47:W51) -> 3128751 | X52: =SUM(X47:X51) -> 1426392.4 | Y52: =SUM(Y47:Y51) -> 91705.96 | Z52: =SUM(Z47:Z51) -> 0 | AA52: =SUM(AA47:AA51) -> -26.52 | AB52: =SUM(AB47:AB51) -> 0 | ... AG52: =SUM(AG47:AG51) -> 6.184564e-11 | AH52: =INT(AG52)=0 -> TRUE
Y54: =SUM(U52:Y52) -> 5751364.2
F56: Firma autorizada
F60: PROCERASEO S.A.S. | I60: NIT: 901 153 639 - 0 | M60: Codigo Remuneración: | N60: =N3 -> 2026091 | U60: PROCERASEO S.A.S. | W60: NIT: 901 153 639 - 0 | AA60: Codigo Remuneración: | AD60: =N60 -> 2026091
F61: 3. ESQUEMA FINANCIERO DEL SERVICIO PUBLICO DE ASEO | U61: 3. ESQUEMA FINANCIERO DEL SERVICIO PUBLICO DE ASEO
F62: Resoluciòn UAESP Número 27 de 2018 | U62: Resoluciòn UAESP Número 27 de 2018
C63: Fecha de Proceso: | D63: =D6 -> 46297 | F63: R4 - REVERSIÓN DE PAGOS | U63: R4 - REVERSIÓN DE PAGOS
C64: Hora: | D64: =D7 -> 0.58333333 | F64: Fecha Desde: | G64: =G7 -> 46266 | J64: Feha Hasta: | K64: =K7 -> 46280 | U64: =F64 -> Fecha Desde: | V64: =G64 -> 46266 | X64: =J64 -> Feha Hasta: | Y64: =K64 -> 46280
B65: ASE | C65: Concesionarios | D65: Recaudo Total | E65: Recaudo por disposicion final | F65: Recaudo por tratamiento de lixiviados | G65: Recaudo por Componente VIAT ( Decreto 2412/2018) | H65: Recaudo por aprovechamiento | I65: Recaudo del componente de comercializacion para Aprovechamiento (11,4%) | J65: Balance de subsidio o contribuciones | K65: RECAUDO BASE DE REMUNERACION | L65: Costo de la Interventoría | M65: REMUNERACION FINAL | N65: Conceptos especiales | O65: REMUNERACION FINAL MAS CONCEPTOS ESPECIALES | S65: ASE | T65: Concesionarios | U65: Tarifa de Comercialización del Servicio. ( TCS) | V65: Tarifa de Limpieza Urbana del Servicio. ( TLU) | W65: Tarifa de Barrido y Limpieza del Servicio. ( TBL) | X65: Tarifa de Recolección y Transporte del Servicio. (TRT) | Y65: Recaudo del componente de comercializacion para Aprovechamiento (18,6%) | Z65: Costo de la Interventoría | AA65: Ajuste a la decena | AB65: Conceptos especiales | AC65: Otros | AD65: Diferencial Balance S / C (Fac vs Rec) | AE65: Balance S / C Con Base en (Recaudo) | AF65: REMUNERACION FINAL MAS CONCEPTOS ESPECIALES
B66: 1 | C66: PROMOAMBIENTAL DISTRITO S.A.S. ESP. | D66: ='Reversion Pagos R4'!D79 -> -3544507.3 | E66: ='Reversion Pagos R4'!E79 -> -219031.92 | F66: ='Reversion Pagos R4'!F79 -> -117594.76 | G66: ='Reversion Pagos R4'!G79 -> -63004.75 | H66: ='Reversion Pagos R4'!H79 -> -1190187.4 | I66: ='Reversion Pagos R4'!I79 -> -45698.67 | J66: 0 | K66: =D66-E66-F66-G66-H66-I66-J66 -> -1908989.8 | L66: 0 | M66: =K66-L66 -> -1908989.8 | N66: ='Reversion Pagos R4'!P79 -> 0 | O66: =M66+N66 -> -1908989.8 | S66: 1 | T66: PROMOAMBIENTAL DISTRITO S.A.S. ESP. | U66: ='Reversion Pagos R4'!J79 -> -400863.96 | V66: ='Reversion Pagos R4'!K79 -> -377006.7 | W66: ='Reversion Pagos R4'!L79 -> -1788474 | X66: ='Reversion Pagos R4'!M79 -> -573353.78 | Y66: ='Reversion Pagos R4'!N79 -> -73936.2 | Z66: =-L66 -> 0 | AA66: ='Reversion Pagos R4'!O79 -> 10.66 | AB66: =N66 -> 0 | AC66: =+'Reversion Pagos R4'!Q79+'Reversion Pagos R4'!R79 -> 0 | AD66: =-J66+AE66 -> 1304634.2 | AE66: ='Reversion Pagos R4'!D80 -> 1304634.2 | AF66: =SUM(U66:AD66) -> -1908989.8 | AG66: =(AF66-O66) -> 0 | AH66: =INT(AG66)=0 -> TRUE
B67: 2 | C67: LIMPIEZA METROPOLITANA S.A. ESP. | D67: ='Reversion Pagos R4'!D180 -> -8713102.4 | E67: ='Reversion Pagos R4'!E180 -> -566211.7 | F67: ='Reversion Pagos R4'!F180 -> -318239.98 | G67: ='Reversion Pagos R4'!G180 -> -167439.25 | H67: ='Reversion Pagos R4'!H180 -> -2642163 | I67: ='Reversion Pagos R4'!I180 -> -90052.6 | J67: 0 | K67: =D67-E67-F67-G67-H67-I67-J67 -> -4928995.8 | L67: 0 | M67: =K67-L67 -> -4928995.8 | N67: ='Reversion Pagos R4'!P180 -> -26500 | O67: =M67+N67 -> -4955495.8 | S67: 2 | T67: LIMPIEZA METROPOLITANA S.A. ESP. | U67: ='Reversion Pagos R4'!J180 -> -789932.39 | V67: ='Reversion Pagos R4'!K180 -> -770822.52 | W67: ='Reversion Pagos R4'!L180 -> -3654042.8 | X67: ='Reversion Pagos R4'!M180 -> -1114650.3 | Y67: ='Reversion Pagos R4'!N180 -> -146927.71 | Z67: =-L67 -> 0 | AA67: ='Reversion Pagos R4'!O180 -> 4.09 | AB67: =N67 -> -26500 | AC67: =+'Reversion Pagos R4'!Q180+'Reversion Pagos R4'!R180 -> 0 | AD67: =-J67+AE67 -> 1547375.8 | AE67: ='Reversion Pagos R4'!D181 -> 1547375.8 | AF67: =SUM(U67:AD67) -> -4955495.8 | AG67: =(AF67-O67) -> 0 | AH67: =INT(AG67)=0 -> TRUE
B68: 3 | C68: CIUDAD LIMPIA BOGOTA S.A. ESP. | D68: ='Reversion Pagos R4'!D217 -> -6125983.9 | E68: ='Reversion Pagos R4'!E217 -> -331141.74 | F68: ='Reversion Pagos R4'!F217 -> -186760.32 | G68: ='Reversion Pagos R4'!G217 -> -98282.84 | H68: ='Reversion Pagos R4'!H217 -> -2019437.3 | I68: ='Reversion Pagos R4'!I217 -> -59765.73 | J68: 0 | K68: =D68-E68-F68-G68-H68-I68-J68 -> -3430595.9 | L68: 0 | M68: =K68-L68 -> -3430595.9 | N68: ='Reversion Pagos R4'!P217 -> 0 | O68: =M68+N68 -> -3430595.9 | S68: 3 | T68: CIUDAD LIMPIA BOGOTA S.A. ESP. | U68: ='Reversion Pagos R4'!J217 -> -521004.73 | V68: ='Reversion Pagos R4'!K217 -> -508266.78 | W68: ='Reversion Pagos R4'!L217 -> -2407798.7 | X68: ='Reversion Pagos R4'!M217 -> -780590.23 | Y68: ='Reversion Pagos R4'!N217 -> -97513.13 | Z68: =-L68 -> 0 | AA68: ='Reversion Pagos R4'!O217 -> -29.01 | AB68: =N68 -> 0 | AC68: =+'Reversion Pagos R4'!Q217+'Reversion Pagos R4'!R217 -> 0 | AD68: =-J68+AE68 -> 884606.68 | AE68: ='Reversion Pagos R4'!D218 -> 884606.68 | AF68: =SUM(U68:AD68) -> -3430595.9 | AG68: =(AF68-O68) -> -1.3969839e-09 | AH68: =INT(AG68)=0 -> FALSE
B69: 4 | C69: BOGOTA LIMPIA S.A.S. ESP. | D69: ='Reversion Pagos R4'!D332 -> -22250060 | E69: ='Reversion Pagos R4'!E332 -> -1367674.7 | F69: ='Reversion Pagos R4'!F332 -> -719170.4 | G69: ='Reversion Pagos R4'!G332 -> -382313.94 | H69: ='Reversion Pagos R4'!H332 -> -5113171.6 | I69: ='Reversion Pagos R4'!I332 -> -183488.2 | J69: 0 | K69: =D69-E69-F69-G69-H69-I69-J69 -> -14484241 | L69: 0 | M69: =K69-L69 -> -14484241 | N69: ='Reversion Pagos R4'!P332 -> 0 | O69: =M69+N69 -> -14484241 | S69: 4 | T69: BOGOTA LIMPIA S.A.S. ESP. | U69: ='Reversion Pagos R4'!J332 -> -1619246.4 | V69: ='Reversion Pagos R4'!K332 -> -1602973.4 | W69: ='Reversion Pagos R4'!L332 -> -8034602.9 | X69: ='Reversion Pagos R4'!M332 -> -3828497.8 | Y69: ='Reversion Pagos R4'!N332 -> -296831.72 | Z69: =-L69 -> 0 | AA69: ='Reversion Pagos R4'!O332 -> 87.93 | AB69: =N69 -> 0 | AC69: =+'Reversion Pagos R4'!Q332+'Reversion Pagos R4'!R332 -> 0 | AD69: =-J69+AE69 -> 897823.39 | AE69: ='Reversion Pagos R4'!D333 -> 897823.39 | AF69: =SUM(U69:AD69) -> -14484241 | AG69: =(AF69-O69) -> 0 | AH69: =INT(AG69)=0 -> TRUE
B70: 5 | C70: AREA LIMPIA DISTRITO CAPITAL S.A.S. ESP. | D70: ='Reversion Pagos R4'!D373 -> -9076100 | E70: ='Reversion Pagos R4'!E373 -> -427564.46 | F70: ='Reversion Pagos R4'!F373 -> -239080.94 | G70: ='Reversion Pagos R4'!G373 -> -126277.96 | H70: ='Reversion Pagos R4'!H373 -> -1933506.8 | I70: ='Reversion Pagos R4'!I373 -> -69553.97 | J70: 0 | K70: =D70-E70-F70-G70-H70-I70-J70 -> -6280115.9 | L70: 0 | M70: =K70-L70 -> -6280115.9 | N70: ='Reversion Pagos R4'!P373 -> 0 | O70: =M70+N70 -> -6280115.9 | S70: 5 | T70: AREA LIMPIA DISTRITO CAPITAL S.A.S. ESP. | U70: ='Reversion Pagos R4'!J373 -> -610117.24 | V70: ='Reversion Pagos R4'!K373 -> -592518.26 | W70: ='Reversion Pagos R4'!L373 -> -3080559.2 | X70: ='Reversion Pagos R4'!M373 -> -1290465.9 | Y70: ='Reversion Pagos R4'!N373 -> -113482.38 | Z70: =-L70 -> 0 | AA70: ='Reversion Pagos R4'!O373 -> -48 | AB70: =N70 -> 0 | AC70: =+'Reversion Pagos R4'!Q373+'Reversion Pagos R4'!R373 -> 0 | AD70: =-J70+AE70 -> -592924.92 | AE70: ='Reversion Pagos R4'!D374 -> -592924.92 | AF70: =SUM(U70:AD70) -> -6280115.9 | AG70: =(AF70-O70) -> 0 | AH70: =INT(AG70)=0 -> TRUE
C71: TOTAL | D71: =SUM(D66:D70) -> -49709753 | E71: =SUM(E66:E70) -> -2911624.5 | F71: =SUM(F66:F70) -> -1580846.4 | G71: =SUM(G66:G70) -> -837318.74 | H71: =SUM(H66:H70) -> -12898466 | I71: =SUM(I66:I70) -> -448559.17 | J71: =SUM(J66:J70) -> 0 | K71: =SUM(K66:K70) -> -31032938 | ... O71: =SUM(O66:O70) -> -31059438 | T71: TOTAL | U71: =SUM(U66:U70) -> -3941164.7 | V71: =SUM(V66:V70) -> -3851587.7 | W71: =SUM(W66:W70) -> -18965478 | X71: =SUM(X66:X70) -> -7587558.1 | Y71: =SUM(Y66:Y70) -> -728691.14 | Z71: =SUM(Z66:Z70) -> 0 | AA71: =SUM(AA66:AA70) -> 25.67 | AB71: =SUM(AB66:AB70) -> -26500 | ... AG71: =SUM(AG66:AG70) -> -1.3969839e-09 | AH71: =INT(AG71)=0 -> FALSE
Y73: =SUM(U71:Y71) -> -35074479
F75: Firma autorizada
F79: PROCERASEO S.A.S. | I79: NIT: 901 153 639 - 0 | M79: Codigo Remuneración: | N79: =N3 -> 2026091 | U79: PROCERASEO S.A.S. | W79: NIT: 901 153 639 - 0 | AA79: Codigo Remuneración: | AD79: =N79 -> 2026091
F80: 3. ESQUEMA FINANCIERO DEL SERVICIO PUBLICO DE ASEO | U80: 3. ESQUEMA FINANCIERO DEL SERVICIO PUBLICO DE ASEO
F81: Resoluciòn UAESP Número 27 de 2018 | U81: Resoluciòn UAESP Número 27 de 2018
C82: Fecha de Proceso: | D82: =D6 -> 46297 | F82: R5 - REMUNERACIÓN SALDOS A FAVOR POR NOTA | U82: =F82 -> R5 - REMUNERACIÓN SALDOS A FAVOR POR NOTA
C83: Hora: | D83: =D7 -> 0.58333333 | F83: Fecha Desde: | G83: =G7 -> 46266 | J83: Feha Hasta: | K83: =K7 -> 46280 | U83: =F83 -> Fecha Desde: | V83: =G83 -> 46266 | X83: =J83 -> Feha Hasta: | Y83: =K83 -> 46280
B84: ASE | C84: Concesionarios | D84: Recaudo Total | E84: Recaudo por disposicion final | F84: Recaudo por tratamiento de lixiviados | G84: Recaudo por Componente VIAT ( Decreto 2412/2018) | H84: Recaudo por aprovechamiento | I84: Recaudo del componente de comercializacion para Aprovechamiento (11,4%) | J84: Balance de subsidio o contribuciones | K84: RECAUDO BASE DE REMUNERACION | L84: Costo de la Interventoría | M84: REMUNERACION FINAL | N84: Conceptos especiales | O84: REMUNERACION FINAL MAS CONCEPTOS ESPECIALES | S84: ASE | T84: Concesionarios | U84: Tarifa de Comercialización del Servicio. ( TCS) | V84: Tarifa de Limpieza Urbana del Servicio. ( TLU) | W84: Tarifa de Barrido y Limpieza del Servicio. ( TBL) | X84: Tarifa de Recolección y Transporte del Servicio. (TRT) | Y84: Recaudo del componente de comercializacion para Aprovechamiento (18,6%) | Z84: Costo de la Interventoría | AA84: Ajuste a la decena | AB84: Conceptos especiales | AC84: Otros | AD84: Diferencial Balance Subsidio y Contribución (Fac vs Rec) | AE84: Balance de subsidio o contribuciones (Recaudo) | AF84: REMUNERACION FINAL MAS CONCEPTOS ESPECIALES
B85: 1 | C85: PROMOAMBIENTAL DISTRITO S.A.S. ESP. | D85: ='AJUSTES - SF-T'!D47 -> 0 | E85: ='AJUSTES - SF-T'!E47 -> 0 | F85: ='AJUSTES - SF-T'!F47 -> 0 | G85: ='AJUSTES - SF-T'!G47 -> 0 | H85: ='AJUSTES - SF-T'!H47 -> 0 | I85: ='AJUSTES - SF-T'!I47 -> 0 | J85: ='AJUSTES - SF-T'!J47 -> 0 | K85: =D85-E85-F85-G85-H85-I85-J85 -> 0 | L85: 0 | M85: =K85-L85 -> 0 | N85: ='AJUSTES - SF-T'!N47 -> 0 | O85: =M85+N85 -> 0 | S85: 1 | T85: PROMOAMBIENTAL DISTRITO S.A.S. ESP. | U85: ='AJUSTES - SF-T'!U47 -> 0 | V85: ='AJUSTES - SF-T'!V47 -> 0 | W85: ='AJUSTES - SF-T'!W47 -> 0 | X85: ='AJUSTES - SF-T'!X47 -> 0 | Y85: ='AJUSTES - SF-T'!Y47 -> 0 | Z85: =-L85 -> 0 | AA85: ='AJUSTES - SF-T'!AA47 -> 0 | AB85: =N85 -> 0 | AC85: 0 | AD85: =-J85+AE85 -> 0 | AE85: ='AJUSTES - SF-T'!AD47 -> 0 | AF85: =SUM(U85:AD85) -> 0 | AG85: =AF85-O85 -> 0 | AH85: =INT(AG85)=0 -> TRUE
B86: 2 | C86: LIMPIEZA METROPOLITANA S.A. ESP. | D86: ='AJUSTES - SF-T'!D48 -> 0 | E86: ='AJUSTES - SF-T'!E48 -> 0 | F86: ='AJUSTES - SF-T'!F48 -> 0 | G86: ='AJUSTES - SF-T'!G48 -> 0 | H86: ='AJUSTES - SF-T'!H48 -> 0 | I86: ='AJUSTES - SF-T'!I48 -> 0 | J86: ='AJUSTES - SF-T'!J48 -> 0 | K86: =D86-E86-F86-G86-H86-I86-J86 -> 0 | L86: 0 | M86: =K86-L86 -> 0 | N86: ='AJUSTES - SF-T'!N48 -> 0 | O86: =M86+N86 -> 0 | S86: 2 | T86: LIMPIEZA METROPOLITANA S.A. ESP. | U86: ='AJUSTES - SF-T'!U48 -> 0 | V86: ='AJUSTES - SF-T'!V48 -> 0 | W86: ='AJUSTES - SF-T'!W48 -> 0 | X86: ='AJUSTES - SF-T'!X48 -> 0 | Y86: ='AJUSTES - SF-T'!Y48 -> 0 | Z86: =-L86 -> 0 | AA86: ='AJUSTES - SF-T'!AA48 -> 0 | AB86: =N86 -> 0 | AC86: 0 | AD86: =-J86+AE86 -> 0 | AE86: ='AJUSTES - SF-T'!AD48 -> 0 | AF86: =SUM(U86:AD86) -> 0 | AG86: =AF86-O86 -> 0 | AH86: =INT(AG86)=0 -> TRUE
B87: 3 | C87: CIUDAD LIMPIA BOGOTA S.A. ESP. | D87: ='AJUSTES - SF-T'!D49 -> 0 | E87: ='AJUSTES - SF-T'!E49 -> 0 | F87: ='AJUSTES - SF-T'!F49 -> 0 | G87: ='AJUSTES - SF-T'!G49 -> 0 | H87: ='AJUSTES - SF-T'!H49 -> 0 | I87: ='AJUSTES - SF-T'!I49 -> 0 | J87: ='AJUSTES - SF-T'!J49 -> 0 | K87: =D87-E87-F87-G87-H87-I87-J87 -> 0 | L87: 0 | M87: =K87-L87 -> 0 | N87: ='AJUSTES - SF-T'!N49 -> 0 | O87: =M87+N87 -> 0 | S87: 3 | T87: CIUDAD LIMPIA BOGOTA S.A. ESP. | U87: ='AJUSTES - SF-T'!U49 -> 0 | V87: ='AJUSTES - SF-T'!V49 -> 0 | W87: ='AJUSTES - SF-T'!W49 -> 0 | X87: ='AJUSTES - SF-T'!X49 -> 0 | Y87: ='AJUSTES - SF-T'!Y49 -> 0 | Z87: =-L87 -> 0 | AA87: ='AJUSTES - SF-T'!AA49 -> 0 | AB87: =N87 -> 0 | AC87: 0 | AD87: =-J87+AE87 -> 0 | AE87: ='AJUSTES - SF-T'!AD49 -> 0 | AF87: =SUM(U87:AD87) -> 0 | AG87: =AF87-O87 -> 0 | AH87: =INT(AG87)=0 -> TRUE
B88: 4 | C88: BOGOTA LIMPIA S.A.S. ESP. | D88: ='AJUSTES - SF-T'!D50 -> 0 | E88: ='AJUSTES - SF-T'!E50 -> 0 | F88: ='AJUSTES - SF-T'!F50 -> 0 | G88: ='AJUSTES - SF-T'!G50 -> 0 | H88: ='AJUSTES - SF-T'!H50 -> 0 | I88: ='AJUSTES - SF-T'!I50 -> 0 | J88: ='AJUSTES - SF-T'!J50 -> 0 | K88: =D88-E88-F88-G88-H88-I88-J88 -> 0 | L88: 0 | M88: =K88-L88 -> 0 | N88: ='AJUSTES - SF-T'!N50 -> 0 | O88: =M88+N88 -> 0 | S88: 4 | T88: BOGOTA LIMPIA S.A.S. ESP. | U88: ='AJUSTES - SF-T'!U50 -> 0 | V88: ='AJUSTES - SF-T'!V50 -> 0 | W88: ='AJUSTES - SF-T'!W50 -> 0 | X88: ='AJUSTES - SF-T'!X50 -> 0 | Y88: ='AJUSTES - SF-T'!Y50 -> 0 | Z88: =-L88 -> 0 | AA88: ='AJUSTES - SF-T'!AA50 -> 0 | AB88: =N88 -> 0 | AC88: 0 | AD88: =-J88+AE88 -> 0 | AE88: ='AJUSTES - SF-T'!AD50 -> 0 | AF88: =SUM(U88:AD88) -> 0 | AG88: =AF88-O88 -> 0 | AH88: =INT(AG88)=0 -> TRUE
B89: 5 | C89: AREA LIMPIA DISTRITO CAPITAL S.A.S. ESP. | D89: ='AJUSTES - SF-T'!D51 -> 0 | E89: ='AJUSTES - SF-T'!E51 -> 0 | F89: ='AJUSTES - SF-T'!F51 -> 0 | G89: ='AJUSTES - SF-T'!G51 -> 0 | H89: ='AJUSTES - SF-T'!H51 -> 0 | I89: ='AJUSTES - SF-T'!I51 -> 0 | J89: ='AJUSTES - SF-T'!J51 -> 0 | K89: =D89-E89-F89-G89-H89-I89-J89 -> 0 | L89: 0 | M89: =K89-L89 -> 0 | N89: ='AJUSTES - SF-T'!N51 -> 0 | O89: =M89+N89 -> 0 | S89: 5 | T89: AREA LIMPIA DISTRITO CAPITAL S.A.S. ESP. | U89: ='AJUSTES - SF-T'!U51 -> 0 | V89: ='AJUSTES - SF-T'!V51 -> 0 | W89: ='AJUSTES - SF-T'!W51 -> 0 | X89: ='AJUSTES - SF-T'!X51 -> 0 | Y89: ='AJUSTES - SF-T'!Y51 -> 0 | Z89: =-L89 -> 0 | AA89: ='AJUSTES - SF-T'!AA51 -> 0 | AB89: =N89 -> 0 | AC89: 0 | AD89: =-J89+AE89 -> 0 | AE89: ='AJUSTES - SF-T'!AD51 -> 0 | AF89: =SUM(U89:AD89) -> 0 | AG89: =AF89-O89 -> 0 | AH89: =INT(AG89)=0 -> TRUE
C90: TOTAL | D90: =SUM(D85:D89) -> 0 | E90: =SUM(E85:E89) -> 0 | F90: =SUM(F85:F89) -> 0 | G90: =SUM(G85:G89) -> 0 | H90: =SUM(H85:H89) -> 0 | I90: =SUM(I85:I89) -> 0 | J90: =SUM(J85:J89) -> 0 | K90: =SUM(K85:K89) -> 0 | ... O90: =SUM(O85:O89) -> 0 | T90: TOTAL | U90: =SUM(U85:U89) -> 0 | V90: =SUM(V85:V89) -> 0 | W90: =SUM(W85:W89) -> 0 | X90: =SUM(X85:X89) -> 0 | Y90: =SUM(Y85:Y89) -> 0 | Z90: =SUM(Z85:Z89) -> 0 | AA90: =SUM(AA85:AA89) -> 0 | AB90: =SUM(AB85:AB89) -> 0 | ... AG90: =SUM(AG85:AG89) -> 0 | AH90: =INT(AG90)=0 -> TRUE
Y92: =SUM(U90:Y90) -> 0
F94: Firma autorizada
F98: PROCERASEO S.A.S. | I98: NIT: 901 153 639 - 0 | M98: Codigo Remuneración: | N98: =N3 -> 2026091 | U98: PROCERASEO S.A.S. | W98: NIT: 901 153 639 - 0 | AA98: Codigo Remuneración: | AD98: =N98 -> 2026091
F99: 3. ESQUEMA FINANCIERO DEL SERVICIO PUBLICO DE ASEO | U99: 3. ESQUEMA FINANCIERO DEL SERVICIO PUBLICO DE ASEO
F100: Resoluciòn UAESP Número 27 de 2018 | U100: Resoluciòn UAESP Número 27 de 2018
C101: Fecha de Proceso: | D101: =D6 -> 46297 | F101: REPORTE CONSOLIDADO TOTAL DE RECAUDO | U101: REPORTE DETALLADO SUBBOLSA RBL DISCRIMINADO POR ACTIVIDADES
C102: Hora: | D102: =D7 -> 0.58333333 | F102: Fecha Desde: | G102: =G7 -> 46266 | J102: Feha Hasta: | K102: =K7 -> 46280 | U102: =F102 -> Fecha Desde: | V102: =G102 -> 46266 | X102: =J102 -> Feha Hasta: | Y102: =K102 -> 46280
B103: ASE | C103: Concesionarios | D103: Recaudo Total | E103: Recaudo por disposicion final | F103: Recaudo por tratamiento de lixiviados | G103: Recaudo por Componente VIAT ( Decreto 2412/2018) | H103: Recaudo por aprovechamiento | I103: Recaudo del componente de comercializacion para Aprovechamiento (11,4%) | J103: Balance de subsidio o contribuciones | K103: RECAUDO BASE DE REMUNERACION | L103: Costo de la Interventoría | M103: REMUNERACION FINAL | N103: Conceptos especiales | O103: REMUNERACION FINAL MAS CONCEPTOS ESPECIALES | S103: ASE | T103: Concesionarios | U103: Tarifa de Comercialización del Servicio. ( TCS) | V103: Tarifa de Limpieza Urbana del Servicio. ( TLU) | W103: Tarifa de Barrido y Limpieza del Servicio. ( TBL) | X103: Tarifa de Recolección y Transporte del Servicio. (TRT) | Y103: Recaudo del componente de comercializacion para Aprovechamiento (18,6%) | Z103: Costo de la Interventoría | AA103: Ajuste a la decena | AB103: Conceptos especiales | AC103: Otros | AD103: Diferencial Balance Subsidio y Contribución (Fac vs Rec) | AE103: Balance de subsidio o contribuciones (Recaudo) | AF103: REMUNERACION FINAL MAS CONCEPTOS ESPECIALES
B104: 1 | C104: PROMOAMBIENTAL DISTRITO S.A.S. ESP. | D104: =D9+D28+D47+D66+D85 -> 1.7450251e+10 | E104: =E9+E28+E47+E66+E85 -> 1.0027305e+09 | F104: =F9+F28+F47+F66+F85 -> 5.5951317e+08 | G104: =G9+G28+G47+G66+G85 -> 2.9634029e+08 | H104: =H9+H28+H47+H66+H85 -> 4858821909 | I104: =I9+I28+I47+I66+I85 -> 1.8220848e+08 | J104: =J9+J28+J47+J66+J85 -> 2.5893357e+09 | K104: =D104-E104-F104-G104-H104-I104-J104 -> 7.9613005e+09 | L104: =L9+L28+L47+L66+L85 -> 189185987 | M104: =K104-L104 -> 7.7721145e+09 | N104: =N9+N28+N47+N66+N85 -> 30635670 | O104: =M104+N104 -> 7.8027501e+09 | S104: 1 | T104: PROMOAMBIENTAL DISTRITO S.A.S. ESP. | U104: =U9+U28+U47+U66+U85 -> 1.5997921e+09 | V104: =V9+V28+V47+V66+V85 -> 1.5287054e+09 | W104: =W9+W28+W47+W66+W85 -> 7.1920556e+09 | X104: =X9+X28+X47+X66+X85 -> 2.7302893e+09 | Y104: =Y9+Y28+Y47+Y66+Y85 -> 2.9732075e+08 | Z104: =Z9+Z28+Z47+Z66+Z85 -> -189185987 | AA104: =AA9+AA28+AA47+AA66+AA85 -> -46885.63 | AB104: =AB9+AB28+AB47+AB66+AB85 -> 30635670 | AC104: =AC9+AC28+AC47+AC66+AC85 -> 392.74 | AD104: =-J104+AE104 -> -5.3868162e+09 | AE104: =AE9+AE28+AE47+AE66+AE85 -> -2.7974805e+09 | AF104: =SUM(U104:AD104) -> 7.8027501e+09 | AG104: =AF104-O104 -> 0 | AH104: =INT(AG104)=0 -> TRUE
B105: 2 | C105: LIMPIEZA METROPOLITANA S.A. ESP. | D105: =D10+D29+D48+D67+D86 -> 1.4147358e+10 | E105: =E10+E29+E48+E67+E86 -> 1.0962419e+09 | F105: =F10+F29+F48+F67+F86 -> 6.0768851e+08 | G105: =G10+G29+G48+G67+G86 -> 3.2074609e+08 | H105: =H10+H29+H48+H67+H86 -> 4.4861569e+09 | I105: =I10+I29+I48+I67+I86 -> 1.5249957e+08 | J105: =J10+J29+J48+J67+J86 -> -5.0932598e+09 | K105: =D105-E105-F105-G105-H105-I105-J105 -> 1.2577285e+10 | L105: =L10+L29+L48+L67+L86 -> 266580255 | M105: =K105-L105 -> 1.2310704e+10 | N105: =N10+N29+N48+N67+N86 -> 43616074 | O105: =M105+N105 -> 1.235432e+10 | S105: 2 | T105: LIMPIEZA METROPOLITANA S.A. ESP. | U105: =U10+U29+U48+U67+U86 -> 1.3386759e+09 | V105: =V10+V29+V48+V67+V86 -> 1.3260463e+09 | W105: =W10+W29+W48+W67+W86 -> 6.2149233e+09 | X105: =X10+X29+X48+X67+X86 -> 2.1545074e+09 | Y105: =Y10+Y29+Y48+Y67+Y86 -> 2.490176e+08 | Z105: =Z10+Z29+Z48+Z67+Z86 -> -266580255 | AA105: =AA10+AA29+AA48+AA67+AA86 -> 61423.42 | AB105: =AB10+AB29+AB48+AB67+AB86 -> 43616074 | AC105: =AC10+AC29+AC48+AC67+AC86 -> -56807.54 | AD105: =-J105+AE105 -> 1.2941095e+09 | AE105: =AE10+AE29+AE48+AE67+AE86 -> -3.7991503e+09 | AF105: =SUM(U105:AD105) -> 1.235432e+10 | AG105: =AF105-O105 -> 0 | AH105: =INT(AG105)=0 -> TRUE
B106: 3 | C106: CIUDAD LIMPIA BOGOTA S.A. ESP. | D106: =D11+D30+D49+D68+D87 -> 1.0891339e+10 | E106: =E11+E30+E49+E68+E87 -> 7.1070608e+08 | F106: =F11+F30+F49+F68+F87 -> 3.9747748e+08 | G106: =G11+G30+G49+G68+G87 -> 2.1036593e+08 | H106: =H11+H30+H49+H68+H87 -> 3.0897857e+09 | I106: =I11+I30+I49+I68+I87 -> 1.0259106e+08 | J106: =J11+J30+J49+J68+J87 -> -1.230397e+09 | K106: =D106-E106-F106-G106-H106-I106-J106 -> 7.6108094e+09 | L106: =L11+L30+L49+L68+L87 -> 154788535 | M106: =K106-L106 -> 7.4560209e+09 | N106: =N11+N30+N49+N68+N87 -> 25562528 | O106: =M106+N106 -> 7.4815834e+09 | S106: 3 | T106: CIUDAD LIMPIA BOGOTA S.A. ESP. | U106: =U11+U30+U49+U68+U87 -> 9.0040444e+08 | V106: =V11+V30+V49+V68+V87 -> 8.8025184e+08 | W106: =W11+W30+W49+W68+W87 -> 4.1430165e+09 | X106: =X11+X30+X49+X68+X87 -> 1.6838613e+09 | Y106: =Y11+Y30+Y49+Y68+Y87 -> 1.6742136e+08 | Z106: =Z11+Z30+Z49+Z68+Z87 -> -154788535 | AA106: =AA11+AA30+AA49+AA68+AA87 -> 46657 | AB106: =AB11+AB30+AB49+AB68+AB87 -> 25562528 | AC106: =AC11+AC30+AC49+AC68+AC87 -> 5.57 | AD106: =-J106+AE106 -> -1.6419266e+08 | AE106: =AE11+AE30+AE49+AE68+AE87 -> -1.3945897e+09 | AF106: =SUM(U106:AD106) -> 7.4815834e+09 | AG106: =AF106-O106 -> 0.099998474 | AH106: =INT(AG106)=0 -> TRUE
B107: 4 | C107: BOGOTA LIMPIA S.A.S. ESP. | D107: =D12+D31+D50+D69+D88 -> 1.1508947e+10 | E107: =E12+E31+E50+E69+E88 -> 6.5162035e+08 | F107: =F12+F31+F50+F69+F88 -> 3.6207689e+08 | G107: =G12+G31+G50+G69+G88 -> 1.9142449e+08 | H107: =H12+H31+H50+H69+H88 -> 2.8505195e+09 | I107: =I12+I31+I50+I69+I88 -> 98433844 | J107: =J12+J31+J50+J69+J88 -> 38133906 | K107: =D107-E107-F107-G107-H107-I107-J107 -> 7.3167382e+09 | L107: =L12+L31+L50+L69+L88 -> 120391083 | M107: =K107-L107 -> 7.1963471e+09 | N107: =N12+N31+N50+N69+N88 -> 23185408 | O107: =M107+N107 -> 7.2195325e+09 | S107: 4 | T107: BOGOTA LIMPIA S.A.S. ESP. | U107: =U12+U31+U50+U69+U88 -> 8.6349652e+08 | V107: =V12+V31+V50+V69+V88 -> 8.5091524e+08 | W107: =W12+W31+W50+W69+W88 -> 4.3369309e+09 | X107: =X12+X31+X50+X69+X88 -> 1.7250123e+09 | Y107: =Y12+Y31+Y50+Y69+Y88 -> 1.6087823e+08 | Z107: =Z12+Z31+Z50+Z69+Z88 -> -120391083 | AA107: =AA12+AA31+AA50+AA69+AA88 -> -64310.54 | AB107: =AB12+AB31+AB50+AB69+AB88 -> 23185408 | AC107: =AC12+AC31+AC50+AC69+AC88 -> 181.07 | AD107: =-J107+AE107 -> -6.2043086e+08 | AE107: =AE12+AE31+AE50+AE69+AE88 -> -5.8229695e+08 | AF107: =SUM(U107:AD107) -> 7.2195325e+09 | AG107: =AF107-O107 -> 0 | AH107: =INT(AG107)=0 -> TRUE
B108: 5 | C108: AREA LIMPIA DISTRITO CAPITAL S.A.S. ESP. | D108: =D13+D32+D51+D70+D89 -> 9.1471794e+09 | E108: =E13+E32+E51+E70+E89 -> 5.0114181e+08 | F108: =F13+F32+F51+F70+F89 -> 2.7995073e+08 | G108: =G13+G32+G51+G70+G89 -> 1.4824291e+08 | H108: =H13+H32+H51+H70+H89 -> 2.1000672e+09 | I108: =I13+I32+I51+I70+I89 -> 75390757 | J108: =J13+J32+J51+J70+J89 -> -1.2241007e+09 | K108: =D108-E108-F108-G108-H108-I108-J108 -> 7.2664867e+09 | L108: =L13+L32+L51+L70+L89 -> 128990445 | M108: =K108-L108 -> 7.1374962e+09 | N108: =N13+N32+N51+N70+N89 -> 32575938 | O108: =M108+N108 -> 7.1700722e+09 | S108: 5 | T108: AREA LIMPIA DISTRITO CAPITAL S.A.S. ESP. | U108: =U13+U32+U51+U70+U89 -> 6.6183483e+08 | V108: =V13+V32+V51+V70+V89 -> 6.438762e+08 | W108: =W13+W32+W51+W70+W89 -> 3.3042169e+09 | X108: =X13+X32+X51+X70+X89 -> 1.5006793e+09 | Y108: =Y13+Y32+Y51+Y70+Y89 -> 1.2309614e+08 | Z108: =Z13+Z32+Z51+Z70+Z89 -> -128990445 | AA108: =AA13+AA32+AA51+AA70+AA89 -> -16582.77 | AB108: =AB13+AB32+AB51+AB70+AB89 -> 32575938 | AC108: =AC13+AC32+AC51+AC70+AC89 -> -105.68 | AD108: =-J108+AE108 -> 1.0327999e+09 | AE108: =AE13+AE32+AE51+AE70+AE89 -> -1.9130078e+08 | AF108: =SUM(U108:AD108) -> 7.1700722e+09 | AG108: =AF108-O108 -> 0 | AH108: =INT(AG108)=0 -> TRUE
C109: TOTAL | D109: =SUM(D104:D108) -> 6.3145074e+10 | E109: =SUM(E104:E108) -> 3.9624407e+09 | F109: =SUM(F104:F108) -> 2.2067068e+09 | G109: =SUM(G104:G108) -> 1.1671197e+09 | H109: =SUM(H104:H108) -> 1.7385351e+10 | I109: =SUM(I104:I108) -> 6.1112371e+08 | J109: =SUM(J104:J108) -> -4.9202879e+09 | K109: =SUM(K104:K108) -> 4.2732619e+10 | ... O109: =SUM(O104:O108) -> 4.2028259e+10 | T109: TOTAL | U109: =SUM(U104:U108) -> 5.3642038e+09 | V109: =SUM(V104:V108) -> 5.229795e+09 | W109: =SUM(W104:W108) -> 2.5191143e+10 | X109: =SUM(X104:X108) -> 9.7943496e+09 | Y109: =SUM(Y104:Y108) -> 9.9773409e+08 | Z109: =SUM(Z104:Z108) -> -859936305 | AA109: =SUM(AA104:AA108) -> -19698.52 | AB109: =SUM(AB104:AB108) -> 1.5557562e+08 | ... AG109: =SUM(AG104:AG108) -> 0.099998474 | AH109: =INT(AG109)=0 -> TRUE
Y111: =SUM(U109:Y109) -> 4.6577226e+10
F113: Firma autorizada | V113: Firma autorizada
F117: PROCERASEO S.A.S. | I117: NIT: 901 153 639 - 0 | L117: Codigo Remuneración: | M117: =N3 -> 2026091
F118: 3. ESQUEMA FINANCIERO DEL SERVICIO PUBLICO DE ASEO
F119: Resoluciòn UAESP Número 27 de 2018
F121: REPORTE CONSOLIDADO DE ANTICIPOS
F122: Fecha Desde: | G122: =G7 -> 46266 | J122: Feha Hasta: | K122: =K7 -> 46280
B124: ASE | C124: Concesionarios | D124: ANTICIPOS GENERADOS | E124: PAGOS PENDIENTES POR APLICAR | G124: RECAUDO APLICADO PERIODOS ANTERIORES | H124: ANTICIPOS QUE DESCARGAN | I124: SALDOS A FAVOR POR NOTA | J124: REVERSIÓN DE PAGOS | K124: SALDOS A FAVOR GENERADOS RECAUDO EXTEMPORANEO | L124: SALDOS A FAVOR QUE DESCARGAN POR REVERSIONES
B125: 1 | C125: PROMOAMBIENTAL DISTRITO S.A.S. ESP. | D125: ='ANTICIPOS USUARIOS'!C3 -> 33419430 | E125: 0 | G125: =D47+N47 -> 42680 | H125: =D28+N28 -> 34844954 | I125: =D85+N85 -> 0 | J125: =D66+N66 -> -3544507.3 | K125: ='ANTICIPOS USUARIOS'!C12 -> 0 | L125: =-'ANTICIPOS USUARIOS'!C21 -> 0
B126: 2 | C126: LIMPIEZA METROPOLITANA S.A. ESP. | D126: ='ANTICIPOS USUARIOS'!C4 -> 88020914 | E126: 0 | G126: =D48+N48 -> 0 | H126: =D29+N29 -> 1.0171347e+08 | I126: =D86+N86 -> 0 | J126: =D67+N67 -> -8739602.4 | K126: ='ANTICIPOS USUARIOS'!C13 -> 0 | L126: =-'ANTICIPOS USUARIOS'!C22 -> 0
B127: 3 | C127: CIUDAD LIMPIA BOGOTA S.A. ESP. | D127: ='ANTICIPOS USUARIOS'!C5 -> 8946171 | E127: 0 | G127: =D49+N49 -> 169120 | H127: =D30+N30 -> 23629214 | I127: =D87+N87 -> 0 | J127: =D68+N68 -> -6125983.9 | K127: ='ANTICIPOS USUARIOS'!C14 -> 0 | L127: =-'ANTICIPOS USUARIOS'!C23 -> 0
B128: 4 | C128: BOGOTA LIMPIA S.A.S. ESP. | D128: ='ANTICIPOS USUARIOS'!C6 -> 41072280 | E128: 0 | G128: =D50+N50 -> 8635714 | H128: =D31+N31 -> 23548210 | I128: =D88+N88 -> 0 | J128: =D69+N69 -> -22250060 | K128: ='ANTICIPOS USUARIOS'!C15 -> 0 | L128: =-'ANTICIPOS USUARIOS'!C24 -> 0
B129: 5 | C129: AREA LIMPIA DISTRITO CAPITAL S.A.S. ESP. | D129: ='ANTICIPOS USUARIOS'!C7 -> 14445987 | E129: 0 | G129: =D51+N51 -> 61140 | H129: =D32+N32 -> 27520061 | I129: =D89+N89 -> 0 | J129: =D70+N70 -> -9076100 | K129: ='ANTICIPOS USUARIOS'!C16 -> 0 | L129: =-'ANTICIPOS USUARIOS'!C25 -> 0
B130: X | C130: PENDIENTE POR APLICAR | E130: ='Recaudo Directa Occidente'!F26 -> 0
C131: TOTAL | D131: =SUM(D125:D130) -> 1.8590478e+08 | E131: =SUM(E125:E130) -> 0 | G131: =SUM(G125:G129) -> 8908654 | H131: =SUM(H125:H130) -> 2.1125591e+08 | I131: =SUM(I125:I130) -> 0 | J131: =SUM(J125:J130) -> -49736253 | K131: =SUM(K125:K130) -> 0 | L131: =SUM(L125:L130) -> 0
F135: PROCERASEO SAS
C138: VALIDACION DEL RECAUDO VERSUS REMUNERACION
B141: ASE | C141: Concesionarios | D141: Recaudo REMUNERADO | E141: RECAUDO RECIBIDO | F141: R2 - ANTICIPOS A USUARIOS | G141: R4 - REVERSION DE PAGOS | H141: R5 - SALDOS A FAVOR POR NOTA | I141: RECAUDO PENDIENTE POR REVERSAR | J141: RECAUDO APLICADO PERIODOS ANTERIORES | K141: RECAUDO APLICADO ANTICIPOS
...

Sheet VALIDACION_TOTAL
B2: ASE | C2: TOTAL RECAUDO RECIBIDO | D2: RECAUDO PERIODOS ANTERIORES | E2: (REMUNERACION) ANTICIPOS QUE DESCARGAN | F2: RECAUDO POR REVERSAR | G2: SALDOS A FAVOR POR NOTA | H2: TOTAL RECAUDO | I2: REMUNERACION RECAUDO TOTAL | J2: REMUNERACION CONCEPTOS ESPECIALES | K2: REMUNERACION ANTICIPOS GENERADOS | L2: REMUNERACION PAGOS PENDIENTES POR APLICAR | M2: REVERSION DE PAGOS | N2: TOTAL REMUNERACION
B3: 1 | C3: ='Recaudo EAAB Reciprocidad'!D21+'Recaudo EAAB + Ciud Limp'!D21+'Recaudo Directa Occidente'!D21+'Recaudo ENEL'!D21+'Recaudo ENERBIT'!D21 -> 17482962516 | D3: ='CONSOLIDADO_TOTAL RECAUDO'!G125 -> 42680 | E3: ='CONSOLIDADO_TOTAL RECAUDO'!D28+'CONSOLIDADO_TOTAL RECAUDO'!N28 -> 34844954 | F3: ='CONSOLIDADO_TOTAL RECAUDO'!I142 -> 0 | G3: ='CONSOLIDADO_TOTAL RECAUDO'!H142 -> 0 | H3: =SUM(C3:G3) -> 1.751785e+10 | I3: ='CONSOLIDADO_TOTAL RECAUDO'!D104 -> 1.7450251e+10 | J3: ='CONSOLIDADO_TOTAL RECAUDO'!N104 -> 30635670 | K3: ='CONSOLIDADO_TOTAL RECAUDO'!D125 -> 33419430 | L3: ='CONSOLIDADO_TOTAL RECAUDO'!E125 -> 0 | M3: =-'CONSOLIDADO_TOTAL RECAUDO'!D66-'CONSOLIDADO_TOTAL RECAUDO'!N66 -> 3544507.3 | N3: =SUM(I3:M3) -> 1.751785e+10 | O3: =H3-N3 -> 0 | P3: =INT(O3)=0 -> TRUE
B4: 2 | C4: ='Recaudo EAAB Reciprocidad'!D22+'Recaudo EAAB + Ciud Limp'!D22+'Recaudo Directa Occidente'!D22+'Recaudo ENEL'!D22+'Recaudo ENERBIT'!D22 -> 14185615645 | D4: ='CONSOLIDADO_TOTAL RECAUDO'!G126 -> 0 | E4: ='CONSOLIDADO_TOTAL RECAUDO'!D29+'CONSOLIDADO_TOTAL RECAUDO'!N29 -> 1.0171347e+08 | F4: ='CONSOLIDADO_TOTAL RECAUDO'!I143 -> 405230 | G4: ='CONSOLIDADO_TOTAL RECAUDO'!H143 -> 0 | H4: =SUM(C4:G4) -> 1.4287734e+10 | I4: ='CONSOLIDADO_TOTAL RECAUDO'!D105 -> 1.4147358e+10 | J4: ='CONSOLIDADO_TOTAL RECAUDO'!N105 -> 43616074 | K4: ='CONSOLIDADO_TOTAL RECAUDO'!D126 -> 88020914 | L4: ='CONSOLIDADO_TOTAL RECAUDO'!E126 -> 0 | M4: =-'CONSOLIDADO_TOTAL RECAUDO'!D67-'CONSOLIDADO_TOTAL RECAUDO'!N67 -> 8739602.4 | N4: =SUM(I4:M4) -> 1.4287734e+10 | O4: =H4-N4 -> 0 | P4: =INT(O4)=0 -> TRUE
