Workbook
Name \0: #REF!
Name _1: #REF!
Name _2: #REF!
Name _A655555: #REF!
Name _CFR1: #REF!
Name _cia1: #REF!
Name _XL250: #REF!
Name A: #REF!
Name ADM: [1]!ADM
Name ADM: [1]!ADM
Name ADM: [1]!ADM
Name ADM: [1]!ADM
Name ADM: [1]!ADM
Name ADM_: [1]!ADM
Name ADM_: [1]!ADM
Name ADM_: [1]!ADM
Name ADM_: [1]!ADM
Name ADM_: [1]!ADM
Name AI: #REF!
Name Air: #REF!
Name AP: '[2]TARIFA no aforos'!$C$12
Name Bancos: [3]Fx!$C$1:$C$23
Name CBL: #REF!
Name CCS: #REF!
Name CDT_p: [4]CDT!$C$3
Name CFR: #REF!
Name cia: #REF!
Name COM: #REF!
Name CRT: #REF!
Name CRT___CTEp___CDTp___CMRv: #REF!
Name CRT_aislados: '[4]COSTOS AJUSTADOS'!$C$13
Name CRT_costas: #REF!
Name CTE_p: [4]CTE!$C$5
Name Denominador: #REF!
Name dg: [1]!ADM
Name dg: [1]!ADM
Name dg: [1]!ADM
Name dg: [1]!ADM
Name dg: [1]!ADM
Name DIAS: [5]CONTRA!#REF!
Name Fmerc: #REF!
Name FPS: #REF!
Name InformacionGeneral: [1]!InformacionGeneral
Name InformacionGeneral: [1]!InformacionGeneral
Name InformacionGeneral: [1]!InformacionGeneral
Name InformacionGeneral: [1]!InformacionGeneral
Name InformacionGeneral: [1]!InformacionGeneral
Name INTFIN: #REF!
Name INV: [1]!INV
Name INV: [1]!INV
Name INV: [1]!INV
Name INV: [1]!INV
Name INV: [1]!INV
Name K: #REF!
Name N: '[4]COSTOS AJUSTADOS'!#REF!
Name Na: '[2]TARIFA no aforos'!$C$39
Name nfc: '[4]COSTOS AJUSTADOS'!#REF!
Name OYM: [1]!OYM
Name OYM: [1]!OYM
Name OYM: [1]!OYM

Sheet Recaudo EAAB Reciprocidad
B2: OPORTUNO | C2: ASE | D2: VALOR 1° Q | E2: NUMERO REG. 1°Q | F2: VALOR 2° Q | G2: NUMERO REG. 2°Q
C3: 1 | D3: 0 | E3: 0 | F3: 0 | G3: 0
C4: 2 | D4: 29345550 | E4: 341 | F4: 18262430 | G4: 217
C5: 3 | D5: 0 | E5: 0 | F5: 0 | G5: 0
C6: 4 | D6: 15240310 | E6: 108 | F6: 8615850 | G6: 64
C7: 5 | D7: 0 | E7: 0 | F7: 0 | G7: 0
C8: X
D9: 44585860 | E9: 449 | F9: 26878280 | G9: 281
C11: ASE | D11: VALOR 1° Q | E11: NUMERO REG. 1°Q | F11: VALOR 2° Q | G11: NUMERO REG. 2°Q
B12: EXTEMP. | C12: 1 | D12: 0 | E12: 0 | F12: 0 | G12: 0
C13: 2 | D13: 0 | E13: 0 | F13: 798760 | G13: 7
C14: 3 | D14: 0 | E14: 0 | F14: 0 | G14: 0
C15: 4 | D15: 0 | E15: 0 | F15: 228530 | G15: 1
C16: 5 | D16: 0 | E16: 0 | F16: 0 | G16: 0
C17: X
D18: 0 | E18: 0 | F18: 1027290 | G18: 8
C20: ASE | D20: VALOR 1° Q | E20: NUMERO REG. 1°Q | F20: VALOR 2° Q | G20: NUMERO REG. 2°Q | I20: VALOR TOTAL MES | J20: NUMERO REGISTROS MES
B21: TOTAL | C21: 1 | D21: 0 | E21: 0 | F21: 0 | G21: 0 | I21: 0 | J21: 0
C22: 2 | D22: 29345550 | E22: 341 | F22: 19061190 | G22: 224 | I22: 53577310 | J22: 672
C23: 3 | D23: 0 | E23: 0 | F23: 0 | G23: 0 | I23: 0 | J23: 0
C24: 4 | D24: 15240310 | E24: 108 | F24: 8844380 | G24: 65 | I24: 31125950 | J24: 242
C25: 5 | D25: 0 | E25: 0 | F25: 0 | G25: 0 | I25: 0 | J25: 0
C26: X | I26: 0 | J26: 0
D27: 44585860 | E27: 449 | F27: 27905570 | G27: 289 | I27: 84703260 | J27: 914
B31: OPORTUNO | D31: =D9=SUM(D3:D8) -> TRUE | E31: =E9=SUM(E3:E8) -> TRUE | F31: =F9=SUM(F3:F8) -> TRUE | G31: =G9=SUM(G3:G8) -> TRUE
B33: EXTEMP. | D33: =D18=SUM(D12:D17) -> TRUE | E33: =E18=SUM(E12:E17) -> TRUE | F33: =F18=SUM(F12:F17) -> TRUE | G33: =G18=SUM(G12:G17) -> TRUE
B35: TOTAL | D35: =D27=SUM(D21:D26) -> TRUE | E35: =E27=SUM(E21:E26) -> TRUE | F35: =F27=SUM(F21:F26) -> TRUE | G35: =G27=SUM(G21:G26) -> TRUE | I35: =I27=SUM(I21:I26) -> TRUE | J35: =J27=SUM(J21:J26) -> TRUE
E69: =C69-G17 -> 0

Sheet Recaudo ENEL
B2: OPORTUNO | C2: ASE | D2: VALOR 1° Q | E2: NUMERO REG. 1°Q | F2: VALOR 2° Q | G2: NUMERO REG. 2°Q
C3: 1 | D3: 16020970408 | E3: 330319 | F3: 17277226302 | G3: 316936
C4: 2 | D4: 11733539858 | E4: 232298 | F4: 19264884848 | G4: 396694
C5: 3 | D5: 9618825681 | E5: 222340 | F5: 15047689272 | G5: 273948
C6: 4 | D6: 10290225466 | E6: 177955 | F6: 7298795841 | G6: 142161
C7: 5 | D7: 8111886280 | E7: 159077 | F7: 11700424846 | G7: 249311
C8: X
D9: 55775447693 | E9: 1121989 | F9: 70589021109 | G9: 1379050
C11: ASE | D11: VALOR 1° Q | E11: NUMERO REG. 1°Q | F11: VALOR 2° Q | G11: NUMERO REG. 2°Q
B12: EXTEMP. | C12: 1 | D12: 223833110 | E12: 3064 | F12: 208241806 | G12: 4505
C13: 2 | D13: 99273804 | E13: 1926 | F13: 47318959 | G13: 914
C14: 3 | D14: 66145670 | E14: 1462 | F14: 96850450 | G14: 2077
C15: 4 | D15: 85892126 | E15: 1255 | F15: 96874840 | G15: 2369
C16: 5 | D16: 166326259 | E16: 2744 | F16: 80297730 | G16: 1887
C17: X
D18: 641470969 | E18: 10451 | F18: 529583785 | G18: 11752
C20: ASE | D20: VALOR 1° Q | E20: NUMERO REG. 1°Q | F20: VALOR 2° Q | G20: NUMERO REG. 2°Q | I20: VALOR TOTAL MES | J20: NUMERO REGISTROS MES
B21: TOTAL | C21: 1 | D21: 16244803518 | E21: 333383 | F21: 17485468108 | G21: 321441 | I21: 32905491709 | J21: 610479
C22: 2 | D22: 11832813662 | E22: 234224 | F22: 19312203807 | G22: 397608 | I22: 30923523804 | J22: 641357
C23: 3 | D23: 9684971351 | E23: 223802 | F23: 15144539722 | G23: 276025 | I23: 23712173173 | J23: 494676
C24: 4 | D24: 10376117592 | E24: 179210 | F24: 7395670681 | G24: 144530 | I24: 17016509002 | J24: 301033
C25: 5 | D25: 8278212539 | E25: 161821 | F25: 11780722576 | G25: 251198 | I25: 20003839166 | J25: 405269
C26: X | I26: 0 | J26: 0
D27: 56416918662 | E27: 1132440 | F27: 71118604894 | G27: 1390802 | I27: 124561536854 | J27: 2452814
B31: OPORTUNO | D31: =D9=SUM(D3:D8) -> TRUE | E31: =E9=SUM(E3:E8) -> TRUE | F31: =F9=SUM(F3:F8) -> TRUE | G31: =G9=SUM(G3:G8) -> TRUE
B33: EXTEMP. | D33: =D18=SUM(D12:D17) -> TRUE | E33: =E18=SUM(E12:E17) -> TRUE | F33: =F18=SUM(F12:F17) -> TRUE | G33: =G18=SUM(G12:G17) -> TRUE
B35: TOTAL | D35: =D27=SUM(D21:D26) -> TRUE | E35: =E27=SUM(E21:E26) -> TRUE | F35: =F27=SUM(F21:F26) -> TRUE | G35: =G27=SUM(G21:G26) -> TRUE | I35: =I27=SUM(I21:I26) -> TRUE | J35: =J27=SUM(J21:J26) -> TRUE
E69: =C69-G17 -> 0

Sheet Recaudo ENERBIT
B2: OPORTUNO | C2: ASE | D2: VALOR 1° Q | E2: NUMERO REG. 1°Q | F2: VALOR 2° Q | G2: NUMERO REG. 2°Q
C3: 1 | D3: 0 | E3: 0 | F3: 0 | G3: 0
C4: 2 | D4: 0 | E4: 0 | F4: 0 | G4: 0
C5: 3 | D5: 0 | E5: 0 | F5: 0 | G5: 0
C6: 4 | D6: 0 | E6: 0 | F6: 0 | G6: 0
C7: 5 | D7: 129429946 | E7: 2854 | F7: 32068500 | G7: 539
C8: X
D9: 129429946 | E9: 2854 | F9: 32068500 | G9: 539
C11: ASE | D11: VALOR 1° Q | E11: NUMERO REG. 1°Q | F11: VALOR 2° Q | G11: NUMERO REG. 2°Q
B12: EXTEMP. | C12: 1 | D12: 0 | E12: 0 | F12: 0 | G12: 0
C13: 2 | D13: 0 | E13: 0 | F13: 0 | G13: 0
C14: 3 | D14: 0 | E14: 0 | F14: 0 | G14: 0
C15: 4 | D15: 0 | E15: 0 | F15: 0 | G15: 0
C16: 5 | D16: 106710 | E16: 1 | F16: 488120 | G16: 11
C17: X
D18: 106710 | E18: 1 | F18: 488120 | G18: 11
C20: ASE | D20: VALOR 1° Q | E20: NUMERO REG. 1°Q | F20: VALOR 2° Q | G20: NUMERO REG. 2°Q | I20: VALOR TOTAL MES | J20: NUMERO REGISTROS MES
B21: TOTAL | C21: 1 | D21: 0 | E21: 0 | F21: 0 | G21: 0 | I21: 0 | J21: 0
C22: 2 | D22: 0 | E22: 0 | F22: 0 | G22: 0 | I22: 0 | J22: 0
C23: 3 | D23: 0 | E23: 0 | F23: 0 | G23: 0 | I23: 0 | J23: 0
C24: 4 | D24: 0 | E24: 0 | F24: 0 | G24: 0 | I24: 0 | J24: 0
C25: 5 | D25: 129536656 | E25: 2855 | F25: 32556620 | G25: 550 | I25: 158181979 | J25: 3400
C26: X | I26: 0 | J26: 0
D27: 129536656 | E27: 2855 | F27: 32556620 | G27: 550 | I27: 158181979 | J27: 3400
B31: OPORTUNO | D31: =D9=SUM(D3:D8) -> TRUE | E31: =E9=SUM(E3:E8) -> TRUE | F31: =F9=SUM(F3:F8) -> TRUE | G31: =G9=SUM(G3:G8) -> TRUE
B33: EXTEMP. | D33: =D18=SUM(D12:D17) -> TRUE | E33: =E18=SUM(E12:E17) -> TRUE | F33: =F18=SUM(F12:F17) -> TRUE | G33: =G18=SUM(G12:G17) -> TRUE
B35: TOTAL | D35: =D27=SUM(D21:D26) -> TRUE | E35: =E27=SUM(E21:E26) -> TRUE | F35: =F27=SUM(F21:F26) -> TRUE | G35: =G27=SUM(G21:G26) -> TRUE | I35: =I27=SUM(I21:I26) -> TRUE | J35: =J27=SUM(J21:J26) -> TRUE
E69: =C69-G17 -> 0

Sheet Recaudo EAAB + Ciud Limp
B2: Ciudad Limpia - Prestador | C2: ASE | D2: VALOR 1° Q | E2: NUMERO REG. 1°Q | F2: VALOR 2° Q | G2: NUMERO REG. 2°Q
C3: 1 | D3: 0 | E3: 0 | F3: 0 | G3: 0
C4: 2 | D4: 0 | E4: 0 | F4: 0 | G4: 0
C5: 3 | D5: 0 | E5: 0 | F5: 0 | G5: 0
C6: 4 | D6: 0 | E6: 0 | F6: 0 | G6: 0
C7: 5 | D7: 0 | E7: 0 | F7: 0 | G7: 0
C8: X
D9: 0 | E9: 0 | F9: 0 | G9: 0
C11: ASE | D11: VALOR 1° Q | E11: NUMERO REG. 1°Q | F11: VALOR 2° Q | G11: NUMERO REG. 2°Q
B12: EAAB - Prestador | C12: 1 | D12: 0 | E12: 0 | F12: 0 | G12: 0
C13: 2 | D13: 0 | E13: 0 | F13: 0 | G13: 0
C14: 3 | D14: 0 | E14: 0 | F14: 0 | G14: 0
C15: 4 | D15: 0 | E15: 0 | F15: 0 | G15: 0
C16: 5 | D16: 0 | E16: 0 | F16: 0 | G16: 0
C17: X
D18: 0 | E18: 0 | F18: 0 | G18: 0
C20: ASE | D20: VALOR 1° Q | E20: NUMERO REG. 1°Q | F20: VALOR 2° Q | G20: NUMERO REG. 2°Q | I20: VALOR TOTAL MES | J20: NUMERO REGISTROS MES
B21: TOTAL | C21: 1 | D21: 0 | E21: 0 | F21: 0 | G21: 0 | I21: 0 | J21: 0
C22: 2 | D22: 0 | E22: 0 | F22: 0 | G22: 0 | I22: 0 | J22: 0
C23: 3 | D23: 0 | E23: 0 | F23: 0 | G23: 0 | I23: 0 | J23: 0
C24: 4 | D24: 0 | E24: 0 | F24: 0 | G24: 0 | I24: 0 | J24: 0
C25: 5 | D25: 0 | E25: 0 | F25: 0 | G25: 0 | I25: 0 | J25: 0
C26: X | I26: 0 | J26: 0
D27: 0 | E27: 0 | F27: 0 | G27: 0 | I27: 0 | J27: 0
B31: OPORTUNO | D31: =D9=SUM(D3:D8) -> TRUE | E31: =E9=SUM(E3:E8) -> TRUE | F31: =F9=SUM(F3:F8) -> TRUE | G31: =G9=SUM(G3:G8) -> TRUE
B33: EXTEMP. | D33: =D18=SUM(D12:D17) -> TRUE | E33: =E18=SUM(E12:E17) -> TRUE | F33: =F18=SUM(F12:F17) -> TRUE | G33: =G18=SUM(G12:G17) -> TRUE
B35: TOTAL | D35: =D27=SUM(D21:D26) -> TRUE | E35: =E27=SUM(E21:E26) -> TRUE | F35: =F27=SUM(F21:F26) -> TRUE | G35: =G27=SUM(G21:G26) -> TRUE | I35: =I27=SUM(I21:I26) -> TRUE | J35: =J27=SUM(J21:J26) -> TRUE

Sheet Recaudo Directa Occidente
B2: OPORTUNO | C2: ASE | D2: VALOR 1° Q | E2: NUMERO REG. 1°Q | F2: VALOR 2° Q | G2: NUMERO REG. 2°Q
C3: 1 | D3: 335015748 | E3: 1590 | F3: 708118766 | G3: 2516
C4: 2 | D4: 389025865 | E4: 2713 | F4: 2044964380 | G4: 10424
C5: 3 | D5: 346289622 | E5: 1123 | F5: 799641564 | G5: 2133
C6: 4 | D6: 236541566 | E6: 1643 | F6: 769620840 | G6: 4462
C7: 5 | D7: 155743651 | E7: 776 | F7: 305626540 | G7: 1484
C8: X | D8: 0 | E8: 0 | F8: 0 | G8: 0
D9: 1462616452 | E9: 7845 | F9: 4627972090 | G9: 21019
C11: ASE | D11: VALOR 1° Q | E11: NUMERO REG. 1°Q | F11: VALOR 2° Q | G11: NUMERO REG. 2°Q
B12: EXTEMP. | C12: 1 | D12: 205459944 | E12: 70 | F12: 202466152 | G12: 535
C13: 2 | D13: 33195420 | E13: 58 | F13: 341841786 | G13: 623
C14: 3 | D14: 126229443 | E14: 55 | F14: 469277064 | G14: 248
C15: 4 | D15: 2600820 | E15: 21 | F15: 208355087 | G15: 216
C16: 5 | D16: 25989911 | E16: 18 | F16: 35584035 | G16: 152
C17: X | D17: 0 | E17: 0 | F17: 0 | G17: 0
D18: 393475538 | E18: 222 | F18: 1257524124 | G18: 1774
C20: ASE | D20: VALOR 1° Q | E20: NUMERO REG. 1°Q | F20: VALOR 2° Q | G20: NUMERO REG. 2°Q | I20: VALOR TOTAL MES | J20: NUMERO REGISTROS MES
B21: TOTAL | C21: 1 | D21: 540475692 | E21: 1660 | F21: 910584918 | G21: 3051 | I21: 1345789409 | J21: 4527
C22: 2 | D22: 422221285 | E22: 2771 | F22: 2386806166 | G22: 11047 | I22: 1848167463 | J22: 12515
C23: 3 | D23: 472519065 | E23: 1178 | F23: 1268918628 | G23: 2381 | I23: 1717689584 | J23: 3716
C24: 4 | D24: 239142386 | E24: 1664 | F24: 977975927 | G24: 4678 | I24: 725781903 | J24: 4147
C25: 5 | D25: 181733562 | E25: 794 | F25: 341210575 | G25: 1636 | I25: 503232683 | J25: 2227
C26: X | D26: 0 | E26: 0 | F26: 0 | G26: 0 | I26: 0 | J26: 0
D27: 1856091990 | E27: 8067 | F27: 5885496214 | G27: 22793 | I27: 6140661042 | J27: 27132
B31: OPORTUNO | D31: =D9=SUM(D3:D8) -> TRUE | E31: =E9=SUM(E3:E8) -> TRUE | F31: =F9=SUM(F3:F8) -> TRUE | G31: =G9=SUM(G3:G8) -> TRUE
B33: EXTEMP. | D33: =D18=SUM(D12:D17) -> TRUE | E33: =E18=SUM(E12:E17) -> TRUE | F33: =F18=SUM(F12:F17) -> TRUE | G33: =G18=SUM(G12:G17) -> TRUE
B35: TOTAL | D35: =D27=SUM(D21:D26) -> TRUE | E35: =E27=SUM(E21:E26) -> TRUE | F35: =F27=SUM(F21:F26) -> TRUE | G35: =G27=SUM(G21:G26) -> TRUE | I35: =I27=SUM(I21:I26) -> TRUE | J35: =J27=SUM(J21:J26) -> TRUE
E69: =C69-G17 -> 0

Sheet REPORTE RECAUDO x BANCO
C1: ENEL | D1: CIUDAD LIMPIA | E1: EAB | F1: NUEVO ESQUEMA | G1: ENERBIT | H1: OCCIDENTE | I1: Total
B2: 1-APLICADOS A FACTURACION | C2: =C13+C23+C32+C41+C51 -> 6.7949268e+10 | D2: =D13+D23+D32+D41+D51 -> 0 | E2: =E13+E23+E32+E41+E51 -> 0 | F2: =F13+F23+F32+F41+F51 -> 17028090 | G2: =G13+G23+G32+G41+G51 -> 26864220 | H2: =H13+H23+H32+H41+H51 -> 4.1068552e+09 | I2: =SUM(C2:H2) -> 7.2100015e+10
B3: 2-SALDOS A FAVOR GENERADOS | C3: =C14+C24+C33+C42+C52 -> 2.3671717e+08 | D3: =D14+D24+D33+D42+D52 -> 0 | E3: =E14+E24+E33+E42+E52 -> 0 | F3: =F14+F24+F33+F42+F52 -> 23089310 | G3: =G14+G24+G33+G42+G52 -> 1781103 | H3: =H14+H24+H33+H42+H52 -> 1.3687274e+08 | I3: =SUM(C3:H3) -> 3.9846032e+08
B4: 3-APLICADOS A FINANCIACIONES NUEVAS | C4: =C15+C25+C34+C43+C53 -> 0 | D4: =D15+D25+D34+D43+D53 -> 0 | E4: =E15+E25+E34+E43+E53 -> 0 | F4: =F15+F25+F34+F43+F53 -> 0 | G4: =G15+G25+G34+G43+G53 -> 0 | H4: =H15+H25+H34+H43+H53 -> 40841134 | I4: =SUM(C4:H4) -> 40841134
B5: 7-APLICADOS A RECIBOS SERVICIOS ESPECIALES | C5: =C16+C26+C35+C44+C54 -> 0 | D5: =D16+D26+D35+D44+D54 -> 0 | E5: =E16+E26+E35+E44+E54 -> 0 | F5: =F16+F26+F35+F44+F54 -> 0 | G5: =G16+G26+G35+G44+G54 -> 0 | H5: =H16+H26+H35+H44+H54 -> 0 | I5: =SUM(C5:H5) -> 0
B6: Total | C6: =SUM(C2:C5) -> 68185984867 | D6: =SUM(D2:D5) -> 0 | E6: =SUM(E2:E5) -> 0 | F6: =SUM(F2:F5) -> 40117400 | G6: =SUM(G2:G5) -> 28645323 | H6: =SUM(H2:H5) -> 4.2845691e+09 | I6: =SUM(I2:I5) -> 7.2539317e+10
C7: =C6=(C17+C27+C36+C45+C55) -> TRUE | D7: =D6=(D17+D27+D36+D45+D55) -> TRUE | E7: =E6=(E17+E27+E36+E45+E55) -> TRUE | F7: =F6=(F17+F27+F36+F45+F55) -> TRUE | H7: =H6=(H17+H27+H36+H45+H55) -> TRUE | I7: =I6=(I17+I27+I36+I45+I55) -> TRUE
B10: ASE 1
B11: Resumen Recaudo Aplicado Por Servicio
C12: ENEL | D12: CIUDAD LIMPIA | E12: EAB | F12: NUEVO ESQUEMA | G12: ENERBIT | H12: OCCIDENTE | I12: Total
B13: 1-APLICADOS A FACTURACION | C13: 17445127414 | H13: 878866230 | I13: =SUM(C13:H13) -> 1.7353338e+10 | J13: =SUM(C13:H13)=I13 -> TRUE
B14: 2-SALDOS A FAVOR GENERADOS | C14: 40340694 | H14: 20016520 | I14: =SUM(C14:H14) -> 1.0093103e+08 | J14: =SUM(C14:H14)=I14 -> TRUE
B15: 3-APLICADOS A FINANCIACIONES NUEVAS | C15: 0 | H15: 11702168 | I15: =SUM(C15:H15) -> 11733000 | J15: =SUM(C15:H15)=I15 -> TRUE
B16: 7-APLICADOS A RECIBOS SERVICIOS ESPECIALES | C16: 0 | H16: 0 | I16: =SUM(C16:H16) -> 0 | J16: =SUM(C16:H16)=I16 -> TRUE
B17: Total | C17: =SUM(C13:C16) -> 16660688191 | D17: =SUM(D13:D16) -> 0 | E17: =SUM(E13:E16) -> 0 | F17: =SUM(F13:F16) -> 0 | G17: =SUM(G13:G16) -> 0 | H17: =SUM(H13:H16) -> 805313717 | I17: =SUM(I13:I16) -> 17466001908 | J17: =SUM(C17:H17)=I17 -> TRUE
B20: ASE 2
B21: Resumen Recaudo Aplicado Por Servicio
C22: ENEL | D22: CIUDAD LIMPIA | E22: EAB | F22: NUEVO ESQUEMA | G22: ENERBIT | H22: OCCIDENTE | I22: Total
B23: 1-APLICADOS A FACTURACION | C23: 1.9260091e+10 | E23: 0 | F23: 9350210 | H23: 2260522795 | I23: =SUM(C23:H23) -> 20405722762 | J23: =SUM(C23:H23)=I23 -> TRUE
B24: 2-SALDOS A FAVOR GENERADOS | C24: 53772356 | E24: 0 | F24: 9710980 | H24: 126283371 | I24: =SUM(C24:H24) -> 136534753 | J24: =SUM(C24:H24)=I24 -> TRUE
B25: 3-APLICADOS A FINANCIACIONES NUEVAS | C25: 0 | E25: 0 | F25: 0 | H25: 0 | I25: =SUM(C25:H25) -> 0 | J25: =SUM(C25:H25)=I25 -> TRUE
B26: 7-APLICADOS A RECIBOS SERVICIOS ESPECIALES | C26: 0 | F26: 0 | H26: 0 | I26: =SUM(C26:H26) -> 0 | J26: =SUM(C26:H26)=I26 -> TRUE
B27: Total | C27: =SUM(C23:C26) -> 19092079577 | D27: =SUM(D23:D26) -> 0 | E27: =SUM(E23:E26) -> 0 | F27: =SUM(F23:F26) -> 24231760 | G27: =SUM(G23:G26) -> 0 | H27: =SUM(H23:H26) -> 1425946178 | I27: =SUM(I23:I26) -> 20542257515 | J27: =SUM(C27:H27)=I27 -> TRUE
B29: ASE 3
B30: Resumen Recaudo Aplicado Por Servicio
C31: ENEL | D31: CIUDAD LIMPIA | E31: EAB | F31: NUEVO ESQUEMA | G31: ENERBIT | H31: OCCIDENTE | I31: Total
B32: 1-APLICADOS A FACTURACION | C32: 15124893786 | F32: 0 | H32: 1.2559242e+09 | I32: =SUM(C32:H32) -> 1.5238046e+10 | J32: =SUM(C32:H32)=I32 -> TRUE
B33: 2-SALDOS A FAVOR GENERADOS | C33: 20418516 | F33: 0 | H33: 10719555 | I33: =SUM(C33:H33) -> 58884033 | J33: =SUM(C33:H33)=I33 -> TRUE
B34: 3-APLICADOS A FINANCIACIONES NUEVAS | C34: 0 | F34: 0 | H34: 2274841.8 | I34: =SUM(C34:H34) -> 2482198.7 | J34: =SUM(C34:H34)=I34 -> TRUE
B35: 7-APLICADOS A RECIBOS SERVICIOS ESPECIALES | C35: 0 | F35: 0 | H35: 0 | I35: =SUM(C35:H35) -> 0 | J35: =SUM(C35:H35)=I35 -> TRUE
B36: Total | C36: =SUM(C32:C35) -> 14054241942 | D36: =SUM(D32:D35) -> 0 | E36: =SUM(E32:E35) -> 0 | F36: =SUM(F32:F35) -> 0 | G36: =SUM(G32:G35) -> 0 | H36: =SUM(H32:H35) -> 1245170519 | I36: =SUM(I32:I35) -> 15299412461 | J36: =SUM(C36:H36)=I36 -> TRUE
B38: ASE 4
B39: Resumen Recaudo Aplicado Por Servicio
C40: ENEL | D40: CIUDAD LIMPIA | E40: EAB | F40: NUEVO ESQUEMA | G40: ENERBIT | H40: OCCIDENTE | I40: Total
B41: 1-APLICADOS A FACTURACION | C41: 7358390426 | E41: 0 | F41: 4363050 | H41: 9.083621e+08 | I41: =SUM(C41:H41) -> 7.0556533e+09 | J41: =SUM(C41:H41)=I41 -> TRUE
B42: 2-SALDOS A FAVOR GENERADOS | C42: 37713515 | E42: 0 | F42: 4481330 | H42: 57223143 | I42: =SUM(C42:H42) -> 73726637 | J42: =SUM(C42:H42)=I42 -> TRUE
B43: 3-APLICADOS A FINANCIACIONES NUEVAS | C43: 0 | E43: 0 | F43: 0 | H43: 12390685 | I43: =SUM(C43:H43) -> 25967508 | J43: =SUM(C43:H43)=I43 -> TRUE
B44: 7-APLICADOS A RECIBOS SERVICIOS ESPECIALES | C44: 0 | F44: 0 | H44: 0 | I44: =SUM(C44:H44) -> 0 | J44: =SUM(C44:H44)=I44 -> TRUE
B45: Total | C45: =SUM(C41:C44) -> 6652822320 | D45: =SUM(D41:D44) -> 0 | E45: =SUM(E41:E44) -> 0 | F45: =SUM(F41:F44) -> 15885640 | G45: =SUM(G41:G44) -> 0 | H45: =SUM(H41:H44) -> 4.8663952e+08 | I45: =SUM(I41:I44) -> 7155347477 | J45: =SUM(C45:H45)=I45 -> TRUE
B48: ASE 5
B49: Resumen Recaudo Aplicado Por Servicio
C50: ENEL | D50: CIUDAD LIMPIA | E50: EAB | F50: NUEVO ESQUEMA | G50: ENERBIT | H50: OCCIDENTE | I50: Total
B51: 1-APLICADOS A FACTURACION | C51: 11757334219 | G51: 28784210 | H51: 3.2889572e+08 | I51: =SUM(C51:H51) -> 1.2047255e+10 | J51: =SUM(C51:H51)=I51 -> TRUE
B52: 2-SALDOS A FAVOR GENERADOS | C52: 23895807 | G52: 3772410 | H52: 11551639 | I52: =SUM(C52:H52) -> 28383866 | J52: =SUM(C52:H52)=I52 -> TRUE
B53: 3-APLICADOS A FINANCIACIONES NUEVAS | C53: 0 | G53: 0 | H53: 763212.95 | I53: =SUM(C53:H53) -> 658426.44 | J53: =SUM(C53:H53)=I53 -> TRUE
B54: 7-APLICADOS A RECIBOS SERVICIOS ESPECIALES | C54: 0 | G54: 0 | H54: 0 | I54: =SUM(C54:H54) -> 0 | J54: =SUM(C54:H54)=I54 -> TRUE
B55: Total | C55: =SUM(C51:C54) -> 11726152837 | D55: =SUM(D51:D54) -> 0 | E55: =SUM(E51:E54) -> 0 | F55: =SUM(F51:F54) -> 0 | G55: =SUM(G51:G54) -> 28645323 | H55: =SUM(H51:H54) -> 321499121 | I55: =SUM(I51:I54) -> 12076297281 | J55: =SUM(C55:H55)=I55 -> TRUE
B59: QUINCENA | C59: 2 | D59: OJO/// DILIGENCIAR
B62: Recaudo ENEL - ASE 1 | C62: =IF($C$59=1,'Recaudo ENEL'!D21,'Recaudo ENEL'!F21) -> 16660688191 | D62: =C17=C62 -> TRUE | E62: =C17-C62 -> 0
B63: Recaudo ENERBIT - ASE 1 | C63: =IF($C$59=1,'Recaudo ENERBIT'!D21,'Recaudo ENERBIT'!F21) -> 0 | D63: =G17=C63 -> TRUE | E63: =G17-C63 -> 0
B64: Recaudo Reciprocidad EAAB - ASE 2 | C64: =IF($C$59=1,'Recaudo EAAB Reciprocidad'!D22,'Recaudo EAAB Reciprocidad'!F22) -> 24231760 | D64: =F27=C64 -> TRUE | E64: =F27-C64 -> 0
B65: Recaudo ENEL - ASE 2 | C65: =IF($C$59=1,'Recaudo ENEL'!D22,'Recaudo ENEL'!F22) -> 19090710142 | D65: =C27=C65 -> FALSE | E65: =C27-C65 -> 1369435 | F65: ok
B66: Recaudo ENERBIT - ASE 2 | C66: =IF($C$59=1,'Recaudo ENERBIT'!D22,'Recaudo ENERBIT'!F22) -> 0 | D66: =G27=C66 -> TRUE | E66: =G27-C66 -> 0
B67: Recaudo ENEL - ASE 3 | C67: =IF($C$59=1,'Recaudo ENEL'!D23,'Recaudo ENEL'!F23) -> 14027201822 | D67: =C36=C67 -> FALSE | E67: =C36-C67 -> 27040120 | F67: ok
B68: Recaudo ENERBIT - ASE 3 | C68: =IF($C$59=1,'Recaudo ENERBIT'!D23,'Recaudo ENERBIT'!F23) -> 0 | D68: =G36=C68 -> TRUE | E68: =G36-C68 -> 0
B69: Recaudo Reciprocidad EAAB - ASE 4 | C69: =IF($C$59=1,'Recaudo EAAB Reciprocidad'!D24,'Recaudo EAAB Reciprocidad'!F24) -> 15885640 | D69: =F45=C69 -> TRUE | E69: =F45-C69 -> 0
B70: Recaudo ENEL - ASE 4 | C70: =IF($C$59=1,'Recaudo ENEL'!D24,'Recaudo ENEL'!F24) -> 6640391410 | D70: =C45=C70 -> FALSE | E70: =C45-C70 -> 12430910 | F70: ok
B71: Recaudo ENERBIT - ASE 4 | C71: =IF($C$59=1,'Recaudo ENERBIT'!D24,'Recaudo ENERBIT'!F24) -> 0 | D71: =G45=C71 -> TRUE | E71: =G45-C71 -> 0
B72: Recaudo ENEL - ASE 5 | C72: =IF($C$59=1,'Recaudo ENEL'!D25,'Recaudo ENEL'!F25) -> 11725626627 | D72: =C55=C72 -> FALSE | E72: =C55-C72 -> 526210 | F72: ok
B73: Recaudo ENERBIT - ASE 5 | C73: =IF($C$59=1,'Recaudo ENERBIT'!D25,'Recaudo ENERBIT'!F25) -> 28645323 | D73: =G55=C73 -> TRUE | E73: =G55-C73 -> 0
B75: Recaudo Banco Occidente ASE 1 | C75: =IF($C$59=1,'Recaudo Directa Occidente'!D21,'Recaudo Directa Occidente'!F21) -> 805313717 | D75: =C75=H17 -> TRUE | E75: =C75-H17 -> 0
B76: Recaudo Banco Occidente ASE 2 | C76: =IF($C$59=1,'Recaudo Directa Occidente'!D22,'Recaudo Directa Occidente'!F22) -> 1425946178 | D76: =C76=H27 -> TRUE | E76: =C76-H27 -> 0
B77: Recaudo Banco Occidente ASE 3 | C77: =IF($C$59=1,'Recaudo Directa Occidente'!D23,'Recaudo Directa Occidente'!F23) -> 1245170519 | D77: =C77=H36 -> TRUE | E77: =C77-H36 -> 0
B78: Recaudo Banco Occidente ASE 4 | C78: =IF($C$59=1,'Recaudo Directa Occidente'!D24,'Recaudo Directa Occidente'!F24) -> 486639517 | D78: =C78=H45 -> TRUE | E78: =C78-H45 -> 0
B79: Recaudo Banco Occidente ASE 5 | C79: =IF($C$59=1,'Recaudo Directa Occidente'!D25,'Recaudo Directa Occidente'!F25) -> 321499121 | D79: =C79=H55 -> TRUE | E79: =C79-H55 -> 0

Sheet ANT EXT-REV
C1: ASE 1 | E1: ASE 2 | G1: ASE 3 | I1: ASE 4 | K1: ASE 5 | M1: TOTAL
C2: REPORTE 3 | D2: REPORTE 4 | E2: REPORTE 3 | F2: REPORTE 4 | G2: REPORTE 3 | H2: REPORTE 4 | I2: REPORTE 3 | J2: REPORTE 4 | K2: REPORTE 3 | L2: REPORTE 4 | M2: REPORTE 3 | N2: REPORTE 4
B3: APLICADO | C3: =C11+C19+C27+C35+C43 -> 49580 | D3: =D11+D19+D27+D35+D43 -> -16536713 | E3: =E11+E19+E27+E35+E43 -> 56190070 | F3: =F11+F19+F27+F35+F43 -> -71069759 | G3: =G11+G19+G27+G35+G43 -> 1307680 | H3: =H11+H19+H27+H35+H43 -> -32310980 | I3: =I11+I19+I27+I35+I43 -> 4343101 | J3: =J11+J19+J27+J35+J43 -> -33738104 | ... L3: =L11+L19+L27+L35+L43 -> -3092375.5 | M3: =C3+E3+G3+I3+K3 -> 62332280 | N3: =D3+F3+H3+J3+L3 -> -1.5674793e+08 | P3: =N3=(-VALIDACION_TOTAL!M9) -> TRUE
B4: ANTICIPOS | C4: =C12+C20+C28+C36+C44 -> 82340 | D4: =D12+D20+D28+D36+D44 -> -182537.91 | E4: =E12+E20+E28+E36+E44 -> 5228610 | F4: =F12+F20+F28+F36+F44 -> 0 | G4: =G12+G20+G28+G36+G44 -> 0 | H4: =H12+H20+H28+H36+H44 -> -2423600.2 | I4: =I12+I20+I28+I36+I44 -> 14538094 | J4: =J12+J20+J28+J36+J44 -> -14979760 | ... L4: =L12+L20+L28+L36+L44 -> -215053.47 | M4: =C4+E4+G4+I4+K4 -> 19936594 | N4: =D4+F4+H4+J4+L4 -> -17800951 | P4: =N4=(-'CONSOLIDADO_TOTAL RECAUDO'!L131) -> TRUE
B5: TOTAL | C5: =SUM(C3:C4) -> 131920 | D5: =SUM(D3:D4) -> -16719251 | E5: =SUM(E3:E4) -> 61418680 | F5: =SUM(F3:F4) -> -71069759 | G5: =SUM(G3:G4) -> 1307680 | H5: =SUM(H3:H4) -> -34734580 | I5: =SUM(I3:I4) -> 18881195 | J5: =SUM(J3:J4) -> -48717864 | ... N5: =SUM(N3:N4) -> -174548883
C6: =C5=(C13+C21+C29+C37+C45) -> TRUE | D6: =D5=(D13+D21+D29+D37+D45) -> TRUE | E6: =E5=(E13+E21+E29+E37+E45) -> TRUE | F6: =F5=(F13+F21+F29+F37+F45) -> TRUE | G6: =G5=(G13+G21+G29+G37+G45) -> TRUE | H6: =H5=(H13+H21+H29+H37+H45) -> TRUE | I6: =I5=(I13+I21+I29+I37+I45) -> TRUE | J6: =J5=(J13+J21+J29+J37+J45) -> TRUE | ... N6: =N5=(N13+N21+N29+N37+N45) -> TRUE
B8: BANCO DE OCCIDENTE
C9: ASE 1 | E9: ASE 2 | G9: ASE 3 | I9: ASE 4 | K9: ASE 5 | M9: TOTAL
C10: REPORTE 3 | D10: REPORTE 4 | E10: REPORTE 3 | F10: REPORTE 4 | G10: REPORTE 3 | H10: REPORTE 4 | I10: REPORTE 3 | J10: REPORTE 4 | K10: REPORTE 3 | L10: REPORTE 4 | M10: REPORTE 3 | N10: REPORTE 4
B11: APLICADO | C11: 0 | D11: -1002751.4 | E11: 111210 | F11: -290750 | G11: 0 | H11: -306659.8 | I11: 691194 | J11: -3233428.3 | K11: 441849 | L11: -1026775.5 | M11: =C11+E11+G11+I11+K11 -> 1244253 | N11: =D11+F11+H11+J11+L11 -> -5860365.1
B12: ANTICIPOS | C12: 82340 | D12: -165648.61 | E12: 1370 | F12: 0 | G12: 0 | H12: -2343750.2 | I12: 2209000 | J12: -14593376 | K12: 87550 | L12: -165773.47 | M12: =C12+E12+G12+I12+K12 -> 2380260 | N12: =D12+F12+H12+J12+L12 -> -17268548
B13: TOTAL | C13: =SUM(C11:C12) -> 82340 | D13: =SUM(D11:D12) -> -1168400 | E13: =SUM(E11:E12) -> 112580 | F13: =SUM(F11:F12) -> -290750 | G13: =SUM(G11:G12) -> 0 | H13: =SUM(H11:H12) -> -2650410 | I13: =SUM(I11:I12) -> 2900194 | J13: =SUM(J11:J12) -> -17826804 | ... N13: =SUM(N11:N12) -> -23128913
B16: EAAB RECIPROCIDAD
C17: ASE 1 | E17: ASE 2 | G17: ASE 3 | I17: ASE 4 | K17: ASE 5 | M17: TOTAL
C18: REPORTE 3 | D18: REPORTE 4 | E18: REPORTE 3 | F18: REPORTE 4 | G18: REPORTE 3 | H18: REPORTE 4 | I18: REPORTE 3 | J18: REPORTE 4 | K18: REPORTE 3 | L18: REPORTE 4 | M18: REPORTE 3 | N18: REPORTE 4
B19: APLICADO | C19: 0 | D19: 0 | E19: 0 | F19: 0 | G19: 0 | H19: 0 | I19: 41900 | J19: -736030 | K19: 0 | L19: 0 | M19: =C19+E19+G19+I19+K19 -> 41900 | N19: =D19+F19+H19+J19+L19 -> -736030
B20: ANTICIPOS | C20: 0 | D20: 0 | E20: 0 | F20: 0 | G20: 0 | H20: 0 | I20: 694130 | J20: 0 | K20: 0 | L20: 0 | M20: =C20+E20+G20+I20+K20 -> 694130 | N20: =D20+F20+H20+J20+L20 -> 0
B21: TOTAL | C21: =SUM(C19:C20) -> 0 | D21: =SUM(D19:D20) -> 0 | E21: =SUM(E19:E20) -> 0 | F21: =SUM(F19:F20) -> 0 | G21: =SUM(G19:G20) -> 0 | H21: =SUM(H19:H20) -> 0 | I21: =SUM(I19:I20) -> 736030 | J21: =SUM(J19:J20) -> -736030 | ... L21: =SUM(L19:L20) -> 0 | M21: =C21+E21+G21+I21+K21 -> 736030 | N21: =SUM(N19:N20) -> -736030
B24: EAAB CIUDAD LIMPIA
C25: ASE 1 | E25: ASE 2 | G25: ASE 3 | I25: ASE 4 | K25: ASE 5 | M25: TOTAL
C26: REPORTE 3 | D26: REPORTE 4 | E26: REPORTE 3 | F26: REPORTE 4 | G26: REPORTE 3 | H26: REPORTE 4 | I26: REPORTE 3 | J26: REPORTE 4 | K26: REPORTE 3 | L26: REPORTE 4 | M26: REPORTE 3 | N26: REPORTE 4
B27: APLICADO | C27: 0 | D27: 0 | E27: 0 | F27: 0 | G27: 0 | H27: 0 | I27: 0 | J27: 0 | K27: 0 | L27: 0 | M27: =C27+E27+G27+I27+K27 -> 0 | N27: =D27+F27+H27+J27+L27 -> 0
B28: ANTICIPOS | C28: 0 | D28: 0 | E28: 0 | F28: 0 | G28: 0 | H28: 0 | I28: 0 | J28: 0 | K28: 0 | L28: 0 | M28: =C28+E28+G28+I28+K28 -> 0 | N28: =D28+F28+H28+J28+L28 -> 0
B29: TOTAL | C29: =SUM(C27:C28) -> 0 | D29: =SUM(D27:D28) -> 0 | E29: =SUM(E27:E28) -> 0 | F29: =SUM(F27:F28) -> 0 | G29: =SUM(G27:G28) -> 0 | H29: =SUM(H27:H28) -> 0 | I29: =SUM(I27:I28) -> 0 | J29: =SUM(J27:J28) -> 0 | ... N29: =SUM(N27:N28) -> 0
B32: ENEL
C33: ASE 1 | E33: ASE 2 | G33: ASE 3 | I33: ASE 4 | K33: ASE 5 | M33: TOTAL
C34: REPORTE 3 | D34: REPORTE 4 | E34: REPORTE 3 | F34: REPORTE 4 | G34: REPORTE 3 | H34: REPORTE 4 | I34: REPORTE 3 | J34: REPORTE 4 | K34: REPORTE 3 | L34: REPORTE 4 | M34: REPORTE 3 | N34: REPORTE 4
B35: APLICADO | C35: 49580 | D35: -15533962 | E35: 56078860 | F35: -70779009 | G35: 1307680 | H35: -32004320 | I35: 3610007 | J35: -29768646 | K35: 0 | L35: -2065600 | M35: =C35+E35+G35+I35+K35 -> 61046127 | N35: =D35+F35+H35+J35+L35 -> -1.5015154e+08
B36: ANTICIPOS | C36: 0 | D36: -16889.3 | E36: 5227240 | F36: 0 | G36: 0 | H36: -79850 | I36: 11634964 | J36: -386384.11 | K36: 0 | L36: -49280 | M36: =C36+E36+G36+I36+K36 -> 16862204 | N36: =D36+F36+H36+J36+L36 -> -532403.41
B37: TOTAL | C37: =SUM(C35:C36) -> 49580 | D37: =SUM(D35:D36) -> -15550851 | E37: =SUM(E35:E36) -> 61306100 | F37: =SUM(F35:F36) -> -70779009 | G37: =SUM(G35:G36) -> 1307680 | H37: =SUM(H35:H36) -> -32084170 | I37: =SUM(I35:I36) -> 15244971 | J37: =SUM(J35:J36) -> -30155030 | ... N37: =SUM(N35:N36) -> -150683940
B40: ENERBIT
C41: ASE 1 | E41: ASE 2 | G41: ASE 3 | I41: ASE 4 | K41: ASE 5 | M41: TOTAL
C42: REPORTE 3 | D42: REPORTE 4 | E42: REPORTE 3 | F42: REPORTE 4 | G42: REPORTE 3 | H42: REPORTE 4 | I42: REPORTE 3 | J42: REPORTE 4 | K42: REPORTE 3 | L42: REPORTE 4 | M42: REPORTE 3 | N42: REPORTE 4
B43: APLICADO | C43: 0 | D43: 0 | E43: 0 | F43: 0 | G43: 0 | H43: 0 | I43: 0 | J43: 0 | K43: 0 | L43: 0 | M43: =C43+E43+G43+I43+K43 -> 0 | N43: =D43+F43+H43+J43+L43 -> 0
B44: ANTICIPOS | C44: 0 | D44: 0 | E44: 0 | F44: 0 | G44: 0 | H44: 0 | I44: 0 | J44: 0 | K44: 0 | L44: 0 | M44: =C44+E44+G44+I44+K44 -> 0 | N44: =D44+F44+H44+J44+L44 -> 0
B45: TOTAL | C45: =SUM(C43:C44) -> 0 | D45: =SUM(D43:D44) -> 0 | E45: =SUM(E43:E44) -> 0 | F45: =SUM(F43:F44) -> 0 | G45: =SUM(G43:G44) -> 0 | H45: =SUM(H43:H44) -> 0 | I45: =SUM(I43:I44) -> 0 | J45: =SUM(J43:J44) -> 0 | ... N45: =SUM(N43:N44) -> 0

Sheet ANTICIPOS USUARIOS
B1: TOTAL | E1: RECIPRCIDAD | H1: ENEL | K1: ENERBIT | N1: OCCIDENTE | Q1: EAAB-CIUDADLIMPIA
B2: ASE | C2: ANTICIPOS GENERADOS POR PAGO | E2: ASE | F2: ANTICIPOS GENERADOS POR PAGO | H2: ASE | I2: ANTICIPOS GENERADOS POR PAGO | K2: ASE | L2: ANTICIPOS GENERADOS POR PAGO | N2: ASE | O2: ANTICIPOS GENERADOS POR PAGO | Q2: ASE | R2: ANTICIPOS GENERADOS POR PAGO | T2: Anticipos generados por pago
B3: 1 | C3: ='REPORTE RECAUDO x BANCO'!I14 -> 1.0093103e+08 | E3: 1 | F3: ='REPORTE RECAUDO x BANCO'!F14 -> 0 | H3: 1 | I3: ='REPORTE RECAUDO x BANCO'!C14 -> 83572548 | K3: 1 | L3: ='REPORTE RECAUDO x BANCO'!G14 -> 0 | N3: 1 | O3: ='REPORTE RECAUDO x BANCO'!H14 -> 17358484 | Q3: 1 | R3: ='REPORTE RECAUDO x BANCO'!D14+'REPORTE RECAUDO x BANCO'!E14 -> 0 | T3: Sale del reporte Recaudo por Bancos.
B4: 2 | C4: ='REPORTE RECAUDO x BANCO'!I24 -> 136534753 | E4: 2 | F4: ='REPORTE RECAUDO x BANCO'!F24 -> 12820520 | H4: 2 | I4: ='REPORTE RECAUDO x BANCO'!C24 -> 44281124 | K4: 2 | L4: ='REPORTE RECAUDO x BANCO'!G24 -> 0 | N4: 2 | O4: ='REPORTE RECAUDO x BANCO'!H24 -> 79433109 | Q4: 2 | R4: ='REPORTE RECAUDO x BANCO'!D24+'REPORTE RECAUDO x BANCO'!E24 -> 0
B5: 3 | C5: ='REPORTE RECAUDO x BANCO'!I33 -> 58884033 | E5: 3 | F5: ='REPORTE RECAUDO x BANCO'!F33 -> 0 | H5: 3 | I5: ='REPORTE RECAUDO x BANCO'!C33 -> 44039530 | K5: 3 | L5: ='REPORTE RECAUDO x BANCO'!G33 -> 0 | N5: 3 | O5: ='REPORTE RECAUDO x BANCO'!H33 -> 14844503 | Q5: 3 | R5: ='REPORTE RECAUDO x BANCO'!D33+'REPORTE RECAUDO x BANCO'!E33 -> 0
B6: 4 | C6: ='REPORTE RECAUDO x BANCO'!I42 -> 73726637 | E6: 4 | F6: ='REPORTE RECAUDO x BANCO'!F42 -> 10268790 | H6: 4 | I6: ='REPORTE RECAUDO x BANCO'!C42 -> 48826052 | K6: 4 | L6: ='REPORTE RECAUDO x BANCO'!G42 -> 0 | N6: 4 | O6: ='REPORTE RECAUDO x BANCO'!H42 -> 14631795 | Q6: 4 | R6: ='REPORTE RECAUDO x BANCO'!D42+'REPORTE RECAUDO x BANCO'!E42 -> 0
B7: 5 | C7: ='REPORTE RECAUDO x BANCO'!I52 -> 28383866 | E7: 5 | F7: ='REPORTE RECAUDO x BANCO'!F52 -> 0 | H7: 5 | I7: ='REPORTE RECAUDO x BANCO'!C52 -> 15997915 | K7: 5 | L7: ='REPORTE RECAUDO x BANCO'!G52 -> 1781103 | N7: 5 | O7: ='REPORTE RECAUDO x BANCO'!H52 -> 10604848 | Q7: 5 | R7: ='REPORTE RECAUDO x BANCO'!D52+'REPORTE RECAUDO x BANCO'!E52 -> 0
C8: =SUM(C3:C7) -> 3.9846032e+08 | F8: =SUM(F3:F7) -> 23089310 | I8: =SUM(I3:I7) -> 2.3671717e+08 | L8: =SUM(L3:L7) -> 1781103 | O8: =SUM(O3:O7) -> 1.3687274e+08 | R8: =SUM(R3:R7) -> 0
C9: =C8='REPORTE RECAUDO x BANCO'!I3 -> TRUE | F9: =F8='REPORTE RECAUDO x BANCO'!F3 -> TRUE | I9: =I8='REPORTE RECAUDO x BANCO'!C3 -> TRUE | L9: =L8='REPORTE RECAUDO x BANCO'!G3 -> TRUE | O9: =O8='REPORTE RECAUDO x BANCO'!H3 -> TRUE | R9: =R8='REPORTE RECAUDO x BANCO'!D3+'REPORTE RECAUDO x BANCO'!E3 -> TRUE
B11: ASE | C11: ANTICIPOS GENERADOS POR EXTEMPORANEOS | E11: ASE | F11: ANTICIPOS GENERADOS POR EXTEMPORANEOS | H11: ASE | I11: ANTICIPOS GENERADOS POR EXTEMPORANEOS | K11: ASE | L11: ANTICIPOS GENERADOS POR EXTEMPORANEOS | N11: ASE | O11: ANTICIPOS GENERADOS POR EXTEMPORANEOS | Q11: ASE | R11: ANTICIPOS GENERADOS POR EXTEMPORANEOS | T11: Anticipos generados por pagos aplicados de reversiones
B12: 1 | C12: ='ANT EXT-REV'!C4 -> 82340 | E12: 1 | F12: ='ANT EXT-REV'!C20 -> 0 | H12: 1 | I12: ='ANT EXT-REV'!C36 -> 0 | K12: 1 | L12: ='ANT EXT-REV'!C44 -> 0 | N12: 1 | O12: ='ANT EXT-REV'!C12 -> 82340 | Q12: 1 | R12: ='ANT EXT-REV'!C28 -> 0 | T12: Sale del reporte Recaudo reversado
B13: 2 | C13: ='ANT EXT-REV'!E4 -> 5228610 | E13: 2 | F13: ='ANT EXT-REV'!E20 -> 0 | H13: 2 | I13: ='ANT EXT-REV'!E36 -> 5227240 | K13: 2 | L13: ='ANT EXT-REV'!E44 -> 0 | N13: 2 | O13: ='ANT EXT-REV'!E12 -> 1370 | Q13: 2 | R13: ='ANT EXT-REV'!E28 -> 0
B14: 3 | C14: ='ANT EXT-REV'!G4 -> 0 | E14: 3 | F14: ='ANT EXT-REV'!G20 -> 0 | H14: 3 | I14: ='ANT EXT-REV'!G36 -> 0 | K14: 3 | L14: ='ANT EXT-REV'!G44 -> 0 | N14: 3 | O14: ='ANT EXT-REV'!G12 -> 0 | Q14: 3 | R14: ='ANT EXT-REV'!G28 -> 0
B15: 4 | C15: ='ANT EXT-REV'!I4 -> 14538094 | E15: 4 | F15: ='ANT EXT-REV'!I20 -> 694130 | H15: 4 | I15: ='ANT EXT-REV'!I36 -> 11634964 | K15: 4 | L15: ='ANT EXT-REV'!I44 -> 0 | N15: 4 | O15: ='ANT EXT-REV'!I12 -> 2209000 | Q15: 4 | R15: ='ANT EXT-REV'!I28 -> 0
B16: 5 | C16: ='ANT EXT-REV'!K4 -> 87550 | E16: 5 | F16: ='ANT EXT-REV'!K20 -> 0 | H16: 5 | I16: ='ANT EXT-REV'!K36 -> 0 | K16: 5 | L16: ='ANT EXT-REV'!K44 -> 0 | N16: 5 | O16: ='ANT EXT-REV'!K12 -> 87550 | Q16: 5 | R16: ='ANT EXT-REV'!K28 -> 0
C17: =SUM(C12:C16) -> 19936594 | F17: =SUM(F12:F16) -> 694130 | I17: =SUM(I12:I16) -> 16862204 | L17: =SUM(L12:L16) -> 0 | O17: =SUM(O12:O16) -> 2380260 | R17: =SUM(R12:R16) -> 0
C18: =C17='ANT EXT-REV'!M4 -> TRUE | F18: =F17='ANT EXT-REV'!M20 -> TRUE | I18: =I17='ANT EXT-REV'!M36 -> TRUE | L18: =L17='ANT EXT-REV'!M44 -> TRUE | O18: =O17='ANT EXT-REV'!M12 -> TRUE | R18: =R17='ANT EXT-REV'!M28 -> TRUE
B20: ASE | C20: ANTICIPOS QUE CARGAN POR REVERSIONES | E20: ASE | F20: ANTICIPOS QUE CARGAN POR REVERSIONES | H20: ASE | I20: ANTICIPOS QUE CARGAN POR REVERSIONES | K20: ASE | L20: ANTICIPOS QUE CARGAN POR REVERSIONES | N20: ASE | O20: ANTICIPOS QUE CARGAN POR REVERSIONES | Q20: ASE | R20: ANTICIPOS QUE CARGAN POR REVERSIONES | T20: Anticipos que cargan de reversiones
B21: 1 | C21: ='ANT EXT-REV'!D4 -> -182537.91 | E21: 1 | F21: ='ANT EXT-REV'!D20 -> 0 | H21: 1 | I21: ='ANT EXT-REV'!D36 -> -16889.3 | K21: 1 | L21: ='ANT EXT-REV'!D44 -> 0 | N21: 1 | O21: ='ANT EXT-REV'!D12 -> -165648.61 | Q21: 1 | R21: ='ANT EXT-REV'!D28 -> 0 | T21: Sale del reporte Recaudo reversado
B22: 2 | C22: ='ANT EXT-REV'!F4 -> 0 | E22: 2 | F22: ='ANT EXT-REV'!F20 -> 0 | H22: 2 | I22: ='ANT EXT-REV'!F36 -> 0 | K22: 2 | L22: ='ANT EXT-REV'!F44 -> 0 | N22: 2 | O22: ='ANT EXT-REV'!F12 -> 0 | Q22: 2 | R22: ='ANT EXT-REV'!F28 -> 0
B23: 3 | C23: ='ANT EXT-REV'!H4 -> -2423600.2 | E23: 3 | F23: ='ANT EXT-REV'!H20 -> 0 | H23: 3 | I23: ='ANT EXT-REV'!H36 -> -79850 | K23: 3 | L23: ='ANT EXT-REV'!H44 -> 0 | N23: 3 | O23: ='ANT EXT-REV'!H12 -> -2343750.2 | Q23: 3 | R23: ='ANT EXT-REV'!H28 -> 0
B24: 4 | C24: ='ANT EXT-REV'!J4 -> -14979760 | E24: 4 | F24: ='ANT EXT-REV'!J20 -> 0 | H24: 4 | I24: ='ANT EXT-REV'!J36 -> -386384.11 | K24: 4 | L24: ='ANT EXT-REV'!J44 -> 0 | N24: 4 | O24: ='ANT EXT-REV'!J12 -> -14593376 | Q24: 4 | R24: ='ANT EXT-REV'!J28 -> 0
B25: 5 | C25: ='ANT EXT-REV'!L4 -> -215053.47 | E25: 5 | F25: ='ANT EXT-REV'!L20 -> 0 | H25: 5 | I25: ='ANT EXT-REV'!L36 -> -49280 | K25: 5 | L25: ='ANT EXT-REV'!L44 -> 0 | N25: 5 | O25: ='ANT EXT-REV'!L12 -> -165773.47 | Q25: 5 | R25: ='ANT EXT-REV'!L28 -> 0
C26: =SUM(C21:C25) -> -17800951 | F26: =SUM(F21:F25) -> 0 | I26: =SUM(I21:I25) -> -532403.41 | L26: =SUM(L21:L25) -> 0 | O26: =SUM(O21:O25) -> -17268548 | R26: =SUM(R21:R25) -> 0
C27: =C26='ANT EXT-REV'!N4 -> TRUE | F27: =F26='ANT EXT-REV'!N20 -> TRUE | I27: =I26='ANT EXT-REV'!N36 -> TRUE | L27: =L26='ANT EXT-REV'!N44 -> TRUE | O27: =O26='ANT EXT-REV'!N12 -> TRUE | R27: =R26='ANT EXT-REV'!N28 -> TRUE

Sheet BCE SC POR FACT.
C2: ASE | D2: SUBSIDIO | E2: CONTRIBUCION | F2: TOTAL BSC | H2: SISTEMA
C3: 1 | D3: 2.5925147e+09 | E3: -6.2027284e+09 | F3: =D3+E3 -> -3.5894547e+09 | H3: =DetRetri2026072!J9 -> -3589454666 | I3: =F3-H3 -> 0.45000029
C4: 2 | D4: 2.3845105e+09 | E4: -6.6743868e+09 | F4: =D4+E4 -> -3.2411937e+09 | H4: =DetRetri2026072!J10 -> -3241193714 | I4: =F4-H4 -> -0.11000013
C5: 3 | D5: 1.3621272e+09 | E5: -2.1913894e+09 | F5: =D5+E5 -> -8.5324456e+08 | H5: =DetRetri2026072!J11 -> -853244565 | I5: =F5-H5 -> 0.49000001
C6: 4 | D6: 1.8779587e+09 | E6: -2.5841946e+09 | F6: =D6+E6 -> -6.9988271e+08 | H6: =DetRetri2026072!J12 -> -699882713 | I6: =F6-H6 -> -0.37000012
C7: 5 | D7: 1.2141671e+09 | E7: -1.237571e+09 | F7: =D7+E7 -> -82959024 | H7: =DetRetri2026072!J13 -> -82959024 | I7: =F7-H7 -> 0.33999991
F9: =SUM(F3:F7) -> -8.4667347e+09 | H9: =SUM(H3:H7) -> -8466734682 | I9: =F9-H9 -> 0.80000019
H10: =H9=DetRetri2026072!J14 -> TRUE
D11: =SUM(D3:D7) -> -1.7266607e+10 | E11: =SUM(E3:E7) -> 8.7998726e+09 | F11: =SUM(D3:E7) -> -8.4667347e+09
F12: =ROUND(F11,2)=ROUND(F9,2) -> TRUE
F13: =ROUND(F11,2)-ROUND(F9,2) -> 0
D18: ASE | E18: REMUN TOTAL | F18: VALIDA 1 | G18: VALIDA 2 | H18: DIFERENCIA VALIDA 2
D19: 1 | E19: ='CONSOLIDADO_TOTAL RECAUDO'!J104 -> -3.5894547e+09 | F19: =E19=F3 -> TRUE | G19: =E19=H3 -> FALSE | H19: =E19-H3 -> 0.45000029
D20: 2 | E20: ='CONSOLIDADO_TOTAL RECAUDO'!J105 -> -3.2411937e+09 | F20: =E20=F4 -> TRUE | G20: =E20=H4 -> FALSE | H20: =E20-H4 -> -0.11000013
D21: 3 | E21: ='CONSOLIDADO_TOTAL RECAUDO'!J106 -> -8.5324456e+08 | F21: =E21=F5 -> TRUE | G21: =E21=H5 -> FALSE | H21: =E21-H5 -> 0.49000001
D22: 4 | E22: ='CONSOLIDADO_TOTAL RECAUDO'!J107 -> -6.9988271e+08 | F22: =E22=F6 -> TRUE | G22: =E22=H6 -> FALSE | H22: =E22-H6 -> -0.37000012
D23: 5 | E23: ='CONSOLIDADO_TOTAL RECAUDO'!J108 -> -82959024 | F23: =E23=F7 -> TRUE | G23: =E23=H7 -> FALSE | H23: =E23-H7 -> 0.33999991
E24: =SUM(E19:E23) -> -8.4667347e+09 | F24: =E24=F9 -> TRUE | G24: =E24=H9 -> FALSE | H24: =E24-H9 -> 0.80000019

Sheet Reporte Componentes R1
B4: PROMOAMBIENTAL
F5: Total | G5: Componente TDF | H5: Componente TTL | I5: Componente TVIAT | J5: Aprovechamiento | K5: CCSA Prest.Aprov. | L5: SERVICIO ESPECIALES | M5: Componente TCS | N5: Componente TLU | O5: Componente TBL | P5: Componente TRT | Q5: CCSA Prest. No Aprov. | R5: Ajuste Decena | S5: Ajuste Recargo Aseo | T5: Intereses Cte Financiac. Aseo | U5: Exonera-Ajuste Decena Aseo | V5: Exonera-Ajuste Decena Aseo | W5: Exonera-Recargo Aseo | X5: Rec.Intereses | Y5: Intereses Cte Financiac. Aseo | Z5: Rec.Intereses
E6: Vlr Servicio | F6: -9123.9 | G6: -625.08 | H6: -265.56 | I6: -115.95 | J6: -1600.92 | K6: -103.46 | L6: 0 | M6: -907.42 | N6: -759.41 | O6: -3031.34 | P6: -1545.97 | Q6: -168.79 | R6: 0 | S6: 0 | T6: 0 | U6: 0 | V6: 0 | W6: 0 | X6: 0 | Y6: 0 | Z6: 0
D7: O | E7: Total | F7: -9123.9 | G7: -625.08 | H7: -265.56 | I7: -115.95 | J7: -1600.92 | K7: -103.46 | L7: 0 | M7: -907.42 | N7: -759.41 | O7: -3031.34 | P7: -1545.97 | Q7: -168.79 | R7: 0 | S7: 0 | T7: 0 | U7: 0 | V7: 0 | W7: 0 | X7: 0 | Y7: 0 | Z7: 0
C8: OCCIDENTE | D8: Total | F8: -9123.9 | G8: -625.08 | H8: -265.56 | I8: -115.95 | J8: -1600.92 | K8: -103.46 | L8: 0 | M8: -907.42 | N8: -759.41 | O8: -3031.34 | P8: -1545.97 | Q8: -168.79 | R8: 0 | S8: 0 | T8: 0 | U8: 0 | V8: 0 | W8: 0 | X8: 0 | Y8: 0 | Z8: 0
B9: Mes | C9: Total | F9: -9123.9 | G9: -625.08 | H9: -265.56 | I9: -115.95 | J9: -1600.92 | K9: -103.46 | L9: 0 | M9: -907.42 | N9: -759.41 | O9: -3031.34 | P9: -1545.97 | Q9: -168.79 | R9: 0 | S9: 0 | T9: 0 | U9: 0 | V9: 0 | W9: 0 | X9: 0 | Y9: 0 | Z9: 0
A10: AFaseo | B10: Total | F10: -9123.9 | G10: -625.08 | H10: -265.56 | I10: -115.95 | J10: -1600.92 | K10: -103.46 | L10: 0 | M10: -907.42 | N10: -759.41 | O10: -3031.34 | P10: -1545.97 | Q10: -168.79 | R10: 0 | S10: 0 | T10: 0 | U10: 0 | V10: 0 | W10: 0 | X10: 0 | Y10: 0 | Z10: 0
E11: Vlr Servicio | F11: 42369.42 | G11: 2242.46 | H11: 1266.09 | I11: 664.53 | J11: 10026.01 | K11: 372.31 | L11: 0 | M11: 3265.88 | N11: 3109.1 | O11: 14722.61 | P11: 6097.75 | Q11: 607.45 | R11: -4.77 | S11: 0 | T11: 0 | U11: 0 | V11: 0 | W11: 0 | X11: 0 | Y11: 0 | Z11: 0
D12: E | E12: Total | F12: 42369.42 | G12: 2242.46 | H12: 1266.09 | I12: 664.53 | J12: 10026.01 | K12: 372.31 | L12: 0 | M12: 3265.88 | N12: 3109.1 | O12: 14722.61 | P12: 6097.75 | Q12: 607.45 | R12: -4.77 | S12: 0 | T12: 0 | U12: 0 | V12: 0 | W12: 0 | X12: 0 | Y12: 0 | Z12: 0
C13: ENEL | D13: Total | F13: 42369.42 | G13: 2242.46 | H13: 1266.09 | I13: 664.53 | J13: 10026.01 | K13: 372.31 | L13: 0 | M13: 3265.88 | N13: 3109.1 | O13: 14722.61 | P13: 6097.75 | Q13: 607.45 | R13: -4.77 | S13: 0 | T13: 0 | U13: 0 | V13: 0 | W13: 0 | X13: 0 | Y13: 0 | Z13: 0
B14: Aplicacion nuevos x reversion | C14: Total | F14: 42369.42 | G14: 2242.46 | H14: 1266.09 | I14: 664.53 | J14: 10026.01 | K14: 372.31 | L14: 0 | M14: 3265.88 | N14: 3109.1 | O14: 14722.61 | P14: 6097.75 | Q14: 607.45 | R14: -4.77 | S14: 0 | T14: 0 | U14: 0 | V14: 0 | W14: 0 | X14: 0 | Y14: 0 | Z14: 0
E15: Vlr Servicio | F15: 1.7290064e+10 | G15: 8.7567923e+08 | H15: 4.9376165e+08 | I15: 2.5970135e+08 | J15: 4.1207765e+09 | K15: 1.5442379e+08 | L15: 16025088 | M15: 1.357667e+09 | N15: 1.2875919e+09 | O15: 6.0939798e+09 | P15: 2.3783689e+09 | Q15: 2.5208609e+08 | R15: 3156.5 | S15: 0 | T15: 0 | U15: 0 | V15: 0 | W15: 0 | X15: 0 | Y15: 0 | Z15: 0
E16: Vlr Intereses | F16: 3168870.3 | G16: 181699.71 | H16: 94563.09 | I16: 50842.1 | J16: 719172.29 | K16: 28488.91 | L16: 600.77 | M16: 251707.71 | N16: 231457.21 | O16: 1072357.8 | P16: 490967.89 | Q16: 46457.99 | R16: 253.72 | S16: 0 | T16: 301.09 | U16: 0 | V16: 0 | W16: 0 | X16: 0 | Y16: 0 | Z16: 0
D17: E | E17: Total | F17: 1.7293233e+10 | G17: 8.7586093e+08 | H17: 4.9385621e+08 | I17: 2.5975219e+08 | J17: 4.1214957e+09 | K17: 1.5445228e+08 | L17: 16025689 | M17: 1.3579187e+09 | N17: 1.2878233e+09 | O17: 6.0950521e+09 | P17: 2.3788598e+09 | Q17: 2.5213255e+08 | R17: 3410.22 | S17: 0 | T17: 301.09 | U17: 0 | V17: 0 | W17: 0 | X17: 0 | Y17: 0 | Z17: 0
C18: ENEL | D18: Total | F18: 1.7293233e+10 | G18: 8.7586093e+08 | H18: 4.9385621e+08 | I18: 2.5975219e+08 | J18: 4.1214957e+09 | K18: 1.5445228e+08 | L18: 16025689 | M18: 1.3579187e+09 | N18: 1.2878233e+09 | O18: 6.0950521e+09 | P18: 2.3788598e+09 | Q18: 2.5213255e+08 | R18: 3410.22 | S18: 0 | T18: 301.09 | U18: 0 | V18: 0 | W18: 0 | X18: 0 | Y18: 0 | Z18: 0
E19: Vlr Servicio | F19: 31630649 | G19: 2116281.5 | H19: 1170722.5 | I19: 622287.66 | J19: 6853780.1 | K19: 205254.36 | L19: 0 | M19: 1791021.5 | N19: 2239705 | O19: 10554766 | P19: 5742154.8 | Q19: 334770.08 | R19: -94.69 | S19: 0 | T19: 0 | U19: 0 | V19: 0 | W19: 0 | X19: 0 | Y19: 0 | Z19: 0
E20: Vlr Intereses | F20: 56566.94 | G20: 3153.2 | H20: 1630.48 | I20: 910.69 | J20: 14196.75 | K20: 404.44 | L20: 0 | M20: 3503.55 | N20: 4189.5 | O20: 19352.39 | P20: 8568.43 | Q20: 658.34 | R20: -0.86 | S20: 0 | T20: 0.03 | U20: 0 | V20: 0 | W20: 0 | X20: 0 | Y20: 0 | Z20: 0
D21: H | E21: Total | F21: 31687216 | G21: 2119434.7 | H21: 1172353 | I21: 623198.35 | J21: 6867976.9 | K21: 205658.8 | L21: 0 | M21: 1794525 | N21: 2243894.5 | O21: 10574119 | P21: 5750723.2 | Q21: 335428.42 | R21: -95.55 | S21: 0 | T21: 0.03 | U21: 0 | V21: 0 | W21: 0 | X21: 0 | Y21: 0 | Z21: 0
E22: Vlr Servicio | F22: 1.1668923e+08 | G22: 12754734 | H22: 7083986 | I22: 3721696.4 | J22: 14791579 | K22: 679432.2 | L22: 200407 | M22: 5966168.7 | N22: 6324114.5 | O22: 29397614 | P22: 34660612 | Q22: 1109795.6 | R22: -904.58 | S22: 0 | T22: 0 | U22: 0 | V22: 0 | W22: 0 | X22: 0 | Y22: 0 | Z22: 0
E23: Vlr Intereses | F23: 298459.58 | G23: 17963.04 | H23: 7955.38 | I23: 3775.96 | J23: 65367.19 | K23: 2954.14 | L23: 175.21 | M23: 26504.61 | N23: 23098.54 | O23: 96645.91 | P23: 49317.74 | Q23: 4814.6 | R23: -5.81 | S23: 0 | T23: 0.13 | U23: 0 | V23: 0 | W23: 0 | X23: 0 | Y23: 0 | Z23: -107.06
D24: O | E24: Total | F24: 1.1698769e+08 | G24: 12772697 | H24: 7091941.4 | I24: 3725472.3 | J24: 14856946 | K24: 682386.34 | L24: 200582.21 | M24: 5992673.3 | N24: 6347213 | O24: 29494260 | P24: 34709929 | Q24: 1114610.2 | R24: -910.39 | S24: 0 | T24: 0.13 | U24: 0 | V24: 0 | W24: 0 | X24: 0 | Y24: 0 | Z24: -107.06
E25: Vlr Servicio | F25: 5.3396346e+08 | G25: 84240997 | H25: 47757392 | I25: 25132510 | J25: 41404004 | K25: 1121828.4 | L25: 20785144 | M25: 9808677.1 | N25: 12792123 | O25: 60185506 | P25: 2.289052e+08 | Q25: 1830367.3 | R25: -289.47 | S25: 0 | T25: 0 | U25: 0 | V25: 0 | W25: 0 | X25: 0 | Y25: 0 | Z25: 0
E26: Vlr Intereses | F26: 1648345.4 | G26: 174887.74 | H26: 87267.15 | I26: 44237.05 | J26: 278588.77 | K26: 9930.26 | L26: 13403.82 | M26: 86925 | N26: 89458.52 | O26: 385189.1 | P26: 462280.45 | Q26: 16184.13 | R26: -6.73 | S26: 0.08 | T26: 0.08 | U26: 0 | V26: 0 | W26: 0 | X26: 0 | Y26: 0 | Z26: 0
D27: T | E27: Total | F27: 5.3561181e+08 | G27: 84415885 | H27: 47844659 | I27: 25176747 | J27: 41682593 | K27: 1131758.7 | L27: 20798548 | M27: 9895602.1 | N27: 12881582 | O27: 60570695 | P27: 2.2936749e+08 | Q27: 1846551.4 | R27: -296.2 | S27: 0.08 | T27: 0.08 | U27: 0 | V27: 0 | W27: 0 | X27: 0 | Y27: 0 | Z27: 0
C28: OCCIDENTE | D28: Total | F28: 6.8428672e+08 | G28: 99308017 | H28: 56108953 | I28: 29525418 | J28: 63407516 | K28: 2019803.8 | L28: 20999130 | M28: 17682800 | N28: 21472689 | O28: 1.0063907e+08 | P28: 2.6982814e+08 | Q28: 3296590 | R28: -1302.14 | S28: 0.08 | T28: 0.24 | U28: 0 | V28: 0 | W28: 0 | X28: 0 | Y28: 0 | Z28: -107.06
B29: Mes | C29: Total | F29: 1.797752e+10 | G29: 9.7516894e+08 | H29: 5.4996517e+08 | I29: 2.8927761e+08 | J29: 4.1849032e+09 | K29: 1.5647208e+08 | L29: 37024819 | M29: 1.3756015e+09 | N29: 1.309296e+09 | O29: 6.1956912e+09 | P29: 2.648688e+09 | Q29: 2.5542914e+08 | R29: 2108.08 | S29: 0.08 | T29: 301.33 | U29: 0 | V29: 0 | W29: 0 | X29: 0 | Y29: 0 | Z29: -107.06
A30: Componente | B30: Total | F30: 1.7977562e+10 | G30: 9.7517119e+08 | H30: 5.4996643e+08 | I30: 2.8927827e+08 | J30: 4.1849132e+09 | K30: 1.5647245e+08 | L30: 37024819 | M30: 1.3756047e+09 | N30: 1.3092991e+09 | O30: 6.1957059e+09 | P30: 2.6486941e+09 | Q30: 2.5542974e+08 | R30: 2103.31 | S30: 0.08 | T30: 301.33 | U30: 0 | V30: 0 | W30: 0 | X30: 0 | Y30: 0 | Z30: -107.06
E31: Subsidio(-)/Contribucion(+) | F31: 21200.58 | G31: 1121.23 | H31: 633.05 | I31: 332.27 | J31: 5013.01 | K31: 186.15 | L31: 0 | M31: 1632.95 | N31: 1554.55 | O31: 7361.31 | P31: 3062.34 | Q31: 303.72 | R31: 0 | S31: 0 | T31: 0 | U31: 0 | V31: 0 | W31: 0 | X31: 0 | Y31: 0 | Z31: 0
D32: E | E32: Total | F32: 21200.58 | G32: 1121.23 | H32: 633.05 | I32: 332.27 | J32: 5013.01 | K32: 186.15 | L32: 0 | M32: 1632.95 | N32: 1554.55 | O32: 7361.31 | P32: 3062.34 | Q32: 303.72 | R32: 0 | S32: 0 | T32: 0 | U32: 0 | V32: 0 | W32: 0 | X32: 0 | Y32: 0 | Z32: 0
C33: ENEL | D33: Total | F33: 21200.58 | G33: 1121.23 | H33: 633.05 | I33: 332.27 | J33: 5013.01 | K33: 186.15 | L33: 0 | M33: 1632.95 | N33: 1554.55 | O33: 7361.31 | P33: 3062.34 | Q33: 303.72 | R33: 0 | S33: 0 | T33: 0 | U33: 0 | V33: 0 | W33: 0 | X33: 0 | Y33: 0 | Z33: 0
B34: Aplicacion nuevos x reversion | C34: Total | F34: 21200.58 | G34: 1121.23 | H34: 633.05 | I34: 332.27 | J34: 5013.01 | K34: 186.15 | L34: 0 | M34: 1632.95 | N34: 1554.55 | O34: 7361.31 | P34: 3062.34 | Q34: 303.72 | R34: 0 | S34: 0 | T34: 0 | U34: 0 | V34: 0 | W34: 0 | X34: 0 | Y34: 0 | Z34: 0
E35: Subsidio(-)/Contribucion(+) | F35: 1.5189423e+08 | G35: 90683812 | H35: 51049002 | I35: 26794378 | J35: -86416493 | K35: -3024948.5 | L35: 0 | M35: -27764106 | N35: -25271108 | O35: -1.2039562e+08 | P35: 2.5115921e+08 | Q35: -4919900.3 | R35: 0 | S35: 0 | T35: 0 | U35: 0 | V35: 0 | W35: 0 | X35: 0 | Y35: 0 | Z35: 0
D36: E | E36: Total | F36: 1.5189423e+08 | G36: 90683812 | H36: 51049002 | I36: 26794378 | J36: -86416493 | K36: -3024948.5 | L36: 0 | M36: -27764106 | N36: -25271108 | O36: -1.2039562e+08 | P36: 2.5115921e+08 | Q36: -4919900.3 | R36: 0 | S36: 0 | T36: 0 | U36: 0 | V36: 0 | W36: 0 | X36: 0 | Y36: 0 | Z36: 0
C37: ENEL | D37: Total | F37: 1.5189423e+08 | G37: 90683812 | H37: 51049002 | I37: 26794378 | J37: -86416493 | K37: -3024948.5 | L37: 0 | M37: -27764106 | N37: -25271108 | O37: -1.2039562e+08 | P37: 2.5115921e+08 | Q37: -4919900.3 | R37: 0 | S37: 0 | T37: 0 | U37: 0 | V37: 0 | W37: 0 | X37: 0 | Y37: 0 | Z37: 0
E38: Subsidio(-)/Contribucion(+) | F38: 2021483 | G38: 707748.14 | H38: 403617.61 | I38: 212434.65 | J38: -402532.63 | K38: -15766.67 | L38: 0 | M38: -141242.42 | N38: -116984.96 | O38: -532807.93 | P38: 1932741 | Q38: -25723.75 | R38: 0 | S38: 0 | T38: 0 | U38: 0 | V38: 0 | W38: 0 | X38: 0 | Y38: 0 | Z38: 0
D39: H | E39: Total | F39: 2021483 | G39: 707748.14 | H39: 403617.61 | I39: 212434.65 | J39: -402532.63 | K39: -15766.67 | L39: 0 | M39: -141242.42 | N39: -116984.96 | O39: -532807.93 | P39: 1932741 | Q39: -25723.75 | R39: 0 | S39: 0 | T39: 0 | U39: 0 | V39: 0 | W39: 0 | X39: 0 | Y39: 0 | Z39: 0
E40: Subsidio(-)/Contribucion(+) | F40: 13967366 | G40: 2999538.8 | H40: 1727763.6 | I40: 908877.93 | J40: -376035.93 | K40: -21939.23 | L40: 0 | M40: -193832.61 | N40: 102993.61 | O40: 642642.72 | P40: 8213151.1 | Q40: -35794.53 | R40: 0 | S40: 0 | T40: 0 | U40: 0 | V40: 0 | W40: 0 | X40: 0 | Y40: 0 | Z40: 0
D41: O | E41: Total | F41: 13967366 | G41: 2999538.8 | H41: 1727763.6 | I41: 908877.93 | J41: -376035.93 | K41: -21939.23 | L41: 0 | M41: -193832.61 | N41: 102993.61 | O41: 642642.72 | P41: 8213151.1 | Q41: -35794.53 | R41: 0 | S41: 0 | T41: 0 | U41: 0 | V41: 0 | W41: 0 | X41: 0 | Y41: 0 | Z41: 0
E42: Subsidio(-)/Contribucion(+) | F42: 1.9030195e+08 | G42: 34107615 | H42: 19171704 | I42: 10096437 | J42: 10987895 | K42: 313087.53 | L42: 0 | M42: 2737745.5 | N42: 3379843 | O42: 15862576 | P42: 93134787 | Q42: 510261.81 | R42: 0 | S42: 0 | T42: 0 | U42: 0 | V42: 0 | W42: 0 | X42: 0 | Y42: 0 | Z42: 0
D43: T | E43: Total | F43: 1.9030195e+08 | G43: 34107615 | H43: 19171704 | I43: 10096437 | J43: 10987895 | K43: 313087.53 | L43: 0 | M43: 2737745.5 | N43: 3379843 | O43: 15862576 | P43: 93134787 | Q43: 510261.81 | R43: 0 | S43: 0 | T43: 0 | U43: 0 | V43: 0 | W43: 0 | X43: 0 | Y43: 0 | Z43: 0
C44: OCCIDENTE | D44: Total | F44: 2.062908e+08 | G44: 37814902 | H44: 21303085 | I44: 11217750 | J44: 10209327 | K44: 275381.63 | L44: 0 | M44: 2402670.5 | N44: 3365851.7 | O44: 15972411 | P44: 1.0328068e+08 | Q44: 448743.53 | R44: 0 | S44: 0 | T44: 0 | U44: 0 | V44: 0 | W44: 0 | X44: 0 | Y44: 0 | Z44: 0
B45: Mes | C45: Total | F45: 3.5818503e+08 | G45: 1.2849871e+08 | H45: 72352087 | I45: 38012127 | J45: -76207166 | K45: -2749566.9 | L45: 0 | M45: -25361435 | N45: -21905256 | O45: -1.0442321e+08 | P45: 3.5443989e+08 | Q45: -4471156.8 | R45: 0 | S45: 0 | T45: 0 | U45: 0 | V45: 0 | W45: 0 | X45: 0 | Y45: 0 | Z45: 0
A46: Subs/Cont | B46: Total | F46: 3.5820623e+08 | G46: 1.2849984e+08 | H46: 72352720 | I46: 38012460 | J46: -76202153 | K46: -2749380.8 | L46: 0 | M46: -25359802 | N46: -21903702 | O46: -1.0441584e+08 | P46: 3.5444295e+08 | Q46: -4470853.1 | R46: 0 | S46: 0 | T46: 0 | U46: 0 | V46: 0 | W46: 0 | X46: 0 | Y46: 0 | Z46: 0
A47: Total | F47: 1.8335759e+10 | G47: 1.1036704e+09 | H47: 6.2231889e+08 | I47: 3.2729062e+08 | J47: 4.1087094e+09 | K47: 1.5372297e+08 | L47: 37024819 | M47: 1.350244e+09 | N47: 1.2873947e+09 | O47: 6.0912871e+09 | P47: 3.0031355e+09 | Q47: 2.5095872e+08 | R47: 2103.31 | S47: 0.08 | T47: 301.33 | U47: 0 | V47: 0 | W47: 0 | X47: 0 | Y47: 0 | Z47: -107.06
C50: TOTAL | D50: OPORTUNO | E50: Total | F50: =F32+F47+F12-L12-L32 -> 1.7339794e+10 | G50: =G32+G12 -> 8.9822314e+08 | H50: =H32+H12 -> 5.0656079e+08 | I50: =I32+I12 -> 2.6613439e+08 | J50: =J32+J12 -> 3.794558e+09 | K50: =K32+K12 -> 1.335427e+08 | L50: =L32+L12 -> 25277316 | M50: =M32+M12 -> 1.1749285e+09 | N50: =N32+N12 -> 1.1308881e+09 | ... AP50: =AP32+AP12 -> 0
E51: Subsidio(-)/Contribucion(+) | F51: =F47 -> 1.4291473e+09
D52: EXTEMPORANEO | E52: Total | F52: =F37+F17-L17 -> 49580 | G52: =G17 -> 2007.44 | H52: =H17 -> 1133.38 | I52: =I17 -> 594.88 | J52: =J17 -> 0 | K52: =K17 -> 0 | L52: =L17 -> 0 | M52: =M17 -> 0 | N52: =N17 -> 0 | ... AP52: =AP17 -> 0
E53: Subsidio(-)/Contribucion(+) | F53: =F37 -> 40364.31
C55: RECIPROCIDAD | D55: OPORTUNO | E55: Total | F55: 0 | G55: 0 | H55: 0 | I55: 0 | J55: 0 | K55: 0 | L55: 0 | M55: 0 | N55: 0 | O55: 0 | P55: 0 | Q55: 0 | R55: 0 | S55: 0 | T55: 0 | U55: 0 | V55: 0 | W55: 0 | X55: 0 | Y55: 0 | Z55: 0 | AA55: 0 | AB55: 0 | AC55: 0 | AD55: 0 | AE55: 0 | AF55: 0 | AG55: 0 | AH55: 0 | AI55: 0 | AJ55: 0 | AK55: 0 | AL55: 0 | AM55: 0 | AN55: 0 | AO55: 0 | AP55: 0
E56: Subsidio(-)/Contribucion(+) | F56: 0
D57: EXTEMPORANEO | E57: Total | F57: 0 | G57: 0 | H57: 0 | I57: 0 | J57: 0 | K57: 0 | L57: 0 | M57: 0 | N57: 0 | O57: 0 | P57: 0 | Q57: 0 | R57: 0 | S57: 0 | T57: 0 | U57: 0 | V57: 0 | W57: 0 | X57: 0 | Y57: 0 | Z57: 0 | AA57: 0 | AB57: 0 | AC57: 0 | AD57: 0 | AE57: 0 | AF57: 0 | AG57: 0 | AH57: 0 | AI57: 0 | AJ57: 0 | AK57: 0 | AL57: 0 | AM57: 0 | AN57: 0 | AO57: 0 | AP57: 0
E58: Subsidio(-)/Contribucion(+) | F58: 0
C60: ENEL | D60: OPORTUNO | E60: Total | F60: =F40+F21+F8-L8-L21 -> 1.6560599e+10 | G60: =G21+G8 -> 8.0164503e+08 | H60: =H21+H8 -> 4.5232889e+08 | I60: =I21+I8 -> 2.3765315e+08 | J60: =J21+J8 -> 3.7433985e+09 | K60: =K21+K8 -> 1.3190921e+08 | L60: =L21+L8 -> 16516492 | M60: =M21+M8 -> 1.1605544e+09 | N60: =N21+N8 -> 1.1134701e+09 | ... AP60: =AP21+AP8 -> 0
E61: Subsidio(-)/Contribucion(+) | F61: =F40 -> 1.2611229e+09
D62: EXTEMPORANEO | E62: Total | F62: =F36+F16-L16 -> 49580 | G62: =G16 -> 2007.44 | H62: =H16 -> 1133.38 | I62: =I16 -> 594.88 | J62: =J16 -> 0 | K62: =K16 -> 0 | L62: =L16 -> 0 | M62: =M16 -> 0 | N62: =N16 -> 0 | ... AP62: =AP16 -> 0
E63: Subsidio(-)/Contribucion(+) | F63: =F36 -> 40364.31
C65: ENERBIT | D65: OPORTUNO | E65: Total | F65: 0 | G65: 0 | H65: 0 | I65: 0 | J65: 0 | K65: 0 | L65: 0 | M65: 0 | N65: 0 | O65: 0 | P65: 0 | Q65: 0 | R65: 0 | S65: 0 | T65: 0 | U65: 0 | V65: 0 | W65: 0 | X65: 0 | Y65: 0 | Z65: 0 | AA65: 0 | AB65: 0 | AC65: 0 | AD65: 0 | AE65: 0 | AF65: 0 | AG65: 0 | AH65: 0 | AI65: 0 | AJ65: 0 | AK65: 0 | AL65: 0 | AM65: 0 | AN65: 0 | AO65: 0
E66: Subsidio(-)/Contribucion(+) | F66: 0
D67: EXTEMPORANEO | E67: Total | F67: 0 | G67: 0 | H67: 0 | I67: 0 | J67: 0 | K67: 0 | L67: 0 | M67: 0 | N67: 0 | O67: 0 | P67: 0 | Q67: 0 | R67: 0 | S67: 0 | T67: 0 | U67: 0 | V67: 0 | W67: 0 | X67: 0 | Y67: 0 | Z67: 0 | AA67: 0 | AB67: 0 | AC67: 0 | AD67: 0 | AE67: 0 | AF67: 0 | AG67: 0 | AH67: 0 | AI67: 0 | AJ67: 0 | AK67: 0 | AL67: 0 | AM67: 0 | AN67: 0 | AO67: 0
E68: Subsidio(-)/Contribucion(+) | F68: 0
C70: OCCIDENTE | D70: OPORTUNO | E70: Total | F70: =F47+F31+F11-L11-L31 -> 7.7919441e+08 | G70: =G31+G11 -> 96578113 | H70: =H31+H11 -> 54231898 | I70: =I31+I11 -> 28481236 | J70: =J31+J11 -> 51159574 | K70: =K31+K11 -> 1633496.9 | L70: =L31+L11 -> 8760824 | M70: =M31+M11 -> 14374092 | N70: =N31+N11 -> 17418029 | ... AP70: =AP31+AP11 -> 0
E71: Subsidio(-)/Contribucion(+) | F71: =F47 -> 1.680244e+08
D72: EXTEMPORANEO | E72: Total | F72: 0 | G72: 0 | H72: 0 | I72: 0 | J72: 0 | K72: 0 | L72: 0 | M72: 0 | N72: 0 | O72: 0 | P72: 0 | Q72: 0 | R72: 0 | S72: 0 | T72: 0 | U72: 0 | V72: 0 | W72: 0 | X72: 0 | Y72: 0 | Z72: 0 | AA72: 0 | AB72: 0 | AC72: 0 | AD72: 0 | AE72: 0 | AF72: 0 | AG72: 0 | AH72: 0 | AI72: 0 | AJ72: 0 | AK72: 0 | AL72: 0 | AM72: 0 | AN72: 0 | AO72: 0 | AP72: 0
E73: Subsidio(-)/Contribucion(+) | F73: 0
C75: CIUDAD LIMPIA-ACUEDUCTO | D75: OPORTUNO | E75: Total | F75: 0 | G75: 0 | H75: 0 | I75: 0 | J75: 0 | K75: 0 | L75: 0 | M75: 0 | N75: 0 | O75: 0 | P75: 0 | Q75: 0 | R75: 0 | S75: 0 | T75: 0 | U75: 0 | V75: 0 | W75: 0 | X75: 0 | Y75: 0 | Z75: 0 | AA75: 0 | AB75: 0 | AC75: 0 | AD75: 0 | AE75: 0 | AF75: 0 | AG75: 0 | AH75: 0 | AI75: 0 | AJ75: 0 | AK75: 0 | AL75: 0 | AM75: 0 | AN75: 0 | AO75: 0 | AP75: 0
E76: Subsidio(-)/Contribucion(+) | F76: 0
D77: EXTEMPORANEO | E77: Total | F77: 0 | G77: 0 | H77: 0 | I77: 0 | J77: 0 | K77: 0 | L77: 0 | M77: 0 | N77: 0 | O77: 0 | P77: 0 | Q77: 0 | R77: 0 | S77: 0 | T77: 0 | U77: 0 | V77: 0 | W77: 0 | X77: 0 | Y77: 0 | Z77: 0 | AA77: 0 | AB77: 0 | AC77: 0 | AD77: 0 | AE77: 0 | AF77: 0 | AG77: 0 | AH77: 0 | AI77: 0 | AJ77: 0 | AK77: 0 | AL77: 0 | AM77: 0 | AN77: 0 | AO77: 0 | AP77: 0
E78: Subsidio(-)/Contribucion(+) | F78: 0
D80: AFaseo | E80: Total | F80: =F13 -> -11217.37 | G80: =G13 -> -766.38 | H80: =H13 -> -325.59 | I80: =I13 -> -142.17 | J80: =J13 -> -1970.37 | K80: =K13 -> -127.32 | L80: =L13 -> 0 | M80: =M13 -> -1116.82 | ... AP80: =AP13 -> 0
B83: LIME
F84: Total | G84: Componente TDF | H84: Componente TTL | I84: Componente TVIAT | J84: Aprovechamiento | K84: CCSA Prest.Aprov. | L84: SERVICIO ESPECIALES | M84: Componente TCS | N84: Componente TLU | O84: Componente TBL | P84: Componente TRT | Q84: CCSA Prest. No Aprov. | R84: Ajuste Decena | S84: Ajuste Recargo Aseo | T84: Intereses Cte Financiac. Aseo | U84: Exonera Rec.Intereses | V84: Exonera-Ajuste Decena Aseo | W84: Exonera-Recargo Aseo | X84: Rec.Intereses | Y84: Intereses Cte Financiac. Aseo | Z84: Rec.Intereses
E85: Vlr Servicio | F85: -1414859.1 | G85: -123592.91 | H85: -52505.96 | I85: -22930.17 | J85: -283718.29 | K85: -11813.11 | L85: 0 | M85: -103626.9 | N85: -129894.77 | O85: -436317.84 | P85: -231183.82 | Q85: -19275.37 | R85: 0 | S85: 0 | T85: 0 | U85: 0 | V85: 0 | W85: 0 | X85: 0 | Y85: 0 | Z85: 0
D86: E | E86: Total | F86: -1414859.1 | G86: -123592.91 | H86: -52505.96 | I86: -22930.17 | J86: -283718.29 | K86: -11813.11 | L86: 0 | M86: -103626.9 | N86: -129894.77 | O86: -436317.84 | P86: -231183.82 | Q86: -19275.37 | R86: 0 | S86: 0 | T86: 0 | U86: 0 | V86: 0 | W86: 0 | X86: 0 | Y86: 0 | Z86: 0
C87: ENEL | D87: Total | F87: -1414859.1 | G87: -123592.91 | H87: -52505.96 | I87: -22930.17 | J87: -283718.29 | K87: -11813.11 | L87: 0 | M87: -103626.9 | N87: -129894.77 | O87: -436317.84 | P87: -231183.82 | Q87: -19275.37 | R87: 0 | S87: 0 | T87: 0 | U87: 0 | V87: 0 | W87: 0 | X87: 0 | Y87: 0 | Z87: 0
E88: Vlr Servicio | F88: -20998.87 | G88: -1840.53 | H88: -781.92 | I88: -341.46 | J88: -4232.84 | K88: -174.41 | L88: 0 | M88: -1529.91 | N88: -1917.75 | O88: -6441.6 | P88: -3453.9 | Q88: -284.55 | R88: 0 | S88: 0 | T88: 0 | U88: 0 | V88: 0 | W88: 0 | X88: 0 | Y88: 0 | Z88: 0
D89: H | E89: Total | F89: -20998.87 | G89: -1840.53 | H89: -781.92 | I89: -341.46 | J89: -4232.84 | K89: -174.41 | L89: 0 | M89: -1529.91 | N89: -1917.75 | O89: -6441.6 | P89: -3453.9 | Q89: -284.55 | R89: 0 | S89: 0 | T89: 0 | U89: 0 | V89: 0 | W89: 0 | X89: 0 | Y89: 0 | Z89: 0
E90: Vlr Servicio | F90: -7651.97 | G90: -673.86 | H90: -286.26 | I90: -125.04 | J90: -1539.21 | K90: -63.42 | L90: 0 | M90: -556.33 | N90: -697.38 | O90: -2342.4 | P90: -1264.56 | Q90: -103.51 | R90: 0 | S90: 0 | T90: 0 | U90: 0 | V90: 0 | W90: 0 | X90: 0 | Y90: 0 | Z90: 0
D91: O | E91: Total | F91: -7651.97 | G91: -673.86 | H91: -286.26 | I91: -125.04 | J91: -1539.21 | K91: -63.42 | L91: 0 | M91: -556.33 | N91: -697.38 | O91: -2342.4 | P91: -1264.56 | Q91: -103.51 | R91: 0 | S91: 0 | T91: 0 | U91: 0 | V91: 0 | W91: 0 | X91: 0 | Y91: 0 | Z91: 0
C92: OCCIDENTE | D92: Total | F92: -28650.84 | G92: -2514.39 | H92: -1068.18 | I92: -466.5 | J92: -5772.05 | K92: -237.83 | L92: 0 | M92: -2086.24 | N92: -2615.13 | O92: -8784 | P92: -4718.46 | Q92: -388.06 | R92: 0 | S92: 0 | T92: 0 | U92: 0 | V92: 0 | W92: 0 | X92: 0 | Y92: 0 | Z92: 0
B93: Mes | C93: Total | F93: -1443510 | G93: -126107.3 | H93: -53574.14 | I93: -23396.67 | J93: -289490.34 | K93: -12050.94 | L93: 0 | M93: -105713.14 | N93: -132509.9 | O93: -445101.84 | P93: -235902.28 | Q93: -19663.43 | R93: 0 | S93: 0 | T93: 0 | U93: 0 | V93: 0 | W93: 0 | X93: 0 | Y93: 0 | Z93: 0
A94: AFaseo | B94: Total | F94: -1443510 | G94: -126107.3 | H94: -53574.14 | I94: -23396.67 | J94: -289490.34 | K94: -12050.94 | L94: 0 | M94: -105713.14 | N94: -132509.9 | O94: -445101.84 | P94: -235902.28 | Q94: -19663.43 | R94: 0 | S94: 0 | T94: 0 | U94: 0 | V94: 0 | W94: 0 | X94: 0 | Y94: 0 | Z94: 0
E95: Vlr Servicio | F95: 131543.19 | G95: 13093.19 | H95: 7370.27 | I95: 4474.7 | J95: 25771.56 | K95: 925.74 | L95: 0 | M95: 8109.96 | N95: 7930.91 | O95: 37461.59 | P95: 24418.29 | Q95: 1987.26 | R95: -0.28 | S95: 0 | T95: 0 | U95: 0 | V95: 0 | W95: 0 | X95: 0 | Y95: 0 | Z95: 0
D96: E | E96: Total | F96: 131543.19 | G96: 13093.19 | H96: 7370.27 | I96: 4474.7 | J96: 25771.56 | K96: 925.74 | L96: 0 | M96: 8109.96 | N96: 7930.91 | O96: 37461.59 | P96: 24418.29 | Q96: 1987.26 | R96: -0.28 | S96: 0 | T96: 0 | U96: 0 | V96: 0 | W96: 0 | X96: 0 | Y96: 0 | Z96: 0
C97: ENEL | D97: Total | F97: 131543.19 | G97: 13093.19 | H97: 7370.27 | I97: 4474.7 | J97: 25771.56 | K97: 925.74 | L97: 0 | M97: 8109.96 | N97: 7930.91 | O97: 37461.59 | P97: 24418.29 | Q97: 1987.26 | R97: -0.28 | S97: 0 | T97: 0 | U97: 0 | V97: 0 | W97: 0 | X97: 0 | Y97: 0 | Z97: 0
E98: Vlr Servicio | F98: 24890 | G98: 0 | H98: 0 | I98: 567.09 | J98: 5122.93 | K98: 373.45 | L98: 0 | M98: 0 | N98: 3176.37 | O98: 15040.85 | P98: 0 | Q98: 609.31 | R98: 0 | S98: 0 | T98: 0 | U98: 0 | V98: 0 | W98: 0 | X98: 0 | Y98: 0 | Z98: 0
D99: O | E99: Total | F99: 24890 | G99: 0 | H99: 0 | I99: 567.09 | J99: 5122.93 | K99: 373.45 | L99: 0 | M99: 0 | N99: 3176.37 | O99: 15040.85 | P99: 0 | Q99: 609.31 | R99: 0 | S99: 0 | T99: 0 | U99: 0 | V99: 0 | W99: 0 | X99: 0 | Y99: 0 | Z99: 0
C100: OCCIDENTE | D100: Total | F100: 24890 | G100: 0 | H100: 0 | I100: 567.09 | J100: 5122.93 | K100: 373.45 | L100: 0 | M100: 0 | N100: 3176.37 | O100: 15040.85 | P100: 0 | Q100: 609.31 | R100: 0 | S100: 0 | T100: 0 | U100: 0 | V100: 0 | W100: 0 | X100: 0 | Y100: 0 | Z100: 0
B101: Aplicacion nuevos x reversion | C101: Total | F101: 156433.19 | G101: 13093.19 | H101: 7370.27 | I101: 5041.79 | J101: 30894.49 | K101: 1299.19 | L101: 0 | M101: 8109.96 | N101: 11107.28 | O101: 52502.44 | P101: 24418.29 | Q101: 2596.57 | R101: -0.28 | S101: 0 | T101: 0 | U101: 0 | V101: 0 | W101: 0 | X101: 0 | Y101: 0 | Z101: 0
E102: Vlr Servicio | F102: 2.4730941e+10 | G102: 1.3641125e+09 | H102: 7.6139919e+08 | I102: 3.9756213e+08 | J102: 6.4356265e+09 | K102: 2.1557829e+08 | L102: 22415640 | M102: 1.8917823e+09 | N102: 1.8583189e+09 | O102: 8.749865e+09 | P102: 2.6823222e+09 | Q102: 3.521783e+08 | R102: -220306.25 | S102: 0 | T102: 0 | U102: 0 | V102: 0 | W102: 0 | X102: 0 | Y102: 0 | Z102: 0
E103: Vlr Intereses | F103: 1.0507885e+08 | G103: 12373208 | H103: 5822118.4 | I103: 2557314.4 | J103: 19359152 | K103: 689674.86 | L103: 17502.71 | M103: 6029529.8 | N103: 7139477.9 | O103: 25859858 | P103: 24102913 | Q103: 1125547.6 | R103: 2527.3 | S103: 50.73 | T103: 0.9 | U103: 0 | V103: 0 | W103: 0 | X103: 0 | Y103: 0 | Z103: -23.48
D104: E | E104: Total | F104: 2.4836019e+10 | G104: 1.3764857e+09 | H104: 7.6722131e+08 | I104: 4.0011944e+08 | J104: 6.4549856e+09 | K104: 2.1626797e+08 | L104: 22433143 | M104: 1.8978118e+09 | N104: 1.8654584e+09 | O104: 8.7757248e+09 | P104: 2.7064251e+09 | Q104: 3.5330385e+08 | R104: -217778.95 | S104: 50.73 | T104: 0.9 | U104: 0 | V104: 0 | W104: 0 | X104: 0 | Y104: 0 | Z104: -23.48
C105: ENEL | D105: Total | F105: 2.4836019e+10 | G105: 1.3764857e+09 | H105: 7.6722131e+08 | I105: 4.0011944e+08 | J105: 6.4549856e+09 | K105: 2.1626797e+08 | L105: 22433143 | M105: 1.8978118e+09 | N105: 1.8654584e+09 | O105: 8.7757248e+09 | P105: 2.7064251e+09 | Q105: 3.5330385e+08 | R105: -217778.95 | S105: 50.73 | T105: 0.9 | U105: 0 | V105: 0 | W105: 0 | X105: 0 | Y105: 0 | Z105: -23.48
E106: Vlr Servicio | F106: 1148755.9 | G106: 103833.95 | H106: 50131.96 | I106: 27876.21 | J106: 257690.34 | K106: 6913.63 | L106: 0 | M106: 60980.16 | N106: 74702.16 | O106: 347093.13 | P106: 208245.74 | Q106: 11280.3 | R106: 8.33 | S106: 0 | T106: 0 | U106: 0 | V106: 0 | W106: 0 | X106: 0 | Y106: 0 | Z106: 0
E107: Vlr Intereses | F107: 199642.47 | G107: 21039.28 | H107: 9401.54 | I107: 5415.39 | J107: 44862.35 | K107: 1038.88 | L107: 0 | M107: 9113.04 | N107: 11405.09 | O107: 53456.23 | P107: 42215.06 | Q107: 1695.12 | R107: 0.49 | S107: 0 | T107: 0 | U107: 0 | V107: 0 | W107: 0 | X107: 0 | Y107: 0 | Z107: 0
D108: 1 | E108: Total | F108: 1348398.4 | G108: 124873.23 | H108: 59533.5 | I108: 33291.6 | J108: 302552.69 | K108: 7952.51 | L108: 0 | M108: 70093.2 | N108: 86107.25 | O108: 400549.36 | P108: 250460.8 | Q108: 12975.42 | R108: 8.82 | S108: 0 | T108: 0 | U108: 0 | V108: 0 | W108: 0 | X108: 0 | Y108: 0 | Z108: 0
E109: Vlr Servicio | F109: 230376.22 | G109: 18333.27 | H109: 9782.29 | I109: 5319.95 | J109: 54717.31 | K109: 1624.1 | L109: 0 | M109: 14246.4 | N109: 15524.85 | O109: 70821.65 | P109: 37360.92 | Q109: 2649.83 | R109: -4.35 | S109: 0 | T109: 0 | U109: 0 | V109: 0 | W109: 0 | X109: 0 | Y109: 0 | Z109: 0
D110: 2 | E110: Total | F110: 230376.22 | G110: 18333.27 | H110: 9782.29 | I110: 5319.95 | J110: 54717.31 | K110: 1624.1 | L110: 0 | M110: 14246.4 | N110: 15524.85 | O110: 70821.65 | P110: 37360.92 | Q110: 2649.83 | R110: -4.35 | S110: 0 | T110: 0 | U110: 0 | V110: 0 | W110: 0 | X110: 0 | Y110: 0 | Z110: 0
E111: Vlr Servicio | F111: 9689217.2 | G111: 518533.02 | H111: 287577.53 | I111: 156432.14 | J111: 2441050.7 | K111: 82298.98 | L111: 0 | M111: 728609.23 | N111: 748449.81 | O111: 3562346.9 | P111: 1027130.6 | Q111: 136840.93 | R111: -52.63 | S111: 0 | T111: 0 | U111: 0 | V111: 0 | W111: 0 | X111: 0 | Y111: 0 | Z111: 0
E112: Vlr Intereses | F112: 217045.55 | G112: 12559.35 | H112: 6390.48 | I112: 3379.76 | J112: 55867.7 | K112: 1678.84 | L112: 0 | M112: 14715.14 | N112: 18428.22 | O112: 76574.75 | P112: 24706.8 | Q112: 2744.21 | R112: 0.42 | S112: 0 | T112: 0 | U112: 0 | V112: 0 | W112: 0 | X112: 0 | Y112: 0 | Z112: -0.12
D113: 5 | E113: Total | F113: 9906262.7 | G113: 531092.37 | H113: 293968.01 | I113: 159811.9 | J113: 2496918.4 | K113: 83977.82 | L113: 0 | M113: 743324.37 | N113: 766878.03 | O113: 3638921.7 | P113: 1051837.4 | Q113: 139585.14 | R113: -52.21 | S113: 0 | T113: 0 | U113: 0 | V113: 0 | W113: 0 | X113: 0 | Y113: 0 | Z113: -0.12
...

Sheet Rem. Anticipos R2
B1: PROMOAMBIENTAL
E2: Total | F2: Componente TDF | G2: Componente TTL | H2: Componente TVIAT | I2: Aprovechamiento | J2: CCSA Prest.Aprov. | K2: Especiales | L2: Componente TCS | M2: Componente TLU | N2: Componente TBL | O2: Componente TRT | P2: CCSA Prest. No Aprov. | Q2: Deb/Cred | R2: Deb/Cred-otros
D3: Vlr Servicio | E3: 1.0475463e+08 | F3: 6975298.7 | G3: 3988878.1 | H3: 1891710.5 | I3: 21813833 | J3: 885097.78 | K3: 0 | L3: 8065770.6 | M3: 7536469.1 | N3: 33213004 | O3: 19115514 | P3: 1269059.6 | Q3: -0.63 | R3: 0
D4: Vlr Intereses | E4: 15816.77 | F4: 1163.38 | G4: 642.32 | H4: 341.55 | I4: 3027.69 | J4: 126.06 | K4: 0 | L4: 1110.61 | M4: 1054.19 | N4: 4963.73 | O4: 3181.55 | P4: 205.61 | Q4: 0.08 | R4: 0
C5: E | D5: Total | E5: 1.0477045e+08 | F5: 6976462.1 | G5: 3989520.4 | H5: 1892052 | I5: 21816861 | J5: 885223.84 | K5: 0 | L5: 8066881.2 | M5: 7537523.3 | N5: 33217967 | O5: 19118696 | P5: 1269265.2 | Q5: -0.55 | R5: 0
B6: ENEL | C6: Total | E6: 1.0477045e+08 | F6: 6976462.1 | G6: 3989520.4 | H6: 1892052 | I6: 21816861 | J6: 885223.84 | K6: 0 | L6: 8066881.2 | M6: 7537523.3 | N6: 33217967 | O6: 19118696 | P6: 1269265.2 | Q6: -0.55 | R6: 0
D7: Vlr Servicio | E7: 2066328.1 | F7: 95509.13 | G7: 53786.6 | H7: 25807.38 | I7: 498516.51 | J7: 14869.65 | K7: 0 | L7: 154839.34 | M7: 178346.64 | N7: 760377.7 | O7: 261105.9 | P7: 23181.14 | Q7: -11.84 | R7: 0
D8: Vlr Intereses | E8: 53.09 | F8: 2.2 | G8: 1.21 | H8: 0.66 | I8: 13.81 | J8: 0.47 | K8: 0 | L8: 4.11 | M8: 4.2 | N8: 19.61 | O8: 6.05 | P8: 0.77 | Q8: 0 | R8: 0
C9: H | D9: Total | E9: 2066381.2 | F9: 95511.33 | G9: 53787.81 | H9: 25808.04 | I9: 498530.32 | J9: 14870.12 | K9: 0 | L9: 154843.45 | M9: 178350.84 | N9: 760397.31 | O9: 261111.95 | P9: 23181.91 | Q9: -11.84 | R9: 0
D10: Vlr Servicio | E10: 1667705.3 | F10: 94831.21 | G10: 53653.37 | H10: 23974.41 | I10: 360931.98 | J10: 13656.23 | K10: 0 | L10: 118901.31 | M10: 135021.65 | N10: 589240.87 | O10: 258802.75 | P10: 18683.4 | Q10: 8.11 | R10: 0
D11: Vlr Intereses | E11: 534.46 | F11: 31.52 | G11: 17.83 | H11: 9.34 | I11: 118.64 | J11: 4.45 | K11: 0 | L11: 39.04 | M11: 38.33 | N11: 181.9 | O11: 86.11 | P11: 7.3 | Q11: 0 | R11: 0
C12: O | D12: Total | E12: 1668239.8 | F12: 94862.73 | G12: 53671.2 | H12: 23983.75 | I12: 361050.62 | J12: 13660.68 | K12: 0 | L12: 118940.35 | M12: 135059.98 | N12: 589422.77 | O12: 258888.86 | P12: 18690.7 | Q12: 8.11 | R12: 0
D13: Vlr Servicio | E13: 18251249 | F13: 2466979.3 | G13: 1389961.4 | H13: 841642.79 | I13: 1865966 | J13: 51082.32 | K13: 0 | L13: 482981.31 | M13: 671717.75 | N13: 3043351.3 | O13: 7354815.6 | P13: 82820.66 | Q13: -69.46 | R13: 0
D14: Vlr Intereses | E14: 35670.7 | F14: 6587.48 | G14: 3721.93 | H14: 1963.44 | I14: 1660.15 | J14: 49.7 | K14: 0 | L14: 436.97 | M14: 541.21 | N14: 2526.1 | O14: 18102.54 | P14: 81.19 | Q14: -0.01 | R14: 0
C15: T | D15: Total | E15: 18286920 | F15: 2473566.8 | G15: 1393683.3 | H15: 843606.23 | I15: 1867626.2 | J15: 51132.02 | K15: 0 | L15: 483418.28 | M15: 672258.96 | N15: 3045877.4 | O15: 7372918.2 | P15: 82901.85 | Q15: -69.47 | R15: 0
B16: OCCIDENTE | C16: Total | E16: 22021541 | F16: 2663940.8 | G16: 1501142.3 | H16: 893398.02 | I16: 2727207.1 | J16: 79662.82 | K16: 0 | L16: 757202.08 | M16: 985669.78 | N16: 4395697.5 | O16: 7892919 | P16: 124774.46 | Q16: -73.2 | R16: 0
A17: Componente | B17: Total | E17: 93477927 | F17: 9640402.9 | G17: 5490662.7 | H17: 2785450 | I17: 24544068 | J17: 964886.66 | K17: 144941.68 | L17: 8824083.3 | M17: 8523193.1 | N17: 37613665 | O17: 27011615 | P17: 1394039.6 | Q17: -73.75 | R17: 0
D18: Subsidio(-)/Contribucion(+) | E18: -7679309.2 | F18: 637875.65 | G18: 341985.27 | H18: 179997 | I18: -2784147.3 | J18: -136924.32 | K18: 0 | L18: -1201987.1 | M18: -1088414.8 | N18: -5141699 | O18: 1734349.6 | P18: -220344.15 | Q18: 0 | R18: 0
C19: E | D19: Total | E19: -7679309.2 | F19: 637875.65 | G19: 341985.27 | H19: 179997 | I19: -2784147.3 | J19: -136924.32 | K19: 0 | L19: -1201987.1 | M19: -1088414.8 | N19: -5141699 | O19: 1734349.6 | P19: -220344.15 | Q19: 0 | R19: 0
B20: ENEL | C20: Total | E20: -7679309.2 | F20: 637875.65 | G20: 341985.27 | H20: 179997 | I20: -2784147.3 | J20: -136924.32 | K20: 0 | L20: -1201987.1 | M20: -1088414.8 | N20: -5141699 | O20: 1734349.6 | P20: -220344.15 | Q20: 0 | R20: 0
D21: Subsidio(-)/Contribucion(+) | E21: -50554.72 | F21: 4736.11 | G21: 2674.07 | H21: 345.4 | I21: -23429.04 | J21: -1776.06 | K21: 0 | L21: -14634.19 | M21: -5072.07 | N21: -23919.85 | O21: 13249.96 | P21: -2729.05 | Q21: 0 | R21: 0
C22: H | D22: Total | E22: -50554.72 | F22: 4736.11 | G22: 2674.07 | H22: 345.4 | I22: -23429.04 | J22: -1776.06 | K22: 0 | L22: -14634.19 | M22: -5072.07 | N22: -23919.85 | O22: 13249.96 | P22: -2729.05 | Q22: 0 | R22: 0
D23: Subsidio(-)/Contribucion(+) | E23: -41372.31 | F23: 12793.71 | G23: 7223.37 | H23: 821.96 | I23: -13378.5 | J23: -1510.5 | K23: 0 | L23: -12344.21 | M23: -12400.64 | N23: -55249.52 | O23: 35136.41 | P23: -2464.39 | Q23: 0 | R23: 0
C24: O | D24: Total | E24: -41372.31 | F24: 12793.71 | G24: 7223.37 | H24: 821.96 | I24: -13378.5 | J24: -1510.5 | K24: 0 | L24: -12344.21 | M24: -12400.64 | N24: -55249.52 | O24: 35136.41 | P24: -2464.39 | Q24: 0 | R24: 0
D25: Subsidio(-)/Contribucion(+) | E25: 6927796.9 | F25: 1130170.6 | G25: 623361.6 | H25: 304609.91 | I25: 533203.52 | J25: 13692.34 | K25: 0 | L25: 126469.3 | M25: 172463.37 | N25: 810419.93 | O25: 3191349.9 | P25: 22056.36 | Q25: 0 | R25: 0
C26: T | D26: Total | E26: 6927796.9 | F26: 1130170.6 | G26: 623361.6 | H26: 304609.91 | I26: 533203.52 | J26: 13692.34 | K26: 0 | L26: 126469.3 | M26: 172463.37 | N26: 810419.93 | O26: 3191349.9 | P26: 22056.36 | Q26: 0 | R26: 0
B27: OCCIDENTE | C27: Total | E27: 6835869.9 | F27: 1147700.5 | G27: 633259.04 | H27: 305777.27 | I27: 496395.98 | J27: 10405.78 | K27: 0 | L27: 99490.9 | M27: 154990.66 | N27: 731250.56 | O27: 3239736.3 | P27: 16862.92 | Q27: 0 | R27: 0
A28: Subs/Cont | B28: Total | E28: -13972083 | F28: 1785576.1 | G28: 975244.31 | H28: 485774.27 | I28: -2287751.4 | J28: -126518.54 | K28: 0 | L28: -1102496.2 | M28: -933424.09 | N28: -4410448.5 | O28: 4974085.9 | P28: -203481.23 | Q28: 0 | R28: 0
A29: Total | E29: 1.2594855e+08 | F29: 11425979 | G29: 6465907 | H29: 3271224.3 | I29: 22256317 | J29: 838368.12 | K29: 0 | L29: 7721587.1 | M29: 7589769 | N29: 33203216 | O29: 31985701 | P29: 1190558.4 | Q29: -73.75 | R29: 0
B43: TOTAL | C43: OPORTUNO | D43: Total | E43: =E17+E28-K17 -> 1.2594855e+08 | F43: =F17 -> 9640402.9 | G43: =G17 -> 5490662.7 | H43: =H17 -> 2785450 | I43: =I17 -> 24544068 | J43: =J17 -> 964886.66 | K43: =K17 -> 0 | L43: =L17 -> 8824083.3 | M43: =M17 -> 8523193.1 | ... S43: =S17 -> 0
D44: Subsidio(-)/Contribucion(+) | E44: =E28 -> -843439.3
B46: RECIPROCIDAD | C46: OPORTUNO | D46: Total | E46: 0 | F46: 0 | G46: 0 | H46: 0 | I46: 0 | J46: 0 | K46: 0 | L46: 0 | M46: 0 | N46: 0 | O46: 0 | P46: 0 | Q46: 0 | R46: 0 | S46: 0
D47: Subsidio(-)/Contribucion(+) | E47: 0
B49: ENEL | C49: OPORTUNO | D49: Total | E49: =E20+E6-K6 -> 97091143 | F49: =F6 -> 6976462.1 | G49: =G6 -> 3989520.4 | H49: =H6 -> 1892052 | I49: =I6 -> 21816861 | J49: =J6 -> 885223.84 | K49: =K6 -> 0 | L49: =L6 -> 8066881.2 | M49: =M6 -> 7537523.3 | ... S49: =S6 -> 0
D50: Subsidio(-)/Contribucion(+) | E50: =E20 -> -7679309.2
B52: ENERBIT | C52: OPORTUNO | D52: Total | E52: 0 | F52: 0 | G52: 0 | H52: 0 | I52: 0 | J52: 0 | K52: 0 | L52: 0 | M52: 0 | N52: 0 | O52: 0 | P52: 0 | Q52: 0 | R52: 0
D53: Subsidio(-)/Contribucion(+) | E53: 0
B55: OCCIDENTE | C55: OPORTUNO | D55: Total | E55: =E16+E27-K16 -> 28857411 | F55: =F16 -> 2663940.8 | G55: =G16 -> 1501142.3 | H55: =H16 -> 893398.02 | I55: =I16 -> 2727207.1 | J55: =J16 -> 79662.82 | K55: =K16 -> 0 | L55: =L16 -> 757202.08 | M55: =M16 -> 985669.78 | ... S55: =S16 -> 0
D56: Subsidio(-)/Contribucion(+) | E56: =E27 -> 6835869.9
B58: CIUDAD LIMPIA-ACUEDUCTO | C58: OPORTUNO | D58: Total | E58: 0 | F58: 0 | G58: 0 | H58: 0 | I58: 0 | J58: 0 | K58: 0 | L58: 0 | M58: 0 | N58: 0 | O58: 0 | P58: 0 | Q58: 0 | R58: 0 | S58: 0
D59: Subsidio(-)/Contribucion(+) | E59: 0
B61: LIME
E62: Total | F62: Componente TDF | G62: Componente TTL | H62: Componente TVIAT | I62: Aprovechamiento | J62: CCSA Prest.Aprov. | K62: Especiales | L62: Componente TCS | M62: Componente TLU | N62: Componente TBL | O62: Componente TRT | P62: CCSA Prest. No Aprov. | Q62: Deb/Cred | R62: Deb/Cred-otros
D63: Vlr Servicio | E63: 71702409 | F63: 4119196.9 | G63: 2445784.3 | H63: 988499.28 | I63: 18958221 | J63: 632942.16 | K63: 0 | L63: 5923929.5 | M63: 5752498 | N63: 23264099 | O63: 8731555.6 | P63: 885560.39 | Q63: 122.44 | R63: 0
D64: Vlr Intereses | E64: 95038.85 | F64: 9024.33 | G64: 4730.41 | H64: 2571.82 | I64: 19131.48 | J64: 648.99 | K64: 0 | L64: 5659.74 | M64: 6117.92 | N64: 28047 | O64: 18026.08 | P64: 1059.27 | Q64: 21.81 | R64: 0
C65: E | D65: Total | E65: 71797448 | F65: 4128221.2 | G65: 2450514.8 | H65: 991071.1 | I65: 18977353 | J65: 633591.15 | K65: 0 | L65: 5929589.2 | M65: 5758616 | N65: 23292146 | O65: 8749581.6 | P65: 886619.66 | Q65: 144.25 | R65: 0
B66: ENEL | C66: Total | E66: 71797448 | F66: 4128221.2 | G66: 2450514.8 | H66: 991071.1 | I66: 18977353 | J66: 633591.15 | K66: 0 | L66: 5929589.2 | M66: 5758616 | N66: 23292146 | O66: 8749581.6 | P66: 886619.66 | Q66: 144.25 | R66: 0
D67: Vlr Servicio | E67: 22093259 | F67: 1421141.7 | G67: 778144.37 | H67: 342749 | I67: 6034872.3 | J67: 158457.39 | K67: 0 | L67: 1458906.2 | M67: 1770857 | N67: 5515356 | O67: 4418000.6 | P67: 194910.48 | Q67: -136.28 | R67: 0
D68: Vlr Intereses | E68: 17021.45 | F68: 1413.33 | G68: 751.77 | H68: 431.98 | I68: 3886.9 | J68: 91.78 | K68: 0 | L68: 805.04 | M68: 1177.57 | N68: 5500.97 | O68: 2812.31 | P68: 149.78 | Q68: 0.02 | R68: 0
C69: 1 | D69: Total | E69: 22110280 | F69: 1422555.1 | G69: 778896.14 | H69: 343180.98 | I69: 6038759.2 | J69: 158549.17 | K69: 0 | L69: 1459711.3 | M69: 1772034.6 | N69: 5520857 | O69: 4420812.9 | P69: 195060.26 | Q69: -136.26 | R69: 0
D70: Vlr Servicio | E70: 1616173.6 | F70: 90529.5 | G70: 47826.83 | H70: 24108.87 | I70: 433611.64 | J70: 13309 | K70: 0 | L70: 100420.03 | M70: 121133.57 | N70: 423371.69 | O70: 346736.28 | P70: 15115.46 | Q70: 10.76 | R70: 0
D71: Vlr Intereses | E71: 406.42 | F71: 41.47 | G71: 21.23 | H71: 12.67 | I71: 83.96 | J71: 1.95 | K71: 0 | L71: 17.12 | M71: 25.02 | N71: 117.24 | O71: 82.58 | P71: 3.19 | Q71: -0.01 | R71: 0
C72: 2 | D72: Total | E72: 1616580.1 | F72: 90570.97 | G72: 47848.06 | H72: 24121.54 | I72: 433695.6 | J72: 13310.95 | K72: 0 | L72: 100437.15 | M72: 121158.59 | N72: 423488.93 | O72: 346818.86 | P72: 15118.65 | Q72: 10.75 | R72: 0
D73: Vlr Servicio | E73: 27690465 | F73: 1701572.3 | G73: 971553.65 | H73: 405189.21 | I73: 7839404.6 | J73: 234550.49 | K73: 0 | L73: 2072653.2 | M73: 2236560 | N73: 8259845.4 | O73: 3677240.6 | P73: 291796.3 | Q73: 99.64 | R73: 0
D74: Vlr Intereses | E74: 220606.32 | F74: 2079.3 | G74: 1101.6 | H74: 634.08 | I74: 4056.19 | J74: 100.05 | K74: 0 | L74: 31497.06 | M74: 39422.95 | N74: 118658.47 | O74: 22893.4 | P74: 163.27 | Q74: -0.05 | R74: 0
C75: 5 | D75: Total | E75: 27911072 | F75: 1703651.6 | G75: 972655.25 | H75: 405823.29 | I75: 7843460.8 | J75: 234650.54 | K75: 0 | L75: 2104150.3 | M75: 2275982.9 | N75: 8378503.9 | O75: 3700134 | P75: 291959.57 | Q75: 99.59 | R75: 0
D76: Vlr Servicio | E76: 831919.29 | F76: 0 | G76: 0 | H76: 0 | I76: 0 | J76: 0 | K76: 0 | L76: 4321.14 | M76: 6126.52 | N76: 6629.52 | O76: 814845.14 | P76: 0 | Q76: -3.03 | R76: 0
C77: 9 | D77: Total | E77: 831919.29 | F77: 0 | G77: 0 | H77: 0 | I77: 0 | J77: 0 | K77: 0 | L77: 4321.14 | M77: 6126.52 | N77: 6629.52 | O77: 814845.14 | P77: 0 | Q77: -3.03 | R77: 0
B78: NUEVO ESQUEMA | C78: Total | E78: 52469851 | F78: 3216777.6 | G78: 1799399.4 | H78: 773125.81 | I78: 14315916 | J78: 406510.66 | K78: 0 | L78: 3668619.8 | M78: 4175302.6 | N78: 14329479 | O78: 9282610.9 | P78: 502138.48 | Q78: -28.95 | R78: 0
D79: Vlr Servicio | E79: 11075335 | F79: 821378.55 | G79: 465927.35 | H79: 215214.87 | I79: 2963943.3 | J79: 82515.34 | K79: 0 | L79: 658290.51 | M79: 834824.5 | N79: 3348380.9 | O79: 1591238.4 | P79: 93600.37 | Q79: 20.46 | R79: 0
D80: Vlr Intereses | E80: 20136.06 | F80: 2455.33 | G80: 1132.97 | H80: 675.49 | I80: 3924.78 | J80: 92.44 | K80: 0 | L80: 810.75 | M80: 1058.05 | N80: 4906.98 | O80: 4928.45 | P80: 150.8 | Q80: 0.02 | R80: 0
C81: H | D81: Total | E81: 11095471 | F81: 823833.88 | G81: 467060.32 | H81: 215890.36 | I81: 2967868 | J81: 82607.78 | K81: 0 | L81: 659101.26 | M81: 835882.55 | N81: 3353287.9 | O81: 1596166.8 | P81: 93751.17 | Q81: 20.48 | R81: 0
D82: Vlr Servicio | E82: 38346937 | F82: 3218428.2 | G82: 1802927.9 | H82: 864947.8 | I82: 8956303.6 | J82: 272835.85 | K82: 0 | L82: 2439524.5 | M82: 2783253.1 | N82: 10966064 | O82: 6668396.5 | P82: 374240.28 | Q82: 15.41 | R82: 0
D83: Vlr Intereses | E83: 435116.55 | F83: 47759.13 | G83: 22622.8 | H83: 11464.99 | I83: 86745.59 | J83: 2665.2 | K83: 0 | L83: 22811.78 | M83: 28601.42 | N83: 113175.65 | O83: 94916.98 | P83: 4352.25 | Q83: 0.76 | R83: 0
C84: O | D84: Total | E84: 38782054 | F84: 3266187.3 | G84: 1825550.7 | H84: 876412.79 | I84: 9043049.2 | J84: 275501.05 | K84: 0 | L84: 2462336.3 | M84: 2811854.5 | N84: 11079240 | O84: 6763313.5 | P84: 378592.53 | Q84: 16.17 | R84: 0
D85: Vlr Servicio | E85: 42498049 | F85: 5756619.9 | G85: 3216233.5 | H85: 1817946.3 | I85: 1910670.2 | J85: 53108.69 | K85: 0 | L85: 473073.31 | M85: 611269.16 | N85: 2270384.9 | O85: 26329366 | P85: 59347.07 | Q85: 29.67 | R85: 0
D86: Vlr Intereses | E86: 9526.39 | F86: 1485.4 | G86: 831.8 | H86: 440.06 | I86: 1225.21 | J86: 39.88 | K86: 0 | L86: 349.95 | M86: 378.78 | N86: 1754.01 | O86: 2956.22 | P86: 65.09 | Q86: -0.01 | R86: 0
C87: T | D87: Total | E87: 42507575 | F87: 5758105.3 | G87: 3217065.3 | H87: 1818386.4 | I87: 1911895.4 | J87: 53148.57 | K87: 0 | L87: 473423.26 | M87: 611647.94 | N87: 2272138.9 | O87: 26332322 | P87: 59412.16 | Q87: 29.66 | R87: 0
B88: OCCIDENTE | C88: Total | E88: 92385100 | F88: 9848126.5 | G88: 5509676.3 | H88: 2910689.5 | I88: 13922813 | J88: 411257.4 | K88: 0 | L88: 3594860.9 | M88: 4259385 | N88: 16704667 | O88: 34691803 | P88: 531755.86 | Q88: 66.31 | R88: 0
A89: Componente | B89: Total | E89: 1.8332212e+08 | F89: 17193125 | G89: 9759590.5 | H89: 4674886.5 | I89: 47216081 | J89: 1451359.2 | K89: 28554.96 | L89: 13193070 | M89: 14193304 | N89: 54326292 | O89: 52723995 | P89: 1920514 | Q89: 181.61 | R89: 0
D90: Subsidio(-)/Contribucion(+) | E90: -16121295 | F90: -535197.19 | G90: -315094.83 | H90: -189104.93 | I90: -4617623.1 | J90: -160785.5 | K90: 0 | L90: -1360058 | M90: -1315487.9 | N90: -6434917.7 | O90: -931826.69 | P90: -261198.98 | Q90: 0 | R90: 0
C91: E | D91: Total | E91: -16121295 | F91: -535197.19 | G91: -315094.83 | H91: -189104.93 | I91: -4617623.1 | J91: -160785.5 | K91: 0 | L91: -1360058 | M91: -1315487.9 | N91: -6434917.7 | O91: -931826.69 | P91: -261198.98 | Q91: 0 | R91: 0
B92: ENEL | C92: Total | E92: -16121295 | F92: -535197.19 | G92: -315094.83 | H92: -189104.93 | I92: -4617623.1 | J92: -160785.5 | K92: 0 | L92: -1360058 | M92: -1315487.9 | N92: -6434917.7 | O92: -931826.69 | P92: -261198.98 | Q92: 0 | R92: 0
D93: Subsidio(-)/Contribucion(+) | E93: -7006158.8 | F93: -282130 | G93: -165135.7 | H93: -90452.73 | I93: -1975335 | J93: -54298.01 | K93: 0 | L93: -461440.15 | M93: -581546.05 | N93: -2784117 | O93: -524106.95 | P93: -87597.22 | Q93: 0 | R93: 0
C94: 1 | D94: Total | E94: -7006158.8 | F94: -282130 | G94: -165135.7 | H94: -90452.73 | I94: -1975335 | J94: -54298.01 | K94: 0 | L94: -461440.15 | M94: -581546.05 | N94: -2784117 | O94: -524106.95 | P94: -87597.22 | Q94: 0 | R94: 0
D95: Subsidio(-)/Contribucion(+) | E95: -413701.38 | F95: -13440.26 | G95: -10533.25 | H95: -5516.47 | I95: -126463.9 | J95: -3757.16 | K95: 0 | L95: -30796.66 | M95: -32644.48 | N95: -158503.21 | O95: -25915.95 | P95: -6130.04 | Q95: 0 | R95: 0
C96: 2 | D96: Total | E96: -413701.38 | F96: -13440.26 | G96: -10533.25 | H96: -5516.47 | I96: -126463.9 | J96: -3757.16 | K96: 0 | L96: -30796.66 | M96: -32644.48 | N96: -158503.21 | O96: -25915.95 | P96: -6130.04 | Q96: 0 | R96: 0
D97: Subsidio(-)/Contribucion(+) | E97: -9635661.9 | F97: -380166.3 | G97: -217737.2 | H97: -115469.42 | I97: -2737350.5 | J97: -82659.66 | K97: 0 | L97: -722316.87 | M97: -795775.12 | N97: -3736800.4 | O97: -713130.36 | P97: -134256.15 | Q97: 0 | R97: 0
C98: 5 | D98: Total | E98: -9635661.9 | F98: -380166.3 | G98: -217737.2 | H98: -115469.42 | I98: -2737350.5 | J98: -82659.66 | K98: 0 | L98: -722316.87 | M98: -795775.12 | N98: -3736800.4 | O98: -713130.36 | P98: -134256.15 | Q98: 0 | R98: 0
B99: NUEVO ESQUEMA | C99: Total | E99: -17055522 | F99: -675736.56 | G99: -393406.15 | H99: -211438.62 | I99: -4839149.3 | J99: -140714.83 | K99: 0 | L99: -1214553.7 | M99: -1409965.6 | N99: -6679420.6 | O99: -1263153.3 | P99: -227983.41 | Q99: 0 | R99: 0
D100: Subsidio(-)/Contribucion(+) | E100: -2195603.1 | F100: -15588.17 | G100: -50720.73 | H100: 1774.73 | I100: -677747.58 | J100: -19775.44 | K100: 0 | L100: -165236.81 | M100: -211413.62 | N100: -1031747.2 | O100: 5802.43 | P100: -30950.71 | Q100: 0 | R100: 0
C101: H | D101: Total | E101: -2195603.1 | F101: -15588.17 | G101: -50720.73 | H101: 1774.73 | I101: -677747.58 | J101: -19775.44 | K101: 0 | L101: -165236.81 | M101: -211413.62 | N101: -1031747.2 | O101: 5802.43 | P101: -30950.71 | Q101: 0 | R101: 0
D102: Subsidio(-)/Contribucion(+) | E102: -3983459.5 | F102: 385104.44 | G102: 177913.53 | H102: 79365.09 | I102: -1770775.2 | J102: -54327.37 | K102: 0 | L102: -463238.89 | M102: -534634.66 | N102: -2522494.7 | O102: 806737.08 | P102: -87108.85 | Q102: 0 | R102: 0
C103: O | D103: Total | E103: -3983459.5 | F103: 385104.44 | G103: 177913.53 | H103: 79365.09 | I103: -1770775.2 | J103: -54327.37 | K103: 0 | L103: -463238.89 | M103: -534634.66 | N103: -2522494.7 | O103: 806737.08 | P103: -87108.85 | Q103: 0 | R103: 0
D104: Subsidio(-)/Contribucion(+) | E104: 1242573 | F104: 343686.51 | G104: 192507.93 | H104: 97880.49 | I104: -39549.62 | J104: -1348.98 | K104: 0 | L104: -4691 | M104: -3711.96 | N104: -23147.87 | O104: 682556.78 | P104: -1609.3 | Q104: 0 | R104: 0
C105: T | D105: Total | E105: 1242573 | F105: 343686.51 | G105: 192507.93 | H105: 97880.49 | I105: -39549.62 | J105: -1348.98 | K105: 0 | L105: -4691 | M105: -3711.96 | N105: -23147.87 | O105: 682556.78 | P105: -1609.3 | Q105: 0 | R105: 0
B106: OCCIDENTE | C106: Total | E106: -4936489.7 | F106: 713202.78 | G106: 319700.73 | H106: 179020.31 | I106: -2488072.4 | J106: -75451.79 | K106: 0 | L106: -633166.7 | M106: -749760.24 | N106: -3577389.8 | O106: 1495096.3 | P106: -119668.86 | Q106: 0 | R106: 0
A107: Subs/Cont | B107: Total | E107: -35128653 | F107: -497730.97 | G107: -388800.25 | H107: -221523.24 | I107: -11944845 | J107: -376952.12 | K107: 0 | L107: -3207778.4 | M107: -3475213.8 | N107: -16691728 | O107: -699883.66 | P107: -608851.25 | Q107: 0 | R107: 0
A108: Total | E108: 1.7853909e+08 | F108: 16695394 | G108: 9370790.3 | H108: 4453363.2 | I108: 35271236 | J108: 1074407.1 | K108: 0 | L108: 9985291.5 | M108: 10718090 | N108: 37634564 | O108: 52024112 | P108: 1311662.8 | Q108: 181.61 | R108: 0
B139: TOTAL | C139: OPORTUNO | D139: Total | E139: =E89+E107-K89 -> 1.7853909e+08 | F139: =F89 -> 17193125 | G139: =G89 -> 9759590.5 | H139: =H89 -> 4674886.5 | I139: =I89 -> 47216081 | J139: =J89 -> 1451359.2 | K139: =K89 -> 0 | L139: =L89 -> 13193070 | M139: =M89 -> 14193304 | ... R139: =R89 -> 0
D140: Subsidio(-)/Contribucion(+) | E140: =E107 -> -38113307
B142: RECIPROCIDAD | C142: OPORTUNO | D142: Total | E142: =E99+E78-K78 -> 35414329 | F142: =F78 -> 3216777.6 | G142: =G78 -> 1799399.4 | H142: =H78 -> 773125.81 | I142: =I78 -> 14315916 | J142: =J78 -> 406510.66 | K142: =K78 -> 0 | L142: =L78 -> 3668619.8 | M142: =M78 -> 4175302.6 | ... R142: =R78 -> 0
D143: Subsidio(-)/Contribucion(+) | E143: =E99 -> -17055522
B145: ENEL | C145: OPORTUNO | D145: Total | E145: =E92+E66-K66 -> 55676153 | F145: =F66 -> 4128221.2 | G145: =G66 -> 2450514.8 | H145: =H66 -> 991071.1 | I145: =I66 -> 18977353 | J145: =J66 -> 633591.15 | K145: =K66 -> 0 | L145: =L66 -> 5929589.2 | M145: =M66 -> 5758616 | ... R145: =R66 -> 0
D146: Subsidio(-)/Contribucion(+) | E146: =E92 -> -16121295
B148: ENERBIT | C148: OPORTUNO | D148: Total | E148: 0 | F148: 0 | G148: 0 | H148: 0 | I148: 0 | J148: 0 | K148: 0 | L148: 0 | M148: 0 | N148: 0 | O148: 0 | P148: 0 | Q148: 0 | R148: 0
D149: Subsidio(-)/Contribucion(+) | E149: 0
B151: OCCIDENTE | C151: OPORTUNO | D151: Total | E151: =E88+E106-K88 -> 87448610 | F151: =F88 -> 9848126.5 | G151: =G88 -> 5509676.3 | H151: =H88 -> 2910689.5 | I151: =I88 -> 13922813 | J151: =J88 -> 411257.4 | K151: =K88 -> 0 | L151: =L88 -> 3594860.9 | M151: =M88 -> 4259385 | ... R151: =R88 -> 0
D152: Subsidio(-)/Contribucion(+) | E152: =E106 -> -4936489.7
B154: CIUDAD LIMPIA-ACUEDUCTO | C154: OPORTUNO | D154: Total | E154: 0 | F154: 0 | G154: 0 | H154: 0 | I154: 0 | J154: 0 | K154: 0 | L154: 0 | M154: 0 | N154: 0 | O154: 0 | P154: 0 | Q154: 0 | R154: 0
...

Sheet Reversion Pagos R4
B1: PROMOAMBIENTAL
D2: Total | E2: Componente TDF | F2: Componente TTL | G2: Componente TVIAT | H2: Aprovechamiento | I2: CCSA Prest.Aprov. | J2: Componente TCS | K2: Componente TLU | L2: Componente TBL | M2: Componente TRT | N2: CCSA Prest. No Aprov. | O2: Ajuste Decena | P2: SERVICIO ESPECIALES | Q2: Ajuste Recargo Aseo | R2: Otros
C3: Vlr Servicio | D3: -15794348 | E3: -792653.97 | F3: -443520.95 | G3: -235150.45 | H3: -3808729.7 | I3: -139986.99 | J3: -1241530.6 | K3: -1202003.5 | L3: -5520144.8 | M3: -2181286.4 | N3: -229451.13 | O3: 110.22 | P3: 0 | Q3: 0 | R3: 0
C4: Vlr Intereses | D4: -23575 | E4: -1070.04 | F4: -517.3 | G4: -287.09 | H4: -5416.02 | I4: -247.11 | J4: -2165.7 | K4: -1867.54 | L4: -8699.17 | M4: -2902.92 | N4: -402.93 | O4: 0.82 | P4: 0 | Q4: 0 | R4: 0
B5: Componente | C5: Total | D5: -15817923 | E5: -793724.01 | F5: -444038.25 | G5: -235437.54 | H5: -3814145.7 | I5: -140234.1 | J5: -1243696.3 | K5: -1203871 | L5: -5528844 | M5: -2184189.4 | N5: -229854.06 | O5: 111.04 | P5: 0 | Q5: 0 | R5: 0
C6: Subsidio(-)/Contribucion(+) | D6: 283961.51 | E6: -50016.63 | F6: -28439.29 | G6: -8473.6 | H6: 123071.72 | I6: 6856.23 | J6: 57818.27 | K6: 55412.62 | L6: 258242.83 | M6: -141530 | N6: 11019.36 | O6: 0 | P6: 0 | Q6: 0 | R6: 0
B7: Subs/Cont | C7: Total | D7: 283961.51 | E7: -50016.63 | F7: -28439.29 | G7: -8473.6 | H7: 123071.72 | I7: 6856.23 | J7: 57818.27 | K7: 55412.62 | L7: 258242.83 | M7: -141530 | N7: 11019.36 | O7: 0 | P7: 0 | Q7: 0 | R7: 0
A8: ENEL | B8: Total | D8: -15533962 | E8: -843740.64 | F8: -472477.54 | G8: -243911.14 | H8: -3691074 | I8: -133377.87 | J8: -1185878 | K8: -1148458.4 | L8: -5270601.2 | M8: -2325719.4 | N8: -218834.7 | O8: 111.04 | P8: 0 | Q8: 0 | R8: 0
C9: Vlr Servicio | D9: -762167.27 | E9: -48309.04 | F9: -26455.25 | G9: -13891.43 | H9: -192277.47 | I9: -4768.85 | J9: -58119.3 | K9: -51919.38 | L9: -246558.5 | M9: -112077.14 | N9: -7780.61 | O9: -10.3 | P9: 0 | Q9: 0 | R9: 0
C10: Vlr Intereses | D10: -177.06 | E10: -11.22 | F10: -6.34 | G10: -3.35 | H10: -43.6 | I10: -1.05 | J10: -9.24 | K10: -12.57 | L10: -57.05 | M10: -30.93 | N10: -1.71 | O10: 0 | P10: 0 | Q10: 0 | R10: 0
B11: Componente | C11: Total | D11: -762344.33 | E11: -48320.26 | F11: -26461.59 | G11: -13894.78 | H11: -192321.07 | I11: -4769.9 | J11: -58128.54 | K11: -51931.95 | L11: -246615.55 | M11: -112108.07 | N11: -7782.32 | O11: -10.3 | P11: 0 | Q11: 0 | R11: 0
C12: Subsidio(-)/Contribucion(+) | D12: -240407.06 | E12: -14057.56 | F12: -7937.89 | G12: -4170.17 | H12: -58249.85 | I12: -1605.37 | J12: -14082 | K12: -17535.88 | L12: -81716.35 | M12: -38432.73 | N12: -2619.26 | O12: 0 | P12: 0 | Q12: 0 | R12: 0
B13: Subs/Cont | C13: Total | D13: -240407.06 | E13: -14057.56 | F13: -7937.89 | G13: -4170.17 | H13: -58249.85 | I13: -1605.37 | J13: -14082 | K13: -17535.88 | L13: -81716.35 | M13: -38432.73 | N13: -2619.26 | O13: 0 | P13: 0 | Q13: 0 | R13: 0
A14: OCCIDENTE | B14: Total | D14: -1002751.4 | E14: -62377.82 | F14: -34399.48 | G14: -18064.95 | H14: -250570.92 | I14: -6375.27 | J14: -72210.54 | K14: -69467.83 | L14: -328331.9 | M14: -150540.8 | N14: -10401.58 | O14: -10.3 | P14: 0 | Q14: 0 | R14: 0
A15: Total | D15: -73090 | E15: -906118.46 | F15: -506877.02 | G15: -261976.09 | H15: -3941644.9 | I15: -139753.14 | J15: -1258088.5 | K15: -1217926.2 | L15: -5598933.1 | M15: -2476260.1 | N15: -229236.28 | O15: 100.74 | P15: 0 | Q15: 0 | R15: 0
A73: TOTAL | B73: OPORTUNO | C73: Total | D73: =D15-P15 -> -16536713 | E73: =E5+E11 -> -842044.27 | F73: =F5+F11 -> -470499.84 | G73: =G5+G11 -> -249332.32 | H73: =H5+H11 -> -4006466.8 | I73: =I5+I11 -> -145004 | J73: =J5+J11 -> -1301824.8 | K73: =K5+K11 -> -1255802.9 | L73: =L5+L11 -> -5775459.5 | ... R73: =R5+R11 -> 0
C74: Subsidio(-)/Contribucion(+) | D74: =D7+D13 -> 43554.45
A76: RECIPROCIDAD | B76: OPORTUNO | C76: Total | D76: 0 | E76: 0 | F76: 0 | G76: 0 | H76: 0 | I76: 0 | J76: 0 | K76: 0 | L76: 0 | M76: 0 | N76: 0 | O76: 0 | P76: 0 | Q76: 0 | R76: 0
C77: Subsidio(-)/Contribucion(+) | D77: 0
A79: ENEL | B79: OPORTUNO | C79: Total | D79: =D8-P8 -> -15533962 | E79: =E5 -> -793724.01 | F79: =F5 -> -444038.25 | G79: =G5 -> -235437.54 | H79: =H5 -> -3814145.7 | I79: =I5 -> -140234.1 | J79: =J5 -> -1243696.3 | K79: =K5 -> -1203871 | L79: =L5 -> -5528844 | ... R79: =R5 -> 0
C80: Subsidio(-)/Contribucion(+) | D80: =D7 -> 283961.51
A82: ENERBIT | B82: OPORTUNO | C82: Total | D82: 0 | E82: 0 | F82: 0 | G82: 0 | H82: 0 | I82: 0 | J82: 0 | K82: 0 | L82: 0 | M82: 0 | N82: 0 | O82: 0 | P82: 0 | Q82: 0 | R82: 0
C83: Subsidio(-)/Contribucion(+) | D83: 0
A85: OCCIDENTE | B85: OPORTUNO | C85: Total | D85: =D14-P14 -> -1002751.4 | E85: =E11 -> -48320.26 | F85: =F11 -> -26461.59 | G85: =G11 -> -13894.78 | H85: =H11 -> -192321.07 | I85: =I11 -> -4769.9 | J85: =J11 -> -58128.54 | K85: =K11 -> -51931.95 | L85: =L11 -> -246615.55 | ... R85: =R11 -> 0
C86: Subsidio(-)/Contribucion(+) | D86: =D13 -> -240407.06
A88: CIUDAD LIMPIA-ACUEDUCTO | B88: OPORTUNO | C88: Total | D88: 0 | E88: 0 | F88: 0 | G88: 0 | H88: 0 | I88: 0 | J88: 0 | K88: 0 | L88: 0 | M88: 0 | N88: 0 | O88: 0 | P88: 0 | Q88: 0 | R88: 0
C89: Subsidio(-)/Contribucion(+) | D89: 0
B91: LIME
D92: Total | E92: Componente TDF | F92: Componente TTL | G92: Componente TVIAT | H92: Aprovechamiento | I92: CCSA Prest.Aprov. | J92: Componente TCS | K92: Componente TLU | L92: Componente TBL | M92: Componente TRT | N92: CCSA Prest. No Aprov. | O92: Ajuste Decena | P92: SERVICIO ESPECIALES | Q92: Ajuste Recargo Aseo | R92: Otros
C93: Vlr Servicio | D93: -53998016 | E93: -11667185 | F93: -5414703.5 | G93: -2951482.2 | H93: -3201477.2 | I93: -115838.75 | J93: -1017620.8 | K93: -1016768.4 | L93: -4764304 | M93: -23659661 | N93: -188999.83 | O93: 24.58 | P93: 0 | Q93: 0 | R93: 0
C94: Vlr Intereses | D94: -15789582 | E94: -4170790.8 | F94: -1943304.3 | G94: -1075258 | H94: -52026.8 | I94: -1440.2 | J94: -12737.8 | K94: -15000.59 | L94: -66290.83 | M94: -8450381.3 | N94: -2350.38 | O94: -0.84 | P94: 0 | Q94: 0 | R94: 0
B95: Componente | C95: Total | D95: -69787598 | E95: -15837976 | F95: -7358007.8 | G95: -4026740.1 | H95: -3253504 | I95: -117278.95 | J95: -1030358.6 | K95: -1031769 | L95: -4830594.8 | M95: -32110042 | N95: -191350.21 | O95: 23.74 | P95: 0 | Q95: 0 | R95: 0
C96: Subsidio(-)/Contribucion(+) | D96: -991410.96 | E96: -916794.52 | F96: -399784.58 | G96: -225583.16 | H96: 753139.3 | I96: 27321.94 | J96: 241143.71 | K96: 238753.51 | L96: 1113806.2 | M96: -1867991.1 | N96: 44577.73 | O96: 0 | P96: 0 | Q96: 0 | R96: 0
B97: Subs/Cont | C97: Total | D97: -991410.96 | E97: -916794.52 | F97: -399784.58 | G97: -225583.16 | H97: 753139.3 | I97: 27321.94 | J97: 241143.71 | K97: 238753.51 | L97: 1113806.2 | M97: -1867991.1 | N97: 44577.73 | O97: 0 | P97: 0 | Q97: 0 | R97: 0
A98: ENEL | B98: Total | D98: -70779009 | E98: -16754771 | F98: -7757792.4 | G98: -4252323.3 | H98: -2500364.7 | I98: -89957.01 | J98: -789214.84 | K98: -793015.48 | L98: -3716788.6 | M98: -33978033 | N98: -146772.48 | O98: 23.74 | P98: 0 | Q98: 0 | R98: 0
C99: Vlr Servicio | D99: -377166.8 | E99: -43251.45 | F99: -24151.06 | G99: -13029.67 | H99: -77002.42 | I99: -2284.76 | J99: -20041.71 | K99: -20313.51 | L99: -87724.06 | M99: -86066.71 | N99: -3305.91 | O99: 4.46 | P99: 0 | Q99: 0 | R99: 0
C100: Vlr Intereses | D100: -9054.66 | E100: -491.84 | F100: -219.75 | G100: -125.76 | H100: -2696.53 | I100: -61.76 | J100: -541.98 | K100: -671.69 | L100: -3161.57 | M100: -983.04 | N100: -100.83 | O100: 0.09 | P100: 0 | Q100: 0 | R100: 0
B101: Componente | C101: Total | D101: -386221.46 | E101: -43743.29 | F101: -24370.81 | G101: -13155.43 | H101: -79698.95 | I101: -2346.52 | J101: -20583.69 | K101: -20985.2 | L101: -90885.63 | M101: -87049.75 | N101: -3406.74 | O101: 4.55 | P101: 0 | Q101: 0 | R101: 0
C102: Subsidio(-)/Contribucion(+) | D102: 95471.46 | E102: 4869.41 | F102: 2653.99 | G102: 1418.22 | H102: 24431.4 | I102: 804.56 | J102: 7057.6 | K102: 7551.54 | L102: 35697.19 | M102: 9674.81 | N102: 1312.74 | O102: 0 | P102: 0 | Q102: 0 | R102: 0
B103: Subs/Cont | C103: Total | D103: 95471.46 | E103: 4869.41 | F103: 2653.99 | G103: 1418.22 | H103: 24431.4 | I103: 804.56 | J103: 7057.6 | K103: 7551.54 | L103: 35697.19 | M103: 9674.81 | N103: 1312.74 | O103: 0 | P103: 0 | Q103: 0 | R103: 0
A104: OCCIDENTE | B104: Total | D104: -290750 | E104: -38873.88 | F104: -21716.82 | G104: -11737.21 | H104: -55267.55 | I104: -1541.96 | J104: -13526.09 | K104: -13433.66 | L104: -55188.44 | M104: -77374.94 | N104: -2094 | O104: 4.55 | P104: 0 | Q104: 0 | R104: 0
A105: Total | D105: -13472482 | E105: -16793644 | F105: -7779509.2 | G105: -4264060.5 | H105: -2555632.3 | I105: -91498.97 | J105: -802740.93 | K105: -806449.14 | L105: -3771977 | M105: -34055408 | N105: -148866.48 | O105: 28.29 | P105: 0 | Q105: 0 | R105: 0
A168: TOTAL | B168: OPORTUNO | C168: Total | D168: =D105-P105 -> -71069759 | E168: =E101+E95 -> -15881719 | F168: =F101+F95 -> -7382378.6 | G168: =G101+G95 -> -4039895.6 | H168: =H101+H95 -> -3333203 | I168: =I101+I95 -> -119625.47 | J168: =J101+J95 -> -1050942.2 | K168: =K101+K95 -> -1052754.2 | L168: =L101+L95 -> -4921480.5 | ... R168: =R101+R95 -> 0
C169: Subsidio(-)/Contribucion(+) | D169: =D103+D97 -> -895939.5
A171: RECIPROCIDAD | B171: OPORTUNO | C171: Total | D171: 0 | E171: 0 | F171: 0 | G171: 0 | H171: 0 | I171: 0 | J171: 0 | K171: 0 | L171: 0 | M171: 0 | N171: 0 | O171: 0 | P171: 0 | Q171: 0 | R171: 0
C172: Subsidio(-)/Contribucion(+) | D172: 0
A174: ENEL | B174: OPORTUNO | C174: Total | D174: =D98-P98 -> -70779009 | E174: =E95 -> -15837976 | F174: =F95 -> -7358007.8 | G174: =G95 -> -4026740.1 | H174: =H95 -> -3253504 | I174: =I95 -> -117278.95 | J174: =J95 -> -1030358.6 | K174: =K95 -> -1031769 | L174: =L95 -> -4830594.8 | ... R174: =R95 -> 0
C175: Subsidio(-)/Contribucion(+) | D175: =D97 -> -991410.96
A177: ENERBIT | B177: OPORTUNO | C177: Total | D177: 0 | E177: 0 | F177: 0 | G177: 0 | H177: 0 | I177: 0 | J177: 0 | K177: 0 | L177: 0 | M177: 0 | N177: 0 | O177: 0 | P177: 0 | Q177: 0 | R177: 0
C178: Subsidio(-)/Contribucion(+) | D178: 0
A180: OCCIDENTE | B180: OPORTUNO | C180: Total | D180: =D104-P104 -> -290750 | E180: =E101 -> -43743.29 | F180: =F101 -> -24370.81 | G180: =G101 -> -13155.43 | H180: =H101 -> -79698.95 | I180: =I101 -> -2346.52 | J180: =J101 -> -20583.69 | K180: =K101 -> -20985.2 | L180: =L101 -> -90885.63 | ... R180: =R101 -> 0
C181: Subsidio(-)/Contribucion(+) | D181: =D103 -> 95471.46
A183: CIUDAD LIMPIA-ACUEDUCTO | B183: OPORTUNO | C183: Total | D183: 0 | E183: 0 | F183: 0 | G183: 0 | H183: 0 | I183: 0 | J183: 0 | K183: 0 | L183: 0 | M183: 0 | N183: 0 | O183: 0 | P183: 0 | Q183: 0 | R183: 0
C184: Subsidio(-)/Contribucion(+) | D184: 0
B186: CIUDAD LIMPIA
D187: Total | E187: Componente TDF | F187: Componente TTL | G187: Componente TVIAT | H187: Aprovechamiento | I187: CCSA Prest.Aprov. | J187: Componente TCS | K187: Componente TLU | L187: Componente TBL | M187: Componente TRT | N187: CCSA Prest. No Aprov. | O187: Ajuste Decena | P187: SERVICIO ESPECIALES | Q187: Ajuste Recargo Aseo | R187: Otros
C188: Vlr Servicio | D188: -27227799 | E188: -2315528.5 | F188: -1284217.6 | G188: -681382.92 | H188: -5451652.2 | I188: -202328.82 | J188: -1782592.4 | K188: -1715323.7 | L188: -8067276.3 | M188: -5394689.7 | N188: -332680.61 | O188: -126.11 | P188: 0 | Q188: 0 | R188: 0
C189: Vlr Intereses | D189: -345928.04 | E189: -25008.84 | F189: -12602.88 | G189: -7036.43 | H189: -80348.21 | I189: -2983.37 | J189: -25907.02 | K189: -22627.65 | L189: -105993.62 | M189: -58451.89 | N189: -4966.27 | O189: -1.86 | P189: 0 | Q189: 0 | R189: 0
B190: Componente | C190: Total | D190: -27573727 | E190: -2340537.3 | F190: -1296820.5 | G190: -688419.35 | H190: -5532000.4 | I190: -205312.19 | J190: -1808499.4 | K190: -1737951.4 | L190: -8173269.9 | M190: -5453141.6 | N190: -337646.88 | O190: -127.97 | P190: 0 | Q190: 0 | R190: 0
C191: Subsidio(-)/Contribucion(+) | D191: -4430593.2 | E191: -1063182.6 | F191: -614089.04 | G191: -323946.96 | H191: -38852 | I191: -204.27 | J191: 8451.79 | K191: 15720.47 | L191: 51334.92 | M191: -2466098.4 | N191: 272.9 | O191: 0 | P191: 0 | Q191: 0 | R191: 0
B192: Subs/Cont | C192: Total | D192: -4430593.2 | E192: -1063182.6 | F192: -614089.04 | G192: -323946.96 | H192: -38852 | I192: -204.27 | J192: 8451.79 | K192: 15720.47 | L192: 51334.92 | M192: -2466098.4 | N192: 272.9 | O192: 0 | P192: 0 | Q192: 0 | R192: 0
A193: ENEL | B193: Total | D193: -32004320 | E193: -3403720 | F193: -1910909.5 | G193: -1012366.3 | H193: -5570852.4 | I193: -205516.46 | J193: -1800047.6 | K193: -1722230.9 | L193: -8121935 | M193: -7919240 | N193: -337373.98 | O193: -127.97 | P193: 0 | Q193: 0 | R193: 0
C194: Vlr Servicio | D194: -397050.36 | E194: -18659.83 | F194: -10362.45 | G194: -4678.66 | H194: -109695.93 | I194: -3357.59 | J194: -29452.65 | K194: -33114.32 | L194: -139136.36 | M194: -43529.99 | N194: -5062.02 | O194: -0.56 | P194: 0 | Q194: 0 | R194: 0
C195: Vlr Intereses | D195: -785.24 | E195: -33.72 | F195: -17.4 | G195: -10.35 | H195: -222.64 | I195: -7.01 | J195: -61.61 | K195: -60.33 | L195: -281.65 | M195: -79.05 | N195: -11.44 | O195: -0.04 | P195: 0 | Q195: 0 | R195: 0
B196: Componente | C196: Total | D196: -397835.6 | E196: -18693.55 | F196: -10379.85 | G196: -4689.01 | H196: -109918.57 | I196: -3364.6 | J196: -29514.26 | K196: -33174.65 | L196: -139418.01 | M196: -43609.04 | N196: -5073.46 | O196: -0.6 | P196: 0 | Q196: 0 | R196: 0
C197: Subsidio(-)/Contribucion(+) | D197: 91175.8 | E197: 4274.38 | F197: 2344.18 | G197: 1290.14 | H197: 24141.72 | I197: 835.82 | J197: 7331.65 | K197: 6999.36 | L197: 32593.77 | M197: 10001.11 | N197: 1363.67 | O197: 0 | P197: 0 | Q197: 0 | R197: 0
B198: Subs/Cont | C198: Total | D198: 91175.8 | E198: 4274.38 | F198: 2344.18 | G198: 1290.14 | H198: 24141.72 | I198: 835.82 | J198: 7331.65 | K198: 6999.36 | L198: 32593.77 | M198: 10001.11 | N198: 1363.67 | O198: 0 | P198: 0 | Q198: 0 | R198: 0
A199: OCCIDENTE | B199: Total | D199: -306659.8 | E199: -14419.17 | F199: -8035.67 | G199: -3398.87 | H199: -85776.85 | I199: -2528.78 | J199: -22182.61 | K199: -26175.29 | L199: -106824.24 | M199: -33607.93 | N199: -3709.79 | O199: -0.6 | P199: 0 | Q199: 0 | R199: 0
A200: Total | D200: -4617354 | E200: -3418139.1 | F200: -1918945.2 | G200: -1015765.2 | H200: -5656629.2 | I200: -208045.24 | J200: -1822230.2 | K200: -1748406.2 | L200: -8228759.2 | M200: -7952847.9 | N200: -341083.77 | O200: -128.57 | P200: 0 | Q200: 0 | R200: 0
A205: TOTAL | B205: OPORTUNO | C205: Total | D205: =D200-P200 -> -32310980 | E205: =E196+E190 -> -2359230.9 | F205: =F196+F190 -> -1307200.3 | G205: =G196+G190 -> -693108.36 | H205: =H196+H190 -> -5641919 | I205: =I196+I190 -> -208676.79 | J205: =J196+J190 -> -1838013.6 | K205: =K196+K190 -> -1771126 | L205: =L196+L190 -> -8312687.9 | ... R205: =R196+R190 -> 0
C206: Subsidio(-)/Contribucion(+) | D206: =D198+D192 -> -4339417.4
A208: RECIPROCIDAD | B208: OPORTUNO | C208: Total | D208: 0 | E208: 0 | F208: 0 | G208: 0 | H208: 0 | I208: 0 | J208: 0 | K208: 0 | L208: 0 | M208: 0 | N208: 0 | O208: 0 | P208: 0 | Q208: 0 | R208: 0
C209: Subsidio(-)/Contribucion(+) | D209: 0
A211: ENEL | B211: OPORTUNO | C211: Total | D211: =D193-P193 -> -32004320 | E211: =E190 -> -2340537.3 | F211: =F190 -> -1296820.5 | G211: =G190 -> -688419.35 | H211: =H190 -> -5532000.4 | I211: =I190 -> -205312.19 | J211: =J190 -> -1808499.4 | K211: =K190 -> -1737951.4 | L211: =L190 -> -8173269.9 | ... R211: =R190 -> 0
C212: Subsidio(-)/Contribucion(+) | D212: =D192 -> -4430593.2
A214: ENERBIT | B214: OPORTUNO | C214: Total | D214: 0 | E214: 0 | F214: 0 | G214: 0 | H214: 0 | I214: 0 | J214: 0 | K214: 0 | L214: 0 | M214: 0 | N214: 0 | O214: 0 | P214: 0 | Q214: 0 | R214: 0
C215: Subsidio(-)/Contribucion(+) | D215: 0
A217: OCCIDENTE | B217: OPORTUNO | C217: Total | D217: =D199-P199 -> -306659.8 | E217: =E196 -> -18693.55 | F217: =F196 -> -10379.85 | G217: =G196 -> -4689.01 | H217: =H196 -> -109918.57 | I217: =I196 -> -3364.6 | J217: =J196 -> -29514.26 | K217: =K196 -> -33174.65 | L217: =L196 -> -139418.01 | ... R217: =R196 -> 0
C218: Subsidio(-)/Contribucion(+) | D218: =D198 -> 91175.8
A220: CIUDAD LIMPIA-ACUEDUCTO | B220: OPORTUNO | C220: Total | D220: 0 | E220: 0 | F220: 0 | G220: 0 | H220: 0 | I220: 0 | J220: 0 | K220: 0 | L220: 0 | M220: 0 | N220: 0 | O220: 0 | P220: 0 | Q220: 0 | R220: 0
C221: Subsidio(-)/Contribucion(+) | D221: 0
B223: BOGOTA LIMPIA
D224: Total | E224: Componente TDF | F224: Componente TTL | G224: Componente TVIAT | H224: Aprovechamiento | I224: CCSA Prest.Aprov. | J224: Componente TCS | K224: Componente TLU | L224: Componente TBL | M224: Componente TRT | N224: CCSA Prest. No Aprov. | O224: Ajuste Decena | P224: SERVICIO ESPECIALES | Q224: Ajuste Recargo Aseo | R224: Otros
C225: Vlr Servicio | D225: -21566863 | E225: -1602733.6 | F225: -896891.02 | G225: -475692.34 | H225: -4329801.2 | I225: -156115.79 | J225: -1354111 | K225: -1357517.4 | L225: -6863140.8 | M225: -4276100.4 | N225: -254729.55 | O225: -30.13 | P225: 0 | Q225: 0 | R225: 0
C226: Vlr Intereses | D226: -10375865 | E226: -1376999.4 | F226: -590233.5 | G226: -209963.97 | H226: -1412012.6 | I226: -55947.15 | J226: -490779.37 | K226: -582672.58 | L226: -1966419 | M226: -3599557 | N226: -91288.76 | O226: 8.34 | P226: 0 | Q226: 0 | R226: -0.29
B227: Componente | C227: Total | D227: -31942729 | E227: -2979733 | F227: -1487124.5 | G227: -685656.31 | H227: -5741813.8 | I227: -212062.94 | J227: -1844890.4 | K227: -1940190 | L227: -8829559.8 | M227: -7875657.5 | N227: -346018.31 | O227: -21.79 | P227: 0 | Q227: 0 | R227: -0.29
C228: Subsidio(-)/Contribucion(+) | D228: 2174082.8 | E228: 22089.07 | F228: 10938.57 | G228: 6096.13 | H228: 636523.27 | I228: 22219.55 | J228: 194912.33 | K228: 197393.84 | L228: 989072.18 | M228: 58583.97 | N228: 36253.89 | O228: 0 | P228: 0 | Q228: 0 | R228: 0
B229: Subs/Cont | C229: Total | D229: 2174082.8 | E229: 22089.07 | F229: 10938.57 | G229: 6096.13 | H229: 636523.27 | I229: 22219.55 | J229: 194912.33 | K229: 197393.84 | L229: 989072.18 | M229: 58583.97 | N229: 36253.89 | O229: 0 | P229: 0 | Q229: 0 | R229: 0
A230: ENEL | B230: Total | D230: -29768646 | E230: -2957643.9 | F230: -1476185.9 | G230: -679560.18 | H230: -5105290.6 | I230: -189843.39 | J230: -1649978 | K230: -1742796.2 | L230: -7840487.6 | M230: -7817073.5 | N230: -309764.42 | O230: -21.79 | P230: 0 | Q230: 0 | R230: -0.29
C231: Vlr Servicio | D231: -855911.65 | E231: -56578.79 | F231: -29944.45 | G231: -16676.99 | H231: -192512.79 | I231: -5218.15 | J231: -44076.57 | K231: -55205.51 | L231: -296108.41 | M231: -151081.81 | N231: -8513.86 | O231: 5.68 | P231: 0 | Q231: 0 | R231: 0
C232: Vlr Intereses | D232: -456.33 | E232: -43.08 | F232: -19.82 | G232: -11.45 | H232: -92.32 | I232: -2.28 | J232: -19.89 | K232: -24.84 | L232: -122.9 | M232: -116.06 | N232: -3.69 | O232: 0 | P232: 0 | Q232: 0 | R232: 0
B233: Componente | C233: Total | D233: -856367.98 | E233: -56621.87 | F233: -29964.27 | G233: -16688.44 | H233: -192605.11 | I233: -5220.43 | J233: -44096.46 | K233: -55230.35 | L233: -296231.31 | M233: -151197.87 | N233: -8517.55 | O233: 5.68 | P233: 0 | Q233: 0 | R233: 0
C234: Subsidio(-)/Contribucion(+) | D234: 120337.98 | E234: -5853.75 | F234: -3466.39 | G234: -1802.77 | H234: 44564.39 | I234: 1338.88 | J234: 11744.63 | K234: 14317.92 | L234: 72511.87 | M234: -15201.3 | N234: 2184.5 | O234: 0 | P234: 0 | Q234: 0 | R234: 0
B235: Subs/Cont | C235: Total | D235: 120337.98 | E235: -5853.75 | F235: -3466.39 | G235: -1802.77 | H235: 44564.39 | I235: 1338.88 | J235: 11744.63 | K235: 14317.92 | L235: 72511.87 | M235: -15201.3 | N235: 2184.5 | O235: 0 | P235: 0 | Q235: 0 | R235: 0
A236: NUEVO ESQUEMA | B236: Total | D236: -736030 | E236: -62475.62 | F236: -33430.66 | G236: -18491.21 | H236: -148040.72 | I236: -3881.55 | J236: -32351.83 | K236: -40912.43 | L236: -223719.44 | M236: -166399.17 | N236: -6333.05 | O236: 5.68 | P236: 0 | Q236: 0 | R236: 0
C237: Vlr Servicio | D237: -3952597.5 | E237: -239180.98 | F237: -134746.5 | G237: -69663.42 | H237: -865036.73 | I237: -28695.58 | J237: -279525.13 | K237: -279118.37 | L237: -1359152.7 | M237: -648894.61 | N237: -48597.18 | O237: 13.73 | P237: 0 | Q237: 0 | R237: 0
C238: Vlr Intereses | D238: -72621.51 | E238: -5294.3 | F238: -1735.02 | G238: -406.34 | H238: -9879.81 | I238: -851.94 | J238: -7477.78 | K238: -6895.96 | L238: -23542.38 | M238: -15148.31 | N238: -1390.75 | O238: 1.08 | P238: 0 | Q238: 0 | R238: 0
B239: Componente | C239: Total | D239: -4025219 | E239: -244475.28 | F239: -136481.52 | G239: -70069.76 | H239: -874916.54 | I239: -29547.52 | J239: -287002.91 | K239: -286014.33 | L239: -1382695.1 | M239: -664042.92 | N239: -49987.93 | O239: 14.81 | P239: 0 | Q239: 0 | R239: 0
C240: Subsidio(-)/Contribucion(+) | D240: 791790.67 | E240: 30614.54 | F240: 15664.41 | G240: 8427.03 | H240: 198488.51 | I240: 7139.75 | J240: 62630.13 | K240: 62193.6 | L240: 307975.48 | M240: 87007.94 | N240: 11649.28 | O240: 0 | P240: 0 | Q240: 0 | R240: 0
B241: Subs/Cont | C241: Total | D241: 791790.67 | E241: 30614.54 | F241: 15664.41 | G241: 8427.03 | H241: 198488.51 | I241: 7139.75 | J241: 62630.13 | K241: 62193.6 | L241: 307975.48 | M241: 87007.94 | N241: 11649.28 | O241: 0 | P241: 0 | Q241: 0 | R241: 0
...

Sheet SALDOS POR NOTA
B1: PROMOAMBIENTAL
C2: Total | D2: Componente TDF | E2: Componente TTL | F2: Componente TVIAT | G2: Aprovechamiento | H2: CCSA Prest.Aprov. | I2: Especiales | J2: Componente TCS | K2: Componente TLU | L2: Componente TBL | M2: Componente TRT | N2: CCSA Prest. No Aprov. | O2: Deb/Cred
B3: Vlr Servicio | C3: 803959.68 | D3: 65039.95 | E3: 36337.02 | F3: 19274.13 | G3: 155423.91 | H3: 5618.35 | I3: 0 | J3: 56003.23 | K3: 48167.15 | L3: 226758.45 | M3: 182170.76 | N3: 9166.69 | O3: 0.04
A4: Componente | B4: Total | C4: 803959.68 | D4: 65039.95 | E4: 36337.02 | F4: 19274.13 | G4: 155423.91 | H4: 5618.35 | I4: 0 | J4: 56003.23 | K4: 48167.15 | L4: 226758.45 | M4: 182170.76 | N4: 9166.69 | O4: 0.04
B5: Subsidio(-)/Contribucion(+) | C5: 2996.3 | D5: 701.47 | E5: 403.84 | F5: 207.9 | G5: -7189.94 | H5: -331.56 | I5: 0 | J5: -1228.7 | K5: 624.41 | L5: 3023.5 | M5: 7326.36 | N5: -540.98 | O5: 0
A6: Subs/Cont | B6: Total | C6: 2996.3 | D6: 701.47 | E6: 403.84 | F6: 207.9 | G6: -7189.94 | H6: -331.56 | I6: 0 | J6: -1228.7 | K6: 624.41 | L6: 3023.5 | M6: 7326.36 | N6: -540.98 | O6: 0
A7: Total | C7: 806955.98 | D7: 65741.42 | E7: 36740.86 | F7: 19482.03 | G7: 148233.97 | H7: 5286.79 | I7: 0 | J7: 54774.53 | K7: 48791.56 | L7: 229781.95 | M7: 189497.12 | N7: 8625.71 | O7: 0.04
B9: Total | C9: =C7-I7 -> 973693.46 | D9: =D4 -> 65524.22 | E9: =E4 -> 36995.02 | F9: =F4 -> 19417.65 | G9: =G4 -> 156624.35 | H9: =H4 -> 5557.5 | I9: =I4 -> 0 | J9: =J4 -> 52109.79 | K9: =K4 -> 47607.03 | ... P9: =P4 -> 0
B10: Subsidio(-)/Contribucion(+) | C10: =C6 -> 176919.99
B13: LIME
C14: Total | D14: Componente TDF | E14: Componente TTL | F14: Componente TVIAT | G14: Aprovechamiento | H14: CCSA Prest.Aprov. | I14: Especiales | J14: Componente TCS | K14: Componente TLU | L14: Componente TBL | M14: Componente TRT | N14: CCSA Prest. No Aprov. | O14: Deb/Cred
B15: Vlr Servicio | C15: 931073.72 | D15: 42296.72 | E15: 23907.98 | F15: 12706.35 | G15: 265979.53 | H15: 11995.53 | I15: 0 | J15: 66026.12 | K15: 73645.62 | L15: 345565.65 | M15: 81955.14 | N15: 6998.74 | O15: -3.66
B16: Vlr Intereses | C16: 0 | D16: 0 | E16: 0 | F16: 0 | G16: 0 | H16: 0 | I16: 0 | J16: 0 | K16: 0 | L16: 0 | M16: 0 | N16: 0 | O16: 0.01
A17: Componente | B17: Total | C17: 931073.72 | D17: 42296.72 | E17: 23907.98 | F17: 12706.35 | G17: 265979.53 | H17: 11995.53 | I17: 0 | J17: 66026.12 | K17: 73645.62 | L17: 345565.65 | M17: 81955.14 | N17: 6998.74 | O17: -3.66
B18: Subsidio(-)/Contribucion(+) | C18: -424218.36 | D18: -25301.13 | E18: -14256.81 | F18: -7179.68 | G18: -99943.77 | H18: -3389 | I18: 0 | J18: -52251.81 | K18: -30693.42 | L18: -136897.35 | M18: -48943.73 | N18: -5361.66 | O18: 0
A19: Subs/Cont | B19: Total | C19: -424218.36 | D19: -25301.13 | E19: -14256.81 | F19: -7179.68 | G19: -99943.77 | H19: -3389 | I19: 0 | J19: -52251.81 | K19: -30693.42 | L19: -136897.35 | M19: -48943.73 | N19: -5361.66 | O19: 0
A20: Total | C20: 506855.36 | D20: 16995.59 | E20: 9651.17 | F20: 5526.67 | G20: 166035.76 | H20: 8606.53 | I20: 0 | J20: 13774.31 | K20: 42952.2 | L20: 208668.3 | M20: 33011.41 | N20: 1637.08 | O20: -3.66
B22: Total | C22: =C20-I20 -> 216025.77 | D22: =D17 -> 31897.62 | E22: =E17 -> 18572.91 | F22: =F17 -> 8867.14 | G22: =G17 -> 92959.49 | H22: =H17 -> 3883.88 | I22: =I17 -> 0 | J22: =J17 -> 61358.09 | K22: =K17 -> 33534.01 | ... P22: =P17 -> 0
B23: Subsidio(-)/Contribucion(+) | C23: =C19 -> -232518.12
B26: CIUDAD LIMPIA
C27: Total | D27: Componente TDF | E27: Componente TTL | F27: Componente TVIAT | G27: Aprovechamiento | H27: CCSA Prest.Aprov. | I27: Especiales | J27: Componente TCS | K27: Componente TLU | L27: Componente TBL | M27: Componente TRT | N27: CCSA Prest. No Aprov. | O27: Deb/Cred
B28: Vlr Servicio | C28: 114219.07 | D28: 6267.13 | E28: 3538.42 | F28: 1857.22 | G28: 42966.81 | H28: 743.08 | I28: 0 | J28: 6518.28 | K28: 6322.58 | L28: 29933.14 | M28: 14860.01 | N28: 1212.4 | O28: 0
A29: Componente | B29: Total | C29: 114219.07 | D29: 6267.13 | E29: 3538.42 | F29: 1857.22 | G29: 42966.81 | H29: 743.08 | I29: 0 | J29: 6518.28 | K29: 6322.58 | L29: 29933.14 | M29: 14860.01 | N29: 1212.4 | O29: 0
B30: Subsidio(-)/Contribucion(+) | C30: 4655.77 | D30: 1594.44 | E30: 900.22 | F30: 472.5 | G30: -4328.45 | H30: 37.15 | I30: 0 | J30: 325.91 | K30: 316.13 | L30: 1496.66 | M30: 3780.59 | N30: 60.62 | O30: 0
A31: Subs/Cont | B31: Total | C31: 4655.77 | D31: 1594.44 | E31: 900.22 | F31: 472.5 | G31: -4328.45 | H31: 37.15 | I31: 0 | J31: 325.91 | K31: 316.13 | L31: 1496.66 | M31: 3780.59 | N31: 60.62 | O31: 0
A32: Total | C32: 118874.84 | D32: 7861.57 | E32: 4438.64 | F32: 2329.72 | G32: 38638.36 | H32: 780.23 | I32: 0 | J32: 6844.19 | K32: 6638.71 | L32: 31429.8 | M32: 18640.6 | N32: 1273.02 | O32: 0
B34: Total | C34: =C32-I32 -> 104231.83 | D34: =D29 -> 6620.63 | E34: =E29 -> 3738.02 | F34: =F29 -> 1961.98 | G34: =G29 -> 20927.5 | H34: =H29 -> 743.08 | I34: =I29 -> 0 | J34: =J29 -> 6518.28 | K34: =K29 -> 6410.86 | ... P34: =P29 -> 0
B35: Subsidio(-)/Contribucion(+) | C35: =C31 -> 10366.88
B38: BOGOTA LIMPIA
C39: Total | D39: Componente TDF | E39: Componente TTL | F39: Componente TVIAT | G39: Aprovechamiento | H39: CCSA Prest.Aprov. | I39: Especiales | J39: Componente TCS | K39: Componente TLU | L39: Componente TBL | M39: Componente TRT | N39: CCSA Prest. No Aprov. | O39: Deb/Cred
B40: Vlr Servicio | C40: 1030030.2 | D40: 30353.42 | E40: 17272.31 | F40: 7260.85 | G40: 195770.56 | H40: 5001.67 | I40: 0 | J40: 31654.75 | K40: 16169.51 | L40: 630665.63 | M40: 92025.49 | N40: 3836.24 | O40: 19.81
B41: Vlr Intereses | C41: -5455.56 | D41: 0 | E41: 0 | F41: 0 | G41: 0 | H41: 0 | I41: 0 | J41: 0 | K41: 0 | L41: -5455.76 | M41: 0 | N41: 0 | O41: 0.2
A42: Componente | B42: Total | C42: 1024574.7 | D42: 30353.42 | E42: 17272.31 | F42: 7260.85 | G42: 195770.56 | H42: 5001.67 | I42: 0 | J42: 31654.75 | K42: 16169.51 | L42: 625209.87 | M42: 92025.49 | N42: 3836.24 | O42: 20.01
B43: Subsidio(-)/Contribucion(+) | C43: -706260.2 | D43: -35225.22 | E43: -19886.85 | F43: -10438.97 | G43: -172708.87 | H43: -4226.24 | I43: 0 | J43: -37074.28 | K43: -53305.25 | L43: -273257.91 | M43: -93241.08 | N43: -6895.53 | O43: 0
A44: Subs/Cont | B44: Total | C44: -706260.2 | D44: -35225.22 | E44: -19886.85 | F44: -10438.97 | G44: -172708.87 | H44: -4226.24 | I44: 0 | J44: -37074.28 | K44: -53305.25 | L44: -273257.91 | M44: -93241.08 | N44: -6895.53 | O44: 0
A45: Total | C45: 318314.48 | D45: -4871.8 | E45: -2614.54 | F45: -3178.12 | G45: 23061.69 | H45: 775.43 | I45: 0 | J45: -5419.53 | K45: -37135.74 | L45: 351951.96 | M45: -1215.59 | N45: -3059.29 | O45: 20.01
B47: Total | C47: =C45-I45 -> 35954.44 | D47: =D42 -> 1890.6 | E47: =E42 -> 1067.43 | F47: =F42 -> 560.27 | G47: =G42 -> 10800.02 | H47: =H42 -> 371.66 | I47: =I42 -> 0 | J47: =J42 -> 3260.18 | K47: =K42 -> 3149.08 | ... P47: =P42 -> 0
B48: Subsidio(-)/Contribucion(+) | C48: =C44 -> -6453.76
B51: AREA LIMPIA
C52: Total | D52: Componente TDF | E52: Componente TTL | F52: Componente TVIAT | G52: Aprovechamiento | H52: CCSA Prest.Aprov. | I52: Especiales | J52: Componente TCS | K52: Componente TLU | L52: Componente TBL | M52: Componente TRT | N52: CCSA Prest. No Aprov. | O52: Deb/Cred
B53: Vlr Servicio | C53: 0 | D53: 0 | E53: 0 | F53: 0 | G53: 0 | H53: 0 | I53: 0 | J53: 0 | K53: 0 | L53: 0 | M53: 0 | N53: 0 | O53: 0
B54: Vlr Intereses | C54: 0 | D54: 0 | E54: 0 | F54: 0 | G54: 0 | H54: 0 | I54: 0 | J54: 0 | K54: 0 | L54: 0 | M54: 0 | N54: 0 | O54: 0
A55: Componente | B55: Total | C55: 0 | D55: 0 | E55: 0 | F55: 0 | G55: 0 | H55: 0 | I55: 0 | J55: 0 | K55: 0 | L55: 0 | M55: 0 | N55: 0 | O55: 0
B56: Subsidio(-)/Contribucion(+) | C56: 0 | D56: 0 | E56: 0 | F56: 0 | G56: 0 | H56: 0 | I56: 0 | J56: 0 | K56: 0 | L56: 0 | M56: 0 | N56: 0 | O56: 0
A57: Subs/Cont | B57: Total | C57: 0 | D57: 0 | E57: 0 | F57: 0 | G57: 0 | H57: 0 | I57: 0 | J57: 0 | K57: 0 | L57: 0 | M57: 0 | N57: 0 | O57: 0
A58: Total | C58: 0 | D58: 0 | E58: 0 | F58: 0 | G58: 0 | H58: 0 | I58: 0 | J58: 0 | K58: 0 | L58: 0 | M58: 0 | N58: 0 | O58: 0
B60: Total | C60: =C58-I58 -> 0 | D60: =D55 -> 0 | E60: =E55 -> 0 | F60: =F55 -> 0 | G60: =G55 -> 0 | H60: =H55 -> 0 | I60: =I55 -> 0 | J60: =J55 -> 0 | K60: =K55 -> 0 | ... P60: =P55 -> 0
B61: Subsidio(-)/Contribucion(+) | C61: =C57 -> 0

Sheet RETRIBUCION NEGATIVA
B1: PROMOAMBIENTAL
C2: Total | D2: Componente TDF | E2: Componente TTL | F2: Componente TVIAT | G2: Aprovechamiento | H2: CCSA Prest.Aprov. | I2: Especiales | J2: Componente TCS | K2: Componente TLU | L2: Componente TBL | M2: Componente TRT | N2: CCSA Prest. No Aprov. | O2: Deb/Cred
B3: Vlr Intereses | C3: 0 | D3: 0 | E3: 0 | F3: 0 | G3: 0 | H3: 0 | I3: 0 | J3: 0 | K3: 0 | L3: 0 | M3: 0 | N3: 0 | O3: 0
B4: Vlr Servicio | C4: 0 | D4: 0 | E4: 0 | F4: 0 | G4: 0 | H4: 0 | I4: 0 | J4: 0 | K4: 0 | L4: 0 | M4: 0 | N4: 0 | O4: 0
A5: Componente | B5: Total | C5: 0 | D5: 0 | E5: 0 | F5: 0 | G5: 0 | H5: 0 | I5: 0 | J5: 0 | K5: 0 | L5: 0 | M5: 0 | N5: 0 | O5: 0
B6: Subsidio(-)/Contribucion(+) | C6: 0 | D6: 0 | E6: 0 | F6: 0 | G6: 0 | H6: 0 | I6: 0 | J6: 0 | K6: 0 | L6: 0 | M6: 0 | N6: 0 | O6: 0
A7: Subs/Cont | B7: Total | C7: 0 | D7: 0 | E7: 0 | F7: 0 | G7: 0 | H7: 0 | I7: 0 | J7: 0 | K7: 0 | L7: 0 | M7: 0 | N7: 0 | O7: 0
A8: Total | C8: 0 | D8: 0 | E8: 0 | F8: 0 | G8: 0 | H8: 0 | I8: 0 | J8: 0 | K8: 0 | L8: 0 | M8: 0 | N8: 0 | O8: 0
B10: Total | C10: =C8-I8 -> 0 | D10: =D5 -> 0 | E10: =E5 -> 0 | F10: =F5 -> 0 | G10: =G5 -> 0 | H10: =H5 -> 0 | I10: =I5 -> 0 | J10: =J5 -> 0 | K10: =K5 -> 0 | ... O10: =O5 -> 0
B11: Subsidio(-)/Contribucion(+) | C11: =C7 -> 0
B14: LIME
C15: Total | D15: Componente TDF | E15: Componente TTL | F15: Componente TVIAT | G15: Aprovechamiento | H15: CCSA Prest.Aprov. | I15: Especiales | J15: Componente TCS | K15: Componente TLU | L15: Componente TBL | M15: Componente TRT | N15: CCSA Prest. No Aprov. | O15: Deb/Cred
B16: Vlr Intereses | C16: 0 | D16: 0 | E16: 0 | F16: 0 | G16: 0 | H16: 0 | I16: 0 | J16: 0 | K16: 0 | L16: 0 | M16: 0 | N16: 0 | O16: 0
B17: Vlr Servicio | C17: 0 | D17: 0 | E17: 0 | F17: 0 | G17: 0 | H17: 0 | I17: 0 | J17: 0 | K17: 0 | L17: 0 | M17: 0 | N17: 0 | O17: 0
A18: Componente | B18: Total | C18: 0 | D18: 0 | E18: 0 | F18: 0 | G18: 0 | H18: 0 | I18: 0 | J18: 0 | K18: 0 | L18: 0 | M18: 0 | N18: 0 | O18: 0
B19: Subsidio(-)/Contribucion(+) | C19: 0 | D19: 0 | E19: 0 | F19: 0 | G19: 0 | H19: 0 | I19: 0 | J19: 0 | K19: 0 | L19: 0 | M19: 0 | N19: 0 | O19: 0
A20: Subs/Cont | B20: Total | C20: 0 | D20: 0 | E20: 0 | F20: 0 | G20: 0 | H20: 0 | I20: 0 | J20: 0 | K20: 0 | L20: 0 | M20: 0 | N20: 0 | O20: 0
A21: Total | C21: 0 | D21: 0 | E21: 0 | F21: 0 | G21: 0 | H21: 0 | I21: 0 | J21: 0 | K21: 0 | L21: 0 | M21: 0 | N21: 0 | O21: 0
B23: Total | C23: =C21-I21 -> 0 | D23: =D18 -> 0 | E23: =E18 -> 0 | F23: =F18 -> 0 | G23: =G18 -> 0 | H23: =H18 -> 0 | I23: =I18 -> 0 | J23: =J18 -> 0 | K23: =K18 -> 0 | ... O23: =O18 -> 0
B24: Subsidio(-)/Contribucion(+) | C24: =C20 -> 0
B27: CIUDAD LIMPIA
C28: Total | D28: Componente TDF | E28: Componente TTL | F28: Componente TVIAT | G28: Aprovechamiento | H28: CCSA Prest.Aprov. | I28: Especiales | J28: Componente TCS | K28: Componente TLU | L28: Componente TBL | M28: Componente TRT | N28: CCSA Prest. No Aprov. | O28: Deb/Cred
B29: Vlr Intereses | C29: 0 | D29: 0 | E29: 0 | F29: 0 | G29: 0 | H29: 0 | I29: 0 | J29: 0 | K29: 0 | L29: 0 | M29: 0 | N29: 0 | O29: 0
B30: Vlr Servicio | C30: 0 | D30: 0 | E30: 0 | F30: 0 | G30: 0 | H30: 0 | I30: 0 | J30: 0 | K30: 0 | L30: 0 | M30: 0 | N30: 0 | O30: 0
A31: Componente | B31: Total | C31: 0 | D31: 0 | E31: 0 | F31: 0 | G31: 0 | H31: 0 | I31: 0 | J31: 0 | K31: 0 | L31: 0 | M31: 0 | N31: 0 | O31: 0
B32: Subsidio(-)/Contribucion(+) | C32: 0 | D32: 0 | E32: 0 | F32: 0 | G32: 0 | H32: 0 | I32: 0 | J32: 0 | K32: 0 | L32: 0 | M32: 0 | N32: 0 | O32: 0
A33: Subs/Cont | B33: Total | C33: 0 | D33: 0 | E33: 0 | F33: 0 | G33: 0 | H33: 0 | I33: 0 | J33: 0 | K33: 0 | L33: 0 | M33: 0 | N33: 0 | O33: 0
A34: Total | C34: 0 | D34: 0 | E34: 0 | F34: 0 | G34: 0 | H34: 0 | I34: 0 | J34: 0 | K34: 0 | L34: 0 | M34: 0 | N34: 0 | O34: 0
B36: Total | C36: =C34-I34 -> 0 | D36: =D31 -> 0 | E36: =E31 -> 0 | F36: =F31 -> 0 | G36: =G31 -> 0 | H36: =H31 -> 0 | I36: =I31 -> 0 | J36: =J31 -> 0 | K36: =K31 -> 0 | ... O36: =O31 -> 0
B37: Subsidio(-)/Contribucion(+) | C37: =C33 -> 0
B40: BOGOTA LIMPIA
C41: Total | D41: Componente TDF | E41: Componente TTL | F41: Componente TVIAT | G41: Aprovechamiento | H41: CCSA Prest.Aprov. | I41: Especiales | J41: Componente TCS | K41: Componente TLU | L41: Componente TBL | M41: Componente TRT | N41: CCSA Prest. No Aprov. | O41: Deb/Cred
B42: Vlr Intereses | C42: 0 | D42: 0 | E42: 0 | F42: 0 | G42: 0 | H42: 0 | I42: 0 | J42: 0 | K42: 0 | L42: 0 | M42: 0 | N42: 0 | O42: 0
B43: Vlr Servicio | C43: 0 | D43: 0 | E43: 0 | F43: 0 | G43: 0 | H43: 0 | I43: 0 | J43: 0 | K43: 0 | L43: 0 | M43: 0 | N43: 0 | O43: 0
A44: Componente | B44: Total | C44: 0 | D44: 0 | E44: 0 | F44: 0 | G44: 0 | H44: 0 | I44: 0 | J44: 0 | K44: 0 | L44: 0 | M44: 0 | N44: 0 | O44: 0
B45: Subsidio(-)/Contribucion(+) | C45: 0 | D45: 0 | E45: 0 | F45: 0 | G45: 0 | H45: 0 | I45: 0 | J45: 0 | K45: 0 | L45: 0 | M45: 0 | N45: 0 | O45: 0
A46: Subs/Cont | B46: Total | C46: 0 | D46: 0 | E46: 0 | F46: 0 | G46: 0 | H46: 0 | I46: 0 | J46: 0 | K46: 0 | L46: 0 | M46: 0 | N46: 0 | O46: 0
A47: Total | C47: 0 | D47: 0 | E47: 0 | F47: 0 | G47: 0 | H47: 0 | I47: 0 | J47: 0 | K47: 0 | L47: 0 | M47: 0 | N47: 0 | O47: 0
B49: Total | C49: =C47-I47 -> 0 | D49: =D44 -> 0 | E49: =E44 -> 0 | F49: =F44 -> 0 | G49: =G44 -> 0 | H49: =H44 -> 0 | I49: =I44 -> 0 | J49: =J44 -> 0 | K49: =K44 -> 0 | ... O49: =O44 -> 0
B50: Subsidio(-)/Contribucion(+) | C50: =C46 -> 0
B53: AREA LIMPIA
C54: Total | D54: Componente TDF | E54: Componente TTL | F54: Componente TVIAT | G54: Aprovechamiento | H54: CCSA Prest.Aprov. | I54: Especiales | J54: Componente TCS | K54: Componente TLU | L54: Componente TBL | M54: Componente TRT | N54: CCSA Prest. No Aprov. | O54: Deb/Cred
B55: Vlr Servicio | C55: 0 | D55: 0 | E55: 0 | F55: 0 | G55: 0 | H55: 0 | I55: 0 | J55: 0 | K55: 0 | L55: 0 | M55: 0 | N55: 0 | O55: 0
A56: Componente | B56: Total | C56: 0 | D56: 0 | E56: 0 | F56: 0 | G56: 0 | H56: 0 | I56: 0 | J56: 0 | K56: 0 | L56: 0 | M56: 0 | N56: 0 | O56: 0
B57: Subsidio(-)/Contribucion(+) | C57: 0 | D57: 0 | E57: 0 | F57: 0 | G57: 0 | H57: 0 | I57: 0 | J57: 0 | K57: 0 | L57: 0 | M57: 0 | N57: 0 | O57: 0
A58: Subs/Cont | B58: Total | C58: 0 | D58: 0 | E58: 0 | F58: 0 | G58: 0 | H58: 0 | I58: 0 | J58: 0 | K58: 0 | L58: 0 | M58: 0 | N58: 0 | O58: 0
A59: Total | C59: 0 | D59: 0 | E59: 0 | F59: 0 | G59: 0 | H59: 0 | I59: 0 | J59: 0 | K59: 0 | L59: 0 | M59: 0 | N59: 0 | O59: 0
B61: Total | C61: =C59-I59 -> 0 | D61: =D56 -> 0 | E61: =E56 -> 0 | F61: =F56 -> 0 | G61: =G56 -> 0 | H61: =H56 -> 0 | I61: =I56 -> 0 | J61: =J56 -> 0 | K61: =K56 -> 0 | ... O61: =O56 -> 0
B62: Subsidio(-)/Contribucion(+) | C62: =C58 -> 0

Sheet AJUSTES - SF-T
F3: PROCERASEO S.A.S. | I3: NIT: 901 153 639 - 0 | M3: Codigo Remuneración: | N3: ='CONSOLIDADO_TOTAL RECAUDO'!N3 -> 2026072 | U3: PROCERASEO S.A.S. | W3: NIT: 901 153 639 - 0 | AA3: Codigo Remuneración: | AC3: =N3 -> 2026072
F4: 3. ESQUEMA FINANCIERO DEL SERVICIO PUBLICO DE ASEO | U4: 3. ESQUEMA FINANCIERO DEL SERVICIO PUBLICO DE ASEO
F5: Resoluciòn UAESP Número 27 de 2018 | U5: Resoluciòn UAESP Número 27 de 2018
C6: Fecha de Proceso: | D6: ='CONSOLIDADO_TOTAL RECAUDO'!D6 -> 46238 | F6: SALDOS A FAVOR POR NOTA | U6: =+F6 -> SALDOS A FAVOR POR NOTA
C7: Hora: | D7: ='CONSOLIDADO_TOTAL RECAUDO'!D7 -> 0.58333333 | F7: Fecha Desde: | H7: ='CONSOLIDADO_TOTAL RECAUDO'!G7 -> 46219 | J7: Feha Hasta: | K7: ='CONSOLIDADO_TOTAL RECAUDO'!K7 -> 46234 | U7: =F7 -> Fecha Desde: | V7: =H7 -> 46219 | X7: =J7 -> Feha Hasta: | Y7: =K7 -> 46234
B8: ASE | C8: Concesionarios | D8: Recaudo Total | E8: Recaudo por disposicion final | F8: Recaudo por tratamiento de lixiviados | G8: Recaudo por Componente VIAT ( Decreto 2412/2018) | H8: Recaudo por aprovechamiento | I8: Recaudo del componente de comercializacion para Aprovechamiento (11,4%) | J8: Balance de subsidio o contribuciones | K8: RECAUDO BASE DE REMUNERACION | L8: Costo de la Interventoría | M8: REMUNERACION FINAL | N8: Conceptos especiales | O8: REMUNERACION FINAL MAS CONCEPTOS ESPECIALES | S8: ASE | T8: Concesionarios | U8: Tarifa de Comercialización del Servicio. ( TCS) | V8: Tarifa de Limpieza Urbana del Servicio. ( TLU) | W8: Tarifa de Barrido y Limpieza del Servicio. ( TBL) | X8: Tarifa de Recolección y Transporte del Servicio. (TRT) | Y8: Recaudo del componente de comercializacion para Aprovechamiento (18,6%) | Z8: Costo de la Interventoría | AA8: Ajuste a la decena | AB8: Conceptos especiales | AC8: Diferencial Balance S / C (Fac vs Rec) | AD8: Balance S / C Con Baase en (Recaudo) | AE8: REMUNERACION FINAL MAS CONCEPTOS ESPECIALES
B9: 1 | C9: PROMOAMBIENTAL DISTRITO S.A.S. ESP. | D9: ='SALDOS POR NOTA'!C9 -> 973693.46 | E9: ='SALDOS POR NOTA'!D9 -> 65524.22 | F9: ='SALDOS POR NOTA'!E9 -> 36995.02 | G9: ='SALDOS POR NOTA'!F9 -> 19417.65 | H9: ='SALDOS POR NOTA'!G9 -> 156624.35 | I9: ='SALDOS POR NOTA'!H9 -> 5557.5 | J9: 0 | K9: =D9-E9-F9-G9-H9-I9-J9 -> 689574.72 | L9: 0 | M9: =K9-L9 -> 689574.72 | N9: ='SALDOS POR NOTA'!I9 -> 0 | O9: =M9+N9 -> 689574.72 | S9: 1 | T9: PROMOAMBIENTAL DISTRITO S.A.S. ESP. | U9: ='SALDOS POR NOTA'!J9 -> 52109.79 | V9: ='SALDOS POR NOTA'!K9 -> 47607.03 | W9: ='SALDOS POR NOTA'!L9 -> 225441.17 | X9: ='SALDOS POR NOTA'!M9 -> 178429.31 | Y9: ='SALDOS POR NOTA'!N9 -> 9067.43 | Z9: =L9*-1 -> 0 | AA9: ='SALDOS POR NOTA'!O9 -> 0 | AB9: =N9 -> 0 | AC9: =-J9+AD9 -> 176919.99 | AD9: ='SALDOS POR NOTA'!C10 -> 176919.99 | AE9: =SUM(U9:AC9) -> 689574.72 | AF9: =(AE9-O9) -> 0 | AG9: =AF9=0 -> TRUE
B10: 2 | C10: LIMPIEZA METROPOLITANA S.A. ESP. | D10: ='SALDOS POR NOTA'!C22 -> 216025.77 | E10: ='SALDOS POR NOTA'!D22 -> 31897.62 | F10: ='SALDOS POR NOTA'!E22 -> 18572.91 | G10: ='SALDOS POR NOTA'!F22 -> 8867.14 | H10: ='SALDOS POR NOTA'!G22 -> 92959.49 | I10: ='SALDOS POR NOTA'!H22 -> 3883.88 | J10: 0 | K10: =D10-E10-F10-G10-H10-I10-J10 -> 59844.73 | L10: 0 | M10: =K10-L10 -> 59844.73 | N10: ='SALDOS POR NOTA'!I22 -> 0 | O10: =M10+N10 -> 59844.73 | S10: 2 | T10: LIMPIEZA METROPOLITANA S.A. ESP. | U10: ='SALDOS POR NOTA'!J22 -> 61358.09 | V10: ='SALDOS POR NOTA'!K22 -> 33534.01 | W10: ='SALDOS POR NOTA'!L22 -> 127815.87 | X10: ='SALDOS POR NOTA'!M22 -> 64515.32 | Y10: ='SALDOS POR NOTA'!N22 -> 5139.92 | Z10: =L10*-1 -> 0 | AA10: ='SALDOS POR NOTA'!O22 -> -0.36 | AB10: =N10 -> 0 | AC10: =-J10+AD10 -> -232518.12 | AD10: ='SALDOS POR NOTA'!C23 -> -232518.12 | AE10: =SUM(U10:AC10) -> 59844.73 | AF10: =(AE10-O10) -> 7.2759576e-12 | AG10: =AF10=0 -> FALSE
B11: 3 | C11: CIUDAD LIMPIA BOGOTA S.A. ESP. | D11: ='SALDOS POR NOTA'!C34 -> 104231.83 | E11: ='SALDOS POR NOTA'!D34 -> 6620.63 | F11: ='SALDOS POR NOTA'!E34 -> 3738.02 | G11: ='SALDOS POR NOTA'!F34 -> 1961.98 | H11: ='SALDOS POR NOTA'!G34 -> 20927.5 | I11: ='SALDOS POR NOTA'!H34 -> 743.08 | J11: 0 | K11: =D11-E11-F11-G11-H11-I11-J11 -> 70240.62 | L11: 0 | M11: =K11-L11 -> 70240.62 | N11: ='SALDOS POR NOTA'!I34 -> 0 | O11: =M11+N11 -> 70240.62 | S11: 3 | T11: CIUDAD LIMPIA BOGOTA S.A. ESP. | U11: ='SALDOS POR NOTA'!J34 -> 6518.28 | V11: ='SALDOS POR NOTA'!K34 -> 6410.86 | W11: ='SALDOS POR NOTA'!L34 -> 30349.1 | X11: ='SALDOS POR NOTA'!M34 -> 15383.1 | Y11: ='SALDOS POR NOTA'!N34 -> 1212.4 | Z11: =L11*-1 -> 0 | AA11: ='SALDOS POR NOTA'!O34 -> 0 | AB11: =N11 -> 0 | AC11: =-J11+AD11 -> 10366.88 | AD11: ='SALDOS POR NOTA'!C35 -> 10366.88 | AE11: =SUM(U11:AC11) -> 70240.62 | AF11: =(AE11-O11) -> 0 | AG11: =AF11=0 -> TRUE
B12: 4 | C12: BOGOTA LIMPIA S.A.S. ESP. | D12: ='SALDOS POR NOTA'!C47 -> 35954.44 | E12: ='SALDOS POR NOTA'!D47 -> 1890.6 | F12: ='SALDOS POR NOTA'!E47 -> 1067.43 | G12: ='SALDOS POR NOTA'!F47 -> 560.27 | H12: ='SALDOS POR NOTA'!G47 -> 10800.02 | I12: ='SALDOS POR NOTA'!H47 -> 371.66 | J12: 0 | K12: =D12-E12-F12-G12-H12-I12-J12 -> 21264.46 | L12: 0 | M12: =K12-L12 -> 21264.46 | N12: ='SALDOS POR NOTA'!I47 -> 0 | O12: =M12+N12 -> 21264.46 | S12: 4 | T12: BOGOTA LIMPIA S.A.S. ESP. | U12: ='SALDOS POR NOTA'!J47 -> 3260.18 | V12: ='SALDOS POR NOTA'!K47 -> 3149.08 | W12: ='SALDOS POR NOTA'!L47 -> 15696.81 | X12: ='SALDOS POR NOTA'!M47 -> 5005.76 | Y12: ='SALDOS POR NOTA'!N47 -> 606.39 | Z12: =L12*-1 -> 0 | AA12: ='SALDOS POR NOTA'!O47 -> 0 | AB12: =N12 -> 0 | AC12: =-J12+AD12 -> -6453.76 | AD12: ='SALDOS POR NOTA'!C48 -> -6453.76 | AE12: =SUM(U12:AC12) -> 21264.46 | AF12: =(AE12-O12) -> -3.6379788e-12 | AG12: =AF12=0 -> FALSE
B13: 5 | C13: AREA LIMPIA DISTRITO CAPITAL S.A.S. ESP. | D13: ='SALDOS POR NOTA'!C60 -> 0 | E13: ='SALDOS POR NOTA'!D60 -> 0 | F13: ='SALDOS POR NOTA'!E60 -> 0 | G13: ='SALDOS POR NOTA'!F60 -> 0 | H13: ='SALDOS POR NOTA'!G60 -> 0 | I13: ='SALDOS POR NOTA'!H60 -> 0 | J13: 0 | K13: =D13-E13-F13-G13-H13-I13-J13 -> 0 | L13: 0 | M13: =K13-L13 -> 0 | N13: ='SALDOS POR NOTA'!I60 -> 0 | O13: =M13+N13 -> 0 | S13: 5 | T13: AREA LIMPIA DISTRITO CAPITAL S.A.S. ESP. | U13: ='SALDOS POR NOTA'!J60 -> 0 | V13: ='SALDOS POR NOTA'!K60 -> 0 | W13: ='SALDOS POR NOTA'!L60 -> 0 | X13: ='SALDOS POR NOTA'!M60 -> 0 | Y13: ='SALDOS POR NOTA'!N60 -> 0 | Z13: =L13*-1 -> 0 | AA13: ='SALDOS POR NOTA'!O60 -> 0 | AB13: =N13 -> 0 | AC13: =-J13+AD13 -> 0 | AD13: ='SALDOS POR NOTA'!C61 -> 0 | AE13: =SUM(U13:AC13) -> 0 | AF13: =(AE13-O13) -> 0 | AG13: =AF13=0 -> TRUE
C14: TOTAL | D14: =SUM(D9:D13) -> 1329905.5 | E14: =SUM(E9:E13) -> 105933.07 | F14: =SUM(F9:F13) -> 60373.38 | G14: =SUM(G9:G13) -> 30807.04 | H14: =SUM(H9:H13) -> 281311.36 | I14: =SUM(I9:I13) -> 10556.12 | J14: =SUM(J9:J13) -> 0 | K14: =SUM(K9:K13) -> 840924.53 | ... O14: =SUM(O9:O13) -> 840924.53 | T14: TOTAL | U14: =SUM(U9:U13) -> 123246.34 | V14: =SUM(V9:V13) -> 90700.98 | W14: =SUM(W9:W13) -> 399302.95 | X14: =SUM(X9:X13) -> 263333.49 | Y14: =SUM(Y9:Y13) -> 16026.14 | Z14: =SUM(Z9:Z13) -> 0 | AA14: =SUM(AA9:AA13) -> -0.36 | AB14: =SUM(AB9:AB13) -> 0 | ... AF14: =SUM(AF9:AF13) -> 3.6379788e-12 | AG14: =AF14=0 -> FALSE
Y16: =SUM(U14:Y14) -> 892609.9
F18: Firma autorizada
F22: PROCERASEO S.A.S. | I22: NIT: 901 153 639 - 0 | M22: Codigo Remuneración: | N22: =N3 -> 2026072 | U22: PROCERASEO S.A.S. | W22: NIT: 901 153 639 - 0 | AA22: Codigo Remuneración: | AC22: =N22 -> 2026072
F23: 3. ESQUEMA FINANCIERO DEL SERVICIO PUBLICO DE ASEO | U23: 3. ESQUEMA FINANCIERO DEL SERVICIO PUBLICO DE ASEO
F24: Resoluciòn UAESP Número 27 de 2018 | U24: Resoluciòn UAESP Número 27 de 2018
C25: Fecha de Proceso: | D25: =D6 -> 46238 | F25: RETRIBUCION NEGATIVA | U25: =+F25 -> RETRIBUCION NEGATIVA
C26: Hora: | D26: =D7 -> 0.58333333 | F26: Fecha Desde: | H26: =H7 -> 46219 | J26: Feha Hasta: | K26: =K7 -> 46234 | U26: =F26 -> Fecha Desde: | V26: =H26 -> 46219 | X26: =J26 -> Feha Hasta: | Y26: =K26 -> 46234
B27: ASE | C27: Concesionarios | D27: Recaudo Total | E27: Recaudo por disposicion final | F27: Recaudo por tratamiento de lixiviados | G27: Recaudo por Componente VIAT ( Decreto 2412/2018) | H27: Recaudo por aprovechamiento | I27: Recaudo del componente de comercializacion para Aprovechamiento (11,4%) | J27: Balance de subsidio o contribuciones | K27: RECAUDO BASE DE REMUNERACION | L27: Costo de la Interventoría | M27: REMUNERACION FINAL | N27: Conceptos especiales | O27: REMUNERACION FINAL MAS CONCEPTOS ESPECIALES | S27: ASE | T27: Concesionarios | U27: Tarifa de Comercialización del Servicio. ( TCS) | V27: Tarifa de Limpieza Urbana del Servicio. ( TLU) | W27: Tarifa de Barrido y Limpieza del Servicio. ( TBL) | X27: Tarifa de Recolección y Transporte del Servicio. (TRT) | Y27: Recaudo del componente de comercializacion para Aprovechamiento (18,6%) | Z27: Costo de la Interventoría | AA27: Ajuste a la decena | AB27: Conceptos especiales | AC27: Diferencial Balance S / C (Fac vs Rec) | AD27: Balance S / C Con Baase en (Recaudo) | AE27: REMUNERACION FINAL MAS CONCEPTOS ESPECIALES
B28: 1 | C28: PROMOAMBIENTAL DISTRITO S.A.S. ESP. | D28: ='RETRIBUCION NEGATIVA'!C10 -> 0 | E28: ='RETRIBUCION NEGATIVA'!D10 -> 0 | F28: ='RETRIBUCION NEGATIVA'!E10 -> 0 | G28: ='RETRIBUCION NEGATIVA'!F10 -> 0 | H28: ='RETRIBUCION NEGATIVA'!G10 -> 0 | I28: ='RETRIBUCION NEGATIVA'!H10 -> 0 | J28: 0 | K28: =D28-E28-F28-H28-I28-J28-G28 -> 0 | L28: 0 | M28: =K28-L28 -> 0 | N28: ='RETRIBUCION NEGATIVA'!I10 -> 0 | O28: =M28+N28 -> 0 | S28: 1 | T28: PROMOAMBIENTAL DISTRITO S.A.S. ESP. | U28: ='RETRIBUCION NEGATIVA'!J10 -> 0 | V28: ='RETRIBUCION NEGATIVA'!K10 -> 0 | W28: ='RETRIBUCION NEGATIVA'!L10 -> 0 | X28: ='RETRIBUCION NEGATIVA'!M10 -> 0 | Y28: ='RETRIBUCION NEGATIVA'!N10 -> 0 | Z28: =L28*-1 -> 0 | AA28: ='RETRIBUCION NEGATIVA'!O10 -> 0 | AB28: =N28 -> 0 | AC28: =-J28+AD28 -> 0 | AD28: ='RETRIBUCION NEGATIVA'!C11 -> 0 | AE28: =SUM(U28:AC28) -> 0 | AF28: =(AE28-O28) -> 0 | AG28: =AF28=0 -> TRUE
B29: 2 | C29: LIMPIEZA METROPOLITANA S.A. ESP. | D29: ='RETRIBUCION NEGATIVA'!C23 -> 0 | E29: ='RETRIBUCION NEGATIVA'!D23 -> 0 | F29: ='RETRIBUCION NEGATIVA'!E23 -> 0 | G29: ='RETRIBUCION NEGATIVA'!F23 -> 0 | H29: ='RETRIBUCION NEGATIVA'!G23 -> 0 | I29: ='RETRIBUCION NEGATIVA'!H23 -> 0 | J29: 0 | K29: =D29-E29-F29-H29-I29-J29-G29 -> 0 | L29: 0 | M29: =K29-L29 -> 0 | N29: ='RETRIBUCION NEGATIVA'!I23 -> 0 | O29: =M29+N29 -> 0 | S29: 2 | T29: LIMPIEZA METROPOLITANA S.A. ESP. | U29: ='RETRIBUCION NEGATIVA'!J23 -> 0 | V29: ='RETRIBUCION NEGATIVA'!K23 -> 0 | W29: ='RETRIBUCION NEGATIVA'!L23 -> 0 | X29: ='RETRIBUCION NEGATIVA'!M23 -> 0 | Y29: ='RETRIBUCION NEGATIVA'!N23 -> 0 | Z29: =L29*-1 -> 0 | AA29: ='RETRIBUCION NEGATIVA'!O23 -> 0 | AB29: =N29 -> 0 | AC29: =-J29+AD29 -> 0 | AD29: ='RETRIBUCION NEGATIVA'!C24 -> 0 | AE29: =SUM(U29:AC29) -> 0 | AF29: =(AE29-O29) -> 0 | AG29: =AF29=0 -> TRUE
B30: 3 | C30: CIUDAD LIMPIA BOGOTA S.A. ESP. | D30: ='RETRIBUCION NEGATIVA'!C36 -> 0 | E30: ='RETRIBUCION NEGATIVA'!D36 -> 0 | F30: ='RETRIBUCION NEGATIVA'!E36 -> 0 | G30: ='RETRIBUCION NEGATIVA'!F36 -> 0 | H30: ='RETRIBUCION NEGATIVA'!G36 -> 0 | I30: ='RETRIBUCION NEGATIVA'!H36 -> 0 | J30: 0 | K30: =D30-E30-F30-H30-I30-J30-G30 -> 0 | L30: 0 | M30: =K30-L30 -> 0 | N30: ='RETRIBUCION NEGATIVA'!I36 -> 0 | O30: =M30+N30 -> 0 | S30: 3 | T30: CIUDAD LIMPIA BOGOTA S.A. ESP. | U30: ='RETRIBUCION NEGATIVA'!J36 -> 0 | V30: ='RETRIBUCION NEGATIVA'!K36 -> 0 | W30: ='RETRIBUCION NEGATIVA'!L36 -> 0 | X30: ='RETRIBUCION NEGATIVA'!M36 -> 0 | Y30: ='RETRIBUCION NEGATIVA'!N36 -> 0 | Z30: =L30*-1 -> 0 | AA30: ='RETRIBUCION NEGATIVA'!O36 -> 0 | AB30: =N30 -> 0 | AC30: =-J30+AD30 -> 0 | AD30: ='RETRIBUCION NEGATIVA'!C37 -> 0 | AE30: =SUM(U30:AC30) -> 0 | AF30: =(AE30-O30) -> 0 | AG30: =AF30=0 -> TRUE
B31: 4 | C31: BOGOTA LIMPIA S.A.S. ESP. | D31: ='RETRIBUCION NEGATIVA'!C49 -> 0 | E31: ='RETRIBUCION NEGATIVA'!D49 -> 0 | F31: ='RETRIBUCION NEGATIVA'!E49 -> 0 | G31: ='RETRIBUCION NEGATIVA'!F49 -> 0 | H31: ='RETRIBUCION NEGATIVA'!G49 -> 0 | I31: ='RETRIBUCION NEGATIVA'!H49 -> 0 | J31: 0 | K31: =D31-E31-F31-H31-I31-J31-G31 -> 0 | L31: 0 | M31: =K31-L31 -> 0 | N31: ='RETRIBUCION NEGATIVA'!I49 -> 0 | O31: =M31+N31 -> 0 | S31: 4 | T31: BOGOTA LIMPIA S.A.S. ESP. | U31: ='RETRIBUCION NEGATIVA'!J49 -> 0 | V31: ='RETRIBUCION NEGATIVA'!K49 -> 0 | W31: ='RETRIBUCION NEGATIVA'!L49 -> 0 | X31: ='RETRIBUCION NEGATIVA'!M49 -> 0 | Y31: ='RETRIBUCION NEGATIVA'!N49 -> 0 | Z31: =L31*-1 -> 0 | AA31: ='RETRIBUCION NEGATIVA'!O49 -> 0 | AB31: =N31 -> 0 | AC31: =-J31+AD31 -> 0 | AD31: ='RETRIBUCION NEGATIVA'!C50 -> 0 | AE31: =SUM(U31:AC31) -> 0 | AF31: =(AE31-O31) -> 0 | AG31: =AF31=0 -> TRUE
B32: 5 | C32: AREA LIMPIA DISTRITO CAPITAL S.A.S. ESP. | D32: ='RETRIBUCION NEGATIVA'!C61 -> 0 | E32: ='RETRIBUCION NEGATIVA'!D61 -> 0 | F32: ='RETRIBUCION NEGATIVA'!E61 -> 0 | G32: ='RETRIBUCION NEGATIVA'!F61 -> 0 | H32: ='RETRIBUCION NEGATIVA'!G61 -> 0 | I32: ='RETRIBUCION NEGATIVA'!H61 -> 0 | J32: 0 | K32: =D32-E32-F32-H32-I32-J32-G32 -> 0 | L32: 0 | M32: =K32-L32 -> 0 | N32: ='RETRIBUCION NEGATIVA'!I61 -> 0 | O32: =M32+N32 -> 0 | S32: 5 | T32: AREA LIMPIA DISTRITO CAPITAL S.A.S. ESP. | U32: ='RETRIBUCION NEGATIVA'!J61 -> 0 | V32: ='RETRIBUCION NEGATIVA'!K61 -> 0 | W32: ='RETRIBUCION NEGATIVA'!L61 -> 0 | X32: ='RETRIBUCION NEGATIVA'!M61 -> 0 | Y32: ='RETRIBUCION NEGATIVA'!N61 -> 0 | Z32: =L32*-1 -> 0 | AA32: ='RETRIBUCION NEGATIVA'!O61 -> 0 | AB32: =N32 -> 0 | AC32: =-J32+AD32 -> 0 | AD32: ='RETRIBUCION NEGATIVA'!C62 -> 0 | AE32: =SUM(U32:AC32) -> 0 | AF32: =(AE32-O32) -> 0 | AG32: =AF32=0 -> TRUE
C33: TOTAL | D33: =SUM(D28:D32) -> 0 | E33: =SUM(E28:E32) -> 0 | F33: =SUM(F28:F32) -> 0 | G33: =SUM(G28:G32) -> 0 | H33: =SUM(H28:H32) -> 0 | I33: =SUM(I28:I32) -> 0 | J33: =SUM(J28:J32) -> 0 | K33: =SUM(K28:K32) -> 0 | ... O33: =SUM(O28:O32) -> 0 | T33: TOTAL | U33: =SUM(U28:U32) -> 0 | V33: =SUM(V28:V32) -> 0 | W33: =SUM(W28:W32) -> 0 | X33: =SUM(X28:X32) -> 0 | Y33: =SUM(Y28:Y32) -> 0 | Z33: =SUM(Z28:Z32) -> 0 | AA33: =SUM(AA28:AA32) -> 0 | AB33: =SUM(AB28:AB32) -> 0 | ... AF33: =SUM(AF28:AF32) -> 0 | AG33: =AF33=0 -> TRUE
J35: VALIDADOR DE POSTIVIOS EN REMUNERACION NEGATIVA | M35: =IF(MAX(D28:O32,U28:AE32)>0.9,"ERROR",TRUE) -> TRUE | Y35: =SUM(U33:Y33) -> 0
F37: Firma autorizada
F41: PROCERASEO S.A.S. | I41: NIT: 901 153 639 - 0 | M41: Codigo Remuneración: | N41: =N3 -> 2026072 | U41: PROCERASEO S.A.S. | W41: NIT: 901 153 639 - 0 | AA41: Codigo Remuneración: | AC41: =N41 -> 2026072
F42: 3. ESQUEMA FINANCIERO DEL SERVICIO PUBLICO DE ASEO | U42: 3. ESQUEMA FINANCIERO DEL SERVICIO PUBLICO DE ASEO
F43: Resoluciòn UAESP Número 27 de 2018 | U43: Resoluciòn UAESP Número 27 de 2018
C44: Fecha de Proceso: | D44: =D6 -> 46238 | F44: CONSOLIDADO SALDOS A FAVOR | U44: =+F44 -> CONSOLIDADO SALDOS A FAVOR
C45: Hora: | D45: =D7 -> 0.58333333 | F45: Fecha Desde: | H45: =H7 -> 46219 | J45: Feha Hasta: | K45: =K7 -> 46234 | U45: =F45 -> Fecha Desde: | V45: =H45 -> 46219 | X45: =J45 -> Feha Hasta: | Y45: =K45 -> 46234
B46: ASE | C46: Concesionarios | D46: Recaudo Total | E46: Recaudo por disposicion final | F46: Recaudo por tratamiento de lixiviados | G46: Recaudo por Componente VIAT ( Decreto 2412/2018) | H46: Recaudo por aprovechamiento | I46: Recaudo del componente de comercializacion para Aprovechamiento (11,4%) | J46: Balance de subsidio o contribuciones | K46: RECAUDO BASE DE REMUNERACION | L46: Costo de la Interventoría | M46: REMUNERACION FINAL | N46: Conceptos especiales | O46: REMUNERACION FINAL MAS CONCEPTOS ESPECIALES | S46: ASE | T46: Concesionarios | U46: Tarifa de Comercialización del Servicio. ( TCS) | V46: Tarifa de Limpieza Urbana del Servicio. ( TLU) | W46: Tarifa de Barrido y Limpieza del Servicio. ( TBL) | X46: Tarifa de Recolección y Transporte del Servicio. (TRT) | Y46: Recaudo del componente de comercializacion para Aprovechamiento (18,6%) | Z46: Costo de la Interventoría | AA46: Ajuste a la decena | AB46: Conceptos especiales | AC46: Diferencial Balance S / C (Fac vs Rec) | AD46: Balance S / C Con Baase en (Recaudo) | AE46: REMUNERACION FINAL MAS CONCEPTOS ESPECIALES
B47: 1 | C47: PROMOAMBIENTAL DISTRITO S.A.S. ESP. | D47: =D9+D28 -> 973693.46 | E47: =E9+E28 -> 65524.22 | F47: =F9+F28 -> 36995.02 | G47: =G9+G28 -> 19417.65 | H47: =H9+H28 -> 156624.35 | I47: =I9+I28 -> 5557.5 | J47: =J9+J28 -> 0 | K47: =D47-E47-F47-G47-H47-I47-J47 -> 689574.72 | L47: 0 | M47: =K47-L47 -> 689574.72 | N47: =N9+N28 -> 0 | O47: =M47+N47 -> 689574.72 | S47: 1 | T47: PROMOAMBIENTAL DISTRITO S.A.S. ESP. | U47: =U9+U28 -> 52109.79 | V47: =V9+V28 -> 47607.03 | W47: =W9+W28 -> 225441.17 | X47: =X9+X28 -> 178429.31 | Y47: =Y9+Y28 -> 9067.43 | Z47: =-L47 -> 0 | AA47: =AA9+AA28 -> 0 | AB47: =AB9+AB28 -> 0 | AC47: =AC9+AC28 -> 176919.99 | AD47: =AD9+AD28 -> 176919.99 | AE47: =SUM(U47:AC47) -> 689574.72 | AF47: =(AE47-O47) -> 0 | AG47: =AF47=0 -> TRUE
B48: 2 | C48: LIMPIEZA METROPOLITANA S.A. ESP. | D48: =D10+D29 -> 216025.77 | E48: =E10+E29 -> 31897.62 | F48: =F10+F29 -> 18572.91 | G48: =G10+G29 -> 8867.14 | H48: =H10+H29 -> 92959.49 | I48: =I10+I29 -> 3883.88 | J48: =J10+J29 -> 0 | K48: =D48-E48-F48-G48-H48-I48-J48 -> 59844.73 | L48: 0 | M48: =K48-L48 -> 59844.73 | N48: =N10+N29 -> 0 | O48: =M48+N48 -> 59844.73 | S48: 2 | T48: LIMPIEZA METROPOLITANA S.A. ESP. | U48: =U10+U29 -> 61358.09 | V48: =V10+V29 -> 33534.01 | W48: =W10+W29 -> 127815.87 | X48: =X10+X29 -> 64515.32 | Y48: =Y10+Y29 -> 5139.92 | Z48: =-L48 -> 0 | AA48: =AA10+AA29 -> -0.36 | AB48: =AB10+AB29 -> 0 | AC48: =AC10+AC29 -> -232518.12 | AD48: =AD10+AD29 -> -232518.12 | AE48: =SUM(U48:AC48) -> 59844.73 | AF48: =(AE48-O48) -> 7.2759576e-12 | AG48: =AF48=0 -> FALSE
B49: 3 | C49: CIUDAD LIMPIA BOGOTA S.A. ESP. | D49: =D11+D30 -> 104231.83 | E49: =E11+E30 -> 6620.63 | F49: =F11+F30 -> 3738.02 | G49: =G11+G30 -> 1961.98 | H49: =H11+H30 -> 20927.5 | I49: =I11+I30 -> 743.08 | J49: =J11+J30 -> 0 | K49: =D49-E49-F49-G49-H49-I49-J49 -> 70240.62 | L49: 0 | M49: =K49-L49 -> 70240.62 | N49: =N11+N30 -> 0 | O49: =M49+N49 -> 70240.62 | S49: 3 | T49: CIUDAD LIMPIA BOGOTA S.A. ESP. | U49: =U11+U30 -> 6518.28 | V49: =V11+V30 -> 6410.86 | W49: =W11+W30 -> 30349.1 | X49: =X11+X30 -> 15383.1 | Y49: =Y11+Y30 -> 1212.4 | Z49: =-L49 -> 0 | AA49: =AA11+AA30 -> 0 | AB49: =AB11+AB30 -> 0 | AC49: =AC11+AC30 -> 10366.88 | AD49: =AD11+AD30 -> 10366.88 | AE49: =SUM(U49:AC49) -> 70240.62 | AF49: =(AE49-O49) -> 0 | AG49: =AF49=0 -> TRUE
B50: 4 | C50: BOGOTA LIMPIA S.A.S. ESP. | D50: =D12+D31 -> 35954.44 | E50: =E12+E31 -> 1890.6 | F50: =F12+F31 -> 1067.43 | G50: =G12+G31 -> 560.27 | H50: =H12+H31 -> 10800.02 | I50: =I12+I31 -> 371.66 | J50: =J12+J31 -> 0 | K50: =D50-E50-F50-G50-H50-I50-J50 -> 21264.46 | L50: 0 | M50: =K50-L50 -> 21264.46 | N50: =N12+N31 -> 0 | O50: =M50+N50 -> 21264.46 | S50: 4 | T50: BOGOTA LIMPIA S.A.S. ESP. | U50: =U12+U31 -> 3260.18 | V50: =V12+V31 -> 3149.08 | W50: =W12+W31 -> 15696.81 | X50: =X12+X31 -> 5005.76 | Y50: =Y12+Y31 -> 606.39 | Z50: =-L50 -> 0 | AA50: =AA12+AA31 -> 0 | AB50: =AB12+AB31 -> 0 | AC50: =AC12+AC31 -> -6453.76 | AD50: =AD12+AD31 -> -6453.76 | AE50: =SUM(U50:AC50) -> 21264.46 | AF50: =(AE50-O50) -> -3.6379788e-12 | AG50: =AF50=0 -> FALSE
B51: 5 | C51: AREA LIMPIA DISTRITO CAPITAL S.A.S. ESP. | D51: =D13+D32 -> 0 | E51: =E13+E32 -> 0 | F51: =F13+F32 -> 0 | G51: =G13+G32 -> 0 | H51: =H13+H32 -> 0 | I51: =I13+I32 -> 0 | J51: =J13+J32 -> 0 | K51: =D51-E51-F51-G51-H51-I51-J51 -> 0 | L51: 0 | M51: =K51-L51 -> 0 | N51: =N13+N32 -> 0 | O51: =M51+N51 -> 0 | S51: 5 | T51: AREA LIMPIA DISTRITO CAPITAL S.A.S. ESP. | U51: =U13+U32 -> 0 | V51: =V13+V32 -> 0 | W51: =W13+W32 -> 0 | X51: =X13+X32 -> 0 | Y51: =Y13+Y32 -> 0 | Z51: =-L51 -> 0 | AA51: =AA13+AA32 -> 0 | AB51: =AB13+AB32 -> 0 | AC51: =AC13+AC32 -> 0 | AD51: =AD13+AD32 -> 0 | AE51: =SUM(U51:AC51) -> 0 | AF51: =(AE51-O51) -> 0 | AG51: =AF51=0 -> TRUE
C52: TOTAL | D52: =SUM(D47:D51) -> 1329905.5 | E52: =SUM(E47:E51) -> 105933.07 | F52: =SUM(F47:F51) -> 60373.38 | G52: =SUM(G47:G51) -> 30807.04 | H52: =SUM(H47:H51) -> 281311.36 | I52: =SUM(I47:I51) -> 10556.12 | J52: =SUM(J47:J51) -> 0 | K52: =SUM(K47:K51) -> 840924.53 | ... O52: =SUM(O47:O51) -> 840924.53 | T52: TOTAL | U52: =SUM(U47:U51) -> 123246.34 | V52: =SUM(V47:V51) -> 90700.98 | W52: =SUM(W47:W51) -> 399302.95 | X52: =SUM(X47:X51) -> 263333.49 | Y52: =SUM(Y47:Y51) -> 16026.14 | Z52: =SUM(Z47:Z51) -> 0 | AA52: =SUM(AA47:AA51) -> -0.36 | AB52: =SUM(AB47:AB51) -> 0 | ... AF52: =SUM(AF47:AF51) -> 3.6379788e-12 | AG52: =AF52=0 -> FALSE
Y54: =SUM(U52:Y52) -> 892609.9
F56: Firma autorizada

Sheet INTERVENTORIA
F2: 2026 01 2 | G2: 2026 02 1 | H2: 2026 02 2 | I2: 2026 03 1 | J2: 2026 03 2 | K2: 2026 04 1 | L2: 2026 04 2 | M2: 2026 05 1 | N2: 2026 05 2 | O2: 2026 06 1 | P2: 2026 06 2 | Q2: 2026 07 1
B3: VALOR MES | C3: ASE | D3: Concesionarios | E3: % | F3: MITAD 1 // ENERO -26 | G3: MITAD 2 // ENERO -26 | H3: MITAD 1 // FEBRERO -26 | I3: MITAD 2 // FEBRERO -26 | J3: MITAD 1 // MARZO -26 | K3: MITAD 2 // MARZO -26 | L3: MITAD 1 // ABRIL -26 | M3: MITAD 2 // ABRIL -26 | N3: MITAD 1 // MAYO -26 | O3: MITAD 2 // MAYO -26 | P3: MITAD 1 // JUNIO -26 | Q3: MITAD 2 // JUNIO -26
B4: 378371975 | C4: 1 | D4: PROMOAMBIENTAL DISTRITO S.A.S. ESP. | E4: 0.22 | F4: 189185988 | G4: 189185987 | H4: 189185988 | I4: 189185987 | J4: 189185988 | K4: 189185987 | L4: 189185988 | M4: 189185987 | N4: 189185988 | O4: 189185987 | P4: 189185988 | Q4: 189185987
B5: 533160511 | C5: 2 | D5: LIMPIEZA METROPOLITANA S.A. ESP. | E5: 0.31 | F5: 266580256 | G5: 266580255 | H5: 266580256 | I5: 266580255 | J5: 266580256 | K5: 266580255 | L5: 266580256 | M5: 266580255 | N5: 266580256 | O5: 266580255 | P5: 266580256 | Q5: 266580255
B6: 309577071 | C6: 3 | D6: CIUDAD LIMPIA BOGOTA S.A. ESP. | E6: 0.18 | F6: 154788536 | G6: 154788535 | H6: 154788536 | I6: 154788535 | J6: 154788536 | K6: 154788535 | L6: 154788536 | M6: 154788535 | N6: 154788536 | O6: 154788535 | P6: 154788536 | Q6: 154788535
B7: 240782166 | C7: 4 | D7: BOGOTA LIMPIA S.A.S. ESP. | E7: 0.14 | F7: 120391083 | G7: 120391083 | H7: 120391083 | I7: 120391083 | J7: 120391083 | K7: 120391083 | L7: 120391083 | M7: 120391083 | N7: 120391083 | O7: 120391083 | P7: 120391083 | Q7: 120391083
B8: 257980891 | C8: 5 | D8: AREA LIMPIA DISTRITO CAPITAL S.A.S. ESP. | E8: 0.15 | F8: 128990446 | G8: 128990445 | H8: 128990446 | I8: 128990445 | J8: 128990446 | K8: 128990445 | L8: 128990446 | M8: 128990445 | N8: 128990446 | O8: 128990445 | P8: 128990446 | Q8: 128990445
B9: 1719872614 | D9: TOTAL | E9: 1 | F9: 859936309 | G9: 859936305 | H9: 859936309 | I9: 859936305 | J9: 859936309 | K9: 859936305 | L9: 859936309 | M9: 859936305 | N9: 859936309 | O9: 859936305 | P9: 859936309 | Q9: 859936305
F10: =SUM(F9:G9) -> 1719872614 | H10: =SUM(H9:I9) -> 1719872614 | J10: =SUM(J9:K9) -> 1719872614 | L10: =SUM(L9:M9) -> 1719872614 | N10: =SUM(N9:O9) -> 1719872614 | P10: =SUM(P9:Q9) -> 1719872614
F13: 2026 07 2 | G13: 2026 08 1 | H13: 2026 08 2 | I13: 2026 09 1 | J13: 2026 09 2 | K13: 2026 10 1 | L13: 2026 10 2 | M13: 2026 11 1 | N13: 2026 11 2 | O13: 2026 12 1 | P13: 2026 12 2 | Q13: 2027 01 1
C14: ASE | D14: Concesionarios | E14: % | F14: MITAD 1 // JULIO -26 | G14: MITAD 2 // JULIO -26 | H14: MITAD 1 // AGOSTO -26 | I14: MITAD 2 // AGOSTO -26 | J14: MITAD 1 // SEPTIEMBRE -26 | K14: MITAD 2 // SEPTIEMBRE -26 | L14: MITAD 1 // OCTUBRE -26 | M14: MITAD 2 // OCTUBRE -26 | N14: MITAD 1 // NOVIEMBRE -26 | O14: MITAD 2 // NOVIEMBRE -26 | P14: MITAD 1 // DICIEMBRE -26 | Q14: MITAD 2 // DICIEMBRE -26
C15: 1 | D15: PROMOAMBIENTAL DISTRITO S.A.S. ESP. | E15: 0.22 | F15: 189185988 | G15: 189185987 | H15: 189185988 | I15: 189185987 | J15: 189185988 | K15: 189185987 | L15: 189185988 | M15: 189185987 | N15: 189185988 | O15: 189185987 | P15: 189185988 | Q15: 189185987
C16: 2 | D16: LIMPIEZA METROPOLITANA S.A. ESP. | E16: 0.31 | F16: 266580256 | G16: 266580255 | H16: 266580256 | I16: 266580255 | J16: 266580256 | K16: 266580255 | L16: 266580256 | M16: 266580255 | N16: 266580256 | O16: 266580255 | P16: 266580256 | Q16: 266580255
C17: 3 | D17: CIUDAD LIMPIA BOGOTA S.A. ESP. | E17: 0.18 | F17: 154788536 | G17: 154788535 | H17: 154788536 | I17: 154788535 | J17: 154788536 | K17: 154788535 | L17: 154788536 | M17: 154788535 | N17: 154788536 | O17: 154788535 | P17: 154788536 | Q17: 154788535
C18: 4 | D18: BOGOTA LIMPIA S.A.S. ESP. | E18: 0.14 | F18: 120391083 | G18: 120391083 | H18: 120391083 | I18: 120391083 | J18: 120391083 | K18: 120391083 | L18: 120391083 | M18: 120391083 | N18: 120391083 | O18: 120391083 | P18: 120391083 | Q18: 120391083
C19: 5 | D19: AREA LIMPIA DISTRITO CAPITAL S.A.S. ESP. | E19: 0.15 | F19: 128990446 | G19: 128990445 | H19: 128990446 | I19: 128990445 | J19: 128990446 | K19: 128990445 | L19: 128990446 | M19: 128990445 | N19: 128990446 | O19: 128990445 | P19: 128990446 | Q19: 128990445
D20: TOTAL | E20: 1 | F20: 859936309 | G20: 859936305 | H20: 859936309 | I20: 859936305 | J20: 859936309 | K20: 859936305 | L20: 859936309 | M20: 859936305 | N20: 859936309 | O20: 859936305 | P20: 859936309 | Q20: 859936305
F21: =SUM(F20:G20) -> 1719872614 | G21: 1191383498 | H21: =SUM(H20:I20) -> 1719872614 | I21: 1191383498 | J21: =SUM(J20:K20) -> 1719872614 | K21: 1191383498 | L21: =SUM(L20:M20) -> 1719872614 | M21: 1191383498 | N21: =SUM(N20:O20) -> 1719872614 | O21: 1191383498 | P21: =SUM(P20:Q20) -> 1719872614 | Q21: 1191383498
K25: VALOR OFICIAL MES | L25: ASE | M25: Segunda quincena | N25: Primera quincena | R25: VALIDACION
K26: 378371975 | L26: 1 | M26: 189185988 | N26: 189185987 | O26: =M26=R26 -> TRUE | Q26: ='CONSOLIDADO_TOTAL RECAUDO'!L104 -> 189185988 | R26: =F15 -> 189185988 | S26: =Q26=R26 -> TRUE
K27: 533160511 | L27: 2 | M27: 266580256 | N27: 266580255 | O27: =M27=R27 -> TRUE | Q27: ='CONSOLIDADO_TOTAL RECAUDO'!L105 -> 266580256 | R27: =F16 -> 266580256 | S27: =Q27=R27 -> TRUE
K28: 309577071 | L28: 3 | M28: 154788536 | N28: 154788535 | O28: =M28=R28 -> TRUE | Q28: ='CONSOLIDADO_TOTAL RECAUDO'!L106 -> 154788536 | R28: =F17 -> 154788536 | S28: =Q28=R28 -> TRUE
K29: 240782166 | L29: 4 | M29: 120391083 | N29: 120391083 | O29: =M29=R29 -> TRUE | Q29: ='CONSOLIDADO_TOTAL RECAUDO'!L107 -> 120391083 | R29: =F18 -> 120391083 | S29: =Q29=R29 -> TRUE
K30: 257980891 | L30: 5 | M30: 128990446 | N30: 128990445 | O30: =M30=R30 -> TRUE | Q30: ='CONSOLIDADO_TOTAL RECAUDO'!L108 -> 128990446 | R30: =F19 -> 128990446 | S30: =Q30=R30 -> TRUE
K31: =SUM(K26:K30) -> 1719872614 | M31: =SUM(M26:M30) -> 859936309 | N31: =SUM(N26:N30) -> 859936305 | O31: =M31=R31 -> TRUE | Q31: ='CONSOLIDADO_TOTAL RECAUDO'!L109 -> 859936309 | R31: =F20 -> 859936309 | S31: =Q31=R31 -> TRUE
K32: =SUM(M31:N31) -> 1719872614

Sheet Informe AFaseo Recaudo 202607-2
D5: PROCERASEO S.A.S. | I5: NIT: 901 153 639 - 0 | P5: PROCERASEO S.A.S. | T5: NIT: 901 153 639 - 0
D6: INFORME Afaseo // RECAUDO | P6: INFORME AFaseo
D7: BENEFICIO TRANSITORIO ALIVIO SOBRE EL VALOR DE LA FACTURA | P7: BENEFICIO TRANSITORIO ALIVIO SOBRE EL VALOR DE LA FACTURA
D8: Según Resoluciòn UAESP Número 273 de 2.020 | P8: Según Resoluciòn UAESP Número 273 de 2.020
E10: Fecha Desde: | F10: ='CONSOLIDADO_TOTAL RECAUDO'!G102 -> 46219 | H10: Feha Hasta: | I10: ='CONSOLIDADO_TOTAL RECAUDO'!K102 -> 46234
B11: ASE | C11: Concesionarios | D11: Valor Afaseo | E11: Afaseo por disposicion final | F11: Afaseo por tratamiento de lixiviados | G11: Afaseo por Componente VIAT ( Decreto 2412/2018) | H11: Afaseo por aprovechamiento | I11: Afaseo del componente de comercializacion para Aprovechamiento (11,4%) | J11: Afaseo RBL | N11: ASE | O11: Concesionarios | P11: Tarifa de Comercialización del Servicio. ( TCS) | Q11: Tarifa de Limpieza Urbana del Servicio. ( TLU) | R11: Tarifa de Barrido y Limpieza del Servicio. ( TBL) | S11: Tarifa de Recolección y Transporte del Servicio. (TRT) | T11: Componente de comercialización para Aprovechamiento (18,6%) | U11: Afaseo RBL
B12: 1 | C12: PROMOAMBIENTAL DISTRITO S.A.S. ESP. | D12: ='Reporte Componentes R1'!F80*$D$24 -> 11217.37 | E12: ='Reporte Componentes R1'!G80*$D$24 -> 766.38 | F12: ='Reporte Componentes R1'!H80*$D$24 -> 325.59 | G12: ='Reporte Componentes R1'!I80*$D$24 -> 142.17 | H12: ='Reporte Componentes R1'!J80*$D$24 -> 1970.37 | I12: ='Reporte Componentes R1'!K80*$D$24 -> 127.32 | J12: =D12-E12-F12-G12-H12-I12 -> 7885.54 | N12: 1 | O12: PROMOAMBIENTAL DISTRITO S.A.S. ESP. | P12: ='Reporte Componentes R1'!M80*$P$24 -> 1116.82 | Q12: ='Reporte Componentes R1'!N80*$P$24 -> 934.67 | R12: ='Reporte Componentes R1'!O80*$P$24 -> 3730.88 | S12: ='Reporte Componentes R1'!P80*$P$24 -> 1895.43 | T12: ='Reporte Componentes R1'!Q80*$P$24 -> 207.74 | U12: =SUM(P12:T12) -> 7885.54 | V12: =J12-U12 -> 0 | W12: =V12=0 -> TRUE
B13: 2 | C13: LIMPIEZA METROPOLITANA S.A. ESP. | D13: ='Reporte Componentes R1'!F224*$D$24 -> 405906.75 | E13: ='Reporte Componentes R1'!G224*$D$24 -> 36253.24 | F13: ='Reporte Componentes R1'!H224*$D$24 -> 15401.35 | G13: ='Reporte Componentes R1'!I224*$D$24 -> 6725.8 | H13: ='Reporte Componentes R1'!J224*$D$24 -> 80022.36 | I13: ='Reporte Componentes R1'!K224*$D$24 -> 3364.46 | J13: =D13-E13-F13-G13-H13-I13 -> 264139.54 | N13: 2 | O13: LIMPIEZA METROPOLITANA S.A. ESP. | P13: ='Reporte Componentes R1'!M224*$P$24 -> 29514 | Q13: ='Reporte Componentes R1'!N224*$P$24 -> 36987.9 | R13: ='Reporte Componentes R1'!O224*$P$24 -> 124266.63 | S13: ='Reporte Componentes R1'!P224*$P$24 -> 67881.4 | T13: ='Reporte Componentes R1'!Q224*$P$24 -> 5489.61 | U13: =SUM(P13:T13) -> 264139.54 | V13: =J13-U13 -> 0 | W13: =V13=0 -> TRUE
B14: 3 | C14: CIUDAD LIMPIA BOGOTA S.A. ESP. | D14: ='Reporte Componentes R1'!F355*$D$24 -> 16458.46 | E14: ='Reporte Componentes R1'!G355*$D$24 -> 1490.88 | F14: ='Reporte Componentes R1'!H355*$D$24 -> 633.39 | G14: ='Reporte Componentes R1'!I355*$D$24 -> 276.6 | H14: ='Reporte Componentes R1'!J355*$D$24 -> 3142.56 | I14: ='Reporte Componentes R1'!K355*$D$24 -> 129.48 | J14: =D14-E14-F14-G14-H14-I14 -> 10785.55 | N14: 3 | O14: CIUDAD LIMPIA BOGOTA S.A. ESP. | P14: ='Reporte Componentes R1'!M355*$P$24 -> 1135.68 | Q14: ='Reporte Componentes R1'!N355*$P$24 -> 1423.48 | R14: ='Reporte Componentes R1'!O355*$P$24 -> 4781.43 | S14: ='Reporte Componentes R1'!P355*$P$24 -> 3233.73 | T14: ='Reporte Componentes R1'!Q355*$P$24 -> 211.23 | U14: =SUM(P14:T14) -> 10785.55 | V14: =J14-U14 -> 0 | W14: =V14=0 -> TRUE
B15: 4 | C15: BOGOTA LIMPIA S.A.S. ESP. | D15: ='Reporte Componentes R1'!F486*$D$24 -> 439956.52 | E15: ='Reporte Componentes R1'!G486*$D$24 -> 35444.41 | F15: ='Reporte Componentes R1'!H486*$D$24 -> 15058.04 | G15: ='Reporte Componentes R1'!I486*$D$24 -> 6575.73 | H15: ='Reporte Componentes R1'!J486*$D$24 -> 81642.18 | I15: ='Reporte Componentes R1'!K486*$D$24 -> 3324.84 | J15: =D15-E15-F15-G15-H15-I15 -> 297911.32 | N15: 4 | O15: BOGOTA LIMPIA S.A.S. ESP. | P15: ='Reporte Componentes R1'!M486*$P$24 -> 29164.3 | Q15: ='Reporte Componentes R1'!N486*$P$24 -> 37085.49 | R15: ='Reporte Componentes R1'!O486*$P$24 -> 136171.69 | S15: ='Reporte Componentes R1'!P486*$P$24 -> 90064.99 | T15: ='Reporte Componentes R1'!Q486*$P$24 -> 5424.85 | U15: =SUM(P15:T15) -> 297911.32 | V15: =J15-U15 -> 0 | W15: =V15=0 -> TRUE
B16: 5 | C16: AREA LIMPIA DISTRITO CAPITAL S.A.S. ESP. | D16: ='Reporte Componentes R1'!F584*$D$24 -> 0 | E16: ='Reporte Componentes R1'!G584*$D$24 -> 0 | F16: ='Reporte Componentes R1'!H584*$D$24 -> 0 | G16: ='Reporte Componentes R1'!I584*$D$24 -> 0 | H16: ='Reporte Componentes R1'!J584*$D$24 -> 0 | I16: ='Reporte Componentes R1'!K584*$D$24 -> 0 | J16: =D16-E16-F16-G16-H16-I16 -> 0 | N16: 5 | O16: AREA LIMPIA DISTRITO CAPITAL S.A.S. ESP. | P16: ='Reporte Componentes R1'!M584*$P$24 -> 0 | Q16: ='Reporte Componentes R1'!N584*$P$24 -> 0 | R16: ='Reporte Componentes R1'!O584*$P$24 -> 0 | S16: ='Reporte Componentes R1'!P584*$P$24 -> 0 | T16: ='Reporte Componentes R1'!Q584*$P$24 -> 0 | U16: =SUM(P16:T16) -> 0 | V16: =J16-U16 -> 0 | W16: =V16=0 -> TRUE
C17: TOTAL | D17: =SUM(D12:D16) -> 873539.1 | E17: =SUM(E12:E16) -> 73954.91 | F17: =SUM(F12:F16) -> 31418.37 | G17: =SUM(G12:G16) -> 13720.3 | H17: =SUM(H12:H16) -> 166777.47 | I17: =SUM(I12:I16) -> 6946.1 | J17: =SUM(J12:J16) -> 580721.95 | O17: TOTAL | P17: =SUM(P12:P16) -> 60930.8 | Q17: =SUM(Q12:Q16) -> 76431.54 | R17: =SUM(R12:R16) -> 268950.63 | S17: =SUM(S12:S16) -> 163075.55 | T17: =SUM(T12:T16) -> 11333.43 | U17: =SUM(U12:U16) -> 580721.95 | V17: =SUM(V12:V16) -> 0 | W17: =V17=0 -> TRUE
T19: =SUM(P17:T17) -> 580721.95
J20: =+IF(MAX(J12:J17)>500000,"VALIDAR",TRUE) -> VALIDAR
F21: Firma autorizada
D24: -1 | P24: -1

Sheet CONSOLIDADO_TOTAL RECAUDO
F3: PROCERASEO S.A.S. | I3: NIT: 901 153 639 - 0 | M3: Codigo Remuneración: | N3: 2026072 | U3: PROCERASEO S.A.S. | W3: NIT: 901 153 639 - 0 | AA3: Codigo Remuneración: | AD3: =N3 -> 2026072
F4: 3. ESQUEMA FINANCIERO DEL SERVICIO PUBLICO DE ASEO | U4: 3. ESQUEMA FINANCIERO DEL SERVICIO PUBLICO DE ASEO
F5: Resoluciòn UAESP Número 27 de 2018 | U5: Resoluciòn UAESP Número 27 de 2018
C6: Fecha de Proceso: | D6: 46238 | F6: R1 - RECAUDO OPORTUNO | U6: R1 - RECAUDO OPORTUNO
C7: Hora: | D7: 0.58333333 | F7: Fecha Desde: | G7: 46219 | J7: Feha Hasta: | K7: 46234 | U7: =F7 -> Fecha Desde: | V7: =G7 -> 46219 | X7: =J7 -> Feha Hasta: | Y7: =K7 -> 46234
B8: ASE | C8: Concesionarios | D8: Recaudo Total | E8: Recaudo por disposicion final | F8: Recaudo por tratamiento de lixiviados | G8: Recaudo por Componente VIAT ( Decreto 2412/2018) | H8: Recaudo por aprovechamiento | I8: Recaudo del componente de comercializacion para Aprovechamiento (11,4%) | J8: Balance de subsidio o contribuciones | K8: RECAUDO BASE DE REMUNERACION | L8: Costo de la Interventoría | M8: REMUNERACION FINAL | N8: Conceptos especiales | O8: REMUNERACION FINAL MAS CONCEPTOS ESPECIALES | S8: ASE | T8: Concesionarios | U8: Tarifa de Comercialización del Servicio. ( TCS) | V8: Tarifa de Limpieza Urbana del Servicio. ( TLU) | W8: Tarifa de Barrido y Limpieza del Servicio. ( TBL) | X8: Tarifa de Recolección y Transporte del Servicio. (TRT) | Y8: Recaudo del componente de comercializacion para Aprovechamiento (18,6%) | Z8: Costo de la Interventoría | AA8: Ajuste a la decena | AB8: Conceptos especiales | AC8: Otros | AD8: Diferencial Balance S / C (Fac vs Rec) | AE8: Balance S / C Con Base en (Recaudo) | AF8: REMUNERACION FINAL MAS CONCEPTOS ESPECIALES
B9: 1 | C9: PROMOAMBIENTAL DISTRITO S.A.S. ESP. | D9: ='Reporte Componentes R1'!F50 -> 1.7339794e+10 | E9: ='Reporte Componentes R1'!G50 -> 8.9822314e+08 | F9: ='Reporte Componentes R1'!H50 -> 5.0656079e+08 | G9: ='Reporte Componentes R1'!I50 -> 2.6613439e+08 | H9: ='Reporte Componentes R1'!J50 -> 3.794558e+09 | I9: ='Reporte Componentes R1'!K50 -> 1.335427e+08 | J9: ='BCE SC POR FACT.'!F3 -> -3.5894547e+09 | K9: =D9-E9-F9-G9-H9-I9-J9 -> 1.5330229e+10 | L9: =INTERVENTORIA!F15 -> 189185988 | M9: =K9-L9 -> 1.5141043e+10 | N9: ='Reporte Componentes R1'!L50 -> 25277316 | O9: =M9+N9 -> 1.516632e+10 | S9: 1 | T9: PROMOAMBIENTAL DISTRITO S.A.S. ESP. | U9: ='Reporte Componentes R1'!M50 -> 1.1749285e+09 | V9: ='Reporte Componentes R1'!N50 -> 1.1308881e+09 | W9: ='Reporte Componentes R1'!O50 -> 5.3521755e+09 | X9: ='Reporte Componentes R1'!P50 -> 2.4357496e+09 | Y9: ='Reporte Componentes R1'!Q50 -> 2.1790458e+08 | Z9: =L9*-1 -> -189185988 | AA9: ='Reporte Componentes R1'!R50+'Reporte Componentes R1'!U50+'Reporte Componentes R1'!V50 -> -17545.2 | AB9: =N9 -> 25277316 | AC9: ='Reporte Componentes R1'!T50+'Reporte Componentes R1'!W50+'Reporte Componentes R1'!X50+'Reporte Componentes R1'!Y50+'Reporte Componentes R1'!Z50+'Reporte Componentes R1'!S50 -> -1592.61 | AD9: =-J9+AE9 -> 5.018602e+09 | AE9: ='Reporte Componentes R1'!F51 -> 1.4291473e+09 | AF9: =SUM(U9:AD9) -> 1.516632e+10 | AG9: =(AF9-O9) -> -1.9073486e-06 | AH9: =INT(AG9)=0 -> FALSE
B10: 2 | C10: LIMPIEZA METROPOLITANA S.A. ESP. | D10: ='Reporte Componentes R1'!F194 -> 2.0352269e+10 | E10: ='Reporte Componentes R1'!G194 -> 1.5751276e+09 | F10: ='Reporte Componentes R1'!H194 -> 8.8334416e+08 | G10: ='Reporte Componentes R1'!I194 -> 4.6365748e+08 | H10: ='Reporte Componentes R1'!J194 -> 5.7709398e+09 | I10: ='Reporte Componentes R1'!K194 -> 2.210878e+08 | J10: ='BCE SC POR FACT.'!F4 -> -3.2411937e+09 | K10: =D10-E10-F10-G10-H10-I10-J10 -> 1.4679305e+10 | L10: =INTERVENTORIA!F16 -> 266580256 | M10: =K10-L10 -> 1.4412725e+10 | N10: ='Reporte Componentes R1'!L194 -> 53454221 | O10: =M10+N10 -> 1.4466179e+10 | S10: 2 | T10: LIMPIEZA METROPOLITANA S.A. ESP. | U10: ='Reporte Componentes R1'!M194 -> 1.9376362e+09 | V10: ='Reporte Componentes R1'!N194 -> 1.932409e+09 | W10: ='Reporte Componentes R1'!O194 -> 9.1061021e+09 | X10: ='Reporte Componentes R1'!P194 -> 3.1061417e+09 | Y10: ='Reporte Componentes R1'!Q194 -> 3.6126402e+08 | Z10: =L10*-1 -> -266580256 | AA10: ='Reporte Componentes R1'!R194+'Reporte Componentes R1'!U194+'Reporte Componentes R1'!V194 -> 86691.03 | AB10: =N10 -> 53454221 | AC10: ='Reporte Componentes R1'!T194+'Reporte Componentes R1'!W194+'Reporte Componentes R1'!X194+'Reporte Componentes R1'!Y194+'Reporte Componentes R1'!Z194+'Reporte Componentes R1'!S194 -> -123.21 | AD10: =-J10+AE10 -> -1.7643341e+09 | AE10: ='Reporte Componentes R1'!F195 -> -5.0055278e+09 | AF10: =SUM(U10:AD10) -> 1.4466179e+10 | AG10: =(AF10-O10) -> 5.7220459e-06 | AH10: =INT(AG10)=0 -> TRUE
B11: 3 | C11: CIUDAD LIMPIA BOGOTA S.A. ESP. | D11: ='Reporte Componentes R1'!F325 -> 1.5226209e+10 | E11: ='Reporte Componentes R1'!G325 -> 1.1543525e+09 | F11: ='Reporte Componentes R1'!H325 -> 6.5077046e+08 | G11: ='Reporte Componentes R1'!I325 -> 3.4205619e+08 | H11: ='Reporte Componentes R1'!J325 -> 3.4214088e+09 | I11: ='Reporte Componentes R1'!K325 -> 1.2577956e+08 | J11: ='BCE SC POR FACT.'!F5 -> -8.5324456e+08 | K11: =D11-E11-F11-G11-H11-I11-J11 -> 1.0385086e+10 | L11: =INTERVENTORIA!F17 -> 154788536 | M11: =K11-L11 -> 1.0230298e+10 | N11: ='Reporte Componentes R1'!L325 -> 14319221 | O11: =M11+N11 -> 1.0244617e+10 | S11: 3 | T11: CIUDAD LIMPIA BOGOTA S.A. ESP. | U11: ='Reporte Componentes R1'!M325 -> 1.1030915e+09 | V11: ='Reporte Componentes R1'!N325 -> 1.086972e+09 | W11: ='Reporte Componentes R1'!O325 -> 5.1439124e+09 | X11: ='Reporte Componentes R1'!P325 -> 2.6844228e+09 | Y11: ='Reporte Componentes R1'!Q325 -> 2.0532074e+08 | Z11: =L11*-1 -> -154788536 | AA11: ='Reporte Componentes R1'!R325+'Reporte Componentes R1'!U325+'Reporte Componentes R1'!V325 -> 246494.88 | AB11: =N11 -> 14319221 | AC11: ='Reporte Componentes R1'!T325+'Reporte Componentes R1'!W325+'Reporte Componentes R1'!X325+'Reporte Componentes R1'!Y325+'Reporte Componentes R1'!Z325+'Reporte Componentes R1'!S325 -> -11886.32 | AD11: =-J11+AE11 -> 1.6113214e+08 | AE11: ='Reporte Componentes R1'!F326 -> -6.9211242e+08 | AF11: =SUM(U11:AD11) -> 1.0244617e+10 | AG11: =(AF11-O11) -> -1.9073486e-06 | AH11: =INT(AG11)=0 -> FALSE
B12: 4 | C12: BOGOTA LIMPIA S.A.S. ESP. | D12: ='Reporte Componentes R1'!F456 -> 7.0474925e+09 | E12: ='Reporte Componentes R1'!G456 -> 4.6047444e+08 | F12: ='Reporte Componentes R1'!H456 -> 2.5701337e+08 | G12: ='Reporte Componentes R1'!I456 -> 1.3430593e+08 | H12: ='Reporte Componentes R1'!J456 -> 1.5789239e+09 | I12: ='Reporte Componentes R1'!K456 -> 61673075 | J12: ='BCE SC POR FACT.'!F6 -> -6.9988271e+08 | K12: =D12-E12-F12-G12-H12-I12-J12 -> 5.2549845e+09 | L12: =INTERVENTORIA!F18 -> 120391083 | M12: =K12-L12 -> 5.1345934e+09 | N12: ='Reporte Componentes R1'!L456 -> 34128345 | O12: =M12+N12 -> 5.1687217e+09 | S12: 4 | T12: BOGOTA LIMPIA S.A.S. ESP. | U12: ='Reporte Componentes R1'!M456 -> 5.4155502e+08 | V12: ='Reporte Componentes R1'!N456 -> 5.4004565e+08 | W12: ='Reporte Componentes R1'!O456 -> 2.7618559e+09 | X12: ='Reporte Componentes R1'!P456 -> 1.2186725e+09 | Y12: ='Reporte Componentes R1'!Q456 -> 1.0084121e+08 | Z12: =L12*-1 -> -120391083 | AA12: ='Reporte Componentes R1'!R456+'Reporte Componentes R1'!U456+'Reporte Componentes R1'!V456 -> -16277.43 | AB12: =N12 -> 34128345 | AC12: ='Reporte Componentes R1'!T456+'Reporte Componentes R1'!W456+'Reporte Componentes R1'!X456+'Reporte Componentes R1'!Y456+'Reporte Componentes R1'!Z456+'Reporte Componentes R1'!S456 -> -440.07 | AD12: =-J12+AE12 -> 92030892 | AE12: ='Reporte Componentes R1'!F457 -> -6.0785182e+08 | AF12: =SUM(U12:AD12) -> 5.1687217e+09 | AG12: =(AF12-O12) -> 1.9073486e-06 | AH12: =INT(AG12)=0 -> TRUE
B13: 5 | C13: AREA LIMPIA DISTRITO CAPITAL S.A.S. ESP. | D13: ='Reporte Componentes R1'!F554 -> 1.2033012e+10 | E13: ='Reporte Componentes R1'!G554 -> 7.2881764e+08 | F13: ='Reporte Componentes R1'!H554 -> 4.1084319e+08 | G13: ='Reporte Componentes R1'!I554 -> 2.1546417e+08 | H13: ='Reporte Componentes R1'!J554 -> 2.7646495e+09 | I13: ='Reporte Componentes R1'!K554 -> 1.0563604e+08 | J13: ='BCE SC POR FACT.'!F7 -> -82959024 | K13: =D13-E13-F13-G13-H13-I13-J13 -> 7.8905601e+09 | L13: =INTERVENTORIA!F19 -> 128990446 | M13: =K13-L13 -> 7.7615697e+09 | N13: ='Reporte Componentes R1'!L554 -> 14901729 | O13: =M13+N13 -> 7.7764714e+09 | S13: 5 | T13: AREA LIMPIA DISTRITO CAPITAL S.A.S. ESP. | U13: ='Reporte Componentes R1'!M554 -> 9.2615879e+08 | V13: ='Reporte Componentes R1'!N554 -> 9.0889738e+08 | W13: ='Reporte Componentes R1'!O554 -> 4.6714789e+09 | X13: ='Reporte Componentes R1'!P554 -> 2.1651157e+09 | Y13: ='Reporte Componentes R1'!Q554 -> 1.7241858e+08 | Z13: =L13*-1 -> -128990446 | AA13: ='Reporte Componentes R1'!R554+'Reporte Componentes R1'!U554+'Reporte Componentes R1'!V554 -> -147734.33 | AB13: =N13 -> 14901729 | AC13: ='Reporte Componentes R1'!T554+'Reporte Componentes R1'!W554+'Reporte Componentes R1'!X554+'Reporte Componentes R1'!Y554+'Reporte Componentes R1'!Z554+'Reporte Componentes R1'!S554 -> -32.98 | AD13: =-J13+AE13 -> -9.533615e+08 | AE13: ='Reporte Componentes R1'!F555 -> -1.0363205e+09 | AF13: =SUM(U13:AD13) -> 7.7764714e+09 | AG13: =(AF13-O13) -> -9.5367432e-07 | AH13: =INT(AG13)=0 -> FALSE
C14: TOTAL | D14: =SUM(D9:D13) -> 7.1998775e+10 | E14: =SUM(E9:E13) -> 4.8169953e+09 | F14: =SUM(F9:F13) -> 2.708532e+09 | G14: =SUM(G9:G13) -> 1.4216182e+09 | H14: =SUM(H9:H13) -> 1.733048e+10 | I14: =SUM(I9:I13) -> 6.4771917e+08 | J14: =SUM(J9:J13) -> -8.4667347e+09 | K14: =SUM(K9:K13) -> 5.3540165e+10 | ... O14: =SUM(O9:O13) -> 5.282231e+10 | T14: TOTAL | U14: =SUM(U9:U13) -> 5.68337e+09 | V14: =SUM(V9:V13) -> 5.5992122e+09 | W14: =SUM(W9:W13) -> 2.7035525e+10 | X14: =SUM(X9:X13) -> 1.1610102e+10 | Y14: =SUM(Y9:Y13) -> 1.0577491e+09 | Z14: =SUM(Z9:Z13) -> -859936309 | AA14: =SUM(AA9:AA13) -> 151628.95 | AB14: =SUM(AB9:AB13) -> 1.4208083e+08 | ... AG14: =SUM(AG9:AG13) -> 2.8610229e-06 | AH14: =INT(AG14)=0 -> TRUE
Y16: =SUM(U14:Y14) -> 5.0985959e+10
F18: Firma autorizada
F22: PROCERASEO S.A.S. | I22: NIT: 901 153 639 - 0 | M22: Codigo Remuneración: | N22: =N3 -> 2026072 | U22: PROCERASEO S.A.S. | W22: NIT: 901 153 639 - 0 | AA22: Codigo Remuneración: | AD22: =N22 -> 2026072
F23: 3. ESQUEMA FINANCIERO DEL SERVICIO PUBLICO DE ASEO | U23: 3. ESQUEMA FINANCIERO DEL SERVICIO PUBLICO DE ASEO
F24: Resoluciòn UAESP Número 27 de 2018 | U24: Resoluciòn UAESP Número 27 de 2018
C25: Fecha de Proceso: | D25: =D6 -> 46238 | F25: R2 - ANTICIPOS A USUARIOS | U25: R2 - ANTICIPOS A USUARIOS
C26: Hora: | D26: =D7 -> 0.58333333 | F26: Fecha Desde: | G26: =G7 -> 46219 | J26: Feha Hasta: | K26: =K7 -> 46234 | U26: =F26 -> Fecha Desde: | V26: =G26 -> 46219 | X26: =J26 -> Feha Hasta: | Y26: =K26 -> 46234
B27: ASE | C27: Concesionarios | D27: Recaudo Total | E27: Recaudo por disposicion final | F27: Recaudo por tratamiento de lixiviados | G27: Recaudo por Componente VIAT ( Decreto 2412/2018) | H27: Recaudo por aprovechamiento | I27: Recaudo del componente de comercializacion para Aprovechamiento (11,4%) | J27: Balance de subsidio o contribuciones | K27: RECAUDO BASE DE REMUNERACION | L27: Costo de la Interventoría | M27: REMUNERACION FINAL | N27: Conceptos especiales | O27: REMUNERACION FINAL MAS CONCEPTOS ESPECIALES | S27: ASE | T27: Concesionarios | U27: Tarifa de Comercialización del Servicio. ( TCS) | V27: Tarifa de Limpieza Urbana del Servicio. ( TLU) | W27: Tarifa de Barrido y Limpieza del Servicio. ( TBL) | X27: Tarifa de Recolección y Transporte del Servicio. (TRT) | Y27: Recaudo del componente de comercializacion para Aprovechamiento (18,6%) | Z27: Costo de la Interventoría | AA27: Ajuste a la decena | AB27: Conceptos especiales | AC27: Otros | AD27: Diferencial Balance S / C (Fac vs Rec) | AE27: Balance S / C Con Base en (Recaudo) | AF27: REMUNERACION FINAL MAS CONCEPTOS ESPECIALES
B28: 1 | C28: PROMOAMBIENTAL DISTRITO S.A.S. ESP. | D28: ='Rem. Anticipos R2'!E43 -> 1.2594855e+08 | E28: ='Rem. Anticipos R2'!F43 -> 9640402.9 | F28: ='Rem. Anticipos R2'!G43 -> 5490662.7 | G28: ='Rem. Anticipos R2'!H43 -> 2785450 | H28: ='Rem. Anticipos R2'!I43 -> 24544068 | I28: ='Rem. Anticipos R2'!J43 -> 964886.66 | J28: 0 | K28: =D28-E28-F28-G28-H28-I28-J28 -> 82523083 | L28: 0 | M28: =K28-L28 -> 82523083 | N28: ='Rem. Anticipos R2'!K43 -> 0 | O28: =M28+N28 -> 82523083 | S28: 1 | T28: PROMOAMBIENTAL DISTRITO S.A.S. ESP. | U28: ='Rem. Anticipos R2'!L43 -> 8824083.3 | V28: ='Rem. Anticipos R2'!M43 -> 8523193.1 | W28: ='Rem. Anticipos R2'!N43 -> 37613665 | X28: ='Rem. Anticipos R2'!O43 -> 27011615 | Y28: ='Rem. Anticipos R2'!P43 -> 1394039.6 | Z28: =L28*-1 -> 0 | AA28: ='Rem. Anticipos R2'!Q43 -> -73.75 | AB28: =N28 -> 0 | AC28: ='Rem. Anticipos R2'!R43 -> 0 | AD28: =-J28+AE28 -> -843439.3 | AE28: ='Rem. Anticipos R2'!E44 -> -843439.3 | AF28: =SUM(U28:AD28) -> 82523083 | AG28: =(AF28-O28) -> 0 | AH28: =INT(AG28)=0 -> TRUE
B29: 2 | C29: LIMPIEZA METROPOLITANA S.A. ESP. | D29: ='Rem. Anticipos R2'!E139 -> 1.7853909e+08 | E29: ='Rem. Anticipos R2'!F139 -> 17193125 | F29: ='Rem. Anticipos R2'!G139 -> 9759590.5 | G29: ='Rem. Anticipos R2'!H139 -> 4674886.5 | H29: ='Rem. Anticipos R2'!I139 -> 47216081 | I29: ='Rem. Anticipos R2'!J139 -> 1451359.2 | J29: 0 | K29: =D29-E29-F29-G29-H29-I29-J29 -> 98244049 | L29: 0 | M29: =K29-L29 -> 98244049 | N29: ='Rem. Anticipos R2'!K139 -> 0 | O29: =M29+N29 -> 98244049 | S29: 2 | T29: LIMPIEZA METROPOLITANA S.A. ESP. | U29: ='Rem. Anticipos R2'!L139 -> 13193070 | V29: ='Rem. Anticipos R2'!M139 -> 14193304 | W29: ='Rem. Anticipos R2'!N139 -> 54326292 | X29: ='Rem. Anticipos R2'!O139 -> 52723995 | Y29: ='Rem. Anticipos R2'!P139 -> 1920514 | Z29: =L29*-1 -> 0 | AA29: ='Rem. Anticipos R2'!Q139 -> 181.61 | AB29: =N29 -> 0 | AC29: ='Rem. Anticipos R2'!R139 -> 0 | AD29: =-J29+AE29 -> -38113307 | AE29: ='Rem. Anticipos R2'!E140 -> -38113307 | AF29: =SUM(U29:AD29) -> 98244049 | AG29: =(AF29-O29) -> 1.4901161e-08 | AH29: =INT(AG29)=0 -> TRUE
B30: 3 | C30: CIUDAD LIMPIA BOGOTA S.A. ESP. | D30: ='Rem. Anticipos R2'!E256 -> 26586328 | E30: ='Rem. Anticipos R2'!F256 -> 2669416 | F30: ='Rem. Anticipos R2'!G256 -> 1115118.9 | G30: ='Rem. Anticipos R2'!H256 -> 766590.87 | H30: ='Rem. Anticipos R2'!I256 -> 3649866.3 | I30: ='Rem. Anticipos R2'!J256 -> 117977.5 | J30: 0 | K30: =D30-E30-F30-G30-H30-I30-J30 -> 18267359 | L30: 0 | M30: =K30-L30 -> 18267359 | N30: ='Rem. Anticipos R2'!K256 -> 22742.37 | O30: =M30+N30 -> 18290101 | S30: 3 | T30: CIUDAD LIMPIA BOGOTA S.A. ESP. | U30: ='Rem. Anticipos R2'!L256 -> 1069586.7 | V30: ='Rem. Anticipos R2'!M256 -> 1249645.9 | W30: ='Rem. Anticipos R2'!N256 -> 6297254.5 | X30: ='Rem. Anticipos R2'!O256 -> 6569127.8 | Y30: ='Rem. Anticipos R2'!P256 -> 179885.12 | Z30: =L30*-1 -> 0 | AA30: ='Rem. Anticipos R2'!Q256 -> 46.22 | AB30: =N30 -> 22742.37 | AC30: ='Rem. Anticipos R2'!R256 -> 0 | AD30: =-J30+AE30 -> 2901812.5 | AE30: ='Rem. Anticipos R2'!E257 -> 2901812.5 | AF30: =SUM(U30:AD30) -> 18290101 | AG30: =(AF30-O30) -> 0 | AH30: =INT(AG30)=0 -> TRUE
B31: 4 | C31: BOGOTA LIMPIA S.A.S. ESP. | D31: ='Rem. Anticipos R2'!E358 -> 1.6146195e+08 | E31: ='Rem. Anticipos R2'!F358 -> 16099105 | F31: ='Rem. Anticipos R2'!G358 -> 9061043.2 | G31: ='Rem. Anticipos R2'!H358 -> 2852946.1 | H31: ='Rem. Anticipos R2'!I358 -> 32340246 | I31: ='Rem. Anticipos R2'!J358 -> 1124253 | J31: 0 | K31: =D31-E31-F31-G31-H31-I31-J31 -> 99984356 | L31: 0 | M31: =K31-L31 -> 99984356 | N31: ='Rem. Anticipos R2'!K358 -> 0 | O31: =M31+N31 -> 99984356 | S31: 4 | T31: BOGOTA LIMPIA S.A.S. ESP. | U31: ='Rem. Anticipos R2'!L358 -> 9787993.9 | V31: ='Rem. Anticipos R2'!M358 -> 10109598 | W31: ='Rem. Anticipos R2'!N358 -> 46326513 | X31: ='Rem. Anticipos R2'!O358 -> 43710042 | Y31: ='Rem. Anticipos R2'!P358 -> 1759287.8 | Z31: =L31*-1 -> 0 | AA31: ='Rem. Anticipos R2'!Q358 -> 4.56 | AB31: =N31 -> 0 | AC31: ='Rem. Anticipos R2'!R358 -> 0 | AD31: =-J31+AE31 -> -11709083 | AE31: ='Rem. Anticipos R2'!E359 -> -11709083 | AF31: =SUM(U31:AD31) -> 99984356 | AG31: =(AF31-O31) -> -2.9802322e-08 | AH31: =INT(AG31)=0 -> FALSE
B32: 5 | C32: AREA LIMPIA DISTRITO CAPITAL S.A.S. ESP. | D32: ='Rem. Anticipos R2'!E438 -> 42983502 | E32: ='Rem. Anticipos R2'!F438 -> 3046795 | F32: ='Rem. Anticipos R2'!G438 -> 1737546.6 | G32: ='Rem. Anticipos R2'!H438 -> 808529.7 | H32: ='Rem. Anticipos R2'!I438 -> 7182406.2 | I32: ='Rem. Anticipos R2'!J438 -> 249175.55 | J32: 0 | K32: =D32-E32-F32-G32-H32-I32-J32 -> 29959049 | L32: 0 | M32: =K32-L32 -> 29959049 | N32: ='Rem. Anticipos R2'!K438 -> 990006.55 | O32: =M32+N32 -> 30949056 | S32: 5 | T32: AREA LIMPIA DISTRITO CAPITAL S.A.S. ESP. | U32: ='Rem. Anticipos R2'!L438 -> 2265402.9 | V32: ='Rem. Anticipos R2'!M438 -> 2501140.3 | W32: ='Rem. Anticipos R2'!N438 -> 10769603 | X32: ='Rem. Anticipos R2'!O438 -> 9260216.2 | Y32: ='Rem. Anticipos R2'!P438 -> 352055.57 | Z32: =L32*-1 -> 0 | AA32: ='Rem. Anticipos R2'!Q438 -> -10.37 | AB32: =N32 -> 990006.55 | AC32: ='Rem. Anticipos R2'!R438 -> 0 | AD32: =-J32+AE32 -> 4810642.2 | AE32: ='Rem. Anticipos R2'!E439 -> 4810642.2 | AF32: =SUM(U32:AD32) -> 30949056 | AG32: =(AF32-O32) -> 7.4505806e-09 | AH32: =INT(AG32)=0 -> TRUE
C33: TOTAL | D33: =SUM(D28:D32) -> 5.3551943e+08 | E33: =SUM(E28:E32) -> 48648844 | F33: =SUM(F28:F32) -> 27163962 | G33: =SUM(G28:G32) -> 11888403 | H33: =SUM(H28:H32) -> 1.1493267e+08 | I33: =SUM(I28:I32) -> 3907652 | J33: =SUM(J28:J32) -> 0 | K33: =SUM(K28:K32) -> 3.289779e+08 | ... O33: =SUM(O28:O32) -> 3.2999065e+08 | T33: TOTAL | U33: =SUM(U28:U32) -> 35140137 | V33: =SUM(V28:V32) -> 36576881 | W33: =SUM(W28:W32) -> 1.5533333e+08 | X33: =SUM(X28:X32) -> 1.39275e+08 | Y33: =SUM(Y28:Y32) -> 5605782.1 | Z33: =SUM(Z28:Z32) -> 0 | AA33: =SUM(AA28:AA32) -> 148.27 | AB33: =SUM(AB28:AB32) -> 1012748.9 | ... AG33: =SUM(AG28:AG32) -> -7.4505806e-09 | AH33: =INT(AG33)=0 -> FALSE
Y35: =SUM(U33:Y33) -> 3.7193112e+08
F37: Firma autorizada
F41: PROCERASEO S.A.S. | I41: NIT: 901 153 639 - 0 | M41: Codigo Remuneración: | N41: =N3 -> 2026072 | U41: PROCERASEO S.A.S. | W41: NIT: 901 153 639 - 0 | AA41: Codigo Remuneración: | AD41: =N41 -> 2026072
F42: 3. ESQUEMA FINANCIERO DEL SERVICIO PUBLICO DE ASEO | U42: 3. ESQUEMA FINANCIERO DEL SERVICIO PUBLICO DE ASEO
F43: Resoluciòn UAESP Número 27 de 2018 | U43: Resoluciòn UAESP Número 27 de 2018
C44: Fecha de Proceso: | D44: =D6 -> 46238 | F44: R3 - RECAUDO EXTEMPORANEO | U44: R3 - RECAUDO EXTEMPORANEO
C45: Hora: | D45: =D7 -> 0.58333333 | F45: Fecha Desde: | G45: =G7 -> 46219 | J45: Feha Hasta: | K45: =K7 -> 46234 | U45: =F45 -> Fecha Desde: | V45: =G45 -> 46219 | X45: =J45 -> Feha Hasta: | Y45: =K45 -> 46234
B46: ASE | C46: Concesionarios | D46: Recaudo Total | E46: Recaudo por disposicion final | F46: Recaudo por tratamiento de lixiviados | G46: Recaudo por Componente VIAT ( Decreto 2412/2018) | H46: Recaudo por aprovechamiento | I46: Recaudo del componente de comercializacion para Aprovechamiento (11,4%) | J46: Balance de subsidio o contribuciones | K46: RECAUDO BASE DE REMUNERACION | L46: Costo de la Interventoría | M46: REMUNERACION FINAL | N46: Conceptos especiales | O46: REMUNERACION FINAL MAS CONCEPTOS ESPECIALES | S46: ASE | T46: Concesionarios | U46: Tarifa de Comercialización del Servicio. ( TCS) | V46: Tarifa de Limpieza Urbana del Servicio. ( TLU) | W46: Tarifa de Barrido y Limpieza del Servicio. ( TBL) | X46: Tarifa de Recolección y Transporte del Servicio. (TRT) | Y46: Recaudo del componente de comercializacion para Aprovechamiento (18,6%) | Z46: Costo de la Interventoría | AA46: Ajuste a la decena | AB46: Conceptos especiales | AC46: Otros | AD46: Diferencial Balance S / C (Fac vs Rec) | AE46: Balance S / C Con Base en (Recaudo) | AF46: REMUNERACION FINAL MAS CONCEPTOS ESPECIALES
B47: 1 | C47: PROMOAMBIENTAL DISTRITO S.A.S. ESP. | D47: ='Reporte Componentes R1'!F52 -> 49580 | E47: ='Reporte Componentes R1'!G52 -> 2007.44 | F47: ='Reporte Componentes R1'!H52 -> 1133.38 | G47: ='Reporte Componentes R1'!I52 -> 594.88 | H47: ='Reporte Componentes R1'!J52 -> 0 | I47: ='Reporte Componentes R1'!K52 -> 0 | J47: 0 | K47: =D47-E47-F47-G47-H47-I47-J47 -> 45844.3 | L47: 0 | M47: =K47-L47 -> 45844.3 | N47: ='Reporte Componentes R1'!L52 -> 0 | O47: =M47+N47 -> 45844.3 | S47: 1 | T47: PROMOAMBIENTAL DISTRITO S.A.S. ESP. | U47: ='Reporte Componentes R1'!M52 -> 0 | V47: ='Reporte Componentes R1'!N52 -> 0 | W47: ='Reporte Componentes R1'!O52 -> 0 | X47: ='Reporte Componentes R1'!P52 -> 5482.6 | Y47: ='Reporte Componentes R1'!Q52 -> 0 | Z47: =-L47 -> 0 | AA47: ='Reporte Componentes R1'!R52+'Reporte Componentes R1'!V52+'Reporte Componentes R1'!U52 -> -2.61 | AB47: =N47 -> 0 | AC47: ='Reporte Componentes R1'!T52+'Reporte Componentes R1'!W52+'Reporte Componentes R1'!X52+'Reporte Componentes R1'!Y52+'Reporte Componentes R1'!Z52+'Reporte Componentes R1'!S52 -> 0 | AD47: =-J47+AE47 -> 40364.31 | AE47: ='Reporte Componentes R1'!F53 -> 40364.31 | AF47: =SUM(U47:AD47) -> 45844.3 | AG47: =(AF47-O47) -> -7.2759576e-12 | AH47: =INT(AG47)=0 -> FALSE
B48: 2 | C48: LIMPIEZA METROPOLITANA S.A. ESP. | D48: ='Reporte Componentes R1'!F196 -> 56190070 | E48: ='Reporte Componentes R1'!G196 -> 7708934.9 | F48: ='Reporte Componentes R1'!H196 -> 4358213 | G48: ='Reporte Componentes R1'!I196 -> 2310135.7 | H48: ='Reporte Componentes R1'!J196 -> 173927.38 | I48: ='Reporte Componentes R1'!K196 -> 5311.09 | J48: 0 | K48: =D48-E48-F48-G48-H48-I48-J48 -> 41633548 | L48: 0 | M48: =K48-L48 -> 41633548 | N48: ='Reporte Componentes R1'!L196 -> 0 | O48: =M48+N48 -> 41633548 | S48: 2 | T48: LIMPIEZA METROPOLITANA S.A. ESP. | U48: ='Reporte Componentes R1'!M196 -> 46588.43 | V48: ='Reporte Componentes R1'!N196 -> 53938.06 | W48: ='Reporte Componentes R1'!O196 -> 251431.52 | X48: ='Reporte Componentes R1'!P196 -> 15476286 | Y48: ='Reporte Componentes R1'!Q196 -> 8665.45 | Z48: =-L48 -> 0 | AA48: ='Reporte Componentes R1'!R196+'Reporte Componentes R1'!V196+'Reporte Componentes R1'!U196 -> -0.41 | AB48: =N48 -> 0 | AC48: ='Reporte Componentes R1'!T196+'Reporte Componentes R1'!W196+'Reporte Componentes R1'!X196+'Reporte Componentes R1'!Y196+'Reporte Componentes R1'!Z196+'Reporte Componentes R1'!S196 -> 0 | AD48: =-J48+AE48 -> 25796638 | AE48: ='Reporte Componentes R1'!F197 -> 25796638 | AF48: =SUM(U48:AD48) -> 41633548 | AG48: =(AF48-O48) -> 0 | AH48: =INT(AG48)=0 -> TRUE
B49: 3 | C49: CIUDAD LIMPIA BOGOTA S.A. ESP. | D49: ='Reporte Componentes R1'!F327 -> 1307680 | E49: ='Reporte Componentes R1'!G327 -> 147598.38 | F49: ='Reporte Componentes R1'!H327 -> 66140.96 | G49: ='Reporte Componentes R1'!I327 -> 37291.57 | H49: ='Reporte Componentes R1'!J327 -> 33572.08 | I49: ='Reporte Componentes R1'!K327 -> 682.45 | J49: 0 | K49: =D49-E49-F49-G49-H49-I49-J49 -> 1022394.6 | L49: 0 | M49: =K49-L49 -> 1022394.6 | N49: ='Reporte Componentes R1'!L327 -> 0 | O49: =M49+N49 -> 1022394.6 | S49: 3 | T49: CIUDAD LIMPIA BOGOTA S.A. ESP. | U49: ='Reporte Componentes R1'!M327 -> 5991.23 | V49: ='Reporte Componentes R1'!N327 -> 7293.25 | W49: ='Reporte Componentes R1'!O327 -> 33919.09 | X49: ='Reporte Componentes R1'!P327 -> 346942.9 | Y49: ='Reporte Componentes R1'!Q327 -> 1113.37 | Z49: =-L49 -> 0 | AA49: ='Reporte Componentes R1'!R327+'Reporte Componentes R1'!V327+'Reporte Componentes R1'!U327 -> -7.95 | AB49: =N49 -> 0 | AC49: ='Reporte Componentes R1'!T327+'Reporte Componentes R1'!W327+'Reporte Componentes R1'!X327+'Reporte Componentes R1'!Y327+'Reporte Componentes R1'!Z327+'Reporte Componentes R1'!S327 -> 0.7 | AD49: =-J49+AE49 -> 627141.97 | AE49: ='Reporte Componentes R1'!F328 -> 627141.97 | AF49: =SUM(U49:AD49) -> 1022394.6 | AG49: =(AF49-O49) -> -1.1641532e-10 | AH49: =INT(AG49)=0 -> FALSE
B50: 4 | C50: BOGOTA LIMPIA S.A.S. ESP. | D50: ='Reporte Componentes R1'!F458 -> 4343101 | E50: ='Reporte Componentes R1'!G458 -> 311438.06 | F50: ='Reporte Componentes R1'!H458 -> 174745.19 | G50: ='Reporte Componentes R1'!I458 -> 94552.57 | H50: ='Reporte Componentes R1'!J458 -> 971475.94 | I50: ='Reporte Componentes R1'!K458 -> 31532.52 | J50: 0 | K50: =D50-E50-F50-G50-H50-I50-J50 -> 2759356.7 | L50: 0 | M50: =K50-L50 -> 2759356.7 | N50: ='Reporte Componentes R1'!L458 -> 0 | O50: =M50+N50 -> 2759356.7 | S50: 4 | T50: BOGOTA LIMPIA S.A.S. ESP. | U50: ='Reporte Componentes R1'!M458 -> 280120.46 | V50: ='Reporte Componentes R1'!N458 -> 309903.63 | W50: ='Reporte Componentes R1'!O458 -> 1543098.8 | X50: ='Reporte Componentes R1'!P458 -> 830464.64 | Y50: ='Reporte Componentes R1'!Q458 -> 53321.16 | Z50: =-L50 -> 0 | AA50: ='Reporte Componentes R1'!R458+'Reporte Componentes R1'!V458+'Reporte Componentes R1'!U458 -> 10.98 | AB50: =N50 -> 0 | AC50: ='Reporte Componentes R1'!T458+'Reporte Componentes R1'!W458+'Reporte Componentes R1'!X458+'Reporte Componentes R1'!Y458+'Reporte Componentes R1'!Z458+'Reporte Componentes R1'!S458 -> -88.74 | AD50: =-J50+AE50 -> -257474.16 | AE50: ='Reporte Componentes R1'!F459 -> -257474.16 | AF50: =SUM(U50:AD50) -> 2759356.7 | AG50: =(AF50-O50) -> -4.6566129e-10 | AH50: =INT(AG50)=0 -> FALSE
B51: 5 | C51: AREA LIMPIA DISTRITO CAPITAL S.A.S. ESP. | D51: ='Reporte Componentes R1'!F556 -> 441849 | E51: ='Reporte Componentes R1'!G556 -> 26657.43 | F51: ='Reporte Componentes R1'!H556 -> 14138.02 | G51: ='Reporte Componentes R1'!I556 -> 7723.27 | H51: ='Reporte Componentes R1'!J556 -> 93911.73 | I51: ='Reporte Componentes R1'!K556 -> 2290.29 | J51: 0 | K51: =D51-E51-F51-G51-H51-I51-J51 -> 297128.26 | L51: 0 | M51: =K51-L51 -> 297128.26 | N51: ='Reporte Componentes R1'!L556 -> 0 | O51: =M51+N51 -> 297128.26 | S51: 5 | T51: AREA LIMPIA DISTRITO CAPITAL S.A.S. ESP. | U51: ='Reporte Componentes R1'!M556 -> 20089.34 | V51: ='Reporte Componentes R1'!N556 -> 28092.36 | W51: ='Reporte Componentes R1'!O556 -> 141333 | X51: ='Reporte Componentes R1'!P556 -> 79544.79 | Y51: ='Reporte Componentes R1'!Q556 -> 3736.7 | Z51: =-L51 -> 0 | AA51: ='Reporte Componentes R1'!R556+'Reporte Componentes R1'!V556+'Reporte Componentes R1'!U556 -> 2.69 | AB51: =N51 -> 0 | AC51: ='Reporte Componentes R1'!T556+'Reporte Componentes R1'!W556+'Reporte Componentes R1'!X556+'Reporte Componentes R1'!Y556+'Reporte Componentes R1'!Z556+'Reporte Componentes R1'!S556 -> 0 | AD51: =-J51+AE51 -> 24329.38 | AE51: ='Reporte Componentes R1'!F557 -> 24329.38 | AF51: =SUM(U51:AD51) -> 297128.26 | AG51: =(AF51-O51) -> 0 | AH51: =INT(AG51)=0 -> TRUE
C52: TOTAL | D52: =SUM(D47:D51) -> 62332280 | E52: =SUM(E47:E51) -> 8196636.2 | F52: =SUM(F47:F51) -> 4614370.6 | G52: =SUM(G47:G51) -> 2450298 | H52: =SUM(H47:H51) -> 1272887.1 | I52: =SUM(I47:I51) -> 39816.35 | J52: =SUM(J47:J51) -> 0 | K52: =SUM(K47:K51) -> 45758272 | ... O52: =SUM(O47:O51) -> 45758272 | T52: TOTAL | U52: =SUM(U47:U51) -> 352789.46 | V52: =SUM(V47:V51) -> 399227.3 | W52: =SUM(W47:W51) -> 1969782.4 | X52: =SUM(X47:X51) -> 16738721 | Y52: =SUM(Y47:Y51) -> 66836.68 | Z52: =SUM(Z47:Z51) -> 0 | AA52: =SUM(AA47:AA51) -> 2.7 | AB52: =SUM(AB47:AB51) -> 0 | ... AG52: =SUM(AG47:AG51) -> -5.8935257e-10 | AH52: =INT(AG52)=0 -> FALSE
Y54: =SUM(U52:Y52) -> 19527357
F56: Firma autorizada
F60: PROCERASEO S.A.S. | I60: NIT: 901 153 639 - 0 | M60: Codigo Remuneración: | N60: =N3 -> 2026072 | U60: PROCERASEO S.A.S. | W60: NIT: 901 153 639 - 0 | AA60: Codigo Remuneración: | AD60: =N60 -> 2026072
F61: 3. ESQUEMA FINANCIERO DEL SERVICIO PUBLICO DE ASEO | U61: 3. ESQUEMA FINANCIERO DEL SERVICIO PUBLICO DE ASEO
F62: Resoluciòn UAESP Número 27 de 2018 | U62: Resoluciòn UAESP Número 27 de 2018
C63: Fecha de Proceso: | D63: =D6 -> 46238 | F63: R4 - REVERSIÓN DE PAGOS | U63: R4 - REVERSIÓN DE PAGOS
C64: Hora: | D64: =D7 -> 0.58333333 | F64: Fecha Desde: | G64: =G7 -> 46219 | J64: Feha Hasta: | K64: =K7 -> 46234 | U64: =F64 -> Fecha Desde: | V64: =G64 -> 46219 | X64: =J64 -> Feha Hasta: | Y64: =K64 -> 46234
B65: ASE | C65: Concesionarios | D65: Recaudo Total | E65: Recaudo por disposicion final | F65: Recaudo por tratamiento de lixiviados | G65: Recaudo por Componente VIAT ( Decreto 2412/2018) | H65: Recaudo por aprovechamiento | I65: Recaudo del componente de comercializacion para Aprovechamiento (11,4%) | J65: Balance de subsidio o contribuciones | K65: RECAUDO BASE DE REMUNERACION | L65: Costo de la Interventoría | M65: REMUNERACION FINAL | N65: Conceptos especiales | O65: REMUNERACION FINAL MAS CONCEPTOS ESPECIALES | S65: ASE | T65: Concesionarios | U65: Tarifa de Comercialización del Servicio. ( TCS) | V65: Tarifa de Limpieza Urbana del Servicio. ( TLU) | W65: Tarifa de Barrido y Limpieza del Servicio. ( TBL) | X65: Tarifa de Recolección y Transporte del Servicio. (TRT) | Y65: Recaudo del componente de comercializacion para Aprovechamiento (18,6%) | Z65: Costo de la Interventoría | AA65: Ajuste a la decena | AB65: Conceptos especiales | AC65: Otros | AD65: Diferencial Balance S / C (Fac vs Rec) | AE65: Balance S / C Con Base en (Recaudo) | AF65: REMUNERACION FINAL MAS CONCEPTOS ESPECIALES
B66: 1 | C66: PROMOAMBIENTAL DISTRITO S.A.S. ESP. | D66: ='Reversion Pagos R4'!D73 -> -16536713 | E66: ='Reversion Pagos R4'!E73 -> -842044.27 | F66: ='Reversion Pagos R4'!F73 -> -470499.84 | G66: ='Reversion Pagos R4'!G73 -> -249332.32 | H66: ='Reversion Pagos R4'!H73 -> -4006466.8 | I66: ='Reversion Pagos R4'!I73 -> -145004 | J66: 0 | K66: =D66-E66-F66-G66-H66-I66-J66 -> -10823366 | L66: 0 | M66: =K66-L66 -> -10823366 | N66: ='Reversion Pagos R4'!P73 -> 0 | O66: =M66+N66 -> -10823366 | S66: 1 | T66: PROMOAMBIENTAL DISTRITO S.A.S. ESP. | U66: ='Reversion Pagos R4'!J73 -> -1301824.8 | V66: ='Reversion Pagos R4'!K73 -> -1255802.9 | W66: ='Reversion Pagos R4'!L73 -> -5775459.5 | X66: ='Reversion Pagos R4'!M73 -> -2296297.4 | Y66: ='Reversion Pagos R4'!N73 -> -237636.38 | Z66: =-L66 -> 0 | AA66: ='Reversion Pagos R4'!O73 -> 100.74 | AB66: =N66 -> 0 | AC66: =+'Reversion Pagos R4'!Q73+'Reversion Pagos R4'!R73 -> 0 | AD66: =-J66+AE66 -> 43554.45 | AE66: ='Reversion Pagos R4'!D74 -> 43554.45 | AF66: =SUM(U66:AD66) -> -10823366 | AG66: =(AF66-O66) -> 0 | AH66: =INT(AG66)=0 -> TRUE
B67: 2 | C67: LIMPIEZA METROPOLITANA S.A. ESP. | D67: ='Reversion Pagos R4'!D168 -> -71069759 | E67: ='Reversion Pagos R4'!E168 -> -15881719 | F67: ='Reversion Pagos R4'!F168 -> -7382378.6 | G67: ='Reversion Pagos R4'!G168 -> -4039895.6 | H67: ='Reversion Pagos R4'!H168 -> -3333203 | I67: ='Reversion Pagos R4'!I168 -> -119625.47 | J67: 0 | K67: =D67-E67-F67-G67-H67-I67-J67 -> -40312937 | L67: 0 | M67: =K67-L67 -> -40312937 | N67: ='Reversion Pagos R4'!P168 -> 0 | O67: =M67+N67 -> -40312937 | S67: 2 | T67: LIMPIEZA METROPOLITANA S.A. ESP. | U67: ='Reversion Pagos R4'!J168 -> -1050942.2 | V67: ='Reversion Pagos R4'!K168 -> -1052754.2 | W67: ='Reversion Pagos R4'!L168 -> -4921480.5 | X67: ='Reversion Pagos R4'!M168 -> -32197092 | Y67: ='Reversion Pagos R4'!N168 -> -194756.95 | Z67: =-L67 -> 0 | AA67: ='Reversion Pagos R4'!O168 -> 28.29 | AB67: =N67 -> 0 | AC67: =+'Reversion Pagos R4'!Q168+'Reversion Pagos R4'!R168 -> 0 | AD67: =-J67+AE67 -> -895939.5 | AE67: ='Reversion Pagos R4'!D169 -> -895939.5 | AF67: =SUM(U67:AD67) -> -40312937 | AG67: =(AF67-O67) -> -1.4901161e-08 | AH67: =INT(AG67)=0 -> FALSE
B68: 3 | C68: CIUDAD LIMPIA BOGOTA S.A. ESP. | D68: ='Reversion Pagos R4'!D205 -> -32310980 | E68: ='Reversion Pagos R4'!E205 -> -2359230.9 | F68: ='Reversion Pagos R4'!F205 -> -1307200.3 | G68: ='Reversion Pagos R4'!G205 -> -693108.36 | H68: ='Reversion Pagos R4'!H205 -> -5641919 | I68: ='Reversion Pagos R4'!I205 -> -208676.79 | J68: 0 | K68: =D68-E68-F68-G68-H68-I68-J68 -> -22100844 | L68: 0 | M68: =K68-L68 -> -22100844 | N68: ='Reversion Pagos R4'!P205 -> 0 | O68: =M68+N68 -> -22100844 | S68: 3 | T68: CIUDAD LIMPIA BOGOTA S.A. ESP. | U68: ='Reversion Pagos R4'!J205 -> -1838013.6 | V68: ='Reversion Pagos R4'!K205 -> -1771126 | W68: ='Reversion Pagos R4'!L205 -> -8312687.9 | X68: ='Reversion Pagos R4'!M205 -> -5496750.7 | Y68: ='Reversion Pagos R4'!N205 -> -342720.34 | Z68: =-L68 -> 0 | AA68: ='Reversion Pagos R4'!O205 -> -128.57 | AB68: =N68 -> 0 | AC68: =+'Reversion Pagos R4'!Q205+'Reversion Pagos R4'!R205 -> 0 | AD68: =-J68+AE68 -> -4339417.4 | AE68: ='Reversion Pagos R4'!D206 -> -4339417.4 | AF68: =SUM(U68:AD68) -> -22100844 | AG68: =(AF68-O68) -> 0 | AH68: =INT(AG68)=0 -> TRUE
B69: 4 | C69: BOGOTA LIMPIA S.A.S. ESP. | D69: ='Reversion Pagos R4'!D320 -> -33738104 | E69: ='Reversion Pagos R4'!E320 -> -3280830.1 | F69: ='Reversion Pagos R4'!F320 -> -1653570.3 | G69: ='Reversion Pagos R4'!G320 -> -772414.51 | H69: ='Reversion Pagos R4'!H320 -> -6809335.5 | I69: ='Reversion Pagos R4'!I320 -> -246830.89 | J69: 0 | K69: =D69-E69-F69-G69-H69-I69-J69 -> -20975123 | L69: 0 | M69: =K69-L69 -> -20975123 | N69: ='Reversion Pagos R4'!P320 -> 0 | O69: =M69+N69 -> -20975123 | S69: 4 | T69: BOGOTA LIMPIA S.A.S. ESP. | U69: ='Reversion Pagos R4'!J320 -> -2175989.7 | V69: ='Reversion Pagos R4'!K320 -> -2281434.7 | W69: ='Reversion Pagos R4'!L320 -> -10508486 | X69: ='Reversion Pagos R4'!M320 -> -8690898.3 | Y69: ='Reversion Pagos R4'!N320 -> -404523.79 | Z69: =-L69 -> 0 | AA69: ='Reversion Pagos R4'!O320 -> -1.3 | AB69: =N69 -> 0 | AC69: =+'Reversion Pagos R4'!Q320+'Reversion Pagos R4'!R320 -> -0.29 | AD69: =-J69+AE69 -> 3086211.4 | AE69: ='Reversion Pagos R4'!D321 -> 3086211.4 | AF69: =SUM(U69:AD69) -> -20975123 | AG69: =(AF69-O69) -> 0 | AH69: =INT(AG69)=0 -> TRUE
B70: 5 | C70: AREA LIMPIA DISTRITO CAPITAL S.A.S. ESP. | D70: ='Reversion Pagos R4'!D355 -> -3092375.5 | E70: ='Reversion Pagos R4'!E355 -> -204651.35 | F70: ='Reversion Pagos R4'!F355 -> -114062.66 | G70: ='Reversion Pagos R4'!G355 -> -59426.1 | H70: ='Reversion Pagos R4'!H355 -> -755065.42 | I70: ='Reversion Pagos R4'!I355 -> -27250.92 | J70: 0 | K70: =D70-E70-F70-G70-H70-I70-J70 -> -1931919.1 | L70: 0 | M70: =K70-L70 -> -1931919.1 | N70: ='Reversion Pagos R4'!P355 -> 0 | O70: =M70+N70 -> -1931919.1 | S70: 5 | T70: AREA LIMPIA DISTRITO CAPITAL S.A.S. ESP. | U70: ='Reversion Pagos R4'!J355 -> -239043.97 | V70: ='Reversion Pagos R4'!K355 -> -246114.56 | W70: ='Reversion Pagos R4'!L355 -> -1258305.7 | X70: ='Reversion Pagos R4'!M355 -> -604168.66 | Y70: ='Reversion Pagos R4'!N355 -> -44461.78 | Z70: =-L70 -> 0 | AA70: ='Reversion Pagos R4'!O355 -> -2.56 | AB70: =N70 -> 0 | AC70: =+'Reversion Pagos R4'!Q355+'Reversion Pagos R4'!R355 -> 0 | AD70: =-J70+AE70 -> 460178.15 | AE70: ='Reversion Pagos R4'!D356 -> 460178.15 | AF70: =SUM(U70:AD70) -> -1931919.1 | AG70: =(AF70-O70) -> -4.6566129e-10 | AH70: =INT(AG70)=0 -> FALSE
C71: TOTAL | D71: =SUM(D66:D70) -> -1.5674793e+08 | E71: =SUM(E66:E70) -> -22568476 | F71: =SUM(F66:F70) -> -10927712 | G71: =SUM(G66:G70) -> -5814176.8 | H71: =SUM(H66:H70) -> -20545990 | I71: =SUM(I66:I70) -> -747388.07 | J71: =SUM(J66:J70) -> 0 | K71: =SUM(K66:K70) -> -96144189 | ... O71: =SUM(O66:O70) -> -96144189 | T71: TOTAL | U71: =SUM(U66:U70) -> -6605814.4 | V71: =SUM(V66:V70) -> -6607232.4 | W71: =SUM(W66:W70) -> -30776420 | X71: =SUM(X66:X70) -> -49285207 | Y71: =SUM(Y66:Y70) -> -1224099.2 | Z71: =SUM(Z66:Z70) -> 0 | AA71: =SUM(AA66:AA70) -> -3.4 | AB71: =SUM(AB66:AB70) -> 0 | ... AG71: =SUM(AG66:AG70) -> -1.5366822e-08 | AH71: =INT(AG71)=0 -> FALSE
Y73: =SUM(U71:Y71) -> -94498773
F75: Firma autorizada
F79: PROCERASEO S.A.S. | I79: NIT: 901 153 639 - 0 | M79: Codigo Remuneración: | N79: =N3 -> 2026072 | U79: PROCERASEO S.A.S. | W79: NIT: 901 153 639 - 0 | AA79: Codigo Remuneración: | AD79: =N79 -> 2026072
F80: 3. ESQUEMA FINANCIERO DEL SERVICIO PUBLICO DE ASEO | U80: 3. ESQUEMA FINANCIERO DEL SERVICIO PUBLICO DE ASEO
F81: Resoluciòn UAESP Número 27 de 2018 | U81: Resoluciòn UAESP Número 27 de 2018
C82: Fecha de Proceso: | D82: =D6 -> 46238 | F82: R5 - REMUNERACIÓN SALDOS A FAVOR POR NOTA | U82: =F82 -> R5 - REMUNERACIÓN SALDOS A FAVOR POR NOTA
C83: Hora: | D83: =D7 -> 0.58333333 | F83: Fecha Desde: | G83: =G7 -> 46219 | J83: Feha Hasta: | K83: =K7 -> 46234 | U83: =F83 -> Fecha Desde: | V83: =G83 -> 46219 | X83: =J83 -> Feha Hasta: | Y83: =K83 -> 46234
B84: ASE | C84: Concesionarios | D84: Recaudo Total | E84: Recaudo por disposicion final | F84: Recaudo por tratamiento de lixiviados | G84: Recaudo por Componente VIAT ( Decreto 2412/2018) | H84: Recaudo por aprovechamiento | I84: Recaudo del componente de comercializacion para Aprovechamiento (11,4%) | J84: Balance de subsidio o contribuciones | K84: RECAUDO BASE DE REMUNERACION | L84: Costo de la Interventoría | M84: REMUNERACION FINAL | N84: Conceptos especiales | O84: REMUNERACION FINAL MAS CONCEPTOS ESPECIALES | S84: ASE | T84: Concesionarios | U84: Tarifa de Comercialización del Servicio. ( TCS) | V84: Tarifa de Limpieza Urbana del Servicio. ( TLU) | W84: Tarifa de Barrido y Limpieza del Servicio. ( TBL) | X84: Tarifa de Recolección y Transporte del Servicio. (TRT) | Y84: Recaudo del componente de comercializacion para Aprovechamiento (18,6%) | Z84: Costo de la Interventoría | AA84: Ajuste a la decena | AB84: Conceptos especiales | AC84: Otros | AD84: Diferencial Balance Subsidio y Contribución (Fac vs Rec) | AE84: Balance de subsidio o contribuciones (Recaudo) | AF84: REMUNERACION FINAL MAS CONCEPTOS ESPECIALES
B85: 1 | C85: PROMOAMBIENTAL DISTRITO S.A.S. ESP. | D85: ='AJUSTES - SF-T'!D47 -> 973693.46 | E85: ='AJUSTES - SF-T'!E47 -> 65524.22 | F85: ='AJUSTES - SF-T'!F47 -> 36995.02 | G85: ='AJUSTES - SF-T'!G47 -> 19417.65 | H85: ='AJUSTES - SF-T'!H47 -> 156624.35 | I85: ='AJUSTES - SF-T'!I47 -> 5557.5 | J85: ='AJUSTES - SF-T'!J47 -> 0 | K85: =D85-E85-F85-G85-H85-I85-J85 -> 689574.72 | L85: 0 | M85: =K85-L85 -> 689574.72 | N85: ='AJUSTES - SF-T'!N47 -> 0 | O85: =M85+N85 -> 689574.72 | S85: 1 | T85: PROMOAMBIENTAL DISTRITO S.A.S. ESP. | U85: ='AJUSTES - SF-T'!U47 -> 52109.79 | V85: ='AJUSTES - SF-T'!V47 -> 47607.03 | W85: ='AJUSTES - SF-T'!W47 -> 225441.17 | X85: ='AJUSTES - SF-T'!X47 -> 178429.31 | Y85: ='AJUSTES - SF-T'!Y47 -> 9067.43 | Z85: =-L85 -> 0 | AA85: ='AJUSTES - SF-T'!AA47 -> 0 | AB85: =N85 -> 0 | AC85: 0 | AD85: =-J85+AE85 -> 176919.99 | AE85: ='AJUSTES - SF-T'!AD47 -> 176919.99 | AF85: =SUM(U85:AD85) -> 689574.72 | AG85: =AF85-O85 -> 0 | AH85: =INT(AG85)=0 -> TRUE
B86: 2 | C86: LIMPIEZA METROPOLITANA S.A. ESP. | D86: ='AJUSTES - SF-T'!D48 -> 216025.77 | E86: ='AJUSTES - SF-T'!E48 -> 31897.62 | F86: ='AJUSTES - SF-T'!F48 -> 18572.91 | G86: ='AJUSTES - SF-T'!G48 -> 8867.14 | H86: ='AJUSTES - SF-T'!H48 -> 92959.49 | I86: ='AJUSTES - SF-T'!I48 -> 3883.88 | J86: ='AJUSTES - SF-T'!J48 -> 0 | K86: =D86-E86-F86-G86-H86-I86-J86 -> 59844.73 | L86: 0 | M86: =K86-L86 -> 59844.73 | N86: ='AJUSTES - SF-T'!N48 -> 0 | O86: =M86+N86 -> 59844.73 | S86: 2 | T86: LIMPIEZA METROPOLITANA S.A. ESP. | U86: ='AJUSTES - SF-T'!U48 -> 61358.09 | V86: ='AJUSTES - SF-T'!V48 -> 33534.01 | W86: ='AJUSTES - SF-T'!W48 -> 127815.87 | X86: ='AJUSTES - SF-T'!X48 -> 64515.32 | Y86: ='AJUSTES - SF-T'!Y48 -> 5139.92 | Z86: =-L86 -> 0 | AA86: ='AJUSTES - SF-T'!AA48 -> -0.36 | AB86: =N86 -> 0 | AC86: 0 | AD86: =-J86+AE86 -> -232518.12 | AE86: ='AJUSTES - SF-T'!AD48 -> -232518.12 | AF86: =SUM(U86:AD86) -> 59844.73 | AG86: =AF86-O86 -> 0 | AH86: =INT(AG86)=0 -> TRUE
B87: 3 | C87: CIUDAD LIMPIA BOGOTA S.A. ESP. | D87: ='AJUSTES - SF-T'!D49 -> 104231.83 | E87: ='AJUSTES - SF-T'!E49 -> 6620.63 | F87: ='AJUSTES - SF-T'!F49 -> 3738.02 | G87: ='AJUSTES - SF-T'!G49 -> 1961.98 | H87: ='AJUSTES - SF-T'!H49 -> 20927.5 | I87: ='AJUSTES - SF-T'!I49 -> 743.08 | J87: ='AJUSTES - SF-T'!J49 -> 0 | K87: =D87-E87-F87-G87-H87-I87-J87 -> 70240.62 | L87: 0 | M87: =K87-L87 -> 70240.62 | N87: ='AJUSTES - SF-T'!N49 -> 0 | O87: =M87+N87 -> 70240.62 | S87: 3 | T87: CIUDAD LIMPIA BOGOTA S.A. ESP. | U87: ='AJUSTES - SF-T'!U49 -> 6518.28 | V87: ='AJUSTES - SF-T'!V49 -> 6410.86 | W87: ='AJUSTES - SF-T'!W49 -> 30349.1 | X87: ='AJUSTES - SF-T'!X49 -> 15383.1 | Y87: ='AJUSTES - SF-T'!Y49 -> 1212.4 | Z87: =-L87 -> 0 | AA87: ='AJUSTES - SF-T'!AA49 -> 0 | AB87: =N87 -> 0 | AC87: 0 | AD87: =-J87+AE87 -> 10366.88 | AE87: ='AJUSTES - SF-T'!AD49 -> 10366.88 | AF87: =SUM(U87:AD87) -> 70240.62 | AG87: =AF87-O87 -> 0 | AH87: =INT(AG87)=0 -> TRUE
B88: 4 | C88: BOGOTA LIMPIA S.A.S. ESP. | D88: ='AJUSTES - SF-T'!D50 -> 35954.44 | E88: ='AJUSTES - SF-T'!E50 -> 1890.6 | F88: ='AJUSTES - SF-T'!F50 -> 1067.43 | G88: ='AJUSTES - SF-T'!G50 -> 560.27 | H88: ='AJUSTES - SF-T'!H50 -> 10800.02 | I88: ='AJUSTES - SF-T'!I50 -> 371.66 | J88: ='AJUSTES - SF-T'!J50 -> 0 | K88: =D88-E88-F88-G88-H88-I88-J88 -> 21264.46 | L88: 0 | M88: =K88-L88 -> 21264.46 | N88: ='AJUSTES - SF-T'!N50 -> 0 | O88: =M88+N88 -> 21264.46 | S88: 4 | T88: BOGOTA LIMPIA S.A.S. ESP. | U88: ='AJUSTES - SF-T'!U50 -> 3260.18 | V88: ='AJUSTES - SF-T'!V50 -> 3149.08 | W88: ='AJUSTES - SF-T'!W50 -> 15696.81 | X88: ='AJUSTES - SF-T'!X50 -> 5005.76 | Y88: ='AJUSTES - SF-T'!Y50 -> 606.39 | Z88: =-L88 -> 0 | AA88: ='AJUSTES - SF-T'!AA50 -> 0 | AB88: =N88 -> 0 | AC88: 0 | AD88: =-J88+AE88 -> -6453.76 | AE88: ='AJUSTES - SF-T'!AD50 -> -6453.76 | AF88: =SUM(U88:AD88) -> 21264.46 | AG88: =AF88-O88 -> 0 | AH88: =INT(AG88)=0 -> TRUE
B89: 5 | C89: AREA LIMPIA DISTRITO CAPITAL S.A.S. ESP. | D89: ='AJUSTES - SF-T'!D51 -> 0 | E89: ='AJUSTES - SF-T'!E51 -> 0 | F89: ='AJUSTES - SF-T'!F51 -> 0 | G89: ='AJUSTES - SF-T'!G51 -> 0 | H89: ='AJUSTES - SF-T'!H51 -> 0 | I89: ='AJUSTES - SF-T'!I51 -> 0 | J89: ='AJUSTES - SF-T'!J51 -> 0 | K89: =D89-E89-F89-G89-H89-I89-J89 -> 0 | L89: 0 | M89: =K89-L89 -> 0 | N89: ='AJUSTES - SF-T'!N51 -> 0 | O89: =M89+N89 -> 0 | S89: 5 | T89: AREA LIMPIA DISTRITO CAPITAL S.A.S. ESP. | U89: ='AJUSTES - SF-T'!U51 -> 0 | V89: ='AJUSTES - SF-T'!V51 -> 0 | W89: ='AJUSTES - SF-T'!W51 -> 0 | X89: ='AJUSTES - SF-T'!X51 -> 0 | Y89: ='AJUSTES - SF-T'!Y51 -> 0 | Z89: =-L89 -> 0 | AA89: ='AJUSTES - SF-T'!AA51 -> 0 | AB89: =N89 -> 0 | AC89: 0 | AD89: =-J89+AE89 -> 0 | AE89: ='AJUSTES - SF-T'!AD51 -> 0 | AF89: =SUM(U89:AD89) -> 0 | AG89: =AF89-O89 -> 0 | AH89: =INT(AG89)=0 -> TRUE
C90: TOTAL | D90: =SUM(D85:D89) -> 1329905.5 | E90: =SUM(E85:E89) -> 105933.07 | F90: =SUM(F85:F89) -> 60373.38 | G90: =SUM(G85:G89) -> 30807.04 | H90: =SUM(H85:H89) -> 281311.36 | I90: =SUM(I85:I89) -> 10556.12 | J90: =SUM(J85:J89) -> 0 | K90: =SUM(K85:K89) -> 840924.53 | ... O90: =SUM(O85:O89) -> 840924.53 | T90: TOTAL | U90: =SUM(U85:U89) -> 123246.34 | V90: =SUM(V85:V89) -> 90700.98 | W90: =SUM(W85:W89) -> 399302.95 | X90: =SUM(X85:X89) -> 263333.49 | Y90: =SUM(Y85:Y89) -> 16026.14 | Z90: =SUM(Z85:Z89) -> 0 | AA90: =SUM(AA85:AA89) -> -0.36 | AB90: =SUM(AB85:AB89) -> 0 | ... AG90: =SUM(AG85:AG89) -> 0 | AH90: =INT(AG90)=0 -> TRUE
Y92: =SUM(U90:Y90) -> 892609.9
F94: Firma autorizada
F98: PROCERASEO S.A.S. | I98: NIT: 901 153 639 - 0 | M98: Codigo Remuneración: | N98: =N3 -> 2026072 | U98: PROCERASEO S.A.S. | W98: NIT: 901 153 639 - 0 | AA98: Codigo Remuneración: | AD98: =N98 -> 2026072
F99: 3. ESQUEMA FINANCIERO DEL SERVICIO PUBLICO DE ASEO | U99: 3. ESQUEMA FINANCIERO DEL SERVICIO PUBLICO DE ASEO
F100: Resoluciòn UAESP Número 27 de 2018 | U100: Resoluciòn UAESP Número 27 de 2018
C101: Fecha de Proceso: | D101: =D6 -> 46238 | F101: REPORTE CONSOLIDADO TOTAL DE RECAUDO | U101: REPORTE DETALLADO SUBBOLSA RBL DISCRIMINADO POR ACTIVIDADES
C102: Hora: | D102: =D7 -> 0.58333333 | F102: Fecha Desde: | G102: =G7 -> 46219 | J102: Feha Hasta: | K102: =K7 -> 46234 | U102: =F102 -> Fecha Desde: | V102: =G102 -> 46219 | X102: =J102 -> Feha Hasta: | Y102: =K102 -> 46234
B103: ASE | C103: Concesionarios | D103: Recaudo Total | E103: Recaudo por disposicion final | F103: Recaudo por tratamiento de lixiviados | G103: Recaudo por Componente VIAT ( Decreto 2412/2018) | H103: Recaudo por aprovechamiento | I103: Recaudo del componente de comercializacion para Aprovechamiento (11,4%) | J103: Balance de subsidio o contribuciones | K103: RECAUDO BASE DE REMUNERACION | L103: Costo de la Interventoría | M103: REMUNERACION FINAL | N103: Conceptos especiales | O103: REMUNERACION FINAL MAS CONCEPTOS ESPECIALES | S103: ASE | T103: Concesionarios | U103: Tarifa de Comercialización del Servicio. ( TCS) | V103: Tarifa de Limpieza Urbana del Servicio. ( TLU) | W103: Tarifa de Barrido y Limpieza del Servicio. ( TBL) | X103: Tarifa de Recolección y Transporte del Servicio. (TRT) | Y103: Recaudo del componente de comercializacion para Aprovechamiento (18,6%) | Z103: Costo de la Interventoría | AA103: Ajuste a la decena | AB103: Conceptos especiales | AC103: Otros | AD103: Diferencial Balance Subsidio y Contribución (Fac vs Rec) | AE103: Balance de subsidio o contribuciones (Recaudo) | AF103: REMUNERACION FINAL MAS CONCEPTOS ESPECIALES
