Workbook
Name \0: #REF!
Name _1: #REF!
Name _2: #REF!
Name _A655555: #REF!
Name _CFR1: #REF!
Name _cia1: #REF!
Name _XL250: #REF!
Name A: #REF!
Name ADM: [1]!ADM
Name ADM: [1]!ADM
Name ADM: [1]!ADM
Name ADM: [1]!ADM
Name ADM: [1]!ADM
Name ADM_: [1]!ADM
Name ADM_: [1]!ADM
Name ADM_: [1]!ADM
Name ADM_: [1]!ADM
Name ADM_: [1]!ADM
Name AI: #REF!
Name Air: #REF!
Name AP: '[2]TARIFA no aforos'!$C$12
Name Bancos: [3]Fx!$C$1:$C$23
Name CBL: #REF!
Name CCS: #REF!
Name CDT_p: [4]CDT!$C$3
Name CFR: #REF!
Name cia: #REF!
Name COM: #REF!
Name CRT: #REF!
Name CRT___CTEp___CDTp___CMRv: #REF!
Name CRT_aislados: '[4]COSTOS AJUSTADOS'!$C$13
Name CRT_costas: #REF!
Name CTE_p: [4]CTE!$C$5
Name Denominador: #REF!
Name dg: [1]!ADM
Name dg: [1]!ADM
Name dg: [1]!ADM
Name dg: [1]!ADM
Name dg: [1]!ADM
Name DIAS: [5]CONTRA!#REF!
Name Fmerc: #REF!
Name FPS: #REF!
Name InformacionGeneral: [1]!InformacionGeneral
Name InformacionGeneral: [1]!InformacionGeneral
Name InformacionGeneral: [1]!InformacionGeneral
Name InformacionGeneral: [1]!InformacionGeneral
Name InformacionGeneral: [1]!InformacionGeneral
Name INTFIN: #REF!
Name INV: [1]!INV
Name INV: [1]!INV
Name INV: [1]!INV
Name INV: [1]!INV
Name INV: [1]!INV
Name K: #REF!
Name N: '[4]COSTOS AJUSTADOS'!#REF!
Name Na: '[2]TARIFA no aforos'!$C$39
Name nfc: '[4]COSTOS AJUSTADOS'!#REF!
Name OYM: [1]!OYM
Name OYM: [1]!OYM
Name OYM: [1]!OYM

Sheet Recaudo EAAB Reciprocidad
B2: OPORTUNO | C2: ASE | D2: VALOR 1° Q | E2: NUMERO REG. 1°Q | F2: VALOR 2° Q | G2: NUMERO REG. 2°Q
C3: 1 | D3: 0 | E3: 0 | F3: 0 | G3: 0
C4: 2 | D4: 21532120 | E4: 250 | F4: 18262430 | G4: 217
C5: 3 | D5: 0 | E5: 0 | F5: 0 | G5: 0
C6: 4 | D6: 14335960 | E6: 80 | F6: 8615850 | G6: 64
C7: 5 | D7: 0 | E7: 0 | F7: 0 | G7: 0
C8: X
D9: 35868080 | E9: 330 | F9: 26878280 | G9: 281
C11: ASE | D11: VALOR 1° Q | E11: NUMERO REG. 1°Q | F11: VALOR 2° Q | G11: NUMERO REG. 2°Q
B12: EXTEMP. | C12: 1 | D12: 0 | E12: 0 | F12: 0 | G12: 0
C13: 2 | D13: 0 | E13: 0 | F13: 798760 | G13: 7
C14: 3 | D14: 0 | E14: 0 | F14: 0 | G14: 0
C15: 4 | D15: 0 | E15: 0 | F15: 228530 | G15: 1
C16: 5 | D16: 0 | E16: 0 | F16: 0 | G16: 0
C17: X
D18: 0 | E18: 0 | F18: 1027290 | G18: 8
C20: ASE | D20: VALOR 1° Q | E20: NUMERO REG. 1°Q | F20: VALOR 2° Q | G20: NUMERO REG. 2°Q | I20: VALOR TOTAL MES | J20: NUMERO REGISTROS MES
B21: TOTAL | C21: 1 | D21: 0 | E21: 0 | F21: 0 | G21: 0 | I21: 0 | J21: 0
C22: 2 | D22: 21532120 | E22: 250 | F22: 19061190 | G22: 224 | I22: 40593310 | J22: 474
C23: 3 | D23: 0 | E23: 0 | F23: 0 | G23: 0 | I23: 0 | J23: 0
C24: 4 | D24: 14335960 | E24: 80 | F24: 8844380 | G24: 65 | I24: 23180340 | J24: 145
C25: 5 | D25: 0 | E25: 0 | F25: 0 | G25: 0 | I25: 0 | J25: 0
C26: X | I26: 0 | J26: 0
D27: 35868080 | E27: 330 | F27: 27905570 | G27: 289 | I27: 63773650 | J27: 619
B31: OPORTUNO | D31: =D9=SUM(D3:D8) -> TRUE | E31: =E9=SUM(E3:E8) -> TRUE | F31: =F9=SUM(F3:F8) -> TRUE | G31: =G9=SUM(G3:G8) -> TRUE
B33: EXTEMP. | D33: =D18=SUM(D12:D17) -> TRUE | E33: =E18=SUM(E12:E17) -> TRUE | F33: =F18=SUM(F12:F17) -> TRUE | G33: =G18=SUM(G12:G17) -> TRUE
B35: TOTAL | D35: =D27=SUM(D21:D26) -> TRUE | E35: =E27=SUM(E21:E26) -> TRUE | F35: =F27=SUM(F21:F26) -> TRUE | G35: =G27=SUM(G21:G26) -> TRUE | I35: =I27=SUM(I21:I26) -> TRUE | J35: =J27=SUM(J21:J26) -> TRUE
E69: =C69-G17 -> 0

Sheet Recaudo ENEL
B2: OPORTUNO | C2: ASE | D2: VALOR 1° Q | E2: NUMERO REG. 1°Q | F2: VALOR 2° Q | G2: NUMERO REG. 2°Q
C3: 1 | D3: 11569331103 | E3: 255523 | F3: 17277226302 | G3: 316936
C4: 2 | D4: 9606604754 | E4: 194100 | F4: 19264884848 | G4: 396694
C5: 3 | D5: 7742246377 | E5: 182798 | F5: 15047689272 | G5: 273948
C6: 4 | D6: 8062155957 | E6: 139505 | F6: 7298795841 | G6: 142161
C7: 5 | D7: 6139322220 | E7: 123536 | F7: 11700424846 | G7: 249311
C8: X
D9: 43119660411 | E9: 895462 | F9: 70589021109 | G9: 1379050
C11: ASE | D11: VALOR 1° Q | E11: NUMERO REG. 1°Q | F11: VALOR 2° Q | G11: NUMERO REG. 2°Q
B12: EXTEMP. | C12: 1 | D12: 122584360 | E12: 2043 | F12: 208241806 | G12: 4505
C13: 2 | D13: 59571250 | E13: 1204 | F13: 47318959 | G13: 914
C14: 3 | D14: 64416890 | E14: 1231 | F14: 96850450 | G14: 2077
C15: 4 | D15: 68519068 | E15: 1069 | F15: 96874840 | G15: 2369
C16: 5 | D16: 107615030 | E16: 2071 | F16: 80297730 | G16: 1887
C17: X
D18: 422706598 | E18: 7618 | F18: 529583785 | G18: 11752
C20: ASE | D20: VALOR 1° Q | E20: NUMERO REG. 1°Q | F20: VALOR 2° Q | G20: NUMERO REG. 2°Q | I20: VALOR TOTAL MES | J20: NUMERO REGISTROS MES
B21: TOTAL | C21: 1 | D21: 11691915463 | E21: 257566 | F21: 17485468108 | G21: 321441 | I21: 29177383571 | J21: 579007
C22: 2 | D22: 9666176004 | E22: 195304 | F22: 19312203807 | G22: 397608 | I22: 28978379811 | J22: 592912
C23: 3 | D23: 7806663267 | E23: 184029 | F23: 15144539722 | G23: 276025 | I23: 22951202989 | J23: 460054
C24: 4 | D24: 8130675025 | E24: 140574 | F24: 7395670681 | G24: 144530 | I24: 15526345706 | J24: 285104
C25: 5 | D25: 6246937250 | E25: 125607 | F25: 11780722576 | G25: 251198 | I25: 18027659826 | J25: 376805
C26: X | I26: 0 | J26: 0
D27: 43542367009 | E27: 903080 | F27: 71118604894 | G27: 1390802 | I27: 114660971903 | J27: 2293882
B31: OPORTUNO | D31: =D9=SUM(D3:D8) -> TRUE | E31: =E9=SUM(E3:E8) -> TRUE | F31: =F9=SUM(F3:F8) -> TRUE | G31: =G9=SUM(G3:G8) -> TRUE
B33: EXTEMP. | D33: =D18=SUM(D12:D17) -> TRUE | E33: =E18=SUM(E12:E17) -> TRUE | F33: =F18=SUM(F12:F17) -> TRUE | G33: =G18=SUM(G12:G17) -> TRUE
B35: TOTAL | D35: =D27=SUM(D21:D26) -> TRUE | E35: =E27=SUM(E21:E26) -> TRUE | F35: =F27=SUM(F21:F26) -> TRUE | G35: =G27=SUM(G21:G26) -> TRUE | I35: =I27=SUM(I21:I26) -> TRUE | J35: =J27=SUM(J21:J26) -> TRUE
E69: =C69-G17 -> 0

Sheet Recaudo ENERBIT
B2: OPORTUNO | C2: ASE | D2: VALOR 1° Q | E2: NUMERO REG. 1°Q | F2: VALOR 2° Q | G2: NUMERO REG. 2°Q
C3: 1 | D3: 0 | E3: 0 | F3: 0 | G3: 0
C4: 2 | D4: 0 | E4: 0 | F4: 0 | G4: 0
C5: 3 | D5: 0 | E5: 0 | F5: 0 | G5: 0
C6: 4 | D6: 0 | E6: 0 | F6: 0 | G6: 0
C7: 5 | D7: 133950890 | E7: 2925 | F7: 32068500 | G7: 539
C8: X
D9: 133950890 | E9: 2925 | F9: 32068500 | G9: 539
C11: ASE | D11: VALOR 1° Q | E11: NUMERO REG. 1°Q | F11: VALOR 2° Q | G11: NUMERO REG. 2°Q
B12: EXTEMP. | C12: 1 | D12: 0 | E12: 0 | F12: 0 | G12: 0
C13: 2 | D13: 0 | E13: 0 | F13: 0 | G13: 0
C14: 3 | D14: 0 | E14: 0 | F14: 0 | G14: 0
C15: 4 | D15: 0 | E15: 0 | F15: 0 | G15: 0
C16: 5 | D16: 0 | E16: 0 | F16: 488120 | G16: 11
C17: X
D18: 0 | E18: 0 | F18: 488120 | G18: 11
C20: ASE | D20: VALOR 1° Q | E20: NUMERO REG. 1°Q | F20: VALOR 2° Q | G20: NUMERO REG. 2°Q | I20: VALOR TOTAL MES | J20: NUMERO REGISTROS MES
B21: TOTAL | C21: 1 | D21: 0 | E21: 0 | F21: 0 | G21: 0 | I21: 0 | J21: 0
C22: 2 | D22: 0 | E22: 0 | F22: 0 | G22: 0 | I22: 0 | J22: 0
C23: 3 | D23: 0 | E23: 0 | F23: 0 | G23: 0 | I23: 0 | J23: 0
C24: 4 | D24: 0 | E24: 0 | F24: 0 | G24: 0 | I24: 0 | J24: 0
C25: 5 | D25: 133950890 | E25: 2925 | F25: 32556620 | G25: 550 | I25: 166507510 | J25: 3475
C26: X | I26: 0 | J26: 0
D27: 133950890 | E27: 2925 | F27: 32556620 | G27: 550 | I27: 166507510 | J27: 3475
B31: OPORTUNO | D31: =D9=SUM(D3:D8) -> TRUE | E31: =E9=SUM(E3:E8) -> TRUE | F31: =F9=SUM(F3:F8) -> TRUE | G31: =G9=SUM(G3:G8) -> TRUE
B33: EXTEMP. | D33: =D18=SUM(D12:D17) -> TRUE | E33: =E18=SUM(E12:E17) -> TRUE | F33: =F18=SUM(F12:F17) -> TRUE | G33: =G18=SUM(G12:G17) -> TRUE
B35: TOTAL | D35: =D27=SUM(D21:D26) -> TRUE | E35: =E27=SUM(E21:E26) -> TRUE | F35: =F27=SUM(F21:F26) -> TRUE | G35: =G27=SUM(G21:G26) -> TRUE | I35: =I27=SUM(I21:I26) -> TRUE | J35: =J27=SUM(J21:J26) -> TRUE
E69: =C69-G17 -> 0

Sheet Recaudo EAAB + Ciud Limp
B2: Ciudad Limpia - Prestador | C2: ASE | D2: VALOR 1° Q | E2: NUMERO REG. 1°Q | F2: VALOR 2° Q | G2: NUMERO REG. 2°Q
C3: 1 | D3: 0 | E3: 0 | F3: 0 | G3: 0
C4: 2 | D4: 0 | E4: 0 | F4: 0 | G4: 0
C5: 3 | D5: 0 | E5: 0 | F5: 0 | G5: 0
C6: 4 | D6: 0 | E6: 0 | F6: 0 | G6: 0
C7: 5 | D7: 0 | E7: 0 | F7: 0 | G7: 0
C8: X
D9: 0 | E9: 0 | F9: 0 | G9: 0
C11: ASE | D11: VALOR 1° Q | E11: NUMERO REG. 1°Q | F11: VALOR 2° Q | G11: NUMERO REG. 2°Q
B12: EAAB - Prestador | C12: 1 | D12: 0 | E12: 0 | F12: 0 | G12: 0
C13: 2 | D13: 0 | E13: 0 | F13: 0 | G13: 0
C14: 3 | D14: 0 | E14: 0 | F14: 0 | G14: 0
C15: 4 | D15: 0 | E15: 0 | F15: 0 | G15: 0
C16: 5 | D16: 0 | E16: 0 | F16: 0 | G16: 0
C17: X
D18: 0 | E18: 0 | F18: 0 | G18: 0
C20: ASE | D20: VALOR 1° Q | E20: NUMERO REG. 1°Q | F20: VALOR 2° Q | G20: NUMERO REG. 2°Q | I20: VALOR TOTAL MES | J20: NUMERO REGISTROS MES
B21: TOTAL | C21: 1 | D21: 0 | E21: 0 | F21: 0 | G21: 0 | I21: 0 | J21: 0
C22: 2 | D22: 0 | E22: 0 | F22: 0 | G22: 0 | I22: 0 | J22: 0
C23: 3 | D23: 0 | E23: 0 | F23: 0 | G23: 0 | I23: 0 | J23: 0
C24: 4 | D24: 0 | E24: 0 | F24: 0 | G24: 0 | I24: 0 | J24: 0
C25: 5 | D25: 0 | E25: 0 | F25: 0 | G25: 0 | I25: 0 | J25: 0
C26: X | I26: 0 | J26: 0
D27: 0 | E27: 0 | F27: 0 | G27: 0 | I27: 0 | J27: 0
B31: OPORTUNO | D31: =D9=SUM(D3:D8) -> TRUE | E31: =E9=SUM(E3:E8) -> TRUE | F31: =F9=SUM(F3:F8) -> TRUE | G31: =G9=SUM(G3:G8) -> TRUE
B33: EXTEMP. | D33: =D18=SUM(D12:D17) -> TRUE | E33: =E18=SUM(E12:E17) -> TRUE | F33: =F18=SUM(F12:F17) -> TRUE | G33: =G18=SUM(G12:G17) -> TRUE
B35: TOTAL | D35: =D27=SUM(D21:D26) -> TRUE | E35: =E27=SUM(E21:E26) -> TRUE | F35: =F27=SUM(F21:F26) -> TRUE | G35: =G27=SUM(G21:G26) -> TRUE | I35: =I27=SUM(I21:I26) -> TRUE | J35: =J27=SUM(J21:J26) -> TRUE

Sheet Recaudo Directa Occidente
B2: OPORTUNO | C2: ASE | D2: VALOR 1° Q | E2: NUMERO REG. 1°Q | F2: VALOR 2° Q | G2: NUMERO REG. 2°Q
C3: 1 | D3: 442776725 | E3: 1586 | F3: 708118766 | G3: 2516
C4: 2 | D4: 658758009 | E4: 3480 | F4: 2044964380 | G4: 10424
C5: 3 | D5: 509207119 | E5: 1312 | F5: 799641564 | G5: 2133
C6: 4 | D6: 398329749 | E6: 2523 | F6: 769620840 | G6: 4462
C7: 5 | D7: 111642450 | E7: 858 | F7: 305626540 | G7: 1484
C8: X | D8: 0 | E8: 0 | F8: 0 | G8: 0
D9: 2120714052 | E9: 9759 | F9: 4627972090 | G9: 21019
C11: ASE | D11: VALOR 1° Q | E11: NUMERO REG. 1°Q | F11: VALOR 2° Q | G11: NUMERO REG. 2°Q
B12: EXTEMP. | C12: 1 | D12: 54415194 | E12: 118 | F12: 202466152 | G12: 535
C13: 2 | D13: 107206036 | E13: 95 | F13: 341841786 | G13: 623
C14: 3 | D14: 37034630 | E14: 34 | F14: 469277064 | G14: 248
C15: 4 | D15: 18558870 | E15: 30 | F15: 208355087 | G15: 216
C16: 5 | D16: 6082405 | E16: 9 | F16: 35584035 | G16: 152
C17: X | D17: 0 | E17: 0 | F17: 0 | G17: 0
D18: 223297135 | E18: 286 | F18: 1257524124 | G18: 1774
C20: ASE | D20: VALOR 1° Q | E20: NUMERO REG. 1°Q | F20: VALOR 2° Q | G20: NUMERO REG. 2°Q | I20: VALOR TOTAL MES | J20: NUMERO REGISTROS MES
B21: TOTAL | C21: 1 | D21: 497191919 | E21: 1704 | F21: 910584918 | G21: 3051 | I21: 1407776837 | J21: 4755
C22: 2 | D22: 765964045 | E22: 3575 | F22: 2386806166 | G22: 11047 | I22: 3152770211 | J22: 14622
C23: 3 | D23: 546241749 | E23: 1346 | F23: 1268918628 | G23: 2381 | I23: 1815160377 | J23: 3727
C24: 4 | D24: 416888619 | E24: 2553 | F24: 977975927 | G24: 4678 | I24: 1394864546 | J24: 7231
C25: 5 | D25: 117724855 | E25: 867 | F25: 341210575 | G25: 1636 | I25: 458935430 | J25: 2503
C26: X | D26: 0 | E26: 0 | F26: 0 | G26: 0 | I26: 0 | J26: 0
D27: 2344011187 | E27: 10045 | F27: 5885496214 | G27: 22793 | I27: 8229507401 | J27: 32838
B31: OPORTUNO | D31: =D9=SUM(D3:D8) -> TRUE | E31: =E9=SUM(E3:E8) -> TRUE | F31: =F9=SUM(F3:F8) -> TRUE | G31: =G9=SUM(G3:G8) -> TRUE
B33: EXTEMP. | D33: =D18=SUM(D12:D17) -> TRUE | E33: =E18=SUM(E12:E17) -> TRUE | F33: =F18=SUM(F12:F17) -> TRUE | G33: =G18=SUM(G12:G17) -> TRUE
B35: TOTAL | D35: =D27=SUM(D21:D26) -> TRUE | E35: =E27=SUM(E21:E26) -> TRUE | F35: =F27=SUM(F21:F26) -> TRUE | G35: =G27=SUM(G21:G26) -> TRUE | I35: =I27=SUM(I21:I26) -> TRUE | J35: =J27=SUM(J21:J26) -> TRUE
E69: =C69-G17 -> 0

Sheet REPORTE RECAUDO x BANCO
C1: ENEL | D1: CIUDAD LIMPIA | E1: EAB | F1: NUEVO ESQUEMA | G1: ENERBIT | H1: OCCIDENTE | I1: Total
B2: 1-APLICADOS A FACTURACION | C2: =C13+C23+C32+C41+C51 -> 7.0945837e+10 | D2: =D13+D23+D32+D41+D51 -> 0 | E2: =E13+E23+E32+E41+E51 -> 0 | F2: =F13+F23+F32+F41+F51 -> 13713260 | G2: =G13+G23+G32+G41+G51 -> 28784210 | H2: =H13+H23+H32+H41+H51 -> 5.6325711e+09 | I2: =SUM(C2:H2) -> 7.6620906e+10
B3: 2-SALDOS A FAVOR GENERADOS | C3: =C14+C24+C33+C42+C52 -> 1.7614089e+08 | D3: =D14+D24+D33+D42+D52 -> 0 | E3: =E14+E24+E33+E42+E52 -> 0 | F3: =F14+F24+F33+F42+F52 -> 14192310 | G3: =G14+G24+G33+G42+G52 -> 3772410 | H3: =H14+H24+H33+H42+H52 -> 2.2579423e+08 | I3: =SUM(C3:H3) -> 4.1989984e+08
B4: 3-APLICADOS A FINANCIACIONES NUEVAS | C4: =C15+C25+C34+C43+C53 -> 0 | D4: =D15+D25+D34+D43+D53 -> 0 | E4: =E15+E25+E34+E43+E53 -> 0 | F4: =F15+F25+F34+F43+F53 -> 0 | G4: =G15+G25+G34+G43+G53 -> 0 | H4: =H15+H25+H34+H43+H53 -> 27130908 | I4: =SUM(C4:H4) -> 27130908
B5: 7-APLICADOS A RECIBOS SERVICIOS ESPECIALES | C5: =C16+C26+C35+C44+C54 -> 0 | D5: =D16+D26+D35+D44+D54 -> 0 | E5: =E16+E26+E35+E44+E54 -> 0 | F5: =F16+F26+F35+F44+F54 -> 0 | G5: =G16+G26+G35+G44+G54 -> 0 | H5: =H16+H26+H35+H44+H54 -> 0 | I5: =SUM(C5:H5) -> 0
B6: Total | C6: =SUM(C2:C5) -> 71121977964 | D6: =SUM(D2:D5) -> 0 | E6: =SUM(E2:E5) -> 0 | F6: =SUM(F2:F5) -> 27905570 | G6: =SUM(G2:G5) -> 32556620 | H6: =SUM(H2:H5) -> 5.8854962e+09 | I6: =SUM(I2:I5) -> 77067936368
C7: =C6=(C17+C27+C36+C45+C55) -> TRUE | D7: =D6=(D17+D27+D36+D45+D55) -> TRUE | E7: =E6=(E17+E27+E36+E45+E55) -> TRUE | F7: =F6=(F17+F27+F36+F45+F55) -> TRUE | H7: =H6=(H17+H27+H36+H45+H55) -> TRUE | I7: =I6=(I17+I27+I36+I45+I55) -> TRUE
B10: ASE 1
B11: Resumen Recaudo Aplicado Por Servicio
C12: ENEL | D12: CIUDAD LIMPIA | E12: EAB | F12: NUEVO ESQUEMA | G12: ENERBIT | H12: OCCIDENTE | I12: Total
B13: 1-APLICADOS A FACTURACION | C13: 17445127414 | H13: 878866230 | I13: =SUM(C13:H13) -> 18323993644 | J13: =SUM(C13:H13)=I13 -> TRUE
B14: 2-SALDOS A FAVOR GENERADOS | C14: 40340694 | H14: 20016520 | I14: =SUM(C14:H14) -> 60357214 | J14: =SUM(C14:H14)=I14 -> TRUE
B15: 3-APLICADOS A FINANCIACIONES NUEVAS | C15: 0 | H15: 11702168 | I15: =SUM(C15:H15) -> 11702168 | J15: =SUM(C15:H15)=I15 -> TRUE
B16: 7-APLICADOS A RECIBOS SERVICIOS ESPECIALES | C16: 0 | I16: =SUM(C16:H16) -> 0 | J16: =SUM(C16:H16)=I16 -> TRUE
B17: Total | C17: =SUM(C13:C16) -> 17485468108 | D17: =SUM(D13:D16) -> 0 | E17: =SUM(E13:E16) -> 0 | F17: =SUM(F13:F16) -> 0 | G17: =SUM(G13:G16) -> 0 | H17: =SUM(H13:H16) -> 910584918 | I17: =SUM(I13:I16) -> 18396053026 | J17: =SUM(C17:H17)=I17 -> TRUE
B20: ASE 2
B21: Resumen Recaudo Aplicado Por Servicio
C22: ENEL | D22: CIUDAD LIMPIA | E22: EAB | F22: NUEVO ESQUEMA | G22: ENERBIT | H22: OCCIDENTE | I22: Total
B23: 1-APLICADOS A FACTURACION | C23: 1.9260091e+10 | E23: 0 | F23: 9350210 | H23: 2260522795 | I23: =SUM(C23:H23) -> 2.1529964e+10 | J23: =SUM(C23:H23)=I23 -> TRUE
B24: 2-SALDOS A FAVOR GENERADOS | C24: 53772356 | E24: 0 | F24: 9710980 | H24: 126283371 | I24: =SUM(C24:H24) -> 1.8976671e+08 | J24: =SUM(C24:H24)=I24 -> TRUE
B25: 3-APLICADOS A FINANCIACIONES NUEVAS | C25: 0 | E25: 0 | F25: 0 | H25: 0 | I25: =SUM(C25:H25) -> 0 | J25: =SUM(C25:H25)=I25 -> TRUE
B26: 7-APLICADOS A RECIBOS SERVICIOS ESPECIALES | F26: 0 | H26: 0 | I26: =SUM(C26:H26) -> 0 | J26: =SUM(C26:H26)=I26 -> TRUE
B27: Total | C27: =SUM(C23:C26) -> 19313863587 | D27: =SUM(D23:D26) -> 0 | E27: =SUM(E23:E26) -> 0 | F27: =SUM(F23:F26) -> 19061190 | G27: =SUM(G23:G26) -> 0 | H27: =SUM(H23:H26) -> 2386806166 | I27: =SUM(I23:I26) -> 21719730943 | J27: =SUM(C27:H27)=I27 -> TRUE
B29: ASE 3
B30: Resumen Recaudo Aplicado Por Servicio
C31: ENEL | D31: CIUDAD LIMPIA | E31: EAB | F31: NUEVO ESQUEMA | G31: ENERBIT | H31: OCCIDENTE | I31: Total
B32: 1-APLICADOS A FACTURACION | C32: 15124893786 | F32: 0 | H32: 1.2559242e+09 | I32: =SUM(C32:H32) -> 1.6380818e+10 | J32: =SUM(C32:H32)=I32 -> TRUE
B33: 2-SALDOS A FAVOR GENERADOS | C33: 20418516 | F33: 0 | H33: 10719555 | I33: =SUM(C33:H33) -> 31138071 | J33: =SUM(C33:H33)=I33 -> TRUE
B34: 3-APLICADOS A FINANCIACIONES NUEVAS | C34: 0 | F34: 0 | H34: 2274841.8 | I34: =SUM(C34:H34) -> 2274841.8 | J34: =SUM(C34:H34)=I34 -> TRUE
B35: 7-APLICADOS A RECIBOS SERVICIOS ESPECIALES | C35: 0 | F35: 0 | I35: =SUM(C35:H35) -> 0 | J35: =SUM(C35:H35)=I35 -> TRUE
B36: Total | C36: =SUM(C32:C35) -> 15145312302 | D36: =SUM(D32:D35) -> 0 | E36: =SUM(E32:E35) -> 0 | F36: =SUM(F32:F35) -> 0 | G36: =SUM(G32:G35) -> 0 | H36: =SUM(H32:H35) -> 1268918628 | I36: =SUM(I32:I35) -> 16414230930 | J36: =SUM(C36:H36)=I36 -> TRUE
B38: ASE 4
B39: Resumen Recaudo Aplicado Por Servicio
C40: ENEL | D40: CIUDAD LIMPIA | E40: EAB | F40: NUEVO ESQUEMA | G40: ENERBIT | H40: OCCIDENTE | I40: Total
B41: 1-APLICADOS A FACTURACION | C41: 7358390426 | E41: 0 | F41: 4363050 | H41: 9.083621e+08 | I41: =SUM(C41:H41) -> 8.2711156e+09 | J41: =SUM(C41:H41)=I41 -> TRUE
B42: 2-SALDOS A FAVOR GENERADOS | C42: 37713515 | E42: 0 | F42: 4481330 | H42: 57223143 | I42: =SUM(C42:H42) -> 99417988 | J42: =SUM(C42:H42)=I42 -> TRUE
B43: 3-APLICADOS A FINANCIACIONES NUEVAS | C43: 0 | E43: 0 | F43: 0 | H43: 12390685 | I43: =SUM(C43:H43) -> 12390685 | J43: =SUM(C43:H43)=I43 -> TRUE
B44: 7-APLICADOS A RECIBOS SERVICIOS ESPECIALES | I44: =SUM(C44:H44) -> 0 | J44: =SUM(C44:H44)=I44 -> TRUE
B45: Total | C45: =SUM(C41:C44) -> 7396103941 | D45: =SUM(D41:D44) -> 0 | E45: =SUM(E41:E44) -> 0 | F45: =SUM(F41:F44) -> 8844380 | G45: =SUM(G41:G44) -> 0 | H45: =SUM(H41:H44) -> 977975927 | I45: =SUM(I41:I44) -> 8382924248 | J45: =SUM(C45:H45)=I45 -> TRUE
B48: ASE 5
B49: Resumen Recaudo Aplicado Por Servicio
C50: ENEL | D50: CIUDAD LIMPIA | E50: EAB | F50: NUEVO ESQUEMA | G50: ENERBIT | H50: OCCIDENTE | I50: Total
B51: 1-APLICADOS A FACTURACION | C51: 11757334219 | G51: 28784210 | H51: 3.2889572e+08 | I51: =SUM(C51:H51) -> 1.2115014e+10 | J51: =SUM(C51:H51)=I51 -> TRUE
B52: 2-SALDOS A FAVOR GENERADOS | C52: 23895807 | G52: 3772410 | H52: 11551639 | I52: =SUM(C52:H52) -> 39219856 | J52: =SUM(C52:H52)=I52 -> TRUE
B53: 3-APLICADOS A FINANCIACIONES NUEVAS | C53: 0 | G53: 0 | H53: 763212.95 | I53: =SUM(C53:H53) -> 763212.95 | J53: =SUM(C53:H53)=I53 -> TRUE
B54: 7-APLICADOS A RECIBOS SERVICIOS ESPECIALES | C54: 0 | I54: =SUM(C54:H54) -> 0 | J54: =SUM(C54:H54)=I54 -> TRUE
B55: Total | C55: =SUM(C51:C54) -> 11781230026 | D55: =SUM(D51:D54) -> 0 | E55: =SUM(E51:E54) -> 0 | F55: =SUM(F51:F54) -> 0 | G55: =SUM(G51:G54) -> 32556620 | H55: =SUM(H51:H54) -> 341210575 | I55: =SUM(I51:I54) -> 12154997221 | J55: =SUM(C55:H55)=I55 -> TRUE
B59: QUINCENA | C59: 2 | D59: OJO/// DILIGENCIAR
B62: Recaudo ENEL - ASE 1 | C62: =IF($C$59=1,'Recaudo ENEL'!D21,'Recaudo ENEL'!F21) -> 17485468108 | D62: =C17=C62 -> TRUE | E62: =C17-C62 -> 0
B63: Recaudo ENERBIT - ASE 1 | C63: =IF($C$59=1,'Recaudo ENERBIT'!D21,'Recaudo ENERBIT'!F21) -> 0 | D63: =G17=C63 -> TRUE | E63: =G17-C63 -> 0
B64: Recaudo Reciprocidad EAAB - ASE 2 | C64: =IF($C$59=1,'Recaudo EAAB Reciprocidad'!D22,'Recaudo EAAB Reciprocidad'!F22) -> 19061190 | D64: =F27=C64 -> TRUE | E64: =F27-C64 -> 0
B65: Recaudo ENEL - ASE 2 | C65: =IF($C$59=1,'Recaudo ENEL'!D22,'Recaudo ENEL'!F22) -> 19312203807 | D65: =C27=C65 -> FALSE | E65: =C27-C65 -> 1659780 | F65: OK
B66: Recaudo ENERBIT - ASE 2 | C66: =IF($C$59=1,'Recaudo ENERBIT'!D22,'Recaudo ENERBIT'!F22) -> 0 | D66: =G27=C66 -> TRUE | E66: =G27-C66 -> 0
B67: Recaudo ENEL - ASE 3 | C67: =IF($C$59=1,'Recaudo ENEL'!D23,'Recaudo ENEL'!F23) -> 15144539722 | D67: =C36=C67 -> FALSE | E67: =C36-C67 -> 772580 | F67: OK
B68: Recaudo ENERBIT - ASE 3 | C68: =IF($C$59=1,'Recaudo ENERBIT'!D23,'Recaudo ENERBIT'!F23) -> 0 | D68: =G36=C68 -> TRUE | E68: =G36-C68 -> 0
B69: Recaudo Reciprocidad EAAB - ASE 4 | C69: =IF($C$59=1,'Recaudo EAAB Reciprocidad'!D24,'Recaudo EAAB Reciprocidad'!F24) -> 8844380 | D69: =F45=C69 -> TRUE | E69: =F45-C69 -> 0
B70: Recaudo ENEL - ASE 4 | C70: =IF($C$59=1,'Recaudo ENEL'!D24,'Recaudo ENEL'!F24) -> 7395670681 | D70: =C45=C70 -> FALSE | E70: =C45-C70 -> 433260 | F70: OK
B71: Recaudo ENERBIT - ASE 4 | C71: =IF($C$59=1,'Recaudo ENERBIT'!D24,'Recaudo ENERBIT'!F24) -> 0 | D71: =G45=C71 -> TRUE | E71: =G45-C71 -> 0
B72: Recaudo ENEL - ASE 5 | C72: =IF($C$59=1,'Recaudo ENEL'!D25,'Recaudo ENEL'!F25) -> 11780722576 | D72: =C55=C72 -> FALSE | E72: =C55-C72 -> 507450 | F72: OK
B73: Recaudo ENERBIT - ASE 5 | C73: =IF($C$59=1,'Recaudo ENERBIT'!D25,'Recaudo ENERBIT'!F25) -> 32556620 | D73: =G55=C73 -> TRUE | E73: =G55-C73 -> 0
B75: Recaudo Banco Occidente ASE 1 | C75: =IF($C$59=1,'Recaudo Directa Occidente'!D21,'Recaudo Directa Occidente'!F21) -> 910584918 | D75: =C75=H17 -> TRUE | E75: =C75-H17 -> 0
B76: Recaudo Banco Occidente ASE 2 | C76: =IF($C$59=1,'Recaudo Directa Occidente'!D22,'Recaudo Directa Occidente'!F22) -> 2386806166 | D76: =C76=H27 -> TRUE | E76: =C76-H27 -> 0
B77: Recaudo Banco Occidente ASE 3 | C77: =IF($C$59=1,'Recaudo Directa Occidente'!D23,'Recaudo Directa Occidente'!F23) -> 1268918628 | D77: =C77=H36 -> TRUE | E77: =C77-H36 -> 0
B78: Recaudo Banco Occidente ASE 4 | C78: =IF($C$59=1,'Recaudo Directa Occidente'!D24,'Recaudo Directa Occidente'!F24) -> 977975927 | D78: =C78=H45 -> TRUE | E78: =C78-H45 -> 0
B79: Recaudo Banco Occidente ASE 5 | C79: =IF($C$59=1,'Recaudo Directa Occidente'!D25,'Recaudo Directa Occidente'!F25) -> 341210575 | D79: =C79=H55 -> TRUE | E79: =C79-H55 -> 0

Sheet ANT EXT-REV
C1: ASE 1 | E1: ASE 2 | G1: ASE 3 | I1: ASE 4 | K1: ASE 5 | M1: TOTAL
C2: REPORTE 3 | D2: REPORTE 4 | E2: REPORTE 3 | F2: REPORTE 4 | G2: REPORTE 3 | H2: REPORTE 4 | I2: REPORTE 3 | J2: REPORTE 4 | K2: REPORTE 3 | L2: REPORTE 4 | M2: REPORTE 3 | N2: REPORTE 4
B3: APLICADO | C3: =C11+C19+C27+C35+C43 -> 63570 | D3: =D11+D19+D27+D35+D43 -> -73090 | E3: =E11+E19+E27+E35+E43 -> 221630 | F3: =F11+F19+F27+F35+F43 -> -13472482 | G3: =G11+G19+G27+G35+G43 -> 0 | H3: =H11+H19+H27+H35+H43 -> -4617354 | I3: =I11+I19+I27+I35+I43 -> 4030410 | J3: =J11+J19+J27+J35+J43 -> -15663330 | ... L3: =L11+L19+L27+L35+L43 -> -4011371.6 | M3: =C3+E3+G3+I3+K3 -> 5565420 | N3: =D3+F3+H3+J3+L3 -> -37837628 | P3: =N3=(-VALIDACION_TOTAL!M9) -> TRUE
B4: ANTICIPOS | C4: =C12+C20+C28+C36+C44 -> 76340 | D4: =D12+D20+D28+D36+D44 -> -66820 | E4: =E12+E20+E28+E36+E44 -> 2593540 | F4: =F12+F20+F28+F36+F44 -> -79350 | G4: =G12+G20+G28+G36+G44 -> 0 | H4: =H12+H20+H28+H36+H44 -> 0 | I4: =I12+I20+I28+I36+I44 -> 8227070 | J4: =J12+J20+J28+J36+J44 -> -36570 | ... L4: =L12+L20+L28+L36+L44 -> -1057608.4 | M4: =C4+E4+G4+I4+K4 -> 13195560 | N4: =D4+F4+H4+J4+L4 -> -1240348.4 | P4: =N4=(-'CONSOLIDADO_TOTAL RECAUDO'!L131) -> TRUE
B5: TOTAL | C5: =SUM(C3:C4) -> 139910 | D5: =SUM(D3:D4) -> -139910 | E5: =SUM(E3:E4) -> 2815170 | F5: =SUM(F3:F4) -> -13551832 | G5: =SUM(G3:G4) -> 0 | H5: =SUM(H3:H4) -> -4617354 | I5: =SUM(I3:I4) -> 12257480 | J5: =SUM(J3:J4) -> -15699900 | ... N5: =SUM(N3:N4) -> -39077976
C6: =C5=(C13+C21+C29+C37+C45) -> TRUE | D6: =D5=(D13+D21+D29+D37+D45) -> TRUE | E6: =E5=(E13+E21+E29+E37+E45) -> TRUE | F6: =F5=(F13+F21+F29+F37+F45) -> TRUE | G6: =G5=(G13+G21+G29+G37+G45) -> TRUE | H6: =H5=(H13+H21+H29+H37+H45) -> TRUE | I6: =I5=(I13+I21+I29+I37+I45) -> TRUE | J6: =J5=(J13+J21+J29+J37+J45) -> TRUE | ... N6: =N5=(N13+N21+N29+N37+N45) -> TRUE
B8: BANCO DE OCCIDENTE
C9: ASE 1 | E9: ASE 2 | G9: ASE 3 | I9: ASE 4 | K9: ASE 5 | M9: TOTAL
C10: REPORTE 3 | D10: REPORTE 4 | E10: REPORTE 3 | F10: REPORTE 4 | G10: REPORTE 3 | H10: REPORTE 4 | I10: REPORTE 3 | J10: REPORTE 4 | K10: REPORTE 3 | L10: REPORTE 4 | M10: REPORTE 3 | N10: REPORTE 4
B11: APLICADO | C11: 0 | D11: 0 | E11: 24890 | F11: -24890 | G11: 0 | H11: 0 | I11: 154832 | J11: -474944 | K11: 1249810 | L11: -2556821.6 | M11: =C11+E11+G11+I11+K11 -> 1429532 | N11: =D11+F11+H11+J11+L11 -> -3056655.6
B12: ANTICIPOS | C12: 0 | D12: 0 | E12: 0 | F12: 0 | G12: 0 | H12: 0 | I12: 320112 | J12: 0 | K12: 2298610 | L12: -1057608.4 | M12: =C12+E12+G12+I12+K12 -> 2618722 | N12: =D12+F12+H12+J12+L12 -> -1057608.4
B13: TOTAL | C13: =SUM(C11:C12) -> 0 | D13: =SUM(D11:D12) -> 0 | E13: =SUM(E11:E12) -> 24890 | F13: =SUM(F11:F12) -> -24890 | G13: =SUM(G11:G12) -> 0 | H13: =SUM(H11:H12) -> 0 | I13: =SUM(I11:I12) -> 474944 | J13: =SUM(J11:J12) -> -474944 | ... N13: =SUM(N11:N12) -> -4114264
B16: EAAB RECIPROCIDAD
C17: ASE 1 | E17: ASE 2 | G17: ASE 3 | I17: ASE 4 | K17: ASE 5 | M17: TOTAL
C18: REPORTE 3 | D18: REPORTE 4 | E18: REPORTE 3 | F18: REPORTE 4 | G18: REPORTE 3 | H18: REPORTE 4 | I18: REPORTE 3 | J18: REPORTE 4 | K18: REPORTE 3 | L18: REPORTE 4 | M18: REPORTE 3 | N18: REPORTE 4
B19: APLICADO | C19: 0 | D19: 0 | E19: 0 | F19: 0 | G19: 0 | H19: 0 | I19: 232870 | J19: -549540 | K19: 0 | L19: 0 | M19: =C19+E19+G19+I19+K19 -> 232870 | N19: =D19+F19+H19+J19+L19 -> -549540
B20: ANTICIPOS | C20: 0 | D20: 0 | E20: 0 | F20: 0 | G20: 0 | H20: 0 | I20: 316670 | J20: 0 | K20: 0 | L20: 0 | M20: =C20+E20+G20+I20+K20 -> 316670 | N20: =D20+F20+H20+J20+L20 -> 0
B21: TOTAL | C21: =SUM(C19:C20) -> 0 | D21: =SUM(D19:D20) -> 0 | E21: =SUM(E19:E20) -> 0 | F21: =SUM(F19:F20) -> 0 | G21: =SUM(G19:G20) -> 0 | H21: =SUM(H19:H20) -> 0 | I21: =SUM(I19:I20) -> 549540 | J21: =SUM(J19:J20) -> -549540 | ... L21: =SUM(L19:L20) -> 0 | M21: =C21+E21+G21+I21+K21 -> 549540 | N21: =SUM(N19:N20) -> -549540
B24: EAAB CIUDAD LIMPIA
C25: ASE 1 | E25: ASE 2 | G25: ASE 3 | I25: ASE 4 | K25: ASE 5 | M25: TOTAL
C26: REPORTE 3 | D26: REPORTE 4 | E26: REPORTE 3 | F26: REPORTE 4 | G26: REPORTE 3 | H26: REPORTE 4 | I26: REPORTE 3 | J26: REPORTE 4 | K26: REPORTE 3 | L26: REPORTE 4 | M26: REPORTE 3 | N26: REPORTE 4
B27: APLICADO | C27: 0 | D27: 0 | E27: 0 | F27: 0 | G27: 0 | H27: 0 | I27: 0 | J27: 0 | K27: 0 | L27: 0 | M27: =C27+E27+G27+I27+K27 -> 0 | N27: =D27+F27+H27+J27+L27 -> 0
B28: ANTICIPOS | C28: 0 | D28: 0 | E28: 0 | F28: 0 | G28: 0 | H28: 0 | I28: 0 | J28: 0 | K28: 0 | L28: 0 | M28: =C28+E28+G28+I28+K28 -> 0 | N28: =D28+F28+H28+J28+L28 -> 0
B29: TOTAL | C29: =SUM(C27:C28) -> 0 | D29: =SUM(D27:D28) -> 0 | E29: =SUM(E27:E28) -> 0 | F29: =SUM(F27:F28) -> 0 | G29: =SUM(G27:G28) -> 0 | H29: =SUM(H27:H28) -> 0 | I29: =SUM(I27:I28) -> 0 | J29: =SUM(J27:J28) -> 0 | ... N29: =SUM(N27:N28) -> 0
B32: ENEL
C33: ASE 1 | E33: ASE 2 | G33: ASE 3 | I33: ASE 4 | K33: ASE 5 | M33: TOTAL
C34: REPORTE 3 | D34: REPORTE 4 | E34: REPORTE 3 | F34: REPORTE 4 | G34: REPORTE 3 | H34: REPORTE 4 | I34: REPORTE 3 | J34: REPORTE 4 | K34: REPORTE 3 | L34: REPORTE 4 | M34: REPORTE 3 | N34: REPORTE 4
B35: APLICADO | C35: 63570 | D35: -73090 | E35: 196740 | F35: -13447592 | G35: 0 | H35: -4617354 | I35: 3642708 | J35: -14638846 | K35: 0 | L35: -1454550 | M35: =C35+E35+G35+I35+K35 -> 3903018 | N35: =D35+F35+H35+J35+L35 -> -34231432
B36: ANTICIPOS | C36: 76340 | D36: -66820 | E36: 2593540 | F36: -79350 | G36: 0 | H36: 0 | I36: 7590288 | J36: -36570 | K36: 0 | L36: 0 | M36: =C36+E36+G36+I36+K36 -> 10260168 | N36: =D36+F36+H36+J36+L36 -> -182740
B37: TOTAL | C37: =SUM(C35:C36) -> 139910 | D37: =SUM(D35:D36) -> -139910 | E37: =SUM(E35:E36) -> 2790280 | F37: =SUM(F35:F36) -> -13526942 | G37: =SUM(G35:G36) -> 0 | H37: =SUM(H35:H36) -> -4617354 | I37: =SUM(I35:I36) -> 11232996 | J37: =SUM(J35:J36) -> -14675416 | ... N37: =SUM(N35:N36) -> -34414172
B40: ENERBIT
C41: ASE 1 | E41: ASE 2 | G41: ASE 3 | I41: ASE 4 | K41: ASE 5 | M41: TOTAL
C42: REPORTE 3 | D42: REPORTE 4 | E42: REPORTE 3 | F42: REPORTE 4 | G42: REPORTE 3 | H42: REPORTE 4 | I42: REPORTE 3 | J42: REPORTE 4 | K42: REPORTE 3 | L42: REPORTE 4 | M42: REPORTE 3 | N42: REPORTE 4
B43: APLICADO | C43: 0 | D43: 0 | E43: 0 | F43: 0 | G43: 0 | H43: 0 | I43: 0 | J43: 0 | K43: 0 | L43: 0 | M43: =C43+E43+G43+I43+K43 -> 0 | N43: =D43+F43+H43+J43+L43 -> 0
B44: ANTICIPOS | C44: 0 | D44: 0 | E44: 0 | F44: 0 | G44: 0 | H44: 0 | I44: 0 | J44: 0 | K44: 0 | L44: 0 | M44: =C44+E44+G44+I44+K44 -> 0 | N44: =D44+F44+H44+J44+L44 -> 0
B45: TOTAL | C45: =SUM(C43:C44) -> 0 | D45: =SUM(D43:D44) -> 0 | E45: =SUM(E43:E44) -> 0 | F45: =SUM(F43:F44) -> 0 | G45: =SUM(G43:G44) -> 0 | H45: =SUM(H43:H44) -> 0 | I45: =SUM(I43:I44) -> 0 | J45: =SUM(J43:J44) -> 0 | ... N45: =SUM(N43:N44) -> 0

Sheet ANTICIPOS USUARIOS
B1: TOTAL | E1: RECIPRCIDAD | H1: ENEL | K1: ENERBIT | N1: OCCIDENTE | Q1: EAAB-CIUDADLIMPIA
B2: ASE | C2: ANTICIPOS GENERADOS POR PAGO | E2: ASE | F2: ANTICIPOS GENERADOS POR PAGO | H2: ASE | I2: ANTICIPOS GENERADOS POR PAGO | K2: ASE | L2: ANTICIPOS GENERADOS POR PAGO | N2: ASE | O2: ANTICIPOS GENERADOS POR PAGO | Q2: ASE | R2: ANTICIPOS GENERADOS POR PAGO | T2: Anticipos generados por pago
B3: 1 | C3: ='REPORTE RECAUDO x BANCO'!I14 -> 60357214 | E3: 1 | F3: ='REPORTE RECAUDO x BANCO'!F14 -> 0 | H3: 1 | I3: ='REPORTE RECAUDO x BANCO'!C14 -> 40340694 | K3: 1 | L3: ='REPORTE RECAUDO x BANCO'!G14 -> 0 | N3: 1 | O3: ='REPORTE RECAUDO x BANCO'!H14 -> 20016520 | Q3: 1 | R3: ='REPORTE RECAUDO x BANCO'!D14+'REPORTE RECAUDO x BANCO'!E14 -> 0 | T3: Sale del reporte Recaudo por Bancos.
B4: 2 | C4: ='REPORTE RECAUDO x BANCO'!I24 -> 1.8976671e+08 | E4: 2 | F4: ='REPORTE RECAUDO x BANCO'!F24 -> 9710980 | H4: 2 | I4: ='REPORTE RECAUDO x BANCO'!C24 -> 53772356 | K4: 2 | L4: ='REPORTE RECAUDO x BANCO'!G24 -> 0 | N4: 2 | O4: ='REPORTE RECAUDO x BANCO'!H24 -> 126283371 | Q4: 2 | R4: ='REPORTE RECAUDO x BANCO'!D24+'REPORTE RECAUDO x BANCO'!E24 -> 0
B5: 3 | C5: ='REPORTE RECAUDO x BANCO'!I33 -> 31138071 | E5: 3 | F5: ='REPORTE RECAUDO x BANCO'!F33 -> 0 | H5: 3 | I5: ='REPORTE RECAUDO x BANCO'!C33 -> 20418516 | K5: 3 | L5: ='REPORTE RECAUDO x BANCO'!G33 -> 0 | N5: 3 | O5: ='REPORTE RECAUDO x BANCO'!H33 -> 10719555 | Q5: 3 | R5: ='REPORTE RECAUDO x BANCO'!D33+'REPORTE RECAUDO x BANCO'!E33 -> 0
B6: 4 | C6: ='REPORTE RECAUDO x BANCO'!I42 -> 99417988 | E6: 4 | F6: ='REPORTE RECAUDO x BANCO'!F42 -> 4481330 | H6: 4 | I6: ='REPORTE RECAUDO x BANCO'!C42 -> 37713515 | K6: 4 | L6: ='REPORTE RECAUDO x BANCO'!G42 -> 0 | N6: 4 | O6: ='REPORTE RECAUDO x BANCO'!H42 -> 57223143 | Q6: 4 | R6: ='REPORTE RECAUDO x BANCO'!D42+'REPORTE RECAUDO x BANCO'!E42 -> 0
B7: 5 | C7: ='REPORTE RECAUDO x BANCO'!I52 -> 39219856 | E7: 5 | F7: ='REPORTE RECAUDO x BANCO'!F52 -> 0 | H7: 5 | I7: ='REPORTE RECAUDO x BANCO'!C52 -> 23895807 | K7: 5 | L7: ='REPORTE RECAUDO x BANCO'!G52 -> 3772410 | N7: 5 | O7: ='REPORTE RECAUDO x BANCO'!H52 -> 11551639 | Q7: 5 | R7: ='REPORTE RECAUDO x BANCO'!D52+'REPORTE RECAUDO x BANCO'!E52 -> 0
C8: =SUM(C3:C7) -> 4.1989984e+08 | F8: =SUM(F3:F7) -> 14192310 | I8: =SUM(I3:I7) -> 1.7614089e+08 | L8: =SUM(L3:L7) -> 3772410 | O8: =SUM(O3:O7) -> 2.2579423e+08 | R8: =SUM(R3:R7) -> 0
C9: =C8='REPORTE RECAUDO x BANCO'!I3 -> TRUE | F9: =F8='REPORTE RECAUDO x BANCO'!F3 -> TRUE | I9: =I8='REPORTE RECAUDO x BANCO'!C3 -> TRUE | L9: =L8='REPORTE RECAUDO x BANCO'!G3 -> TRUE | O9: =O8='REPORTE RECAUDO x BANCO'!H3 -> TRUE | R9: =R8='REPORTE RECAUDO x BANCO'!D3+'REPORTE RECAUDO x BANCO'!E3 -> TRUE
B11: ASE | C11: ANTICIPOS GENERADOS POR EXTEMPORANEOS | E11: ASE | F11: ANTICIPOS GENERADOS POR EXTEMPORANEOS | H11: ASE | I11: ANTICIPOS GENERADOS POR EXTEMPORANEOS | K11: ASE | L11: ANTICIPOS GENERADOS POR EXTEMPORANEOS | N11: ASE | O11: ANTICIPOS GENERADOS POR EXTEMPORANEOS | Q11: ASE | R11: ANTICIPOS GENERADOS POR EXTEMPORANEOS | T11: Anticipos generados por pagos aplicados de reversiones
B12: 1 | C12: ='ANT EXT-REV'!C4 -> 76340 | E12: 1 | F12: ='ANT EXT-REV'!C20 -> 0 | H12: 1 | I12: ='ANT EXT-REV'!C36 -> 76340 | K12: 1 | L12: ='ANT EXT-REV'!C44 -> 0 | N12: 1 | O12: ='ANT EXT-REV'!C12 -> 0 | Q12: 1 | R12: ='ANT EXT-REV'!C28 -> 0 | T12: Sale del reporte Recaudo reversado
B13: 2 | C13: ='ANT EXT-REV'!E4 -> 2593540 | E13: 2 | F13: ='ANT EXT-REV'!E20 -> 0 | H13: 2 | I13: ='ANT EXT-REV'!E36 -> 2593540 | K13: 2 | L13: ='ANT EXT-REV'!E44 -> 0 | N13: 2 | O13: ='ANT EXT-REV'!E12 -> 0 | Q13: 2 | R13: ='ANT EXT-REV'!E28 -> 0
B14: 3 | C14: ='ANT EXT-REV'!G4 -> 0 | E14: 3 | F14: ='ANT EXT-REV'!G20 -> 0 | H14: 3 | I14: ='ANT EXT-REV'!G36 -> 0 | K14: 3 | L14: ='ANT EXT-REV'!G44 -> 0 | N14: 3 | O14: ='ANT EXT-REV'!G12 -> 0 | Q14: 3 | R14: ='ANT EXT-REV'!G28 -> 0
B15: 4 | C15: ='ANT EXT-REV'!I4 -> 8227070 | E15: 4 | F15: ='ANT EXT-REV'!I20 -> 316670 | H15: 4 | I15: ='ANT EXT-REV'!I36 -> 7590288 | K15: 4 | L15: ='ANT EXT-REV'!I44 -> 0 | N15: 4 | O15: ='ANT EXT-REV'!I12 -> 320112 | Q15: 4 | R15: ='ANT EXT-REV'!I28 -> 0
B16: 5 | C16: ='ANT EXT-REV'!K4 -> 2298610 | E16: 5 | F16: ='ANT EXT-REV'!K20 -> 0 | H16: 5 | I16: ='ANT EXT-REV'!K36 -> 0 | K16: 5 | L16: ='ANT EXT-REV'!K44 -> 0 | N16: 5 | O16: ='ANT EXT-REV'!K12 -> 2298610 | Q16: 5 | R16: ='ANT EXT-REV'!K28 -> 0
C17: =SUM(C12:C16) -> 13195560 | F17: =SUM(F12:F16) -> 316670 | I17: =SUM(I12:I16) -> 10260168 | L17: =SUM(L12:L16) -> 0 | O17: =SUM(O12:O16) -> 2618722 | R17: =SUM(R12:R16) -> 0
C18: =C17='ANT EXT-REV'!M4 -> TRUE | F18: =F17='ANT EXT-REV'!M20 -> TRUE | I18: =I17='ANT EXT-REV'!M36 -> TRUE | L18: =L17='ANT EXT-REV'!M44 -> TRUE | O18: =O17='ANT EXT-REV'!M12 -> TRUE | R18: =R17='ANT EXT-REV'!M28 -> TRUE
B20: ASE | C20: ANTICIPOS QUE CARGAN POR REVERSIONES | E20: ASE | F20: ANTICIPOS QUE CARGAN POR REVERSIONES | H20: ASE | I20: ANTICIPOS QUE CARGAN POR REVERSIONES | K20: ASE | L20: ANTICIPOS QUE CARGAN POR REVERSIONES | N20: ASE | O20: ANTICIPOS QUE CARGAN POR REVERSIONES | Q20: ASE | R20: ANTICIPOS QUE CARGAN POR REVERSIONES | T20: Anticipos que cargan de reversiones
B21: 1 | C21: ='ANT EXT-REV'!D4 -> -66820 | E21: 1 | F21: ='ANT EXT-REV'!D20 -> 0 | H21: 1 | I21: ='ANT EXT-REV'!D36 -> -66820 | K21: 1 | L21: ='ANT EXT-REV'!D44 -> 0 | N21: 1 | O21: ='ANT EXT-REV'!D12 -> 0 | Q21: 1 | R21: ='ANT EXT-REV'!D28 -> 0 | T21: Sale del reporte Recaudo reversado
B22: 2 | C22: ='ANT EXT-REV'!F4 -> -79350 | E22: 2 | F22: ='ANT EXT-REV'!F20 -> 0 | H22: 2 | I22: ='ANT EXT-REV'!F36 -> -79350 | K22: 2 | L22: ='ANT EXT-REV'!F44 -> 0 | N22: 2 | O22: ='ANT EXT-REV'!F12 -> 0 | Q22: 2 | R22: ='ANT EXT-REV'!F28 -> 0
B23: 3 | C23: ='ANT EXT-REV'!H4 -> 0 | E23: 3 | F23: ='ANT EXT-REV'!H20 -> 0 | H23: 3 | I23: ='ANT EXT-REV'!H36 -> 0 | K23: 3 | L23: ='ANT EXT-REV'!H44 -> 0 | N23: 3 | O23: ='ANT EXT-REV'!H12 -> 0 | Q23: 3 | R23: ='ANT EXT-REV'!H28 -> 0
B24: 4 | C24: ='ANT EXT-REV'!J4 -> -36570 | E24: 4 | F24: ='ANT EXT-REV'!J20 -> 0 | H24: 4 | I24: ='ANT EXT-REV'!J36 -> -36570 | K24: 4 | L24: ='ANT EXT-REV'!J44 -> 0 | N24: 4 | O24: ='ANT EXT-REV'!J12 -> 0 | Q24: 4 | R24: ='ANT EXT-REV'!J28 -> 0
B25: 5 | C25: ='ANT EXT-REV'!L4 -> -1057608.4 | E25: 5 | F25: ='ANT EXT-REV'!L20 -> 0 | H25: 5 | I25: ='ANT EXT-REV'!L36 -> 0 | K25: 5 | L25: ='ANT EXT-REV'!L44 -> 0 | N25: 5 | O25: ='ANT EXT-REV'!L12 -> -1057608.4 | Q25: 5 | R25: ='ANT EXT-REV'!L28 -> 0
C26: =SUM(C21:C25) -> -1240348.4 | F26: =SUM(F21:F25) -> 0 | I26: =SUM(I21:I25) -> -182740 | L26: =SUM(L21:L25) -> 0 | O26: =SUM(O21:O25) -> -1057608.4 | R26: =SUM(R21:R25) -> 0
C27: =C26='ANT EXT-REV'!N4 -> TRUE | F27: =F26='ANT EXT-REV'!N20 -> TRUE | I27: =I26='ANT EXT-REV'!N36 -> TRUE | L27: =L26='ANT EXT-REV'!N44 -> TRUE | O27: =O26='ANT EXT-REV'!N12 -> TRUE | R27: =R26='ANT EXT-REV'!N28 -> TRUE

Sheet BCE SC POR FACT.
C2: ASE | D2: SUBSIDIO | E2: CONTRIBUCION | F2: TOTAL BSC | H2: SISTEMA
C3: 1 | D3: -6.2027284e+09 | E3: 2.5925147e+09 | F3: =D3+E3 -> -3.6102137e+09 | H3: =DetRetri2026082!J9 -> -3610213749 | I3: =F3-H3 -> -0.27000046
C4: 2 | D4: -6.6743868e+09 | E4: 2.3845105e+09 | F4: =D4+E4 -> -4.2898763e+09 | H4: =DetRetri2026082!J10 -> -4289876341 | I4: =F4-H4 -> -0.32999992
C5: 3 | D5: -2.1913894e+09 | E5: 1.3621272e+09 | F5: =D5+E5 -> -8.2926223e+08 | H5: =DetRetri2026082!J11 -> -829262233 | I5: =F5-H5 -> -0.29999995
C6: 4 | D6: -2.5841946e+09 | E6: 1.8779587e+09 | F6: =D6+E6 -> -7.0623593e+08 | H6: =DetRetri2026082!J12 -> -706235925 | I6: =F6-H6 -> -0.21000028
C7: 5 | D7: -1.237571e+09 | E7: 1.2141671e+09 | F7: =D7+E7 -> -23403941 | H7: =DetRetri2026082!J13 -> -23403941 | I7: =F7-H7 -> -0.30999994
F9: =SUM(F3:F7) -> -9.4589922e+09 | H9: =SUM(H3:H7) -> -9458992189 | I9: =F9-H9 -> -1.4200001
H10: =H9=DetRetri2026082!J14 -> TRUE
D11: =SUM(D3:D7) -> -1.889027e+10 | E11: =SUM(E3:E7) -> 9.4312781e+09 | F11: =SUM(D3:E7) -> -9.4589922e+09
F12: =ROUND(F11,2)=ROUND(F9,2) -> TRUE
F13: =ROUND(F11,2)-ROUND(F9,2) -> 0
D18: ASE | E18: REMUN TOTAL | F18: VALIDA 1 | G18: VALIDA 2 | H18: DIFERENCIA VALIDA 2
D19: 1 | E19: ='CONSOLIDADO_TOTAL RECAUDO'!J104 -> -3.6102137e+09 | F19: =E19=F3 -> TRUE | G19: =E19=H3 -> FALSE | H19: =E19-H3 -> -0.27000046
D20: 2 | E20: ='CONSOLIDADO_TOTAL RECAUDO'!J105 -> -4.2898763e+09 | F20: =E20=F4 -> TRUE | G20: =E20=H4 -> FALSE | H20: =E20-H4 -> -0.32999992
D21: 3 | E21: ='CONSOLIDADO_TOTAL RECAUDO'!J106 -> -8.2926223e+08 | F21: =E21=F5 -> TRUE | G21: =E21=H5 -> FALSE | H21: =E21-H5 -> -0.29999995
D22: 4 | E22: ='CONSOLIDADO_TOTAL RECAUDO'!J107 -> -7.0623593e+08 | F22: =E22=F6 -> TRUE | G22: =E22=H6 -> FALSE | H22: =E22-H6 -> -0.21000028
D23: 5 | E23: ='CONSOLIDADO_TOTAL RECAUDO'!J108 -> -23403941 | F23: =E23=F7 -> TRUE | G23: =E23=H7 -> FALSE | H23: =E23-H7 -> -0.30999994
E24: =SUM(E19:E23) -> -9.4589922e+09 | F24: =E24=F9 -> TRUE | G24: =E24=H9 -> FALSE | H24: =E24-H9 -> -1.4200001

Sheet Reporte Componentes R1
B4: PROMOAMBIENTAL
F5: Total | G5: Componente TDF | H5: Componente TTL | I5: Componente TVIAT | J5: Aprovechamiento | K5: CCSA Prest.Aprov. | L5: SERVICIO ESPECIALES | M5: Componente TCS | N5: Componente TLU | O5: Componente TBL | P5: Componente TRT | Q5: CCSA Prest. No Aprov. | R5: Ajuste Decena | S5: Ajuste Recargo Aseo | T5: Intereses Cte Financiac. Aseo | U5: Exonera-Ajuste Decena Aseo | V5: Exonera-Ajuste Decena Aseo | W5: Exonera-Recargo Aseo | X5: Rec.Intereses | Y5: Intereses Cte Financiac. Aseo | Z5: Rec.Intereses
E6: Vlr Servicio | F6: -9123.9 | G6: -625.08 | H6: -265.56 | I6: -115.95 | J6: -1600.92 | K6: -103.46 | L6: 0 | M6: -907.42 | N6: -759.41 | O6: -3031.34 | P6: -1545.97 | Q6: -168.79 | R6: 0 | S6: 0 | T6: 0 | U6: 0 | V6: 0 | W6: 0 | X6: 0 | Y6: 0 | Z6: 0
D7: O | E7: Total | F7: -9123.9 | G7: -625.08 | H7: -265.56 | I7: -115.95 | J7: -1600.92 | K7: -103.46 | L7: 0 | M7: -907.42 | N7: -759.41 | O7: -3031.34 | P7: -1545.97 | Q7: -168.79 | R7: 0 | S7: 0 | T7: 0 | U7: 0 | V7: 0 | W7: 0 | X7: 0 | Y7: 0 | Z7: 0
C8: OCCIDENTE | D8: Total | F8: -9123.9 | G8: -625.08 | H8: -265.56 | I8: -115.95 | J8: -1600.92 | K8: -103.46 | L8: 0 | M8: -907.42 | N8: -759.41 | O8: -3031.34 | P8: -1545.97 | Q8: -168.79 | R8: 0 | S8: 0 | T8: 0 | U8: 0 | V8: 0 | W8: 0 | X8: 0 | Y8: 0 | Z8: 0
B9: Mes | C9: Total | F9: -9123.9 | G9: -625.08 | H9: -265.56 | I9: -115.95 | J9: -1600.92 | K9: -103.46 | L9: 0 | M9: -907.42 | N9: -759.41 | O9: -3031.34 | P9: -1545.97 | Q9: -168.79 | R9: 0 | S9: 0 | T9: 0 | U9: 0 | V9: 0 | W9: 0 | X9: 0 | Y9: 0 | Z9: 0
A10: AFaseo | B10: Total | F10: -9123.9 | G10: -625.08 | H10: -265.56 | I10: -115.95 | J10: -1600.92 | K10: -103.46 | L10: 0 | M10: -907.42 | N10: -759.41 | O10: -3031.34 | P10: -1545.97 | Q10: -168.79 | R10: 0 | S10: 0 | T10: 0 | U10: 0 | V10: 0 | W10: 0 | X10: 0 | Y10: 0 | Z10: 0
E11: Vlr Servicio | F11: 42369.42 | G11: 2242.46 | H11: 1266.09 | I11: 664.53 | J11: 10026.01 | K11: 372.31 | L11: 0 | M11: 3265.88 | N11: 3109.1 | O11: 14722.61 | P11: 6097.75 | Q11: 607.45 | R11: -4.77 | S11: 0 | T11: 0 | U11: 0 | V11: 0 | W11: 0 | X11: 0 | Y11: 0 | Z11: 0
D12: E | E12: Total | F12: 42369.42 | G12: 2242.46 | H12: 1266.09 | I12: 664.53 | J12: 10026.01 | K12: 372.31 | L12: 0 | M12: 3265.88 | N12: 3109.1 | O12: 14722.61 | P12: 6097.75 | Q12: 607.45 | R12: -4.77 | S12: 0 | T12: 0 | U12: 0 | V12: 0 | W12: 0 | X12: 0 | Y12: 0 | Z12: 0
C13: ENEL | D13: Total | F13: 42369.42 | G13: 2242.46 | H13: 1266.09 | I13: 664.53 | J13: 10026.01 | K13: 372.31 | L13: 0 | M13: 3265.88 | N13: 3109.1 | O13: 14722.61 | P13: 6097.75 | Q13: 607.45 | R13: -4.77 | S13: 0 | T13: 0 | U13: 0 | V13: 0 | W13: 0 | X13: 0 | Y13: 0 | Z13: 0
B14: Aplicacion nuevos x reversion | C14: Total | F14: 42369.42 | G14: 2242.46 | H14: 1266.09 | I14: 664.53 | J14: 10026.01 | K14: 372.31 | L14: 0 | M14: 3265.88 | N14: 3109.1 | O14: 14722.61 | P14: 6097.75 | Q14: 607.45 | R14: -4.77 | S14: 0 | T14: 0 | U14: 0 | V14: 0 | W14: 0 | X14: 0 | Y14: 0 | Z14: 0
E15: Vlr Servicio | F15: 1.7290064e+10 | G15: 8.7567923e+08 | H15: 4.9376165e+08 | I15: 2.5970135e+08 | J15: 4.1207765e+09 | K15: 1.5442379e+08 | L15: 16025088 | M15: 1.357667e+09 | N15: 1.2875919e+09 | O15: 6.0939798e+09 | P15: 2.3783689e+09 | Q15: 2.5208609e+08 | R15: 3156.5 | S15: 0 | T15: 0 | U15: 0 | V15: 0 | W15: 0 | X15: 0 | Y15: 0 | Z15: 0
E16: Vlr Intereses | F16: 3168870.3 | G16: 181699.71 | H16: 94563.09 | I16: 50842.1 | J16: 719172.29 | K16: 28488.91 | L16: 600.77 | M16: 251707.71 | N16: 231457.21 | O16: 1072357.8 | P16: 490967.89 | Q16: 46457.99 | R16: 253.72 | S16: 0 | T16: 301.09 | U16: 0 | V16: 0 | W16: 0 | X16: 0 | Y16: 0 | Z16: 0
D17: E | E17: Total | F17: 1.7293233e+10 | G17: 8.7586093e+08 | H17: 4.9385621e+08 | I17: 2.5975219e+08 | J17: 4.1214957e+09 | K17: 1.5445228e+08 | L17: 16025689 | M17: 1.3579187e+09 | N17: 1.2878233e+09 | O17: 6.0950521e+09 | P17: 2.3788598e+09 | Q17: 2.5213255e+08 | R17: 3410.22 | S17: 0 | T17: 301.09 | U17: 0 | V17: 0 | W17: 0 | X17: 0 | Y17: 0 | Z17: 0
C18: ENEL | D18: Total | F18: 1.7293233e+10 | G18: 8.7586093e+08 | H18: 4.9385621e+08 | I18: 2.5975219e+08 | J18: 4.1214957e+09 | K18: 1.5445228e+08 | L18: 16025689 | M18: 1.3579187e+09 | N18: 1.2878233e+09 | O18: 6.0950521e+09 | P18: 2.3788598e+09 | Q18: 2.5213255e+08 | R18: 3410.22 | S18: 0 | T18: 301.09 | U18: 0 | V18: 0 | W18: 0 | X18: 0 | Y18: 0 | Z18: 0
E19: Vlr Servicio | F19: 31630649 | G19: 2116281.5 | H19: 1170722.5 | I19: 622287.66 | J19: 6853780.1 | K19: 205254.36 | L19: 0 | M19: 1791021.5 | N19: 2239705 | O19: 10554766 | P19: 5742154.8 | Q19: 334770.08 | R19: -94.69 | S19: 0 | T19: 0 | U19: 0 | V19: 0 | W19: 0 | X19: 0 | Y19: 0 | Z19: 0
E20: Vlr Intereses | F20: 56566.94 | G20: 3153.2 | H20: 1630.48 | I20: 910.69 | J20: 14196.75 | K20: 404.44 | L20: 0 | M20: 3503.55 | N20: 4189.5 | O20: 19352.39 | P20: 8568.43 | Q20: 658.34 | R20: -0.86 | S20: 0 | T20: 0.03 | U20: 0 | V20: 0 | W20: 0 | X20: 0 | Y20: 0 | Z20: 0
D21: H | E21: Total | F21: 31687216 | G21: 2119434.7 | H21: 1172353 | I21: 623198.35 | J21: 6867976.9 | K21: 205658.8 | L21: 0 | M21: 1794525 | N21: 2243894.5 | O21: 10574119 | P21: 5750723.2 | Q21: 335428.42 | R21: -95.55 | S21: 0 | T21: 0.03 | U21: 0 | V21: 0 | W21: 0 | X21: 0 | Y21: 0 | Z21: 0
E22: Vlr Servicio | F22: 1.1668923e+08 | G22: 12754734 | H22: 7083986 | I22: 3721696.4 | J22: 14791579 | K22: 679432.2 | L22: 200407 | M22: 5966168.7 | N22: 6324114.5 | O22: 29397614 | P22: 34660612 | Q22: 1109795.6 | R22: -904.58 | S22: 0 | T22: 0 | U22: 0 | V22: 0 | W22: 0 | X22: 0 | Y22: 0 | Z22: 0
E23: Vlr Intereses | F23: 298459.58 | G23: 17963.04 | H23: 7955.38 | I23: 3775.96 | J23: 65367.19 | K23: 2954.14 | L23: 175.21 | M23: 26504.61 | N23: 23098.54 | O23: 96645.91 | P23: 49317.74 | Q23: 4814.6 | R23: -5.81 | S23: 0 | T23: 0.13 | U23: 0 | V23: 0 | W23: 0 | X23: 0 | Y23: 0 | Z23: -107.06
D24: O | E24: Total | F24: 1.1698769e+08 | G24: 12772697 | H24: 7091941.4 | I24: 3725472.3 | J24: 14856946 | K24: 682386.34 | L24: 200582.21 | M24: 5992673.3 | N24: 6347213 | O24: 29494260 | P24: 34709929 | Q24: 1114610.2 | R24: -910.39 | S24: 0 | T24: 0.13 | U24: 0 | V24: 0 | W24: 0 | X24: 0 | Y24: 0 | Z24: -107.06
E25: Vlr Servicio | F25: 5.3396346e+08 | G25: 84240997 | H25: 47757392 | I25: 25132510 | J25: 41404004 | K25: 1121828.4 | L25: 20785144 | M25: 9808677.1 | N25: 12792123 | O25: 60185506 | P25: 2.289052e+08 | Q25: 1830367.3 | R25: -289.47 | S25: 0 | T25: 0 | U25: 0 | V25: 0 | W25: 0 | X25: 0 | Y25: 0 | Z25: 0
E26: Vlr Intereses | F26: 1648345.4 | G26: 174887.74 | H26: 87267.15 | I26: 44237.05 | J26: 278588.77 | K26: 9930.26 | L26: 13403.82 | M26: 86925 | N26: 89458.52 | O26: 385189.1 | P26: 462280.45 | Q26: 16184.13 | R26: -6.73 | S26: 0.08 | T26: 0.08 | U26: 0 | V26: 0 | W26: 0 | X26: 0 | Y26: 0 | Z26: 0
D27: T | E27: Total | F27: 5.3561181e+08 | G27: 84415885 | H27: 47844659 | I27: 25176747 | J27: 41682593 | K27: 1131758.7 | L27: 20798548 | M27: 9895602.1 | N27: 12881582 | O27: 60570695 | P27: 2.2936749e+08 | Q27: 1846551.4 | R27: -296.2 | S27: 0.08 | T27: 0.08 | U27: 0 | V27: 0 | W27: 0 | X27: 0 | Y27: 0 | Z27: 0
C28: OCCIDENTE | D28: Total | F28: 6.8428672e+08 | G28: 99308017 | H28: 56108953 | I28: 29525418 | J28: 63407516 | K28: 2019803.8 | L28: 20999130 | M28: 17682800 | N28: 21472689 | O28: 1.0063907e+08 | P28: 2.6982814e+08 | Q28: 3296590 | R28: -1302.14 | S28: 0.08 | T28: 0.24 | U28: 0 | V28: 0 | W28: 0 | X28: 0 | Y28: 0 | Z28: -107.06
B29: Mes | C29: Total | F29: 1.797752e+10 | G29: 9.7516894e+08 | H29: 5.4996517e+08 | I29: 2.8927761e+08 | J29: 4.1849032e+09 | K29: 1.5647208e+08 | L29: 37024819 | M29: 1.3756015e+09 | N29: 1.309296e+09 | O29: 6.1956912e+09 | P29: 2.648688e+09 | Q29: 2.5542914e+08 | R29: 2108.08 | S29: 0.08 | T29: 301.33 | U29: 0 | V29: 0 | W29: 0 | X29: 0 | Y29: 0 | Z29: -107.06
A30: Componente | B30: Total | F30: 1.7977562e+10 | G30: 9.7517119e+08 | H30: 5.4996643e+08 | I30: 2.8927827e+08 | J30: 4.1849132e+09 | K30: 1.5647245e+08 | L30: 37024819 | M30: 1.3756047e+09 | N30: 1.3092991e+09 | O30: 6.1957059e+09 | P30: 2.6486941e+09 | Q30: 2.5542974e+08 | R30: 2103.31 | S30: 0.08 | T30: 301.33 | U30: 0 | V30: 0 | W30: 0 | X30: 0 | Y30: 0 | Z30: -107.06
E31: Subsidio(-)/Contribucion(+) | F31: 21200.58 | G31: 1121.23 | H31: 633.05 | I31: 332.27 | J31: 5013.01 | K31: 186.15 | L31: 0 | M31: 1632.95 | N31: 1554.55 | O31: 7361.31 | P31: 3062.34 | Q31: 303.72 | R31: 0 | S31: 0 | T31: 0 | U31: 0 | V31: 0 | W31: 0 | X31: 0 | Y31: 0 | Z31: 0
D32: E | E32: Total | F32: 21200.58 | G32: 1121.23 | H32: 633.05 | I32: 332.27 | J32: 5013.01 | K32: 186.15 | L32: 0 | M32: 1632.95 | N32: 1554.55 | O32: 7361.31 | P32: 3062.34 | Q32: 303.72 | R32: 0 | S32: 0 | T32: 0 | U32: 0 | V32: 0 | W32: 0 | X32: 0 | Y32: 0 | Z32: 0
C33: ENEL | D33: Total | F33: 21200.58 | G33: 1121.23 | H33: 633.05 | I33: 332.27 | J33: 5013.01 | K33: 186.15 | L33: 0 | M33: 1632.95 | N33: 1554.55 | O33: 7361.31 | P33: 3062.34 | Q33: 303.72 | R33: 0 | S33: 0 | T33: 0 | U33: 0 | V33: 0 | W33: 0 | X33: 0 | Y33: 0 | Z33: 0
B34: Aplicacion nuevos x reversion | C34: Total | F34: 21200.58 | G34: 1121.23 | H34: 633.05 | I34: 332.27 | J34: 5013.01 | K34: 186.15 | L34: 0 | M34: 1632.95 | N34: 1554.55 | O34: 7361.31 | P34: 3062.34 | Q34: 303.72 | R34: 0 | S34: 0 | T34: 0 | U34: 0 | V34: 0 | W34: 0 | X34: 0 | Y34: 0 | Z34: 0
E35: Subsidio(-)/Contribucion(+) | F35: 1.5189423e+08 | G35: 90683812 | H35: 51049002 | I35: 26794378 | J35: -86416493 | K35: -3024948.5 | L35: 0 | M35: -27764106 | N35: -25271108 | O35: -1.2039562e+08 | P35: 2.5115921e+08 | Q35: -4919900.3 | R35: 0 | S35: 0 | T35: 0 | U35: 0 | V35: 0 | W35: 0 | X35: 0 | Y35: 0 | Z35: 0
D36: E | E36: Total | F36: 1.5189423e+08 | G36: 90683812 | H36: 51049002 | I36: 26794378 | J36: -86416493 | K36: -3024948.5 | L36: 0 | M36: -27764106 | N36: -25271108 | O36: -1.2039562e+08 | P36: 2.5115921e+08 | Q36: -4919900.3 | R36: 0 | S36: 0 | T36: 0 | U36: 0 | V36: 0 | W36: 0 | X36: 0 | Y36: 0 | Z36: 0
C37: ENEL | D37: Total | F37: 1.5189423e+08 | G37: 90683812 | H37: 51049002 | I37: 26794378 | J37: -86416493 | K37: -3024948.5 | L37: 0 | M37: -27764106 | N37: -25271108 | O37: -1.2039562e+08 | P37: 2.5115921e+08 | Q37: -4919900.3 | R37: 0 | S37: 0 | T37: 0 | U37: 0 | V37: 0 | W37: 0 | X37: 0 | Y37: 0 | Z37: 0
E38: Subsidio(-)/Contribucion(+) | F38: 2021483 | G38: 707748.14 | H38: 403617.61 | I38: 212434.65 | J38: -402532.63 | K38: -15766.67 | L38: 0 | M38: -141242.42 | N38: -116984.96 | O38: -532807.93 | P38: 1932741 | Q38: -25723.75 | R38: 0 | S38: 0 | T38: 0 | U38: 0 | V38: 0 | W38: 0 | X38: 0 | Y38: 0 | Z38: 0
D39: H | E39: Total | F39: 2021483 | G39: 707748.14 | H39: 403617.61 | I39: 212434.65 | J39: -402532.63 | K39: -15766.67 | L39: 0 | M39: -141242.42 | N39: -116984.96 | O39: -532807.93 | P39: 1932741 | Q39: -25723.75 | R39: 0 | S39: 0 | T39: 0 | U39: 0 | V39: 0 | W39: 0 | X39: 0 | Y39: 0 | Z39: 0
E40: Subsidio(-)/Contribucion(+) | F40: 13967366 | G40: 2999538.8 | H40: 1727763.6 | I40: 908877.93 | J40: -376035.93 | K40: -21939.23 | L40: 0 | M40: -193832.61 | N40: 102993.61 | O40: 642642.72 | P40: 8213151.1 | Q40: -35794.53 | R40: 0 | S40: 0 | T40: 0 | U40: 0 | V40: 0 | W40: 0 | X40: 0 | Y40: 0 | Z40: 0
D41: O | E41: Total | F41: 13967366 | G41: 2999538.8 | H41: 1727763.6 | I41: 908877.93 | J41: -376035.93 | K41: -21939.23 | L41: 0 | M41: -193832.61 | N41: 102993.61 | O41: 642642.72 | P41: 8213151.1 | Q41: -35794.53 | R41: 0 | S41: 0 | T41: 0 | U41: 0 | V41: 0 | W41: 0 | X41: 0 | Y41: 0 | Z41: 0
E42: Subsidio(-)/Contribucion(+) | F42: 1.9030195e+08 | G42: 34107615 | H42: 19171704 | I42: 10096437 | J42: 10987895 | K42: 313087.53 | L42: 0 | M42: 2737745.5 | N42: 3379843 | O42: 15862576 | P42: 93134787 | Q42: 510261.81 | R42: 0 | S42: 0 | T42: 0 | U42: 0 | V42: 0 | W42: 0 | X42: 0 | Y42: 0 | Z42: 0
D43: T | E43: Total | F43: 1.9030195e+08 | G43: 34107615 | H43: 19171704 | I43: 10096437 | J43: 10987895 | K43: 313087.53 | L43: 0 | M43: 2737745.5 | N43: 3379843 | O43: 15862576 | P43: 93134787 | Q43: 510261.81 | R43: 0 | S43: 0 | T43: 0 | U43: 0 | V43: 0 | W43: 0 | X43: 0 | Y43: 0 | Z43: 0
C44: OCCIDENTE | D44: Total | F44: 2.062908e+08 | G44: 37814902 | H44: 21303085 | I44: 11217750 | J44: 10209327 | K44: 275381.63 | L44: 0 | M44: 2402670.5 | N44: 3365851.7 | O44: 15972411 | P44: 1.0328068e+08 | Q44: 448743.53 | R44: 0 | S44: 0 | T44: 0 | U44: 0 | V44: 0 | W44: 0 | X44: 0 | Y44: 0 | Z44: 0
B45: Mes | C45: Total | F45: 3.5818503e+08 | G45: 1.2849871e+08 | H45: 72352087 | I45: 38012127 | J45: -76207166 | K45: -2749566.9 | L45: 0 | M45: -25361435 | N45: -21905256 | O45: -1.0442321e+08 | P45: 3.5443989e+08 | Q45: -4471156.8 | R45: 0 | S45: 0 | T45: 0 | U45: 0 | V45: 0 | W45: 0 | X45: 0 | Y45: 0 | Z45: 0
A46: Subs/Cont | B46: Total | F46: 3.5820623e+08 | G46: 1.2849984e+08 | H46: 72352720 | I46: 38012460 | J46: -76202153 | K46: -2749380.8 | L46: 0 | M46: -25359802 | N46: -21903702 | O46: -1.0441584e+08 | P46: 3.5444295e+08 | Q46: -4470853.1 | R46: 0 | S46: 0 | T46: 0 | U46: 0 | V46: 0 | W46: 0 | X46: 0 | Y46: 0 | Z46: 0
A47: Total | F47: 1.8335759e+10 | G47: 1.1036704e+09 | H47: 6.2231889e+08 | I47: 3.2729062e+08 | J47: 4.1087094e+09 | K47: 1.5372297e+08 | L47: 37024819 | M47: 1.350244e+09 | N47: 1.2873947e+09 | O47: 6.0912871e+09 | P47: 3.0031355e+09 | Q47: 2.5095872e+08 | R47: 2103.31 | S47: 0.08 | T47: 301.33 | U47: 0 | V47: 0 | W47: 0 | X47: 0 | Y47: 0 | Z47: -107.06
C50: TOTAL | D50: OPORTUNO | E50: Total | F50: =F29+F45+F9-L9-L29 -> 1.8298671e+10 | G50: =G29+G9 -> 9.7516832e+08 | H50: =H29+H9 -> 5.499649e+08 | I50: =I29+I9 -> 2.8927749e+08 | J50: =J29+J9 -> 4.1849016e+09 | K50: =K29+K9 -> 1.5647198e+08 | L50: =L29+L9 -> 37024819 | M50: =M29+M9 -> 1.3756006e+09 | N50: =N29+N9 -> 1.3092952e+09 | ... AP50: =AP29+AP9 -> 0
E51: Subsidio(-)/Contribucion(+) | F51: =F45 -> 3.5818503e+08
D52: EXTEMPORANEO | E52: Total | F52: =F34+F14-L14 -> 63570 | G52: =G14 -> 2242.46 | H52: =H14 -> 1266.09 | I52: =I14 -> 664.53 | J52: =J14 -> 10026.01 | K52: =K14 -> 372.31 | L52: =L14 -> 0 | M52: =M14 -> 3265.88 | N52: =N14 -> 3109.1 | ... AP52: =AP14 -> 0
E53: Subsidio(-)/Contribucion(+) | F53: =F34 -> 21200.58
C55: RECIPROCIDAD | D55: OPORTUNO | E55: Total | F55: 0 | G55: 0 | H55: 0 | I55: 0 | J55: 0 | K55: 0 | L55: 0 | M55: 0 | N55: 0 | O55: 0 | P55: 0 | Q55: 0 | R55: 0 | S55: 0 | T55: 0 | U55: 0 | V55: 0 | W55: 0 | X55: 0 | Y55: 0 | Z55: 0 | AA55: 0 | AB55: 0 | AC55: 0 | AD55: 0 | AE55: 0 | AF55: 0 | AG55: 0 | AH55: 0 | AI55: 0 | AJ55: 0 | AK55: 0 | AL55: 0 | AM55: 0 | AN55: 0 | AO55: 0 | AP55: 0
E56: Subsidio(-)/Contribucion(+) | F56: 0
D57: EXTEMPORANEO | E57: Total | F57: 0 | G57: 0 | H57: 0 | I57: 0 | J57: 0 | K57: 0 | L57: 0 | M57: 0 | N57: 0 | O57: 0 | P57: 0 | Q57: 0 | R57: 0 | S57: 0 | T57: 0 | U57: 0 | V57: 0 | W57: 0 | X57: 0 | Y57: 0 | Z57: 0 | AA57: 0 | AB57: 0 | AC57: 0 | AD57: 0 | AE57: 0 | AF57: 0 | AG57: 0 | AH57: 0 | AI57: 0 | AJ57: 0 | AK57: 0 | AL57: 0 | AM57: 0 | AN57: 0 | AO57: 0 | AP57: 0
E58: Subsidio(-)/Contribucion(+) | F58: 0
C60: ENEL | D60: OPORTUNO | E60: Total | F60: =F37+F18-L18 -> 1.7429102e+10 | G60: =G18 -> 8.7586093e+08 | H60: =H18 -> 4.9385621e+08 | I60: =I18 -> 2.5975219e+08 | J60: =J18 -> 4.1214957e+09 | K60: =K18 -> 1.5445228e+08 | L60: =L18 -> 16025689 | M60: =M18 -> 1.3579187e+09 | N60: =N18 -> 1.2878233e+09 | ... AP60: =AP18 -> 0
E61: Subsidio(-)/Contribucion(+) | F61: =F37 -> 1.5189423e+08
D62: EXTEMPORANEO | E62: Total | F62: =F33+F13-L13 -> 63570 | G62: =G13 -> 2242.46 | H62: =H13 -> 1266.09 | I62: =I13 -> 664.53 | J62: =J13 -> 10026.01 | K62: =K13 -> 372.31 | L62: =L13 -> 0 | M62: =M13 -> 3265.88 | N62: =N13 -> 3109.1 | ... AP62: =AP13 -> 0
E63: Subsidio(-)/Contribucion(+) | F63: =F33 -> 21200.58
C65: ENERBIT | D65: OPORTUNO | E65: Total | F65: 0 | G65: 0 | H65: 0 | I65: 0 | J65: 0 | K65: 0 | L65: 0 | M65: 0 | N65: 0 | O65: 0 | P65: 0 | Q65: 0 | R65: 0 | S65: 0 | T65: 0 | U65: 0 | V65: 0 | W65: 0 | X65: 0 | Y65: 0 | Z65: 0 | AA65: 0 | AB65: 0 | AC65: 0 | AD65: 0 | AE65: 0 | AF65: 0 | AG65: 0 | AH65: 0 | AI65: 0 | AJ65: 0 | AK65: 0 | AL65: 0 | AM65: 0 | AN65: 0 | AO65: 0
E66: Subsidio(-)/Contribucion(+) | F66: 0
D67: EXTEMPORANEO | E67: Total | F67: 0 | G67: 0 | H67: 0 | I67: 0 | J67: 0 | K67: 0 | L67: 0 | M67: 0 | N67: 0 | O67: 0 | P67: 0 | Q67: 0 | R67: 0 | S67: 0 | T67: 0 | U67: 0 | V67: 0 | W67: 0 | X67: 0 | Y67: 0 | Z67: 0 | AA67: 0 | AB67: 0 | AC67: 0 | AD67: 0 | AE67: 0 | AF67: 0 | AG67: 0 | AH67: 0 | AI67: 0 | AJ67: 0 | AK67: 0 | AL67: 0 | AM67: 0 | AN67: 0 | AO67: 0
E68: Subsidio(-)/Contribucion(+) | F68: 0
C70: OCCIDENTE | D70: OPORTUNO | E70: Total | F70: =F44+F28+F8-L8-L28 -> 8.6956927e+08 | G70: =G28+G8 -> 99307392 | H70: =H28+H8 -> 56108688 | I70: =I28+I8 -> 29525302 | J70: =J28+J8 -> 63405915 | K70: =K28+K8 -> 2019700.4 | L70: =L28+L8 -> 20999130 | M70: =M28+M8 -> 17681893 | N70: =N28+N8 -> 21471930 | ... AP70: =AP28+AP8 -> 0
E71: Subsidio(-)/Contribucion(+) | F71: =F44 -> 2.062908e+08
D72: EXTEMPORANEO | E72: Total | F72: 0 | G72: 0 | H72: 0 | I72: 0 | J72: 0 | K72: 0 | L72: 0 | M72: 0 | N72: 0 | O72: 0 | P72: 0 | Q72: 0 | R72: 0 | S72: 0 | T72: 0 | U72: 0 | V72: 0 | W72: 0 | X72: 0 | Y72: 0 | Z72: 0 | AA72: 0 | AB72: 0 | AC72: 0 | AD72: 0 | AE72: 0 | AF72: 0 | AG72: 0 | AH72: 0 | AI72: 0 | AJ72: 0 | AK72: 0 | AL72: 0 | AM72: 0 | AN72: 0 | AO72: 0 | AP72: 0
E73: Subsidio(-)/Contribucion(+) | F73: 0
C75: CIUDAD LIMPIA-ACUEDUCTO | D75: OPORTUNO | E75: Total | F75: 0 | G75: 0 | H75: 0 | I75: 0 | J75: 0 | K75: 0 | L75: 0 | M75: 0 | N75: 0 | O75: 0 | P75: 0 | Q75: 0 | R75: 0 | S75: 0 | T75: 0 | U75: 0 | V75: 0 | W75: 0 | X75: 0 | Y75: 0 | Z75: 0 | AA75: 0 | AB75: 0 | AC75: 0 | AD75: 0 | AE75: 0 | AF75: 0 | AG75: 0 | AH75: 0 | AI75: 0 | AJ75: 0 | AK75: 0 | AL75: 0 | AM75: 0 | AN75: 0 | AO75: 0 | AP75: 0
E76: Subsidio(-)/Contribucion(+) | F76: 0
D77: EXTEMPORANEO | E77: Total | F77: 0 | G77: 0 | H77: 0 | I77: 0 | J77: 0 | K77: 0 | L77: 0 | M77: 0 | N77: 0 | O77: 0 | P77: 0 | Q77: 0 | R77: 0 | S77: 0 | T77: 0 | U77: 0 | V77: 0 | W77: 0 | X77: 0 | Y77: 0 | Z77: 0 | AA77: 0 | AB77: 0 | AC77: 0 | AD77: 0 | AE77: 0 | AF77: 0 | AG77: 0 | AH77: 0 | AI77: 0 | AJ77: 0 | AK77: 0 | AL77: 0 | AM77: 0 | AN77: 0 | AO77: 0 | AP77: 0
E78: Subsidio(-)/Contribucion(+) | F78: 0
D80: AFaseo | E80: Total | F80: =F10 -> -9123.9 | G80: =G10 -> -625.08 | H80: =H10 -> -265.56 | I80: =I10 -> -115.95 | J80: =J10 -> -1600.92 | K80: =K10 -> -103.46 | L80: =L10 -> 0 | M80: =M10 -> -907.42 | ... AP80: =AP10 -> 0
B83: LIME
F84: Total | G84: Componente TDF | H84: Componente TTL | I84: Componente TVIAT | J84: Aprovechamiento | K84: CCSA Prest.Aprov. | L84: SERVICIO ESPECIALES | M84: Componente TCS | N84: Componente TLU | O84: Componente TBL | P84: Componente TRT | Q84: CCSA Prest. No Aprov. | R84: Ajuste Decena | S84: Ajuste Recargo Aseo | T84: Intereses Cte Financiac. Aseo | U84: Exonera Rec.Intereses | V84: Exonera-Ajuste Decena Aseo | W84: Exonera-Recargo Aseo | X84: Rec.Intereses | Y84: Intereses Cte Financiac. Aseo | Z84: Rec.Intereses
E85: Vlr Servicio | F85: -1414859.1 | G85: -123592.91 | H85: -52505.96 | I85: -22930.17 | J85: -283718.29 | K85: -11813.11 | L85: 0 | M85: -103626.9 | N85: -129894.77 | O85: -436317.84 | P85: -231183.82 | Q85: -19275.37 | R85: 0 | S85: 0 | T85: 0 | U85: 0 | V85: 0 | W85: 0 | X85: 0 | Y85: 0 | Z85: 0
D86: E | E86: Total | F86: -1414859.1 | G86: -123592.91 | H86: -52505.96 | I86: -22930.17 | J86: -283718.29 | K86: -11813.11 | L86: 0 | M86: -103626.9 | N86: -129894.77 | O86: -436317.84 | P86: -231183.82 | Q86: -19275.37 | R86: 0 | S86: 0 | T86: 0 | U86: 0 | V86: 0 | W86: 0 | X86: 0 | Y86: 0 | Z86: 0
C87: ENEL | D87: Total | F87: -1414859.1 | G87: -123592.91 | H87: -52505.96 | I87: -22930.17 | J87: -283718.29 | K87: -11813.11 | L87: 0 | M87: -103626.9 | N87: -129894.77 | O87: -436317.84 | P87: -231183.82 | Q87: -19275.37 | R87: 0 | S87: 0 | T87: 0 | U87: 0 | V87: 0 | W87: 0 | X87: 0 | Y87: 0 | Z87: 0
E88: Vlr Servicio | F88: -20998.87 | G88: -1840.53 | H88: -781.92 | I88: -341.46 | J88: -4232.84 | K88: -174.41 | L88: 0 | M88: -1529.91 | N88: -1917.75 | O88: -6441.6 | P88: -3453.9 | Q88: -284.55 | R88: 0 | S88: 0 | T88: 0 | U88: 0 | V88: 0 | W88: 0 | X88: 0 | Y88: 0 | Z88: 0
D89: H | E89: Total | F89: -20998.87 | G89: -1840.53 | H89: -781.92 | I89: -341.46 | J89: -4232.84 | K89: -174.41 | L89: 0 | M89: -1529.91 | N89: -1917.75 | O89: -6441.6 | P89: -3453.9 | Q89: -284.55 | R89: 0 | S89: 0 | T89: 0 | U89: 0 | V89: 0 | W89: 0 | X89: 0 | Y89: 0 | Z89: 0
E90: Vlr Servicio | F90: -7651.97 | G90: -673.86 | H90: -286.26 | I90: -125.04 | J90: -1539.21 | K90: -63.42 | L90: 0 | M90: -556.33 | N90: -697.38 | O90: -2342.4 | P90: -1264.56 | Q90: -103.51 | R90: 0 | S90: 0 | T90: 0 | U90: 0 | V90: 0 | W90: 0 | X90: 0 | Y90: 0 | Z90: 0
D91: O | E91: Total | F91: -7651.97 | G91: -673.86 | H91: -286.26 | I91: -125.04 | J91: -1539.21 | K91: -63.42 | L91: 0 | M91: -556.33 | N91: -697.38 | O91: -2342.4 | P91: -1264.56 | Q91: -103.51 | R91: 0 | S91: 0 | T91: 0 | U91: 0 | V91: 0 | W91: 0 | X91: 0 | Y91: 0 | Z91: 0
C92: OCCIDENTE | D92: Total | F92: -28650.84 | G92: -2514.39 | H92: -1068.18 | I92: -466.5 | J92: -5772.05 | K92: -237.83 | L92: 0 | M92: -2086.24 | N92: -2615.13 | O92: -8784 | P92: -4718.46 | Q92: -388.06 | R92: 0 | S92: 0 | T92: 0 | U92: 0 | V92: 0 | W92: 0 | X92: 0 | Y92: 0 | Z92: 0
B93: Mes | C93: Total | F93: -1443510 | G93: -126107.3 | H93: -53574.14 | I93: -23396.67 | J93: -289490.34 | K93: -12050.94 | L93: 0 | M93: -105713.14 | N93: -132509.9 | O93: -445101.84 | P93: -235902.28 | Q93: -19663.43 | R93: 0 | S93: 0 | T93: 0 | U93: 0 | V93: 0 | W93: 0 | X93: 0 | Y93: 0 | Z93: 0
A94: AFaseo | B94: Total | F94: -1443510 | G94: -126107.3 | H94: -53574.14 | I94: -23396.67 | J94: -289490.34 | K94: -12050.94 | L94: 0 | M94: -105713.14 | N94: -132509.9 | O94: -445101.84 | P94: -235902.28 | Q94: -19663.43 | R94: 0 | S94: 0 | T94: 0 | U94: 0 | V94: 0 | W94: 0 | X94: 0 | Y94: 0 | Z94: 0
E95: Vlr Servicio | F95: 131543.19 | G95: 13093.19 | H95: 7370.27 | I95: 4474.7 | J95: 25771.56 | K95: 925.74 | L95: 0 | M95: 8109.96 | N95: 7930.91 | O95: 37461.59 | P95: 24418.29 | Q95: 1987.26 | R95: -0.28 | S95: 0 | T95: 0 | U95: 0 | V95: 0 | W95: 0 | X95: 0 | Y95: 0 | Z95: 0
D96: E | E96: Total | F96: 131543.19 | G96: 13093.19 | H96: 7370.27 | I96: 4474.7 | J96: 25771.56 | K96: 925.74 | L96: 0 | M96: 8109.96 | N96: 7930.91 | O96: 37461.59 | P96: 24418.29 | Q96: 1987.26 | R96: -0.28 | S96: 0 | T96: 0 | U96: 0 | V96: 0 | W96: 0 | X96: 0 | Y96: 0 | Z96: 0
C97: ENEL | D97: Total | F97: 131543.19 | G97: 13093.19 | H97: 7370.27 | I97: 4474.7 | J97: 25771.56 | K97: 925.74 | L97: 0 | M97: 8109.96 | N97: 7930.91 | O97: 37461.59 | P97: 24418.29 | Q97: 1987.26 | R97: -0.28 | S97: 0 | T97: 0 | U97: 0 | V97: 0 | W97: 0 | X97: 0 | Y97: 0 | Z97: 0
E98: Vlr Servicio | F98: 24890 | G98: 0 | H98: 0 | I98: 567.09 | J98: 5122.93 | K98: 373.45 | L98: 0 | M98: 0 | N98: 3176.37 | O98: 15040.85 | P98: 0 | Q98: 609.31 | R98: 0 | S98: 0 | T98: 0 | U98: 0 | V98: 0 | W98: 0 | X98: 0 | Y98: 0 | Z98: 0
D99: O | E99: Total | F99: 24890 | G99: 0 | H99: 0 | I99: 567.09 | J99: 5122.93 | K99: 373.45 | L99: 0 | M99: 0 | N99: 3176.37 | O99: 15040.85 | P99: 0 | Q99: 609.31 | R99: 0 | S99: 0 | T99: 0 | U99: 0 | V99: 0 | W99: 0 | X99: 0 | Y99: 0 | Z99: 0
C100: OCCIDENTE | D100: Total | F100: 24890 | G100: 0 | H100: 0 | I100: 567.09 | J100: 5122.93 | K100: 373.45 | L100: 0 | M100: 0 | N100: 3176.37 | O100: 15040.85 | P100: 0 | Q100: 609.31 | R100: 0 | S100: 0 | T100: 0 | U100: 0 | V100: 0 | W100: 0 | X100: 0 | Y100: 0 | Z100: 0
B101: Aplicacion nuevos x reversion | C101: Total | F101: 156433.19 | G101: 13093.19 | H101: 7370.27 | I101: 5041.79 | J101: 30894.49 | K101: 1299.19 | L101: 0 | M101: 8109.96 | N101: 11107.28 | O101: 52502.44 | P101: 24418.29 | Q101: 2596.57 | R101: -0.28 | S101: 0 | T101: 0 | U101: 0 | V101: 0 | W101: 0 | X101: 0 | Y101: 0 | Z101: 0
E102: Vlr Servicio | F102: 2.4730941e+10 | G102: 1.3641125e+09 | H102: 7.6139919e+08 | I102: 3.9756213e+08 | J102: 6.4356265e+09 | K102: 2.1557829e+08 | L102: 22415640 | M102: 1.8917823e+09 | N102: 1.8583189e+09 | O102: 8.749865e+09 | P102: 2.6823222e+09 | Q102: 3.521783e+08 | R102: -220306.25 | S102: 0 | T102: 0 | U102: 0 | V102: 0 | W102: 0 | X102: 0 | Y102: 0 | Z102: 0
E103: Vlr Intereses | F103: 1.0507885e+08 | G103: 12373208 | H103: 5822118.4 | I103: 2557314.4 | J103: 19359152 | K103: 689674.86 | L103: 17502.71 | M103: 6029529.8 | N103: 7139477.9 | O103: 25859858 | P103: 24102913 | Q103: 1125547.6 | R103: 2527.3 | S103: 50.73 | T103: 0.9 | U103: 0 | V103: 0 | W103: 0 | X103: 0 | Y103: 0 | Z103: -23.48
D104: E | E104: Total | F104: 2.4836019e+10 | G104: 1.3764857e+09 | H104: 7.6722131e+08 | I104: 4.0011944e+08 | J104: 6.4549856e+09 | K104: 2.1626797e+08 | L104: 22433143 | M104: 1.8978118e+09 | N104: 1.8654584e+09 | O104: 8.7757248e+09 | P104: 2.7064251e+09 | Q104: 3.5330385e+08 | R104: -217778.95 | S104: 50.73 | T104: 0.9 | U104: 0 | V104: 0 | W104: 0 | X104: 0 | Y104: 0 | Z104: -23.48
C105: ENEL | D105: Total | F105: 2.4836019e+10 | G105: 1.3764857e+09 | H105: 7.6722131e+08 | I105: 4.0011944e+08 | J105: 6.4549856e+09 | K105: 2.1626797e+08 | L105: 22433143 | M105: 1.8978118e+09 | N105: 1.8654584e+09 | O105: 8.7757248e+09 | P105: 2.7064251e+09 | Q105: 3.5330385e+08 | R105: -217778.95 | S105: 50.73 | T105: 0.9 | U105: 0 | V105: 0 | W105: 0 | X105: 0 | Y105: 0 | Z105: -23.48
E106: Vlr Servicio | F106: 1148755.9 | G106: 103833.95 | H106: 50131.96 | I106: 27876.21 | J106: 257690.34 | K106: 6913.63 | L106: 0 | M106: 60980.16 | N106: 74702.16 | O106: 347093.13 | P106: 208245.74 | Q106: 11280.3 | R106: 8.33 | S106: 0 | T106: 0 | U106: 0 | V106: 0 | W106: 0 | X106: 0 | Y106: 0 | Z106: 0
E107: Vlr Intereses | F107: 199642.47 | G107: 21039.28 | H107: 9401.54 | I107: 5415.39 | J107: 44862.35 | K107: 1038.88 | L107: 0 | M107: 9113.04 | N107: 11405.09 | O107: 53456.23 | P107: 42215.06 | Q107: 1695.12 | R107: 0.49 | S107: 0 | T107: 0 | U107: 0 | V107: 0 | W107: 0 | X107: 0 | Y107: 0 | Z107: 0
D108: 1 | E108: Total | F108: 1348398.4 | G108: 124873.23 | H108: 59533.5 | I108: 33291.6 | J108: 302552.69 | K108: 7952.51 | L108: 0 | M108: 70093.2 | N108: 86107.25 | O108: 400549.36 | P108: 250460.8 | Q108: 12975.42 | R108: 8.82 | S108: 0 | T108: 0 | U108: 0 | V108: 0 | W108: 0 | X108: 0 | Y108: 0 | Z108: 0
E109: Vlr Servicio | F109: 230376.22 | G109: 18333.27 | H109: 9782.29 | I109: 5319.95 | J109: 54717.31 | K109: 1624.1 | L109: 0 | M109: 14246.4 | N109: 15524.85 | O109: 70821.65 | P109: 37360.92 | Q109: 2649.83 | R109: -4.35 | S109: 0 | T109: 0 | U109: 0 | V109: 0 | W109: 0 | X109: 0 | Y109: 0 | Z109: 0
D110: 2 | E110: Total | F110: 230376.22 | G110: 18333.27 | H110: 9782.29 | I110: 5319.95 | J110: 54717.31 | K110: 1624.1 | L110: 0 | M110: 14246.4 | N110: 15524.85 | O110: 70821.65 | P110: 37360.92 | Q110: 2649.83 | R110: -4.35 | S110: 0 | T110: 0 | U110: 0 | V110: 0 | W110: 0 | X110: 0 | Y110: 0 | Z110: 0
E111: Vlr Servicio | F111: 9689217.2 | G111: 518533.02 | H111: 287577.53 | I111: 156432.14 | J111: 2441050.7 | K111: 82298.98 | L111: 0 | M111: 728609.23 | N111: 748449.81 | O111: 3562346.9 | P111: 1027130.6 | Q111: 136840.93 | R111: -52.63 | S111: 0 | T111: 0 | U111: 0 | V111: 0 | W111: 0 | X111: 0 | Y111: 0 | Z111: 0
E112: Vlr Intereses | F112: 217045.55 | G112: 12559.35 | H112: 6390.48 | I112: 3379.76 | J112: 55867.7 | K112: 1678.84 | L112: 0 | M112: 14715.14 | N112: 18428.22 | O112: 76574.75 | P112: 24706.8 | Q112: 2744.21 | R112: 0.42 | S112: 0 | T112: 0 | U112: 0 | V112: 0 | W112: 0 | X112: 0 | Y112: 0 | Z112: -0.12
D113: 5 | E113: Total | F113: 9906262.7 | G113: 531092.37 | H113: 293968.01 | I113: 159811.9 | J113: 2496918.4 | K113: 83977.82 | L113: 0 | M113: 743324.37 | N113: 766878.03 | O113: 3638921.7 | P113: 1051837.4 | Q113: 139585.14 | R113: -52.21 | S113: 0 | T113: 0 | U113: 0 | V113: 0 | W113: 0 | X113: 0 | Y113: 0 | Z113: -0.12
...

Sheet Rem. Anticipos R2
B1: PROMOAMBIENTAL
E2: Total | F2: Componente TDF | G2: Componente TTL | H2: Componente TVIAT | I2: Aprovechamiento | J2: CCSA Prest.Aprov. | K2: Especiales | L2: Componente TCS | M2: Componente TLU | N2: Componente TBL | O2: Componente TRT | P2: CCSA Prest. No Aprov. | Q2: Deb/Cred | R2: Deb/Cred-otros
D3: Vlr Servicio | E3: 68638686 | F3: 3508770.1 | G3: 1937288.9 | H3: 1197110.4 | I3: 11380562 | J3: 443407.1 | K3: 144941.68 | L3: 5045467.7 | M3: 6828093.9 | N3: 27654990 | O3: 9809312.2 | P3: 689599.67 | Q3: -857.27 | R3: 0
D4: Vlr Intereses | E4: 3528.82 | F4: 170.02 | G4: 95.73 | H4: 50.84 | I4: 743.09 | J4: 33.55 | K4: 0 | L4: 294.89 | M4: 285.6 | N4: 1334.86 | O4: 465.51 | P4: 54.68 | Q4: 0.05 | R4: 0
C5: E | D5: Total | E5: 68642215 | F5: 3508940.1 | G5: 1937384.7 | H5: 1197161.2 | I5: 11381305 | J5: 443440.65 | K5: 144941.68 | L5: 5045762.5 | M5: 6828379.5 | N5: 27656325 | O5: 9809777.8 | P5: 689654.35 | Q5: -857.22 | R5: 0
B6: ENEL | C6: Total | E6: 68642215 | F6: 3508940.1 | G6: 1937384.7 | H6: 1197161.2 | I6: 11381305 | J6: 443440.65 | K6: 144941.68 | L6: 5045762.5 | M6: 6828379.5 | N6: 27656325 | O6: 9809777.8 | P6: 689654.35 | Q6: -857.22 | R6: 0
D7: Vlr Servicio | E7: 5479070.7 | F7: 243932.99 | G7: 135534 | H7: 68532.32 | I7: 1313846.9 | J7: 46576.22 | K7: 0 | L7: 417929.46 | M7: 436871.77 | N7: 2070548 | O7: 668883.46 | P7: 76726.72 | Q7: -311.17 | R7: 0
D8: Vlr Intereses | E8: 24.04 | F8: 1.51 | G8: 0.84 | H8: 0.45 | I8: 5.71 | J8: 0.14 | K8: 0 | L8: 1.12 | M8: 1.78 | N8: 8.4 | O8: 3.85 | P8: 0.24 | Q8: 0 | R8: 0
C9: H | D9: Total | E9: 5479094.7 | F9: 243934.5 | G9: 135534.84 | H9: 68532.77 | I9: 1313852.6 | J9: 46576.36 | K9: 0 | L9: 417930.58 | M9: 436873.55 | N9: 2070556.4 | O9: 668887.31 | P9: 76726.96 | Q9: -311.17 | R9: 0
D10: Vlr Servicio | E10: 2699596.4 | F10: 95549.78 | G10: 53478.14 | H10: 29682.43 | I10: 366661.73 | J10: 13313.03 | K10: 0 | L10: 130811.46 | M10: 240997.61 | N10: 1493886.8 | O10: 253812.51 | P10: 21392.67 | Q10: 10.29 | R10: 0
D11: Vlr Intereses | E11: 170.73 | F11: 2.1 | G11: 1.34 | H11: 0.69 | I11: 38.16 | J11: 1.84 | K11: 0 | L11: 16.16 | M11: 20.39 | N11: 80.99 | O11: 6.05 | P11: 3.01 | Q11: 0 | R11: 0
C12: O | D12: Total | E12: 2699767.2 | F12: 95551.88 | G12: 53479.48 | H12: 29683.12 | I12: 366699.89 | J12: 13314.87 | K12: 0 | L12: 130827.62 | M12: 241018 | N12: 1493967.8 | O12: 253818.56 | P12: 21395.68 | Q12: 10.29 | R12: 0
D13: Vlr Servicio | E13: 16559735 | F13: 1740094.5 | G13: 958303.25 | H13: 447836.01 | I13: 2709661.2 | J13: 85664.82 | K13: 0 | L13: 781263.06 | M13: 852821.92 | N13: 4145411.9 | O13: 4699990 | P13: 138915.45 | Q13: -226.89 | R13: 0
D14: Vlr Intereses | E14: 97115.22 | F14: 1611.55 | G14: 741.57 | H14: 427.39 | I14: 6355.99 | J14: 233.02 | K14: 0 | L14: 2044.02 | M14: 1803.07 | N14: 8235.95 | O14: 4412.45 | P14: 380.2 | Q14: 70870.01 | R14: 0
C15: T | D15: Total | E15: 16656850 | F15: 1741706 | G15: 959044.82 | H15: 448263.4 | I15: 2716017.2 | J15: 85897.84 | K15: 0 | L15: 783307.08 | M15: 854624.99 | N15: 4153647.8 | O15: 4704402.5 | P15: 139295.65 | Q15: 70643.12 | R15: 0
B16: OCCIDENTE | C16: Total | E16: 24835712 | F16: 2081192.4 | G16: 1148059.1 | H16: 546479.29 | I16: 4396569.8 | J16: 145789.07 | K16: 0 | L16: 1332065.3 | M16: 1532516.5 | N16: 7718171.9 | O16: 5627108.3 | P16: 237418.29 | Q16: 70342.24 | R16: 0
A17: Componente | B17: Total | E17: 93477927 | F17: 5590132.5 | G17: 3085443.8 | H17: 1743640.5 | I17: 15777875 | J17: 589229.72 | K17: 144941.68 | L17: 6377827.8 | M17: 8360896 | N17: 35374497 | O17: 15436886 | P17: 927072.64 | Q17: 69485.02 | R17: 0
D18: Subsidio(-)/Contribucion(+) | E18: -16919808 | F18: -6426.91 | G18: -7107.75 | H18: -34767.29 | I18: -4744685.9 | J18: -208801.3 | K18: 0 | L18: -1830873.3 | M18: -1718121.5 | N18: -8045333.7 | O18: 17277.31 | P18: -340967.18 | Q18: 0 | R18: 0
C19: E | D19: Total | E19: -16919808 | F19: -6426.91 | G19: -7107.75 | H19: -34767.29 | I19: -4744685.9 | J19: -208801.3 | K19: 0 | L19: -1830873.3 | M19: -1718121.5 | N19: -8045333.7 | O19: 17277.31 | P19: -340967.18 | Q19: 0 | R19: 0
B20: ENEL | C20: Total | E20: -16919808 | F20: -6426.91 | G20: -7107.75 | H20: -34767.29 | I20: -4744685.9 | J20: -208801.3 | K20: 0 | L20: -1830873.3 | M20: -1718121.5 | N20: -8045333.7 | O20: 17277.31 | P20: -340967.18 | Q20: 0 | R20: 0
D21: Subsidio(-)/Contribucion(+) | E21: -1356390.2 | F21: -51804.26 | G21: -28844.43 | H21: -17259.48 | I21: -345570.32 | J21: -14236.76 | K21: 0 | L21: -122635.53 | M21: -108695.22 | N21: -510206.19 | O21: -133910.1 | P21: -23227.96 | Q21: 0 | R21: 0
C22: H | D22: Total | E22: -1356390.2 | F22: -51804.26 | G22: -28844.43 | H22: -17259.48 | I22: -345570.32 | J22: -14236.76 | K22: 0 | L22: -122635.53 | M22: -108695.22 | N22: -510206.19 | O22: -133910.1 | P22: -23227.96 | Q22: 0 | R22: 0
D23: Subsidio(-)/Contribucion(+) | E23: 61917.71 | F23: 13174.66 | G23: 7205.8 | H23: 3797.3 | I23: -12047.96 | J23: -622.88 | K23: 0 | L23: -5223.01 | M23: 2354.17 | N23: 15672.26 | O23: 38623.8 | P23: -1016.43 | Q23: 0 | R23: 0
C24: O | D24: Total | E24: 61917.71 | F24: 13174.66 | G24: 7205.8 | H24: 3797.3 | I24: -12047.96 | J24: -622.88 | K24: 0 | L24: -5223.01 | M24: 2354.17 | N24: 15672.26 | O24: 38623.8 | P24: -1016.43 | Q24: 0 | R24: 0
D25: Subsidio(-)/Contribucion(+) | E25: 4242196.6 | F25: 775349.09 | G25: 387936.56 | H25: 236215.92 | I25: 186954.68 | J25: 2849.95 | K25: 0 | L25: 32697.31 | M25: 67381.58 | N25: 316544.44 | O25: 2231313.3 | P25: 4953.78 | Q25: 0 | R25: 0
C26: T | D26: Total | E26: 4242196.6 | F26: 775349.09 | G26: 387936.56 | H26: 236215.92 | I26: 186954.68 | J26: 2849.95 | K26: 0 | L26: 32697.31 | M26: 67381.58 | N26: 316544.44 | O26: 2231313.3 | P26: 4953.78 | Q26: 0 | R26: 0
B27: OCCIDENTE | C27: Total | E27: 2947724.1 | F27: 736719.49 | G27: 366297.93 | H27: 222753.74 | I27: -170663.6 | J27: -12009.69 | K27: 0 | L27: -95161.23 | M27: -38959.47 | N27: -177989.49 | O27: 2136027 | P27: -19290.61 | Q27: 0 | R27: 0
A28: Subs/Cont | B28: Total | E28: -13972083 | F28: 730292.58 | G28: 359190.18 | H28: 187986.45 | I28: -4915349.5 | J28: -220810.99 | K28: 0 | L28: -1926034.6 | M28: -1757080.9 | N28: -8223323.2 | O28: 2153304.3 | P28: -360257.79 | Q28: 0 | R28: 0
A29: Total | E29: 79505844 | F29: 6320425 | G29: 3444634 | H29: 1931627 | I29: 10862525 | J29: 368418.73 | K29: 144941.68 | L29: 4451793.3 | M29: 6603815.1 | N29: 27151173 | O29: 17590190 | P29: 566814.85 | Q29: 69485.02 | R29: 0
B43: TOTAL | C43: OPORTUNO | D43: Total | E43: =E17+E28-K17 -> 79360902 | F43: =F17 -> 5590132.5 | G43: =G17 -> 3085443.8 | H43: =H17 -> 1743640.5 | I43: =I17 -> 15777875 | J43: =J17 -> 589229.72 | K43: =K17 -> 144941.68 | L43: =L17 -> 6377827.8 | M43: =M17 -> 8360896 | ... S43: =S17 -> 0
D44: Subsidio(-)/Contribucion(+) | E44: =E28 -> -13972083
B46: RECIPROCIDAD | C46: OPORTUNO | D46: Total | E46: 0 | F46: 0 | G46: 0 | H46: 0 | I46: 0 | J46: 0 | K46: 0 | L46: 0 | M46: 0 | N46: 0 | O46: 0 | P46: 0 | Q46: 0 | R46: 0 | S46: 0
D47: Subsidio(-)/Contribucion(+) | E47: 0
B49: ENEL | C49: OPORTUNO | D49: Total | E49: =E20+E6-K6 -> 51577466 | F49: =F6 -> 3508940.1 | G49: =G6 -> 1937384.7 | H49: =H6 -> 1197161.2 | I49: =I6 -> 11381305 | J49: =J6 -> 443440.65 | K49: =K6 -> 144941.68 | L49: =L6 -> 5045762.5 | M49: =M6 -> 6828379.5 | ... S49: =S6 -> 0
D50: Subsidio(-)/Contribucion(+) | E50: =E20 -> -16919808
B52: ENERBIT | C52: OPORTUNO | D52: Total | E52: 0 | F52: 0 | G52: 0 | H52: 0 | I52: 0 | J52: 0 | K52: 0 | L52: 0 | M52: 0 | N52: 0 | O52: 0 | P52: 0 | Q52: 0 | R52: 0
D53: Subsidio(-)/Contribucion(+) | E53: 0
B55: OCCIDENTE | C55: OPORTUNO | D55: Total | E55: =E16+E27-K16 -> 27783436 | F55: =F16 -> 2081192.4 | G55: =G16 -> 1148059.1 | H55: =H16 -> 546479.29 | I55: =I16 -> 4396569.8 | J55: =J16 -> 145789.07 | K55: =K16 -> 0 | L55: =L16 -> 1332065.3 | M55: =M16 -> 1532516.5 | ... S55: =S16 -> 0
D56: Subsidio(-)/Contribucion(+) | E56: =E27 -> 2947724.1
B58: CIUDAD LIMPIA-ACUEDUCTO | C58: OPORTUNO | D58: Total | E58: 0 | F58: 0 | G58: 0 | H58: 0 | I58: 0 | J58: 0 | K58: 0 | L58: 0 | M58: 0 | N58: 0 | O58: 0 | P58: 0 | Q58: 0 | R58: 0 | S58: 0
D59: Subsidio(-)/Contribucion(+) | E59: 0
B61: LIME
E62: Total | F62: Componente TDF | G62: Componente TTL | H62: Componente TVIAT | I62: Aprovechamiento | J62: CCSA Prest.Aprov. | K62: Especiales | L62: Componente TCS | M62: Componente TLU | N62: Componente TBL | O62: Componente TRT | P62: CCSA Prest. No Aprov. | Q62: Deb/Cred | R62: Deb/Cred-otros
D63: Vlr Servicio | E63: 51343920 | F63: 2602110 | G63: 1429988.8 | H63: 515936.95 | I63: 13400417 | J63: 521328 | K63: 28554.96 | L63: 4092012.5 | M63: 4006644.8 | N63: 14502764 | O63: 9664419.2 | P63: 579615.45 | Q63: 128.38 | R63: 0
D64: Vlr Intereses | E64: 47786.6 | F64: 3922.53 | G64: 2121.07 | H64: 1145.18 | I64: 10319.58 | J64: 371.38 | K64: 0 | L64: 3208.8 | M64: 3232.38 | N64: 15260.76 | O64: 7598.97 | P64: 605.77 | Q64: 0.18 | R64: 0
C65: E | D65: Total | E65: 51391707 | F65: 2606032.5 | G65: 1432109.8 | H65: 517082.13 | I65: 13410737 | J65: 521699.38 | K65: 28554.96 | L65: 4095221.3 | M65: 4009877.2 | N65: 14518025 | O65: 9672018.1 | P65: 580221.22 | Q65: 128.56 | R65: 0
B66: ENEL | C66: Total | E66: 51391707 | F66: 2606032.5 | G66: 1432109.8 | H66: 517082.13 | I66: 13410737 | J66: 521699.38 | K66: 28554.96 | L66: 4095221.3 | M66: 4009877.2 | N66: 14518025 | O66: 9672018.1 | P66: 580221.22 | Q66: 128.56 | R66: 0
D67: Vlr Servicio | E67: 6840138.1 | F67: 454112 | G67: 245161.57 | H67: 117090.1 | I67: 1872723.9 | J67: 60005.28 | K67: 0 | L67: 508018.52 | M67: 552024.64 | N67: 2050457.3 | O67: 910258.22 | P67: 70256.97 | Q67: 29.63 | R67: 0
D68: Vlr Intereses | E68: 709.39 | F68: 68.6 | G68: 38.73 | H68: 20.33 | I68: 148.28 | J68: 4.93 | K68: 0 | L68: 43.25 | M68: 42.04 | N68: 199.02 | O68: 136.2 | P68: 8.04 | Q68: -0.03 | R68: 0
C69: 1 | D69: Total | E69: 6840847.5 | F69: 454180.6 | G69: 245200.3 | H69: 117110.43 | I69: 1872872.2 | J69: 60010.21 | K69: 0 | L69: 508061.77 | M69: 552066.68 | N69: 2050656.3 | O69: 910394.42 | P69: 70265.01 | Q69: 29.6 | R69: 0
D70: Vlr Servicio | E70: 673112.23 | F70: 32650.05 | G70: 17891.02 | H70: 9047.72 | I70: 167209.89 | J70: 5398.62 | K70: 0 | L70: 55941.8 | M70: 60888.8 | N70: 234687.16 | O70: 81377.99 | P70: 8018.16 | Q70: 1.02 | R70: 0
C71: 2 | D71: Total | E71: 673112.23 | F71: 32650.05 | G71: 17891.02 | H71: 9047.72 | I71: 167209.89 | J71: 5398.62 | K71: 0 | L71: 55941.8 | M71: 60888.8 | N71: 234687.16 | O71: 81377.99 | P71: 8018.16 | Q71: 1.02 | R71: 0
D72: Vlr Servicio | E72: 20435057 | F72: 1240239.7 | G72: 689953.48 | H72: 216277.61 | I72: 5859087.4 | J72: 195777.3 | K72: 0 | L72: 1695471.1 | M72: 1662718.7 | N72: 6214723 | O72: 2429272.6 | P72: 231590.8 | Q72: -54.95 | R72: 0
D73: Vlr Intereses | E73: 702.71 | F73: 34.64 | G73: 19.29 | H73: 10.35 | I73: 188.6 | J73: 5.12 | K73: 0 | L73: 44.89 | M73: 57.5 | N73: 264.51 | O73: 69.3 | P73: 8.36 | Q73: 0.15 | R73: 0
C74: 5 | D74: Total | E74: 20435760 | F74: 1240274.4 | G74: 689972.77 | H74: 216287.96 | I74: 5859276 | J74: 195782.42 | K74: 0 | L74: 1695516 | M74: 1662776.2 | N74: 6214987.5 | O74: 2429341.9 | P74: 231599.16 | Q74: -54.8 | R74: 0
D75: Vlr Servicio | E75: 81263.29 | F75: 8070.53 | G75: 4576.92 | H75: 2482.05 | I75: 15776.58 | J75: 568.04 | K75: 0 | L75: 4982.79 | M75: 4911.41 | N75: 22701.82 | O75: 16262.61 | P75: 926.79 | Q75: 3.75 | R75: 0
C76: 9 | D76: Total | E76: 81263.29 | F76: 8070.53 | G76: 4576.92 | H76: 2482.05 | I76: 15776.58 | J76: 568.04 | K76: 0 | L76: 4982.79 | M76: 4911.41 | N76: 22701.82 | O76: 16262.61 | P76: 926.79 | Q76: 3.75 | R76: 0
B77: NUEVO ESQUEMA | C77: Total | E77: 28030983 | F77: 1735175.5 | G77: 957641.01 | H77: 344928.16 | I77: 7915134.7 | J77: 261759.29 | K77: 0 | L77: 2264502.4 | M77: 2280643.1 | N77: 8523032.8 | O77: 3437377 | P77: 310809.12 | Q77: -20.43 | R77: 0
D78: Vlr Servicio | E78: 17110679 | F78: 1114965.1 | G78: 643217.02 | H78: 278759.27 | I78: 4743645.5 | J78: 124686.84 | K78: 0 | L78: 1039349.2 | M78: 1361869.3 | N78: 5411757.2 | O78: 2250306.1 | P78: 142101.98 | Q78: 21.36 | R78: 0
D79: Vlr Intereses | E79: 5496.87 | F79: 560.72 | G79: 294.57 | H79: 160.58 | I79: 1113.88 | J79: 33.65 | K79: 0 | L79: 294.88 | M79: 330.22 | N79: 1524.41 | O79: 1129.12 | P79: 54.86 | Q79: -0.02 | R79: 0
C80: H | D80: Total | E80: 17116176 | F80: 1115525.8 | G80: 643511.59 | H80: 278919.85 | I80: 4744759.4 | J80: 124720.49 | K80: 0 | L80: 1039644.1 | M80: 1362199.6 | N80: 5413281.7 | O80: 2251435.3 | P80: 142156.84 | Q80: 21.34 | R80: 0
D81: Vlr Servicio | E81: 32351571 | F81: 2802163.5 | G81: 1486957.6 | H81: 716604.05 | I81: 7418941.5 | J81: 232182.66 | K81: 0 | L81: 2029167.7 | M81: 2313955.3 | N81: 9378853.3 | O81: 5650385 | P81: 322358.31 | Q81: 1.93 | R81: 0
D82: Vlr Intereses | E82: 565319.19 | F82: 88502.96 | G82: 46189.73 | H82: 14629.19 | I82: 80560.75 | J82: 2874.33 | K82: 0 | L82: 25174.27 | M82: 31831.15 | N82: 106543.83 | O82: 164313.7 | P82: 4695.18 | Q82: 4.1 | R82: 0
C83: O | D83: Total | E83: 32916890 | F83: 2890666.5 | G83: 1533147.3 | H83: 731233.24 | I83: 7499502.3 | J83: 235056.99 | K83: 0 | L83: 2054342 | M83: 2345786.4 | N83: 9485397.1 | O83: 5814698.7 | P83: 327053.49 | Q83: 6.03 | R83: 0
D84: Vlr Servicio | E84: 53826318 | F84: 9840743.7 | G84: 5329739.7 | H84: 2938001.1 | I84: 4729695.1 | J84: 121866.12 | K84: 0 | L84: 1109113.6 | M84: 1550787.7 | N84: 6188221 | O84: 21862538 | P84: 155603.12 | Q84: 8.48 | R84: 0
D85: Vlr Intereses | E85: 40047.6 | F85: 9707.52 | G85: 5489.99 | H85: 2917.7 | I85: 710.14 | J85: 28.8 | K85: 0 | L85: 249.94 | M85: 255.78 | N85: 1213.95 | O85: 19426.94 | P85: 46.91 | Q85: -0.07 | R85: 0
C86: T | D86: Total | E86: 53866365 | F86: 9850451.2 | G86: 5335229.7 | H86: 2940918.8 | I86: 4730405.3 | J86: 121894.92 | K86: 0 | L86: 1109363.6 | M86: 1551043.5 | N86: 6189435 | O86: 21881965 | P86: 155650.03 | Q86: 8.41 | R86: 0
B87: OCCIDENTE | C87: Total | E87: 1.0389943e+08 | F87: 13856644 | G87: 7511888.5 | H87: 3951071.9 | I87: 16974667 | J87: 481672.4 | K87: 0 | L87: 4203349.7 | M87: 5259029.5 | N87: 21088114 | O87: 29948099 | P87: 624860.36 | Q87: 35.78 | R87: 0
A88: Componente | B88: Total | E88: 1.8332212e+08 | F88: 18197852 | G88: 9901639.4 | H88: 4813082.2 | I88: 38300538 | J88: 1265131.1 | K88: 28554.96 | L88: 10563073 | M88: 11549550 | N88: 44129172 | O88: 43057494 | P88: 1515890.7 | Q88: 143.91 | R88: 0
D89: Subsidio(-)/Contribucion(+) | E89: -18164297 | F89: -693265.31 | G89: -389013.13 | H89: -209776.64 | I89: -4971553 | J89: -176925.19 | K89: 0 | L89: -1541962.2 | M89: -1497870.5 | N89: -7051526.6 | O89: -1344264.5 | P89: -288140.16 | Q89: 0 | R89: 0
C90: E | D90: Total | E90: -18164297 | F90: -693265.31 | G90: -389013.13 | H90: -209776.64 | I90: -4971553 | J90: -176925.19 | K90: 0 | L90: -1541962.2 | M90: -1497870.5 | N90: -7051526.6 | O90: -1344264.5 | P90: -288140.16 | Q90: 0 | R90: 0
B91: ENEL | C91: Total | E91: -18164297 | F91: -693265.31 | G91: -389013.13 | H91: -209776.64 | I91: -4971553 | J91: -176925.19 | K91: 0 | L91: -1541962.2 | M91: -1497870.5 | N91: -7051526.6 | O91: -1344264.5 | P91: -288140.16 | Q91: 0 | R91: 0
D92: Subsidio(-)/Contribucion(+) | E92: -1980469.9 | F92: -76573.37 | G92: -43012.32 | H92: -23132.33 | I92: -578166.06 | J92: -15167.61 | K92: 0 | L92: -150753.13 | M92: -170817.35 | N92: -748635.28 | O92: -149465.37 | P92: -24747.06 | Q92: 0 | R92: 0
C93: 1 | D93: Total | E93: -1980469.9 | F93: -76573.37 | G93: -43012.32 | H93: -23132.33 | I93: -578166.06 | J93: -15167.61 | K93: 0 | L93: -150753.13 | M93: -170817.35 | N93: -748635.28 | O93: -149465.37 | P93: -24747.06 | Q93: 0 | R93: 0
D94: Subsidio(-)/Contribucion(+) | E94: -241632.93 | F94: -9797.62 | G94: -5505.85 | H94: -2902.58 | I94: -68225.73 | J94: -2234.25 | K94: 0 | L94: -19598.29 | M94: -19781.05 | N94: -90737.12 | O94: -19205.14 | P94: -3645.3 | Q94: 0 | R94: 0
C95: 2 | D95: Total | E95: -241632.93 | F95: -9797.62 | G95: -5505.85 | H95: -2902.58 | I95: -68225.73 | J95: -2234.25 | K95: 0 | L95: -19598.29 | M95: -19781.05 | N95: -90737.12 | O95: -19205.14 | P95: -3645.3 | Q95: 0 | R95: 0
D96: Subsidio(-)/Contribucion(+) | E96: -7912371.1 | F96: -321556.94 | G96: -184379.29 | H96: -97803.02 | I96: -2235433.1 | J96: -73085.65 | K96: 0 | L96: -636486.21 | M96: -640153.78 | N96: -3002675.5 | O96: -602120.33 | P96: -118677.23 | Q96: 0 | R96: 0
C97: 5 | D97: Total | E97: -7912371.1 | F97: -321556.94 | G97: -184379.29 | H97: -97803.02 | I97: -2235433.1 | J97: -73085.65 | K97: 0 | L97: -636486.21 | M97: -640153.78 | N97: -3002675.5 | O97: -602120.33 | P97: -118677.23 | Q97: 0 | R97: 0
D98: Subsidio(-)/Contribucion(+) | E98: 6719.84 | F98: 0 | G98: 0 | H98: 0 | I98: 0 | J98: 181.3 | K98: 0 | L98: 0 | M98: 0 | N98: 6242.75 | O98: 0 | P98: 295.79 | Q98: 0 | R98: 0
C99: 9 | D99: Total | E99: 6719.84 | F99: 0 | G99: 0 | H99: 0 | I99: 0 | J99: 181.3 | K99: 0 | L99: 0 | M99: 0 | N99: 6242.75 | O99: 0 | P99: 295.79 | Q99: 0 | R99: 0
B100: NUEVO ESQUEMA | C100: Total | E100: -10127754 | F100: -407927.93 | G100: -232897.46 | H100: -123837.93 | I100: -2881824.9 | J100: -90306.21 | K100: 0 | L100: -806837.63 | M100: -830752.18 | N100: -3835805.2 | O100: -770790.84 | P100: -146773.8 | Q100: 0 | R100: 0
D101: Subsidio(-)/Contribucion(+) | E101: -3182911.7 | F101: -139157.84 | G101: -86072.83 | H101: -50455.48 | I101: -1005938.3 | J101: -25590.57 | K101: 0 | L101: -206580.44 | M101: -276320.95 | N101: -1228793.6 | O101: -123045.53 | P101: -40956.18 | Q101: 0 | R101: 0
C102: H | D102: Total | E102: -3182911.7 | F102: -139157.84 | G102: -86072.83 | H102: -50455.48 | I102: -1005938.3 | J102: -25590.57 | K102: 0 | L102: -206580.44 | M102: -276320.95 | N102: -1228793.6 | O102: -123045.53 | P102: -40956.18 | Q102: 0 | R102: 0
D103: Subsidio(-)/Contribucion(+) | E103: -4176689.8 | F103: 451770.66 | G103: 48673.05 | H103: 72202.01 | I103: -1893477.1 | J103: -59581.05 | K103: 0 | L103: -518650.72 | M103: -601656.88 | N103: -2836991.9 | O103: 1257256 | P103: -96233.83 | Q103: 0 | R103: 0
C104: O | D104: Total | E104: -4176689.8 | F104: 451770.66 | G104: 48673.05 | H104: 72202.01 | I104: -1893477.1 | J104: -59581.05 | K104: 0 | L104: -518650.72 | M104: -601656.88 | N104: -2836991.9 | O104: 1257256 | P104: -96233.83 | Q104: 0 | R104: 0
D105: Subsidio(-)/Contribucion(+) | E105: 522999.54 | F105: 54236.07 | G105: -13360.86 | H105: -8558.53 | I105: -495268.04 | J105: -11654.1 | K105: 0 | L105: -52422.98 | M105: -98595.04 | N105: -410478.9 | O105: 1577530.6 | P105: -18428.63 | Q105: 0 | R105: 0
C106: T | D106: Total | E106: 522999.54 | F106: 54236.07 | G106: -13360.86 | H106: -8558.53 | I106: -495268.04 | J106: -11654.1 | K106: 0 | L106: -52422.98 | M106: -98595.04 | N106: -410478.9 | O106: 1577530.6 | P106: -18428.63 | Q106: 0 | R106: 0
B107: OCCIDENTE | C107: Total | E107: -6836601.9 | F107: 366848.89 | G107: -50760.64 | H107: 13188 | I107: -3394683.4 | J107: -96825.72 | K107: 0 | L107: -777654.14 | M107: -976572.87 | N107: -4476264.4 | O107: 2711741.1 | P107: -155618.64 | Q107: 0 | R107: 0
A108: Subs/Cont | B108: Total | E108: -35128653 | F108: -734344.35 | G108: -672671.23 | H108: -320426.57 | I108: -11248061 | J108: -364057.12 | K108: 0 | L108: -3126454 | M108: -3305195.5 | N108: -15363596 | O108: 596685.7 | P108: -590532.6 | Q108: 0 | R108: 0
A109: Total | E109: 1.4819347e+08 | F109: 17463507 | G109: 9228968.1 | H109: 4492655.6 | I109: 27052477 | J109: 901073.95 | K109: 28554.96 | L109: 7436619.3 | M109: 8244354.2 | N109: 28765575 | O109: 43654180 | P109: 925358.1 | Q109: 143.91 | R109: 0
B140: TOTAL | C140: OPORTUNO | D140: Total | E140: =E88+E108-K88 -> 1.4816491e+08 | F140: =F88 -> 18197852 | G140: =G88 -> 9901639.4 | H140: =H88 -> 4813082.2 | I140: =I88 -> 38300538 | J140: =J88 -> 1265131.1 | K140: =K88 -> 28554.96 | L140: =L88 -> 10563073 | M140: =M88 -> 11549550 | ... R140: =R88 -> 0
D141: Subsidio(-)/Contribucion(+) | E141: =E108 -> -35128653
B143: RECIPROCIDAD | C143: OPORTUNO | D143: Total | E143: =E100+E77-K77 -> 17903228 | F143: =F77 -> 1735175.5 | G143: =G77 -> 957641.01 | H143: =H77 -> 344928.16 | I143: =I77 -> 7915134.7 | J143: =J77 -> 261759.29 | K143: =K77 -> 0 | L143: =L77 -> 2264502.4 | M143: =M77 -> 2280643.1 | ... R143: =R77 -> 0
D144: Subsidio(-)/Contribucion(+) | E144: =E100 -> -10127754
B146: ENEL | C146: OPORTUNO | D146: Total | E146: =E91+E66-K66 -> 33198855 | F146: =F66 -> 2606032.5 | G146: =G66 -> 1432109.8 | H146: =H66 -> 517082.13 | I146: =I66 -> 13410737 | J146: =J66 -> 521699.38 | K146: =K66 -> 28554.96 | L146: =L66 -> 4095221.3 | M146: =M66 -> 4009877.2 | ... R146: =R66 -> 0
D147: Subsidio(-)/Contribucion(+) | E147: =E91 -> -18164297
B149: ENERBIT | C149: OPORTUNO | D149: Total | E149: 0 | F149: 0 | G149: 0 | H149: 0 | I149: 0 | J149: 0 | K149: 0 | L149: 0 | M149: 0 | N149: 0 | O149: 0 | P149: 0 | Q149: 0 | R149: 0
D150: Subsidio(-)/Contribucion(+) | E150: 0
B152: OCCIDENTE | C152: OPORTUNO | D152: Total | E152: =E87+E107-K87 -> 97062829 | F152: =F87 -> 13856644 | G152: =G87 -> 7511888.5 | H152: =H87 -> 3951071.9 | I152: =I87 -> 16974667 | J152: =J87 -> 481672.4 | K152: =K87 -> 0 | L152: =L87 -> 4203349.7 | M152: =M87 -> 5259029.5 | ... R152: =R87 -> 0
D153: Subsidio(-)/Contribucion(+) | E153: =E107 -> -6836601.9
...

Sheet Reversion Pagos R4
B1: PROMOAMBIENTAL
D2: Total | E2: Componente TDF | F2: Componente TTL | G2: Componente TVIAT | H2: Aprovechamiento | I2: CCSA Prest.Aprov. | J2: Componente TCS | K2: Componente TLU | L2: Componente TBL | M2: Componente TRT | N2: CCSA Prest. No Aprov. | O2: Ajuste Decena | P2: SERVICIO ESPECIALES | Q2: Ajuste Recargo Aseo | R2: Otros
C3: Vlr Servicio | D3: -48725.8 | E3: -2974.76 | F3: -1679.55 | G3: -881.55 | H3: -11542.33 | I3: -391.85 | J3: -3437.25 | K3: -3322.9 | L3: -15733.99 | M3: -8124.53 | N3: -639.32 | O3: 2.23 | P3: 0 | Q3: 0 | R3: 0
B4: Componente | C4: Total | D4: -48725.8 | E4: -2974.76 | F4: -1679.55 | G4: -881.55 | H4: -11542.33 | I4: -391.85 | J4: -3437.25 | K4: -3322.9 | L4: -15733.99 | M4: -8124.53 | N4: -639.32 | O4: 2.23 | P4: 0 | Q4: 0 | R4: 0
C5: Subsidio(-)/Contribucion(+) | D5: -24364.2 | E5: -1487.39 | F5: -839.77 | G5: -440.78 | H5: -5771.33 | I5: -195.93 | J5: -1718.62 | K5: -1661.45 | L5: -7867 | M5: -4062.27 | N5: -319.66 | O5: 0 | P5: 0 | Q5: 0 | R5: 0
B6: Subs/Cont | C6: Total | D6: -24364.2 | E6: -1487.39 | F6: -839.77 | G6: -440.78 | H6: -5771.33 | I6: -195.93 | J6: -1718.62 | K6: -1661.45 | L6: -7867 | M6: -4062.27 | N6: -319.66 | O6: 0 | P6: 0 | Q6: 0 | R6: 0
A7: ENEL | B7: Total | D7: -73090 | E7: -4462.15 | F7: -2519.32 | G7: -1322.33 | H7: -17313.66 | I7: -587.78 | J7: -5155.87 | K7: -4984.35 | L7: -23600.99 | M7: -12186.8 | N7: -958.98 | O7: 2.23 | P7: 0 | Q7: 0 | R7: 0
A8: Total | D8: -73090 | E8: -4462.15 | F8: -2519.32 | G8: -1322.33 | H8: -17313.66 | I8: -587.78 | J8: -5155.87 | K8: -4984.35 | L8: -23600.99 | M8: -12186.8 | N8: -958.98 | O8: 2.23 | P8: 0 | Q8: 0 | R8: 0
A66: TOTAL | B66: OPORTUNO | C66: Total | D66: =D8-P8 -> -73090 | E66: =E4 -> -2974.76 | F66: =F4 -> -1679.55 | G66: =G4 -> -881.55 | H66: =H4 -> -11542.33 | I66: =I4 -> -391.85 | J66: =J4 -> -3437.25 | K66: =K4 -> -3322.9 | L66: =L4 -> -15733.99 | ... R66: =R4 -> 0
C67: Subsidio(-)/Contribucion(+) | D67: =D6 -> -24364.2
A69: RECIPROCIDAD | B69: OPORTUNO | C69: Total | D69: 0 | E69: 0 | F69: 0 | G69: 0 | H69: 0 | I69: 0 | J69: 0 | K69: 0 | L69: 0 | M69: 0 | N69: 0 | O69: 0 | P69: 0 | Q69: 0 | R69: 0
C70: Subsidio(-)/Contribucion(+) | D70: 0
A72: ENEL | B72: OPORTUNO | C72: Total | D72: =D7-P7 -> -73090 | E72: =E4 -> -2974.76 | F72: =F4 -> -1679.55 | G72: =G4 -> -881.55 | H72: =H4 -> -11542.33 | I72: =I4 -> -391.85 | J72: =J4 -> -3437.25 | K72: =K4 -> -3322.9 | L72: =L4 -> -15733.99 | ... R72: =R4 -> 0
C73: Subsidio(-)/Contribucion(+) | D73: =D6 -> -24364.2
A75: ENERBIT | B75: OPORTUNO | C75: Total | D75: 0 | E75: 0 | F75: 0 | G75: 0 | H75: 0 | I75: 0 | J75: 0 | K75: 0 | L75: 0 | M75: 0 | N75: 0 | O75: 0 | P75: 0 | Q75: 0 | R75: 0
C76: Subsidio(-)/Contribucion(+) | D76: 0
A78: OCCIDENTE | B78: OPORTUNO | C78: Total | D78: 0 | E78: 0 | F78: 0 | G78: 0 | H78: 0 | I78: 0 | J78: 0 | K78: 0 | L78: 0 | M78: 0 | N78: 0 | O78: 0 | P78: 0 | Q78: 0 | R78: 0
C79: Subsidio(-)/Contribucion(+) | D79: 0
A81: CIUDAD LIMPIA-ACUEDUCTO | B81: OPORTUNO | C81: Total | D81: 0 | E81: 0 | F81: 0 | G81: 0 | H81: 0 | I81: 0 | J81: 0 | K81: 0 | L81: 0 | M81: 0 | N81: 0 | O81: 0 | P81: 0 | Q81: 0 | R81: 0
C82: Subsidio(-)/Contribucion(+) | D82: 0
B84: LIME
D85: Total | E85: Componente TDF | F85: Componente TTL | G85: Componente TVIAT | H85: Aprovechamiento | I85: CCSA Prest.Aprov. | J85: Componente TCS | K85: Componente TLU | L85: Componente TBL | M85: Componente TRT | N85: CCSA Prest. No Aprov. | O85: Ajuste Decena | P85: SERVICIO ESPECIALES | Q85: Ajuste Recargo Aseo | R85: Otros
C86: Vlr Servicio | D86: -13979536 | E86: -1011021 | F86: -569741.9 | G86: -302808.68 | H86: -3143579.3 | I86: -114670.57 | J86: -999077.71 | K86: -992418.25 | L86: -4654848.1 | M86: -2004239.6 | N86: -187093.83 | O86: -37.31 | P86: 0 | Q86: 0 | R86: 0
C87: Vlr Intereses | D87: -233620.09 | E87: -22452.42 | F87: -8081.16 | G87: -2654.63 | H87: -44917.62 | I87: -2082.42 | J87: -18240.53 | K87: -18956.12 | L87: -65568.83 | M87: -47271.83 | N87: -3396.54 | O87: 2.01 | P87: 0 | Q87: 0 | R87: 0
B88: Componente | C88: Total | D88: -14213156 | E88: -1033473.4 | F88: -577823.06 | G88: -305463.31 | H88: -3188497 | I88: -116752.99 | J88: -1017318.2 | K88: -1011374.4 | L88: -4720416.9 | M88: -2051511.4 | N88: -190490.37 | O88: -35.3 | P88: 0 | Q88: 0 | R88: 0
C89: Subsidio(-)/Contribucion(+) | D89: 765564.32 | E89: -205919.7 | F89: -115649.85 | G89: -63315.96 | H89: 488474.53 | I89: 18030.1 | J89: 158157.98 | K89: 154048.7 | L89: 723098.08 | M89: -420776.85 | N89: 29417.29 | O89: 0 | P89: 0 | Q89: 0 | R89: 0
B90: Subs/Cont | C90: Total | D90: 765564.32 | E90: -205919.7 | F90: -115649.85 | G90: -63315.96 | H90: 488474.53 | I90: 18030.1 | J90: 158157.98 | K90: 154048.7 | L90: 723098.08 | M90: -420776.85 | N90: 29417.29 | O90: 0 | P90: 0 | Q90: 0 | R90: 0
A91: ENEL | B91: Total | D91: -13447592 | E91: -1239393.1 | F91: -693472.91 | G91: -368779.27 | H91: -2700022.4 | I91: -98722.89 | J91: -859160.26 | K91: -857325.67 | L91: -3997318.8 | M91: -2472288.3 | N91: -161073.08 | O91: -35.3 | P91: 0 | Q91: 0 | R91: 0
C92: Vlr Servicio | D92: -58047.64 | E92: -2786 | F92: -1572.46 | G92: -825.44 | H92: -16700.46 | I92: -517.68 | J92: -4541.08 | K92: -4465.33 | L92: -20259.13 | M92: -5531.04 | N92: -844.64 | O92: -4.38 | P92: 0 | Q92: 0 | R92: 0
C93: Vlr Intereses | D93: -15.66 | E93: -0.76 | F93: -0.43 | G93: -0.23 | H93: -4.05 | I93: -0.15 | J93: -1.28 | K93: -1.25 | L93: -5.71 | M93: -1.56 | N93: -0.24 | O93: 0 | P93: 0 | Q93: 0 | R93: 0
B94: Componente | C94: Total | D94: -58063.3 | E94: -2786.76 | F94: -1572.89 | G94: -825.67 | H94: -16704.51 | I94: -517.83 | J94: -4542.36 | K94: -4466.58 | L94: -20264.84 | M94: -5532.6 | N94: -844.88 | O94: -4.38 | P94: 0 | Q94: 0 | R94: 0
C95: Subsidio(-)/Contribucion(+) | D95: 33173.3 | E95: 1612.12 | F95: 910 | G95: 477.62 | H95: 9240.6 | I95: 299.72 | J95: 2629.12 | K95: 2585.26 | L95: 11729.28 | M95: 3200.56 | N95: 489.02 | O95: 0 | P95: 0 | Q95: 0 | R95: 0
B96: Subs/Cont | C96: Total | D96: 33173.3 | E96: 1612.12 | F96: 910 | G96: 477.62 | H96: 9240.6 | I96: 299.72 | J96: 2629.12 | K96: 2585.26 | L96: 11729.28 | M96: 3200.56 | N96: 489.02 | O96: 0 | P96: 0 | Q96: 0 | R96: 0
A97: OCCIDENTE | B97: Total | D97: -24890 | E97: -1174.64 | F97: -662.89 | G97: -348.05 | H97: -7463.91 | I97: -218.11 | J97: -1913.24 | K97: -1881.32 | L97: -8535.56 | M97: -2332.04 | N97: -355.86 | O97: -4.38 | P97: 0 | Q97: 0 | R97: 0
A98: Total | D98: -13472482 | E98: -1240567.7 | F98: -694135.8 | G98: -369127.32 | H98: -2707486.3 | I98: -98941 | J98: -861073.5 | K98: -859206.99 | L98: -4005854.4 | M98: -2474620.3 | N98: -161428.94 | O98: -39.68 | P98: 0 | Q98: 0 | R98: 0
A161: TOTAL | B161: OPORTUNO | C161: Total | D161: =D98-P98 -> -13472482 | E161: =E94+E88 -> -1036260.1 | F161: =F94+F88 -> -579395.95 | G161: =G94+G88 -> -306288.98 | H161: =H94+H88 -> -3205201.5 | I161: =I94+I88 -> -117270.82 | J161: =J94+J88 -> -1021860.6 | K161: =K94+K88 -> -1015840.9 | L161: =L94+L88 -> -4740681.8 | ... R161: =R94+R88 -> 0
C162: Subsidio(-)/Contribucion(+) | D162: =D96+D90 -> 798737.62
A164: RECIPROCIDAD | B164: OPORTUNO | C164: Total | D164: 0 | E164: 0 | F164: 0 | G164: 0 | H164: 0 | I164: 0 | J164: 0 | K164: 0 | L164: 0 | M164: 0 | N164: 0 | O164: 0 | P164: 0 | Q164: 0 | R164: 0
C165: Subsidio(-)/Contribucion(+) | D165: 0
A167: ENEL | B167: OPORTUNO | C167: Total | D167: =D91-P91 -> -13447592 | E167: =E88 -> -1033473.4 | F167: =F88 -> -577823.06 | G167: =G88 -> -305463.31 | H167: =H88 -> -3188497 | I167: =I88 -> -116752.99 | J167: =J88 -> -1017318.2 | K167: =K88 -> -1011374.4 | L167: =L88 -> -4720416.9 | ... R167: =R88 -> 0
C168: Subsidio(-)/Contribucion(+) | D168: =D90 -> 765564.32
A170: ENERBIT | B170: OPORTUNO | C170: Total | D170: 0 | E170: 0 | F170: 0 | G170: 0 | H170: 0 | I170: 0 | J170: 0 | K170: 0 | L170: 0 | M170: 0 | N170: 0 | O170: 0 | P170: 0 | Q170: 0 | R170: 0
C171: Subsidio(-)/Contribucion(+) | D171: 0
A173: OCCIDENTE | B173: OPORTUNO | C173: Total | D173: =D97-P97 -> -24890 | E173: =E94 -> -2786.76 | F173: =F94 -> -1572.89 | G173: =G94 -> -825.67 | H173: =H94 -> -16704.51 | I173: =I94 -> -517.83 | J173: =J94 -> -4542.36 | K173: =K94 -> -4466.58 | L173: =L94 -> -20264.84 | ... R173: =R94 -> 0
C174: Subsidio(-)/Contribucion(+) | D174: =D96 -> 33173.3
A176: CIUDAD LIMPIA-ACUEDUCTO | B176: OPORTUNO | C176: Total | D176: 0 | E176: 0 | F176: 0 | G176: 0 | H176: 0 | I176: 0 | J176: 0 | K176: 0 | L176: 0 | M176: 0 | N176: 0 | O176: 0 | P176: 0 | Q176: 0 | R176: 0
C177: Subsidio(-)/Contribucion(+) | D177: 0
B179: CIUDAD LIMPIA
D180: Total | E180: Componente TDF | F180: Componente TTL | G180: Componente TVIAT | H180: Aprovechamiento | I180: CCSA Prest.Aprov. | J180: Componente TCS | K180: Componente TLU | L180: Componente TBL | M180: Componente TRT | N180: CCSA Prest. No Aprov. | O180: Ajuste Decena | P180: SERVICIO ESPECIALES | Q180: Ajuste Recargo Aseo | R180: Otros
C181: Vlr Servicio | D181: -5300396.6 | E181: -266920.99 | F181: -151747.72 | G181: -79709.62 | H181: -1324855.6 | I181: -47299.87 | J181: -411237.59 | K181: -406044.91 | L181: -1913952.8 | M181: -621177.47 | N181: -77374.18 | O181: -75.73 | P181: 0 | Q181: 0 | R181: 0
C182: Vlr Intereses | D182: -13190.83 | E182: -1425.35 | F182: -806.4 | G182: -429.71 | H182: -2212.35 | I182: -83.37 | J182: -731.34 | K182: -716.14 | L182: -3293.42 | M182: -3354.87 | N182: -138 | O182: 0.12 | P182: 0 | Q182: 0 | R182: 0
B183: Componente | C183: Total | D183: -5313587.4 | E183: -268346.34 | F183: -152554.12 | G183: -80139.33 | H183: -1327068 | I183: -47383.24 | J183: -411968.93 | K183: -406761.05 | L183: -1917246.2 | M183: -624532.34 | N183: -77512.18 | O183: -75.61 | P183: 0 | Q183: 0 | R183: 0
C184: Subsidio(-)/Contribucion(+) | D184: 696233.39 | E184: 17764.59 | F184: 10022.19 | G184: 5230.07 | H184: 200028.75 | I184: 6936.39 | J184: 60845.81 | K184: 59558.35 | L184: 282324.82 | M184: 42205.1 | N184: 11317.32 | O184: 0 | P184: 0 | Q184: 0 | R184: 0
B185: Subs/Cont | C185: Total | D185: 696233.39 | E185: 17764.59 | F185: 10022.19 | G185: 5230.07 | H185: 200028.75 | I185: 6936.39 | J185: 60845.81 | K185: 59558.35 | L185: 282324.82 | M185: 42205.1 | N185: 11317.32 | O185: 0 | P185: 0 | Q185: 0 | R185: 0
A186: ENEL | B186: Total | D186: -4617354 | E186: -250581.75 | F186: -142531.93 | G186: -74909.26 | H186: -1127039.2 | I186: -40446.85 | J186: -351123.12 | K186: -347202.7 | L186: -1634921.4 | M186: -582327.24 | N186: -66194.86 | O186: -75.61 | P186: 0 | Q186: 0 | R186: 0
A187: Total | D187: -4617354 | E187: -250581.75 | F187: -142531.93 | G187: -74909.26 | H187: -1127039.2 | I187: -40446.85 | J187: -351123.12 | K187: -347202.7 | L187: -1634921.4 | M187: -582327.24 | N187: -66194.86 | O187: -75.61 | P187: 0 | Q187: 0 | R187: 0
A192: TOTAL | B192: OPORTUNO | C192: Total | D192: =D187-P187 -> -4617354 | E192: =E183 -> -268346.34 | F192: =F183 -> -152554.12 | G192: =G183 -> -80139.33 | H192: =H183 -> -1327068 | I192: =I183 -> -47383.24 | J192: =J183 -> -411968.93 | K192: =K183 -> -406761.05 | L192: =L183 -> -1917246.2 | ... R192: =R183 -> 0
C193: Subsidio(-)/Contribucion(+) | D193: =D185 -> 696233.39
A195: RECIPROCIDAD | B195: OPORTUNO | C195: Total | D195: 0 | E195: 0 | F195: 0 | G195: 0 | H195: 0 | I195: 0 | J195: 0 | K195: 0 | L195: 0 | M195: 0 | N195: 0 | O195: 0 | P195: 0 | Q195: 0 | R195: 0
C196: Subsidio(-)/Contribucion(+) | D196: 0
A198: ENEL | B198: OPORTUNO | C198: Total | D198: =D186-P186 -> -4617354 | E198: =E183 -> -268346.34 | F198: =F183 -> -152554.12 | G198: =G183 -> -80139.33 | H198: =H183 -> -1327068 | I198: =I183 -> -47383.24 | J198: =J183 -> -411968.93 | K198: =K183 -> -406761.05 | L198: =L183 -> -1917246.2 | ... R198: =R183 -> 0
C199: Subsidio(-)/Contribucion(+) | D199: =D185 -> 696233.39
A201: ENERBIT | B201: OPORTUNO | C201: Total | D201: 0 | E201: 0 | F201: 0 | G201: 0 | H201: 0 | I201: 0 | J201: 0 | K201: 0 | L201: 0 | M201: 0 | N201: 0 | O201: 0 | P201: 0 | Q201: 0 | R201: 0
C202: Subsidio(-)/Contribucion(+) | D202: 0
A204: OCCIDENTE | B204: OPORTUNO | C204: Total | D204: 0 | E204: 0 | F204: 0 | G204: 0 | H204: 0 | I204: 0 | J204: 0 | K204: 0 | L204: 0 | M204: 0 | N204: 0 | O204: 0 | P204: 0 | Q204: 0 | R204: 0
C205: Subsidio(-)/Contribucion(+) | D205: 0
A207: CIUDAD LIMPIA-ACUEDUCTO | B207: OPORTUNO | C207: Total | D207: 0 | E207: 0 | F207: 0 | G207: 0 | H207: 0 | I207: 0 | J207: 0 | K207: 0 | L207: 0 | M207: 0 | N207: 0 | O207: 0 | P207: 0 | Q207: 0 | R207: 0
C208: Subsidio(-)/Contribucion(+) | D208: 0
B210: BOGOTA LIMPIA
D211: Total | E211: Componente TDF | F211: Componente TTL | G211: Componente TVIAT | H211: Aprovechamiento | I211: CCSA Prest.Aprov. | J211: Componente TCS | K211: Componente TLU | L211: Componente TBL | M211: Componente TRT | N211: CCSA Prest. No Aprov. | O211: Ajuste Decena | P211: SERVICIO ESPECIALES | Q211: Ajuste Recargo Aseo | R211: Otros
C212: Vlr Servicio | D212: -16028064 | E212: -894905.66 | F212: -492355.87 | G212: -260069.56 | H212: -3577229.8 | I212: -128056.41 | J212: -1134137.2 | K212: -1154847.2 | L212: -5786675.9 | M212: -2388638 | N212: -211133.08 | O212: -15.19 | P212: 0 | Q212: 0 | R212: 0
C213: Vlr Intereses | D213: -873377.98 | E213: -87078.56 | F213: -39363.66 | G213: -16918.14 | H213: -156091.38 | I213: -5880.81 | J213: -52156.61 | K213: -64640.54 | L213: -223252.32 | M213: -218532.37 | N213: -9702.68 | O213: 6.65 | P213: 0 | Q213: 0 | R213: 232.44
B214: Componente | C214: Total | D214: -16901442 | E214: -981984.22 | F214: -531719.53 | G214: -276987.7 | H214: -3733321.2 | I214: -133937.22 | J214: -1186293.9 | K214: -1219487.8 | L214: -6009928.2 | M214: -2607170.3 | N214: -220835.76 | O214: -8.54 | P214: 0 | Q214: 0 | R214: 232.44
C215: Subsidio(-)/Contribucion(+) | D215: 2262595.9 | E215: 33634.28 | F215: 15223.86 | G215: 8043.35 | H215: 652911.02 | I215: 21769 | J215: 190935.03 | K215: 209235.4 | L215: 1005246.8 | M215: 90086.02 | N215: 35511.21 | O215: 0 | P215: 0 | Q215: 0 | R215: 0
B216: Subs/Cont | C216: Total | D216: 2262595.9 | E216: 33634.28 | F216: 15223.86 | G216: 8043.35 | H216: 652911.02 | I216: 21769 | J216: 190935.03 | K216: 209235.4 | L216: 1005246.8 | M216: 90086.02 | N216: 35511.21 | O216: 0 | P216: 0 | Q216: 0 | R216: 0
A217: ENEL | B217: Total | D217: -14638846 | E217: -948349.94 | F217: -516495.67 | G217: -268944.35 | H217: -3080410.2 | I217: -112168.22 | J217: -995358.83 | K217: -1010252.4 | L217: -5004681.5 | M217: -2517084.3 | N217: -185324.55 | O217: -8.54 | P217: 0 | Q217: 0 | R217: 232.44
C218: Vlr Servicio | D218: -565175.82 | E218: -37306.34 | F218: -19442.38 | G218: -11255.47 | H218: -125115.98 | I218: -3102.84 | J218: -27218.32 | K218: -39044.45 | L218: -198435.12 | M218: -99198.9 | N218: -5062.58 | O218: 6.56 | P218: 0 | Q218: 0 | R218: 0
C219: Vlr Intereses | D219: -8.36 | E219: -0.84 | F219: -0.39 | G219: -0.21 | H219: -1.63 | I219: -0.04 | J219: -0.35 | K219: -0.43 | L219: -2.12 | M219: -2.28 | N219: -0.07 | O219: 0 | P219: 0 | Q219: 0 | R219: 0
B220: Componente | C220: Total | D220: -565184.18 | E220: -37307.18 | F220: -19442.77 | G220: -11255.68 | H220: -125117.61 | I220: -3102.88 | J220: -27218.67 | K220: -39044.88 | L220: -198437.24 | M220: -99201.18 | N220: -5062.65 | O220: 6.56 | P220: 0 | Q220: 0 | R220: 0
C221: Subsidio(-)/Contribucion(+) | D221: 15644.18 | E221: -3723.05 | F221: -2050.97 | G221: -1232.73 | H221: 10995.31 | I221: 269.17 | J221: 2361.18 | K221: 3071.33 | L221: 15308.82 | M221: -9794.02 | N221: 439.14 | O221: 0 | P221: 0 | Q221: 0 | R221: 0
B222: Subs/Cont | C222: Total | D222: 15644.18 | E222: -3723.05 | F222: -2050.97 | G222: -1232.73 | H222: 10995.31 | I222: 269.17 | J222: 2361.18 | K222: 3071.33 | L222: 15308.82 | M222: -9794.02 | N222: 439.14 | O222: 0 | P222: 0 | Q222: 0 | R222: 0
A223: NUEVO ESQUEMA | B223: Total | D223: -549540 | E223: -41030.23 | F223: -21493.74 | G223: -12488.41 | H223: -114122.3 | I223: -2833.71 | J223: -24857.49 | K223: -35973.55 | L223: -183128.42 | M223: -108995.2 | N223: -4623.51 | O223: 6.56 | P223: 0 | Q223: 0 | R223: 0
C224: Vlr Servicio | D224: -862480.46 | E224: -39715.51 | F224: -22469.48 | G224: -11974.92 | H224: -209441.11 | I224: -7713.34 | J224: -64306.22 | K224: -62901.08 | L224: -325046.79 | M224: -106961.73 | N224: -11960.9 | O224: 10.62 | P224: 0 | Q224: 0 | R224: 0
B225: Componente | C225: Total | D225: -862480.46 | E225: -39715.51 | F225: -22469.48 | G225: -11974.92 | H225: -209441.11 | I225: -7713.34 | J225: -64306.22 | K225: -62901.08 | L225: -325046.79 | M225: -106961.73 | N225: -11960.9 | O225: 10.62 | P225: 0 | Q225: 0 | R225: 0
C226: Subsidio(-)/Contribucion(+) | D226: 387536.46 | E226: 18163.82 | F226: 10270.54 | G226: 5450.54 | H226: 92818.77 | I226: 3350.44 | J226: 29390.52 | K226: 28751.18 | L226: 145188.92 | M226: 48685.04 | N226: 5466.69 | O226: 0 | P226: 0 | Q226: 0 | R226: 0
B227: Subs/Cont | C227: Total | D227: 387536.46 | E227: 18163.82 | F227: 10270.54 | G227: 5450.54 | H227: 92818.77 | I227: 3350.44 | J227: 29390.52 | K227: 28751.18 | L227: 145188.92 | M227: 48685.04 | N227: 5466.69 | O227: 0 | P227: 0 | Q227: 0 | R227: 0
A228: OCCIDENTE | B228: Total | D228: -474944 | E228: -21551.69 | F228: -12198.94 | G228: -6524.38 | H228: -116622.34 | I228: -4362.9 | J228: -34915.7 | K228: -34149.9 | L228: -179857.87 | M228: -58276.69 | N228: -6494.21 | O228: 10.62 | P228: 0 | Q228: 0 | R228: 0
A229: Total | D229: -15663330 | E229: -1010931.9 | F229: -550188.35 | G229: -287957.14 | H229: -3311154.8 | I229: -119364.83 | J229: -1055132 | K229: -1080375.8 | L229: -5367667.7 | M229: -2684356.2 | N229: -196442.27 | O229: 8.64 | P229: 0 | Q229: 0 | R229: 232.44
A306: TOTAL | B306: OPORTUNO | C306: Total | D306: =D229-P229 -> -15663330 | E306: =E225+E220+E214 -> -1059006.9 | F306: =F225+F220+F214 -> -573631.78 | G306: =G225+G220+G214 -> -300218.3 | H306: =H225+H220+H214 -> -4067879.9 | I306: =I225+I220+I214 -> -144753.44 | J306: =J225+J220+J214 -> -1277818.8 | K306: =K225+K220+K214 -> -1321433.8 | L306: =L225+L220+L214 -> -6533412.2 | ... R306: =R225+R220+R214 -> 232.44
C307: Subsidio(-)/Contribucion(+) | D307: =D227+D222+D216 -> 2665776.6
A309: RECIPROCIDAD | B309: OPORTUNO | C309: Total | D309: =D223-P223 -> -549540 | E309: =E220 -> -37307.18 | F309: =F220 -> -19442.77 | G309: =G220 -> -11255.68 | H309: =H220 -> -125117.61 | I309: =I220 -> -3102.88 | J309: =J220 -> -27218.67 | K309: =K220 -> -39044.88 | L309: =L220 -> -198437.24 | ... R309: =R220 -> 0
C310: Subsidio(-)/Contribucion(+) | D310: =D222 -> 15644.18
A312: ENEL | B312: OPORTUNO | C312: Total | D312: =D217-P217 -> -14638846 | E312: =E214 -> -981984.22 | F312: =F214 -> -531719.53 | G312: =G214 -> -276987.7 | H312: =H214 -> -3733321.2 | I312: =I214 -> -133937.22 | J312: =J214 -> -1186293.9 | K312: =K214 -> -1219487.8 | L312: =L214 -> -6009928.2 | ... R312: =R214 -> 232.44
C313: Subsidio(-)/Contribucion(+) | D313: =D216 -> 2262595.9
A315: ENERBIT | B315: OPORTUNO | C315: Total | D315: 0 | E315: 0 | F315: 0 | G315: 0 | H315: 0 | I315: 0 | J315: 0 | K315: 0 | L315: 0 | M315: 0 | N315: 0 | O315: 0 | P315: 0 | Q315: 0 | R315: 0
C316: Subsidio(-)/Contribucion(+) | D316: 0
A318: OCCIDENTE | B318: OPORTUNO | C318: Total | D318: =D228-P228 -> -474944 | E318: =E225 -> -39715.51 | F318: =F225 -> -22469.48 | G318: =G225 -> -11974.92 | H318: =H225 -> -209441.11 | I318: =I225 -> -7713.34 | J318: =J225 -> -64306.22 | K318: =K225 -> -62901.08 | L318: =L225 -> -325046.79 | ... R318: =R225 -> 0
C319: Subsidio(-)/Contribucion(+) | D319: =D227 -> 387536.46
A321: CIUDAD LIMPIA-ACUEDUCTO | B321: OPORTUNO | C321: Total | D321: 0 | E321: 0 | F321: 0 | G321: 0 | H321: 0 | I321: 0 | J321: 0 | K321: 0 | L321: 0 | M321: 0 | N321: 0 | O321: 0 | P321: 0 | Q321: 0 | R321: 0
C322: Subsidio(-)/Contribucion(+) | D322: 0
...

Sheet SALDOS POR NOTA
B1: PROMOAMBIENTAL
C2: Total | D2: Componente TDF | E2: Componente TTL | F2: Componente TVIAT | G2: Aprovechamiento | H2: CCSA Prest.Aprov. | I2: Especiales | J2: Componente TCS | K2: Componente TLU | L2: Componente TBL | M2: Componente TRT | N2: CCSA Prest. No Aprov. | O2: Deb/Cred
B3: Vlr Servicio | C3: 803959.68 | D3: 65039.95 | E3: 36337.02 | F3: 19274.13 | G3: 155423.91 | H3: 5618.35 | I3: 0 | J3: 56003.23 | K3: 48167.15 | L3: 226758.45 | M3: 182170.76 | N3: 9166.69 | O3: 0.04
A4: Componente | B4: Total | C4: 803959.68 | D4: 65039.95 | E4: 36337.02 | F4: 19274.13 | G4: 155423.91 | H4: 5618.35 | I4: 0 | J4: 56003.23 | K4: 48167.15 | L4: 226758.45 | M4: 182170.76 | N4: 9166.69 | O4: 0.04
B5: Subsidio(-)/Contribucion(+) | C5: 2996.3 | D5: 701.47 | E5: 403.84 | F5: 207.9 | G5: -7189.94 | H5: -331.56 | I5: 0 | J5: -1228.7 | K5: 624.41 | L5: 3023.5 | M5: 7326.36 | N5: -540.98 | O5: 0
A6: Subs/Cont | B6: Total | C6: 2996.3 | D6: 701.47 | E6: 403.84 | F6: 207.9 | G6: -7189.94 | H6: -331.56 | I6: 0 | J6: -1228.7 | K6: 624.41 | L6: 3023.5 | M6: 7326.36 | N6: -540.98 | O6: 0
A7: Total | C7: 806955.98 | D7: 65741.42 | E7: 36740.86 | F7: 19482.03 | G7: 148233.97 | H7: 5286.79 | I7: 0 | J7: 54774.53 | K7: 48791.56 | L7: 229781.95 | M7: 189497.12 | N7: 8625.71 | O7: 0.04
B9: Total | C9: =C7-I7 -> 806955.98 | D9: =D4 -> 65039.95 | E9: =E4 -> 36337.02 | F9: =F4 -> 19274.13 | G9: =G4 -> 155423.91 | H9: =H4 -> 5618.35 | I9: =I4 -> 0 | J9: =J4 -> 56003.23 | K9: =K4 -> 48167.15 | ... P9: =P4 -> 0
B10: Subsidio(-)/Contribucion(+) | C10: =C6 -> 2996.3
B13: LIME
C14: Total | D14: Componente TDF | E14: Componente TTL | F14: Componente TVIAT | G14: Aprovechamiento | H14: CCSA Prest.Aprov. | I14: Especiales | J14: Componente TCS | K14: Componente TLU | L14: Componente TBL | M14: Componente TRT | N14: CCSA Prest. No Aprov. | O14: Deb/Cred
B15: Vlr Servicio | C15: 931073.72 | D15: 42296.72 | E15: 23907.98 | F15: 12706.35 | G15: 265979.53 | H15: 11995.53 | I15: 0 | J15: 66026.12 | K15: 73645.62 | L15: 345565.65 | M15: 81955.14 | N15: 6998.74 | O15: -3.66
A16: Componente | B16: Total | C16: 931073.72 | D16: 42296.72 | E16: 23907.98 | F16: 12706.35 | G16: 265979.53 | H16: 11995.53 | I16: 0 | J16: 66026.12 | K16: 73645.62 | L16: 345565.65 | M16: 81955.14 | N16: 6998.74 | O16: -3.66
B17: Subsidio(-)/Contribucion(+) | C17: -424218.36 | D17: -25301.13 | E17: -14256.81 | F17: -7179.68 | G17: -99943.77 | H17: -3389 | I17: 0 | J17: -52251.81 | K17: -30693.42 | L17: -136897.35 | M17: -48943.73 | N17: -5361.66 | O17: 0
A18: Subs/Cont | B18: Total | C18: -424218.36 | D18: -25301.13 | E18: -14256.81 | F18: -7179.68 | G18: -99943.77 | H18: -3389 | I18: 0 | J18: -52251.81 | K18: -30693.42 | L18: -136897.35 | M18: -48943.73 | N18: -5361.66 | O18: 0
A19: Total | C19: 506855.36 | D19: 16995.59 | E19: 9651.17 | F19: 5526.67 | G19: 166035.76 | H19: 8606.53 | I19: 0 | J19: 13774.31 | K19: 42952.2 | L19: 208668.3 | M19: 33011.41 | N19: 1637.08 | O19: -3.66
B21: Total | C21: =C19-I19 -> 506855.36 | D21: =D16 -> 42296.72 | E21: =E16 -> 23907.98 | F21: =F16 -> 12706.35 | G21: =G16 -> 265979.53 | H21: =H16 -> 11995.53 | I21: =I16 -> 0 | J21: =J16 -> 66026.12 | K21: =K16 -> 73645.62 | ... P21: =P16 -> 0
B22: Subsidio(-)/Contribucion(+) | C22: =C18 -> -424218.36
B25: CIUDAD LIMPIA
C26: Total | D26: Componente TDF | E26: Componente TTL | F26: Componente TVIAT | G26: Aprovechamiento | H26: CCSA Prest.Aprov. | I26: Especiales | J26: Componente TCS | K26: Componente TLU | L26: Componente TBL | M26: Componente TRT | N26: CCSA Prest. No Aprov. | O26: Deb/Cred
B27: Vlr Servicio | C27: 114219.07 | D27: 6267.13 | E27: 3538.42 | F27: 1857.22 | G27: 42966.81 | H27: 743.08 | I27: 0 | J27: 6518.28 | K27: 6322.58 | L27: 29933.14 | M27: 14860.01 | N27: 1212.4 | O27: 0
A28: Componente | B28: Total | C28: 114219.07 | D28: 6267.13 | E28: 3538.42 | F28: 1857.22 | G28: 42966.81 | H28: 743.08 | I28: 0 | J28: 6518.28 | K28: 6322.58 | L28: 29933.14 | M28: 14860.01 | N28: 1212.4 | O28: 0
B29: Subsidio(-)/Contribucion(+) | C29: 4655.77 | D29: 1594.44 | E29: 900.22 | F29: 472.5 | G29: -4328.45 | H29: 37.15 | I29: 0 | J29: 325.91 | K29: 316.13 | L29: 1496.66 | M29: 3780.59 | N29: 60.62 | O29: 0
A30: Subs/Cont | B30: Total | C30: 4655.77 | D30: 1594.44 | E30: 900.22 | F30: 472.5 | G30: -4328.45 | H30: 37.15 | I30: 0 | J30: 325.91 | K30: 316.13 | L30: 1496.66 | M30: 3780.59 | N30: 60.62 | O30: 0
A31: Total | C31: 118874.84 | D31: 7861.57 | E31: 4438.64 | F31: 2329.72 | G31: 38638.36 | H31: 780.23 | I31: 0 | J31: 6844.19 | K31: 6638.71 | L31: 31429.8 | M31: 18640.6 | N31: 1273.02 | O31: 0
B33: Total | C33: =C31-I31 -> 118874.84 | D33: =D28 -> 6267.13 | E33: =E28 -> 3538.42 | F33: =F28 -> 1857.22 | G33: =G28 -> 42966.81 | H33: =H28 -> 743.08 | I33: =I28 -> 0 | J33: =J28 -> 6518.28 | K33: =K28 -> 6322.58 | ... P33: =P28 -> 0
B34: Subsidio(-)/Contribucion(+) | C34: =C30 -> 4655.77
B37: BOGOTA LIMPIA
C38: Total | D38: Componente TDF | E38: Componente TTL | F38: Componente TVIAT | G38: Aprovechamiento | H38: CCSA Prest.Aprov. | I38: Especiales | J38: Componente TCS | K38: Componente TLU | L38: Componente TBL | M38: Componente TRT | N38: CCSA Prest. No Aprov. | O38: Deb/Cred
B39: Vlr Servicio | C39: 1030030.2 | D39: 30353.42 | E39: 17272.31 | F39: 7260.85 | G39: 195770.56 | H39: 5001.67 | I39: 0 | J39: 31654.75 | K39: 16169.51 | L39: 630665.63 | M39: 92025.49 | N39: 3836.24 | O39: 19.81
B40: Vlr Intereses | C40: -5455.56 | D40: 0 | E40: 0 | F40: 0 | G40: 0 | H40: 0 | I40: 0 | J40: 0 | K40: 0 | L40: -5455.76 | M40: 0 | N40: 0 | O40: 0.2
A41: Componente | B41: Total | C41: 1024574.7 | D41: 30353.42 | E41: 17272.31 | F41: 7260.85 | G41: 195770.56 | H41: 5001.67 | I41: 0 | J41: 31654.75 | K41: 16169.51 | L41: 625209.87 | M41: 92025.49 | N41: 3836.24 | O41: 20.01
B42: Subsidio(-)/Contribucion(+) | C42: -706260.2 | D42: -35225.22 | E42: -19886.85 | F42: -10438.97 | G42: -172708.87 | H42: -4226.24 | I42: 0 | J42: -37074.28 | K42: -53305.25 | L42: -273257.91 | M42: -93241.08 | N42: -6895.53 | O42: 0
A43: Subs/Cont | B43: Total | C43: -706260.2 | D43: -35225.22 | E43: -19886.85 | F43: -10438.97 | G43: -172708.87 | H43: -4226.24 | I43: 0 | J43: -37074.28 | K43: -53305.25 | L43: -273257.91 | M43: -93241.08 | N43: -6895.53 | O43: 0
A44: Total | C44: 318314.48 | D44: -4871.8 | E44: -2614.54 | F44: -3178.12 | G44: 23061.69 | H44: 775.43 | I44: 0 | J44: -5419.53 | K44: -37135.74 | L44: 351951.96 | M44: -1215.59 | N44: -3059.29 | O44: 20.01
B46: Total | C46: =C44-I44 -> 318314.48 | D46: =D41 -> 30353.42 | E46: =E41 -> 17272.31 | F46: =F41 -> 7260.85 | G46: =G41 -> 195770.56 | H46: =H41 -> 5001.67 | I46: =I41 -> 0 | J46: =J41 -> 31654.75 | K46: =K41 -> 16169.51 | ... P46: =P41 -> 0
B47: Subsidio(-)/Contribucion(+) | C47: =C43 -> -706260.2
B50: AREA LIMPIA
C51: Total | D51: Componente TDF | E51: Componente TTL | F51: Componente TVIAT | G51: Aprovechamiento | H51: CCSA Prest.Aprov. | I51: Especiales | J51: Componente TCS | K51: Componente TLU | L51: Componente TBL | M51: Componente TRT | N51: CCSA Prest. No Aprov. | O51: Deb/Cred
B52: Vlr Servicio | C52: 0 | D52: 0 | E52: 0 | F52: 0 | G52: 0 | H52: 0 | I52: 0 | J52: 0 | K52: 0 | L52: 0 | M52: 0 | N52: 0 | O52: 0
B53: Vlr Intereses | C53: 0 | D53: 0 | E53: 0 | F53: 0 | G53: 0 | H53: 0 | I53: 0 | J53: 0 | K53: 0 | L53: 0 | M53: 0 | N53: 0 | O53: 0
A54: Componente | B54: Total | C54: 0 | D54: 0 | E54: 0 | F54: 0 | G54: 0 | H54: 0 | I54: 0 | J54: 0 | K54: 0 | L54: 0 | M54: 0 | N54: 0 | O54: 0
B55: Subsidio(-)/Contribucion(+) | C55: 0 | D55: 0 | E55: 0 | F55: 0 | G55: 0 | H55: 0 | I55: 0 | J55: 0 | K55: 0 | L55: 0 | M55: 0 | N55: 0 | O55: 0
A56: Subs/Cont | B56: Total | C56: 0 | D56: 0 | E56: 0 | F56: 0 | G56: 0 | H56: 0 | I56: 0 | J56: 0 | K56: 0 | L56: 0 | M56: 0 | N56: 0 | O56: 0
A57: Total | C57: 0 | D57: 0 | E57: 0 | F57: 0 | G57: 0 | H57: 0 | I57: 0 | J57: 0 | K57: 0 | L57: 0 | M57: 0 | N57: 0 | O57: 0
B59: Total | C59: =C57-I57 -> 0 | D59: =D54 -> 0 | E59: =E54 -> 0 | F59: =F54 -> 0 | G59: =G54 -> 0 | H59: =H54 -> 0 | I59: =I54 -> 0 | J59: =J54 -> 0 | K59: =K54 -> 0 | ... P59: =P54 -> 0
B60: Subsidio(-)/Contribucion(+) | C60: =C56 -> 0

Sheet RETRIBUCION NEGATIVA
B1: PROMOAMBIENTAL
C2: Total | D2: Componente TDF | E2: Componente TTL | F2: Componente TVIAT | G2: Aprovechamiento | H2: CCSA Prest.Aprov. | I2: Especiales | J2: Componente TCS | K2: Componente TLU | L2: Componente TBL | M2: Componente TRT | N2: CCSA Prest. No Aprov. | O2: Deb/Cred
B3: Vlr Intereses | C3: 0 | D3: 0 | E3: 0 | F3: 0 | G3: 0 | H3: 0 | I3: 0 | J3: 0 | K3: 0 | L3: 0 | M3: 0 | N3: 0 | O3: 0
B4: Vlr Servicio | C4: 0 | D4: 0 | E4: 0 | F4: 0 | G4: 0 | H4: 0 | I4: 0 | J4: 0 | K4: 0 | L4: 0 | M4: 0 | N4: 0 | O4: 0
A5: Componente | B5: Total | C5: 0 | D5: 0 | E5: 0 | F5: 0 | G5: 0 | H5: 0 | I5: 0 | J5: 0 | K5: 0 | L5: 0 | M5: 0 | N5: 0 | O5: 0
B6: Subsidio(-)/Contribucion(+) | C6: 0 | D6: 0 | E6: 0 | F6: 0 | G6: 0 | H6: 0 | I6: 0 | J6: 0 | K6: 0 | L6: 0 | M6: 0 | N6: 0 | O6: 0
A7: Subs/Cont | B7: Total | C7: 0 | D7: 0 | E7: 0 | F7: 0 | G7: 0 | H7: 0 | I7: 0 | J7: 0 | K7: 0 | L7: 0 | M7: 0 | N7: 0 | O7: 0
A8: Total | C8: 0 | D8: 0 | E8: 0 | F8: 0 | G8: 0 | H8: 0 | I8: 0 | J8: 0 | K8: 0 | L8: 0 | M8: 0 | N8: 0 | O8: 0
B10: Total | C10: =C8-I8 -> 0 | D10: =D5 -> 0 | E10: =E5 -> 0 | F10: =F5 -> 0 | G10: =G5 -> 0 | H10: =H5 -> 0 | I10: =I5 -> 0 | J10: =J5 -> 0 | K10: =K5 -> 0 | ... O10: =O5 -> 0
B11: Subsidio(-)/Contribucion(+) | C11: =C7 -> 0
B14: LIME
C15: Total | D15: Componente TDF | E15: Componente TTL | F15: Componente TVIAT | G15: Aprovechamiento | H15: CCSA Prest.Aprov. | I15: Especiales | J15: Componente TCS | K15: Componente TLU | L15: Componente TBL | M15: Componente TRT | N15: CCSA Prest. No Aprov. | O15: Deb/Cred
B16: Vlr Intereses | C16: 0 | D16: 0 | E16: 0 | F16: 0 | G16: 0 | H16: 0 | I16: 0 | J16: 0 | K16: 0 | L16: 0 | M16: 0 | N16: 0 | O16: 0
B17: Vlr Servicio | C17: 0 | D17: 0 | E17: 0 | F17: 0 | G17: 0 | H17: 0 | I17: 0 | J17: 0 | K17: 0 | L17: 0 | M17: 0 | N17: 0 | O17: 0
A18: Componente | B18: Total | C18: 0 | D18: 0 | E18: 0 | F18: 0 | G18: 0 | H18: 0 | I18: 0 | J18: 0 | K18: 0 | L18: 0 | M18: 0 | N18: 0 | O18: 0
B19: Subsidio(-)/Contribucion(+) | C19: 0 | D19: 0 | E19: 0 | F19: 0 | G19: 0 | H19: 0 | I19: 0 | J19: 0 | K19: 0 | L19: 0 | M19: 0 | N19: 0 | O19: 0
A20: Subs/Cont | B20: Total | C20: 0 | D20: 0 | E20: 0 | F20: 0 | G20: 0 | H20: 0 | I20: 0 | J20: 0 | K20: 0 | L20: 0 | M20: 0 | N20: 0 | O20: 0
A21: Total | C21: 0 | D21: 0 | E21: 0 | F21: 0 | G21: 0 | H21: 0 | I21: 0 | J21: 0 | K21: 0 | L21: 0 | M21: 0 | N21: 0 | O21: 0
B23: Total | C23: =C21-I21 -> 0 | D23: =D18 -> 0 | E23: =E18 -> 0 | F23: =F18 -> 0 | G23: =G18 -> 0 | H23: =H18 -> 0 | I23: =I18 -> 0 | J23: =J18 -> 0 | K23: =K18 -> 0 | ... O23: =O18 -> 0
B24: Subsidio(-)/Contribucion(+) | C24: =C20 -> 0
B27: CIUDAD LIMPIA
C28: Total | D28: Componente TDF | E28: Componente TTL | F28: Componente TVIAT | G28: Aprovechamiento | H28: CCSA Prest.Aprov. | I28: Especiales | J28: Componente TCS | K28: Componente TLU | L28: Componente TBL | M28: Componente TRT | N28: CCSA Prest. No Aprov. | O28: Deb/Cred
B29: Vlr Intereses | C29: 0 | D29: 0 | E29: 0 | F29: 0 | G29: 0 | H29: 0 | I29: 0 | J29: 0 | K29: 0 | L29: 0 | M29: 0 | N29: 0 | O29: 0
B30: Vlr Servicio | C30: 0 | D30: 0 | E30: 0 | F30: 0 | G30: 0 | H30: 0 | I30: 0 | J30: 0 | K30: 0 | L30: 0 | M30: 0 | N30: 0 | O30: 0
A31: Componente | B31: Total | C31: 0 | D31: 0 | E31: 0 | F31: 0 | G31: 0 | H31: 0 | I31: 0 | J31: 0 | K31: 0 | L31: 0 | M31: 0 | N31: 0 | O31: 0
B32: Subsidio(-)/Contribucion(+) | C32: 0 | D32: 0 | E32: 0 | F32: 0 | G32: 0 | H32: 0 | I32: 0 | J32: 0 | K32: 0 | L32: 0 | M32: 0 | N32: 0 | O32: 0
A33: Subs/Cont | B33: Total | C33: 0 | D33: 0 | E33: 0 | F33: 0 | G33: 0 | H33: 0 | I33: 0 | J33: 0 | K33: 0 | L33: 0 | M33: 0 | N33: 0 | O33: 0
A34: Total | C34: 0 | D34: 0 | E34: 0 | F34: 0 | G34: 0 | H34: 0 | I34: 0 | J34: 0 | K34: 0 | L34: 0 | M34: 0 | N34: 0 | O34: 0
B36: Total | C36: =C34-I34 -> 0 | D36: =D31 -> 0 | E36: =E31 -> 0 | F36: =F31 -> 0 | G36: =G31 -> 0 | H36: =H31 -> 0 | I36: =I31 -> 0 | J36: =J31 -> 0 | K36: =K31 -> 0 | ... O36: =O31 -> 0
B37: Subsidio(-)/Contribucion(+) | C37: =C33 -> 0
B40: BOGOTA LIMPIA
C41: Total | D41: Componente TDF | E41: Componente TTL | F41: Componente TVIAT | G41: Aprovechamiento | H41: CCSA Prest.Aprov. | I41: Especiales | J41: Componente TCS | K41: Componente TLU | L41: Componente TBL | M41: Componente TRT | N41: CCSA Prest. No Aprov. | O41: Deb/Cred
B42: Vlr Intereses | C42: 0 | D42: 0 | E42: 0 | F42: 0 | G42: 0 | H42: 0 | I42: 0 | J42: 0 | K42: 0 | L42: 0 | M42: 0 | N42: 0 | O42: 0
B43: Vlr Servicio | C43: 0 | D43: 0 | E43: 0 | F43: 0 | G43: 0 | H43: 0 | I43: 0 | J43: 0 | K43: 0 | L43: 0 | M43: 0 | N43: 0 | O43: 0
A44: Componente | B44: Total | C44: 0 | D44: 0 | E44: 0 | F44: 0 | G44: 0 | H44: 0 | I44: 0 | J44: 0 | K44: 0 | L44: 0 | M44: 0 | N44: 0 | O44: 0
B45: Subsidio(-)/Contribucion(+) | C45: 0 | D45: 0 | E45: 0 | F45: 0 | G45: 0 | H45: 0 | I45: 0 | J45: 0 | K45: 0 | L45: 0 | M45: 0 | N45: 0 | O45: 0
A46: Subs/Cont | B46: Total | C46: 0 | D46: 0 | E46: 0 | F46: 0 | G46: 0 | H46: 0 | I46: 0 | J46: 0 | K46: 0 | L46: 0 | M46: 0 | N46: 0 | O46: 0
A47: Total | C47: 0 | D47: 0 | E47: 0 | F47: 0 | G47: 0 | H47: 0 | I47: 0 | J47: 0 | K47: 0 | L47: 0 | M47: 0 | N47: 0 | O47: 0
B49: Total | C49: =C47-I47 -> 0 | D49: =D44 -> 0 | E49: =E44 -> 0 | F49: =F44 -> 0 | G49: =G44 -> 0 | H49: =H44 -> 0 | I49: =I44 -> 0 | J49: =J44 -> 0 | K49: =K44 -> 0 | ... O49: =O44 -> 0
B50: Subsidio(-)/Contribucion(+) | C50: =C46 -> 0
B53: AREA LIMPIA
C54: Total | D54: Componente TDF | E54: Componente TTL | F54: Componente TVIAT | G54: Aprovechamiento | H54: CCSA Prest.Aprov. | I54: Especiales | J54: Componente TCS | K54: Componente TLU | L54: Componente TBL | M54: Componente TRT | N54: CCSA Prest. No Aprov. | O54: Deb/Cred
B55: Vlr Servicio | C55: 0 | D55: 0 | E55: 0 | F55: 0 | G55: 0 | H55: 0 | I55: 0 | J55: 0 | K55: 0 | L55: 0 | M55: 0 | N55: 0 | O55: 0
A56: Componente | B56: Total | C56: 0 | D56: 0 | E56: 0 | F56: 0 | G56: 0 | H56: 0 | I56: 0 | J56: 0 | K56: 0 | L56: 0 | M56: 0 | N56: 0 | O56: 0
B57: Subsidio(-)/Contribucion(+) | C57: 0 | D57: 0 | E57: 0 | F57: 0 | G57: 0 | H57: 0 | I57: 0 | J57: 0 | K57: 0 | L57: 0 | M57: 0 | N57: 0 | O57: 0
A58: Subs/Cont | B58: Total | C58: 0 | D58: 0 | E58: 0 | F58: 0 | G58: 0 | H58: 0 | I58: 0 | J58: 0 | K58: 0 | L58: 0 | M58: 0 | N58: 0 | O58: 0
A59: Total | C59: 0 | D59: 0 | E59: 0 | F59: 0 | G59: 0 | H59: 0 | I59: 0 | J59: 0 | K59: 0 | L59: 0 | M59: 0 | N59: 0 | O59: 0
B61: Total | C61: =C59-I59 -> 0 | D61: =D56 -> 0 | E61: =E56 -> 0 | F61: =F56 -> 0 | G61: =G56 -> 0 | H61: =H56 -> 0 | I61: =I56 -> 0 | J61: =J56 -> 0 | K61: =K56 -> 0 | ... O61: =O56 -> 0
B62: Subsidio(-)/Contribucion(+) | C62: =C58 -> 0

Sheet AJUSTES - SF-T
F3: PROCERASEO S.A.S. | I3: NIT: 901 153 639 - 0 | M3: Codigo Remuneración: | N3: ='CONSOLIDADO_TOTAL RECAUDO'!N3 -> 2026082 | U3: PROCERASEO S.A.S. | W3: NIT: 901 153 639 - 0 | AA3: Codigo Remuneración: | AC3: =N3 -> 2026082
F4: 3. ESQUEMA FINANCIERO DEL SERVICIO PUBLICO DE ASEO | U4: 3. ESQUEMA FINANCIERO DEL SERVICIO PUBLICO DE ASEO
F5: Resoluciòn UAESP Número 27 de 2018 | U5: Resoluciòn UAESP Número 27 de 2018
C6: Fecha de Proceso: | D6: ='CONSOLIDADO_TOTAL RECAUDO'!D6 -> 46267 | F6: SALDOS A FAVOR POR NOTA | U6: =+F6 -> SALDOS A FAVOR POR NOTA
C7: Hora: | D7: ='CONSOLIDADO_TOTAL RECAUDO'!D7 -> 0.58333333 | F7: Fecha Desde: | H7: ='CONSOLIDADO_TOTAL RECAUDO'!G7 -> 46250 | J7: Feha Hasta: | K7: ='CONSOLIDADO_TOTAL RECAUDO'!K7 -> 46265 | U7: =F7 -> Fecha Desde: | V7: =H7 -> 46250 | X7: =J7 -> Feha Hasta: | Y7: =K7 -> 46265
B8: ASE | C8: Concesionarios | D8: Recaudo Total | E8: Recaudo por disposicion final | F8: Recaudo por tratamiento de lixiviados | G8: Recaudo por Componente VIAT ( Decreto 2412/2018) | H8: Recaudo por aprovechamiento | I8: Recaudo del componente de comercializacion para Aprovechamiento (11,4%) | J8: Balance de subsidio o contribuciones | K8: RECAUDO BASE DE REMUNERACION | L8: Costo de la Interventoría | M8: REMUNERACION FINAL | N8: Conceptos especiales | O8: REMUNERACION FINAL MAS CONCEPTOS ESPECIALES | S8: ASE | T8: Concesionarios | U8: Tarifa de Comercialización del Servicio. ( TCS) | V8: Tarifa de Limpieza Urbana del Servicio. ( TLU) | W8: Tarifa de Barrido y Limpieza del Servicio. ( TBL) | X8: Tarifa de Recolección y Transporte del Servicio. (TRT) | Y8: Recaudo del componente de comercializacion para Aprovechamiento (18,6%) | Z8: Costo de la Interventoría | AA8: Ajuste a la decena | AB8: Conceptos especiales | AC8: Diferencial Balance S / C (Fac vs Rec) | AD8: Balance S / C Con Baase en (Recaudo) | AE8: REMUNERACION FINAL MAS CONCEPTOS ESPECIALES
B9: 1 | C9: PROMOAMBIENTAL DISTRITO S.A.S. ESP. | D9: ='SALDOS POR NOTA'!C9 -> 806955.98 | E9: ='SALDOS POR NOTA'!D9 -> 65039.95 | F9: ='SALDOS POR NOTA'!E9 -> 36337.02 | G9: ='SALDOS POR NOTA'!F9 -> 19274.13 | H9: ='SALDOS POR NOTA'!G9 -> 155423.91 | I9: ='SALDOS POR NOTA'!H9 -> 5618.35 | J9: 0 | K9: =D9-E9-F9-G9-H9-I9-J9 -> 525262.62 | L9: 0 | M9: =K9-L9 -> 525262.62 | N9: ='SALDOS POR NOTA'!I9 -> 0 | O9: =M9+N9 -> 525262.62 | S9: 1 | T9: PROMOAMBIENTAL DISTRITO S.A.S. ESP. | U9: ='SALDOS POR NOTA'!J9 -> 56003.23 | V9: ='SALDOS POR NOTA'!K9 -> 48167.15 | W9: ='SALDOS POR NOTA'!L9 -> 226758.45 | X9: ='SALDOS POR NOTA'!M9 -> 182170.76 | Y9: ='SALDOS POR NOTA'!N9 -> 9166.69 | Z9: =L9*-1 -> 0 | AA9: ='SALDOS POR NOTA'!O9 -> 0.04 | AB9: =N9 -> 0 | AC9: =-J9+AD9 -> 2996.3 | AD9: ='SALDOS POR NOTA'!C10 -> 2996.3 | AE9: =SUM(U9:AC9) -> 525262.62 | AF9: =(AE9-O9) -> 0 | AG9: =AF9=0 -> TRUE
B10: 2 | C10: LIMPIEZA METROPOLITANA S.A. ESP. | D10: ='SALDOS POR NOTA'!C21 -> 506855.36 | E10: ='SALDOS POR NOTA'!D21 -> 42296.72 | F10: ='SALDOS POR NOTA'!E21 -> 23907.98 | G10: ='SALDOS POR NOTA'!F21 -> 12706.35 | H10: ='SALDOS POR NOTA'!G21 -> 265979.53 | I10: ='SALDOS POR NOTA'!H21 -> 11995.53 | J10: 0 | K10: =D10-E10-F10-G10-H10-I10-J10 -> 149969.25 | L10: 0 | M10: =K10-L10 -> 149969.25 | N10: ='SALDOS POR NOTA'!I21 -> 0 | O10: =M10+N10 -> 149969.25 | S10: 2 | T10: LIMPIEZA METROPOLITANA S.A. ESP. | U10: ='SALDOS POR NOTA'!J21 -> 66026.12 | V10: ='SALDOS POR NOTA'!K21 -> 73645.62 | W10: ='SALDOS POR NOTA'!L21 -> 345565.65 | X10: ='SALDOS POR NOTA'!M21 -> 81955.14 | Y10: ='SALDOS POR NOTA'!N21 -> 6998.74 | Z10: =L10*-1 -> 0 | AA10: ='SALDOS POR NOTA'!O21 -> -3.66 | AB10: =N10 -> 0 | AC10: =-J10+AD10 -> -424218.36 | AD10: ='SALDOS POR NOTA'!C22 -> -424218.36 | AE10: =SUM(U10:AC10) -> 149969.25 | AF10: =(AE10-O10) -> -2.910383e-11 | AG10: =AF10=0 -> FALSE
B11: 3 | C11: CIUDAD LIMPIA BOGOTA S.A. ESP. | D11: ='SALDOS POR NOTA'!C33 -> 118874.84 | E11: ='SALDOS POR NOTA'!D33 -> 6267.13 | F11: ='SALDOS POR NOTA'!E33 -> 3538.42 | G11: ='SALDOS POR NOTA'!F33 -> 1857.22 | H11: ='SALDOS POR NOTA'!G33 -> 42966.81 | I11: ='SALDOS POR NOTA'!H33 -> 743.08 | J11: 0 | K11: =D11-E11-F11-G11-H11-I11-J11 -> 63502.18 | L11: 0 | M11: =K11-L11 -> 63502.18 | N11: ='SALDOS POR NOTA'!I33 -> 0 | O11: =M11+N11 -> 63502.18 | S11: 3 | T11: CIUDAD LIMPIA BOGOTA S.A. ESP. | U11: ='SALDOS POR NOTA'!J33 -> 6518.28 | V11: ='SALDOS POR NOTA'!K33 -> 6322.58 | W11: ='SALDOS POR NOTA'!L33 -> 29933.14 | X11: ='SALDOS POR NOTA'!M33 -> 14860.01 | Y11: ='SALDOS POR NOTA'!N33 -> 1212.4 | Z11: =L11*-1 -> 0 | AA11: ='SALDOS POR NOTA'!O33 -> 0 | AB11: =N11 -> 0 | AC11: =-J11+AD11 -> 4655.77 | AD11: ='SALDOS POR NOTA'!C34 -> 4655.77 | AE11: =SUM(U11:AC11) -> 63502.18 | AF11: =(AE11-O11) -> 1.4551915e-11 | AG11: =AF11=0 -> FALSE
B12: 4 | C12: BOGOTA LIMPIA S.A.S. ESP. | D12: ='SALDOS POR NOTA'!C46 -> 318314.48 | E12: ='SALDOS POR NOTA'!D46 -> 30353.42 | F12: ='SALDOS POR NOTA'!E46 -> 17272.31 | G12: ='SALDOS POR NOTA'!F46 -> 7260.85 | H12: ='SALDOS POR NOTA'!G46 -> 195770.56 | I12: ='SALDOS POR NOTA'!H46 -> 5001.67 | J12: 0 | K12: =D12-E12-F12-G12-H12-I12-J12 -> 62655.67 | L12: 0 | M12: =K12-L12 -> 62655.67 | N12: ='SALDOS POR NOTA'!I46 -> 0 | O12: =M12+N12 -> 62655.67 | S12: 4 | T12: BOGOTA LIMPIA S.A.S. ESP. | U12: ='SALDOS POR NOTA'!J46 -> 31654.75 | V12: ='SALDOS POR NOTA'!K46 -> 16169.51 | W12: ='SALDOS POR NOTA'!L46 -> 625209.87 | X12: ='SALDOS POR NOTA'!M46 -> 92025.49 | Y12: ='SALDOS POR NOTA'!N46 -> 3836.24 | Z12: =L12*-1 -> 0 | AA12: ='SALDOS POR NOTA'!O46 -> 20.01 | AB12: =N12 -> 0 | AC12: =-J12+AD12 -> -706260.2 | AD12: ='SALDOS POR NOTA'!C47 -> -706260.2 | AE12: =SUM(U12:AC12) -> 62655.67 | AF12: =(AE12-O12) -> 1.4551915e-11 | AG12: =AF12=0 -> FALSE
B13: 5 | C13: AREA LIMPIA DISTRITO CAPITAL S.A.S. ESP. | D13: ='SALDOS POR NOTA'!C59 -> 0 | E13: ='SALDOS POR NOTA'!D59 -> 0 | F13: ='SALDOS POR NOTA'!E59 -> 0 | G13: ='SALDOS POR NOTA'!F59 -> 0 | H13: ='SALDOS POR NOTA'!G59 -> 0 | I13: ='SALDOS POR NOTA'!H59 -> 0 | J13: 0 | K13: =D13-E13-F13-G13-H13-I13-J13 -> 0 | L13: 0 | M13: =K13-L13 -> 0 | N13: ='SALDOS POR NOTA'!I59 -> 0 | O13: =M13+N13 -> 0 | S13: 5 | T13: AREA LIMPIA DISTRITO CAPITAL S.A.S. ESP. | U13: ='SALDOS POR NOTA'!J59 -> 0 | V13: ='SALDOS POR NOTA'!K59 -> 0 | W13: ='SALDOS POR NOTA'!L59 -> 0 | X13: ='SALDOS POR NOTA'!M59 -> 0 | Y13: ='SALDOS POR NOTA'!N59 -> 0 | Z13: =L13*-1 -> 0 | AA13: ='SALDOS POR NOTA'!O59 -> 0 | AB13: =N13 -> 0 | AC13: =-J13+AD13 -> 0 | AD13: ='SALDOS POR NOTA'!C60 -> 0 | AE13: =SUM(U13:AC13) -> 0 | AF13: =(AE13-O13) -> 0 | AG13: =AF13=0 -> TRUE
C14: TOTAL | D14: =SUM(D9:D13) -> 1751000.7 | E14: =SUM(E9:E13) -> 143957.22 | F14: =SUM(F9:F13) -> 81055.73 | G14: =SUM(G9:G13) -> 41098.55 | H14: =SUM(H9:H13) -> 660140.81 | I14: =SUM(I9:I13) -> 23358.63 | J14: =SUM(J9:J13) -> 0 | K14: =SUM(K9:K13) -> 801389.72 | ... O14: =SUM(O9:O13) -> 801389.72 | T14: TOTAL | U14: =SUM(U9:U13) -> 160202.38 | V14: =SUM(V9:V13) -> 144304.86 | W14: =SUM(W9:W13) -> 1227467.1 | X14: =SUM(X9:X13) -> 371011.4 | Y14: =SUM(Y9:Y13) -> 21214.07 | Z14: =SUM(Z9:Z13) -> 0 | AA14: =SUM(AA9:AA13) -> 16.39 | AB14: =SUM(AB9:AB13) -> 0 | ... AF14: =SUM(AF9:AF13) -> 0 | AG14: =AF14=0 -> TRUE
Y16: =SUM(U14:Y14) -> 1924199.8
F18: Firma autorizada
F22: PROCERASEO S.A.S. | I22: NIT: 901 153 639 - 0 | M22: Codigo Remuneración: | N22: =N3 -> 2026082 | U22: PROCERASEO S.A.S. | W22: NIT: 901 153 639 - 0 | AA22: Codigo Remuneración: | AC22: =N22 -> 2026082
F23: 3. ESQUEMA FINANCIERO DEL SERVICIO PUBLICO DE ASEO | U23: 3. ESQUEMA FINANCIERO DEL SERVICIO PUBLICO DE ASEO
F24: Resoluciòn UAESP Número 27 de 2018 | U24: Resoluciòn UAESP Número 27 de 2018
C25: Fecha de Proceso: | D25: =D6 -> 46267 | F25: RETRIBUCION NEGATIVA | U25: =+F25 -> RETRIBUCION NEGATIVA
C26: Hora: | D26: =D7 -> 0.58333333 | F26: Fecha Desde: | H26: =H7 -> 46250 | J26: Feha Hasta: | K26: =K7 -> 46265 | U26: =F26 -> Fecha Desde: | V26: =H26 -> 46250 | X26: =J26 -> Feha Hasta: | Y26: =K26 -> 46265
B27: ASE | C27: Concesionarios | D27: Recaudo Total | E27: Recaudo por disposicion final | F27: Recaudo por tratamiento de lixiviados | G27: Recaudo por Componente VIAT ( Decreto 2412/2018) | H27: Recaudo por aprovechamiento | I27: Recaudo del componente de comercializacion para Aprovechamiento (11,4%) | J27: Balance de subsidio o contribuciones | K27: RECAUDO BASE DE REMUNERACION | L27: Costo de la Interventoría | M27: REMUNERACION FINAL | N27: Conceptos especiales | O27: REMUNERACION FINAL MAS CONCEPTOS ESPECIALES | S27: ASE | T27: Concesionarios | U27: Tarifa de Comercialización del Servicio. ( TCS) | V27: Tarifa de Limpieza Urbana del Servicio. ( TLU) | W27: Tarifa de Barrido y Limpieza del Servicio. ( TBL) | X27: Tarifa de Recolección y Transporte del Servicio. (TRT) | Y27: Recaudo del componente de comercializacion para Aprovechamiento (18,6%) | Z27: Costo de la Interventoría | AA27: Ajuste a la decena | AB27: Conceptos especiales | AC27: Diferencial Balance S / C (Fac vs Rec) | AD27: Balance S / C Con Baase en (Recaudo) | AE27: REMUNERACION FINAL MAS CONCEPTOS ESPECIALES
B28: 1 | C28: PROMOAMBIENTAL DISTRITO S.A.S. ESP. | D28: ='RETRIBUCION NEGATIVA'!C10 -> 0 | E28: ='RETRIBUCION NEGATIVA'!D10 -> 0 | F28: ='RETRIBUCION NEGATIVA'!E10 -> 0 | G28: ='RETRIBUCION NEGATIVA'!F10 -> 0 | H28: ='RETRIBUCION NEGATIVA'!G10 -> 0 | I28: ='RETRIBUCION NEGATIVA'!H10 -> 0 | J28: 0 | K28: =D28-E28-F28-H28-I28-J28-G28 -> 0 | L28: 0 | M28: =K28-L28 -> 0 | N28: ='RETRIBUCION NEGATIVA'!I10 -> 0 | O28: =M28+N28 -> 0 | S28: 1 | T28: PROMOAMBIENTAL DISTRITO S.A.S. ESP. | U28: ='RETRIBUCION NEGATIVA'!J10 -> 0 | V28: ='RETRIBUCION NEGATIVA'!K10 -> 0 | W28: ='RETRIBUCION NEGATIVA'!L10 -> 0 | X28: ='RETRIBUCION NEGATIVA'!M10 -> 0 | Y28: ='RETRIBUCION NEGATIVA'!N10 -> 0 | Z28: =L28*-1 -> 0 | AA28: ='RETRIBUCION NEGATIVA'!O10 -> 0 | AB28: =N28 -> 0 | AC28: =-J28+AD28 -> 0 | AD28: ='RETRIBUCION NEGATIVA'!C11 -> 0 | AE28: =SUM(U28:AC28) -> 0 | AF28: =(AE28-O28) -> 0 | AG28: =AF28=0 -> TRUE
B29: 2 | C29: LIMPIEZA METROPOLITANA S.A. ESP. | D29: ='RETRIBUCION NEGATIVA'!C23 -> 0 | E29: ='RETRIBUCION NEGATIVA'!D23 -> 0 | F29: ='RETRIBUCION NEGATIVA'!E23 -> 0 | G29: ='RETRIBUCION NEGATIVA'!F23 -> 0 | H29: ='RETRIBUCION NEGATIVA'!G23 -> 0 | I29: ='RETRIBUCION NEGATIVA'!H23 -> 0 | J29: 0 | K29: =D29-E29-F29-H29-I29-J29-G29 -> 0 | L29: 0 | M29: =K29-L29 -> 0 | N29: ='RETRIBUCION NEGATIVA'!I23 -> 0 | O29: =M29+N29 -> 0 | S29: 2 | T29: LIMPIEZA METROPOLITANA S.A. ESP. | U29: ='RETRIBUCION NEGATIVA'!J23 -> 0 | V29: ='RETRIBUCION NEGATIVA'!K23 -> 0 | W29: ='RETRIBUCION NEGATIVA'!L23 -> 0 | X29: ='RETRIBUCION NEGATIVA'!M23 -> 0 | Y29: ='RETRIBUCION NEGATIVA'!N23 -> 0 | Z29: =L29*-1 -> 0 | AA29: ='RETRIBUCION NEGATIVA'!O23 -> 0 | AB29: =N29 -> 0 | AC29: =-J29+AD29 -> 0 | AD29: ='RETRIBUCION NEGATIVA'!C24 -> 0 | AE29: =SUM(U29:AC29) -> 0 | AF29: =(AE29-O29) -> 0 | AG29: =AF29=0 -> TRUE
B30: 3 | C30: CIUDAD LIMPIA BOGOTA S.A. ESP. | D30: ='RETRIBUCION NEGATIVA'!C36 -> 0 | E30: ='RETRIBUCION NEGATIVA'!D36 -> 0 | F30: ='RETRIBUCION NEGATIVA'!E36 -> 0 | G30: ='RETRIBUCION NEGATIVA'!F36 -> 0 | H30: ='RETRIBUCION NEGATIVA'!G36 -> 0 | I30: ='RETRIBUCION NEGATIVA'!H36 -> 0 | J30: 0 | K30: =D30-E30-F30-H30-I30-J30-G30 -> 0 | L30: 0 | M30: =K30-L30 -> 0 | N30: ='RETRIBUCION NEGATIVA'!I36 -> 0 | O30: =M30+N30 -> 0 | S30: 3 | T30: CIUDAD LIMPIA BOGOTA S.A. ESP. | U30: ='RETRIBUCION NEGATIVA'!J36 -> 0 | V30: ='RETRIBUCION NEGATIVA'!K36 -> 0 | W30: ='RETRIBUCION NEGATIVA'!L36 -> 0 | X30: ='RETRIBUCION NEGATIVA'!M36 -> 0 | Y30: ='RETRIBUCION NEGATIVA'!N36 -> 0 | Z30: =L30*-1 -> 0 | AA30: ='RETRIBUCION NEGATIVA'!O36 -> 0 | AB30: =N30 -> 0 | AC30: =-J30+AD30 -> 0 | AD30: ='RETRIBUCION NEGATIVA'!C37 -> 0 | AE30: =SUM(U30:AC30) -> 0 | AF30: =(AE30-O30) -> 0 | AG30: =AF30=0 -> TRUE
B31: 4 | C31: BOGOTA LIMPIA S.A.S. ESP. | D31: ='RETRIBUCION NEGATIVA'!C49 -> 0 | E31: ='RETRIBUCION NEGATIVA'!D49 -> 0 | F31: ='RETRIBUCION NEGATIVA'!E49 -> 0 | G31: ='RETRIBUCION NEGATIVA'!F49 -> 0 | H31: ='RETRIBUCION NEGATIVA'!G49 -> 0 | I31: ='RETRIBUCION NEGATIVA'!H49 -> 0 | J31: 0 | K31: =D31-E31-F31-H31-I31-J31-G31 -> 0 | L31: 0 | M31: =K31-L31 -> 0 | N31: ='RETRIBUCION NEGATIVA'!I49 -> 0 | O31: =M31+N31 -> 0 | S31: 4 | T31: BOGOTA LIMPIA S.A.S. ESP. | U31: ='RETRIBUCION NEGATIVA'!J49 -> 0 | V31: ='RETRIBUCION NEGATIVA'!K49 -> 0 | W31: ='RETRIBUCION NEGATIVA'!L49 -> 0 | X31: ='RETRIBUCION NEGATIVA'!M49 -> 0 | Y31: ='RETRIBUCION NEGATIVA'!N49 -> 0 | Z31: =L31*-1 -> 0 | AA31: ='RETRIBUCION NEGATIVA'!O49 -> 0 | AB31: =N31 -> 0 | AC31: =-J31+AD31 -> 0 | AD31: ='RETRIBUCION NEGATIVA'!C50 -> 0 | AE31: =SUM(U31:AC31) -> 0 | AF31: =(AE31-O31) -> 0 | AG31: =AF31=0 -> TRUE
B32: 5 | C32: AREA LIMPIA DISTRITO CAPITAL S.A.S. ESP. | D32: ='RETRIBUCION NEGATIVA'!C61 -> 0 | E32: ='RETRIBUCION NEGATIVA'!D61 -> 0 | F32: ='RETRIBUCION NEGATIVA'!E61 -> 0 | G32: ='RETRIBUCION NEGATIVA'!F61 -> 0 | H32: ='RETRIBUCION NEGATIVA'!G61 -> 0 | I32: ='RETRIBUCION NEGATIVA'!H61 -> 0 | J32: 0 | K32: =D32-E32-F32-H32-I32-J32-G32 -> 0 | L32: 0 | M32: =K32-L32 -> 0 | N32: ='RETRIBUCION NEGATIVA'!I61 -> 0 | O32: =M32+N32 -> 0 | S32: 5 | T32: AREA LIMPIA DISTRITO CAPITAL S.A.S. ESP. | U32: ='RETRIBUCION NEGATIVA'!J61 -> 0 | V32: ='RETRIBUCION NEGATIVA'!K61 -> 0 | W32: ='RETRIBUCION NEGATIVA'!L61 -> 0 | X32: ='RETRIBUCION NEGATIVA'!M61 -> 0 | Y32: ='RETRIBUCION NEGATIVA'!N61 -> 0 | Z32: =L32*-1 -> 0 | AA32: ='RETRIBUCION NEGATIVA'!O61 -> 0 | AB32: =N32 -> 0 | AC32: =-J32+AD32 -> 0 | AD32: ='RETRIBUCION NEGATIVA'!C62 -> 0 | AE32: =SUM(U32:AC32) -> 0 | AF32: =(AE32-O32) -> 0 | AG32: =AF32=0 -> TRUE
C33: TOTAL | D33: =SUM(D28:D32) -> 0 | E33: =SUM(E28:E32) -> 0 | F33: =SUM(F28:F32) -> 0 | G33: =SUM(G28:G32) -> 0 | H33: =SUM(H28:H32) -> 0 | I33: =SUM(I28:I32) -> 0 | J33: =SUM(J28:J32) -> 0 | K33: =SUM(K28:K32) -> 0 | ... O33: =SUM(O28:O32) -> 0 | T33: TOTAL | U33: =SUM(U28:U32) -> 0 | V33: =SUM(V28:V32) -> 0 | W33: =SUM(W28:W32) -> 0 | X33: =SUM(X28:X32) -> 0 | Y33: =SUM(Y28:Y32) -> 0 | Z33: =SUM(Z28:Z32) -> 0 | AA33: =SUM(AA28:AA32) -> 0 | AB33: =SUM(AB28:AB32) -> 0 | ... AF33: =SUM(AF28:AF32) -> 0 | AG33: =AF33=0 -> TRUE
J35: VALIDADOR DE POSTIVIOS EN REMUNERACION NEGATIVA | M35: =IF(MAX(D28:O32,U28:AE32)>0.9,"ERROR",TRUE) -> TRUE | Y35: =SUM(U33:Y33) -> 0
F37: Firma autorizada
F41: PROCERASEO S.A.S. | I41: NIT: 901 153 639 - 0 | M41: Codigo Remuneración: | N41: =N3 -> 2026082 | U41: PROCERASEO S.A.S. | W41: NIT: 901 153 639 - 0 | AA41: Codigo Remuneración: | AC41: =N41 -> 2026082
F42: 3. ESQUEMA FINANCIERO DEL SERVICIO PUBLICO DE ASEO | U42: 3. ESQUEMA FINANCIERO DEL SERVICIO PUBLICO DE ASEO
F43: Resoluciòn UAESP Número 27 de 2018 | U43: Resoluciòn UAESP Número 27 de 2018
C44: Fecha de Proceso: | D44: =D6 -> 46267 | F44: CONSOLIDADO SALDOS A FAVOR | U44: =+F44 -> CONSOLIDADO SALDOS A FAVOR
C45: Hora: | D45: =D7 -> 0.58333333 | F45: Fecha Desde: | H45: =H7 -> 46250 | J45: Feha Hasta: | K45: =K7 -> 46265 | U45: =F45 -> Fecha Desde: | V45: =H45 -> 46250 | X45: =J45 -> Feha Hasta: | Y45: =K45 -> 46265
B46: ASE | C46: Concesionarios | D46: Recaudo Total | E46: Recaudo por disposicion final | F46: Recaudo por tratamiento de lixiviados | G46: Recaudo por Componente VIAT ( Decreto 2412/2018) | H46: Recaudo por aprovechamiento | I46: Recaudo del componente de comercializacion para Aprovechamiento (11,4%) | J46: Balance de subsidio o contribuciones | K46: RECAUDO BASE DE REMUNERACION | L46: Costo de la Interventoría | M46: REMUNERACION FINAL | N46: Conceptos especiales | O46: REMUNERACION FINAL MAS CONCEPTOS ESPECIALES | S46: ASE | T46: Concesionarios | U46: Tarifa de Comercialización del Servicio. ( TCS) | V46: Tarifa de Limpieza Urbana del Servicio. ( TLU) | W46: Tarifa de Barrido y Limpieza del Servicio. ( TBL) | X46: Tarifa de Recolección y Transporte del Servicio. (TRT) | Y46: Recaudo del componente de comercializacion para Aprovechamiento (18,6%) | Z46: Costo de la Interventoría | AA46: Ajuste a la decena | AB46: Conceptos especiales | AC46: Diferencial Balance S / C (Fac vs Rec) | AD46: Balance S / C Con Baase en (Recaudo) | AE46: REMUNERACION FINAL MAS CONCEPTOS ESPECIALES
B47: 1 | C47: PROMOAMBIENTAL DISTRITO S.A.S. ESP. | D47: =D9+D28 -> 806955.98 | E47: =E9+E28 -> 65039.95 | F47: =F9+F28 -> 36337.02 | G47: =G9+G28 -> 19274.13 | H47: =H9+H28 -> 155423.91 | I47: =I9+I28 -> 5618.35 | J47: =J9+J28 -> 0 | K47: =D47-E47-F47-G47-H47-I47-J47 -> 525262.62 | L47: 0 | M47: =K47-L47 -> 525262.62 | N47: =N9+N28 -> 0 | O47: =M47+N47 -> 525262.62 | S47: 1 | T47: PROMOAMBIENTAL DISTRITO S.A.S. ESP. | U47: =U9+U28 -> 56003.23 | V47: =V9+V28 -> 48167.15 | W47: =W9+W28 -> 226758.45 | X47: =X9+X28 -> 182170.76 | Y47: =Y9+Y28 -> 9166.69 | Z47: =-L47 -> 0 | AA47: =AA9+AA28 -> 0.04 | AB47: =AB9+AB28 -> 0 | AC47: =AC9+AC28 -> 2996.3 | AD47: =AD9+AD28 -> 2996.3 | AE47: =SUM(U47:AC47) -> 525262.62 | AF47: =(AE47-O47) -> 0 | AG47: =AF47=0 -> TRUE
B48: 2 | C48: LIMPIEZA METROPOLITANA S.A. ESP. | D48: =D10+D29 -> 506855.36 | E48: =E10+E29 -> 42296.72 | F48: =F10+F29 -> 23907.98 | G48: =G10+G29 -> 12706.35 | H48: =H10+H29 -> 265979.53 | I48: =I10+I29 -> 11995.53 | J48: =J10+J29 -> 0 | K48: =D48-E48-F48-G48-H48-I48-J48 -> 149969.25 | L48: 0 | M48: =K48-L48 -> 149969.25 | N48: =N10+N29 -> 0 | O48: =M48+N48 -> 149969.25 | S48: 2 | T48: LIMPIEZA METROPOLITANA S.A. ESP. | U48: =U10+U29 -> 66026.12 | V48: =V10+V29 -> 73645.62 | W48: =W10+W29 -> 345565.65 | X48: =X10+X29 -> 81955.14 | Y48: =Y10+Y29 -> 6998.74 | Z48: =-L48 -> 0 | AA48: =AA10+AA29 -> -3.66 | AB48: =AB10+AB29 -> 0 | AC48: =AC10+AC29 -> -424218.36 | AD48: =AD10+AD29 -> -424218.36 | AE48: =SUM(U48:AC48) -> 149969.25 | AF48: =(AE48-O48) -> -2.910383e-11 | AG48: =AF48=0 -> FALSE
B49: 3 | C49: CIUDAD LIMPIA BOGOTA S.A. ESP. | D49: =D11+D30 -> 118874.84 | E49: =E11+E30 -> 6267.13 | F49: =F11+F30 -> 3538.42 | G49: =G11+G30 -> 1857.22 | H49: =H11+H30 -> 42966.81 | I49: =I11+I30 -> 743.08 | J49: =J11+J30 -> 0 | K49: =D49-E49-F49-G49-H49-I49-J49 -> 63502.18 | L49: 0 | M49: =K49-L49 -> 63502.18 | N49: =N11+N30 -> 0 | O49: =M49+N49 -> 63502.18 | S49: 3 | T49: CIUDAD LIMPIA BOGOTA S.A. ESP. | U49: =U11+U30 -> 6518.28 | V49: =V11+V30 -> 6322.58 | W49: =W11+W30 -> 29933.14 | X49: =X11+X30 -> 14860.01 | Y49: =Y11+Y30 -> 1212.4 | Z49: =-L49 -> 0 | AA49: =AA11+AA30 -> 0 | AB49: =AB11+AB30 -> 0 | AC49: =AC11+AC30 -> 4655.77 | AD49: =AD11+AD30 -> 4655.77 | AE49: =SUM(U49:AC49) -> 63502.18 | AF49: =(AE49-O49) -> 1.4551915e-11 | AG49: =AF49=0 -> FALSE
B50: 4 | C50: BOGOTA LIMPIA S.A.S. ESP. | D50: =D12+D31 -> 318314.48 | E50: =E12+E31 -> 30353.42 | F50: =F12+F31 -> 17272.31 | G50: =G12+G31 -> 7260.85 | H50: =H12+H31 -> 195770.56 | I50: =I12+I31 -> 5001.67 | J50: =J12+J31 -> 0 | K50: =D50-E50-F50-G50-H50-I50-J50 -> 62655.67 | L50: 0 | M50: =K50-L50 -> 62655.67 | N50: =N12+N31 -> 0 | O50: =M50+N50 -> 62655.67 | S50: 4 | T50: BOGOTA LIMPIA S.A.S. ESP. | U50: =U12+U31 -> 31654.75 | V50: =V12+V31 -> 16169.51 | W50: =W12+W31 -> 625209.87 | X50: =X12+X31 -> 92025.49 | Y50: =Y12+Y31 -> 3836.24 | Z50: =-L50 -> 0 | AA50: =AA12+AA31 -> 20.01 | AB50: =AB12+AB31 -> 0 | AC50: =AC12+AC31 -> -706260.2 | AD50: =AD12+AD31 -> -706260.2 | AE50: =SUM(U50:AC50) -> 62655.67 | AF50: =(AE50-O50) -> 1.4551915e-11 | AG50: =AF50=0 -> FALSE
B51: 5 | C51: AREA LIMPIA DISTRITO CAPITAL S.A.S. ESP. | D51: =D13+D32 -> 0 | E51: =E13+E32 -> 0 | F51: =F13+F32 -> 0 | G51: =G13+G32 -> 0 | H51: =H13+H32 -> 0 | I51: =I13+I32 -> 0 | J51: =J13+J32 -> 0 | K51: =D51-E51-F51-G51-H51-I51-J51 -> 0 | L51: 0 | M51: =K51-L51 -> 0 | N51: =N13+N32 -> 0 | O51: =M51+N51 -> 0 | S51: 5 | T51: AREA LIMPIA DISTRITO CAPITAL S.A.S. ESP. | U51: =U13+U32 -> 0 | V51: =V13+V32 -> 0 | W51: =W13+W32 -> 0 | X51: =X13+X32 -> 0 | Y51: =Y13+Y32 -> 0 | Z51: =-L51 -> 0 | AA51: =AA13+AA32 -> 0 | AB51: =AB13+AB32 -> 0 | AC51: =AC13+AC32 -> 0 | AD51: =AD13+AD32 -> 0 | AE51: =SUM(U51:AC51) -> 0 | AF51: =(AE51-O51) -> 0 | AG51: =AF51=0 -> TRUE
C52: TOTAL | D52: =SUM(D47:D51) -> 1751000.7 | E52: =SUM(E47:E51) -> 143957.22 | F52: =SUM(F47:F51) -> 81055.73 | G52: =SUM(G47:G51) -> 41098.55 | H52: =SUM(H47:H51) -> 660140.81 | I52: =SUM(I47:I51) -> 23358.63 | J52: =SUM(J47:J51) -> 0 | K52: =SUM(K47:K51) -> 801389.72 | ... O52: =SUM(O47:O51) -> 801389.72 | T52: TOTAL | U52: =SUM(U47:U51) -> 160202.38 | V52: =SUM(V47:V51) -> 144304.86 | W52: =SUM(W47:W51) -> 1227467.1 | X52: =SUM(X47:X51) -> 371011.4 | Y52: =SUM(Y47:Y51) -> 21214.07 | Z52: =SUM(Z47:Z51) -> 0 | AA52: =SUM(AA47:AA51) -> 16.39 | AB52: =SUM(AB47:AB51) -> 0 | ... AF52: =SUM(AF47:AF51) -> 0 | AG52: =AF52=0 -> TRUE
Y54: =SUM(U52:Y52) -> 1924199.8
F56: Firma autorizada

Sheet INTERVENTORIA
F2: 2026 01 2 | G2: 2026 02 1 | H2: 2026 02 2 | I2: 2026 03 1 | J2: 2026 03 2 | K2: 2026 04 1 | L2: 2026 04 2 | M2: 2026 05 1 | N2: 2026 05 2 | O2: 2026 06 1 | P2: 2026 06 2 | Q2: 2026 07 1
B3: VALOR MES | C3: ASE | D3: Concesionarios | E3: % | F3: MITAD 1 // ENERO -26 | G3: MITAD 2 // ENERO -26 | H3: MITAD 1 // FEBRERO -26 | I3: MITAD 2 // FEBRERO -26 | J3: MITAD 1 // MARZO -26 | K3: MITAD 2 // MARZO -26 | L3: MITAD 1 // ABRIL -26 | M3: MITAD 2 // ABRIL -26 | N3: MITAD 1 // MAYO -26 | O3: MITAD 2 // MAYO -26 | P3: MITAD 1 // JUNIO -26 | Q3: MITAD 2 // JUNIO -26
B4: 378371975 | C4: 1 | D4: PROMOAMBIENTAL DISTRITO S.A.S. ESP. | E4: 0.22 | F4: 189185988 | G4: 189185987 | H4: 189185988 | I4: 189185987 | J4: 189185988 | K4: 189185987 | L4: 189185988 | M4: 189185987 | N4: 189185988 | O4: 189185987 | P4: 189185988 | Q4: 189185987
B5: 533160511 | C5: 2 | D5: LIMPIEZA METROPOLITANA S.A. ESP. | E5: 0.31 | F5: 266580256 | G5: 266580255 | H5: 266580256 | I5: 266580255 | J5: 266580256 | K5: 266580255 | L5: 266580256 | M5: 266580255 | N5: 266580256 | O5: 266580255 | P5: 266580256 | Q5: 266580255
B6: 309577071 | C6: 3 | D6: CIUDAD LIMPIA BOGOTA S.A. ESP. | E6: 0.18 | F6: 154788536 | G6: 154788535 | H6: 154788536 | I6: 154788535 | J6: 154788536 | K6: 154788535 | L6: 154788536 | M6: 154788535 | N6: 154788536 | O6: 154788535 | P6: 154788536 | Q6: 154788535
B7: 240782166 | C7: 4 | D7: BOGOTA LIMPIA S.A.S. ESP. | E7: 0.14 | F7: 120391083 | G7: 120391083 | H7: 120391083 | I7: 120391083 | J7: 120391083 | K7: 120391083 | L7: 120391083 | M7: 120391083 | N7: 120391083 | O7: 120391083 | P7: 120391083 | Q7: 120391083
B8: 257980891 | C8: 5 | D8: AREA LIMPIA DISTRITO CAPITAL S.A.S. ESP. | E8: 0.15 | F8: 128990446 | G8: 128990445 | H8: 128990446 | I8: 128990445 | J8: 128990446 | K8: 128990445 | L8: 128990446 | M8: 128990445 | N8: 128990446 | O8: 128990445 | P8: 128990446 | Q8: 128990445
B9: 1719872614 | D9: TOTAL | E9: 1 | F9: 859936309 | G9: 859936305 | H9: 859936309 | I9: 859936305 | J9: 859936309 | K9: 859936305 | L9: 859936309 | M9: 859936305 | N9: 859936309 | O9: 859936305 | P9: 859936309 | Q9: 859936305
F10: =SUM(F9:G9) -> 1719872614 | H10: =SUM(H9:I9) -> 1719872614 | J10: =SUM(J9:K9) -> 1719872614 | L10: =SUM(L9:M9) -> 1719872614 | N10: =SUM(N9:O9) -> 1719872614 | P10: =SUM(P9:Q9) -> 1719872614
F13: 2026 07 2 | G13: 2026 08 1 | H13: 2026 08 2 | I13: 2026 09 1 | J13: 2026 09 2 | K13: 2026 10 1 | L13: 2026 10 2 | M13: 2026 11 1 | N13: 2026 11 2 | O13: 2026 12 1 | P13: 2026 12 2 | Q13: 2027 01 1
C14: ASE | D14: Concesionarios | E14: % | F14: MITAD 1 // JULIO -26 | G14: MITAD 2 // JULIO -26 | H14: MITAD 1 // AGOSTO -26 | I14: MITAD 2 // AGOSTO -26 | J14: MITAD 1 // SEPTIEMBRE -26 | K14: MITAD 2 // SEPTIEMBRE -26 | L14: MITAD 1 // OCTUBRE -26 | M14: MITAD 2 // OCTUBRE -26 | N14: MITAD 1 // NOVIEMBRE -26 | O14: MITAD 2 // NOVIEMBRE -26 | P14: MITAD 1 // DICIEMBRE -26 | Q14: MITAD 2 // DICIEMBRE -26
C15: 1 | D15: PROMOAMBIENTAL DISTRITO S.A.S. ESP. | E15: 0.22 | F15: 189185988 | G15: 189185987 | H15: 189185988 | I15: 189185987 | J15: 189185988 | K15: 189185987 | L15: 189185988 | M15: 189185987 | N15: 189185988 | O15: 189185987 | P15: 189185988 | Q15: 189185987
C16: 2 | D16: LIMPIEZA METROPOLITANA S.A. ESP. | E16: 0.31 | F16: 266580256 | G16: 266580255 | H16: 266580256 | I16: 266580255 | J16: 266580256 | K16: 266580255 | L16: 266580256 | M16: 266580255 | N16: 266580256 | O16: 266580255 | P16: 266580256 | Q16: 266580255
C17: 3 | D17: CIUDAD LIMPIA BOGOTA S.A. ESP. | E17: 0.18 | F17: 154788536 | G17: 154788535 | H17: 154788536 | I17: 154788535 | J17: 154788536 | K17: 154788535 | L17: 154788536 | M17: 154788535 | N17: 154788536 | O17: 154788535 | P17: 154788536 | Q17: 154788535
C18: 4 | D18: BOGOTA LIMPIA S.A.S. ESP. | E18: 0.14 | F18: 120391083 | G18: 120391083 | H18: 120391083 | I18: 120391083 | J18: 120391083 | K18: 120391083 | L18: 120391083 | M18: 120391083 | N18: 120391083 | O18: 120391083 | P18: 120391083 | Q18: 120391083
C19: 5 | D19: AREA LIMPIA DISTRITO CAPITAL S.A.S. ESP. | E19: 0.15 | F19: 128990446 | G19: 128990445 | H19: 128990446 | I19: 128990445 | J19: 128990446 | K19: 128990445 | L19: 128990446 | M19: 128990445 | N19: 128990446 | O19: 128990445 | P19: 128990446 | Q19: 128990445
D20: TOTAL | E20: 1 | F20: 859936309 | G20: 859936305 | H20: 859936309 | I20: 859936305 | J20: 859936309 | K20: 859936305 | L20: 859936309 | M20: 859936305 | N20: 859936309 | O20: 859936305 | P20: 859936309 | Q20: 859936305
F21: =SUM(F20:G20) -> 1719872614 | G21: 1191383498 | H21: =SUM(H20:I20) -> 1719872614 | I21: 1191383498 | J21: =SUM(J20:K20) -> 1719872614 | K21: 1191383498 | L21: =SUM(L20:M20) -> 1719872614 | M21: 1191383498 | N21: =SUM(N20:O20) -> 1719872614 | O21: 1191383498 | P21: =SUM(P20:Q20) -> 1719872614 | Q21: 1191383498
K25: VALOR OFICIAL MES | L25: ASE | M25: Segunda quincena | N25: Primera quincena | R25: VALIDACION
K26: 378371975 | L26: 1 | M26: 189185988 | N26: 189185987 | O26: =M26=R26 -> TRUE | Q26: ='CONSOLIDADO_TOTAL RECAUDO'!L104 -> 189185988 | R26: =H15 -> 189185988 | S26: =Q26=R26 -> TRUE
K27: 533160511 | L27: 2 | M27: 266580256 | N27: 266580255 | O27: =M27=R27 -> TRUE | Q27: ='CONSOLIDADO_TOTAL RECAUDO'!L105 -> 266580256 | R27: =H16 -> 266580256 | S27: =Q27=R27 -> TRUE
K28: 309577071 | L28: 3 | M28: 154788536 | N28: 154788535 | O28: =M28=R28 -> TRUE | Q28: ='CONSOLIDADO_TOTAL RECAUDO'!L106 -> 154788536 | R28: =H17 -> 154788536 | S28: =Q28=R28 -> TRUE
K29: 240782166 | L29: 4 | M29: 120391083 | N29: 120391083 | O29: =M29=R29 -> TRUE | Q29: ='CONSOLIDADO_TOTAL RECAUDO'!L107 -> 120391083 | R29: =H18 -> 120391083 | S29: =Q29=R29 -> TRUE
K30: 257980891 | L30: 5 | M30: 128990446 | N30: 128990445 | O30: =M30=R30 -> TRUE | Q30: ='CONSOLIDADO_TOTAL RECAUDO'!L108 -> 128990446 | R30: =H19 -> 128990446 | S30: =Q30=R30 -> TRUE
K31: =SUM(K26:K30) -> 1719872614 | M31: =SUM(M26:M30) -> 859936309 | N31: =SUM(N26:N30) -> 859936305 | O31: =M31=R31 -> TRUE | Q31: ='CONSOLIDADO_TOTAL RECAUDO'!L109 -> 859936309 | R31: =H20 -> 859936309 | S31: =Q31=R31 -> TRUE
K32: =SUM(M31:N31) -> 1719872614

Sheet Informe AFaseo Recaudo 202608-2
D5: PROCERASEO S.A.S. | I5: NIT: 901 153 639 - 0 | P5: PROCERASEO S.A.S. | T5: NIT: 901 153 639 - 0
D6: INFORME Afaseo // RECAUDO | P6: INFORME AFaseo
D7: BENEFICIO TRANSITORIO ALIVIO SOBRE EL VALOR DE LA FACTURA | P7: BENEFICIO TRANSITORIO ALIVIO SOBRE EL VALOR DE LA FACTURA
D8: Según Resoluciòn UAESP Número 273 de 2.020 | P8: Según Resoluciòn UAESP Número 273 de 2.020
E10: Fecha Desde: | F10: ='CONSOLIDADO_TOTAL RECAUDO'!G102 -> 46250 | H10: Feha Hasta: | I10: ='CONSOLIDADO_TOTAL RECAUDO'!K102 -> 46265
B11: ASE | C11: Concesionarios | D11: Valor Afaseo | E11: Afaseo por disposicion final | F11: Afaseo por tratamiento de lixiviados | G11: Afaseo por Componente VIAT ( Decreto 2412/2018) | H11: Afaseo por aprovechamiento | I11: Afaseo del componente de comercializacion para Aprovechamiento (11,4%) | J11: Afaseo RBL | N11: ASE | O11: Concesionarios | P11: Tarifa de Comercialización del Servicio. ( TCS) | Q11: Tarifa de Limpieza Urbana del Servicio. ( TLU) | R11: Tarifa de Barrido y Limpieza del Servicio. ( TBL) | S11: Tarifa de Recolección y Transporte del Servicio. (TRT) | T11: Componente de comercialización para Aprovechamiento (18,6%) | U11: Afaseo RBL
B12: 1 | C12: PROMOAMBIENTAL DISTRITO S.A.S. ESP. | D12: ='Reporte Componentes R1'!F80*$D$24 -> 9123.9 | E12: ='Reporte Componentes R1'!G80*$D$24 -> 625.08 | F12: ='Reporte Componentes R1'!H80*$D$24 -> 265.56 | G12: ='Reporte Componentes R1'!I80*$D$24 -> 115.95 | H12: ='Reporte Componentes R1'!J80*$D$24 -> 1600.92 | I12: ='Reporte Componentes R1'!K80*$D$24 -> 103.46 | J12: =D12-E12-F12-G12-H12-I12 -> 6412.93 | N12: 1 | O12: PROMOAMBIENTAL DISTRITO S.A.S. ESP. | P12: ='Reporte Componentes R1'!M80*$P$24 -> 907.42 | Q12: ='Reporte Componentes R1'!N80*$P$24 -> 759.41 | R12: ='Reporte Componentes R1'!O80*$P$24 -> 3031.34 | S12: ='Reporte Componentes R1'!P80*$P$24 -> 1545.97 | T12: ='Reporte Componentes R1'!Q80*$P$24 -> 168.79 | U12: =SUM(P12:T12) -> 6412.93 | V12: =J12-U12 -> 0 | W12: =V12=0 -> TRUE
B13: 2 | C13: LIMPIEZA METROPOLITANA S.A. ESP. | D13: ='Reporte Componentes R1'!F224*$D$24 -> 1443510 | E13: ='Reporte Componentes R1'!G224*$D$24 -> 126107.3 | F13: ='Reporte Componentes R1'!H224*$D$24 -> 53574.14 | G13: ='Reporte Componentes R1'!I224*$D$24 -> 23396.67 | H13: ='Reporte Componentes R1'!J224*$D$24 -> 289490.34 | I13: ='Reporte Componentes R1'!K224*$D$24 -> 12050.94 | J13: =D13-E13-F13-G13-H13-I13 -> 938890.59 | N13: 2 | O13: LIMPIEZA METROPOLITANA S.A. ESP. | P13: ='Reporte Componentes R1'!M224*$P$24 -> 105713.14 | Q13: ='Reporte Componentes R1'!N224*$P$24 -> 132509.9 | R13: ='Reporte Componentes R1'!O224*$P$24 -> 445101.84 | S13: ='Reporte Componentes R1'!P224*$P$24 -> 235902.28 | T13: ='Reporte Componentes R1'!Q224*$P$24 -> 19663.43 | U13: =SUM(P13:T13) -> 938890.59 | V13: =J13-U13 -> 0 | W13: =V13=0 -> TRUE
B14: 3 | C14: CIUDAD LIMPIA BOGOTA S.A. ESP. | D14: ='Reporte Componentes R1'!F355*$D$24 -> 4456.11 | E14: ='Reporte Componentes R1'!G355*$D$24 -> 384.61 | F14: ='Reporte Componentes R1'!H355*$D$24 -> 163.4 | G14: ='Reporte Componentes R1'!I355*$D$24 -> 71.36 | H14: ='Reporte Componentes R1'!J355*$D$24 -> 870.46 | I14: ='Reporte Componentes R1'!K355*$D$24 -> 35.94 | J14: =D14-E14-F14-G14-H14-I14 -> 2930.34 | N14: 3 | O14: CIUDAD LIMPIA BOGOTA S.A. ESP. | P14: ='Reporte Componentes R1'!M355*$P$24 -> 315.21 | Q14: ='Reporte Componentes R1'!N355*$P$24 -> 395.2 | R14: ='Reporte Componentes R1'!O355*$P$24 -> 1327.09 | S14: ='Reporte Componentes R1'!P355*$P$24 -> 834.22 | T14: ='Reporte Componentes R1'!Q355*$P$24 -> 58.62 | U14: =SUM(P14:T14) -> 2930.34 | V14: =J14-U14 -> 0 | W14: =V14=0 -> TRUE
B15: 4 | C15: BOGOTA LIMPIA S.A.S. ESP. | D15: ='Reporte Componentes R1'!F486*$D$24 -> 51713.94 | E15: ='Reporte Componentes R1'!G486*$D$24 -> 4225.07 | F15: ='Reporte Componentes R1'!H486*$D$24 -> 1794.94 | G15: ='Reporte Componentes R1'!I486*$D$24 -> 783.85 | H15: ='Reporte Componentes R1'!J486*$D$24 -> 9523.33 | I15: ='Reporte Componentes R1'!K486*$D$24 -> 387.6 | J15: =D15-E15-F15-G15-H15-I15 -> 34999.15 | N15: 4 | O15: BOGOTA LIMPIA S.A.S. ESP. | P15: ='Reporte Componentes R1'!M486*$P$24 -> 3399.75 | Q15: ='Reporte Componentes R1'!N486*$P$24 -> 4326.89 | R15: ='Reporte Componentes R1'!O486*$P$24 -> 15874.06 | S15: ='Reporte Componentes R1'!P486*$P$24 -> 10765.99 | T15: ='Reporte Componentes R1'!Q486*$P$24 -> 632.46 | U15: =SUM(P15:T15) -> 34999.15 | V15: =J15-U15 -> 0 | W15: =V15=0 -> TRUE
B16: 5 | C16: AREA LIMPIA DISTRITO CAPITAL S.A.S. ESP. | D16: ='Reporte Componentes R1'!F584*$D$24 -> 4485.01 | E16: ='Reporte Componentes R1'!G584*$D$24 -> 355.56 | F16: ='Reporte Componentes R1'!H584*$D$24 -> 151.05 | G16: ='Reporte Componentes R1'!I584*$D$24 -> 65.98 | H16: ='Reporte Componentes R1'!J584*$D$24 -> 769.61 | I16: ='Reporte Componentes R1'!K584*$D$24 -> 47.44 | J16: =D16-E16-F16-G16-H16-I16 -> 3095.37 | N16: 5 | O16: AREA LIMPIA DISTRITO CAPITAL S.A.S. ESP. | P16: ='Reporte Componentes R1'!M584*$P$24 -> 415.95 | Q16: ='Reporte Componentes R1'!N584*$P$24 -> 348.63 | R16: ='Reporte Componentes R1'!O584*$P$24 -> 1274.28 | S16: ='Reporte Componentes R1'!P584*$P$24 -> 979.14 | T16: ='Reporte Componentes R1'!Q584*$P$24 -> 77.37 | U16: =SUM(P16:T16) -> 3095.37 | V16: =J16-U16 -> 0 | W16: =V16=0 -> TRUE
C17: TOTAL | D17: =SUM(D12:D16) -> 1513288.9 | E17: =SUM(E12:E16) -> 131697.62 | F17: =SUM(F12:F16) -> 55949.09 | G17: =SUM(G12:G16) -> 24433.81 | H17: =SUM(H12:H16) -> 302254.66 | I17: =SUM(I12:I16) -> 12625.38 | J17: =SUM(J12:J16) -> 986328.38 | O17: TOTAL | P17: =SUM(P12:P16) -> 110751.47 | Q17: =SUM(Q12:Q16) -> 138340.03 | R17: =SUM(R12:R16) -> 466608.61 | S17: =SUM(S12:S16) -> 250027.6 | T17: =SUM(T12:T16) -> 20600.67 | U17: =SUM(U12:U16) -> 986328.38 | V17: =SUM(V12:V16) -> 0 | W17: =V17=0 -> TRUE
T19: =SUM(P17:T17) -> 986328.38
J20: =+IF(MAX(J12:J17)>500000,"VALIDAR",TRUE) -> VALIDAR
F21: Firma autorizada
D24: -1 | P24: -1

Sheet CONSOLIDADO_TOTAL RECAUDO
F3: PROCERASEO S.A.S. | I3: NIT: 901 153 639 - 0 | M3: Codigo Remuneración: | N3: 2026082 | U3: PROCERASEO S.A.S. | W3: NIT: 901 153 639 - 0 | AA3: Codigo Remuneración: | AD3: =N3 -> 2026082
F4: 3. ESQUEMA FINANCIERO DEL SERVICIO PUBLICO DE ASEO | U4: 3. ESQUEMA FINANCIERO DEL SERVICIO PUBLICO DE ASEO
F5: Resoluciòn UAESP Número 27 de 2018 | U5: Resoluciòn UAESP Número 27 de 2018
C6: Fecha de Proceso: | D6: 46267 | F6: R1 - RECAUDO OPORTUNO | U6: R1 - RECAUDO OPORTUNO
C7: Hora: | D7: 0.58333333 | F7: Fecha Desde: | G7: 46250 | J7: Feha Hasta: | K7: 46265 | U7: =F7 -> Fecha Desde: | V7: =G7 -> 46250 | X7: =J7 -> Feha Hasta: | Y7: =K7 -> 46265
B8: ASE | C8: Concesionarios | D8: Recaudo Total | E8: Recaudo por disposicion final | F8: Recaudo por tratamiento de lixiviados | G8: Recaudo por Componente VIAT ( Decreto 2412/2018) | H8: Recaudo por aprovechamiento | I8: Recaudo del componente de comercializacion para Aprovechamiento (11,4%) | J8: Balance de subsidio o contribuciones | K8: RECAUDO BASE DE REMUNERACION | L8: Costo de la Interventoría | M8: REMUNERACION FINAL | N8: Conceptos especiales | O8: REMUNERACION FINAL MAS CONCEPTOS ESPECIALES | S8: ASE | T8: Concesionarios | U8: Tarifa de Comercialización del Servicio. ( TCS) | V8: Tarifa de Limpieza Urbana del Servicio. ( TLU) | W8: Tarifa de Barrido y Limpieza del Servicio. ( TBL) | X8: Tarifa de Recolección y Transporte del Servicio. (TRT) | Y8: Recaudo del componente de comercializacion para Aprovechamiento (18,6%) | Z8: Costo de la Interventoría | AA8: Ajuste a la decena | AB8: Conceptos especiales | AC8: Otros | AD8: Diferencial Balance S / C (Fac vs Rec) | AE8: Balance S / C Con Base en (Recaudo) | AF8: REMUNERACION FINAL MAS CONCEPTOS ESPECIALES
B9: 1 | C9: PROMOAMBIENTAL DISTRITO S.A.S. ESP. | D9: ='Reporte Componentes R1'!F50 -> 1.8298671e+10 | E9: ='Reporte Componentes R1'!G50 -> 9.7516832e+08 | F9: ='Reporte Componentes R1'!H50 -> 5.499649e+08 | G9: ='Reporte Componentes R1'!I50 -> 2.8927749e+08 | H9: ='Reporte Componentes R1'!J50 -> 4.1849016e+09 | I9: ='Reporte Componentes R1'!K50 -> 1.5647198e+08 | J9: ='BCE SC POR FACT.'!F3 -> -3.6102137e+09 | K9: =D9-E9-F9-G9-H9-I9-J9 -> 1.57531e+10 | L9: =INTERVENTORIA!H15 -> 189185988 | M9: =K9-L9 -> 1.5563914e+10 | N9: ='Reporte Componentes R1'!L50 -> 37024819 | O9: =M9+N9 -> 1.5600939e+10 | S9: 1 | T9: PROMOAMBIENTAL DISTRITO S.A.S. ESP. | U9: ='Reporte Componentes R1'!M50 -> 1.3756006e+09 | V9: ='Reporte Componentes R1'!N50 -> 1.3092952e+09 | W9: ='Reporte Componentes R1'!O50 -> 6.1956882e+09 | X9: ='Reporte Componentes R1'!P50 -> 2.6486864e+09 | Y9: ='Reporte Componentes R1'!Q50 -> 2.5542897e+08 | Z9: =L9*-1 -> -189185988 | AA9: ='Reporte Componentes R1'!R50+'Reporte Componentes R1'!U50+'Reporte Componentes R1'!V50 -> 2108.08 | AB9: =N9 -> 37024819 | AC9: ='Reporte Componentes R1'!T50+'Reporte Componentes R1'!W50+'Reporte Componentes R1'!X50+'Reporte Componentes R1'!Y50+'Reporte Componentes R1'!Z50+'Reporte Componentes R1'!S50 -> 194.35 | AD9: =-J9+AE9 -> 3.9683988e+09 | AE9: ='Reporte Componentes R1'!F51 -> 3.5818503e+08 | AF9: =SUM(U9:AD9) -> 1.5600939e+10 | AG9: =(AF9-O9) -> 3.8146973e-06 | AH9: =INT(AG9)=0 -> TRUE
B10: 2 | C10: LIMPIEZA METROPOLITANA S.A. ESP. | D10: ='Reporte Componentes R1'!F194 -> 2.1464289e+10 | E10: ='Reporte Componentes R1'!G194 -> 1.6476962e+09 | F10: ='Reporte Componentes R1'!H194 -> 9.1955952e+08 | G10: ='Reporte Componentes R1'!I194 -> 4.8037508e+08 | H10: ='Reporte Componentes R1'!J194 -> 6.8012725e+09 | I10: ='Reporte Componentes R1'!K194 -> 2.2530363e+08 | J10: ='BCE SC POR FACT.'!F4 -> -4.2898763e+09 | K10: =D10-E10-F10-G10-H10-I10-J10 -> 1.5679958e+10 | L10: =INTERVENTORIA!H16 -> 266580256 | M10: =K10-L10 -> 1.5413378e+10 | N10: ='Reporte Componentes R1'!L194 -> 65675504 | O10: =M10+N10 -> 1.5479053e+10 | S10: 2 | T10: LIMPIEZA METROPOLITANA S.A. ESP. | U10: ='Reporte Componentes R1'!M194 -> 1.9771461e+09 | V10: ='Reporte Componentes R1'!N194 -> 1.97506e+09 | W10: ='Reporte Componentes R1'!O194 -> 9.2991205e+09 | X10: ='Reporte Componentes R1'!P194 -> 3.2312867e+09 | Y10: ='Reporte Componentes R1'!Q194 -> 3.6812319e+08 | Z10: =L10*-1 -> -266580256 | AA10: ='Reporte Componentes R1'!R194+'Reporte Componentes R1'!U194+'Reporte Componentes R1'!V194 -> -219558.69 | AB10: =N10 -> 65675504 | AC10: ='Reporte Componentes R1'!T194+'Reporte Componentes R1'!W194+'Reporte Componentes R1'!X194+'Reporte Componentes R1'!Y194+'Reporte Componentes R1'!Z194+'Reporte Componentes R1'!S194 -> 39.32 | AD10: =-J10+AE10 -> -1.1705588e+09 | AE10: ='Reporte Componentes R1'!F195 -> -5.4604351e+09 | AF10: =SUM(U10:AD10) -> 1.5479053e+10 | AG10: =(AF10-O10) -> -5.7220459e-06 | AH10: =INT(AG10)=0 -> FALSE
B11: 3 | C11: CIUDAD LIMPIA BOGOTA S.A. ESP. | D11: ='Reporte Componentes R1'!F325 -> 1.6345752e+10 | E11: ='Reporte Componentes R1'!G325 -> 1.144017e+09 | F11: ='Reporte Componentes R1'!H325 -> 6.4506598e+08 | G11: ='Reporte Componentes R1'!I325 -> 3.3876794e+08 | H11: ='Reporte Componentes R1'!J325 -> 4.5578715e+09 | I11: ='Reporte Componentes R1'!K325 -> 1.2722967e+08 | J11: ='BCE SC POR FACT.'!F5 -> -8.2926223e+08 | K11: =D11-E11-F11-G11-H11-I11-J11 -> 1.0362062e+10 | L11: =INTERVENTORIA!H17 -> 154788536 | M11: =K11-L11 -> 1.0207273e+10 | N11: ='Reporte Componentes R1'!L325 -> 37341349 | O11: =M11+N11 -> 1.0244614e+10 | S11: 3 | T11: CIUDAD LIMPIA BOGOTA S.A. ESP. | U11: ='Reporte Componentes R1'!M325 -> 1.1157039e+09 | V11: ='Reporte Componentes R1'!N325 -> 1.0884971e+09 | W11: ='Reporte Componentes R1'!O325 -> 5.1459307e+09 | X11: ='Reporte Componentes R1'!P325 -> 2.7064049e+09 | Y11: ='Reporte Componentes R1'!Q325 -> 2.0762755e+08 | Z11: =L11*-1 -> -154788536 | AA11: ='Reporte Componentes R1'!R325+'Reporte Componentes R1'!U325+'Reporte Componentes R1'!V325 -> 116676.53 | AB11: =N11 -> 37341349 | AC11: ='Reporte Componentes R1'!T325+'Reporte Componentes R1'!W325+'Reporte Componentes R1'!X325+'Reporte Componentes R1'!Y325+'Reporte Componentes R1'!Z325+'Reporte Componentes R1'!S325 -> -3973599.1 | AD11: =-J11+AE11 -> 1.0175438e+08 | AE11: ='Reporte Componentes R1'!F326 -> -7.2750785e+08 | AF11: =SUM(U11:AD11) -> 1.0244614e+10 | AG11: =(AF11-O11) -> 3.8146973e-06 | AH11: =INT(AG11)=0 -> TRUE
B12: 4 | C12: BOGOTA LIMPIA S.A.S. ESP. | D12: ='Reporte Componentes R1'!F456 -> 8.2722888e+09 | E12: ='Reporte Componentes R1'!G456 -> 5.1131447e+08 | F12: ='Reporte Componentes R1'!H456 -> 2.8671239e+08 | G12: ='Reporte Componentes R1'!I456 -> 1.511682e+08 | H12: ='Reporte Componentes R1'!J456 -> 2.0895108e+09 | I12: ='Reporte Componentes R1'!K456 -> 72385159 | J12: ='BCE SC POR FACT.'!F6 -> -7.0623593e+08 | K12: =D12-E12-F12-G12-H12-I12-J12 -> 5.8674337e+09 | L12: =INTERVENTORIA!H18 -> 120391083 | M12: =K12-L12 -> 5.7470426e+09 | N12: ='Reporte Componentes R1'!L456 -> 11217477 | O12: =M12+N12 -> 5.7582601e+09 | S12: 4 | T12: BOGOTA LIMPIA S.A.S. ESP. | U12: ='Reporte Componentes R1'!M456 -> 6.3435485e+08 | V12: ='Reporte Componentes R1'!N456 -> 6.2797963e+08 | W12: ='Reporte Componentes R1'!O456 -> 3.1813905e+09 | X12: ='Reporte Componentes R1'!P456 -> 1354897293 | Y12: ='Reporte Componentes R1'!Q456 -> 1.1813039e+08 | Z12: =L12*-1 -> -120391083 | AA12: ='Reporte Componentes R1'!R456+'Reporte Componentes R1'!U456+'Reporte Componentes R1'!V456 -> -12115.9 | AB12: =N12 -> 11217477 | AC12: ='Reporte Componentes R1'!T456+'Reporte Componentes R1'!W456+'Reporte Componentes R1'!X456+'Reporte Componentes R1'!Y456+'Reporte Componentes R1'!Z456+'Reporte Componentes R1'!S456 -> -35.57 | AD12: =-J12+AE12 -> -49306771 | AE12: ='Reporte Componentes R1'!F457 -> -7.555427e+08 | AF12: =SUM(U12:AD12) -> 5.7582601e+09 | AG12: =(AF12-O12) -> -9.5367432e-07 | AH12: =INT(AG12)=0 -> FALSE
B13: 5 | C13: AREA LIMPIA DISTRITO CAPITAL S.A.S. ESP. | D13: ='Reporte Componentes R1'!F554 -> 1.2105459e+10 | E13: ='Reporte Componentes R1'!G554 -> 7.2304739e+08 | F13: ='Reporte Componentes R1'!H554 -> 4.0687903e+08 | G13: ='Reporte Componentes R1'!I554 -> 2.1399976e+08 | H13: ='Reporte Componentes R1'!J554 -> 3.0037138e+09 | I13: ='Reporte Componentes R1'!K554 -> 1.092758e+08 | J13: ='BCE SC POR FACT.'!F7 -> -23403941 | K13: =D13-E13-F13-G13-H13-I13-J13 -> 7.6719467e+09 | L13: =INTERVENTORIA!H19 -> 128990446 | M13: =K13-L13 -> 7.5429563e+09 | N13: ='Reporte Componentes R1'!L554 -> 10318779 | O13: =M13+N13 -> 7.5532751e+09 | S13: 5 | T13: AREA LIMPIA DISTRITO CAPITAL S.A.S. ESP. | U13: ='Reporte Componentes R1'!M554 -> 9.5820819e+08 | V13: ='Reporte Componentes R1'!N554 -> 9.3073183e+08 | W13: ='Reporte Componentes R1'!O554 -> 4.8265257e+09 | X13: ='Reporte Componentes R1'!P554 -> 2.1858219e+09 | Y13: ='Reporte Componentes R1'!Q554 -> 1.783708e+08 | Z13: =L13*-1 -> -128990446 | AA13: ='Reporte Componentes R1'!R554+'Reporte Componentes R1'!U554+'Reporte Componentes R1'!V554 -> -105785.99 | AB13: =N13 -> 10318779 | AC13: ='Reporte Componentes R1'!T554+'Reporte Componentes R1'!W554+'Reporte Componentes R1'!X554+'Reporte Componentes R1'!Y554+'Reporte Componentes R1'!Z554+'Reporte Componentes R1'!S554 -> -29.2 | AD13: =-J13+AE13 -> -1.4076059e+09 | AE13: ='Reporte Componentes R1'!F555 -> -1.4310098e+09 | AF13: =SUM(U13:AD13) -> 7.5532751e+09 | AG13: =(AF13-O13) -> -1.9073486e-06 | AH13: =INT(AG13)=0 -> FALSE
C14: TOTAL | D14: =SUM(D9:D13) -> 7.6486459e+10 | E14: =SUM(E9:E13) -> 5.0012434e+09 | F14: =SUM(F9:F13) -> 2.8081818e+09 | G14: =SUM(G9:G13) -> 1.4735885e+09 | H14: =SUM(H9:H13) -> 2.063727e+10 | I14: =SUM(I9:I13) -> 6.9066623e+08 | J14: =SUM(J9:J13) -> -9.4589922e+09 | K14: =SUM(K9:K13) -> 5.5334501e+10 | ... O14: =SUM(O9:O13) -> 5.4636142e+10 | T14: TOTAL | U14: =SUM(U9:U13) -> 6.0610136e+09 | V14: =SUM(V9:V13) -> 5.9315638e+09 | W14: =SUM(W9:W13) -> 2.8648656e+10 | X14: =SUM(X9:X13) -> 1.2127097e+10 | Y14: =SUM(Y9:Y13) -> 1.1276809e+09 | Z14: =SUM(Z9:Z13) -> -859936309 | AA14: =SUM(AA9:AA13) -> -218675.97 | AB14: =SUM(AB9:AB13) -> 1.6157793e+08 | ... AG14: =SUM(AG9:AG13) -> -9.5367432e-07 | AH14: =INT(AG14)=0 -> FALSE
Y16: =SUM(U14:Y14) -> 5.3896011e+10
F18: Firma autorizada
F22: PROCERASEO S.A.S. | I22: NIT: 901 153 639 - 0 | M22: Codigo Remuneración: | N22: =N3 -> 2026082 | U22: PROCERASEO S.A.S. | W22: NIT: 901 153 639 - 0 | AA22: Codigo Remuneración: | AD22: =N22 -> 2026082
F23: 3. ESQUEMA FINANCIERO DEL SERVICIO PUBLICO DE ASEO | U23: 3. ESQUEMA FINANCIERO DEL SERVICIO PUBLICO DE ASEO
F24: Resoluciòn UAESP Número 27 de 2018 | U24: Resoluciòn UAESP Número 27 de 2018
C25: Fecha de Proceso: | D25: =D6 -> 46267 | F25: R2 - ANTICIPOS A USUARIOS | U25: R2 - ANTICIPOS A USUARIOS
C26: Hora: | D26: =D7 -> 0.58333333 | F26: Fecha Desde: | G26: =G7 -> 46250 | J26: Feha Hasta: | K26: =K7 -> 46265 | U26: =F26 -> Fecha Desde: | V26: =G26 -> 46250 | X26: =J26 -> Feha Hasta: | Y26: =K26 -> 46265
B27: ASE | C27: Concesionarios | D27: Recaudo Total | E27: Recaudo por disposicion final | F27: Recaudo por tratamiento de lixiviados | G27: Recaudo por Componente VIAT ( Decreto 2412/2018) | H27: Recaudo por aprovechamiento | I27: Recaudo del componente de comercializacion para Aprovechamiento (11,4%) | J27: Balance de subsidio o contribuciones | K27: RECAUDO BASE DE REMUNERACION | L27: Costo de la Interventoría | M27: REMUNERACION FINAL | N27: Conceptos especiales | O27: REMUNERACION FINAL MAS CONCEPTOS ESPECIALES | S27: ASE | T27: Concesionarios | U27: Tarifa de Comercialización del Servicio. ( TCS) | V27: Tarifa de Limpieza Urbana del Servicio. ( TLU) | W27: Tarifa de Barrido y Limpieza del Servicio. ( TBL) | X27: Tarifa de Recolección y Transporte del Servicio. (TRT) | Y27: Recaudo del componente de comercializacion para Aprovechamiento (18,6%) | Z27: Costo de la Interventoría | AA27: Ajuste a la decena | AB27: Conceptos especiales | AC27: Otros | AD27: Diferencial Balance S / C (Fac vs Rec) | AE27: Balance S / C Con Base en (Recaudo) | AF27: REMUNERACION FINAL MAS CONCEPTOS ESPECIALES
B28: 1 | C28: PROMOAMBIENTAL DISTRITO S.A.S. ESP. | D28: ='Rem. Anticipos R2'!E43 -> 79360902 | E28: ='Rem. Anticipos R2'!F43 -> 5590132.5 | F28: ='Rem. Anticipos R2'!G43 -> 3085443.8 | G28: ='Rem. Anticipos R2'!H43 -> 1743640.5 | H28: ='Rem. Anticipos R2'!I43 -> 15777875 | I28: ='Rem. Anticipos R2'!J43 -> 589229.72 | J28: 0 | K28: =D28-E28-F28-G28-H28-I28-J28 -> 52574581 | L28: 0 | M28: =K28-L28 -> 52574581 | N28: ='Rem. Anticipos R2'!K43 -> 144941.68 | O28: =M28+N28 -> 52719522 | S28: 1 | T28: PROMOAMBIENTAL DISTRITO S.A.S. ESP. | U28: ='Rem. Anticipos R2'!L43 -> 6377827.8 | V28: ='Rem. Anticipos R2'!M43 -> 8360896 | W28: ='Rem. Anticipos R2'!N43 -> 35374497 | X28: ='Rem. Anticipos R2'!O43 -> 15436886 | Y28: ='Rem. Anticipos R2'!P43 -> 927072.64 | Z28: =L28*-1 -> 0 | AA28: ='Rem. Anticipos R2'!Q43 -> 69485.02 | AB28: =N28 -> 144941.68 | AC28: ='Rem. Anticipos R2'!R43 -> 0 | AD28: =-J28+AE28 -> -13972083 | AE28: ='Rem. Anticipos R2'!E44 -> -13972083 | AF28: =SUM(U28:AD28) -> 52719522 | AG28: =(AF28-O28) -> 7.4505806e-09 | AH28: =INT(AG28)=0 -> TRUE
B29: 2 | C29: LIMPIEZA METROPOLITANA S.A. ESP. | D29: ='Rem. Anticipos R2'!E140 -> 1.4816491e+08 | E29: ='Rem. Anticipos R2'!F140 -> 18197852 | F29: ='Rem. Anticipos R2'!G140 -> 9901639.4 | G29: ='Rem. Anticipos R2'!H140 -> 4813082.2 | H29: ='Rem. Anticipos R2'!I140 -> 38300538 | I29: ='Rem. Anticipos R2'!J140 -> 1265131.1 | J29: 0 | K29: =D29-E29-F29-G29-H29-I29-J29 -> 75686670 | L29: 0 | M29: =K29-L29 -> 75686670 | N29: ='Rem. Anticipos R2'!K140 -> 28554.96 | O29: =M29+N29 -> 75715225 | S29: 2 | T29: LIMPIEZA METROPOLITANA S.A. ESP. | U29: ='Rem. Anticipos R2'!L140 -> 10563073 | V29: ='Rem. Anticipos R2'!M140 -> 11549550 | W29: ='Rem. Anticipos R2'!N140 -> 44129172 | X29: ='Rem. Anticipos R2'!O140 -> 43057494 | Y29: ='Rem. Anticipos R2'!P140 -> 1515890.7 | Z29: =L29*-1 -> 0 | AA29: ='Rem. Anticipos R2'!Q140 -> 143.91 | AB29: =N29 -> 28554.96 | AC29: ='Rem. Anticipos R2'!R140 -> 0 | AD29: =-J29+AE29 -> -35128653 | AE29: ='Rem. Anticipos R2'!E141 -> -35128653 | AF29: =SUM(U29:AD29) -> 75715225 | AG29: =(AF29-O29) -> 1.4901161e-08 | AH29: =INT(AG29)=0 -> TRUE
B30: 3 | C30: CIUDAD LIMPIA BOGOTA S.A. ESP. | D30: ='Rem. Anticipos R2'!E257 -> 27806865 | E30: ='Rem. Anticipos R2'!F257 -> 1765770.1 | F30: ='Rem. Anticipos R2'!G257 -> 991068.55 | G30: ='Rem. Anticipos R2'!H257 -> 522289.1 | H30: ='Rem. Anticipos R2'!I257 -> 7371762.1 | I30: ='Rem. Anticipos R2'!J257 -> 270953.79 | J30: 0 | K30: =D30-E30-F30-G30-H30-I30-J30 -> 16885021 | L30: 0 | M30: =K30-L30 -> 16885021 | N30: ='Rem. Anticipos R2'!K257 -> 156736.31 | O30: =M30+N30 -> 17041758 | S30: 3 | T30: CIUDAD LIMPIA BOGOTA S.A. ESP. | U30: ='Rem. Anticipos R2'!L257 -> 2092606 | V30: ='Rem. Anticipos R2'!M257 -> 2311442.2 | W30: ='Rem. Anticipos R2'!N257 -> 10561392 | X30: ='Rem. Anticipos R2'!O257 -> 4830144.4 | Y30: ='Rem. Anticipos R2'!P257 -> 357286.91 | Z30: =L30*-1 -> 0 | AA30: ='Rem. Anticipos R2'!Q257 -> -61.37 | AB30: =N30 -> 156736.31 | AC30: ='Rem. Anticipos R2'!R257 -> 0 | AD30: =-J30+AE30 -> -3267789 | AE30: ='Rem. Anticipos R2'!E258 -> -3267789 | AF30: =SUM(U30:AD30) -> 17041758 | AG30: =(AF30-O30) -> 3.7252903e-09 | AH30: =INT(AG30)=0 -> TRUE
B31: 4 | C31: BOGOTA LIMPIA S.A.S. ESP. | D31: ='Rem. Anticipos R2'!E360 -> 1.1111794e+08 | E31: ='Rem. Anticipos R2'!F360 -> 9279153.1 | F31: ='Rem. Anticipos R2'!G360 -> 5189442.7 | G31: ='Rem. Anticipos R2'!H360 -> 2412201.8 | H31: ='Rem. Anticipos R2'!I360 -> 27609479 | I31: ='Rem. Anticipos R2'!J360 -> 984542.62 | J31: 0 | K31: =D31-E31-F31-G31-H31-I31-J31 -> 65643116 | L31: 0 | M31: =K31-L31 -> 65643116 | N31: ='Rem. Anticipos R2'!K360 -> 95764.91 | O31: =M31+N31 -> 65738881 | S31: 4 | T31: BOGOTA LIMPIA S.A.S. ESP. | U31: ='Rem. Anticipos R2'!L360 -> 8797727.6 | V31: ='Rem. Anticipos R2'!M360 -> 8327012.3 | W31: ='Rem. Anticipos R2'!N360 -> 37437707 | X31: ='Rem. Anticipos R2'!O360 -> 25385807 | Y31: ='Rem. Anticipos R2'!P360 -> 1263833.1 | Z31: =L31*-1 -> 0 | AA31: ='Rem. Anticipos R2'!Q360 -> -217.62 | AB31: =N31 -> 95764.91 | AC31: ='Rem. Anticipos R2'!R360 -> 0 | AD31: =-J31+AE31 -> -15568753 | AE31: ='Rem. Anticipos R2'!E361 -> -15568753 | AF31: =SUM(U31:AD31) -> 65738881 | AG31: =(AF31-O31) -> -2.2351742e-08 | AH31: =INT(AG31)=0 -> FALSE
B32: 5 | C32: AREA LIMPIA DISTRITO CAPITAL S.A.S. ESP. | D32: ='Rem. Anticipos R2'!E440 -> 34963154 | E32: ='Rem. Anticipos R2'!F440 -> 2546995.1 | F32: ='Rem. Anticipos R2'!G440 -> 1435013 | G32: ='Rem. Anticipos R2'!H440 -> 691553.71 | H32: ='Rem. Anticipos R2'!I440 -> 6730923.1 | I32: ='Rem. Anticipos R2'!J440 -> 264456.01 | J32: 0 | K32: =D32-E32-F32-G32-H32-I32-J32 -> 23294213 | L32: 0 | M32: =K32-L32 -> 23294213 | N32: ='Rem. Anticipos R2'!K440 -> 855801.18 | O32: =M32+N32 -> 24150014 | S32: 5 | T32: AREA LIMPIA DISTRITO CAPITAL S.A.S. ESP. | U32: ='Rem. Anticipos R2'!L440 -> 1758367.2 | V32: ='Rem. Anticipos R2'!M440 -> 1742050.5 | W32: ='Rem. Anticipos R2'!N440 -> 8920088.5 | X32: ='Rem. Anticipos R2'!O440 -> 7619607.4 | Y32: ='Rem. Anticipos R2'!P440 -> 337866.91 | Z32: =L32*-1 -> 0 | AA32: ='Rem. Anticipos R2'!Q440 -> -165.4 | AB32: =N32 -> 855801.18 | AC32: ='Rem. Anticipos R2'!R440 -> 0 | AD32: =-J32+AE32 -> 2916397.7 | AE32: ='Rem. Anticipos R2'!E441 -> 2916397.7 | AF32: =SUM(U32:AD32) -> 24150014 | AG32: =(AF32-O32) -> 3.7252903e-09 | AH32: =INT(AG32)=0 -> TRUE
C33: TOTAL | D33: =SUM(D28:D32) -> 4.0141377e+08 | E33: =SUM(E28:E32) -> 37379902 | F33: =SUM(F28:F32) -> 20602607 | G33: =SUM(G28:G32) -> 10182767 | H33: =SUM(H28:H32) -> 95790578 | I33: =SUM(I28:I32) -> 3374313.2 | J33: =SUM(J28:J32) -> 0 | K33: =SUM(K28:K32) -> 2.340836e+08 | ... O33: =SUM(O28:O32) -> 2.353654e+08 | T33: TOTAL | U33: =SUM(U28:U32) -> 29589602 | V33: =SUM(V28:V32) -> 32290951 | W33: =SUM(W28:W32) -> 1.3642286e+08 | X33: =SUM(X28:X32) -> 96329939 | Y33: =SUM(Y28:Y32) -> 4401950.3 | Z33: =SUM(Z28:Z32) -> 0 | AA33: =SUM(AA28:AA32) -> 69184.54 | AB33: =SUM(AB28:AB32) -> 1281799 | ... AG33: =SUM(AG28:AG32) -> 7.4505806e-09 | AH33: =INT(AG33)=0 -> TRUE
Y35: =SUM(U33:Y33) -> 2.990353e+08
F37: Firma autorizada
F41: PROCERASEO S.A.S. | I41: NIT: 901 153 639 - 0 | M41: Codigo Remuneración: | N41: =N3 -> 2026082 | U41: PROCERASEO S.A.S. | W41: NIT: 901 153 639 - 0 | AA41: Codigo Remuneración: | AD41: =N41 -> 2026082
F42: 3. ESQUEMA FINANCIERO DEL SERVICIO PUBLICO DE ASEO | U42: 3. ESQUEMA FINANCIERO DEL SERVICIO PUBLICO DE ASEO
F43: Resoluciòn UAESP Número 27 de 2018 | U43: Resoluciòn UAESP Número 27 de 2018
C44: Fecha de Proceso: | D44: =D6 -> 46267 | F44: R3 - RECAUDO EXTEMPORANEO | U44: R3 - RECAUDO EXTEMPORANEO
C45: Hora: | D45: =D7 -> 0.58333333 | F45: Fecha Desde: | G45: =G7 -> 46250 | J45: Feha Hasta: | K45: =K7 -> 46265 | U45: =F45 -> Fecha Desde: | V45: =G45 -> 46250 | X45: =J45 -> Feha Hasta: | Y45: =K45 -> 46265
B46: ASE | C46: Concesionarios | D46: Recaudo Total | E46: Recaudo por disposicion final | F46: Recaudo por tratamiento de lixiviados | G46: Recaudo por Componente VIAT ( Decreto 2412/2018) | H46: Recaudo por aprovechamiento | I46: Recaudo del componente de comercializacion para Aprovechamiento (11,4%) | J46: Balance de subsidio o contribuciones | K46: RECAUDO BASE DE REMUNERACION | L46: Costo de la Interventoría | M46: REMUNERACION FINAL | N46: Conceptos especiales | O46: REMUNERACION FINAL MAS CONCEPTOS ESPECIALES | S46: ASE | T46: Concesionarios | U46: Tarifa de Comercialización del Servicio. ( TCS) | V46: Tarifa de Limpieza Urbana del Servicio. ( TLU) | W46: Tarifa de Barrido y Limpieza del Servicio. ( TBL) | X46: Tarifa de Recolección y Transporte del Servicio. (TRT) | Y46: Recaudo del componente de comercializacion para Aprovechamiento (18,6%) | Z46: Costo de la Interventoría | AA46: Ajuste a la decena | AB46: Conceptos especiales | AC46: Otros | AD46: Diferencial Balance S / C (Fac vs Rec) | AE46: Balance S / C Con Base en (Recaudo) | AF46: REMUNERACION FINAL MAS CONCEPTOS ESPECIALES
B47: 1 | C47: PROMOAMBIENTAL DISTRITO S.A.S. ESP. | D47: ='Reporte Componentes R1'!F52 -> 63570 | E47: ='Reporte Componentes R1'!G52 -> 2242.46 | F47: ='Reporte Componentes R1'!H52 -> 1266.09 | G47: ='Reporte Componentes R1'!I52 -> 664.53 | H47: ='Reporte Componentes R1'!J52 -> 10026.01 | I47: ='Reporte Componentes R1'!K52 -> 372.31 | J47: 0 | K47: =D47-E47-F47-G47-H47-I47-J47 -> 48998.6 | L47: 0 | M47: =K47-L47 -> 48998.6 | N47: ='Reporte Componentes R1'!L52 -> 0 | O47: =M47+N47 -> 48998.6 | S47: 1 | T47: PROMOAMBIENTAL DISTRITO S.A.S. ESP. | U47: ='Reporte Componentes R1'!M52 -> 3265.88 | V47: ='Reporte Componentes R1'!N52 -> 3109.1 | W47: ='Reporte Componentes R1'!O52 -> 14722.61 | X47: ='Reporte Componentes R1'!P52 -> 6097.75 | Y47: ='Reporte Componentes R1'!Q52 -> 607.45 | Z47: =-L47 -> 0 | AA47: ='Reporte Componentes R1'!R52+'Reporte Componentes R1'!V52+'Reporte Componentes R1'!U52 -> -4.77 | AB47: =N47 -> 0 | AC47: ='Reporte Componentes R1'!T52+'Reporte Componentes R1'!W52+'Reporte Componentes R1'!X52+'Reporte Componentes R1'!Y52+'Reporte Componentes R1'!Z52+'Reporte Componentes R1'!S52 -> 0 | AD47: =-J47+AE47 -> 21200.58 | AE47: ='Reporte Componentes R1'!F53 -> 21200.58 | AF47: =SUM(U47:AD47) -> 48998.6 | AG47: =(AF47-O47) -> 0 | AH47: =INT(AG47)=0 -> TRUE
B48: 2 | C48: LIMPIEZA METROPOLITANA S.A. ESP. | D48: ='Reporte Componentes R1'!F196 -> 221630 | E48: ='Reporte Componentes R1'!G196 -> 13093.19 | F48: ='Reporte Componentes R1'!H196 -> 7370.27 | G48: ='Reporte Componentes R1'!I196 -> 5041.79 | H48: ='Reporte Componentes R1'!J196 -> 30894.49 | I48: ='Reporte Componentes R1'!K196 -> 1299.19 | J48: 0 | K48: =D48-E48-F48-G48-H48-I48-J48 -> 163931.07 | L48: 0 | M48: =K48-L48 -> 163931.07 | N48: ='Reporte Componentes R1'!L196 -> 0 | O48: =M48+N48 -> 163931.07 | S48: 2 | T48: LIMPIEZA METROPOLITANA S.A. ESP. | U48: ='Reporte Componentes R1'!M196 -> 8109.96 | V48: ='Reporte Componentes R1'!N196 -> 11107.28 | W48: ='Reporte Componentes R1'!O196 -> 52502.44 | X48: ='Reporte Componentes R1'!P196 -> 24418.29 | Y48: ='Reporte Componentes R1'!Q196 -> 2596.57 | Z48: =-L48 -> 0 | AA48: ='Reporte Componentes R1'!R196+'Reporte Componentes R1'!V196+'Reporte Componentes R1'!U196 -> -0.28 | AB48: =N48 -> 0 | AC48: ='Reporte Componentes R1'!T196+'Reporte Componentes R1'!W196+'Reporte Componentes R1'!X196+'Reporte Componentes R1'!Y196+'Reporte Componentes R1'!Z196+'Reporte Componentes R1'!S196 -> 0 | AD48: =-J48+AE48 -> 65196.81 | AE48: ='Reporte Componentes R1'!F197 -> 65196.81 | AF48: =SUM(U48:AD48) -> 163931.07 | AG48: =(AF48-O48) -> 0 | AH48: =INT(AG48)=0 -> TRUE
B49: 3 | C49: CIUDAD LIMPIA BOGOTA S.A. ESP. | D49: ='Reporte Componentes R1'!F327 -> 0 | E49: ='Reporte Componentes R1'!G327 -> 0 | F49: ='Reporte Componentes R1'!H327 -> 0 | G49: ='Reporte Componentes R1'!I327 -> 0 | H49: ='Reporte Componentes R1'!J327 -> 0 | I49: ='Reporte Componentes R1'!K327 -> 0 | J49: 0 | K49: =D49-E49-F49-G49-H49-I49-J49 -> 0 | L49: 0 | M49: =K49-L49 -> 0 | N49: ='Reporte Componentes R1'!L327 -> 0 | O49: =M49+N49 -> 0 | S49: 3 | T49: CIUDAD LIMPIA BOGOTA S.A. ESP. | U49: ='Reporte Componentes R1'!M327 -> 0 | V49: ='Reporte Componentes R1'!N327 -> 0 | W49: ='Reporte Componentes R1'!O327 -> 0 | X49: ='Reporte Componentes R1'!P327 -> 0 | Y49: ='Reporte Componentes R1'!Q327 -> 0 | Z49: =-L49 -> 0 | AA49: ='Reporte Componentes R1'!R327+'Reporte Componentes R1'!V327+'Reporte Componentes R1'!U327 -> 0 | AB49: =N49 -> 0 | AC49: ='Reporte Componentes R1'!T327+'Reporte Componentes R1'!W327+'Reporte Componentes R1'!X327+'Reporte Componentes R1'!Y327+'Reporte Componentes R1'!Z327+'Reporte Componentes R1'!S327 -> 0 | AD49: =-J49+AE49 -> 0 | AE49: ='Reporte Componentes R1'!F328 -> 0 | AF49: =SUM(U49:AD49) -> 0 | AG49: =(AF49-O49) -> 0 | AH49: =INT(AG49)=0 -> TRUE
B50: 4 | C50: BOGOTA LIMPIA S.A.S. ESP. | D50: ='Reporte Componentes R1'!F458 -> 4030410 | E50: ='Reporte Componentes R1'!G458 -> 234259.57 | F50: ='Reporte Componentes R1'!H458 -> 135887.63 | G50: ='Reporte Componentes R1'!I458 -> 70012.65 | H50: ='Reporte Componentes R1'!J458 -> 941307.97 | I50: ='Reporte Componentes R1'!K458 -> 31280.22 | J50: 0 | K50: =D50-E50-F50-G50-H50-I50-J50 -> 2617662 | L50: 0 | M50: =K50-L50 -> 2617662 | N50: ='Reporte Componentes R1'!L458 -> 0 | O50: =M50+N50 -> 2617662 | S50: 4 | T50: BOGOTA LIMPIA S.A.S. ESP. | U50: ='Reporte Componentes R1'!M458 -> 274387.94 | V50: ='Reporte Componentes R1'!N458 -> 297006.06 | W50: ='Reporte Componentes R1'!O458 -> 1496102.4 | X50: ='Reporte Componentes R1'!P458 -> 622968.34 | Y50: ='Reporte Componentes R1'!Q458 -> 51035.97 | Z50: =-L50 -> 0 | AA50: ='Reporte Componentes R1'!R458+'Reporte Componentes R1'!V458+'Reporte Componentes R1'!U458 -> 2.03 | AB50: =N50 -> 0 | AC50: ='Reporte Componentes R1'!T458+'Reporte Componentes R1'!W458+'Reporte Componentes R1'!X458+'Reporte Componentes R1'!Y458+'Reporte Componentes R1'!Z458+'Reporte Componentes R1'!S458 -> 0 | AD50: =-J50+AE50 -> -123840.82 | AE50: ='Reporte Componentes R1'!F459 -> -123840.82 | AF50: =SUM(U50:AD50) -> 2617662 | AG50: =(AF50-O50) -> -4.6566129e-10 | AH50: =INT(AG50)=0 -> FALSE
B51: 5 | C51: AREA LIMPIA DISTRITO CAPITAL S.A.S. ESP. | D51: ='Reporte Componentes R1'!F556 -> 1249810 | E51: ='Reporte Componentes R1'!G556 -> 89451.49 | F51: ='Reporte Componentes R1'!H556 -> 50203.36 | G51: ='Reporte Componentes R1'!I556 -> 26464.2 | H51: ='Reporte Componentes R1'!J556 -> 371981.73 | I51: ='Reporte Componentes R1'!K556 -> 13370.78 | J51: 0 | K51: =D51-E51-F51-G51-H51-I51-J51 -> 698338.44 | L51: 0 | M51: =K51-L51 -> 698338.44 | N51: ='Reporte Componentes R1'!L556 -> 0 | O51: =M51+N51 -> 698338.44 | S51: 5 | T51: AREA LIMPIA DISTRITO CAPITAL S.A.S. ESP. | U51: ='Reporte Componentes R1'!M556 -> 117292.3 | V51: ='Reporte Componentes R1'!N556 -> 115277.54 | W51: ='Reporte Componentes R1'!O556 -> 591928.6 | X51: ='Reporte Componentes R1'!P556 -> 268663.04 | Y51: ='Reporte Componentes R1'!Q556 -> 21816.48 | Z51: =-L51 -> 0 | AA51: ='Reporte Componentes R1'!R556+'Reporte Componentes R1'!V556+'Reporte Componentes R1'!U556 -> 57.02 | AB51: =N51 -> 0 | AC51: ='Reporte Componentes R1'!T556+'Reporte Componentes R1'!W556+'Reporte Componentes R1'!X556+'Reporte Componentes R1'!Y556+'Reporte Componentes R1'!Z556+'Reporte Componentes R1'!S556 -> 0 | AD51: =-J51+AE51 -> -416696.54 | AE51: ='Reporte Componentes R1'!F557 -> -416696.54 | AF51: =SUM(U51:AD51) -> 698338.44 | AG51: =(AF51-O51) -> 0 | AH51: =INT(AG51)=0 -> TRUE
C52: TOTAL | D52: =SUM(D47:D51) -> 5565420 | E52: =SUM(E47:E51) -> 339046.71 | F52: =SUM(F47:F51) -> 194727.35 | G52: =SUM(G47:G51) -> 102183.17 | H52: =SUM(H47:H51) -> 1354210.2 | I52: =SUM(I47:I51) -> 46322.5 | J52: =SUM(J47:J51) -> 0 | K52: =SUM(K47:K51) -> 3528930.1 | ... O52: =SUM(O47:O51) -> 3528930.1 | T52: TOTAL | U52: =SUM(U47:U51) -> 403056.08 | V52: =SUM(V47:V51) -> 426499.98 | W52: =SUM(W47:W51) -> 2155256.1 | X52: =SUM(X47:X51) -> 922147.42 | Y52: =SUM(Y47:Y51) -> 76056.47 | Z52: =SUM(Z47:Z51) -> 0 | AA52: =SUM(AA47:AA51) -> 54 | AB52: =SUM(AB47:AB51) -> 0 | ... AG52: =SUM(AG47:AG51) -> -4.6566129e-10 | AH52: =INT(AG52)=0 -> FALSE
Y54: =SUM(U52:Y52) -> 3983016
F56: Firma autorizada
F60: PROCERASEO S.A.S. | I60: NIT: 901 153 639 - 0 | M60: Codigo Remuneración: | N60: =N3 -> 2026082 | U60: PROCERASEO S.A.S. | W60: NIT: 901 153 639 - 0 | AA60: Codigo Remuneración: | AD60: =N60 -> 2026082
F61: 3. ESQUEMA FINANCIERO DEL SERVICIO PUBLICO DE ASEO | U61: 3. ESQUEMA FINANCIERO DEL SERVICIO PUBLICO DE ASEO
F62: Resoluciòn UAESP Número 27 de 2018 | U62: Resoluciòn UAESP Número 27 de 2018
C63: Fecha de Proceso: | D63: =D6 -> 46267 | F63: R4 - REVERSIÓN DE PAGOS | U63: R4 - REVERSIÓN DE PAGOS
C64: Hora: | D64: =D7 -> 0.58333333 | F64: Fecha Desde: | G64: =G7 -> 46250 | J64: Feha Hasta: | K64: =K7 -> 46265 | U64: =F64 -> Fecha Desde: | V64: =G64 -> 46250 | X64: =J64 -> Feha Hasta: | Y64: =K64 -> 46265
B65: ASE | C65: Concesionarios | D65: Recaudo Total | E65: Recaudo por disposicion final | F65: Recaudo por tratamiento de lixiviados | G65: Recaudo por Componente VIAT ( Decreto 2412/2018) | H65: Recaudo por aprovechamiento | I65: Recaudo del componente de comercializacion para Aprovechamiento (11,4%) | J65: Balance de subsidio o contribuciones | K65: RECAUDO BASE DE REMUNERACION | L65: Costo de la Interventoría | M65: REMUNERACION FINAL | N65: Conceptos especiales | O65: REMUNERACION FINAL MAS CONCEPTOS ESPECIALES | S65: ASE | T65: Concesionarios | U65: Tarifa de Comercialización del Servicio. ( TCS) | V65: Tarifa de Limpieza Urbana del Servicio. ( TLU) | W65: Tarifa de Barrido y Limpieza del Servicio. ( TBL) | X65: Tarifa de Recolección y Transporte del Servicio. (TRT) | Y65: Recaudo del componente de comercializacion para Aprovechamiento (18,6%) | Z65: Costo de la Interventoría | AA65: Ajuste a la decena | AB65: Conceptos especiales | AC65: Otros | AD65: Diferencial Balance S / C (Fac vs Rec) | AE65: Balance S / C Con Base en (Recaudo) | AF65: REMUNERACION FINAL MAS CONCEPTOS ESPECIALES
B66: 1 | C66: PROMOAMBIENTAL DISTRITO S.A.S. ESP. | D66: ='Reversion Pagos R4'!D66 -> -73090 | E66: ='Reversion Pagos R4'!E66 -> -2974.76 | F66: ='Reversion Pagos R4'!F66 -> -1679.55 | G66: ='Reversion Pagos R4'!G66 -> -881.55 | H66: ='Reversion Pagos R4'!H66 -> -11542.33 | I66: ='Reversion Pagos R4'!I66 -> -391.85 | J66: 0 | K66: =D66-E66-F66-G66-H66-I66-J66 -> -55619.96 | L66: 0 | M66: =K66-L66 -> -55619.96 | N66: ='Reversion Pagos R4'!P66 -> 0 | O66: =M66+N66 -> -55619.96 | S66: 1 | T66: PROMOAMBIENTAL DISTRITO S.A.S. ESP. | U66: ='Reversion Pagos R4'!J66 -> -3437.25 | V66: ='Reversion Pagos R4'!K66 -> -3322.9 | W66: ='Reversion Pagos R4'!L66 -> -15733.99 | X66: ='Reversion Pagos R4'!M66 -> -8124.53 | Y66: ='Reversion Pagos R4'!N66 -> -639.32 | Z66: =-L66 -> 0 | AA66: ='Reversion Pagos R4'!O66 -> 2.23 | AB66: =N66 -> 0 | AC66: =+'Reversion Pagos R4'!Q66+'Reversion Pagos R4'!R66 -> 0 | AD66: =-J66+AE66 -> -24364.2 | AE66: ='Reversion Pagos R4'!D67 -> -24364.2 | AF66: =SUM(U66:AD66) -> -55619.96 | AG66: =(AF66-O66) -> 0 | AH66: =INT(AG66)=0 -> TRUE
B67: 2 | C67: LIMPIEZA METROPOLITANA S.A. ESP. | D67: ='Reversion Pagos R4'!D161 -> -13472482 | E67: ='Reversion Pagos R4'!E161 -> -1036260.1 | F67: ='Reversion Pagos R4'!F161 -> -579395.95 | G67: ='Reversion Pagos R4'!G161 -> -306288.98 | H67: ='Reversion Pagos R4'!H161 -> -3205201.5 | I67: ='Reversion Pagos R4'!I161 -> -117270.82 | J67: 0 | K67: =D67-E67-F67-G67-H67-I67-J67 -> -8228064.6 | L67: 0 | M67: =K67-L67 -> -8228064.6 | N67: ='Reversion Pagos R4'!P161 -> 0 | O67: =M67+N67 -> -8228064.6 | S67: 2 | T67: LIMPIEZA METROPOLITANA S.A. ESP. | U67: ='Reversion Pagos R4'!J161 -> -1021860.6 | V67: ='Reversion Pagos R4'!K161 -> -1015840.9 | W67: ='Reversion Pagos R4'!L161 -> -4740681.8 | X67: ='Reversion Pagos R4'!M161 -> -2057044 | Y67: ='Reversion Pagos R4'!N161 -> -191335.25 | Z67: =-L67 -> 0 | AA67: ='Reversion Pagos R4'!O161 -> -39.68 | AB67: =N67 -> 0 | AC67: =+'Reversion Pagos R4'!Q161+'Reversion Pagos R4'!R161 -> 0 | AD67: =-J67+AE67 -> 798737.62 | AE67: ='Reversion Pagos R4'!D162 -> 798737.62 | AF67: =SUM(U67:AD67) -> -8228064.6 | AG67: =(AF67-O67) -> 0 | AH67: =INT(AG67)=0 -> TRUE
B68: 3 | C68: CIUDAD LIMPIA BOGOTA S.A. ESP. | D68: ='Reversion Pagos R4'!D192 -> -4617354 | E68: ='Reversion Pagos R4'!E192 -> -268346.34 | F68: ='Reversion Pagos R4'!F192 -> -152554.12 | G68: ='Reversion Pagos R4'!G192 -> -80139.33 | H68: ='Reversion Pagos R4'!H192 -> -1327068 | I68: ='Reversion Pagos R4'!I192 -> -47383.24 | J68: 0 | K68: =D68-E68-F68-G68-H68-I68-J68 -> -2741863 | L68: 0 | M68: =K68-L68 -> -2741863 | N68: ='Reversion Pagos R4'!P192 -> 0 | O68: =M68+N68 -> -2741863 | S68: 3 | T68: CIUDAD LIMPIA BOGOTA S.A. ESP. | U68: ='Reversion Pagos R4'!J192 -> -411968.93 | V68: ='Reversion Pagos R4'!K192 -> -406761.05 | W68: ='Reversion Pagos R4'!L192 -> -1917246.2 | X68: ='Reversion Pagos R4'!M192 -> -624532.34 | Y68: ='Reversion Pagos R4'!N192 -> -77512.18 | Z68: =-L68 -> 0 | AA68: ='Reversion Pagos R4'!O192 -> -75.61 | AB68: =N68 -> 0 | AC68: =+'Reversion Pagos R4'!Q192+'Reversion Pagos R4'!R192 -> 0 | AD68: =-J68+AE68 -> 696233.39 | AE68: ='Reversion Pagos R4'!D193 -> 696233.39 | AF68: =SUM(U68:AD68) -> -2741863 | AG68: =(AF68-O68) -> 0 | AH68: =INT(AG68)=0 -> TRUE
B69: 4 | C69: BOGOTA LIMPIA S.A.S. ESP. | D69: ='Reversion Pagos R4'!D306 -> -15663330 | E69: ='Reversion Pagos R4'!E306 -> -1059006.9 | F69: ='Reversion Pagos R4'!F306 -> -573631.78 | G69: ='Reversion Pagos R4'!G306 -> -300218.3 | H69: ='Reversion Pagos R4'!H306 -> -4067879.9 | I69: ='Reversion Pagos R4'!I306 -> -144753.44 | J69: 0 | K69: =D69-E69-F69-G69-H69-I69-J69 -> -9517839.6 | L69: 0 | M69: =K69-L69 -> -9517839.6 | N69: ='Reversion Pagos R4'!P306 -> 0 | O69: =M69+N69 -> -9517839.6 | S69: 4 | T69: BOGOTA LIMPIA S.A.S. ESP. | U69: ='Reversion Pagos R4'!J306 -> -1277818.8 | V69: ='Reversion Pagos R4'!K306 -> -1321433.8 | W69: ='Reversion Pagos R4'!L306 -> -6533412.2 | X69: ='Reversion Pagos R4'!M306 -> -2813333.2 | Y69: ='Reversion Pagos R4'!N306 -> -237859.31 | Z69: =-L69 -> 0 | AA69: ='Reversion Pagos R4'!O306 -> 8.64 | AB69: =N69 -> 0 | AC69: =+'Reversion Pagos R4'!Q306+'Reversion Pagos R4'!R306 -> 232.44 | AD69: =-J69+AE69 -> 2665776.6 | AE69: ='Reversion Pagos R4'!D307 -> 2665776.6 | AF69: =SUM(U69:AD69) -> -9517839.6 | AG69: =(AF69-O69) -> 0 | AH69: =INT(AG69)=0 -> TRUE
B70: 5 | C70: AREA LIMPIA DISTRITO CAPITAL S.A.S. ESP. | D70: ='Reversion Pagos R4'!D341 -> -4011371.6 | E70: ='Reversion Pagos R4'!E341 -> -274671.01 | F70: ='Reversion Pagos R4'!F341 -> -136526.62 | G70: ='Reversion Pagos R4'!G341 -> -73359.51 | H70: ='Reversion Pagos R4'!H341 -> -1044262.1 | I70: ='Reversion Pagos R4'!I341 -> -31578.27 | J70: 0 | K70: =D70-E70-F70-G70-H70-I70-J70 -> -2450974.1 | L70: 0 | M70: =K70-L70 -> -2450974.1 | N70: ='Reversion Pagos R4'!P341 -> 0 | O70: =M70+N70 -> -2450974.1 | S70: 5 | T70: AREA LIMPIA DISTRITO CAPITAL S.A.S. ESP. | U70: ='Reversion Pagos R4'!J341 -> -276998.02 | V70: ='Reversion Pagos R4'!K341 -> -308585.74 | W70: ='Reversion Pagos R4'!L341 -> -1559384.6 | X70: ='Reversion Pagos R4'!M341 -> -820306.52 | Y70: ='Reversion Pagos R4'!N341 -> -51521.64 | Z70: =-L70 -> 0 | AA70: ='Reversion Pagos R4'!O341 -> -44.07 | AB70: =N70 -> 0 | AC70: =+'Reversion Pagos R4'!Q341+'Reversion Pagos R4'!R341 -> 0 | AD70: =-J70+AE70 -> 565866.5 | AE70: ='Reversion Pagos R4'!D342 -> 565866.5 | AF70: =SUM(U70:AD70) -> -2450974.1 | AG70: =(AF70-O70) -> 0 | AH70: =INT(AG70)=0 -> TRUE
C71: TOTAL | D71: =SUM(D66:D70) -> -37837628 | E71: =SUM(E66:E70) -> -2641259.2 | F71: =SUM(F66:F70) -> -1443788 | G71: =SUM(G66:G70) -> -760887.67 | H71: =SUM(H66:H70) -> -9655953.9 | I71: =SUM(I66:I70) -> -341377.62 | J71: =SUM(J66:J70) -> 0 | K71: =SUM(K66:K70) -> -22994361 | ... O71: =SUM(O66:O70) -> -22994361 | T71: TOTAL | U71: =SUM(U66:U70) -> -2992083.6 | V71: =SUM(V66:V70) -> -3055944.4 | W71: =SUM(W66:W70) -> -14766459 | X71: =SUM(X66:X70) -> -6323340.6 | Y71: =SUM(Y66:Y70) -> -558867.7 | Z71: =SUM(Z66:Z70) -> 0 | AA71: =SUM(AA66:AA70) -> -148.49 | AB71: =SUM(AB66:AB70) -> 0 | ... AG71: =SUM(AG66:AG70) -> 0 | AH71: =INT(AG71)=0 -> TRUE
Y73: =SUM(U71:Y71) -> -27696695
F75: Firma autorizada
F79: PROCERASEO S.A.S. | I79: NIT: 901 153 639 - 0 | M79: Codigo Remuneración: | N79: =N3 -> 2026082 | U79: PROCERASEO S.A.S. | W79: NIT: 901 153 639 - 0 | AA79: Codigo Remuneración: | AD79: =N79 -> 2026082
F80: 3. ESQUEMA FINANCIERO DEL SERVICIO PUBLICO DE ASEO | U80: 3. ESQUEMA FINANCIERO DEL SERVICIO PUBLICO DE ASEO
F81: Resoluciòn UAESP Número 27 de 2018 | U81: Resoluciòn UAESP Número 27 de 2018
C82: Fecha de Proceso: | D82: =D6 -> 46267 | F82: R5 - REMUNERACIÓN SALDOS A FAVOR POR NOTA | U82: =F82 -> R5 - REMUNERACIÓN SALDOS A FAVOR POR NOTA
C83: Hora: | D83: =D7 -> 0.58333333 | F83: Fecha Desde: | G83: =G7 -> 46250 | J83: Feha Hasta: | K83: =K7 -> 46265 | U83: =F83 -> Fecha Desde: | V83: =G83 -> 46250 | X83: =J83 -> Feha Hasta: | Y83: =K83 -> 46265
B84: ASE | C84: Concesionarios | D84: Recaudo Total | E84: Recaudo por disposicion final | F84: Recaudo por tratamiento de lixiviados | G84: Recaudo por Componente VIAT ( Decreto 2412/2018) | H84: Recaudo por aprovechamiento | I84: Recaudo del componente de comercializacion para Aprovechamiento (11,4%) | J84: Balance de subsidio o contribuciones | K84: RECAUDO BASE DE REMUNERACION | L84: Costo de la Interventoría | M84: REMUNERACION FINAL | N84: Conceptos especiales | O84: REMUNERACION FINAL MAS CONCEPTOS ESPECIALES | S84: ASE | T84: Concesionarios | U84: Tarifa de Comercialización del Servicio. ( TCS) | V84: Tarifa de Limpieza Urbana del Servicio. ( TLU) | W84: Tarifa de Barrido y Limpieza del Servicio. ( TBL) | X84: Tarifa de Recolección y Transporte del Servicio. (TRT) | Y84: Recaudo del componente de comercializacion para Aprovechamiento (18,6%) | Z84: Costo de la Interventoría | AA84: Ajuste a la decena | AB84: Conceptos especiales | AC84: Otros | AD84: Diferencial Balance Subsidio y Contribución (Fac vs Rec) | AE84: Balance de subsidio o contribuciones (Recaudo) | AF84: REMUNERACION FINAL MAS CONCEPTOS ESPECIALES
B85: 1 | C85: PROMOAMBIENTAL DISTRITO S.A.S. ESP. | D85: ='AJUSTES - SF-T'!D47 -> 806955.98 | E85: ='AJUSTES - SF-T'!E47 -> 65039.95 | F85: ='AJUSTES - SF-T'!F47 -> 36337.02 | G85: ='AJUSTES - SF-T'!G47 -> 19274.13 | H85: ='AJUSTES - SF-T'!H47 -> 155423.91 | I85: ='AJUSTES - SF-T'!I47 -> 5618.35 | J85: ='AJUSTES - SF-T'!J47 -> 0 | K85: =D85-E85-F85-G85-H85-I85-J85 -> 525262.62 | L85: 0 | M85: =K85-L85 -> 525262.62 | N85: ='AJUSTES - SF-T'!N47 -> 0 | O85: =M85+N85 -> 525262.62 | S85: 1 | T85: PROMOAMBIENTAL DISTRITO S.A.S. ESP. | U85: ='AJUSTES - SF-T'!U47 -> 56003.23 | V85: ='AJUSTES - SF-T'!V47 -> 48167.15 | W85: ='AJUSTES - SF-T'!W47 -> 226758.45 | X85: ='AJUSTES - SF-T'!X47 -> 182170.76 | Y85: ='AJUSTES - SF-T'!Y47 -> 9166.69 | Z85: =-L85 -> 0 | AA85: ='AJUSTES - SF-T'!AA47 -> 0.04 | AB85: =N85 -> 0 | AC85: 0 | AD85: =-J85+AE85 -> 2996.3 | AE85: ='AJUSTES - SF-T'!AD47 -> 2996.3 | AF85: =SUM(U85:AD85) -> 525262.62 | AG85: =AF85-O85 -> 0 | AH85: =INT(AG85)=0 -> TRUE
B86: 2 | C86: LIMPIEZA METROPOLITANA S.A. ESP. | D86: ='AJUSTES - SF-T'!D48 -> 506855.36 | E86: ='AJUSTES - SF-T'!E48 -> 42296.72 | F86: ='AJUSTES - SF-T'!F48 -> 23907.98 | G86: ='AJUSTES - SF-T'!G48 -> 12706.35 | H86: ='AJUSTES - SF-T'!H48 -> 265979.53 | I86: ='AJUSTES - SF-T'!I48 -> 11995.53 | J86: ='AJUSTES - SF-T'!J48 -> 0 | K86: =D86-E86-F86-G86-H86-I86-J86 -> 149969.25 | L86: 0 | M86: =K86-L86 -> 149969.25 | N86: ='AJUSTES - SF-T'!N48 -> 0 | O86: =M86+N86 -> 149969.25 | S86: 2 | T86: LIMPIEZA METROPOLITANA S.A. ESP. | U86: ='AJUSTES - SF-T'!U48 -> 66026.12 | V86: ='AJUSTES - SF-T'!V48 -> 73645.62 | W86: ='AJUSTES - SF-T'!W48 -> 345565.65 | X86: ='AJUSTES - SF-T'!X48 -> 81955.14 | Y86: ='AJUSTES - SF-T'!Y48 -> 6998.74 | Z86: =-L86 -> 0 | AA86: ='AJUSTES - SF-T'!AA48 -> -3.66 | AB86: =N86 -> 0 | AC86: 0 | AD86: =-J86+AE86 -> -424218.36 | AE86: ='AJUSTES - SF-T'!AD48 -> -424218.36 | AF86: =SUM(U86:AD86) -> 149969.25 | AG86: =AF86-O86 -> 0 | AH86: =INT(AG86)=0 -> TRUE
B87: 3 | C87: CIUDAD LIMPIA BOGOTA S.A. ESP. | D87: ='AJUSTES - SF-T'!D49 -> 118874.84 | E87: ='AJUSTES - SF-T'!E49 -> 6267.13 | F87: ='AJUSTES - SF-T'!F49 -> 3538.42 | G87: ='AJUSTES - SF-T'!G49 -> 1857.22 | H87: ='AJUSTES - SF-T'!H49 -> 42966.81 | I87: ='AJUSTES - SF-T'!I49 -> 743.08 | J87: ='AJUSTES - SF-T'!J49 -> 0 | K87: =D87-E87-F87-G87-H87-I87-J87 -> 63502.18 | L87: 0 | M87: =K87-L87 -> 63502.18 | N87: ='AJUSTES - SF-T'!N49 -> 0 | O87: =M87+N87 -> 63502.18 | S87: 3 | T87: CIUDAD LIMPIA BOGOTA S.A. ESP. | U87: ='AJUSTES - SF-T'!U49 -> 6518.28 | V87: ='AJUSTES - SF-T'!V49 -> 6322.58 | W87: ='AJUSTES - SF-T'!W49 -> 29933.14 | X87: ='AJUSTES - SF-T'!X49 -> 14860.01 | Y87: ='AJUSTES - SF-T'!Y49 -> 1212.4 | Z87: =-L87 -> 0 | AA87: ='AJUSTES - SF-T'!AA49 -> 0 | AB87: =N87 -> 0 | AC87: 0 | AD87: =-J87+AE87 -> 4655.77 | AE87: ='AJUSTES - SF-T'!AD49 -> 4655.77 | AF87: =SUM(U87:AD87) -> 63502.18 | AG87: =AF87-O87 -> 0 | AH87: =INT(AG87)=0 -> TRUE
B88: 4 | C88: BOGOTA LIMPIA S.A.S. ESP. | D88: ='AJUSTES - SF-T'!D50 -> 318314.48 | E88: ='AJUSTES - SF-T'!E50 -> 30353.42 | F88: ='AJUSTES - SF-T'!F50 -> 17272.31 | G88: ='AJUSTES - SF-T'!G50 -> 7260.85 | H88: ='AJUSTES - SF-T'!H50 -> 195770.56 | I88: ='AJUSTES - SF-T'!I50 -> 5001.67 | J88: ='AJUSTES - SF-T'!J50 -> 0 | K88: =D88-E88-F88-G88-H88-I88-J88 -> 62655.67 | L88: 0 | M88: =K88-L88 -> 62655.67 | N88: ='AJUSTES - SF-T'!N50 -> 0 | O88: =M88+N88 -> 62655.67 | S88: 4 | T88: BOGOTA LIMPIA S.A.S. ESP. | U88: ='AJUSTES - SF-T'!U50 -> 31654.75 | V88: ='AJUSTES - SF-T'!V50 -> 16169.51 | W88: ='AJUSTES - SF-T'!W50 -> 625209.87 | X88: ='AJUSTES - SF-T'!X50 -> 92025.49 | Y88: ='AJUSTES - SF-T'!Y50 -> 3836.24 | Z88: =-L88 -> 0 | AA88: ='AJUSTES - SF-T'!AA50 -> 20.01 | AB88: =N88 -> 0 | AC88: 0 | AD88: =-J88+AE88 -> -706260.2 | AE88: ='AJUSTES - SF-T'!AD50 -> -706260.2 | AF88: =SUM(U88:AD88) -> 62655.67 | AG88: =AF88-O88 -> 0 | AH88: =INT(AG88)=0 -> TRUE
B89: 5 | C89: AREA LIMPIA DISTRITO CAPITAL S.A.S. ESP. | D89: ='AJUSTES - SF-T'!D51 -> 0 | E89: ='AJUSTES - SF-T'!E51 -> 0 | F89: ='AJUSTES - SF-T'!F51 -> 0 | G89: ='AJUSTES - SF-T'!G51 -> 0 | H89: ='AJUSTES - SF-T'!H51 -> 0 | I89: ='AJUSTES - SF-T'!I51 -> 0 | J89: ='AJUSTES - SF-T'!J51 -> 0 | K89: =D89-E89-F89-G89-H89-I89-J89 -> 0 | L89: 0 | M89: =K89-L89 -> 0 | N89: ='AJUSTES - SF-T'!N51 -> 0 | O89: =M89+N89 -> 0 | S89: 5 | T89: AREA LIMPIA DISTRITO CAPITAL S.A.S. ESP. | U89: ='AJUSTES - SF-T'!U51 -> 0 | V89: ='AJUSTES - SF-T'!V51 -> 0 | W89: ='AJUSTES - SF-T'!W51 -> 0 | X89: ='AJUSTES - SF-T'!X51 -> 0 | Y89: ='AJUSTES - SF-T'!Y51 -> 0 | Z89: =-L89 -> 0 | AA89: ='AJUSTES - SF-T'!AA51 -> 0 | AB89: =N89 -> 0 | AC89: 0 | AD89: =-J89+AE89 -> 0 | AE89: ='AJUSTES - SF-T'!AD51 -> 0 | AF89: =SUM(U89:AD89) -> 0 | AG89: =AF89-O89 -> 0 | AH89: =INT(AG89)=0 -> TRUE
C90: TOTAL | D90: =SUM(D85:D89) -> 1751000.7 | E90: =SUM(E85:E89) -> 143957.22 | F90: =SUM(F85:F89) -> 81055.73 | G90: =SUM(G85:G89) -> 41098.55 | H90: =SUM(H85:H89) -> 660140.81 | I90: =SUM(I85:I89) -> 23358.63 | J90: =SUM(J85:J89) -> 0 | K90: =SUM(K85:K89) -> 801389.72 | ... O90: =SUM(O85:O89) -> 801389.72 | T90: TOTAL | U90: =SUM(U85:U89) -> 160202.38 | V90: =SUM(V85:V89) -> 144304.86 | W90: =SUM(W85:W89) -> 1227467.1 | X90: =SUM(X85:X89) -> 371011.4 | Y90: =SUM(Y85:Y89) -> 21214.07 | Z90: =SUM(Z85:Z89) -> 0 | AA90: =SUM(AA85:AA89) -> 16.39 | AB90: =SUM(AB85:AB89) -> 0 | ... AG90: =SUM(AG85:AG89) -> 0 | AH90: =INT(AG90)=0 -> TRUE
Y92: =SUM(U90:Y90) -> 1924199.8
F94: Firma autorizada
F98: PROCERASEO S.A.S. | I98: NIT: 901 153 639 - 0 | M98: Codigo Remuneración: | N98: =N3 -> 2026082 | U98: PROCERASEO S.A.S. | W98: NIT: 901 153 639 - 0 | AA98: Codigo Remuneración: | AD98: =N98 -> 2026082
F99: 3. ESQUEMA FINANCIERO DEL SERVICIO PUBLICO DE ASEO | U99: 3. ESQUEMA FINANCIERO DEL SERVICIO PUBLICO DE ASEO
F100: Resoluciòn UAESP Número 27 de 2018 | U100: Resoluciòn UAESP Número 27 de 2018
C101: Fecha de Proceso: | D101: =D6 -> 46267 | F101: REPORTE CONSOLIDADO TOTAL DE RECAUDO | U101: REPORTE DETALLADO SUBBOLSA RBL DISCRIMINADO POR ACTIVIDADES
C102: Hora: | D102: =D7 -> 0.58333333 | F102: Fecha Desde: | G102: =G7 -> 46250 | J102: Feha Hasta: | K102: =K7 -> 46265 | U102: =F102 -> Fecha Desde: | V102: =G102 -> 46250 | X102: =J102 -> Feha Hasta: | Y102: =K102 -> 46265
B103: ASE | C103: Concesionarios | D103: Recaudo Total | E103: Recaudo por disposicion final | F103: Recaudo por tratamiento de lixiviados | G103: Recaudo por Componente VIAT ( Decreto 2412/2018) | H103: Recaudo por aprovechamiento | I103: Recaudo del componente de comercializacion para Aprovechamiento (11,4%) | J103: Balance de subsidio o contribuciones | K103: RECAUDO BASE DE REMUNERACION | L103: Costo de la Interventoría | M103: REMUNERACION FINAL | N103: Conceptos especiales | O103: REMUNERACION FINAL MAS CONCEPTOS ESPECIALES | S103: ASE | T103: Concesionarios | U103: Tarifa de Comercialización del Servicio. ( TCS) | V103: Tarifa de Limpieza Urbana del Servicio. ( TLU) | W103: Tarifa de Barrido y Limpieza del Servicio. ( TBL) | X103: Tarifa de Recolección y Transporte del Servicio. (TRT) | Y103: Recaudo del componente de comercializacion para Aprovechamiento (18,6%) | Z103: Costo de la Interventoría | AA103: Ajuste a la decena | AB103: Conceptos especiales | AC103: Otros | AD103: Diferencial Balance Subsidio y Contribución (Fac vs Rec) | AE103: Balance de subsidio o contribuciones (Recaudo) | AF103: REMUNERACION FINAL MAS CONCEPTOS ESPECIALES
B104: 1 | C104: PROMOAMBIENTAL DISTRITO S.A.S. ESP. | D104: =D9+D28+D47+D66+D85 -> 1.8378829e+10 | E104: =E9+E28+E47+E66+E85 -> 9.8082276e+08 | F104: =F9+F28+F47+F66+F85 -> 5.5308627e+08 | G104: =G9+G28+G47+G66+G85 -> 2.9104019e+08 | H104: =H9+H28+H47+H66+H85 -> 4.2008333e+09 | I104: =I9+I28+I47+I66+I85 -> 1.570668e+08 | J104: =J9+J28+J47+J66+J85 -> -3.6102137e+09 | K104: =D104-E104-F104-G104-H104-I104-J104 -> 1.5806194e+10 | L104: =L9+L28+L47+L66+L85 -> 189185988 | M104: =K104-L104 -> 1.5617008e+10 | N104: =N9+N28+N47+N66+N85 -> 37169760 | O104: =M104+N104 -> 1.5654177e+10 | S104: 1 | T104: PROMOAMBIENTAL DISTRITO S.A.S. ESP. | U104: =U9+U28+U47+U66+U85 -> 1.3820342e+09 | V104: =V9+V28+V47+V66+V85 -> 1.3177041e+09 | W104: =W9+W28+W47+W66+W85 -> 6.2312884e+09 | X104: =X9+X28+X47+X66+X85 -> 2.6643035e+09 | Y104: =Y9+Y28+Y47+Y66+Y85 -> 2.5636518e+08 | Z104: =Z9+Z28+Z47+Z66+Z85 -> -189185988 | AA104: =AA9+AA28+AA47+AA66+AA85 -> 71590.6 | AB104: =AB9+AB28+AB47+AB66+AB85 -> 37169760 | AC104: =AC9+AC28+AC47+AC66+AC85 -> 194.35 | AD104: =-J104+AE104 -> 3.9544265e+09 | AE104: =AE9+AE28+AE47+AE66+AE85 -> 3.4421278e+08 | AF104: =SUM(U104:AD104) -> 1.5654177e+10 | AG104: =AF104-O104 -> 0 | AH104: =INT(AG104)=0 -> TRUE
B105: 2 | C105: LIMPIEZA METROPOLITANA S.A. ESP. | D105: =D10+D29+D48+D67+D86 -> 2.159971e+10 | E105: =E10+E29+E48+E67+E86 -> 1.6649132e+09 | F105: =F10+F29+F48+F67+F86 -> 9.2891304e+08 | G105: =G10+G29+G48+G67+G86 -> 4.8489963e+08 | H105: =H10+H29+H48+H67+H86 -> 6.8366647e+09 | I105: =I10+I29+I48+I67+I86 -> 2.2646478e+08 | J105: =J10+J29+J48+J67+J86 -> -4.2898763e+09 | K105: =D105-E105-F105-G105-H105-I105-J105 -> 1.5747731e+10 | L105: =L10+L29+L48+L67+L86 -> 266580256 | M105: =K105-L105 -> 1.548115e+10 | N105: =N10+N29+N48+N67+N86 -> 65704059 | O105: =M105+N105 -> 1.5546854e+10 | S105: 2 | T105: LIMPIEZA METROPOLITANA S.A. ESP. | U105: =U10+U29+U48+U67+U86 -> 1.9867614e+09 | V105: =V10+V29+V48+V67+V86 -> 1.9856784e+09 | W105: =W10+W29+W48+W67+W86 -> 9.3389071e+09 | X105: =X10+X29+X48+X67+X86 -> 3.2723935e+09 | Y105: =Y10+Y29+Y48+Y67+Y86 -> 3.6945734e+08 | Z105: =Z10+Z29+Z48+Z67+Z86 -> -266580256 | AA105: =AA10+AA29+AA48+AA67+AA86 -> -219458.4 | AB105: =AB10+AB29+AB48+AB67+AB86 -> 65704059 | AC105: =AC10+AC29+AC48+AC67+AC86 -> 39.32 | AD105: =-J105+AE105 -> -1.2052477e+09 | AE105: =AE10+AE29+AE48+AE67+AE86 -> -5.495124e+09 | AF105: =SUM(U105:AD105) -> 1.5546854e+10 | AG105: =AF105-O105 -> 0 | AH105: =INT(AG105)=0 -> TRUE
