Workbook
Name \0: #REF!
Name _1: #REF!
Name _2: #REF!
Name _A655555: #REF!
Name _CFR1: #REF!
Name _cia1: #REF!
Name _XL250: #REF!
Name A: #REF!
Name ADM: [1]!ADM
Name ADM: [1]!ADM
Name ADM: [1]!ADM
Name ADM: [1]!ADM
Name ADM: [1]!ADM
Name ADM_: [1]!ADM
Name ADM_: [1]!ADM
Name ADM_: [1]!ADM
Name ADM_: [1]!ADM
Name ADM_: [1]!ADM
Name AI: #REF!
Name Air: #REF!
Name AP: '[2]TARIFA no aforos'!$C$12
Name Bancos: [3]Fx!$C$1:$C$23
Name CBL: #REF!
Name CCS: #REF!
Name CDT_p: [4]CDT!$C$3
Name CFR: #REF!
Name cia: #REF!
Name COM: #REF!
Name CRT: #REF!
Name CRT___CTEp___CDTp___CMRv: #REF!
Name CRT_aislados: '[4]COSTOS AJUSTADOS'!$C$13
Name CRT_costas: #REF!
Name CTE_p: [4]CTE!$C$5
Name Denominador: #REF!
Name dg: [1]!ADM
Name dg: [1]!ADM
Name dg: [1]!ADM
Name dg: [1]!ADM
Name dg: [1]!ADM
Name DIAS: [5]CONTRA!#REF!
Name Fmerc: #REF!
Name FPS: #REF!
Name InformacionGeneral: [1]!InformacionGeneral
Name InformacionGeneral: [1]!InformacionGeneral
Name InformacionGeneral: [1]!InformacionGeneral
Name InformacionGeneral: [1]!InformacionGeneral
Name InformacionGeneral: [1]!InformacionGeneral
Name INTFIN: #REF!
Name INV: [1]!INV
Name INV: [1]!INV
Name INV: [1]!INV
Name INV: [1]!INV
Name INV: [1]!INV
Name K: #REF!
Name N: '[4]COSTOS AJUSTADOS'!#REF!
Name Na: '[2]TARIFA no aforos'!$C$39
Name nfc: '[4]COSTOS AJUSTADOS'!#REF!
Name OYM: [1]!OYM
Name OYM: [1]!OYM
Name OYM: [1]!OYM

Sheet Recaudo EAAB Reciprocidad
B2: OPORTUNO | C2: ASE | D2: VALOR 1° Q | E2: NUMERO REG. 1°Q | F2: VALOR 2° Q | G2: NUMERO REG. 2°Q
C3: 1 | D3: 0 | E3: 0 | F3: 0 | G3: 0
C4: 2 | D4: 29345550 | E4: 341 | F4: 0 | G4: 0
C5: 3 | D5: 0 | E5: 0 | F5: 0 | G5: 0
C6: 4 | D6: 15240310 | E6: 108 | F6: 0 | G6: 0
C7: 5 | D7: 0 | E7: 0 | F7: 0 | G7: 0
C8: X
D9: 44585860 | E9: 449 | F9: 0 | G9: 0
C11: ASE | D11: VALOR 1° Q | E11: NUMERO REG. 1°Q | F11: VALOR 2° Q | G11: NUMERO REG. 2°Q
B12: EXTEMP. | C12: 1 | D12: 0 | E12: 0 | F12: 0 | G12: 0
C13: 2 | D13: 0 | E13: 0 | F13: 0 | G13: 0
C14: 3 | D14: 0 | E14: 0 | F14: 0 | G14: 0
C15: 4 | D15: 0 | E15: 0 | F15: 0 | G15: 0
C16: 5 | D16: 0 | E16: 0 | F16: 0 | G16: 0
C17: X
D18: 0 | E18: 0 | F18: 0 | G18: 0
C20: ASE | D20: VALOR 1° Q | E20: NUMERO REG. 1°Q | F20: VALOR 2° Q | G20: NUMERO REG. 2°Q | I20: VALOR TOTAL MES | J20: NUMERO REGISTROS MES
B21: TOTAL | C21: 1 | D21: 0 | E21: 0 | F21: 0 | G21: 0 | I21: 0 | J21: 0
C22: 2 | D22: 29345550 | E22: 341 | F22: 0 | G22: 0 | I22: 29345550 | J22: 341
C23: 3 | D23: 0 | E23: 0 | F23: 0 | G23: 0 | I23: 0 | J23: 0
C24: 4 | D24: 15240310 | E24: 108 | F24: 0 | G24: 0 | I24: 15240310 | J24: 108
C25: 5 | D25: 0 | E25: 0 | F25: 0 | G25: 0 | I25: 0 | J25: 0
C26: X | I26: 0 | J26: 0
D27: 44585860 | E27: 449 | F27: 0 | G27: 0 | I27: 44585860 | J27: 449
B31: OPORTUNO | D31: =D9=SUM(D3:D8) -> TRUE | E31: =E9=SUM(E3:E8) -> TRUE | F31: =F9=SUM(F3:F8) -> TRUE | G31: =G9=SUM(G3:G8) -> TRUE
B33: EXTEMP. | D33: =D18=SUM(D12:D17) -> TRUE | E33: =E18=SUM(E12:E17) -> TRUE | F33: =F18=SUM(F12:F17) -> TRUE | G33: =G18=SUM(G12:G17) -> TRUE
B35: TOTAL | D35: =D27=SUM(D21:D26) -> TRUE | E35: =E27=SUM(E21:E26) -> TRUE | F35: =F27=SUM(F21:F26) -> TRUE | G35: =G27=SUM(G21:G26) -> TRUE | I35: =I27=SUM(I21:I26) -> TRUE | J35: =J27=SUM(J21:J26) -> TRUE
E69: =C69-G17 -> 0

Sheet Recaudo ENEL
B2: OPORTUNO | C2: ASE | D2: VALOR 1° Q | E2: NUMERO REG. 1°Q | F2: VALOR 2° Q | G2: NUMERO REG. 2°Q
C3: 1 | D3: 16020970408 | E3: 330319 | F3: 0 | G3: 0
C4: 2 | D4: 11733539858 | E4: 232298 | F4: 0 | G4: 0
C5: 3 | D5: 9618825681 | E5: 222340 | F5: 0 | G5: 0
C6: 4 | D6: 10290225466 | E6: 177955 | F6: 0 | G6: 0
C7: 5 | D7: 8111886280 | E7: 159077 | F7: 0 | G7: 0
C8: X
D9: 55775447693 | E9: 1121989 | F9: 0 | G9: 0
C11: ASE | D11: VALOR 1° Q | E11: NUMERO REG. 1°Q | F11: VALOR 2° Q | G11: NUMERO REG. 2°Q
B12: EXTEMP. | C12: 1 | D12: 223833110 | E12: 3064 | F12: 0 | G12: 0
C13: 2 | D13: 99273804 | E13: 1926 | F13: 0 | G13: 0
C14: 3 | D14: 66145670 | E14: 1462 | F14: 0 | G14: 0
C15: 4 | D15: 85892126 | E15: 1255 | F15: 0 | G15: 0
C16: 5 | D16: 166326259 | E16: 2744 | F16: 0 | G16: 0
C17: X
D18: 641470969 | E18: 10451 | F18: 0 | G18: 0
C20: ASE | D20: VALOR 1° Q | E20: NUMERO REG. 1°Q | F20: VALOR 2° Q | G20: NUMERO REG. 2°Q | I20: VALOR TOTAL MES | J20: NUMERO REGISTROS MES
B21: TOTAL | C21: 1 | D21: 16244803518 | E21: 333383 | F21: 0 | G21: 0 | I21: 16244803518 | J21: 333383
C22: 2 | D22: 11832813662 | E22: 234224 | F22: 0 | G22: 0 | I22: 11832813662 | J22: 234224
C23: 3 | D23: 9684971351 | E23: 223802 | F23: 0 | G23: 0 | I23: 9684971351 | J23: 223802
C24: 4 | D24: 10376117592 | E24: 179210 | F24: 0 | G24: 0 | I24: 10376117592 | J24: 179210
C25: 5 | D25: 8278212539 | E25: 161821 | F25: 0 | G25: 0 | I25: 8278212539 | J25: 161821
C26: X | I26: 0 | J26: 0
D27: 56416918662 | E27: 1132440 | F27: 0 | G27: 0 | I27: 56416918662 | J27: 1132440
B31: OPORTUNO | D31: =D9=SUM(D3:D8) -> TRUE | E31: =E9=SUM(E3:E8) -> TRUE | F31: =F9=SUM(F3:F8) -> TRUE | G31: =G9=SUM(G3:G8) -> TRUE
B33: EXTEMP. | D33: =D18=SUM(D12:D17) -> TRUE | E33: =E18=SUM(E12:E17) -> TRUE | F33: =F18=SUM(F12:F17) -> TRUE | G33: =G18=SUM(G12:G17) -> TRUE
B35: TOTAL | D35: =D27=SUM(D21:D26) -> TRUE | E35: =E27=SUM(E21:E26) -> TRUE | F35: =F27=SUM(F21:F26) -> TRUE | G35: =G27=SUM(G21:G26) -> TRUE | I35: =I27=SUM(I21:I26) -> TRUE | J35: =J27=SUM(J21:J26) -> TRUE
E69: =C69-G17 -> 0

Sheet Recaudo ENERBIT
B2: OPORTUNO | C2: ASE | D2: VALOR 1° Q | E2: NUMERO REG. 1°Q | F2: VALOR 2° Q | G2: NUMERO REG. 2°Q
C3: 1 | D3: 0 | E3: 0 | F3: 0 | G3: 0
C4: 2 | D4: 0 | E4: 0 | F4: 0 | G4: 0
C5: 3 | D5: 0 | E5: 0 | F5: 0 | G5: 0
C6: 4 | D6: 0 | E6: 0 | F6: 0 | G6: 0
C7: 5 | D7: 129429946 | E7: 2854 | F7: 0 | G7: 0
C8: X
D9: 129429946 | E9: 2854 | F9: 0 | G9: 0
C11: ASE | D11: VALOR 1° Q | E11: NUMERO REG. 1°Q | F11: VALOR 2° Q | G11: NUMERO REG. 2°Q
B12: EXTEMP. | C12: 1 | D12: 0 | E12: 0 | F12: 0 | G12: 0
C13: 2 | D13: 0 | E13: 0 | F13: 0 | G13: 0
C14: 3 | D14: 0 | E14: 0 | F14: 0 | G14: 0
C15: 4 | D15: 0 | E15: 0 | F15: 0 | G15: 0
C16: 5 | D16: 106710 | E16: 1 | F16: 0 | G16: 0
C17: X
D18: 106710 | E18: 1 | F18: 0 | G18: 0
C20: ASE | D20: VALOR 1° Q | E20: NUMERO REG. 1°Q | F20: VALOR 2° Q | G20: NUMERO REG. 2°Q | I20: VALOR TOTAL MES | J20: NUMERO REGISTROS MES
B21: TOTAL | C21: 1 | D21: 0 | E21: 0 | F21: 0 | G21: 0 | I21: 0 | J21: 0
C22: 2 | D22: 0 | E22: 0 | F22: 0 | G22: 0 | I22: 0 | J22: 0
C23: 3 | D23: 0 | E23: 0 | F23: 0 | G23: 0 | I23: 0 | J23: 0
C24: 4 | D24: 0 | E24: 0 | F24: 0 | G24: 0 | I24: 0 | J24: 0
C25: 5 | D25: 129536656 | E25: 2855 | F25: 0 | G25: 0 | I25: 129536656 | J25: 2855
C26: X | I26: 0 | J26: 0
D27: 129536656 | E27: 2855 | F27: 0 | G27: 0 | I27: 129536656 | J27: 2855
B31: OPORTUNO | D31: =D9=SUM(D3:D8) -> TRUE | E31: =E9=SUM(E3:E8) -> TRUE | F31: =F9=SUM(F3:F8) -> TRUE | G31: =G9=SUM(G3:G8) -> TRUE
B33: EXTEMP. | D33: =D18=SUM(D12:D17) -> TRUE | E33: =E18=SUM(E12:E17) -> TRUE | F33: =F18=SUM(F12:F17) -> TRUE | G33: =G18=SUM(G12:G17) -> TRUE
B35: TOTAL | D35: =D27=SUM(D21:D26) -> TRUE | E35: =E27=SUM(E21:E26) -> TRUE | F35: =F27=SUM(F21:F26) -> TRUE | G35: =G27=SUM(G21:G26) -> TRUE | I35: =I27=SUM(I21:I26) -> TRUE | J35: =J27=SUM(J21:J26) -> TRUE
E69: =C69-G17 -> 0

Sheet Recaudo EAAB + Ciud Limp
B2: Ciudad Limpia - Prestador | C2: ASE | D2: VALOR 1° Q | E2: NUMERO REG. 1°Q | F2: VALOR 2° Q | G2: NUMERO REG. 2°Q
C3: 1 | D3: 0 | E3: 0 | F3: 0 | G3: 0
C4: 2 | D4: 0 | E4: 0 | F4: 0 | G4: 0
C5: 3 | D5: 0 | E5: 0 | F5: 0 | G5: 0
C6: 4 | D6: 0 | E6: 0 | F6: 0 | G6: 0
C7: 5 | D7: 0 | E7: 0 | F7: 0 | G7: 0
C8: X
D9: 0 | E9: 0 | F9: 0 | G9: 0
C11: ASE | D11: VALOR 1° Q | E11: NUMERO REG. 1°Q | F11: VALOR 2° Q | G11: NUMERO REG. 2°Q
B12: EAAB - Prestador | C12: 1 | D12: 0 | E12: 0 | F12: 0 | G12: 0
C13: 2 | D13: 0 | E13: 0 | F13: 0 | G13: 0
C14: 3 | D14: 0 | E14: 0 | F14: 0 | G14: 0
C15: 4 | D15: 0 | E15: 0 | F15: 0 | G15: 0
C16: 5 | D16: 0 | E16: 0 | F16: 0 | G16: 0
C17: X
D18: 0 | E18: 0 | F18: 0 | G18: 0
C20: ASE | D20: VALOR 1° Q | E20: NUMERO REG. 1°Q | F20: VALOR 2° Q | G20: NUMERO REG. 2°Q | I20: VALOR TOTAL MES | J20: NUMERO REGISTROS MES
B21: TOTAL | C21: 1 | D21: 0 | E21: 0 | F21: 0 | G21: 0 | I21: 0 | J21: 0
C22: 2 | D22: 0 | E22: 0 | F22: 0 | G22: 0 | I22: 0 | J22: 0
C23: 3 | D23: 0 | E23: 0 | F23: 0 | G23: 0 | I23: 0 | J23: 0
C24: 4 | D24: 0 | E24: 0 | F24: 0 | G24: 0 | I24: 0 | J24: 0
C25: 5 | D25: 0 | E25: 0 | F25: 0 | G25: 0 | I25: 0 | J25: 0
C26: X | I26: 0 | J26: 0
D27: 0 | E27: 0 | F27: 0 | G27: 0 | I27: 0 | J27: 0
B31: OPORTUNO | D31: =D9=SUM(D3:D8) -> TRUE | E31: =E9=SUM(E3:E8) -> TRUE | F31: =F9=SUM(F3:F8) -> TRUE | G31: =G9=SUM(G3:G8) -> TRUE
B33: EXTEMP. | D33: =D18=SUM(D12:D17) -> TRUE | E33: =E18=SUM(E12:E17) -> TRUE | F33: =F18=SUM(F12:F17) -> TRUE | G33: =G18=SUM(G12:G17) -> TRUE
B35: TOTAL | D35: =D27=SUM(D21:D26) -> TRUE | E35: =E27=SUM(E21:E26) -> TRUE | F35: =F27=SUM(F21:F26) -> TRUE | G35: =G27=SUM(G21:G26) -> TRUE | I35: =I27=SUM(I21:I26) -> TRUE | J35: =J27=SUM(J21:J26) -> TRUE

Sheet Recaudo Directa Occidente
B2: OPORTUNO | C2: ASE | D2: VALOR 1° Q | E2: NUMERO REG. 1°Q | F2: VALOR 2° Q | G2: NUMERO REG. 2°Q
C3: 1 | D3: 335015748 | E3: 1590 | F3: 0 | G3: 0
C4: 2 | D4: 389025865 | E4: 2713 | F4: 0 | G4: 0
C5: 3 | D5: 346289622 | E5: 1123 | F5: 0 | G5: 0
C6: 4 | D6: 236541566 | E6: 1643 | F6: 0 | G6: 0
C7: 5 | D7: 155743651 | E7: 776 | F7: 0 | G7: 0
C8: X | D8: 0 | E8: 0 | F8: 0 | G8: 0
D9: 1462616452 | E9: 7845 | F9: 0 | G9: 0
C11: ASE | D11: VALOR 1° Q | E11: NUMERO REG. 1°Q | F11: VALOR 2° Q | G11: NUMERO REG. 2°Q
B12: EXTEMP. | C12: 1 | D12: 205459944 | E12: 70 | F12: 0 | G12: 0
C13: 2 | D13: 33195420 | E13: 58 | F13: 0 | G13: 0
C14: 3 | D14: 126229443 | E14: 55 | F14: 0 | G14: 0
C15: 4 | D15: 2600820 | E15: 21 | F15: 0 | G15: 0
C16: 5 | D16: 25989911 | E16: 18 | F16: 0 | G16: 0
C17: X | D17: 0 | E17: 0 | F17: 0 | G17: 0
D18: 393475538 | E18: 222 | F18: 0 | G18: 0
C20: ASE | D20: VALOR 1° Q | E20: NUMERO REG. 1°Q | F20: VALOR 2° Q | G20: NUMERO REG. 2°Q | I20: VALOR TOTAL MES | J20: NUMERO REGISTROS MES
B21: TOTAL | C21: 1 | D21: 540475692 | E21: 1660 | F21: 0 | G21: 0 | I21: 540475692 | J21: 1660
C22: 2 | D22: 422221285 | E22: 2771 | F22: 0 | G22: 0 | I22: 422221285 | J22: 2771
C23: 3 | D23: 472519065 | E23: 1178 | F23: 0 | G23: 0 | I23: 472519065 | J23: 1178
C24: 4 | D24: 239142386 | E24: 1664 | F24: 0 | G24: 0 | I24: 239142386 | J24: 1664
C25: 5 | D25: 181733562 | E25: 794 | F25: 0 | G25: 0 | I25: 181733562 | J25: 794
C26: X | D26: 0 | E26: 0 | F26: 0 | G26: 0 | I26: 0 | J26: 0
D27: 1856091990 | E27: 8067 | F27: 0 | G27: 0 | I27: 1856091990 | J27: 8067
B31: OPORTUNO | D31: =D9=SUM(D3:D8) -> TRUE | E31: =E9=SUM(E3:E8) -> TRUE | F31: =F9=SUM(F3:F8) -> TRUE | G31: =G9=SUM(G3:G8) -> TRUE
B33: EXTEMP. | D33: =D18=SUM(D12:D17) -> TRUE | E33: =E18=SUM(E12:E17) -> TRUE | F33: =F18=SUM(F12:F17) -> TRUE | G33: =G18=SUM(G12:G17) -> TRUE
B35: TOTAL | D35: =D27=SUM(D21:D26) -> TRUE | E35: =E27=SUM(E21:E26) -> TRUE | F35: =F27=SUM(F21:F26) -> TRUE | G35: =G27=SUM(G21:G26) -> TRUE | I35: =I27=SUM(I21:I26) -> TRUE | J35: =J27=SUM(J21:J26) -> TRUE
E69: =C69-G17 -> 0

Sheet REPORTE RECAUDO x BANCO
C1: ENEL | D1: CIUDAD LIMPIA | E1: EAB | F1: NUEVO ESQUEMA | G1: ENERBIT | H1: OCCIDENTE | I1: Total
B2: 1-APLICADOS A FACTURACION | C2: =C13+C23+C32+C41+C51 -> 56225936823 | D2: =D13+D23+D32+D41+D51 -> 0 | E2: =E13+E23+E32+E41+E51 -> 0 | F2: =F13+F23+F32+F41+F51 -> 20835040 | G2: =G13+G23+G32+G41+G51 -> 126372915 | H2: =H13+H23+H32+H41+H51 -> 1.7599753e+09 | I2: =SUM(C2:H2) -> 5.813312e+10
B3: 2-SALDOS A FAVOR GENERADOS | C3: =C14+C24+C33+C42+C52 -> 192969109 | D3: =D14+D24+D33+D42+D52 -> 0 | E3: =E14+E24+E33+E42+E52 -> 0 | F3: =F14+F24+F33+F42+F52 -> 23750820 | G3: =G14+G24+G33+G42+G52 -> 3163741 | H3: =H14+H24+H33+H42+H52 -> 61262183 | I3: =SUM(C3:H3) -> 2.8114585e+08
B4: 3-APLICADOS A FINANCIACIONES NUEVAS | C4: =C15+C25+C34+C43+C53 -> 0 | D4: =D15+D25+D34+D43+D53 -> 0 | E4: =E15+E25+E34+E43+E53 -> 0 | F4: =F15+F25+F34+F43+F53 -> 0 | G4: =G15+G25+G34+G43+G53 -> 0 | H4: =H15+H25+H34+H43+H53 -> 34854485 | I4: =SUM(C4:H4) -> 34854485
B5: 7-APLICADOS A RECIBOS SERVICIOS ESPECIALES | C5: =C16+C26+C35+C44+C54 -> 0 | D5: =D16+D26+D35+D44+D54 -> 0 | E5: =E16+E26+E35+E44+E54 -> 0 | F5: =F16+F26+F35+F44+F54 -> 0 | G5: =G16+G26+G35+G44+G54 -> 0 | H5: =H16+H26+H35+H44+H54 -> 0 | I5: =SUM(C5:H5) -> 0
B6: Total | C6: =SUM(C2:C5) -> 56418905932 | D6: =SUM(D2:D5) -> 0 | E6: =SUM(E2:E5) -> 0 | F6: =SUM(F2:F5) -> 44585860 | G6: =SUM(G2:G5) -> 129536656 | H6: =SUM(H2:H5) -> 1856091990 | I6: =SUM(I2:I5) -> 5.844912e+10
C7: =C6=(C17+C27+C36+C45+C55) -> TRUE | D7: =D6=(D17+D27+D36+D45+D55) -> TRUE | E7: =E6=(E17+E27+E36+E45+E55) -> TRUE | F7: =F6=(F17+F27+F36+F45+F55) -> TRUE | H7: =H6=(H17+H27+H36+H45+H55) -> TRUE | I7: =I6=(I17+I27+I36+I45+I55) -> TRUE
B10: ASE 1
B11: Resumen Recaudo Aplicado Por Servicio
C12: ENEL | D12: CIUDAD LIMPIA | E12: EAB | F12: NUEVO ESQUEMA | G12: ENERBIT | H12: OCCIDENTE | I12: Total
B13: 1-APLICADOS A FACTURACION | C13: 16194517449 | H13: 5.2378272e+08 | I13: =SUM(C13:H13) -> 1.67183e+10 | J13: =SUM(C13:H13)=I13 -> TRUE
B14: 2-SALDOS A FAVOR GENERADOS | C14: 50286069 | H14: 12466967 | I14: =SUM(C14:H14) -> 62753036 | J14: =SUM(C14:H14)=I14 -> TRUE
B15: 3-APLICADOS A FINANCIACIONES NUEVAS | C15: 0 | H15: 4226000 | I15: =SUM(C15:H15) -> 4226000 | J15: =SUM(C15:H15)=I15 -> TRUE
B16: 7-APLICADOS A RECIBOS SERVICIOS ESPECIALES | C16: 0 | I16: =SUM(C16:H16) -> 0 | J16: =SUM(C16:H16)=I16 -> TRUE
B17: Total | C17: =SUM(C13:C16) -> 16244803518 | D17: =SUM(D13:D16) -> 0 | E17: =SUM(E13:E16) -> 0 | F17: =SUM(F13:F16) -> 0 | G17: =SUM(G13:G16) -> 0 | H17: =SUM(H13:H16) -> 540475692 | I17: =SUM(I13:I16) -> 16785279210 | J17: =SUM(C17:H17)=I17 -> TRUE
B20: ASE 2
B21: Resumen Recaudo Aplicado Por Servicio
C22: ENEL | D22: CIUDAD LIMPIA | E22: EAB | F22: NUEVO ESQUEMA | G22: ENERBIT | H22: OCCIDENTE | I22: Total
B23: 1-APLICADOS A FACTURACION | C23: 11785775189 | E23: 0 | F23: 13570060 | H23: 390172374 | I23: =SUM(C23:H23) -> 12189517623 | J23: =SUM(C23:H23)=I23 -> TRUE
B24: 2-SALDOS A FAVOR GENERADOS | C24: 47435723 | E24: 0 | F24: 15775490 | H24: 32048911 | I24: =SUM(C24:H24) -> 95260124 | J24: =SUM(C24:H24)=I24 -> TRUE
B25: 3-APLICADOS A FINANCIACIONES NUEVAS | C25: 0 | E25: 0 | F25: 0 | H25: 0 | I25: =SUM(C25:H25) -> 0 | J25: =SUM(C25:H25)=I25 -> TRUE
B26: 7-APLICADOS A RECIBOS SERVICIOS ESPECIALES | F26: 0 | H26: 0 | I26: =SUM(C26:H26) -> 0 | J26: =SUM(C26:H26)=I26 -> TRUE
B27: Total | C27: =SUM(C23:C26) -> 11833210912 | D27: =SUM(D23:D26) -> 0 | E27: =SUM(E23:E26) -> 0 | F27: =SUM(F23:F26) -> 29345550 | G27: =SUM(G23:G26) -> 0 | H27: =SUM(H23:H26) -> 422221285 | I27: =SUM(I23:I26) -> 12284777747 | J27: =SUM(C27:H27)=I27 -> TRUE
B29: ASE 3
B30: Resumen Recaudo Aplicado Por Servicio
C31: ENEL | D31: CIUDAD LIMPIA | E31: EAB | F31: NUEVO ESQUEMA | G31: ENERBIT | H31: OCCIDENTE | I31: Total
B32: 1-APLICADOS A FACTURACION | C32: 9664176949 | F32: 0 | H32: 4.6662827e+08 | I32: =SUM(C32:H32) -> 1.0130805e+10 | J32: =SUM(C32:H32)=I32 -> TRUE
B33: 2-SALDOS A FAVOR GENERADOS | C33: 21042512 | F33: 0 | H33: 2387269 | I33: =SUM(C33:H33) -> 23429781 | J33: =SUM(C33:H33)=I33 -> TRUE
B34: 3-APLICADOS A FINANCIACIONES NUEVAS | C34: 0 | F34: 0 | H34: 3503528.1 | I34: =SUM(C34:H34) -> 3503528.1 | J34: =SUM(C34:H34)=I34 -> TRUE
B35: 7-APLICADOS A RECIBOS SERVICIOS ESPECIALES | C35: 0 | F35: 0 | I35: =SUM(C35:H35) -> 0 | J35: =SUM(C35:H35)=I35 -> TRUE
B36: Total | C36: =SUM(C32:C35) -> 9685219461 | D36: =SUM(D32:D35) -> 0 | E36: =SUM(E32:E35) -> 0 | F36: =SUM(F32:F35) -> 0 | G36: =SUM(G32:G35) -> 0 | H36: =SUM(H32:H35) -> 472519065 | I36: =SUM(I32:I35) -> 10157738526 | J36: =SUM(C36:H36)=I36 -> TRUE
B38: ASE 4
B39: Resumen Recaudo Aplicado Por Servicio
C40: ENEL | D40: CIUDAD LIMPIA | E40: EAB | F40: NUEVO ESQUEMA | G40: ENERBIT | H40: OCCIDENTE | I40: Total
B41: 1-APLICADOS A FACTURACION | C41: 10340898687 | E41: 0 | F41: 7264980 | H41: 2.0075764e+08 | I41: =SUM(C41:H41) -> 1.0548921e+10 | J41: =SUM(C41:H41)=I41 -> TRUE
B42: 2-SALDOS A FAVOR GENERADOS | C42: 35795695 | E42: 0 | F42: 7975330 | H42: 11928036 | I42: =SUM(C42:H42) -> 55699061 | J42: =SUM(C42:H42)=I42 -> TRUE
B43: 3-APLICADOS A FINANCIACIONES NUEVAS | C43: 0 | E43: 0 | F43: 0 | H43: 26456711 | I43: =SUM(C43:H43) -> 26456711 | J43: =SUM(C43:H43)=I43 -> TRUE
B44: 7-APLICADOS A RECIBOS SERVICIOS ESPECIALES | I44: =SUM(C44:H44) -> 0 | J44: =SUM(C44:H44)=I44 -> TRUE
B45: Total | C45: =SUM(C41:C44) -> 10376694382 | D45: =SUM(D41:D44) -> 0 | E45: =SUM(E41:E44) -> 0 | F45: =SUM(F41:F44) -> 15240310 | G45: =SUM(G41:G44) -> 0 | H45: =SUM(H41:H44) -> 239142386 | I45: =SUM(I41:I44) -> 10631077078 | J45: =SUM(C45:H45)=I45 -> TRUE
B48: ASE 5
B49: Resumen Recaudo Aplicado Por Servicio
C50: ENEL | D50: CIUDAD LIMPIA | E50: EAB | F50: NUEVO ESQUEMA | G50: ENERBIT | H50: OCCIDENTE | I50: Total
B51: 1-APLICADOS A FACTURACION | C51: 8240568549 | G51: 126372915 | H51: 1.7863432e+08 | I51: =SUM(C51:H51) -> 8.5455758e+09 | J51: =SUM(C51:H51)=I51 -> TRUE
B52: 2-SALDOS A FAVOR GENERADOS | C52: 38409110 | G52: 3163741 | H52: 2431000 | I52: =SUM(C52:H52) -> 44003851 | J52: =SUM(C52:H52)=I52 -> TRUE
B53: 3-APLICADOS A FINANCIACIONES NUEVAS | C53: 0 | G53: 0 | H53: 668245.85 | I53: =SUM(C53:H53) -> 668245.85 | J53: =SUM(C53:H53)=I53 -> TRUE
B54: 7-APLICADOS A RECIBOS SERVICIOS ESPECIALES | C54: 0 | I54: =SUM(C54:H54) -> 0 | J54: =SUM(C54:H54)=I54 -> TRUE
B55: Total | C55: =SUM(C51:C54) -> 8278977659 | D55: =SUM(D51:D54) -> 0 | E55: =SUM(E51:E54) -> 0 | F55: =SUM(F51:F54) -> 0 | G55: =SUM(G51:G54) -> 129536656 | H55: =SUM(H51:H54) -> 181733562 | I55: =SUM(I51:I54) -> 8590247877 | J55: =SUM(C55:H55)=I55 -> TRUE
B59: QUINCENA | C59: 1 | D59: OJO/// DILIGENCIAR
B62: Recaudo ENEL - ASE 1 | C62: =IF($C$59=1,'Recaudo ENEL'!D21,'Recaudo ENEL'!F21) -> 16244803518 | D62: =C17=C62 -> TRUE | E62: =C17-C62 -> 0
B63: Recaudo ENERBIT - ASE 1 | C63: =IF($C$59=1,'Recaudo ENERBIT'!D21,'Recaudo ENERBIT'!F21) -> 0 | D63: =G17=C63 -> TRUE | E63: =G17-C63 -> 0
B64: Recaudo Reciprocidad EAAB - ASE 2 | C64: =IF($C$59=1,'Recaudo EAAB Reciprocidad'!D22,'Recaudo EAAB Reciprocidad'!F22) -> 29345550 | D64: =F27=C64 -> TRUE | E64: =F27-C64 -> 0
B65: Recaudo ENEL - ASE 2 | C65: =IF($C$59=1,'Recaudo ENEL'!D22,'Recaudo ENEL'!F22) -> 11832813662 | D65: =C27=C65 -> FALSE | E65: =C27-C65 -> 397250
B66: Recaudo ENERBIT - ASE 2 | C66: =IF($C$59=1,'Recaudo ENERBIT'!D22,'Recaudo ENERBIT'!F22) -> 0 | D66: =G27=C66 -> TRUE | E66: =G27-C66 -> 0
B67: Recaudo ENEL - ASE 3 | C67: =IF($C$59=1,'Recaudo ENEL'!D23,'Recaudo ENEL'!F23) -> 9684971351 | D67: =C36=C67 -> FALSE | E67: =C36-C67 -> 248110
B68: Recaudo ENERBIT - ASE 3 | C68: =IF($C$59=1,'Recaudo ENERBIT'!D23,'Recaudo ENERBIT'!F23) -> 0 | D68: =G36=C68 -> TRUE | E68: =G36-C68 -> 0
B69: Recaudo Reciprocidad EAAB - ASE 4 | C69: =IF($C$59=1,'Recaudo EAAB Reciprocidad'!D24,'Recaudo EAAB Reciprocidad'!F24) -> 15240310 | D69: =F45=C69 -> TRUE | E69: =F45-C69 -> 0
B70: Recaudo ENEL - ASE 4 | C70: =IF($C$59=1,'Recaudo ENEL'!D24,'Recaudo ENEL'!F24) -> 10376117592 | D70: =C45=C70 -> FALSE | E70: =C45-C70 -> 576790
B71: Recaudo ENERBIT - ASE 4 | C71: =IF($C$59=1,'Recaudo ENERBIT'!D24,'Recaudo ENERBIT'!F24) -> 0 | D71: =G45=C71 -> TRUE | E71: =G45-C71 -> 0
B72: Recaudo ENEL - ASE 5 | C72: =IF($C$59=1,'Recaudo ENEL'!D25,'Recaudo ENEL'!F25) -> 8278212539 | D72: =C55=C72 -> FALSE | E72: =C55-C72 -> 765120
B73: Recaudo ENERBIT - ASE 5 | C73: =IF($C$59=1,'Recaudo ENERBIT'!D25,'Recaudo ENERBIT'!F25) -> 129536656 | D73: =G55=C73 -> TRUE | E73: =G55-C73 -> 0
B75: Recaudo Banco Occidente ASE 1 | C75: =IF($C$59=1,'Recaudo Directa Occidente'!D21,'Recaudo Directa Occidente'!F21) -> 540475692 | D75: =C75=H17 -> TRUE | E75: =H17-C75 -> 0
B76: Recaudo Banco Occidente ASE 2 | C76: =IF($C$59=1,'Recaudo Directa Occidente'!D22,'Recaudo Directa Occidente'!F22) -> 422221285 | D76: =C76=H27 -> TRUE | E76: =H27-C76 -> 0
B77: Recaudo Banco Occidente ASE 3 | C77: =IF($C$59=1,'Recaudo Directa Occidente'!D23,'Recaudo Directa Occidente'!F23) -> 472519065 | D77: =C77=H36 -> TRUE | E77: =H36-C77 -> 0
B78: Recaudo Banco Occidente ASE 4 | C78: =IF($C$59=1,'Recaudo Directa Occidente'!D24,'Recaudo Directa Occidente'!F24) -> 239142386 | D78: =C78=H45 -> TRUE | E78: =H45-C78 -> 0
B79: Recaudo Banco Occidente ASE 5 | C79: =IF($C$59=1,'Recaudo Directa Occidente'!D25,'Recaudo Directa Occidente'!F25) -> 181733562 | D79: =C79=H55 -> TRUE | E79: =H55-C79 -> 0
B81: TOTAL RECAUDO | C81: =SUM(C62:C79) -> 58447133168 | D81: =C81=(I6-SUM(E62:E79)) -> TRUE

Sheet ANT EXT-REV
C1: ASE 1 | E1: ASE 2 | G1: ASE 3 | I1: ASE 4 | K1: ASE 5 | M1: TOTAL
C2: REPORTE 3 | D2: REPORTE 4 | E2: REPORTE 3 | F2: REPORTE 4 | G2: REPORTE 3 | H2: REPORTE 4 | I2: REPORTE 3 | J2: REPORTE 4 | K2: REPORTE 3 | L2: REPORTE 4 | M2: REPORTE 3 | N2: REPORTE 4
B3: APLICADO | C3: =C11+C19+C27+C35+C43 -> 11673020 | D3: =D11+D19+D27+D35+D43 -> -12054256 | E3: =E11+E19+E27+E35+E43 -> 0 | F3: =F11+F19+F27+F35+F43 -> -9889189.7 | G3: =G11+G19+G27+G35+G43 -> 10198723 | H3: =H11+H19+H27+H35+H43 -> -16103443 | I3: =I11+I19+I27+I35+I43 -> 5419780 | J3: =J11+J19+J27+J35+J43 -> -21288909 | ... L3: =L11+L19+L27+L35+L43 -> -6421274.7 | M3: =C3+E3+G3+I3+K3 -> 27291523 | N3: =D3+F3+H3+J3+L3 -> -65757072 | P3: =N3=(-VALIDACION_TOTAL!M9) -> TRUE
B4: ANTICIPOS | C4: =C12+C20+C28+C36+C44 -> 1944280 | D4: =D12+D20+D28+D36+D44 -> -8965804.3 | E4: =E12+E20+E28+E36+E44 -> 0 | F4: =F12+F20+F28+F36+F44 -> -649106.28 | G4: =G12+G20+G28+G36+G44 -> 426786.93 | H4: =H12+H20+H28+H36+H44 -> -10201649 | I4: =I12+I20+I28+I36+I44 -> 12360680 | J4: =J12+J20+J28+J36+J44 -> -489671.43 | ... L4: =L12+L20+L28+L36+L44 -> -750593.32 | M4: =C4+E4+G4+I4+K4 -> 15046237 | N4: =D4+F4+H4+J4+L4 -> -21056824 | P4: =N4=(-'CONSOLIDADO_TOTAL RECAUDO'!L131) -> TRUE
B5: TOTAL | C5: =SUM(C3:C4) -> 13617300 | D5: =SUM(D3:D4) -> -21020060 | E5: =SUM(E3:E4) -> 0 | F5: =SUM(F3:F4) -> -10538296 | G5: =SUM(G3:G4) -> 10625510 | H5: =SUM(H3:H4) -> -26305092 | I5: =SUM(I3:I4) -> 17780460 | J5: =SUM(J3:J4) -> -21778580 | ... N5: =SUM(N3:N4) -> -86813896
C6: =C5=(C13+C21+C29+C37+C45) -> TRUE | D6: =D5=(D13+D21+D29+D37+D45) -> TRUE | E6: =E5=(E13+E21+E29+E37+E45) -> TRUE | F6: =F5=(F13+F21+F29+F37+F45) -> TRUE | G6: =G5=(G13+G21+G29+G37+G45) -> TRUE | H6: =H5=(H13+H21+H29+H37+H45) -> TRUE | I6: =I5=(I13+I21+I29+I37+I45) -> TRUE | J6: =J5=(J13+J21+J29+J37+J45) -> TRUE | ... N6: =N5=(N13+N21+N29+N37+N45) -> TRUE
B8: BANCO DE OCCIDENTE
C9: ASE 1 | E9: ASE 2 | G9: ASE 3 | I9: ASE 4 | K9: ASE 5 | M9: TOTAL
C10: REPORTE 3 | D10: REPORTE 4 | E10: REPORTE 3 | F10: REPORTE 4 | G10: REPORTE 3 | H10: REPORTE 4 | I10: REPORTE 3 | J10: REPORTE 4 | K10: REPORTE 3 | L10: REPORTE 4 | M10: REPORTE 3 | N10: REPORTE 4
B11: APLICADO | C11: 11673020 | D11: -12054256 | E11: 0 | F11: 0 | G11: 10198723 | H11: -10531482 | I11: 1855630 | J11: -4856352 | K11: 0 | L11: -950286.68 | M11: =C11+E11+G11+I11+K11 -> 23727373 | N11: =D11+F11+H11+J11+L11 -> -28392376
B12: ANTICIPOS | C12: 1944280 | D12: -8965804.3 | E12: 0 | F12: 0 | G12: 426786.93 | H12: -10145808 | I12: 2723150 | J12: -245148.04 | K12: 314490 | L12: -750593.32 | M12: =C12+E12+G12+I12+K12 -> 5408706.9 | N12: =D12+F12+H12+J12+L12 -> -20107354
B13: TOTAL | C13: =SUM(C11:C12) -> 13617300 | D13: =SUM(D11:D12) -> -21020060 | E13: =SUM(E11:E12) -> 0 | F13: =SUM(F11:F12) -> 0 | G13: =SUM(G11:G12) -> 10625510 | H13: =SUM(H11:H12) -> -20677290 | I13: =SUM(I11:I12) -> 4578780 | J13: =SUM(J11:J12) -> -5101500 | ... N13: =SUM(N11:N12) -> -48499730
B16: EAAB RECIPROCIDAD
C17: ASE 1 | E17: ASE 2 | G17: ASE 3 | I17: ASE 4 | K17: ASE 5 | M17: TOTAL
C18: REPORTE 3 | D18: REPORTE 4 | E18: REPORTE 3 | F18: REPORTE 4 | G18: REPORTE 3 | H18: REPORTE 4 | I18: REPORTE 3 | J18: REPORTE 4 | K18: REPORTE 3 | L18: REPORTE 4 | M18: REPORTE 3 | N18: REPORTE 4
B19: APLICADO | C19: 0 | D19: 0 | E19: 0 | F19: -19778.72 | G19: 0 | H19: 0 | I19: 0 | J19: -464370 | K19: 0 | L19: 0 | M19: =C19+E19+G19+I19+K19 -> 0 | N19: =D19+F19+H19+J19+L19 -> -484148.72
B20: ANTICIPOS | C20: 0 | D20: 0 | E20: 0 | F20: -600714.28 | G20: 0 | H20: 0 | I20: 464370 | J20: 0 | K20: 0 | L20: 0 | M20: =C20+E20+G20+I20+K20 -> 464370 | N20: =D20+F20+H20+J20+L20 -> -600714.28
B21: TOTAL | C21: =SUM(C19:C20) -> 0 | D21: =SUM(D19:D20) -> 0 | E21: =SUM(E19:E20) -> 0 | F21: =SUM(F19:F20) -> -620493 | G21: =SUM(G19:G20) -> 0 | H21: =SUM(H19:H20) -> 0 | I21: =SUM(I19:I20) -> 464370 | J21: =SUM(J19:J20) -> -464370 | ... L21: =SUM(L19:L20) -> 0 | M21: =C21+E21+G21+I21+K21 -> 464370 | N21: =SUM(N19:N20) -> -1084863
B24: EAAB CIUDAD LIMPIA
C25: ASE 1 | E25: ASE 2 | G25: ASE 3 | I25: ASE 4 | K25: ASE 5 | M25: TOTAL
C26: REPORTE 3 | D26: REPORTE 4 | E26: REPORTE 3 | F26: REPORTE 4 | G26: REPORTE 3 | H26: REPORTE 4 | I26: REPORTE 3 | J26: REPORTE 4 | K26: REPORTE 3 | L26: REPORTE 4 | M26: REPORTE 3 | N26: REPORTE 4
B27: APLICADO | C27: 0 | D27: 0 | E27: 0 | F27: 0 | G27: 0 | H27: 0 | I27: 0 | J27: 0 | K27: 0 | L27: 0 | M27: =C27+E27+G27+I27+K27 -> 0 | N27: =D27+F27+H27+J27+L27 -> 0
B28: ANTICIPOS | C28: 0 | D28: 0 | E28: 0 | F28: 0 | G28: 0 | H28: 0 | I28: 0 | J28: 0 | K28: 0 | L28: 0 | M28: =C28+E28+G28+I28+K28 -> 0 | N28: =D28+F28+H28+J28+L28 -> 0
B29: TOTAL | C29: =SUM(C27:C28) -> 0 | D29: =SUM(D27:D28) -> 0 | E29: =SUM(E27:E28) -> 0 | F29: =SUM(F27:F28) -> 0 | G29: =SUM(G27:G28) -> 0 | H29: =SUM(H27:H28) -> 0 | I29: =SUM(I27:I28) -> 0 | J29: =SUM(J27:J28) -> 0 | ... N29: =SUM(N27:N28) -> 0
B32: ENEL
C33: ASE 1 | E33: ASE 2 | G33: ASE 3 | I33: ASE 4 | K33: ASE 5 | M33: TOTAL
C34: REPORTE 3 | D34: REPORTE 4 | E34: REPORTE 3 | F34: REPORTE 4 | G34: REPORTE 3 | H34: REPORTE 4 | I34: REPORTE 3 | J34: REPORTE 4 | K34: REPORTE 3 | L34: REPORTE 4 | M34: REPORTE 3 | N34: REPORTE 4
B35: APLICADO | C35: 0 | D35: 0 | E35: 0 | F35: -9869411 | G35: 0 | H35: -5571961 | I35: 3564150 | J35: -15968187 | K35: 0 | L35: -5470988 | M35: =C35+E35+G35+I35+K35 -> 3564150 | N35: =D35+F35+H35+J35+L35 -> -36880547
B36: ANTICIPOS | C36: 0 | D36: 0 | E36: 0 | F36: -48392 | G36: 0 | H36: -55841 | I36: 9173160 | J36: -244523.39 | K36: 0 | L36: 0 | M36: =C36+E36+G36+I36+K36 -> 9173160 | N36: =D36+F36+H36+J36+L36 -> -348756.39
B37: TOTAL | C37: =SUM(C35:C36) -> 0 | D37: =SUM(D35:D36) -> 0 | E37: =SUM(E35:E36) -> 0 | F37: =SUM(F35:F36) -> -9917803 | G37: =SUM(G35:G36) -> 0 | H37: =SUM(H35:H36) -> -5627802 | I37: =SUM(I35:I36) -> 12737310 | J37: =SUM(J35:J36) -> -16212710 | ... N37: =SUM(N35:N36) -> -37229303
B40: ENERBIT
C41: ASE 1 | E41: ASE 2 | G41: ASE 3 | I41: ASE 4 | K41: ASE 5 | M41: TOTAL
C42: REPORTE 3 | D42: REPORTE 4 | E42: REPORTE 3 | F42: REPORTE 4 | G42: REPORTE 3 | H42: REPORTE 4 | I42: REPORTE 3 | J42: REPORTE 4 | K42: REPORTE 3 | L42: REPORTE 4 | M42: REPORTE 3 | N42: REPORTE 4
B43: APLICADO | C43: 0 | D43: 0 | E43: 0 | F43: 0 | G43: 0 | H43: 0 | I43: 0 | J43: 0 | K43: 0 | L43: 0 | M43: =C43+E43+G43+I43+K43 -> 0 | N43: =D43+F43+H43+J43+L43 -> 0
B44: ANTICIPOS | C44: 0 | D44: 0 | E44: 0 | F44: 0 | G44: 0 | H44: 0 | I44: 0 | J44: 0 | K44: 0 | L44: 0 | M44: =C44+E44+G44+I44+K44 -> 0 | N44: =D44+F44+H44+J44+L44 -> 0
B45: TOTAL | C45: =SUM(C43:C44) -> 0 | D45: =SUM(D43:D44) -> 0 | E45: =SUM(E43:E44) -> 0 | F45: =SUM(F43:F44) -> 0 | G45: =SUM(G43:G44) -> 0 | H45: =SUM(H43:H44) -> 0 | I45: =SUM(I43:I44) -> 0 | J45: =SUM(J43:J44) -> 0 | ... N45: =SUM(N43:N44) -> 0

Sheet ANTICIPOS USUARIOS
B1: TOTAL | E1: RECIPROCIDAD | H1: ENEL | K1: ENERBIT | N1: OCCIDENTE | Q1: EAAB-CIUDADLIMPIA
B2: ASE | C2: ANTICIPOS GENERADOS POR PAGO | E2: ASE | F2: ANTICIPOS GENERADOS POR PAGO | H2: ASE | I2: ANTICIPOS GENERADOS POR PAGO | K2: ASE | L2: ANTICIPOS GENERADOS POR PAGO | N2: ASE | O2: ANTICIPOS GENERADOS POR PAGO | Q2: ASE | R2: ANTICIPOS GENERADOS POR PAGO | T2: Anticipos generados por pago
B3: 1 | C3: ='REPORTE RECAUDO x BANCO'!I14 -> 62753036 | E3: 1 | F3: ='REPORTE RECAUDO x BANCO'!F14 -> 0 | H3: 1 | I3: ='REPORTE RECAUDO x BANCO'!C14 -> 50286069 | K3: 1 | L3: ='REPORTE RECAUDO x BANCO'!G14 -> 0 | N3: 1 | O3: ='REPORTE RECAUDO x BANCO'!H14 -> 12466967 | Q3: 1 | R3: ='REPORTE RECAUDO x BANCO'!D14+'REPORTE RECAUDO x BANCO'!E14 -> 0 | T3: Sale del reporte Recaudo por Bancos.
B4: 2 | C4: ='REPORTE RECAUDO x BANCO'!I24 -> 95260124 | E4: 2 | F4: ='REPORTE RECAUDO x BANCO'!F24 -> 15775490 | H4: 2 | I4: ='REPORTE RECAUDO x BANCO'!C24 -> 47435723 | K4: 2 | L4: ='REPORTE RECAUDO x BANCO'!G24 -> 0 | N4: 2 | O4: ='REPORTE RECAUDO x BANCO'!H24 -> 32048911 | Q4: 2 | R4: ='REPORTE RECAUDO x BANCO'!D24+'REPORTE RECAUDO x BANCO'!E24 -> 0
B5: 3 | C5: ='REPORTE RECAUDO x BANCO'!I33 -> 23429781 | E5: 3 | F5: ='REPORTE RECAUDO x BANCO'!F33 -> 0 | H5: 3 | I5: ='REPORTE RECAUDO x BANCO'!C33 -> 21042512 | K5: 3 | L5: ='REPORTE RECAUDO x BANCO'!G33 -> 0 | N5: 3 | O5: ='REPORTE RECAUDO x BANCO'!H33 -> 2387269 | Q5: 3 | R5: ='REPORTE RECAUDO x BANCO'!D33+'REPORTE RECAUDO x BANCO'!E33 -> 0
B6: 4 | C6: ='REPORTE RECAUDO x BANCO'!I42 -> 55699061 | E6: 4 | F6: ='REPORTE RECAUDO x BANCO'!F42 -> 7975330 | H6: 4 | I6: ='REPORTE RECAUDO x BANCO'!C42 -> 35795695 | K6: 4 | L6: ='REPORTE RECAUDO x BANCO'!G42 -> 0 | N6: 4 | O6: ='REPORTE RECAUDO x BANCO'!H42 -> 11928036 | Q6: 4 | R6: ='REPORTE RECAUDO x BANCO'!D42+'REPORTE RECAUDO x BANCO'!E42 -> 0
B7: 5 | C7: ='REPORTE RECAUDO x BANCO'!I52 -> 44003851 | E7: 5 | F7: ='REPORTE RECAUDO x BANCO'!F52 -> 0 | H7: 5 | I7: ='REPORTE RECAUDO x BANCO'!C52 -> 38409110 | K7: 5 | L7: ='REPORTE RECAUDO x BANCO'!G52 -> 3163741 | N7: 5 | O7: ='REPORTE RECAUDO x BANCO'!H52 -> 2431000 | Q7: 5 | R7: ='REPORTE RECAUDO x BANCO'!D52+'REPORTE RECAUDO x BANCO'!E52 -> 0
C8: =SUM(C3:C7) -> 2.8114585e+08 | F8: =SUM(F3:F7) -> 23750820 | I8: =SUM(I3:I7) -> 192969109 | L8: =SUM(L3:L7) -> 3163741 | O8: =SUM(O3:O7) -> 61262183 | R8: =SUM(R3:R7) -> 0
C9: =C8='REPORTE RECAUDO x BANCO'!I3 -> TRUE | F9: =F8='REPORTE RECAUDO x BANCO'!F3 -> TRUE | I9: =I8='REPORTE RECAUDO x BANCO'!C3 -> TRUE | L9: =L8='REPORTE RECAUDO x BANCO'!G3 -> TRUE | O9: =O8='REPORTE RECAUDO x BANCO'!H3 -> TRUE | R9: =R8='REPORTE RECAUDO x BANCO'!D3+'REPORTE RECAUDO x BANCO'!E3 -> TRUE
B11: ASE | C11: ANTICIPOS GENERADOS POR EXTEMPORANEOS | E11: ASE | F11: ANTICIPOS GENERADOS POR EXTEMPORANEOS | H11: ASE | I11: ANTICIPOS GENERADOS POR EXTEMPORANEOS | K11: ASE | L11: ANTICIPOS GENERADOS POR EXTEMPORANEOS | N11: ASE | O11: ANTICIPOS GENERADOS POR EXTEMPORANEOS | Q11: ASE | R11: ANTICIPOS GENERADOS POR EXTEMPORANEOS | T11: Anticipos generados por pagos aplicados de reversiones
B12: 1 | C12: ='ANT EXT-REV'!C4 -> 1944280 | E12: 1 | F12: ='ANT EXT-REV'!C20 -> 0 | H12: 1 | I12: ='ANT EXT-REV'!C36 -> 0 | K12: 1 | L12: ='ANT EXT-REV'!A12 -> 0 | N12: 1 | O12: ='ANT EXT-REV'!C12 -> 1944280 | Q12: 1 | R12: ='ANT EXT-REV'!C28 -> 0 | T12: Sale del reporte Recaudo reversado
B13: 2 | C13: ='ANT EXT-REV'!E4 -> 0 | E13: 2 | F13: ='ANT EXT-REV'!E20 -> 0 | H13: 2 | I13: ='ANT EXT-REV'!E36 -> 0 | K13: 2 | L13: ='ANT EXT-REV'!E44 -> 0 | N13: 2 | O13: ='ANT EXT-REV'!E12 -> 0 | Q13: 2 | R13: ='ANT EXT-REV'!E28 -> 0
B14: 3 | C14: ='ANT EXT-REV'!G4 -> 426786.93 | E14: 3 | F14: ='ANT EXT-REV'!G20 -> 0 | H14: 3 | I14: ='ANT EXT-REV'!G36 -> 0 | K14: 3 | L14: ='ANT EXT-REV'!G44 -> 0 | N14: 3 | O14: ='ANT EXT-REV'!G12 -> 426786.93 | Q14: 3 | R14: ='ANT EXT-REV'!G28 -> 0
B15: 4 | C15: ='ANT EXT-REV'!I4 -> 12360680 | E15: 4 | F15: ='ANT EXT-REV'!I20 -> 464370 | H15: 4 | I15: ='ANT EXT-REV'!I36 -> 9173160 | K15: 4 | L15: ='ANT EXT-REV'!I44 -> 0 | N15: 4 | O15: ='ANT EXT-REV'!I12 -> 2723150 | Q15: 4 | R15: ='ANT EXT-REV'!I28 -> 0
B16: 5 | C16: ='ANT EXT-REV'!K4 -> 314490 | E16: 5 | F16: ='ANT EXT-REV'!K20 -> 0 | H16: 5 | I16: ='ANT EXT-REV'!K36 -> 0 | K16: 5 | L16: ='ANT EXT-REV'!K44 -> 0 | N16: 5 | O16: ='ANT EXT-REV'!K12 -> 314490 | Q16: 5 | R16: ='ANT EXT-REV'!K28 -> 0
C17: =SUM(C12:C16) -> 15046237 | F17: =SUM(F12:F16) -> 464370 | I17: =SUM(I12:I16) -> 9173160 | L17: =SUM(L12:L16) -> 0 | O17: =SUM(O12:O16) -> 5408706.9 | R17: =SUM(R12:R16) -> 0
C18: =C17='ANT EXT-REV'!M4 -> TRUE | F18: =F17='ANT EXT-REV'!M20 -> TRUE | I18: =I17='ANT EXT-REV'!M36 -> TRUE | L18: =L17='ANT EXT-REV'!M44 -> TRUE | O18: =O17='ANT EXT-REV'!M12 -> TRUE | R18: =R17='ANT EXT-REV'!M28 -> TRUE
B20: ASE | C20: ANTICIPOS QUE CARGAN POR REVERSIONES | E20: ASE | F20: ANTICIPOS QUE CARGAN POR REVERSIONES | H20: ASE | I20: ANTICIPOS QUE CARGAN POR REVERSIONES | K20: ASE | L20: ANTICIPOS QUE CARGAN POR REVERSIONES | N20: ASE | O20: ANTICIPOS QUE CARGAN POR REVERSIONES | Q20: ASE | R20: ANTICIPOS QUE CARGAN POR REVERSIONES | T20: Anticipos que cargan de reversiones
B21: 1 | C21: ='ANT EXT-REV'!D4 -> -8965804.3 | E21: 1 | F21: ='ANT EXT-REV'!D20 -> 0 | H21: 1 | I21: ='ANT EXT-REV'!D36 -> 0 | K21: 1 | L21: ='ANT EXT-REV'!D44 -> 0 | N21: 1 | O21: ='ANT EXT-REV'!D12 -> -8965804.3 | Q21: 1 | R21: ='ANT EXT-REV'!D28 -> 0 | T21: Sale del reporte Recaudo reversado
B22: 2 | C22: ='ANT EXT-REV'!F4 -> -649106.28 | E22: 2 | F22: ='ANT EXT-REV'!F20 -> -600714.28 | H22: 2 | I22: ='ANT EXT-REV'!F36 -> -48392 | K22: 2 | L22: ='ANT EXT-REV'!F44 -> 0 | N22: 2 | O22: ='ANT EXT-REV'!F12 -> 0 | Q22: 2 | R22: ='ANT EXT-REV'!F28 -> 0
B23: 3 | C23: ='ANT EXT-REV'!H4 -> -10201649 | E23: 3 | F23: ='ANT EXT-REV'!H20 -> 0 | H23: 3 | I23: ='ANT EXT-REV'!H36 -> -55841 | K23: 3 | L23: ='ANT EXT-REV'!H44 -> 0 | N23: 3 | O23: ='ANT EXT-REV'!H12 -> -10145808 | Q23: 3 | R23: ='ANT EXT-REV'!H28 -> 0
B24: 4 | C24: ='ANT EXT-REV'!J4 -> -489671.43 | E24: 4 | F24: ='ANT EXT-REV'!J20 -> 0 | H24: 4 | I24: ='ANT EXT-REV'!J36 -> -244523.39 | K24: 4 | L24: ='ANT EXT-REV'!J44 -> 0 | N24: 4 | O24: ='ANT EXT-REV'!J12 -> -245148.04 | Q24: 4 | R24: ='ANT EXT-REV'!J28 -> 0
B25: 5 | C25: ='ANT EXT-REV'!L4 -> -750593.32 | E25: 5 | F25: ='ANT EXT-REV'!L20 -> 0 | H25: 5 | I25: ='ANT EXT-REV'!L36 -> 0 | K25: 5 | L25: ='ANT EXT-REV'!L44 -> 0 | N25: 5 | O25: ='ANT EXT-REV'!L12 -> -750593.32 | Q25: 5 | R25: ='ANT EXT-REV'!L28 -> 0
C26: =SUM(C21:C25) -> -21056824 | F26: =SUM(F21:F25) -> -600714.28 | I26: =SUM(I21:I25) -> -348756.39 | L26: =SUM(L21:L25) -> 0 | O26: =SUM(O21:O25) -> -20107354 | R26: =SUM(R21:R25) -> 0
C27: =C26='ANT EXT-REV'!N4 -> TRUE | F27: =F26='ANT EXT-REV'!N20 -> TRUE | I27: =I26='ANT EXT-REV'!N36 -> TRUE | L27: =L26='ANT EXT-REV'!N44 -> TRUE | O27: =O26='ANT EXT-REV'!N12 -> TRUE | R27: =R26='ANT EXT-REV'!N28 -> TRUE

Sheet BCE SC POR FACT.
C2: ASE | D2: CONTRIBUCION | E2: SUBSIDIO | F2: TOTAL BSC | H2: SISTEMA
C3: 1 | D3: 3.2562352e+09 | E3: -1.2238715e+09 | F3: =D3+E3 -> 2.0323637e+09 | H3: =DetRetri2026071!J9 -> 2032363679 | I3: =F3-H3 -> -0.16000032
C4: 2 | D4: 1.9464918e+09 | E4: -6.9580075e+09 | F4: =D4+E4 -> -5.0115157e+09 | H4: =DetRetri2026071!J10 -> -5011515654 | I4: =F4-H4 -> 0.4100008
C5: 3 | D5: 1.9361099e+09 | E5: -3.1329323e+09 | F5: =D5+E5 -> -1.1968224e+09 | H5: =DetRetri2026071!J11 -> -1196822411 | I5: =F5-H5 -> -0.31000018
C6: 4 | D6: 4.741562e+08 | E6: -4.3820038e+08 | F6: =D6+E6 -> 35955816 | H6: =DetRetri2026071!J12 -> 35955816 | I6: =F6-H6 -> 0.039999962
C7: 5 | D7: 1.2667695e+09 | E7: -2.4771952e+09 | F7: =D7+E7 -> -1.2104256e+09 | H7: =DetRetri2026071!J13 -> -1210425628 | I7: =F7-H7 -> -0.31000018
F9: =SUM(F3:F7) -> -5.3504442e+09 | H9: =SUM(H3:H7) -> -5350444198 | I9: =F9-H9 -> -0.32999992
H10: =H9=DetRetri2026071!J14 -> TRUE
D11: =SUM(D3:D7) -> 8.8797626e+09 | E11: =SUM(E3:E7) -> -1.4230207e+10 | F11: =SUM(D3:E7) -> -5.3504442e+09
F12: =ROUND(F11,2)=ROUND(F9,2) -> TRUE
F13: =ROUND(F11,2)-ROUND(F9,2) -> 0
D18: ASE | E18: REMUN TOTAL | F18: VALIDA 1 | G18: VALIDA 2 | H18: DIFERENCIA VALIDA 2
D19: 1 | E19: ='CONSOLIDADO_TOTAL RECAUDO'!J104 -> 2.0323637e+09 | F19: =E19=F3 -> TRUE | G19: =E19=H3 -> FALSE | H19: =E19-H3 -> -0.16000032
D20: 2 | E20: ='CONSOLIDADO_TOTAL RECAUDO'!J105 -> -5.0115157e+09 | F20: =E20=F4 -> TRUE | G20: =E20=H4 -> FALSE | H20: =E20-H4 -> 0.4100008
D21: 3 | E21: ='CONSOLIDADO_TOTAL RECAUDO'!J106 -> -1.1968224e+09 | F21: =E21=F5 -> TRUE | G21: =E21=H5 -> FALSE | H21: =E21-H5 -> -0.31000018
D22: 4 | E22: ='CONSOLIDADO_TOTAL RECAUDO'!J107 -> 35955816 | F22: =E22=F6 -> TRUE | G22: =E22=H6 -> FALSE | H22: =E22-H6 -> 0.039999962
D23: 5 | E23: ='CONSOLIDADO_TOTAL RECAUDO'!J108 -> -1.2104256e+09 | F23: =E23=F7 -> TRUE | G23: =E23=H7 -> FALSE | H23: =E23-H7 -> -0.31000018
E24: =SUM(E19:E23) -> -5.3504442e+09 | F24: =E24=F9 -> TRUE | G24: =E24=H9 -> FALSE | H24: =E24-H9 -> -0.32999992

Sheet Reporte Componentes R1
B4: PROMOAMBIENTAL
F5: Total | G5: Componente TDF | H5: Componente TTL | I5: Componente TVIAT | J5: Aprovechamiento | K5: CCSA Prest.Aprov. | L5: SERVICIO ESPECIALES | M5: Componente TCS | N5: Componente TLU | O5: Componente TBL | P5: Componente TRT | Q5: CCSA Prest. No Aprov. | R5: Ajuste Decena | S5: Ajuste Recargo Aseo | T5: Intereses Cte Financiac. Aseo | U5: Exonera-Ajuste Decena Aseo | V5: Exonera-Ajuste Decena Aseo | W5: Exonera-Recargo Aseo | X5: Rec.Intereses | Y5: Intereses Cte Financiac. Aseo | Z5: Rec.Intereses
E6: Vlr Servicio | F6: 6311519.1 | G6: 1237789 | H6: 698932.72 | I6: 368148.99 | J6: 164076.41 | K6: 5902 | L6: 0 | M6: 51771.85 | N6: 67502.58 | O6: 315251.82 | P6: 3392526.7 | Q6: 9629.46 | R6: -12.4 | S6: 0 | T6: 0 | U6: 0 | V6: 0 | W6: 0 | X6: 0 | Y6: 0 | Z6: 0
E7: Vlr Intereses | F7: 19996.26 | G7: 4031.92 | H7: 2277.16 | I7: 1198.72 | J7: 279.31 | K7: 16.58 | L7: 0 | M7: 145.13 | N7: 172.52 | O7: 800.55 | P7: 11047.38 | Q7: 26.98 | R7: 0.01 | S7: 0 | T7: 0 | U7: 0 | V7: 0 | W7: 0 | X7: 0 | Y7: 0 | Z7: 0
D8: T | E8: Total | F8: 6331515.4 | G8: 1241820.9 | H8: 701209.88 | I8: 369347.71 | J8: 164355.72 | K8: 5918.58 | L8: 0 | M8: 51916.98 | N8: 67675.1 | O8: 316052.37 | P8: 3403574.1 | Q8: 9656.44 | R8: -12.39 | S8: 0 | T8: 0 | U8: 0 | V8: 0 | W8: 0 | X8: 0 | Y8: 0 | Z8: 0
C9: OCCIDENTE | D9: Total | F9: 6331515.4 | G9: 1241820.9 | H9: 701209.88 | I9: 369347.71 | J9: 164355.72 | K9: 5918.58 | L9: 0 | M9: 51916.98 | N9: 67675.1 | O9: 316052.37 | P9: 3403574.1 | Q9: 9656.44 | R9: -12.39 | S9: 0 | T9: 0 | U9: 0 | V9: 0 | W9: 0 | X9: 0 | Y9: 0 | Z9: 0
B10: Aplicacion nuevos x reversion | C10: Total | F10: 6331515.4 | G10: 1241820.9 | H10: 701209.88 | I10: 369347.71 | J10: 164355.72 | K10: 5918.58 | L10: 0 | M10: 51916.98 | N10: 67675.1 | O10: 316052.37 | P10: 3403574.1 | Q10: 9656.44 | R10: -12.39 | S10: 0 | T10: 0 | U10: 0 | V10: 0 | W10: 0 | X10: 0 | Y10: 0 | Z10: 0
E11: Vlr Servicio | F11: 1.9101452e+10 | G11: 9.1336903e+08 | H11: 5.1531429e+08 | I11: 2.705651e+08 | J11: 4.8346181e+09 | K11: 1.6775998e+08 | L11: 14321632 | M11: 1.4724397e+09 | N11: 1.4224992e+09 | O11: 6.7317027e+09 | P11: 2.4851645e+09 | Q11: 2.7373194e+08 | R11: -33913.97 | S11: 0 | T11: 0 | U11: 0 | V11: 0 | W11: 0 | X11: 0 | Y11: 0 | Z11: 0
E12: Vlr Intereses | F12: 2792245.8 | G12: 155660.99 | H12: 79689.82 | I12: 41740.83 | J12: 633473.57 | K12: 26506.79 | L12: 312.58 | M12: 234143.87 | N12: 212449.63 | O12: 946855.03 | P12: 417682.52 | Q12: 43448.47 | R12: 2.45 | S12: -0.01 | T12: 279.23 | U12: 0 | V12: 0 | W12: 0 | X12: 0 | Y12: 0 | Z12: 0
D13: E | E13: Total | F13: 1.9104245e+10 | G13: 9.1352469e+08 | H13: 5.1539398e+08 | I13: 2.7060684e+08 | J13: 4.8352516e+09 | K13: 1.6778649e+08 | L13: 14321945 | M13: 1.4726738e+09 | N13: 1422711691 | O13: 6.7326496e+09 | P13: 2.4855822e+09 | Q13: 2.7377539e+08 | R13: -33911.52 | S13: -0.01 | T13: 279.23 | U13: 0 | V13: 0 | W13: 0 | X13: 0 | Y13: 0 | Z13: 0
C14: ENEL | D14: Total | F14: 1.9104245e+10 | G14: 9.1352469e+08 | H14: 5.1539398e+08 | I14: 2.7060684e+08 | J14: 4.8352516e+09 | K14: 1.6778649e+08 | L14: 14321945 | M14: 1.4726738e+09 | N14: 1422711691 | O14: 6.7326496e+09 | P14: 2.4855822e+09 | Q14: 2.7377539e+08 | R14: -33911.52 | S14: -0.01 | T14: 279.23 | U14: 0 | V14: 0 | W14: 0 | X14: 0 | Y14: 0 | Z14: 0
E15: Vlr Servicio | F15: 28587198 | G15: 2185895.5 | H15: 1219113.6 | I15: 644213.84 | J15: 5793883.4 | K15: 177172.65 | L15: 0 | M15: 1538870.8 | N15: 1889153.4 | O15: 8885237.5 | P15: 5963781.7 | Q15: 289690.76 | R15: 184.57 | S15: 0 | T15: 0 | U15: 0 | V15: 0 | W15: 0 | X15: 0 | Y15: 0 | Z15: 0
E16: Vlr Intereses | F16: 82135.18 | G16: 4908.79 | H16: 2288.07 | I16: 1256.9 | J16: 18570 | K16: 653.25 | L16: 0 | M16: 5731.29 | N16: 6136.85 | O16: 28338.84 | P16: 13182.06 | Q16: 1068.81 | R16: 0.36 | S16: -0.04 | T16: 0 | U16: 0 | V16: 0 | W16: 0 | X16: 0 | Y16: 0 | Z16: 0
D17: H | E17: Total | F17: 28669333 | G17: 2190804.3 | H17: 1221401.6 | I17: 645470.74 | J17: 5812453.4 | K17: 177825.9 | L17: 0 | M17: 1544602.1 | N17: 1895290.3 | O17: 8913576.4 | P17: 5976963.7 | Q17: 290759.57 | R17: 184.93 | S17: -0.04 | T17: 0 | U17: 0 | V17: 0 | W17: 0 | X17: 0 | Y17: 0 | Z17: 0
E18: Vlr Servicio | F18: 47294938 | G18: 3974790.2 | H18: 2180819.5 | I18: 1154125.1 | J18: 8019548.8 | K18: 328408.33 | L18: 0 | M18: 2889896.9 | N18: 3056486.5 | O18: 14327777 | P18: 10827506 | Q18: 535821.41 | R18: -241.11 | S18: 0 | T18: 0 | U18: 0 | V18: 0 | W18: 0 | X18: 0 | Y18: 0 | Z18: 0
E19: Vlr Intereses | F19: 4126283.3 | G19: 86954.59 | H19: 33264.93 | I19: 11195.04 | J19: 965832.37 | K19: 60914.74 | L19: 0 | M19: 534335.02 | N19: 449770.44 | O19: 1653345.4 | P19: 231094.93 | Q19: 99387.59 | R19: 188.15 | S19: 0 | T19: 0.08 | U19: 0 | V19: 0 | W19: 0 | X19: 0 | Y19: 0 | Z19: 0
D20: O | E20: Total | F20: 51421222 | G20: 4061744.8 | H20: 2214084.4 | I20: 1165320.1 | J20: 8985381.2 | K20: 389323.07 | L20: 0 | M20: 3424231.9 | N20: 3506257 | O20: 15981122 | P20: 11058601 | Q20: 635209 | R20: -52.96 | S20: 0 | T20: 0.08 | U20: 0 | V20: 0 | W20: 0 | X20: 0 | Y20: 0 | Z20: 0
E21: Vlr Servicio | F21: 3.6429799e+08 | G21: 65257819 | H21: 34884827 | I21: 18959565 | J21: 20111069 | K21: 558599.01 | L21: 3865005 | M21: 4887941.6 | N21: 6309959 | O21: 29570698 | P21: 1.7898112e+08 | Q21: 911394.98 | R21: -1.52 | S21: 0 | T21: 0 | U21: 0 | V21: 0 | W21: 0 | X21: 0 | Y21: 0 | Z21: 0
E22: Vlr Intereses | F22: 1153870.1 | G22: 222671.28 | H22: 115190.8 | I22: 63892.82 | J22: 40091.93 | K22: 1378.05 | L22: 6789.53 | M22: 12094.95 | N22: 13714.71 | O22: 63652.17 | P22: 612144.4 | Q22: 2249.01 | R22: 0.47 | S22: -0.01 | T22: 0.02 | U22: 0 | V22: 0 | W22: 0 | X22: 0 | Y22: 0 | Z22: 0
D23: T | E23: Total | F23: 3.6545186e+08 | G23: 65480490 | H23: 35000017 | I23: 19023458 | J23: 20151160 | K23: 559977.06 | L23: 3871794.5 | M23: 4900036.5 | N23: 6323673.7 | O23: 29634350 | P23: 1.7959326e+08 | Q23: 913643.99 | R23: -1.05 | S23: -0.01 | T23: 0.02 | U23: 0 | V23: 0 | W23: 0 | X23: 0 | Y23: 0 | Z23: 0
C24: OCCIDENTE | D24: Total | F24: 4.4554242e+08 | G24: 71733039 | H24: 38435503 | I24: 20834248 | J24: 34948995 | K24: 1127126 | L24: 3871794.5 | M24: 9868870.5 | N24: 11725221 | O24: 54529049 | P24: 1.9662883e+08 | Q24: 1839612.6 | R24: 130.92 | S24: -0.05 | T24: 0.1 | U24: 0 | V24: 0 | W24: 0 | X24: 0 | Y24: 0 | Z24: 0
B25: Mes | C25: Total | F25: 1.9549787e+10 | G25: 9.8525773e+08 | H25: 5.5382948e+08 | I25: 2.9144109e+08 | J25: 4.8702006e+09 | K25: 1.6891361e+08 | L25: 18193739 | M25: 1.4825427e+09 | N25: 1.4344369e+09 | O25: 6.7871786e+09 | P25: 2.682211e+09 | Q25: 2.7561501e+08 | R25: -33780.6 | S25: -0.06 | T25: 279.33 | U25: 0 | V25: 0 | W25: 0 | X25: 0 | Y25: 0 | Z25: 0
A26: Componente | B26: Total | F26: 1.9556118e+10 | G26: 9.8649955e+08 | H26: 5.5453069e+08 | I26: 2.9181043e+08 | J26: 4.8703649e+09 | K26: 168919531 | L26: 18193739 | M26: 1.4825946e+09 | N26: 1.4345046e+09 | O26: 6.7874947e+09 | P26: 2.6856146e+09 | Q26: 2.7562466e+08 | R26: -33792.99 | S26: -0.06 | T26: 279.33 | U26: 0 | V26: 0 | W26: 0 | X26: 0 | Y26: 0 | Z26: 0
E27: Subsidio(-)/Contribucion(+) | F27: 5341504.6 | G27: 1097764.1 | H27: 620054.15 | I27: 326455.64 | J27: 77296.09 | K27: 2815.34 | L27: 0 | M27: 24695.93 | N27: 31713.91 | O27: 147438.86 | P27: 3008677.2 | Q27: 4593.42 | R27: 0 | S27: 0 | T27: 0 | U27: 0 | V27: 0 | W27: 0 | X27: 0 | Y27: 0 | Z27: 0
D28: T | E28: Total | F28: 5341504.6 | G28: 1097764.1 | H28: 620054.15 | I28: 326455.64 | J28: 77296.09 | K28: 2815.34 | L28: 0 | M28: 24695.93 | N28: 31713.91 | O28: 147438.86 | P28: 3008677.2 | Q28: 4593.42 | R28: 0 | S28: 0 | T28: 0 | U28: 0 | V28: 0 | W28: 0 | X28: 0 | Y28: 0 | Z28: 0
C29: OCCIDENTE | D29: Total | F29: 5341504.6 | G29: 1097764.1 | H29: 620054.15 | I29: 326455.64 | J29: 77296.09 | K29: 2815.34 | L29: 0 | M29: 24695.93 | N29: 31713.91 | O29: 147438.86 | P29: 3008677.2 | Q29: 4593.42 | R29: 0 | S29: 0 | T29: 0 | U29: 0 | V29: 0 | W29: 0 | X29: 0 | Y29: 0 | Z29: 0
B30: Aplicacion nuevos x reversion | C30: Total | F30: 5341504.6 | G30: 1097764.1 | H30: 620054.15 | I30: 326455.64 | J30: 77296.09 | K30: 2815.34 | L30: 0 | M30: 24695.93 | N30: 31713.91 | O30: 147438.86 | P30: 3008677.2 | Q30: 4593.42 | R30: 0 | S30: 0 | T30: 0 | U30: 0 | V30: 0 | W30: 0 | X30: 0 | Y30: 0 | Z30: 0
E31: Subsidio(-)/Contribucion(+) | F31: -2.9097271e+09 | G31: -71434201 | H31: -40271751 | I31: -21151234 | J31: -8.5108048e+08 | K31: -28933267 | L31: 0 | M31: -2.5394018e+08 | N31: -2.4481763e+08 | O31: -1.1593136e+09 | P31: -1.9158028e+08 | Q31: -47204497 | R31: 0 | S31: 0 | T31: 0 | U31: 0 | V31: 0 | W31: 0 | X31: 0 | Y31: 0 | Z31: 0
D32: E | E32: Total | F32: -2.9097271e+09 | G32: -71434201 | H32: -40271751 | I32: -21151234 | J32: -8.5108048e+08 | K32: -28933267 | L32: 0 | M32: -2.5394018e+08 | N32: -2.4481763e+08 | O32: -1.1593136e+09 | P32: -1.9158028e+08 | Q32: -47204497 | R32: 0 | S32: 0 | T32: 0 | U32: 0 | V32: 0 | W32: 0 | X32: 0 | Y32: 0 | Z32: 0
C33: ENEL | D33: Total | F33: -2.9097271e+09 | G33: -71434201 | H33: -40271751 | I33: -21151234 | J33: -8.5108048e+08 | K33: -28933267 | L33: 0 | M33: -2.5394018e+08 | N33: -2.4481763e+08 | O33: -1.1593136e+09 | P33: -1.9158028e+08 | Q33: -47204497 | R33: 0 | S33: 0 | T33: 0 | U33: 0 | V33: 0 | W33: 0 | X33: 0 | Y33: 0 | Z33: 0
E34: Subsidio(-)/Contribucion(+) | F34: 6544837.2 | G34: 1138624.2 | H34: 635941.02 | I34: 334662.94 | J34: 575474.01 | K34: 3731.32 | L34: 0 | M34: 34025.38 | N34: 125376.87 | O34: 588048.51 | P34: 3102866.2 | Q34: 6086.75 | R34: 0 | S34: 0 | T34: 0 | U34: 0 | V34: 0 | W34: 0 | X34: 0 | Y34: 0 | Z34: 0
D35: H | E35: Total | F35: 6544837.2 | G35: 1138624.2 | H35: 635941.02 | I35: 334662.94 | J35: 575474.01 | K35: 3731.32 | L35: 0 | M35: 34025.38 | N35: 125376.87 | O35: 588048.51 | P35: 3102866.2 | Q35: 6086.75 | R35: 0 | S35: 0 | T35: 0 | U35: 0 | V35: 0 | W35: 0 | X35: 0 | Y35: 0 | Z35: 0
E36: Subsidio(-)/Contribucion(+) | F36: 4991152.4 | G36: 1838282.8 | H36: 703264.52 | I36: 369579.31 | J36: -596884.46 | K36: -26041.38 | L36: 0 | M36: -227782.49 | N36: -105769.99 | O36: -532864.03 | P36: 3611859.3 | Q36: -42491.1 | R36: 0 | S36: 0 | T36: 0 | U36: 0 | V36: 0 | W36: 0 | X36: 0 | Y36: 0 | Z36: 0
D37: O | E37: Total | F37: 4991152.4 | G37: 1838282.8 | H37: 703264.52 | I37: 369579.31 | J37: -596884.46 | K37: -26041.38 | L37: 0 | M37: -227782.49 | N37: -105769.99 | O37: -532864.03 | P37: 3611859.3 | Q37: -42491.1 | R37: 0 | S37: 0 | T37: 0 | U37: 0 | V37: 0 | W37: 0 | X37: 0 | Y37: 0 | Z37: 0
E38: Subsidio(-)/Contribucion(+) | F38: 70930319 | G38: 13105076 | H38: 7318853 | I38: 3844097.6 | J38: 3676388.6 | K38: 77320.12 | L38: 0 | M38: 692817.17 | N38: 1177808.5 | O38: 5457053.5 | P38: 35454664 | Q38: 126240.53 | R38: 0 | S38: 0 | T38: 0 | U38: 0 | V38: 0 | W38: 0 | X38: 0 | Y38: 0 | Z38: 0
D39: T | E39: Total | F39: 70930319 | G39: 13105076 | H39: 7318853 | I39: 3844097.6 | J39: 3676388.6 | K39: 77320.12 | L39: 0 | M39: 692817.17 | N39: 1177808.5 | O39: 5457053.5 | P39: 35454664 | Q39: 126240.53 | R39: 0 | S39: 0 | T39: 0 | U39: 0 | V39: 0 | W39: 0 | X39: 0 | Y39: 0 | Z39: 0
C40: OCCIDENTE | D40: Total | F40: 82466308 | G40: 16081983 | H40: 8658058.5 | I40: 4548339.8 | J40: 3654978.2 | K40: 55010.06 | L40: 0 | M40: 499060.06 | N40: 1197415.4 | O40: 5512238 | P40: 42169389 | Q40: 89836.18 | R40: 0 | S40: 0 | T40: 0 | U40: 0 | V40: 0 | W40: 0 | X40: 0 | Y40: 0 | Z40: 0
B41: Mes | C41: Total | F41: -2.8272608e+09 | G41: -55352218 | H41: -31613692 | I41: -16602894 | J41: -8.474255e+08 | K41: -28878257 | L41: 0 | M41: -2.5344112e+08 | N41: -2.4362022e+08 | O41: -1.1538013e+09 | P41: -1.4941089e+08 | Q41: -47114661 | R41: 0 | S41: 0 | T41: 0 | U41: 0 | V41: 0 | W41: 0 | X41: 0 | Y41: 0 | Z41: 0
A42: Subs/Cont | B42: Total | F42: -2.8219193e+09 | G42: -54254454 | H42: -30993638 | I42: -16276439 | J42: -8.473482e+08 | K42: -28875442 | L42: 0 | M42: -2.5341642e+08 | N42: -2.435885e+08 | O42: -1.1536539e+09 | P42: -1.4640221e+08 | Q42: -47110067 | R42: 0 | S42: 0 | T42: 0 | U42: 0 | V42: 0 | W42: 0 | X42: 0 | Y42: 0 | Z42: 0
A43: Total | F43: 1.6734199e+10 | G43: 9.322451e+08 | H43: 5.2353705e+08 | I43: 2.75534e+08 | J43: 4.0230167e+09 | K43: 1.4004409e+08 | L43: 18193739 | M43: 1.2291782e+09 | N43: 1.1909161e+09 | O43: 5.6338408e+09 | P43: 2.5392124e+09 | Q43: 2.2851459e+08 | R43: -33792.99 | S43: -0.06 | T43: 279.33 | U43: 0 | V43: 0 | W43: 0 | X43: 0 | Y43: 0 | Z43: 0
C46: TOTAL | D46: OPORTUNO | E46: Total | F46: =F25+F41-L25 -> 1.6704332e+10 | G46: =G25 -> 9.8525773e+08 | H46: =H25 -> 5.5382948e+08 | I46: =I25 -> 2.9144109e+08 | J46: =J25 -> 4.8702006e+09 | K46: =K25 -> 1.6891361e+08 | L46: =L25 -> 18193739 | M46: =M25 -> 1.4825427e+09 | N46: =N25 -> 1.4344369e+09 | ... AP46: =AP25 -> 0
E47: Subsidio(-)/Contribucion(+) | F47: =F41 -> -2.8272608e+09
D48: EXTEMPORANEO | E48: Total | F48: =F30+F10-L10 -> 11673020 | G48: =G10 -> 1241820.9 | H48: =H10 -> 701209.88 | I48: =I10 -> 369347.71 | J48: =J10 -> 164355.72 | K48: =K10 -> 5918.58 | L48: =L10 -> 0 | M48: =M10 -> 51916.98 | N48: =N10 -> 67675.1 | ... AP48: =AP10 -> 0
E49: Subsidio(-)/Contribucion(+) | F49: =F30 -> 5341504.6
C51: RECIPROCIDAD | D51: OPORTUNO | E51: Total | F51: 0 | G51: 0 | H51: 0 | I51: 0 | J51: 0 | K51: 0 | L51: 0 | M51: 0 | N51: 0 | O51: 0 | P51: 0 | Q51: 0 | R51: 0 | S51: 0 | T51: 0 | U51: 0 | V51: 0 | W51: 0 | X51: 0 | Y51: 0 | Z51: 0 | AA51: 0 | AB51: 0 | AC51: 0 | AD51: 0 | AE51: 0 | AF51: 0 | AG51: 0 | AH51: 0 | AI51: 0 | AJ51: 0 | AK51: 0 | AL51: 0 | AM51: 0 | AN51: 0 | AO51: 0 | AP51: 0
E52: Subsidio(-)/Contribucion(+) | F52: 0
D53: EXTEMPORANEO | E53: Total | F53: 0 | G53: 0 | H53: 0 | I53: 0 | J53: 0 | K53: 0 | L53: 0 | M53: 0 | N53: 0 | O53: 0 | P53: 0 | Q53: 0 | R53: 0 | S53: 0 | T53: 0 | U53: 0 | V53: 0 | W53: 0 | X53: 0 | Y53: 0 | Z53: 0 | AA53: 0 | AB53: 0 | AC53: 0 | AD53: 0 | AE53: 0 | AF53: 0 | AG53: 0 | AH53: 0 | AI53: 0 | AJ53: 0 | AK53: 0 | AL53: 0 | AM53: 0 | AN53: 0 | AO53: 0 | AP53: 0
E54: Subsidio(-)/Contribucion(+) | F54: 0
C56: ENEL | D56: OPORTUNO | E56: Total | F56: =F33+F14-L14 -> 1.6180196e+10 | G56: =G14 -> 9.1352469e+08 | H56: =H14 -> 5.1539398e+08 | I56: =I14 -> 2.7060684e+08 | J56: =J14 -> 4.8352516e+09 | K56: =K14 -> 1.6778649e+08 | L56: =L14 -> 14321945 | M56: =M14 -> 1.4726738e+09 | N56: =N14 -> 1422711691 | ... AP56: =AP14 -> 0
E57: Subsidio(-)/Contribucion(+) | F57: =F33 -> -2.9097271e+09
D58: EXTEMPORANEO | E58: Total | F58: 0 | G58: 0 | H58: 0 | I58: 0 | J58: 0 | K58: 0 | L58: 0 | M58: 0 | N58: 0 | O58: 0 | P58: 0 | Q58: 0 | R58: 0 | S58: 0 | T58: 0 | U58: 0 | V58: 0 | W58: 0 | X58: 0 | Y58: 0 | Z58: 0 | AA58: 0 | AB58: 0 | AC58: 0 | AD58: 0 | AE58: 0 | AF58: 0 | AG58: 0 | AH58: 0 | AI58: 0 | AJ58: 0 | AK58: 0 | AL58: 0 | AM58: 0 | AN58: 0 | AO58: 0 | AP58: 0
E59: Subsidio(-)/Contribucion(+) | F59: 0
C61: ENERBIT | D61: OPORTUNO | E61: Total | F61: 0 | G61: 0 | H61: 0 | I61: 0 | J61: 0 | K61: 0 | L61: 0 | M61: 0 | N61: 0 | O61: 0 | P61: 0 | Q61: 0 | R61: 0 | S61: 0 | T61: 0 | U61: 0 | V61: 0 | W61: 0 | X61: 0 | Y61: 0 | Z61: 0 | AA61: 0 | AB61: 0 | AC61: 0 | AD61: 0 | AE61: 0 | AF61: 0 | AG61: 0 | AH61: 0 | AI61: 0 | AJ61: 0 | AK61: 0 | AL61: 0 | AM61: 0 | AN61: 0 | AO61: 0
E62: Subsidio(-)/Contribucion(+) | F62: 0
D63: EXTEMPORANEO | E63: Total | F63: 0 | G63: 0 | H63: 0 | I63: 0 | J63: 0 | K63: 0 | L63: 0 | M63: 0 | N63: 0 | O63: 0 | P63: 0 | Q63: 0 | R63: 0 | S63: 0 | T63: 0 | U63: 0 | V63: 0 | W63: 0 | X63: 0 | Y63: 0 | Z63: 0 | AA63: 0 | AB63: 0 | AC63: 0 | AD63: 0 | AE63: 0 | AF63: 0 | AG63: 0 | AH63: 0 | AI63: 0 | AJ63: 0 | AK63: 0 | AL63: 0 | AM63: 0 | AN63: 0 | AO63: 0
E64: Subsidio(-)/Contribucion(+) | F64: 0
C66: OCCIDENTE | D66: OPORTUNO | E66: Total | F66: =F40+F24-L24 -> 5.2413693e+08 | G66: =G24 -> 71733039 | H66: =H24 -> 38435503 | I66: =I24 -> 20834248 | J66: =J24 -> 34948995 | K66: =K24 -> 1127126 | L66: =L24 -> 3871794.5 | M66: =M24 -> 9868870.5 | N66: =N24 -> 11725221 | ... AP66: =AP24 -> 0
E67: Subsidio(-)/Contribucion(+) | F67: =F40 -> 82466308
D68: EXTEMPORANEO | E68: Total | F68: =F29+F9-L9 -> 11673020 | G68: =G9 -> 1241820.9 | H68: =H9 -> 701209.88 | I68: =I9 -> 369347.71 | J68: =J9 -> 164355.72 | K68: =K9 -> 5918.58 | L68: =L9 -> 0 | M68: =M9 -> 51916.98 | N68: =N9 -> 67675.1 | ... AP68: =AP9 -> 0
E69: Subsidio(-)/Contribucion(+) | F69: =F29 -> 5341504.6
C71: CIUDAD LIMPIA-ACUEDUCTO | D71: OPORTUNO | E71: Total | F71: 0 | G71: 0 | H71: 0 | I71: 0 | J71: 0 | K71: 0 | L71: 0 | M71: 0 | N71: 0 | O71: 0 | P71: 0 | Q71: 0 | R71: 0 | S71: 0 | T71: 0 | U71: 0 | V71: 0 | W71: 0 | X71: 0 | Y71: 0 | Z71: 0 | AA71: 0 | AB71: 0 | AC71: 0 | AD71: 0 | AE71: 0 | AF71: 0 | AG71: 0 | AH71: 0 | AI71: 0 | AJ71: 0 | AK71: 0 | AL71: 0 | AM71: 0 | AN71: 0 | AO71: 0 | AP71: 0
E72: Subsidio(-)/Contribucion(+) | F72: 0
D73: EXTEMPORANEO | E73: Total | F73: 0 | G73: 0 | H73: 0 | I73: 0 | J73: 0 | K73: 0 | L73: 0 | M73: 0 | N73: 0 | O73: 0 | P73: 0 | Q73: 0 | R73: 0 | S73: 0 | T73: 0 | U73: 0 | V73: 0 | W73: 0 | X73: 0 | Y73: 0 | Z73: 0 | AA73: 0 | AB73: 0 | AC73: 0 | AD73: 0 | AE73: 0 | AF73: 0 | AG73: 0 | AH73: 0 | AI73: 0 | AJ73: 0 | AK73: 0 | AL73: 0 | AM73: 0 | AN73: 0 | AO73: 0 | AP73: 0
E74: Subsidio(-)/Contribucion(+) | F74: 0
D76: AFaseo | E76: Total | F76: 0 | G76: 0 | H76: 0 | I76: 0 | J76: 0 | K76: 0 | L76: 0 | M76: 0 | N76: 0 | O76: 0 | P76: 0 | Q76: 0 | R76: 0 | S76: 0 | T76: 0 | U76: 0 | V76: 0 | W76: 0 | X76: 0 | Y76: 0 | Z76: 0 | AA76: 0 | AB76: 0 | AC76: 0 | AD76: 0 | AE76: 0 | AF76: 0 | AG76: 0 | AH76: 0 | AI76: 0 | AJ76: 0 | AK76: 0 | AL76: 0 | AM76: 0 | AN76: 0 | AO76: 0 | AP76: 0
B79: LIME
F80: Total | G80: Componente TDF | H80: Componente TTL | I80: Componente TVIAT | J80: Aprovechamiento | K80: CCSA Prest.Aprov. | L80: SERVICIO ESPECIALES | M80: Componente TCS | N80: Componente TLU | O80: Componente TBL | P80: Componente TRT | Q80: CCSA Prest. No Aprov. | R80: Ajuste Decena | S80: Ajuste Recargo Aseo | T80: Intereses Cte Financiac. Aseo | U80: Exonera Rec.Intereses | V80: Exonera-Ajuste Decena Aseo | W80: Exonera-Recargo Aseo | X80: Rec.Intereses | Y80: Intereses Cte Financiac. Aseo | Z80: Rec.Intereses
E81: Vlr Servicio | F81: -1046185.4 | G81: -91219.33 | H81: -38751.51 | I81: -16923.62 | J81: -211175.82 | K81: -8741.75 | L81: 0 | M81: -77575.3 | N81: -96108.28 | O81: -322822.01 | P81: -168607.62 | Q81: -14260.13 | R81: 0 | S81: 0 | T81: 0 | U81: 0 | V81: 0 | W81: 0 | X81: 0 | Y81: 0 | Z81: 0
D82: E | E82: Total | F82: -1046185.4 | G82: -91219.33 | H82: -38751.51 | I82: -16923.62 | J82: -211175.82 | K82: -8741.75 | L82: 0 | M82: -77575.3 | N82: -96108.28 | O82: -322822.01 | P82: -168607.62 | Q82: -14260.13 | R82: 0 | S82: 0 | T82: 0 | U82: 0 | V82: 0 | W82: 0 | X82: 0 | Y82: 0 | Z82: 0
C83: ENEL | D83: Total | F83: -1046185.4 | G83: -91219.33 | H83: -38751.51 | I83: -16923.62 | J83: -211175.82 | K83: -8741.75 | L83: 0 | M83: -77575.3 | N83: -96108.28 | O83: -322822.01 | P83: -168607.62 | Q83: -14260.13 | R83: 0 | S83: 0 | T83: 0 | U83: 0 | V83: 0 | W83: 0 | X83: 0 | Y83: 0 | Z83: 0
E84: Vlr Servicio | F84: -16473.56 | G84: -1493.1 | H84: -634.32 | I84: -277.02 | J84: -3270.82 | K84: -134.76 | L84: 0 | M84: -1182.21 | N84: -1481.89 | O84: -4977.6 | P84: -2801.97 | Q84: -219.87 | R84: 0 | S84: 0 | T84: 0 | U84: 0 | V84: 0 | W84: 0 | X84: 0 | Y84: 0 | Z84: 0
D85: 5 | E85: Total | F85: -16473.56 | G85: -1493.1 | H85: -634.32 | I85: -277.02 | J85: -3270.82 | K85: -134.76 | L85: 0 | M85: -1182.21 | N85: -1481.89 | O85: -4977.6 | P85: -2801.97 | Q85: -219.87 | R85: 0 | S85: 0 | T85: 0 | U85: 0 | V85: 0 | W85: 0 | X85: 0 | Y85: 0 | Z85: 0
C86: NUEVO ESQUEMA | D86: Total | F86: -16473.56 | G86: -1493.1 | H86: -634.32 | I86: -277.02 | J86: -3270.82 | K86: -134.76 | L86: 0 | M86: -1182.21 | N86: -1481.89 | O86: -4977.6 | P86: -2801.97 | Q86: -219.87 | R86: 0 | S86: 0 | T86: 0 | U86: 0 | V86: 0 | W86: 0 | X86: 0 | Y86: 0 | Z86: 0
E87: Vlr Servicio | F87: -57062.45 | G87: -4986.76 | H87: -2118.48 | I87: -925.2 | J87: -11544.09 | K87: -475.66 | L87: 0 | M87: -4172.45 | N87: -5230.23 | O87: -17568 | P87: -9265.53 | Q87: -776.05 | R87: 0 | S87: 0 | T87: 0 | U87: 0 | V87: 0 | W87: 0 | X87: 0 | Y87: 0 | Z87: 0
D88: O | E88: Total | F88: -57062.45 | G88: -4986.76 | H88: -2118.48 | I88: -925.2 | J88: -11544.09 | K88: -475.66 | L88: 0 | M88: -4172.45 | N88: -5230.23 | O88: -17568 | P88: -9265.53 | Q88: -776.05 | R88: 0 | S88: 0 | T88: 0 | U88: 0 | V88: 0 | W88: 0 | X88: 0 | Y88: 0 | Z88: 0
C89: OCCIDENTE | D89: Total | F89: -57062.45 | G89: -4986.76 | H89: -2118.48 | I89: -925.2 | J89: -11544.09 | K89: -475.66 | L89: 0 | M89: -4172.45 | N89: -5230.23 | O89: -17568 | P89: -9265.53 | Q89: -776.05 | R89: 0 | S89: 0 | T89: 0 | U89: 0 | V89: 0 | W89: 0 | X89: 0 | Y89: 0 | Z89: 0
B90: Mes | C90: Total | F90: -1119721.4 | G90: -97699.19 | H90: -41504.31 | I90: -18125.84 | J90: -225990.73 | K90: -9352.17 | L90: 0 | M90: -82929.96 | N90: -102820.4 | O90: -345367.61 | P90: -180675.12 | Q90: -15256.05 | R90: 0 | S90: 0 | T90: 0 | U90: 0 | V90: 0 | W90: 0 | X90: 0 | Y90: 0 | Z90: 0
A91: AFaseo | B91: Total | F91: -1119721.4 | G91: -97699.19 | H91: -41504.31 | I91: -18125.84 | J91: -225990.73 | K91: -9352.17 | L91: 0 | M91: -82929.96 | N91: -102820.4 | O91: -345367.61 | P91: -180675.12 | Q91: -15256.05 | R91: 0 | S91: 0 | T91: 0 | U91: 0 | V91: 0 | W91: 0 | X91: 0 | Y91: 0 | Z91: 0
E92: Vlr Servicio | F92: 1.6314208e+10 | G92: 9.5151507e+08 | H92: 5.285219e+08 | I92: 2.7547386e+08 | J92: 3.8041861e+09 | K92: 1.4512649e+08 | L92: 23299358 | M92: 1.2756992e+09 | N92: 1.2731836e+09 | O92: 5.9433725e+09 | P92: 1.8563991e+09 | Q92: 2.3744556e+08 | R92: -15052.26 | S92: 0 | T92: 0 | U92: 0 | V92: 0 | W92: 0 | X92: 0 | Y92: 0 | Z92: 0
E93: Vlr Intereses | F93: 1.0887135e+08 | G93: 12946606 | H93: 5915805.3 | I93: 2579809.7 | J93: 20057775 | K93: 708344.44 | L93: 17761.05 | M93: 6224482.3 | N93: 7418679.7 | O93: 26472037 | P93: 25373910 | Q93: 1156004.6 | R93: 259.58 | S93: -3.99 | T93: 1.23 | U93: 0 | V93: 0 | W93: 0 | X93: 0 | Y93: 0 | Z93: -118.36
D94: E | E94: Total | F94: 1.6423079e+10 | G94: 9.6446167e+08 | H94: 5.3443771e+08 | I94: 2.7805367e+08 | J94: 3.8242438e+09 | K94: 1.4583483e+08 | L94: 23317119 | M94: 1.2819237e+09 | N94: 1.2806023e+09 | O94: 5.9698445e+09 | P94: 1.881773e+09 | Q94: 2.3860156e+08 | R94: -14792.68 | S94: -3.99 | T94: 1.23 | U94: 0 | V94: 0 | W94: 0 | X94: 0 | Y94: 0 | Z94: -118.36
C95: ENEL | D95: Total | F95: 1.6423079e+10 | G95: 9.6446167e+08 | H95: 5.3443771e+08 | I95: 2.7805367e+08 | J95: 3.8242438e+09 | K95: 1.4583483e+08 | L95: 23317119 | M95: 1.2819237e+09 | N95: 1.2806023e+09 | O95: 5.9698445e+09 | P95: 1.881773e+09 | Q95: 2.3860156e+08 | R95: -14792.68 | S95: -3.99 | T95: 1.23 | U95: 0 | V95: 0 | W95: 0 | X95: 0 | Y95: 0 | Z95: -118.36
E96: Vlr Servicio | F96: 2793830.6 | G96: 183700.22 | H96: 89369.61 | I96: 48325.39 | J96: 675666.11 | K96: 21056.87 | L96: 0 | M96: 184710.54 | N96: 221403.18 | O96: 967920.99 | P96: 367343.89 | Q96: 34356.29 | R96: -22.44 | S96: 0 | T96: 0 | U96: 0 | V96: 0 | W96: 0 | X96: 0 | Y96: 0 | Z96: 0
E97: Vlr Intereses | F97: 19935.41 | G97: 2043.67 | H97: 992.48 | I97: 555.42 | J97: 4248.25 | K97: 115.41 | L97: 0 | M97: 1012.75 | N97: 1184.9 | O97: 5496.69 | P97: 4097.45 | Q97: 188.34 | R97: 0.05 | S97: 0 | T97: 0 | U97: 0 | V97: 0 | W97: 0 | X97: 0 | Y97: 0 | Z97: 0
D98: 1 | E98: Total | F98: 2813766.1 | G98: 185743.89 | H98: 90362.09 | I98: 48880.81 | J98: 679914.36 | K98: 21172.28 | L98: 0 | M98: 185723.29 | N98: 222588.08 | O98: 973417.68 | P98: 371441.34 | Q98: 34544.63 | R98: -22.39 | S98: 0 | T98: 0 | U98: 0 | V98: 0 | W98: 0 | X98: 0 | Y98: 0 | Z98: 0
E99: Vlr Servicio | F99: 15556996 | G99: 906855.52 | H99: 477150.29 | I99: 245091.03 | J99: 3757740.2 | K99: 130011.87 | L99: 0 | M99: 1141338.1 | N99: 1242665.9 | O99: 5691716 | P99: 1752231 | Q99: 212228.37 | R99: -32.37 | S99: 0 | T99: 0 | U99: 0 | V99: 0 | W99: 0 | X99: 0 | Y99: 0 | Z99: 0
E100: Vlr Intereses | F100: 532474.38 | G100: 54438.68 | H100: 25649.66 | I100: 10870.44 | J100: 111667.2 | K100: 3936.77 | L100: 0 | M100: 34539.11 | N100: 42873.9 | O100: 140567.45 | P100: 101505.72 | Q100: 6424.9 | R100: 0.55 | S100: 0 | T100: 0 | U100: 0 | V100: 0 | W100: 0 | X100: 0 | Y100: 0 | Z100: 0
D101: 5 | E101: Total | F101: 16089470 | G101: 961294.2 | H101: 502799.95 | I101: 255961.47 | J101: 3869407.4 | K101: 133948.64 | L101: 0 | M101: 1175877.2 | N101: 1285539.8 | O101: 5832283.5 | P101: 1853736.7 | Q101: 218653.27 | R101: -31.82 | S101: 0 | T101: 0 | U101: 0 | V101: 0 | W101: 0 | X101: 0 | Y101: 0 | Z101: 0
C102: NUEVO ESQUEMA | D102: Total | F102: 18903236 | G102: 1147038.1 | H102: 593162.04 | I102: 304842.28 | J102: 4549321.8 | K102: 155120.92 | L102: 0 | M102: 1361600.5 | N102: 1508127.8 | O102: 6805701.2 | P102: 2225178.1 | Q102: 253197.9 | R102: -54.21 | S102: 0 | T102: 0 | U102: 0 | V102: 0 | W102: 0 | X102: 0 | Y102: 0 | Z102: 0
E103: Vlr Servicio | F103: 92091469 | G103: 5700742.1 | H103: 3218713.7 | I103: 1723015.4 | J103: 22316123 | K103: 580773.74 | L103: 0 | M103: 5106713.5 | N103: 7329496.9 | O103: 33820604 | P103: 11341911 | Q103: 953919.19 | R103: -544.09 | S103: 0 | T103: 0 | U103: 0 | V103: 0 | W103: 0 | X103: 0 | Y103: 0 | Z103: 0
E104: Vlr Intereses | F104: 461993.92 | G104: 40365.84 | H104: 20104.67 | I104: 11175.93 | J104: 99859.49 | K104: 2757.39 | L104: 0 | M104: 23994.83 | N104: 31896.67 | O104: 149946.68 | P104: 77393.45 | Q104: 4501.53 | R104: -2.56 | S104: 0 | T104: 0 | U104: 0 | V104: 0 | W104: 0 | X104: 0 | Y104: 0 | Z104: 0
D105: H | E105: Total | F105: 92553462 | G105: 5741107.9 | H105: 3238818.3 | I105: 1734191.4 | J105: 22415983 | K105: 583531.13 | L105: 0 | M105: 5130708.3 | N105: 7361393.5 | O105: 33970551 | P105: 11419304 | Q105: 958420.72 | R105: -546.65 | S105: 0 | T105: 0 | U105: 0 | V105: 0 | W105: 0 | X105: 0 | Y105: 0 | Z105: 0
E106: Vlr Servicio | F106: 1.3633417e+08 | G106: 13504608 | H106: 7144893.8 | I106: 3636218.5 | J106: 25044743 | K106: 879698.86 | L106: 3139000 | M106: 7792515.8 | N106: 8946101.7 | O106: 38207276 | P106: 26597253 | Q106: 1442290.7 | R106: -427.23 | S106: 0 | T106: 0 | U106: 0 | V106: 0 | W106: 0 | X106: 0 | Y106: 0 | Z106: 0
E107: Vlr Intereses | F107: 6368193.6 | G107: 809166.87 | H107: 387770.76 | I107: 176730.68 | J107: 1124122.4 | K107: 37781.04 | L107: 25063.1 | M107: 330975.59 | N107: 400076.03 | O107: 1459319.2 | P107: 1555514 | Q107: 61661.2 | R107: 0.5 | S107: 13.08 | T107: 0.18 | U107: 0 | V107: 0 | W107: 0 | X107: 0 | Y107: 0 | Z107: -1.11
D108: O | E108: Total | F108: 1.4270237e+08 | G108: 14313775 | H108: 7532664.5 | I108: 3812949.2 | J108: 26168866 | K108: 917479.9 | L108: 3164063.1 | M108: 8123491.4 | N108: 9346177.7 | O108: 39666595 | P108: 28152767 | Q108: 1503951.9 | R108: -426.73 | S108: 13.08 | T108: 0.18 | U108: 0 | V108: 0 | W108: 0 | X108: 0 | Y108: 0 | Z108: -1.11
E109: Vlr Servicio | F109: 1.744718e+08 | G109: 29959757 | H109: 16875022 | I109: 8893691.3 | J109: 18333755 | K109: 428407.94 | L109: 5256000 | M109: 3787836 | N109: 5386608.7 | O109: 25200363 | P109: 59642588 | Q109: 707849.71 | R109: -73.96 | S109: 0 | T109: 0 | U109: 0 | V109: 0 | W109: 0 | X109: 0 | Y109: 0 | Z109: 0
E110: Vlr Intereses | F110: 1310407.9 | G110: 244581.12 | H110: 133735.29 | I110: 69359.72 | J110: 111129.64 | K110: 3614.72 | L110: 0 | M110: 31543.09 | N110: 42996.83 | O110: 184629.13 | P110: 482915.58 | Q110: 5897.64 | R110: 4.99 | S110: 0.13 | T110: 0 | U110: 0 | V110: 0 | W110: 0 | X110: 0 | Y110: 0 | Z110: 0
D111: T | E111: Total | F111: 1.7578221e+08 | G111: 30204338 | H111: 17008757 | I111: 8963051 | J111: 18444884 | K111: 432022.66 | L111: 5256000 | M111: 3819379.1 | N111: 5429605.5 | O111: 25384992 | P111: 60125504 | Q111: 713747.35 | R111: -68.97 | S111: 0.13 | T111: 0 | U111: 0 | V111: 0 | W111: 0 | X111: 0 | Y111: 0 | Z111: 0
C112: OCCIDENTE | D112: Total | F112: 4.1103804e+08 | G112: 50259221 | H112: 27780240 | I112: 14510192 | J112: 67029732 | K112: 1933033.7 | L112: 8420063.1 | M112: 17073579 | N112: 22137177 | O112: 99022138 | P112: 99697576 | Q112: 3176120 | R112: -1042.35 | S112: 13.21 | T112: 0.18 | U112: 0 | V112: 0 | W112: 0 | X112: 0 | Y112: 0 | Z112: -1.11
B113: Mes | C113: Total | F113: 1.685302e+10 | G113: 1.0158679e+09 | H113: 5.6281111e+08 | I113: 2.9286871e+08 | J113: 3.8958229e+09 | K113: 1.4792299e+08 | L113: 31737182 | M113: 1.3003589e+09 | N113: 1.3042476e+09 | O113: 6.0756724e+09 | P113: 1.9836957e+09 | Q113: 2.4203088e+08 | R113: -15889.24 | S113: 9.22 | T113: 1.41 | U113: 0 | V113: 0 | W113: 0 | X113: 0 | Y113: 0 | Z113: -119.47
...

Sheet Rem. Anticipos R2
B1: PROMOAMBIENTAL
E2: Total | F2: Componente TDF | G2: Componente TTL | H2: Componente TVIAT | I2: Aprovechamiento | J2: CCSA Prest.Aprov. | K2: Especiales | L2: Componente TCS | M2: Componente TLU | N2: Componente TBL | O2: Componente TRT | P2: CCSA Prest. No Aprov. | Q2: Deb/Cred | R2: Deb/Cred-otros
D3: Vlr Servicio | E3: 52775108 | F3: 3005934.7 | G3: 1639699.6 | H3: 850296.11 | I3: 9434909.6 | J3: 259660.97 | K3: 57261.7 | L3: 4787838.2 | M3: 4258606.9 | N3: 19821214 | O3: 8235997.8 | P3: 424283.05 | Q3: -594.76 | R3: 0
D4: Vlr Intereses | E4: 78527.4 | F4: 286.62 | G4: 160.63 | H4: 84.75 | I4: 591.75 | J4: 22.99 | K4: 0 | L4: 196.2 | M4: 185.94 | N4: 856.99 | O4: 783.97 | P4: 37.53 | Q4: 75320.03 | R4: 0
C5: E | D5: Total | E5: 52853635 | F5: 3006221.3 | G5: 1639860.2 | H5: 850380.86 | I5: 9435501.3 | J5: 259683.96 | K5: 57261.7 | L5: 4788034.4 | M5: 4258792.9 | N5: 19822071 | O5: 8236781.7 | P5: 424320.58 | Q5: 74725.27 | R5: 0
B6: ENEL | C6: Total | E6: 52853635 | F6: 3006221.3 | G6: 1639860.2 | H6: 850380.86 | I6: 9435501.3 | J6: 259683.96 | K6: 57261.7 | L6: 4788034.4 | M6: 4258792.9 | N6: 19822071 | O6: 8236781.7 | P6: 424320.58 | Q6: 74725.27 | R6: 0
D7: Vlr Servicio | E7: 217567.77 | F7: 8801.93 | G7: 4969.56 | H7: 1578.39 | I7: 55004.69 | J7: 1915.1 | K7: 0 | L7: 16799.05 | M7: 16182.6 | N7: 85190.74 | O7: 23998.79 | P7: 3124.6 | Q7: 2.32 | R7: 0
C8: H | D8: Total | E8: 217567.77 | F8: 8801.93 | G8: 4969.56 | H8: 1578.39 | I8: 55004.69 | J8: 1915.1 | K8: 0 | L8: 16799.05 | M8: 16182.6 | N8: 85190.74 | O8: 23998.79 | P8: 3124.6 | Q8: 2.32 | R8: 0
D9: Vlr Servicio | E9: 2348432.2 | F9: 133715.17 | G9: 76606.43 | H9: 18339.36 | I9: 656909.12 | J9: 22734.38 | K9: 0 | L9: 268184.65 | M9: 134174.67 | N9: 638198.91 | O9: 360128.88 | P9: 39397.09 | Q9: 43.56 | R9: 0
D10: Vlr Intereses | E10: 1273.6 | F10: 35.71 | G10: 17.46 | H10: 9.61 | I10: 202.72 | J10: 16.33 | K10: 0 | L10: 143.17 | M10: 133.71 | N10: 591.26 | O10: 96.97 | P10: 26.63 | Q10: 0.03 | R10: 0
C11: O | D11: Total | E11: 2349705.8 | F11: 133750.88 | G11: 76623.89 | H11: 18348.97 | I11: 657111.84 | J11: 22750.71 | K11: 0 | L11: 268327.82 | M11: 134308.38 | N11: 638790.17 | O11: 360225.85 | P11: 39423.72 | Q11: 43.59 | R11: 0
D12: Vlr Servicio | E12: 932978.37 | F12: 50950.7 | G12: 28766.79 | H12: 13978.58 | I12: 228040.09 | J12: 7660.4 | K12: 0 | L12: 70556.01 | M12: 64730.4 | N12: 319858.46 | O12: 138447.13 | P12: 9998.72 | Q12: -8.91 | R12: 0
C13: T | D13: Total | E13: 932978.37 | F13: 50950.7 | G13: 28766.79 | H13: 13978.58 | I13: 228040.09 | J13: 7660.4 | K13: 0 | L13: 70556.01 | M13: 64730.4 | N13: 319858.46 | O13: 138447.13 | P13: 9998.72 | Q13: -8.91 | R13: 0
B14: OCCIDENTE | C14: Total | E14: 3500252 | F14: 193503.51 | G14: 110360.24 | H14: 33905.94 | I14: 940156.62 | J14: 32326.21 | K14: 0 | L14: 355682.88 | M14: 215221.38 | N14: 1043839.4 | O14: 522671.77 | P14: 52547.04 | Q14: 37 | R14: 0
A15: Componente | B15: Total | E15: 56353887 | F15: 3199724.8 | G15: 1750220.5 | H15: 884286.8 | I15: 10375658 | J15: 292010.17 | K15: 57261.7 | L15: 5143717.2 | M15: 4474014.3 | N15: 20865910 | O15: 8759453.5 | P15: 476867.62 | Q15: 74762.27 | R15: 0
D16: Subsidio(-)/Contribucion(+) | E16: -891046.91 | F16: 346354.38 | G16: 188770.63 | H16: 112441.44 | I16: -875398.47 | J16: -36178.21 | K16: 0 | L16: -243429.06 | M16: -212863.85 | N16: -1106133.6 | O16: 994081.82 | P16: -58691.97 | Q16: 0 | R16: 0
C17: E | D17: Total | E17: -891046.91 | F17: 346354.38 | G17: 188770.63 | H17: 112441.44 | I17: -875398.47 | J17: -36178.21 | K17: 0 | L17: -243429.06 | M17: -212863.85 | N17: -1106133.6 | O17: 994081.82 | P17: -58691.97 | Q17: 0 | R17: 0
B18: ENEL | C18: Total | E18: -891046.91 | F18: 346354.38 | G18: 188770.63 | H18: 112441.44 | I18: -875398.47 | J18: -36178.21 | K18: 0 | L18: -243429.06 | M18: -212863.85 | N18: -1106133.6 | O18: 994081.82 | P18: -58691.97 | Q18: 0 | R18: 0
D19: Subsidio(-)/Contribucion(+) | E19: 13129.64 | F19: 251.85 | G19: 142.19 | H19: 124.92 | I19: 5077.05 | J19: 191.51 | K19: 0 | L19: 646.85 | M19: 0 | N19: 5694.98 | O19: 687.83 | P19: 312.46 | Q19: 0 | R19: 0
C20: H | D20: Total | E20: 13129.64 | F20: 251.85 | G20: 142.19 | H20: 124.92 | I20: 5077.05 | J20: 191.51 | K20: 0 | L20: 646.85 | M20: 0 | N20: 5694.98 | O20: 687.83 | P20: 312.46 | Q20: 0 | R20: 0
D21: Subsidio(-)/Contribucion(+) | E21: -1366753.9 | F21: -48164.56 | G21: -27193.52 | H21: -14273.06 | I21: -298390.72 | J21: -14114.49 | K21: 0 | L21: -123808.53 | M21: -119265.98 | N21: -566524.06 | O21: -131990.43 | P21: -23028.52 | Q21: 0 | R21: 0
C22: O | D22: Total | E22: -1366753.9 | F22: -48164.56 | G22: -27193.52 | H22: -14273.06 | I22: -298390.72 | J22: -14114.49 | K22: 0 | L22: -123808.53 | M22: -119265.98 | N22: -566524.06 | O22: -131990.43 | P22: -23028.52 | Q22: 0 | R22: 0
D23: Subsidio(-)/Contribucion(+) | E23: 164431.29 | F23: 9572.57 | G23: 5404.71 | H23: 3830.1 | I23: 25069.49 | J23: 1091.6 | K23: 0 | L23: 13271.32 | M23: 12784.24 | N23: 62966.18 | O23: 28660.07 | P23: 1781.01 | Q23: 0 | R23: 0
C24: T | D24: Total | E24: 164431.29 | F24: 9572.57 | G24: 5404.71 | H24: 3830.1 | I24: 25069.49 | J24: 1091.6 | K24: 0 | L24: 13271.32 | M24: 12784.24 | N24: 62966.18 | O24: 28660.07 | P24: 1781.01 | Q24: 0 | R24: 0
B25: OCCIDENTE | C25: Total | E25: -1189192.9 | F25: -38340.14 | G25: -21646.62 | H25: -10318.04 | I25: -268244.18 | J25: -12831.38 | K25: 0 | L25: -109890.36 | M25: -106481.74 | N25: -497862.9 | O25: -102642.53 | P25: -20935.05 | Q25: 0 | R25: 0
A26: Subs/Cont | B26: Total | E26: -2080239.9 | F26: 308014.24 | G26: 167124.01 | H26: 102123.4 | I26: -1143642.6 | J26: -49009.59 | K26: 0 | L26: -353319.42 | M26: -319345.59 | N26: -1603996.5 | O26: 891439.29 | P26: -79627.02 | Q26: 0 | R26: 0
A27: Total | E27: 54273647 | F27: 3507739 | G27: 1917344.5 | H27: 986410.2 | I27: 9232015.3 | J27: 243000.58 | K27: 57261.7 | L27: 4790397.8 | M27: 4154668.7 | N27: 19261914 | O27: 9650892.8 | P27: 397240.6 | Q27: 74762.27 | R27: 0
B41: TOTAL | C41: OPORTUNO | D41: Total | E41: =E15+E26-K15 -> 54216386 | F41: =F15 -> 3199724.8 | G41: =G15 -> 1750220.5 | H41: =H15 -> 884286.8 | I41: =I15 -> 10375658 | J41: =J15 -> 292010.17 | K41: =K15 -> 57261.7 | L41: =L15 -> 5143717.2 | M41: =M15 -> 4474014.3 | ... S41: =S15 -> 0
D42: Subsidio(-)/Contribucion(+) | E42: =E26 -> -2080239.9
B44: RECIPROCIDAD | C44: OPORTUNO | D44: Total | E44: 0 | F44: 0 | G44: 0 | H44: 0 | I44: 0 | J44: 0 | K44: 0 | L44: 0 | M44: 0 | N44: 0 | O44: 0 | P44: 0 | Q44: 0 | R44: 0 | S44: 0
D45: Subsidio(-)/Contribucion(+) | E45: 0
B47: ENEL | C47: OPORTUNO | D47: Total | E47: =E18+E6-K6 -> 51905327 | F47: =F6 -> 3006221.3 | G47: =G6 -> 1639860.2 | H47: =H6 -> 850380.86 | I47: =I6 -> 9435501.3 | J47: =J6 -> 259683.96 | K47: =K6 -> 57261.7 | L47: =L6 -> 4788034.4 | M47: =M6 -> 4258792.9 | ... S47: =S6 -> 0
D48: Subsidio(-)/Contribucion(+) | E48: =E18 -> -891046.91
B50: ENERBIT | C50: OPORTUNO | D50: Total | E50: 0 | F50: 0 | G50: 0 | H50: 0 | I50: 0 | J50: 0 | K50: 0 | L50: 0 | M50: 0 | N50: 0 | O50: 0 | P50: 0 | Q50: 0 | R50: 0
D51: Subsidio(-)/Contribucion(+) | E51: 0
B53: OCCIDENTE | C53: OPORTUNO | D53: Total | E53: =E14+E25-K14 -> 2311059 | F53: =F14 -> 193503.51 | G53: =G14 -> 110360.24 | H53: =H14 -> 33905.94 | I53: =I14 -> 940156.62 | J53: =J14 -> 32326.21 | K53: =K14 -> 0 | L53: =L14 -> 355682.88 | M53: =M14 -> 215221.38 | ... S53: =S14 -> 0
D54: Subsidio(-)/Contribucion(+) | E54: =E25 -> -1189192.9
B56: CIUDAD LIMPIA-ACUEDUCTO | C56: OPORTUNO | D56: Total | E56: 0 | F56: 0 | G56: 0 | H56: 0 | I56: 0 | J56: 0 | K56: 0 | L56: 0 | M56: 0 | N56: 0 | O56: 0 | P56: 0 | Q56: 0 | R56: 0 | S56: 0
D57: Subsidio(-)/Contribucion(+) | E57: 0
B59: LIME
E60: Total | F60: Componente TDF | G60: Componente TTL | H60: Componente TVIAT | I60: Aprovechamiento | J60: CCSA Prest.Aprov. | K60: Especiales | L60: Componente TCS | M60: Componente TLU | N60: Componente TBL | O60: Componente TRT | P60: CCSA Prest. No Aprov. | Q60: Deb/Cred | R60: Deb/Cred-otros
D61: Vlr Servicio | E61: 50271236 | F61: 3276677.1 | G61: 1833935.5 | H61: 672265.76 | I61: 12214565 | J61: 442175.89 | K61: 0 | L61: 4727156.5 | M61: 3746436.1 | N61: 16069327 | O61: 6709601.1 | P61: 578953.47 | Q61: 142.45 | R61: 0
D62: Vlr Intereses | E62: 46479.5 | F62: 3409.96 | G62: 1920.55 | H62: 1043.33 | I62: 10019.75 | J62: 383.79 | K62: 0 | L62: 3308.56 | M62: 3357.79 | N62: 15781.07 | O62: 6620.49 | P62: 634.21 | Q62: 0 | R62: 0
C63: E | D63: Total | E63: 50317715 | F63: 3280087.1 | G63: 1835856 | H63: 673309.09 | I63: 12224585 | J63: 442559.68 | K63: 0 | L63: 4730465.1 | M63: 3749793.9 | N63: 16085108 | O63: 6716221.6 | P63: 579587.68 | Q63: 142.45 | R63: 0
B64: ENEL | C64: Total | E64: 50317715 | F64: 3280087.1 | G64: 1835856 | H64: 673309.09 | I64: 12224585 | J64: 442559.68 | K64: 0 | L64: 4730465.1 | M64: 3749793.9 | N64: 16085108 | O64: 6716221.6 | P64: 579587.68 | Q64: 142.45 | R64: 0
D65: Vlr Servicio | E65: 16040915 | F65: 1001818.6 | G65: 611637.46 | H65: 185472.06 | I65: 4195926.7 | J65: 150329.6 | K65: 0 | L65: 1384619.2 | M65: 1219913.8 | N65: 5113816.9 | O65: 2013991.9 | P65: 163358.54 | Q65: 30.24 | R65: 0
D66: Vlr Intereses | E66: 201.04 | F66: 10.1 | G66: 5.55 | H66: 3.1 | I66: 53.59 | J66: 1.33 | K66: 0 | L66: 11.64 | M66: 16.53 | N66: 77.04 | O66: 20.01 | P66: 2.17 | Q66: -0.02 | R66: 0
C67: 1 | D67: Total | E67: 16041116 | F67: 1001828.7 | G67: 611643.01 | H67: 185475.16 | I67: 4195980.2 | J67: 150330.93 | K67: 0 | L67: 1384630.8 | M67: 1219930.3 | N67: 5113893.9 | O67: 2014011.9 | P67: 163360.71 | Q67: 30.22 | R67: 0
D68: Vlr Servicio | E68: 1818547.6 | F68: 128760.39 | G68: 71047.39 | H68: 26311.36 | I68: 457821.68 | J68: 16416.52 | K68: 0 | L68: 161313.48 | M68: 145157.77 | N68: 531816.23 | O68: 260084.65 | P68: 19812.38 | Q68: 5.7 | R68: 0
D69: Vlr Intereses | E69: 33.95 | F69: 1.8 | G69: 0.98 | H69: 0.55 | I69: 9.01 | J69: 0.21 | K69: 0 | L69: 1.87 | M69: 2.76 | N69: 12.89 | O69: 3.54 | P69: 0.35 | Q69: -0.01 | R69: 0
C70: 2 | D70: Total | E70: 1818581.5 | F70: 128762.19 | G70: 71048.37 | H70: 26311.91 | I70: 457830.69 | J70: 16416.73 | K70: 0 | L70: 161315.35 | M70: 145160.53 | N70: 531829.12 | O70: 260088.19 | P70: 19812.73 | Q70: 5.69 | R70: 0
D71: Vlr Servicio | E71: 30899067 | F71: 1881991.3 | G71: 1144839.6 | H71: 333958.81 | I71: 8271733.5 | J71: 285997.26 | K71: 0 | L71: 2769930.4 | M71: 2359306.7 | N71: 9850848.8 | O71: 3701576.6 | P71: 298981.81 | Q71: -97.37 | R71: 0
D72: Vlr Intereses | E72: 2727.84 | F72: 175.12 | G72: 97.39 | H72: 52.41 | I72: 622.13 | J72: 21.51 | K72: 0 | L72: 188.54 | M72: 205.56 | N72: 981.44 | O72: 348.76 | P72: 35.08 | Q72: -0.1 | R72: 0
C73: 5 | D73: Total | E73: 30901795 | F73: 1882166.4 | G73: 1144937 | H73: 334011.22 | I73: 8272355.7 | J73: 286018.77 | K73: 0 | L73: 2770118.9 | M73: 2359512.2 | N73: 9851830.2 | O73: 3701925.4 | P73: 299016.89 | Q73: -97.47 | R73: 0
B74: NUEVO ESQUEMA | C74: Total | E74: 48761493 | F74: 3012757.2 | G74: 1827628.4 | H74: 545798.29 | I74: 12926167 | J74: 452766.43 | K74: 0 | L74: 4316065.1 | M74: 3724603.1 | N74: 15497553 | O74: 5976025.5 | P74: 482190.33 | Q74: -61.56 | R74: 0
D75: Vlr Servicio | E75: 2832969.5 | F75: 151240.95 | G75: 85811.39 | H75: 53309.98 | I75: 635923.5 | J75: 26212.2 | K75: 0 | L75: 253538.15 | M75: 216274.95 | N75: 962811.09 | O75: 409511.49 | P75: 38330.22 | Q75: 5.58 | R75: 0
D76: Vlr Intereses | E76: 8920.03 | F76: 886.52 | G76: 436 | H76: 238.26 | I76: 1935.69 | J76: 52.61 | K76: 0 | L76: 468.77 | M76: 543.69 | N76: 2482.69 | O76: 1790.06 | P76: 85.7 | Q76: 0.04 | R76: 0
C77: H | D77: Total | E77: 2841889.5 | F77: 152127.47 | G77: 86247.39 | H77: 53548.24 | I77: 637859.19 | J77: 26264.81 | K77: 0 | L77: 254006.92 | M77: 216818.64 | N77: 965293.78 | O77: 411301.55 | P77: 38415.92 | Q77: 5.62 | R77: 0
D78: Vlr Servicio | E78: 7841401.2 | F78: 490784.72 | G78: 272032.52 | H78: 97603.63 | I78: 1831399 | J78: 63689.67 | K78: 0 | L78: 762797.92 | M78: 636964.27 | N78: 2562177.2 | O78: 1034271.2 | P78: 89661.79 | Q78: 19.22 | R78: 0
D79: Vlr Intereses | E79: 17262.18 | F79: 1309.11 | G79: 641 | H79: 350.32 | I79: 4389.42 | J79: 115.12 | K79: 0 | L79: 1004.92 | M79: 1185.69 | N79: 5466.07 | O79: 2612.65 | P79: 187.8 | Q79: 0.08 | R79: 0
C80: O | D80: Total | E80: 7858663.3 | F80: 492093.83 | G80: 272673.52 | H80: 97953.95 | I80: 1835788.4 | J80: 63804.79 | K80: 0 | L80: 763802.84 | M80: 638149.96 | N80: 2567643.3 | O80: 1036883.9 | P80: 89849.59 | Q80: 19.3 | R80: 0
D81: Vlr Servicio | E81: 2941813.1 | F81: 487451.46 | G81: 275498.82 | H81: 318443.36 | I81: 244485.23 | J81: 8955.27 | K81: 0 | L81: 104367.36 | M81: 81249.1 | N81: 382028.35 | O81: 1025612.4 | P81: 13704.15 | Q81: 17.57 | R81: 0
D82: Vlr Intereses | E82: 11803.62 | F82: 2463.61 | G82: 1086.48 | H82: 616.15 | I82: 1006.67 | J82: 23.61 | K82: 0 | L82: 207.14 | M82: 252.86 | N82: 1159.56 | O82: 4948.98 | P82: 38.53 | Q82: 0.03 | R82: 0
C83: T | D83: Total | E83: 2953616.7 | F83: 489915.07 | G83: 276585.3 | H83: 319059.51 | I83: 245491.9 | J83: 8978.88 | K83: 0 | L83: 104574.5 | M83: 81501.96 | N83: 383187.91 | O83: 1030561.4 | P83: 13742.68 | Q83: 17.6 | R83: 0
B84: OCCIDENTE | C84: Total | E84: 13654170 | F84: 1134136.4 | G84: 635506.21 | H84: 470561.7 | I84: 2719139.5 | J84: 99048.48 | K84: 0 | L84: 1122384.3 | M84: 936470.56 | N84: 3916125 | O84: 2478746.9 | P84: 142008.19 | Q84: 42.52 | R84: 0
A85: Componente | B85: Total | E85: 1.1273338e+08 | F85: 7426980.7 | G85: 4298990.7 | H85: 1689669.1 | I85: 27869891 | J85: 994374.59 | K85: 0 | L85: 10168914 | M85: 8410867.6 | N85: 35498786 | O85: 15170994 | P85: 1203786.2 | Q85: 123.41 | R85: 0
D86: Subsidio(-)/Contribucion(+) | E86: -16181131 | F86: -635494.97 | G86: -363664.93 | H86: -193985.45 | I86: -4026468 | J86: -160751.43 | K86: 0 | L86: -1413674.1 | M86: -1384494.6 | N86: -6532433.8 | O86: -1208617 | P86: -261546.83 | Q86: 0 | R86: 0
C87: E | D87: Total | E87: -16181131 | F87: -635494.97 | G87: -363664.93 | H87: -193985.45 | I87: -4026468 | J87: -160751.43 | K87: 0 | L87: -1413674.1 | M87: -1384494.6 | N87: -6532433.8 | O87: -1208617 | P87: -261546.83 | Q87: 0 | R87: 0
B88: ENEL | C88: Total | E88: -16181131 | F88: -635494.97 | G88: -363664.93 | H88: -193985.45 | I88: -4026468 | J88: -160751.43 | K88: 0 | L88: -1413674.1 | M88: -1384494.6 | N88: -6532433.8 | O88: -1208617 | P88: -261546.83 | Q88: 0 | R88: 0
D89: Subsidio(-)/Contribucion(+) | E89: -5446380.4 | F89: -238020.56 | G89: -135232.46 | H89: -71812.46 | I89: -1290222.5 | J89: -53723.56 | K89: 0 | L89: -466608.74 | M89: -457322.67 | N89: -2169125.5 | O89: -477467.23 | P89: -86844.72 | Q89: 0 | R89: 0
C90: 1 | D90: Total | E90: -5446380.4 | F90: -238020.56 | G90: -135232.46 | H90: -71812.46 | I90: -1290222.5 | J90: -53723.56 | K90: 0 | L90: -466608.74 | M90: -457322.67 | N90: -2169125.5 | O90: -477467.23 | P90: -86844.72 | Q90: 0 | R90: 0
D91: Subsidio(-)/Contribucion(+) | E91: -428945.36 | F91: -13901.43 | G91: -7854.47 | H91: -4144.29 | I91: -115247.22 | J91: -4419.95 | K91: 0 | L91: -38771.53 | M91: -38049.79 | N91: -172384.25 | O91: -27404.39 | P91: -6768.04 | Q91: 0 | R91: 0
C92: 2 | D92: Total | E92: -428945.36 | F92: -13901.43 | G92: -7854.47 | H92: -4144.29 | I92: -115247.22 | J92: -4419.95 | K92: 0 | L92: -38771.53 | M92: -38049.79 | N92: -172384.25 | O92: -27404.39 | P92: -6768.04 | Q92: 0 | R92: 0
D93: Subsidio(-)/Contribucion(+) | E93: -10063322 | F93: -396769.96 | G93: -274205.72 | H93: -138254.55 | I93: -2470580.2 | J93: -99016.97 | K93: 0 | L93: -858324.83 | M93: -844697.72 | N93: -4012841.8 | O93: -808674.97 | P93: -159954.79 | Q93: 0 | R93: 0
C94: 5 | D94: Total | E94: -10063322 | F94: -396769.96 | G94: -274205.72 | H94: -138254.55 | I94: -2470580.2 | J94: -99016.97 | K94: 0 | L94: -858324.83 | M94: -844697.72 | N94: -4012841.8 | O94: -808674.97 | P94: -159954.79 | Q94: 0 | R94: 0
B95: NUEVO ESQUEMA | C95: Total | E95: -15938647 | F95: -648691.95 | G95: -417292.65 | H95: -214211.3 | I95: -3876049.9 | J95: -157160.48 | K95: 0 | L95: -1363705.1 | M95: -1340070.2 | N95: -6354351.6 | O95: -1313546.6 | P95: -253567.55 | Q95: 0 | R95: 0
D96: Subsidio(-)/Contribucion(+) | E96: -508303.18 | F96: -9658.23 | G96: -5452.27 | H96: -2856.43 | I96: -132147.93 | J96: -5596.95 | K96: 0 | L96: -49095.88 | M96: -48163.12 | N96: -227811.56 | O96: -18388.98 | P96: -9131.83 | Q96: 0 | R96: 0
C97: H | D97: Total | E97: -508303.18 | F97: -9658.23 | G97: -5452.27 | H97: -2856.43 | I97: -132147.93 | J97: -5596.95 | K97: 0 | L97: -49095.88 | M97: -48163.12 | N97: -227811.56 | O97: -18388.98 | P97: -9131.83 | Q97: 0 | R97: 0
D98: Subsidio(-)/Contribucion(+) | E98: -1818607.1 | F98: -63308.61 | G98: -36684.93 | H98: -19294.22 | I98: -441210.27 | J98: -19148.39 | K98: 0 | L98: -167785.83 | M98: -162128.29 | N98: -750855.38 | O98: -126978.94 | P98: -31212.28 | Q98: 0 | R98: 0
C99: O | D99: Total | E99: -1818607.1 | F99: -63308.61 | G99: -36684.93 | H99: -19294.22 | I99: -441210.27 | J99: -19148.39 | K99: 0 | L99: -167785.83 | M99: -162128.29 | N99: -750855.38 | O99: -126978.94 | P99: -31212.28 | Q99: 0 | R99: 0
D100: Subsidio(-)/Contribucion(+) | E100: 1114112.5 | F100: 317443.15 | G100: 153311.5 | H100: 641.25 | I100: -25002.52 | J100: -1282.57 | K100: 0 | L100: -3875.6 | M100: -4931.11 | N100: -44626.25 | O100: 724527.24 | P100: -2092.62 | Q100: 0 | R100: 0
C101: T | D101: Total | E101: 1114112.5 | F101: 317443.15 | G101: 153311.5 | H101: 641.25 | I101: -25002.52 | J101: -1282.57 | K101: 0 | L101: -3875.6 | M101: -4931.11 | N101: -44626.25 | O101: 724527.24 | P101: -2092.62 | Q101: 0 | R101: 0
B102: OCCIDENTE | C102: Total | E102: -1212797.9 | F102: 244476.31 | G102: 111174.3 | H102: -21509.4 | I102: -598360.72 | J102: -26027.91 | K102: 0 | L102: -220757.31 | M102: -215222.52 | N102: -1023293.2 | O102: 579159.32 | P102: -42436.73 | Q102: 0 | R102: 0
A103: Subs/Cont | B103: Total | E103: -33332576 | F103: -1039710.6 | G103: -669783.28 | H103: -429706.15 | I103: -8500878.6 | J103: -343939.82 | K103: 0 | L103: -2998136.5 | M103: -2939787.3 | N103: -13910079 | O103: -1943004.3 | P103: -557551.11 | Q103: 0 | R103: 0
A104: Total | E104: 79400801 | F104: 6387270.1 | G104: 3629207.4 | H104: 1259962.9 | I104: 19369012 | J104: 650434.77 | K104: 0 | L104: 7170777.9 | M104: 5471080.2 | N104: 21588708 | O104: 13227990 | P104: 646235.09 | Q104: 123.41 | R104: 0
B135: TOTAL | C135: OPORTUNO | D135: Total | E135: =E85+E103-K85 -> 79400801 | F135: =F85 -> 7426980.7 | G135: =G85 -> 4298990.7 | H135: =H85 -> 1689669.1 | I135: =I85 -> 27869891 | J135: =J85 -> 994374.59 | K135: =K85 -> 0 | L135: =L85 -> 10168914 | M135: =M85 -> 8410867.6 | ... R135: =R85 -> 0
D136: Subsidio(-)/Contribucion(+) | E136: =E103 -> -33332576
B138: RECIPROCIDAD | C138: OPORTUNO | D138: Total | E138: =E95+E74-K74 -> 32822845 | F138: =F74 -> 3012757.2 | G138: =G74 -> 1827628.4 | H138: =H74 -> 545798.29 | I138: =I74 -> 12926167 | J138: =J74 -> 452766.43 | K138: =K74 -> 0 | L138: =L74 -> 4316065.1 | M138: =M74 -> 3724603.1 | ... R138: =R74 -> 0
D139: Subsidio(-)/Contribucion(+) | E139: =E95 -> -15938647
B141: ENEL | C141: OPORTUNO | D141: Total | E141: =E88+E64-K64 -> 34136584 | F141: =F64 -> 3280087.1 | G141: =G64 -> 1835856 | H141: =H64 -> 673309.09 | I141: =I64 -> 12224585 | J141: =J64 -> 442559.68 | K141: =K64 -> 0 | L141: =L64 -> 4730465.1 | M141: =M64 -> 3749793.9 | ... R141: =R64 -> 0
D142: Subsidio(-)/Contribucion(+) | E142: =E88 -> -16181131
B144: ENERBIT | C144: OPORTUNO | D144: Total | E144: 0 | F144: 0 | G144: 0 | H144: 0 | I144: 0 | J144: 0 | K144: 0 | L144: 0 | M144: 0 | N144: 0 | O144: 0 | P144: 0 | Q144: 0 | R144: 0
D145: Subsidio(-)/Contribucion(+) | E145: 0
B147: OCCIDENTE | C147: OPORTUNO | D147: Total | E147: =E84+E102-K84 -> 12441372 | F147: =F84 -> 1134136.4 | G147: =G84 -> 635506.21 | H147: =H84 -> 470561.7 | I147: =I84 -> 2719139.5 | J147: =J84 -> 99048.48 | K147: =K84 -> 0 | L147: =L84 -> 1122384.3 | M147: =M84 -> 936470.56 | ... R147: =R84 -> 0
D148: Subsidio(-)/Contribucion(+) | E148: =E102 -> -1212797.9
B150: CIUDAD LIMPIA-ACUEDUCTO | C150: OPORTUNO | D150: Total | E150: 0 | F150: 0 | G150: 0 | H150: 0 | I150: 0 | J150: 0 | K150: 0 | L150: 0 | M150: 0 | N150: 0 | O150: 0 | P150: 0 | Q150: 0 | R150: 0
D151: Subsidio(-)/Contribucion(+) | E151: 0
B153: CIUDAD LIMPIA
E154: Total | F154: Componente TDF | G154: Componente TTL | H154: Componente TVIAT | I154: Aprovechamiento | J154: CCSA Prest.Aprov. | K154: Especiales | L154: Componente TCS | M154: Componente TLU | N154: Componente TBL | O154: Componente TRT | P154: CCSA Prest. No Aprov. | Q154: Deb/Cred | R154: Deb/Cred-otros
D155: Vlr Servicio | E155: 31046837 | F155: 2023853.4 | G155: 1165352.6 | H155: 492083.55 | I155: 6720888.4 | J155: 258589.27 | K155: 0 | L155: 2632179.6 | M155: 2263134.4 | N155: 10289906 | O155: 4844871.2 | P155: 355642.13 | Q155: 336.05 | R155: 0
...

Sheet Reversion Pagos R4
B1: PROMOAMBIENTAL
D2: Total | E2: Componente TDF | F2: Componente TTL | G2: Componente TVIAT | H2: Aprovechamiento | I2: CCSA Prest.Aprov. | J2: Componente TCS | K2: Componente TLU | L2: Componente TBL | M2: Componente TRT | N2: CCSA Prest. No Aprov. | O2: Ajuste Decena | P2: SERVICIO ESPECIALES | Q2: Ajuste Recargo Aseo | R2: Otros
C3: Vlr Servicio | D3: -8485687.6 | E3: -1533145.5 | F3: -865959.97 | G3: -456267.38 | H3: -382091.3 | I3: -12179.47 | J3: -112932.75 | K3: -152004.56 | L3: -737957.5 | M3: -4213305.4 | N3: -19871.42 | O3: 27.66 | P3: 0 | Q3: 0 | R3: 0
C4: Vlr Intereses | D4: -26833.73 | E4: -5410.19 | F4: -3055.42 | G4: -1614.59 | H4: -512.83 | I4: -18.28 | J4: -160.4 | K4: -207 | L4: -945.64 | M4: -14879.62 | N4: -29.75 | O4: -0.01 | P4: 0 | Q4: 0 | R4: 0
B5: Componente | C5: Total | D5: -8512521.3 | E5: -1538555.7 | F5: -869015.39 | G5: -457881.97 | H5: -382604.13 | I5: -12197.75 | J5: -113093.15 | K5: -152211.56 | L5: -738903.14 | M5: -4228185 | N5: -19901.17 | O5: 27.65 | P5: 0 | Q5: 0 | R5: 0
C6: Subsidio(-)/Contribucion(+) | D6: -3541734.4 | E6: -668084.55 | F6: -378722.34 | G6: -199766.06 | H6: -126968.15 | I6: -4568.7 | J6: -38734.16 | K6: -50056.15 | L6: -232448.97 | M6: -1834931.2 | N6: -7454.1 | O6: 0 | P6: 0 | Q6: 0 | R6: 0
B7: Subs/Cont | C7: Total | D7: -3541734.4 | E7: -668084.55 | F7: -378722.34 | G7: -199766.06 | H7: -126968.15 | I7: -4568.7 | J7: -38734.16 | K7: -50056.15 | L7: -232448.97 | M7: -1834931.2 | N7: -7454.1 | O7: 0 | P7: 0 | Q7: 0 | R7: 0
A8: OCCIDENTE | B8: Total | D8: -12054256 | E8: -2206640.2 | F8: -1247737.7 | G8: -657648.03 | H8: -509572.28 | I8: -16766.45 | J8: -151827.31 | K8: -202267.71 | L8: -971352.11 | M8: -6063116.2 | N8: -27355.27 | O8: 27.65 | P8: 0 | Q8: 0 | R8: 0
A9: Total | D9: -12054256 | E9: -2206640.2 | F9: -1247737.7 | G9: -657648.03 | H9: -509572.28 | I9: -16766.45 | J9: -151827.31 | K9: -202267.71 | L9: -971352.11 | M9: -6063116.2 | N9: -27355.27 | O9: 27.65 | P9: 0 | Q9: 0 | R9: 0
A67: TOTAL | B67: OPORTUNO | C67: Total | D67: =D9-P9 -> -12054256 | E67: =E5 -> -1538555.7 | F67: =F5 -> -869015.39 | G67: =G5 -> -457881.97 | H67: =H5 -> -382604.13 | I67: =I5 -> -12197.75 | J67: =J5 -> -113093.15 | K67: =K5 -> -152211.56 | L67: =L5 -> -738903.14 | ... R67: =R5 -> 0
C68: Subsidio(-)/Contribucion(+) | D68: =D7 -> -3541734.4
A70: RECIPROCIDAD | B70: OPORTUNO | C70: Total | D70: 0 | E70: 0 | F70: 0 | G70: 0 | H70: 0 | I70: 0 | J70: 0 | K70: 0 | L70: 0 | M70: 0 | N70: 0 | O70: 0 | P70: 0 | Q70: 0 | R70: 0
C71: Subsidio(-)/Contribucion(+) | D71: 0
A73: ENEL | B73: OPORTUNO | C73: Total | D73: 0 | E73: 0 | F73: 0 | G73: 0 | H73: 0 | I73: 0 | J73: 0 | K73: 0 | L73: 0 | M73: 0 | N73: 0 | O73: 0 | P73: 0 | Q73: 0 | R73: 0
C74: Subsidio(-)/Contribucion(+) | D74: 0
A76: ENERBIT | B76: OPORTUNO | C76: Total | D76: 0 | E76: 0 | F76: 0 | G76: 0 | H76: 0 | I76: 0 | J76: 0 | K76: 0 | L76: 0 | M76: 0 | N76: 0 | O76: 0 | P76: 0 | Q76: 0 | R76: 0
C77: Subsidio(-)/Contribucion(+) | D77: 0
A79: OCCIDENTE | B79: OPORTUNO | C79: Total | D79: =D8-P8 -> -12054256 | E79: =E5 -> -1538555.7 | F79: =F5 -> -869015.39 | G79: =G5 -> -457881.97 | H79: =H5 -> -382604.13 | I79: =I5 -> -12197.75 | J79: =J5 -> -113093.15 | K79: =K5 -> -152211.56 | L79: =L5 -> -738903.14 | ... R79: =R5 -> 0
C80: Subsidio(-)/Contribucion(+) | D80: =D7 -> -3541734.4
A82: CIUDAD LIMPIA-ACUEDUCTO | B82: OPORTUNO | C82: Total | D82: 0 | E82: 0 | F82: 0 | G82: 0 | H82: 0 | I82: 0 | J82: 0 | K82: 0 | L82: 0 | M82: 0 | N82: 0 | O82: 0 | P82: 0 | Q82: 0 | R82: 0
C83: Subsidio(-)/Contribucion(+) | D83: 0
B85: LIME
D86: Total | E86: Componente TDF | F86: Componente TTL | G86: Componente TVIAT | H86: Aprovechamiento | I86: CCSA Prest.Aprov. | J86: Componente TCS | K86: Componente TLU | L86: Componente TBL | M86: Componente TRT | N86: CCSA Prest. No Aprov. | O86: Ajuste Decena | P86: SERVICIO ESPECIALES | Q86: Ajuste Recargo Aseo | R86: Otros
C87: Vlr Servicio | D87: -12510091 | E87: -685319.88 | F87: -386138.78 | G87: -203450.42 | H87: -3018006.6 | I87: -115581.1 | J87: -1004303.4 | K87: -984101.17 | L87: -4576813.8 | M87: -1348439.4 | N87: -187944.08 | O87: 7.45 | P87: 0 | Q87: 0 | R87: 0
C88: Vlr Intereses | D88: -28375.39 | E88: -1910.39 | F88: -986.27 | G88: -479.41 | H88: -5748.48 | I88: -254.76 | J88: -2231.44 | K88: -2549.78 | L88: -10026.67 | M88: -3773.44 | N88: -414.85 | O88: 0.1 | P88: 0 | Q88: 0 | R88: 0
B89: Componente | C89: Total | D89: -12538467 | E89: -687230.27 | F89: -387125.05 | G89: -203929.83 | H89: -3023755.1 | I89: -115835.86 | J89: -1006534.8 | K89: -986650.95 | L89: -4586840.5 | M89: -1352212.9 | N89: -188358.93 | O89: 7.55 | P89: 0 | Q89: 0 | R89: 0
C90: Subsidio(-)/Contribucion(+) | D90: 2669055.6 | E90: 90356.23 | F90: 51012.76 | G90: 26867.42 | H90: 688638.15 | I90: 27274.93 | J90: 239249.96 | K90: 234515.54 | L90: 1090962.4 | M90: 175677.7 | N90: 44500.53 | O90: 0 | P90: 0 | Q90: 0 | R90: 0
B91: Subs/Cont | C91: Total | D91: 2669055.6 | E91: 90356.23 | F91: 51012.76 | G91: 26867.42 | H91: 688638.15 | I91: 27274.93 | J91: 239249.96 | K91: 234515.54 | L91: 1090962.4 | M91: 175677.7 | N91: 44500.53 | O91: 0 | P91: 0 | Q91: 0 | R91: 0
A92: ENEL | B92: Total | D92: -9869411 | E92: -596874.04 | F92: -336112.29 | G92: -177062.41 | H92: -2335117 | I92: -88560.93 | J92: -767284.84 | K92: -752135.41 | L92: -3495878.1 | M92: -1176535.2 | N92: -143858.4 | O92: 7.55 | P92: 0 | Q92: 0 | R92: 0
C93: Vlr Servicio | D93: -23269.08 | E93: -163.23 | F93: -92.16 | G93: -48.37 | H93: 0 | I93: -374.65 | J93: -3286.39 | K93: -3205.2 | L93: -15163.76 | M93: -324.05 | N93: -611.27 | O93: 0 | P93: 0 | Q93: 0 | R93: 0
B94: Componente | C94: Total | D94: -23269.08 | E94: -163.23 | F94: -92.16 | G94: -48.37 | H94: 0 | I94: -374.65 | J94: -3286.39 | K94: -3205.2 | L94: -15163.76 | M94: -324.05 | N94: -611.27 | O94: 0 | P94: 0 | Q94: 0 | R94: 0
C95: Subsidio(-)/Contribucion(+) | D95: 3490.36 | E95: 24.48 | F95: 13.82 | G95: 7.26 | H95: 0 | I95: 56.2 | J95: 492.96 | K95: 480.78 | L95: 2274.56 | M95: 48.61 | N95: 91.69 | O95: 0 | P95: 0 | Q95: 0 | R95: 0
B96: Subs/Cont | C96: Total | D96: 3490.36 | E96: 24.48 | F96: 13.82 | G96: 7.26 | H96: 0 | I96: 56.2 | J96: 492.96 | K96: 480.78 | L96: 2274.56 | M96: 48.61 | N96: 91.69 | O96: 0 | P96: 0 | Q96: 0 | R96: 0
A97: NUEVO ESQUEMA | B97: Total | D97: -19778.72 | E97: -138.75 | F97: -78.34 | G97: -41.11 | H97: 0 | I97: -318.45 | J97: -2793.43 | K97: -2724.42 | L97: -12889.2 | M97: -275.44 | N97: -519.58 | O97: 0 | P97: 0 | Q97: 0 | R97: 0
A98: Total | D98: -9889189.7 | E98: -597012.79 | F98: -336190.63 | G98: -177103.52 | H98: -2335117 | I98: -88879.38 | J98: -770078.27 | K98: -754859.83 | L98: -3508767.3 | M98: -1176810.6 | N98: -144377.98 | O98: 7.55 | P98: 0 | Q98: 0 | R98: 0
A161: TOTAL | B161: OPORTUNO | C161: Total | D161: =D98-P98 -> -9889189.7 | E161: =E94+E89 -> -687393.5 | F161: =F94+F89 -> -387217.21 | G161: =G94+G89 -> -203978.2 | H161: =H94+H89 -> -3023755.1 | I161: =I94+I89 -> -116210.51 | J161: =J94+J89 -> -1009821.2 | K161: =K94+K89 -> -989856.15 | L161: =L94+L89 -> -4602004.2 | ... R161: =R94+R89 -> 0
C162: Subsidio(-)/Contribucion(+) | D162: =D96+D91 -> 2672546
A164: RECIPROCIDAD | B164: OPORTUNO | C164: Total | D164: =D97-P97 -> -19778.72 | E164: =E94 -> -163.23 | F164: =F94 -> -92.16 | G164: =G94 -> -48.37 | H164: =H94 -> 0 | I164: =I94 -> -374.65 | J164: =J94 -> -3286.39 | K164: =K94 -> -3205.2 | L164: =L94 -> -15163.76 | ... R164: =R94 -> 0
C165: Subsidio(-)/Contribucion(+) | D165: =D96 -> 3490.36
A167: ENEL | B167: OPORTUNO | C167: Total | D167: =D92-P92 -> -9869411 | E167: =E89 -> -687230.27 | F167: =F89 -> -387125.05 | G167: =G89 -> -203929.83 | H167: =H89 -> -3023755.1 | I167: =I89 -> -115835.86 | J167: =J89 -> -1006534.8 | K167: =K89 -> -986650.95 | L167: =L89 -> -4586840.5 | ... R167: =R89 -> 0
C168: Subsidio(-)/Contribucion(+) | D168: =D91 -> 2669055.6
A170: ENERBIT | B170: OPORTUNO | C170: Total | D170: 0 | E170: 0 | F170: 0 | G170: 0 | H170: 0 | I170: 0 | J170: 0 | K170: 0 | L170: 0 | M170: 0 | N170: 0 | O170: 0 | P170: 0 | Q170: 0 | R170: 0
C171: Subsidio(-)/Contribucion(+) | D171: 0
A173: OCCIDENTE | B173: OPORTUNO | C173: Total | D173: 0 | E173: 0 | F173: 0 | G173: 0 | H173: 0 | I173: 0 | J173: 0 | K173: 0 | L173: 0 | M173: 0 | N173: 0 | O173: 0 | P173: 0 | Q173: 0 | R173: 0
C174: Subsidio(-)/Contribucion(+) | D174: 0
A176: CIUDAD LIMPIA-ACUEDUCTO | B176: OPORTUNO | C176: Total | D176: 0 | E176: 0 | F176: 0 | G176: 0 | H176: 0 | I176: 0 | J176: 0 | K176: 0 | L176: 0 | M176: 0 | N176: 0 | O176: 0 | P176: 0 | Q176: 0 | R176: 0
C177: Subsidio(-)/Contribucion(+) | D177: 0
B179: CIUDAD LIMPIA
D180: Total | E180: Componente TDF | F180: Componente TTL | G180: Componente TVIAT | H180: Aprovechamiento | I180: CCSA Prest.Aprov. | J180: Componente TCS | K180: Componente TLU | L180: Componente TBL | M180: Componente TRT | N180: CCSA Prest. No Aprov. | O180: Ajuste Decena | P180: SERVICIO ESPECIALES | Q180: Ajuste Recargo Aseo | R180: Otros
C181: Vlr Servicio | D181: -6145967.1 | E181: -349180.17 | F181: -196775.04 | G181: -103888.74 | H181: -1434778.6 | I181: -54350.68 | J181: -476763.32 | K181: -466428.2 | L181: -2167699.4 | M181: -807353.75 | N181: -88678.1 | O181: -71.02 | P181: 0 | Q181: 0 | R181: 0
C182: Vlr Intereses | D182: -8558.43 | E182: -1248.82 | F182: -702.2 | G182: -373.05 | H182: -1035.82 | I182: -38.3 | J182: -336.02 | K182: -329.37 | L182: -1510.98 | M182: -2921.34 | N182: -62.48 | O182: -0.05 | P182: 0 | Q182: 0 | R182: 0
B183: Componente | C183: Total | D183: -6154525.5 | E183: -350428.99 | F183: -197477.24 | G183: -104261.79 | H183: -1435814.4 | I183: -54388.98 | J183: -477099.34 | K183: -466757.57 | L183: -2169210.4 | M183: -810275.09 | N183: -88740.58 | O183: -71.07 | P183: 0 | Q183: 0 | R183: 0
C184: Subsidio(-)/Contribucion(+) | D184: 582564.49 | E184: -17627.28 | F184: -10061.43 | G184: -5205.25 | H184: 205245.27 | I184: 7510.5 | J184: 65881.45 | K184: 64440.83 | L184: 301226.99 | M184: -41100.53 | N184: 12253.94 | O184: 0 | P184: 0 | Q184: 0 | R184: 0
B185: Subs/Cont | C185: Total | D185: 582564.49 | E185: -17627.28 | F185: -10061.43 | G185: -5205.25 | H185: 205245.27 | I185: 7510.5 | J185: 65881.45 | K185: 64440.83 | L185: 301226.99 | M185: -41100.53 | N185: 12253.94 | O185: 0 | P185: 0 | Q185: 0 | R185: 0
A186: ENEL | B186: Total | D186: -5571961 | E186: -368056.27 | F186: -207538.67 | G186: -109467.04 | H186: -1230569.2 | I186: -46878.48 | J186: -411217.89 | K186: -402316.74 | L186: -1867983.4 | M186: -851375.62 | N186: -76486.64 | O186: -71.07 | P186: 0 | Q186: 0 | R186: 0
C187: Vlr Servicio | D187: -7191231.3 | E187: -1290187.2 | F187: -727655.58 | G187: -383403.13 | H187: -546142.94 | I187: -14831.06 | J187: -132335.31 | K187: -192881.75 | L187: -868987.31 | M187: -3010588.4 | N187: -24198.32 | O187: -20.31 | P187: 0 | Q187: 0 | R187: 0
C188: Vlr Intereses | D188: -168206.84 | E188: -35174.64 | F188: -19828.27 | G188: -10500.45 | H188: -6841.22 | I188: -164.45 | J188: -1443.15 | K188: -2078.83 | L188: -9557.77 | M188: -82350.12 | N188: -268.2 | O188: 0.26 | P188: 0 | Q188: 0 | R188: 0
B189: Componente | C189: Total | D189: -7359438.1 | E189: -1325361.8 | F189: -747483.85 | G189: -393903.58 | H189: -552984.16 | I189: -14995.51 | J189: -133778.46 | K189: -194960.58 | L189: -878545.08 | M189: -3092938.5 | N189: -24466.52 | O189: -20.05 | P189: 0 | Q189: 0 | R189: 0
C190: Subsidio(-)/Contribucion(+) | D190: -3172043.8 | E190: -685613.87 | F190: -387173.36 | G190: -202748.11 | H190: -74920.64 | I190: -1731.91 | J190: -18114.04 | K190: -24106.17 | L190: -112026.93 | M190: -1662782.9 | N190: -2825.88 | O190: 0 | P190: 0 | Q190: 0 | R190: 0
B191: Subs/Cont | C191: Total | D191: -3172043.8 | E191: -685613.87 | F191: -387173.36 | G191: -202748.11 | H191: -74920.64 | I191: -1731.91 | J191: -18114.04 | K191: -24106.17 | L191: -112026.93 | M191: -1662782.9 | N191: -2825.88 | O191: 0 | P191: 0 | Q191: 0 | R191: 0
A192: OCCIDENTE | B192: Total | D192: -10531482 | E192: -2010975.7 | F192: -1134657.2 | G192: -596651.69 | H192: -627904.8 | I192: -16727.42 | J192: -151892.5 | K192: -219066.75 | L192: -990572.01 | M192: -4755721.4 | N192: -27292.4 | O192: -20.05 | P192: 0 | Q192: 0 | R192: 0
A193: Total | D193: -16103443 | E193: -2379032 | F193: -1342195.9 | G193: -706118.73 | H193: -1858474 | I193: -63605.9 | J193: -563110.39 | K193: -621383.49 | L193: -2858555.4 | M193: -5607097 | N193: -103779.04 | O193: -91.12 | P193: 0 | Q193: 0 | R193: 0
A198: TOTAL | B198: OPORTUNO | C198: Total | D198: =D193-P193 -> -16103443 | E198: =E189+E183 -> -1675790.8 | F198: =F189+F183 -> -944961.09 | G198: =G189+G183 -> -498165.37 | H198: =H189+H183 -> -1988798.6 | I198: =I189+I183 -> -69384.49 | J198: =J189+J183 -> -610877.8 | K198: =K189+K183 -> -661718.15 | L198: =L189+L183 -> -3047755.5 | ... R198: =R189+R183 -> 0
C199: Subsidio(-)/Contribucion(+) | D199: =D191+D185 -> -2589479.3
A201: RECIPROCIDAD | B201: OPORTUNO | C201: Total | D201: 0 | E201: 0 | F201: 0 | G201: 0 | H201: 0 | I201: 0 | J201: 0 | K201: 0 | L201: 0 | M201: 0 | N201: 0 | O201: 0 | P201: 0 | Q201: 0 | R201: 0
C202: Subsidio(-)/Contribucion(+) | D202: 0
A204: ENEL | B204: OPORTUNO | C204: Total | D204: =D186-P186 -> -5571961 | E204: =E183 -> -350428.99 | F204: =F183 -> -197477.24 | G204: =G183 -> -104261.79 | H204: =H183 -> -1435814.4 | I204: =I183 -> -54388.98 | J204: =J183 -> -477099.34 | K204: =K183 -> -466757.57 | L204: =L183 -> -2169210.4 | ... R204: =R183 -> 0
C205: Subsidio(-)/Contribucion(+) | D205: =D185 -> 582564.49
A207: ENERBIT | B207: OPORTUNO | C207: Total | D207: 0 | E207: 0 | F207: 0 | G207: 0 | H207: 0 | I207: 0 | J207: 0 | K207: 0 | L207: 0 | M207: 0 | N207: 0 | O207: 0 | P207: 0 | Q207: 0 | R207: 0
C208: Subsidio(-)/Contribucion(+) | D208: 0
A210: OCCIDENTE | B210: OPORTUNO | C210: Total | D210: =D192-P192 -> -10531482 | E210: =E189 -> -1325361.8 | F210: =F189 -> -747483.85 | G210: =G189 -> -393903.58 | H210: =H189 -> -552984.16 | I210: =I189 -> -14995.51 | J210: =J189 -> -133778.46 | K210: =K189 -> -194960.58 | L210: =L189 -> -878545.08 | ... R210: =R189 -> 0
C211: Subsidio(-)/Contribucion(+) | D211: =D191 -> -3172043.8
A213: CIUDAD LIMPIA-ACUEDUCTO | B213: OPORTUNO | C213: Total | D213: 0 | E213: 0 | F213: 0 | G213: 0 | H213: 0 | I213: 0 | J213: 0 | K213: 0 | L213: 0 | M213: 0 | N213: 0 | O213: 0 | P213: 0 | Q213: 0 | R213: 0
C214: Subsidio(-)/Contribucion(+) | D214: 0
B216: BOGOTA LIMPIA
D217: Total | E217: Componente TDF | F217: Componente TTL | G217: Componente TVIAT | H217: Aprovechamiento | I217: CCSA Prest.Aprov. | J217: Componente TCS | K217: Componente TLU | L217: Componente TBL | M217: Componente TRT | N217: CCSA Prest. No Aprov. | O217: Ajuste Decena | P217: SERVICIO ESPECIALES | Q217: Ajuste Recargo Aseo | R217: Otros
C218: Vlr Servicio | D218: -15076053 | E218: -950203.7 | F218: -529101.01 | G218: -276975.39 | H218: -3249908.5 | I218: -118563 | J218: -1039649.7 | K218: -1027919.1 | L218: -5136480.3 | M218: -2554589.3 | N218: -192796.2 | O218: 133.47 | P218: 0 | Q218: 0 | R218: 0
C219: Vlr Intereses | D219: -538967.52 | E219: -65025.4 | F219: -32049.68 | G219: -13139.44 | H219: -75519.1 | I219: -3209.32 | J219: -28151.47 | K219: -35321.99 | L219: -115622.58 | M219: -165690.43 | N219: -5237.14 | O219: -2.24 | P219: 0 | Q219: 0 | R219: 1.27
B220: Componente | C220: Total | D220: -15615020 | E220: -1015229.1 | F220: -561150.69 | G220: -290114.83 | H220: -3325427.6 | I220: -121772.32 | J220: -1067801.1 | K220: -1063241.1 | L220: -5252102.9 | M220: -2720279.7 | N220: -198033.34 | O220: 131.23 | P220: 0 | Q220: 0 | R220: 1.27
C221: Subsidio(-)/Contribucion(+) | D221: -353166.37 | E221: -159690.26 | F221: -92306.89 | G221: -49591.41 | H221: 127872.79 | I221: 4017.75 | J221: 35242.87 | K221: 34118.14 | L221: 166138.88 | M221: -425523.39 | N221: 6555.15 | O221: 0 | P221: 0 | Q221: 0 | R221: 0
B222: Subs/Cont | C222: Total | D222: -353166.37 | E222: -159690.26 | F222: -92306.89 | G222: -49591.41 | H222: 127872.79 | I222: 4017.75 | J222: 35242.87 | K222: 34118.14 | L222: 166138.88 | M222: -425523.39 | N222: 6555.15 | O222: 0 | P222: 0 | Q222: 0 | R222: 0
A223: ENEL | B223: Total | D223: -15968187 | E223: -1174919.4 | F223: -653457.58 | G223: -339706.24 | H223: -3197554.8 | I223: -117754.57 | J223: -1032558.3 | K223: -1029123 | L223: -5085964 | M223: -3145803.1 | N223: -191478.19 | O223: 131.23 | P223: 0 | Q223: 0 | R223: 1.27
C224: Vlr Servicio | D224: -367858.16 | E224: -25757.99 | F224: -13609.93 | G224: -7922.5 | H224: -71079.73 | I224: -1946.36 | J224: -17073.54 | K224: -22906.17 | L224: -135380.64 | M224: -69013.4 | N224: -3175.66 | O224: 7.76 | P224: 0 | Q224: 0 | R224: 0
C225: Vlr Intereses | D225: -30.53 | E225: -2.43 | F225: -1.12 | G225: -0.61 | H225: -6.94 | I225: -0.17 | J225: -1.49 | K225: -1.84 | L225: -9.06 | M225: -6.59 | N225: -0.28 | O225: 0 | P225: 0 | Q225: 0 | R225: 0
B226: Componente | C226: Total | D226: -367888.69 | E226: -25760.42 | F226: -13611.05 | G226: -7923.11 | H226: -71086.67 | I226: -1946.53 | J226: -17075.03 | K226: -22908.01 | L226: -135389.7 | M226: -69019.99 | N226: -3175.94 | O226: 7.76 | P226: 0 | Q226: 0 | R226: 0
C227: Subsidio(-)/Contribucion(+) | D227: -96481.31 | E227: -7964.87 | F227: -4293 | G227: -2449.79 | H227: -11884.32 | I227: -613.8 | J227: -5384.03 | K227: -6824.33 | L227: -34597.89 | M227: -21467.82 | N227: -1001.46 | O227: 0 | P227: 0 | Q227: 0 | R227: 0
B228: Subs/Cont | C228: Total | D228: -96481.31 | E228: -7964.87 | F228: -4293 | G228: -2449.79 | H228: -11884.32 | I228: -613.8 | J228: -5384.03 | K228: -6824.33 | L228: -34597.89 | M228: -21467.82 | N228: -1001.46 | O228: 0 | P228: 0 | Q228: 0 | R228: 0
A229: NUEVO ESQUEMA | B229: Total | D229: -464370 | E229: -33725.29 | F229: -17904.05 | G229: -10372.9 | H229: -82970.99 | I229: -2560.33 | J229: -22459.06 | K229: -29732.34 | L229: -169987.59 | M229: -90487.81 | N229: -4177.4 | O229: 7.76 | P229: 0 | Q229: 0 | R229: 0
C230: Vlr Servicio | D230: -4794726.1 | E230: -316630.93 | F230: -178230.21 | G230: -95686.73 | H230: -1006887.6 | I230: -34872.41 | J230: -308680.75 | K230: -326282.53 | L230: -1616571.9 | M230: -853956.66 | N230: -56912.41 | O230: -13.95 | P230: 0 | Q230: 0 | R230: 0
C231: Vlr Intereses | D231: -687500.88 | E231: -116224.77 | F231: -31590.51 | G231: -3782.11 | H231: -40136.84 | I231: -2590.69 | J231: -22728.64 | K231: -23035.81 | L231: -71995.31 | M231: -371186.11 | N231: -4228.18 | O231: -1.91 | P231: 0 | Q231: 0 | R231: 0
B232: Componente | C232: Total | D232: -5482227 | E232: -432855.7 | F232: -209820.72 | G232: -99468.84 | H232: -1047024.5 | I232: -37463.1 | J232: -331409.39 | K232: -349318.34 | L232: -1688567.2 | M232: -1225142.8 | N232: -61140.59 | O232: -15.86 | P232: 0 | Q232: 0 | R232: 0
C233: Subsidio(-)/Contribucion(+) | D233: 625875 | E233: 21424.75 | F233: 11771.93 | G233: 6328.28 | H233: 165668.93 | I233: 5797.77 | J233: 50833.32 | K233: 49420.33 | L233: 247212.36 | M233: 57965.13 | N233: 9452.2 | O233: 0 | P233: 0 | Q233: 0 | R233: 0
B234: Subs/Cont | C234: Total | D234: 625875 | E234: 21424.75 | F234: 11771.93 | G234: 6328.28 | H234: 165668.93 | I234: 5797.77 | J234: 50833.32 | K234: 49420.33 | L234: 247212.36 | M234: 57965.13 | N234: 9452.2 | O234: 0 | P234: 0 | Q234: 0 | R234: 0
A235: OCCIDENTE | B235: Total | D235: -4856352 | E235: -411430.95 | F235: -198048.79 | G235: -93140.56 | H235: -881355.54 | I235: -31665.33 | J235: -280576.07 | K235: -299898.01 | L235: -1441354.8 | M235: -1167177.6 | N235: -51688.39 | O235: -15.86 | P235: 0 | Q235: 0 | R235: 0
A236: Total | D236: -21288909 | E236: -1620075.6 | F236: -869410.42 | G236: -443219.7 | H236: -4161881.3 | I236: -151980.23 | J236: -1335593.4 | K236: -1358753.3 | L236: -6697306.4 | M236: -4403468.6 | N236: -247343.98 | O236: 123.13 | P236: 0 | Q236: 0 | R236: 1.27
A312: TOTAL | B312: OPORTUNO | C312: Total | D312: =D236-P236 -> -21288909 | E312: =E232+E226+E220 -> -1473845.2 | F312: =F232+F226+F220 -> -784582.46 | G312: =G232+G226+G220 -> -397506.78 | H312: =H232+H226+H220 -> -4443538.7 | I312: =I232+I226+I220 -> -161181.95 | J312: =J232+J226+J220 -> -1416285.5 | K312: =K232+K226+K220 -> -1435467.5 | L312: =L232+L226+L220 -> -7076059.8 | ... R312: =R232+R226+R220 -> 1.27
C313: Subsidio(-)/Contribucion(+) | D313: =D234+D228+D222 -> 176227.32
A315: RECIPROCIDAD | B315: OPORTUNO | C315: Total | D315: =D229-P229 -> -464370 | E315: =E226 -> -25760.42 | F315: =F226 -> -13611.05 | G315: =G226 -> -7923.11 | H315: =H226 -> -71086.67 | I315: =I226 -> -1946.53 | J315: =J226 -> -17075.03 | K315: =K226 -> -22908.01 | L315: =L226 -> -135389.7 | ... R315: =R226 -> 0
C316: Subsidio(-)/Contribucion(+) | D316: =D228 -> -96481.31
A318: ENEL | B318: OPORTUNO | C318: Total | D318: =D223-P223 -> -15968187 | E318: =E220 -> -1015229.1 | F318: =F220 -> -561150.69 | G318: =G220 -> -290114.83 | H318: =H220 -> -3325427.6 | I318: =I220 -> -121772.32 | J318: =J220 -> -1067801.1 | K318: =K220 -> -1063241.1 | L318: =L220 -> -5252102.9 | ... R318: =R220 -> 1.27
...

Sheet SALDOS POR NOTA
B1: PROMOAMBIENTAL
C2: Total | D2: Componente TDF | E2: Componente TTL | F2: Componente TVIAT | G2: Aprovechamiento | H2: CCSA Prest.Aprov. | I2: Especiales | J2: Componente TCS | K2: Componente TLU | L2: Componente TBL | M2: Componente TRT | N2: CCSA Prest. No Aprov. | O2: Deb/Cred
B3: Vlr Servicio | C3: 0 | D3: 0 | E3: 0 | F3: 0 | G3: 0 | H3: 0 | I3: 0 | J3: 0 | K3: 0 | L3: 0 | M3: 0 | N3: 0 | O3: 0
B4: Vlr Intereses | C4: 0 | D4: 0 | E4: 0 | F4: 0 | G4: 0 | H4: 0 | I4: 0 | J4: 0 | K4: 0 | L4: 0 | M4: 0 | N4: 0 | O4: 0
A5: Componente | B5: Total | C5: 0 | D5: 0 | E5: 0 | F5: 0 | G5: 0 | H5: 0 | I5: 0 | J5: 0 | K5: 0 | L5: 0 | M5: 0 | N5: 0 | O5: 0
B6: Subsidio(-)/Contribucion(+) | C6: 0 | D6: 0 | E6: 0 | F6: 0 | G6: 0 | H6: 0 | I6: 0 | J6: 0 | K6: 0 | L6: 0 | M6: 0 | N6: 0 | O6: 0
A7: Subs/Cont | B7: Total | C7: 0 | D7: 0 | E7: 0 | F7: 0 | G7: 0 | H7: 0 | I7: 0 | J7: 0 | K7: 0 | L7: 0 | M7: 0 | N7: 0 | O7: 0
A8: Total | C8: 0 | D8: 0 | E8: 0 | F8: 0 | G8: 0 | H8: 0 | I8: 0 | J8: 0 | K8: 0 | L8: 0 | M8: 0 | N8: 0 | O8: 0
B10: Total | C10: =C8-I8 -> 0 | D10: =D5 -> 0 | E10: =E5 -> 0 | F10: =F5 -> 0 | G10: =G5 -> 0 | H10: =H5 -> 0 | I10: =I5 -> 0 | J10: =J5 -> 0 | K10: =K5 -> 0 | ... P10: =P5 -> 0
B11: Subsidio(-)/Contribucion(+) | C11: =C7 -> 0
B14: LIME
C15: Total | D15: Componente TDF | E15: Componente TTL | F15: Componente TVIAT | G15: Aprovechamiento | H15: CCSA Prest.Aprov. | I15: Especiales | J15: Componente TCS | K15: Componente TLU | L15: Componente TBL | M15: Componente TRT | N15: CCSA Prest. No Aprov. | O15: Deb/Cred
B16: Vlr Servicio | C16: 0 | D16: 0 | E16: 0 | F16: 0 | G16: 0 | H16: 0 | I16: 0 | J16: 0 | K16: 0 | L16: 0 | M16: 0 | N16: 0 | O16: 0
B17: Vlr Intereses | C17: 0 | D17: 0 | E17: 0 | F17: 0 | G17: 0 | H17: 0 | I17: 0 | J17: 0 | K17: 0 | L17: 0 | M17: 0 | N17: 0 | O17: 0
A18: Componente | B18: Total | C18: 0 | D18: 0 | E18: 0 | F18: 0 | G18: 0 | H18: 0 | I18: 0 | J18: 0 | K18: 0 | L18: 0 | M18: 0 | N18: 0 | O18: 0
B19: Subsidio(-)/Contribucion(+) | C19: 0 | D19: 0 | E19: 0 | F19: 0 | G19: 0 | H19: 0 | I19: 0 | J19: 0 | K19: 0 | L19: 0 | M19: 0 | N19: 0 | O19: 0
A20: Subs/Cont | B20: Total | C20: 0 | D20: 0 | E20: 0 | F20: 0 | G20: 0 | H20: 0 | I20: 0 | J20: 0 | K20: 0 | L20: 0 | M20: 0 | N20: 0 | O20: 0
A21: Total | C21: 0 | D21: 0 | E21: 0 | F21: 0 | G21: 0 | H21: 0 | I21: 0 | J21: 0 | K21: 0 | L21: 0 | M21: 0 | N21: 0 | O21: 0
B23: Total | C23: =C21-I21 -> 0 | D23: =D18 -> 0 | E23: =E18 -> 0 | F23: =F18 -> 0 | G23: =G18 -> 0 | H23: =H18 -> 0 | I23: =I18 -> 0 | J23: =J18 -> 0 | K23: =K18 -> 0 | ... P23: =P18 -> 0
B24: Subsidio(-)/Contribucion(+) | C24: =C20 -> 0
B27: CIUDAD LIMPIA
C28: Total | D28: Componente TDF | E28: Componente TTL | F28: Componente TVIAT | G28: Aprovechamiento | H28: CCSA Prest.Aprov. | I28: Especiales | J28: Componente TCS | K28: Componente TLU | L28: Componente TBL | M28: Componente TRT | N28: CCSA Prest. No Aprov. | O28: Deb/Cred
B29: Vlr Servicio | C29: 0 | D29: 0 | E29: 0 | F29: 0 | G29: 0 | H29: 0 | I29: 0 | J29: 0 | K29: 0 | L29: 0 | M29: 0 | N29: 0 | O29: 0
B30: Vlr Intereses | C30: 0 | D30: 0 | E30: 0 | F30: 0 | G30: 0 | H30: 0 | I30: 0 | J30: 0 | K30: 0 | L30: 0 | M30: 0 | N30: 0 | O30: 0
A31: Componente | B31: Total | C31: 0 | D31: 0 | E31: 0 | F31: 0 | G31: 0 | H31: 0 | I31: 0 | J31: 0 | K31: 0 | L31: 0 | M31: 0 | N31: 0 | O31: 0
B32: Subsidio(-)/Contribucion(+) | C32: 0 | D32: 0 | E32: 0 | F32: 0 | G32: 0 | H32: 0 | I32: 0 | J32: 0 | K32: 0 | L32: 0 | M32: 0 | N32: 0 | O32: 0
A33: Subs/Cont | B33: Total | C33: 0 | D33: 0 | E33: 0 | F33: 0 | G33: 0 | H33: 0 | I33: 0 | J33: 0 | K33: 0 | L33: 0 | M33: 0 | N33: 0 | O33: 0
A34: Total | C34: 0 | D34: 0 | E34: 0 | F34: 0 | G34: 0 | H34: 0 | I34: 0 | J34: 0 | K34: 0 | L34: 0 | M34: 0 | N34: 0 | O34: 0
B36: Total | C36: =C34-I34 -> 0 | D36: =D31 -> 0 | E36: =E31 -> 0 | F36: =F31 -> 0 | G36: =G31 -> 0 | H36: =H31 -> 0 | I36: =I31 -> 0 | J36: =J31 -> 0 | K36: =K31 -> 0 | ... P36: =P31 -> 0
B37: Subsidio(-)/Contribucion(+) | C37: =C33 -> 0
B40: BOGOTA LIMPIA
C41: Total | D41: Componente TDF | E41: Componente TTL | F41: Componente TVIAT | G41: Aprovechamiento | H41: CCSA Prest.Aprov. | I41: Especiales | J41: Componente TCS | K41: Componente TLU | L41: Componente TBL | M41: Componente TRT | N41: CCSA Prest. No Aprov. | O41: Deb/Cred
B42: Vlr Servicio | C42: 0 | D42: 0 | E42: 0 | F42: 0 | G42: 0 | H42: 0 | I42: 0 | J42: 0 | K42: 0 | L42: 0 | M42: 0 | N42: 0 | O42: 0
B43: Vlr Intereses | C43: 0 | D43: 0 | E43: 0 | F43: 0 | G43: 0 | H43: 0 | I43: 0 | J43: 0 | K43: 0 | L43: 0 | M43: 0 | N43: 0 | O43: 0
A44: Componente | B44: Total | C44: 0 | D44: 0 | E44: 0 | F44: 0 | G44: 0 | H44: 0 | I44: 0 | J44: 0 | K44: 0 | L44: 0 | M44: 0 | N44: 0 | O44: 0
B45: Subsidio(-)/Contribucion(+) | C45: 0 | D45: 0 | E45: 0 | F45: 0 | G45: 0 | H45: 0 | I45: 0 | J45: 0 | K45: 0 | L45: 0 | M45: 0 | N45: 0 | O45: 0
A46: Subs/Cont | B46: Total | C46: 0 | D46: 0 | E46: 0 | F46: 0 | G46: 0 | H46: 0 | I46: 0 | J46: 0 | K46: 0 | L46: 0 | M46: 0 | N46: 0 | O46: 0
A47: Total | C47: 0 | D47: 0 | E47: 0 | F47: 0 | G47: 0 | H47: 0 | I47: 0 | J47: 0 | K47: 0 | L47: 0 | M47: 0 | N47: 0 | O47: 0
B49: Total | C49: =C47-I47 -> 0 | D49: =D44 -> 0 | E49: =E44 -> 0 | F49: =F44 -> 0 | G49: =G44 -> 0 | H49: =H44 -> 0 | I49: =I44 -> 0 | J49: =J44 -> 0 | K49: =K44 -> 0 | ... P49: =P44 -> 0
B50: Subsidio(-)/Contribucion(+) | C50: =C46 -> 0
B53: AREA LIMPIA
C54: Total | D54: Componente TDF | E54: Componente TTL | F54: Componente TVIAT | G54: Aprovechamiento | H54: CCSA Prest.Aprov. | I54: Especiales | J54: Componente TCS | K54: Componente TLU | L54: Componente TBL | M54: Componente TRT | N54: CCSA Prest. No Aprov. | O54: Deb/Cred
B55: Vlr Servicio | C55: 0 | D55: 0 | E55: 0 | F55: 0 | G55: 0 | H55: 0 | I55: 0 | J55: 0 | K55: 0 | L55: 0 | M55: 0 | N55: 0 | O55: 0
B56: Vlr Intereses | C56: 0 | D56: 0 | E56: 0 | F56: 0 | G56: 0 | H56: 0 | I56: 0 | J56: 0 | K56: 0 | L56: 0 | M56: 0 | N56: 0 | O56: 0
A57: Componente | B57: Total | C57: 0 | D57: 0 | E57: 0 | F57: 0 | G57: 0 | H57: 0 | I57: 0 | J57: 0 | K57: 0 | L57: 0 | M57: 0 | N57: 0 | O57: 0
B58: Subsidio(-)/Contribucion(+) | C58: 0 | D58: 0 | E58: 0 | F58: 0 | G58: 0 | H58: 0 | I58: 0 | J58: 0 | K58: 0 | L58: 0 | M58: 0 | N58: 0 | O58: 0
A59: Subs/Cont | B59: Total | C59: 0 | D59: 0 | E59: 0 | F59: 0 | G59: 0 | H59: 0 | I59: 0 | J59: 0 | K59: 0 | L59: 0 | M59: 0 | N59: 0 | O59: 0
A60: Total | C60: 0 | D60: 0 | E60: 0 | F60: 0 | G60: 0 | H60: 0 | I60: 0 | J60: 0 | K60: 0 | L60: 0 | M60: 0 | N60: 0 | O60: 0
B62: Total | C62: =C60-I60 -> 0 | D62: =D57 -> 0 | E62: =E57 -> 0 | F62: =F57 -> 0 | G62: =G57 -> 0 | H62: =H57 -> 0 | I62: =I57 -> 0 | J62: =J57 -> 0 | K62: =K57 -> 0 | ... P62: =P57 -> 0
B63: Subsidio(-)/Contribucion(+) | C63: =C59 -> 0

Sheet RETRIBUCION NEGATIVA
B1: PROMOAMBIENTAL
C2: Total | D2: Componente TDF | E2: Componente TTL | F2: Componente TVIAT | G2: Aprovechamiento | H2: CCSA Prest.Aprov. | I2: Especiales | J2: Componente TCS | K2: Componente TLU | L2: Componente TBL | M2: Componente TRT | N2: CCSA Prest. No Aprov. | O2: Deb/Cred
B3: Vlr Intereses | C3: 0 | D3: 0 | E3: 0 | F3: 0 | G3: 0 | H3: 0 | I3: 0 | J3: 0 | K3: 0 | L3: 0 | M3: 0 | N3: 0 | O3: 0
B4: Vlr Servicio | C4: 0 | D4: 0 | E4: 0 | F4: 0 | G4: 0 | H4: 0 | I4: 0 | J4: 0 | K4: 0 | L4: 0 | M4: 0 | N4: 0 | O4: 0
A5: Componente | B5: Total | C5: 0 | D5: 0 | E5: 0 | F5: 0 | G5: 0 | H5: 0 | I5: 0 | J5: 0 | K5: 0 | L5: 0 | M5: 0 | N5: 0 | O5: 0
B6: Subsidio(-)/Contribucion(+) | C6: 0 | D6: 0 | E6: 0 | F6: 0 | G6: 0 | H6: 0 | I6: 0 | J6: 0 | K6: 0 | L6: 0 | M6: 0 | N6: 0 | O6: 0
A7: Subs/Cont | B7: Total | C7: 0 | D7: 0 | E7: 0 | F7: 0 | G7: 0 | H7: 0 | I7: 0 | J7: 0 | K7: 0 | L7: 0 | M7: 0 | N7: 0 | O7: 0
A8: Total | C8: 0 | D8: 0 | E8: 0 | F8: 0 | G8: 0 | H8: 0 | I8: 0 | J8: 0 | K8: 0 | L8: 0 | M8: 0 | N8: 0 | O8: 0
B10: Total | C10: =C8-I8 -> 0 | D10: =D5 -> 0 | E10: =E5 -> 0 | F10: =F5 -> 0 | G10: =G5 -> 0 | H10: =H5 -> 0 | I10: =I5 -> 0 | J10: =J5 -> 0 | K10: =K5 -> 0 | ... O10: =O5 -> 0
B11: Subsidio(-)/Contribucion(+) | C11: =C7 -> 0
B14: LIME
C15: Total | D15: Componente TDF | E15: Componente TTL | F15: Componente TVIAT | G15: Aprovechamiento | H15: CCSA Prest.Aprov. | I15: Especiales | J15: Componente TCS | K15: Componente TLU | L15: Componente TBL | M15: Componente TRT | N15: CCSA Prest. No Aprov. | O15: Deb/Cred
B16: Vlr Intereses | C16: 0 | D16: 0 | E16: 0 | F16: 0 | G16: 0 | H16: 0 | I16: 0 | J16: 0 | K16: 0 | L16: 0 | M16: 0 | N16: 0 | O16: 0
B17: Vlr Servicio | C17: 0 | D17: 0 | E17: 0 | F17: 0 | G17: 0 | H17: 0 | I17: 0 | J17: 0 | K17: 0 | L17: 0 | M17: 0 | N17: 0 | O17: 0
A18: Componente | B18: Total | C18: 0 | D18: 0 | E18: 0 | F18: 0 | G18: 0 | H18: 0 | I18: 0 | J18: 0 | K18: 0 | L18: 0 | M18: 0 | N18: 0 | O18: 0
B19: Subsidio(-)/Contribucion(+) | C19: 0 | D19: 0 | E19: 0 | F19: 0 | G19: 0 | H19: 0 | I19: 0 | J19: 0 | K19: 0 | L19: 0 | M19: 0 | N19: 0 | O19: 0
A20: Subs/Cont | B20: Total | C20: 0 | D20: 0 | E20: 0 | F20: 0 | G20: 0 | H20: 0 | I20: 0 | J20: 0 | K20: 0 | L20: 0 | M20: 0 | N20: 0 | O20: 0
A21: Total | C21: 0 | D21: 0 | E21: 0 | F21: 0 | G21: 0 | H21: 0 | I21: 0 | J21: 0 | K21: 0 | L21: 0 | M21: 0 | N21: 0 | O21: 0
B23: Total | C23: =C21-I21 -> 0 | D23: =D18 -> 0 | E23: =E18 -> 0 | F23: =F18 -> 0 | G23: =G18 -> 0 | H23: =H18 -> 0 | I23: =I18 -> 0 | J23: =J18 -> 0 | K23: =K18 -> 0 | ... O23: =O18 -> 0
B24: Subsidio(-)/Contribucion(+) | C24: =C20 -> 0
B27: CIUDAD LIMPIA
C28: Total | D28: Componente TDF | E28: Componente TTL | F28: Componente TVIAT | G28: Aprovechamiento | H28: CCSA Prest.Aprov. | I28: Especiales | J28: Componente TCS | K28: Componente TLU | L28: Componente TBL | M28: Componente TRT | N28: CCSA Prest. No Aprov. | O28: Deb/Cred
B29: Vlr Intereses | C29: 0 | D29: 0 | E29: 0 | F29: 0 | G29: 0 | H29: 0 | I29: 0 | J29: 0 | K29: 0 | L29: 0 | M29: 0 | N29: 0 | O29: 0
B30: Vlr Servicio | C30: 0 | D30: 0 | E30: 0 | F30: 0 | G30: 0 | H30: 0 | I30: 0 | J30: 0 | K30: 0 | L30: 0 | M30: 0 | N30: 0 | O30: 0
A31: Componente | B31: Total | C31: 0 | D31: 0 | E31: 0 | F31: 0 | G31: 0 | H31: 0 | I31: 0 | J31: 0 | K31: 0 | L31: 0 | M31: 0 | N31: 0 | O31: 0
B32: Subsidio(-)/Contribucion(+) | C32: 0 | D32: 0 | E32: 0 | F32: 0 | G32: 0 | H32: 0 | I32: 0 | J32: 0 | K32: 0 | L32: 0 | M32: 0 | N32: 0 | O32: 0
A33: Subs/Cont | B33: Total | C33: 0 | D33: 0 | E33: 0 | F33: 0 | G33: 0 | H33: 0 | I33: 0 | J33: 0 | K33: 0 | L33: 0 | M33: 0 | N33: 0 | O33: 0
A34: Total | C34: 0 | D34: 0 | E34: 0 | F34: 0 | G34: 0 | H34: 0 | I34: 0 | J34: 0 | K34: 0 | L34: 0 | M34: 0 | N34: 0 | O34: 0
B36: Total | C36: =C34-I34 -> 0 | D36: =D31 -> 0 | E36: =E31 -> 0 | F36: =F31 -> 0 | G36: =G31 -> 0 | H36: =H31 -> 0 | I36: =I31 -> 0 | J36: =J31 -> 0 | K36: =K31 -> 0 | ... O36: =O31 -> 0
B37: Subsidio(-)/Contribucion(+) | C37: =C33 -> 0
B40: BOGOTA LIMPIA
C41: Total | D41: Componente TDF | E41: Componente TTL | F41: Componente TVIAT | G41: Aprovechamiento | H41: CCSA Prest.Aprov. | I41: Especiales | J41: Componente TCS | K41: Componente TLU | L41: Componente TBL | M41: Componente TRT | N41: CCSA Prest. No Aprov. | O41: Deb/Cred
B42: Vlr Intereses | C42: 0 | D42: 0 | E42: 0 | F42: 0 | G42: 0 | H42: 0 | I42: 0 | J42: 0 | K42: 0 | L42: 0 | M42: 0 | N42: 0 | O42: 0
B43: Vlr Servicio | C43: 0 | D43: 0 | E43: 0 | F43: 0 | G43: 0 | H43: 0 | I43: 0 | J43: 0 | K43: 0 | L43: 0 | M43: 0 | N43: 0 | O43: 0
A44: Componente | B44: Total | C44: 0 | D44: 0 | E44: 0 | F44: 0 | G44: 0 | H44: 0 | I44: 0 | J44: 0 | K44: 0 | L44: 0 | M44: 0 | N44: 0 | O44: 0
B45: Subsidio(-)/Contribucion(+) | C45: 0 | D45: 0 | E45: 0 | F45: 0 | G45: 0 | H45: 0 | I45: 0 | J45: 0 | K45: 0 | L45: 0 | M45: 0 | N45: 0 | O45: 0
A46: Subs/Cont | B46: Total | C46: 0 | D46: 0 | E46: 0 | F46: 0 | G46: 0 | H46: 0 | I46: 0 | J46: 0 | K46: 0 | L46: 0 | M46: 0 | N46: 0 | O46: 0
A47: Total | C47: 0 | D47: 0 | E47: 0 | F47: 0 | G47: 0 | H47: 0 | I47: 0 | J47: 0 | K47: 0 | L47: 0 | M47: 0 | N47: 0 | O47: 0
B49: Total | C49: =C47-I47 -> 0 | D49: =D44 -> 0 | E49: =E44 -> 0 | F49: =F44 -> 0 | G49: =G44 -> 0 | H49: =H44 -> 0 | I49: =I44 -> 0 | J49: =J44 -> 0 | K49: =K44 -> 0 | ... O49: =O44 -> 0
B50: Subsidio(-)/Contribucion(+) | C50: =C46 -> 0
B53: AREA LIMPIA
C54: Total | D54: Componente TDF | E54: Componente TTL | F54: Componente TVIAT | G54: Aprovechamiento | H54: CCSA Prest.Aprov. | I54: Especiales | J54: Componente TCS | K54: Componente TLU | L54: Componente TBL | M54: Componente TRT | N54: CCSA Prest. No Aprov. | O54: Deb/Cred
B55: Vlr Servicio | C55: 0 | D55: 0 | E55: 0 | F55: 0 | G55: 0 | H55: 0 | I55: 0 | J55: 0 | K55: 0 | L55: 0 | M55: 0 | N55: 0 | O55: 0
A56: Componente | B56: Total | C56: 0 | D56: 0 | E56: 0 | F56: 0 | G56: 0 | H56: 0 | I56: 0 | J56: 0 | K56: 0 | L56: 0 | M56: 0 | N56: 0 | O56: 0
B57: Subsidio(-)/Contribucion(+) | C57: 0 | D57: 0 | E57: 0 | F57: 0 | G57: 0 | H57: 0 | I57: 0 | J57: 0 | K57: 0 | L57: 0 | M57: 0 | N57: 0 | O57: 0
A58: Subs/Cont | B58: Total | C58: 0 | D58: 0 | E58: 0 | F58: 0 | G58: 0 | H58: 0 | I58: 0 | J58: 0 | K58: 0 | L58: 0 | M58: 0 | N58: 0 | O58: 0
A59: Total | C59: 0 | D59: 0 | E59: 0 | F59: 0 | G59: 0 | H59: 0 | I59: 0 | J59: 0 | K59: 0 | L59: 0 | M59: 0 | N59: 0 | O59: 0
B61: Total | C61: =C59-I59 -> 0 | D61: =D56 -> 0 | E61: =E56 -> 0 | F61: =F56 -> 0 | G61: =G56 -> 0 | H61: =H56 -> 0 | I61: =I56 -> 0 | J61: =J56 -> 0 | K61: =K56 -> 0 | ... O61: =O56 -> 0
B62: Subsidio(-)/Contribucion(+) | C62: =C58 -> 0

Sheet AJUSTES - SF-T
F3: PROCERASEO S.A.S. | I3: NIT: 901 153 639 - 0 | M3: Codigo Remuneración: | N3: ='CONSOLIDADO_TOTAL RECAUDO'!N3 -> 2026071 | U3: PROCERASEO S.A.S. | W3: NIT: 901 153 639 - 0 | AA3: Codigo Remuneración: | AC3: =N3 -> 2026071
F4: 3. ESQUEMA FINANCIERO DEL SERVICIO PUBLICO DE ASEO | U4: 3. ESQUEMA FINANCIERO DEL SERVICIO PUBLICO DE ASEO
F5: Resoluciòn UAESP Número 27 de 2018 | U5: Resoluciòn UAESP Número 27 de 2018
C6: Fecha de Proceso: | D6: ='CONSOLIDADO_TOTAL RECAUDO'!D6 -> 46220 | F6: SALDOS A FAVOR POR NOTA | U6: =+F6 -> SALDOS A FAVOR POR NOTA
C7: Hora: | D7: ='CONSOLIDADO_TOTAL RECAUDO'!D7 -> 0.58333333 | F7: Fecha Desde: | H7: ='CONSOLIDADO_TOTAL RECAUDO'!G7 -> 46204 | J7: Feha Hasta: | K7: ='CONSOLIDADO_TOTAL RECAUDO'!K7 -> 46218 | U7: =F7 -> Fecha Desde: | V7: =H7 -> 46204 | X7: =J7 -> Feha Hasta: | Y7: =K7 -> 46218
B8: ASE | C8: Concesionarios | D8: Recaudo Total | E8: Recaudo por disposicion final | F8: Recaudo por tratamiento de lixiviados | G8: Recaudo por Componente VIAT ( Decreto 2412/2018) | H8: Recaudo por aprovechamiento | I8: Recaudo del componente de comercializacion para Aprovechamiento (11,4%) | J8: Balance de subsidio o contribuciones | K8: RECAUDO BASE DE REMUNERACION | L8: Costo de la Interventoría | M8: REMUNERACION FINAL | N8: Conceptos especiales | O8: REMUNERACION FINAL MAS CONCEPTOS ESPECIALES | S8: ASE | T8: Concesionarios | U8: Tarifa de Comercialización del Servicio. ( TCS) | V8: Tarifa de Limpieza Urbana del Servicio. ( TLU) | W8: Tarifa de Barrido y Limpieza del Servicio. ( TBL) | X8: Tarifa de Recolección y Transporte del Servicio. (TRT) | Y8: Recaudo del componente de comercializacion para Aprovechamiento (18,6%) | Z8: Costo de la Interventoría | AA8: Ajuste a la decena | AB8: Conceptos especiales | AC8: Diferencial Balance S / C (Fac vs Rec) | AD8: Balance S / C Con Baase en (Recaudo) | AE8: REMUNERACION FINAL MAS CONCEPTOS ESPECIALES
B9: 1 | C9: PROMOAMBIENTAL DISTRITO S.A.S. ESP. | D9: ='SALDOS POR NOTA'!C10 -> 0 | E9: ='SALDOS POR NOTA'!D10 -> 0 | F9: ='SALDOS POR NOTA'!E10 -> 0 | G9: ='SALDOS POR NOTA'!F10 -> 0 | H9: ='SALDOS POR NOTA'!G10 -> 0 | I9: ='SALDOS POR NOTA'!H10 -> 0 | J9: 0 | K9: =D9-E9-F9-G9-H9-I9-J9 -> 0 | L9: 0 | M9: =K9-L9 -> 0 | N9: ='SALDOS POR NOTA'!I10 -> 0 | O9: =M9+N9 -> 0 | S9: 1 | T9: PROMOAMBIENTAL DISTRITO S.A.S. ESP. | U9: ='SALDOS POR NOTA'!J10 -> 0 | V9: ='SALDOS POR NOTA'!K10 -> 0 | W9: ='SALDOS POR NOTA'!L10 -> 0 | X9: ='SALDOS POR NOTA'!M10 -> 0 | Y9: ='SALDOS POR NOTA'!N10 -> 0 | Z9: =L9*-1 -> 0 | AA9: ='SALDOS POR NOTA'!O10 -> 0 | AB9: =N9 -> 0 | AC9: =-J9+AD9 -> 0 | AD9: ='SALDOS POR NOTA'!C11 -> 0 | AE9: =SUM(U9:AC9) -> 0 | AF9: =(AE9-O9) -> 0 | AG9: =AF9=0 -> TRUE
B10: 2 | C10: LIMPIEZA METROPOLITANA S.A. ESP. | D10: ='SALDOS POR NOTA'!C23 -> 0 | E10: ='SALDOS POR NOTA'!D23 -> 0 | F10: ='SALDOS POR NOTA'!E23 -> 0 | G10: ='SALDOS POR NOTA'!F23 -> 0 | H10: ='SALDOS POR NOTA'!G23 -> 0 | I10: ='SALDOS POR NOTA'!H23 -> 0 | J10: 0 | K10: =D10-E10-F10-G10-H10-I10-J10 -> 0 | L10: 0 | M10: =K10-L10 -> 0 | N10: ='SALDOS POR NOTA'!I23 -> 0 | O10: =M10+N10 -> 0 | S10: 2 | T10: LIMPIEZA METROPOLITANA S.A. ESP. | U10: ='SALDOS POR NOTA'!J23 -> 0 | V10: ='SALDOS POR NOTA'!K23 -> 0 | W10: ='SALDOS POR NOTA'!L23 -> 0 | X10: ='SALDOS POR NOTA'!M23 -> 0 | Y10: ='SALDOS POR NOTA'!N23 -> 0 | Z10: =L10*-1 -> 0 | AA10: ='SALDOS POR NOTA'!O23 -> 0 | AB10: =N10 -> 0 | AC10: =-J10+AD10 -> 0 | AD10: ='SALDOS POR NOTA'!C24 -> 0 | AE10: =SUM(U10:AC10) -> 0 | AF10: =(AE10-O10) -> 0 | AG10: =AF10=0 -> TRUE
B11: 3 | C11: CIUDAD LIMPIA BOGOTA S.A. ESP. | D11: ='SALDOS POR NOTA'!C36 -> 0 | E11: ='SALDOS POR NOTA'!D36 -> 0 | F11: ='SALDOS POR NOTA'!E36 -> 0 | G11: ='SALDOS POR NOTA'!F36 -> 0 | H11: ='SALDOS POR NOTA'!G36 -> 0 | I11: ='SALDOS POR NOTA'!H36 -> 0 | J11: 0 | K11: =D11-E11-F11-G11-H11-I11-J11 -> 0 | L11: 0 | M11: =K11-L11 -> 0 | N11: ='SALDOS POR NOTA'!I36 -> 0 | O11: =M11+N11 -> 0 | S11: 3 | T11: CIUDAD LIMPIA BOGOTA S.A. ESP. | U11: ='SALDOS POR NOTA'!J36 -> 0 | V11: ='SALDOS POR NOTA'!K36 -> 0 | W11: ='SALDOS POR NOTA'!L36 -> 0 | X11: ='SALDOS POR NOTA'!M36 -> 0 | Y11: ='SALDOS POR NOTA'!N36 -> 0 | Z11: =L11*-1 -> 0 | AA11: ='SALDOS POR NOTA'!O36 -> 0 | AB11: =N11 -> 0 | AC11: =-J11+AD11 -> 0 | AD11: ='SALDOS POR NOTA'!C37 -> 0 | AE11: =SUM(U11:AC11) -> 0 | AF11: =(AE11-O11) -> 0 | AG11: =AF11=0 -> TRUE
B12: 4 | C12: BOGOTA LIMPIA S.A.S. ESP. | D12: ='SALDOS POR NOTA'!C49 -> 0 | E12: ='SALDOS POR NOTA'!D49 -> 0 | F12: ='SALDOS POR NOTA'!E49 -> 0 | G12: ='SALDOS POR NOTA'!F49 -> 0 | H12: ='SALDOS POR NOTA'!G49 -> 0 | I12: ='SALDOS POR NOTA'!H49 -> 0 | J12: 0 | K12: =D12-E12-F12-G12-H12-I12-J12 -> 0 | L12: 0 | M12: =K12-L12 -> 0 | N12: ='SALDOS POR NOTA'!I49 -> 0 | O12: =M12+N12 -> 0 | S12: 4 | T12: BOGOTA LIMPIA S.A.S. ESP. | U12: ='SALDOS POR NOTA'!J49 -> 0 | V12: ='SALDOS POR NOTA'!K49 -> 0 | W12: ='SALDOS POR NOTA'!L49 -> 0 | X12: ='SALDOS POR NOTA'!M49 -> 0 | Y12: ='SALDOS POR NOTA'!N49 -> 0 | Z12: =L12*-1 -> 0 | AA12: ='SALDOS POR NOTA'!O49 -> 0 | AB12: =N12 -> 0 | AC12: =-J12+AD12 -> 0 | AD12: ='SALDOS POR NOTA'!C50 -> 0 | AE12: =SUM(U12:AC12) -> 0 | AF12: =(AE12-O12) -> 0 | AG12: =AF12=0 -> TRUE
B13: 5 | C13: AREA LIMPIA DISTRITO CAPITAL S.A.S. ESP. | D13: ='SALDOS POR NOTA'!C62 -> 0 | E13: ='SALDOS POR NOTA'!D62 -> 0 | F13: ='SALDOS POR NOTA'!E62 -> 0 | G13: ='SALDOS POR NOTA'!F62 -> 0 | H13: ='SALDOS POR NOTA'!G62 -> 0 | I13: ='SALDOS POR NOTA'!H62 -> 0 | J13: 0 | K13: =D13-E13-F13-G13-H13-I13-J13 -> 0 | L13: 0 | M13: =K13-L13 -> 0 | N13: ='SALDOS POR NOTA'!I62 -> 0 | O13: =M13+N13 -> 0 | S13: 5 | T13: AREA LIMPIA DISTRITO CAPITAL S.A.S. ESP. | U13: ='SALDOS POR NOTA'!J62 -> 0 | V13: ='SALDOS POR NOTA'!K62 -> 0 | W13: ='SALDOS POR NOTA'!L62 -> 0 | X13: ='SALDOS POR NOTA'!M62 -> 0 | Y13: ='SALDOS POR NOTA'!N62 -> 0 | Z13: =L13*-1 -> 0 | AA13: ='SALDOS POR NOTA'!O62 -> 0 | AB13: =N13 -> 0 | AC13: =-J13+AD13 -> 0 | AD13: ='SALDOS POR NOTA'!C63 -> 0 | AE13: =SUM(U13:AC13) -> 0 | AF13: =(AE13-O13) -> 0 | AG13: =AF13=0 -> TRUE
C14: TOTAL | D14: =SUM(D9:D13) -> 0 | E14: =SUM(E9:E13) -> 0 | F14: =SUM(F9:F13) -> 0 | G14: =SUM(G9:G13) -> 0 | H14: =SUM(H9:H13) -> 0 | I14: =SUM(I9:I13) -> 0 | J14: =SUM(J9:J13) -> 0 | K14: =SUM(K9:K13) -> 0 | ... O14: =SUM(O9:O13) -> 0 | T14: TOTAL | U14: =SUM(U9:U13) -> 0 | V14: =SUM(V9:V13) -> 0 | W14: =SUM(W9:W13) -> 0 | X14: =SUM(X9:X13) -> 0 | Y14: =SUM(Y9:Y13) -> 0 | Z14: =SUM(Z9:Z13) -> 0 | AA14: =SUM(AA9:AA13) -> 0 | AB14: =SUM(AB9:AB13) -> 0 | ... AF14: =SUM(AF9:AF13) -> 0 | AG14: =AF14=0 -> TRUE
Y16: =SUM(U14:Y14) -> 0
F18: Firma autorizada
F22: PROCERASEO S.A.S. | I22: NIT: 901 153 639 - 0 | M22: Codigo Remuneración: | N22: =N3 -> 2026071 | U22: PROCERASEO S.A.S. | W22: NIT: 901 153 639 - 0 | AA22: Codigo Remuneración: | AC22: =N22 -> 2026071
F23: 3. ESQUEMA FINANCIERO DEL SERVICIO PUBLICO DE ASEO | U23: 3. ESQUEMA FINANCIERO DEL SERVICIO PUBLICO DE ASEO
F24: Resoluciòn UAESP Número 27 de 2018 | U24: Resoluciòn UAESP Número 27 de 2018
C25: Fecha de Proceso: | D25: =D6 -> 46220 | F25: RETRIBUCION NEGATIVA | U25: =+F25 -> RETRIBUCION NEGATIVA
C26: Hora: | D26: =D7 -> 0.58333333 | F26: Fecha Desde: | H26: =H7 -> 46204 | J26: Feha Hasta: | K26: =K7 -> 46218 | U26: =F26 -> Fecha Desde: | V26: =H26 -> 46204 | X26: =J26 -> Feha Hasta: | Y26: =K26 -> 46218
B27: ASE | C27: Concesionarios | D27: Recaudo Total | E27: Recaudo por disposicion final | F27: Recaudo por tratamiento de lixiviados | G27: Recaudo por Componente VIAT ( Decreto 2412/2018) | H27: Recaudo por aprovechamiento | I27: Recaudo del componente de comercializacion para Aprovechamiento (11,4%) | J27: Balance de subsidio o contribuciones | K27: RECAUDO BASE DE REMUNERACION | L27: Costo de la Interventoría | M27: REMUNERACION FINAL | N27: Conceptos especiales | O27: REMUNERACION FINAL MAS CONCEPTOS ESPECIALES | S27: ASE | T27: Concesionarios | U27: Tarifa de Comercialización del Servicio. ( TCS) | V27: Tarifa de Limpieza Urbana del Servicio. ( TLU) | W27: Tarifa de Barrido y Limpieza del Servicio. ( TBL) | X27: Tarifa de Recolección y Transporte del Servicio. (TRT) | Y27: Recaudo del componente de comercializacion para Aprovechamiento (18,6%) | Z27: Costo de la Interventoría | AA27: Ajuste a la decena | AB27: Conceptos especiales | AC27: Diferencial Balance S / C (Fac vs Rec) | AD27: Balance S / C Con Baase en (Recaudo) | AE27: REMUNERACION FINAL MAS CONCEPTOS ESPECIALES
B28: 1 | C28: PROMOAMBIENTAL DISTRITO S.A.S. ESP. | D28: ='RETRIBUCION NEGATIVA'!C10 -> 0 | E28: ='RETRIBUCION NEGATIVA'!D10 -> 0 | F28: ='RETRIBUCION NEGATIVA'!E10 -> 0 | G28: ='RETRIBUCION NEGATIVA'!F10 -> 0 | H28: ='RETRIBUCION NEGATIVA'!G10 -> 0 | I28: ='RETRIBUCION NEGATIVA'!H10 -> 0 | J28: 0 | K28: =D28-E28-F28-H28-I28-J28-G28 -> 0 | L28: 0 | M28: =K28-L28 -> 0 | N28: ='RETRIBUCION NEGATIVA'!I10 -> 0 | O28: =M28+N28 -> 0 | S28: 1 | T28: PROMOAMBIENTAL DISTRITO S.A.S. ESP. | U28: ='RETRIBUCION NEGATIVA'!J10 -> 0 | V28: ='RETRIBUCION NEGATIVA'!K10 -> 0 | W28: ='RETRIBUCION NEGATIVA'!L10 -> 0 | X28: ='RETRIBUCION NEGATIVA'!M10 -> 0 | Y28: ='RETRIBUCION NEGATIVA'!N10 -> 0 | Z28: =L28*-1 -> 0 | AA28: ='RETRIBUCION NEGATIVA'!O10 -> 0 | AB28: =N28 -> 0 | AC28: =-J28+AD28 -> 0 | AD28: ='RETRIBUCION NEGATIVA'!C11 -> 0 | AE28: =SUM(U28:AC28) -> 0 | AF28: =(AE28-O28) -> 0 | AG28: =AF28=0 -> TRUE
B29: 2 | C29: LIMPIEZA METROPOLITANA S.A. ESP. | D29: ='RETRIBUCION NEGATIVA'!C23 -> 0 | E29: ='RETRIBUCION NEGATIVA'!D23 -> 0 | F29: ='RETRIBUCION NEGATIVA'!E23 -> 0 | G29: ='RETRIBUCION NEGATIVA'!F23 -> 0 | H29: ='RETRIBUCION NEGATIVA'!G23 -> 0 | I29: ='RETRIBUCION NEGATIVA'!H23 -> 0 | J29: 0 | K29: =D29-E29-F29-H29-I29-J29-G29 -> 0 | L29: 0 | M29: =K29-L29 -> 0 | N29: ='RETRIBUCION NEGATIVA'!I23 -> 0 | O29: =M29+N29 -> 0 | S29: 2 | T29: LIMPIEZA METROPOLITANA S.A. ESP. | U29: ='RETRIBUCION NEGATIVA'!J23 -> 0 | V29: ='RETRIBUCION NEGATIVA'!K23 -> 0 | W29: ='RETRIBUCION NEGATIVA'!L23 -> 0 | X29: ='RETRIBUCION NEGATIVA'!M23 -> 0 | Y29: ='RETRIBUCION NEGATIVA'!N23 -> 0 | Z29: =L29*-1 -> 0 | AA29: ='RETRIBUCION NEGATIVA'!O23 -> 0 | AB29: =N29 -> 0 | AC29: =-J29+AD29 -> 0 | AD29: ='RETRIBUCION NEGATIVA'!C24 -> 0 | AE29: =SUM(U29:AC29) -> 0 | AF29: =(AE29-O29) -> 0 | AG29: =AF29=0 -> TRUE
B30: 3 | C30: CIUDAD LIMPIA BOGOTA S.A. ESP. | D30: ='RETRIBUCION NEGATIVA'!C36 -> 0 | E30: ='RETRIBUCION NEGATIVA'!D36 -> 0 | F30: ='RETRIBUCION NEGATIVA'!E36 -> 0 | G30: ='RETRIBUCION NEGATIVA'!F36 -> 0 | H30: ='RETRIBUCION NEGATIVA'!G36 -> 0 | I30: ='RETRIBUCION NEGATIVA'!H36 -> 0 | J30: 0 | K30: =D30-E30-F30-H30-I30-J30-G30 -> 0 | L30: 0 | M30: =K30-L30 -> 0 | N30: ='RETRIBUCION NEGATIVA'!I36 -> 0 | O30: =M30+N30 -> 0 | S30: 3 | T30: CIUDAD LIMPIA BOGOTA S.A. ESP. | U30: ='RETRIBUCION NEGATIVA'!J36 -> 0 | V30: ='RETRIBUCION NEGATIVA'!K36 -> 0 | W30: ='RETRIBUCION NEGATIVA'!L36 -> 0 | X30: ='RETRIBUCION NEGATIVA'!M36 -> 0 | Y30: ='RETRIBUCION NEGATIVA'!N36 -> 0 | Z30: =L30*-1 -> 0 | AA30: ='RETRIBUCION NEGATIVA'!O36 -> 0 | AB30: =N30 -> 0 | AC30: =-J30+AD30 -> 0 | AD30: ='RETRIBUCION NEGATIVA'!C37 -> 0 | AE30: =SUM(U30:AC30) -> 0 | AF30: =(AE30-O30) -> 0 | AG30: =AF30=0 -> TRUE
B31: 4 | C31: BOGOTA LIMPIA S.A.S. ESP. | D31: ='RETRIBUCION NEGATIVA'!C49 -> 0 | E31: ='RETRIBUCION NEGATIVA'!D49 -> 0 | F31: ='RETRIBUCION NEGATIVA'!E49 -> 0 | G31: ='RETRIBUCION NEGATIVA'!F49 -> 0 | H31: ='RETRIBUCION NEGATIVA'!G49 -> 0 | I31: ='RETRIBUCION NEGATIVA'!H49 -> 0 | J31: 0 | K31: =D31-E31-F31-H31-I31-J31-G31 -> 0 | L31: 0 | M31: =K31-L31 -> 0 | N31: ='RETRIBUCION NEGATIVA'!I49 -> 0 | O31: =M31+N31 -> 0 | S31: 4 | T31: BOGOTA LIMPIA S.A.S. ESP. | U31: ='RETRIBUCION NEGATIVA'!J49 -> 0 | V31: ='RETRIBUCION NEGATIVA'!K49 -> 0 | W31: ='RETRIBUCION NEGATIVA'!L49 -> 0 | X31: ='RETRIBUCION NEGATIVA'!M49 -> 0 | Y31: ='RETRIBUCION NEGATIVA'!N49 -> 0 | Z31: =L31*-1 -> 0 | AA31: ='RETRIBUCION NEGATIVA'!O49 -> 0 | AB31: =N31 -> 0 | AC31: =-J31+AD31 -> 0 | AD31: ='RETRIBUCION NEGATIVA'!C50 -> 0 | AE31: =SUM(U31:AC31) -> 0 | AF31: =(AE31-O31) -> 0 | AG31: =AF31=0 -> TRUE
B32: 5 | C32: AREA LIMPIA DISTRITO CAPITAL S.A.S. ESP. | D32: ='RETRIBUCION NEGATIVA'!C61 -> 0 | E32: ='RETRIBUCION NEGATIVA'!D61 -> 0 | F32: ='RETRIBUCION NEGATIVA'!E61 -> 0 | G32: ='RETRIBUCION NEGATIVA'!F61 -> 0 | H32: ='RETRIBUCION NEGATIVA'!G61 -> 0 | I32: ='RETRIBUCION NEGATIVA'!H61 -> 0 | J32: 0 | K32: =D32-E32-F32-H32-I32-J32-G32 -> 0 | L32: 0 | M32: =K32-L32 -> 0 | N32: ='RETRIBUCION NEGATIVA'!I61 -> 0 | O32: =M32+N32 -> 0 | S32: 5 | T32: AREA LIMPIA DISTRITO CAPITAL S.A.S. ESP. | U32: ='RETRIBUCION NEGATIVA'!J61 -> 0 | V32: ='RETRIBUCION NEGATIVA'!K61 -> 0 | W32: ='RETRIBUCION NEGATIVA'!L61 -> 0 | X32: ='RETRIBUCION NEGATIVA'!M61 -> 0 | Y32: ='RETRIBUCION NEGATIVA'!N61 -> 0 | Z32: =L32*-1 -> 0 | AA32: ='RETRIBUCION NEGATIVA'!O61 -> 0 | AB32: =N32 -> 0 | AC32: =-J32+AD32 -> 0 | AD32: ='RETRIBUCION NEGATIVA'!C62 -> 0 | AE32: =SUM(U32:AC32) -> 0 | AF32: =(AE32-O32) -> 0 | AG32: =AF32=0 -> TRUE
C33: TOTAL | D33: =SUM(D28:D32) -> 0 | E33: =SUM(E28:E32) -> 0 | F33: =SUM(F28:F32) -> 0 | G33: =SUM(G28:G32) -> 0 | H33: =SUM(H28:H32) -> 0 | I33: =SUM(I28:I32) -> 0 | J33: =SUM(J28:J32) -> 0 | K33: =SUM(K28:K32) -> 0 | ... O33: =SUM(O28:O32) -> 0 | T33: TOTAL | U33: =SUM(U28:U32) -> 0 | V33: =SUM(V28:V32) -> 0 | W33: =SUM(W28:W32) -> 0 | X33: =SUM(X28:X32) -> 0 | Y33: =SUM(Y28:Y32) -> 0 | Z33: =SUM(Z28:Z32) -> 0 | AA33: =SUM(AA28:AA32) -> 0 | AB33: =SUM(AB28:AB32) -> 0 | ... AF33: =SUM(AF28:AF32) -> 0 | AG33: =AF33=0 -> TRUE
J35: VALIDADOR DE POSTIVIOS EN REMUNERACION NEGATIVA | M35: =IF(MAX(D28:O32,U28:AE32)>0.9,"ERROR",TRUE) -> TRUE | Y35: =SUM(U33:Y33) -> 0
F37: Firma autorizada
F41: PROCERASEO S.A.S. | I41: NIT: 901 153 639 - 0 | M41: Codigo Remuneración: | N41: =N3 -> 2026071 | U41: PROCERASEO S.A.S. | W41: NIT: 901 153 639 - 0 | AA41: Codigo Remuneración: | AC41: =N41 -> 2026071
F42: 3. ESQUEMA FINANCIERO DEL SERVICIO PUBLICO DE ASEO | U42: 3. ESQUEMA FINANCIERO DEL SERVICIO PUBLICO DE ASEO
F43: Resoluciòn UAESP Número 27 de 2018 | U43: Resoluciòn UAESP Número 27 de 2018
C44: Fecha de Proceso: | D44: =D6 -> 46220 | F44: CONSOLIDADO SALDOS A FAVOR | U44: =+F44 -> CONSOLIDADO SALDOS A FAVOR
C45: Hora: | D45: =D7 -> 0.58333333 | F45: Fecha Desde: | H45: =H7 -> 46204 | J45: Feha Hasta: | K45: =K7 -> 46218 | U45: =F45 -> Fecha Desde: | V45: =H45 -> 46204 | X45: =J45 -> Feha Hasta: | Y45: =K45 -> 46218
B46: ASE | C46: Concesionarios | D46: Recaudo Total | E46: Recaudo por disposicion final | F46: Recaudo por tratamiento de lixiviados | G46: Recaudo por Componente VIAT ( Decreto 2412/2018) | H46: Recaudo por aprovechamiento | I46: Recaudo del componente de comercializacion para Aprovechamiento (11,4%) | J46: Balance de subsidio o contribuciones | K46: RECAUDO BASE DE REMUNERACION | L46: Costo de la Interventoría | M46: REMUNERACION FINAL | N46: Conceptos especiales | O46: REMUNERACION FINAL MAS CONCEPTOS ESPECIALES | S46: ASE | T46: Concesionarios | U46: Tarifa de Comercialización del Servicio. ( TCS) | V46: Tarifa de Limpieza Urbana del Servicio. ( TLU) | W46: Tarifa de Barrido y Limpieza del Servicio. ( TBL) | X46: Tarifa de Recolección y Transporte del Servicio. (TRT) | Y46: Recaudo del componente de comercializacion para Aprovechamiento (18,6%) | Z46: Costo de la Interventoría | AA46: Ajuste a la decena | AB46: Conceptos especiales | AC46: Diferencial Balance S / C (Fac vs Rec) | AD46: Balance S / C Con Baase en (Recaudo) | AE46: REMUNERACION FINAL MAS CONCEPTOS ESPECIALES
B47: 1 | C47: PROMOAMBIENTAL DISTRITO S.A.S. ESP. | D47: =D9+D28 -> 0 | E47: =E9+E28 -> 0 | F47: =F9+F28 -> 0 | G47: =G9+G28 -> 0 | H47: =H9+H28 -> 0 | I47: =I9+I28 -> 0 | J47: =J9+J28 -> 0 | K47: =D47-E47-F47-G47-H47-I47-J47 -> 0 | L47: 0 | M47: =K47-L47 -> 0 | N47: =N9+N28 -> 0 | O47: =M47+N47 -> 0 | S47: 1 | T47: PROMOAMBIENTAL DISTRITO S.A.S. ESP. | U47: =U9+U28 -> 0 | V47: =V9+V28 -> 0 | W47: =W9+W28 -> 0 | X47: =X9+X28 -> 0 | Y47: =Y9+Y28 -> 0 | Z47: =-L47 -> 0 | AA47: =AA9+AA28 -> 0 | AB47: =AB9+AB28 -> 0 | AC47: =AC9+AC28 -> 0 | AD47: =AD9+AD28 -> 0 | AE47: =SUM(U47:AC47) -> 0 | AF47: =(AE47-O47) -> 0 | AG47: =AF47=0 -> TRUE
B48: 2 | C48: LIMPIEZA METROPOLITANA S.A. ESP. | D48: =D10+D29 -> 0 | E48: =E10+E29 -> 0 | F48: =F10+F29 -> 0 | G48: =G10+G29 -> 0 | H48: =H10+H29 -> 0 | I48: =I10+I29 -> 0 | J48: =J10+J29 -> 0 | K48: =D48-E48-F48-G48-H48-I48-J48 -> 0 | L48: 0 | M48: =K48-L48 -> 0 | N48: =N10+N29 -> 0 | O48: =M48+N48 -> 0 | S48: 2 | T48: LIMPIEZA METROPOLITANA S.A. ESP. | U48: =U10+U29 -> 0 | V48: =V10+V29 -> 0 | W48: =W10+W29 -> 0 | X48: =X10+X29 -> 0 | Y48: =Y10+Y29 -> 0 | Z48: =-L48 -> 0 | AA48: =AA10+AA29 -> 0 | AB48: =AB10+AB29 -> 0 | AC48: =AC10+AC29 -> 0 | AD48: =AD10+AD29 -> 0 | AE48: =SUM(U48:AC48) -> 0 | AF48: =(AE48-O48) -> 0 | AG48: =AF48=0 -> TRUE
B49: 3 | C49: CIUDAD LIMPIA BOGOTA S.A. ESP. | D49: =D11+D30 -> 0 | E49: =E11+E30 -> 0 | F49: =F11+F30 -> 0 | G49: =G11+G30 -> 0 | H49: =H11+H30 -> 0 | I49: =I11+I30 -> 0 | J49: =J11+J30 -> 0 | K49: =D49-E49-F49-G49-H49-I49-J49 -> 0 | L49: 0 | M49: =K49-L49 -> 0 | N49: =N11+N30 -> 0 | O49: =M49+N49 -> 0 | S49: 3 | T49: CIUDAD LIMPIA BOGOTA S.A. ESP. | U49: =U11+U30 -> 0 | V49: =V11+V30 -> 0 | W49: =W11+W30 -> 0 | X49: =X11+X30 -> 0 | Y49: =Y11+Y30 -> 0 | Z49: =-L49 -> 0 | AA49: =AA11+AA30 -> 0 | AB49: =AB11+AB30 -> 0 | AC49: =AC11+AC30 -> 0 | AD49: =AD11+AD30 -> 0 | AE49: =SUM(U49:AC49) -> 0 | AF49: =(AE49-O49) -> 0 | AG49: =AF49=0 -> TRUE
B50: 4 | C50: BOGOTA LIMPIA S.A.S. ESP. | D50: =D12+D31 -> 0 | E50: =E12+E31 -> 0 | F50: =F12+F31 -> 0 | G50: =G12+G31 -> 0 | H50: =H12+H31 -> 0 | I50: =I12+I31 -> 0 | J50: =J12+J31 -> 0 | K50: =D50-E50-F50-G50-H50-I50-J50 -> 0 | L50: 0 | M50: =K50-L50 -> 0 | N50: =N12+N31 -> 0 | O50: =M50+N50 -> 0 | S50: 4 | T50: BOGOTA LIMPIA S.A.S. ESP. | U50: =U12+U31 -> 0 | V50: =V12+V31 -> 0 | W50: =W12+W31 -> 0 | X50: =X12+X31 -> 0 | Y50: =Y12+Y31 -> 0 | Z50: =-L50 -> 0 | AA50: =AA12+AA31 -> 0 | AB50: =AB12+AB31 -> 0 | AC50: =AC12+AC31 -> 0 | AD50: =AD12+AD31 -> 0 | AE50: =SUM(U50:AC50) -> 0 | AF50: =(AE50-O50) -> 0 | AG50: =AF50=0 -> TRUE
B51: 5 | C51: AREA LIMPIA DISTRITO CAPITAL S.A.S. ESP. | D51: =D13+D32 -> 0 | E51: =E13+E32 -> 0 | F51: =F13+F32 -> 0 | G51: =G13+G32 -> 0 | H51: =H13+H32 -> 0 | I51: =I13+I32 -> 0 | J51: =J13+J32 -> 0 | K51: =D51-E51-F51-G51-H51-I51-J51 -> 0 | L51: 0 | M51: =K51-L51 -> 0 | N51: =N13+N32 -> 0 | O51: =M51+N51 -> 0 | S51: 5 | T51: AREA LIMPIA DISTRITO CAPITAL S.A.S. ESP. | U51: =U13+U32 -> 0 | V51: =V13+V32 -> 0 | W51: =W13+W32 -> 0 | X51: =X13+X32 -> 0 | Y51: =Y13+Y32 -> 0 | Z51: =-L51 -> 0 | AA51: =AA13+AA32 -> 0 | AB51: =AB13+AB32 -> 0 | AC51: =AC13+AC32 -> 0 | AD51: =AD13+AD32 -> 0 | AE51: =SUM(U51:AC51) -> 0 | AF51: =(AE51-O51) -> 0 | AG51: =AF51=0 -> TRUE
C52: TOTAL | D52: =SUM(D47:D51) -> 0 | E52: =SUM(E47:E51) -> 0 | F52: =SUM(F47:F51) -> 0 | G52: =SUM(G47:G51) -> 0 | H52: =SUM(H47:H51) -> 0 | I52: =SUM(I47:I51) -> 0 | J52: =SUM(J47:J51) -> 0 | K52: =SUM(K47:K51) -> 0 | ... O52: =SUM(O47:O51) -> 0 | T52: TOTAL | U52: =SUM(U47:U51) -> 0 | V52: =SUM(V47:V51) -> 0 | W52: =SUM(W47:W51) -> 0 | X52: =SUM(X47:X51) -> 0 | Y52: =SUM(Y47:Y51) -> 0 | Z52: =SUM(Z47:Z51) -> 0 | AA52: =SUM(AA47:AA51) -> 0 | AB52: =SUM(AB47:AB51) -> 0 | ... AF52: =SUM(AF47:AF51) -> 0 | AG52: =AF52=0 -> TRUE
Y54: =SUM(U52:Y52) -> 0
F56: Firma autorizada

Sheet INTERVENTORIA
F2: 2026 01 2 | G2: 2026 02 1 | H2: 2026 02 2 | I2: 2026 03 1 | J2: 2026 03 2 | K2: 2026 04 1 | L2: 2026 04 2 | M2: 2026 05 1 | N2: 2026 05 2 | O2: 2026 06 1 | P2: 2026 06 2 | Q2: 2026 07 1
B3: VALOR MES | C3: ASE | D3: Concesionarios | E3: % | F3: MITAD 1 // ENERO -26 | G3: MITAD 2 // ENERO -26 | H3: MITAD 1 // FEBRERO -26 | I3: MITAD 2 // FEBRERO -26 | J3: MITAD 1 // MARZO -26 | K3: MITAD 2 // MARZO -26 | L3: MITAD 1 // ABRIL -26 | M3: MITAD 2 // ABRIL -26 | N3: MITAD 1 // MAYO -26 | O3: MITAD 2 // MAYO -26 | P3: MITAD 1 // JUNIO -26 | Q3: MITAD 2 // JUNIO -26
B4: 378371975 | C4: 1 | D4: PROMOAMBIENTAL DISTRITO S.A.S. ESP. | E4: 0.22 | F4: 189185988 | G4: 189185987 | H4: 189185988 | I4: 189185987 | J4: 189185988 | K4: 189185987 | L4: 189185988 | M4: 189185987 | N4: 189185988 | O4: 189185987 | P4: 189185988 | Q4: 189185987
B5: 533160511 | C5: 2 | D5: LIMPIEZA METROPOLITANA S.A. ESP. | E5: 0.31 | F5: 266580256 | G5: 266580255 | H5: 266580256 | I5: 266580255 | J5: 266580256 | K5: 266580255 | L5: 266580256 | M5: 266580255 | N5: 266580256 | O5: 266580255 | P5: 266580256 | Q5: 266580255
B6: 309577071 | C6: 3 | D6: CIUDAD LIMPIA BOGOTA S.A. ESP. | E6: 0.18 | F6: 154788536 | G6: 154788535 | H6: 154788536 | I6: 154788535 | J6: 154788536 | K6: 154788535 | L6: 154788536 | M6: 154788535 | N6: 154788536 | O6: 154788535 | P6: 154788536 | Q6: 154788535
B7: 240782166 | C7: 4 | D7: BOGOTA LIMPIA S.A.S. ESP. | E7: 0.14 | F7: 120391083 | G7: 120391083 | H7: 120391083 | I7: 120391083 | J7: 120391083 | K7: 120391083 | L7: 120391083 | M7: 120391083 | N7: 120391083 | O7: 120391083 | P7: 120391083 | Q7: 120391083
B8: 257980891 | C8: 5 | D8: AREA LIMPIA DISTRITO CAPITAL S.A.S. ESP. | E8: 0.15 | F8: 128990446 | G8: 128990445 | H8: 128990446 | I8: 128990445 | J8: 128990446 | K8: 128990445 | L8: 128990446 | M8: 128990445 | N8: 128990446 | O8: 128990445 | P8: 128990446 | Q8: 128990445
B9: 1719872614 | D9: TOTAL | E9: 1 | F9: 859936309 | G9: 859936305 | H9: 859936309 | I9: 859936305 | J9: 859936309 | K9: 859936305 | L9: 859936309 | M9: 859936305 | N9: 859936309 | O9: 859936305 | P9: 859936309 | Q9: 859936305
F10: =SUM(F9:G9) -> 1719872614 | H10: =SUM(H9:I9) -> 1719872614 | J10: =SUM(J9:K9) -> 1719872614 | L10: =SUM(L9:M9) -> 1719872614 | N10: =SUM(N9:O9) -> 1719872614 | P10: =SUM(P9:Q9) -> 1719872614
F13: 2026 07 2 | G13: 2026 08 1 | H13: 2026 08 2 | I13: 2026 09 1 | J13: 2026 09 2 | K13: 2026 10 1 | L13: 2026 10 2 | M13: 2026 11 1 | N13: 2026 11 2 | O13: 2026 12 1 | P13: 2026 12 2 | Q13: 2027 01 1
C14: ASE | D14: Concesionarios | E14: % | F14: MITAD 1 // JULIO -26 | G14: MITAD 2 // JULIO -26 | H14: MITAD 1 // AGOSTO -26 | I14: MITAD 2 // AGOSTO -26 | J14: MITAD 1 // SEPTIEMBRE -26 | K14: MITAD 2 // SEPTIEMBRE -26 | L14: MITAD 1 // OCTUBRE -26 | M14: MITAD 2 // OCTUBRE -26 | N14: MITAD 1 // NOVIEMBRE -26 | O14: MITAD 2 // NOVIEMBRE -26 | P14: MITAD 1 // DICIEMBRE -26 | Q14: MITAD 2 // DICIEMBRE -26
C15: 1 | D15: PROMOAMBIENTAL DISTRITO S.A.S. ESP. | E15: 0.22 | F15: 189185988 | G15: 189185987 | H15: 189185988 | I15: 189185987 | J15: 189185988 | K15: 189185987 | L15: 189185988 | M15: 189185987 | N15: 189185988 | O15: 189185987 | P15: 189185988 | Q15: 189185987
C16: 2 | D16: LIMPIEZA METROPOLITANA S.A. ESP. | E16: 0.31 | F16: 266580256 | G16: 266580255 | H16: 266580256 | I16: 266580255 | J16: 266580256 | K16: 266580255 | L16: 266580256 | M16: 266580255 | N16: 266580256 | O16: 266580255 | P16: 266580256 | Q16: 266580255
C17: 3 | D17: CIUDAD LIMPIA BOGOTA S.A. ESP. | E17: 0.18 | F17: 154788536 | G17: 154788535 | H17: 154788536 | I17: 154788535 | J17: 154788536 | K17: 154788535 | L17: 154788536 | M17: 154788535 | N17: 154788536 | O17: 154788535 | P17: 154788536 | Q17: 154788535
C18: 4 | D18: BOGOTA LIMPIA S.A.S. ESP. | E18: 0.14 | F18: 120391083 | G18: 120391083 | H18: 120391083 | I18: 120391083 | J18: 120391083 | K18: 120391083 | L18: 120391083 | M18: 120391083 | N18: 120391083 | O18: 120391083 | P18: 120391083 | Q18: 120391083
C19: 5 | D19: AREA LIMPIA DISTRITO CAPITAL S.A.S. ESP. | E19: 0.15 | F19: 128990446 | G19: 128990445 | H19: 128990446 | I19: 128990445 | J19: 128990446 | K19: 128990445 | L19: 128990446 | M19: 128990445 | N19: 128990446 | O19: 128990445 | P19: 128990446 | Q19: 128990445
D20: TOTAL | E20: 1 | F20: 859936309 | G20: 859936305 | H20: 859936309 | I20: 859936305 | J20: 859936309 | K20: 859936305 | L20: 859936309 | M20: 859936305 | N20: 859936309 | O20: 859936305 | P20: 859936309 | Q20: 859936305
F21: =SUM(F20:G20) -> 1719872614 | G21: 1191383498 | H21: =SUM(H20:I20) -> 1719872614 | I21: 1191383498 | J21: =SUM(J20:K20) -> 1719872614 | K21: 1191383498 | L21: =SUM(L20:M20) -> 1719872614 | M21: 1191383498 | N21: =SUM(N20:O20) -> 1719872614 | O21: 1191383498 | P21: =SUM(P20:Q20) -> 1719872614 | Q21: 1191383498
K25: VALOR OFICIAL MES | L25: ASE | M25: Segunda quincena | N25: Primera quincena | R25: VALIDACION
K26: 378371975 | L26: 1 | M26: 189185988 | N26: 189185987 | O26: =N26=R26 -> TRUE | Q26: ='CONSOLIDADO_TOTAL RECAUDO'!L104 -> 189185987 | R26: =Q4 -> 189185987 | S26: =Q26=R26 -> TRUE
K27: 533160511 | L27: 2 | M27: 266580256 | N27: 266580255 | O27: =N27=R27 -> TRUE | Q27: ='CONSOLIDADO_TOTAL RECAUDO'!L105 -> 266580255 | R27: =Q5 -> 266580255 | S27: =Q27=R27 -> TRUE
K28: 309577071 | L28: 3 | M28: 154788536 | N28: 154788535 | O28: =N28=R28 -> TRUE | Q28: ='CONSOLIDADO_TOTAL RECAUDO'!L106 -> 154788535 | R28: =Q6 -> 154788535 | S28: =Q28=R28 -> TRUE
K29: 240782166 | L29: 4 | M29: 120391083 | N29: 120391083 | O29: =N29=R29 -> TRUE | Q29: ='CONSOLIDADO_TOTAL RECAUDO'!L107 -> 120391083 | R29: =Q7 -> 120391083 | S29: =Q29=R29 -> TRUE
K30: 257980891 | L30: 5 | M30: 128990446 | N30: 128990445 | O30: =N30=R30 -> TRUE | Q30: ='CONSOLIDADO_TOTAL RECAUDO'!L108 -> 128990445 | R30: =Q8 -> 128990445 | S30: =Q30=R30 -> TRUE
K31: =SUM(K26:K30) -> 1719872614 | M31: =SUM(M26:M30) -> 859936309 | N31: =SUM(N26:N30) -> 859936305 | O31: =N31=R31 -> TRUE | Q31: ='CONSOLIDADO_TOTAL RECAUDO'!L109 -> 859936305 | R31: =Q9 -> 859936305 | S31: =Q31=R31 -> TRUE
K32: =SUM(M31:N31) -> 1719872614

Sheet Informe AFaseo Recaudo 202607-1
D5: PROCERASEO S.A.S. | I5: NIT: 901 153 639 - 0 | P5: PROCERASEO S.A.S. | T5: NIT: 901 153 639 - 0
D6: INFORME Afaseo // RECAUDO | P6: INFORME AFaseo
D7: BENEFICIO TRANSITORIO ALIVIO SOBRE EL VALOR DE LA FACTURA | P7: BENEFICIO TRANSITORIO ALIVIO SOBRE EL VALOR DE LA FACTURA
D8: Según Resoluciòn UAESP Número 273 de 2.020 | P8: Según Resoluciòn UAESP Número 273 de 2.020
E10: Fecha Desde: | F10: ='CONSOLIDADO_TOTAL RECAUDO'!G102 -> 46204 | H10: Feha Hasta: | I10: ='CONSOLIDADO_TOTAL RECAUDO'!K102 -> 46218
B11: ASE | C11: Concesionarios | D11: Valor Afaseo | E11: Afaseo por disposicion final | F11: Afaseo por tratamiento de lixiviados | G11: Afaseo por Componente VIAT ( Decreto 2412/2018) | H11: Afaseo por aprovechamiento | I11: Afaseo del componente de comercializacion para Aprovechamiento (11,4%) | J11: Afaseo RBL | N11: ASE | O11: Concesionarios | P11: Tarifa de Comercialización del Servicio. ( TCS) | Q11: Tarifa de Limpieza Urbana del Servicio. ( TLU) | R11: Tarifa de Barrido y Limpieza del Servicio. ( TBL) | S11: Tarifa de Recolección y Transporte del Servicio. (TRT) | T11: Componente de comercialización para Aprovechamiento (18,6%) | U11: Afaseo RBL
B12: 1 | C12: PROMOAMBIENTAL DISTRITO S.A.S. ESP. | D12: ='Reporte Componentes R1'!F76*$D$24 -> 0 | E12: ='Reporte Componentes R1'!G76*$D$24 -> 0 | F12: ='Reporte Componentes R1'!H76*$D$24 -> 0 | G12: ='Reporte Componentes R1'!I76*$D$24 -> 0 | H12: ='Reporte Componentes R1'!J76*$D$24 -> 0 | I12: ='Reporte Componentes R1'!K76*$D$24 -> 0 | J12: =D12-E12-F12-G12-H12-I12 -> 0 | N12: 1 | O12: PROMOAMBIENTAL DISTRITO S.A.S. ESP. | P12: ='Reporte Componentes R1'!M76*$P$24 -> 0 | Q12: ='Reporte Componentes R1'!N76*$P$24 -> 0 | R12: ='Reporte Componentes R1'!O76*$P$24 -> 0 | S12: ='Reporte Componentes R1'!P76*$P$24 -> 0 | T12: ='Reporte Componentes R1'!Q76*$P$24 -> 0 | U12: =SUM(P12:T12) -> 0 | V12: =J12-U12 -> 0 | W12: =V12=0 -> TRUE
B13: 2 | C13: LIMPIEZA METROPOLITANA S.A. ESP. | D13: ='Reporte Componentes R1'!F206*$D$24 -> 1119721.4 | E13: ='Reporte Componentes R1'!G206*$D$24 -> 97699.19 | F13: ='Reporte Componentes R1'!H206*$D$24 -> 41504.31 | G13: ='Reporte Componentes R1'!I206*$D$24 -> 18125.84 | H13: ='Reporte Componentes R1'!J206*$D$24 -> 225990.73 | I13: ='Reporte Componentes R1'!K206*$D$24 -> 9352.17 | J13: =D13-E13-F13-G13-H13-I13 -> 727049.14 | N13: 2 | O13: LIMPIEZA METROPOLITANA S.A. ESP. | P13: ='Reporte Componentes R1'!M206*$P$24 -> 82929.96 | Q13: ='Reporte Componentes R1'!N206*$P$24 -> 102820.4 | R13: ='Reporte Componentes R1'!O206*$P$24 -> 345367.61 | S13: ='Reporte Componentes R1'!P206*$P$24 -> 180675.12 | T13: ='Reporte Componentes R1'!Q206*$P$24 -> 15256.05 | U13: =SUM(P13:T13) -> 727049.14 | V13: =J13-U13 -> 0 | W13: =V13=0 -> TRUE
B14: 3 | C14: CIUDAD LIMPIA BOGOTA S.A. ESP. | D14: ='Reporte Componentes R1'!F346*$D$24 -> 20882.81 | E14: ='Reporte Componentes R1'!G346*$D$24 -> 1843.26 | F14: ='Reporte Componentes R1'!H346*$D$24 -> 783.09 | G14: ='Reporte Componentes R1'!I346*$D$24 -> 341.97 | H14: ='Reporte Componentes R1'!J346*$D$24 -> 4040.42 | I14: ='Reporte Componentes R1'!K346*$D$24 -> 166.45 | J14: =D14-E14-F14-G14-H14-I14 -> 13707.62 | N14: 3 | O14: CIUDAD LIMPIA BOGOTA S.A. ESP. | P14: ='Reporte Componentes R1'!M346*$P$24 -> 1460.16 | Q14: ='Reporte Componentes R1'!N346*$P$24 -> 1830.2 | R14: ='Reporte Componentes R1'!O346*$P$24 -> 6147.57 | S14: ='Reporte Componentes R1'!P346*$P$24 -> 3998.1 | T14: ='Reporte Componentes R1'!Q346*$P$24 -> 271.59 | U14: =SUM(P14:T14) -> 13707.62 | V14: =J14-U14 -> 0 | W14: =V14=0 -> TRUE
B15: 4 | C15: BOGOTA LIMPIA S.A.S. ESP. | D15: ='Reporte Componentes R1'!F467*$D$24 -> 194589.84 | E15: ='Reporte Componentes R1'!G467*$D$24 -> 15762.93 | F15: ='Reporte Componentes R1'!H467*$D$24 -> 6696.6 | G15: ='Reporte Componentes R1'!I467*$D$24 -> 2924.39 | H15: ='Reporte Componentes R1'!J467*$D$24 -> 35979.04 | I15: ='Reporte Componentes R1'!K467*$D$24 -> 1465.17 | J15: =D15-E15-F15-G15-H15-I15 -> 131761.71 | N15: 4 | O15: BOGOTA LIMPIA S.A.S. ESP. | P15: ='Reporte Componentes R1'!M467*$P$24 -> 12852.44 | Q15: ='Reporte Componentes R1'!N467*$P$24 -> 16343.2 | R15: ='Reporte Componentes R1'!O467*$P$24 -> 60009.6 | S15: ='Reporte Componentes R1'!P467*$P$24 -> 40165.83 | T15: ='Reporte Componentes R1'!Q467*$P$24 -> 2390.64 | U15: =SUM(P15:T15) -> 131761.71 | V15: =J15-U15 -> 0 | W15: =V15=0 -> TRUE
B16: 5 | C16: AREA LIMPIA DISTRITO CAPITAL S.A.S. ESP. | D16: ='Reporte Componentes R1'!F549*$D$24 -> 0 | E16: ='Reporte Componentes R1'!G549*$D$24 -> 0 | F16: ='Reporte Componentes R1'!H549*$D$24 -> 0 | G16: ='Reporte Componentes R1'!I549*$D$24 -> 0 | H16: ='Reporte Componentes R1'!J549*$D$24 -> 0 | I16: ='Reporte Componentes R1'!K549*$D$24 -> 0 | J16: =D16-E16-F16-G16-H16-I16 -> 0 | N16: 5 | O16: AREA LIMPIA DISTRITO CAPITAL S.A.S. ESP. | P16: ='Reporte Componentes R1'!M549*$P$24 -> 0 | Q16: ='Reporte Componentes R1'!N549*$P$24 -> 0 | R16: ='Reporte Componentes R1'!O549*$P$24 -> 0 | S16: ='Reporte Componentes R1'!P549*$P$24 -> 0 | T16: ='Reporte Componentes R1'!Q549*$P$24 -> 0 | U16: =SUM(P16:T16) -> 0 | V16: =J16-U16 -> 0 | W16: =V16=0 -> TRUE
C17: TOTAL | D17: =SUM(D12:D16) -> 1335194 | E17: =SUM(E12:E16) -> 115305.38 | F17: =SUM(F12:F16) -> 48984 | G17: =SUM(G12:G16) -> 21392.2 | H17: =SUM(H12:H16) -> 266010.19 | I17: =SUM(I12:I16) -> 10983.79 | J17: =SUM(J12:J16) -> 872518.47 | O17: TOTAL | P17: =SUM(P12:P16) -> 97242.56 | Q17: =SUM(Q12:Q16) -> 120993.8 | R17: =SUM(R12:R16) -> 411524.78 | S17: =SUM(S12:S16) -> 224839.05 | T17: =SUM(T12:T16) -> 17918.28 | U17: =SUM(U12:U16) -> 872518.47 | V17: =SUM(V12:V16) -> 0 | W17: =V17=0 -> TRUE
T19: =SUM(P17:T17) -> 872518.47
J20: =+IF(MAX(J12:J17)>500000,"VALIDAR",TRUE) -> VALIDAR
F21: Firma autorizada
D24: -1 | P24: -1

Sheet CONSOLIDADO_TOTAL RECAUDO
F3: PROCERASEO S.A.S. | I3: NIT: 901 153 639 - 0 | M3: Codigo Remuneración: | N3: 2026071 | U3: PROCERASEO S.A.S. | W3: NIT: 901 153 639 - 0 | AA3: Codigo Remuneración: | AD3: =N3 -> 2026071
F4: 3. ESQUEMA FINANCIERO DEL SERVICIO PUBLICO DE ASEO | U4: 3. ESQUEMA FINANCIERO DEL SERVICIO PUBLICO DE ASEO
F5: Resoluciòn UAESP Número 27 de 2018 | U5: Resoluciòn UAESP Número 27 de 2018
C6: Fecha de Proceso: | D6: 46220 | F6: R1 - RECAUDO OPORTUNO | U6: R1 - RECAUDO OPORTUNO
C7: Hora: | D7: 0.58333333 | F7: Fecha Desde: | G7: 46204 | J7: Feha Hasta: | K7: 46218 | U7: =F7 -> Fecha Desde: | V7: =G7 -> 46204 | X7: =J7 -> Feha Hasta: | Y7: =K7 -> 46218
B8: ASE | C8: Concesionarios | D8: Recaudo Total | E8: Recaudo por disposicion final | F8: Recaudo por tratamiento de lixiviados | G8: Recaudo por Componente VIAT ( Decreto 2412/2018) | H8: Recaudo por aprovechamiento | I8: Recaudo del componente de comercializacion para Aprovechamiento (11,4%) | J8: Balance de subsidio o contribuciones | K8: RECAUDO BASE DE REMUNERACION | L8: Costo de la Interventoría | M8: REMUNERACION FINAL | N8: Conceptos especiales | O8: REMUNERACION FINAL MAS CONCEPTOS ESPECIALES | S8: ASE | T8: Concesionarios | U8: Tarifa de Comercialización del Servicio. ( TCS) | V8: Tarifa de Limpieza Urbana del Servicio. ( TLU) | W8: Tarifa de Barrido y Limpieza del Servicio. ( TBL) | X8: Tarifa de Recolección y Transporte del Servicio. (TRT) | Y8: Recaudo del componente de comercializacion para Aprovechamiento (18,6%) | Z8: Costo de la Interventoría | AA8: Ajuste a la decena | AB8: Conceptos especiales | AC8: Otros | AD8: Diferencial Balance S / C (Fac vs Rec) | AE8: Balance S / C Con Base en (Recaudo) | AF8: REMUNERACION FINAL MAS CONCEPTOS ESPECIALES
B9: 1 | C9: PROMOAMBIENTAL DISTRITO S.A.S. ESP. | D9: ='Reporte Componentes R1'!F46 -> 1.6704332e+10 | E9: ='Reporte Componentes R1'!G46 -> 9.8525773e+08 | F9: ='Reporte Componentes R1'!H46 -> 5.5382948e+08 | G9: ='Reporte Componentes R1'!I46 -> 2.9144109e+08 | H9: ='Reporte Componentes R1'!J46 -> 4.8702006e+09 | I9: ='Reporte Componentes R1'!K46 -> 1.6891361e+08 | J9: ='BCE SC POR FACT.'!F3 -> 2.0323637e+09 | K9: =D9-E9-F9-G9-H9-I9-J9 -> 7.8023263e+09 | L9: =INTERVENTORIA!Q4 -> 189185987 | M9: =K9-L9 -> 7.6131403e+09 | N9: ='Reporte Componentes R1'!L46 -> 18193739 | O9: =M9+N9 -> 7.631334e+09 | S9: 1 | T9: PROMOAMBIENTAL DISTRITO S.A.S. ESP. | U9: ='Reporte Componentes R1'!M46 -> 1.4825427e+09 | V9: ='Reporte Componentes R1'!N46 -> 1.4344369e+09 | W9: ='Reporte Componentes R1'!O46 -> 6.7871786e+09 | X9: ='Reporte Componentes R1'!P46 -> 2.682211e+09 | Y9: ='Reporte Componentes R1'!Q46 -> 2.7561501e+08 | Z9: =L9*-1 -> -189185987 | AA9: ='Reporte Componentes R1'!R46+'Reporte Componentes R1'!U46+'Reporte Componentes R1'!V46 -> -33780.6 | AB9: =N9 -> 18193739 | AC9: ='Reporte Componentes R1'!T46+'Reporte Componentes R1'!W46+'Reporte Componentes R1'!X46+'Reporte Componentes R1'!Y46+'Reporte Componentes R1'!Z46+'Reporte Componentes R1'!S46 -> 279.27 | AD9: =-J9+AE9 -> -4.8596245e+09 | AE9: ='Reporte Componentes R1'!F47 -> -2.8272608e+09 | AF9: =SUM(U9:AD9) -> 7.631334e+09 | AG9: =(AF9-O9) -> 1.9073486e-06 | AH9: =INT(AG9)=0 -> TRUE
B10: 2 | C10: LIMPIEZA METROPOLITANA S.A. ESP. | D10: ='Reporte Componentes R1'!F176 -> 1.215778e+10 | E10: ='Reporte Componentes R1'!G176 -> 1.0157702e+09 | F10: ='Reporte Componentes R1'!H176 -> 5.6276961e+08 | G10: ='Reporte Componentes R1'!I176 -> 2.9285058e+08 | H10: ='Reporte Componentes R1'!J176 -> 3.8955969e+09 | I10: ='Reporte Componentes R1'!K176 -> 1.4791363e+08 | J10: ='BCE SC POR FACT.'!F4 -> -5.0115157e+09 | K10: =D10-E10-F10-G10-H10-I10-J10 -> 1.1254395e+10 | L10: =INTERVENTORIA!Q5 -> 266580255 | M10: =K10-L10 -> 1.0987815e+10 | N10: ='Reporte Componentes R1'!L176 -> 31737182 | O10: =M10+N10 -> 1.1019552e+10 | S10: 2 | T10: LIMPIEZA METROPOLITANA S.A. ESP. | U10: ='Reporte Componentes R1'!M176 -> 1.3002759e+09 | V10: ='Reporte Componentes R1'!N176 -> 1.3041448e+09 | W10: ='Reporte Componentes R1'!O176 -> 6.075327e+09 | X10: ='Reporte Componentes R1'!P176 -> 1.9835151e+09 | Y10: ='Reporte Componentes R1'!Q176 -> 2.4201562e+08 | Z10: =L10*-1 -> -266580255 | AA10: ='Reporte Componentes R1'!R176+'Reporte Componentes R1'!U176+'Reporte Componentes R1'!V176 -> -15889.24 | AB10: =N10 -> 31737182 | AC10: ='Reporte Componentes R1'!T176+'Reporte Componentes R1'!W176+'Reporte Componentes R1'!X176+'Reporte Componentes R1'!Y176+'Reporte Componentes R1'!Z176+'Reporte Componentes R1'!S176 -> -108.84 | AD10: =-J10+AE10 -> 3.4913277e+08 | AE10: ='Reporte Componentes R1'!F177 -> -4.6623829e+09 | AF10: =SUM(U10:AD10) -> 1.1019552e+10 | AG10: =(AF10-O10) -> -1.9073486e-06 | AH10: =INT(AG10)=0 -> FALSE
B11: 3 | C11: CIUDAD LIMPIA BOGOTA S.A. ESP. | D11: ='Reporte Componentes R1'!F316 -> 1.0101989e+10 | E11: ='Reporte Componentes R1'!G316 -> 6.8170614e+08 | F11: ='Reporte Componentes R1'!H316 -> 3.8431835e+08 | G11: ='Reporte Componentes R1'!I316 -> 2.0192622e+08 | H11: ='Reporte Componentes R1'!J316 -> 2.6437719e+09 | I11: ='Reporte Componentes R1'!K316 -> 98939010 | J11: ='BCE SC POR FACT.'!F5 -> -1.1968224e+09 | K11: =D11-E11-F11-G11-H11-I11-J11 -> 7.2881493e+09 | L11: =INTERVENTORIA!Q6 -> 154788535 | M11: =K11-L11 -> 7.1333607e+09 | N11: ='Reporte Componentes R1'!L316 -> 32320230 | O11: =M11+N11 -> 7.165681e+09 | S11: 3 | T11: CIUDAD LIMPIA BOGOTA S.A. ESP. | U11: ='Reporte Componentes R1'!M316 -> 8.6864205e+08 | V11: ='Reporte Componentes R1'!N316 -> 8.5282012e+08 | W11: ='Reporte Componentes R1'!O316 -> 4.0329535e+09 | X11: ='Reporte Componentes R1'!P316 -> 1.5828358e+09 | Y11: ='Reporte Componentes R1'!Q316 -> 1.6158378e+08 | Z11: =L11*-1 -> -154788535 | AA11: ='Reporte Componentes R1'!R316+'Reporte Componentes R1'!U316+'Reporte Componentes R1'!V316 -> 80346.08 | AB11: =N11 -> 32320230 | AC11: ='Reporte Componentes R1'!T316+'Reporte Componentes R1'!W316+'Reporte Componentes R1'!X316+'Reporte Componentes R1'!Y316+'Reporte Componentes R1'!Z316+'Reporte Componentes R1'!S316 -> 2.67 | AD11: =-J11+AE11 -> -2.1076636e+08 | AE11: ='Reporte Componentes R1'!F317 -> -1.4075888e+09 | AF11: =SUM(U11:AD11) -> 7.165681e+09 | AG11: =(AF11-O11) -> -1.9073486e-06 | AH11: =INT(AG11)=0 -> FALSE
B12: 4 | C12: BOGOTA LIMPIA S.A.S. ESP. | D12: ='Reporte Componentes R1'!F437 -> 1.055241e+10 | E12: ='Reporte Componentes R1'!G437 -> 6.4165611e+08 | F12: ='Reporte Componentes R1'!H437 -> 3.591839e+08 | G12: ='Reporte Componentes R1'!I437 -> 1.8846511e+08 | H12: ='Reporte Componentes R1'!J437 -> 2.3572763e+09 | I12: ='Reporte Componentes R1'!K437 -> 90994609 | J12: ='BCE SC POR FACT.'!F6 -> 35955816 | K12: =D12-E12-F12-G12-H12-I12-J12 -> 6.8788776e+09 | L12: =INTERVENTORIA!Q7 -> 120391083 | M12: =K12-L12 -> 6.7584865e+09 | N12: ='Reporte Componentes R1'!L437 -> 22968514 | O12: =M12+N12 -> 6.781455e+09 | S12: 4 | T12: BOGOTA LIMPIA S.A.S. ESP. | U12: ='Reporte Componentes R1'!M437 -> 7.9755293e+08 | V12: ='Reporte Componentes R1'!N437 -> 7.8857774e+08 | W12: ='Reporte Componentes R1'!O437 -> 4.0570764e+09 | X12: ='Reporte Componentes R1'!P437 -> 1.697115e+09 | Y12: ='Reporte Componentes R1'!Q437 -> 1.4896885e+08 | Z12: =L12*-1 -> -120391083 | AA12: ='Reporte Componentes R1'!R437+'Reporte Componentes R1'!U437+'Reporte Componentes R1'!V437 -> -160678.67 | AB12: =N12 -> 22968514 | AC12: ='Reporte Componentes R1'!T437+'Reporte Componentes R1'!W437+'Reporte Componentes R1'!X437+'Reporte Componentes R1'!Y437+'Reporte Componentes R1'!Z437+'Reporte Componentes R1'!S437 -> -50.1 | AD12: =-J12+AE12 -> -6.1025259e+08 | AE12: ='Reporte Componentes R1'!F438 -> -5.7429677e+08 | AF12: =SUM(U12:AD12) -> 6.781455e+09 | AG12: =(AF12-O12) -> 0 | AH12: =INT(AG12)=0 -> TRUE
B13: 5 | C13: AREA LIMPIA DISTRITO CAPITAL S.A.S. ESP. | D13: ='Reporte Componentes R1'!F519 -> 8.5193103e+09 | E13: ='Reporte Componentes R1'!G519 -> 4.9686511e+08 | F13: ='Reporte Componentes R1'!H519 -> 2.7915884e+08 | G13: ='Reporte Componentes R1'!I519 -> 1.4397019e+08 | H13: ='Reporte Componentes R1'!J519 -> 1.819505e+09 | I13: ='Reporte Componentes R1'!K519 -> 70488341 | J13: ='BCE SC POR FACT.'!F7 -> -1.2104256e+09 | K13: =D13-E13-F13-G13-H13-I13-J13 -> 6.9197484e+09 | L13: =INTERVENTORIA!Q8 -> 128990445 | M13: =K13-L13 -> 6.790758e+09 | N13: ='Reporte Componentes R1'!L519 -> 26933697 | O13: =M13+N13 -> 6.8176917e+09 | S13: 5 | T13: AREA LIMPIA DISTRITO CAPITAL S.A.S. ESP. | U13: ='Reporte Componentes R1'!M519 -> 6.1874847e+08 | V13: ='Reporte Componentes R1'!N519 -> 6.0435656e+08 | W13: ='Reporte Componentes R1'!O519 -> 3.1099794e+09 | X13: ='Reporte Componentes R1'!P519 -> 1.4461727e+09 | Y13: ='Reporte Componentes R1'!Q519 -> 1.1504076e+08 | Z13: =L13*-1 -> -128990445 | AA13: ='Reporte Componentes R1'!R519+'Reporte Componentes R1'!U519+'Reporte Componentes R1'!V519 -> -78410.78 | AB13: =N13 -> 26933697 | AC13: ='Reporte Componentes R1'!T519+'Reporte Componentes R1'!W519+'Reporte Componentes R1'!X519+'Reporte Componentes R1'!Y519+'Reporte Componentes R1'!Z519+'Reporte Componentes R1'!S519 -> -103.71 | AD13: =-J13+AE13 -> 1.0255291e+09 | AE13: ='Reporte Componentes R1'!F520 -> -1.8489651e+08 | AF13: =SUM(U13:AD13) -> 6.8176917e+09 | AG13: =(AF13-O13) -> -9.5367432e-07 | AH13: =INT(AG13)=0 -> FALSE
C14: TOTAL | D14: =SUM(D9:D13) -> 5.8035821e+10 | E14: =SUM(E9:E13) -> 3.8212553e+09 | F14: =SUM(F9:F13) -> 2.1392602e+09 | G14: =SUM(G9:G13) -> 1.1186532e+09 | H14: =SUM(H9:H13) -> 1.5586351e+10 | I14: =SUM(I9:I13) -> 5.7724921e+08 | J14: =SUM(J9:J13) -> -5.3504442e+09 | K14: =SUM(K9:K13) -> 4.0143497e+10 | ... O14: =SUM(O9:O13) -> 3.9415714e+10 | T14: TOTAL | U14: =SUM(U9:U13) -> 5.0677621e+09 | V14: =SUM(V9:V13) -> 4.9843361e+09 | W14: =SUM(W9:W13) -> 2.4062515e+10 | X14: =SUM(X9:X13) -> 9.3918496e+09 | Y14: =SUM(Y9:Y13) -> 9.4322402e+08 | Z14: =SUM(Z9:Z13) -> -859936305 | AA14: =SUM(AA9:AA13) -> -208413.21 | AB14: =SUM(AB9:AB13) -> 1.3215336e+08 | ... AG14: =SUM(AG9:AG13) -> -2.8610229e-06 | AH14: =INT(AG14)=0 -> FALSE
Y16: =SUM(U14:Y14) -> 4.4449687e+10
F18: Firma autorizada
F22: PROCERASEO S.A.S. | I22: NIT: 901 153 639 - 0 | M22: Codigo Remuneración: | N22: =N3 -> 2026071 | U22: PROCERASEO S.A.S. | W22: NIT: 901 153 639 - 0 | AA22: Codigo Remuneración: | AD22: =N22 -> 2026071
F23: 3. ESQUEMA FINANCIERO DEL SERVICIO PUBLICO DE ASEO | U23: 3. ESQUEMA FINANCIERO DEL SERVICIO PUBLICO DE ASEO
F24: Resoluciòn UAESP Número 27 de 2018 | U24: Resoluciòn UAESP Número 27 de 2018
C25: Fecha de Proceso: | D25: =D6 -> 46220 | F25: R2 - ANTICIPOS A USUARIOS | U25: R2 - ANTICIPOS A USUARIOS
C26: Hora: | D26: =D7 -> 0.58333333 | F26: Fecha Desde: | G26: =G7 -> 46204 | J26: Feha Hasta: | K26: =K7 -> 46218 | U26: =F26 -> Fecha Desde: | V26: =G26 -> 46204 | X26: =J26 -> Feha Hasta: | Y26: =K26 -> 46218
B27: ASE | C27: Concesionarios | D27: Recaudo Total | E27: Recaudo por disposicion final | F27: Recaudo por tratamiento de lixiviados | G27: Recaudo por Componente VIAT ( Decreto 2412/2018) | H27: Recaudo por aprovechamiento | I27: Recaudo del componente de comercializacion para Aprovechamiento (11,4%) | J27: Balance de subsidio o contribuciones | K27: RECAUDO BASE DE REMUNERACION | L27: Costo de la Interventoría | M27: REMUNERACION FINAL | N27: Conceptos especiales | O27: REMUNERACION FINAL MAS CONCEPTOS ESPECIALES | S27: ASE | T27: Concesionarios | U27: Tarifa de Comercialización del Servicio. ( TCS) | V27: Tarifa de Limpieza Urbana del Servicio. ( TLU) | W27: Tarifa de Barrido y Limpieza del Servicio. ( TBL) | X27: Tarifa de Recolección y Transporte del Servicio. (TRT) | Y27: Recaudo del componente de comercializacion para Aprovechamiento (18,6%) | Z27: Costo de la Interventoría | AA27: Ajuste a la decena | AB27: Conceptos especiales | AC27: Otros | AD27: Diferencial Balance S / C (Fac vs Rec) | AE27: Balance S / C Con Base en (Recaudo) | AF27: REMUNERACION FINAL MAS CONCEPTOS ESPECIALES
B28: 1 | C28: PROMOAMBIENTAL DISTRITO S.A.S. ESP. | D28: ='Rem. Anticipos R2'!E41 -> 54216386 | E28: ='Rem. Anticipos R2'!F41 -> 3199724.8 | F28: ='Rem. Anticipos R2'!G41 -> 1750220.5 | G28: ='Rem. Anticipos R2'!H41 -> 884286.8 | H28: ='Rem. Anticipos R2'!I41 -> 10375658 | I28: ='Rem. Anticipos R2'!J41 -> 292010.17 | J28: 0 | K28: =D28-E28-F28-G28-H28-I28-J28 -> 37714485 | L28: 0 | M28: =K28-L28 -> 37714485 | N28: ='Rem. Anticipos R2'!K41 -> 57261.7 | O28: =M28+N28 -> 37771747 | S28: 1 | T28: PROMOAMBIENTAL DISTRITO S.A.S. ESP. | U28: ='Rem. Anticipos R2'!L41 -> 5143717.2 | V28: ='Rem. Anticipos R2'!M41 -> 4474014.3 | W28: ='Rem. Anticipos R2'!N41 -> 20865910 | X28: ='Rem. Anticipos R2'!O41 -> 8759453.5 | Y28: ='Rem. Anticipos R2'!P41 -> 476867.62 | Z28: =L28*-1 -> 0 | AA28: ='Rem. Anticipos R2'!Q41 -> 74762.27 | AB28: =N28 -> 57261.7 | AC28: ='Rem. Anticipos R2'!R41 -> 0 | AD28: =-J28+AE28 -> -2080239.9 | AE28: ='Rem. Anticipos R2'!E42 -> -2080239.9 | AF28: =SUM(U28:AD28) -> 37771747 | AG28: =(AF28-O28) -> 7.4505806e-09 | AH28: =INT(AG28)=0 -> TRUE
B29: 2 | C29: LIMPIEZA METROPOLITANA S.A. ESP. | D29: ='Rem. Anticipos R2'!E135 -> 79400801 | E29: ='Rem. Anticipos R2'!F135 -> 7426980.7 | F29: ='Rem. Anticipos R2'!G135 -> 4298990.7 | G29: ='Rem. Anticipos R2'!H135 -> 1689669.1 | H29: ='Rem. Anticipos R2'!I135 -> 27869891 | I29: ='Rem. Anticipos R2'!J135 -> 994374.59 | J29: 0 | K29: =D29-E29-F29-G29-H29-I29-J29 -> 37120895 | L29: 0 | M29: =K29-L29 -> 37120895 | N29: ='Rem. Anticipos R2'!K135 -> 0 | O29: =M29+N29 -> 37120895 | S29: 2 | T29: LIMPIEZA METROPOLITANA S.A. ESP. | U29: ='Rem. Anticipos R2'!L135 -> 10168914 | V29: ='Rem. Anticipos R2'!M135 -> 8410867.6 | W29: ='Rem. Anticipos R2'!N135 -> 35498786 | X29: ='Rem. Anticipos R2'!O135 -> 15170994 | Y29: ='Rem. Anticipos R2'!P135 -> 1203786.2 | Z29: =L29*-1 -> 0 | AA29: ='Rem. Anticipos R2'!Q135 -> 123.41 | AB29: =N29 -> 0 | AC29: ='Rem. Anticipos R2'!R135 -> 0 | AD29: =-J29+AE29 -> -33332576 | AE29: ='Rem. Anticipos R2'!E136 -> -33332576 | AF29: =SUM(U29:AD29) -> 37120895 | AG29: =(AF29-O29) -> 2.2351742e-08 | AH29: =INT(AG29)=0 -> TRUE
B30: 3 | C30: CIUDAD LIMPIA BOGOTA S.A. ESP. | D30: ='Rem. Anticipos R2'!E247 -> 31111804 | E30: ='Rem. Anticipos R2'!F247 -> 2080581.8 | F30: ='Rem. Anticipos R2'!G247 -> 1197235.9 | G30: ='Rem. Anticipos R2'!H247 -> 507278.7 | H30: ='Rem. Anticipos R2'!I247 -> 6892671.2 | I30: ='Rem. Anticipos R2'!J247 -> 265030.34 | J30: 0 | K30: =D30-E30-F30-G30-H30-I30-J30 -> 20169006 | L30: 0 | M30: =K30-L30 -> 20169006 | N30: ='Rem. Anticipos R2'!K247 -> 0 | O30: =M30+N30 -> 20169006 | S30: 3 | T30: CIUDAD LIMPIA BOGOTA S.A. ESP. | U30: ='Rem. Anticipos R2'!L247 -> 2692006.6 | V30: ='Rem. Anticipos R2'!M247 -> 2314780.5 | W30: ='Rem. Anticipos R2'!N247 -> 10535562 | X30: ='Rem. Anticipos R2'!O247 -> 4977155 | Y30: ='Rem. Anticipos R2'!P247 -> 365457.45 | Z30: =L30*-1 -> 0 | AA30: ='Rem. Anticipos R2'!Q247 -> 324.25 | AB30: =N30 -> 0 | AC30: ='Rem. Anticipos R2'!R247 -> 0 | AD30: =-J30+AE30 -> -716279.64 | AE30: ='Rem. Anticipos R2'!E248 -> -716279.64 | AF30: =SUM(U30:AD30) -> 20169006 | AG30: =(AF30-O30) -> 0 | AH30: =INT(AG30)=0 -> TRUE
B31: 4 | C31: BOGOTA LIMPIA S.A.S. ESP. | D31: ='Rem. Anticipos R2'!E343 -> 17236000 | E31: ='Rem. Anticipos R2'!F343 -> 1160186.1 | F31: ='Rem. Anticipos R2'!G343 -> 673044.71 | G31: ='Rem. Anticipos R2'!H343 -> 276501.18 | H31: ='Rem. Anticipos R2'!I343 -> 3666021.9 | I31: ='Rem. Anticipos R2'!J343 -> 145285.36 | J31: 0 | K31: =D31-E31-F31-G31-H31-I31-J31 -> 11314961 | L31: 0 | M31: =K31-L31 -> 11314961 | N31: ='Rem. Anticipos R2'!K343 -> 0 | O31: =M31+N31 -> 11314961 | S31: 4 | T31: BOGOTA LIMPIA S.A.S. ESP. | U31: ='Rem. Anticipos R2'!L343 -> 1457671.1 | V31: ='Rem. Anticipos R2'!M343 -> 1215190.9 | W31: ='Rem. Anticipos R2'!N343 -> 5739976.5 | X31: ='Rem. Anticipos R2'!O343 -> 3143067.6 | Y31: ='Rem. Anticipos R2'!P343 -> 193988.62 | Z31: =L31*-1 -> 0 | AA31: ='Rem. Anticipos R2'!Q343 -> 158.09 | AB31: =N31 -> 0 | AC31: ='Rem. Anticipos R2'!R343 -> 0 | AD31: =-J31+AE31 -> -435091.74 | AE31: ='Rem. Anticipos R2'!E344 -> -435091.74 | AF31: =SUM(U31:AD31) -> 11314961 | AG31: =(AF31-O31) -> -5.5879354e-09 | AH31: =INT(AG31)=0 -> FALSE
B32: 5 | C32: AREA LIMPIA DISTRITO CAPITAL S.A.S. ESP. | D32: ='Rem. Anticipos R2'!E413 -> 30774154 | E32: ='Rem. Anticipos R2'!F413 -> 2142757.9 | F32: ='Rem. Anticipos R2'!G413 -> 1217701.4 | G32: ='Rem. Anticipos R2'!H413 -> 530191.01 | H32: ='Rem. Anticipos R2'!I413 -> 7032005.8 | I32: ='Rem. Anticipos R2'!J413 -> 237434.2 | J32: 0 | K32: =D32-E32-F32-G32-H32-I32-J32 -> 19614064 | L32: 0 | M32: =K32-L32 -> 19614064 | N32: ='Rem. Anticipos R2'!K413 -> 308996.91 | O32: =M32+N32 -> 19923061 | S32: 5 | T32: AREA LIMPIA DISTRITO CAPITAL S.A.S. ESP. | U32: ='Rem. Anticipos R2'!L413 -> 2755023.9 | V32: ='Rem. Anticipos R2'!M413 -> 2156919.8 | W32: ='Rem. Anticipos R2'!N413 -> 10532773 | X32: ='Rem. Anticipos R2'!O413 -> 6552890.9 | Y32: ='Rem. Anticipos R2'!P413 -> 342253.62 | Z32: =L32*-1 -> 0 | AA32: ='Rem. Anticipos R2'!Q413 -> -344.22 | AB32: =N32 -> 308996.91 | AC32: ='Rem. Anticipos R2'!R413 -> 0 | AD32: =-J32+AE32 -> -2725453.2 | AE32: ='Rem. Anticipos R2'!E414 -> -2725453.2 | AF32: =SUM(U32:AD32) -> 19923061 | AG32: =(AF32-O32) -> 3.7252903e-09 | AH32: =INT(AG32)=0 -> TRUE
C33: TOTAL | D33: =SUM(D28:D32) -> 2.1273915e+08 | E33: =SUM(E28:E32) -> 16010231 | F33: =SUM(F28:F32) -> 9137193.1 | G33: =SUM(G28:G32) -> 3887926.8 | H33: =SUM(H28:H32) -> 55836248 | I33: =SUM(I28:I32) -> 1934134.7 | J33: =SUM(J28:J32) -> 0 | K33: =SUM(K28:K32) -> 1.2593341e+08 | ... O33: =SUM(O28:O32) -> 1.2629967e+08 | T33: TOTAL | U33: =SUM(U28:U32) -> 22217333 | V33: =SUM(V28:V32) -> 18571773 | W33: =SUM(W28:W32) -> 83173008 | X33: =SUM(X28:X32) -> 38603561 | Y33: =SUM(Y28:Y32) -> 2582353.5 | Z33: =SUM(Z28:Z32) -> 0 | AA33: =SUM(AA28:AA32) -> 75023.8 | AB33: =SUM(AB28:AB32) -> 366258.61 | ... AG33: =SUM(AG28:AG32) -> 2.7939677e-08 | AH33: =INT(AG33)=0 -> TRUE
Y35: =SUM(U33:Y33) -> 1.6514803e+08
F37: Firma autorizada
F41: PROCERASEO S.A.S. | I41: NIT: 901 153 639 - 0 | M41: Codigo Remuneración: | N41: =N3 -> 2026071 | U41: PROCERASEO S.A.S. | W41: NIT: 901 153 639 - 0 | AA41: Codigo Remuneración: | AD41: =N41 -> 2026071
F42: 3. ESQUEMA FINANCIERO DEL SERVICIO PUBLICO DE ASEO | U42: 3. ESQUEMA FINANCIERO DEL SERVICIO PUBLICO DE ASEO
F43: Resoluciòn UAESP Número 27 de 2018 | U43: Resoluciòn UAESP Número 27 de 2018
C44: Fecha de Proceso: | D44: =D6 -> 46220 | F44: R3 - RECAUDO EXTEMPORANEO | U44: R3 - RECAUDO EXTEMPORANEO
C45: Hora: | D45: =D7 -> 0.58333333 | F45: Fecha Desde: | G45: =G7 -> 46204 | J45: Feha Hasta: | K45: =K7 -> 46218 | U45: =F45 -> Fecha Desde: | V45: =G45 -> 46204 | X45: =J45 -> Feha Hasta: | Y45: =K45 -> 46218
B46: ASE | C46: Concesionarios | D46: Recaudo Total | E46: Recaudo por disposicion final | F46: Recaudo por tratamiento de lixiviados | G46: Recaudo por Componente VIAT ( Decreto 2412/2018) | H46: Recaudo por aprovechamiento | I46: Recaudo del componente de comercializacion para Aprovechamiento (11,4%) | J46: Balance de subsidio o contribuciones | K46: RECAUDO BASE DE REMUNERACION | L46: Costo de la Interventoría | M46: REMUNERACION FINAL | N46: Conceptos especiales | O46: REMUNERACION FINAL MAS CONCEPTOS ESPECIALES | S46: ASE | T46: Concesionarios | U46: Tarifa de Comercialización del Servicio. ( TCS) | V46: Tarifa de Limpieza Urbana del Servicio. ( TLU) | W46: Tarifa de Barrido y Limpieza del Servicio. ( TBL) | X46: Tarifa de Recolección y Transporte del Servicio. (TRT) | Y46: Recaudo del componente de comercializacion para Aprovechamiento (18,6%) | Z46: Costo de la Interventoría | AA46: Ajuste a la decena | AB46: Conceptos especiales | AC46: Otros | AD46: Diferencial Balance S / C (Fac vs Rec) | AE46: Balance S / C Con Base en (Recaudo) | AF46: REMUNERACION FINAL MAS CONCEPTOS ESPECIALES
B47: 1 | C47: PROMOAMBIENTAL DISTRITO S.A.S. ESP. | D47: ='Reporte Componentes R1'!F48 -> 11673020 | E47: ='Reporte Componentes R1'!G48 -> 1241820.9 | F47: ='Reporte Componentes R1'!H48 -> 701209.88 | G47: ='Reporte Componentes R1'!I48 -> 369347.71 | H47: ='Reporte Componentes R1'!J48 -> 164355.72 | I47: ='Reporte Componentes R1'!K48 -> 5918.58 | J47: 0 | K47: =D47-E47-F47-G47-H47-I47-J47 -> 9190367.2 | L47: 0 | M47: =K47-L47 -> 9190367.2 | N47: ='Reporte Componentes R1'!L48 -> 0 | O47: =M47+N47 -> 9190367.2 | S47: 1 | T47: PROMOAMBIENTAL DISTRITO S.A.S. ESP. | U47: ='Reporte Componentes R1'!M48 -> 51916.98 | V47: ='Reporte Componentes R1'!N48 -> 67675.1 | W47: ='Reporte Componentes R1'!O48 -> 316052.37 | X47: ='Reporte Componentes R1'!P48 -> 3403574.1 | Y47: ='Reporte Componentes R1'!Q48 -> 9656.44 | Z47: =-L47 -> 0 | AA47: ='Reporte Componentes R1'!R48+'Reporte Componentes R1'!V48+'Reporte Componentes R1'!U48 -> -12.39 | AB47: =N47 -> 0 | AC47: ='Reporte Componentes R1'!T48+'Reporte Componentes R1'!W48+'Reporte Componentes R1'!X48+'Reporte Componentes R1'!Y48+'Reporte Componentes R1'!Z48+'Reporte Componentes R1'!S48 -> 0 | AD47: =-J47+AE47 -> 5341504.6 | AE47: ='Reporte Componentes R1'!F49 -> 5341504.6 | AF47: =SUM(U47:AD47) -> 9190367.2 | AG47: =(AF47-O47) -> 1.8626451e-09 | AH47: =INT(AG47)=0 -> TRUE
B48: 2 | C48: LIMPIEZA METROPOLITANA S.A. ESP. | D48: ='Reporte Componentes R1'!F178 -> 0 | E48: ='Reporte Componentes R1'!G178 -> 0 | F48: ='Reporte Componentes R1'!H178 -> 0 | G48: ='Reporte Componentes R1'!I178 -> 0 | H48: ='Reporte Componentes R1'!J178 -> 0 | I48: ='Reporte Componentes R1'!K178 -> 0 | J48: 0 | K48: =D48-E48-F48-G48-H48-I48-J48 -> 0 | L48: 0 | M48: =K48-L48 -> 0 | N48: ='Reporte Componentes R1'!L178 -> 0 | O48: =M48+N48 -> 0 | S48: 2 | T48: LIMPIEZA METROPOLITANA S.A. ESP. | U48: ='Reporte Componentes R1'!M178 -> 0 | V48: ='Reporte Componentes R1'!N178 -> 0 | W48: ='Reporte Componentes R1'!O178 -> 0 | X48: ='Reporte Componentes R1'!P178 -> 0 | Y48: ='Reporte Componentes R1'!Q178 -> 0 | Z48: =-L48 -> 0 | AA48: ='Reporte Componentes R1'!R178+'Reporte Componentes R1'!V178+'Reporte Componentes R1'!U178 -> 0 | AB48: =N48 -> 0 | AC48: ='Reporte Componentes R1'!T178+'Reporte Componentes R1'!W178+'Reporte Componentes R1'!X178+'Reporte Componentes R1'!Y178+'Reporte Componentes R1'!Z178+'Reporte Componentes R1'!S178 -> 0 | AD48: =-J48+AE48 -> 0 | AE48: ='Reporte Componentes R1'!F179 -> 0 | AF48: =SUM(U48:AD48) -> 0 | AG48: =(AF48-O48) -> 0 | AH48: =INT(AG48)=0 -> TRUE
B49: 3 | C49: CIUDAD LIMPIA BOGOTA S.A. ESP. | D49: ='Reporte Componentes R1'!F318 -> 10198723 | E49: ='Reporte Componentes R1'!G318 -> 1240516.5 | F49: ='Reporte Componentes R1'!H318 -> 700393.35 | G49: ='Reporte Componentes R1'!I318 -> 368494.74 | H49: ='Reporte Componentes R1'!J318 -> 149096.63 | I49: ='Reporte Componentes R1'!K318 -> 4140.01 | J49: 0 | K49: =D49-E49-F49-G49-H49-I49-J49 -> 7736081.9 | L49: 0 | M49: =K49-L49 -> 7736081.9 | N49: ='Reporte Componentes R1'!L318 -> 0 | O49: =M49+N49 -> 7736081.9 | S49: 3 | T49: CIUDAD LIMPIA BOGOTA S.A. ESP. | U49: ='Reporte Componentes R1'!M318 -> 36316.12 | V49: ='Reporte Componentes R1'!N318 -> 53217.55 | W49: ='Reporte Componentes R1'!O318 -> 250685.64 | X49: ='Reporte Componentes R1'!P318 -> 2889220 | Y49: ='Reporte Componentes R1'!Q318 -> 6754.81 | Z49: =-L49 -> 0 | AA49: ='Reporte Componentes R1'!R318+'Reporte Componentes R1'!V318+'Reporte Componentes R1'!U318 -> -10.43 | AB49: =N49 -> 0 | AC49: ='Reporte Componentes R1'!T318+'Reporte Componentes R1'!W318+'Reporte Componentes R1'!X318+'Reporte Componentes R1'!Y318+'Reporte Componentes R1'!Z318+'Reporte Componentes R1'!S318 -> 0 | AD49: =-J49+AE49 -> 4499898.2 | AE49: ='Reporte Componentes R1'!F319 -> 4499898.2 | AF49: =SUM(U49:AD49) -> 7736081.9 | AG49: =(AF49-O49) -> -9.3132257e-10 | AH49: =INT(AG49)=0 -> FALSE
B50: 4 | C50: BOGOTA LIMPIA S.A.S. ESP. | D50: ='Reporte Componentes R1'!F439 -> 5419780 | E50: ='Reporte Componentes R1'!G439 -> 265698.21 | F50: ='Reporte Componentes R1'!H439 -> 146273.84 | G50: ='Reporte Componentes R1'!I439 -> 78115.94 | H50: ='Reporte Componentes R1'!J439 -> 998599.42 | I50: ='Reporte Componentes R1'!K439 -> 35953.06 | J50: 0 | K50: =D50-E50-F50-G50-H50-I50-J50 -> 3895139.5 | L50: 0 | M50: =K50-L50 -> 3895139.5 | N50: ='Reporte Componentes R1'!L439 -> 0 | O50: =M50+N50 -> 3895139.5 | S50: 4 | T50: BOGOTA LIMPIA S.A.S. ESP. | U50: ='Reporte Componentes R1'!M439 -> 298752.57 | V50: ='Reporte Componentes R1'!N439 -> 307661.96 | W50: ='Reporte Componentes R1'!O439 -> 2386148.2 | X50: ='Reporte Componentes R1'!P439 -> 712936.36 | Y50: ='Reporte Componentes R1'!Q439 -> 59549.52 | Z50: =-L50 -> 0 | AA50: ='Reporte Componentes R1'!R439+'Reporte Componentes R1'!V439+'Reporte Componentes R1'!U439 -> 8.81 | AB50: =N50 -> 0 | AC50: ='Reporte Componentes R1'!T439+'Reporte Componentes R1'!W439+'Reporte Componentes R1'!X439+'Reporte Componentes R1'!Y439+'Reporte Componentes R1'!Z439+'Reporte Componentes R1'!S439 -> 0 | AD50: =-J50+AE50 -> 130082.13 | AE50: ='Reporte Componentes R1'!F440 -> 130082.13 | AF50: =SUM(U50:AD50) -> 3895139.5 | AG50: =(AF50-O50) -> 0 | AH50: =INT(AG50)=0 -> TRUE
B51: 5 | C51: AREA LIMPIA DISTRITO CAPITAL S.A.S. ESP. | D51: ='Reporte Componentes R1'!F521 -> 0 | E51: ='Reporte Componentes R1'!G521 -> 0 | F51: ='Reporte Componentes R1'!H521 -> 0 | G51: ='Reporte Componentes R1'!I521 -> 0 | H51: ='Reporte Componentes R1'!J521 -> 0 | I51: ='Reporte Componentes R1'!K521 -> 0 | J51: 0 | K51: =D51-E51-F51-G51-H51-I51-J51 -> 0 | L51: 0 | M51: =K51-L51 -> 0 | N51: ='Reporte Componentes R1'!L521 -> 0 | O51: =M51+N51 -> 0 | S51: 5 | T51: AREA LIMPIA DISTRITO CAPITAL S.A.S. ESP. | U51: ='Reporte Componentes R1'!M521 -> 0 | V51: ='Reporte Componentes R1'!N521 -> 0 | W51: ='Reporte Componentes R1'!O521 -> 0 | X51: ='Reporte Componentes R1'!P521 -> 0 | Y51: ='Reporte Componentes R1'!Q521 -> 0 | Z51: =-L51 -> 0 | AA51: ='Reporte Componentes R1'!R521+'Reporte Componentes R1'!V521+'Reporte Componentes R1'!U521 -> 0 | AB51: =N51 -> 0 | AC51: ='Reporte Componentes R1'!T521+'Reporte Componentes R1'!W521+'Reporte Componentes R1'!X521+'Reporte Componentes R1'!Y521+'Reporte Componentes R1'!Z521+'Reporte Componentes R1'!S521 -> 0 | AD51: =-J51+AE51 -> 0 | AE51: ='Reporte Componentes R1'!F522 -> 0 | AF51: =SUM(U51:AD51) -> 0 | AG51: =(AF51-O51) -> 0 | AH51: =INT(AG51)=0 -> TRUE
C52: TOTAL | D52: =SUM(D47:D51) -> 27291523 | E52: =SUM(E47:E51) -> 2748035.6 | F52: =SUM(F47:F51) -> 1547877.1 | G52: =SUM(G47:G51) -> 815958.39 | H52: =SUM(H47:H51) -> 1312051.8 | I52: =SUM(I47:I51) -> 46011.65 | J52: =SUM(J47:J51) -> 0 | K52: =SUM(K47:K51) -> 20821589 | ... O52: =SUM(O47:O51) -> 20821589 | T52: TOTAL | U52: =SUM(U47:U51) -> 386985.67 | V52: =SUM(V47:V51) -> 428554.61 | W52: =SUM(W47:W51) -> 2952886.2 | X52: =SUM(X47:X51) -> 7005730.4 | Y52: =SUM(Y47:Y51) -> 75960.77 | Z52: =SUM(Z47:Z51) -> 0 | AA52: =SUM(AA47:AA51) -> -14.01 | AB52: =SUM(AB47:AB51) -> 0 | ... AG52: =SUM(AG47:AG51) -> 9.3132257e-10 | AH52: =INT(AG52)=0 -> TRUE
Y54: =SUM(U52:Y52) -> 10850118
F56: Firma autorizada
F60: PROCERASEO S.A.S. | I60: NIT: 901 153 639 - 0 | M60: Codigo Remuneración: | N60: =N3 -> 2026071 | U60: PROCERASEO S.A.S. | W60: NIT: 901 153 639 - 0 | AA60: Codigo Remuneración: | AD60: =N60 -> 2026071
F61: 3. ESQUEMA FINANCIERO DEL SERVICIO PUBLICO DE ASEO | U61: 3. ESQUEMA FINANCIERO DEL SERVICIO PUBLICO DE ASEO
F62: Resoluciòn UAESP Número 27 de 2018 | U62: Resoluciòn UAESP Número 27 de 2018
C63: Fecha de Proceso: | D63: =D6 -> 46220 | F63: R4 - REVERSIÓN DE PAGOS | U63: R4 - REVERSIÓN DE PAGOS
C64: Hora: | D64: =D7 -> 0.58333333 | F64: Fecha Desde: | G64: =G7 -> 46204 | J64: Feha Hasta: | K64: =K7 -> 46218 | U64: =F64 -> Fecha Desde: | V64: =G64 -> 46204 | X64: =J64 -> Feha Hasta: | Y64: =K64 -> 46218
B65: ASE | C65: Concesionarios | D65: Recaudo Total | E65: Recaudo por disposicion final | F65: Recaudo por tratamiento de lixiviados | G65: Recaudo por Componente VIAT ( Decreto 2412/2018) | H65: Recaudo por aprovechamiento | I65: Recaudo del componente de comercializacion para Aprovechamiento (11,4%) | J65: Balance de subsidio o contribuciones | K65: RECAUDO BASE DE REMUNERACION | L65: Costo de la Interventoría | M65: REMUNERACION FINAL | N65: Conceptos especiales | O65: REMUNERACION FINAL MAS CONCEPTOS ESPECIALES | S65: ASE | T65: Concesionarios | U65: Tarifa de Comercialización del Servicio. ( TCS) | V65: Tarifa de Limpieza Urbana del Servicio. ( TLU) | W65: Tarifa de Barrido y Limpieza del Servicio. ( TBL) | X65: Tarifa de Recolección y Transporte del Servicio. (TRT) | Y65: Recaudo del componente de comercializacion para Aprovechamiento (18,6%) | Z65: Costo de la Interventoría | AA65: Ajuste a la decena | AB65: Conceptos especiales | AC65: Otros | AD65: Diferencial Balance S / C (Fac vs Rec) | AE65: Balance S / C Con Base en (Recaudo) | AF65: REMUNERACION FINAL MAS CONCEPTOS ESPECIALES
B66: 1 | C66: PROMOAMBIENTAL DISTRITO S.A.S. ESP. | D66: ='Reversion Pagos R4'!D67 -> -12054256 | E66: ='Reversion Pagos R4'!E67 -> -1538555.7 | F66: ='Reversion Pagos R4'!F67 -> -869015.39 | G66: ='Reversion Pagos R4'!G67 -> -457881.97 | H66: ='Reversion Pagos R4'!H67 -> -382604.13 | I66: ='Reversion Pagos R4'!I67 -> -12197.75 | J66: 0 | K66: =D66-E66-F66-G66-H66-I66-J66 -> -8794000.7 | L66: 0 | M66: =K66-L66 -> -8794000.7 | N66: ='Reversion Pagos R4'!P67 -> 0 | O66: =M66+N66 -> -8794000.7 | S66: 1 | T66: PROMOAMBIENTAL DISTRITO S.A.S. ESP. | U66: ='Reversion Pagos R4'!J67 -> -113093.15 | V66: ='Reversion Pagos R4'!K67 -> -152211.56 | W66: ='Reversion Pagos R4'!L67 -> -738903.14 | X66: ='Reversion Pagos R4'!M67 -> -4228185 | Y66: ='Reversion Pagos R4'!N67 -> -19901.17 | Z66: =-L66 -> 0 | AA66: ='Reversion Pagos R4'!O67 -> 27.65 | AB66: =N66 -> 0 | AC66: =+'Reversion Pagos R4'!Q67+'Reversion Pagos R4'!R67 -> 0 | AD66: =-J66+AE66 -> -3541734.4 | AE66: ='Reversion Pagos R4'!D68 -> -3541734.4 | AF66: =SUM(U66:AD66) -> -8794000.7 | AG66: =(AF66-O66) -> 0 | AH66: =INT(AG66)=0 -> TRUE
B67: 2 | C67: LIMPIEZA METROPOLITANA S.A. ESP. | D67: ='Reversion Pagos R4'!D161 -> -9889189.7 | E67: ='Reversion Pagos R4'!E161 -> -687393.5 | F67: ='Reversion Pagos R4'!F161 -> -387217.21 | G67: ='Reversion Pagos R4'!G161 -> -203978.2 | H67: ='Reversion Pagos R4'!H161 -> -3023755.1 | I67: ='Reversion Pagos R4'!I161 -> -116210.51 | J67: 0 | K67: =D67-E67-F67-G67-H67-I67-J67 -> -5470635.2 | L67: 0 | M67: =K67-L67 -> -5470635.2 | N67: ='Reversion Pagos R4'!P161 -> 0 | O67: =M67+N67 -> -5470635.2 | S67: 2 | T67: LIMPIEZA METROPOLITANA S.A. ESP. | U67: ='Reversion Pagos R4'!J161 -> -1009821.2 | V67: ='Reversion Pagos R4'!K161 -> -989856.15 | W67: ='Reversion Pagos R4'!L161 -> -4602004.2 | X67: ='Reversion Pagos R4'!M161 -> -1352536.9 | Y67: ='Reversion Pagos R4'!N161 -> -188970.2 | Z67: =-L67 -> 0 | AA67: ='Reversion Pagos R4'!O161 -> 7.55 | AB67: =N67 -> 0 | AC67: =+'Reversion Pagos R4'!Q161+'Reversion Pagos R4'!R161 -> 0 | AD67: =-J67+AE67 -> 2672546 | AE67: ='Reversion Pagos R4'!D162 -> 2672546 | AF67: =SUM(U67:AD67) -> -5470635.2 | AG67: =(AF67-O67) -> 2.7939677e-09 | AH67: =INT(AG67)=0 -> TRUE
B68: 3 | C68: CIUDAD LIMPIA BOGOTA S.A. ESP. | D68: ='Reversion Pagos R4'!D198 -> -16103443 | E68: ='Reversion Pagos R4'!E198 -> -1675790.8 | F68: ='Reversion Pagos R4'!F198 -> -944961.09 | G68: ='Reversion Pagos R4'!G198 -> -498165.37 | H68: ='Reversion Pagos R4'!H198 -> -1988798.6 | I68: ='Reversion Pagos R4'!I198 -> -69384.49 | J68: 0 | K68: =D68-E68-F68-G68-H68-I68-J68 -> -10926343 | L68: 0 | M68: =K68-L68 -> -10926343 | N68: ='Reversion Pagos R4'!P198 -> 0 | O68: =M68+N68 -> -10926343 | S68: 3 | T68: CIUDAD LIMPIA BOGOTA S.A. ESP. | U68: ='Reversion Pagos R4'!J198 -> -610877.8 | V68: ='Reversion Pagos R4'!K198 -> -661718.15 | W68: ='Reversion Pagos R4'!L198 -> -3047755.5 | X68: ='Reversion Pagos R4'!M198 -> -3903213.6 | Y68: ='Reversion Pagos R4'!N198 -> -113207.1 | Z68: =-L68 -> 0 | AA68: ='Reversion Pagos R4'!O198 -> -91.12 | AB68: =N68 -> 0 | AC68: =+'Reversion Pagos R4'!Q198+'Reversion Pagos R4'!R198 -> 0 | AD68: =-J68+AE68 -> -2589479.3 | AE68: ='Reversion Pagos R4'!D199 -> -2589479.3 | AF68: =SUM(U68:AD68) -> -10926343 | AG68: =(AF68-O68) -> 1.8626451e-09 | AH68: =INT(AG68)=0 -> TRUE
B69: 4 | C69: BOGOTA LIMPIA S.A.S. ESP. | D69: ='Reversion Pagos R4'!D312 -> -21288909 | E69: ='Reversion Pagos R4'!E312 -> -1473845.2 | F69: ='Reversion Pagos R4'!F312 -> -784582.46 | G69: ='Reversion Pagos R4'!G312 -> -397506.78 | H69: ='Reversion Pagos R4'!H312 -> -4443538.7 | I69: ='Reversion Pagos R4'!I312 -> -161181.95 | J69: 0 | K69: =D69-E69-F69-G69-H69-I69-J69 -> -14028253 | L69: 0 | M69: =K69-L69 -> -14028253 | N69: ='Reversion Pagos R4'!P312 -> 0 | O69: =M69+N69 -> -14028253 | S69: 4 | T69: BOGOTA LIMPIA S.A.S. ESP. | U69: ='Reversion Pagos R4'!J312 -> -1416285.5 | V69: ='Reversion Pagos R4'!K312 -> -1435467.5 | W69: ='Reversion Pagos R4'!L312 -> -7076059.8 | X69: ='Reversion Pagos R4'!M312 -> -4014442.5 | Y69: ='Reversion Pagos R4'!N312 -> -262349.87 | Z69: =-L69 -> 0 | AA69: ='Reversion Pagos R4'!O312 -> 123.13 | AB69: =N69 -> 0 | AC69: =+'Reversion Pagos R4'!Q312+'Reversion Pagos R4'!R312 -> 1.27 | AD69: =-J69+AE69 -> 176227.32 | AE69: ='Reversion Pagos R4'!D313 -> 176227.32 | AF69: =SUM(U69:AD69) -> -14028253 | AG69: =(AF69-O69) -> 0 | AH69: =INT(AG69)=0 -> TRUE
B70: 5 | C70: AREA LIMPIA DISTRITO CAPITAL S.A.S. ESP. | D70: ='Reversion Pagos R4'!D347 -> -6421274.7 | E70: ='Reversion Pagos R4'!E347 -> -378745.74 | F70: ='Reversion Pagos R4'!F347 -> -211921.94 | G70: ='Reversion Pagos R4'!G347 -> -112229.11 | H70: ='Reversion Pagos R4'!H347 -> -1389935 | I70: ='Reversion Pagos R4'!I347 -> -51431.34 | J70: 0 | K70: =D70-E70-F70-G70-H70-I70-J70 -> -4277011.5 | L70: 0 | M70: =K70-L70 -> -4277011.5 | N70: ='Reversion Pagos R4'!P347 -> 0 | O70: =M70+N70 -> -4277011.5 | S70: 5 | T70: AREA LIMPIA DISTRITO CAPITAL S.A.S. ESP. | U70: ='Reversion Pagos R4'!J347 -> -453409.32 | V70: ='Reversion Pagos R4'!K347 -> -464039.4 | W70: ='Reversion Pagos R4'!L347 -> -2352412.5 | X70: ='Reversion Pagos R4'!M347 -> -1117764.2 | Y70: ='Reversion Pagos R4'!N347 -> -83914.08 | Z70: =-L70 -> 0 | AA70: ='Reversion Pagos R4'!O347 -> 51.27 | AB70: =N70 -> 0 | AC70: =+'Reversion Pagos R4'!Q347+'Reversion Pagos R4'!R347 -> 0.02 | AD70: =-J70+AE70 -> 194476.68 | AE70: ='Reversion Pagos R4'!D348 -> 194476.68 | AF70: =SUM(U70:AD70) -> -4277011.6 | AG70: =(AF70-O70) -> -1.8626451e-09 | AH70: =INT(AG70)=0 -> FALSE
C71: TOTAL | D71: =SUM(D66:D70) -> -65757072 | E71: =SUM(E66:E70) -> -5754331 | F71: =SUM(F66:F70) -> -3197698.1 | G71: =SUM(G66:G70) -> -1669761.4 | H71: =SUM(H66:H70) -> -11228632 | I71: =SUM(I66:I70) -> -410406.04 | J71: =SUM(J66:J70) -> 0 | K71: =SUM(K66:K70) -> -43496243 | ... O71: =SUM(O66:O70) -> -43496243 | T71: TOTAL | U71: =SUM(U66:U70) -> -3603487 | V71: =SUM(V66:V70) -> -3703292.7 | W71: =SUM(W66:W70) -> -17817135 | X71: =SUM(X66:X70) -> -14616142 | Y71: =SUM(Y66:Y70) -> -668342.42 | Z71: =SUM(Z66:Z70) -> 0 | AA71: =SUM(AA66:AA70) -> 118.48 | AB71: =SUM(AB66:AB70) -> 0 | ... AG71: =SUM(AG66:AG70) -> 2.7939677e-09 | AH71: =INT(AG71)=0 -> TRUE
Y73: =SUM(U71:Y71) -> -40408400
F75: Firma autorizada
F79: PROCERASEO S.A.S. | I79: NIT: 901 153 639 - 0 | M79: Codigo Remuneración: | N79: =N3 -> 2026071 | U79: PROCERASEO S.A.S. | W79: NIT: 901 153 639 - 0 | AA79: Codigo Remuneración: | AD79: =N79 -> 2026071
F80: 3. ESQUEMA FINANCIERO DEL SERVICIO PUBLICO DE ASEO | U80: 3. ESQUEMA FINANCIERO DEL SERVICIO PUBLICO DE ASEO
F81: Resoluciòn UAESP Número 27 de 2018 | U81: Resoluciòn UAESP Número 27 de 2018
C82: Fecha de Proceso: | D82: =D6 -> 46220 | F82: R5 - REMUNERACIÓN SALDOS A FAVOR POR NOTA | U82: =F82 -> R5 - REMUNERACIÓN SALDOS A FAVOR POR NOTA
C83: Hora: | D83: =D7 -> 0.58333333 | F83: Fecha Desde: | G83: =G7 -> 46204 | J83: Feha Hasta: | K83: =K7 -> 46218 | U83: =F83 -> Fecha Desde: | V83: =G83 -> 46204 | X83: =J83 -> Feha Hasta: | Y83: =K83 -> 46218
B84: ASE | C84: Concesionarios | D84: Recaudo Total | E84: Recaudo por disposicion final | F84: Recaudo por tratamiento de lixiviados | G84: Recaudo por Componente VIAT ( Decreto 2412/2018) | H84: Recaudo por aprovechamiento | I84: Recaudo del componente de comercializacion para Aprovechamiento (11,4%) | J84: Balance de subsidio o contribuciones | K84: RECAUDO BASE DE REMUNERACION | L84: Costo de la Interventoría | M84: REMUNERACION FINAL | N84: Conceptos especiales | O84: REMUNERACION FINAL MAS CONCEPTOS ESPECIALES | S84: ASE | T84: Concesionarios | U84: Tarifa de Comercialización del Servicio. ( TCS) | V84: Tarifa de Limpieza Urbana del Servicio. ( TLU) | W84: Tarifa de Barrido y Limpieza del Servicio. ( TBL) | X84: Tarifa de Recolección y Transporte del Servicio. (TRT) | Y84: Recaudo del componente de comercializacion para Aprovechamiento (18,6%) | Z84: Costo de la Interventoría | AA84: Ajuste a la decena | AB84: Conceptos especiales | AC84: Otros | AD84: Diferencial Balance Subsidio y Contribución (Fac vs Rec) | AE84: Balance de subsidio o contribuciones (Recaudo) | AF84: REMUNERACION FINAL MAS CONCEPTOS ESPECIALES
B85: 1 | C85: PROMOAMBIENTAL DISTRITO S.A.S. ESP. | D85: ='AJUSTES - SF-T'!D47 -> 0 | E85: ='AJUSTES - SF-T'!E47 -> 0 | F85: ='AJUSTES - SF-T'!F47 -> 0 | G85: ='AJUSTES - SF-T'!G47 -> 0 | H85: ='AJUSTES - SF-T'!H47 -> 0 | I85: ='AJUSTES - SF-T'!I47 -> 0 | J85: ='AJUSTES - SF-T'!J47 -> 0 | K85: =D85-E85-F85-G85-H85-I85-J85 -> 0 | L85: 0 | M85: =K85-L85 -> 0 | N85: ='AJUSTES - SF-T'!N47 -> 0 | O85: =M85+N85 -> 0 | S85: 1 | T85: PROMOAMBIENTAL DISTRITO S.A.S. ESP. | U85: ='AJUSTES - SF-T'!U47 -> 0 | V85: ='AJUSTES - SF-T'!V47 -> 0 | W85: ='AJUSTES - SF-T'!W47 -> 0 | X85: ='AJUSTES - SF-T'!X47 -> 0 | Y85: ='AJUSTES - SF-T'!Y47 -> 0 | Z85: =-L85 -> 0 | AA85: 0 | AB85: =N85 -> 0 | AC85: ='AJUSTES - SF-T'!AA47 -> 0 | AD85: =-J85+AE85 -> 0 | AE85: ='AJUSTES - SF-T'!AD47 -> 0 | AF85: =SUM(U85:AD85) -> 0 | AG85: =AF85-O85 -> 0 | AH85: =INT(AG85)=0 -> TRUE
B86: 2 | C86: LIMPIEZA METROPOLITANA S.A. ESP. | D86: ='AJUSTES - SF-T'!D48 -> 0 | E86: ='AJUSTES - SF-T'!E48 -> 0 | F86: ='AJUSTES - SF-T'!F48 -> 0 | G86: ='AJUSTES - SF-T'!G48 -> 0 | H86: ='AJUSTES - SF-T'!H48 -> 0 | I86: ='AJUSTES - SF-T'!I48 -> 0 | J86: ='AJUSTES - SF-T'!J48 -> 0 | K86: =D86-E86-F86-G86-H86-I86-J86 -> 0 | L86: 0 | M86: =K86-L86 -> 0 | N86: ='AJUSTES - SF-T'!N48 -> 0 | O86: =M86+N86 -> 0 | S86: 2 | T86: LIMPIEZA METROPOLITANA S.A. ESP. | U86: ='AJUSTES - SF-T'!U48 -> 0 | V86: ='AJUSTES - SF-T'!V48 -> 0 | W86: ='AJUSTES - SF-T'!W48 -> 0 | X86: ='AJUSTES - SF-T'!X48 -> 0 | Y86: ='AJUSTES - SF-T'!Y48 -> 0 | Z86: =-L86 -> 0 | AA86: ='AJUSTES - SF-T'!AA48 -> 0 | AB86: =N86 -> 0 | AC86: 0 | AD86: =-J86+AE86 -> 0 | AE86: ='AJUSTES - SF-T'!AD48 -> 0 | AF86: =SUM(U86:AD86) -> 0 | AG86: =AF86-O86 -> 0 | AH86: =INT(AG86)=0 -> TRUE
B87: 3 | C87: CIUDAD LIMPIA BOGOTA S.A. ESP. | D87: ='AJUSTES - SF-T'!D49 -> 0 | E87: ='AJUSTES - SF-T'!E49 -> 0 | F87: ='AJUSTES - SF-T'!F49 -> 0 | G87: ='AJUSTES - SF-T'!G49 -> 0 | H87: ='AJUSTES - SF-T'!H49 -> 0 | I87: ='AJUSTES - SF-T'!I49 -> 0 | J87: ='AJUSTES - SF-T'!J49 -> 0 | K87: =D87-E87-F87-G87-H87-I87-J87 -> 0 | L87: 0 | M87: =K87-L87 -> 0 | N87: ='AJUSTES - SF-T'!N49 -> 0 | O87: =M87+N87 -> 0 | S87: 3 | T87: CIUDAD LIMPIA BOGOTA S.A. ESP. | U87: ='AJUSTES - SF-T'!U49 -> 0 | V87: ='AJUSTES - SF-T'!V49 -> 0 | W87: ='AJUSTES - SF-T'!W49 -> 0 | X87: ='AJUSTES - SF-T'!X49 -> 0 | Y87: ='AJUSTES - SF-T'!Y49 -> 0 | Z87: =-L87 -> 0 | AA87: ='AJUSTES - SF-T'!AA49 -> 0 | AB87: =N87 -> 0 | AC87: 0 | AD87: =-J87+AE87 -> 0 | AE87: ='AJUSTES - SF-T'!AD49 -> 0 | AF87: =SUM(U87:AD87) -> 0 | AG87: =AF87-O87 -> 0 | AH87: =INT(AG87)=0 -> TRUE
B88: 4 | C88: BOGOTA LIMPIA S.A.S. ESP. | D88: ='AJUSTES - SF-T'!D50 -> 0 | E88: ='AJUSTES - SF-T'!E50 -> 0 | F88: ='AJUSTES - SF-T'!F50 -> 0 | G88: ='AJUSTES - SF-T'!G50 -> 0 | H88: ='AJUSTES - SF-T'!H50 -> 0 | I88: ='AJUSTES - SF-T'!I50 -> 0 | J88: ='AJUSTES - SF-T'!J50 -> 0 | K88: =D88-E88-F88-G88-H88-I88-J88 -> 0 | L88: 0 | M88: =K88-L88 -> 0 | N88: ='AJUSTES - SF-T'!N50 -> 0 | O88: =M88+N88 -> 0 | S88: 4 | T88: BOGOTA LIMPIA S.A.S. ESP. | U88: ='AJUSTES - SF-T'!U50 -> 0 | V88: ='AJUSTES - SF-T'!V50 -> 0 | W88: ='AJUSTES - SF-T'!W50 -> 0 | X88: ='AJUSTES - SF-T'!X50 -> 0 | Y88: ='AJUSTES - SF-T'!Y50 -> 0 | Z88: =-L88 -> 0 | AA88: ='AJUSTES - SF-T'!AA50 -> 0 | AB88: =N88 -> 0 | AC88: 0 | AD88: =-J88+AE88 -> 0 | AE88: ='AJUSTES - SF-T'!AD50 -> 0 | AF88: =SUM(U88:AD88) -> 0 | AG88: =AF88-O88 -> 0 | AH88: =INT(AG88)=0 -> TRUE
B89: 5 | C89: AREA LIMPIA DISTRITO CAPITAL S.A.S. ESP. | D89: ='AJUSTES - SF-T'!D51 -> 0 | E89: ='AJUSTES - SF-T'!E51 -> 0 | F89: ='AJUSTES - SF-T'!F51 -> 0 | G89: ='AJUSTES - SF-T'!G51 -> 0 | H89: ='AJUSTES - SF-T'!H51 -> 0 | I89: ='AJUSTES - SF-T'!I51 -> 0 | J89: ='AJUSTES - SF-T'!J51 -> 0 | K89: =D89-E89-F89-G89-H89-I89-J89 -> 0 | L89: 0 | M89: =K89-L89 -> 0 | N89: ='AJUSTES - SF-T'!N51 -> 0 | O89: =M89+N89 -> 0 | S89: 5 | T89: AREA LIMPIA DISTRITO CAPITAL S.A.S. ESP. | U89: ='AJUSTES - SF-T'!U51 -> 0 | V89: ='AJUSTES - SF-T'!V51 -> 0 | W89: ='AJUSTES - SF-T'!W51 -> 0 | X89: ='AJUSTES - SF-T'!X51 -> 0 | Y89: ='AJUSTES - SF-T'!Y51 -> 0 | Z89: =-L89 -> 0 | AA89: ='AJUSTES - SF-T'!AA51 -> 0 | AB89: =N89 -> 0 | AC89: 0 | AD89: =-J89+AE89 -> 0 | AE89: ='AJUSTES - SF-T'!AD51 -> 0 | AF89: =SUM(U89:AD89) -> 0 | AG89: =AF89-O89 -> 0 | AH89: =INT(AG89)=0 -> TRUE
C90: TOTAL | D90: =SUM(D85:D89) -> 0 | E90: =SUM(E85:E89) -> 0 | F90: =SUM(F85:F89) -> 0 | G90: =SUM(G85:G89) -> 0 | H90: =SUM(H85:H89) -> 0 | I90: =SUM(I85:I89) -> 0 | J90: =SUM(J85:J89) -> 0 | K90: =SUM(K85:K89) -> 0 | ... O90: =SUM(O85:O89) -> 0 | T90: TOTAL | U90: =SUM(U85:U89) -> 0 | V90: =SUM(V85:V89) -> 0 | W90: =SUM(W85:W89) -> 0 | X90: =SUM(X85:X89) -> 0 | Y90: =SUM(Y85:Y89) -> 0 | Z90: =SUM(Z85:Z89) -> 0 | AA90: =SUM(AA85:AA89) -> 0 | AB90: =SUM(AB85:AB89) -> 0 | ... AG90: =SUM(AG85:AG89) -> 0 | AH90: =INT(AG90)=0 -> TRUE
Y92: =SUM(U90:Y90) -> 0
F94: Firma autorizada
F98: PROCERASEO S.A.S. | I98: NIT: 901 153 639 - 0 | M98: Codigo Remuneración: | N98: =N3 -> 2026071 | U98: PROCERASEO S.A.S. | W98: NIT: 901 153 639 - 0 | AA98: Codigo Remuneración: | AD98: =N98 -> 2026071
F99: 3. ESQUEMA FINANCIERO DEL SERVICIO PUBLICO DE ASEO | U99: 3. ESQUEMA FINANCIERO DEL SERVICIO PUBLICO DE ASEO
F100: Resoluciòn UAESP Número 27 de 2018 | U100: Resoluciòn UAESP Número 27 de 2018
C101: Fecha de Proceso: | D101: =D6 -> 46220 | F101: REPORTE CONSOLIDADO TOTAL DE RECAUDO | U101: REPORTE DETALLADO SUBBOLSA RBL DISCRIMINADO POR ACTIVIDADES
C102: Hora: | D102: =D7 -> 0.58333333 | F102: Fecha Desde: | G102: =G7 -> 46204 | J102: Feha Hasta: | K102: =K7 -> 46218 | U102: =F102 -> Fecha Desde: | V102: =G102 -> 46204 | X102: =J102 -> Feha Hasta: | Y102: =K102 -> 46218
B103: ASE | C103: Concesionarios | D103: Recaudo Total | E103: Recaudo por disposicion final | F103: Recaudo por tratamiento de lixiviados | G103: Recaudo por Componente VIAT ( Decreto 2412/2018) | H103: Recaudo por aprovechamiento | I103: Recaudo del componente de comercializacion para Aprovechamiento (11,4%) | J103: Balance de subsidio o contribuciones | K103: RECAUDO BASE DE REMUNERACION | L103: Costo de la Interventoría | M103: REMUNERACION FINAL | N103: Conceptos especiales | O103: REMUNERACION FINAL MAS CONCEPTOS ESPECIALES | S103: ASE | T103: Concesionarios | U103: Tarifa de Comercialización del Servicio. ( TCS) | V103: Tarifa de Limpieza Urbana del Servicio. ( TLU) | W103: Tarifa de Barrido y Limpieza del Servicio. ( TBL) | X103: Tarifa de Recolección y Transporte del Servicio. (TRT) | Y103: Recaudo del componente de comercializacion para Aprovechamiento (18,6%) | Z103: Costo de la Interventoría | AA103: Ajuste a la decena | AB103: Conceptos especiales | AC103: Otros | AD103: Diferencial Balance Subsidio y Contribución (Fac vs Rec) | AE103: Balance de subsidio o contribuciones (Recaudo) | AF103: REMUNERACION FINAL MAS CONCEPTOS ESPECIALES
B104: 1 | C104: PROMOAMBIENTAL DISTRITO S.A.S. ESP. | D104: =D9+D28+D47+D66+D85 -> 1.6758168e+10 | E104: =E9+E28+E47+E66+E85 -> 9.8816072e+08 | F104: =F9+F28+F47+F66+F85 -> 5.554119e+08 | G104: =G9+G28+G47+G66+G85 -> 2.9223684e+08 | H104: =H9+H28+H47+H66+H85 -> 4.880358e+09 | I104: =I9+I28+I47+I66+I85 -> 1.6919934e+08 | J104: =J9+J28+J47+J66+J85 -> 2.0323637e+09 | K104: =D104-E104-F104-G104-H104-I104-J104 -> 7.8404371e+09 | L104: =L9+L28+L47+L66+L85 -> 189185987 | M104: =K104-L104 -> 7.6512512e+09 | N104: =N9+N28+N47+N66+N85 -> 18251001 | O104: =M104+N104 -> 7.6695022e+09 | S104: 1 | T104: PROMOAMBIENTAL DISTRITO S.A.S. ESP. | U104: =U9+U28+U47+U66+U85 -> 1.4876253e+09 | V104: =V9+V28+V47+V66+V85 -> 1.4388264e+09 | W104: =W9+W28+W47+W66+W85 -> 6.8076217e+09 | X104: =X9+X28+X47+X66+X85 -> 2.6901459e+09 | Y104: =Y9+Y28+Y47+Y66+Y85 -> 2.7608163e+08 | Z104: =Z9+Z28+Z47+Z66+Z85 -> -189185987 | AA104: =AA9+AA28+AA47+AA66+AA85 -> 40996.93 | AB104: =AB9+AB28+AB47+AB66+AB85 -> 18251001 | AC104: =AC9+AC28+AC47+AC66+AC85 -> 279.27 | AD104: =-J104+AE104 -> -4.8599049e+09 | AE104: =AE9+AE28+AE47+AE66+AE85 -> -2.8275412e+09 | AF104: =SUM(U104:AD104) -> 7.6695022e+09 | AG104: =AF104-O104 -> 0 | AH104: =INT(AG104)=0 -> TRUE
B105: 2 | C105: LIMPIEZA METROPOLITANA S.A. ESP. | D105: =D10+D29+D48+D67+D86 -> 1.2227292e+10 | E105: =E10+E29+E48+E67+E86 -> 1.0225098e+09 | F105: =F10+F29+F48+F67+F86 -> 5.6668138e+08 | G105: =G10+G29+G48+G67+G86 -> 2.9433627e+08 | H105: =H10+H29+H48+H67+H86 -> 3.920443e+09 | I105: =I10+I29+I48+I67+I86 -> 1.487918e+08 | J105: =J10+J29+J48+J67+J86 -> -5.0115157e+09 | K105: =D105-E105-F105-G105-H105-I105-J105 -> 1.1286045e+10 | L105: =L10+L29+L48+L67+L86 -> 266580255 | M105: =K105-L105 -> 1.1019465e+10 | N105: =N10+N29+N48+N67+N86 -> 31737182 | O105: =M105+N105 -> 1.1051202e+10 | S105: 2 | T105: LIMPIEZA METROPOLITANA S.A. ESP. | U105: =U10+U29+U48+U67+U86 -> 1.309435e+09 | V105: =V10+V29+V48+V67+V86 -> 1.3115658e+09 | W105: =W10+W29+W48+W67+W86 -> 6.1062238e+09 | X105: =X10+X29+X48+X67+X86 -> 1.9973335e+09 | Y105: =Y10+Y29+Y48+Y67+Y86 -> 2.4303044e+08 | Z105: =Z10+Z29+Z48+Z67+Z86 -> -266580255 | AA105: =AA10+AA29+AA48+AA67+AA86 -> -15758.28 | AB105: =AB10+AB29+AB48+AB67+AB86 -> 31737182 | AC105: =AC10+AC29+AC48+AC67+AC86 -> -108.84 | AD105: =-J105+AE105 -> 3.1847274e+08 | AE105: =AE10+AE29+AE48+AE67+AE86 -> -4.6930429e+09 | AF105: =SUM(U105:AD105) -> 1.1051202e+10 | AG105: =AF105-O105 -> 0 | AH105: =INT(AG105)=0 -> TRUE
B106: 3 | C106: CIUDAD LIMPIA BOGOTA S.A. ESP. | D106: =D11+D30+D49+D68+D87 -> 1.0127196e+10 | E106: =E11+E30+E49+E68+E87 -> 6.8335145e+08 | F106: =F11+F30+F49+F68+F87 -> 3.8527102e+08 | G106: =G11+G30+G49+G68+G87 -> 2.0230383e+08 | H106: =H11+H30+H49+H68+H87 -> 2.6488249e+09 | I106: =I11+I30+I49+I68+I87 -> 99138796 | J106: =J11+J30+J49+J68+J87 -> -1.1968224e+09 | K106: =D106-E106-F106-G106-H106-I106-J106 -> 7.305128e+09 | L106: =L11+L30+L49+L68+L87 -> 154788535 | M106: =K106-L106 -> 7.1503395e+09 | N106: =N11+N30+N49+N68+N87 -> 32320230 | O106: =M106+N106 -> 7.1826597e+09 | S106: 3 | T106: CIUDAD LIMPIA BOGOTA S.A. ESP. | U106: =U11+U30+U49+U68+U87 -> 8.7075949e+08 | V106: =V11+V30+V49+V68+V87 -> 8.545264e+08 | W106: =W11+W30+W49+W68+W87 -> 4.040692e+09 | X106: =X11+X30+X49+X68+X87 -> 1.586799e+09 | Y106: =Y11+Y30+Y49+Y68+Y87 -> 1.6184279e+08 | Z106: =Z11+Z30+Z49+Z68+Z87 -> -154788535 | AA106: =AA11+AA30+AA49+AA68+AA87 -> 80568.78 | AB106: =AB11+AB30+AB49+AB68+AB87 -> 32320230 | AC106: =AC11+AC30+AC49+AC68+AC87 -> 2.67 | AD106: =-J106+AE106 -> -2.0957222e+08 | AE106: =AE11+AE30+AE49+AE68+AE87 -> -1.4063946e+09 | AF106: =SUM(U106:AD106) -> 7.1826597e+09 | AG106: =AF106-O106 -> 0 | AH106: =INT(AG106)=0 -> TRUE
B107: 4 | C107: BOGOTA LIMPIA S.A.S. ESP. | D107: =D12+D31+D50+D69+D88 -> 1.0553776e+10 | E107: =E12+E31+E50+E69+E88 -> 6.4160815e+08 | F107: =F12+F31+F50+F69+F88 -> 3.5921863e+08 | G107: =G12+G31+G50+G69+G88 -> 1.8842222e+08 | H107: =H12+H31+H50+H69+H88 -> 2.3574974e+09 | I107: =I12+I31+I50+I69+I88 -> 91014665 | J107: =J12+J31+J50+J69+J88 -> 35955816 | K107: =D107-E107-F107-G107-H107-I107-J107 -> 6.8800595e+09 | L107: =L12+L31+L50+L69+L88 -> 120391083 | M107: =K107-L107 -> 6.7596684e+09 | N107: =N12+N31+N50+N69+N88 -> 22968514 | O107: =M107+N107 -> 6.7826369e+09 | S107: 4 | T107: BOGOTA LIMPIA S.A.S. ESP. | U107: =U12+U31+U50+U69+U88 -> 7.9789307e+08 | V107: =V12+V31+V50+V69+V88 -> 7.8866513e+08 | W107: =W12+W31+W50+W69+W88 -> 4.0581264e+09 | X107: =X12+X31+X50+X69+X88 -> 1.6969566e+09 | Y107: =Y12+Y31+Y50+Y69+Y88 -> 1.4896004e+08 | Z107: =Z12+Z31+Z50+Z69+Z88 -> -120391083 | AA107: =AA12+AA31+AA50+AA69+AA88 -> -160388.64 | AB107: =AB12+AB31+AB50+AB69+AB88 -> 22968514 | AC107: =AC12+AC31+AC50+AC69+AC88 -> -48.83 | AD107: =-J107+AE107 -> -6.1038137e+08 | AE107: =AE12+AE31+AE50+AE69+AE88 -> -5.7442556e+08 | AF107: =SUM(U107:AD107) -> 6.7826369e+09 | AG107: =AF107-O107 -> 0 | AH107: =INT(AG107)=0 -> TRUE
