Workbook
Name \0: #REF!
Name _1: #REF!
Name _2: #REF!
Name _A655555: #REF!
Name _CFR1: #REF!
Name _cia1: #REF!
Name _XL250: #REF!
Name A: #REF!
Name ADM: [1]!ADM
Name ADM: [1]!ADM
Name ADM: [1]!ADM
Name ADM: [1]!ADM
Name ADM: [1]!ADM
Name ADM_: [1]!ADM
Name ADM_: [1]!ADM
Name ADM_: [1]!ADM
Name ADM_: [1]!ADM
Name ADM_: [1]!ADM
Name AI: #REF!
Name Air: #REF!
Name AP: '[2]TARIFA no aforos'!$C$12
Name Bancos: [3]Fx!$C$1:$C$23
Name CBL: #REF!
Name CCS: #REF!
Name CDT_p: [4]CDT!$C$3
Name CFR: #REF!
Name cia: #REF!
Name COM: #REF!
Name CRT: #REF!
Name CRT___CTEp___CDTp___CMRv: #REF!
Name CRT_aislados: '[4]COSTOS AJUSTADOS'!$C$13
Name CRT_costas: #REF!
Name CTE_p: [4]CTE!$C$5
Name Denominador: #REF!
Name dg: [1]!ADM
Name dg: [1]!ADM
Name dg: [1]!ADM
Name dg: [1]!ADM
Name dg: [1]!ADM
Name DIAS: [5]CONTRA!#REF!
Name Fmerc: #REF!
Name FPS: #REF!
Name InformacionGeneral: [1]!InformacionGeneral
Name InformacionGeneral: [1]!InformacionGeneral
Name InformacionGeneral: [1]!InformacionGeneral
Name InformacionGeneral: [1]!InformacionGeneral
Name InformacionGeneral: [1]!InformacionGeneral
Name INTFIN: #REF!
Name INV: [1]!INV
Name INV: [1]!INV
Name INV: [1]!INV
Name INV: [1]!INV
Name INV: [1]!INV
Name K: #REF!
Name N: '[4]COSTOS AJUSTADOS'!#REF!
Name Na: '[2]TARIFA no aforos'!$C$39
Name nfc: '[4]COSTOS AJUSTADOS'!#REF!
Name OYM: [1]!OYM
Name OYM: [1]!OYM
Name OYM: [1]!OYM

Sheet Recaudo EAAB Reciprocidad
B2: OPORTUNO | C2: ASE | D2: VALOR 1° Q | E2: NUMERO REG. 1°Q | F2: VALOR 2° Q | G2: NUMERO REG. 2°Q
C3: 1 | D3: 0 | E3: 0 | F3: 0 | G3: 0
C4: 2 | D4: 11627730 | E4: 116 | F4: 0 | G4: 0
C5: 3 | D5: 0 | E5: 0 | F5: 0 | G5: 0
C6: 4 | D6: 7382710 | E6: 66 | F6: 0 | G6: 0
C7: 5 | D7: 0 | E7: 0 | F7: 0 | G7: 0
C8: X
D9: 19010440 | E9: 182 | F9: 0 | G9: 0
C11: ASE | D11: VALOR 1° Q | E11: NUMERO REG. 1°Q | F11: VALOR 2° Q | G11: NUMERO REG. 2°Q
B12: EXTEMP. | C12: 1 | D12: 0 | E12: 0 | F12: 0 | G12: 0
C13: 2 | D13: 0 | E13: 0 | F13: 0 | G13: 0
C14: 3 | D14: 0 | E14: 0 | F14: 0 | G14: 0
C15: 4 | D15: 0 | E15: 0 | F15: 0 | G15: 0
C16: 5 | D16: 0 | E16: 0 | F16: 0 | G16: 0
C17: X
D18: 0 | E18: 0 | F18: 0 | G18: 0
C20: ASE | D20: VALOR 1° Q | E20: NUMERO REG. 1°Q | F20: VALOR 2° Q | G20: NUMERO REG. 2°Q | I20: VALOR TOTAL MES | J20: NUMERO REGISTROS MES
B21: TOTAL | C21: 1 | D21: 0 | E21: 0 | F21: 0 | G21: 0 | I21: 0 | J21: 0
C22: 2 | D22: 11627730 | E22: 116 | F22: 0 | G22: 0 | I22: 11627730 | J22: 116
C23: 3 | D23: 0 | E23: 0 | F23: 0 | G23: 0 | I23: 0 | J23: 0
C24: 4 | D24: 7382710 | E24: 66 | F24: 0 | G24: 0 | I24: 7382710 | J24: 66
C25: 5 | D25: 0 | E25: 0 | F25: 0 | G25: 0 | I25: 0 | J25: 0
C26: X | I26: 0 | J26: 0
D27: 19010440 | E27: 182 | F27: 0 | G27: 0 | I27: 19010440 | J27: 182
B31: OPORTUNO | D31: =D9=SUM(D3:D8) -> TRUE | E31: =E9=SUM(E3:E8) -> TRUE | F31: =F9=SUM(F3:F8) -> TRUE | G31: =G9=SUM(G3:G8) -> TRUE
B33: EXTEMP. | D33: =D18=SUM(D12:D17) -> TRUE | E33: =E18=SUM(E12:E17) -> TRUE | F33: =F18=SUM(F12:F17) -> TRUE | G33: =G18=SUM(G12:G17) -> TRUE
B35: TOTAL | D35: =D27=SUM(D21:D26) -> TRUE | E35: =E27=SUM(E21:E26) -> TRUE | F35: =F27=SUM(F21:F26) -> TRUE | G35: =G27=SUM(G21:G26) -> TRUE | I35: =I27=SUM(I21:I26) -> TRUE | J35: =J27=SUM(J21:J26) -> TRUE
E69: =C69-G17 -> 0

Sheet Recaudo ENEL
B2: OPORTUNO | C2: ASE | D2: VALOR 1° Q | E2: NUMERO REG. 1°Q | F2: VALOR 2° Q | G2: NUMERO REG. 2°Q
C3: 1 | D3: 16745673525 | E3: 356945 | F3: 0 | G3: 0
C4: 2 | D4: 12677941411 | E4: 247628 | F4: 0 | G4: 0
C5: 3 | D5: 10157711962 | E5: 233934 | F5: 0 | G5: 0
C6: 4 | D6: 10972037248 | E6: 193770 | F6: 0 | G6: 0
C7: 5 | D7: 8639656940 | E7: 172542 | F7: 0 | G7: 0
C8: X
D9: 59193021086 | E9: 1204819 | F9: 0 | G9: 0
C11: ASE | D11: VALOR 1° Q | E11: NUMERO REG. 1°Q | F11: VALOR 2° Q | G11: NUMERO REG. 2°Q
B12: EXTEMP. | C12: 1 | D12: 202711553 | E12: 2558 | F12: 0 | G12: 0
C13: 2 | D13: 73096641 | E13: 1473 | F13: 0 | G13: 0
C14: 3 | D14: 51248640 | E14: 963 | F14: 0 | G14: 0
C15: 4 | D15: 62236830 | E15: 857 | F15: 0 | G15: 0
C16: 5 | D16: 158575115 | E16: 2854 | F16: 0 | G16: 0
C17: X
D18: 547868779 | E18: 8705 | F18: 0 | G18: 0
C20: ASE | D20: VALOR 1° Q | E20: NUMERO REG. 1°Q | F20: VALOR 2° Q | G20: NUMERO REG. 2°Q | I20: VALOR TOTAL MES | J20: NUMERO REGISTROS MES
B21: TOTAL | C21: 1 | D21: 16948385078 | E21: 359503 | F21: 0 | G21: 0 | I21: 16948385078 | J21: 359503
C22: 2 | D22: 12751038052 | E22: 249101 | F22: 0 | G22: 0 | I22: 12751038052 | J22: 249101
C23: 3 | D23: 10208960602 | E23: 234897 | F23: 0 | G23: 0 | I23: 10208960602 | J23: 234897
C24: 4 | D24: 11034274078 | E24: 194627 | F24: 0 | G24: 0 | I24: 11034274078 | J24: 194627
C25: 5 | D25: 8798232055 | E25: 175396 | F25: 0 | G25: 0 | I25: 8798232055 | J25: 175396
C26: X | I26: 0 | J26: 0
D27: 59740889865 | E27: 1213524 | F27: 0 | G27: 0 | I27: 59740889865 | J27: 1213524
B31: OPORTUNO | D31: =D9=SUM(D3:D8) -> TRUE | E31: =E9=SUM(E3:E8) -> TRUE | F31: =F9=SUM(F3:F8) -> TRUE | G31: =G9=SUM(G3:G8) -> TRUE
B33: EXTEMP. | D33: =D18=SUM(D12:D17) -> TRUE | E33: =E18=SUM(E12:E17) -> TRUE | F33: =F18=SUM(F12:F17) -> TRUE | G33: =G18=SUM(G12:G17) -> TRUE
B35: TOTAL | D35: =D27=SUM(D21:D26) -> TRUE | E35: =E27=SUM(E21:E26) -> TRUE | F35: =F27=SUM(F21:F26) -> TRUE | G35: =G27=SUM(G21:G26) -> TRUE | I35: =I27=SUM(I21:I26) -> TRUE | J35: =J27=SUM(J21:J26) -> TRUE
E69: =C69-G17 -> 0

Sheet Recaudo ENERBIT
B2: OPORTUNO | C2: ASE | D2: VALOR 1° Q | E2: NUMERO REG. 1°Q | F2: VALOR 2° Q | G2: NUMERO REG. 2°Q
C3: 1 | D3: 0 | E3: 0 | F3: 0 | G3: 0
C4: 2 | D4: 0 | E4: 0 | F4: 0 | G4: 0
C5: 3 | D5: 0 | E5: 0 | F5: 0 | G5: 0
C6: 4 | D6: 0 | E6: 0 | F6: 0 | G6: 0
C7: 5 | D7: 137371512 | E7: 3020 | F7: 0 | G7: 0
C8: X
D9: 137371512 | E9: 3020 | F9: 0 | G9: 0
C11: ASE | D11: VALOR 1° Q | E11: NUMERO REG. 1°Q | F11: VALOR 2° Q | G11: NUMERO REG. 2°Q
B12: EXTEMP. | C12: 1 | D12: 0 | E12: 0 | F12: 0 | G12: 0
C13: 2 | D13: 0 | E13: 0 | F13: 0 | G13: 0
C14: 3 | D14: 0 | E14: 0 | F14: 0 | G14: 0
C15: 4 | D15: 0 | E15: 0 | F15: 0 | G15: 0
C16: 5 | D16: 1179300 | E16: 6 | F16: 0 | G16: 0
C17: X
D18: 1179300 | E18: 6 | F18: 0 | G18: 0
C20: ASE | D20: VALOR 1° Q | E20: NUMERO REG. 1°Q | F20: VALOR 2° Q | G20: NUMERO REG. 2°Q | I20: VALOR TOTAL MES | J20: NUMERO REGISTROS MES
B21: TOTAL | C21: 1 | D21: 0 | E21: 0 | F21: 0 | G21: 0 | I21: 0 | J21: 0
C22: 2 | D22: 0 | E22: 0 | F22: 0 | G22: 0 | I22: 0 | J22: 0
C23: 3 | D23: 0 | E23: 0 | F23: 0 | G23: 0 | I23: 0 | J23: 0
C24: 4 | D24: 0 | E24: 0 | F24: 0 | G24: 0 | I24: 0 | J24: 0
C25: 5 | D25: 138550812 | E25: 3026 | F25: 0 | G25: 0 | I25: 138550812 | J25: 3026
C26: X | I26: 0 | J26: 0
D27: 138550812 | E27: 3026 | F27: 0 | G27: 0 | I27: 138550812 | J27: 3026
B31: OPORTUNO | D31: =D9=SUM(D3:D8) -> TRUE | E31: =E9=SUM(E3:E8) -> TRUE | F31: =F9=SUM(F3:F8) -> TRUE | G31: =G9=SUM(G3:G8) -> TRUE
B33: EXTEMP. | D33: =D18=SUM(D12:D17) -> TRUE | E33: =E18=SUM(E12:E17) -> TRUE | F33: =F18=SUM(F12:F17) -> TRUE | G33: =G18=SUM(G12:G17) -> TRUE
B35: TOTAL | D35: =D27=SUM(D21:D26) -> TRUE | E35: =E27=SUM(E21:E26) -> TRUE | F35: =F27=SUM(F21:F26) -> TRUE | G35: =G27=SUM(G21:G26) -> TRUE | I35: =I27=SUM(I21:I26) -> TRUE | J35: =J27=SUM(J21:J26) -> TRUE
E69: =C69-G17 -> 0

Sheet Recaudo EAAB + Ciud Limp
B2: Ciudad Limpia - Prestador | C2: ASE | D2: VALOR 1° Q | E2: NUMERO REG. 1°Q | F2: VALOR 2° Q | G2: NUMERO REG. 2°Q
C3: 1 | D3: 0 | E3: 0 | F3: 0 | G3: 0
C4: 2 | D4: 0 | E4: 0 | F4: 0 | G4: 0
C5: 3 | D5: 0 | E5: 0 | F5: 0 | G5: 0
C6: 4 | D6: 0 | E6: 0 | F6: 0 | G6: 0
C7: 5 | D7: 0 | E7: 0 | F7: 0 | G7: 0
C8: X
D9: 0 | E9: 0 | F9: 0 | G9: 0
C11: ASE | D11: VALOR 1° Q | E11: NUMERO REG. 1°Q | F11: VALOR 2° Q | G11: NUMERO REG. 2°Q
B12: EAAB - Prestador | C12: 1 | D12: 0 | E12: 0 | F12: 0 | G12: 0
C13: 2 | D13: 0 | E13: 0 | F13: 0 | G13: 0
C14: 3 | D14: 0 | E14: 0 | F14: 0 | G14: 0
C15: 4 | D15: 0 | E15: 0 | F15: 0 | G15: 0
C16: 5 | D16: 0 | E16: 0 | F16: 0 | G16: 0
C17: X
D18: 0 | E18: 0 | F18: 0 | G18: 0
C20: ASE | D20: VALOR 1° Q | E20: NUMERO REG. 1°Q | F20: VALOR 2° Q | G20: NUMERO REG. 2°Q | I20: VALOR TOTAL MES | J20: NUMERO REGISTROS MES
B21: TOTAL | C21: 1 | D21: 0 | E21: 0 | F21: 0 | G21: 0 | I21: 0 | J21: 0
C22: 2 | D22: 0 | E22: 0 | F22: 0 | G22: 0 | I22: 0 | J22: 0
C23: 3 | D23: 0 | E23: 0 | F23: 0 | G23: 0 | I23: 0 | J23: 0
C24: 4 | D24: 0 | E24: 0 | F24: 0 | G24: 0 | I24: 0 | J24: 0
C25: 5 | D25: 0 | E25: 0 | F25: 0 | G25: 0 | I25: 0 | J25: 0
C26: X | I26: 0 | J26: 0
D27: 0 | E27: 0 | F27: 0 | G27: 0 | I27: 0 | J27: 0
B31: OPORTUNO | D31: =D9=SUM(D3:D8) -> TRUE | E31: =E9=SUM(E3:E8) -> TRUE | F31: =F9=SUM(F3:F8) -> TRUE | G31: =G9=SUM(G3:G8) -> TRUE
B33: EXTEMP. | D33: =D18=SUM(D12:D17) -> TRUE | E33: =E18=SUM(E12:E17) -> TRUE | F33: =F18=SUM(F12:F17) -> TRUE | G33: =G18=SUM(G12:G17) -> TRUE
B35: TOTAL | D35: =D27=SUM(D21:D26) -> TRUE | E35: =E27=SUM(E21:E26) -> TRUE | F35: =F27=SUM(F21:F26) -> TRUE | G35: =G27=SUM(G21:G26) -> TRUE | I35: =I27=SUM(I21:I26) -> TRUE | J35: =J27=SUM(J21:J26) -> TRUE

Sheet Recaudo Directa Occidente
B2: OPORTUNO | C2: ASE | D2: VALOR 1° Q | E2: NUMERO REG. 1°Q | F2: VALOR 2° Q | G2: NUMERO REG. 2°Q
C3: 1 | D3: 510782327 | E3: 2083 | F3: 0 | G3: 0
C4: 2 | D4: 1360190364 | E4: 4795 | F4: 0 | G4: 0
C5: 3 | D5: 650826874 | E5: 1469 | F5: 0 | G5: 0
C6: 4 | D6: 515587332 | E6: 3012 | F6: 0 | G6: 0
C7: 5 | D7: 224557157 | E7: 1221 | F7: 0 | G7: 0
C8: X | D8: 0 | E8: 0 | F8: 0 | G8: 0
D9: 3261944054 | E9: 12580 | F9: 0 | G9: 0
C11: ASE | D11: VALOR 1° Q | E11: NUMERO REG. 1°Q | F11: VALOR 2° Q | G11: NUMERO REG. 2°Q
B12: EXTEMP. | C12: 1 | D12: 23795111 | E12: 50 | F12: 0 | G12: 0
C13: 2 | D13: 62759499 | E13: 134 | F13: 0 | G13: 0
C14: 3 | D14: 48196023 | E14: 55 | F14: 0 | G14: 0
C15: 4 | D15: 5014320 | E15: 32 | F15: 0 | G15: 0
C16: 5 | D16: 14004529 | E16: 30 | F16: 0 | G16: 0
C17: X | D17: 0 | E17: 0 | F17: 0 | G17: 0
D18: 153769482 | E18: 301 | F18: 0 | G18: 0
C20: ASE | D20: VALOR 1° Q | E20: NUMERO REG. 1°Q | F20: VALOR 2° Q | G20: NUMERO REG. 2°Q | I20: VALOR TOTAL MES | J20: NUMERO REGISTROS MES
B21: TOTAL | C21: 1 | D21: 534577438 | E21: 2133 | F21: 0 | G21: 0 | I21: 534577438 | J21: 2133
C22: 2 | D22: 1422949863 | E22: 4929 | F22: 0 | G22: 0 | I22: 1422949863 | J22: 4929
C23: 3 | D23: 699022897 | E23: 1524 | F23: 0 | G23: 0 | I23: 699022897 | J23: 1524
C24: 4 | D24: 520601652 | E24: 3044 | F24: 0 | G24: 0 | I24: 520601652 | J24: 3044
C25: 5 | D25: 238561686 | E25: 1251 | F25: 0 | G25: 0 | I25: 238561686 | J25: 1251
C26: X | D26: 0 | E26: 0 | F26: 0 | G26: 0 | I26: 0 | J26: 0
D27: 3415713536 | E27: 12881 | F27: 0 | G27: 0 | I27: 3415713536 | J27: 12881
B31: OPORTUNO | D31: =D9=SUM(D3:D8) -> TRUE | E31: =E9=SUM(E3:E8) -> TRUE | F31: =F9=SUM(F3:F8) -> TRUE | G31: =G9=SUM(G3:G8) -> TRUE
B33: EXTEMP. | D33: =D18=SUM(D12:D17) -> TRUE | E33: =E18=SUM(E12:E17) -> TRUE | F33: =F18=SUM(F12:F17) -> TRUE | G33: =G18=SUM(G12:G17) -> TRUE
B35: TOTAL | D35: =D27=SUM(D21:D26) -> TRUE | E35: =E27=SUM(E21:E26) -> TRUE | F35: =F27=SUM(F21:F26) -> TRUE | G35: =G27=SUM(G21:G26) -> TRUE | I35: =I27=SUM(I21:I26) -> TRUE | J35: =J27=SUM(J21:J26) -> TRUE
E69: =C69-G17 -> 0

Sheet REPORTE RECAUDO x BANCO
C1: ENEL | D1: CIUDAD LIMPIA | E1: EAB | F1: NUEVO ESQUEMA | G1: ENERBIT | H1: OCCIDENTE | I1: Total
B2: 1-APLICADOS A FACTURACION | C2: =C13+C23+C32+C41+C51 -> 59646927181 | D2: =D13+D23+D32+D41+D51 -> 0 | E2: =E13+E23+E32+E41+E51 -> 0 | F2: =F13+F23+F32+F41+F51 -> 5603210 | G2: =G13+G23+G32+G41+G51 -> 137170902 | H2: =H13+H23+H32+H41+H51 -> 3.2507019e+09 | I2: =SUM(C2:H2) -> 6.3040403e+10
B3: 2-SALDOS A FAVOR GENERADOS | C3: =C14+C24+C33+C42+C52 -> 95923744 | D3: =D14+D24+D33+D42+D52 -> 0 | E3: =E14+E24+E33+E42+E52 -> 0 | F3: =F14+F24+F33+F42+F52 -> 13407230 | G3: =G14+G24+G33+G42+G52 -> 1379910 | H3: =H14+H24+H33+H42+H52 -> 75193898 | I3: =SUM(C3:H3) -> 1.8590478e+08
B4: 3-APLICADOS A FINANCIACIONES NUEVAS | C4: =C15+C25+C34+C43+C53 -> 0 | D4: =D15+D25+D34+D43+D53 -> 0 | E4: =E15+E25+E34+E43+E53 -> 0 | F4: =F15+F25+F34+F43+F53 -> 0 | G4: =G15+G25+G34+G43+G53 -> 0 | H4: =H15+H25+H34+H43+H53 -> 89817711 | I4: =SUM(C4:H4) -> 89817711
B5: 7-APLICADOS A RECIBOS SERVICIOS ESPECIALES | C5: =C16+C26+C35+C44+C54 -> 0 | D5: =D16+D26+D35+D44+D54 -> 0 | E5: =E16+E26+E35+E44+E54 -> 0 | F5: =F16+F26+F35+F44+F54 -> 0 | G5: =G16+G26+G35+G44+G54 -> 0 | H5: =H16+H26+H35+H44+H54 -> 0 | I5: =SUM(C5:H5) -> 0
B6: Total | C6: =SUM(C2:C5) -> 59742850925 | D6: =SUM(D2:D5) -> 0 | E6: =SUM(E2:E5) -> 0 | F6: =SUM(F2:F5) -> 19010440 | G6: =SUM(G2:G5) -> 138550812 | H6: =SUM(H2:H5) -> 3.4157135e+09 | I6: =SUM(I2:I5) -> 63316125713
C7: =C6=(C17+C27+C36+C45+C55) -> TRUE | D7: =D6=(D17+D27+D36+D45+D55) -> TRUE | E7: =E6=(E17+E27+E36+E45+E55) -> TRUE | F7: =F6=(F17+F27+F36+F45+F55) -> TRUE | H7: =H6=(H17+H27+H36+H45+H55) -> TRUE | I7: =I6=(I17+I27+I36+I45+I55) -> TRUE
B10: ASE 1
B11: Resumen Recaudo Aplicado Por Servicio
C12: ENEL | D12: CIUDAD LIMPIA | E12: EAB | F12: NUEVO ESQUEMA | G12: ENERBIT | H12: OCCIDENTE | I12: Total
B13: 1-APLICADOS A FACTURACION | C13: 16922955923 | H13: 5.2128716e+08 | I13: =SUM(C13:H13) -> 1.7444243e+10 | J13: =SUM(C13:H13)=I13 -> TRUE
B14: 2-SALDOS A FAVOR GENERADOS | C14: 25429155 | H14: 7990275.5 | I14: =SUM(C14:H14) -> 33419430 | J14: =SUM(C14:H14)=I14 -> TRUE
B15: 3-APLICADOS A FINANCIACIONES NUEVAS | C15: 0 | H15: 5300003 | I15: =SUM(C15:H15) -> 5300003 | J15: =SUM(C15:H15)=I15 -> TRUE
B16: 7-APLICADOS A RECIBOS SERVICIOS ESPECIALES | C16: 0 | I16: =SUM(C16:H16) -> 0 | J16: =SUM(C16:H16)=I16 -> TRUE
B17: Total | C17: =SUM(C13:C16) -> 16948385078 | D17: =SUM(D13:D16) -> 0 | E17: =SUM(E13:E16) -> 0 | F17: =SUM(F13:F16) -> 0 | G17: =SUM(G13:G16) -> 0 | H17: =SUM(H13:H16) -> 534577438 | I17: =SUM(I13:I16) -> 17482962516 | J17: =SUM(C17:H17)=I17 -> TRUE
B20: ASE 2
B21: Resumen Recaudo Aplicado Por Servicio
C22: ENEL | D22: CIUDAD LIMPIA | E22: EAB | F22: NUEVO ESQUEMA | G22: ENERBIT | H22: OCCIDENTE | I22: Total
B23: 1-APLICADOS A FACTURACION | C23: 12724393063 | E23: 0 | F23: 3445900 | H23: 1.3616741e+09 | I23: =SUM(C23:H23) -> 1.4089513e+10 | J23: =SUM(C23:H23)=I23 -> TRUE
B24: 2-SALDOS A FAVOR GENERADOS | C24: 27050219 | E24: 0 | F24: 8181830 | H24: 52788865 | I24: =SUM(C24:H24) -> 88020914 | J24: =SUM(C24:H24)=I24 -> TRUE
B25: 3-APLICADOS A FINANCIACIONES NUEVAS | C25: 0 | E25: 0 | F25: 0 | H25: 8486848.6 | I25: =SUM(C25:H25) -> 8486848.6 | J25: =SUM(C25:H25)=I25 -> TRUE
B26: 7-APLICADOS A RECIBOS SERVICIOS ESPECIALES | F26: 0 | H26: 0 | I26: =SUM(C26:H26) -> 0 | J26: =SUM(C26:H26)=I26 -> TRUE
B27: Total | C27: =SUM(C23:C26) -> 12751443282 | D27: =SUM(D23:D26) -> 0 | E27: =SUM(E23:E26) -> 0 | F27: =SUM(F23:F26) -> 11627730 | G27: =SUM(G23:G26) -> 0 | H27: =SUM(H23:H26) -> 1422949863 | I27: =SUM(I23:I26) -> 1.4186021e+10 | J27: =SUM(C27:H27)=I27 -> TRUE
B29: ASE 3
B30: Resumen Recaudo Aplicado Por Servicio
C31: ENEL | D31: CIUDAD LIMPIA | E31: EAB | F31: NUEVO ESQUEMA | G31: ENERBIT | H31: OCCIDENTE | I31: Total
B32: 1-APLICADOS A FACTURACION | C32: 10203127061 | F32: 0 | H32: 6.9348502e+08 | I32: =SUM(C32:H32) -> 1.0896612e+10 | J32: =SUM(C32:H32)=I32 -> TRUE
B33: 2-SALDOS A FAVOR GENERADOS | C33: 6025131 | F33: 0 | H33: 2921040 | I33: =SUM(C33:H33) -> 8946171 | J33: =SUM(C33:H33)=I33 -> TRUE
B34: 3-APLICADOS A FINANCIACIONES NUEVAS | C34: 0 | F34: 0 | H34: 2616838.9 | I34: =SUM(C34:H34) -> 2616838.9 | J34: =SUM(C34:H34)=I34 -> TRUE
B35: 7-APLICADOS A RECIBOS SERVICIOS ESPECIALES | C35: 0 | F35: 0 | I35: =SUM(C35:H35) -> 0 | J35: =SUM(C35:H35)=I35 -> TRUE
B36: Total | C36: =SUM(C32:C35) -> 10209152192 | D36: =SUM(D32:D35) -> 0 | E36: =SUM(E32:E35) -> 0 | F36: =SUM(F32:F35) -> 0 | G36: =SUM(G32:G35) -> 0 | H36: =SUM(H32:H35) -> 699022897 | I36: =SUM(I32:I35) -> 10908175089 | J36: =SUM(C36:H36)=I36 -> TRUE
B38: ASE 4
B39: Resumen Recaudo Aplicado Por Servicio
C40: ENEL | D40: CIUDAD LIMPIA | E40: EAB | F40: NUEVO ESQUEMA | G40: ENERBIT | H40: OCCIDENTE | I40: Total
B41: 1-APLICADOS A FACTURACION | C41: 11007626472 | E41: 0 | F41: 2157310 | H41: 4.4153236e+08 | I41: =SUM(C41:H41) -> 1.1451316e+10 | J41: =SUM(C41:H41)=I41 -> TRUE
B42: 2-SALDOS A FAVOR GENERADOS | C42: 27660196 | E42: 0 | F42: 5225400 | H42: 8186683.7 | I42: =SUM(C42:H42) -> 41072280 | J42: =SUM(C42:H42)=I42 -> TRUE
B43: 3-APLICADOS A FINANCIACIONES NUEVAS | C43: 0 | E43: 0 | F43: 0 | H43: 70882609 | I43: =SUM(C43:H43) -> 70882609 | J43: =SUM(C43:H43)=I43 -> TRUE
B44: 7-APLICADOS A RECIBOS SERVICIOS ESPECIALES | I44: =SUM(C44:H44) -> 0 | J44: =SUM(C44:H44)=I44 -> TRUE
B45: Total | C45: =SUM(C41:C44) -> 11035286668 | D45: =SUM(D41:D44) -> 0 | E45: =SUM(E41:E44) -> 0 | F45: =SUM(F41:F44) -> 7382710 | G45: =SUM(G41:G44) -> 0 | H45: =SUM(H41:H44) -> 5.2060165e+08 | I45: =SUM(I41:I44) -> 11563271030 | J45: =SUM(C45:H45)=I45 -> TRUE
B48: ASE 5
B49: Resumen Recaudo Aplicado Por Servicio
C50: ENEL | D50: CIUDAD LIMPIA | E50: EAB | F50: NUEVO ESQUEMA | G50: ENERBIT | H50: OCCIDENTE | I50: Total
B51: 1-APLICADOS A FACTURACION | C51: 8788824662 | G51: 137170902 | H51: 2.3272324e+08 | I51: =SUM(C51:H51) -> 9.1587188e+09 | J51: =SUM(C51:H51)=I51 -> TRUE
B52: 2-SALDOS A FAVOR GENERADOS | C52: 9759043 | G52: 1379910 | H52: 3307034 | I52: =SUM(C52:H52) -> 14445987 | J52: =SUM(C52:H52)=I52 -> TRUE
B53: 3-APLICADOS A FINANCIACIONES NUEVAS | C53: 0 | G53: 0 | H53: 2531411 | I53: =SUM(C53:H53) -> 2531411 | J53: =SUM(C53:H53)=I53 -> TRUE
B54: 7-APLICADOS A RECIBOS SERVICIOS ESPECIALES | C54: 0 | I54: =SUM(C54:H54) -> 0 | J54: =SUM(C54:H54)=I54 -> TRUE
B55: Total | C55: =SUM(C51:C54) -> 8798583705 | D55: =SUM(D51:D54) -> 0 | E55: =SUM(E51:E54) -> 0 | F55: =SUM(F51:F54) -> 0 | G55: =SUM(G51:G54) -> 138550812 | H55: =SUM(H51:H54) -> 238561686 | I55: =SUM(I51:I54) -> 9175696203 | J55: =SUM(C55:H55)=I55 -> TRUE
B59: QUINCENA | C59: 1 | D59: OJO/// DILIGENCIAR
B62: Recaudo ENEL - ASE 1 | C62: =IF($C$59=1,'Recaudo ENEL'!D21,'Recaudo ENEL'!F21) -> 16948385078 | D62: =C17=C62 -> TRUE | E62: =C17-C62 -> 0
B63: Recaudo ENERBIT - ASE 1 | C63: =IF($C$59=1,'Recaudo ENERBIT'!D21,'Recaudo ENERBIT'!F21) -> 0 | D63: =G17=C63 -> TRUE | E63: =G17-C63 -> 0
B64: Recaudo Reciprocidad EAAB - ASE 2 | C64: =IF($C$59=1,'Recaudo EAAB Reciprocidad'!D22,'Recaudo EAAB Reciprocidad'!F22) -> 11627730 | D64: =F27=C64 -> TRUE | E64: =F27-C64 -> 0
B65: Recaudo ENEL - ASE 2 | C65: =IF($C$59=1,'Recaudo ENEL'!D22,'Recaudo ENEL'!F22) -> 12751038052 | D65: =C27=C65 -> FALSE | E65: =C27-C65 -> 405230 | F65: ok
B66: Recaudo ENERBIT - ASE 2 | C66: =IF($C$59=1,'Recaudo ENERBIT'!D22,'Recaudo ENERBIT'!F22) -> 0 | D66: =G27=C66 -> TRUE | E66: =G27-C66 -> 0
B67: Recaudo ENEL - ASE 3 | C67: =IF($C$59=1,'Recaudo ENEL'!D23,'Recaudo ENEL'!F23) -> 10208960602 | D67: =C36=C67 -> FALSE | E67: =C36-C67 -> 191590 | F67: ok
B68: Recaudo ENERBIT - ASE 3 | C68: =IF($C$59=1,'Recaudo ENERBIT'!D23,'Recaudo ENERBIT'!F23) -> 0 | D68: =G36=C68 -> TRUE | E68: =G36-C68 -> 0
B69: Recaudo Reciprocidad EAAB - ASE 4 | C69: =IF($C$59=1,'Recaudo EAAB Reciprocidad'!D24,'Recaudo EAAB Reciprocidad'!F24) -> 7382710 | D69: =F45=C69 -> TRUE | E69: =F45-C69 -> 0
B70: Recaudo ENEL - ASE 4 | C70: =IF($C$59=1,'Recaudo ENEL'!D24,'Recaudo ENEL'!F24) -> 11034274078 | D70: =C45=C70 -> FALSE | E70: =C45-C70 -> 1012590 | F70: ok
B71: Recaudo ENERBIT - ASE 4 | C71: =IF($C$59=1,'Recaudo ENERBIT'!D24,'Recaudo ENERBIT'!F24) -> 0 | D71: =G45=C71 -> TRUE | E71: =G45-C71 -> 0
B72: Recaudo ENEL - ASE 5 | C72: =IF($C$59=1,'Recaudo ENEL'!D25,'Recaudo ENEL'!F25) -> 8798232055 | D72: =C55=C72 -> FALSE | E72: =C55-C72 -> 351650 | F72: ok
B73: Recaudo ENERBIT - ASE 5 | C73: =IF($C$59=1,'Recaudo ENERBIT'!D25,'Recaudo ENERBIT'!F25) -> 138550812 | D73: =G55=C73 -> TRUE | E73: =G55-C73 -> 0
B75: Recaudo Banco Occidente ASE 1 | C75: =IF($C$59=1,'Recaudo Directa Occidente'!D21,'Recaudo Directa Occidente'!F21) -> 534577438 | D75: =C75=H17 -> TRUE | E75: =H17-C75 -> 0
B76: Recaudo Banco Occidente ASE 2 | C76: =IF($C$59=1,'Recaudo Directa Occidente'!D22,'Recaudo Directa Occidente'!F22) -> 1422949863 | D76: =C76=H27 -> TRUE | E76: =H27-C76 -> 0
B77: Recaudo Banco Occidente ASE 3 | C77: =IF($C$59=1,'Recaudo Directa Occidente'!D23,'Recaudo Directa Occidente'!F23) -> 699022897 | D77: =C77=H36 -> TRUE | E77: =H36-C77 -> 0
B78: Recaudo Banco Occidente ASE 4 | C78: =IF($C$59=1,'Recaudo Directa Occidente'!D24,'Recaudo Directa Occidente'!F24) -> 520601652 | D78: =C78=H45 -> TRUE | E78: =H45-C78 -> 0
B79: Recaudo Banco Occidente ASE 5 | C79: =IF($C$59=1,'Recaudo Directa Occidente'!D25,'Recaudo Directa Occidente'!F25) -> 238561686 | D79: =C79=H55 -> TRUE | E79: =H55-C79 -> 0
B81: TOTAL RECAUDO | C81: =SUM(C62:C79) -> 63314164653 | D81: =C81=(I6-SUM(E62:E79)) -> TRUE

Sheet ANT EXT-REV
C1: ASE 1 | E1: ASE 2 | G1: ASE 3 | I1: ASE 4 | K1: ASE 5 | M1: TOTAL
C2: REPORTE 3 | D2: REPORTE 4 | E2: REPORTE 3 | F2: REPORTE 4 | G2: REPORTE 3 | H2: REPORTE 4 | I2: REPORTE 3 | J2: REPORTE 4 | K2: REPORTE 3 | L2: REPORTE 4 | M2: REPORTE 3 | N2: REPORTE 4
B3: APLICADO | C3: =C11+C19+C27+C35+C43 -> 42680 | D3: =D11+D19+D27+D35+D43 -> -3544507.3 | E3: =E11+E19+E27+E35+E43 -> 0 | F3: =F11+F19+F27+F35+F43 -> -8739602.4 | G3: =G11+G19+G27+G35+G43 -> 169120 | H3: =H11+H19+H27+H35+H43 -> -6125983.9 | I3: =I11+I19+I27+I35+I43 -> 8635714 | J3: =J11+J19+J27+J35+J43 -> -22250060 | ... L3: =L11+L19+L27+L35+L43 -> -9076100 | M3: =C3+E3+G3+I3+K3 -> 8908654 | N3: =D3+F3+H3+J3+L3 -> -49736253 | P3: =N3=(-VALIDACION_TOTAL!M9) -> TRUE
B4: ANTICIPOS | C4: =C12+C20+C28+C36+C44 -> 40630 | D4: =D12+D20+D28+D36+D44 -> -1752.71 | E4: =E12+E20+E28+E36+E44 -> 0 | F4: =F12+F20+F28+F36+F44 -> -310.63 | G4: =G12+G20+G28+G36+G44 -> 2320 | H4: =H12+H20+H28+H36+H44 -> -984746.11 | I4: =I12+I20+I28+I36+I44 -> 10812878 | J4: =J12+J20+J28+J36+J44 -> -459462.22 | ... L4: =L12+L20+L28+L36+L44 -> -133820 | M4: =C4+E4+G4+I4+K4 -> 11165808 | N4: =D4+F4+H4+J4+L4 -> -1580091.7 | P4: =N4=(-'CONSOLIDADO_TOTAL RECAUDO'!L131) -> TRUE
B5: TOTAL | C5: =SUM(C3:C4) -> 83310 | D5: =SUM(D3:D4) -> -3546260 | E5: =SUM(E3:E4) -> 0 | F5: =SUM(F3:F4) -> -8739913 | G5: =SUM(G3:G4) -> 171440 | H5: =SUM(H3:H4) -> -7110730 | I5: =SUM(I3:I4) -> 19448592 | J5: =SUM(J3:J4) -> -22709522 | ... N5: =SUM(N3:N4) -> -51316345
C6: =C5=(C13+C21+C29+C37+C45) -> TRUE | D6: =D5=(D13+D21+D29+D37+D45) -> TRUE | E6: =E5=(E13+E21+E29+E37+E45) -> TRUE | F6: =F5=(F13+F21+F29+F37+F45) -> TRUE | G6: =G5=(G13+G21+G29+G37+G45) -> TRUE | H6: =H5=(H13+H21+H29+H37+H45) -> TRUE | I6: =I5=(I13+I21+I29+I37+I45) -> TRUE | J6: =J5=(J13+J21+J29+J37+J45) -> TRUE | ... N6: =N5=(N13+N21+N29+N37+N45) -> TRUE
B8: BANCO DE OCCIDENTE
C9: ASE 1 | E9: ASE 2 | G9: ASE 3 | I9: ASE 4 | K9: ASE 5 | M9: TOTAL
C10: REPORTE 3 | D10: REPORTE 4 | E10: REPORTE 3 | F10: REPORTE 4 | G10: REPORTE 3 | H10: REPORTE 4 | I10: REPORTE 3 | J10: REPORTE 4 | K10: REPORTE 3 | L10: REPORTE 4 | M10: REPORTE 3 | N10: REPORTE 4
B11: APLICADO | C11: 42680 | D11: -83310 | E11: 0 | F11: 0 | G11: 33180 | H11: -34410 | I11: 239834 | J11: -1742535 | K11: 61140 | L11: -304780 | M11: =C11+E11+G11+I11+K11 -> 376834 | N11: =D11+F11+H11+J11+L11 -> -2165035
B12: ANTICIPOS | C12: 40630 | D12: 0 | E12: 0 | F12: 0 | G12: 1230 | H12: 0 | I12: 1438701 | J12: 0 | K12: 309980 | L12: -66340 | M12: =C12+E12+G12+I12+K12 -> 1790541 | N12: =D12+F12+H12+J12+L12 -> -66340
B13: TOTAL | C13: =SUM(C11:C12) -> 83310 | D13: =SUM(D11:D12) -> -83310 | E13: =SUM(E11:E12) -> 0 | F13: =SUM(F11:F12) -> 0 | G13: =SUM(G11:G12) -> 34410 | H13: =SUM(H11:H12) -> -34410 | I13: =SUM(I11:I12) -> 1678535 | J13: =SUM(J11:J12) -> -1742535 | ... N13: =SUM(N11:N12) -> -2231375
B16: EAAB RECIPROCIDAD
C17: ASE 1 | E17: ASE 2 | G17: ASE 3 | I17: ASE 4 | K17: ASE 5 | M17: TOTAL
C18: REPORTE 3 | D18: REPORTE 4 | E18: REPORTE 3 | F18: REPORTE 4 | G18: REPORTE 3 | H18: REPORTE 4 | I18: REPORTE 3 | J18: REPORTE 4 | K18: REPORTE 3 | L18: REPORTE 4 | M18: REPORTE 3 | N18: REPORTE 4
B19: APLICADO | C19: 0 | D19: 0 | E19: 0 | F19: 0 | G19: 0 | H19: 0 | I19: 208970 | J19: -262000 | K19: 0 | L19: 0 | M19: =C19+E19+G19+I19+K19 -> 208970 | N19: =D19+F19+H19+J19+L19 -> -262000
B20: ANTICIPOS | C20: 0 | D20: 0 | E20: 0 | F20: 0 | G20: 0 | H20: 0 | I20: 53030 | J20: 0 | K20: 0 | L20: 0 | M20: =C20+E20+G20+I20+K20 -> 53030 | N20: =D20+F20+H20+J20+L20 -> 0
B21: TOTAL | C21: =SUM(C19:C20) -> 0 | D21: =SUM(D19:D20) -> 0 | E21: =SUM(E19:E20) -> 0 | F21: =SUM(F19:F20) -> 0 | G21: =SUM(G19:G20) -> 0 | H21: =SUM(H19:H20) -> 0 | I21: =SUM(I19:I20) -> 262000 | J21: =SUM(J19:J20) -> -262000 | ... L21: =SUM(L19:L20) -> 0 | M21: =C21+E21+G21+I21+K21 -> 262000 | N21: =SUM(N19:N20) -> -262000
B24: EAAB CIUDAD LIMPIA
C25: ASE 1 | E25: ASE 2 | G25: ASE 3 | I25: ASE 4 | K25: ASE 5 | M25: TOTAL
C26: REPORTE 3 | D26: REPORTE 4 | E26: REPORTE 3 | F26: REPORTE 4 | G26: REPORTE 3 | H26: REPORTE 4 | I26: REPORTE 3 | J26: REPORTE 4 | K26: REPORTE 3 | L26: REPORTE 4 | M26: REPORTE 3 | N26: REPORTE 4
B27: APLICADO | C27: 0 | D27: 0 | E27: 0 | F27: 0 | G27: 0 | H27: 0 | I27: 0 | J27: 0 | K27: 0 | L27: 0 | M27: =C27+E27+G27+I27+K27 -> 0 | N27: =D27+F27+H27+J27+L27 -> 0
B28: ANTICIPOS | C28: 0 | D28: 0 | E28: 0 | F28: 0 | G28: 0 | H28: 0 | I28: 0 | J28: 0 | K28: 0 | L28: 0 | M28: =C28+E28+G28+I28+K28 -> 0 | N28: =D28+F28+H28+J28+L28 -> 0
B29: TOTAL | C29: =SUM(C27:C28) -> 0 | D29: =SUM(D27:D28) -> 0 | E29: =SUM(E27:E28) -> 0 | F29: =SUM(F27:F28) -> 0 | G29: =SUM(G27:G28) -> 0 | H29: =SUM(H27:H28) -> 0 | I29: =SUM(I27:I28) -> 0 | J29: =SUM(J27:J28) -> 0 | ... N29: =SUM(N27:N28) -> 0
B32: ENEL
C33: ASE 1 | E33: ASE 2 | G33: ASE 3 | I33: ASE 4 | K33: ASE 5 | M33: TOTAL
C34: REPORTE 3 | D34: REPORTE 4 | E34: REPORTE 3 | F34: REPORTE 4 | G34: REPORTE 3 | H34: REPORTE 4 | I34: REPORTE 3 | J34: REPORTE 4 | K34: REPORTE 3 | L34: REPORTE 4 | M34: REPORTE 3 | N34: REPORTE 4
B35: APLICADO | C35: 0 | D35: -3461197.3 | E35: 0 | F35: -8739602.4 | G35: 135940 | H35: -6091573.9 | I35: 8186910 | J35: -20245525 | K35: 0 | L35: -8771320 | M35: =C35+E35+G35+I35+K35 -> 8322850 | N35: =D35+F35+H35+J35+L35 -> -47309218
B36: ANTICIPOS | C36: 0 | D36: -1752.71 | E36: 0 | F36: -310.63 | G36: 1090 | H36: -984746.11 | I36: 9321147 | J36: -459462.22 | K36: 0 | L36: -67480 | M36: =C36+E36+G36+I36+K36 -> 9322237 | N36: =D36+F36+H36+J36+L36 -> -1513751.7
B37: TOTAL | C37: =SUM(C35:C36) -> 0 | D37: =SUM(D35:D36) -> -3462950 | E37: =SUM(E35:E36) -> 0 | F37: =SUM(F35:F36) -> -8739913 | G37: =SUM(G35:G36) -> 137030 | H37: =SUM(H35:H36) -> -7076320 | I37: =SUM(I35:I36) -> 17508057 | J37: =SUM(J35:J36) -> -20704987 | ... N37: =SUM(N35:N36) -> -48822970
B40: ENERBIT
C41: ASE 1 | E41: ASE 2 | G41: ASE 3 | I41: ASE 4 | K41: ASE 5 | M41: TOTAL
C42: REPORTE 3 | D42: REPORTE 4 | E42: REPORTE 3 | F42: REPORTE 4 | G42: REPORTE 3 | H42: REPORTE 4 | I42: REPORTE 3 | J42: REPORTE 4 | K42: REPORTE 3 | L42: REPORTE 4 | M42: REPORTE 3 | N42: REPORTE 4
B43: APLICADO | C43: 0 | D43: 0 | E43: 0 | F43: 0 | G43: 0 | H43: 0 | I43: 0 | J43: 0 | K43: 0 | L43: 0 | M43: =C43+E43+G43+I43+K43 -> 0 | N43: =D43+F43+H43+J43+L43 -> 0
B44: ANTICIPOS | C44: 0 | D44: 0 | E44: 0 | F44: 0 | G44: 0 | H44: 0 | I44: 0 | J44: 0 | K44: 0 | L44: 0 | M44: =C44+E44+G44+I44+K44 -> 0 | N44: =D44+F44+H44+J44+L44 -> 0
B45: TOTAL | C45: =SUM(C43:C44) -> 0 | D45: =SUM(D43:D44) -> 0 | E45: =SUM(E43:E44) -> 0 | F45: =SUM(F43:F44) -> 0 | G45: =SUM(G43:G44) -> 0 | H45: =SUM(H43:H44) -> 0 | I45: =SUM(I43:I44) -> 0 | J45: =SUM(J43:J44) -> 0 | ... N45: =SUM(N43:N44) -> 0

Sheet ANTICIPOS USUARIOS
B1: TOTAL | E1: RECIPROCIDAD | H1: ENEL | K1: ENERBIT | N1: OCCIDENTE | Q1: EAAB-CIUDADLIMPIA
B2: ASE | C2: ANTICIPOS GENERADOS POR PAGO | E2: ASE | F2: ANTICIPOS GENERADOS POR PAGO | H2: ASE | I2: ANTICIPOS GENERADOS POR PAGO | K2: ASE | L2: ANTICIPOS GENERADOS POR PAGO | N2: ASE | O2: ANTICIPOS GENERADOS POR PAGO | Q2: ASE | R2: ANTICIPOS GENERADOS POR PAGO | T2: Anticipos generados por pago
B3: 1 | C3: ='REPORTE RECAUDO x BANCO'!I14 -> 33419430 | E3: 1 | F3: ='REPORTE RECAUDO x BANCO'!F14 -> 0 | H3: 1 | I3: ='REPORTE RECAUDO x BANCO'!C14 -> 25429155 | K3: 1 | L3: ='REPORTE RECAUDO x BANCO'!G14 -> 0 | N3: 1 | O3: ='REPORTE RECAUDO x BANCO'!H14 -> 7990275.5 | Q3: 1 | R3: ='REPORTE RECAUDO x BANCO'!D14+'REPORTE RECAUDO x BANCO'!E14 -> 0 | T3: Sale del reporte Recaudo por Bancos.
B4: 2 | C4: ='REPORTE RECAUDO x BANCO'!I24 -> 88020914 | E4: 2 | F4: ='REPORTE RECAUDO x BANCO'!F24 -> 8181830 | H4: 2 | I4: ='REPORTE RECAUDO x BANCO'!C24 -> 27050219 | K4: 2 | L4: ='REPORTE RECAUDO x BANCO'!G24 -> 0 | N4: 2 | O4: ='REPORTE RECAUDO x BANCO'!H24 -> 52788865 | Q4: 2 | R4: ='REPORTE RECAUDO x BANCO'!D24+'REPORTE RECAUDO x BANCO'!E24 -> 0
B5: 3 | C5: ='REPORTE RECAUDO x BANCO'!I33 -> 8946171 | E5: 3 | F5: ='REPORTE RECAUDO x BANCO'!F33 -> 0 | H5: 3 | I5: ='REPORTE RECAUDO x BANCO'!C33 -> 6025131 | K5: 3 | L5: ='REPORTE RECAUDO x BANCO'!G33 -> 0 | N5: 3 | O5: ='REPORTE RECAUDO x BANCO'!H33 -> 2921040 | Q5: 3 | R5: ='REPORTE RECAUDO x BANCO'!D33+'REPORTE RECAUDO x BANCO'!E33 -> 0
B6: 4 | C6: ='REPORTE RECAUDO x BANCO'!I42 -> 41072280 | E6: 4 | F6: ='REPORTE RECAUDO x BANCO'!F42 -> 5225400 | H6: 4 | I6: ='REPORTE RECAUDO x BANCO'!C42 -> 27660196 | K6: 4 | L6: ='REPORTE RECAUDO x BANCO'!G42 -> 0 | N6: 4 | O6: ='REPORTE RECAUDO x BANCO'!H42 -> 8186683.7 | Q6: 4 | R6: ='REPORTE RECAUDO x BANCO'!D42+'REPORTE RECAUDO x BANCO'!E42 -> 0
B7: 5 | C7: ='REPORTE RECAUDO x BANCO'!I52 -> 14445987 | E7: 5 | F7: ='REPORTE RECAUDO x BANCO'!F52 -> 0 | H7: 5 | I7: ='REPORTE RECAUDO x BANCO'!C52 -> 9759043 | K7: 5 | L7: ='REPORTE RECAUDO x BANCO'!G52 -> 1379910 | N7: 5 | O7: ='REPORTE RECAUDO x BANCO'!H52 -> 3307034 | Q7: 5 | R7: ='REPORTE RECAUDO x BANCO'!D52+'REPORTE RECAUDO x BANCO'!E52 -> 0
C8: =SUM(C3:C7) -> 1.8590478e+08 | F8: =SUM(F3:F7) -> 13407230 | I8: =SUM(I3:I7) -> 95923744 | L8: =SUM(L3:L7) -> 1379910 | O8: =SUM(O3:O7) -> 75193898 | R8: =SUM(R3:R7) -> 0
C9: =C8='REPORTE RECAUDO x BANCO'!I3 -> TRUE | F9: =F8='REPORTE RECAUDO x BANCO'!F3 -> TRUE | I9: =I8='REPORTE RECAUDO x BANCO'!C3 -> TRUE | L9: =L8='REPORTE RECAUDO x BANCO'!G3 -> TRUE | O9: =O8='REPORTE RECAUDO x BANCO'!H3 -> TRUE | R9: =R8='REPORTE RECAUDO x BANCO'!D3+'REPORTE RECAUDO x BANCO'!E3 -> TRUE
B11: ASE | C11: ANTICIPOS GENERADOS POR EXTEMPORANEOS | E11: ASE | F11: ANTICIPOS GENERADOS POR EXTEMPORANEOS | H11: ASE | I11: ANTICIPOS GENERADOS POR EXTEMPORANEOS | K11: ASE | L11: ANTICIPOS GENERADOS POR EXTEMPORANEOS | N11: ASE | O11: ANTICIPOS GENERADOS POR EXTEMPORANEOS | Q11: ASE | R11: ANTICIPOS GENERADOS POR EXTEMPORANEOS | T11: Anticipos generados por pagos aplicados de reversiones
B12: 1 | C12: ='ANT EXT-REV'!C4 -> 40630 | E12: 1 | F12: ='ANT EXT-REV'!C20 -> 0 | H12: 1 | I12: ='ANT EXT-REV'!C36 -> 0 | K12: 1 | L12: ='ANT EXT-REV'!A12 -> 0 | N12: 1 | O12: ='ANT EXT-REV'!C12 -> 40630 | Q12: 1 | R12: ='ANT EXT-REV'!C28 -> 0 | T12: Sale del reporte Recaudo reversado
B13: 2 | C13: ='ANT EXT-REV'!E4 -> 0 | E13: 2 | F13: ='ANT EXT-REV'!E20 -> 0 | H13: 2 | I13: ='ANT EXT-REV'!E36 -> 0 | K13: 2 | L13: ='ANT EXT-REV'!E44 -> 0 | N13: 2 | O13: ='ANT EXT-REV'!E12 -> 0 | Q13: 2 | R13: ='ANT EXT-REV'!E28 -> 0
B14: 3 | C14: ='ANT EXT-REV'!G4 -> 2320 | E14: 3 | F14: ='ANT EXT-REV'!G20 -> 0 | H14: 3 | I14: ='ANT EXT-REV'!G36 -> 1090 | K14: 3 | L14: ='ANT EXT-REV'!G44 -> 0 | N14: 3 | O14: ='ANT EXT-REV'!G12 -> 1230 | Q14: 3 | R14: ='ANT EXT-REV'!G28 -> 0
B15: 4 | C15: ='ANT EXT-REV'!I4 -> 10812878 | E15: 4 | F15: ='ANT EXT-REV'!I20 -> 53030 | H15: 4 | I15: ='ANT EXT-REV'!I36 -> 9321147 | K15: 4 | L15: ='ANT EXT-REV'!I44 -> 0 | N15: 4 | O15: ='ANT EXT-REV'!I12 -> 1438701 | Q15: 4 | R15: ='ANT EXT-REV'!I28 -> 0
B16: 5 | C16: ='ANT EXT-REV'!K4 -> 309980 | E16: 5 | F16: ='ANT EXT-REV'!K20 -> 0 | H16: 5 | I16: ='ANT EXT-REV'!K36 -> 0 | K16: 5 | L16: ='ANT EXT-REV'!K44 -> 0 | N16: 5 | O16: ='ANT EXT-REV'!K12 -> 309980 | Q16: 5 | R16: ='ANT EXT-REV'!K28 -> 0
C17: =SUM(C12:C16) -> 11165808 | F17: =SUM(F12:F16) -> 53030 | I17: =SUM(I12:I16) -> 9322237 | L17: =SUM(L12:L16) -> 0 | O17: =SUM(O12:O16) -> 1790541 | R17: =SUM(R12:R16) -> 0
C18: =C17='ANT EXT-REV'!M4 -> TRUE | F18: =F17='ANT EXT-REV'!M20 -> TRUE | I18: =I17='ANT EXT-REV'!M36 -> TRUE | L18: =L17='ANT EXT-REV'!M44 -> TRUE | O18: =O17='ANT EXT-REV'!M12 -> TRUE | R18: =R17='ANT EXT-REV'!M28 -> TRUE
B20: ASE | C20: ANTICIPOS QUE CARGAN POR REVERSIONES | E20: ASE | F20: ANTICIPOS QUE CARGAN POR REVERSIONES | H20: ASE | I20: ANTICIPOS QUE CARGAN POR REVERSIONES | K20: ASE | L20: ANTICIPOS QUE CARGAN POR REVERSIONES | N20: ASE | O20: ANTICIPOS QUE CARGAN POR REVERSIONES | Q20: ASE | R20: ANTICIPOS QUE CARGAN POR REVERSIONES | T20: Anticipos que cargan de reversiones
B21: 1 | C21: ='ANT EXT-REV'!D4 -> -1752.71 | E21: 1 | F21: ='ANT EXT-REV'!D20 -> 0 | H21: 1 | I21: ='ANT EXT-REV'!D36 -> -1752.71 | K21: 1 | L21: ='ANT EXT-REV'!D44 -> 0 | N21: 1 | O21: ='ANT EXT-REV'!D12 -> 0 | Q21: 1 | R21: ='ANT EXT-REV'!D28 -> 0 | T21: Sale del reporte Recaudo reversado
B22: 2 | C22: ='ANT EXT-REV'!F4 -> -310.63 | E22: 2 | F22: ='ANT EXT-REV'!F20 -> 0 | H22: 2 | I22: ='ANT EXT-REV'!F36 -> -310.63 | K22: 2 | L22: ='ANT EXT-REV'!F44 -> 0 | N22: 2 | O22: ='ANT EXT-REV'!F12 -> 0 | Q22: 2 | R22: ='ANT EXT-REV'!F28 -> 0
B23: 3 | C23: ='ANT EXT-REV'!H4 -> -984746.11 | E23: 3 | F23: ='ANT EXT-REV'!H20 -> 0 | H23: 3 | I23: ='ANT EXT-REV'!H36 -> -984746.11 | K23: 3 | L23: ='ANT EXT-REV'!H44 -> 0 | N23: 3 | O23: ='ANT EXT-REV'!H12 -> 0 | Q23: 3 | R23: ='ANT EXT-REV'!H28 -> 0
B24: 4 | C24: ='ANT EXT-REV'!J4 -> -459462.22 | E24: 4 | F24: ='ANT EXT-REV'!J20 -> 0 | H24: 4 | I24: ='ANT EXT-REV'!J36 -> -459462.22 | K24: 4 | L24: ='ANT EXT-REV'!J44 -> 0 | N24: 4 | O24: ='ANT EXT-REV'!J12 -> 0 | Q24: 4 | R24: ='ANT EXT-REV'!J28 -> 0
B25: 5 | C25: ='ANT EXT-REV'!L4 -> -133820 | E25: 5 | F25: ='ANT EXT-REV'!L20 -> 0 | H25: 5 | I25: ='ANT EXT-REV'!L36 -> -67480 | K25: 5 | L25: ='ANT EXT-REV'!L44 -> 0 | N25: 5 | O25: ='ANT EXT-REV'!L12 -> -66340 | Q25: 5 | R25: ='ANT EXT-REV'!L28 -> 0
C26: =SUM(C21:C25) -> -1580091.7 | F26: =SUM(F21:F25) -> 0 | I26: =SUM(I21:I25) -> -1513751.7 | L26: =SUM(L21:L25) -> 0 | O26: =SUM(O21:O25) -> -66340 | R26: =SUM(R21:R25) -> 0
C27: =C26='ANT EXT-REV'!N4 -> TRUE | F27: =F26='ANT EXT-REV'!N20 -> TRUE | I27: =I26='ANT EXT-REV'!N36 -> TRUE | L27: =L26='ANT EXT-REV'!N44 -> TRUE | O27: =O26='ANT EXT-REV'!N12 -> TRUE | R27: =R26='ANT EXT-REV'!N28 -> TRUE

Sheet BCE SC POR FACT.
C2: ASE | D2: SUBSIDIO | E2: CONTRIBUCION | F2: TOTAL BSC | H2: SISTEMA
C3: 1 | D3: -1.2144311e+09 | E3: 3.8037668e+09 | F3: =D3+E3 -> 2.5893357e+09 | H3: =DetRetri2026091!J9 -> 2589335717 | I3: =F3-H3 -> -0.46000004
C4: 2 | D4: -7.0202293e+09 | E4: 1.9269695e+09 | F4: =D4+E4 -> -5.0932598e+09 | H4: =DetRetri2026091!J10 -> -5093259797 | I4: =F4-H4 -> -0.21999931
C5: 3 | D5: -3.1336986e+09 | E5: 1.9033016e+09 | F5: =D5+E5 -> -1.230397e+09 | H5: =DetRetri2026091!J11 -> -1230396998 | I5: =F5-H5 -> -0.43999982
C6: 4 | D6: -4.4790574e+08 | E6: 4.8603964e+08 | F6: =D6+E6 -> 38133906 | H6: =DetRetri2026091!J12 -> 38133906 | I6: =F6-H6 -> -0.19999999
C7: 5 | D7: -2.5354614e+09 | E7: 1.3113607e+09 | F7: =D7+E7 -> -1.2241007e+09 | H7: =DetRetri2026091!J13 -> -1224100690 | I7: =F7-H7 -> -0.46000028
F9: =SUM(F3:F7) -> -4.9202879e+09 | H9: =SUM(H3:H7) -> -4920287862 | I9: =F9-H9 -> -1.7799988
H10: =H9=DetRetri2026091!J14 -> TRUE
D11: =SUM(D3:D7) -> -1.4351726e+10 | E11: =SUM(E3:E7) -> 9.4314383e+09 | F11: =SUM(D3:E7) -> -4.9202879e+09
F12: =ROUND(F11,2)=ROUND(F9,2) -> TRUE
F13: =ROUND(F11,2)-ROUND(F9,2) -> 0
D18: ASE | E18: REMUN TOTAL | F18: VALIDA 1 | G18: VALIDA 2 | H18: DIFERENCIA VALIDA 2
D19: 1 | E19: ='CONSOLIDADO_TOTAL RECAUDO'!J104 -> 2.5893357e+09 | F19: =E19=F3 -> TRUE | G19: =E19=H3 -> FALSE | H19: =E19-H3 -> -0.46000004
D20: 2 | E20: ='CONSOLIDADO_TOTAL RECAUDO'!J105 -> -5.0932598e+09 | F20: =E20=F4 -> TRUE | G20: =E20=H4 -> FALSE | H20: =E20-H4 -> -0.21999931
D21: 3 | E21: ='CONSOLIDADO_TOTAL RECAUDO'!J106 -> -1.230397e+09 | F21: =E21=F5 -> TRUE | G21: =E21=H5 -> FALSE | H21: =E21-H5 -> -0.43999982
D22: 4 | E22: ='CONSOLIDADO_TOTAL RECAUDO'!J107 -> 38133906 | F22: =E22=F6 -> TRUE | G22: =E22=H6 -> FALSE | H22: =E22-H6 -> -0.19999999
D23: 5 | E23: ='CONSOLIDADO_TOTAL RECAUDO'!J108 -> -1.2241007e+09 | F23: =E23=F7 -> TRUE | G23: =E23=H7 -> FALSE | H23: =E23-H7 -> -0.46000028
E24: =SUM(E19:E23) -> -4.9202879e+09 | F24: =E24=F9 -> TRUE | G24: =E24=H9 -> FALSE | H24: =E24-H9 -> -1.7799988

Sheet Reporte Componentes R1
B4: PROMOAMBIENTAL
F5: Total | G5: Componente TDF | H5: Componente TTL | I5: Componente TVIAT | J5: Aprovechamiento | K5: CCSA Prest.Aprov. | L5: SERVICIO ESPECIALES | M5: Componente TCS | N5: Componente TLU | O5: Componente TBL | P5: Componente TRT | Q5: CCSA Prest. No Aprov. | R5: Ajuste Decena | S5: Ajuste Recargo Aseo | T5: Intereses Cte Financiac. Aseo | U5: Exonera-Recargo Aseo | V5: Exonera-Ajuste Decena Aseo | W5: Exonera-Recargo Aseo | X5: Exonera-Recargo Aseo | Y5: Intereses Cte Financiac. Aseo | Z5: Rec.Intereses
E6: Vlr Servicio | F6: -7108.83 | G6: -502.98 | H6: -213.69 | I6: -93.3 | J6: -1231.48 | K6: -79.58 | L6: 0 | M6: -698.02 | N6: -584.16 | O6: -2331.79 | P6: -1243.99 | Q6: -129.84 | R6: 0 | S6: 0 | T6: 0 | U6: 0 | V6: 0 | W6: 0 | X6: 0 | Y6: 0 | Z6: 0
D7: E | E7: Total | F7: -7108.83 | G7: -502.98 | H7: -213.69 | I7: -93.3 | J7: -1231.48 | K7: -79.58 | L7: 0 | M7: -698.02 | N7: -584.16 | O7: -2331.79 | P7: -1243.99 | Q7: -129.84 | R7: 0 | S7: 0 | T7: 0 | U7: 0 | V7: 0 | W7: 0 | X7: 0 | Y7: 0 | Z7: 0
C8: ENEL | D8: Total | F8: -7108.83 | G8: -502.98 | H8: -213.69 | I8: -93.3 | J8: -1231.48 | K8: -79.58 | L8: 0 | M8: -698.02 | N8: -584.16 | O8: -2331.79 | P8: -1243.99 | Q8: -129.84 | R8: 0 | S8: 0 | T8: 0 | U8: 0 | V8: 0 | W8: 0 | X8: 0 | Y8: 0 | Z8: 0
B9: Mes | C9: Total | F9: -7108.83 | G9: -502.98 | H9: -213.69 | I9: -93.3 | J9: -1231.48 | K9: -79.58 | L9: 0 | M9: -698.02 | N9: -584.16 | O9: -2331.79 | P9: -1243.99 | Q9: -129.84 | R9: 0 | S9: 0 | T9: 0 | U9: 0 | V9: 0 | W9: 0 | X9: 0 | Y9: 0 | Z9: 0
A10: AFaseo | B10: Total | F10: -7108.83 | G10: -502.98 | H10: -213.69 | I10: -93.3 | J10: -1231.48 | K10: -79.58 | L10: 0 | M10: -698.02 | N10: -584.16 | O10: -2331.79 | P10: -1243.99 | Q10: -129.84 | R10: 0 | S10: 0 | T10: 0 | U10: 0 | V10: 0 | W10: 0 | X10: 0 | Y10: 0 | Z10: 0
E11: Vlr Servicio | F11: 42672.75 | G11: 2083.59 | H11: 1160.96 | I11: 617.46 | J11: 10415.64 | K11: 383.02 | L11: 0 | M11: 3359.81 | N11: 3220.39 | O11: 15117.23 | P11: 5690.79 | Q11: 624.92 | R11: -1.06 | S11: 0 | T11: 0 | U11: 0 | V11: 0 | W11: 0 | X11: 0 | Y11: 0 | Z11: 0
E12: Vlr Intereses | F12: 7.25 | G12: 0.35 | H12: 0.2 | I12: 0.1 | J12: 1.77 | K12: 0.07 | L12: 0 | M12: 0.57 | N12: 0.54 | O12: 2.57 | P12: 0.97 | Q12: 0.11 | R12: 0 | S12: 0 | T12: 0 | U12: 0 | V12: 0 | W12: 0 | X12: 0 | Y12: 0 | Z12: 0
D13: T | E13: Total | F13: 42680 | G13: 2083.94 | H13: 1161.16 | I13: 617.56 | J13: 10417.41 | K13: 383.09 | L13: 0 | M13: 3360.38 | N13: 3220.93 | O13: 15119.8 | P13: 5691.76 | Q13: 625.03 | R13: -1.06 | S13: 0 | T13: 0 | U13: 0 | V13: 0 | W13: 0 | X13: 0 | Y13: 0 | Z13: 0
C14: OCCIDENTE | D14: Total | F14: 42680 | G14: 2083.94 | H14: 1161.16 | I14: 617.56 | J14: 10417.41 | K14: 383.09 | L14: 0 | M14: 3360.38 | N14: 3220.93 | O14: 15119.8 | P14: 5691.76 | Q14: 625.03 | R14: -1.06 | S14: 0 | T14: 0 | U14: 0 | V14: 0 | W14: 0 | X14: 0 | Y14: 0 | Z14: 0
B15: Aplicacion nuevos x reversion | C15: Total | F15: 42680 | G15: 2083.94 | H15: 1161.16 | I15: 617.56 | J15: 10417.41 | K15: 383.09 | L15: 0 | M15: 3360.38 | N15: 3220.93 | O15: 15119.8 | P15: 5691.76 | Q15: 625.03 | R15: -1.06 | S15: 0 | T15: 0 | U15: 0 | V15: 0 | W15: 0 | X15: 0 | Y15: 0 | Z15: 0
E16: Vlr Servicio | F16: 1.9865858e+10 | G16: 9.4982754e+08 | H16: 5.3058782e+08 | I16: 2.8117925e+08 | J16: 4.8115398e+09 | K16: 1.8047125e+08 | L16: 28843603 | M16: 1.5840574e+09 | N16: 1.5109569e+09 | O16: 7.108873e+09 | P16: 2.585077e+09 | Q16: 2.9449051e+08 | R16: -46186.47 | S16: 0 | T16: 0 | U16: 0 | V16: 0 | W16: 0 | X16: 0 | Y16: 0 | Z16: 0
E17: Vlr Intereses | F17: 3221187.2 | G17: 191257.04 | H17: 96240.8 | I17: 48070.33 | J17: 691627.43 | K17: 30779.35 | L17: 1888.23 | M17: 270442.29 | N17: 245214.4 | O17: 1082415 | P17: 513014.61 | Q17: 50206.13 | R17: -5.69 | S17: 0 | T17: 53.13 | U17: 0 | V17: 0 | W17: 0 | X17: 0 | Y17: 0 | Z17: -15.86
D18: E | E18: Total | F18: 1.9869079e+10 | G18: 9.500188e+08 | H18: 5.3068406e+08 | I18: 2.8122732e+08 | J18: 4.8122314e+09 | K18: 1.8050203e+08 | L18: 28845491 | M18: 1.5843279e+09 | N18: 1.5112021e+09 | O18: 7.1099554e+09 | P18: 2.58559e+09 | Q18: 2.9454072e+08 | R18: -46192.16 | S18: 0 | T18: 53.13 | U18: 0 | V18: 0 | W18: 0 | X18: 0 | Y18: 0 | Z18: -15.86
C19: ENEL | D19: Total | F19: 1.9869079e+10 | G19: 9.500188e+08 | H19: 5.3068406e+08 | I19: 2.8122732e+08 | J19: 4.8122314e+09 | K19: 1.8050203e+08 | L19: 28845491 | M19: 1.5843279e+09 | N19: 1.5112021e+09 | O19: 7.1099554e+09 | P19: 2.58559e+09 | Q19: 2.9454072e+08 | R19: -46192.16 | S19: 0 | T19: 53.13 | U19: 0 | V19: 0 | W19: 0 | X19: 0 | Y19: 0 | Z19: -15.86
E20: Vlr Servicio | F20: 34834776 | G20: 3050420.4 | H20: 1694569.4 | I20: 901684.59 | J20: 6258963.8 | K20: 206736.51 | L20: 0 | M20: 1810170.8 | N20: 2156347.4 | O20: 10098959 | P20: 8319284.7 | Q20: 337911.22 | R20: -271.21 | S20: 0 | T20: 0 | U20: 0 | V20: 0 | W20: 0 | X20: 0 | Y20: 0 | Z20: 0
E21: Vlr Intereses | F21: 73612.43 | G21: 3963.92 | H21: 2089.52 | I21: 1132.4 | J21: 18172.87 | K21: 548.71 | L21: 0 | M21: 4821.44 | N21: 5503.49 | O21: 25681.1 | P21: 10802.17 | Q21: 897.07 | R21: -0.3 | S21: 0 | T21: 0.04 | U21: 0 | V21: 0 | W21: 0 | X21: 0 | Y21: 0 | Z21: 0
D22: H | E22: Total | F22: 34908389 | G22: 3054384.4 | H22: 1696658.9 | I22: 902816.99 | J22: 6277136.7 | K22: 207285.22 | L22: 0 | M22: 1814992.3 | N22: 2161850.9 | O22: 10124640 | P22: 8330086.8 | Q22: 338808.29 | R22: -271.51 | S22: 0 | T22: 0.04 | U22: 0 | V22: 0 | W22: 0 | X22: 0 | Y22: 0 | Z22: 0
E23: Vlr Servicio | F23: 99460670 | G23: 8743467.5 | H23: 4501924.5 | I23: 2257268.8 | J23: 15226576 | K23: 720340.83 | L23: 71191.32 | M23: 6347720.1 | N23: 6458242.7 | O23: 29949150 | P23: 24008686 | Q23: 1175914.7 | R23: 186.99 | S23: 0 | T23: 0 | U23: 0 | V23: 0 | W23: 0 | X23: 0 | Y23: 0 | Z23: 0
E24: Vlr Intereses | F24: 8554576 | G24: 822696.95 | H24: 248641.09 | I24: 50902.54 | J24: 1306165.8 | K24: 80047.98 | L24: 0 | M24: 702034.32 | N24: 586868.46 | O24: 2182750.4 | P24: 2443333.5 | Q24: 130594.62 | R24: 184.84 | S24: 0 | T24: 355.38 | U24: 0 | V24: 0 | W24: 0 | X24: 0 | Y24: 0 | Z24: 0
D25: O | E25: Total | F25: 1.0801525e+08 | G25: 9566164.5 | H25: 4750565.5 | I25: 2308171.3 | J25: 16532742 | K25: 800388.81 | L25: 71191.32 | M25: 7049754.4 | N25: 7045111.2 | O25: 32131901 | P25: 26452020 | Q25: 1306509.3 | R25: 371.83 | S25: 0 | T25: 355.38 | U25: 0 | V25: 0 | W25: 0 | X25: 0 | Y25: 0 | Z25: 0
E26: Vlr Servicio | F26: 2.3738431e+08 | G26: 38284622 | H26: 21414097 | I26: 11342632 | J26: 19779058 | K26: 508140.34 | L26: 1717780 | M26: 4440916.8 | N26: 6082873.5 | O26: 28426345 | P26: 1.0455968e+08 | Q26: 828965.34 | R26: -796.43 | S26: 0 | T26: 0 | U26: 0 | V26: 0 | W26: 0 | X26: 0 | Y26: 0 | Z26: 0
E27: Vlr Intereses | F27: 1223054.1 | G27: 158799.91 | H27: 78943.63 | I27: 38013.15 | J27: 162199.93 | K27: 5653.98 | L27: 1207.03 | M27: 49618.45 | N27: 61442.74 | O27: 241587.84 | P27: 416341.81 | Q27: 9230.55 | R27: 15.01 | S27: -0.06 | T27: 0.11 | U27: 0 | V27: 0 | W27: 0 | X27: 0 | Y27: 0 | Z27: 0
D28: T | E28: Total | F28: 2.3860737e+08 | G28: 38443422 | H28: 21493041 | I28: 11380645 | J28: 19941258 | K28: 513794.32 | L28: 1718987 | M28: 4490535.3 | N28: 6144316.2 | O28: 28667933 | P28: 1.0497602e+08 | Q28: 838195.89 | R28: -781.42 | S28: -0.06 | T28: 0.11 | U28: 0 | V28: 0 | W28: 0 | X28: 0 | Y28: 0 | Z28: 0
C29: OCCIDENTE | D29: Total | F29: 3.81531e+08 | G29: 51063971 | H29: 27940265 | I29: 14591634 | J29: 42751137 | K29: 1521468.4 | L29: 1790178.4 | M29: 13355282 | N29: 15351278 | O29: 70924473 | P29: 1.3975813e+08 | Q29: 2483513.5 | R29: -681.1 | S29: -0.06 | T29: 355.53 | U29: 0 | V29: 0 | W29: 0 | X29: 0 | Y29: 0 | Z29: 0
B30: Mes | C30: Total | F30: 2.025061e+10 | G30: 1.0010828e+09 | H30: 5.5862433e+08 | I30: 2.9581895e+08 | J30: 4.8549825e+09 | K30: 1.820235e+08 | L30: 30635670 | M30: 1.5976832e+09 | N30: 1.5265534e+09 | O30: 7.1808799e+09 | P30: 2.7253481e+09 | Q30: 2.9702423e+08 | R30: -46873.26 | S30: -0.06 | T30: 408.66 | U30: 0 | V30: 0 | W30: 0 | X30: 0 | Y30: 0 | Z30: -15.86
A31: Componente | B31: Total | F31: 2.0250653e+10 | G31: 1.0010849e+09 | H31: 5.5862549e+08 | I31: 2.9581957e+08 | J31: 4.8549929e+09 | K31: 1.8202388e+08 | L31: 30635670 | M31: 1.5976865e+09 | N31: 1.5265566e+09 | O31: 7.180895e+09 | P31: 2.7253538e+09 | Q31: 2.9702486e+08 | R31: -46874.32 | S31: -0.06 | T31: 408.66 | U31: 0 | V31: 0 | W31: 0 | X31: 0 | Y31: 0 | Z31: -15.86
E32: Subsidio(-)/Contribucion(+) | F32: -2.946116e+09 | G32: -66231005 | H32: -36832734 | I32: -19652614 | J32: -8.2718576e+08 | K32: -30673428 | L32: 0 | M32: -2.6937726e+08 | N32: -2.5777835e+08 | O32: -1.2109156e+09 | P32: -1.7742294e+08 | Q32: -50046274 | R32: 0 | S32: 0 | T32: 0 | U32: 0 | V32: 0 | W32: 0 | X32: 0 | Y32: 0 | Z32: 0
D33: E | E33: Total | F33: -2.946116e+09 | G33: -66231005 | H33: -36832734 | I33: -19652614 | J33: -8.2718576e+08 | K33: -30673428 | L33: 0 | M33: -2.6937726e+08 | N33: -2.5777835e+08 | O33: -1.2109156e+09 | P33: -1.7742294e+08 | Q33: -50046274 | R33: 0 | S33: 0 | T33: 0 | U33: 0 | V33: 0 | W33: 0 | X33: 0 | Y33: 0 | Z33: 0
C34: ENEL | D34: Total | F34: -2.946116e+09 | G34: -66231005 | H34: -36832734 | I34: -19652614 | J34: -8.2718576e+08 | K34: -30673428 | L34: 0 | M34: -2.6937726e+08 | N34: -2.5777835e+08 | O34: -1.2109156e+09 | P34: -1.7742294e+08 | Q34: -50046274 | R34: 0 | S34: 0 | T34: 0 | U34: 0 | V34: 0 | W34: 0 | X34: 0 | Y34: 0 | Z34: 0
E35: Subsidio(-)/Contribucion(+) | F35: 6948561.3 | G35: 1410581.2 | H35: 792768.83 | I35: 419896.52 | J35: 180596.23 | K35: -3882.3 | L35: 0 | M35: -34057.21 | N35: 57414.32 | O35: 271593.35 | P35: 3859983.6 | Q35: -6333.32 | R35: 0 | S35: 0 | T35: 0 | U35: 0 | V35: 0 | W35: 0 | X35: 0 | Y35: 0 | Z35: 0
D36: H | E36: Total | F36: 6948561.3 | G36: 1410581.2 | H36: 792768.83 | I36: 419896.52 | J36: 180596.23 | K36: -3882.3 | L36: 0 | M36: -34057.21 | N36: 57414.32 | O36: 271593.35 | P36: 3859983.6 | Q36: -6333.32 | R36: 0 | S36: 0 | T36: 0 | U36: 0 | V36: 0 | W36: 0 | X36: 0 | Y36: 0 | Z36: 0
E37: Subsidio(-)/Contribucion(+) | F37: 18379766 | G37: 3896523 | H37: 1932685.5 | I37: 904936.27 | J37: 174866.47 | K37: -4332.57 | L37: 0 | M37: -47024.58 | N37: 133689.19 | O37: 548414.37 | P37: 10847077 | Q37: -7068.65 | R37: 0 | S37: 0 | T37: 0 | U37: 0 | V37: 0 | W37: 0 | X37: 0 | Y37: 0 | Z37: 0
D38: O | E38: Total | F38: 18379766 | G38: 3896523 | H38: 1932685.5 | I38: 904936.27 | J38: 174866.47 | K38: -4332.57 | L38: 0 | M38: -47024.58 | N38: 133689.19 | O38: 548414.37 | P38: 10847077 | Q38: -7068.65 | R38: 0 | S38: 0 | T38: 0 | U38: 0 | V38: 0 | W38: 0 | X38: 0 | Y38: 0 | Z38: 0
E39: Subsidio(-)/Contribucion(+) | F39: 1.1972783e+08 | G39: 21174918 | H39: 11896575 | I39: 6266740.5 | J39: 7356037.8 | K39: 191531.36 | L39: 0 | M39: 1677524.2 | N39: 2303267 | O39: 10782216 | P39: 57766394 | Q39: 312627.59 | R39: 0 | S39: 0 | T39: 0 | U39: 0 | V39: 0 | W39: 0 | X39: 0 | Y39: 0 | Z39: 0
D40: T | E40: Total | F40: 1.1972783e+08 | G40: 21174918 | H40: 11896575 | I40: 6266740.5 | J40: 7356037.8 | K40: 191531.36 | L40: 0 | M40: 1677524.2 | N40: 2303267 | O40: 10782216 | P40: 57766394 | Q40: 312627.59 | R40: 0 | S40: 0 | T40: 0 | U40: 0 | V40: 0 | W40: 0 | X40: 0 | Y40: 0 | Z40: 0
C41: OCCIDENTE | D41: Total | F41: 1.4505616e+08 | G41: 26482022 | H41: 14622030 | I41: 7591573.3 | J41: 7711500.5 | K41: 183316.49 | L41: 0 | M41: 1596442.5 | N41: 2494370.5 | O41: 11602224 | P41: 72473455 | Q41: 299225.62 | R41: 0 | S41: 0 | T41: 0 | U41: 0 | V41: 0 | W41: 0 | X41: 0 | Y41: 0 | Z41: 0
B42: Mes | C42: Total | F42: -2.8010598e+09 | G42: -39748983 | H42: -22210705 | I42: -12061041 | J42: -8.1947426e+08 | K42: -30490112 | L42: 0 | M42: -2.6778081e+08 | N42: -2.5528398e+08 | O42: -1.1993134e+09 | P42: -1.0494949e+08 | Q42: -49747048 | R42: 0 | S42: 0 | T42: 0 | U42: 0 | V42: 0 | W42: 0 | X42: 0 | Y42: 0 | Z42: 0
A43: Subs/Cont | B43: Total | F43: -2.8010598e+09 | G43: -39748983 | H43: -22210705 | I43: -12061041 | J43: -8.1947426e+08 | K43: -30490112 | L43: 0 | M43: -2.6778081e+08 | N43: -2.5528398e+08 | O43: -1.1993134e+09 | P43: -1.0494949e+08 | Q43: -49747048 | R43: 0 | S43: 0 | T43: 0 | U43: 0 | V43: 0 | W43: 0 | X43: 0 | Y43: 0 | Z43: 0
A44: Total | F44: 1.7449586e+10 | G44: 9.6133536e+08 | H44: 5.3641457e+08 | I44: 2.8375844e+08 | J44: 4.0355174e+09 | K44: 1.5153369e+08 | L44: 30635670 | M44: 1.329905e+09 | N44: 1.271272e+09 | O44: 5.9815793e+09 | P44: 2.6204031e+09 | Q44: 2.4727768e+08 | R44: -46874.32 | S44: -0.06 | T44: 408.66 | U44: 0 | V44: 0 | W44: 0 | X44: 0 | Y44: 0 | Z44: -15.86
C47: TOTAL | D47: OPORTUNO | E47: Total | F47: =F30+F42+F9-L9-L30 -> 1.7418907e+10 | G47: =G30+G9 -> 1.0010823e+09 | H47: =H30+H9 -> 5.5862411e+08 | I47: =I30+I9 -> 2.9581886e+08 | J47: =J30+J9 -> 4.8549813e+09 | K47: =K30+K9 -> 1.8202342e+08 | L47: =L30+L9 -> 30635670 | M47: =M30+M9 -> 1.5976825e+09 | N47: =N30+N9 -> 1.5265528e+09 | ... AP47: =AP30+AP9 -> 0
E48: Subsidio(-)/Contribucion(+) | F48: =F42 -> -2.8010598e+09
D49: EXTEMPORANEO | E49: Total | F49: =F15-L15 -> 42680 | G49: =G15 -> 2083.94 | H49: =H15 -> 1161.16 | I49: =I15 -> 617.56 | J49: =J15 -> 10417.41 | K49: =K15 -> 383.09 | L49: =L15 -> 0 | M49: =M15 -> 3360.38 | N49: =N15 -> 3220.93 | ... AP49: =AP15 -> 0
E50: Subsidio(-)/Contribucion(+) | F50: 0
C52: RECIPROCIDAD | D52: OPORTUNO | E52: Total | F52: 0 | G52: 0 | H52: 0 | I52: 0 | J52: 0 | K52: 0 | L52: 0 | M52: 0 | N52: 0 | O52: 0 | P52: 0 | Q52: 0 | R52: 0 | S52: 0 | T52: 0 | U52: 0 | V52: 0 | W52: 0 | X52: 0 | Y52: 0 | Z52: 0 | AA52: 0 | AB52: 0 | AC52: 0 | AD52: 0 | AE52: 0 | AF52: 0 | AG52: 0 | AH52: 0 | AI52: 0 | AJ52: 0 | AK52: 0 | AL52: 0 | AM52: 0 | AN52: 0 | AO52: 0 | AP52: 0
E53: Subsidio(-)/Contribucion(+) | F53: 0
D54: EXTEMPORANEO | E54: Total | F54: 0 | G54: 0 | H54: 0 | I54: 0 | J54: 0 | K54: 0 | L54: 0 | M54: 0 | N54: 0 | O54: 0 | P54: 0 | Q54: 0 | R54: 0 | S54: 0 | T54: 0 | U54: 0 | V54: 0 | W54: 0 | X54: 0 | Y54: 0 | Z54: 0 | AA54: 0 | AB54: 0 | AC54: 0 | AD54: 0 | AE54: 0 | AF54: 0 | AG54: 0 | AH54: 0 | AI54: 0 | AJ54: 0 | AK54: 0 | AL54: 0 | AM54: 0 | AN54: 0 | AO54: 0 | AP54: 0
E55: Subsidio(-)/Contribucion(+) | F55: 0
C57: ENEL | D57: OPORTUNO | E57: Total | F57: =F34+F19+F8-L8-L19 -> 1.689411e+10 | G57: =G19 -> 9.500188e+08 | H57: =H19 -> 5.3068406e+08 | I57: =I19 -> 2.8122732e+08 | J57: =J19 -> 4.8122314e+09 | K57: =K19 -> 1.8050203e+08 | L57: =L19 -> 28845491 | M57: =M19 -> 1.5843279e+09 | N57: =N19 -> 1.5112021e+09 | ... AP57: =AP19 -> 0
E58: Subsidio(-)/Contribucion(+) | F58: =F34 -> -2.946116e+09
D59: EXTEMPORANEO | E59: Total | F59: 0 | G59: 0 | H59: 0 | I59: 0 | J59: 0 | K59: 0 | L59: 0 | M59: 0 | N59: 0 | O59: 0 | P59: 0 | Q59: 0 | R59: 0 | S59: 0 | T59: 0 | U59: 0 | V59: 0 | W59: 0 | X59: 0 | Y59: 0 | Z59: 0 | AA59: 0 | AB59: 0 | AC59: 0 | AD59: 0 | AE59: 0 | AF59: 0 | AG59: 0 | AH59: 0 | AI59: 0 | AJ59: 0 | AK59: 0 | AL59: 0 | AM59: 0 | AN59: 0 | AO59: 0 | AP59: 0
E60: Subsidio(-)/Contribucion(+) | F60: 0
C62: ENERBIT | D62: OPORTUNO | E62: Total | F62: 0 | G62: 0 | H62: 0 | I62: 0 | J62: 0 | K62: 0 | L62: 0 | M62: 0 | N62: 0 | O62: 0 | P62: 0 | Q62: 0 | R62: 0 | S62: 0 | T62: 0 | U62: 0 | V62: 0 | W62: 0 | X62: 0 | Y62: 0 | Z62: 0 | AA62: 0 | AB62: 0 | AC62: 0 | AD62: 0 | AE62: 0 | AF62: 0 | AG62: 0 | AH62: 0 | AI62: 0 | AJ62: 0 | AK62: 0 | AL62: 0 | AM62: 0 | AN62: 0 | AO62: 0
E63: Subsidio(-)/Contribucion(+) | F63: 0
D64: EXTEMPORANEO | E64: Total | F64: 0 | G64: 0 | H64: 0 | I64: 0 | J64: 0 | K64: 0 | L64: 0 | M64: 0 | N64: 0 | O64: 0 | P64: 0 | Q64: 0 | R64: 0 | S64: 0 | T64: 0 | U64: 0 | V64: 0 | W64: 0 | X64: 0 | Y64: 0 | Z64: 0 | AA64: 0 | AB64: 0 | AC64: 0 | AD64: 0 | AE64: 0 | AF64: 0 | AG64: 0 | AH64: 0 | AI64: 0 | AJ64: 0 | AK64: 0 | AL64: 0 | AM64: 0 | AN64: 0 | AO64: 0
E65: Subsidio(-)/Contribucion(+) | F65: 0
C67: OCCIDENTE | D67: OPORTUNO | E67: Total | F67: =F41+F29-L29 -> 5.2479698e+08 | G67: =G29+G8 -> 51063468 | H67: =H29+H8 -> 27940051 | I67: =I29+I8 -> 14591541 | J67: =J29+J8 -> 42749906 | K67: =K29+K8 -> 1521388.8 | L67: =L29+L8 -> 1790178.4 | M67: =M29+M8 -> 13354584 | N67: =N29+N8 -> 15350694 | ... AP67: =AP29+AP8 -> 0
E68: Subsidio(-)/Contribucion(+) | F68: =F41 -> 1.4505616e+08
D69: EXTEMPORANEO | E69: Total | F69: =F14-L14 -> 42680 | G69: =G14 -> 2083.94 | H69: =H14 -> 1161.16 | I69: =I14 -> 617.56 | J69: =J14 -> 10417.41 | K69: =K14 -> 383.09 | L69: =L14 -> 0 | M69: =M14 -> 3360.38 | N69: =N14 -> 3220.93 | ... AP69: =AP14 -> 0
E70: Subsidio(-)/Contribucion(+) | F70: 0
C72: CIUDAD LIMPIA-ACUEDUCTO | D72: OPORTUNO | E72: Total | F72: 0 | G72: 0 | H72: 0 | I72: 0 | J72: 0 | K72: 0 | L72: 0 | M72: 0 | N72: 0 | O72: 0 | P72: 0 | Q72: 0 | R72: 0 | S72: 0 | T72: 0 | U72: 0 | V72: 0 | W72: 0 | X72: 0 | Y72: 0 | Z72: 0 | AA72: 0 | AB72: 0 | AC72: 0 | AD72: 0 | AE72: 0 | AF72: 0 | AG72: 0 | AH72: 0 | AI72: 0 | AJ72: 0 | AK72: 0 | AL72: 0 | AM72: 0 | AN72: 0 | AO72: 0 | AP72: 0
E73: Subsidio(-)/Contribucion(+) | F73: 0
D74: EXTEMPORANEO | E74: Total | F74: 0 | G74: 0 | H74: 0 | I74: 0 | J74: 0 | K74: 0 | L74: 0 | M74: 0 | N74: 0 | O74: 0 | P74: 0 | Q74: 0 | R74: 0 | S74: 0 | T74: 0 | U74: 0 | V74: 0 | W74: 0 | X74: 0 | Y74: 0 | Z74: 0 | AA74: 0 | AB74: 0 | AC74: 0 | AD74: 0 | AE74: 0 | AF74: 0 | AG74: 0 | AH74: 0 | AI74: 0 | AJ74: 0 | AK74: 0 | AL74: 0 | AM74: 0 | AN74: 0 | AO74: 0 | AP74: 0
E75: Subsidio(-)/Contribucion(+) | F75: 0
D77: AFaseo | E77: Total | F77: =F10 -> -7108.83 | G77: =G10 -> -502.98 | H77: =H10 -> -213.69 | I77: =I10 -> -93.3 | J77: =J10 -> -1231.48 | K77: =K10 -> -79.58 | L77: =L10 -> 0 | M77: =M10 -> -698.02 | ... AP77: =AP10 -> 0
B80: LIME
F81: Total | G81: Componente TDF | H81: Componente TTL | I81: Componente TVIAT | J81: Aprovechamiento | K81: CCSA Prest.Aprov. | L81: SERVICIO ESPECIALES | M81: Componente TCS | N81: Componente TLU | O81: Componente TBL | P81: Componente TRT | Q81: CCSA Prest. No Aprov. | R81: Ajuste Decena | S81: Ajuste Recargo Aseo | T81: Intereses Cte Financiac. Aseo | U81: Exonera-Recargo Aseo | V81: Exonera-Ajuste Decena Aseo | W81: Exonera-Recargo Aseo | X81: Exonera-Recargo Aseo | Y81: Intereses Cte Financiac. Aseo | Z81: Rec.Intereses
E82: Vlr Servicio | F82: -248232.18 | G82: -22158.18 | H82: -9413.47 | I82: -4110.92 | J82: -49703.6 | K82: -2047.9 | L82: 0 | M82: -17964.77 | N82: -22519.09 | O82: -75640.01 | P82: -41332.7 | Q82: -3341.54 | R82: 0 | S82: 0 | T82: 0 | U82: 0 | V82: 0 | W82: 0 | X82: 0 | Y82: 0 | Z82: 0
D83: E | E83: Total | F83: -248232.18 | G83: -22158.18 | H83: -9413.47 | I83: -4110.92 | J83: -49703.6 | K83: -2047.9 | L83: 0 | M83: -17964.77 | N83: -22519.09 | O83: -75640.01 | P83: -41332.7 | Q83: -3341.54 | R83: 0 | S83: 0 | T83: 0 | U83: 0 | V83: 0 | W83: 0 | X83: 0 | Y83: 0 | Z83: 0
C84: ENEL | D84: Total | F84: -248232.18 | G84: -22158.18 | H84: -9413.47 | I84: -4110.92 | J84: -49703.6 | K84: -2047.9 | L84: 0 | M84: -17964.77 | N84: -22519.09 | O84: -75640.01 | P84: -41332.7 | Q84: -3341.54 | R84: 0 | S84: 0 | T84: 0 | U84: 0 | V84: 0 | W84: 0 | X84: 0 | Y84: 0 | Z84: 0
E85: Vlr Servicio | F85: -3708.89 | G85: -311.76 | H85: -132.43 | I85: -57.84 | J85: -769.62 | K85: -31.73 | L85: 0 | M85: -278.16 | N85: -348.68 | O85: -1171.2 | P85: -555.75 | Q85: -51.72 | R85: 0 | S85: 0 | T85: 0 | U85: 0 | V85: 0 | W85: 0 | X85: 0 | Y85: 0 | Z85: 0
D86: H | E86: Total | F86: -3708.89 | G86: -311.76 | H86: -132.43 | I86: -57.84 | J86: -769.62 | K86: -31.73 | L86: 0 | M86: -278.16 | N86: -348.68 | O86: -1171.2 | P86: -555.75 | Q86: -51.72 | R86: 0 | S86: 0 | T86: 0 | U86: 0 | V86: 0 | W86: 0 | X86: 0 | Y86: 0 | Z86: 0
E87: Vlr Servicio | F87: -22830.34 | G87: -2120.73 | H87: -900.96 | I87: -393.42 | J87: -4489.36 | K87: -184.98 | L87: 0 | M87: -1622.61 | N87: -2033.98 | O87: -6831.99 | P87: -3950.51 | Q87: -301.8 | R87: 0 | S87: 0 | T87: 0 | U87: 0 | V87: 0 | W87: 0 | X87: 0 | Y87: 0 | Z87: 0
D88: O | E88: Total | F88: -22830.34 | G88: -2120.73 | H88: -900.96 | I88: -393.42 | J88: -4489.36 | K88: -184.98 | L88: 0 | M88: -1622.61 | N88: -2033.98 | O88: -6831.99 | P88: -3950.51 | Q88: -301.8 | R88: 0 | S88: 0 | T88: 0 | U88: 0 | V88: 0 | W88: 0 | X88: 0 | Y88: 0 | Z88: 0
C89: OCCIDENTE | D89: Total | F89: -26539.23 | G89: -2432.49 | H89: -1033.39 | I89: -451.26 | J89: -5258.98 | K89: -216.71 | L89: 0 | M89: -1900.77 | N89: -2382.66 | O89: -8003.19 | P89: -4506.26 | Q89: -353.52 | R89: 0 | S89: 0 | T89: 0 | U89: 0 | V89: 0 | W89: 0 | X89: 0 | Y89: 0 | Z89: 0
B90: Mes | C90: Total | F90: -274771.41 | G90: -24590.67 | H90: -10446.86 | I90: -4562.18 | J90: -54962.58 | K90: -2264.61 | L90: 0 | M90: -19865.54 | N90: -24901.75 | O90: -83643.2 | P90: -45838.96 | Q90: -3695.06 | R90: 0 | S90: 0 | T90: 0 | U90: 0 | V90: 0 | W90: 0 | X90: 0 | Y90: 0 | Z90: 0
A91: AFaseo | B91: Total | F91: -274771.41 | G91: -24590.67 | H91: -10446.86 | I91: -4562.18 | J91: -54962.58 | K91: -2264.61 | L91: 0 | M91: -19865.54 | N91: -24901.75 | O91: -83643.2 | P91: -45838.96 | Q91: -3695.06 | R91: 0 | S91: 0 | T91: 0 | U91: 0 | V91: 0 | W91: 0 | X91: 0 | Y91: 0 | Z91: 0
E92: Vlr Servicio | F92: 1.6685741e+10 | G92: 9.1959102e+08 | H92: 5.1273951e+08 | I92: 2.7108344e+08 | J92: 4.2917994e+09 | K92: 1.470824e+08 | L92: 12943377 | M92: 1.2893405e+09 | N92: 1.2645254e+09 | O92: 5.9339796e+09 | P92: 1.8022125e+09 | Q92: 2.4039084e+08 | R92: 52510.15 | S92: 0 | T92: 0 | U92: 0 | V92: 0 | W92: 0 | X92: 0 | Y92: 0 | Z92: 0
E93: Vlr Intereses | F93: 78737842 | G93: 9460273.4 | H93: 4424900.5 | I93: 1934559 | J93: 14260430 | K93: 511443.13 | L93: 15763.97 | M93: 4483671.1 | N93: 5230341.7 | O93: 19009918 | P93: 18562623 | Q93: 834701.88 | R93: 9249.55 | S93: -4.22 | T93: 0.1 | U93: 0 | V93: 0 | W93: 0 | X93: 0 | Y93: 0 | Z93: -30.45
D94: E | E94: Total | F94: 1.6764478e+10 | G94: 9.2905129e+08 | H94: 5.1716441e+08 | I94: 2.73018e+08 | J94: 4.3060598e+09 | K94: 1.4759384e+08 | L94: 12959141 | M94: 1.2938242e+09 | N94: 1.2697557e+09 | O94: 5.9529895e+09 | P94: 1.8207751e+09 | Q94: 2.4122554e+08 | R94: 61759.7 | S94: -4.22 | T94: 0.1 | U94: 0 | V94: 0 | W94: 0 | X94: 0 | Y94: 0 | Z94: -30.45
C95: ENEL | D95: Total | F95: 1.6764478e+10 | G95: 9.2905129e+08 | H95: 5.1716441e+08 | I95: 2.73018e+08 | J95: 4.3060598e+09 | K95: 1.4759384e+08 | L95: 12959141 | M95: 1.2938242e+09 | N95: 1.2697557e+09 | O95: 5.9529895e+09 | P95: 1.8207751e+09 | Q95: 2.4122554e+08 | R95: 61759.7 | S95: -4.22 | T95: 0.1 | U95: 0 | V95: 0 | W95: 0 | X95: 0 | Y95: 0 | Z95: -30.45
E96: Vlr Servicio | F96: 801481.23 | G96: 65507.33 | H96: 33525.01 | I96: 16830.45 | J96: 178494.6 | K96: 6230.79 | L96: 0 | M96: 54509.86 | N96: 57104.8 | O96: 249196.3 | P96: 129916.42 | Q96: 10165.96 | R96: -0.29 | S96: 0 | T96: 0 | U96: 0 | V96: 0 | W96: 0 | X96: 0 | Y96: 0 | Z96: 0
E97: Vlr Intereses | F97: 40975.59 | G97: 3240.77 | H97: 1616.94 | I97: 765.23 | J97: 9414.75 | K97: 324.5 | L97: 0 | M97: 2843.79 | N97: 3391.48 | O97: 12527.15 | P97: 6321.75 | Q97: 529.49 | R97: -1.68 | S97: 1.42 | T97: 0 | U97: 0 | V97: 0 | W97: 0 | X97: 0 | Y97: 0 | Z97: 0
D98: 1 | E98: Total | F98: 842456.82 | G98: 68748.1 | H98: 35141.95 | I98: 17595.68 | J98: 187909.35 | K98: 6555.29 | L98: 0 | M98: 57353.65 | N98: 60496.28 | O98: 261723.45 | P98: 136238.17 | Q98: 10695.45 | R98: -1.97 | S98: 1.42 | T98: 0 | U98: 0 | V98: 0 | W98: 0 | X98: 0 | Y98: 0 | Z98: 0
E99: Vlr Servicio | F99: 143981.13 | G99: 12534.22 | H99: 10637.79 | I99: 5634.58 | J99: 35725.67 | K99: 880.45 | L99: 0 | M99: 3402.08 | N99: 4736.62 | O99: 52366.57 | P99: 16629.67 | Q99: 1436.53 | R99: -3.05 | S99: 0 | T99: 0 | U99: 0 | V99: 0 | W99: 0 | X99: 0 | Y99: 0 | Z99: 0
E100: Vlr Intereses | F100: 5018.2 | G100: 410.44 | H100: 387.85 | I100: 206.95 | J100: 1339.76 | K100: 32.34 | L100: 0 | M100: 94.55 | N100: 138.61 | O100: 1892.78 | P100: 462.17 | Q100: 52.75 | R100: 0 | S100: 0 | T100: 0 | U100: 0 | V100: 0 | W100: 0 | X100: 0 | Y100: 0 | Z100: 0
D101: 2 | E101: Total | F101: 148999.33 | G101: 12944.66 | H101: 11025.64 | I101: 5841.53 | J101: 37065.43 | K101: 912.79 | L101: 0 | M101: 3496.63 | N101: 4875.23 | O101: 54259.35 | P101: 17091.84 | Q101: 1489.28 | R101: -3.05 | S101: 0 | T101: 0 | U101: 0 | V101: 0 | W101: 0 | X101: 0 | Y101: 0 | Z101: 0
E102: Vlr Servicio | F102: 3596790.3 | G102: 184464.34 | H102: 101131.59 | I102: 54378.84 | J102: 952840.52 | K102: 28739.95 | L102: 0 | M102: 251240.84 | N102: 284032.07 | O102: 1332401 | P102: 360636.4 | Q102: 46891.61 | R102: 33.11 | S102: 0 | T102: 0 | U102: 0 | V102: 0 | W102: 0 | X102: 0 | Y102: 0 | Z102: 0
E103: Vlr Intereses | F103: 24410.77 | G103: 1307.03 | H103: 654 | I103: 363.03 | J103: 6808.05 | K103: 163.9 | L103: 0 | M103: 1437.9 | N103: 1902.43 | O103: 8907.03 | P103: 2599.83 | Q103: 267.46 | R103: 0.18 | S103: 0 | T103: 0 | U103: 0 | V103: 0 | W103: 0 | X103: 0 | Y103: 0 | Z103: -0.07
D104: 5 | E104: Total | F104: 3621201.1 | G104: 185771.37 | H104: 101785.59 | I104: 54741.87 | J104: 959648.57 | K104: 28903.85 | L104: 0 | M104: 252678.74 | N104: 285934.5 | O104: 1341308.1 | P104: 363236.23 | Q104: 47159.07 | R104: 33.29 | S104: 0 | T104: 0 | U104: 0 | V104: 0 | W104: 0 | X104: 0 | Y104: 0 | Z104: -0.07
C105: NUEVO ESQUEMA | D105: Total | F105: 4612657.2 | G105: 267464.13 | H105: 147953.18 | I105: 78179.08 | J105: 1184623.4 | K105: 36371.93 | L105: 0 | M105: 313529.02 | N105: 351306.01 | O105: 1657290.9 | P105: 516566.24 | Q105: 59343.8 | R105: 28.27 | S105: 1.42 | T105: 0 | U105: 0 | V105: 0 | W105: 0 | X105: 0 | Y105: 0 | Z105: -0.07
E106: Vlr Servicio | F106: 2.7865517e+08 | G106: 17004069 | H106: 9519465.1 | I106: 5026439.6 | J106: 69338749 | K106: 1749839.1 | L106: 390000 | M106: 15331339 | N106: 21314920 | O106: 1.0263663e+08 | P106: 33470803 | Q106: 2873532.7 | R106: -626.04 | S106: 0 | T106: 0 | U106: 0 | V106: 0 | W106: 0 | X106: 0 | Y106: 0 | Z106: 0
E107: Vlr Intereses | F107: 2510654.2 | G107: 228049.21 | H107: 126508.23 | I107: 67376.45 | J107: 536093.23 | K107: 13546.98 | L107: 2131.75 | M107: 118645.14 | N107: 165974.06 | O107: 777577.68 | P107: 452600.04 | Q107: 22150.15 | R107: 4.48 | S107: -3.17 | T107: 0 | U107: 0 | V107: 0 | W107: 0 | X107: 0 | Y107: 0 | Z107: -0.06
D108: H | E108: Total | F108: 2.8116582e+08 | G108: 17232119 | H108: 9645973.3 | I108: 5093816.1 | J108: 69874842 | K108: 1763386.1 | L108: 392131.75 | M108: 15449984 | N108: 21480894 | O108: 1.0341421e+08 | P108: 33923403 | Q108: 2895682.9 | R108: -621.56 | S108: -3.17 | T108: 0 | U108: 0 | V108: 0 | W108: 0 | X108: 0 | Y108: 0 | Z108: -0.06
E109: Vlr Servicio | F109: 1.9786532e+08 | G109: 23349813 | H109: 12922414 | I109: 6807384.1 | J109: 34566257 | K109: 1024246 | L109: 179000 | M109: 8975669.2 | N109: 11111516 | O109: 50911317 | P109: 46331241 | Q109: 1685715.3 | R109: 744.11 | S109: 0 | T109: 0 | U109: 0 | V109: 0 | W109: 0 | X109: 0 | Y109: 0 | Z109: 0
E110: Vlr Intereses | F110: 10117667 | G110: 1681999.6 | H110: 897472.28 | I110: 454565.02 | J110: 1209142.4 | K110: 39215.57 | L110: 533.1 | M110: 344368.89 | N110: 426855.66 | O110: 1667257.6 | P110: 3332174.2 | Q110: 64074.96 | R110: -41.05 | S110: 49.93 | T110: 0.49 | U110: 0 | V110: 0 | W110: 0 | X110: 0 | Y110: 0 | Z110: -1.71
D111: O | E111: Total | F111: 2.0798298e+08 | G111: 25031813 | H111: 13819887 | I111: 7261949.1 | J111: 35775399 | K111: 1063461.6 | L111: 179533.1 | M111: 9320038.1 | N111: 11538372 | O111: 52578575 | P111: 49663415 | Q111: 1749790.3 | R111: 703.06 | S111: 49.93 | T111: 0.49 | U111: 0 | V111: 0 | W111: 0 | X111: 0 | Y111: 0 | Z111: -1.71
E112: Vlr Servicio | F112: 5.7737497e+08 | G112: 1.0717298e+08 | H112: 57612984 | I112: 30979977 | J112: 44257386 | K112: 1113733.6 | L112: 29820500 | M112: 9778691.2 | N112: 13884957 | O112: 66802059 | P112: 2.1412303e+08 | Q112: 1829612.3 | R112: -948.27 | S112: 0 | T112: 0 | U112: 0 | V112: 0 | W112: 0 | X112: 0 | Y112: 0 | Z112: 0
E113: Vlr Intereses | F113: 38194204 | G113: 9471442.8 | H113: 4689051.3 | I113: 2581818.5 | J113: 710451.95 | K113: 17737.79 | L113: 239895.54 | M113: 155547.43 | N113: 216057.5 | O113: 1016661.3 | P113: 19123423 | Q113: 28936.31 | R113: 0.73 | S113: -56818.93 | T113: 0 | U113: 0 | V113: 0 | W113: 0 | X113: 0 | Y113: 0 | Z113: -0.87
...

Sheet Rem. Anticipos R2
B1: PROMOAMBIENTAL
E2: Total | F2: Componente TDF | G2: Componente TTL | H2: Componente TVIAT | I2: Aprovechamiento | J2: CCSA Prest.Aprov. | K2: Especiales | L2: Componente TCS | M2: Componente TLU | N2: Componente TBL | O2: Componente TRT | P2: CCSA Prest. No Aprov. | Q2: Deb/Cred | R2: Deb/Cred-otros
D3: Vlr Servicio | E3: 29113116 | F3: 1628607.2 | G3: 888839.63 | H3: 520100 | I3: 4494462.8 | J3: 206660.7 | K3: 0 | L3: 2285816.4 | M3: 2318036.2 | N3: 11916210 | O3: 4523138.8 | P3: 331271.2 | Q3: -26.69 | R3: 0
D4: Vlr Intereses | E4: 1903.01 | F4: 73.46 | G4: 40.2 | H4: 21.55 | I4: 326.7 | J4: 21.37 | K4: 0 | L4: 192.26 | M4: 174.97 | N4: 818.31 | O4: 199.3 | P4: 34.85 | Q4: 0.04 | R4: 0
C5: E | D5: Total | E5: 29115019 | F5: 1628680.7 | G5: 888879.83 | H5: 520121.55 | I5: 4494789.5 | J5: 206682.07 | K5: 0 | L5: 2286008.7 | M5: 2318211.1 | N5: 11917028 | O5: 4523338.1 | P5: 331306.05 | Q5: -26.65 | R5: 0
B6: ENEL | C6: Total | E6: 29115019 | F6: 1628680.7 | G6: 888879.83 | H6: 520121.55 | I6: 4494789.5 | J6: 206682.07 | K6: 0 | L6: 2286008.7 | M6: 2318211.1 | N6: 11917028 | O6: 4523338.1 | P6: 331306.05 | Q6: -26.65 | R6: 0
D7: Vlr Servicio | E7: 793692.13 | F7: 30716.86 | G7: 16909.04 | H7: 9688.4 | I7: 151298.66 | J7: 7470.71 | K7: 0 | L7: 68892.29 | M7: 68745.87 | N7: 346268.88 | O7: 81506.79 | P7: 12188.93 | Q7: 5.7 | R7: 0
D8: Vlr Intereses | E8: 390.56 | F8: 13.47 | G8: 6.62 | H8: 4.12 | I8: 56.72 | J8: 4.51 | K8: 0 | L8: 39.61 | M8: 38.85 | N8: 182.43 | O8: 36.86 | P8: 7.36 | Q8: 0.01 | R8: 0
C9: H | D9: Total | E9: 794082.69 | F9: 30730.33 | G9: 16915.66 | H9: 9692.52 | I9: 151355.38 | J9: 7475.22 | K9: 0 | L9: 68931.9 | M9: 68784.72 | N9: 346451.31 | O9: 81543.65 | P9: 12196.29 | Q9: 5.71 | R9: 0
D10: Vlr Servicio | E10: 462871.22 | F10: 17750.61 | G10: 9935.12 | H10: 5797.01 | I10: 63590.58 | J10: 4697.55 | K10: 0 | L10: 43276.6 | M10: 42645.09 | N10: 218816.26 | O10: 48699.89 | P10: 7664.33 | Q10: -1.82 | R10: 0
C11: O | D11: Total | E11: 462871.22 | F11: 17750.61 | G11: 9935.12 | H11: 5797.01 | I11: 63590.58 | J11: 4697.55 | K11: 0 | L11: 43276.6 | M11: 42645.09 | N11: 218816.26 | O11: 48699.89 | P11: 7664.33 | Q11: -1.82 | R11: 0
D12: Vlr Servicio | E12: 2198318.9 | F12: 188049.69 | G12: 89756.71 | H12: 48201.07 | I12: 310657.06 | J12: 11520.24 | K12: 0 | L12: 108962.88 | M12: 96743.8 | N12: 469156.33 | O12: 856474.39 | P12: 18795.96 | Q12: 0.79 | R12: 0
D13: Vlr Intereses | E13: 0 | F13: 0 | G13: 0 | H13: 0 | I13: 0 | J13: 0 | K13: 0 | L13: 0 | M13: 0 | N13: 0 | O13: 0 | P13: 0 | Q13: 0 | R13: 0
C14: T | D14: Total | E14: 2198318.9 | F14: 188049.69 | G14: 89756.71 | H14: 48201.07 | I14: 310657.06 | J14: 11520.24 | K14: 0 | L14: 108962.88 | M14: 96743.8 | N14: 469156.33 | O14: 856474.39 | P14: 18795.96 | Q14: 0.79 | R14: 0
B15: OCCIDENTE | C15: Total | E15: 3455272.8 | F15: 236530.63 | G15: 116607.49 | H15: 63690.6 | I15: 525603.02 | J15: 23693.01 | K15: 0 | L15: 221171.38 | M15: 208173.61 | N15: 1034423.9 | O15: 986717.93 | P15: 38656.58 | Q15: 4.68 | R15: 0
A16: Componente | B16: Total | E16: 32570292 | F16: 1865211.3 | G16: 1005487.3 | H16: 583812.15 | I16: 5020392.6 | J16: 230375.08 | K16: 0 | L16: 2507180.1 | M16: 2526384.8 | N16: 12951452 | O16: 5510056 | P16: 369962.63 | Q16: -21.97 | R16: 0
D17: Subsidio(-)/Contribucion(+) | E17: 1139503.2 | F17: 264067.13 | G17: 147039.05 | H17: 72868.6 | I17: -136480.3 | J17: 3896.46 | K17: 0 | L17: -61838.04 | M17: -5695.54 | N17: 107985.49 | O17: 741490.48 | P17: 6169.9 | Q17: 0 | R17: 0
C18: E | D18: Total | E18: 1139503.2 | F18: 264067.13 | G18: 147039.05 | H18: 72868.6 | I18: -136480.3 | J18: 3896.46 | K18: 0 | L18: -61838.04 | M18: -5695.54 | N18: 107985.49 | O18: 741490.48 | P18: 6169.9 | Q18: 0 | R18: 0
B19: ENEL | C19: Total | E19: 1139503.2 | F19: 264067.13 | G19: 147039.05 | H19: 72868.6 | I19: -136480.3 | J19: 3896.46 | K19: 0 | L19: -61838.04 | M19: -5695.54 | N19: 107985.49 | O19: 741490.48 | P19: 6169.9 | Q19: 0 | R19: 0
D20: Subsidio(-)/Contribucion(+) | E20: 124917.68 | F20: 5425.49 | G20: 3470.55 | H20: 2025.09 | I20: 30214.16 | J20: 1088.11 | K20: 0 | L20: 9544.97 | M20: 9235.05 | N20: 43751.21 | O20: 18387.71 | P20: 1775.34 | Q20: 0 | R20: 0
C21: H | D21: Total | E21: 124917.68 | F21: 5425.49 | G21: 3470.55 | H21: 2025.09 | I21: 30214.16 | J21: 1088.11 | K21: 0 | L21: 9544.97 | M21: 9235.05 | N21: 43751.21 | O21: 18387.71 | P21: 1775.34 | Q21: 0 | R21: 0
D22: Subsidio(-)/Contribucion(+) | E22: 166291.05 | F22: 8434.38 | G22: 4699.6 | H22: 2499.5 | I22: 29821.33 | J22: 1737.19 | K22: 0 | L22: 13525.99 | M22: 12946.73 | N22: 66755.66 | O22: 23036.36 | P22: 2834.31 | Q22: 0 | R22: 0
C23: O | D23: Total | E23: 166291.05 | F23: 8434.38 | G23: 4699.6 | H23: 2499.5 | I23: 29821.33 | J23: 1737.19 | K23: 0 | L23: 13525.99 | M23: 12946.73 | N23: 66755.66 | O23: 23036.36 | P23: 2834.31 | Q23: 0 | R23: 0
D24: Subsidio(-)/Contribucion(+) | E24: 843950.15 | F24: 106181.23 | G24: 59113.51 | H24: 30954.51 | I24: 107753.85 | J24: 4247.21 | K24: 0 | L24: 35494.18 | M24: 35638.24 | N24: 167630.68 | O24: 290007.18 | P24: 6929.56 | Q24: 0 | R24: 0
C25: T | D25: Total | E25: 843950.15 | F25: 106181.23 | G25: 59113.51 | H25: 30954.51 | I25: 107753.85 | J25: 4247.21 | K25: 0 | L25: 35494.18 | M25: 35638.24 | N25: 167630.68 | O25: 290007.18 | P25: 6929.56 | Q25: 0 | R25: 0
B26: OCCIDENTE | C26: Total | E26: 1135158.9 | F26: 120041.1 | G26: 67283.66 | H26: 35479.1 | I26: 167789.34 | J26: 7072.51 | K26: 0 | L26: 58565.14 | M26: 57820.02 | N26: 278137.55 | O26: 331431.25 | P26: 11539.21 | Q26: 0 | R26: 0
A27: Subs/Cont | B27: Total | E27: 2274662.1 | F27: 384108.23 | G27: 214322.71 | H27: 108347.7 | I27: 31309.04 | J27: 10968.97 | K27: 0 | L27: -3272.9 | M27: 52124.48 | N27: 386123.04 | O27: 1072921.7 | P27: 17709.11 | Q27: 0 | R27: 0
A28: Total | E28: 34844954 | F28: 2249319.5 | G28: 1219810 | H28: 692159.85 | I28: 5051701.6 | J28: 241344.05 | K28: 0 | L28: 2503907.2 | M28: 2578509.2 | N28: 13337575 | O28: 6582977.7 | P28: 387671.74 | Q28: -21.97 | R28: 0
B42: TOTAL | C42: OPORTUNO | D42: Total | E42: =E16+E27-K16 -> 34844954 | F42: =F16 -> 1865211.3 | G42: =G16 -> 1005487.3 | H42: =H16 -> 583812.15 | I42: =I16 -> 5020392.6 | J42: =J16 -> 230375.08 | K42: =K16 -> 0 | L42: =L16 -> 2507180.1 | M42: =M16 -> 2526384.8 | ... S42: =S16 -> 0
D43: Subsidio(-)/Contribucion(+) | E43: =E27 -> 2274662.1
B45: RECIPROCIDAD | C45: OPORTUNO | D45: Total | E45: 0 | F45: 0 | G45: 0 | H45: 0 | I45: 0 | J45: 0 | K45: 0 | L45: 0 | M45: 0 | N45: 0 | O45: 0 | P45: 0 | Q45: 0 | R45: 0 | S45: 0
D46: Subsidio(-)/Contribucion(+) | E46: 0
B48: ENEL | C48: OPORTUNO | D48: Total | E48: =E19+E6-K6 -> 30254522 | F48: =F6 -> 1628680.7 | G48: =G6 -> 888879.83 | H48: =H6 -> 520121.55 | I48: =I6 -> 4494789.5 | J48: =J6 -> 206682.07 | K48: =K6 -> 0 | L48: =L6 -> 2286008.7 | M48: =M6 -> 2318211.1 | ... S48: =S6 -> 0
D49: Subsidio(-)/Contribucion(+) | E49: =E19 -> 1139503.2
B51: ENERBIT | C51: OPORTUNO | D51: Total | E51: 0 | F51: 0 | G51: 0 | H51: 0 | I51: 0 | J51: 0 | K51: 0 | L51: 0 | M51: 0 | N51: 0 | O51: 0 | P51: 0 | Q51: 0 | R51: 0
D52: Subsidio(-)/Contribucion(+) | E52: 0
B54: OCCIDENTE | C54: OPORTUNO | D54: Total | E54: =E15+E26-K15 -> 4590431.7 | F54: =F15 -> 236530.63 | G54: =G15 -> 116607.49 | H54: =H15 -> 63690.6 | I54: =I15 -> 525603.02 | J54: =J15 -> 23693.01 | K54: =K15 -> 0 | L54: =L15 -> 221171.38 | M54: =M15 -> 208173.61 | ... S54: =S15 -> 0
D55: Subsidio(-)/Contribucion(+) | E55: =E26 -> 1135158.9
B57: CIUDAD LIMPIA-ACUEDUCTO | C57: OPORTUNO | D57: Total | E57: 0 | F57: 0 | G57: 0 | H57: 0 | I57: 0 | J57: 0 | K57: 0 | L57: 0 | M57: 0 | N57: 0 | O57: 0 | P57: 0 | Q57: 0 | R57: 0 | S57: 0
D58: Subsidio(-)/Contribucion(+) | E58: 0
B60: LIME
E61: Total | F61: Componente TDF | G61: Componente TTL | H61: Componente TVIAT | I61: Aprovechamiento | J61: CCSA Prest.Aprov. | K61: Especiales | L61: Componente TCS | M61: Componente TLU | N61: Componente TBL | O61: Componente TRT | P61: CCSA Prest. No Aprov. | Q61: Deb/Cred | R61: Deb/Cred-otros
D62: Vlr Servicio | E62: 76172813 | F62: 4284667.4 | G62: 2478920 | H62: 894079.85 | I62: 19165035 | J62: 613033.04 | K62: 51372.12 | L62: 6695698 | M62: 6139885.2 | N62: 26107831 | O62: 8845683.5 | P62: 896338.13 | Q62: 269.69 | R62: 0
D63: Vlr Intereses | E63: 405301.06 | F63: 45882.1 | G63: 21905.35 | H63: 6058.48 | I63: 53792.9 | J63: 1687.15 | K63: 0 | L63: 24878.6 | M63: 29440.99 | N63: 127695.47 | O63: 91205.49 | P63: 2753.1 | Q63: 1.43 | R63: 0
C64: E | D64: Total | E64: 76578114 | F64: 4330549.5 | G64: 2500825.3 | H64: 900138.33 | I64: 19218828 | J64: 614720.19 | K64: 51372.12 | L64: 6720576.6 | M64: 6169326.2 | N64: 26235526 | O64: 8936889 | P64: 899091.23 | Q64: 271.12 | R64: 0
B65: ENEL | C65: Total | E65: 76578114 | F65: 4330549.5 | G65: 2500825.3 | H65: 900138.33 | I65: 19218828 | J65: 614720.19 | K65: 51372.12 | L65: 6720576.6 | M65: 6169326.2 | N65: 26235526 | O65: 8936889 | P65: 899091.23 | Q65: 271.12 | R65: 0
D66: Vlr Servicio | E66: 3697205.2 | F66: 224587.06 | G66: 131985.45 | H66: 46899.61 | I66: 1009958.8 | J66: 32320.93 | K66: 0 | L66: 324307.81 | M66: 265069.78 | N66: 1170089.6 | O66: 450797.77 | P66: 41194.89 | Q66: -6.51 | R66: 0
D67: Vlr Intereses | E67: 438.11 | F67: 43.19 | G67: 22.78 | H67: 12.09 | I67: 96.81 | J67: 2.8 | K67: 0 | L67: 24.54 | M67: 25.59 | N67: 119.35 | O67: 86.42 | P67: 4.57 | Q67: -0.03 | R67: 0
C68: 1 | D68: Total | E68: 3697643.3 | F68: 224630.25 | G68: 132008.23 | H68: 46911.7 | I68: 1010055.6 | J68: 32323.73 | K68: 0 | L68: 324332.35 | M68: 265095.37 | N68: 1170209 | O68: 450884.19 | P68: 41199.46 | Q68: -6.54 | R68: 0
D69: Vlr Servicio | E69: 985683.46 | F69: 69109.02 | G69: 36538.01 | H69: 13453.14 | I69: 287582.83 | J69: 9153.37 | K69: 0 | L69: 82037.98 | M69: 69059.03 | N69: 274803.2 | O69: 134412.31 | P69: 9540.6 | Q69: -6.03 | R69: 0
C70: 2 | D70: Total | E70: 985683.46 | F70: 69109.02 | G70: 36538.01 | H70: 13453.14 | I70: 287582.83 | J70: 9153.37 | K70: 0 | L70: 82037.98 | M70: 69059.03 | N70: 274803.2 | O70: 134412.31 | P70: 9540.6 | Q70: -6.03 | R70: 0
D71: Vlr Servicio | E71: 18762806 | F71: 1069718.5 | G71: 652346.13 | H71: 178774.19 | I71: 5624013.3 | J71: 166253.39 | K71: 0 | L71: 1667800.4 | M71: 1432331.3 | N71: 5647380.5 | O71: 2150226.7 | P71: 173791.57 | Q71: 169.78 | R71: 0
D72: Vlr Intereses | E72: 1557.48 | F72: 105.97 | G72: 58.29 | H72: 31.24 | I72: 365.86 | J72: 12.42 | K72: 0 | L72: 109 | M72: 112.67 | N72: 531.07 | O72: 210.73 | P72: 20.27 | Q72: -0.04 | R72: 0
C73: 5 | D73: Total | E73: 18764363 | F73: 1069824.4 | G73: 652404.42 | H73: 178805.43 | I73: 5624379.2 | J73: 166265.81 | K73: 0 | L73: 1667909.4 | M73: 1432444 | N73: 5647911.5 | O73: 2150437.5 | P73: 173811.84 | Q73: 169.74 | R73: 0
B74: NUEVO ESQUEMA | C74: Total | E74: 23447690 | F74: 1363563.7 | G74: 820950.66 | H74: 239170.27 | I74: 6922017.7 | J74: 207742.91 | K74: 0 | L74: 2074279.7 | M74: 1766598.4 | N74: 7092923.7 | O74: 2735734 | P74: 224551.9 | Q74: 157.17 | R74: 0
D75: Vlr Servicio | E75: 3424363.4 | F75: 193904.51 | G75: 105926.68 | H75: 44650.24 | I75: 871174.9 | J75: 28634.07 | K75: 0 | L75: 280560.08 | M75: 271116.53 | N75: 1194088 | O75: 396460.66 | P75: 37858.56 | Q75: -10.77 | R75: 0
D76: Vlr Intereses | E76: 9177.03 | F76: 847.38 | G76: 479.07 | H76: 253.95 | I76: 1842.43 | J76: 67 | K76: 0 | L76: 587.73 | M76: 577.57 | N76: 2703.44 | O76: 1709.06 | P76: 109.33 | Q76: 0.07 | R76: 0
C77: H | D77: Total | E77: 3433540.5 | F77: 194751.89 | G77: 106405.75 | H77: 44904.19 | I77: 873017.33 | J77: 28701.07 | K77: 0 | L77: 281147.81 | M77: 271694.1 | N77: 1196791.4 | O77: 398169.72 | P77: 37967.89 | Q77: -10.7 | R77: 0
D78: Vlr Servicio | E78: 21026339 | F78: 2447720.8 | G78: 1370734.8 | H78: 666552.07 | I78: 3536069 | J78: 136948.11 | K78: 0 | L78: 1395691.4 | M78: 1241864.2 | N78: 5125598.2 | O78: 4911373.5 | P78: 193726.12 | Q78: 61.33 | R78: 0
D79: Vlr Intereses | E79: 1143672.6 | F79: 164527.55 | G79: 76426.08 | H79: 30595.99 | I79: 168828.35 | J79: 6886.01 | K79: 0 | L79: 60313.09 | M79: 71428.55 | N79: 229600.44 | O79: 323815.18 | P79: 11246.94 | Q79: 4.4 | R79: 0
C80: O | D80: Total | E80: 22170012 | F80: 2612248.3 | G80: 1447160.9 | H80: 697148.06 | I80: 3704897.3 | J80: 143834.12 | K80: 0 | L80: 1456004.5 | M80: 1313292.8 | N80: 5355198.7 | O80: 5235188.7 | P80: 204973.06 | Q80: 65.73 | R80: 0
D81: Vlr Servicio | E81: 1247383.2 | F81: 104470.27 | G81: 61589.36 | H81: 22988.66 | I81: 272684.1 | J81: 8354.34 | K81: 0 | L81: 111652.21 | M81: 93795.87 | N81: 322239.45 | O81: 236861.37 | P81: 12733.53 | Q81: 14.06 | R81: 0
D82: Vlr Intereses | E82: 112.94 | F82: 8.95 | G82: 5.05 | H82: 2.65 | I82: 31.41 | J82: 0.88 | K82: 0 | L82: 7.77 | M82: 8.75 | N82: 26.93 | O82: 17.76 | P82: 2.77 | Q82: 0.02 | R82: 0
C83: T | D83: Total | E83: 1247496.2 | F83: 104479.22 | G83: 61594.41 | H83: 22991.31 | I83: 272715.51 | J83: 8355.22 | K83: 0 | L83: 111659.98 | M83: 93804.62 | N83: 322266.38 | O83: 236879.13 | P83: 12736.3 | Q83: 14.08 | R83: 0
B84: OCCIDENTE | C84: Total | E84: 26851049 | F84: 2911479.5 | G84: 1615161 | H84: 765043.56 | I84: 4850630.2 | J84: 180890.41 | K84: 0 | L84: 1848812.3 | M84: 1678791.5 | N84: 6874256.4 | O84: 5870237.5 | P84: 255677.25 | Q84: 69.11 | R84: 0
A85: Componente | B85: Total | E85: 1.2687685e+08 | F85: 8605592.6 | G85: 4936937 | H85: 1904352.2 | I85: 30991476 | J85: 1003353.5 | K85: 51372.12 | L85: 10643669 | M85: 9614716.1 | N85: 40202706 | O85: 17542860 | P85: 1379320.4 | Q85: 497.4 | R85: 0
D86: Subsidio(-)/Contribucion(+) | E86: -20136934 | F86: -733600.76 | G86: -420838.98 | H86: -246337.87 | I86: -5403916.5 | J86: -198124.8 | K86: 0 | L86: -1723396.6 | M86: -1708957.8 | N86: -8115340.4 | O86: -1253175.4 | P86: -333245.06 | Q86: 0 | R86: 0
C87: E | D87: Total | E87: -20136934 | F87: -733600.76 | G87: -420838.98 | H87: -246337.87 | I87: -5403916.5 | J87: -198124.8 | K87: 0 | L87: -1723396.6 | M87: -1708957.8 | N87: -8115340.4 | O87: -1253175.4 | P87: -333245.06 | Q87: 0 | R87: 0
B88: ENEL | C88: Total | E88: -20136934 | F88: -733600.76 | G88: -420838.98 | H88: -246337.87 | I88: -5403916.5 | J88: -198124.8 | K88: 0 | L88: -1723396.6 | M88: -1708957.8 | N88: -8115340.4 | O88: -1253175.4 | P88: -333245.06 | Q88: 0 | R88: 0
D89: Subsidio(-)/Contribucion(+) | E89: -1106250.7 | F89: -41906.77 | G89: -23555.44 | H89: -12506.48 | I89: -284568.59 | J89: -11004 | K89: 0 | L89: -96525.39 | M89: -94067.83 | N89: -441672.35 | O89: -82490.11 | P89: -17953.78 | Q89: 0 | R89: 0
C90: 1 | D90: Total | E90: -1106250.7 | F90: -41906.77 | G90: -23555.44 | H90: -12506.48 | I90: -284568.59 | J90: -11004 | K90: 0 | L90: -96525.39 | M90: -94067.83 | N90: -441672.35 | O90: -82490.11 | P90: -17953.78 | Q90: 0 | R90: 0
D91: Subsidio(-)/Contribucion(+) | E91: -124474.09 | F91: 1487.57 | G91: 889.3 | H91: -1103.13 | I91: -40257.58 | J91: -1303.18 | K91: 0 | L91: -11431.5 | M91: -11193.46 | N91: -52137.19 | O91: -7298.67 | P91: -2126.25 | Q91: 0 | R91: 0
C92: 2 | D92: Total | E92: -124474.09 | F92: 1487.57 | G92: 889.3 | H92: -1103.13 | I92: -40257.58 | J92: -1303.18 | K92: 0 | L92: -11431.5 | M92: -11193.46 | N92: -52137.19 | O92: -7298.67 | P92: -2126.25 | Q92: 0 | R92: 0
D93: Subsidio(-)/Contribucion(+) | E93: -6194145.2 | F93: -244820.14 | G93: -142606.5 | H93: -79186.47 | I93: -1710597.2 | J93: -59039.59 | K93: 0 | L93: -507349.02 | M93: -491066.4 | N93: -2363435.6 | O93: -500022.5 | P93: -96021.65 | Q93: 0 | R93: 0
C94: 5 | D94: Total | E94: -6194145.2 | F94: -244820.14 | G94: -142606.5 | H94: -79186.47 | I94: -1710597.2 | J94: -59039.59 | K94: 0 | L94: -507349.02 | M94: -491066.4 | N94: -2363435.6 | O94: -500022.5 | P94: -96021.65 | Q94: 0 | R94: 0
B95: NUEVO ESQUEMA | C95: Total | E95: -7424870 | F95: -285239.34 | G95: -165272.64 | H95: -92796.08 | I95: -2035423.4 | J95: -71346.77 | K95: 0 | L95: -615305.91 | M95: -596327.69 | N95: -2857245.2 | O95: -589811.28 | P95: -116101.68 | Q95: 0 | R95: 0
D96: Subsidio(-)/Contribucion(+) | E96: -702492.5 | F96: -14521.12 | G96: -8315.81 | H96: -4324.36 | I96: -200536.28 | J96: -7255.75 | K96: 0 | L96: -63647.28 | M96: -63025.67 | N96: -296143.19 | O96: -32884.7 | P96: -11838.34 | Q96: 0 | R96: 0
C97: H | D97: Total | E97: -702492.5 | F97: -14521.12 | G97: -8315.81 | H97: -4324.36 | I97: -200536.28 | J97: -7255.75 | K97: 0 | L97: -63647.28 | M97: -63025.67 | N97: -296143.19 | O97: -32884.7 | P97: -11838.34 | Q97: 0 | R97: 0
D98: Subsidio(-)/Contribucion(+) | E98: 2991899 | F98: 1356625.7 | G98: 761821.94 | H98: 401733.5 | I98: -655687.55 | J98: -25954.75 | K98: 0 | L98: -222683.06 | M98: -220639.47 | N98: -1059056.4 | O98: 2697993.6 | P98: -42254.49 | Q98: 0 | R98: 0
C99: O | D99: Total | E99: 2991899 | F99: 1356625.7 | G99: 761821.94 | H99: 401733.5 | I99: -655687.55 | J99: -25954.75 | K99: 0 | L99: -222683.06 | M99: -220639.47 | N99: -1059056.4 | O99: 2697993.6 | P99: -42254.49 | Q99: 0 | R99: 0
D100: Subsidio(-)/Contribucion(+) | E100: 109015.24 | F100: 19894.14 | G100: 10729.02 | H100: 4929.67 | I100: 13052.9 | J100: 120.98 | K100: 0 | L100: 2492.3 | M100: 3185.16 | N100: 14573.83 | O100: 39839.82 | P100: 197.42 | Q100: 0 | R100: 0
C101: T | D101: Total | E101: 109015.24 | F101: 19894.14 | G101: 10729.02 | H101: 4929.67 | I101: 13052.9 | J101: 120.98 | K101: 0 | L101: 2492.3 | M101: 3185.16 | N101: 14573.83 | O101: 39839.82 | P101: 197.42 | Q101: 0 | R101: 0
B102: OCCIDENTE | C102: Total | E102: 2398421.8 | F102: 1361998.8 | G102: 764235.15 | H102: 402338.81 | I102: -843170.93 | J102: -33089.52 | K102: 0 | L102: -283838.04 | M102: -280479.98 | N102: -1340625.8 | O102: 2704948.7 | P102: -53895.41 | Q102: 0 | R102: 0
A103: Subs/Cont | B103: Total | E103: -25163382 | F103: 343158.66 | G103: 178123.53 | H103: 63204.86 | I103: -8282510.9 | J103: -302561.09 | K103: 0 | L103: -2622540.6 | M103: -2585765.5 | N103: -12313211 | O103: 861962 | P103: -503242.15 | Q103: 0 | R103: 0
A104: Total | E104: 1.0171347e+08 | F104: 8948751.3 | G104: 5115060.6 | H104: 1967557 | I104: 22708965 | J104: 700792.42 | K104: 51372.12 | L104: 8021128 | M104: 7028950.6 | N104: 27889495 | O104: 18404822 | P104: 876078.23 | Q104: 497.4 | R104: 0
B135: TOTAL | C135: OPORTUNO | D135: Total | E135: =E85+E103-K85 -> 1.016621e+08 | F135: =F85 -> 8605592.6 | G135: =G85 -> 4936937 | H135: =H85 -> 1904352.2 | I135: =I85 -> 30991476 | J135: =J85 -> 1003353.5 | K135: =K85 -> 51372.12 | L135: =L85 -> 10643669 | M135: =M85 -> 9614716.1 | ... R135: =R85 -> 0
D136: Subsidio(-)/Contribucion(+) | E136: =E103 -> -25163382
B138: RECIPROCIDAD | C138: OPORTUNO | D138: Total | E138: =E95+E74-K74 -> 16022820 | F138: =F74 -> 1363563.7 | G138: =G74 -> 820950.66 | H138: =H74 -> 239170.27 | I138: =I74 -> 6922017.7 | J138: =J74 -> 207742.91 | K138: =K74 -> 0 | L138: =L74 -> 2074279.7 | M138: =M74 -> 1766598.4 | ... R138: =R74 -> 0
D139: Subsidio(-)/Contribucion(+) | E139: =E95 -> -7424870
B141: ENEL | C141: OPORTUNO | D141: Total | E141: =E88+E65-K65 -> 56389808 | F141: =F65 -> 4330549.5 | G141: =G65 -> 2500825.3 | H141: =H65 -> 900138.33 | I141: =I65 -> 19218828 | J141: =J65 -> 614720.19 | K141: =K65 -> 51372.12 | L141: =L65 -> 6720576.6 | M141: =M65 -> 6169326.2 | ... R141: =R65 -> 0
D142: Subsidio(-)/Contribucion(+) | E142: =E88 -> -20136934
B144: ENERBIT | C144: OPORTUNO | D144: Total | E144: 0 | F144: 0 | G144: 0 | H144: 0 | I144: 0 | J144: 0 | K144: 0 | L144: 0 | M144: 0 | N144: 0 | O144: 0 | P144: 0 | Q144: 0 | R144: 0
D145: Subsidio(-)/Contribucion(+) | E145: 0
B147: OCCIDENTE | C147: OPORTUNO | D147: Total | E147: =E84+E102-K84 -> 29249470 | F147: =F84 -> 2911479.5 | G147: =G84 -> 1615161 | H147: =H84 -> 765043.56 | I147: =I84 -> 4850630.2 | J147: =J84 -> 180890.41 | K147: =K84 -> 0 | L147: =L84 -> 1848812.3 | M147: =M84 -> 1678791.5 | ... R147: =R84 -> 0
D148: Subsidio(-)/Contribucion(+) | E148: =E102 -> 2398421.8
B150: CIUDAD LIMPIA-ACUEDUCTO | C150: OPORTUNO | D150: Total | E150: 0 | F150: 0 | G150: 0 | H150: 0 | I150: 0 | J150: 0 | K150: 0 | L150: 0 | M150: 0 | N150: 0 | O150: 0 | P150: 0 | Q150: 0 | R150: 0
D151: Subsidio(-)/Contribucion(+) | E151: 0
B153: CIUDAD LIMPIA
E154: Total | F154: Componente TDF | G154: Componente TTL | H154: Componente TVIAT | I154: Aprovechamiento | J154: CCSA Prest.Aprov. | K154: Especiales | L154: Componente TCS | M154: Componente TLU | N154: Componente TBL | O154: Componente TRT | P154: CCSA Prest. No Aprov. | Q154: Deb/Cred | R154: Deb/Cred-otros
D155: Vlr Servicio | E155: 23412670 | F155: 1358095.3 | G155: 758078.16 | H155: 333219.24 | I155: 5453410.1 | J155: 184934.16 | K155: 45286.42 | L155: 2062901.2 | M155: 1587462 | N155: 7131830.5 | O155: 4229900.8 | P155: 267739.32 | Q155: -187.3 | R155: 0
...

Sheet Reversion Pagos R4
B1: PROMOAMBIENTAL
D2: Total | E2: Componente TDF | F2: Componente TTL | G2: Componente TVIAT | H2: Aprovechamiento | I2: CCSA Prest.Aprov. | J2: Componente TCS | K2: Componente TLU | L2: Componente TBL | M2: Componente TRT | N2: CCSA Prest. No Aprov. | O2: Ajuste Decena | P2: SERVICIO ESPECIALES | Q2: Ajuste Recargo Aseo | R2: Otros
C3: Vlr Servicio | D3: -4753329.9 | E3: -214159.07 | F3: -114902.14 | G3: -61576.43 | H3: -1165948.6 | I3: -45063.11 | J3: -395289.43 | K3: -369526.83 | L3: -1753828.5 | M3: -560155.38 | N3: -72898.32 | O3: 17.99 | P3: 0 | Q3: 0 | R3: 0
C4: Vlr Intereses | D4: -12501.61 | E4: -542.19 | F4: -246.5 | G4: -140.42 | H4: -2800.13 | I4: -138.59 | J4: -1215.05 | K4: -1024.58 | L4: -4838.23 | M4: -1328.64 | N4: -227.04 | O4: -0.24 | P4: 0 | Q4: 0 | R4: 0
B5: Componente | C5: Total | D5: -4765831.5 | E5: -214701.26 | F5: -115148.64 | G5: -61716.85 | H5: -1168748.8 | I5: -45201.7 | J5: -396504.48 | K5: -370551.41 | L5: -1758666.8 | M5: -561484.02 | N5: -73125.36 | O5: 17.75 | P5: 0 | Q5: 0 | R5: 0
C6: Subsidio(-)/Contribucion(+) | D6: 1304634.2 | E6: 54873.86 | F6: 28576.76 | G6: 15506.07 | H6: 320570.26 | I6: 12973.15 | J6: 113799.96 | K6: 105110.1 | L6: 491550.49 | M6: 140506.71 | N6: 21166.82 | O6: 0 | P6: 0 | Q6: 0 | R6: 0
B7: Subs/Cont | C7: Total | D7: 1304634.2 | E7: 54873.86 | F7: 28576.76 | G7: 15506.07 | H7: 320570.26 | I7: 12973.15 | J7: 113799.96 | K7: 105110.1 | L7: 491550.49 | M7: 140506.71 | N7: 21166.82 | O7: 0 | P7: 0 | Q7: 0 | R7: 0
A8: ENEL | B8: Total | D8: -3461197.3 | E8: -159827.4 | F8: -86571.88 | G8: -46210.78 | H8: -848178.49 | I8: -32228.55 | J8: -282704.52 | K8: -265441.31 | L8: -1267116.3 | M8: -420977.31 | N8: -51958.54 | O8: 17.75 | P8: 0 | Q8: 0 | R8: 0
C9: Vlr Servicio | D9: -83090.08 | E9: -4319.28 | F9: -2439.7 | G9: -1284.52 | H9: -21380.91 | I9: -495.68 | J9: -4348.01 | K9: -6438.31 | L9: -29729.3 | M9: -11838.57 | N9: -808.72 | O9: -7.08 | P9: 0 | Q9: 0 | R9: 0
C10: Vlr Intereses | D10: -219.92 | E10: -11.38 | F10: -6.42 | G10: -3.38 | H10: -57.73 | I10: -1.29 | J10: -11.47 | K10: -16.98 | L10: -77.95 | M10: -31.19 | N10: -2.12 | O10: -0.01 | P10: 0 | Q10: 0 | R10: 0
B11: Componente | C11: Total | D11: -83310 | E11: -4330.66 | F11: -2446.12 | G11: -1287.9 | H11: -21438.64 | I11: -496.97 | J11: -4359.48 | K11: -6455.29 | L11: -29807.25 | M11: -11869.76 | N11: -810.84 | O11: -7.09 | P11: 0 | Q11: 0 | R11: 0
A12: OCCIDENTE | B12: Total | D12: -83310 | E12: -4330.66 | F12: -2446.12 | G12: -1287.9 | H12: -21438.64 | I12: -496.97 | J12: -4359.48 | K12: -6455.29 | L12: -29807.25 | M12: -11869.76 | N12: -810.84 | O12: -7.09 | P12: 0 | Q12: 0 | R12: 0
A13: Total | D13: -3544507.3 | E13: -164158.06 | F13: -89018 | G13: -47498.68 | H13: -869617.13 | I13: -32725.52 | J13: -287064 | K13: -271896.6 | L13: -1296923.5 | M13: -432847.07 | N13: -52769.38 | O13: 10.66 | P13: 0 | Q13: 0 | R13: 0
A71: TOTAL | B71: OPORTUNO | C71: Total | D71: =D13-P13 -> -3544507.3 | E71: =E11+E5 -> -219031.92 | F71: =F11+F5 -> -117594.76 | G71: =G11+G5 -> -63004.75 | H71: =H11+H5 -> -1190187.4 | I71: =I11+I5 -> -45698.67 | J71: =J11+J5 -> -400863.96 | K71: =K11+K5 -> -377006.7 | L71: =L11+L5 -> -1788474 | ... R71: =R11+R5 -> 0
C72: Subsidio(-)/Contribucion(+) | D72: =D7 -> 1304634.2
A74: RECIPROCIDAD | B74: OPORTUNO | C74: Total | D74: 0 | E74: 0 | F74: 0 | G74: 0 | H74: 0 | I74: 0 | J74: 0 | K74: 0 | L74: 0 | M74: 0 | N74: 0 | O74: 0 | P74: 0 | Q74: 0 | R74: 0
C75: Subsidio(-)/Contribucion(+) | D75: 0
A77: ENEL | B77: OPORTUNO | C77: Total | D77: =D8-P8 -> -3461197.3 | E77: =E5 -> -214701.26 | F77: =F5 -> -115148.64 | G77: =G5 -> -61716.85 | H77: =H5 -> -1168748.8 | I77: =I5 -> -45201.7 | J77: =J5 -> -396504.48 | K77: =K5 -> -370551.41 | L77: =L5 -> -1758666.8 | ... R77: =R5 -> 0
C78: Subsidio(-)/Contribucion(+) | D78: =D7 -> 1304634.2
A80: ENERBIT | B80: OPORTUNO | C80: Total | D80: 0 | E80: 0 | F80: 0 | G80: 0 | H80: 0 | I80: 0 | J80: 0 | K80: 0 | L80: 0 | M80: 0 | N80: 0 | O80: 0 | P80: 0 | Q80: 0 | R80: 0
C81: Subsidio(-)/Contribucion(+) | D81: 0
A83: OCCIDENTE | B83: OPORTUNO | C83: Total | D83: =D12-P12 -> -83310 | E83: =E11 -> -4330.66 | F83: =F11 -> -2446.12 | G83: =G11 -> -1287.9 | H83: =H11 -> -21438.64 | I83: =I11 -> -496.97 | J83: =J11 -> -4359.48 | K83: =K11 -> -6455.29 | L83: =L11 -> -29807.25 | ... R83: =R11 -> 0
C84: Subsidio(-)/Contribucion(+) | D84: 0
A86: CIUDAD LIMPIA-ACUEDUCTO | B86: OPORTUNO | C86: Total | D86: 0 | E86: 0 | F86: 0 | G86: 0 | H86: 0 | I86: 0 | J86: 0 | K86: 0 | L86: 0 | M86: 0 | N86: 0 | O86: 0 | P86: 0 | Q86: 0 | R86: 0
C87: Subsidio(-)/Contribucion(+) | D87: 0
B89: LIME
D90: Total | E90: Componente TDF | F90: Componente TTL | G90: Componente TVIAT | H90: Aprovechamiento | I90: CCSA Prest.Aprov. | J90: Componente TCS | K90: Componente TLU | L90: Componente TBL | M90: Componente TRT | N90: CCSA Prest. No Aprov. | O90: Ajuste Decena | P90: SERVICIO ESPECIALES | Q90: Ajuste Recargo Aseo | R90: Otros
C91: Vlr Servicio | D91: -10237443 | E91: -563399.38 | F91: -316917.62 | G91: -166722.74 | H91: -2628414.2 | I91: -89684.05 | J91: -786699.09 | K91: -766969.55 | L91: -3636763.4 | M91: -1109050.8 | N91: -146326.35 | O91: 4.57 | P91: -26500 | Q91: 0 | R91: 0
C92: Vlr Intereses | D92: -49535.64 | E92: -2812.32 | F92: -1322.36 | G92: -716.51 | H92: -13748.88 | I92: -368.55 | J92: -3233.3 | K92: -3852.97 | L92: -17279.39 | M92: -5599.52 | N92: -601.36 | O92: -0.48 | P92: 0 | Q92: 0 | R92: 0
B93: Componente | C93: Total | D93: -10286978 | E93: -566211.7 | F93: -318239.98 | G93: -167439.25 | H93: -2642163 | I93: -90052.6 | J93: -789932.39 | K93: -770822.52 | L93: -3654042.8 | M93: -1114650.3 | N93: -146927.71 | O93: 4.09 | P93: -26500 | Q93: 0 | R93: 0
C94: Subsidio(-)/Contribucion(+) | D94: 1547375.8 | E94: 29312.92 | F94: 16341.6 | G94: 8648.05 | H94: 470464.34 | I94: 15992.12 | J94: 140279.81 | K94: 136965.6 | L94: 646070.43 | M94: 57208.93 | N94: 26092.04 | O94: 0 | P94: 0 | Q94: 0 | R94: 0
B95: Subs/Cont | C95: Total | D95: 1547375.8 | E95: 29312.92 | F95: 16341.6 | G95: 8648.05 | H95: 470464.34 | I95: 15992.12 | J95: 140279.81 | K95: 136965.6 | L95: 646070.43 | M95: 57208.93 | N95: 26092.04 | O95: 0 | P95: 0 | Q95: 0 | R95: 0
A96: ENEL | B96: Total | D96: -8739602.4 | E96: -536898.78 | F96: -301898.38 | G96: -158791.2 | H96: -2171698.7 | I96: -74060.48 | J96: -649652.58 | K96: -633856.92 | L96: -3007972.4 | M96: -1057441.4 | N96: -120835.67 | O96: 4.09 | P96: -26500 | Q96: 0 | R96: 0
A97: Total | D97: -8739602.4 | E97: -536898.78 | F97: -301898.38 | G97: -158791.2 | H97: -2171698.7 | I97: -74060.48 | J97: -649652.58 | K97: -633856.92 | L97: -3007972.4 | M97: -1057441.4 | N97: -120835.67 | O97: 4.09 | P97: -26500 | Q97: 0 | R97: 0
A160: TOTAL | B160: OPORTUNO | C160: Total | D160: =D97-P97 -> -8713102.4 | E160: =E93 -> -566211.7 | F160: =F93 -> -318239.98 | G160: =G93 -> -167439.25 | H160: =H93 -> -2642163 | I160: =I93 -> -90052.6 | J160: =J93 -> -789932.39 | K160: =K93 -> -770822.52 | L160: =L93 -> -3654042.8 | ... R160: =R93 -> 0
C161: Subsidio(-)/Contribucion(+) | D161: =D95 -> 1547375.8
A163: RECIPROCIDAD | B163: OPORTUNO | C163: Total | D163: 0 | E163: 0 | F163: 0 | G163: 0 | H163: 0 | I163: 0 | J163: 0 | K163: 0 | L163: 0 | M163: 0 | N163: 0 | O163: 0 | P163: 0 | Q163: 0 | R163: 0
C164: Subsidio(-)/Contribucion(+) | D164: 0
A166: ENEL | B166: OPORTUNO | C166: Total | D166: =D96-P96 -> -8713102.4 | E166: =E93 -> -566211.7 | F166: =F93 -> -318239.98 | G166: =G93 -> -167439.25 | H166: =H93 -> -2642163 | I166: =I93 -> -90052.6 | J166: =J93 -> -789932.39 | K166: =K93 -> -770822.52 | L166: =L93 -> -3654042.8 | ... R166: =R93 -> 0
C167: Subsidio(-)/Contribucion(+) | D167: =D95 -> 1547375.8
A169: ENERBIT | B169: OPORTUNO | C169: Total | D169: 0 | E169: 0 | F169: 0 | G169: 0 | H169: 0 | I169: 0 | J169: 0 | K169: 0 | L169: 0 | M169: 0 | N169: 0 | O169: 0 | P169: 0 | Q169: 0 | R169: 0
C170: Subsidio(-)/Contribucion(+) | D170: 0
A172: OCCIDENTE | B172: OPORTUNO | C172: Total | D172: 0 | E172: 0 | F172: 0 | G172: 0 | H172: 0 | I172: 0 | J172: 0 | K172: 0 | L172: 0 | M172: 0 | N172: 0 | O172: 0 | P172: 0 | Q172: 0 | R172: 0
C173: Subsidio(-)/Contribucion(+) | D173: 0
A175: CIUDAD LIMPIA-ACUEDUCTO | B175: OPORTUNO | C175: Total | D175: 0 | E175: 0 | F175: 0 | G175: 0 | H175: 0 | I175: 0 | J175: 0 | K175: 0 | L175: 0 | M175: 0 | N175: 0 | O175: 0 | P175: 0 | Q175: 0 | R175: 0
C176: Subsidio(-)/Contribucion(+) | D176: 0
B178: CIUDAD LIMPIA
D179: Total | E179: Componente TDF | F179: Componente TTL | G179: Componente TVIAT | H179: Aprovechamiento | I179: CCSA Prest.Aprov. | J179: Componente TCS | K179: Componente TLU | L179: Componente TBL | M179: Componente TRT | N179: CCSA Prest. No Aprov. | O179: Ajuste Decena | P179: SERVICIO ESPECIALES | Q179: Ajuste Recargo Aseo | R179: Otros
C180: Vlr Servicio | D180: -6968154.2 | E180: -329081.64 | F180: -185597.2 | G180: -97672.38 | H180: -2008331.1 | I180: -59494.92 | J180: -518628.97 | K180: -504844.61 | L180: -2391600.7 | M180: -775803.2 | N180: -97071.22 | O180: -28.2 | P180: 0 | Q180: 0 | R180: 0
C181: Vlr Intereses | D181: -1954.21 | E181: -129.5 | F181: -73.1 | G181: -38.35 | H181: -455.19 | I181: -15.73 | J181: -138.23 | K181: -135.61 | L181: -641.52 | M181: -301.27 | N181: -25.73 | O181: 0.02 | P181: 0 | Q181: 0 | R181: 0
B182: Componente | C182: Total | D182: -6970108.4 | E182: -329211.14 | F182: -185670.3 | G182: -97710.73 | H182: -2008786.3 | I182: -59510.65 | J182: -518767.2 | K182: -504980.22 | L182: -2392242.2 | M182: -776104.47 | N182: -97096.95 | O182: -28.18 | P182: 0 | Q182: 0 | R182: 0
C183: Subsidio(-)/Contribucion(+) | D183: 878534.48 | E183: 23290.01 | F183: 13131.96 | G183: 6902.39 | H183: 294747.35 | I183: 8059.48 | J183: 70696.62 | K183: 68683.76 | L183: 324708.43 | M183: 55164.96 | N183: 13149.52 | O183: 0 | P183: 0 | Q183: 0 | R183: 0
B184: Subs/Cont | C184: Total | D184: 878534.48 | E184: 23290.01 | F184: 13131.96 | G184: 6902.39 | H184: 294747.35 | I184: 8059.48 | J184: 70696.62 | K184: 68683.76 | L184: 324708.43 | M184: 55164.96 | N184: 13149.52 | O184: 0 | P184: 0 | Q184: 0 | R184: 0
A185: ENEL | B185: Total | D185: -6091573.9 | E185: -305921.13 | F185: -172538.34 | G185: -90808.34 | H185: -1714039 | I185: -51451.17 | J185: -448070.58 | K185: -436296.46 | L185: -2067533.8 | M185: -720939.51 | N185: -83947.43 | O185: -28.18 | P185: 0 | Q185: 0 | R185: 0
C186: Vlr Servicio | D186: -40482.2 | E186: -1930.6 | F186: -1090.02 | G186: -572.11 | H186: -10651 | I186: -255.08 | J186: -2237.53 | K186: -3286.56 | L186: -15556.53 | M186: -4485.76 | N186: -416.18 | O186: -0.83 | P186: 0 | Q186: 0 | R186: 0
B187: Componente | C187: Total | D187: -40482.2 | E187: -1930.6 | F187: -1090.02 | G187: -572.11 | H187: -10651 | I187: -255.08 | J187: -2237.53 | K187: -3286.56 | L187: -15556.53 | M187: -4485.76 | N187: -416.18 | O187: -0.83 | P187: 0 | Q187: 0 | R187: 0
C188: Subsidio(-)/Contribucion(+) | D188: 6072.2 | E188: 289.59 | F188: 163.5 | G188: 85.81 | H188: 1597.65 | I188: 38.26 | J188: 335.63 | K188: 492.99 | L188: 2333.48 | M188: 672.86 | N188: 62.43 | O188: 0 | P188: 0 | Q188: 0 | R188: 0
B189: Subs/Cont | C189: Total | D189: 6072.2 | E189: 289.59 | F189: 163.5 | G189: 85.81 | H189: 1597.65 | I189: 38.26 | J189: 335.63 | K189: 492.99 | L189: 2333.48 | M189: 672.86 | N189: 62.43 | O189: 0 | P189: 0 | Q189: 0 | R189: 0
A190: OCCIDENTE | B190: Total | D190: -34410 | E190: -1641.01 | F190: -926.52 | G190: -486.3 | H190: -9053.35 | I190: -216.82 | J190: -1901.9 | K190: -2793.57 | L190: -13223.05 | M190: -3812.9 | N190: -353.75 | O190: -0.83 | P190: 0 | Q190: 0 | R190: 0
A191: Total | D191: -6125983.9 | E191: -307562.14 | F191: -173464.86 | G191: -91294.64 | H191: -1723092.3 | I191: -51667.99 | J191: -449972.48 | K191: -439090.03 | L191: -2080756.8 | M191: -724752.41 | N191: -84301.18 | O191: -29.01 | P191: 0 | Q191: 0 | R191: 0
A196: TOTAL | B196: OPORTUNO | C196: Total | D196: =D191-P191 -> -6125983.9 | E196: =E187+E182 -> -331141.74 | F196: =F187+F182 -> -186760.32 | G196: =G187+G182 -> -98282.84 | H196: =H187+H182 -> -2019437.3 | I196: =I187+I182 -> -59765.73 | J196: =J187+J182 -> -521004.73 | K196: =K187+K182 -> -508266.78 | L196: =L187+L182 -> -2407798.7 | ... R196: =R187+R182 -> 0
C197: Subsidio(-)/Contribucion(+) | D197: =D189+D184 -> 884606.68
A199: RECIPROCIDAD | B199: OPORTUNO | C199: Total | D199: 0 | E199: 0 | F199: 0 | G199: 0 | H199: 0 | I199: 0 | J199: 0 | K199: 0 | L199: 0 | M199: 0 | N199: 0 | O199: 0 | P199: 0 | Q199: 0 | R199: 0
C200: Subsidio(-)/Contribucion(+) | D200: 0
A202: ENEL | B202: OPORTUNO | C202: Total | D202: =D185-P185 -> -6091573.9 | E202: =E182 -> -329211.14 | F202: =F182 -> -185670.3 | G202: =G182 -> -97710.73 | H202: =H182 -> -2008786.3 | I202: =I182 -> -59510.65 | J202: =J182 -> -518767.2 | K202: =K182 -> -504980.22 | L202: =L182 -> -2392242.2 | ... R202: =R182 -> 0
C203: Subsidio(-)/Contribucion(+) | D203: =D184 -> 878534.48
A205: ENERBIT | B205: OPORTUNO | C205: Total | D205: 0 | E205: 0 | F205: 0 | G205: 0 | H205: 0 | I205: 0 | J205: 0 | K205: 0 | L205: 0 | M205: 0 | N205: 0 | O205: 0 | P205: 0 | Q205: 0 | R205: 0
C206: Subsidio(-)/Contribucion(+) | D206: 0
A208: OCCIDENTE | B208: OPORTUNO | C208: Total | D208: =D190-P190 -> -34410 | E208: =E187 -> -1930.6 | F208: =F187 -> -1090.02 | G208: =G187 -> -572.11 | H208: =H187 -> -10651 | I208: =I187 -> -255.08 | J208: =J187 -> -2237.53 | K208: =K187 -> -3286.56 | L208: =L187 -> -15556.53 | ... R208: =R187 -> 0
C209: Subsidio(-)/Contribucion(+) | D209: =D189 -> 6072.2
A211: CIUDAD LIMPIA-ACUEDUCTO | B211: OPORTUNO | C211: Total | D211: 0 | E211: 0 | F211: 0 | G211: 0 | H211: 0 | I211: 0 | J211: 0 | K211: 0 | L211: 0 | M211: 0 | N211: 0 | O211: 0 | P211: 0 | Q211: 0 | R211: 0
C212: Subsidio(-)/Contribucion(+) | D212: 0
B214: BOGOTA LIMPIA
D215: Total | E215: Componente TDF | F215: Componente TTL | G215: Componente TVIAT | H215: Aprovechamiento | I215: CCSA Prest.Aprov. | J215: Componente TCS | K215: Componente TLU | L215: Componente TBL | M215: Componente TRT | N215: CCSA Prest. No Aprov. | O215: Ajuste Decena | P215: SERVICIO ESPECIALES | Q215: Ajuste Recargo Aseo | R215: Otros
C216: Vlr Servicio | D216: -20867961 | E216: -1183575.9 | F216: -660785.56 | G216: -360417.26 | H216: -4675852.3 | I216: -165970.21 | J216: -1465578.8 | K216: -1450674.8 | L216: -7405960.4 | M216: -3230098.4 | N216: -269110.48 | O216: 62.73 | P216: 0 | Q216: 0 | R216: 0
C217: Vlr Intereses | D217: -70844.04 | E217: -12872.38 | F217: -3618.8 | G217: -466.49 | H217: -10077.28 | I217: -549.6 | J217: -4821.86 | K217: -4702.86 | L217: 6554.19 | M217: -39396.22 | N217: -896.75 | O217: 4.01 | P217: 0 | Q217: 0 | R217: 0
B218: Componente | C218: Total | D218: -20938805 | E218: -1196448.3 | F218: -664404.36 | G218: -360883.75 | H218: -4685929.5 | I218: -166519.81 | J218: -1470400.6 | K218: -1455377.7 | L218: -7399406.2 | M218: -3269494.6 | N218: -270007.23 | O218: 66.74 | P218: 0 | Q218: 0 | R218: 0
C219: Subsidio(-)/Contribucion(+) | D219: 693280.58 | E219: -60645.51 | F219: -33250.49 | G219: -18054.75 | H219: 283080.41 | I219: 10777.75 | J219: 94543.45 | K219: 92360.66 | L219: 468946.29 | M219: -162062.32 | N219: 17585.09 | O219: 0 | P219: 0 | Q219: 0 | R219: 0
B220: Subs/Cont | C220: Total | D220: 693280.58 | E220: -60645.51 | F220: -33250.49 | G220: -18054.75 | H220: 283080.41 | I220: 10777.75 | J220: 94543.45 | K220: 92360.66 | L220: 468946.29 | M220: -162062.32 | N220: 17585.09 | O220: 0 | P220: 0 | Q220: 0 | R220: 0
A221: ENEL | B221: Total | D221: -20245525 | E221: -1257093.8 | F221: -697654.85 | G221: -378938.5 | H221: -4402849.1 | I221: -155742.06 | J221: -1375857.2 | K221: -1363017 | L221: -6930459.9 | M221: -3431557 | N221: -252422.14 | O221: 66.74 | P221: 0 | Q221: 0 | R221: 0
C222: Vlr Servicio | D222: -259479.77 | E222: -15026.46 | F222: -8271.59 | G222: -4621.74 | H222: -60252.47 | I222: -1586.3 | J222: -13915.03 | K222: -18903.75 | L222: -95910.51 | M222: -38402.41 | N222: -2588.19 | O222: -1.32 | P222: 0 | Q222: 0 | R222: 0
C223: Vlr Intereses | D223: -49.05 | E223: -4.09 | F223: -1.88 | G223: -1.12 | H223: -10.47 | I223: -0.26 | J223: -2.32 | K223: -3.03 | L223: -15.29 | M223: -10.16 | N223: -0.43 | O223: 0 | P223: 0 | Q223: 0 | R223: 0
B224: Componente | C224: Total | D224: -259528.82 | E224: -15030.55 | F224: -8273.47 | G224: -4622.86 | H224: -60262.94 | I224: -1586.56 | J224: -13917.35 | K224: -18906.78 | L224: -95925.8 | M224: -38412.57 | N224: -2588.62 | O224: -1.32 | P224: 0 | Q224: 0 | R224: 0
C225: Subsidio(-)/Contribucion(+) | D225: -2471.18 | E225: -1736.67 | F225: -963.5 | G225: -534.14 | H225: 1365.54 | I225: 52.25 | J225: 458.4 | K225: 430.98 | L225: 2147.44 | M225: -3776.73 | N225: 85.25 | O225: 0 | P225: 0 | Q225: 0 | R225: 0
B226: Subs/Cont | C226: Total | D226: -2471.18 | E226: -1736.67 | F226: -963.5 | G226: -534.14 | H226: 1365.54 | I226: 52.25 | J226: 458.4 | K226: 430.98 | L226: 2147.44 | M226: -3776.73 | N226: 85.25 | O226: 0 | P226: 0 | Q226: 0 | R226: 0
A227: NUEVO ESQUEMA | B227: Total | D227: -262000 | E227: -16767.22 | F227: -9236.97 | G227: -5157 | H227: -58897.4 | I227: -1534.31 | J227: -13458.95 | K227: -18475.8 | L227: -93778.36 | M227: -42189.3 | N227: -2503.37 | O227: -1.32 | P227: 0 | Q227: 0 | R227: 0
C228: Vlr Servicio | D228: -1635050.2 | E228: -111870.23 | F228: -35415.45 | G228: -15333.31 | H228: -336426.68 | I228: -13502.83 | J228: -118446.26 | K228: -113401.48 | L228: -491215.82 | M228: -378289.34 | N228: -21170.29 | O228: 21.48 | P228: 0 | Q228: 0 | R228: 0
C229: Vlr Intereses | D229: -314498.78 | E229: -44325.59 | F229: -11077.12 | G229: -1474.02 | H229: -30552.42 | I229: -1879 | J229: -16482.18 | K229: -15287.5 | L229: -48055.15 | M229: -142301.25 | N229: -3065.58 | O229: 1.03 | P229: 0 | Q229: 0 | R229: 0
B230: Componente | C230: Total | D230: -1949549 | E230: -156195.82 | F230: -46492.57 | G230: -16807.33 | H230: -366979.1 | I230: -15381.83 | J230: -134928.44 | K230: -128688.98 | L230: -539270.97 | M230: -520590.59 | N230: -24235.87 | O230: 22.51 | P230: 0 | Q230: 0 | R230: 0
C231: Subsidio(-)/Contribucion(+) | D231: 207013.99 | E231: 4148.27 | F231: 10450.38 | G231: 6186.7 | H231: 62465.45 | I231: 1934.51 | J231: 16968.9 | K231: 17248.9 | L231: 95821.56 | M231: -11366.89 | N231: 3156.21 | O231: 0 | P231: 0 | Q231: 0 | R231: 0
B232: Subs/Cont | C232: Total | D232: 207013.99 | E232: 4148.27 | F232: 10450.38 | G232: 6186.7 | H232: 62465.45 | I232: 1934.51 | J232: 16968.9 | K232: 17248.9 | L232: 95821.56 | M232: -11366.89 | N232: 3156.21 | O232: 0 | P232: 0 | Q232: 0 | R232: 0
A233: OCCIDENTE | B233: Total | D233: -1742535 | E233: -152047.55 | F233: -36042.19 | G233: -10620.63 | H233: -304513.65 | I233: -13447.32 | J233: -117959.54 | K233: -111440.08 | L233: -443449.41 | M233: -531957.48 | N233: -21079.66 | O233: 22.51 | P233: 0 | Q233: 0 | R233: 0
A234: Total | D234: -22250060 | E234: -1425908.6 | F234: -742934.01 | G234: -394716.13 | H234: -4766260.2 | I234: -170723.69 | J234: -1507275.7 | K234: -1492932.9 | L234: -7467687.7 | M234: -4005703.8 | N234: -276005.17 | O234: 87.93 | P234: 0 | Q234: 0 | R234: 0
A310: TOTAL | B310: OPORTUNO | C310: Total | D310: =D234-P234 -> -22250060 | E310: =E230+E224+E218 -> -1367674.7 | F310: =F230+F224+F218 -> -719170.4 | G310: =G230+G224+G218 -> -382313.94 | H310: =H230+H224+H218 -> -5113171.6 | I310: =I230+I224+I218 -> -183488.2 | J310: =J230+J224+J218 -> -1619246.4 | K310: =K230+K224+K218 -> -1602973.4 | L310: =L230+L224+L218 -> -8034602.9 | ... R310: =R230+R224+R218 -> 0
C311: Subsidio(-)/Contribucion(+) | D311: =D232+D226+D220 -> 897823.39
A313: RECIPROCIDAD | B313: OPORTUNO | C313: Total | D313: =D227-P227 -> -262000 | E313: =E224 -> -15030.55 | F313: =F224 -> -8273.47 | G313: =G224 -> -4622.86 | H313: =H224 -> -60262.94 | I313: =I224 -> -1586.56 | J313: =J224 -> -13917.35 | K313: =K224 -> -18906.78 | L313: =L224 -> -95925.8 | ... R313: =R224 -> 0
C314: Subsidio(-)/Contribucion(+) | D314: =D226 -> -2471.18
A316: ENEL | B316: OPORTUNO | C316: Total | D316: =D221-P221 -> -20245525 | E316: =E218 -> -1196448.3 | F316: =F218 -> -664404.36 | G316: =G218 -> -360883.75 | H316: =H218 -> -4685929.5 | I316: =I218 -> -166519.81 | J316: =J218 -> -1470400.6 | K316: =K218 -> -1455377.7 | L316: =L218 -> -7399406.2 | ... R316: =R218 -> 0
C317: Subsidio(-)/Contribucion(+) | D317: =D220 -> 693280.58
A319: ENERBIT | B319: OPORTUNO | C319: Total | D319: 0 | E319: 0 | F319: 0 | G319: 0 | H319: 0 | I319: 0 | J319: 0 | K319: 0 | L319: 0 | M319: 0 | N319: 0 | O319: 0 | P319: 0 | Q319: 0 | R319: 0
...

Sheet SALDOS POR NOTA
B1: PROMOAMBIENTAL
C2: Total | D2: Componente TDF | E2: Componente TTL | F2: Componente TVIAT | G2: Aprovechamiento | H2: CCSA Prest.Aprov. | I2: Especiales | J2: Componente TCS | K2: Componente TLU | L2: Componente TBL | M2: Componente TRT | N2: CCSA Prest. No Aprov. | O2: Deb/Cred
B3: Vlr Servicio | C3: 0 | D3: 0 | E3: 0 | F3: 0 | G3: 0 | H3: 0 | I3: 0 | J3: 0 | K3: 0 | L3: 0 | M3: 0 | N3: 0 | O3: 0
B4: Vlr Intereses | C4: 0 | D4: 0 | E4: 0 | F4: 0 | G4: 0 | H4: 0 | I4: 0 | J4: 0 | K4: 0 | L4: 0 | M4: 0 | N4: 0 | O4: 0
A5: Componente | B5: Total | C5: 0 | D5: 0 | E5: 0 | F5: 0 | G5: 0 | H5: 0 | I5: 0 | J5: 0 | K5: 0 | L5: 0 | M5: 0 | N5: 0 | O5: 0
B6: Subsidio(-)/Contribucion(+) | C6: 0 | D6: 0 | E6: 0 | F6: 0 | G6: 0 | H6: 0 | I6: 0 | J6: 0 | K6: 0 | L6: 0 | M6: 0 | N6: 0 | O6: 0
A7: Subs/Cont | B7: Total | C7: 0 | D7: 0 | E7: 0 | F7: 0 | G7: 0 | H7: 0 | I7: 0 | J7: 0 | K7: 0 | L7: 0 | M7: 0 | N7: 0 | O7: 0
A8: Total | C8: 0 | D8: 0 | E8: 0 | F8: 0 | G8: 0 | H8: 0 | I8: 0 | J8: 0 | K8: 0 | L8: 0 | M8: 0 | N8: 0 | O8: 0
B10: Total | C10: =C8-I8 -> 0 | D10: =D5 -> 0 | E10: =E5 -> 0 | F10: =F5 -> 0 | G10: =G5 -> 0 | H10: =H5 -> 0 | I10: =I5 -> 0 | J10: =J5 -> 0 | K10: =K5 -> 0 | ... P10: =P5 -> 0
B11: Subsidio(-)/Contribucion(+) | C11: =C7 -> 0
B14: LIME
C15: Total | D15: Componente TDF | E15: Componente TTL | F15: Componente TVIAT | G15: Aprovechamiento | H15: CCSA Prest.Aprov. | I15: Especiales | J15: Componente TCS | K15: Componente TLU | L15: Componente TBL | M15: Componente TRT | N15: CCSA Prest. No Aprov. | O15: Deb/Cred
B16: Vlr Servicio | C16: 0 | D16: 0 | E16: 0 | F16: 0 | G16: 0 | H16: 0 | I16: 0 | J16: 0 | K16: 0 | L16: 0 | M16: 0 | N16: 0 | O16: 0
B17: Vlr Intereses | C17: 0 | D17: 0 | E17: 0 | F17: 0 | G17: 0 | H17: 0 | I17: 0 | J17: 0 | K17: 0 | L17: 0 | M17: 0 | N17: 0 | O17: 0
A18: Componente | B18: Total | C18: 0 | D18: 0 | E18: 0 | F18: 0 | G18: 0 | H18: 0 | I18: 0 | J18: 0 | K18: 0 | L18: 0 | M18: 0 | N18: 0 | O18: 0
B19: Subsidio(-)/Contribucion(+) | C19: 0 | D19: 0 | E19: 0 | F19: 0 | G19: 0 | H19: 0 | I19: 0 | J19: 0 | K19: 0 | L19: 0 | M19: 0 | N19: 0 | O19: 0
A20: Subs/Cont | B20: Total | C20: 0 | D20: 0 | E20: 0 | F20: 0 | G20: 0 | H20: 0 | I20: 0 | J20: 0 | K20: 0 | L20: 0 | M20: 0 | N20: 0 | O20: 0
A21: Total | C21: 0 | D21: 0 | E21: 0 | F21: 0 | G21: 0 | H21: 0 | I21: 0 | J21: 0 | K21: 0 | L21: 0 | M21: 0 | N21: 0 | O21: 0
B23: Total | C23: =C21-I21 -> 0 | D23: =D18 -> 0 | E23: =E18 -> 0 | F23: =F18 -> 0 | G23: =G18 -> 0 | H23: =H18 -> 0 | I23: =I18 -> 0 | J23: =J18 -> 0 | K23: =K18 -> 0 | ... P23: =P18 -> 0
B24: Subsidio(-)/Contribucion(+) | C24: =C20 -> 0
B27: CIUDAD LIMPIA
C28: Total | D28: Componente TDF | E28: Componente TTL | F28: Componente TVIAT | G28: Aprovechamiento | H28: CCSA Prest.Aprov. | I28: Especiales | J28: Componente TCS | K28: Componente TLU | L28: Componente TBL | M28: Componente TRT | N28: CCSA Prest. No Aprov. | O28: Deb/Cred
B29: Vlr Servicio | C29: 0 | D29: 0 | E29: 0 | F29: 0 | G29: 0 | H29: 0 | I29: 0 | J29: 0 | K29: 0 | L29: 0 | M29: 0 | N29: 0 | O29: 0
B30: Vlr Intereses | C30: 0 | D30: 0 | E30: 0 | F30: 0 | G30: 0 | H30: 0 | I30: 0 | J30: 0 | K30: 0 | L30: 0 | M30: 0 | N30: 0 | O30: 0
A31: Componente | B31: Total | C31: 0 | D31: 0 | E31: 0 | F31: 0 | G31: 0 | H31: 0 | I31: 0 | J31: 0 | K31: 0 | L31: 0 | M31: 0 | N31: 0 | O31: 0
B32: Subsidio(-)/Contribucion(+) | C32: 0 | D32: 0 | E32: 0 | F32: 0 | G32: 0 | H32: 0 | I32: 0 | J32: 0 | K32: 0 | L32: 0 | M32: 0 | N32: 0 | O32: 0
A33: Subs/Cont | B33: Total | C33: 0 | D33: 0 | E33: 0 | F33: 0 | G33: 0 | H33: 0 | I33: 0 | J33: 0 | K33: 0 | L33: 0 | M33: 0 | N33: 0 | O33: 0
A34: Total | C34: 0 | D34: 0 | E34: 0 | F34: 0 | G34: 0 | H34: 0 | I34: 0 | J34: 0 | K34: 0 | L34: 0 | M34: 0 | N34: 0 | O34: 0
B36: Total | C36: =C34-I34 -> 0 | D36: =D31 -> 0 | E36: =E31 -> 0 | F36: =F31 -> 0 | G36: =G31 -> 0 | H36: =H31 -> 0 | I36: =I31 -> 0 | J36: =J31 -> 0 | K36: =K31 -> 0 | ... P36: =P31 -> 0
B37: Subsidio(-)/Contribucion(+) | C37: =C33 -> 0
B40: BOGOTA LIMPIA
C41: Total | D41: Componente TDF | E41: Componente TTL | F41: Componente TVIAT | G41: Aprovechamiento | H41: CCSA Prest.Aprov. | I41: Especiales | J41: Componente TCS | K41: Componente TLU | L41: Componente TBL | M41: Componente TRT | N41: CCSA Prest. No Aprov. | O41: Deb/Cred
B42: Vlr Servicio | C42: 0 | D42: 0 | E42: 0 | F42: 0 | G42: 0 | H42: 0 | I42: 0 | J42: 0 | K42: 0 | L42: 0 | M42: 0 | N42: 0 | O42: 0
B43: Vlr Intereses | C43: 0 | D43: 0 | E43: 0 | F43: 0 | G43: 0 | H43: 0 | I43: 0 | J43: 0 | K43: 0 | L43: 0 | M43: 0 | N43: 0 | O43: 0
A44: Componente | B44: Total | C44: 0 | D44: 0 | E44: 0 | F44: 0 | G44: 0 | H44: 0 | I44: 0 | J44: 0 | K44: 0 | L44: 0 | M44: 0 | N44: 0 | O44: 0
B45: Subsidio(-)/Contribucion(+) | C45: 0 | D45: 0 | E45: 0 | F45: 0 | G45: 0 | H45: 0 | I45: 0 | J45: 0 | K45: 0 | L45: 0 | M45: 0 | N45: 0 | O45: 0
A46: Subs/Cont | B46: Total | C46: 0 | D46: 0 | E46: 0 | F46: 0 | G46: 0 | H46: 0 | I46: 0 | J46: 0 | K46: 0 | L46: 0 | M46: 0 | N46: 0 | O46: 0
A47: Total | C47: 0 | D47: 0 | E47: 0 | F47: 0 | G47: 0 | H47: 0 | I47: 0 | J47: 0 | K47: 0 | L47: 0 | M47: 0 | N47: 0 | O47: 0
B49: Total | C49: =C47-I47 -> 0 | D49: =D44 -> 0 | E49: =E44 -> 0 | F49: =F44 -> 0 | G49: =G44 -> 0 | H49: =H44 -> 0 | I49: =I44 -> 0 | J49: =J44 -> 0 | K49: =K44 -> 0 | ... P49: =P44 -> 0
B50: Subsidio(-)/Contribucion(+) | C50: =C46 -> 0
B53: AREA LIMPIA
C54: Total | D54: Componente TDF | E54: Componente TTL | F54: Componente TVIAT | G54: Aprovechamiento | H54: CCSA Prest.Aprov. | I54: Especiales | J54: Componente TCS | K54: Componente TLU | L54: Componente TBL | M54: Componente TRT | N54: CCSA Prest. No Aprov. | O54: Deb/Cred
B55: Vlr Servicio | C55: 0 | D55: 0 | E55: 0 | F55: 0 | G55: 0 | H55: 0 | I55: 0 | J55: 0 | K55: 0 | L55: 0 | M55: 0 | N55: 0 | O55: 0
B56: Vlr Intereses | C56: 0 | D56: 0 | E56: 0 | F56: 0 | G56: 0 | H56: 0 | I56: 0 | J56: 0 | K56: 0 | L56: 0 | M56: 0 | N56: 0 | O56: 0
A57: Componente | B57: Total | C57: 0 | D57: 0 | E57: 0 | F57: 0 | G57: 0 | H57: 0 | I57: 0 | J57: 0 | K57: 0 | L57: 0 | M57: 0 | N57: 0 | O57: 0
B58: Subsidio(-)/Contribucion(+) | C58: 0 | D58: 0 | E58: 0 | F58: 0 | G58: 0 | H58: 0 | I58: 0 | J58: 0 | K58: 0 | L58: 0 | M58: 0 | N58: 0 | O58: 0
A59: Subs/Cont | B59: Total | C59: 0 | D59: 0 | E59: 0 | F59: 0 | G59: 0 | H59: 0 | I59: 0 | J59: 0 | K59: 0 | L59: 0 | M59: 0 | N59: 0 | O59: 0
A60: Total | C60: 0 | D60: 0 | E60: 0 | F60: 0 | G60: 0 | H60: 0 | I60: 0 | J60: 0 | K60: 0 | L60: 0 | M60: 0 | N60: 0 | O60: 0
B62: Total | C62: =C60-I60 -> 0 | D62: =D57 -> 0 | E62: =E57 -> 0 | F62: =F57 -> 0 | G62: =G57 -> 0 | H62: =H57 -> 0 | I62: =I57 -> 0 | J62: =J57 -> 0 | K62: =K57 -> 0 | ... P62: =P57 -> 0
B63: Subsidio(-)/Contribucion(+) | C63: =C59 -> 0

Sheet RETRIBUCION NEGATIVA
B1: PROMOAMBIENTAL
C2: Total | D2: Componente TDF | E2: Componente TTL | F2: Componente TVIAT | G2: Aprovechamiento | H2: CCSA Prest.Aprov. | I2: Especiales | J2: Componente TCS | K2: Componente TLU | L2: Componente TBL | M2: Componente TRT | N2: CCSA Prest. No Aprov. | O2: Deb/Cred
B3: Vlr Intereses | C3: 0 | D3: 0 | E3: 0 | F3: 0 | G3: 0 | H3: 0 | I3: 0 | J3: 0 | K3: 0 | L3: 0 | M3: 0 | N3: 0 | O3: 0
B4: Vlr Servicio | C4: 0 | D4: 0 | E4: 0 | F4: 0 | G4: 0 | H4: 0 | I4: 0 | J4: 0 | K4: 0 | L4: 0 | M4: 0 | N4: 0 | O4: 0
A5: Componente | B5: Total | C5: 0 | D5: 0 | E5: 0 | F5: 0 | G5: 0 | H5: 0 | I5: 0 | J5: 0 | K5: 0 | L5: 0 | M5: 0 | N5: 0 | O5: 0
B6: Subsidio(-)/Contribucion(+) | C6: 0 | D6: 0 | E6: 0 | F6: 0 | G6: 0 | H6: 0 | I6: 0 | J6: 0 | K6: 0 | L6: 0 | M6: 0 | N6: 0 | O6: 0
A7: Subs/Cont | B7: Total | C7: 0 | D7: 0 | E7: 0 | F7: 0 | G7: 0 | H7: 0 | I7: 0 | J7: 0 | K7: 0 | L7: 0 | M7: 0 | N7: 0 | O7: 0
A8: Total | C8: 0 | D8: 0 | E8: 0 | F8: 0 | G8: 0 | H8: 0 | I8: 0 | J8: 0 | K8: 0 | L8: 0 | M8: 0 | N8: 0 | O8: 0
B10: Total | C10: =C8-I8 -> 0 | D10: =D5 -> 0 | E10: =E5 -> 0 | F10: =F5 -> 0 | G10: =G5 -> 0 | H10: =H5 -> 0 | I10: =I5 -> 0 | J10: =J5 -> 0 | K10: =K5 -> 0 | ... O10: =O5 -> 0
B11: Subsidio(-)/Contribucion(+) | C11: =C7 -> 0
B14: LIME
C15: Total | D15: Componente TDF | E15: Componente TTL | F15: Componente TVIAT | G15: Aprovechamiento | H15: CCSA Prest.Aprov. | I15: Especiales | J15: Componente TCS | K15: Componente TLU | L15: Componente TBL | M15: Componente TRT | N15: CCSA Prest. No Aprov. | O15: Deb/Cred
B16: Vlr Intereses | C16: 0 | D16: 0 | E16: 0 | F16: 0 | G16: 0 | H16: 0 | I16: 0 | J16: 0 | K16: 0 | L16: 0 | M16: 0 | N16: 0 | O16: 0
B17: Vlr Servicio | C17: 0 | D17: 0 | E17: 0 | F17: 0 | G17: 0 | H17: 0 | I17: 0 | J17: 0 | K17: 0 | L17: 0 | M17: 0 | N17: 0 | O17: 0
A18: Componente | B18: Total | C18: 0 | D18: 0 | E18: 0 | F18: 0 | G18: 0 | H18: 0 | I18: 0 | J18: 0 | K18: 0 | L18: 0 | M18: 0 | N18: 0 | O18: 0
B19: Subsidio(-)/Contribucion(+) | C19: 0 | D19: 0 | E19: 0 | F19: 0 | G19: 0 | H19: 0 | I19: 0 | J19: 0 | K19: 0 | L19: 0 | M19: 0 | N19: 0 | O19: 0
A20: Subs/Cont | B20: Total | C20: 0 | D20: 0 | E20: 0 | F20: 0 | G20: 0 | H20: 0 | I20: 0 | J20: 0 | K20: 0 | L20: 0 | M20: 0 | N20: 0 | O20: 0
A21: Total | C21: 0 | D21: 0 | E21: 0 | F21: 0 | G21: 0 | H21: 0 | I21: 0 | J21: 0 | K21: 0 | L21: 0 | M21: 0 | N21: 0 | O21: 0
B23: Total | C23: =C21-I21 -> 0 | D23: =D18 -> 0 | E23: =E18 -> 0 | F23: =F18 -> 0 | G23: =G18 -> 0 | H23: =H18 -> 0 | I23: =I18 -> 0 | J23: =J18 -> 0 | K23: =K18 -> 0 | ... O23: =O18 -> 0
B24: Subsidio(-)/Contribucion(+) | C24: =C20 -> 0
B27: CIUDAD LIMPIA
C28: Total | D28: Componente TDF | E28: Componente TTL | F28: Componente TVIAT | G28: Aprovechamiento | H28: CCSA Prest.Aprov. | I28: Especiales | J28: Componente TCS | K28: Componente TLU | L28: Componente TBL | M28: Componente TRT | N28: CCSA Prest. No Aprov. | O28: Deb/Cred
B29: Vlr Intereses | C29: 0 | D29: 0 | E29: 0 | F29: 0 | G29: 0 | H29: 0 | I29: 0 | J29: 0 | K29: 0 | L29: 0 | M29: 0 | N29: 0 | O29: 0
B30: Vlr Servicio | C30: 0 | D30: 0 | E30: 0 | F30: 0 | G30: 0 | H30: 0 | I30: 0 | J30: 0 | K30: 0 | L30: 0 | M30: 0 | N30: 0 | O30: 0
A31: Componente | B31: Total | C31: 0 | D31: 0 | E31: 0 | F31: 0 | G31: 0 | H31: 0 | I31: 0 | J31: 0 | K31: 0 | L31: 0 | M31: 0 | N31: 0 | O31: 0
B32: Subsidio(-)/Contribucion(+) | C32: 0 | D32: 0 | E32: 0 | F32: 0 | G32: 0 | H32: 0 | I32: 0 | J32: 0 | K32: 0 | L32: 0 | M32: 0 | N32: 0 | O32: 0
A33: Subs/Cont | B33: Total | C33: 0 | D33: 0 | E33: 0 | F33: 0 | G33: 0 | H33: 0 | I33: 0 | J33: 0 | K33: 0 | L33: 0 | M33: 0 | N33: 0 | O33: 0
A34: Total | C34: 0 | D34: 0 | E34: 0 | F34: 0 | G34: 0 | H34: 0 | I34: 0 | J34: 0 | K34: 0 | L34: 0 | M34: 0 | N34: 0 | O34: 0
B36: Total | C36: =C34-I34 -> 0 | D36: =D31 -> 0 | E36: =E31 -> 0 | F36: =F31 -> 0 | G36: =G31 -> 0 | H36: =H31 -> 0 | I36: =I31 -> 0 | J36: =J31 -> 0 | K36: =K31 -> 0 | ... O36: =O31 -> 0
B37: Subsidio(-)/Contribucion(+) | C37: =C33 -> 0
B40: BOGOTA LIMPIA
C41: Total | D41: Componente TDF | E41: Componente TTL | F41: Componente TVIAT | G41: Aprovechamiento | H41: CCSA Prest.Aprov. | I41: Especiales | J41: Componente TCS | K41: Componente TLU | L41: Componente TBL | M41: Componente TRT | N41: CCSA Prest. No Aprov. | O41: Deb/Cred
B42: Vlr Intereses | C42: 0 | D42: 0 | E42: 0 | F42: 0 | G42: 0 | H42: 0 | I42: 0 | J42: 0 | K42: 0 | L42: 0 | M42: 0 | N42: 0 | O42: 0
B43: Vlr Servicio | C43: 0 | D43: 0 | E43: 0 | F43: 0 | G43: 0 | H43: 0 | I43: 0 | J43: 0 | K43: 0 | L43: 0 | M43: 0 | N43: 0 | O43: 0
A44: Componente | B44: Total | C44: 0 | D44: 0 | E44: 0 | F44: 0 | G44: 0 | H44: 0 | I44: 0 | J44: 0 | K44: 0 | L44: 0 | M44: 0 | N44: 0 | O44: 0
B45: Subsidio(-)/Contribucion(+) | C45: 0 | D45: 0 | E45: 0 | F45: 0 | G45: 0 | H45: 0 | I45: 0 | J45: 0 | K45: 0 | L45: 0 | M45: 0 | N45: 0 | O45: 0
A46: Subs/Cont | B46: Total | C46: 0 | D46: 0 | E46: 0 | F46: 0 | G46: 0 | H46: 0 | I46: 0 | J46: 0 | K46: 0 | L46: 0 | M46: 0 | N46: 0 | O46: 0
A47: Total | C47: 0 | D47: 0 | E47: 0 | F47: 0 | G47: 0 | H47: 0 | I47: 0 | J47: 0 | K47: 0 | L47: 0 | M47: 0 | N47: 0 | O47: 0
B49: Total | C49: =C47-I47 -> 0 | D49: =D44 -> 0 | E49: =E44 -> 0 | F49: =F44 -> 0 | G49: =G44 -> 0 | H49: =H44 -> 0 | I49: =I44 -> 0 | J49: =J44 -> 0 | K49: =K44 -> 0 | ... O49: =O44 -> 0
B50: Subsidio(-)/Contribucion(+) | C50: =C46 -> 0
B53: AREA LIMPIA
C54: Total | D54: Componente TDF | E54: Componente TTL | F54: Componente TVIAT | G54: Aprovechamiento | H54: CCSA Prest.Aprov. | I54: Especiales | J54: Componente TCS | K54: Componente TLU | L54: Componente TBL | M54: Componente TRT | N54: CCSA Prest. No Aprov. | O54: Deb/Cred
B55: Vlr Servicio | C55: 0 | D55: 0 | E55: 0 | F55: 0 | G55: 0 | H55: 0 | I55: 0 | J55: 0 | K55: 0 | L55: 0 | M55: 0 | N55: 0 | O55: 0
A56: Componente | B56: Total | C56: 0 | D56: 0 | E56: 0 | F56: 0 | G56: 0 | H56: 0 | I56: 0 | J56: 0 | K56: 0 | L56: 0 | M56: 0 | N56: 0 | O56: 0
B57: Subsidio(-)/Contribucion(+) | C57: 0 | D57: 0 | E57: 0 | F57: 0 | G57: 0 | H57: 0 | I57: 0 | J57: 0 | K57: 0 | L57: 0 | M57: 0 | N57: 0 | O57: 0
A58: Subs/Cont | B58: Total | C58: 0 | D58: 0 | E58: 0 | F58: 0 | G58: 0 | H58: 0 | I58: 0 | J58: 0 | K58: 0 | L58: 0 | M58: 0 | N58: 0 | O58: 0
A59: Total | C59: 0 | D59: 0 | E59: 0 | F59: 0 | G59: 0 | H59: 0 | I59: 0 | J59: 0 | K59: 0 | L59: 0 | M59: 0 | N59: 0 | O59: 0
B61: Total | C61: =C59-I59 -> 0 | D61: =D56 -> 0 | E61: =E56 -> 0 | F61: =F56 -> 0 | G61: =G56 -> 0 | H61: =H56 -> 0 | I61: =I56 -> 0 | J61: =J56 -> 0 | K61: =K56 -> 0 | ... O61: =O56 -> 0
B62: Subsidio(-)/Contribucion(+) | C62: =C58 -> 0

Sheet AJUSTES - SF-T
F3: PROCERASEO S.A.S. | I3: NIT: 901 153 639 - 0 | M3: Codigo Remuneración: | N3: ='CONSOLIDADO_TOTAL RECAUDO'!N3 -> 2026091 | U3: PROCERASEO S.A.S. | W3: NIT: 901 153 639 - 0 | AA3: Codigo Remuneración: | AC3: =N3 -> 2026091
F4: 3. ESQUEMA FINANCIERO DEL SERVICIO PUBLICO DE ASEO | U4: 3. ESQUEMA FINANCIERO DEL SERVICIO PUBLICO DE ASEO
F5: Resoluciòn UAESP Número 27 de 2018 | U5: Resoluciòn UAESP Número 27 de 2018
C6: Fecha de Proceso: | D6: ='CONSOLIDADO_TOTAL RECAUDO'!D6 -> 46282 | F6: SALDOS A FAVOR POR NOTA | U6: =+F6 -> SALDOS A FAVOR POR NOTA
C7: Hora: | D7: ='CONSOLIDADO_TOTAL RECAUDO'!D7 -> 0.58333333 | F7: Fecha Desde: | H7: ='CONSOLIDADO_TOTAL RECAUDO'!G7 -> 46266 | J7: Feha Hasta: | K7: ='CONSOLIDADO_TOTAL RECAUDO'!K7 -> 46280 | U7: =F7 -> Fecha Desde: | V7: =H7 -> 46266 | X7: =J7 -> Feha Hasta: | Y7: =K7 -> 46280
B8: ASE | C8: Concesionarios | D8: Recaudo Total | E8: Recaudo por disposicion final | F8: Recaudo por tratamiento de lixiviados | G8: Recaudo por Componente VIAT ( Decreto 2412/2018) | H8: Recaudo por aprovechamiento | I8: Recaudo del componente de comercializacion para Aprovechamiento (11,4%) | J8: Balance de subsidio o contribuciones | K8: RECAUDO BASE DE REMUNERACION | L8: Costo de la Interventoría | M8: REMUNERACION FINAL | N8: Conceptos especiales | O8: REMUNERACION FINAL MAS CONCEPTOS ESPECIALES | S8: ASE | T8: Concesionarios | U8: Tarifa de Comercialización del Servicio. ( TCS) | V8: Tarifa de Limpieza Urbana del Servicio. ( TLU) | W8: Tarifa de Barrido y Limpieza del Servicio. ( TBL) | X8: Tarifa de Recolección y Transporte del Servicio. (TRT) | Y8: Recaudo del componente de comercializacion para Aprovechamiento (18,6%) | Z8: Costo de la Interventoría | AA8: Ajuste a la decena | AB8: Conceptos especiales | AC8: Diferencial Balance S / C (Fac vs Rec) | AD8: Balance S / C Con Baase en (Recaudo) | AE8: REMUNERACION FINAL MAS CONCEPTOS ESPECIALES
B9: 1 | C9: PROMOAMBIENTAL DISTRITO S.A.S. ESP. | D9: ='SALDOS POR NOTA'!C10 -> 0 | E9: ='SALDOS POR NOTA'!D10 -> 0 | F9: ='SALDOS POR NOTA'!E10 -> 0 | G9: ='SALDOS POR NOTA'!F10 -> 0 | H9: ='SALDOS POR NOTA'!G10 -> 0 | I9: ='SALDOS POR NOTA'!H10 -> 0 | J9: 0 | K9: =D9-E9-F9-G9-H9-I9-J9 -> 0 | L9: 0 | M9: =K9-L9 -> 0 | N9: ='SALDOS POR NOTA'!I10 -> 0 | O9: =M9+N9 -> 0 | S9: 1 | T9: PROMOAMBIENTAL DISTRITO S.A.S. ESP. | U9: ='SALDOS POR NOTA'!J10 -> 0 | V9: ='SALDOS POR NOTA'!K10 -> 0 | W9: ='SALDOS POR NOTA'!L10 -> 0 | X9: ='SALDOS POR NOTA'!M10 -> 0 | Y9: ='SALDOS POR NOTA'!N10 -> 0 | Z9: =L9*-1 -> 0 | AA9: ='SALDOS POR NOTA'!O10 -> 0 | AB9: =N9 -> 0 | AC9: =-J9+AD9 -> 0 | AD9: ='SALDOS POR NOTA'!C11 -> 0 | AE9: =SUM(U9:AC9) -> 0 | AF9: =(AE9-O9) -> 0 | AG9: =AF9=0 -> TRUE
B10: 2 | C10: LIMPIEZA METROPOLITANA S.A. ESP. | D10: ='SALDOS POR NOTA'!C23 -> 0 | E10: ='SALDOS POR NOTA'!D23 -> 0 | F10: ='SALDOS POR NOTA'!E23 -> 0 | G10: ='SALDOS POR NOTA'!F23 -> 0 | H10: ='SALDOS POR NOTA'!G23 -> 0 | I10: ='SALDOS POR NOTA'!H23 -> 0 | J10: 0 | K10: =D10-E10-F10-G10-H10-I10-J10 -> 0 | L10: 0 | M10: =K10-L10 -> 0 | N10: ='SALDOS POR NOTA'!I23 -> 0 | O10: =M10+N10 -> 0 | S10: 2 | T10: LIMPIEZA METROPOLITANA S.A. ESP. | U10: ='SALDOS POR NOTA'!J23 -> 0 | V10: ='SALDOS POR NOTA'!K23 -> 0 | W10: ='SALDOS POR NOTA'!L23 -> 0 | X10: ='SALDOS POR NOTA'!M23 -> 0 | Y10: ='SALDOS POR NOTA'!N23 -> 0 | Z10: =L10*-1 -> 0 | AA10: ='SALDOS POR NOTA'!O23 -> 0 | AB10: =N10 -> 0 | AC10: =-J10+AD10 -> 0 | AD10: ='SALDOS POR NOTA'!C24 -> 0 | AE10: =SUM(U10:AC10) -> 0 | AF10: =(AE10-O10) -> 0 | AG10: =AF10=0 -> TRUE
B11: 3 | C11: CIUDAD LIMPIA BOGOTA S.A. ESP. | D11: ='SALDOS POR NOTA'!C36 -> 0 | E11: ='SALDOS POR NOTA'!D36 -> 0 | F11: ='SALDOS POR NOTA'!E36 -> 0 | G11: ='SALDOS POR NOTA'!F36 -> 0 | H11: ='SALDOS POR NOTA'!G36 -> 0 | I11: ='SALDOS POR NOTA'!H36 -> 0 | J11: 0 | K11: =D11-E11-F11-G11-H11-I11-J11 -> 0 | L11: 0 | M11: =K11-L11 -> 0 | N11: ='SALDOS POR NOTA'!I36 -> 0 | O11: =M11+N11 -> 0 | S11: 3 | T11: CIUDAD LIMPIA BOGOTA S.A. ESP. | U11: ='SALDOS POR NOTA'!J36 -> 0 | V11: ='SALDOS POR NOTA'!K36 -> 0 | W11: ='SALDOS POR NOTA'!L36 -> 0 | X11: ='SALDOS POR NOTA'!M36 -> 0 | Y11: ='SALDOS POR NOTA'!N36 -> 0 | Z11: =L11*-1 -> 0 | AA11: ='SALDOS POR NOTA'!O36 -> 0 | AB11: =N11 -> 0 | AC11: =-J11+AD11 -> 0 | AD11: ='SALDOS POR NOTA'!C37 -> 0 | AE11: =SUM(U11:AC11) -> 0 | AF11: =(AE11-O11) -> 0 | AG11: =AF11=0 -> TRUE
B12: 4 | C12: BOGOTA LIMPIA S.A.S. ESP. | D12: ='SALDOS POR NOTA'!C49 -> 0 | E12: ='SALDOS POR NOTA'!D49 -> 0 | F12: ='SALDOS POR NOTA'!E49 -> 0 | G12: ='SALDOS POR NOTA'!F49 -> 0 | H12: ='SALDOS POR NOTA'!G49 -> 0 | I12: ='SALDOS POR NOTA'!H49 -> 0 | J12: 0 | K12: =D12-E12-F12-G12-H12-I12-J12 -> 0 | L12: 0 | M12: =K12-L12 -> 0 | N12: ='SALDOS POR NOTA'!I49 -> 0 | O12: =M12+N12 -> 0 | S12: 4 | T12: BOGOTA LIMPIA S.A.S. ESP. | U12: ='SALDOS POR NOTA'!J49 -> 0 | V12: ='SALDOS POR NOTA'!K49 -> 0 | W12: ='SALDOS POR NOTA'!L49 -> 0 | X12: ='SALDOS POR NOTA'!M49 -> 0 | Y12: ='SALDOS POR NOTA'!N49 -> 0 | Z12: =L12*-1 -> 0 | AA12: ='SALDOS POR NOTA'!O49 -> 0 | AB12: =N12 -> 0 | AC12: =-J12+AD12 -> 0 | AD12: ='SALDOS POR NOTA'!C50 -> 0 | AE12: =SUM(U12:AC12) -> 0 | AF12: =(AE12-O12) -> 0 | AG12: =AF12=0 -> TRUE
B13: 5 | C13: AREA LIMPIA DISTRITO CAPITAL S.A.S. ESP. | D13: ='SALDOS POR NOTA'!C62 -> 0 | E13: ='SALDOS POR NOTA'!D62 -> 0 | F13: ='SALDOS POR NOTA'!E62 -> 0 | G13: ='SALDOS POR NOTA'!F62 -> 0 | H13: ='SALDOS POR NOTA'!G62 -> 0 | I13: ='SALDOS POR NOTA'!H62 -> 0 | J13: 0 | K13: =D13-E13-F13-G13-H13-I13-J13 -> 0 | L13: 0 | M13: =K13-L13 -> 0 | N13: ='SALDOS POR NOTA'!I62 -> 0 | O13: =M13+N13 -> 0 | S13: 5 | T13: AREA LIMPIA DISTRITO CAPITAL S.A.S. ESP. | U13: ='SALDOS POR NOTA'!J62 -> 0 | V13: ='SALDOS POR NOTA'!K62 -> 0 | W13: ='SALDOS POR NOTA'!L62 -> 0 | X13: ='SALDOS POR NOTA'!M62 -> 0 | Y13: ='SALDOS POR NOTA'!N62 -> 0 | Z13: =L13*-1 -> 0 | AA13: ='SALDOS POR NOTA'!O62 -> 0 | AB13: =N13 -> 0 | AC13: =-J13+AD13 -> 0 | AD13: ='SALDOS POR NOTA'!C63 -> 0 | AE13: =SUM(U13:AC13) -> 0 | AF13: =(AE13-O13) -> 0 | AG13: =AF13=0 -> TRUE
C14: TOTAL | D14: =SUM(D9:D13) -> 0 | E14: =SUM(E9:E13) -> 0 | F14: =SUM(F9:F13) -> 0 | G14: =SUM(G9:G13) -> 0 | H14: =SUM(H9:H13) -> 0 | I14: =SUM(I9:I13) -> 0 | J14: =SUM(J9:J13) -> 0 | K14: =SUM(K9:K13) -> 0 | ... O14: =SUM(O9:O13) -> 0 | T14: TOTAL | U14: =SUM(U9:U13) -> 0 | V14: =SUM(V9:V13) -> 0 | W14: =SUM(W9:W13) -> 0 | X14: =SUM(X9:X13) -> 0 | Y14: =SUM(Y9:Y13) -> 0 | Z14: =SUM(Z9:Z13) -> 0 | AA14: =SUM(AA9:AA13) -> 0 | AB14: =SUM(AB9:AB13) -> 0 | ... AF14: =SUM(AF9:AF13) -> 0 | AG14: =AF14=0 -> TRUE
Y16: =SUM(U14:Y14) -> 0
F18: Firma autorizada
F22: PROCERASEO S.A.S. | I22: NIT: 901 153 639 - 0 | M22: Codigo Remuneración: | N22: =N3 -> 2026091 | U22: PROCERASEO S.A.S. | W22: NIT: 901 153 639 - 0 | AA22: Codigo Remuneración: | AC22: =N22 -> 2026091
F23: 3. ESQUEMA FINANCIERO DEL SERVICIO PUBLICO DE ASEO | U23: 3. ESQUEMA FINANCIERO DEL SERVICIO PUBLICO DE ASEO
F24: Resoluciòn UAESP Número 27 de 2018 | U24: Resoluciòn UAESP Número 27 de 2018
C25: Fecha de Proceso: | D25: =D6 -> 46282 | F25: RETRIBUCION NEGATIVA | U25: =+F25 -> RETRIBUCION NEGATIVA
C26: Hora: | D26: =D7 -> 0.58333333 | F26: Fecha Desde: | H26: =H7 -> 46266 | J26: Feha Hasta: | K26: =K7 -> 46280 | U26: =F26 -> Fecha Desde: | V26: =H26 -> 46266 | X26: =J26 -> Feha Hasta: | Y26: =K26 -> 46280
B27: ASE | C27: Concesionarios | D27: Recaudo Total | E27: Recaudo por disposicion final | F27: Recaudo por tratamiento de lixiviados | G27: Recaudo por Componente VIAT ( Decreto 2412/2018) | H27: Recaudo por aprovechamiento | I27: Recaudo del componente de comercializacion para Aprovechamiento (11,4%) | J27: Balance de subsidio o contribuciones | K27: RECAUDO BASE DE REMUNERACION | L27: Costo de la Interventoría | M27: REMUNERACION FINAL | N27: Conceptos especiales | O27: REMUNERACION FINAL MAS CONCEPTOS ESPECIALES | S27: ASE | T27: Concesionarios | U27: Tarifa de Comercialización del Servicio. ( TCS) | V27: Tarifa de Limpieza Urbana del Servicio. ( TLU) | W27: Tarifa de Barrido y Limpieza del Servicio. ( TBL) | X27: Tarifa de Recolección y Transporte del Servicio. (TRT) | Y27: Recaudo del componente de comercializacion para Aprovechamiento (18,6%) | Z27: Costo de la Interventoría | AA27: Ajuste a la decena | AB27: Conceptos especiales | AC27: Diferencial Balance S / C (Fac vs Rec) | AD27: Balance S / C Con Baase en (Recaudo) | AE27: REMUNERACION FINAL MAS CONCEPTOS ESPECIALES
B28: 1 | C28: PROMOAMBIENTAL DISTRITO S.A.S. ESP. | D28: ='RETRIBUCION NEGATIVA'!C10 -> 0 | E28: ='RETRIBUCION NEGATIVA'!D10 -> 0 | F28: ='RETRIBUCION NEGATIVA'!E10 -> 0 | G28: ='RETRIBUCION NEGATIVA'!F10 -> 0 | H28: ='RETRIBUCION NEGATIVA'!G10 -> 0 | I28: ='RETRIBUCION NEGATIVA'!H10 -> 0 | J28: 0 | K28: =D28-E28-F28-H28-I28-J28-G28 -> 0 | L28: 0 | M28: =K28-L28 -> 0 | N28: ='RETRIBUCION NEGATIVA'!I10 -> 0 | O28: =M28+N28 -> 0 | S28: 1 | T28: PROMOAMBIENTAL DISTRITO S.A.S. ESP. | U28: ='RETRIBUCION NEGATIVA'!J10 -> 0 | V28: ='RETRIBUCION NEGATIVA'!K10 -> 0 | W28: ='RETRIBUCION NEGATIVA'!L10 -> 0 | X28: ='RETRIBUCION NEGATIVA'!M10 -> 0 | Y28: ='RETRIBUCION NEGATIVA'!N10 -> 0 | Z28: =L28*-1 -> 0 | AA28: ='RETRIBUCION NEGATIVA'!O10 -> 0 | AB28: =N28 -> 0 | AC28: =-J28+AD28 -> 0 | AD28: ='RETRIBUCION NEGATIVA'!C11 -> 0 | AE28: =SUM(U28:AC28) -> 0 | AF28: =(AE28-O28) -> 0 | AG28: =AF28=0 -> TRUE
B29: 2 | C29: LIMPIEZA METROPOLITANA S.A. ESP. | D29: ='RETRIBUCION NEGATIVA'!C23 -> 0 | E29: ='RETRIBUCION NEGATIVA'!D23 -> 0 | F29: ='RETRIBUCION NEGATIVA'!E23 -> 0 | G29: ='RETRIBUCION NEGATIVA'!F23 -> 0 | H29: ='RETRIBUCION NEGATIVA'!G23 -> 0 | I29: ='RETRIBUCION NEGATIVA'!H23 -> 0 | J29: 0 | K29: =D29-E29-F29-H29-I29-J29-G29 -> 0 | L29: 0 | M29: =K29-L29 -> 0 | N29: ='RETRIBUCION NEGATIVA'!I23 -> 0 | O29: =M29+N29 -> 0 | S29: 2 | T29: LIMPIEZA METROPOLITANA S.A. ESP. | U29: ='RETRIBUCION NEGATIVA'!J23 -> 0 | V29: ='RETRIBUCION NEGATIVA'!K23 -> 0 | W29: ='RETRIBUCION NEGATIVA'!L23 -> 0 | X29: ='RETRIBUCION NEGATIVA'!M23 -> 0 | Y29: ='RETRIBUCION NEGATIVA'!N23 -> 0 | Z29: =L29*-1 -> 0 | AA29: ='RETRIBUCION NEGATIVA'!O23 -> 0 | AB29: =N29 -> 0 | AC29: =-J29+AD29 -> 0 | AD29: ='RETRIBUCION NEGATIVA'!C24 -> 0 | AE29: =SUM(U29:AC29) -> 0 | AF29: =(AE29-O29) -> 0 | AG29: =AF29=0 -> TRUE
B30: 3 | C30: CIUDAD LIMPIA BOGOTA S.A. ESP. | D30: ='RETRIBUCION NEGATIVA'!C36 -> 0 | E30: ='RETRIBUCION NEGATIVA'!D36 -> 0 | F30: ='RETRIBUCION NEGATIVA'!E36 -> 0 | G30: ='RETRIBUCION NEGATIVA'!F36 -> 0 | H30: ='RETRIBUCION NEGATIVA'!G36 -> 0 | I30: ='RETRIBUCION NEGATIVA'!H36 -> 0 | J30: 0 | K30: =D30-E30-F30-H30-I30-J30-G30 -> 0 | L30: 0 | M30: =K30-L30 -> 0 | N30: ='RETRIBUCION NEGATIVA'!I36 -> 0 | O30: =M30+N30 -> 0 | S30: 3 | T30: CIUDAD LIMPIA BOGOTA S.A. ESP. | U30: ='RETRIBUCION NEGATIVA'!J36 -> 0 | V30: ='RETRIBUCION NEGATIVA'!K36 -> 0 | W30: ='RETRIBUCION NEGATIVA'!L36 -> 0 | X30: ='RETRIBUCION NEGATIVA'!M36 -> 0 | Y30: ='RETRIBUCION NEGATIVA'!N36 -> 0 | Z30: =L30*-1 -> 0 | AA30: ='RETRIBUCION NEGATIVA'!O36 -> 0 | AB30: =N30 -> 0 | AC30: =-J30+AD30 -> 0 | AD30: ='RETRIBUCION NEGATIVA'!C37 -> 0 | AE30: =SUM(U30:AC30) -> 0 | AF30: =(AE30-O30) -> 0 | AG30: =AF30=0 -> TRUE
B31: 4 | C31: BOGOTA LIMPIA S.A.S. ESP. | D31: ='RETRIBUCION NEGATIVA'!C49 -> 0 | E31: ='RETRIBUCION NEGATIVA'!D49 -> 0 | F31: ='RETRIBUCION NEGATIVA'!E49 -> 0 | G31: ='RETRIBUCION NEGATIVA'!F49 -> 0 | H31: ='RETRIBUCION NEGATIVA'!G49 -> 0 | I31: ='RETRIBUCION NEGATIVA'!H49 -> 0 | J31: 0 | K31: =D31-E31-F31-H31-I31-J31-G31 -> 0 | L31: 0 | M31: =K31-L31 -> 0 | N31: ='RETRIBUCION NEGATIVA'!I49 -> 0 | O31: =M31+N31 -> 0 | S31: 4 | T31: BOGOTA LIMPIA S.A.S. ESP. | U31: ='RETRIBUCION NEGATIVA'!J49 -> 0 | V31: ='RETRIBUCION NEGATIVA'!K49 -> 0 | W31: ='RETRIBUCION NEGATIVA'!L49 -> 0 | X31: ='RETRIBUCION NEGATIVA'!M49 -> 0 | Y31: ='RETRIBUCION NEGATIVA'!N49 -> 0 | Z31: =L31*-1 -> 0 | AA31: ='RETRIBUCION NEGATIVA'!O49 -> 0 | AB31: =N31 -> 0 | AC31: =-J31+AD31 -> 0 | AD31: ='RETRIBUCION NEGATIVA'!C50 -> 0 | AE31: =SUM(U31:AC31) -> 0 | AF31: =(AE31-O31) -> 0 | AG31: =AF31=0 -> TRUE
B32: 5 | C32: AREA LIMPIA DISTRITO CAPITAL S.A.S. ESP. | D32: ='RETRIBUCION NEGATIVA'!C61 -> 0 | E32: ='RETRIBUCION NEGATIVA'!D61 -> 0 | F32: ='RETRIBUCION NEGATIVA'!E61 -> 0 | G32: ='RETRIBUCION NEGATIVA'!F61 -> 0 | H32: ='RETRIBUCION NEGATIVA'!G61 -> 0 | I32: ='RETRIBUCION NEGATIVA'!H61 -> 0 | J32: 0 | K32: =D32-E32-F32-H32-I32-J32-G32 -> 0 | L32: 0 | M32: =K32-L32 -> 0 | N32: ='RETRIBUCION NEGATIVA'!I61 -> 0 | O32: =M32+N32 -> 0 | S32: 5 | T32: AREA LIMPIA DISTRITO CAPITAL S.A.S. ESP. | U32: ='RETRIBUCION NEGATIVA'!J61 -> 0 | V32: ='RETRIBUCION NEGATIVA'!K61 -> 0 | W32: ='RETRIBUCION NEGATIVA'!L61 -> 0 | X32: ='RETRIBUCION NEGATIVA'!M61 -> 0 | Y32: ='RETRIBUCION NEGATIVA'!N61 -> 0 | Z32: =L32*-1 -> 0 | AA32: ='RETRIBUCION NEGATIVA'!O61 -> 0 | AB32: =N32 -> 0 | AC32: =-J32+AD32 -> 0 | AD32: ='RETRIBUCION NEGATIVA'!C62 -> 0 | AE32: =SUM(U32:AC32) -> 0 | AF32: =(AE32-O32) -> 0 | AG32: =AF32=0 -> TRUE
C33: TOTAL | D33: =SUM(D28:D32) -> 0 | E33: =SUM(E28:E32) -> 0 | F33: =SUM(F28:F32) -> 0 | G33: =SUM(G28:G32) -> 0 | H33: =SUM(H28:H32) -> 0 | I33: =SUM(I28:I32) -> 0 | J33: =SUM(J28:J32) -> 0 | K33: =SUM(K28:K32) -> 0 | ... O33: =SUM(O28:O32) -> 0 | T33: TOTAL | U33: =SUM(U28:U32) -> 0 | V33: =SUM(V28:V32) -> 0 | W33: =SUM(W28:W32) -> 0 | X33: =SUM(X28:X32) -> 0 | Y33: =SUM(Y28:Y32) -> 0 | Z33: =SUM(Z28:Z32) -> 0 | AA33: =SUM(AA28:AA32) -> 0 | AB33: =SUM(AB28:AB32) -> 0 | ... AF33: =SUM(AF28:AF32) -> 0 | AG33: =AF33=0 -> TRUE
J35: VALIDADOR DE POSTIVIOS EN REMUNERACION NEGATIVA | M35: =IF(MAX(D28:O32,U28:AE32)>0.9,"ERROR",TRUE) -> TRUE | Y35: =SUM(U33:Y33) -> 0
F37: Firma autorizada
F41: PROCERASEO S.A.S. | I41: NIT: 901 153 639 - 0 | M41: Codigo Remuneración: | N41: =N3 -> 2026091 | U41: PROCERASEO S.A.S. | W41: NIT: 901 153 639 - 0 | AA41: Codigo Remuneración: | AC41: =N41 -> 2026091
F42: 3. ESQUEMA FINANCIERO DEL SERVICIO PUBLICO DE ASEO | U42: 3. ESQUEMA FINANCIERO DEL SERVICIO PUBLICO DE ASEO
F43: Resoluciòn UAESP Número 27 de 2018 | U43: Resoluciòn UAESP Número 27 de 2018
C44: Fecha de Proceso: | D44: =D6 -> 46282 | F44: CONSOLIDADO SALDOS A FAVOR | U44: =+F44 -> CONSOLIDADO SALDOS A FAVOR
C45: Hora: | D45: =D7 -> 0.58333333 | F45: Fecha Desde: | H45: =H7 -> 46266 | J45: Feha Hasta: | K45: =K7 -> 46280 | U45: =F45 -> Fecha Desde: | V45: =H45 -> 46266 | X45: =J45 -> Feha Hasta: | Y45: =K45 -> 46280
B46: ASE | C46: Concesionarios | D46: Recaudo Total | E46: Recaudo por disposicion final | F46: Recaudo por tratamiento de lixiviados | G46: Recaudo por Componente VIAT ( Decreto 2412/2018) | H46: Recaudo por aprovechamiento | I46: Recaudo del componente de comercializacion para Aprovechamiento (11,4%) | J46: Balance de subsidio o contribuciones | K46: RECAUDO BASE DE REMUNERACION | L46: Costo de la Interventoría | M46: REMUNERACION FINAL | N46: Conceptos especiales | O46: REMUNERACION FINAL MAS CONCEPTOS ESPECIALES | S46: ASE | T46: Concesionarios | U46: Tarifa de Comercialización del Servicio. ( TCS) | V46: Tarifa de Limpieza Urbana del Servicio. ( TLU) | W46: Tarifa de Barrido y Limpieza del Servicio. ( TBL) | X46: Tarifa de Recolección y Transporte del Servicio. (TRT) | Y46: Recaudo del componente de comercializacion para Aprovechamiento (18,6%) | Z46: Costo de la Interventoría | AA46: Ajuste a la decena | AB46: Conceptos especiales | AC46: Diferencial Balance S / C (Fac vs Rec) | AD46: Balance S / C Con Baase en (Recaudo) | AE46: REMUNERACION FINAL MAS CONCEPTOS ESPECIALES
B47: 1 | C47: PROMOAMBIENTAL DISTRITO S.A.S. ESP. | D47: =D9+D28 -> 0 | E47: =E9+E28 -> 0 | F47: =F9+F28 -> 0 | G47: =G9+G28 -> 0 | H47: =H9+H28 -> 0 | I47: =I9+I28 -> 0 | J47: =J9+J28 -> 0 | K47: =D47-E47-F47-G47-H47-I47-J47 -> 0 | L47: 0 | M47: =K47-L47 -> 0 | N47: =N9+N28 -> 0 | O47: =M47+N47 -> 0 | S47: 1 | T47: PROMOAMBIENTAL DISTRITO S.A.S. ESP. | U47: =U9+U28 -> 0 | V47: =V9+V28 -> 0 | W47: =W9+W28 -> 0 | X47: =X9+X28 -> 0 | Y47: =Y9+Y28 -> 0 | Z47: =-L47 -> 0 | AA47: =AA9+AA28 -> 0 | AB47: =AB9+AB28 -> 0 | AC47: =AC9+AC28 -> 0 | AD47: =AD9+AD28 -> 0 | AE47: =SUM(U47:AC47) -> 0 | AF47: =(AE47-O47) -> 0 | AG47: =AF47=0 -> TRUE
B48: 2 | C48: LIMPIEZA METROPOLITANA S.A. ESP. | D48: =D10+D29 -> 0 | E48: =E10+E29 -> 0 | F48: =F10+F29 -> 0 | G48: =G10+G29 -> 0 | H48: =H10+H29 -> 0 | I48: =I10+I29 -> 0 | J48: =J10+J29 -> 0 | K48: =D48-E48-F48-G48-H48-I48-J48 -> 0 | L48: 0 | M48: =K48-L48 -> 0 | N48: =N10+N29 -> 0 | O48: =M48+N48 -> 0 | S48: 2 | T48: LIMPIEZA METROPOLITANA S.A. ESP. | U48: =U10+U29 -> 0 | V48: =V10+V29 -> 0 | W48: =W10+W29 -> 0 | X48: =X10+X29 -> 0 | Y48: =Y10+Y29 -> 0 | Z48: =-L48 -> 0 | AA48: =AA10+AA29 -> 0 | AB48: =AB10+AB29 -> 0 | AC48: =AC10+AC29 -> 0 | AD48: =AD10+AD29 -> 0 | AE48: =SUM(U48:AC48) -> 0 | AF48: =(AE48-O48) -> 0 | AG48: =AF48=0 -> TRUE
B49: 3 | C49: CIUDAD LIMPIA BOGOTA S.A. ESP. | D49: =D11+D30 -> 0 | E49: =E11+E30 -> 0 | F49: =F11+F30 -> 0 | G49: =G11+G30 -> 0 | H49: =H11+H30 -> 0 | I49: =I11+I30 -> 0 | J49: =J11+J30 -> 0 | K49: =D49-E49-F49-G49-H49-I49-J49 -> 0 | L49: 0 | M49: =K49-L49 -> 0 | N49: =N11+N30 -> 0 | O49: =M49+N49 -> 0 | S49: 3 | T49: CIUDAD LIMPIA BOGOTA S.A. ESP. | U49: =U11+U30 -> 0 | V49: =V11+V30 -> 0 | W49: =W11+W30 -> 0 | X49: =X11+X30 -> 0 | Y49: =Y11+Y30 -> 0 | Z49: =-L49 -> 0 | AA49: =AA11+AA30 -> 0 | AB49: =AB11+AB30 -> 0 | AC49: =AC11+AC30 -> 0 | AD49: =AD11+AD30 -> 0 | AE49: =SUM(U49:AC49) -> 0 | AF49: =(AE49-O49) -> 0 | AG49: =AF49=0 -> TRUE
B50: 4 | C50: BOGOTA LIMPIA S.A.S. ESP. | D50: =D12+D31 -> 0 | E50: =E12+E31 -> 0 | F50: =F12+F31 -> 0 | G50: =G12+G31 -> 0 | H50: =H12+H31 -> 0 | I50: =I12+I31 -> 0 | J50: =J12+J31 -> 0 | K50: =D50-E50-F50-G50-H50-I50-J50 -> 0 | L50: 0 | M50: =K50-L50 -> 0 | N50: =N12+N31 -> 0 | O50: =M50+N50 -> 0 | S50: 4 | T50: BOGOTA LIMPIA S.A.S. ESP. | U50: =U12+U31 -> 0 | V50: =V12+V31 -> 0 | W50: =W12+W31 -> 0 | X50: =X12+X31 -> 0 | Y50: =Y12+Y31 -> 0 | Z50: =-L50 -> 0 | AA50: =AA12+AA31 -> 0 | AB50: =AB12+AB31 -> 0 | AC50: =AC12+AC31 -> 0 | AD50: =AD12+AD31 -> 0 | AE50: =SUM(U50:AC50) -> 0 | AF50: =(AE50-O50) -> 0 | AG50: =AF50=0 -> TRUE
B51: 5 | C51: AREA LIMPIA DISTRITO CAPITAL S.A.S. ESP. | D51: =D13+D32 -> 0 | E51: =E13+E32 -> 0 | F51: =F13+F32 -> 0 | G51: =G13+G32 -> 0 | H51: =H13+H32 -> 0 | I51: =I13+I32 -> 0 | J51: =J13+J32 -> 0 | K51: =D51-E51-F51-G51-H51-I51-J51 -> 0 | L51: 0 | M51: =K51-L51 -> 0 | N51: =N13+N32 -> 0 | O51: =M51+N51 -> 0 | S51: 5 | T51: AREA LIMPIA DISTRITO CAPITAL S.A.S. ESP. | U51: =U13+U32 -> 0 | V51: =V13+V32 -> 0 | W51: =W13+W32 -> 0 | X51: =X13+X32 -> 0 | Y51: =Y13+Y32 -> 0 | Z51: =-L51 -> 0 | AA51: =AA13+AA32 -> 0 | AB51: =AB13+AB32 -> 0 | AC51: =AC13+AC32 -> 0 | AD51: =AD13+AD32 -> 0 | AE51: =SUM(U51:AC51) -> 0 | AF51: =(AE51-O51) -> 0 | AG51: =AF51=0 -> TRUE
C52: TOTAL | D52: =SUM(D47:D51) -> 0 | E52: =SUM(E47:E51) -> 0 | F52: =SUM(F47:F51) -> 0 | G52: =SUM(G47:G51) -> 0 | H52: =SUM(H47:H51) -> 0 | I52: =SUM(I47:I51) -> 0 | J52: =SUM(J47:J51) -> 0 | K52: =SUM(K47:K51) -> 0 | ... O52: =SUM(O47:O51) -> 0 | T52: TOTAL | U52: =SUM(U47:U51) -> 0 | V52: =SUM(V47:V51) -> 0 | W52: =SUM(W47:W51) -> 0 | X52: =SUM(X47:X51) -> 0 | Y52: =SUM(Y47:Y51) -> 0 | Z52: =SUM(Z47:Z51) -> 0 | AA52: =SUM(AA47:AA51) -> 0 | AB52: =SUM(AB47:AB51) -> 0 | ... AF52: =SUM(AF47:AF51) -> 0 | AG52: =AF52=0 -> TRUE
Y54: =SUM(U52:Y52) -> 0
F56: Firma autorizada

Sheet INTERVENTORIA
F2: 2026 01 2 | G2: 2026 02 1 | H2: 2026 02 2 | I2: 2026 03 1 | J2: 2026 03 2 | K2: 2026 04 1 | L2: 2026 04 2 | M2: 2026 05 1 | N2: 2026 05 2 | O2: 2026 06 1 | P2: 2026 06 2 | Q2: 2026 07 1
B3: VALOR MES | C3: ASE | D3: Concesionarios | E3: % | F3: MITAD 1 // ENERO -26 | G3: MITAD 2 // ENERO -26 | H3: MITAD 1 // FEBRERO -26 | I3: MITAD 2 // FEBRERO -26 | J3: MITAD 1 // MARZO -26 | K3: MITAD 2 // MARZO -26 | L3: MITAD 1 // ABRIL -26 | M3: MITAD 2 // ABRIL -26 | N3: MITAD 1 // MAYO -26 | O3: MITAD 2 // MAYO -26 | P3: MITAD 1 // JUNIO -26 | Q3: MITAD 2 // JUNIO -26
B4: 378371975 | C4: 1 | D4: PROMOAMBIENTAL DISTRITO S.A.S. ESP. | E4: 0.22 | F4: 189185988 | G4: 189185987 | H4: 189185988 | I4: 189185987 | J4: 189185988 | K4: 189185987 | L4: 189185988 | M4: 189185987 | N4: 189185988 | O4: 189185987 | P4: 189185988 | Q4: 189185987
B5: 533160511 | C5: 2 | D5: LIMPIEZA METROPOLITANA S.A. ESP. | E5: 0.31 | F5: 266580256 | G5: 266580255 | H5: 266580256 | I5: 266580255 | J5: 266580256 | K5: 266580255 | L5: 266580256 | M5: 266580255 | N5: 266580256 | O5: 266580255 | P5: 266580256 | Q5: 266580255
B6: 309577071 | C6: 3 | D6: CIUDAD LIMPIA BOGOTA S.A. ESP. | E6: 0.18 | F6: 154788536 | G6: 154788535 | H6: 154788536 | I6: 154788535 | J6: 154788536 | K6: 154788535 | L6: 154788536 | M6: 154788535 | N6: 154788536 | O6: 154788535 | P6: 154788536 | Q6: 154788535
B7: 240782166 | C7: 4 | D7: BOGOTA LIMPIA S.A.S. ESP. | E7: 0.14 | F7: 120391083 | G7: 120391083 | H7: 120391083 | I7: 120391083 | J7: 120391083 | K7: 120391083 | L7: 120391083 | M7: 120391083 | N7: 120391083 | O7: 120391083 | P7: 120391083 | Q7: 120391083
B8: 257980891 | C8: 5 | D8: AREA LIMPIA DISTRITO CAPITAL S.A.S. ESP. | E8: 0.15 | F8: 128990446 | G8: 128990445 | H8: 128990446 | I8: 128990445 | J8: 128990446 | K8: 128990445 | L8: 128990446 | M8: 128990445 | N8: 128990446 | O8: 128990445 | P8: 128990446 | Q8: 128990445
B9: 1719872614 | D9: TOTAL | E9: 1 | F9: 859936309 | G9: 859936305 | H9: 859936309 | I9: 859936305 | J9: 859936309 | K9: 859936305 | L9: 859936309 | M9: 859936305 | N9: 859936309 | O9: 859936305 | P9: 859936309 | Q9: 859936305
F10: =SUM(F9:G9) -> 1719872614 | H10: =SUM(H9:I9) -> 1719872614 | J10: =SUM(J9:K9) -> 1719872614 | L10: =SUM(L9:M9) -> 1719872614 | N10: =SUM(N9:O9) -> 1719872614 | P10: =SUM(P9:Q9) -> 1719872614
F13: 2026 07 2 | G13: 2026 08 1 | H13: 2026 08 2 | I13: 2026 09 1 | J13: 2026 09 2 | K13: 2026 10 1 | L13: 2026 10 2 | M13: 2026 11 1 | N13: 2026 11 2 | O13: 2026 12 1 | P13: 2026 12 2 | Q13: 2027 01 1
C14: ASE | D14: Concesionarios | E14: % | F14: MITAD 1 // JULIO -26 | G14: MITAD 2 // JULIO -26 | H14: MITAD 1 // AGOSTO -26 | I14: MITAD 2 // AGOSTO -26 | J14: MITAD 1 // SEPTIEMBRE -26 | K14: MITAD 2 // SEPTIEMBRE -26 | L14: MITAD 1 // OCTUBRE -26 | M14: MITAD 2 // OCTUBRE -26 | N14: MITAD 1 // NOVIEMBRE -26 | O14: MITAD 2 // NOVIEMBRE -26 | P14: MITAD 1 // DICIEMBRE -26 | Q14: MITAD 2 // DICIEMBRE -26
C15: 1 | D15: PROMOAMBIENTAL DISTRITO S.A.S. ESP. | E15: 0.22 | F15: 189185988 | G15: 189185987 | H15: 189185988 | I15: 189185987 | J15: 189185988 | K15: 189185987 | L15: 189185988 | M15: 189185987 | N15: 189185988 | O15: 189185987 | P15: 189185988 | Q15: 189185987
C16: 2 | D16: LIMPIEZA METROPOLITANA S.A. ESP. | E16: 0.31 | F16: 266580256 | G16: 266580255 | H16: 266580256 | I16: 266580255 | J16: 266580256 | K16: 266580255 | L16: 266580256 | M16: 266580255 | N16: 266580256 | O16: 266580255 | P16: 266580256 | Q16: 266580255
C17: 3 | D17: CIUDAD LIMPIA BOGOTA S.A. ESP. | E17: 0.18 | F17: 154788536 | G17: 154788535 | H17: 154788536 | I17: 154788535 | J17: 154788536 | K17: 154788535 | L17: 154788536 | M17: 154788535 | N17: 154788536 | O17: 154788535 | P17: 154788536 | Q17: 154788535
C18: 4 | D18: BOGOTA LIMPIA S.A.S. ESP. | E18: 0.14 | F18: 120391083 | G18: 120391083 | H18: 120391083 | I18: 120391083 | J18: 120391083 | K18: 120391083 | L18: 120391083 | M18: 120391083 | N18: 120391083 | O18: 120391083 | P18: 120391083 | Q18: 120391083
C19: 5 | D19: AREA LIMPIA DISTRITO CAPITAL S.A.S. ESP. | E19: 0.15 | F19: 128990446 | G19: 128990445 | H19: 128990446 | I19: 128990445 | J19: 128990446 | K19: 128990445 | L19: 128990446 | M19: 128990445 | N19: 128990446 | O19: 128990445 | P19: 128990446 | Q19: 128990445
D20: TOTAL | E20: 1 | F20: 859936309 | G20: 859936305 | H20: 859936309 | I20: 859936305 | J20: 859936309 | K20: 859936305 | L20: 859936309 | M20: 859936305 | N20: 859936309 | O20: 859936305 | P20: 859936309 | Q20: 859936305
F21: =SUM(F20:G20) -> 1719872614 | G21: 1191383498 | H21: =SUM(H20:I20) -> 1719872614 | I21: 1191383498 | J21: =SUM(J20:K20) -> 1719872614 | K21: 1191383498 | L21: =SUM(L20:M20) -> 1719872614 | M21: 1191383498 | N21: =SUM(N20:O20) -> 1719872614 | O21: 1191383498 | P21: =SUM(P20:Q20) -> 1719872614 | Q21: 1191383498
K25: VALOR OFICIAL MES | L25: ASE | M25: Segunda quincena | N25: Primera quincena | R25: VALIDACION
K26: 378371975 | L26: 1 | M26: 189185988 | N26: 189185987 | O26: =N26=R26 -> TRUE | Q26: ='CONSOLIDADO_TOTAL RECAUDO'!L104 -> 189185987 | R26: =I15 -> 189185987 | S26: =Q26=R26 -> TRUE
K27: 533160511 | L27: 2 | M27: 266580256 | N27: 266580255 | O27: =N27=R27 -> TRUE | Q27: ='CONSOLIDADO_TOTAL RECAUDO'!L105 -> 266580255 | R27: =I16 -> 266580255 | S27: =Q27=R27 -> TRUE
K28: 309577071 | L28: 3 | M28: 154788536 | N28: 154788535 | O28: =N28=R28 -> TRUE | Q28: ='CONSOLIDADO_TOTAL RECAUDO'!L106 -> 154788535 | R28: =I17 -> 154788535 | S28: =Q28=R28 -> TRUE
K29: 240782166 | L29: 4 | M29: 120391083 | N29: 120391083 | O29: =N29=R29 -> TRUE | Q29: ='CONSOLIDADO_TOTAL RECAUDO'!L107 -> 120391083 | R29: =I18 -> 120391083 | S29: =Q29=R29 -> TRUE
K30: 257980891 | L30: 5 | M30: 128990446 | N30: 128990445 | O30: =N30=R30 -> TRUE | Q30: ='CONSOLIDADO_TOTAL RECAUDO'!L108 -> 128990445 | R30: =I19 -> 128990445 | S30: =Q30=R30 -> TRUE
K31: =SUM(K26:K30) -> 1719872614 | M31: =SUM(M26:M30) -> 859936309 | N31: =SUM(N26:N30) -> 859936305 | O31: =N31=R31 -> TRUE | Q31: ='CONSOLIDADO_TOTAL RECAUDO'!L109 -> 859936305 | R31: =I20 -> 859936305 | S31: =Q31=R31 -> TRUE
K32: =SUM(M31:N31) -> 1719872614

Sheet Informe AFaseo Recaudo 202609-1
D5: PROCERASEO S.A.S. | I5: NIT: 901 153 639 - 0 | P5: PROCERASEO S.A.S. | T5: NIT: 901 153 639 - 0
D6: INFORME Afaseo // RECAUDO | P6: INFORME AFaseo
D7: BENEFICIO TRANSITORIO ALIVIO SOBRE EL VALOR DE LA FACTURA | P7: BENEFICIO TRANSITORIO ALIVIO SOBRE EL VALOR DE LA FACTURA
D8: Según Resoluciòn UAESP Número 273 de 2.020 | P8: Según Resoluciòn UAESP Número 273 de 2.020
E10: Fecha Desde: | F10: ='CONSOLIDADO_TOTAL RECAUDO'!G102 -> 46266 | H10: Feha Hasta: | I10: ='CONSOLIDADO_TOTAL RECAUDO'!K102 -> 46280
B11: ASE | C11: Concesionarios | D11: Valor Afaseo | E11: Afaseo por disposicion final | F11: Afaseo por tratamiento de lixiviados | G11: Afaseo por Componente VIAT ( Decreto 2412/2018) | H11: Afaseo por aprovechamiento | I11: Afaseo del componente de comercializacion para Aprovechamiento (11,4%) | J11: Afaseo RBL | N11: ASE | O11: Concesionarios | P11: Tarifa de Comercialización del Servicio. ( TCS) | Q11: Tarifa de Limpieza Urbana del Servicio. ( TLU) | R11: Tarifa de Barrido y Limpieza del Servicio. ( TBL) | S11: Tarifa de Recolección y Transporte del Servicio. (TRT) | T11: Componente de comercialización para Aprovechamiento (18,6%) | U11: Afaseo RBL
B12: 1 | C12: PROMOAMBIENTAL DISTRITO S.A.S. ESP. | D12: ='Reporte Componentes R1'!F77*$D$24 -> 7108.83 | E12: ='Reporte Componentes R1'!G77*$D$24 -> 502.98 | F12: ='Reporte Componentes R1'!H77*$D$24 -> 213.69 | G12: ='Reporte Componentes R1'!I77*$D$24 -> 93.3 | H12: ='Reporte Componentes R1'!J77*$D$24 -> 1231.48 | I12: ='Reporte Componentes R1'!K77*$D$24 -> 79.58 | J12: =D12-E12-F12-G12-H12-I12 -> 4987.8 | N12: 1 | O12: PROMOAMBIENTAL DISTRITO S.A.S. ESP. | P12: ='Reporte Componentes R1'!M77*$P$24 -> 698.02 | Q12: ='Reporte Componentes R1'!N77*$P$24 -> 584.16 | R12: ='Reporte Componentes R1'!O77*$P$24 -> 2331.79 | S12: ='Reporte Componentes R1'!P77*$P$24 -> 1243.99 | T12: ='Reporte Componentes R1'!Q77*$P$24 -> 129.84 | U12: =SUM(P12:T12) -> 4987.8 | V12: =J12-U12 -> 0 | W12: =V12=0 -> TRUE
B13: 2 | C13: LIMPIEZA METROPOLITANA S.A. ESP. | D13: ='Reporte Componentes R1'!F211*$D$24 -> 274771.41 | E13: ='Reporte Componentes R1'!G211*$D$24 -> 24590.67 | F13: ='Reporte Componentes R1'!H211*$D$24 -> 10446.86 | G13: ='Reporte Componentes R1'!I211*$D$24 -> 4562.18 | H13: ='Reporte Componentes R1'!J211*$D$24 -> 54962.58 | I13: ='Reporte Componentes R1'!K211*$D$24 -> 2264.61 | J13: =D13-E13-F13-G13-H13-I13 -> 177944.51 | N13: 2 | O13: LIMPIEZA METROPOLITANA S.A. ESP. | P13: ='Reporte Componentes R1'!M211*$P$24 -> 19865.54 | Q13: ='Reporte Componentes R1'!N211*$P$24 -> 24901.75 | R13: ='Reporte Componentes R1'!O211*$P$24 -> 83643.2 | S13: ='Reporte Componentes R1'!P211*$P$24 -> 45838.96 | T13: ='Reporte Componentes R1'!Q211*$P$24 -> 3695.06 | U13: =SUM(P13:T13) -> 177944.51 | V13: =J13-U13 -> 0 | W13: =V13=0 -> TRUE
B14: 3 | C14: CIUDAD LIMPIA BOGOTA S.A. ESP. | D14: ='Reporte Componentes R1'!F355*$D$24 -> 5649.87 | E14: ='Reporte Componentes R1'!G355*$D$24 -> 501.3 | F14: ='Reporte Componentes R1'!H355*$D$24 -> 212.97 | G14: ='Reporte Componentes R1'!I355*$D$24 -> 93 | H14: ='Reporte Componentes R1'!J355*$D$24 -> 1090.28 | I14: ='Reporte Componentes R1'!K355*$D$24 -> 44.92 | J14: =D14-E14-F14-G14-H14-I14 -> 3707.4 | N14: 3 | O14: CIUDAD LIMPIA BOGOTA S.A. ESP. | P14: ='Reporte Componentes R1'!M355*$P$24 -> 394.01 | Q14: ='Reporte Componentes R1'!N355*$P$24 -> 493.87 | R14: ='Reporte Componentes R1'!O355*$P$24 -> 1658.87 | S14: ='Reporte Componentes R1'!P355*$P$24 -> 1087.36 | T14: ='Reporte Componentes R1'!Q355*$P$24 -> 73.29 | U14: =SUM(P14:T14) -> 3707.4 | V14: =J14-U14 -> 0 | W14: =V14=0 -> TRUE
B15: 4 | C15: BOGOTA LIMPIA S.A.S. ESP. | D15: ='Reporte Componentes R1'!F488*$D$24 -> 45650 | E15: ='Reporte Componentes R1'!G488*$D$24 -> 3731.55 | F15: ='Reporte Componentes R1'!H488*$D$24 -> 1585.29 | G15: ='Reporte Componentes R1'!I488*$D$24 -> 692.31 | H15: ='Reporte Componentes R1'!J488*$D$24 -> 8401.52 | I15: ='Reporte Componentes R1'!K488*$D$24 -> 342.15 | J15: =D15-E15-F15-G15-H15-I15 -> 30897.18 | N15: 4 | O15: BOGOTA LIMPIA S.A.S. ESP. | P15: ='Reporte Componentes R1'!M488*$P$24 -> 3001.2 | Q15: ='Reporte Componentes R1'!N488*$P$24 -> 3816.34 | R15: ='Reporte Componentes R1'!O488*$P$24 -> 14012.94 | S15: ='Reporte Componentes R1'!P488*$P$24 -> 9508.44 | T15: ='Reporte Componentes R1'!Q488*$P$24 -> 558.26 | U15: =SUM(P15:T15) -> 30897.18 | V15: =J15-U15 -> 0 | W15: =V15=0 -> TRUE
B16: 5 | C16: AREA LIMPIA DISTRITO CAPITAL S.A.S. ESP. | D16: ='Reporte Componentes R1'!F582*$D$24 -> 29681.86 | E16: ='Reporte Componentes R1'!G582*$D$24 -> 2042.55 | F16: ='Reporte Componentes R1'!H582*$D$24 -> 867.73 | G16: ='Reporte Componentes R1'!I582*$D$24 -> 378.94 | H16: ='Reporte Componentes R1'!J582*$D$24 -> 5515.52 | I16: ='Reporte Componentes R1'!K582*$D$24 -> 317.57 | J16: =D16-E16-F16-G16-H16-I16 -> 20559.55 | N16: 5 | O16: AREA LIMPIA DISTRITO CAPITAL S.A.S. ESP. | P16: ='Reporte Componentes R1'!M582*$P$24 -> 2785.77 | Q16: ='Reporte Componentes R1'!N582*$P$24 -> 2498.45 | R16: ='Reporte Componentes R1'!O582*$P$24 -> 9132.41 | S16: ='Reporte Componentes R1'!P582*$P$24 -> 5624.76 | T16: ='Reporte Componentes R1'!Q582*$P$24 -> 518.16 | U16: =SUM(P16:T16) -> 20559.55 | V16: =J16-U16 -> 0 | W16: =V16=0 -> TRUE
C17: TOTAL | D17: =SUM(D12:D16) -> 362861.97 | E17: =SUM(E12:E16) -> 31369.05 | F17: =SUM(F12:F16) -> 13326.54 | G17: =SUM(G12:G16) -> 5819.73 | H17: =SUM(H12:H16) -> 71201.38 | I17: =SUM(I12:I16) -> 3048.83 | J17: =SUM(J12:J16) -> 238096.44 | O17: TOTAL | P17: =SUM(P12:P16) -> 26744.54 | Q17: =SUM(Q12:Q16) -> 32294.57 | R17: =SUM(R12:R16) -> 110779.21 | S17: =SUM(S12:S16) -> 63303.51 | T17: =SUM(T12:T16) -> 4974.61 | U17: =SUM(U12:U16) -> 238096.44 | V17: =SUM(V12:V16) -> 0 | W17: =V17=0 -> TRUE
T19: =SUM(P17:T17) -> 238096.44
J20: =+IF(MAX(J12:J17)>500000,"VALIDAR",TRUE) -> TRUE
F21: Firma autorizada
D24: -1 | P24: -1

Sheet CONSOLIDADO_TOTAL RECAUDO
F3: PROCERASEO S.A.S. | I3: NIT: 901 153 639 - 0 | M3: Codigo Remuneración: | N3: 2026091 | U3: PROCERASEO S.A.S. | W3: NIT: 901 153 639 - 0 | AA3: Codigo Remuneración: | AD3: =N3 -> 2026091
F4: 3. ESQUEMA FINANCIERO DEL SERVICIO PUBLICO DE ASEO | U4: 3. ESQUEMA FINANCIERO DEL SERVICIO PUBLICO DE ASEO
F5: Resoluciòn UAESP Número 27 de 2018 | U5: Resoluciòn UAESP Número 27 de 2018
C6: Fecha de Proceso: | D6: 46282 | F6: R1 - RECAUDO OPORTUNO | U6: R1 - RECAUDO OPORTUNO
C7: Hora: | D7: 0.58333333 | F7: Fecha Desde: | G7: 46266 | J7: Feha Hasta: | K7: 46280 | U7: =F7 -> Fecha Desde: | V7: =G7 -> 46266 | X7: =J7 -> Feha Hasta: | Y7: =K7 -> 46280
B8: ASE | C8: Concesionarios | D8: Recaudo Total | E8: Recaudo por disposicion final | F8: Recaudo por tratamiento de lixiviados | G8: Recaudo por Componente VIAT ( Decreto 2412/2018) | H8: Recaudo por aprovechamiento | I8: Recaudo del componente de comercializacion para Aprovechamiento (11,4%) | J8: Balance de subsidio o contribuciones | K8: RECAUDO BASE DE REMUNERACION | L8: Costo de la Interventoría | M8: REMUNERACION FINAL | N8: Conceptos especiales | O8: REMUNERACION FINAL MAS CONCEPTOS ESPECIALES | S8: ASE | T8: Concesionarios | U8: Tarifa de Comercialización del Servicio. ( TCS) | V8: Tarifa de Limpieza Urbana del Servicio. ( TLU) | W8: Tarifa de Barrido y Limpieza del Servicio. ( TBL) | X8: Tarifa de Recolección y Transporte del Servicio. (TRT) | Y8: Recaudo del componente de comercializacion para Aprovechamiento (18,6%) | Z8: Costo de la Interventoría | AA8: Ajuste a la decena | AB8: Conceptos especiales | AC8: Otros | AD8: Diferencial Balance S / C (Fac vs Rec) | AE8: Balance S / C Con Base en (Recaudo) | AF8: REMUNERACION FINAL MAS CONCEPTOS ESPECIALES
B9: 1 | C9: PROMOAMBIENTAL DISTRITO S.A.S. ESP. | D9: ='Reporte Componentes R1'!F47 -> 1.7418907e+10 | E9: ='Reporte Componentes R1'!G47 -> 1.0010823e+09 | F9: ='Reporte Componentes R1'!H47 -> 5.5862411e+08 | G9: ='Reporte Componentes R1'!I47 -> 2.9581886e+08 | H9: ='Reporte Componentes R1'!J47 -> 4.8549813e+09 | I9: ='Reporte Componentes R1'!K47 -> 1.8202342e+08 | J9: ='BCE SC POR FACT.'!F3 -> 2.5893357e+09 | K9: =D9-E9-F9-G9-H9-I9-J9 -> 7.9370418e+09 | L9: =INTERVENTORIA!I15 -> 189185987 | M9: =K9-L9 -> 7.7478558e+09 | N9: ='Reporte Componentes R1'!L47 -> 30635670 | O9: =M9+N9 -> 7.7784914e+09 | S9: 1 | T9: PROMOAMBIENTAL DISTRITO S.A.S. ESP. | U9: ='Reporte Componentes R1'!M47 -> 1.5976825e+09 | V9: ='Reporte Componentes R1'!N47 -> 1.5265528e+09 | W9: ='Reporte Componentes R1'!O47 -> 7.1808775e+09 | X9: ='Reporte Componentes R1'!P47 -> 2.7253469e+09 | Y9: ='Reporte Componentes R1'!Q47 -> 2.970241e+08 | Z9: =L9*-1 -> -189185987 | AA9: ='Reporte Componentes R1'!R47+'Reporte Componentes R1'!U47+'Reporte Componentes R1'!V47 -> -46873.26 | AB9: =N9 -> 30635670 | AC9: ='Reporte Componentes R1'!T47+'Reporte Componentes R1'!W47+'Reporte Componentes R1'!X47+'Reporte Componentes R1'!Y47+'Reporte Componentes R1'!Z47+'Reporte Componentes R1'!S47 -> 392.74 | AD9: =-J9+AE9 -> -5.3903955e+09 | AE9: ='Reporte Componentes R1'!F48 -> -2.8010598e+09 | AF9: =SUM(U9:AD9) -> 7.7784914e+09 | AG9: =(AF9-O9) -> 6.6757202e-06 | AH9: =INT(AG9)=0 -> TRUE
B10: 2 | C10: LIMPIEZA METROPOLITANA S.A. ESP. | D10: ='Reporte Componentes R1'!F181 -> 1.4054409e+10 | E10: ='Reporte Componentes R1'!G181 -> 1.0882025e+09 | F10: ='Reporte Componentes R1'!H181 -> 6.0306981e+08 | G10: ='Reporte Componentes R1'!I181 -> 3.1900917e+08 | H10: ='Reporte Componentes R1'!J181 -> 4.4578076e+09 | I10: ='Reporte Componentes R1'!K181 -> 1.5158627e+08 | J10: ='BCE SC POR FACT.'!F4 -> -5.0932598e+09 | K10: =D10-E10-F10-G10-H10-I10-J10 -> 1.2527993e+10 | L10: =INTERVENTORIA!I16 -> 266580255 | M10: =K10-L10 -> 1.2261413e+10 | N10: ='Reporte Componentes R1'!L181 -> 43591202 | O10: =M10+N10 -> 1.2305004e+10 | S10: 2 | T10: LIMPIEZA METROPOLITANA S.A. ESP. | U10: ='Reporte Componentes R1'!M181 -> 1.3288221e+09 | V10: ='Reporte Componentes R1'!N181 -> 1.3172024e+09 | W10: ='Reporte Componentes R1'!O181 -> 6.1783747e+09 | X10: ='Reporte Componentes R1'!P181 -> 2.1380791e+09 | Y10: ='Reporte Componentes R1'!Q181 -> 2.4778521e+08 | Z10: =L10*-1 -> -266580255 | AA10: ='Reporte Componentes R1'!R181+'Reporte Componentes R1'!U181+'Reporte Componentes R1'!V181 -> 60921.93 | AB10: =N10 -> 43591202 | AC10: ='Reporte Componentes R1'!T181+'Reporte Componentes R1'!W181+'Reporte Componentes R1'!X181+'Reporte Componentes R1'!Y181+'Reporte Componentes R1'!Z181+'Reporte Componentes R1'!S181 -> -56807.54 | AD10: =-J10+AE10 -> 1.3177255e+09 | AE10: ='Reporte Componentes R1'!F182 -> -3.7755343e+09 | AF10: =SUM(U10:AD10) -> 1.2305004e+10 | AG10: =(AF10-O10) -> -1.9073486e-06 | AH10: =INT(AG10)=0 -> FALSE
B11: 3 | C11: CIUDAD LIMPIA BOGOTA S.A. ESP. | D11: ='Reporte Componentes R1'!F325 -> 1.0873712e+10 | E11: ='Reporte Componentes R1'!G325 -> 7.094801e+08 | F11: ='Reporte Componentes R1'!H325 -> 3.9679768e+08 | G11: ='Reporte Componentes R1'!I325 -> 2.1007236e+08 | H11: ='Reporte Componentes R1'!J325 -> 3.0860385e+09 | I11: ='Reporte Componentes R1'!K325 -> 1.0245381e+08 | J11: ='BCE SC POR FACT.'!F5 -> -1.230397e+09 | K11: =D11-E11-F11-G11-H11-I11-J11 -> 7.5992662e+09 | L11: =INTERVENTORIA!I17 -> 154788535 | M11: =K11-L11 -> 7.4444777e+09 | N11: ='Reporte Componentes R1'!L325 -> 25517242 | O11: =M11+N11 -> 7.4699949e+09 | S11: 3 | T11: CIUDAD LIMPIA BOGOTA S.A. ESP. | U11: ='Reporte Componentes R1'!M325 -> 8.9876063e+08 | V11: ='Reporte Componentes R1'!N325 -> 8.790698e+08 | W11: ='Reporte Componentes R1'!O325 -> 4.1378283e+09 | X11: ='Reporte Componentes R1'!P325 -> 1.6799445e+09 | Y11: ='Reporte Componentes R1'!Q325 -> 1.6723142e+08 | Z11: =L11*-1 -> -154788535 | AA11: ='Reporte Componentes R1'!R325+'Reporte Componentes R1'!U325+'Reporte Componentes R1'!V325 -> 46878 | AB11: =N11 -> 25517242 | AC11: ='Reporte Componentes R1'!T325+'Reporte Componentes R1'!W325+'Reporte Componentes R1'!X325+'Reporte Componentes R1'!Y325+'Reporte Componentes R1'!Z325+'Reporte Componentes R1'!S325 -> 5.47 | AD11: =-J11+AE11 -> -1.6361542e+08 | AE11: ='Reporte Componentes R1'!F326 -> -1.3940124e+09 | AF11: =SUM(U11:AD11) -> 7.4699949e+09 | AG11: =(AF11-O11) -> -9.5367432e-07 | AH11: =INT(AG11)=0 -> FALSE
B12: 4 | C12: BOGOTA LIMPIA S.A.S. ESP. | D12: ='Reporte Componentes R1'!F458 -> 1.1499013e+10 | E12: ='Reporte Componentes R1'!G458 -> 6.509964e+08 | F12: ='Reporte Componentes R1'!H458 -> 3.6166457e+08 | G12: ='Reporte Componentes R1'!I458 -> 1.913117e+08 | H12: ='Reporte Componentes R1'!J458 -> 2.8484436e+09 | I12: ='Reporte Componentes R1'!K458 -> 98370577 | J12: ='BCE SC POR FACT.'!F6 -> 38133906 | K12: =D12-E12-F12-G12-H12-I12-J12 -> 7.3100926e+09 | L12: =INTERVENTORIA!I18 -> 120391083 | M12: =K12-L12 -> 7.1897015e+09 | N12: ='Reporte Componentes R1'!L458 -> 23185408 | O12: =M12+N12 -> 7.2128869e+09 | S12: 4 | T12: BOGOTA LIMPIA S.A.S. ESP. | U12: ='Reporte Componentes R1'!M458 -> 8.6252558e+08 | V12: ='Reporte Componentes R1'!N458 -> 8.5027888e+08 | W12: ='Reporte Componentes R1'!O458 -> 4.3346851e+09 | X12: ='Reporte Componentes R1'!P458 -> 1.7232123e+09 | Y12: ='Reporte Componentes R1'!Q458 -> 1.608079e+08 | Z12: =L12*-1 -> -120391083 | AA12: ='Reporte Componentes R1'!R458+'Reporte Componentes R1'!U458+'Reporte Componentes R1'!V458 -> -64274.34 | AB12: =N12 -> 23185408 | AC12: ='Reporte Componentes R1'!T458+'Reporte Componentes R1'!W458+'Reporte Componentes R1'!X458+'Reporte Componentes R1'!Y458+'Reporte Componentes R1'!Z458+'Reporte Componentes R1'!S458 -> 181.07 | AD12: =-J12+AE12 -> -6.2135311e+08 | AE12: ='Reporte Componentes R1'!F459 -> -5.832192e+08 | AF12: =SUM(U12:AD12) -> 7.2128869e+09 | AG12: =(AF12-O12) -> -1.9073486e-06 | AH12: =INT(AG12)=0 -> FALSE
B13: 5 | C13: AREA LIMPIA DISTRITO CAPITAL S.A.S. ESP. | D13: ='Reporte Componentes R1'!F552 -> 9.1286743e+09 | E13: ='Reporte Componentes R1'!G552 -> 4.9999386e+08 | F13: ='Reporte Componentes R1'!H552 -> 2.7929527e+08 | G13: ='Reporte Componentes R1'!I552 -> 1.4792873e+08 | H13: ='Reporte Componentes R1'!J552 -> 2.0955676e+09 | I13: ='Reporte Componentes R1'!K552 -> 75251314 | J13: ='BCE SC POR FACT.'!F7 -> -1.2241007e+09 | K13: =D13-E13-F13-G13-H13-I13-J13 -> 7.2547382e+09 | L13: =INTERVENTORIA!I19 -> 128990445 | M13: =K13-L13 -> 7.1257478e+09 | N13: ='Reporte Componentes R1'!L552 -> 32575938 | O13: =M13+N13 -> 7.1583237e+09 | S13: 5 | T13: AREA LIMPIA DISTRITO CAPITAL S.A.S. ESP. | U13: ='Reporte Componentes R1'!M552 -> 6.6045214e+08 | V13: ='Reporte Componentes R1'!N552 -> 6.4266044e+08 | W13: ='Reporte Componentes R1'!O552 -> 3.2982859e+09 | X13: ='Reporte Componentes R1'!P552 -> 1.4970148e+09 | Y13: ='Reporte Componentes R1'!Q552 -> 1.2287348e+08 | Z13: =L13*-1 -> -128990445 | AA13: ='Reporte Componentes R1'!R552+'Reporte Componentes R1'!U552+'Reporte Componentes R1'!V552 -> -16285.89 | AB13: =N13 -> 32575938 | AC13: ='Reporte Componentes R1'!T552+'Reporte Componentes R1'!W552+'Reporte Componentes R1'!X552+'Reporte Componentes R1'!Y552+'Reporte Componentes R1'!Z552+'Reporte Componentes R1'!S552 -> -105.68 | AD13: =-J13+AE13 -> 1.0334679e+09 | AE13: ='Reporte Componentes R1'!F553 -> -1.9063282e+08 | AF13: =SUM(U13:AD13) -> 7.1583237e+09 | AG13: =(AF13-O13) -> -9.5367432e-07 | AH13: =INT(AG13)=0 -> FALSE
C14: TOTAL | D14: =SUM(D9:D13) -> 6.2974715e+10 | E14: =SUM(E9:E13) -> 3.9497551e+09 | F14: =SUM(F9:F13) -> 2.1994514e+09 | G14: =SUM(G9:G13) -> 1.1641408e+09 | H14: =SUM(H9:H13) -> 1.7342839e+10 | I14: =SUM(I9:I13) -> 6.0968539e+08 | J14: =SUM(J9:J13) -> -4.9202879e+09 | K14: =SUM(K9:K13) -> 4.2629132e+10 | ... O14: =SUM(O9:O13) -> 4.1924701e+10 | T14: TOTAL | U14: =SUM(U9:U13) -> 5.348243e+09 | V14: =SUM(V9:V13) -> 5.2157643e+09 | W14: =SUM(W9:W13) -> 2.5130052e+10 | X14: =SUM(X9:X13) -> 9.7635977e+09 | Y14: =SUM(Y9:Y13) -> 9.9572211e+08 | Z14: =SUM(Z9:Z13) -> -859936305 | AA14: =SUM(AA9:AA13) -> -19633.56 | AB14: =SUM(AB9:AB13) -> 1.5550546e+08 | ... AG14: =SUM(AG9:AG13) -> 9.5367432e-07 | AH14: =INT(AG14)=0 -> TRUE
Y16: =SUM(U14:Y14) -> 4.6453379e+10
F18: Firma autorizada
F22: PROCERASEO S.A.S. | I22: NIT: 901 153 639 - 0 | M22: Codigo Remuneración: | N22: =N3 -> 2026091 | U22: PROCERASEO S.A.S. | W22: NIT: 901 153 639 - 0 | AA22: Codigo Remuneración: | AD22: =N22 -> 2026091
F23: 3. ESQUEMA FINANCIERO DEL SERVICIO PUBLICO DE ASEO | U23: 3. ESQUEMA FINANCIERO DEL SERVICIO PUBLICO DE ASEO
F24: Resoluciòn UAESP Número 27 de 2018 | U24: Resoluciòn UAESP Número 27 de 2018
C25: Fecha de Proceso: | D25: =D6 -> 46282 | F25: R2 - ANTICIPOS A USUARIOS | U25: R2 - ANTICIPOS A USUARIOS
C26: Hora: | D26: =D7 -> 0.58333333 | F26: Fecha Desde: | G26: =G7 -> 46266 | J26: Feha Hasta: | K26: =K7 -> 46280 | U26: =F26 -> Fecha Desde: | V26: =G26 -> 46266 | X26: =J26 -> Feha Hasta: | Y26: =K26 -> 46280
B27: ASE | C27: Concesionarios | D27: Recaudo Total | E27: Recaudo por disposicion final | F27: Recaudo por tratamiento de lixiviados | G27: Recaudo por Componente VIAT ( Decreto 2412/2018) | H27: Recaudo por aprovechamiento | I27: Recaudo del componente de comercializacion para Aprovechamiento (11,4%) | J27: Balance de subsidio o contribuciones | K27: RECAUDO BASE DE REMUNERACION | L27: Costo de la Interventoría | M27: REMUNERACION FINAL | N27: Conceptos especiales | O27: REMUNERACION FINAL MAS CONCEPTOS ESPECIALES | S27: ASE | T27: Concesionarios | U27: Tarifa de Comercialización del Servicio. ( TCS) | V27: Tarifa de Limpieza Urbana del Servicio. ( TLU) | W27: Tarifa de Barrido y Limpieza del Servicio. ( TBL) | X27: Tarifa de Recolección y Transporte del Servicio. (TRT) | Y27: Recaudo del componente de comercializacion para Aprovechamiento (18,6%) | Z27: Costo de la Interventoría | AA27: Ajuste a la decena | AB27: Conceptos especiales | AC27: Otros | AD27: Diferencial Balance S / C (Fac vs Rec) | AE27: Balance S / C Con Base en (Recaudo) | AF27: REMUNERACION FINAL MAS CONCEPTOS ESPECIALES
B28: 1 | C28: PROMOAMBIENTAL DISTRITO S.A.S. ESP. | D28: ='Rem. Anticipos R2'!E42 -> 34844954 | E28: ='Rem. Anticipos R2'!F42 -> 1865211.3 | F28: ='Rem. Anticipos R2'!G42 -> 1005487.3 | G28: ='Rem. Anticipos R2'!H42 -> 583812.15 | H28: ='Rem. Anticipos R2'!I42 -> 5020392.6 | I28: ='Rem. Anticipos R2'!J42 -> 230375.08 | J28: 0 | K28: =D28-E28-F28-G28-H28-I28-J28 -> 26139676 | L28: 0 | M28: =K28-L28 -> 26139676 | N28: ='Rem. Anticipos R2'!K42 -> 0 | O28: =M28+N28 -> 26139676 | S28: 1 | T28: PROMOAMBIENTAL DISTRITO S.A.S. ESP. | U28: ='Rem. Anticipos R2'!L42 -> 2507180.1 | V28: ='Rem. Anticipos R2'!M42 -> 2526384.8 | W28: ='Rem. Anticipos R2'!N42 -> 12951452 | X28: ='Rem. Anticipos R2'!O42 -> 5510056 | Y28: ='Rem. Anticipos R2'!P42 -> 369962.63 | Z28: =L28*-1 -> 0 | AA28: ='Rem. Anticipos R2'!Q42 -> -21.97 | AB28: =N28 -> 0 | AC28: ='Rem. Anticipos R2'!R42 -> 0 | AD28: =-J28+AE28 -> 2274662.1 | AE28: ='Rem. Anticipos R2'!E43 -> 2274662.1 | AF28: =SUM(U28:AD28) -> 26139676 | AG28: =(AF28-O28) -> -7.4505806e-09 | AH28: =INT(AG28)=0 -> FALSE
B29: 2 | C29: LIMPIEZA METROPOLITANA S.A. ESP. | D29: ='Rem. Anticipos R2'!E135 -> 1.016621e+08 | E29: ='Rem. Anticipos R2'!F135 -> 8605592.6 | F29: ='Rem. Anticipos R2'!G135 -> 4936937 | G29: ='Rem. Anticipos R2'!H135 -> 1904352.2 | H29: ='Rem. Anticipos R2'!I135 -> 30991476 | I29: ='Rem. Anticipos R2'!J135 -> 1003353.5 | J29: 0 | K29: =D29-E29-F29-G29-H29-I29-J29 -> 54220387 | L29: 0 | M29: =K29-L29 -> 54220387 | N29: ='Rem. Anticipos R2'!K135 -> 51372.12 | O29: =M29+N29 -> 54271759 | S29: 2 | T29: LIMPIEZA METROPOLITANA S.A. ESP. | U29: ='Rem. Anticipos R2'!L135 -> 10643669 | V29: ='Rem. Anticipos R2'!M135 -> 9614716.1 | W29: ='Rem. Anticipos R2'!N135 -> 40202706 | X29: ='Rem. Anticipos R2'!O135 -> 17542860 | Y29: ='Rem. Anticipos R2'!P135 -> 1379320.4 | Z29: =L29*-1 -> 0 | AA29: ='Rem. Anticipos R2'!Q135 -> 497.4 | AB29: =N29 -> 51372.12 | AC29: ='Rem. Anticipos R2'!R135 -> 0 | AD29: =-J29+AE29 -> -25163382 | AE29: ='Rem. Anticipos R2'!E136 -> -25163382 | AF29: =SUM(U29:AD29) -> 54271759 | AG29: =(AF29-O29) -> 1.4901161e-08 | AH29: =INT(AG29)=0 -> TRUE
B30: 3 | C30: CIUDAD LIMPIA BOGOTA S.A. ESP. | D30: ='Rem. Anticipos R2'!E248 -> 23583927 | E30: ='Rem. Anticipos R2'!F248 -> 1547938 | F30: ='Rem. Anticipos R2'!G248 -> 861396.51 | G30: ='Rem. Anticipos R2'!H248 -> 389140.56 | H30: ='Rem. Anticipos R2'!I248 -> 5713748.3 | I30: ='Rem. Anticipos R2'!J248 -> 195637.95 | J30: 0 | K30: =D30-E30-F30-G30-H30-I30-J30 -> 14876066 | L30: 0 | M30: =K30-L30 -> 14876066 | N30: ='Rem. Anticipos R2'!K248 -> 45286.42 | O30: =M30+N30 -> 14921353 | S30: 3 | T30: CIUDAD LIMPIA BOGOTA S.A. ESP. | U30: ='Rem. Anticipos R2'!L248 -> 2152729 | V30: ='Rem. Anticipos R2'!M248 -> 1674276.1 | W30: ='Rem. Anticipos R2'!N248 -> 7520400.5 | X30: ='Rem. Anticipos R2'!O248 -> 4675829.6 | Y30: ='Rem. Anticipos R2'!P248 -> 285203.72 | Z30: =L30*-1 -> 0 | AA30: ='Rem. Anticipos R2'!Q248 -> -187.1 | AB30: =N30 -> 45286.42 | AC30: ='Rem. Anticipos R2'!R248 -> 0 | AD30: =-J30+AE30 -> -1432185.7 | AE30: ='Rem. Anticipos R2'!E249 -> -1432185.7 | AF30: =SUM(U30:AD30) -> 14921353 | AG30: =(AF30-O30) -> 3.7252903e-09 | AH30: =INT(AG30)=0 -> TRUE
B31: 4 | C31: BOGOTA LIMPIA S.A.S. ESP. | D31: ='Rem. Anticipos R2'!E344 -> 23548210 | E31: ='Rem. Anticipos R2'!F344 -> 1470007.4 | F31: ='Rem. Anticipos R2'!G344 -> 836215.45 | G31: ='Rem. Anticipos R2'!H344 -> 336141.94 | H31: ='Rem. Anticipos R2'!I344 -> 5278546.5 | I31: ='Rem. Anticipos R2'!J344 -> 193637.28 | J31: 0 | K31: =D31-E31-F31-G31-H31-I31-J31 -> 15433662 | L31: 0 | M31: =K31-L31 -> 15433662 | N31: ='Rem. Anticipos R2'!K344 -> 0 | O31: =M31+N31 -> 15433662 | S31: 4 | T31: BOGOTA LIMPIA S.A.S. ESP. | U31: ='Rem. Anticipos R2'!L344 -> 2124229.1 | V31: ='Rem. Anticipos R2'!M344 -> 1645599 | W31: ='Rem. Anticipos R2'!N344 -> 7267809.3 | X31: ='Rem. Anticipos R2'!O344 -> 4237012.9 | Y31: ='Rem. Anticipos R2'!P344 -> 279286.86 | Z31: =L31*-1 -> 0 | AA31: ='Rem. Anticipos R2'!Q344 -> -108.3 | AB31: =N31 -> 0 | AC31: ='Rem. Anticipos R2'!R344 -> 0 | AD31: =-J31+AE31 -> -120167.08 | AE31: ='Rem. Anticipos R2'!E345 -> -120167.08 | AF31: =SUM(U31:AD31) -> 15433662 | AG31: =(AF31-O31) -> -3.7252903e-09 | AH31: =INT(AG31)=0 -> FALSE
B32: 5 | C32: AREA LIMPIA DISTRITO CAPITAL S.A.S. ESP. | D32: ='Rem. Anticipos R2'!E415 -> 27520061 | E32: ='Rem. Anticipos R2'!F415 -> 1572950.5 | F32: ='Rem. Anticipos R2'!G415 -> 893114.93 | G32: ='Rem. Anticipos R2'!H415 -> 439698.34 | H32: ='Rem. Anticipos R2'!I415 -> 6421366.7 | I32: ='Rem. Anticipos R2'!J415 -> 208412.06 | J32: 0 | K32: =D32-E32-F32-G32-H32-I32-J32 -> 17984518 | L32: 0 | M32: =K32-L32 -> 17984518 | N32: ='Rem. Anticipos R2'!K415 -> 0 | O32: =M32+N32 -> 17984518 | S32: 5 | T32: AREA LIMPIA DISTRITO CAPITAL S.A.S. ESP. | U32: ='Rem. Anticipos R2'!L415 -> 1987677.6 | V32: ='Rem. Anticipos R2'!M415 -> 1803263.4 | W32: ='Rem. Anticipos R2'!N415 -> 8986120.5 | X32: ='Rem. Anticipos R2'!O415 -> 4947370 | Y32: ='Rem. Anticipos R2'!P415 -> 335190.24 | Z32: =L32*-1 -> 0 | AA32: ='Rem. Anticipos R2'!Q415 -> -244.14 | AB32: =N32 -> 0 | AC32: ='Rem. Anticipos R2'!R415 -> 0 | AD32: =-J32+AE32 -> -74859.4 | AE32: ='Rem. Anticipos R2'!E416 -> -74859.4 | AF32: =SUM(U32:AD32) -> 17984518 | AG32: =(AF32-O32) -> -3.7252903e-09 | AH32: =INT(AG32)=0 -> FALSE
C33: TOTAL | D33: =SUM(D28:D32) -> 2.1115925e+08 | E33: =SUM(E28:E32) -> 15061700 | F33: =SUM(F28:F32) -> 8533151.2 | G33: =SUM(G28:G32) -> 3653145.1 | H33: =SUM(H28:H32) -> 53425530 | I33: =SUM(I28:I32) -> 1831415.9 | J33: =SUM(J28:J32) -> 0 | K33: =SUM(K28:K32) -> 1.2865431e+08 | ... O33: =SUM(O28:O32) -> 1.2875097e+08 | T33: TOTAL | U33: =SUM(U28:U32) -> 19415484 | V33: =SUM(V28:V32) -> 17264239 | W33: =SUM(W28:W32) -> 76928489 | X33: =SUM(X28:X32) -> 36913129 | Y33: =SUM(Y28:Y32) -> 2648963.8 | Z33: =SUM(Z28:Z32) -> 0 | AA33: =SUM(AA28:AA32) -> -64.11 | AB33: =SUM(AB28:AB32) -> 96658.54 | ... AG33: =SUM(AG28:AG32) -> 3.7252903e-09 | AH33: =INT(AG33)=0 -> TRUE
Y35: =SUM(U33:Y33) -> 1.5317031e+08
F37: Firma autorizada
F41: PROCERASEO S.A.S. | I41: NIT: 901 153 639 - 0 | M41: Codigo Remuneración: | N41: =N3 -> 2026091 | U41: PROCERASEO S.A.S. | W41: NIT: 901 153 639 - 0 | AA41: Codigo Remuneración: | AD41: =N41 -> 2026091
F42: 3. ESQUEMA FINANCIERO DEL SERVICIO PUBLICO DE ASEO | U42: 3. ESQUEMA FINANCIERO DEL SERVICIO PUBLICO DE ASEO
F43: Resoluciòn UAESP Número 27 de 2018 | U43: Resoluciòn UAESP Número 27 de 2018
C44: Fecha de Proceso: | D44: =D6 -> 46282 | F44: R3 - RECAUDO EXTEMPORANEO | U44: R3 - RECAUDO EXTEMPORANEO
C45: Hora: | D45: =D7 -> 0.58333333 | F45: Fecha Desde: | G45: =G7 -> 46266 | J45: Feha Hasta: | K45: =K7 -> 46280 | U45: =F45 -> Fecha Desde: | V45: =G45 -> 46266 | X45: =J45 -> Feha Hasta: | Y45: =K45 -> 46280
B46: ASE | C46: Concesionarios | D46: Recaudo Total | E46: Recaudo por disposicion final | F46: Recaudo por tratamiento de lixiviados | G46: Recaudo por Componente VIAT ( Decreto 2412/2018) | H46: Recaudo por aprovechamiento | I46: Recaudo del componente de comercializacion para Aprovechamiento (11,4%) | J46: Balance de subsidio o contribuciones | K46: RECAUDO BASE DE REMUNERACION | L46: Costo de la Interventoría | M46: REMUNERACION FINAL | N46: Conceptos especiales | O46: REMUNERACION FINAL MAS CONCEPTOS ESPECIALES | S46: ASE | T46: Concesionarios | U46: Tarifa de Comercialización del Servicio. ( TCS) | V46: Tarifa de Limpieza Urbana del Servicio. ( TLU) | W46: Tarifa de Barrido y Limpieza del Servicio. ( TBL) | X46: Tarifa de Recolección y Transporte del Servicio. (TRT) | Y46: Recaudo del componente de comercializacion para Aprovechamiento (18,6%) | Z46: Costo de la Interventoría | AA46: Ajuste a la decena | AB46: Conceptos especiales | AC46: Otros | AD46: Diferencial Balance S / C (Fac vs Rec) | AE46: Balance S / C Con Base en (Recaudo) | AF46: REMUNERACION FINAL MAS CONCEPTOS ESPECIALES
B47: 1 | C47: PROMOAMBIENTAL DISTRITO S.A.S. ESP. | D47: ='Reporte Componentes R1'!F49 -> 42680 | E47: ='Reporte Componentes R1'!G49 -> 2083.94 | F47: ='Reporte Componentes R1'!H49 -> 1161.16 | G47: ='Reporte Componentes R1'!I49 -> 617.56 | H47: ='Reporte Componentes R1'!J49 -> 10417.41 | I47: ='Reporte Componentes R1'!K49 -> 383.09 | J47: 0 | K47: =D47-E47-F47-G47-H47-I47-J47 -> 28016.84 | L47: 0 | M47: =K47-L47 -> 28016.84 | N47: ='Reporte Componentes R1'!L49 -> 0 | O47: =M47+N47 -> 28016.84 | S47: 1 | T47: PROMOAMBIENTAL DISTRITO S.A.S. ESP. | U47: ='Reporte Componentes R1'!M49 -> 3360.38 | V47: ='Reporte Componentes R1'!N49 -> 3220.93 | W47: ='Reporte Componentes R1'!O49 -> 15119.8 | X47: ='Reporte Componentes R1'!P49 -> 5691.76 | Y47: ='Reporte Componentes R1'!Q49 -> 625.03 | Z47: =-L47 -> 0 | AA47: ='Reporte Componentes R1'!R49+'Reporte Componentes R1'!V49+'Reporte Componentes R1'!U49 -> -1.06 | AB47: =N47 -> 0 | AC47: ='Reporte Componentes R1'!T49+'Reporte Componentes R1'!W49+'Reporte Componentes R1'!X49+'Reporte Componentes R1'!Y49+'Reporte Componentes R1'!Z49+'Reporte Componentes R1'!S49 -> 0 | AD47: =-J47+AE47 -> 0 | AE47: ='Reporte Componentes R1'!F50 -> 0 | AF47: =SUM(U47:AD47) -> 28016.84 | AG47: =(AF47-O47) -> 3.6379788e-12 | AH47: =INT(AG47)=0 -> TRUE
B48: 2 | C48: LIMPIEZA METROPOLITANA S.A. ESP. | D48: ='Reporte Componentes R1'!F183 -> 0 | E48: ='Reporte Componentes R1'!G183 -> 0 | F48: ='Reporte Componentes R1'!H183 -> 0 | G48: ='Reporte Componentes R1'!I183 -> 0 | H48: ='Reporte Componentes R1'!J183 -> 0 | I48: ='Reporte Componentes R1'!K183 -> 0 | J48: 0 | K48: =D48-E48-F48-G48-H48-I48-J48 -> 0 | L48: 0 | M48: =K48-L48 -> 0 | N48: ='Reporte Componentes R1'!L183 -> 0 | O48: =M48+N48 -> 0 | S48: 2 | T48: LIMPIEZA METROPOLITANA S.A. ESP. | U48: ='Reporte Componentes R1'!M183 -> 0 | V48: ='Reporte Componentes R1'!N183 -> 0 | W48: ='Reporte Componentes R1'!O183 -> 0 | X48: ='Reporte Componentes R1'!P183 -> 0 | Y48: ='Reporte Componentes R1'!Q183 -> 0 | Z48: =-L48 -> 0 | AA48: ='Reporte Componentes R1'!R183+'Reporte Componentes R1'!V183+'Reporte Componentes R1'!U183 -> 0 | AB48: =N48 -> 0 | AC48: ='Reporte Componentes R1'!T183+'Reporte Componentes R1'!W183+'Reporte Componentes R1'!X183+'Reporte Componentes R1'!Y183+'Reporte Componentes R1'!Z183+'Reporte Componentes R1'!S183 -> 0 | AD48: =-J48+AE48 -> 0 | AE48: ='Reporte Componentes R1'!F184 -> 0 | AF48: =SUM(U48:AD48) -> 0 | AG48: =(AF48-O48) -> 0 | AH48: =INT(AG48)=0 -> TRUE
B49: 3 | C49: CIUDAD LIMPIA BOGOTA S.A. ESP. | D49: ='Reporte Componentes R1'!F327 -> 169120 | E49: ='Reporte Componentes R1'!G327 -> 9182.42 | F49: ='Reporte Componentes R1'!H327 -> 5162.64 | G49: ='Reporte Componentes R1'!I327 -> 2721.2 | H49: ='Reporte Componentes R1'!J327 -> 52890.57 | I49: ='Reporte Componentes R1'!K327 -> 1377.07 | J49: 0 | K49: =D49-E49-F49-G49-H49-I49-J49 -> 97786.1 | L49: 0 | M49: =K49-L49 -> 97786.1 | N49: ='Reporte Componentes R1'!L327 -> 0 | O49: =M49+N49 -> 97786.1 | S49: 3 | T49: CIUDAD LIMPIA BOGOTA S.A. ESP. | U49: ='Reporte Componentes R1'!M327 -> 12079.7 | V49: ='Reporte Componentes R1'!N327 -> 16023.47 | W49: ='Reporte Componentes R1'!O327 -> 75525.46 | X49: ='Reporte Componentes R1'!P327 -> 21576.6 | Y49: ='Reporte Componentes R1'!Q327 -> 2246.83 | Z49: =-L49 -> 0 | AA49: ='Reporte Componentes R1'!R327+'Reporte Componentes R1'!V327+'Reporte Componentes R1'!U327 -> -4.89 | AB49: =N49 -> 0 | AC49: ='Reporte Componentes R1'!T327+'Reporte Componentes R1'!W327+'Reporte Componentes R1'!X327+'Reporte Componentes R1'!Y327+'Reporte Componentes R1'!Z327+'Reporte Componentes R1'!S327 -> 0 | AD49: =-J49+AE49 -> -29661.07 | AE49: ='Reporte Componentes R1'!F328 -> -29661.07 | AF49: =SUM(U49:AD49) -> 97786.1 | AG49: =(AF49-O49) -> 5.8207661e-11 | AH49: =INT(AG49)=0 -> TRUE
B50: 4 | C50: BOGOTA LIMPIA S.A.S. ESP. | D50: ='Reporte Componentes R1'!F460 -> 8635714 | E50: ='Reporte Componentes R1'!G460 -> 521617.57 | F50: ='Reporte Componentes R1'!H460 -> 295276.31 | G50: ='Reporte Componentes R1'!I460 -> 158970.97 | H50: ='Reporte Componentes R1'!J460 -> 1910496.6 | I50: ='Reporte Componentes R1'!K460 -> 53118.02 | J50: 0 | K50: =D50-E50-F50-G50-H50-I50-J50 -> 5696234.5 | L50: 0 | M50: =K50-L50 -> 5696234.5 | N50: ='Reporte Componentes R1'!L460 -> 0 | O50: =M50+N50 -> 5696234.5 | S50: 4 | T50: BOGOTA LIMPIA S.A.S. ESP. | U50: ='Reporte Componentes R1'!M460 -> 465949.63 | V50: ='Reporte Componentes R1'!N460 -> 593731.16 | W50: ='Reporte Componentes R1'!O460 -> 3012620.8 | X50: ='Reporte Componentes R1'!P460 -> 1391475 | Y50: ='Reporte Componentes R1'!Q460 -> 87879.79 | Z50: =-L50 -> 0 | AA50: ='Reporte Componentes R1'!R460+'Reporte Componentes R1'!V460+'Reporte Componentes R1'!U460 -> -15.83 | AB50: =N50 -> 0 | AC50: ='Reporte Componentes R1'!T460+'Reporte Componentes R1'!W460+'Reporte Componentes R1'!X460+'Reporte Componentes R1'!Y460+'Reporte Componentes R1'!Z460+'Reporte Componentes R1'!S460 -> 0 | AD50: =-J50+AE50 -> 144593.98 | AE50: ='Reporte Componentes R1'!F461 -> 144593.98 | AF50: =SUM(U50:AD50) -> 5696234.5 | AG50: =(AF50-O50) -> 0 | AH50: =INT(AG50)=0 -> TRUE
B51: 5 | C51: AREA LIMPIA DISTRITO CAPITAL S.A.S. ESP. | D51: ='Reporte Componentes R1'!F554 -> 61140 | E51: ='Reporte Componentes R1'!G554 -> 2566.43 | F51: ='Reporte Componentes R1'!H554 -> 1430.01 | G51: ='Reporte Componentes R1'!I554 -> 760.56 | H51: ='Reporte Componentes R1'!J554 -> 11744.12 | I51: ='Reporte Componentes R1'!K554 -> 584.9 | J51: 0 | K51: =D51-E51-F51-G51-H51-I51-J51 -> 44053.98 | L51: 0 | M51: =K51-L51 -> 44053.98 | N51: ='Reporte Componentes R1'!L554 -> 0 | O51: =M51+N51 -> 44053.98 | S51: 5 | T51: AREA LIMPIA DISTRITO CAPITAL S.A.S. ESP. | U51: ='Reporte Componentes R1'!M554 -> 5130.67 | V51: ='Reporte Componentes R1'!N554 -> 5018.9 | W51: ='Reporte Componentes R1'!O554 -> 25484.97 | X51: ='Reporte Componentes R1'!P554 -> 7649.02 | Y51: ='Reporte Componentes R1'!Q554 -> 954.31 | Z51: =-L51 -> 0 | AA51: ='Reporte Componentes R1'!R554+'Reporte Componentes R1'!V554+'Reporte Componentes R1'!U554 -> -4.74 | AB51: =N51 -> 0 | AC51: ='Reporte Componentes R1'!T554+'Reporte Componentes R1'!W554+'Reporte Componentes R1'!X554+'Reporte Componentes R1'!Y554+'Reporte Componentes R1'!Z554+'Reporte Componentes R1'!S554 -> 0 | AD51: =-J51+AE51 -> -179.15 | AE51: ='Reporte Componentes R1'!F555 -> -179.15 | AF51: =SUM(U51:AD51) -> 44053.98 | AG51: =(AF51-O51) -> 0 | AH51: =INT(AG51)=0 -> TRUE
C52: TOTAL | D52: =SUM(D47:D51) -> 8908654 | E52: =SUM(E47:E51) -> 535450.36 | F52: =SUM(F47:F51) -> 303030.12 | G52: =SUM(G47:G51) -> 163070.29 | H52: =SUM(H47:H51) -> 1985548.7 | I52: =SUM(I47:I51) -> 55463.08 | J52: =SUM(J47:J51) -> 0 | K52: =SUM(K47:K51) -> 5866091.4 | ... O52: =SUM(O47:O51) -> 5866091.4 | T52: TOTAL | U52: =SUM(U47:U51) -> 486520.38 | V52: =SUM(V47:V51) -> 617994.46 | W52: =SUM(W47:W51) -> 3128751 | X52: =SUM(X47:X51) -> 1426392.4 | Y52: =SUM(Y47:Y51) -> 91705.96 | Z52: =SUM(Z47:Z51) -> 0 | AA52: =SUM(AA47:AA51) -> -26.52 | AB52: =SUM(AB47:AB51) -> 0 | ... AG52: =SUM(AG47:AG51) -> 6.184564e-11 | AH52: =INT(AG52)=0 -> TRUE
Y54: =SUM(U52:Y52) -> 5751364.2
F56: Firma autorizada
F60: PROCERASEO S.A.S. | I60: NIT: 901 153 639 - 0 | M60: Codigo Remuneración: | N60: =N3 -> 2026091 | U60: PROCERASEO S.A.S. | W60: NIT: 901 153 639 - 0 | AA60: Codigo Remuneración: | AD60: =N60 -> 2026091
F61: 3. ESQUEMA FINANCIERO DEL SERVICIO PUBLICO DE ASEO | U61: 3. ESQUEMA FINANCIERO DEL SERVICIO PUBLICO DE ASEO
F62: Resoluciòn UAESP Número 27 de 2018 | U62: Resoluciòn UAESP Número 27 de 2018
C63: Fecha de Proceso: | D63: =D6 -> 46282 | F63: R4 - REVERSIÓN DE PAGOS | U63: R4 - REVERSIÓN DE PAGOS
C64: Hora: | D64: =D7 -> 0.58333333 | F64: Fecha Desde: | G64: =G7 -> 46266 | J64: Feha Hasta: | K64: =K7 -> 46280 | U64: =F64 -> Fecha Desde: | V64: =G64 -> 46266 | X64: =J64 -> Feha Hasta: | Y64: =K64 -> 46280
B65: ASE | C65: Concesionarios | D65: Recaudo Total | E65: Recaudo por disposicion final | F65: Recaudo por tratamiento de lixiviados | G65: Recaudo por Componente VIAT ( Decreto 2412/2018) | H65: Recaudo por aprovechamiento | I65: Recaudo del componente de comercializacion para Aprovechamiento (11,4%) | J65: Balance de subsidio o contribuciones | K65: RECAUDO BASE DE REMUNERACION | L65: Costo de la Interventoría | M65: REMUNERACION FINAL | N65: Conceptos especiales | O65: REMUNERACION FINAL MAS CONCEPTOS ESPECIALES | S65: ASE | T65: Concesionarios | U65: Tarifa de Comercialización del Servicio. ( TCS) | V65: Tarifa de Limpieza Urbana del Servicio. ( TLU) | W65: Tarifa de Barrido y Limpieza del Servicio. ( TBL) | X65: Tarifa de Recolección y Transporte del Servicio. (TRT) | Y65: Recaudo del componente de comercializacion para Aprovechamiento (18,6%) | Z65: Costo de la Interventoría | AA65: Ajuste a la decena | AB65: Conceptos especiales | AC65: Otros | AD65: Diferencial Balance S / C (Fac vs Rec) | AE65: Balance S / C Con Base en (Recaudo) | AF65: REMUNERACION FINAL MAS CONCEPTOS ESPECIALES
B66: 1 | C66: PROMOAMBIENTAL DISTRITO S.A.S. ESP. | D66: ='Reversion Pagos R4'!D71 -> -3544507.3 | E66: ='Reversion Pagos R4'!E71 -> -219031.92 | F66: ='Reversion Pagos R4'!F71 -> -117594.76 | G66: ='Reversion Pagos R4'!G71 -> -63004.75 | H66: ='Reversion Pagos R4'!H71 -> -1190187.4 | I66: ='Reversion Pagos R4'!I71 -> -45698.67 | J66: 0 | K66: =D66-E66-F66-G66-H66-I66-J66 -> -1908989.8 | L66: 0 | M66: =K66-L66 -> -1908989.8 | N66: ='Reversion Pagos R4'!P71 -> 0 | O66: =M66+N66 -> -1908989.8 | S66: 1 | T66: PROMOAMBIENTAL DISTRITO S.A.S. ESP. | U66: ='Reversion Pagos R4'!J71 -> -400863.96 | V66: ='Reversion Pagos R4'!K71 -> -377006.7 | W66: ='Reversion Pagos R4'!L71 -> -1788474 | X66: ='Reversion Pagos R4'!M71 -> -573353.78 | Y66: ='Reversion Pagos R4'!N71 -> -73936.2 | Z66: =-L66 -> 0 | AA66: ='Reversion Pagos R4'!O71 -> 10.66 | AB66: =N66 -> 0 | AC66: =+'Reversion Pagos R4'!Q71+'Reversion Pagos R4'!R71 -> 0 | AD66: =-J66+AE66 -> 1304634.2 | AE66: ='Reversion Pagos R4'!D72 -> 1304634.2 | AF66: =SUM(U66:AD66) -> -1908989.8 | AG66: =(AF66-O66) -> 0 | AH66: =INT(AG66)=0 -> TRUE
B67: 2 | C67: LIMPIEZA METROPOLITANA S.A. ESP. | D67: ='Reversion Pagos R4'!D160 -> -8713102.4 | E67: ='Reversion Pagos R4'!E160 -> -566211.7 | F67: ='Reversion Pagos R4'!F160 -> -318239.98 | G67: ='Reversion Pagos R4'!G160 -> -167439.25 | H67: ='Reversion Pagos R4'!H160 -> -2642163 | I67: ='Reversion Pagos R4'!I160 -> -90052.6 | J67: 0 | K67: =D67-E67-F67-G67-H67-I67-J67 -> -4928995.8 | L67: 0 | M67: =K67-L67 -> -4928995.8 | N67: ='Reversion Pagos R4'!P160 -> -26500 | O67: =M67+N67 -> -4955495.8 | S67: 2 | T67: LIMPIEZA METROPOLITANA S.A. ESP. | U67: ='Reversion Pagos R4'!J160 -> -789932.39 | V67: ='Reversion Pagos R4'!K160 -> -770822.52 | W67: ='Reversion Pagos R4'!L160 -> -3654042.8 | X67: ='Reversion Pagos R4'!M160 -> -1114650.3 | Y67: ='Reversion Pagos R4'!N160 -> -146927.71 | Z67: =-L67 -> 0 | AA67: ='Reversion Pagos R4'!O160 -> 4.09 | AB67: =N67 -> -26500 | AC67: =+'Reversion Pagos R4'!Q160+'Reversion Pagos R4'!R160 -> 0 | AD67: =-J67+AE67 -> 1547375.8 | AE67: ='Reversion Pagos R4'!D161 -> 1547375.8 | AF67: =SUM(U67:AD67) -> -4955495.8 | AG67: =(AF67-O67) -> 0 | AH67: =INT(AG67)=0 -> TRUE
B68: 3 | C68: CIUDAD LIMPIA BOGOTA S.A. ESP. | D68: ='Reversion Pagos R4'!D196 -> -6125983.9 | E68: ='Reversion Pagos R4'!E196 -> -331141.74 | F68: ='Reversion Pagos R4'!F196 -> -186760.32 | G68: ='Reversion Pagos R4'!G196 -> -98282.84 | H68: ='Reversion Pagos R4'!H196 -> -2019437.3 | I68: ='Reversion Pagos R4'!I196 -> -59765.73 | J68: 0 | K68: =D68-E68-F68-G68-H68-I68-J68 -> -3430595.9 | L68: 0 | M68: =K68-L68 -> -3430595.9 | N68: ='Reversion Pagos R4'!P196 -> 0 | O68: =M68+N68 -> -3430595.9 | S68: 3 | T68: CIUDAD LIMPIA BOGOTA S.A. ESP. | U68: ='Reversion Pagos R4'!J196 -> -521004.73 | V68: ='Reversion Pagos R4'!K196 -> -508266.78 | W68: ='Reversion Pagos R4'!L196 -> -2407798.7 | X68: ='Reversion Pagos R4'!M196 -> -780590.23 | Y68: ='Reversion Pagos R4'!N196 -> -97513.13 | Z68: =-L68 -> 0 | AA68: ='Reversion Pagos R4'!O196 -> -29.01 | AB68: =N68 -> 0 | AC68: =+'Reversion Pagos R4'!Q196+'Reversion Pagos R4'!R196 -> 0 | AD68: =-J68+AE68 -> 884606.68 | AE68: ='Reversion Pagos R4'!D197 -> 884606.68 | AF68: =SUM(U68:AD68) -> -3430595.9 | AG68: =(AF68-O68) -> -1.3969839e-09 | AH68: =INT(AG68)=0 -> FALSE
B69: 4 | C69: BOGOTA LIMPIA S.A.S. ESP. | D69: ='Reversion Pagos R4'!D310 -> -22250060 | E69: ='Reversion Pagos R4'!E310 -> -1367674.7 | F69: ='Reversion Pagos R4'!F310 -> -719170.4 | G69: ='Reversion Pagos R4'!G310 -> -382313.94 | H69: ='Reversion Pagos R4'!H310 -> -5113171.6 | I69: ='Reversion Pagos R4'!I310 -> -183488.2 | J69: 0 | K69: =D69-E69-F69-G69-H69-I69-J69 -> -14484241 | L69: 0 | M69: =K69-L69 -> -14484241 | N69: ='Reversion Pagos R4'!P310 -> 0 | O69: =M69+N69 -> -14484241 | S69: 4 | T69: BOGOTA LIMPIA S.A.S. ESP. | U69: ='Reversion Pagos R4'!J310 -> -1619246.4 | V69: ='Reversion Pagos R4'!K310 -> -1602973.4 | W69: ='Reversion Pagos R4'!L310 -> -8034602.9 | X69: ='Reversion Pagos R4'!M310 -> -3828497.8 | Y69: ='Reversion Pagos R4'!N310 -> -296831.72 | Z69: =-L69 -> 0 | AA69: ='Reversion Pagos R4'!O310 -> 87.93 | AB69: =N69 -> 0 | AC69: =+'Reversion Pagos R4'!Q310+'Reversion Pagos R4'!R310 -> 0 | AD69: =-J69+AE69 -> 897823.39 | AE69: ='Reversion Pagos R4'!D311 -> 897823.39 | AF69: =SUM(U69:AD69) -> -14484241 | AG69: =(AF69-O69) -> 0 | AH69: =INT(AG69)=0 -> TRUE
B70: 5 | C70: AREA LIMPIA DISTRITO CAPITAL S.A.S. ESP. | D70: ='Reversion Pagos R4'!D345 -> -9076100 | E70: ='Reversion Pagos R4'!E345 -> -427564.46 | F70: ='Reversion Pagos R4'!F345 -> -239080.94 | G70: ='Reversion Pagos R4'!G345 -> -126277.96 | H70: ='Reversion Pagos R4'!H345 -> -1933506.8 | I70: ='Reversion Pagos R4'!I345 -> -69553.97 | J70: 0 | K70: =D70-E70-F70-G70-H70-I70-J70 -> -6280115.9 | L70: 0 | M70: =K70-L70 -> -6280115.9 | N70: ='Reversion Pagos R4'!P345 -> 0 | O70: =M70+N70 -> -6280115.9 | S70: 5 | T70: AREA LIMPIA DISTRITO CAPITAL S.A.S. ESP. | U70: ='Reversion Pagos R4'!J345 -> -610117.24 | V70: ='Reversion Pagos R4'!K345 -> -592518.26 | W70: ='Reversion Pagos R4'!L345 -> -3080559.2 | X70: ='Reversion Pagos R4'!M345 -> -1290465.9 | Y70: ='Reversion Pagos R4'!N345 -> -113482.38 | Z70: =-L70 -> 0 | AA70: ='Reversion Pagos R4'!O345 -> -48 | AB70: =N70 -> 0 | AC70: =+'Reversion Pagos R4'!Q345+'Reversion Pagos R4'!R345 -> 0 | AD70: =-J70+AE70 -> -592924.92 | AE70: ='Reversion Pagos R4'!D346 -> -592924.92 | AF70: =SUM(U70:AD70) -> -6280115.9 | AG70: =(AF70-O70) -> 0 | AH70: =INT(AG70)=0 -> TRUE
C71: TOTAL | D71: =SUM(D66:D70) -> -49709753 | E71: =SUM(E66:E70) -> -2911624.5 | F71: =SUM(F66:F70) -> -1580846.4 | G71: =SUM(G66:G70) -> -837318.74 | H71: =SUM(H66:H70) -> -12898466 | I71: =SUM(I66:I70) -> -448559.17 | J71: =SUM(J66:J70) -> 0 | K71: =SUM(K66:K70) -> -31032938 | ... O71: =SUM(O66:O70) -> -31059438 | T71: TOTAL | U71: =SUM(U66:U70) -> -3941164.7 | V71: =SUM(V66:V70) -> -3851587.7 | W71: =SUM(W66:W70) -> -18965478 | X71: =SUM(X66:X70) -> -7587558.1 | Y71: =SUM(Y66:Y70) -> -728691.14 | Z71: =SUM(Z66:Z70) -> 0 | AA71: =SUM(AA66:AA70) -> 25.67 | AB71: =SUM(AB66:AB70) -> -26500 | ... AG71: =SUM(AG66:AG70) -> -1.3969839e-09 | AH71: =INT(AG71)=0 -> FALSE
Y73: =SUM(U71:Y71) -> -35074479
F75: Firma autorizada
F79: PROCERASEO S.A.S. | I79: NIT: 901 153 639 - 0 | M79: Codigo Remuneración: | N79: =N3 -> 2026091 | U79: PROCERASEO S.A.S. | W79: NIT: 901 153 639 - 0 | AA79: Codigo Remuneración: | AD79: =N79 -> 2026091
F80: 3. ESQUEMA FINANCIERO DEL SERVICIO PUBLICO DE ASEO | U80: 3. ESQUEMA FINANCIERO DEL SERVICIO PUBLICO DE ASEO
F81: Resoluciòn UAESP Número 27 de 2018 | U81: Resoluciòn UAESP Número 27 de 2018
C82: Fecha de Proceso: | D82: =D6 -> 46282 | F82: R5 - REMUNERACIÓN SALDOS A FAVOR POR NOTA | U82: =F82 -> R5 - REMUNERACIÓN SALDOS A FAVOR POR NOTA
C83: Hora: | D83: =D7 -> 0.58333333 | F83: Fecha Desde: | G83: =G7 -> 46266 | J83: Feha Hasta: | K83: =K7 -> 46280 | U83: =F83 -> Fecha Desde: | V83: =G83 -> 46266 | X83: =J83 -> Feha Hasta: | Y83: =K83 -> 46280
B84: ASE | C84: Concesionarios | D84: Recaudo Total | E84: Recaudo por disposicion final | F84: Recaudo por tratamiento de lixiviados | G84: Recaudo por Componente VIAT ( Decreto 2412/2018) | H84: Recaudo por aprovechamiento | I84: Recaudo del componente de comercializacion para Aprovechamiento (11,4%) | J84: Balance de subsidio o contribuciones | K84: RECAUDO BASE DE REMUNERACION | L84: Costo de la Interventoría | M84: REMUNERACION FINAL | N84: Conceptos especiales | O84: REMUNERACION FINAL MAS CONCEPTOS ESPECIALES | S84: ASE | T84: Concesionarios | U84: Tarifa de Comercialización del Servicio. ( TCS) | V84: Tarifa de Limpieza Urbana del Servicio. ( TLU) | W84: Tarifa de Barrido y Limpieza del Servicio. ( TBL) | X84: Tarifa de Recolección y Transporte del Servicio. (TRT) | Y84: Recaudo del componente de comercializacion para Aprovechamiento (18,6%) | Z84: Costo de la Interventoría | AA84: Ajuste a la decena | AB84: Conceptos especiales | AC84: Otros | AD84: Diferencial Balance Subsidio y Contribución (Fac vs Rec) | AE84: Balance de subsidio o contribuciones (Recaudo) | AF84: REMUNERACION FINAL MAS CONCEPTOS ESPECIALES
B85: 1 | C85: PROMOAMBIENTAL DISTRITO S.A.S. ESP. | D85: ='AJUSTES - SF-T'!D47 -> 0 | E85: ='AJUSTES - SF-T'!E47 -> 0 | F85: ='AJUSTES - SF-T'!F47 -> 0 | G85: ='AJUSTES - SF-T'!G47 -> 0 | H85: ='AJUSTES - SF-T'!H47 -> 0 | I85: ='AJUSTES - SF-T'!I47 -> 0 | J85: ='AJUSTES - SF-T'!J47 -> 0 | K85: =D85-E85-F85-G85-H85-I85-J85 -> 0 | L85: 0 | M85: =K85-L85 -> 0 | N85: ='AJUSTES - SF-T'!N47 -> 0 | O85: =M85+N85 -> 0 | S85: 1 | T85: PROMOAMBIENTAL DISTRITO S.A.S. ESP. | U85: ='AJUSTES - SF-T'!U47 -> 0 | V85: ='AJUSTES - SF-T'!V47 -> 0 | W85: ='AJUSTES - SF-T'!W47 -> 0 | X85: ='AJUSTES - SF-T'!X47 -> 0 | Y85: ='AJUSTES - SF-T'!Y47 -> 0 | Z85: =-L85 -> 0 | AA85: 0 | AB85: =N85 -> 0 | AC85: ='AJUSTES - SF-T'!AA47 -> 0 | AD85: =-J85+AE85 -> 0 | AE85: ='AJUSTES - SF-T'!AD47 -> 0 | AF85: =SUM(U85:AD85) -> 0 | AG85: =AF85-O85 -> 0 | AH85: =INT(AG85)=0 -> TRUE
B86: 2 | C86: LIMPIEZA METROPOLITANA S.A. ESP. | D86: ='AJUSTES - SF-T'!D48 -> 0 | E86: ='AJUSTES - SF-T'!E48 -> 0 | F86: ='AJUSTES - SF-T'!F48 -> 0 | G86: ='AJUSTES - SF-T'!G48 -> 0 | H86: ='AJUSTES - SF-T'!H48 -> 0 | I86: ='AJUSTES - SF-T'!I48 -> 0 | J86: ='AJUSTES - SF-T'!J48 -> 0 | K86: =D86-E86-F86-G86-H86-I86-J86 -> 0 | L86: 0 | M86: =K86-L86 -> 0 | N86: ='AJUSTES - SF-T'!N48 -> 0 | O86: =M86+N86 -> 0 | S86: 2 | T86: LIMPIEZA METROPOLITANA S.A. ESP. | U86: ='AJUSTES - SF-T'!U48 -> 0 | V86: ='AJUSTES - SF-T'!V48 -> 0 | W86: ='AJUSTES - SF-T'!W48 -> 0 | X86: ='AJUSTES - SF-T'!X48 -> 0 | Y86: ='AJUSTES - SF-T'!Y48 -> 0 | Z86: =-L86 -> 0 | AA86: ='AJUSTES - SF-T'!AA48 -> 0 | AB86: =N86 -> 0 | AC86: 0 | AD86: =-J86+AE86 -> 0 | AE86: ='AJUSTES - SF-T'!AD48 -> 0 | AF86: =SUM(U86:AD86) -> 0 | AG86: =AF86-O86 -> 0 | AH86: =INT(AG86)=0 -> TRUE
B87: 3 | C87: CIUDAD LIMPIA BOGOTA S.A. ESP. | D87: ='AJUSTES - SF-T'!D49 -> 0 | E87: ='AJUSTES - SF-T'!E49 -> 0 | F87: ='AJUSTES - SF-T'!F49 -> 0 | G87: ='AJUSTES - SF-T'!G49 -> 0 | H87: ='AJUSTES - SF-T'!H49 -> 0 | I87: ='AJUSTES - SF-T'!I49 -> 0 | J87: ='AJUSTES - SF-T'!J49 -> 0 | K87: =D87-E87-F87-G87-H87-I87-J87 -> 0 | L87: 0 | M87: =K87-L87 -> 0 | N87: ='AJUSTES - SF-T'!N49 -> 0 | O87: =M87+N87 -> 0 | S87: 3 | T87: CIUDAD LIMPIA BOGOTA S.A. ESP. | U87: ='AJUSTES - SF-T'!U49 -> 0 | V87: ='AJUSTES - SF-T'!V49 -> 0 | W87: ='AJUSTES - SF-T'!W49 -> 0 | X87: ='AJUSTES - SF-T'!X49 -> 0 | Y87: ='AJUSTES - SF-T'!Y49 -> 0 | Z87: =-L87 -> 0 | AA87: ='AJUSTES - SF-T'!AA49 -> 0 | AB87: =N87 -> 0 | AC87: 0 | AD87: =-J87+AE87 -> 0 | AE87: ='AJUSTES - SF-T'!AD49 -> 0 | AF87: =SUM(U87:AD87) -> 0 | AG87: =AF87-O87 -> 0 | AH87: =INT(AG87)=0 -> TRUE
B88: 4 | C88: BOGOTA LIMPIA S.A.S. ESP. | D88: ='AJUSTES - SF-T'!D50 -> 0 | E88: ='AJUSTES - SF-T'!E50 -> 0 | F88: ='AJUSTES - SF-T'!F50 -> 0 | G88: ='AJUSTES - SF-T'!G50 -> 0 | H88: ='AJUSTES - SF-T'!H50 -> 0 | I88: ='AJUSTES - SF-T'!I50 -> 0 | J88: ='AJUSTES - SF-T'!J50 -> 0 | K88: =D88-E88-F88-G88-H88-I88-J88 -> 0 | L88: 0 | M88: =K88-L88 -> 0 | N88: ='AJUSTES - SF-T'!N50 -> 0 | O88: =M88+N88 -> 0 | S88: 4 | T88: BOGOTA LIMPIA S.A.S. ESP. | U88: ='AJUSTES - SF-T'!U50 -> 0 | V88: ='AJUSTES - SF-T'!V50 -> 0 | W88: ='AJUSTES - SF-T'!W50 -> 0 | X88: ='AJUSTES - SF-T'!X50 -> 0 | Y88: ='AJUSTES - SF-T'!Y50 -> 0 | Z88: =-L88 -> 0 | AA88: ='AJUSTES - SF-T'!AA50 -> 0 | AB88: =N88 -> 0 | AC88: 0 | AD88: =-J88+AE88 -> 0 | AE88: ='AJUSTES - SF-T'!AD50 -> 0 | AF88: =SUM(U88:AD88) -> 0 | AG88: =AF88-O88 -> 0 | AH88: =INT(AG88)=0 -> TRUE
B89: 5 | C89: AREA LIMPIA DISTRITO CAPITAL S.A.S. ESP. | D89: ='AJUSTES - SF-T'!D51 -> 0 | E89: ='AJUSTES - SF-T'!E51 -> 0 | F89: ='AJUSTES - SF-T'!F51 -> 0 | G89: ='AJUSTES - SF-T'!G51 -> 0 | H89: ='AJUSTES - SF-T'!H51 -> 0 | I89: ='AJUSTES - SF-T'!I51 -> 0 | J89: ='AJUSTES - SF-T'!J51 -> 0 | K89: =D89-E89-F89-G89-H89-I89-J89 -> 0 | L89: 0 | M89: =K89-L89 -> 0 | N89: ='AJUSTES - SF-T'!N51 -> 0 | O89: =M89+N89 -> 0 | S89: 5 | T89: AREA LIMPIA DISTRITO CAPITAL S.A.S. ESP. | U89: ='AJUSTES - SF-T'!U51 -> 0 | V89: ='AJUSTES - SF-T'!V51 -> 0 | W89: ='AJUSTES - SF-T'!W51 -> 0 | X89: ='AJUSTES - SF-T'!X51 -> 0 | Y89: ='AJUSTES - SF-T'!Y51 -> 0 | Z89: =-L89 -> 0 | AA89: ='AJUSTES - SF-T'!AA51 -> 0 | AB89: =N89 -> 0 | AC89: 0 | AD89: =-J89+AE89 -> 0 | AE89: ='AJUSTES - SF-T'!AD51 -> 0 | AF89: =SUM(U89:AD89) -> 0 | AG89: =AF89-O89 -> 0 | AH89: =INT(AG89)=0 -> TRUE
C90: TOTAL | D90: =SUM(D85:D89) -> 0 | E90: =SUM(E85:E89) -> 0 | F90: =SUM(F85:F89) -> 0 | G90: =SUM(G85:G89) -> 0 | H90: =SUM(H85:H89) -> 0 | I90: =SUM(I85:I89) -> 0 | J90: =SUM(J85:J89) -> 0 | K90: =SUM(K85:K89) -> 0 | ... O90: =SUM(O85:O89) -> 0 | T90: TOTAL | U90: =SUM(U85:U89) -> 0 | V90: =SUM(V85:V89) -> 0 | W90: =SUM(W85:W89) -> 0 | X90: =SUM(X85:X89) -> 0 | Y90: =SUM(Y85:Y89) -> 0 | Z90: =SUM(Z85:Z89) -> 0 | AA90: =SUM(AA85:AA89) -> 0 | AB90: =SUM(AB85:AB89) -> 0 | ... AG90: =SUM(AG85:AG89) -> 0 | AH90: =INT(AG90)=0 -> TRUE
Y92: =SUM(U90:Y90) -> 0
F94: Firma autorizada
F98: PROCERASEO S.A.S. | I98: NIT: 901 153 639 - 0 | M98: Codigo Remuneración: | N98: =N3 -> 2026091 | U98: PROCERASEO S.A.S. | W98: NIT: 901 153 639 - 0 | AA98: Codigo Remuneración: | AD98: =N98 -> 2026091
F99: 3. ESQUEMA FINANCIERO DEL SERVICIO PUBLICO DE ASEO | U99: 3. ESQUEMA FINANCIERO DEL SERVICIO PUBLICO DE ASEO
F100: Resoluciòn UAESP Número 27 de 2018 | U100: Resoluciòn UAESP Número 27 de 2018
C101: Fecha de Proceso: | D101: =D6 -> 46282 | F101: REPORTE CONSOLIDADO TOTAL DE RECAUDO | U101: REPORTE DETALLADO SUBBOLSA RBL DISCRIMINADO POR ACTIVIDADES
C102: Hora: | D102: =D7 -> 0.58333333 | F102: Fecha Desde: | G102: =G7 -> 46266 | J102: Feha Hasta: | K102: =K7 -> 46280 | U102: =F102 -> Fecha Desde: | V102: =G102 -> 46266 | X102: =J102 -> Feha Hasta: | Y102: =K102 -> 46280
B103: ASE | C103: Concesionarios | D103: Recaudo Total | E103: Recaudo por disposicion final | F103: Recaudo por tratamiento de lixiviados | G103: Recaudo por Componente VIAT ( Decreto 2412/2018) | H103: Recaudo por aprovechamiento | I103: Recaudo del componente de comercializacion para Aprovechamiento (11,4%) | J103: Balance de subsidio o contribuciones | K103: RECAUDO BASE DE REMUNERACION | L103: Costo de la Interventoría | M103: REMUNERACION FINAL | N103: Conceptos especiales | O103: REMUNERACION FINAL MAS CONCEPTOS ESPECIALES | S103: ASE | T103: Concesionarios | U103: Tarifa de Comercialización del Servicio. ( TCS) | V103: Tarifa de Limpieza Urbana del Servicio. ( TLU) | W103: Tarifa de Barrido y Limpieza del Servicio. ( TBL) | X103: Tarifa de Recolección y Transporte del Servicio. (TRT) | Y103: Recaudo del componente de comercializacion para Aprovechamiento (18,6%) | Z103: Costo de la Interventoría | AA103: Ajuste a la decena | AB103: Conceptos especiales | AC103: Otros | AD103: Diferencial Balance Subsidio y Contribución (Fac vs Rec) | AE103: Balance de subsidio o contribuciones (Recaudo) | AF103: REMUNERACION FINAL MAS CONCEPTOS ESPECIALES
B104: 1 | C104: PROMOAMBIENTAL DISTRITO S.A.S. ESP. | D104: =D9+D28+D47+D66+D85 -> 1.7450251e+10 | E104: =E9+E28+E47+E66+E85 -> 1.0027305e+09 | F104: =F9+F28+F47+F66+F85 -> 5.5951317e+08 | G104: =G9+G28+G47+G66+G85 -> 2.9634029e+08 | H104: =H9+H28+H47+H66+H85 -> 4858821909 | I104: =I9+I28+I47+I66+I85 -> 1.8220848e+08 | J104: =J9+J28+J47+J66+J85 -> 2.5893357e+09 | K104: =D104-E104-F104-G104-H104-I104-J104 -> 7.9613005e+09 | L104: =L9+L28+L47+L66+L85 -> 189185987 | M104: =K104-L104 -> 7.7721145e+09 | N104: =N9+N28+N47+N66+N85 -> 30635670 | O104: =M104+N104 -> 7.8027501e+09 | S104: 1 | T104: PROMOAMBIENTAL DISTRITO S.A.S. ESP. | U104: =U9+U28+U47+U66+U85 -> 1.5997921e+09 | V104: =V9+V28+V47+V66+V85 -> 1.5287054e+09 | W104: =W9+W28+W47+W66+W85 -> 7.1920556e+09 | X104: =X9+X28+X47+X66+X85 -> 2.7302893e+09 | Y104: =Y9+Y28+Y47+Y66+Y85 -> 2.9732075e+08 | Z104: =Z9+Z28+Z47+Z66+Z85 -> -189185987 | AA104: =AA9+AA28+AA47+AA66+AA85 -> -46885.63 | AB104: =AB9+AB28+AB47+AB66+AB85 -> 30635670 | AC104: =AC9+AC28+AC47+AC66+AC85 -> 392.74 | AD104: =-J104+AE104 -> -5.3868162e+09 | AE104: =AE9+AE28+AE47+AE66+AE85 -> -2.7974805e+09 | AF104: =SUM(U104:AD104) -> 7.8027501e+09 | AG104: =AF104-O104 -> 0 | AH104: =INT(AG104)=0 -> TRUE
B105: 2 | C105: LIMPIEZA METROPOLITANA S.A. ESP. | D105: =D10+D29+D48+D67+D86 -> 1.4147358e+10 | E105: =E10+E29+E48+E67+E86 -> 1.0962419e+09 | F105: =F10+F29+F48+F67+F86 -> 6.0768851e+08 | G105: =G10+G29+G48+G67+G86 -> 3.2074609e+08 | H105: =H10+H29+H48+H67+H86 -> 4.4861569e+09 | I105: =I10+I29+I48+I67+I86 -> 1.5249957e+08 | J105: =J10+J29+J48+J67+J86 -> -5.0932598e+09 | K105: =D105-E105-F105-G105-H105-I105-J105 -> 1.2577285e+10 | L105: =L10+L29+L48+L67+L86 -> 266580255 | M105: =K105-L105 -> 1.2310704e+10 | N105: =N10+N29+N48+N67+N86 -> 43616074 | O105: =M105+N105 -> 1.235432e+10 | S105: 2 | T105: LIMPIEZA METROPOLITANA S.A. ESP. | U105: =U10+U29+U48+U67+U86 -> 1.3386759e+09 | V105: =V10+V29+V48+V67+V86 -> 1.3260463e+09 | W105: =W10+W29+W48+W67+W86 -> 6.2149233e+09 | X105: =X10+X29+X48+X67+X86 -> 2.1545074e+09 | Y105: =Y10+Y29+Y48+Y67+Y86 -> 2.490176e+08 | Z105: =Z10+Z29+Z48+Z67+Z86 -> -266580255 | AA105: =AA10+AA29+AA48+AA67+AA86 -> 61423.42 | AB105: =AB10+AB29+AB48+AB67+AB86 -> 43616074 | AC105: =AC10+AC29+AC48+AC67+AC86 -> -56807.54 | AD105: =-J105+AE105 -> 1.2941095e+09 | AE105: =AE10+AE29+AE48+AE67+AE86 -> -3.7991503e+09 | AF105: =SUM(U105:AD105) -> 1.235432e+10 | AG105: =AF105-O105 -> 0 | AH105: =INT(AG105)=0 -> TRUE
B106: 3 | C106: CIUDAD LIMPIA BOGOTA S.A. ESP. | D106: =D11+D30+D49+D68+D87 -> 1.0891339e+10 | E106: =E11+E30+E49+E68+E87 -> 7.1070608e+08 | F106: =F11+F30+F49+F68+F87 -> 3.9747748e+08 | G106: =G11+G30+G49+G68+G87 -> 2.1036593e+08 | H106: =H11+H30+H49+H68+H87 -> 3.0897857e+09 | I106: =I11+I30+I49+I68+I87 -> 1.0259106e+08 | J106: =J11+J30+J49+J68+J87 -> -1.230397e+09 | K106: =D106-E106-F106-G106-H106-I106-J106 -> 7.6108094e+09 | L106: =L11+L30+L49+L68+L87 -> 154788535 | M106: =K106-L106 -> 7.4560209e+09 | N106: =N11+N30+N49+N68+N87 -> 25562528 | O106: =M106+N106 -> 7.4815834e+09 | S106: 3 | T106: CIUDAD LIMPIA BOGOTA S.A. ESP. | U106: =U11+U30+U49+U68+U87 -> 9.0040444e+08 | V106: =V11+V30+V49+V68+V87 -> 8.8025184e+08 | W106: =W11+W30+W49+W68+W87 -> 4.1430165e+09 | X106: =X11+X30+X49+X68+X87 -> 1.6838613e+09 | Y106: =Y11+Y30+Y49+Y68+Y87 -> 1.6742136e+08 | Z106: =Z11+Z30+Z49+Z68+Z87 -> -154788535 | AA106: =AA11+AA30+AA49+AA68+AA87 -> 46657 | AB106: =AB11+AB30+AB49+AB68+AB87 -> 25562528 | AC106: =AC11+AC30+AC49+AC68+AC87 -> 5.47 | AD106: =-J106+AE106 -> -1.6419266e+08 | AE106: =AE11+AE30+AE49+AE68+AE87 -> -1.3945897e+09 | AF106: =SUM(U106:AD106) -> 7.4815834e+09 | AG106: =AF106-O106 -> 0 | AH106: =INT(AG106)=0 -> TRUE
B107: 4 | C107: BOGOTA LIMPIA S.A.S. ESP. | D107: =D12+D31+D50+D69+D88 -> 1.1508947e+10 | E107: =E12+E31+E50+E69+E88 -> 6.5162035e+08 | F107: =F12+F31+F50+F69+F88 -> 3.6207689e+08 | G107: =G12+G31+G50+G69+G88 -> 1.9142449e+08 | H107: =H12+H31+H50+H69+H88 -> 2.8505195e+09 | I107: =I12+I31+I50+I69+I88 -> 98433844 | J107: =J12+J31+J50+J69+J88 -> 38133906 | K107: =D107-E107-F107-G107-H107-I107-J107 -> 7.3167382e+09 | L107: =L12+L31+L50+L69+L88 -> 120391083 | M107: =K107-L107 -> 7.1963471e+09 | N107: =N12+N31+N50+N69+N88 -> 23185408 | O107: =M107+N107 -> 7.2195325e+09 | S107: 4 | T107: BOGOTA LIMPIA S.A.S. ESP. | U107: =U12+U31+U50+U69+U88 -> 8.6349652e+08 | V107: =V12+V31+V50+V69+V88 -> 8.5091524e+08 | W107: =W12+W31+W50+W69+W88 -> 4.3369309e+09 | X107: =X12+X31+X50+X69+X88 -> 1.7250123e+09 | Y107: =Y12+Y31+Y50+Y69+Y88 -> 1.6087823e+08 | Z107: =Z12+Z31+Z50+Z69+Z88 -> -120391083 | AA107: =AA12+AA31+AA50+AA69+AA88 -> -64310.54 | AB107: =AB12+AB31+AB50+AB69+AB88 -> 23185408 | AC107: =AC12+AC31+AC50+AC69+AC88 -> 181.07 | AD107: =-J107+AE107 -> -6.2043086e+08 | AE107: =AE12+AE31+AE50+AE69+AE88 -> -5.8229695e+08 | AF107: =SUM(U107:AD107) -> 7.2195325e+09 | AG107: =AF107-O107 -> 0 | AH107: =INT(AG107)=0 -> TRUE
B108: 5 | C108: AREA LIMPIA DISTRITO CAPITAL S.A.S. ESP. | D108: =D13+D32+D51+D70+D89 -> 9.1471794e+09 | E108: =E13+E32+E51+E70+E89 -> 5.0114181e+08 | F108: =F13+F32+F51+F70+F89 -> 2.7995073e+08 | G108: =G13+G32+G51+G70+G89 -> 1.4824291e+08 | H108: =H13+H32+H51+H70+H89 -> 2.1000672e+09 | I108: =I13+I32+I51+I70+I89 -> 75390757 | J108: =J13+J32+J51+J70+J89 -> -1.2241007e+09 | K108: =D108-E108-F108-G108-H108-I108-J108 -> 7.2664867e+09 | L108: =L13+L32+L51+L70+L89 -> 128990445 | M108: =K108-L108 -> 7.1374962e+09 | N108: =N13+N32+N51+N70+N89 -> 32575938 | O108: =M108+N108 -> 7.1700722e+09 | S108: 5 | T108: AREA LIMPIA DISTRITO CAPITAL S.A.S. ESP. | U108: =U13+U32+U51+U70+U89 -> 6.6183483e+08 | V108: =V13+V32+V51+V70+V89 -> 6.438762e+08 | W108: =W13+W32+W51+W70+W89 -> 3.3042169e+09 | X108: =X13+X32+X51+X70+X89 -> 1.5006793e+09 | Y108: =Y13+Y32+Y51+Y70+Y89 -> 1.2309614e+08 | Z108: =Z13+Z32+Z51+Z70+Z89 -> -128990445 | AA108: =AA13+AA32+AA51+AA70+AA89 -> -16582.77 | AB108: =AB13+AB32+AB51+AB70+AB89 -> 32575938 | AC108: =AC13+AC32+AC51+AC70+AC89 -> -105.68 | AD108: =-J108+AE108 -> 1.0327999e+09 | AE108: =AE13+AE32+AE51+AE70+AE89 -> -1.9130078e+08 | AF108: =SUM(U108:AD108) -> 7.1700722e+09 | AG108: =AF108-O108 -> 0 | AH108: =INT(AG108)=0 -> TRUE
