Workbook
Name \0: #REF!
Name _1: #REF!
Name _2: #REF!
Name _A655555: #REF!
Name _CFR1: #REF!
Name _cia1: #REF!
Name _XL250: #REF!
Name A: #REF!
Name ADM: [1]!ADM
Name ADM: [1]!ADM
Name ADM: [1]!ADM
Name ADM: [1]!ADM
Name ADM: [1]!ADM
Name ADM_: [1]!ADM
Name ADM_: [1]!ADM
Name ADM_: [1]!ADM
Name ADM_: [1]!ADM
Name ADM_: [1]!ADM
Name AI: #REF!
Name Air: #REF!
Name AP: '[2]TARIFA no aforos'!$C$12
Name Bancos: [3]Fx!$C$1:$C$23
Name CBL: #REF!
Name CCS: #REF!
Name CDT_p: [4]CDT!$C$3
Name CFR: #REF!
Name cia: #REF!
Name COM: #REF!
Name CRT: #REF!
Name CRT___CTEp___CDTp___CMRv: #REF!
Name CRT_aislados: '[4]COSTOS AJUSTADOS'!$C$13
Name CRT_costas: #REF!
Name CTE_p: [4]CTE!$C$5
Name Denominador: #REF!
Name dg: [1]!ADM
Name dg: [1]!ADM
Name dg: [1]!ADM
Name dg: [1]!ADM
Name dg: [1]!ADM
Name DIAS: [5]CONTRA!#REF!
Name Fmerc: #REF!
Name FPS: #REF!
Name InformacionGeneral: [1]!InformacionGeneral
Name InformacionGeneral: [1]!InformacionGeneral
Name InformacionGeneral: [1]!InformacionGeneral
Name InformacionGeneral: [1]!InformacionGeneral
Name InformacionGeneral: [1]!InformacionGeneral
Name INTFIN: #REF!
Name INV: [1]!INV
Name INV: [1]!INV
Name INV: [1]!INV
Name INV: [1]!INV
Name INV: [1]!INV
Name K: #REF!
Name N: '[4]COSTOS AJUSTADOS'!#REF!
Name Na: '[2]TARIFA no aforos'!$C$39
Name nfc: '[4]COSTOS AJUSTADOS'!#REF!
Name OYM: [1]!OYM
Name OYM: [1]!OYM
Name OYM: [1]!OYM

Sheet Recaudo EAAB Reciprocidad
B2: OPORTUNO | C2: ASE | D2: VALOR 1° Q | E2: NUMERO REG. 1°Q | F2: VALOR 2° Q | G2: NUMERO REG. 2°Q
C3: 1 | D3: 0 | E3: 0 | F3: 0 | G3: 0
C4: 2 | D4: 0 | E4: 0 | F4: 0 | G4: 0
C5: 3 | D5: 0 | E5: 0 | F5: 0 | G5: 0
C6: 4 | D6: 0 | E6: 0 | F6: 0 | G6: 0
C7: 5 | D7: 0 | E7: 0 | F7: 0 | G7: 0
C8: X
D9: 0 | E9: 0 | F9: 0 | G9: 0
C11: ASE | D11: VALOR 1° Q | E11: NUMERO REG. 1°Q | F11: VALOR 2° Q | G11: NUMERO REG. 2°Q
B12: EXTEMP. | C12: 1 | D12: 0 | E12: 0 | F12: 0 | G12: 0
C13: 2 | D13: 0 | E13: 0 | F13: 0 | G13: 0
C14: 3 | D14: 0 | E14: 0 | F14: 0 | G14: 0
C15: 4 | D15: 0 | E15: 0 | F15: 0 | G15: 0
C16: 5 | D16: 0 | E16: 0 | F16: 0 | G16: 0
C17: X
D18: 0 | E18: 0 | F18: 0 | G18: 0
C20: ASE | D20: VALOR 1° Q | E20: NUMERO REG. 1°Q | F20: VALOR 2° Q | G20: NUMERO REG. 2°Q | I20: VALOR TOTAL MES | J20: NUMERO REGISTROS MES
B21: TOTAL | C21: 1 | D21: 0 | E21: 0 | F21: 0 | G21: 0 | I21: 0 | J21: 0
C22: 2 | D22: 0 | E22: 0 | F22: 0 | G22: 0 | I22: 0 | J22: 0
C23: 3 | D23: 0 | E23: 0 | F23: 0 | G23: 0 | I23: 0 | J23: 0
C24: 4 | D24: 0 | E24: 0 | F24: 0 | G24: 0 | I24: 0 | J24: 0
C25: 5 | D25: 0 | E25: 0 | F25: 0 | G25: 0 | I25: 0 | J25: 0
C26: X | I26: 0 | J26: 0
D27: 0 | E27: 0 | F27: 0 | G27: 0 | I27: 0 | J27: 0
B31: OPORTUNO | D31: =D9=SUM(D3:D8) -> TRUE | E31: =E9=SUM(E3:E8) -> TRUE | F31: =F9=SUM(F3:F8) -> TRUE | G31: =G9=SUM(G3:G8) -> TRUE
B33: EXTEMP. | D33: =D18=SUM(D12:D17) -> TRUE | E33: =E18=SUM(E12:E17) -> TRUE | F33: =F18=SUM(F12:F17) -> TRUE | G33: =G18=SUM(G12:G17) -> TRUE
B35: TOTAL | D35: =D27=SUM(D21:D26) -> TRUE | E35: =E27=SUM(E21:E26) -> TRUE | F35: =F27=SUM(F21:F26) -> TRUE | G35: =G27=SUM(G21:G26) -> TRUE | I35: =I27=SUM(I21:I26) -> TRUE | J35: =J27=SUM(J21:J26) -> TRUE
E69: =C69-G17 -> 0

Sheet Recaudo ENEL
B2: OPORTUNO | C2: ASE | D2: VALOR 1° Q | E2: NUMERO REG. 1°Q | F2: VALOR 2° Q | G2: NUMERO REG. 2°Q
C3: 1 | D3: 14382259562 | E3: 305702 | F3: 0 | G3: 0
C4: 2 | D4: 10247752463 | E4: 198695 | F4: 0 | G4: 0
C5: 3 | D5: 8348318512 | E5: 195122 | F5: 0 | G5: 0
C6: 4 | D6: 9859647946 | E6: 172571 | F6: 0 | G6: 0
C7: 5 | D7: 7125653520 | E7: 137028 | F7: 0 | G7: 0
C8: X
D9: 49963632003 | E9: 1009118 | F9: 0 | G9: 0
C11: ASE | D11: VALOR 1° Q | E11: NUMERO REG. 1°Q | F11: VALOR 2° Q | G11: NUMERO REG. 2°Q
B12: EXTEMP. | C12: 1 | D12: 128684600 | E12: 2090 | F12: 0 | G12: 0
C13: 2 | D13: 60162560 | E13: 1233 | F13: 0 | G13: 0
C14: 3 | D14: 58639078 | E14: 1146 | F14: 0 | G14: 0
C15: 4 | D15: 72782190 | E15: 1190 | F15: 0 | G15: 0
C16: 5 | D16: 122557965 | E16: 2207 | F16: 0 | G16: 0
C17: X
D18: 442826393 | E18: 7866 | F18: 0 | G18: 0
C20: ASE | D20: VALOR 1° Q | E20: NUMERO REG. 1°Q | F20: VALOR 2° Q | G20: NUMERO REG. 2°Q | I20: VALOR TOTAL MES | J20: NUMERO REGISTROS MES
B21: TOTAL | C21: 1 | D21: 14510944162 | E21: 307792 | F21: 0 | G21: 0 | I21: 14510944162 | J21: 307792
C22: 2 | D22: 10307915023 | E22: 199928 | F22: 0 | G22: 0 | I22: 10307915023 | J22: 199928
C23: 3 | D23: 8406957590 | E23: 196268 | F23: 0 | G23: 0 | I23: 8406957590 | J23: 196268
C24: 4 | D24: 9932430136 | E24: 173761 | F24: 0 | G24: 0 | I24: 9932430136 | J24: 173761
C25: 5 | D25: 7248211485 | E25: 139235 | F25: 0 | G25: 0 | I25: 7248211485 | J25: 139235
C26: X | I26: 0 | J26: 0
D27: 50406458396 | E27: 1016984 | F27: 0 | G27: 0 | I27: 50406458396 | J27: 1016984
B31: OPORTUNO | D31: =D9=SUM(D3:D8) -> TRUE | E31: =E9=SUM(E3:E8) -> TRUE | F31: =F9=SUM(F3:F8) -> TRUE | G31: =G9=SUM(G3:G8) -> TRUE
B33: EXTEMP. | D33: =D18=SUM(D12:D17) -> TRUE | E33: =E18=SUM(E12:E17) -> TRUE | F33: =F18=SUM(F12:F17) -> TRUE | G33: =G18=SUM(G12:G17) -> TRUE
B35: TOTAL | D35: =D27=SUM(D21:D26) -> TRUE | E35: =E27=SUM(E21:E26) -> TRUE | F35: =F27=SUM(F21:F26) -> TRUE | G35: =G27=SUM(G21:G26) -> TRUE | I35: =I27=SUM(I21:I26) -> TRUE | J35: =J27=SUM(J21:J26) -> TRUE
E69: =C69-G17 -> 0

Sheet Recaudo ENERBIT
B2: OPORTUNO | C2: ASE | D2: VALOR 1° Q | E2: NUMERO REG. 1°Q | F2: VALOR 2° Q | G2: NUMERO REG. 2°Q
C3: 1 | D3: 0 | E3: 0 | F3: 0 | G3: 0
C4: 2 | D4: 0 | E4: 0 | F4: 0 | G4: 0
C5: 3 | D5: 0 | E5: 0 | F5: 0 | G5: 0
C6: 4 | D6: 0 | E6: 0 | F6: 0 | G6: 0
C7: 5 | D7: 140424760 | E7: 2998 | F7: 0 | G7: 0
C8: X
D9: 140424760 | E9: 2998 | F9: 0 | G9: 0
C11: ASE | D11: VALOR 1° Q | E11: NUMERO REG. 1°Q | F11: VALOR 2° Q | G11: NUMERO REG. 2°Q
B12: EXTEMP. | C12: 1 | D12: 0 | E12: 0 | F12: 0 | G12: 0
C13: 2 | D13: 0 | E13: 0 | F13: 0 | G13: 0
C14: 3 | D14: 0 | E14: 0 | F14: 0 | G14: 0
C15: 4 | D15: 0 | E15: 0 | F15: 0 | G15: 0
C16: 5 | D16: 0 | E16: 0 | F16: 0 | G16: 0
C17: X
D18: 0 | E18: 0 | F18: 0 | G18: 0
C20: ASE | D20: VALOR 1° Q | E20: NUMERO REG. 1°Q | F20: VALOR 2° Q | G20: NUMERO REG. 2°Q | I20: VALOR TOTAL MES | J20: NUMERO REGISTROS MES
B21: TOTAL | C21: 1 | D21: 0 | E21: 0 | F21: 0 | G21: 0 | I21: 0 | J21: 0
C22: 2 | D22: 0 | E22: 0 | F22: 0 | G22: 0 | I22: 0 | J22: 0
C23: 3 | D23: 0 | E23: 0 | F23: 0 | G23: 0 | I23: 0 | J23: 0
C24: 4 | D24: 0 | E24: 0 | F24: 0 | G24: 0 | I24: 0 | J24: 0
C25: 5 | D25: 140424760 | E25: 2998 | F25: 0 | G25: 0 | I25: 140424760 | J25: 2998
C26: X | I26: 0 | J26: 0
D27: 140424760 | E27: 2998 | F27: 0 | G27: 0 | I27: 140424760 | J27: 2998
B31: OPORTUNO | D31: =D9=SUM(D3:D8) -> TRUE | E31: =E9=SUM(E3:E8) -> TRUE | F31: =F9=SUM(F3:F8) -> TRUE | G31: =G9=SUM(G3:G8) -> TRUE
B33: EXTEMP. | D33: =D18=SUM(D12:D17) -> TRUE | E33: =E18=SUM(E12:E17) -> TRUE | F33: =F18=SUM(F12:F17) -> TRUE | G33: =G18=SUM(G12:G17) -> TRUE
B35: TOTAL | D35: =D27=SUM(D21:D26) -> TRUE | E35: =E27=SUM(E21:E26) -> TRUE | F35: =F27=SUM(F21:F26) -> TRUE | G35: =G27=SUM(G21:G26) -> TRUE | I35: =I27=SUM(I21:I26) -> TRUE | J35: =J27=SUM(J21:J26) -> TRUE
E69: =C69-G17 -> 0

Sheet Recaudo EAAB + Ciud Limp
B2: Ciudad Limpia - Prestador | C2: ASE | D2: VALOR 1° Q | E2: NUMERO REG. 1°Q | F2: VALOR 2° Q | G2: NUMERO REG. 2°Q
C3: 1 | D3: 0 | E3: 0 | F3: 0 | G3: 0
C4: 2 | D4: 0 | E4: 0 | F4: 0 | G4: 0
C5: 3 | D5: 0 | E5: 0 | F5: 0 | G5: 0
C6: 4 | D6: 0 | E6: 0 | F6: 0 | G6: 0
C7: 5 | D7: 0 | E7: 0 | F7: 0 | G7: 0
C8: X
D9: 0 | E9: 0 | F9: 0 | G9: 0
C11: ASE | D11: VALOR 1° Q | E11: NUMERO REG. 1°Q | F11: VALOR 2° Q | G11: NUMERO REG. 2°Q
B12: EAAB - Prestador | C12: 1 | D12: 0 | E12: 0 | F12: 0 | G12: 0
C13: 2 | D13: 0 | E13: 0 | F13: 0 | G13: 0
C14: 3 | D14: 0 | E14: 0 | F14: 0 | G14: 0
C15: 4 | D15: 0 | E15: 0 | F15: 0 | G15: 0
C16: 5 | D16: 0 | E16: 0 | F16: 0 | G16: 0
C17: X
D18: 0 | E18: 0 | F18: 0 | G18: 0
C20: ASE | D20: VALOR 1° Q | E20: NUMERO REG. 1°Q | F20: VALOR 2° Q | G20: NUMERO REG. 2°Q | I20: VALOR TOTAL MES | J20: NUMERO REGISTROS MES
B21: TOTAL | C21: 1 | D21: 0 | E21: 0 | F21: 0 | G21: 0 | I21: 0 | J21: 0
C22: 2 | D22: 0 | E22: 0 | F22: 0 | G22: 0 | I22: 0 | J22: 0
C23: 3 | D23: 0 | E23: 0 | F23: 0 | G23: 0 | I23: 0 | J23: 0
C24: 4 | D24: 0 | E24: 0 | F24: 0 | G24: 0 | I24: 0 | J24: 0
C25: 5 | D25: 0 | E25: 0 | F25: 0 | G25: 0 | I25: 0 | J25: 0
C26: X | I26: 0 | J26: 0
D27: 0 | E27: 0 | F27: 0 | G27: 0 | I27: 0 | J27: 0
B31: OPORTUNO | D31: =D9=SUM(D3:D8) -> TRUE | E31: =E9=SUM(E3:E8) -> TRUE | F31: =F9=SUM(F3:F8) -> TRUE | G31: =G9=SUM(G3:G8) -> TRUE
B33: EXTEMP. | D33: =D18=SUM(D12:D17) -> TRUE | E33: =E18=SUM(E12:E17) -> TRUE | F33: =F18=SUM(F12:F17) -> TRUE | G33: =G18=SUM(G12:G17) -> TRUE
B35: TOTAL | D35: =D27=SUM(D21:D26) -> TRUE | E35: =E27=SUM(E21:E26) -> TRUE | F35: =F27=SUM(F21:F26) -> TRUE | G35: =G27=SUM(G21:G26) -> TRUE | I35: =I27=SUM(I21:I26) -> TRUE | J35: =J27=SUM(J21:J26) -> TRUE

Sheet Recaudo Directa Occidente
B2: OPORTUNO | C2: ASE | D2: VALOR 1° Q | E2: NUMERO REG. 1°Q | F2: VALOR 2° Q | G2: NUMERO REG. 2°Q
C3: 1 | D3: 322739090 | E3: 1616 | F3: 0 | G3: 0
C4: 2 | D4: 839789795 | E4: 3964 | F4: 0 | G4: 0
C5: 3 | D5: 417500887 | E5: 1376 | F5: 0 | G5: 0
C6: 4 | D6: 481464262 | E6: 2591 | F6: 0 | G6: 0
C7: 5 | D7: 168793421 | E7: 1160 | F7: 0 | G7: 0
C8: X | D8: 0 | E8: 0 | F8: 0 | G8: 0
D9: 2230287455 | E9: 10707 | F9: 0 | G9: 0
C11: ASE | D11: VALOR 1° Q | E11: NUMERO REG. 1°Q | F11: VALOR 2° Q | G11: NUMERO REG. 2°Q
B12: EXTEMP. | C12: 1 | D12: 48127653 | E12: 74 | F12: 0 | G12: 0
C13: 2 | D13: 132160935 | E13: 54 | F13: 0 | G13: 0
C14: 3 | D14: 19609348 | E14: 11 | F14: 0 | G14: 0
C15: 4 | D15: 118198907 | E15: 9 | F15: 0 | G15: 0
C16: 5 | D16: 7112332 | E16: 27 | F16: 0 | G16: 0
C17: X | D17: 0 | E17: 0 | F17: 0 | G17: 0
D18: 325209175 | E18: 175 | F18: 0 | G18: 0
C20: ASE | D20: VALOR 1° Q | E20: NUMERO REG. 1°Q | F20: VALOR 2° Q | G20: NUMERO REG. 2°Q | I20: VALOR TOTAL MES | J20: NUMERO REGISTROS MES
B21: TOTAL | C21: 1 | D21: 370866743 | E21: 1690 | F21: 0 | G21: 0 | I21: 370866743 | J21: 1690
C22: 2 | D22: 971950730 | E22: 4018 | F22: 0 | G22: 0 | I22: 971950730 | J22: 4018
C23: 3 | D23: 437110235 | E23: 1387 | F23: 0 | G23: 0 | I23: 437110235 | J23: 1387
C24: 4 | D24: 599663169 | E24: 2600 | F24: 0 | G24: 0 | I24: 599663169 | J24: 2600
C25: 5 | D25: 175905753 | E25: 1187 | F25: 0 | G25: 0 | I25: 175905753 | J25: 1187
C26: X | D26: 0 | E26: 0 | F26: 0 | G26: 0 | I26: 0 | J26: 0
D27: 2555496630 | E27: 10882 | F27: 0 | G27: 0 | I27: 2555496630 | J27: 10882
B31: OPORTUNO | D31: =D9=SUM(D3:D8) -> TRUE | E31: =E9=SUM(E3:E8) -> TRUE | F31: =F9=SUM(F3:F8) -> TRUE | G31: =G9=SUM(G3:G8) -> TRUE
B33: EXTEMP. | D33: =D18=SUM(D12:D17) -> TRUE | E33: =E18=SUM(E12:E17) -> TRUE | F33: =F18=SUM(F12:F17) -> TRUE | G33: =G18=SUM(G12:G17) -> TRUE
B35: TOTAL | D35: =D27=SUM(D21:D26) -> TRUE | E35: =E27=SUM(E21:E26) -> TRUE | F35: =F27=SUM(F21:F26) -> TRUE | G35: =G27=SUM(G21:G26) -> TRUE | I35: =I27=SUM(I21:I26) -> TRUE | J35: =J27=SUM(J21:J26) -> TRUE
E69: =C69-G17 -> 0

Sheet REPORTE RECAUDO x BANCO
C1: ENEL | D1: CIUDAD LIMPIA | E1: EAB | F1: NUEVO ESQUEMA | G1: ENERBIT | H1: OCCIDENTE | I1: Total
B2: 1-APLICADOS A FACTURACION | C2: =C13+C23+C32+C41+C51 -> 5.0300863e+10 | D2: =D13+D23+D32+D41+D51 -> 0 | E2: =E13+E23+E32+E41+E51 -> 0 | F2: =F13+F23+F32+F41+F51 -> 0 | G2: =G13+G23+G32+G41+G51 -> 139510580 | H2: =H13+H23+H32+H41+H51 -> 2.4480562e+09 | I2: =SUM(C2:H2) -> 5.288843e+10
B3: 2-SALDOS A FAVOR GENERADOS | C3: =C14+C24+C33+C42+C52 -> 1.0831116e+08 | D3: =D14+D24+D33+D42+D52 -> 0 | E3: =E14+E24+E33+E42+E52 -> 0 | F3: =F14+F24+F33+F42+F52 -> 0 | G3: =G14+G24+G33+G42+G52 -> 914180 | H3: =H14+H24+H33+H42+H52 -> 61958868 | I3: =SUM(C3:H3) -> 1.7118421e+08
B4: 3-APLICADOS A FINANCIACIONES NUEVAS | C4: =C15+C25+C34+C43+C53 -> 0 | D4: =D15+D25+D34+D43+D53 -> 0 | E4: =E15+E25+E34+E43+E53 -> 0 | F4: =F15+F25+F34+F43+F53 -> 0 | G4: =G15+G25+G34+G43+G53 -> 0 | H4: =H15+H25+H34+H43+H53 -> 45481533 | I4: =SUM(C4:H4) -> 45481533
B5: 7-APLICADOS A RECIBOS SERVICIOS ESPECIALES | C5: =C16+C26+C35+C44+C54 -> 0 | D5: =D16+D26+D35+D44+D54 -> 0 | E5: =E16+E26+E35+E44+E54 -> 0 | F5: =F16+F26+F35+F44+F54 -> 0 | G5: =G16+G26+G35+G44+G54 -> 0 | H5: =H16+H26+H35+H44+H54 -> 0 | I5: =SUM(C5:H5) -> 0
B6: Total | C6: =SUM(C2:C5) -> 50409174172 | D6: =SUM(D2:D5) -> 0 | E6: =SUM(E2:E5) -> 0 | F6: =SUM(F2:F5) -> 0 | G6: =SUM(G2:G5) -> 140424760 | H6: =SUM(H2:H5) -> 2.5554966e+09 | I6: =SUM(I2:I5) -> 5.3105096e+10
C7: =C6=(C17+C27+C36+C45+C55) -> TRUE | D7: =D6=(D17+D27+D36+D45+D55) -> TRUE | E7: =E6=(E17+E27+E36+E45+E55) -> TRUE | F7: =F6=(F17+F27+F36+F45+F55) -> TRUE | H7: =H6=(H17+H27+H36+H45+H55) -> TRUE | I7: =I6=(I17+I27+I36+I45+I55) -> TRUE
B10: ASE 1
B11: Resumen Recaudo Aplicado Por Servicio
C12: ENEL | D12: CIUDAD LIMPIA | E12: EAB | F12: NUEVO ESQUEMA | G12: ENERBIT | H12: OCCIDENTE | I12: Total
B13: 1-APLICADOS A FACTURACION | C13: 14481337615 | H13: 3.5146605e+08 | I13: =SUM(C13:H13) -> 1.4832804e+10 | J13: =SUM(C13:H13)=I13 -> TRUE
B14: 2-SALDOS A FAVOR GENERADOS | C14: 29606547 | H14: 17250690 | I14: =SUM(C14:H14) -> 46857237 | J14: =SUM(C14:H14)=I14 -> TRUE
B15: 3-APLICADOS A FINANCIACIONES NUEVAS | C15: 0 | H15: 2150000 | I15: =SUM(C15:H15) -> 2150000 | J15: =SUM(C15:H15)=I15 -> TRUE
B16: 7-APLICADOS A RECIBOS SERVICIOS ESPECIALES | C16: 0 | I16: =SUM(C16:H16) -> 0 | J16: =SUM(C16:H16)=I16 -> TRUE
B17: Total | C17: =SUM(C13:C16) -> 14510944162 | D17: =SUM(D13:D16) -> 0 | E17: =SUM(E13:E16) -> 0 | F17: =SUM(F13:F16) -> 0 | G17: =SUM(G13:G16) -> 0 | H17: =SUM(H13:H16) -> 370866743 | I17: =SUM(I13:I16) -> 14881810905 | J17: =SUM(C17:H17)=I17 -> TRUE
B20: ASE 2
B21: Resumen Recaudo Aplicado Por Servicio
C22: ENEL | D22: CIUDAD LIMPIA | E22: EAB | F22: NUEVO ESQUEMA | G22: ENERBIT | H22: OCCIDENTE | I22: Total
B23: 1-APLICADOS A FACTURACION | C23: 1.0286935e+10 | E23: 0 | F23: 0 | H23: 9.240376e+08 | I23: =SUM(C23:H23) -> 1.1210973e+10 | J23: =SUM(C23:H23)=I23 -> TRUE
B24: 2-SALDOS A FAVOR GENERADOS | C24: 22325147 | E24: 0 | F24: 0 | H24: 29950515 | I24: =SUM(C24:H24) -> 52275662 | J24: =SUM(C24:H24)=I24 -> TRUE
B25: 3-APLICADOS A FINANCIACIONES NUEVAS | C25: 0 | E25: 0 | F25: 0 | H25: 17962612 | I25: =SUM(C25:H25) -> 17962612 | J25: =SUM(C25:H25)=I25 -> TRUE
B26: 7-APLICADOS A RECIBOS SERVICIOS ESPECIALES | F26: 0 | H26: 0 | I26: =SUM(C26:H26) -> 0 | J26: =SUM(C26:H26)=I26 -> TRUE
B27: Total | C27: =SUM(C23:C26) -> 10309260573 | D27: =SUM(D23:D26) -> 0 | E27: =SUM(E23:E26) -> 0 | F27: =SUM(F23:F26) -> 0 | G27: =SUM(G23:G26) -> 0 | H27: =SUM(H23:H26) -> 971950730 | I27: =SUM(I23:I26) -> 11281211303 | J27: =SUM(C27:H27)=I27 -> TRUE
B29: ASE 3
B30: Resumen Recaudo Aplicado Por Servicio
C31: ENEL | D31: CIUDAD LIMPIA | E31: EAB | F31: NUEVO ESQUEMA | G31: ENERBIT | H31: OCCIDENTE | I31: Total
B32: 1-APLICADOS A FACTURACION | C32: 8398576932 | F32: 0 | H32: 4.3152163e+08 | I32: =SUM(C32:H32) -> 8.8300986e+09 | J32: =SUM(C32:H32)=I32 -> TRUE
B33: 2-SALDOS A FAVOR GENERADOS | C33: 8845080 | F33: 0 | H33: 4909289 | I33: =SUM(C33:H33) -> 13754369 | J33: =SUM(C33:H33)=I33 -> TRUE
B34: 3-APLICADOS A FINANCIACIONES NUEVAS | C34: 0 | F34: 0 | H34: 679320.71 | I34: =SUM(C34:H34) -> 679320.71 | J34: =SUM(C34:H34)=I34 -> TRUE
B35: 7-APLICADOS A RECIBOS SERVICIOS ESPECIALES | C35: 0 | F35: 0 | I35: =SUM(C35:H35) -> 0 | J35: =SUM(C35:H35)=I35 -> TRUE
B36: Total | C36: =SUM(C32:C35) -> 8407422012 | D36: =SUM(D32:D35) -> 0 | E36: =SUM(E32:E35) -> 0 | F36: =SUM(F32:F35) -> 0 | G36: =SUM(G32:G35) -> 0 | H36: =SUM(H32:H35) -> 437110235 | I36: =SUM(I32:I35) -> 8844532247 | J36: =SUM(C36:H36)=I36 -> TRUE
B38: ASE 4
B39: Resumen Recaudo Aplicado Por Servicio
C40: ENEL | D40: CIUDAD LIMPIA | E40: EAB | F40: NUEVO ESQUEMA | G40: ENERBIT | H40: OCCIDENTE | I40: Total
B41: 1-APLICADOS A FACTURACION | C41: 9890363914 | E41: 0 | F41: 0 | H41: 5.6767788e+08 | I41: =SUM(C41:H41) -> 1.0458042e+10 | J41: =SUM(C41:H41)=I41 -> TRUE
B42: 2-SALDOS A FAVOR GENERADOS | C42: 42284806 | E42: 0 | F42: 0 | H42: 7416134 | I42: =SUM(C42:H42) -> 49700940 | J42: =SUM(C42:H42)=I42 -> TRUE
B43: 3-APLICADOS A FINANCIACIONES NUEVAS | C43: 0 | E43: 0 | F43: 0 | H43: 24569155 | I43: =SUM(C43:H43) -> 24569155 | J43: =SUM(C43:H43)=I43 -> TRUE
B44: 7-APLICADOS A RECIBOS SERVICIOS ESPECIALES | F44: 0 | I44: =SUM(C44:H44) -> 0 | J44: =SUM(C44:H44)=I44 -> TRUE
B45: Total | C45: =SUM(C41:C44) -> 9932648720 | D45: =SUM(D41:D44) -> 0 | E45: =SUM(E41:E44) -> 0 | F45: =SUM(F41:F44) -> 0 | G45: =SUM(G41:G44) -> 0 | H45: =SUM(H41:H44) -> 599663169 | I45: =SUM(I41:I44) -> 10532311889 | J45: =SUM(C45:H45)=I45 -> TRUE
B48: ASE 5
B49: Resumen Recaudo Aplicado Por Servicio
C50: ENEL | D50: CIUDAD LIMPIA | E50: EAB | F50: NUEVO ESQUEMA | G50: ENERBIT | H50: OCCIDENTE | I50: Total
B51: 1-APLICADOS A FACTURACION | C51: 7243649125 | G51: 139510580 | H51: 1.7335307e+08 | I51: =SUM(C51:H51) -> 7.5565128e+09 | J51: =SUM(C51:H51)=I51 -> TRUE
B52: 2-SALDOS A FAVOR GENERADOS | C52: 5249580 | G52: 914180 | H52: 2432240 | I52: =SUM(C52:H52) -> 8596000 | J52: =SUM(C52:H52)=I52 -> TRUE
B53: 3-APLICADOS A FINANCIACIONES NUEVAS | C53: 0 | G53: 0 | H53: 120445.76 | I53: =SUM(C53:H53) -> 120445.76 | J53: =SUM(C53:H53)=I53 -> TRUE
B54: 7-APLICADOS A RECIBOS SERVICIOS ESPECIALES | C54: 0 | I54: =SUM(C54:H54) -> 0 | J54: =SUM(C54:H54)=I54 -> TRUE
B55: Total | C55: =SUM(C51:C54) -> 7248898705 | D55: =SUM(D51:D54) -> 0 | E55: =SUM(E51:E54) -> 0 | F55: =SUM(F51:F54) -> 0 | G55: =SUM(G51:G54) -> 140424760 | H55: =SUM(H51:H54) -> 175905753 | I55: =SUM(I51:I54) -> 7565229218 | J55: =SUM(C55:H55)=I55 -> TRUE
B59: QUINCENA | C59: 1 | D59: OJO/// DILIGENCIAR
B62: Recaudo ENEL - ASE 1 | C62: =IF($C$59=1,'Recaudo ENEL'!D21,'Recaudo ENEL'!F21) -> 14510944162 | D62: =C17=C62 -> TRUE | E62: =C17-C62 -> 0
B63: Recaudo ENERBIT - ASE 1 | C63: =IF($C$59=1,'Recaudo ENERBIT'!D21,'Recaudo ENERBIT'!F21) -> 0 | D63: =G17=C63 -> TRUE | E63: =G17-C63 -> 0
B64: Recaudo Reciprocidad EAAB - ASE 2 | C64: =IF($C$59=1,'Recaudo EAAB Reciprocidad'!D22,'Recaudo EAAB Reciprocidad'!F22) -> 0 | D64: =F27=C64 -> TRUE | E64: =F27-C64 -> 0
B65: Recaudo ENEL - ASE 2 | C65: =IF($C$59=1,'Recaudo ENEL'!D22,'Recaudo ENEL'!F22) -> 10307915023 | D65: =C27=C65 -> FALSE | E65: =C27-C65 -> 1345550 | F65: ok
B66: Recaudo ENERBIT - ASE 2 | C66: =IF($C$59=1,'Recaudo ENERBIT'!D22,'Recaudo ENERBIT'!F22) -> 0 | D66: =G27=C66 -> TRUE | E66: =G27-C66 -> 0
B67: Recaudo ENEL - ASE 3 | C67: =IF($C$59=1,'Recaudo ENEL'!D23,'Recaudo ENEL'!F23) -> 8406957590 | D67: =C36=C67 -> FALSE | E67: =C36-C67 -> 464422 | F67: ok
B68: Recaudo ENERBIT - ASE 3 | C68: =IF($C$59=1,'Recaudo ENERBIT'!D23,'Recaudo ENERBIT'!F23) -> 0 | D68: =G36=C68 -> TRUE | E68: =G36-C68 -> 0
B69: Recaudo Reciprocidad EAAB - ASE 4 | C69: =IF($C$59=1,'Recaudo EAAB Reciprocidad'!D24,'Recaudo EAAB Reciprocidad'!F24) -> 0 | D69: =F45=C69 -> TRUE | E69: =F45-C69 -> 0
B70: Recaudo ENEL - ASE 4 | C70: =IF($C$59=1,'Recaudo ENEL'!D24,'Recaudo ENEL'!F24) -> 9932430136 | D70: =C45=C70 -> FALSE | E70: =C45-C70 -> 218584 | F70: ok
B71: Recaudo ENERBIT - ASE 4 | C71: =IF($C$59=1,'Recaudo ENERBIT'!D24,'Recaudo ENERBIT'!F24) -> 0 | D71: =G45=C71 -> TRUE | E71: =G45-C71 -> 0
B72: Recaudo ENEL - ASE 5 | C72: =IF($C$59=1,'Recaudo ENEL'!D25,'Recaudo ENEL'!F25) -> 7248211485 | D72: =C55=C72 -> FALSE | E72: =C55-C72 -> 687220 | F72: ok
B73: Recaudo ENERBIT - ASE 5 | C73: =IF($C$59=1,'Recaudo ENERBIT'!D25,'Recaudo ENERBIT'!F25) -> 140424760 | D73: =G55=C73 -> TRUE | E73: =G55-C73 -> 0
B75: Recaudo Banco Occidente ASE 1 | C75: =IF($C$59=1,'Recaudo Directa Occidente'!D21,'Recaudo Directa Occidente'!F21) -> 370866743 | D75: =C75=H17 -> TRUE | E75: =H17-C75 -> 0
B76: Recaudo Banco Occidente ASE 2 | C76: =IF($C$59=1,'Recaudo Directa Occidente'!D22,'Recaudo Directa Occidente'!F22) -> 971950730 | D76: =C76=H27 -> TRUE | E76: =H27-C76 -> 0
B77: Recaudo Banco Occidente ASE 3 | C77: =IF($C$59=1,'Recaudo Directa Occidente'!D23,'Recaudo Directa Occidente'!F23) -> 437110235 | D77: =C77=H36 -> TRUE | E77: =H36-C77 -> 0
B78: Recaudo Banco Occidente ASE 4 | C78: =IF($C$59=1,'Recaudo Directa Occidente'!D24,'Recaudo Directa Occidente'!F24) -> 599663169 | D78: =C78=H45 -> TRUE | E78: =H45-C78 -> 0
B79: Recaudo Banco Occidente ASE 5 | C79: =IF($C$59=1,'Recaudo Directa Occidente'!D25,'Recaudo Directa Occidente'!F25) -> 175905753 | D79: =C79=H55 -> TRUE | E79: =H55-C79 -> 0
B81: TOTAL RECAUDO | C81: =SUM(C62:C79) -> 53102379786 | D81: =C81=(I6-SUM(E62:E79)) -> TRUE

Sheet ANT EXT-REV
C1: ASE 1 | E1: ASE 2 | G1: ASE 3 | I1: ASE 4 | K1: ASE 5 | M1: TOTAL
C2: REPORTE 3 | D2: REPORTE 4 | E2: REPORTE 3 | F2: REPORTE 4 | G2: REPORTE 3 | H2: REPORTE 4 | I2: REPORTE 3 | J2: REPORTE 4 | K2: REPORTE 3 | L2: REPORTE 4 | M2: REPORTE 3 | N2: REPORTE 4
B3: APLICADO | C3: =C11+C19+C27+C35+C43 -> 648870 | D3: =D11+D19+D27+D35+D43 -> -3833780 | E3: =E11+E19+E27+E35+E43 -> 9704974 | F3: =F11+F19+F27+F35+F43 -> -21803648 | G3: =G11+G19+G27+G35+G43 -> 0 | H3: =H11+H19+H27+H35+H43 -> -2259272 | I3: =I11+I19+I27+I35+I43 -> 21557177 | J3: =J11+J19+J27+J35+J43 -> -41558585 | ... L3: =L11+L19+L27+L35+L43 -> -3964157 | M3: =C3+E3+G3+I3+K3 -> 31911021 | N3: =D3+F3+H3+J3+L3 -> -73419443 | P3: =N3=(-VALIDACION_TOTAL!M9) -> TRUE
B4: ANTICIPOS | C4: =C12+C20+C28+C36+C44 -> 0 | D4: =D12+D20+D28+D36+D44 -> 0 | E4: =E12+E20+E28+E36+E44 -> 6055989 | F4: =F12+F20+F28+F36+F44 -> -255254.55 | G4: =G12+G20+G28+G36+G44 -> 0 | H4: =H12+H20+H28+H36+H44 -> 0 | I4: =I12+I20+I28+I36+I44 -> 19678542 | J4: =J12+J20+J28+J36+J44 -> -1258817.6 | ... L4: =L12+L20+L28+L36+L44 -> -41240 | M4: =C4+E4+G4+I4+K4 -> 25734531 | N4: =D4+F4+H4+J4+L4 -> -1555312.1 | P4: =N4=(-'CONSOLIDADO_TOTAL RECAUDO'!L131) -> TRUE
B5: TOTAL | C5: =SUM(C3:C4) -> 648870 | D5: =SUM(D3:D4) -> -3833780 | E5: =SUM(E3:E4) -> 15760963 | F5: =SUM(F3:F4) -> -22058903 | G5: =SUM(G3:G4) -> 0 | H5: =SUM(H3:H4) -> -2259272 | I5: =SUM(I3:I4) -> 41235719 | J5: =SUM(J3:J4) -> -42817403 | ... N5: =SUM(N3:N4) -> -74974755
C6: =C5=(C13+C21+C29+C37+C45) -> TRUE | D6: =D5=(D13+D21+D29+D37+D45) -> TRUE | E6: =E5=(E13+E21+E29+E37+E45) -> TRUE | F6: =F5=(F13+F21+F29+F37+F45) -> TRUE | G6: =G5=(G13+G21+G29+G37+G45) -> TRUE | H6: =H5=(H13+H21+H29+H37+H45) -> TRUE | I6: =I5=(I13+I21+I29+I37+I45) -> TRUE | J6: =J5=(J13+J21+J29+J37+J45) -> TRUE | ... N6: =N5=(N13+N21+N29+N37+N45) -> TRUE
B8: BANCO DE OCCIDENTE
C9: ASE 1 | E9: ASE 2 | G9: ASE 3 | I9: ASE 4 | K9: ASE 5 | M9: TOTAL
C10: REPORTE 3 | D10: REPORTE 4 | E10: REPORTE 3 | F10: REPORTE 4 | G10: REPORTE 3 | H10: REPORTE 4 | I10: REPORTE 3 | J10: REPORTE 4 | K10: REPORTE 3 | L10: REPORTE 4 | M10: REPORTE 3 | N10: REPORTE 4
B11: APLICADO | C11: 134910 | D11: -134910 | E11: 464154 | F11: -945063 | G11: 0 | H11: 0 | I11: 850737 | J11: -1371252 | K11: 0 | L11: 0 | M11: =C11+E11+G11+I11+K11 -> 1449801 | N11: =D11+F11+H11+J11+L11 -> -2451225
B12: ANTICIPOS | C12: 0 | D12: 0 | E12: 529459 | F12: -48550 | G12: 0 | H12: 0 | I12: 606286 | J12: -85771 | K12: 0 | L12: 0 | M12: =C12+E12+G12+I12+K12 -> 1135745 | N12: =D12+F12+H12+J12+L12 -> -134321
B13: TOTAL | C13: =SUM(C11:C12) -> 134910 | D13: =SUM(D11:D12) -> -134910 | E13: =SUM(E11:E12) -> 993613 | F13: =SUM(F11:F12) -> -993613 | G13: =SUM(G11:G12) -> 0 | H13: =SUM(H11:H12) -> 0 | I13: =SUM(I11:I12) -> 1457023 | J13: =SUM(J11:J12) -> -1457023 | ... N13: =SUM(N11:N12) -> -2585546
B16: EAAB RECIPROCIDAD
C17: ASE 1 | E17: ASE 2 | G17: ASE 3 | I17: ASE 4 | K17: ASE 5 | M17: TOTAL
C18: REPORTE 3 | D18: REPORTE 4 | E18: REPORTE 3 | F18: REPORTE 4 | G18: REPORTE 3 | H18: REPORTE 4 | I18: REPORTE 3 | J18: REPORTE 4 | K18: REPORTE 3 | L18: REPORTE 4 | M18: REPORTE 3 | N18: REPORTE 4
B19: APLICADO | C19: 0 | D19: 0 | E19: 0 | F19: 0 | G19: 0 | H19: 0 | I19: 309350 | J19: -554080 | K19: 0 | L19: 0 | M19: =C19+E19+G19+I19+K19 -> 309350 | N19: =D19+F19+H19+J19+L19 -> -554080
B20: ANTICIPOS | C20: 0 | D20: 0 | E20: 0 | F20: 0 | G20: 0 | H20: 0 | I20: 244730 | J20: 0 | K20: 0 | L20: 0 | M20: =C20+E20+G20+I20+K20 -> 244730 | N20: =D20+F20+H20+J20+L20 -> 0
B21: TOTAL | C21: =SUM(C19:C20) -> 0 | D21: =SUM(D19:D20) -> 0 | E21: =SUM(E19:E20) -> 0 | F21: =SUM(F19:F20) -> 0 | G21: =SUM(G19:G20) -> 0 | H21: =SUM(H19:H20) -> 0 | I21: =SUM(I19:I20) -> 554080 | J21: =SUM(J19:J20) -> -554080 | ... L21: =SUM(L19:L20) -> 0 | M21: =C21+E21+G21+I21+K21 -> 554080 | N21: =SUM(N19:N20) -> -554080
B24: EAAB CIUDAD LIMPIA
C25: ASE 1 | E25: ASE 2 | G25: ASE 3 | I25: ASE 4 | K25: ASE 5 | M25: TOTAL
C26: REPORTE 3 | D26: REPORTE 4 | E26: REPORTE 3 | F26: REPORTE 4 | G26: REPORTE 3 | H26: REPORTE 4 | I26: REPORTE 3 | J26: REPORTE 4 | K26: REPORTE 3 | L26: REPORTE 4 | M26: REPORTE 3 | N26: REPORTE 4
B27: APLICADO | C27: 0 | D27: 0 | E27: 0 | F27: 0 | G27: 0 | H27: 0 | I27: 0 | J27: 0 | K27: 0 | L27: 0 | M27: =C27+E27+G27+I27+K27 -> 0 | N27: =D27+F27+H27+J27+L27 -> 0
B28: ANTICIPOS | C28: 0 | D28: 0 | E28: 0 | F28: 0 | G28: 0 | H28: 0 | I28: 0 | J28: 0 | K28: 0 | L28: 0 | M28: =C28+E28+G28+I28+K28 -> 0 | N28: =D28+F28+H28+J28+L28 -> 0
B29: TOTAL | C29: =SUM(C27:C28) -> 0 | D29: =SUM(D27:D28) -> 0 | E29: =SUM(E27:E28) -> 0 | F29: =SUM(F27:F28) -> 0 | G29: =SUM(G27:G28) -> 0 | H29: =SUM(H27:H28) -> 0 | I29: =SUM(I27:I28) -> 0 | J29: =SUM(J27:J28) -> 0 | ... N29: =SUM(N27:N28) -> 0
B32: ENEL
C33: ASE 1 | E33: ASE 2 | G33: ASE 3 | I33: ASE 4 | K33: ASE 5 | M33: TOTAL
C34: REPORTE 3 | D34: REPORTE 4 | E34: REPORTE 3 | F34: REPORTE 4 | G34: REPORTE 3 | H34: REPORTE 4 | I34: REPORTE 3 | J34: REPORTE 4 | K34: REPORTE 3 | L34: REPORTE 4 | M34: REPORTE 3 | N34: REPORTE 4
B35: APLICADO | C35: 513960 | D35: -3698870 | E35: 9240820 | F35: -20858585 | G35: 0 | H35: -2259272 | I35: 20397090 | J35: -39633253 | K35: 0 | L35: -3964157 | M35: =C35+E35+G35+I35+K35 -> 30151870 | N35: =D35+F35+H35+J35+L35 -> -70414138
B36: ANTICIPOS | C36: 0 | D36: 0 | E36: 5526530 | F36: -206704.55 | G36: 0 | H36: 0 | I36: 18827526 | J36: -1173046.6 | K36: 0 | L36: -41240 | M36: =C36+E36+G36+I36+K36 -> 24354056 | N36: =D36+F36+H36+J36+L36 -> -1420991.1
B37: TOTAL | C37: =SUM(C35:C36) -> 513960 | D37: =SUM(D35:D36) -> -3698870 | E37: =SUM(E35:E36) -> 14767350 | F37: =SUM(F35:F36) -> -21065290 | G37: =SUM(G35:G36) -> 0 | H37: =SUM(H35:H36) -> -2259272 | I37: =SUM(I35:I36) -> 39224616 | J37: =SUM(J35:J36) -> -40806300 | ... N37: =SUM(N35:N36) -> -71835129
B40: ENERBIT
C41: ASE 1 | E41: ASE 2 | G41: ASE 3 | I41: ASE 4 | K41: ASE 5 | M41: TOTAL
C42: REPORTE 3 | D42: REPORTE 4 | E42: REPORTE 3 | F42: REPORTE 4 | G42: REPORTE 3 | H42: REPORTE 4 | I42: REPORTE 3 | J42: REPORTE 4 | K42: REPORTE 3 | L42: REPORTE 4 | M42: REPORTE 3 | N42: REPORTE 4
B43: APLICADO | C43: 0 | D43: 0 | E43: 0 | F43: 0 | G43: 0 | H43: 0 | I43: 0 | J43: 0 | K43: 0 | L43: 0 | M43: =C43+E43+G43+I43+K43 -> 0 | N43: =D43+F43+H43+J43+L43 -> 0
B44: ANTICIPOS | C44: 0 | D44: 0 | E44: 0 | F44: 0 | G44: 0 | H44: 0 | I44: 0 | J44: 0 | K44: 0 | L44: 0 | M44: =C44+E44+G44+I44+K44 -> 0 | N44: =D44+F44+H44+J44+L44 -> 0
B45: TOTAL | C45: =SUM(C43:C44) -> 0 | D45: =SUM(D43:D44) -> 0 | E45: =SUM(E43:E44) -> 0 | F45: =SUM(F43:F44) -> 0 | G45: =SUM(G43:G44) -> 0 | H45: =SUM(H43:H44) -> 0 | I45: =SUM(I43:I44) -> 0 | J45: =SUM(J43:J44) -> 0 | ... N45: =SUM(N43:N44) -> 0

Sheet ANTICIPOS USUARIOS
B1: TOTAL | E1: RECIPROCIDAD | H1: ENEL | K1: ENERBIT | N1: OCCIDENTE | Q1: EAAB-CIUDADLIMPIA
B2: ASE | C2: ANTICIPOS GENERADOS POR PAGO | E2: ASE | F2: ANTICIPOS GENERADOS POR PAGO | H2: ASE | I2: ANTICIPOS GENERADOS POR PAGO | K2: ASE | L2: ANTICIPOS GENERADOS POR PAGO | N2: ASE | O2: ANTICIPOS GENERADOS POR PAGO | Q2: ASE | R2: ANTICIPOS GENERADOS POR PAGO | T2: Anticipos generados por pago
B3: 1 | C3: ='REPORTE RECAUDO x BANCO'!I14 -> 46857237 | E3: 1 | F3: ='REPORTE RECAUDO x BANCO'!F14 -> 0 | H3: 1 | I3: ='REPORTE RECAUDO x BANCO'!C14 -> 29606547 | K3: 1 | L3: ='REPORTE RECAUDO x BANCO'!G14 -> 0 | N3: 1 | O3: ='REPORTE RECAUDO x BANCO'!H14 -> 17250690 | Q3: 1 | R3: ='REPORTE RECAUDO x BANCO'!D14+'REPORTE RECAUDO x BANCO'!E14 -> 0 | T3: Sale del reporte Recaudo por Bancos.
B4: 2 | C4: ='REPORTE RECAUDO x BANCO'!I24 -> 52275662 | E4: 2 | F4: ='REPORTE RECAUDO x BANCO'!F24 -> 0 | H4: 2 | I4: ='REPORTE RECAUDO x BANCO'!C24 -> 22325147 | K4: 2 | L4: ='REPORTE RECAUDO x BANCO'!G24 -> 0 | N4: 2 | O4: ='REPORTE RECAUDO x BANCO'!H24 -> 29950515 | Q4: 2 | R4: ='REPORTE RECAUDO x BANCO'!D24+'REPORTE RECAUDO x BANCO'!E24 -> 0
B5: 3 | C5: ='REPORTE RECAUDO x BANCO'!I33 -> 13754369 | E5: 3 | F5: ='REPORTE RECAUDO x BANCO'!F33 -> 0 | H5: 3 | I5: ='REPORTE RECAUDO x BANCO'!C33 -> 8845080 | K5: 3 | L5: ='REPORTE RECAUDO x BANCO'!G33 -> 0 | N5: 3 | O5: ='REPORTE RECAUDO x BANCO'!H33 -> 4909289 | Q5: 3 | R5: ='REPORTE RECAUDO x BANCO'!D33+'REPORTE RECAUDO x BANCO'!E33 -> 0
B6: 4 | C6: ='REPORTE RECAUDO x BANCO'!I42 -> 49700940 | E6: 4 | F6: ='REPORTE RECAUDO x BANCO'!F42 -> 0 | H6: 4 | I6: ='REPORTE RECAUDO x BANCO'!C42 -> 42284806 | K6: 4 | L6: ='REPORTE RECAUDO x BANCO'!G42 -> 0 | N6: 4 | O6: ='REPORTE RECAUDO x BANCO'!H42 -> 7416134 | Q6: 4 | R6: ='REPORTE RECAUDO x BANCO'!D42+'REPORTE RECAUDO x BANCO'!E42 -> 0
B7: 5 | C7: ='REPORTE RECAUDO x BANCO'!I52 -> 8596000 | E7: 5 | F7: ='REPORTE RECAUDO x BANCO'!F52 -> 0 | H7: 5 | I7: ='REPORTE RECAUDO x BANCO'!C52 -> 5249580 | K7: 5 | L7: ='REPORTE RECAUDO x BANCO'!G52 -> 914180 | N7: 5 | O7: ='REPORTE RECAUDO x BANCO'!H52 -> 2432240 | Q7: 5 | R7: ='REPORTE RECAUDO x BANCO'!D52+'REPORTE RECAUDO x BANCO'!E52 -> 0
C8: =SUM(C3:C7) -> 1.7118421e+08 | F8: =SUM(F3:F7) -> 0 | I8: =SUM(I3:I7) -> 1.0831116e+08 | L8: =SUM(L3:L7) -> 914180 | O8: =SUM(O3:O7) -> 61958868 | R8: =SUM(R3:R7) -> 0
C9: =C8='REPORTE RECAUDO x BANCO'!I3 -> TRUE | F9: =F8='REPORTE RECAUDO x BANCO'!F3 -> TRUE | I9: =I8='REPORTE RECAUDO x BANCO'!C3 -> TRUE | L9: =L8='REPORTE RECAUDO x BANCO'!G3 -> TRUE | O9: =O8='REPORTE RECAUDO x BANCO'!H3 -> TRUE | R9: =R8='REPORTE RECAUDO x BANCO'!D3+'REPORTE RECAUDO x BANCO'!E3 -> TRUE
B11: ASE | C11: ANTICIPOS GENERADOS POR EXTEMPORANEOS | E11: ASE | F11: ANTICIPOS GENERADOS POR EXTEMPORANEOS | H11: ASE | I11: ANTICIPOS GENERADOS POR EXTEMPORANEOS | K11: ASE | L11: ANTICIPOS GENERADOS POR EXTEMPORANEOS | N11: ASE | O11: ANTICIPOS GENERADOS POR EXTEMPORANEOS | Q11: ASE | R11: ANTICIPOS GENERADOS POR EXTEMPORANEOS | T11: Anticipos generados por pagos aplicados de reversiones
B12: 1 | C12: ='ANT EXT-REV'!C4 -> 0 | E12: 1 | F12: ='ANT EXT-REV'!C20 -> 0 | H12: 1 | I12: ='ANT EXT-REV'!C36 -> 0 | K12: 1 | L12: ='ANT EXT-REV'!A12 -> 0 | N12: 1 | O12: ='ANT EXT-REV'!C12 -> 0 | Q12: 1 | R12: ='ANT EXT-REV'!C28 -> 0 | T12: Sale del reporte Recaudo reversado
B13: 2 | C13: ='ANT EXT-REV'!E4 -> 6055989 | E13: 2 | F13: ='ANT EXT-REV'!E20 -> 0 | H13: 2 | I13: ='ANT EXT-REV'!E36 -> 5526530 | K13: 2 | L13: ='ANT EXT-REV'!E44 -> 0 | N13: 2 | O13: ='ANT EXT-REV'!E12 -> 529459 | Q13: 2 | R13: ='ANT EXT-REV'!E28 -> 0
B14: 3 | C14: ='ANT EXT-REV'!G4 -> 0 | E14: 3 | F14: ='ANT EXT-REV'!G20 -> 0 | H14: 3 | I14: ='ANT EXT-REV'!G36 -> 0 | K14: 3 | L14: ='ANT EXT-REV'!G44 -> 0 | N14: 3 | O14: ='ANT EXT-REV'!G12 -> 0 | Q14: 3 | R14: ='ANT EXT-REV'!G28 -> 0
B15: 4 | C15: ='ANT EXT-REV'!I4 -> 19678542 | E15: 4 | F15: ='ANT EXT-REV'!I20 -> 244730 | H15: 4 | I15: ='ANT EXT-REV'!I36 -> 18827526 | K15: 4 | L15: ='ANT EXT-REV'!I44 -> 0 | N15: 4 | O15: ='ANT EXT-REV'!I12 -> 606286 | Q15: 4 | R15: ='ANT EXT-REV'!I28 -> 0
B16: 5 | C16: ='ANT EXT-REV'!K4 -> 0 | E16: 5 | F16: ='ANT EXT-REV'!K20 -> 0 | H16: 5 | I16: ='ANT EXT-REV'!K36 -> 0 | K16: 5 | L16: ='ANT EXT-REV'!K44 -> 0 | N16: 5 | O16: ='ANT EXT-REV'!K12 -> 0 | Q16: 5 | R16: ='ANT EXT-REV'!K28 -> 0
C17: =SUM(C12:C16) -> 25734531 | F17: =SUM(F12:F16) -> 244730 | I17: =SUM(I12:I16) -> 24354056 | L17: =SUM(L12:L16) -> 0 | O17: =SUM(O12:O16) -> 1135745 | R17: =SUM(R12:R16) -> 0
C18: =C17='ANT EXT-REV'!M4 -> TRUE | F18: =F17='ANT EXT-REV'!M20 -> TRUE | I18: =I17='ANT EXT-REV'!M36 -> TRUE | L18: =L17='ANT EXT-REV'!M44 -> TRUE | O18: =O17='ANT EXT-REV'!M12 -> TRUE | R18: =R17='ANT EXT-REV'!M28 -> TRUE
B20: ASE | C20: ANTICIPOS QUE CARGAN POR REVERSIONES | E20: ASE | F20: ANTICIPOS QUE CARGAN POR REVERSIONES | H20: ASE | I20: ANTICIPOS QUE CARGAN POR REVERSIONES | K20: ASE | L20: ANTICIPOS QUE CARGAN POR REVERSIONES | N20: ASE | O20: ANTICIPOS QUE CARGAN POR REVERSIONES | Q20: ASE | R20: ANTICIPOS QUE CARGAN POR REVERSIONES | T20: Anticipos que cargan de reversiones
B21: 1 | C21: ='ANT EXT-REV'!D4 -> 0 | E21: 1 | F21: ='ANT EXT-REV'!D20 -> 0 | H21: 1 | I21: ='ANT EXT-REV'!D36 -> 0 | K21: 1 | L21: ='ANT EXT-REV'!D44 -> 0 | N21: 1 | O21: ='ANT EXT-REV'!D12 -> 0 | Q21: 1 | R21: ='ANT EXT-REV'!D28 -> 0 | T21: Sale del reporte Recaudo reversado
B22: 2 | C22: ='ANT EXT-REV'!F4 -> -255254.55 | E22: 2 | F22: ='ANT EXT-REV'!F20 -> 0 | H22: 2 | I22: ='ANT EXT-REV'!F36 -> -206704.55 | K22: 2 | L22: ='ANT EXT-REV'!F44 -> 0 | N22: 2 | O22: ='ANT EXT-REV'!F12 -> -48550 | Q22: 2 | R22: ='ANT EXT-REV'!F28 -> 0
B23: 3 | C23: ='ANT EXT-REV'!H4 -> 0 | E23: 3 | F23: ='ANT EXT-REV'!H20 -> 0 | H23: 3 | I23: ='ANT EXT-REV'!H36 -> 0 | K23: 3 | L23: ='ANT EXT-REV'!H44 -> 0 | N23: 3 | O23: ='ANT EXT-REV'!H12 -> 0 | Q23: 3 | R23: ='ANT EXT-REV'!H28 -> 0
B24: 4 | C24: ='ANT EXT-REV'!J4 -> -1258817.6 | E24: 4 | F24: ='ANT EXT-REV'!J20 -> 0 | H24: 4 | I24: ='ANT EXT-REV'!J36 -> -1173046.6 | K24: 4 | L24: ='ANT EXT-REV'!J44 -> 0 | N24: 4 | O24: ='ANT EXT-REV'!J12 -> -85771 | Q24: 4 | R24: ='ANT EXT-REV'!J28 -> 0
B25: 5 | C25: ='ANT EXT-REV'!L4 -> -41240 | E25: 5 | F25: ='ANT EXT-REV'!L20 -> 0 | H25: 5 | I25: ='ANT EXT-REV'!L36 -> -41240 | K25: 5 | L25: ='ANT EXT-REV'!L44 -> 0 | N25: 5 | O25: ='ANT EXT-REV'!L12 -> 0 | Q25: 5 | R25: ='ANT EXT-REV'!L28 -> 0
C26: =SUM(C21:C25) -> -1555312.1 | F26: =SUM(F21:F25) -> 0 | I26: =SUM(I21:I25) -> -1420991.1 | L26: =SUM(L21:L25) -> 0 | O26: =SUM(O21:O25) -> -134321 | R26: =SUM(R21:R25) -> 0
C27: =C26='ANT EXT-REV'!N4 -> TRUE | F27: =F26='ANT EXT-REV'!N20 -> TRUE | I27: =I26='ANT EXT-REV'!N36 -> TRUE | L27: =L26='ANT EXT-REV'!N44 -> TRUE | O27: =O26='ANT EXT-REV'!N12 -> TRUE | R27: =R26='ANT EXT-REV'!N28 -> TRUE

Sheet BCE SC POR FACT.
C2: ASE | D2: SUBSIDIO | E2: CONTRIBUCION | F2: TOTAL BSC | H2: SISTEMA
C3: 1 | D3: -1.3280729e+09 | E3: 3.4820238e+09 | F3: =D3+E3 -> 2.1539508e+09 | H3: =DetRetri2026101!J9 -> 2153950828 | I3: =F3-H3 -> 0.16000032
C4: 2 | D4: -6.051832e+09 | E4: 1.8346864e+09 | F4: =D4+E4 -> -4.2171455e+09 | H4: =DetRetri2026101!J10 -> -4217145527 | I4: =F4-H4 -> 0.090000153
C5: 3 | D5: -3.1050034e+09 | E5: 1.816197e+09 | F5: =D5+E5 -> -1.2888063e+09 | H5: =DetRetri2026101!J11 -> -1288806337 | I5: =F5-H5 -> -0.090000153
C6: 4 | D6: -3.693256e+08 | E6: 4.3085756e+08 | F6: =D6+E6 -> 61531954 | H6: =DetRetri2026101!J12 -> 61531954 | I6: =F6-H6 -> -0.31
C7: 5 | D7: -2.3876069e+09 | E7: 1.1411338e+09 | F7: =D7+E7 -> -1.2464731e+09 | H7: =DetRetri2026101!J13 -> -1246473094 | I7: =F7-H7 -> -0.40999985
F9: =SUM(F3:F7) -> -4.5369422e+09 | H9: =SUM(H3:H7) -> -4536942176 | I9: =F9-H9 -> -0.55999947
H10: =H9=DetRetri2026101!J14 -> TRUE
D11: =SUM(D3:D7) -> -1.3241841e+10 | E11: =SUM(E3:E7) -> 8.7048987e+09 | F11: =SUM(D3:E7) -> -4.5369422e+09
F12: =ROUND(F11,2)=ROUND(F9,2) -> TRUE
F13: =ROUND(F11,2)-ROUND(F9,2) -> 0
D18: ASE | E18: REMUN TOTAL | F18: VALIDA 1 | G18: VALIDA 2 | H18: DIFERENCIA VALIDA 2
D19: 1 | E19: ='CONSOLIDADO_TOTAL RECAUDO'!J104 -> 2.1539508e+09 | F19: =E19=F3 -> TRUE | G19: =E19=H3 -> FALSE | H19: =E19-H3 -> 0.16000032
D20: 2 | E20: ='CONSOLIDADO_TOTAL RECAUDO'!J105 -> -4.2171455e+09 | F20: =E20=F4 -> TRUE | G20: =E20=H4 -> FALSE | H20: =E20-H4 -> 0.090000153
D21: 3 | E21: ='CONSOLIDADO_TOTAL RECAUDO'!J106 -> -1.2888063e+09 | F21: =E21=F5 -> TRUE | G21: =E21=H5 -> FALSE | H21: =E21-H5 -> -0.090000153
D22: 4 | E22: ='CONSOLIDADO_TOTAL RECAUDO'!J107 -> 61531954 | F22: =E22=F6 -> TRUE | G22: =E22=H6 -> FALSE | H22: =E22-H6 -> -0.31
D23: 5 | E23: ='CONSOLIDADO_TOTAL RECAUDO'!J108 -> -1.2464731e+09 | F23: =E23=F7 -> TRUE | G23: =E23=H7 -> FALSE | H23: =E23-H7 -> -0.40999985
E24: =SUM(E19:E23) -> -4.5369422e+09 | F24: =E24=F9 -> TRUE | G24: =E24=H9 -> FALSE | H24: =E24-H9 -> -0.55999947

Sheet Reporte Componentes R1
B4: PROMOAMBIENTAL
F5: Total | G5: Componente TDF | H5: Componente TTL | I5: Componente TVIAT | J5: Aprovechamiento | K5: CCSA Prest.Aprov. | L5: SERVICIO ESPECIALES | M5: Componente TCS | N5: Componente TLU | O5: Componente TBL | P5: Componente TRT | Q5: CCSA Prest. No Aprov. | R5: Ajuste Decena | S5: Ajuste Recargo Aseo | T5: Intereses Cte Financiac. Aseo | U5: Exonera-Recargo Aseo | V5: Exonera-Ajuste Decena Aseo | W5: Exonera-Recargo Aseo | X5: Exonera-Recargo Aseo | Y5: Intereses Cte Financiac. Aseo | Z5: Rec.Intereses
E6: Vlr Servicio | F6: -2015.07 | G6: -122.1 | H6: -51.87 | I6: -22.65 | J6: -369.44 | K6: -23.88 | L6: 0 | M6: -209.4 | N6: -175.25 | O6: -699.55 | P6: -301.98 | Q6: -38.95 | R6: 0 | S6: 0 | T6: 0 | U6: 0 | V6: 0 | W6: 0 | X6: 0 | Y6: 0 | Z6: 0
D7: E | E7: Total | F7: -2015.07 | G7: -122.1 | H7: -51.87 | I7: -22.65 | J7: -369.44 | K7: -23.88 | L7: 0 | M7: -209.4 | N7: -175.25 | O7: -699.55 | P7: -301.98 | Q7: -38.95 | R7: 0 | S7: 0 | T7: 0 | U7: 0 | V7: 0 | W7: 0 | X7: 0 | Y7: 0 | Z7: 0
C8: ENEL | D8: Total | F8: -2015.07 | G8: -122.1 | H8: -51.87 | I8: -22.65 | J8: -369.44 | K8: -23.88 | L8: 0 | M8: -209.4 | N8: -175.25 | O8: -699.55 | P8: -301.98 | Q8: -38.95 | R8: 0 | S8: 0 | T8: 0 | U8: 0 | V8: 0 | W8: 0 | X8: 0 | Y8: 0 | Z8: 0
B9: Mes | C9: Total | F9: -2015.07 | G9: -122.1 | H9: -51.87 | I9: -22.65 | J9: -369.44 | K9: -23.88 | L9: 0 | M9: -209.4 | N9: -175.25 | O9: -699.55 | P9: -301.98 | Q9: -38.95 | R9: 0 | S9: 0 | T9: 0 | U9: 0 | V9: 0 | W9: 0 | X9: 0 | Y9: 0 | Z9: 0
A10: AFaseo | B10: Total | F10: -2015.07 | G10: -122.1 | H10: -51.87 | I10: -22.65 | J10: -369.44 | K10: -23.88 | L10: 0 | M10: -209.4 | N10: -175.25 | O10: -699.55 | P10: -301.98 | Q10: -38.95 | R10: 0 | S10: 0 | T10: 0 | U10: 0 | V10: 0 | W10: 0 | X10: 0 | Y10: 0 | Z10: 0
E11: Vlr Servicio | F11: 543996.54 | G11: 23503.13 | H11: 13266.51 | I11: 6965.01 | J11: 119922.22 | K11: 5285.43 | L11: 0 | M11: 46363.01 | N11: 44625.42 | O11: 211250.82 | P11: 64191.45 | Q11: 8623.46 | R11: 0.08 | S11: 0 | T11: 0 | U11: 0 | V11: 0 | W11: 0 | X11: 0 | Y11: 0 | Z11: 0
E12: Vlr Intereses | F12: 2063.1 | G12: 86.78 | H12: 48.91 | I12: 25.71 | J12: 441.75 | K12: 20.42 | L12: 0 | M12: 179.53 | N12: 172.72 | O12: 816.93 | P12: 236.94 | Q12: 33.41 | R12: 0 | S12: 0 | T12: 0 | U12: 0 | V12: 0 | W12: 0 | X12: 0 | Y12: 0 | Z12: 0
D13: E | E13: Total | F13: 546059.64 | G13: 23589.91 | H13: 13315.42 | I13: 6990.72 | J13: 120363.97 | K13: 5305.85 | L13: 0 | M13: 46542.54 | N13: 44798.14 | O13: 212067.75 | P13: 64428.39 | Q13: 8656.87 | R13: 0.08 | S13: 0 | T13: 0 | U13: 0 | V13: 0 | W13: 0 | X13: 0 | Y13: 0 | Z13: 0
C14: ENEL | D14: Total | F14: 546059.64 | G14: 23589.91 | H14: 13315.42 | I14: 6990.72 | J14: 120363.97 | K14: 5305.85 | L14: 0 | M14: 46542.54 | N14: 44798.14 | O14: 212067.75 | P14: 64428.39 | Q14: 8656.87 | R14: 0.08 | S14: 0 | T14: 0 | U14: 0 | V14: 0 | W14: 0 | X14: 0 | Y14: 0 | Z14: 0
E15: Vlr Servicio | F15: 89870.51 | G15: 5626.37 | H15: 3138.96 | I15: 1667.33 | J15: 21034.12 | K15: 519.02 | L15: 0 | M15: 4552.92 | N15: 6472.07 | O15: 30640.84 | P15: 15366.98 | Q15: 846.86 | R15: 5.04 | S15: 0 | T15: 0 | U15: 0 | V15: 0 | W15: 0 | X15: 0 | Y15: 0 | Z15: 0
E16: Vlr Intereses | F16: 116.92 | G16: 7.31 | H16: 4.09 | I16: 2.17 | J16: 27.38 | K16: 0.67 | L16: 0 | M16: 5.91 | N16: 8.47 | O16: 39.84 | P16: 19.98 | Q16: 1.1 | R16: 0 | S16: 0 | T16: 0 | U16: 0 | V16: 0 | W16: 0 | X16: 0 | Y16: 0 | Z16: 0
D17: T | E17: Total | F17: 89987.43 | G17: 5633.68 | H17: 3143.05 | I17: 1669.5 | J17: 21061.5 | K17: 519.69 | L17: 0 | M17: 4558.83 | N17: 6480.54 | O17: 30680.68 | P17: 15386.96 | Q17: 847.96 | R17: 5.04 | S17: 0 | T17: 0 | U17: 0 | V17: 0 | W17: 0 | X17: 0 | Y17: 0 | Z17: 0
C18: OCCIDENTE | D18: Total | F18: 89987.43 | G18: 5633.68 | H18: 3143.05 | I18: 1669.5 | J18: 21061.5 | K18: 519.69 | L18: 0 | M18: 4558.83 | N18: 6480.54 | O18: 30680.68 | P18: 15386.96 | Q18: 847.96 | R18: 5.04 | S18: 0 | T18: 0 | U18: 0 | V18: 0 | W18: 0 | X18: 0 | Y18: 0 | Z18: 0
B19: Aplicacion nuevos x reversion | C19: Total | F19: 636047.07 | G19: 29223.59 | H19: 16458.47 | I19: 8660.22 | J19: 141425.47 | K19: 5825.54 | L19: 0 | M19: 51101.37 | N19: 51278.68 | O19: 242748.43 | P19: 79815.35 | Q19: 9504.83 | R19: 5.12 | S19: 0 | T19: 0 | U19: 0 | V19: 0 | W19: 0 | X19: 0 | Y19: 0 | Z19: 0
E20: Vlr Servicio | F20: 1.7732826e+10 | G20: 8.0811608e+08 | H20: 4.5018145e+08 | I20: 2.396397e+08 | J20: 4.7172894e+09 | K20: 1.5731653e+08 | L20: 9937432.2 | M20: 1.3814111e+09 | N20: 1.3028635e+09 | O20: 6.2103431e+09 | P20: 2.1989365e+09 | Q20: 2.5681561e+08 | R20: -24243.8 | S20: 0 | T20: 0 | U20: 0 | V20: 0 | W20: 0 | X20: 0 | Y20: 0 | Z20: 0
E21: Vlr Intereses | F21: 2121030.6 | G21: 114429.04 | H21: 59031.07 | I21: 30884.79 | J21: 467332.66 | K21: 20333.36 | L21: 491.86 | M21: 178752.52 | N21: 163509.31 | O21: 744605.58 | P21: 308414.05 | Q21: 33078.85 | R21: 18.46 | S21: 19.47 | T21: 236.47 | U21: 0 | V21: 0 | W21: 0 | X21: 0 | Y21: 0 | Z21: -106.9
D22: E | E22: Total | F22: 1.7734947e+10 | G22: 8.0823051e+08 | H22: 4.5024048e+08 | I22: 2.3967059e+08 | J22: 4.7177568e+09 | K22: 1.5733686e+08 | L22: 9937924.1 | M22: 1.3815898e+09 | N22: 1.303027e+09 | O22: 6.2110877e+09 | P22: 2.1992449e+09 | Q22: 2.5684868e+08 | R22: -24225.34 | S22: 19.47 | T22: 236.47 | U22: 0 | V22: 0 | W22: 0 | X22: 0 | Y22: 0 | Z22: -106.9
C23: ENEL | D23: Total | F23: 1.7734947e+10 | G23: 8.0823051e+08 | H23: 4.5024048e+08 | I23: 2.3967059e+08 | J23: 4.7177568e+09 | K23: 1.5733686e+08 | L23: 9937924.1 | M23: 1.3815898e+09 | N23: 1.303027e+09 | O23: 6.2110877e+09 | P23: 2.1992449e+09 | Q23: 2.5684868e+08 | R23: -24225.34 | S23: 19.47 | T23: 236.47 | U23: 0 | V23: 0 | W23: 0 | X23: 0 | Y23: 0 | Z23: -106.9
E24: Vlr Servicio | F24: 27812534 | G24: 3127682.6 | H24: 1787750.6 | I24: 994482.9 | J24: 3900132.4 | K24: 128394.64 | L24: 65261.43 | M24: 1108739.3 | N24: 1377785.4 | O24: 6585392.2 | P24: 8526230.1 | Q24: 210777.87 | R24: -95.43 | S24: 0 | T24: 0 | U24: 0 | V24: 0 | W24: 0 | X24: 0 | Y24: 0 | Z24: 0
E25: Vlr Intereses | F25: 52627 | G25: 3905.72 | H25: 2108.89 | I25: 1129.02 | J25: 9194.6 | K25: 397.89 | L25: 0 | M25: 3497.21 | N25: 3710.89 | O25: 17365.58 | P25: 10667.02 | Q25: 649.71 | R25: 0.42 | S25: -0.01 | T25: 0.06 | U25: 0 | V25: 0 | W25: 0 | X25: 0 | Y25: 0 | Z25: 0
D26: H | E26: Total | F26: 27865161 | G26: 3131588.3 | H26: 1789859.5 | I26: 995611.92 | J26: 3909327 | K26: 128792.53 | L26: 65261.43 | M26: 1112236.5 | N26: 1381496.3 | O26: 6602757.8 | P26: 8536897.1 | Q26: 211427.58 | R26: -95.01 | S26: -0.01 | T26: 0.06 | U26: 0 | V26: 0 | W26: 0 | X26: 0 | Y26: 0 | Z26: 0
E27: Vlr Servicio | F27: 38733807 | G27: 3039800.2 | H27: 1655044.1 | I27: 884056.68 | J27: 6291646.5 | K27: 298351.07 | L27: 43507.62 | M27: 2623588.8 | N27: 2661210.6 | O27: 12473941 | P27: 8276274 | Q27: 486783.55 | R27: -397.6 | S27: 0 | T27: 0 | U27: 0 | V27: 0 | W27: 0 | X27: 0 | Y27: 0 | Z27: 0
E28: Vlr Intereses | F28: 103423.02 | G28: 5231.83 | H28: 2620.78 | I28: 1432.53 | J28: 22089.08 | K28: 1012.15 | L28: 0 | M28: 8840.42 | N28: 8284.39 | O28: 37991.28 | P28: 14270.12 | Q28: 1651.75 | R28: -1.34 | S28: 0 | T28: 0.03 | U28: 0 | V28: 0 | W28: 0 | X28: 0 | Y28: 0 | Z28: 0
D29: O | E29: Total | F29: 38837230 | G29: 3045032.1 | H29: 1657664.9 | I29: 885489.21 | J29: 6313735.6 | K29: 299363.22 | L29: 43507.62 | M29: 2632429.2 | N29: 2669495 | O29: 12511933 | P29: 8290544.1 | Q29: 488435.3 | R29: -398.94 | S29: 0 | T29: 0.03 | U29: 0 | V29: 0 | W29: 0 | X29: 0 | Y29: 0 | Z29: 0
E30: Vlr Servicio | F30: 2.2289166e+08 | G30: 27345007 | H30: 15201201 | I30: 8089797.9 | J30: 28735246 | K30: 729515.15 | L30: 9878361.2 | M30: 6370953.3 | N30: 8839869.6 | O30: 41844064 | P30: 74669973 | Q30: 1190722.6 | R30: -3045.97 | S30: 0 | T30: 0 | U30: 0 | V30: 0 | W30: 0 | X30: 0 | Y30: 0 | Z30: 0
E31: Vlr Intereses | F31: 650065.1 | G31: 54025.13 | H31: 28815.72 | I31: 15452.4 | J31: 131416.37 | K31: 3462.06 | L31: 6638.64 | M31: 30369.24 | N31: 40871.66 | O31: 186410.2 | P31: 147007.48 | Q31: 5632.59 | R31: -36.4 | S31: 0.01 | T31: 0 | U31: 0 | V31: 0 | W31: 0 | X31: 0 | Y31: 0 | Z31: 0
D32: T | E32: Total | F32: 2.2354173e+08 | G32: 27399032 | H32: 15230017 | I32: 8105250.3 | J32: 28866662 | K32: 732977.21 | L32: 9884999.9 | M32: 6401322.6 | N32: 8880741.2 | O32: 42030474 | P32: 74816980 | Q32: 1196355.2 | R32: -3082.37 | S32: 0.01 | T32: 0 | U32: 0 | V32: 0 | W32: 0 | X32: 0 | Y32: 0 | Z32: 0
C33: OCCIDENTE | D33: Total | F33: 2.9024412e+08 | G33: 33575652 | H33: 18677541 | I33: 9986351.4 | J33: 39089725 | K33: 1161133 | L33: 9993768.9 | M33: 10145988 | N33: 12931733 | O33: 61145165 | P33: 91644422 | Q33: 1896218.1 | R33: -3576.32 | S33: 0 | T33: 0.09 | U33: 0 | V33: 0 | W33: 0 | X33: 0 | Y33: 0 | Z33: 0
B34: Mes | C34: Total | F34: 1.8025191e+10 | G34: 8.4180616e+08 | H34: 4.6891802e+08 | I34: 2.4965694e+08 | J34: 4.7568465e+09 | K34: 1.58498e+08 | L34: 19931693 | M34: 1.3917358e+09 | N34: 1.3159588e+09 | O34: 6.2722329e+09 | P34: 2.2908894e+09 | Q34: 2.587449e+08 | R34: -27801.66 | S34: 19.47 | T34: 236.56 | U34: 0 | V34: 0 | W34: 0 | X34: 0 | Y34: 0 | Z34: -106.9
A35: Componente | B35: Total | F35: 1.8025827e+10 | G35: 8.4183538e+08 | H35: 4.6893448e+08 | I35: 2.496656e+08 | J35: 4.7569879e+09 | K35: 1.5850382e+08 | L35: 19931693 | M35: 1391786912 | N35: 1.3160101e+09 | O35: 6.2724756e+09 | P35: 2.2909692e+09 | Q35: 2.5875441e+08 | R35: -27796.54 | S35: 19.47 | T35: 236.56 | U35: 0 | V35: 0 | W35: 0 | X35: 0 | Y35: 0 | Z35: -106.9
E36: Subsidio(-)/Contribucion(+) | F36: -32099.64 | G36: -1182.8 | H36: -661.02 | I36: -350.52 | J36: -6245.62 | K36: -344.7 | L36: 0 | M36: -3023.82 | N36: -2892.68 | O36: -13605.48 | P36: -3230.56 | Q36: -562.44 | R36: 0 | S36: 0 | T36: 0 | U36: 0 | V36: 0 | W36: 0 | X36: 0 | Y36: 0 | Z36: 0
D37: E | E37: Total | F37: -32099.64 | G37: -1182.8 | H37: -661.02 | I37: -350.52 | J37: -6245.62 | K37: -344.7 | L37: 0 | M37: -3023.82 | N37: -2892.68 | O37: -13605.48 | P37: -3230.56 | Q37: -562.44 | R37: 0 | S37: 0 | T37: 0 | U37: 0 | V37: 0 | W37: 0 | X37: 0 | Y37: 0 | Z37: 0
C38: ENEL | D38: Total | F38: -32099.64 | G38: -1182.8 | H38: -661.02 | I38: -350.52 | J38: -6245.62 | K38: -344.7 | L38: 0 | M38: -3023.82 | N38: -2892.68 | O38: -13605.48 | P38: -3230.56 | Q38: -562.44 | R38: 0 | S38: 0 | T38: 0 | U38: 0 | V38: 0 | W38: 0 | X38: 0 | Y38: 0 | Z38: 0
E39: Subsidio(-)/Contribucion(+) | F39: 44922.57 | G39: 2812.56 | H39: 1569.13 | I39: 833.5 | J39: 10514.48 | K39: 259.46 | L39: 0 | M39: 2275.96 | N39: 3235.33 | O39: 15317.02 | P39: 7681.79 | Q39: 423.34 | R39: 0 | S39: 0 | T39: 0 | U39: 0 | V39: 0 | W39: 0 | X39: 0 | Y39: 0 | Z39: 0
D40: T | E40: Total | F40: 44922.57 | G40: 2812.56 | H40: 1569.13 | I40: 833.5 | J40: 10514.48 | K40: 259.46 | L40: 0 | M40: 2275.96 | N40: 3235.33 | O40: 15317.02 | P40: 7681.79 | Q40: 423.34 | R40: 0 | S40: 0 | T40: 0 | U40: 0 | V40: 0 | W40: 0 | X40: 0 | Y40: 0 | Z40: 0
C41: OCCIDENTE | D41: Total | F41: 44922.57 | G41: 2812.56 | H41: 1569.13 | I41: 833.5 | J41: 10514.48 | K41: 259.46 | L41: 0 | M41: 2275.96 | N41: 3235.33 | O41: 15317.02 | P41: 7681.79 | Q41: 423.34 | R41: 0 | S41: 0 | T41: 0 | U41: 0 | V41: 0 | W41: 0 | X41: 0 | Y41: 0 | Z41: 0
B42: Aplicacion nuevos x reversion | C42: Total | F42: 12822.93 | G42: 1629.76 | H42: 908.11 | I42: 482.98 | J42: 4268.86 | K42: -85.24 | L42: 0 | M42: -747.86 | N42: 342.65 | O42: 1711.54 | P42: 4451.23 | Q42: -139.1 | R42: 0 | S42: 0 | T42: 0 | U42: 0 | V42: 0 | W42: 0 | X42: 0 | Y42: 0 | Z42: 0
E43: Subsidio(-)/Contribucion(+) | F43: -3.2536076e+09 | G43: -91345711 | H43: -50905404 | I43: -27078429 | J43: -9.643413e+08 | K43: -31681533 | L43: 0 | M43: -2.7807169e+08 | N43: -2.6199779e+08 | O43: -1.2502637e+09 | P43: -2.4623216e+08 | Q43: -51689935 | R43: 0 | S43: 0 | T43: 0 | U43: 0 | V43: 0 | W43: 0 | X43: 0 | Y43: 0 | Z43: 0
D44: E | E44: Total | F44: -3.2536076e+09 | G44: -91345711 | H44: -50905404 | I44: -27078429 | J44: -9.643413e+08 | K44: -31681533 | L44: 0 | M44: -2.7807169e+08 | N44: -2.6199779e+08 | O44: -1.2502637e+09 | P44: -2.4623216e+08 | Q44: -51689935 | R44: 0 | S44: 0 | T44: 0 | U44: 0 | V44: 0 | W44: 0 | X44: 0 | Y44: 0 | Z44: 0
C45: ENEL | D45: Total | F45: -3.2536076e+09 | G45: -91345711 | H45: -50905404 | I45: -27078429 | J45: -9.643413e+08 | K45: -31681533 | L45: 0 | M45: -2.7807169e+08 | N45: -2.6199779e+08 | O45: -1.2502637e+09 | P45: -2.4623216e+08 | Q45: -51689935 | R45: 0 | S45: 0 | T45: 0 | U45: 0 | V45: 0 | W45: 0 | X45: 0 | Y45: 0 | Z45: 0
E46: Subsidio(-)/Contribucion(+) | F46: 13423599 | G46: 2490552.8 | H46: 1387405.4 | I46: 737634.79 | J46: 631013.34 | K46: 16984.56 | L46: 0 | M46: 150899.5 | N46: 207661.14 | O46: 966790.95 | P46: 6806944.6 | Q46: 27712.01 | R46: 0 | S46: 0 | T46: 0 | U46: 0 | V46: 0 | W46: 0 | X46: 0 | Y46: 0 | Z46: 0
D47: H | E47: Total | F47: 13423599 | G47: 2490552.8 | H47: 1387405.4 | I47: 737634.79 | J47: 631013.34 | K47: 16984.56 | L47: 0 | M47: 150899.5 | N47: 207661.14 | O47: 966790.95 | P47: 6806944.6 | Q47: 27712.01 | R47: 0 | S47: 0 | T47: 0 | U47: 0 | V47: 0 | W47: 0 | X47: 0 | Y47: 0 | Z47: 0
E48: Subsidio(-)/Contribucion(+) | F48: -325150.37 | G48: 488590.2 | H48: 270618.04 | I48: 137804.15 | J48: -905950.9 | K48: -31107.48 | L48: 0 | M48: -273355.91 | N48: -212055.38 | O48: -1075614 | P48: 1326676.2 | Q48: -50755.33 | R48: 0 | S48: 0 | T48: 0 | U48: 0 | V48: 0 | W48: 0 | X48: 0 | Y48: 0 | Z48: 0
D49: O | E49: Total | F49: -325150.37 | G49: 488590.2 | H49: 270618.04 | I49: 137804.15 | J49: -905950.9 | K49: -31107.48 | L49: 0 | M49: -273355.91 | N49: -212055.38 | O49: -1075614 | P49: 1326676.2 | Q49: -50755.33 | R49: 0 | S49: 0 | T49: 0 | U49: 0 | V49: 0 | W49: 0 | X49: 0 | Y49: 0 | Z49: 0
E50: Subsidio(-)/Contribucion(+) | F50: 50273483 | G50: 8795896.6 | H50: 4922970.6 | I50: 2633606.2 | J50: 2971274.2 | K50: 89779.5 | L50: 0 | M50: 777804.41 | N50: 1027778.3 | O50: 4888775.7 | P50: 24019519 | Q50: 146078.4 | R50: 0 | S50: 0 | T50: 0 | U50: 0 | V50: 0 | W50: 0 | X50: 0 | Y50: 0 | Z50: 0
D51: T | E51: Total | F51: 50273483 | G51: 8795896.6 | H51: 4922970.6 | I51: 2633606.2 | J51: 2971274.2 | K51: 89779.5 | L51: 0 | M51: 777804.41 | N51: 1027778.3 | O51: 4888775.7 | P51: 24019519 | Q51: 146078.4 | R51: 0 | S51: 0 | T51: 0 | U51: 0 | V51: 0 | W51: 0 | X51: 0 | Y51: 0 | Z51: 0
C52: OCCIDENTE | D52: Total | F52: 63371932 | G52: 11775040 | H52: 6580994 | I52: 3509045.2 | J52: 2696336.7 | K52: 75656.58 | L52: 0 | M52: 655348 | N52: 1023384 | O52: 4779952.6 | P52: 32153140 | Q52: 123035.08 | R52: 0 | S52: 0 | T52: 0 | U52: 0 | V52: 0 | W52: 0 | X52: 0 | Y52: 0 | Z52: 0
B53: Mes | C53: Total | F53: -3.1902357e+09 | G53: -79570672 | H53: -44324410 | I53: -23569383 | J53: -9.6164497e+08 | K53: -31605876 | L53: 0 | M53: -2.7741635e+08 | N53: -2.6097441e+08 | O53: -1.2454837e+09 | P53: -2.1407902e+08 | Q53: -51566900 | R53: 0 | S53: 0 | T53: 0 | U53: 0 | V53: 0 | W53: 0 | X53: 0 | Y53: 0 | Z53: 0
A54: Subs/Cont | B54: Total | F54: -3.1902229e+09 | G54: -79569042 | H54: -44323502 | I54: -23568900 | J54: -9.616407e+08 | K54: -31605962 | L54: 0 | M54: -2.7741709e+08 | N54: -2.6097407e+08 | O54: -1.245482e+09 | P54: -2.1407457e+08 | Q54: -51567039 | R54: 0 | S54: 0 | T54: 0 | U54: 0 | V54: 0 | W54: 0 | X54: 0 | Y54: 0 | Z54: 0
A55: Total | F55: 1.4835603e+10 | G55: 7.6226622e+08 | H55: 4.2461093e+08 | I55: 2.2609668e+08 | J55: 3.7953468e+09 | K55: 1.2689784e+08 | L55: 19931693 | M55: 1.1143696e+09 | N55: 1.0550358e+09 | O55: 5.0269929e+09 | P55: 2.0768943e+09 | Q55: 2.0718733e+08 | R55: -27796.54 | S55: 19.47 | T55: 236.56 | U55: 0 | V55: 0 | W55: 0 | X55: 0 | Y55: 0 | Z55: -106.9
C58: TOTAL | D58: OPORTUNO | E58: Total | F58: =F34+F53+F9-L9-L34 -> 1.4815022e+10 | G58: =G34+G9 -> 8.4180604e+08 | H58: =H34+H9 -> 4.6891797e+08 | I58: =I34+I9 -> 2.4965692e+08 | J58: =J34+J9 -> 4.7568461e+09 | K58: =K34+K9 -> 1.5849797e+08 | L58: =L34+L9 -> 19931693 | M58: =M34+M9 -> 1.3917356e+09 | N58: =N34+N9 -> 1.3159586e+09 | ... AP58: =AP34+AP9 -> 0
E59: Subsidio(-)/Contribucion(+) | F59: =F53 -> -3.1902357e+09
D60: EXTEMPORANEO | E60: Total | F60: =F42+F19-L19 -> 648870 | G60: =G19 -> 29223.59 | H60: =H19 -> 16458.47 | I60: =I19 -> 8660.22 | J60: =J19 -> 141425.47 | K60: =K19 -> 5825.54 | L60: =L19 -> 0 | M60: =M19 -> 51101.37 | N60: =N19 -> 51278.68 | ... AP60: =AP19 -> 0
E61: Subsidio(-)/Contribucion(+) | F61: =F42 -> 12822.93
C63: RECIPROCIDAD | D63: OPORTUNO | E63: Total | F63: 0 | G63: 0 | H63: 0 | I63: 0 | J63: 0 | K63: 0 | L63: 0 | M63: 0 | N63: 0 | O63: 0 | P63: 0 | Q63: 0 | R63: 0 | S63: 0 | T63: 0 | U63: 0 | V63: 0 | W63: 0 | X63: 0 | Y63: 0 | Z63: 0 | AA63: 0 | AB63: 0 | AC63: 0 | AD63: 0 | AE63: 0 | AF63: 0 | AG63: 0 | AH63: 0 | AI63: 0 | AJ63: 0 | AK63: 0 | AL63: 0 | AM63: 0 | AN63: 0 | AO63: 0 | AP63: 0
E64: Subsidio(-)/Contribucion(+) | F64: 0
D65: EXTEMPORANEO | E65: Total | F65: 0 | G65: 0 | H65: 0 | I65: 0 | J65: 0 | K65: 0 | L65: 0 | M65: 0 | N65: 0 | O65: 0 | P65: 0 | Q65: 0 | R65: 0 | S65: 0 | T65: 0 | U65: 0 | V65: 0 | W65: 0 | X65: 0 | Y65: 0 | Z65: 0 | AA65: 0 | AB65: 0 | AC65: 0 | AD65: 0 | AE65: 0 | AF65: 0 | AG65: 0 | AH65: 0 | AI65: 0 | AJ65: 0 | AK65: 0 | AL65: 0 | AM65: 0 | AN65: 0 | AO65: 0 | AP65: 0
E66: Subsidio(-)/Contribucion(+) | F66: 0
C68: ENEL | D68: OPORTUNO | E68: Total | F68: =F45+F23+F8-L8-L23 -> 1.44714e+10 | G68: =G23+G8 -> 8.0823038e+08 | H68: =H23+H8 -> 4.5024043e+08 | I68: =I23+I8 -> 2.3967057e+08 | J68: =J23+J8 -> 4.7177564e+09 | K68: =K23+K8 -> 1.5733684e+08 | L68: =L23+L8 -> 9937924.1 | M68: =M23+M8 -> 1.3815896e+09 | N68: =N23+N8 -> 1.3030269e+09 | ... AP68: =AP23+AP8 -> 0
E69: Subsidio(-)/Contribucion(+) | F69: =F45 -> -3.2536076e+09
D70: EXTEMPORANEO | E70: Total | F70: =F38+F14-L14 -> 513960 | G70: =G14 -> 23589.91 | H70: =H14 -> 13315.42 | I70: =I14 -> 6990.72 | J70: =J14 -> 120363.97 | K70: =K14 -> 5305.85 | L70: =L14 -> 0 | M70: =M14 -> 46542.54 | N70: =N14 -> 44798.14 | ... AP70: =AP14 -> 0
E71: Subsidio(-)/Contribucion(+) | F71: =F38 -> -32099.64
C73: ENERBIT | D73: OPORTUNO | E73: Total | F73: 0 | G73: 0 | H73: 0 | I73: 0 | J73: 0 | K73: 0 | L73: 0 | M73: 0 | N73: 0 | O73: 0 | P73: 0 | Q73: 0 | R73: 0 | S73: 0 | T73: 0 | U73: 0 | V73: 0 | W73: 0 | X73: 0 | Y73: 0 | Z73: 0 | AA73: 0 | AB73: 0 | AC73: 0 | AD73: 0 | AE73: 0 | AF73: 0 | AG73: 0 | AH73: 0 | AI73: 0 | AJ73: 0 | AK73: 0 | AL73: 0 | AM73: 0 | AN73: 0 | AO73: 0
E74: Subsidio(-)/Contribucion(+) | F74: 0
D75: EXTEMPORANEO | E75: Total | F75: 0 | G75: 0 | H75: 0 | I75: 0 | J75: 0 | K75: 0 | L75: 0 | M75: 0 | N75: 0 | O75: 0 | P75: 0 | Q75: 0 | R75: 0 | S75: 0 | T75: 0 | U75: 0 | V75: 0 | W75: 0 | X75: 0 | Y75: 0 | Z75: 0 | AA75: 0 | AB75: 0 | AC75: 0 | AD75: 0 | AE75: 0 | AF75: 0 | AG75: 0 | AH75: 0 | AI75: 0 | AJ75: 0 | AK75: 0 | AL75: 0 | AM75: 0 | AN75: 0 | AO75: 0
E76: Subsidio(-)/Contribucion(+) | F76: 0
C78: OCCIDENTE | D78: OPORTUNO | E78: Total | F78: =F52+F33-L33 -> 3.4362228e+08 | G78: =G33 -> 33575652 | H78: =H33 -> 18677541 | I78: =I33 -> 9986351.4 | J78: =J33 -> 39089725 | K78: =K33 -> 1161133 | L78: =L33 -> 9993768.9 | M78: =M33 -> 10145988 | N78: =N33 -> 12931733 | ... AP78: =AP33 -> 0
E79: Subsidio(-)/Contribucion(+) | F79: =F52 -> 63371932
D80: EXTEMPORANEO | E80: Total | F80: =F41+F18-L18 -> 134910 | G80: =G18 -> 5633.68 | H80: =H18 -> 3143.05 | I80: =I18 -> 1669.5 | J80: =J18 -> 21061.5 | K80: =K18 -> 519.69 | L80: =L18 -> 0 | M80: =M18 -> 4558.83 | N80: =N18 -> 6480.54 | ... AP80: =AP18 -> 0
E81: Subsidio(-)/Contribucion(+) | F81: =F41 -> 44922.57
C83: CIUDAD LIMPIA-ACUEDUCTO | D83: OPORTUNO | E83: Total | F83: 0 | G83: 0 | H83: 0 | I83: 0 | J83: 0 | K83: 0 | L83: 0 | M83: 0 | N83: 0 | O83: 0 | P83: 0 | Q83: 0 | R83: 0 | S83: 0 | T83: 0 | U83: 0 | V83: 0 | W83: 0 | X83: 0 | Y83: 0 | Z83: 0 | AA83: 0 | AB83: 0 | AC83: 0 | AD83: 0 | AE83: 0 | AF83: 0 | AG83: 0 | AH83: 0 | AI83: 0 | AJ83: 0 | AK83: 0 | AL83: 0 | AM83: 0 | AN83: 0 | AO83: 0 | AP83: 0
E84: Subsidio(-)/Contribucion(+) | F84: 0
D85: EXTEMPORANEO | E85: Total | F85: 0 | G85: 0 | H85: 0 | I85: 0 | J85: 0 | K85: 0 | L85: 0 | M85: 0 | N85: 0 | O85: 0 | P85: 0 | Q85: 0 | R85: 0 | S85: 0 | T85: 0 | U85: 0 | V85: 0 | W85: 0 | X85: 0 | Y85: 0 | Z85: 0 | AA85: 0 | AB85: 0 | AC85: 0 | AD85: 0 | AE85: 0 | AF85: 0 | AG85: 0 | AH85: 0 | AI85: 0 | AJ85: 0 | AK85: 0 | AL85: 0 | AM85: 0 | AN85: 0 | AO85: 0 | AP85: 0
E86: Subsidio(-)/Contribucion(+) | F86: 0
D88: AFaseo | E88: Total | F88: =F10 -> -2015.07 | G88: =G10 -> -122.1 | H88: =H10 -> -51.87 | I88: =I10 -> -22.65 | J88: =J10 -> -369.44 | K88: =K10 -> -23.88 | L88: =L10 -> 0 | M88: =M10 -> -209.4 | ... AP88: =AP10 -> 0
B91: LIME
F92: Total | G92: Componente TDF | H92: Componente TTL | I92: Componente TVIAT | J92: Aprovechamiento | K92: CCSA Prest.Aprov. | L92: SERVICIO ESPECIALES | M92: Componente TCS | N92: Componente TLU | O92: Componente TBL | P92: Componente TRT | Q92: CCSA Prest. No Aprov. | R92: Ajuste Decena | S92: Ajuste Recargo Aseo | T92: Intereses Cte Financiac. Aseo | U92: Exonera-Recargo Aseo | V92: Exonera-Ajuste Decena Aseo | W92: Exonera-Recargo Aseo | X92: Exonera-Recargo Aseo | Y92: Intereses Cte Financiac. Aseo | Z92: Rec.Intereses
E93: Vlr Servicio | F93: -221284.53 | G93: -19000.06 | H93: -8071.66 | I93: -3524.84 | J93: -43884.29 | K93: -1875.37 | L93: 0 | M93: -16450.29 | N93: -20625.78 | O93: -69263.49 | P93: -35528.63 | Q93: -3060.12 | R93: 0 | S93: 0 | T93: 0 | U93: 0 | V93: 0 | W93: 0 | X93: 0 | Y93: 0 | Z93: 0
D94: E | E94: Total | F94: -221284.53 | G94: -19000.06 | H94: -8071.66 | I94: -3524.84 | J94: -43884.29 | K94: -1875.37 | L94: 0 | M94: -16450.29 | N94: -20625.78 | O94: -69263.49 | P94: -35528.63 | Q94: -3060.12 | R94: 0 | S94: 0 | T94: 0 | U94: 0 | V94: 0 | W94: 0 | X94: 0 | Y94: 0 | Z94: 0
C95: ENEL | D95: Total | F95: -221284.53 | G95: -19000.06 | H95: -8071.66 | I95: -3524.84 | J95: -43884.29 | K95: -1875.37 | L95: 0 | M95: -16450.29 | N95: -20625.78 | O95: -69263.49 | P95: -35528.63 | Q95: -3060.12 | R95: 0 | S95: 0 | T95: 0 | U95: 0 | V95: 0 | W95: 0 | X95: 0 | Y95: 0 | Z95: 0
E96: Vlr Servicio | F96: -22430.12 | G96: -1950.96 | H96: -828.84 | I96: -361.97 | J96: -4553.51 | K96: -187.61 | L96: 0 | M96: -1645.8 | N96: -2063.04 | O96: -6929.61 | P96: -3602.61 | Q96: -306.17 | R96: 0 | S96: 0 | T96: 0 | U96: 0 | V96: 0 | W96: 0 | X96: 0 | Y96: 0 | Z96: 0
D97: O | E97: Total | F97: -22430.12 | G97: -1950.96 | H97: -828.84 | I97: -361.97 | J97: -4553.51 | K97: -187.61 | L97: 0 | M97: -1645.8 | N97: -2063.04 | O97: -6929.61 | P97: -3602.61 | Q97: -306.17 | R97: 0 | S97: 0 | T97: 0 | U97: 0 | V97: 0 | W97: 0 | X97: 0 | Y97: 0 | Z97: 0
C98: OCCIDENTE | D98: Total | F98: -22430.12 | G98: -1950.96 | H98: -828.84 | I98: -361.97 | J98: -4553.51 | K98: -187.61 | L98: 0 | M98: -1645.8 | N98: -2063.04 | O98: -6929.61 | P98: -3602.61 | Q98: -306.17 | R98: 0 | S98: 0 | T98: 0 | U98: 0 | V98: 0 | W98: 0 | X98: 0 | Y98: 0 | Z98: 0
B99: Mes | C99: Total | F99: -243714.65 | G99: -20951.02 | H99: -8900.5 | I99: -3886.81 | J99: -48437.8 | K99: -2062.98 | L99: 0 | M99: -18096.09 | N99: -22688.82 | O99: -76193.1 | P99: -39131.24 | Q99: -3366.29 | R99: 0 | S99: 0 | T99: 0 | U99: 0 | V99: 0 | W99: 0 | X99: 0 | Y99: 0 | Z99: 0
A100: AFaseo | B100: Total | F100: -243714.65 | G100: -20951.02 | H100: -8900.5 | I100: -3886.81 | J100: -48437.8 | K100: -2062.98 | L100: 0 | M100: -18096.09 | N100: -22688.82 | O100: -76193.1 | P100: -39131.24 | Q100: -3366.29 | R100: 0 | S100: 0 | T100: 0 | U100: 0 | V100: 0 | W100: 0 | X100: 0 | Y100: 0 | Z100: 0
E101: Vlr Servicio | F101: 10824948 | G101: 599182.03 | H101: 337540.82 | I101: 180499.34 | J101: 2716624.4 | K101: 72704.94 | L101: 0 | M101: 637761.97 | N101: 850902.17 | O101: 4118632.1 | P101: 1191361.2 | Q101: 119849.06 | R101: -109.95 | S101: 0 | T101: 0 | U101: 0 | V101: 0 | W101: 0 | X101: 0 | Y101: 0 | Z101: 0
E102: Vlr Intereses | F102: 262991.94 | G102: 20187.32 | H102: 11399.94 | I102: 6057.06 | J102: 60641.69 | K102: 1509.5 | L102: 0 | M102: 13242.77 | N102: 18648.2 | O102: 88493.41 | P102: 40335.12 | Q102: 2478.59 | R102: -1.7 | S102: 0.04 | T102: 0 | U102: 0 | V102: 0 | W102: 0 | X102: 0 | Y102: 0 | Z102: 0
D103: E | E103: Total | F103: 11087940 | G103: 619369.35 | H103: 348940.76 | I103: 186556.4 | J103: 2777266.1 | K103: 74214.44 | L103: 0 | M103: 651004.74 | N103: 869550.37 | O103: 4207125.6 | P103: 1231696.3 | Q103: 122327.65 | R103: -111.65 | S103: 0.04 | T103: 0 | U103: 0 | V103: 0 | W103: 0 | X103: 0 | Y103: 0 | Z103: 0
C104: ENEL | D104: Total | F104: 11087940 | G104: 619369.35 | H104: 348940.76 | I104: 186556.4 | J104: 2777266.1 | K104: 74214.44 | L104: 0 | M104: 651004.74 | N104: 869550.37 | O104: 4207125.6 | P104: 1231696.3 | Q104: 122327.65 | R104: -111.65 | S104: 0.04 | T104: 0 | U104: 0 | V104: 0 | W104: 0 | X104: 0 | Y104: 0 | Z104: 0
E105: Vlr Servicio | F105: 21770 | G105: 1004.16 | H105: 566.95 | I105: 297.5 | J105: 6117.42 | K105: 195.92 | L105: 0 | M105: 1718.59 | N105: 1666.39 | O105: 7890.73 | P105: 1993.69 | Q105: 319.65 | R105: -1 | S105: 0 | T105: 0 | U105: 0 | V105: 0 | W105: 0 | X105: 0 | Y105: 0 | Z105: 0
D106: H | E106: Total | F106: 21770 | G106: 1004.16 | H106: 566.95 | I106: 297.5 | J106: 6117.42 | K106: 195.92 | L106: 0 | M106: 1718.59 | N106: 1666.39 | O106: 7890.73 | P106: 1993.69 | Q106: 319.65 | R106: -1 | S106: 0 | T106: 0 | U106: 0 | V106: 0 | W106: 0 | X106: 0 | Y106: 0 | Z106: 0
E107: Vlr Servicio | F107: 642782.27 | G107: 31379.48 | H107: 17705.74 | I107: 9385.95 | J107: 152267.08 | K107: 4852.15 | L107: 0 | M107: 42562.72 | N107: 54528.92 | O107: 260815.06 | P107: 61357.46 | Q107: 7916.7 | R107: 11.01 | S107: 0 | T107: 0 | U107: 0 | V107: 0 | W107: 0 | X107: 0 | Y107: 0 | Z107: 0
E108: Vlr Intereses | F108: 1590.27 | G108: 84.26 | H108: 47.65 | I108: 25.29 | J108: 415.91 | K108: 10.2 | L108: 0 | M108: 89.36 | N108: 128.29 | O108: 603.23 | P108: 169.46 | Q108: 16.61 | R108: 0.01 | S108: 0 | T108: 0 | U108: 0 | V108: 0 | W108: 0 | X108: 0 | Y108: 0 | Z108: 0
D109: O | E109: Total | F109: 644372.54 | G109: 31463.74 | H109: 17753.39 | I109: 9411.24 | J109: 152682.99 | K109: 4862.35 | L109: 0 | M109: 42652.08 | N109: 54657.21 | O109: 261418.29 | P109: 61526.92 | Q109: 7933.31 | R109: 11.02 | S109: 0 | T109: 0 | U109: 0 | V109: 0 | W109: 0 | X109: 0 | Y109: 0 | Z109: 0
C110: OCCIDENTE | D110: Total | F110: 666142.54 | G110: 32467.9 | H110: 18320.34 | I110: 9708.74 | J110: 158800.41 | K110: 5058.27 | L110: 0 | M110: 44370.67 | N110: 56323.6 | O110: 269309.02 | P110: 63520.61 | Q110: 8252.96 | R110: 10.02 | S110: 0 | T110: 0 | U110: 0 | V110: 0 | W110: 0 | X110: 0 | Y110: 0 | Z110: 0
B111: Aplicacion nuevos x reversion | C111: Total | F111: 11754083 | G111: 651837.25 | H111: 367261.1 | I111: 196265.14 | J111: 2936066.5 | K111: 79272.71 | L111: 0 | M111: 695375.41 | N111: 925873.97 | O111: 4476434.6 | P111: 1295216.9 | Q111: 130580.61 | R111: -101.63 | S111: 0.04 | T111: 0 | U111: 0 | V111: 0 | W111: 0 | X111: 0 | Y111: 0 | Z111: 0
E112: Vlr Servicio | F112: 1.366175e+10 | G112: 7.5583264e+08 | H112: 4.1909529e+08 | I112: 2.2251427e+08 | J112: 3.4498799e+09 | K112: 1.233423e+08 | L112: 6720394 | M112: 1.0814806e+09 | N112: 1.0289576e+09 | O112: 4.8927623e+09 | P112: 1.4798031e+09 | Q112: 2.0138122e+08 | R112: -19315.95 | S112: 0 | T112: 0 | U112: 0 | V112: 0 | W112: 0 | X112: 0 | Y112: 0 | Z112: 0
E113: Vlr Intereses | F113: 43503310 | G113: 5204775.2 | H113: 2452189.3 | I113: 1088195.4 | J113: 7935008.9 | K113: 278098.06 | L113: 1669.26 | M113: 2439581.4 | N113: 2815332.6 | O113: 10614690 | P113: 10213916 | Q113: 453845.12 | R113: 6057.83 | S113: -48.93 | T113: 0.4 | U113: 0 | V113: 0 | W113: 0 | X113: 0 | Y113: 0 | Z113: -0.4
...

Sheet Rem. Anticipos R2
B1: PROMOAMBIENTAL
E2: Total | F2: Componente TDF | G2: Componente TTL | H2: Componente TVIAT | I2: Aprovechamiento | J2: CCSA Prest.Aprov. | K2: Especiales | L2: Componente TCS | M2: Componente TLU | N2: Componente TBL | O2: Componente TRT | P2: CCSA Prest. No Aprov. | Q2: Deb/Cred | R2: Deb/Cred-otros
D3: Vlr Servicio | E3: 28276858 | F3: 1878439.3 | G3: 985949.48 | H3: 400118.84 | I3: 6330266.9 | J3: 223633.39 | K3: 0 | L3: 2828219.3 | M3: 1761600.2 | N3: 8194935.5 | O3: 5327754.2 | P3: 345780.7 | Q3: 159.95 | R3: 0
D4: Vlr Intereses | E4: 4361.05 | F4: 174.89 | G4: 94.31 | H4: 51.05 | I4: 867.88 | J4: 42.71 | K4: 0 | L4: 386.27 | M4: 363.74 | N4: 1826.85 | O4: 483.6 | P4: 69.65 | Q4: 0.1 | R4: 0
C5: E | D5: Total | E5: 28281219 | F5: 1878614.2 | G5: 986043.79 | H5: 400169.89 | I5: 6331134.8 | J5: 223676.1 | K5: 0 | L5: 2828605.6 | M5: 1761964 | N5: 8196762.3 | O5: 5328237.8 | P5: 345850.35 | Q5: 160.05 | R5: 0
B6: ENEL | C6: Total | E6: 28281219 | F6: 1878614.2 | G6: 986043.79 | H6: 400169.89 | I6: 6331134.8 | J6: 223676.1 | K6: 0 | L6: 2828605.6 | M6: 1761964 | N6: 8196762.3 | O6: 5328237.8 | P6: 345850.35 | Q6: 160.05 | R6: 0
D7: Vlr Servicio | E7: 603814.81 | F7: 22956.62 | G7: 13137.59 | H7: 7524.92 | I7: 152984.36 | J7: 6128.32 | K7: 0 | L7: 63509.52 | M7: 47408.1 | N7: 220781.98 | O7: 58741.12 | P7: 10623.64 | Q7: 18.64 | R7: 0
D8: Vlr Intereses | E8: 360.62 | F8: 3.45 | G8: 1.78 | H8: 0.98 | I8: 52.98 | J8: 5.18 | K8: 0 | L8: 45.52 | M8: 41 | N8: 191.87 | O8: 9.4 | P8: 8.46 | Q8: 0 | R8: 0
C9: H | D9: Total | E9: 604175.43 | F9: 22960.07 | G9: 13139.37 | H9: 7525.9 | I9: 153037.34 | J9: 6133.5 | K9: 0 | L9: 63555.04 | M9: 47449.1 | N9: 220973.85 | O9: 58750.52 | P9: 10632.1 | Q9: 18.64 | R9: 0
D10: Vlr Servicio | E10: 448565.61 | F10: 11179.62 | G10: 6229.22 | H10: 3290.21 | I10: 128320.56 | J10: 16086.84 | K10: 0 | L10: 61274.39 | M10: 33671.14 | N10: 131140.71 | O10: 34633.76 | P10: 22652.26 | Q10: 86.9 | R10: 0
D11: Vlr Intereses | E11: 11.93 | F11: 0.08 | G11: 0.04 | H11: 0.02 | I11: -0.02 | J11: 0.2 | K11: 0 | L11: 1.72 | M11: 1.64 | N11: 7.71 | O11: 0.22 | P11: 0.32 | Q11: 0 | R11: 0
C12: O | D12: Total | E12: 448577.54 | F12: 11179.7 | G12: 6229.26 | H12: 3290.23 | I12: 128320.54 | J12: 16087.04 | K12: 0 | L12: 61276.11 | M12: 33672.78 | N12: 131148.42 | O12: 34633.98 | P12: 22652.58 | Q12: 86.9 | R12: 0
D13: Vlr Servicio | E13: 1942713.6 | F13: 100160.14 | G13: 100233.78 | H13: 28448.06 | I13: 472285.73 | J13: 14554.76 | K13: 0 | L13: 137745.27 | M13: 129582.14 | N13: 604849.23 | O13: 331094.18 | P13: 23746.96 | Q13: 13.38 | R13: 0
D14: Vlr Intereses | E14: 57.05 | F14: 3.33 | G14: 1.86 | H14: 0.99 | I14: 12.38 | J14: 0.53 | K14: 0 | L14: 4.57 | M14: 4.38 | N14: 19.07 | O14: 9.09 | P14: 0.85 | Q14: 0 | R14: 0
C15: T | D15: Total | E15: 1942770.7 | F15: 100163.47 | G15: 100235.64 | H15: 28449.05 | I15: 472298.11 | J15: 14555.29 | K15: 0 | L15: 137749.84 | M15: 129586.52 | N15: 604868.3 | O15: 331103.27 | P15: 23747.81 | Q15: 13.38 | R15: 0
B16: OCCIDENTE | C16: Total | E16: 2995523.6 | F16: 134303.24 | G16: 119604.27 | H16: 39265.18 | I16: 753655.99 | J16: 36775.83 | K16: 0 | L16: 262580.99 | M16: 210708.4 | N16: 956990.57 | O16: 424487.77 | P16: 57032.49 | Q16: 118.92 | R16: 0
A17: Componente | B17: Total | E17: 31276742 | F17: 2012917.5 | G17: 1105648.1 | H17: 439435.07 | I17: 7084790.8 | J17: 260451.93 | K17: 0 | L17: 3091186.5 | M17: 1972672.4 | N17: 9153752.9 | O17: 5752725.5 | P17: 402882.84 | Q17: 278.97 | R17: 0
D18: Subsidio(-)/Contribucion(+) | E18: -1549869.4 | F18: 185823.17 | G18: 103275.64 | H18: 53808.19 | I18: -1128778.2 | J18: -31133.11 | K18: 0 | L18: -258857.59 | M18: -225710.03 | N18: -698982.91 | O18: 501335.93 | P18: -50650.46 | Q18: 0 | R18: 0
C19: E | D19: Total | E19: -1549869.4 | F19: 185823.17 | G19: 103275.64 | H19: 53808.19 | I19: -1128778.2 | J19: -31133.11 | K19: 0 | L19: -258857.59 | M19: -225710.03 | N19: -698982.91 | O19: 501335.93 | P19: -50650.46 | Q19: 0 | R19: 0
B20: ENEL | C20: Total | E20: -1549869.4 | F20: 185823.17 | G20: 103275.64 | H20: 53808.19 | I20: -1128778.2 | J20: -31133.11 | K20: 0 | L20: -258857.59 | M20: -225710.03 | N20: -698982.91 | O20: 501335.93 | P20: -50650.46 | Q20: 0 | R20: 0
D21: Subsidio(-)/Contribucion(+) | E21: 111513.88 | F21: 6336.61 | G21: 2760.73 | H21: 1928.26 | I21: 26391.68 | J21: 1378.86 | K21: 0 | L21: 10415.46 | M21: 9797.65 | N21: 32948.04 | O21: 17306.89 | P21: 2249.7 | Q21: 0 | R21: 0
C22: H | D22: Total | E22: 111513.88 | F22: 6336.61 | G22: 2760.73 | H22: 1928.26 | I22: 26391.68 | J22: 1378.86 | K22: 0 | L22: 10415.46 | M22: 9797.65 | N22: 32948.04 | O22: 17306.89 | P22: 2249.7 | Q22: 0 | R22: 0
D23: Subsidio(-)/Contribucion(+) | E23: 95516.58 | F23: 4186.32 | G23: 2332.6 | H23: 1240.6 | I23: 21396.66 | J23: 900.1 | K23: 0 | L23: 7895.59 | M23: 5846.99 | N23: 38815.29 | O23: 11433.88 | P23: 1468.55 | Q23: 0 | R23: 0
C24: O | D24: Total | E24: 95516.58 | F24: 4186.32 | G24: 2332.6 | H24: 1240.6 | I24: 21396.66 | J24: 900.1 | K24: 0 | L24: 7895.59 | M24: 5846.99 | N24: 38815.29 | O24: 11433.88 | P24: 1468.55 | Q24: 0 | R24: 0
D25: Subsidio(-)/Contribucion(+) | E25: 654167.52 | F25: 41222.62 | G25: 22968.96 | H25: 12216.06 | I25: 166867.65 | J25: 4462.16 | K25: 0 | L25: 47541.46 | M25: 44721.58 | N25: 194297.55 | O25: 112589.19 | P25: 7280.29 | Q25: 0 | R25: 0
C26: T | D26: Total | E26: 654167.52 | F26: 41222.62 | G26: 22968.96 | H26: 12216.06 | I26: 166867.65 | J26: 4462.16 | K26: 0 | L26: 47541.46 | M26: 44721.58 | N26: 194297.55 | O26: 112589.19 | P26: 7280.29 | Q26: 0 | R26: 0
B27: OCCIDENTE | C27: Total | E27: 861197.98 | F27: 51745.55 | G27: 28062.29 | H27: 15384.92 | I27: 214655.99 | J27: 6741.12 | K27: 0 | L27: 65852.51 | M27: 60366.22 | N27: 266060.88 | O27: 141329.96 | P27: 10998.54 | Q27: 0 | R27: 0
A28: Subs/Cont | B28: Total | E28: -688671.4 | F28: 237568.72 | G28: 131337.93 | H28: 69193.11 | I28: -914122.22 | J28: -24391.99 | K28: 0 | L28: -193005.08 | M28: -165343.81 | N28: -432922.03 | O28: 642665.89 | P28: -39651.92 | Q28: 0 | R28: 0
A29: Total | E29: 30588071 | F29: 2250486.2 | G29: 1236986 | H29: 508628.18 | I29: 6170668.5 | J29: 236059.94 | K29: 0 | L29: 2898181.5 | M29: 1807328.6 | N29: 8720830.8 | O29: 6395391.4 | P29: 363230.92 | Q29: 278.97 | R29: 0
B43: TOTAL | C43: OPORTUNO | D43: Total | E43: =E17+E28-K17 -> 30588071 | F43: =F17 -> 2012917.5 | G43: =G17 -> 1105648.1 | H43: =H17 -> 439435.07 | I43: =I17 -> 7084790.8 | J43: =J17 -> 260451.93 | K43: =K17 -> 0 | L43: =L17 -> 3091186.5 | M43: =M17 -> 1972672.4 | ... S43: =S17 -> 0
D44: Subsidio(-)/Contribucion(+) | E44: =E28 -> -688671.4
B46: RECIPROCIDAD | C46: OPORTUNO | D46: Total | E46: 0 | F46: 0 | G46: 0 | H46: 0 | I46: 0 | J46: 0 | K46: 0 | L46: 0 | M46: 0 | N46: 0 | O46: 0 | P46: 0 | Q46: 0 | R46: 0 | S46: 0
D47: Subsidio(-)/Contribucion(+) | E47: 0
B49: ENEL | C49: OPORTUNO | D49: Total | E49: =E20+E6-K6 -> 26731349 | F49: =F6 -> 1878614.2 | G49: =G6 -> 986043.79 | H49: =H6 -> 400169.89 | I49: =I6 -> 6331134.8 | J49: =J6 -> 223676.1 | K49: =K6 -> 0 | L49: =L6 -> 2828605.6 | M49: =M6 -> 1761964 | ... S49: =S6 -> 0
D50: Subsidio(-)/Contribucion(+) | E50: =E20 -> -1549869.4
B52: ENERBIT | C52: OPORTUNO | D52: Total | E52: 0 | F52: 0 | G52: 0 | H52: 0 | I52: 0 | J52: 0 | K52: 0 | L52: 0 | M52: 0 | N52: 0 | O52: 0 | P52: 0 | Q52: 0 | R52: 0
D53: Subsidio(-)/Contribucion(+) | E53: 0
B55: OCCIDENTE | C55: OPORTUNO | D55: Total | E55: =E16+E27-K16 -> 3856721.6 | F55: =F16 -> 134303.24 | G55: =G16 -> 119604.27 | H55: =H16 -> 39265.18 | I55: =I16 -> 753655.99 | J55: =J16 -> 36775.83 | K55: =K16 -> 0 | L55: =L16 -> 262580.99 | M55: =M16 -> 210708.4 | ... S55: =S16 -> 0
D56: Subsidio(-)/Contribucion(+) | E56: =E27 -> 861197.98
B58: CIUDAD LIMPIA-ACUEDUCTO | C58: OPORTUNO | D58: Total | E58: 0 | F58: 0 | G58: 0 | H58: 0 | I58: 0 | J58: 0 | K58: 0 | L58: 0 | M58: 0 | N58: 0 | O58: 0 | P58: 0 | Q58: 0 | R58: 0 | S58: 0
D59: Subsidio(-)/Contribucion(+) | E59: 0
B61: LIME
E62: Total | F62: Componente TDF | G62: Componente TTL | H62: Componente TVIAT | I62: Aprovechamiento | J62: CCSA Prest.Aprov. | K62: Especiales | L62: Componente TCS | M62: Componente TLU | N62: Componente TBL | O62: Componente TRT | P62: CCSA Prest. No Aprov. | Q62: Deb/Cred | R62: Deb/Cred-otros
D63: Vlr Servicio | E63: 149137.87 | F63: 6262.05 | G63: 3551.29 | H63: 0 | I63: 31553.16 | J63: 1136.09 | K63: 0 | L63: 30987.04 | M63: 43686.95 | N63: 12652.17 | O63: 19303.95 | P63: 0 | Q63: 5.17 | R63: 0
C64: A | D64: Total | E64: 149137.87 | F64: 6262.05 | G64: 3551.29 | H64: 0 | I64: 31553.16 | J64: 1136.09 | K64: 0 | L64: 30987.04 | M64: 43686.95 | N64: 12652.17 | O64: 19303.95 | P64: 0 | Q64: 5.17 | R64: 0
B65: EAB | C65: Total | E65: 149137.87 | F65: 6262.05 | G65: 3551.29 | H65: 0 | I65: 31553.16 | J65: 1136.09 | K65: 0 | L65: 30987.04 | M65: 43686.95 | N65: 12652.17 | O65: 19303.95 | P65: 0 | Q65: 5.17 | R65: 0
D66: Vlr Servicio | E66: 58158652 | F66: 3176259.8 | G66: 1891584.6 | H66: 682200.73 | I66: 15161402 | J66: 514726.63 | K66: 70736.95 | L66: 5862596.7 | M66: 4133779.9 | N66: 18400815 | O66: 7460194.3 | P66: 804325.61 | Q66: 30.25 | R66: 0
D67: Vlr Intereses | E67: 385390.29 | F67: 21101.33 | G67: 9688.81 | H67: 4482.7 | I67: 57677.97 | J67: 2085.3 | K67: 0 | L67: 34177.52 | M67: 40098.93 | N67: 135112.39 | O67: 77560.57 | P67: 3403.62 | Q67: 1.15 | R67: 0
C68: E | D68: Total | E68: 58544042 | F68: 3197361.1 | G68: 1901273.4 | H68: 686683.43 | I68: 15219080 | J68: 516811.93 | K68: 70736.95 | L68: 5896774.2 | M68: 4173878.9 | N68: 18535927 | O68: 7537754.9 | P68: 807729.23 | Q68: 31.4 | R68: 0
B69: ENEL | C69: Total | E69: 58544042 | F69: 3197361.1 | G69: 1901273.4 | H69: 686683.43 | I69: 15219080 | J69: 516811.93 | K69: 70736.95 | L69: 5896774.2 | M69: 4173878.9 | N69: 18535927 | O69: 7537754.9 | P69: 807729.23 | Q69: 31.4 | R69: 0
D70: Vlr Servicio | E70: 5353012.8 | F70: 340456.01 | G70: 194172.73 | H70: 77889.51 | I70: 1783061.1 | J70: 63585.54 | K70: 0 | L70: 379727.63 | M70: 340061.86 | N70: 1429241.9 | O70: 683113.4 | P70: 61690.18 | Q70: 12.99 | R70: 0
D71: Vlr Intereses | E71: 1967.83 | F71: 178.78 | G71: 85.67 | H71: 47.84 | I71: 440.91 | J71: 11.11 | K71: 0 | L71: 97.53 | M71: 129.83 | N71: 604.01 | O71: 354.04 | P71: 18.15 | Q71: -0.04 | R71: 0
C72: 1 | D72: Total | E72: 5354980.7 | F72: 340634.79 | G72: 194258.4 | H72: 77937.35 | I72: 1783502 | J72: 63596.65 | K72: 0 | L72: 379825.16 | M72: 340191.69 | N72: 1429845.9 | O72: 683467.44 | P72: 61708.33 | Q72: 12.95 | R72: 0
D73: Vlr Servicio | E73: 773856.37 | F73: 51813.78 | G73: 29065.98 | H73: 10104.92 | I73: 223027.82 | J73: 7933.34 | K73: 0 | L73: 69590.33 | M73: 64152.35 | N73: 206149.26 | O73: 103917.73 | P73: 8098.42 | Q73: 2.44 | R73: 0
C74: 2 | D74: Total | E74: 773856.37 | F74: 51813.78 | G74: 29065.98 | H74: 10104.92 | I74: 223027.82 | J74: 7933.34 | K74: 0 | L74: 69590.33 | M74: 64152.35 | N74: 206149.26 | O74: 103917.73 | P74: 8098.42 | Q74: 2.44 | R74: 0
D75: Vlr Servicio | E75: 289572.07 | F75: 18539.08 | G75: 11360.38 | H75: 3449.63 | I75: 113245.66 | J75: 4170.57 | K75: 0 | L75: 31600.95 | M75: 19396.93 | N75: 48037.65 | O75: 36985.94 | P75: 2780.38 | Q75: 4.9 | R75: 0
C76: 3 | D76: Total | E76: 289572.07 | F76: 18539.08 | G76: 11360.38 | H76: 3449.63 | I76: 113245.66 | J76: 4170.57 | K76: 0 | L76: 31600.95 | M76: 19396.93 | N76: 48037.65 | O76: 36985.94 | P76: 2780.38 | Q76: 4.9 | R76: 0
D77: Vlr Servicio | E77: 9596139 | F77: 553444.49 | G77: 295604.04 | H77: 101351.24 | I77: 2769928 | J77: 100606.56 | K77: 0 | L77: 869067.7 | M77: 740751.48 | N77: 2887339.7 | O77: 1133019.1 | P77: 145054.46 | Q77: -27.76 | R77: 0
D78: Vlr Intereses | E78: 528.8 | F78: 36.99 | G78: 20 | H78: 11.08 | I78: 128.15 | J78: 3.77 | K78: 0 | L78: 33.14 | M78: 38.2 | N78: 175.77 | O78: 75.52 | P78: 6.17 | Q78: 0.01 | R78: 0
C79: 5 | D79: Total | E79: 9596667.8 | F79: 553481.48 | G79: 295624.04 | H79: 101362.32 | I79: 2770056.2 | J79: 100610.33 | K79: 0 | L79: 869100.84 | M79: 740789.68 | N79: 2887515.4 | O79: 1133094.6 | P79: 145060.63 | Q79: -27.75 | R79: 0
B80: NUEVO ESQUEMA | C80: Total | E80: 16015077 | F80: 964469.13 | G80: 530308.8 | H80: 192854.22 | I80: 4889831.7 | J80: 176310.89 | K80: 0 | L80: 1350117.3 | M80: 1164530.6 | N80: 4571548.3 | O80: 1957465.7 | P80: 217647.76 | Q80: -7.46 | R80: 0
D81: Vlr Servicio | E81: 2796487 | F81: 192507.26 | G81: 101676.69 | H81: 44197.98 | I81: 751979.34 | J81: 24819.19 | K81: 0 | L81: 277866.97 | M81: 205710.84 | N81: 763438.13 | O81: 397204.16 | P81: 37108.43 | Q81: -21.95 | R81: 0
D82: Vlr Intereses | E82: 1845.08 | F82: 98.21 | G82: 55.4 | H82: 29.08 | I82: 501.84 | J82: 14.19 | K82: 0 | L82: 124.57 | M82: 152.24 | N82: 651.36 | O82: 195 | P82: 23.19 | Q82: 0 | R82: 0
C83: H | D83: Total | E83: 2798332.1 | F83: 192605.47 | G83: 101732.09 | H83: 44227.06 | I83: 752481.18 | J83: 24833.38 | K83: 0 | L83: 277991.54 | M83: 205863.08 | N83: 764089.49 | O83: 397399.16 | P83: 37131.62 | Q83: -21.95 | R83: 0
D84: Vlr Servicio | E84: 30547301 | F84: 3139010.2 | G84: 1762045.2 | H84: 886537.48 | I84: 5764443.6 | J84: 224728.7 | K84: 0 | L84: 2040522.4 | M84: 1872333.1 | N84: 8013600.8 | O84: 6529298.3 | P84: 314727.38 | Q84: 0 | R84: 54
D85: Vlr Intereses | E85: 7189025.5 | F85: 39323.91 | G85: 19195.48 | H85: 10242.02 | I85: 79611.71 | J85: 2728.86 | K85: 0 | L85: 23956.4 | M85: 28179.49 | N85: 139371.52 | O85: 82663.24 | P85: 4458.01 | Q85: 0 | R85: 6759294.8
C86: O | D86: Total | E86: 37736327 | F86: 3178334.1 | G86: 1781240.7 | H86: 896779.5 | I86: 5844055.3 | J86: 227457.56 | K86: 0 | L86: 2064478.8 | M86: 1900512.6 | N86: 8152972.3 | O86: 6611961.5 | P86: 319185.39 | Q86: 0 | R86: 6759348.8
D87: Vlr Servicio | E87: 1167477.6 | F87: 85368.47 | G87: 46259.88 | H87: 25458.06 | I87: 302710.16 | J87: 9905.46 | K87: 0 | L87: 84512.69 | M87: 75027.44 | N87: 350733.41 | O87: 173213.68 | P87: 14272.58 | Q87: 15.8 | R87: 0
D88: Vlr Intereses | E88: 27.23 | F88: 1.43 | G88: 0.8 | H88: 0.42 | I88: 7.09 | J88: 0.24 | K88: 0 | L88: 2.13 | M88: 2.09 | N88: 9.79 | O88: 2.84 | P88: 0.4 | Q88: 0 | R88: 0
C89: T | D89: Total | E89: 1167504.9 | F89: 85369.9 | G89: 46260.68 | H89: 25458.48 | I89: 302717.25 | J89: 9905.7 | K89: 0 | L89: 84514.82 | M89: 75029.53 | N89: 350743.2 | O89: 173216.52 | P89: 14272.98 | Q89: 15.8 | R89: 0
B90: OCCIDENTE | C90: Total | E90: 41702164 | F90: 3456309.4 | G90: 1929233.5 | H90: 966465.04 | I90: 6899253.8 | J90: 262196.64 | K90: 0 | L90: 2426985.1 | M90: 2181405.2 | N90: 9267805 | O90: 7182577.2 | P90: 370589.99 | Q90: -6.15 | R90: 6759348.8
A91: Componente | B91: Total | E91: 1.1641042e+08 | F91: 7624401.8 | G91: 4364367 | H91: 1846002.7 | I91: 27039718 | J91: 956455.55 | K91: 70736.95 | L91: 9704863.7 | M91: 7563501.6 | N91: 32387932 | O91: 16697102 | P91: 1395967 | Q91: 22.96 | R91: 6759348.8
D92: Subsidio(-)/Contribucion(+) | E92: -18613.87 | F92: -939.31 | G92: -532.71 | H92: -288.84 | I92: -4732.97 | J92: -170.42 | K92: 0 | L92: -1494.85 | M92: -1473.42 | N92: -6810.55 | O92: -1892.76 | P92: -278.04 | Q92: 0 | R92: 0
C93: A | D93: Total | E93: -18613.87 | F93: -939.31 | G93: -532.71 | H93: -288.84 | I93: -4732.97 | J93: -170.42 | K93: 0 | L93: -1494.85 | M93: -1473.42 | N93: -6810.55 | O93: -1892.76 | P93: -278.04 | Q93: 0 | R93: 0
B94: EAB | C94: Total | E94: -18613.87 | F94: -939.31 | G94: -532.71 | H94: -288.84 | I94: -4732.97 | J94: -170.42 | K94: 0 | L94: -1494.85 | M94: -1473.42 | N94: -6810.55 | O94: -1892.76 | P94: -278.04 | Q94: 0 | R94: 0
D95: Subsidio(-)/Contribucion(+) | E95: -19130404 | F95: -759669.49 | G95: -416915.67 | H95: -207487.55 | I95: -5142228.2 | J95: -191605.67 | K95: 0 | L95: -1646829.4 | M95: -1557842.2 | N95: -7394669.4 | O95: -1508038.6 | P95: -305117.55 | Q95: 0 | R95: 0
C96: E | D96: Total | E96: -19130404 | F96: -759669.49 | G96: -416915.67 | H96: -207487.55 | I96: -5142228.2 | J96: -191605.67 | K96: 0 | L96: -1646829.4 | M96: -1557842.2 | N96: -7394669.4 | O96: -1508038.6 | P96: -305117.55 | Q96: 0 | R96: 0
B97: ENEL | C97: Total | E97: -19130404 | F97: -759669.49 | G97: -416915.67 | H97: -207487.55 | I97: -5142228.2 | J97: -191605.67 | K97: 0 | L97: -1646829.4 | M97: -1557842.2 | N97: -7394669.4 | O97: -1508038.6 | P97: -305117.55 | Q97: 0 | R97: 0
D98: Subsidio(-)/Contribucion(+) | E98: -1194830.5 | F98: -44596.94 | G98: -24853.5 | H98: -11298.95 | I98: -327899.39 | J98: -11609.2 | K98: 0 | L98: -106444.02 | M98: -101959.31 | N98: -459380.09 | O98: -88967.03 | P98: -17822.07 | Q98: 0 | R98: 0
C99: 1 | D99: Total | E99: -1194830.5 | F99: -44596.94 | G99: -24853.5 | H99: -11298.95 | I99: -327899.39 | J99: -11609.2 | K99: 0 | L99: -106444.02 | M99: -101959.31 | N99: -459380.09 | O99: -88967.03 | P99: -17822.07 | Q99: 0 | R99: 0
D100: Subsidio(-)/Contribucion(+) | E100: -63316.89 | F100: 860.74 | G100: 438.02 | H100: 220.87 | I100: -20838.06 | J100: -767.73 | K100: 0 | L100: -6733.95 | M100: -6648.55 | N100: -30073.81 | O100: 1478.08 | P100: -1252.5 | Q100: 0 | R100: 0
C101: 2 | D101: Total | E101: -63316.89 | F101: 860.74 | G101: 438.02 | H101: 220.87 | I101: -20838.06 | J101: -767.73 | K101: 0 | L101: -6733.95 | M101: -6648.55 | N101: -30073.81 | O101: 1478.08 | P101: -1252.5 | Q101: 0 | R101: 0
D102: Subsidio(-)/Contribucion(+) | E102: -133645.28 | F102: -6414.59 | G102: -3598.02 | H102: -1927.38 | I102: -34645.42 | J102: -1248.07 | K102: 0 | L102: -10947.77 | M102: -10522.53 | N102: -49498.34 | O102: -12806.89 | P102: -2036.27 | Q102: 0 | R102: 0
C103: 3 | D103: Total | E103: -133645.28 | F103: -6414.59 | G103: -3598.02 | H103: -1927.38 | I103: -34645.42 | J103: -1248.07 | K103: 0 | L103: -10947.77 | M103: -10522.53 | N103: -49498.34 | O103: -12806.89 | P103: -2036.27 | Q103: 0 | R103: 0
D104: Subsidio(-)/Contribucion(+) | E104: -2991427 | F104: -127467.28 | G104: -70646.61 | H104: -36323.06 | I104: -803772.72 | J104: -29335.93 | K104: 0 | L104: -252466.93 | M104: -236368.74 | N104: -1130006.7 | O104: -257176.04 | P104: -47862.97 | Q104: 0 | R104: 0
C105: 5 | D105: Total | E105: -2991427 | F105: -127467.28 | G105: -70646.61 | H105: -36323.06 | I105: -803772.72 | J105: -29335.93 | K105: 0 | L105: -252466.93 | M105: -236368.74 | N105: -1130006.7 | O105: -257176.04 | P105: -47862.97 | Q105: 0 | R105: 0
B106: NUEVO ESQUEMA | C106: Total | E106: -4383219.7 | F106: -177618.07 | G106: -98660.11 | H106: -49328.52 | I106: -1187155.6 | J106: -42960.93 | K106: 0 | L106: -376592.67 | M106: -355499.13 | N106: -1668958.9 | O106: -357471.88 | P106: -68973.81 | Q106: 0 | R106: 0
D107: Subsidio(-)/Contribucion(+) | E107: -514526.65 | F107: -8131.89 | G107: -4889.84 | H107: -2387.76 | I107: -141534.36 | J107: -6055.97 | K107: 0 | L107: -51721.56 | M107: -48223.47 | N107: -230340.95 | O107: -11478.08 | P107: -9762.77 | Q107: 0 | R107: 0
C108: H | D108: Total | E108: -514526.65 | F108: -8131.89 | G108: -4889.84 | H108: -2387.76 | I108: -141534.36 | J108: -6055.97 | K108: 0 | L108: -51721.56 | M108: -48223.47 | N108: -230340.95 | O108: -11478.08 | P108: -9762.77 | Q108: 0 | R108: 0
D109: Subsidio(-)/Contribucion(+) | E109: 3162669.2 | F109: 1558830.7 | G109: 869728.56 | H109: 458243.59 | I109: -775600.27 | J109: -32196.27 | K109: 0 | L109: -279610.34 | M109: -247708.66 | N109: -1433428.4 | O109: 3097340.6 | P109: -52930.32 | Q109: 0 | R109: 0
C110: O | D110: Total | E110: 3162669.2 | F110: 1558830.7 | G110: 869728.56 | H110: 458243.59 | I110: -775600.27 | J110: -32196.27 | K110: 0 | L110: -279610.34 | M110: -247708.66 | N110: -1433428.4 | O110: 3097340.6 | P110: -52930.32 | Q110: 0 | R110: 0
D111: Subsidio(-)/Contribucion(+) | E111: 179385.18 | F111: 26473.77 | G111: 12639.61 | H111: 6934.49 | I111: 22445.77 | J111: 787.78 | K111: 0 | L111: 6910.4 | M111: 8725.23 | N111: 40155.9 | O111: 53026.89 | P111: 1285.34 | Q111: 0 | R111: 0
C112: T | D112: Total | E112: 179385.18 | F112: 26473.77 | G112: 12639.61 | H112: 6934.49 | I112: 22445.77 | J112: 787.78 | K112: 0 | L112: 6910.4 | M112: 8725.23 | N112: 40155.9 | O112: 53026.89 | P112: 1285.34 | Q112: 0 | R112: 0
B113: OCCIDENTE | C113: Total | E113: 2827527.8 | F113: 1577172.6 | G113: 877478.33 | H113: 462790.32 | I113: -894688.86 | J113: -37464.46 | K113: 0 | L113: -324421.5 | M113: -287206.9 | N113: -1623613.4 | O113: 3138889.4 | P113: -61407.75 | Q113: 0 | R113: 0
A114: Subs/Cont | B114: Total | E114: -20704709 | F114: 638945.75 | G114: 361369.84 | H114: 205685.41 | I114: -7228805.6 | J114: -272201.48 | K114: 0 | L114: -2349338.4 | M114: -2202021.7 | N114: -10694052 | O114: 1271486.2 | P114: -435777.15 | Q114: 0 | R114: 0
A115: Total | E115: 95705711 | F115: 8263347.5 | G115: 4725736.8 | H115: 2051688.1 | I115: 19810913 | J115: 684254.07 | K115: 70736.95 | L115: 7355525.3 | M115: 5361480 | N115: 21693880 | O115: 17968588 | P115: 960189.83 | Q115: 22.96 | R115: 6759348.8
B146: TOTAL | C146: OPORTUNO | D146: Total | E146: =E91+E114-K91 -> 95634974 | F146: =F91 -> 7624401.8 | G146: =G91 -> 4364367 | H146: =H91 -> 1846002.7 | I146: =I91 -> 27039718 | J146: =J91 -> 956455.55 | K146: =K91 -> 70736.95 | L146: =L91 -> 9704863.7 | M146: =M91 -> 7563501.6 | ... R146: =R91 -> 6759348.8
D147: Subsidio(-)/Contribucion(+) | E147: =E114 -> -20704709
B149: RECIPROCIDAD | C149: OPORTUNO | D149: Total | E149: =E106+E94+E80+E65-K65-K80 -> 11762381 | F149: =F80+F65 -> 970731.18 | G149: =G80+G65 -> 533860.09 | H149: =H80+H65 -> 192854.22 | I149: =I80+I65 -> 4921384.8 | J149: =J80+J65 -> 177446.98 | K149: =K80+K65 -> 0 | L149: =L80+L65 -> 1381104.3 | M149: =M80+M65 -> 1208217.6 | ... R149: =R80+R65 -> 0
D150: Subsidio(-)/Contribucion(+) | E150: =E106+E94 -> -4401833.5
...

Sheet Reversion Pagos R4
B1: PROMOAMBIENTAL
D2: Total | E2: Componente TDF | F2: Componente TTL | G2: Componente TVIAT | H2: Aprovechamiento | I2: CCSA Prest.Aprov. | J2: Componente TCS | K2: Componente TLU | L2: Componente TBL | M2: Componente TRT | N2: CCSA Prest. No Aprov. | O2: Ajuste Decena | P2: SERVICIO ESPECIALES | Q2: Ajuste Recargo Aseo | R2: Otros
C3: Vlr Servicio | D3: -4304657 | E3: -204234.44 | F3: -114903.02 | G3: -58910.61 | H3: -1052437.8 | I3: -38840.3 | J3: -350782.23 | K3: -326414.03 | L3: -1541278.5 | M3: -553450.68 | N3: -63370.25 | O3: -35.1 | P3: 0 | Q3: 0 | R3: 0
C4: Vlr Intereses | D4: -437.51 | E4: -20.61 | F4: -11.62 | G4: -6.13 | H4: -99.06 | I4: -4.11 | J4: -35.82 | K4: -34.53 | L4: -162.79 | M4: -56.17 | N4: -6.66 | O4: -0.01 | P4: 0 | Q4: 0 | R4: 0
B5: Componente | C5: Total | D5: -4305094.5 | E5: -204255.05 | F5: -114914.64 | G5: -58916.74 | H5: -1052536.9 | I5: -38844.41 | J5: -350818.05 | K5: -326448.56 | L5: -1541441.3 | M5: -553506.85 | N5: -63376.91 | O5: -35.11 | P5: 0 | Q5: 0 | R5: 0
C6: Subsidio(-)/Contribucion(+) | D6: 606224.47 | E6: 20070.35 | F6: 11288.32 | G6: 5947.61 | H6: 174148.52 | I6: 5843.46 | J6: 51257.62 | K6: 49095.51 | L6: 225712.61 | M6: 53326.47 | N6: 9534 | O6: 0 | P6: 0 | Q6: 0 | R6: 0
B7: Subs/Cont | C7: Total | D7: 606224.47 | E7: 20070.35 | F7: 11288.32 | G7: 5947.61 | H7: 174148.52 | I7: 5843.46 | J7: 51257.62 | K7: 49095.51 | L7: 225712.61 | M7: 53326.47 | N7: 9534 | O7: 0 | P7: 0 | Q7: 0 | R7: 0
A8: ENEL | B8: Total | D8: -3698870 | E8: -184184.7 | F8: -103626.32 | G8: -52969.13 | H8: -878388.36 | I8: -33000.95 | J8: -299560.43 | K8: -277353.05 | L8: -1315728.7 | M8: -500180.38 | N8: -53842.91 | O8: -35.11 | P8: 0 | Q8: 0 | R8: 0
C9: Vlr Servicio | D9: -90290.21 | E9: -5787.72 | F9: -3267.74 | G9: -1715.14 | H9: -21117.15 | I9: -503.05 | J9: -4412.75 | K9: -6447.78 | L9: -30412.84 | M9: -15807.14 | N9: -820.77 | O9: 1.87 | P9: 0 | Q9: 0 | R9: 0
C10: Vlr Intereses | D10: -230.5 | E10: -14.77 | F10: -8.34 | G10: -4.37 | H10: -53.93 | I10: -1.28 | J10: -11.27 | K10: -16.46 | L10: -77.62 | M10: -40.36 | N10: -2.1 | O10: 0 | P10: 0 | Q10: 0 | R10: 0
B11: Componente | C11: Total | D11: -90520.71 | E11: -5802.49 | F11: -3276.08 | G11: -1719.51 | H11: -21171.08 | I11: -504.33 | J11: -4424.02 | K11: -6464.24 | L11: -30490.46 | M11: -15847.5 | N11: -822.87 | O11: 1.87 | P11: 0 | Q11: 0 | R11: 0
C12: Subsidio(-)/Contribucion(+) | D12: -44389.29 | E12: -2901.74 | F12: -1638.32 | G12: -2.33 | H12: -10566.74 | I12: -252.21 | J12: -2212.3 | K12: -3232.7 | L12: -15246.38 | M12: -7925.08 | N12: -411.49 | O12: 0 | P12: 0 | Q12: 0 | R12: 0
B13: Subs/Cont | C13: Total | D13: -44389.29 | E13: -2901.74 | F13: -1638.32 | G13: -2.33 | H13: -10566.74 | I13: -252.21 | J13: -2212.3 | K13: -3232.7 | L13: -15246.38 | M13: -7925.08 | N13: -411.49 | O13: 0 | P13: 0 | Q13: 0 | R13: 0
A14: OCCIDENTE | B14: Total | D14: -134910 | E14: -8704.23 | F14: -4914.4 | G14: -1721.84 | H14: -31737.82 | I14: -756.54 | J14: -6636.32 | K14: -9696.94 | L14: -45736.84 | M14: -23772.58 | N14: -1234.36 | O14: 1.87 | P14: 0 | Q14: 0 | R14: 0
A15: Total | D15: -3833780 | E15: -192888.93 | F15: -108540.72 | G15: -54690.97 | H15: -910126.18 | I15: -33757.49 | J15: -306196.75 | K15: -287049.99 | L15: -1361465.5 | M15: -523952.96 | N15: -55077.27 | O15: -33.24 | P15: 0 | Q15: 0 | R15: 0
A73: TOTAL | B73: OPORTUNO | C73: Total | D73: =D15-P15 -> -3833780 | E73: =E11+E5 -> -210057.54 | F73: =F11+F5 -> -118190.72 | G73: =G11+G5 -> -60636.25 | H73: =H11+H5 -> -1073708 | I73: =I11+I5 -> -39348.74 | J73: =J11+J5 -> -355242.07 | K73: =K11+K5 -> -332912.8 | L73: =L11+L5 -> -1571931.7 | ... R73: =R11+R5 -> 0
C74: Subsidio(-)/Contribucion(+) | D74: =D7+D13 -> 561835.18
A76: RECIPROCIDAD | B76: OPORTUNO | C76: Total | D76: 0 | E76: 0 | F76: 0 | G76: 0 | H76: 0 | I76: 0 | J76: 0 | K76: 0 | L76: 0 | M76: 0 | N76: 0 | O76: 0 | P76: 0 | Q76: 0 | R76: 0
C77: Subsidio(-)/Contribucion(+) | D77: 0
A79: ENEL | B79: OPORTUNO | C79: Total | D79: =D8-P8 -> -3698870 | E79: =E5 -> -204255.05 | F79: =F5 -> -114914.64 | G79: =G5 -> -58916.74 | H79: =H5 -> -1052536.9 | I79: =I5 -> -38844.41 | J79: =J5 -> -350818.05 | K79: =K5 -> -326448.56 | L79: =L5 -> -1541441.3 | ... R79: =R5 -> 0
C80: Subsidio(-)/Contribucion(+) | D80: =D7 -> 606224.47
A82: ENERBIT | B82: OPORTUNO | C82: Total | D82: 0 | E82: 0 | F82: 0 | G82: 0 | H82: 0 | I82: 0 | J82: 0 | K82: 0 | L82: 0 | M82: 0 | N82: 0 | O82: 0 | P82: 0 | Q82: 0 | R82: 0
C83: Subsidio(-)/Contribucion(+) | D83: 0
A85: OCCIDENTE | B85: OPORTUNO | C85: Total | D85: =D14-P14 -> -134910 | E85: =E11 -> -5802.49 | F85: =F11 -> -3276.08 | G85: =G11 -> -1719.51 | H85: =H11 -> -21171.08 | I85: =I11 -> -504.33 | J85: =J11 -> -4424.02 | K85: =K11 -> -6464.24 | L85: =L11 -> -30490.46 | ... R85: =R11 -> 0
C86: Subsidio(-)/Contribucion(+) | D86: =D13 -> -44389.29
A88: CIUDAD LIMPIA-ACUEDUCTO | B88: OPORTUNO | C88: Total | D88: 0 | E88: 0 | F88: 0 | G88: 0 | H88: 0 | I88: 0 | J88: 0 | K88: 0 | L88: 0 | M88: 0 | N88: 0 | O88: 0 | P88: 0 | Q88: 0 | R88: 0
C89: Subsidio(-)/Contribucion(+) | D89: 0
B91: LIME
D92: Total | E92: Componente TDF | F92: Componente TTL | G92: Componente TVIAT | H92: Aprovechamiento | I92: CCSA Prest.Aprov. | J92: Componente TCS | K92: Componente TLU | L92: Componente TBL | M92: Componente TRT | N92: CCSA Prest. No Aprov. | O92: Ajuste Decena | P92: SERVICIO ESPECIALES | Q92: Ajuste Recargo Aseo | R92: Otros
C93: Vlr Servicio | D93: -26888437 | E93: -1660901.3 | F93: -899968.47 | G93: -460891.41 | H93: -6488857 | I93: -230262.37 | J93: -2029454.6 | K93: -2051952.9 | L93: -9182422.9 | M93: -3507972.9 | N93: -375690.45 | O93: -62.47 | P93: 0 | Q93: 0 | R93: 0
C94: Vlr Intereses | D94: -508997.86 | E94: -53684.14 | F94: -25853.97 | G94: -10930.09 | H94: -103686.96 | I94: -3626.84 | J94: -32144.78 | K94: -39085.05 | L94: -127629.69 | M94: -106438.52 | N94: -5916.12 | O94: -1.89 | P94: 0 | Q94: 0 | R94: 0.19
B95: Componente | C95: Total | D95: -27397435 | E95: -1714585.5 | F95: -925822.44 | G95: -471821.5 | H95: -6592544 | I95: -233889.21 | J95: -2061599.4 | K95: -2091038 | L95: -9310052.6 | M95: -3614411.4 | N95: -381606.57 | O95: -64.36 | P95: 0 | Q95: 0 | R95: 0.19
C96: Subsidio(-)/Contribucion(+) | D96: 6538849.3 | E96: 226514.95 | F96: 99793.49 | G96: 42188.77 | H96: 1862301.5 | I96: 64413.78 | J96: 565028 | K96: 610776.83 | L96: 2539725 | M96: 423011.57 | N96: 105095.33 | O96: 0 | P96: 0 | Q96: 0 | R96: 0
B97: Subs/Cont | C97: Total | D97: 6538849.3 | E97: 226514.95 | F97: 99793.49 | G97: 42188.77 | H97: 1862301.5 | I97: 64413.78 | J97: 565028 | K97: 610776.83 | L97: 2539725 | M97: 423011.57 | N97: 105095.33 | O97: 0 | P97: 0 | Q97: 0 | R97: 0
A98: ENEL | B98: Total | D98: -20858585 | E98: -1488070.5 | F98: -826028.95 | G98: -429632.73 | H98: -4730242.5 | I98: -169475.43 | J98: -1496571.4 | K98: -1480261.2 | L98: -6770327.5 | M98: -3191399.8 | N98: -276511.24 | O98: -64.36 | P98: 0 | Q98: 0 | R98: 0.19
C99: Vlr Servicio | D99: -3980237.6 | E99: -286462.52 | F99: -142022.56 | G99: -63580.64 | H99: -969928.29 | I99: -33251.02 | J99: -289558.91 | K99: -349827.6 | L99: -1253345.6 | M99: -538054.56 | N99: -54251.66 | O99: 45.81 | P99: 0 | Q99: 0 | R99: 0
C100: Vlr Intereses | D100: -18211.28 | E100: -1812.96 | F100: -926.34 | G100: -486.28 | H100: -4026.88 | I100: -107.04 | J100: -911.93 | K100: -1140.23 | L100: -4993.66 | M100: -3631.56 | N100: -174.64 | O100: 0.08 | P100: 0 | Q100: 0.16 | R100: 0
B101: Componente | C101: Total | D101: -3998448.9 | E101: -288275.48 | F101: -142948.9 | G101: -64066.92 | H101: -973955.17 | I101: -33358.06 | J101: -290470.84 | K101: -350967.83 | L101: -1258339.3 | M101: -541686.12 | N101: -54426.3 | O101: 45.89 | P101: 0 | Q101: 0.16 | R101: 0
C102: Subsidio(-)/Contribucion(+) | D102: 3053385.9 | E102: 191175.93 | F102: 90448.03 | G102: 40403.45 | H102: 788542.93 | I102: 25367.94 | J102: 222523.7 | K102: 271617.33 | L102: 1010650.4 | M102: 371266.58 | N102: 41389.52 | O102: 0 | P102: 0 | Q102: 0 | R102: 0
B103: Subs/Cont | C103: Total | D103: 3053385.9 | E103: 191175.93 | F103: 90448.03 | G103: 40403.45 | H103: 788542.93 | I103: 25367.94 | J103: 222523.7 | K103: 271617.33 | L103: 1010650.4 | M103: 371266.58 | N103: 41389.52 | O103: 0 | P103: 0 | Q103: 0 | R103: 0
A104: OCCIDENTE | B104: Total | D104: -945063 | E104: -97099.55 | F104: -52500.87 | G104: -23663.47 | H104: -185412.24 | I104: -7990.12 | J104: -67947.14 | K104: -79350.5 | L104: -247688.84 | M104: -170419.54 | N104: -13036.78 | O104: 45.89 | P104: 0 | Q104: 0.16 | R104: 0
A105: Total | D105: -21803648 | E105: -1585170.1 | F105: -878529.82 | G105: -453296.2 | H105: -4915654.7 | I105: -177465.55 | J105: -1564518.6 | K105: -1559611.7 | L105: -7018016.4 | M105: -3361819.3 | N105: -289548.02 | O105: -18.47 | P105: 0 | Q105: 0.16 | R105: 0.19
A168: TOTAL | B168: OPORTUNO | C168: Total | D168: =D105-P105 -> -21803648 | E168: =E95+E101 -> -2002860.9 | F168: =F95+F101 -> -1068771.3 | G168: =G95+G101 -> -535888.42 | H168: =H95+H101 -> -7566499.2 | I168: =I95+I101 -> -267247.27 | J168: =J95+J101 -> -2352070.3 | K168: =K95+K101 -> -2442005.8 | L168: =L95+L101 -> -10568392 | ... R168: =R95+R101 -> 0.19
C169: Subsidio(-)/Contribucion(+) | D169: =D97+D103 -> 9592235.1
A171: RECIPROCIDAD | B171: OPORTUNO | C171: Total | D171: 0 | E171: 0 | F171: 0 | G171: 0 | H171: 0 | I171: 0 | J171: 0 | K171: 0 | L171: 0 | M171: 0 | N171: 0 | O171: 0 | P171: 0 | Q171: 0 | R171: 0
C172: Subsidio(-)/Contribucion(+) | D172: 0
A174: ENEL | B174: OPORTUNO | C174: Total | D174: =D98-P98 -> -20858585 | E174: =E95 -> -1714585.5 | F174: =F95 -> -925822.44 | G174: =G95 -> -471821.5 | H174: =H95 -> -6592544 | I174: =I95 -> -233889.21 | J174: =J95 -> -2061599.4 | K174: =K95 -> -2091038 | L174: =L95 -> -9310052.6 | ... R174: =R95 -> 0.19
C175: Subsidio(-)/Contribucion(+) | D175: =D97 -> 6538849.3
A177: ENERBIT | B177: OPORTUNO | C177: Total | D177: 0 | E177: 0 | F177: 0 | G177: 0 | H177: 0 | I177: 0 | J177: 0 | K177: 0 | L177: 0 | M177: 0 | N177: 0 | O177: 0 | P177: 0 | Q177: 0 | R177: 0
C178: Subsidio(-)/Contribucion(+) | D178: 0
A180: OCCIDENTE | B180: OPORTUNO | C180: Total | D180: =D104-P104 -> -945063 | E180: =E101 -> -288275.48 | F180: =F101 -> -142948.9 | G180: =G101 -> -64066.92 | H180: =H101 -> -973955.17 | I180: =I101 -> -33358.06 | J180: =J101 -> -290470.84 | K180: =K101 -> -350967.83 | L180: =L101 -> -1258339.3 | ... R180: =R101 -> 0
C181: Subsidio(-)/Contribucion(+) | D181: =D103 -> 3053385.9
A183: CIUDAD LIMPIA-ACUEDUCTO | B183: OPORTUNO | C183: Total | D183: 0 | E183: 0 | F183: 0 | G183: 0 | H183: 0 | I183: 0 | J183: 0 | K183: 0 | L183: 0 | M183: 0 | N183: 0 | O183: 0 | P183: 0 | Q183: 0 | R183: 0
C184: Subsidio(-)/Contribucion(+) | D184: 0
B186: CIUDAD LIMPIA
D187: Total | E187: Componente TDF | F187: Componente TTL | G187: Componente TVIAT | H187: Aprovechamiento | I187: CCSA Prest.Aprov. | J187: Componente TCS | K187: Componente TLU | L187: Componente TBL | M187: Componente TRT | N187: CCSA Prest. No Aprov. | O187: Ajuste Decena | P187: SERVICIO ESPECIALES | Q187: Ajuste Recargo Aseo | R187: Otros
C188: Vlr Servicio | D188: -2333584.4 | E188: -142234.05 | F188: -79508.24 | G188: -41622.06 | H188: -589653.39 | I188: -19071.97 | J188: -167298.18 | K188: -161825.48 | L188: -764442.41 | M188: -336808.98 | N188: -31117.46 | O188: -2.15 | P188: 0 | Q188: 0 | R188: 0
C189: Vlr Intereses | D189: -1304.63 | E189: -63.58 | F189: -35.71 | G189: -16.17 | H189: -347.09 | I189: -11.46 | J189: -100.53 | K189: -98.14 | L189: -463 | M189: -150.24 | N189: -18.7 | O189: -0.01 | P189: 0 | Q189: 0 | R189: 0
B190: Componente | C190: Total | D190: -2334889 | E190: -142297.63 | F190: -79543.95 | G190: -41638.23 | H190: -590000.48 | I190: -19083.43 | J190: -167398.71 | K190: -161923.62 | L190: -764905.41 | M190: -336959.22 | N190: -31136.16 | O190: -2.16 | P190: 0 | Q190: 0 | R190: 0
C191: Subsidio(-)/Contribucion(+) | D191: 75617 | E191: -25929.73 | F191: -14396.34 | G191: -7684.12 | H191: 63193.43 | I191: 2030.11 | J191: 17807.82 | K191: 17247.61 | L191: 81606.06 | M191: -61570.07 | N191: 3312.23 | O191: 0 | P191: 0 | Q191: 0 | R191: 0
B192: Subs/Cont | C192: Total | D192: 75617 | E192: -25929.73 | F192: -14396.34 | G192: -7684.12 | H192: 63193.43 | I192: 2030.11 | J192: 17807.82 | K192: 17247.61 | L192: 81606.06 | M192: -61570.07 | N192: 3312.23 | O192: 0 | P192: 0 | Q192: 0 | R192: 0
A193: ENEL | B193: Total | D193: -2259272 | E193: -168227.36 | F193: -93940.29 | G193: -49322.35 | H193: -526807.05 | I193: -17053.32 | J193: -149590.89 | K193: -144676.01 | L193: -683299.35 | M193: -398529.29 | N193: -27823.93 | O193: -2.16 | P193: 0 | Q193: 0 | R193: 0
A194: Total | D194: -2259272 | E194: -168227.36 | F194: -93940.29 | G194: -49322.35 | H194: -526807.05 | I194: -17053.32 | J194: -149590.89 | K194: -144676.01 | L194: -683299.35 | M194: -398529.29 | N194: -27823.93 | O194: -2.16 | P194: 0 | Q194: 0 | R194: 0
A199: TOTAL | B199: OPORTUNO | C199: Total | D199: =D194-P194 -> -2259272 | E199: =E190 -> -142297.63 | F199: =F190 -> -79543.95 | G199: =G190 -> -41638.23 | H199: =H190 -> -590000.48 | I199: =I190 -> -19083.43 | J199: =J190 -> -167398.71 | K199: =K190 -> -161923.62 | L199: =L190 -> -764905.41 | ... R199: =R190 -> 0
C200: Subsidio(-)/Contribucion(+) | D200: =D192 -> 75617
A202: RECIPROCIDAD | B202: OPORTUNO | C202: Total | D202: 0 | E202: 0 | F202: 0 | G202: 0 | H202: 0 | I202: 0 | J202: 0 | K202: 0 | L202: 0 | M202: 0 | N202: 0 | O202: 0 | P202: 0 | Q202: 0 | R202: 0
C203: Subsidio(-)/Contribucion(+) | D203: 0
A205: ENEL | B205: OPORTUNO | C205: Total | D205: =D193-P193 -> -2259272 | E205: =E190 -> -142297.63 | F205: =F190 -> -79543.95 | G205: =G190 -> -41638.23 | H205: =H190 -> -590000.48 | I205: =I190 -> -19083.43 | J205: =J190 -> -167398.71 | K205: =K190 -> -161923.62 | L205: =L190 -> -764905.41 | ... R205: =R190 -> 0
C206: Subsidio(-)/Contribucion(+) | D206: =D192 -> 75617
A208: ENERBIT | B208: OPORTUNO | C208: Total | D208: 0 | E208: 0 | F208: 0 | G208: 0 | H208: 0 | I208: 0 | J208: 0 | K208: 0 | L208: 0 | M208: 0 | N208: 0 | O208: 0 | P208: 0 | Q208: 0 | R208: 0
C209: Subsidio(-)/Contribucion(+) | D209: 0
A211: OCCIDENTE | B211: OPORTUNO | C211: Total | D211: 0 | E211: 0 | F211: 0 | G211: 0 | H211: 0 | I211: 0 | J211: 0 | K211: 0 | L211: 0 | M211: 0 | N211: 0 | O211: 0 | P211: 0 | Q211: 0 | R211: 0
C212: Subsidio(-)/Contribucion(+) | D212: 0
A214: CIUDAD LIMPIA-ACUEDUCTO | B214: OPORTUNO | C214: Total | D214: 0 | E214: 0 | F214: 0 | G214: 0 | H214: 0 | I214: 0 | J214: 0 | K214: 0 | L214: 0 | M214: 0 | N214: 0 | O214: 0 | P214: 0 | Q214: 0 | R214: 0
C215: Subsidio(-)/Contribucion(+) | D215: 0
B217: BOGOTA LIMPIA
D218: Total | E218: Componente TDF | F218: Componente TTL | G218: Componente TVIAT | H218: Aprovechamiento | I218: CCSA Prest.Aprov. | J218: Componente TCS | K218: Componente TLU | L218: Componente TBL | M218: Componente TRT | N218: CCSA Prest. No Aprov. | O218: Ajuste Decena | P218: SERVICIO ESPECIALES | Q218: Ajuste Recargo Aseo | R218: Otros
C219: Vlr Servicio | D219: -43408442 | E219: -2282274.8 | F219: -1272856.3 | G219: -670044.95 | H219: -10021477 | I219: -361301.3 | J219: -3166106.8 | K219: -3122693.5 | L219: -15845091 | M219: -6075216.7 | N219: -591304.8 | O219: -75.26 | P219: 0 | Q219: 0 | R219: 0
C220: Vlr Intereses | D220: -797951.11 | E220: -97853.35 | F220: -29290.31 | G220: -5127.29 | H220: -108866.47 | I220: -6170.66 | J220: -54138.52 | K220: -51509.34 | L220: -145509.41 | M220: -289414.72 | N220: -10070.84 | O220: -0.2 | P220: 0 | Q220: 0 | R220: 0
B221: Componente | C221: Total | D221: -44206393 | E221: -2380128.1 | F221: -1302146.6 | G221: -675172.24 | H221: -10130343 | I221: -367471.96 | J221: -3220245.3 | K221: -3174202.8 | L221: -15990600 | M221: -6364631.4 | N221: -601375.64 | O221: -75.46 | P221: 0 | Q221: 0 | R221: 0
C222: Subsidio(-)/Contribucion(+) | D222: 4573139.3 | E222: 87413.39 | F222: 51896.33 | G222: 29363.21 | H222: 1298833.1 | I222: 45156.38 | J222: 396094.23 | K222: 393885.09 | L222: 1961083.1 | M222: 235440.02 | N222: 73974.4 | O222: 0 | P222: 0 | Q222: 0 | R222: 0
B223: Subs/Cont | C223: Total | D223: 4573139.3 | E223: 87413.39 | F223: 51896.33 | G223: 29363.21 | H223: 1298833.1 | I223: 45156.38 | J223: 396094.23 | K223: 393885.09 | L223: 1961083.1 | M223: 235440.02 | N223: 73974.4 | O223: 0 | P223: 0 | Q223: 0 | R223: 0
A224: ENEL | B224: Total | D224: -39633253 | E224: -2292714.7 | F224: -1250250.3 | G224: -645809.03 | H224: -8831510.1 | I224: -322315.58 | J224: -2824151 | K224: -2780317.7 | L224: -14029517 | M224: -6129191.4 | N224: -527401.24 | O224: -75.46 | P224: 0 | Q224: 0 | R224: 0
C225: Vlr Servicio | D225: -565271.2 | E225: -34473.06 | F225: -18653.84 | G225: -10167.59 | H225: -130203.13 | I225: -3588.89 | J225: -31481.84 | K225: -41310.69 | L225: -197869.25 | M225: -91658.33 | N225: -5855.59 | O225: -8.99 | P225: 0 | Q225: 0 | R225: 0
C226: Vlr Intereses | D226: -67.28 | E226: -4.33 | F226: -2 | G226: -1.13 | H226: -16.44 | I226: -0.4 | J226: -3.58 | K226: -4.52 | L226: -22.51 | M226: -11.71 | N226: -0.66 | O226: 0 | P226: 0 | Q226: 0 | R226: 0
B227: Componente | C227: Total | D227: -565338.48 | E227: -34477.39 | F227: -18655.84 | G227: -10168.72 | H227: -130219.57 | I227: -3589.29 | J227: -31485.42 | K227: -41315.21 | L227: -197891.76 | M227: -91670.04 | N227: -5856.25 | O227: -8.99 | P227: 0 | Q227: 0 | R227: 0
C228: Subsidio(-)/Contribucion(+) | D228: 11258.48 | E228: -3470.2 | F228: -1973.63 | G228: -1059.4 | H228: 8396.94 | I228: 151.48 | J228: 1328.97 | K228: 2767.74 | L228: 14072.68 | M228: -9203.25 | N228: 247.15 | O228: 0 | P228: 0 | Q228: 0 | R228: 0
B229: Subs/Cont | C229: Total | D229: 11258.48 | E229: -3470.2 | F229: -1973.63 | G229: -1059.4 | H229: 8396.94 | I229: 151.48 | J229: 1328.97 | K229: 2767.74 | L229: 14072.68 | M229: -9203.25 | N229: 247.15 | O229: 0 | P229: 0 | Q229: 0 | R229: 0
A230: NUEVO ESQUEMA | B230: Total | D230: -554080 | E230: -37947.59 | F230: -20629.47 | G230: -11228.12 | H230: -121822.63 | I230: -3437.81 | J230: -30156.45 | K230: -38547.47 | L230: -183819.08 | M230: -100873.29 | N230: -5609.1 | O230: -8.99 | P230: 0 | Q230: 0 | R230: 0
C231: Vlr Servicio | D231: -1390690.7 | E231: -77877.35 | F231: -43905.19 | G231: -23195.75 | H231: -322683.66 | I231: -9947.79 | J231: -87261.32 | K231: -99487.88 | L231: -502667.02 | M231: -207435.92 | N231: -16230.6 | O231: 1.74 | P231: 0 | Q231: 0 | R231: 0
C232: Vlr Intereses | D232: -25687 | E232: -3851.9 | F232: -1228.88 | G232: -324.38 | H232: -3216.32 | I232: -155.62 | J232: -1365.1 | K232: -1459.5 | L232: -2589.28 | M232: -11273.99 | N232: -253.89 | O232: 31.86 | P232: 0 | Q232: 0 | R232: 0
B233: Componente | C233: Total | D233: -1416377.7 | E233: -81729.25 | F233: -45134.07 | G233: -23520.13 | H233: -325899.98 | I233: -10103.41 | J233: -88626.42 | K233: -100947.38 | L233: -505256.3 | M233: -218709.91 | N233: -16484.49 | O233: 33.6 | P233: 0 | Q233: 0 | R233: 0
C234: Subsidio(-)/Contribucion(+) | D234: 45125.74 | E234: -2259.8 | F234: -1198.78 | G234: -664.04 | H234: 17199.88 | I234: 642.06 | J234: 5632.34 | K234: 5147.82 | L234: 25383.21 | M234: -5804.53 | N234: 1047.58 | O234: 0 | P234: 0 | Q234: 0 | R234: 0
B235: Subs/Cont | C235: Total | D235: 45125.74 | E235: -2259.8 | F235: -1198.78 | G235: -664.04 | H235: 17199.88 | I235: 642.06 | J235: 5632.34 | K235: 5147.82 | L235: 25383.21 | M235: -5804.53 | N235: 1047.58 | O235: 0 | P235: 0 | Q235: 0 | R235: 0
A236: OCCIDENTE | B236: Total | D236: -1371252 | E236: -83989.05 | F236: -46332.85 | G236: -24184.17 | H236: -308700.1 | I236: -9461.35 | J236: -82994.08 | K236: -95799.56 | L236: -479873.09 | M236: -224514.44 | N236: -15436.91 | O236: 33.6 | P236: 0 | Q236: 0 | R236: 0
A237: Total | D237: -41558585 | E237: -2414651.4 | F237: -1317212.6 | G237: -681221.32 | H237: -9262032.8 | I237: -335214.74 | J237: -2937301.6 | K237: -2914664.7 | L237: -14693209 | M237: -6454579.1 | N237: -548447.25 | O237: -50.85 | P237: 0 | Q237: 0 | R237: 0
A313: TOTAL | B313: OPORTUNO | C313: Total | D313: =D237-P237 -> -41558585 | E313: =E233+E227+E221 -> -2496334.8 | F313: =F233+F227+F221 -> -1365936.5 | G313: =G233+G227+G221 -> -708861.09 | H313: =H233+H227+H221 -> -10586463 | I313: =I233+I227+I221 -> -381164.66 | J313: =J233+J227+J221 -> -3340357.1 | K313: =K233+K227+K221 -> -3316465.4 | L313: =L233+L227+L221 -> -16693748 | ... R313: =R233+R227+R221 -> 0
C314: Subsidio(-)/Contribucion(+) | D314: =D235+D229+D223 -> 4629523.5
A316: RECIPROCIDAD | B316: OPORTUNO | C316: Total | D316: =D230-P230 -> -554080 | E316: =E227 -> -34477.39 | F316: =F227 -> -18655.84 | G316: =G227 -> -10168.72 | H316: =H227 -> -130219.57 | I316: =I227 -> -3589.29 | J316: =J227 -> -31485.42 | K316: =K227 -> -41315.21 | L316: =L227 -> -197891.76 | ... R316: =R227 -> 0
C317: Subsidio(-)/Contribucion(+) | D317: =D229 -> 11258.48
...

Sheet SALDOS POR NOTA
B1: PROMOAMBIENTAL
C2: Total | D2: Componente TDF | E2: Componente TTL | F2: Componente TVIAT | G2: Aprovechamiento | H2: CCSA Prest.Aprov. | I2: Especiales | J2: Componente TCS | K2: Componente TLU | L2: Componente TBL | M2: Componente TRT | N2: CCSA Prest. No Aprov. | O2: Deb/Cred
B3: Vlr Servicio | C3: 0 | D3: 0 | E3: 0 | F3: 0 | G3: 0 | H3: 0 | I3: 0 | J3: 0 | K3: 0 | L3: 0 | M3: 0 | N3: 0 | O3: 0
B4: Vlr Intereses | C4: 0 | D4: 0 | E4: 0 | F4: 0 | G4: 0 | H4: 0 | I4: 0 | J4: 0 | K4: 0 | L4: 0 | M4: 0 | N4: 0 | O4: 0
A5: Componente | B5: Total | C5: 0 | D5: 0 | E5: 0 | F5: 0 | G5: 0 | H5: 0 | I5: 0 | J5: 0 | K5: 0 | L5: 0 | M5: 0 | N5: 0 | O5: 0
B6: Subsidio(-)/Contribucion(+) | C6: 0 | D6: 0 | E6: 0 | F6: 0 | G6: 0 | H6: 0 | I6: 0 | J6: 0 | K6: 0 | L6: 0 | M6: 0 | N6: 0 | O6: 0
A7: Subs/Cont | B7: Total | C7: 0 | D7: 0 | E7: 0 | F7: 0 | G7: 0 | H7: 0 | I7: 0 | J7: 0 | K7: 0 | L7: 0 | M7: 0 | N7: 0 | O7: 0
A8: Total | C8: 0 | D8: 0 | E8: 0 | F8: 0 | G8: 0 | H8: 0 | I8: 0 | J8: 0 | K8: 0 | L8: 0 | M8: 0 | N8: 0 | O8: 0
B10: Total | C10: =C8-I8 -> 0 | D10: =D5 -> 0 | E10: =E5 -> 0 | F10: =F5 -> 0 | G10: =G5 -> 0 | H10: =H5 -> 0 | I10: =I5 -> 0 | J10: =J5 -> 0 | K10: =K5 -> 0 | ... P10: =P5 -> 0
B11: Subsidio(-)/Contribucion(+) | C11: =C7 -> 0
B14: LIME
C15: Total | D15: Componente TDF | E15: Componente TTL | F15: Componente TVIAT | G15: Aprovechamiento | H15: CCSA Prest.Aprov. | I15: Especiales | J15: Componente TCS | K15: Componente TLU | L15: Componente TBL | M15: Componente TRT | N15: CCSA Prest. No Aprov. | O15: Deb/Cred
B16: Vlr Servicio | C16: 0 | D16: 0 | E16: 0 | F16: 0 | G16: 0 | H16: 0 | I16: 0 | J16: 0 | K16: 0 | L16: 0 | M16: 0 | N16: 0 | O16: 0
B17: Vlr Intereses | C17: 0 | D17: 0 | E17: 0 | F17: 0 | G17: 0 | H17: 0 | I17: 0 | J17: 0 | K17: 0 | L17: 0 | M17: 0 | N17: 0 | O17: 0
A18: Componente | B18: Total | C18: 0 | D18: 0 | E18: 0 | F18: 0 | G18: 0 | H18: 0 | I18: 0 | J18: 0 | K18: 0 | L18: 0 | M18: 0 | N18: 0 | O18: 0
B19: Subsidio(-)/Contribucion(+) | C19: 0 | D19: 0 | E19: 0 | F19: 0 | G19: 0 | H19: 0 | I19: 0 | J19: 0 | K19: 0 | L19: 0 | M19: 0 | N19: 0 | O19: 0
A20: Subs/Cont | B20: Total | C20: 0 | D20: 0 | E20: 0 | F20: 0 | G20: 0 | H20: 0 | I20: 0 | J20: 0 | K20: 0 | L20: 0 | M20: 0 | N20: 0 | O20: 0
A21: Total | C21: 0 | D21: 0 | E21: 0 | F21: 0 | G21: 0 | H21: 0 | I21: 0 | J21: 0 | K21: 0 | L21: 0 | M21: 0 | N21: 0 | O21: 0
B23: Total | C23: =C21-I21 -> 0 | D23: =D18 -> 0 | E23: =E18 -> 0 | F23: =F18 -> 0 | G23: =G18 -> 0 | H23: =H18 -> 0 | I23: =I18 -> 0 | J23: =J18 -> 0 | K23: =K18 -> 0 | ... P23: =P18 -> 0
B24: Subsidio(-)/Contribucion(+) | C24: =C20 -> 0
B27: CIUDAD LIMPIA
C28: Total | D28: Componente TDF | E28: Componente TTL | F28: Componente TVIAT | G28: Aprovechamiento | H28: CCSA Prest.Aprov. | I28: Especiales | J28: Componente TCS | K28: Componente TLU | L28: Componente TBL | M28: Componente TRT | N28: CCSA Prest. No Aprov. | O28: Deb/Cred
B29: Vlr Servicio | C29: 0 | D29: 0 | E29: 0 | F29: 0 | G29: 0 | H29: 0 | I29: 0 | J29: 0 | K29: 0 | L29: 0 | M29: 0 | N29: 0 | O29: 0
B30: Vlr Intereses | C30: 0 | D30: 0 | E30: 0 | F30: 0 | G30: 0 | H30: 0 | I30: 0 | J30: 0 | K30: 0 | L30: 0 | M30: 0 | N30: 0 | O30: 0
A31: Componente | B31: Total | C31: 0 | D31: 0 | E31: 0 | F31: 0 | G31: 0 | H31: 0 | I31: 0 | J31: 0 | K31: 0 | L31: 0 | M31: 0 | N31: 0 | O31: 0
B32: Subsidio(-)/Contribucion(+) | C32: 0 | D32: 0 | E32: 0 | F32: 0 | G32: 0 | H32: 0 | I32: 0 | J32: 0 | K32: 0 | L32: 0 | M32: 0 | N32: 0 | O32: 0
A33: Subs/Cont | B33: Total | C33: 0 | D33: 0 | E33: 0 | F33: 0 | G33: 0 | H33: 0 | I33: 0 | J33: 0 | K33: 0 | L33: 0 | M33: 0 | N33: 0 | O33: 0
A34: Total | C34: 0 | D34: 0 | E34: 0 | F34: 0 | G34: 0 | H34: 0 | I34: 0 | J34: 0 | K34: 0 | L34: 0 | M34: 0 | N34: 0 | O34: 0
B36: Total | C36: =C34-I34 -> 0 | D36: =D31 -> 0 | E36: =E31 -> 0 | F36: =F31 -> 0 | G36: =G31 -> 0 | H36: =H31 -> 0 | I36: =I31 -> 0 | J36: =J31 -> 0 | K36: =K31 -> 0 | ... P36: =P31 -> 0
B37: Subsidio(-)/Contribucion(+) | C37: =C33 -> 0
B40: BOGOTA LIMPIA
C41: Total | D41: Componente TDF | E41: Componente TTL | F41: Componente TVIAT | G41: Aprovechamiento | H41: CCSA Prest.Aprov. | I41: Especiales | J41: Componente TCS | K41: Componente TLU | L41: Componente TBL | M41: Componente TRT | N41: CCSA Prest. No Aprov. | O41: Deb/Cred
B42: Vlr Servicio | C42: 0 | D42: 0 | E42: 0 | F42: 0 | G42: 0 | H42: 0 | I42: 0 | J42: 0 | K42: 0 | L42: 0 | M42: 0 | N42: 0 | O42: 0
B43: Vlr Intereses | C43: 0 | D43: 0 | E43: 0 | F43: 0 | G43: 0 | H43: 0 | I43: 0 | J43: 0 | K43: 0 | L43: 0 | M43: 0 | N43: 0 | O43: 0
A44: Componente | B44: Total | C44: 0 | D44: 0 | E44: 0 | F44: 0 | G44: 0 | H44: 0 | I44: 0 | J44: 0 | K44: 0 | L44: 0 | M44: 0 | N44: 0 | O44: 0
B45: Subsidio(-)/Contribucion(+) | C45: 0 | D45: 0 | E45: 0 | F45: 0 | G45: 0 | H45: 0 | I45: 0 | J45: 0 | K45: 0 | L45: 0 | M45: 0 | N45: 0 | O45: 0
A46: Subs/Cont | B46: Total | C46: 0 | D46: 0 | E46: 0 | F46: 0 | G46: 0 | H46: 0 | I46: 0 | J46: 0 | K46: 0 | L46: 0 | M46: 0 | N46: 0 | O46: 0
A47: Total | C47: 0 | D47: 0 | E47: 0 | F47: 0 | G47: 0 | H47: 0 | I47: 0 | J47: 0 | K47: 0 | L47: 0 | M47: 0 | N47: 0 | O47: 0
B49: Total | C49: =C47-I47 -> 0 | D49: =D44 -> 0 | E49: =E44 -> 0 | F49: =F44 -> 0 | G49: =G44 -> 0 | H49: =H44 -> 0 | I49: =I44 -> 0 | J49: =J44 -> 0 | K49: =K44 -> 0 | ... P49: =P44 -> 0
B50: Subsidio(-)/Contribucion(+) | C50: =C46 -> 0
B53: AREA LIMPIA
C54: Total | D54: Componente TDF | E54: Componente TTL | F54: Componente TVIAT | G54: Aprovechamiento | H54: CCSA Prest.Aprov. | I54: Especiales | J54: Componente TCS | K54: Componente TLU | L54: Componente TBL | M54: Componente TRT | N54: CCSA Prest. No Aprov. | O54: Deb/Cred
B55: Vlr Servicio | C55: 0 | D55: 0 | E55: 0 | F55: 0 | G55: 0 | H55: 0 | I55: 0 | J55: 0 | K55: 0 | L55: 0 | M55: 0 | N55: 0 | O55: 0
B56: Vlr Intereses | C56: 0 | D56: 0 | E56: 0 | F56: 0 | G56: 0 | H56: 0 | I56: 0 | J56: 0 | K56: 0 | L56: 0 | M56: 0 | N56: 0 | O56: 0
A57: Componente | B57: Total | C57: 0 | D57: 0 | E57: 0 | F57: 0 | G57: 0 | H57: 0 | I57: 0 | J57: 0 | K57: 0 | L57: 0 | M57: 0 | N57: 0 | O57: 0
B58: Subsidio(-)/Contribucion(+) | C58: 0 | D58: 0 | E58: 0 | F58: 0 | G58: 0 | H58: 0 | I58: 0 | J58: 0 | K58: 0 | L58: 0 | M58: 0 | N58: 0 | O58: 0
A59: Subs/Cont | B59: Total | C59: 0 | D59: 0 | E59: 0 | F59: 0 | G59: 0 | H59: 0 | I59: 0 | J59: 0 | K59: 0 | L59: 0 | M59: 0 | N59: 0 | O59: 0
A60: Total | C60: 0 | D60: 0 | E60: 0 | F60: 0 | G60: 0 | H60: 0 | I60: 0 | J60: 0 | K60: 0 | L60: 0 | M60: 0 | N60: 0 | O60: 0
B62: Total | C62: =C60-I60 -> 0 | D62: =D57 -> 0 | E62: =E57 -> 0 | F62: =F57 -> 0 | G62: =G57 -> 0 | H62: =H57 -> 0 | I62: =I57 -> 0 | J62: =J57 -> 0 | K62: =K57 -> 0 | ... P62: =P57 -> 0
B63: Subsidio(-)/Contribucion(+) | C63: =C59 -> 0

Sheet RETRIBUCION NEGATIVA
B1: PROMOAMBIENTAL
C2: Total | D2: Componente TDF | E2: Componente TTL | F2: Componente TVIAT | G2: Aprovechamiento | H2: CCSA Prest.Aprov. | I2: Especiales | J2: Componente TCS | K2: Componente TLU | L2: Componente TBL | M2: Componente TRT | N2: CCSA Prest. No Aprov. | O2: Deb/Cred
B3: Vlr Intereses | C3: 0 | D3: 0 | E3: 0 | F3: 0 | G3: 0 | H3: 0 | I3: 0 | J3: 0 | K3: 0 | L3: 0 | M3: 0 | N3: 0 | O3: 0
B4: Vlr Servicio | C4: 0 | D4: 0 | E4: 0 | F4: 0 | G4: 0 | H4: 0 | I4: 0 | J4: 0 | K4: 0 | L4: 0 | M4: 0 | N4: 0 | O4: 0
A5: Componente | B5: Total | C5: 0 | D5: 0 | E5: 0 | F5: 0 | G5: 0 | H5: 0 | I5: 0 | J5: 0 | K5: 0 | L5: 0 | M5: 0 | N5: 0 | O5: 0
B6: Subsidio(-)/Contribucion(+) | C6: 0 | D6: 0 | E6: 0 | F6: 0 | G6: 0 | H6: 0 | I6: 0 | J6: 0 | K6: 0 | L6: 0 | M6: 0 | N6: 0 | O6: 0
A7: Subs/Cont | B7: Total | C7: 0 | D7: 0 | E7: 0 | F7: 0 | G7: 0 | H7: 0 | I7: 0 | J7: 0 | K7: 0 | L7: 0 | M7: 0 | N7: 0 | O7: 0
A8: Total | C8: 0 | D8: 0 | E8: 0 | F8: 0 | G8: 0 | H8: 0 | I8: 0 | J8: 0 | K8: 0 | L8: 0 | M8: 0 | N8: 0 | O8: 0
B10: Total | C10: =C8-I8 -> 0 | D10: =D5 -> 0 | E10: =E5 -> 0 | F10: =F5 -> 0 | G10: =G5 -> 0 | H10: =H5 -> 0 | I10: =I5 -> 0 | J10: =J5 -> 0 | K10: =K5 -> 0 | ... O10: =O5 -> 0
B11: Subsidio(-)/Contribucion(+) | C11: =C7 -> 0
B14: LIME
C15: Total | D15: Componente TDF | E15: Componente TTL | F15: Componente TVIAT | G15: Aprovechamiento | H15: CCSA Prest.Aprov. | I15: Especiales | J15: Componente TCS | K15: Componente TLU | L15: Componente TBL | M15: Componente TRT | N15: CCSA Prest. No Aprov. | O15: Deb/Cred
B16: Vlr Intereses | C16: 0 | D16: 0 | E16: 0 | F16: 0 | G16: 0 | H16: 0 | I16: 0 | J16: 0 | K16: 0 | L16: 0 | M16: 0 | N16: 0 | O16: 0
B17: Vlr Servicio | C17: 0 | D17: 0 | E17: 0 | F17: 0 | G17: 0 | H17: 0 | I17: 0 | J17: 0 | K17: 0 | L17: 0 | M17: 0 | N17: 0 | O17: 0
A18: Componente | B18: Total | C18: 0 | D18: 0 | E18: 0 | F18: 0 | G18: 0 | H18: 0 | I18: 0 | J18: 0 | K18: 0 | L18: 0 | M18: 0 | N18: 0 | O18: 0
B19: Subsidio(-)/Contribucion(+) | C19: 0 | D19: 0 | E19: 0 | F19: 0 | G19: 0 | H19: 0 | I19: 0 | J19: 0 | K19: 0 | L19: 0 | M19: 0 | N19: 0 | O19: 0
A20: Subs/Cont | B20: Total | C20: 0 | D20: 0 | E20: 0 | F20: 0 | G20: 0 | H20: 0 | I20: 0 | J20: 0 | K20: 0 | L20: 0 | M20: 0 | N20: 0 | O20: 0
A21: Total | C21: 0 | D21: 0 | E21: 0 | F21: 0 | G21: 0 | H21: 0 | I21: 0 | J21: 0 | K21: 0 | L21: 0 | M21: 0 | N21: 0 | O21: 0
B23: Total | C23: =C21-I21 -> 0 | D23: =D18 -> 0 | E23: =E18 -> 0 | F23: =F18 -> 0 | G23: =G18 -> 0 | H23: =H18 -> 0 | I23: =I18 -> 0 | J23: =J18 -> 0 | K23: =K18 -> 0 | ... O23: =O18 -> 0
B24: Subsidio(-)/Contribucion(+) | C24: =C20 -> 0
B27: CIUDAD LIMPIA
C28: Total | D28: Componente TDF | E28: Componente TTL | F28: Componente TVIAT | G28: Aprovechamiento | H28: CCSA Prest.Aprov. | I28: Especiales | J28: Componente TCS | K28: Componente TLU | L28: Componente TBL | M28: Componente TRT | N28: CCSA Prest. No Aprov. | O28: Deb/Cred
B29: Vlr Intereses | C29: 0 | D29: 0 | E29: 0 | F29: 0 | G29: 0 | H29: 0 | I29: 0 | J29: 0 | K29: 0 | L29: 0 | M29: 0 | N29: 0 | O29: 0
B30: Vlr Servicio | C30: 0 | D30: 0 | E30: 0 | F30: 0 | G30: 0 | H30: 0 | I30: 0 | J30: 0 | K30: 0 | L30: 0 | M30: 0 | N30: 0 | O30: 0
A31: Componente | B31: Total | C31: 0 | D31: 0 | E31: 0 | F31: 0 | G31: 0 | H31: 0 | I31: 0 | J31: 0 | K31: 0 | L31: 0 | M31: 0 | N31: 0 | O31: 0
B32: Subsidio(-)/Contribucion(+) | C32: 0 | D32: 0 | E32: 0 | F32: 0 | G32: 0 | H32: 0 | I32: 0 | J32: 0 | K32: 0 | L32: 0 | M32: 0 | N32: 0 | O32: 0
A33: Subs/Cont | B33: Total | C33: 0 | D33: 0 | E33: 0 | F33: 0 | G33: 0 | H33: 0 | I33: 0 | J33: 0 | K33: 0 | L33: 0 | M33: 0 | N33: 0 | O33: 0
A34: Total | C34: 0 | D34: 0 | E34: 0 | F34: 0 | G34: 0 | H34: 0 | I34: 0 | J34: 0 | K34: 0 | L34: 0 | M34: 0 | N34: 0 | O34: 0
B36: Total | C36: =C34-I34 -> 0 | D36: =D31 -> 0 | E36: =E31 -> 0 | F36: =F31 -> 0 | G36: =G31 -> 0 | H36: =H31 -> 0 | I36: =I31 -> 0 | J36: =J31 -> 0 | K36: =K31 -> 0 | ... O36: =O31 -> 0
B37: Subsidio(-)/Contribucion(+) | C37: =C33 -> 0
B40: BOGOTA LIMPIA
C41: Total | D41: Componente TDF | E41: Componente TTL | F41: Componente TVIAT | G41: Aprovechamiento | H41: CCSA Prest.Aprov. | I41: Especiales | J41: Componente TCS | K41: Componente TLU | L41: Componente TBL | M41: Componente TRT | N41: CCSA Prest. No Aprov. | O41: Deb/Cred
B42: Vlr Intereses | C42: 0 | D42: 0 | E42: 0 | F42: 0 | G42: 0 | H42: 0 | I42: 0 | J42: 0 | K42: 0 | L42: 0 | M42: 0 | N42: 0 | O42: 0
B43: Vlr Servicio | C43: 0 | D43: 0 | E43: 0 | F43: 0 | G43: 0 | H43: 0 | I43: 0 | J43: 0 | K43: 0 | L43: 0 | M43: 0 | N43: 0 | O43: 0
A44: Componente | B44: Total | C44: 0 | D44: 0 | E44: 0 | F44: 0 | G44: 0 | H44: 0 | I44: 0 | J44: 0 | K44: 0 | L44: 0 | M44: 0 | N44: 0 | O44: 0
B45: Subsidio(-)/Contribucion(+) | C45: 0 | D45: 0 | E45: 0 | F45: 0 | G45: 0 | H45: 0 | I45: 0 | J45: 0 | K45: 0 | L45: 0 | M45: 0 | N45: 0 | O45: 0
A46: Subs/Cont | B46: Total | C46: 0 | D46: 0 | E46: 0 | F46: 0 | G46: 0 | H46: 0 | I46: 0 | J46: 0 | K46: 0 | L46: 0 | M46: 0 | N46: 0 | O46: 0
A47: Total | C47: 0 | D47: 0 | E47: 0 | F47: 0 | G47: 0 | H47: 0 | I47: 0 | J47: 0 | K47: 0 | L47: 0 | M47: 0 | N47: 0 | O47: 0
B49: Total | C49: =C47-I47 -> 0 | D49: =D44 -> 0 | E49: =E44 -> 0 | F49: =F44 -> 0 | G49: =G44 -> 0 | H49: =H44 -> 0 | I49: =I44 -> 0 | J49: =J44 -> 0 | K49: =K44 -> 0 | ... O49: =O44 -> 0
B50: Subsidio(-)/Contribucion(+) | C50: =C46 -> 0
B53: AREA LIMPIA
C54: Total | D54: Componente TDF | E54: Componente TTL | F54: Componente TVIAT | G54: Aprovechamiento | H54: CCSA Prest.Aprov. | I54: Especiales | J54: Componente TCS | K54: Componente TLU | L54: Componente TBL | M54: Componente TRT | N54: CCSA Prest. No Aprov. | O54: Deb/Cred
B55: Vlr Servicio | C55: 0 | D55: 0 | E55: 0 | F55: 0 | G55: 0 | H55: 0 | I55: 0 | J55: 0 | K55: 0 | L55: 0 | M55: 0 | N55: 0 | O55: 0
A56: Componente | B56: Total | C56: 0 | D56: 0 | E56: 0 | F56: 0 | G56: 0 | H56: 0 | I56: 0 | J56: 0 | K56: 0 | L56: 0 | M56: 0 | N56: 0 | O56: 0
B57: Subsidio(-)/Contribucion(+) | C57: 0 | D57: 0 | E57: 0 | F57: 0 | G57: 0 | H57: 0 | I57: 0 | J57: 0 | K57: 0 | L57: 0 | M57: 0 | N57: 0 | O57: 0
A58: Subs/Cont | B58: Total | C58: 0 | D58: 0 | E58: 0 | F58: 0 | G58: 0 | H58: 0 | I58: 0 | J58: 0 | K58: 0 | L58: 0 | M58: 0 | N58: 0 | O58: 0
A59: Total | C59: 0 | D59: 0 | E59: 0 | F59: 0 | G59: 0 | H59: 0 | I59: 0 | J59: 0 | K59: 0 | L59: 0 | M59: 0 | N59: 0 | O59: 0
B61: Total | C61: =C59-I59 -> 0 | D61: =D56 -> 0 | E61: =E56 -> 0 | F61: =F56 -> 0 | G61: =G56 -> 0 | H61: =H56 -> 0 | I61: =I56 -> 0 | J61: =J56 -> 0 | K61: =K56 -> 0 | ... O61: =O56 -> 0
B62: Subsidio(-)/Contribucion(+) | C62: =C58 -> 0

Sheet AJUSTES - SF-T
F3: PROCERASEO S.A.S. | I3: NIT: 901 153 639 - 0 | M3: Codigo Remuneración: | N3: ='CONSOLIDADO_TOTAL RECAUDO'!N3 -> 2026101 | U3: PROCERASEO S.A.S. | W3: NIT: 901 153 639 - 0 | AA3: Codigo Remuneración: | AC3: =N3 -> 2026101
F4: 3. ESQUEMA FINANCIERO DEL SERVICIO PUBLICO DE ASEO | U4: 3. ESQUEMA FINANCIERO DEL SERVICIO PUBLICO DE ASEO
F5: Resoluciòn UAESP Número 27 de 2018 | U5: Resoluciòn UAESP Número 27 de 2018
C6: Fecha de Proceso: | D6: ='CONSOLIDADO_TOTAL RECAUDO'!D6 -> 46314 | F6: SALDOS A FAVOR POR NOTA | U6: =+F6 -> SALDOS A FAVOR POR NOTA
C7: Hora: | D7: ='CONSOLIDADO_TOTAL RECAUDO'!D7 -> 0.58333333 | F7: Fecha Desde: | H7: ='CONSOLIDADO_TOTAL RECAUDO'!G7 -> 46296 | J7: Feha Hasta: | K7: ='CONSOLIDADO_TOTAL RECAUDO'!K7 -> 46310 | U7: =F7 -> Fecha Desde: | V7: =H7 -> 46296 | X7: =J7 -> Feha Hasta: | Y7: =K7 -> 46310
B8: ASE | C8: Concesionarios | D8: Recaudo Total | E8: Recaudo por disposicion final | F8: Recaudo por tratamiento de lixiviados | G8: Recaudo por Componente VIAT ( Decreto 2412/2018) | H8: Recaudo por aprovechamiento | I8: Recaudo del componente de comercializacion para Aprovechamiento (11,4%) | J8: Balance de subsidio o contribuciones | K8: RECAUDO BASE DE REMUNERACION | L8: Costo de la Interventoría | M8: REMUNERACION FINAL | N8: Conceptos especiales | O8: REMUNERACION FINAL MAS CONCEPTOS ESPECIALES | S8: ASE | T8: Concesionarios | U8: Tarifa de Comercialización del Servicio. ( TCS) | V8: Tarifa de Limpieza Urbana del Servicio. ( TLU) | W8: Tarifa de Barrido y Limpieza del Servicio. ( TBL) | X8: Tarifa de Recolección y Transporte del Servicio. (TRT) | Y8: Recaudo del componente de comercializacion para Aprovechamiento (18,6%) | Z8: Costo de la Interventoría | AA8: Ajuste a la decena | AB8: Conceptos especiales | AC8: Diferencial Balance S / C (Fac vs Rec) | AD8: Balance S / C Con Baase en (Recaudo) | AE8: REMUNERACION FINAL MAS CONCEPTOS ESPECIALES
B9: 1 | C9: PROMOAMBIENTAL DISTRITO S.A.S. ESP. | D9: ='SALDOS POR NOTA'!C10 -> 0 | E9: ='SALDOS POR NOTA'!D10 -> 0 | F9: ='SALDOS POR NOTA'!E10 -> 0 | G9: ='SALDOS POR NOTA'!F10 -> 0 | H9: ='SALDOS POR NOTA'!G10 -> 0 | I9: ='SALDOS POR NOTA'!H10 -> 0 | J9: 0 | K9: =D9-E9-F9-G9-H9-I9-J9 -> 0 | L9: 0 | M9: =K9-L9 -> 0 | N9: ='SALDOS POR NOTA'!I10 -> 0 | O9: =M9+N9 -> 0 | S9: 1 | T9: PROMOAMBIENTAL DISTRITO S.A.S. ESP. | U9: ='SALDOS POR NOTA'!J10 -> 0 | V9: ='SALDOS POR NOTA'!K10 -> 0 | W9: ='SALDOS POR NOTA'!L10 -> 0 | X9: ='SALDOS POR NOTA'!M10 -> 0 | Y9: ='SALDOS POR NOTA'!N10 -> 0 | Z9: =L9*-1 -> 0 | AA9: ='SALDOS POR NOTA'!O10 -> 0 | AB9: =N9 -> 0 | AC9: =-J9+AD9 -> 0 | AD9: ='SALDOS POR NOTA'!C11 -> 0 | AE9: =SUM(U9:AC9) -> 0 | AF9: =(AE9-O9) -> 0 | AG9: =AF9=0 -> TRUE
B10: 2 | C10: LIMPIEZA METROPOLITANA S.A. ESP. | D10: ='SALDOS POR NOTA'!C23 -> 0 | E10: ='SALDOS POR NOTA'!D23 -> 0 | F10: ='SALDOS POR NOTA'!E23 -> 0 | G10: ='SALDOS POR NOTA'!F23 -> 0 | H10: ='SALDOS POR NOTA'!G23 -> 0 | I10: ='SALDOS POR NOTA'!H23 -> 0 | J10: 0 | K10: =D10-E10-F10-G10-H10-I10-J10 -> 0 | L10: 0 | M10: =K10-L10 -> 0 | N10: ='SALDOS POR NOTA'!I23 -> 0 | O10: =M10+N10 -> 0 | S10: 2 | T10: LIMPIEZA METROPOLITANA S.A. ESP. | U10: ='SALDOS POR NOTA'!J23 -> 0 | V10: ='SALDOS POR NOTA'!K23 -> 0 | W10: ='SALDOS POR NOTA'!L23 -> 0 | X10: ='SALDOS POR NOTA'!M23 -> 0 | Y10: ='SALDOS POR NOTA'!N23 -> 0 | Z10: =L10*-1 -> 0 | AA10: ='SALDOS POR NOTA'!O23 -> 0 | AB10: =N10 -> 0 | AC10: =-J10+AD10 -> 0 | AD10: ='SALDOS POR NOTA'!C24 -> 0 | AE10: =SUM(U10:AC10) -> 0 | AF10: =(AE10-O10) -> 0 | AG10: =AF10=0 -> TRUE
B11: 3 | C11: CIUDAD LIMPIA BOGOTA S.A. ESP. | D11: ='SALDOS POR NOTA'!C36 -> 0 | E11: ='SALDOS POR NOTA'!D36 -> 0 | F11: ='SALDOS POR NOTA'!E36 -> 0 | G11: ='SALDOS POR NOTA'!F36 -> 0 | H11: ='SALDOS POR NOTA'!G36 -> 0 | I11: ='SALDOS POR NOTA'!H36 -> 0 | J11: 0 | K11: =D11-E11-F11-G11-H11-I11-J11 -> 0 | L11: 0 | M11: =K11-L11 -> 0 | N11: ='SALDOS POR NOTA'!I36 -> 0 | O11: =M11+N11 -> 0 | S11: 3 | T11: CIUDAD LIMPIA BOGOTA S.A. ESP. | U11: ='SALDOS POR NOTA'!J36 -> 0 | V11: ='SALDOS POR NOTA'!K36 -> 0 | W11: ='SALDOS POR NOTA'!L36 -> 0 | X11: ='SALDOS POR NOTA'!M36 -> 0 | Y11: ='SALDOS POR NOTA'!N36 -> 0 | Z11: =L11*-1 -> 0 | AA11: ='SALDOS POR NOTA'!O36 -> 0 | AB11: =N11 -> 0 | AC11: =-J11+AD11 -> 0 | AD11: ='SALDOS POR NOTA'!C37 -> 0 | AE11: =SUM(U11:AC11) -> 0 | AF11: =(AE11-O11) -> 0 | AG11: =AF11=0 -> TRUE
B12: 4 | C12: BOGOTA LIMPIA S.A.S. ESP. | D12: ='SALDOS POR NOTA'!C49 -> 0 | E12: ='SALDOS POR NOTA'!D49 -> 0 | F12: ='SALDOS POR NOTA'!E49 -> 0 | G12: ='SALDOS POR NOTA'!F49 -> 0 | H12: ='SALDOS POR NOTA'!G49 -> 0 | I12: ='SALDOS POR NOTA'!H49 -> 0 | J12: 0 | K12: =D12-E12-F12-G12-H12-I12-J12 -> 0 | L12: 0 | M12: =K12-L12 -> 0 | N12: ='SALDOS POR NOTA'!I49 -> 0 | O12: =M12+N12 -> 0 | S12: 4 | T12: BOGOTA LIMPIA S.A.S. ESP. | U12: ='SALDOS POR NOTA'!J49 -> 0 | V12: ='SALDOS POR NOTA'!K49 -> 0 | W12: ='SALDOS POR NOTA'!L49 -> 0 | X12: ='SALDOS POR NOTA'!M49 -> 0 | Y12: ='SALDOS POR NOTA'!N49 -> 0 | Z12: =L12*-1 -> 0 | AA12: ='SALDOS POR NOTA'!O49 -> 0 | AB12: =N12 -> 0 | AC12: =-J12+AD12 -> 0 | AD12: ='SALDOS POR NOTA'!C50 -> 0 | AE12: =SUM(U12:AC12) -> 0 | AF12: =(AE12-O12) -> 0 | AG12: =AF12=0 -> TRUE
B13: 5 | C13: AREA LIMPIA DISTRITO CAPITAL S.A.S. ESP. | D13: ='SALDOS POR NOTA'!C62 -> 0 | E13: ='SALDOS POR NOTA'!D62 -> 0 | F13: ='SALDOS POR NOTA'!E62 -> 0 | G13: ='SALDOS POR NOTA'!F62 -> 0 | H13: ='SALDOS POR NOTA'!G62 -> 0 | I13: ='SALDOS POR NOTA'!H62 -> 0 | J13: 0 | K13: =D13-E13-F13-G13-H13-I13-J13 -> 0 | L13: 0 | M13: =K13-L13 -> 0 | N13: ='SALDOS POR NOTA'!I62 -> 0 | O13: =M13+N13 -> 0 | S13: 5 | T13: AREA LIMPIA DISTRITO CAPITAL S.A.S. ESP. | U13: ='SALDOS POR NOTA'!J62 -> 0 | V13: ='SALDOS POR NOTA'!K62 -> 0 | W13: ='SALDOS POR NOTA'!L62 -> 0 | X13: ='SALDOS POR NOTA'!M62 -> 0 | Y13: ='SALDOS POR NOTA'!N62 -> 0 | Z13: =L13*-1 -> 0 | AA13: ='SALDOS POR NOTA'!O62 -> 0 | AB13: =N13 -> 0 | AC13: =-J13+AD13 -> 0 | AD13: ='SALDOS POR NOTA'!C63 -> 0 | AE13: =SUM(U13:AC13) -> 0 | AF13: =(AE13-O13) -> 0 | AG13: =AF13=0 -> TRUE
C14: TOTAL | D14: =SUM(D9:D13) -> 0 | E14: =SUM(E9:E13) -> 0 | F14: =SUM(F9:F13) -> 0 | G14: =SUM(G9:G13) -> 0 | H14: =SUM(H9:H13) -> 0 | I14: =SUM(I9:I13) -> 0 | J14: =SUM(J9:J13) -> 0 | K14: =SUM(K9:K13) -> 0 | ... O14: =SUM(O9:O13) -> 0 | T14: TOTAL | U14: =SUM(U9:U13) -> 0 | V14: =SUM(V9:V13) -> 0 | W14: =SUM(W9:W13) -> 0 | X14: =SUM(X9:X13) -> 0 | Y14: =SUM(Y9:Y13) -> 0 | Z14: =SUM(Z9:Z13) -> 0 | AA14: =SUM(AA9:AA13) -> 0 | AB14: =SUM(AB9:AB13) -> 0 | ... AF14: =SUM(AF9:AF13) -> 0 | AG14: =AF14=0 -> TRUE
Y16: =SUM(U14:Y14) -> 0
F18: Firma autorizada
F22: PROCERASEO S.A.S. | I22: NIT: 901 153 639 - 0 | M22: Codigo Remuneración: | N22: =N3 -> 2026101 | U22: PROCERASEO S.A.S. | W22: NIT: 901 153 639 - 0 | AA22: Codigo Remuneración: | AC22: =N22 -> 2026101
F23: 3. ESQUEMA FINANCIERO DEL SERVICIO PUBLICO DE ASEO | U23: 3. ESQUEMA FINANCIERO DEL SERVICIO PUBLICO DE ASEO
F24: Resoluciòn UAESP Número 27 de 2018 | U24: Resoluciòn UAESP Número 27 de 2018
C25: Fecha de Proceso: | D25: =D6 -> 46314 | F25: RETRIBUCION NEGATIVA | U25: =+F25 -> RETRIBUCION NEGATIVA
C26: Hora: | D26: =D7 -> 0.58333333 | F26: Fecha Desde: | H26: =H7 -> 46296 | J26: Feha Hasta: | K26: =K7 -> 46310 | U26: =F26 -> Fecha Desde: | V26: =H26 -> 46296 | X26: =J26 -> Feha Hasta: | Y26: =K26 -> 46310
B27: ASE | C27: Concesionarios | D27: Recaudo Total | E27: Recaudo por disposicion final | F27: Recaudo por tratamiento de lixiviados | G27: Recaudo por Componente VIAT ( Decreto 2412/2018) | H27: Recaudo por aprovechamiento | I27: Recaudo del componente de comercializacion para Aprovechamiento (11,4%) | J27: Balance de subsidio o contribuciones | K27: RECAUDO BASE DE REMUNERACION | L27: Costo de la Interventoría | M27: REMUNERACION FINAL | N27: Conceptos especiales | O27: REMUNERACION FINAL MAS CONCEPTOS ESPECIALES | S27: ASE | T27: Concesionarios | U27: Tarifa de Comercialización del Servicio. ( TCS) | V27: Tarifa de Limpieza Urbana del Servicio. ( TLU) | W27: Tarifa de Barrido y Limpieza del Servicio. ( TBL) | X27: Tarifa de Recolección y Transporte del Servicio. (TRT) | Y27: Recaudo del componente de comercializacion para Aprovechamiento (18,6%) | Z27: Costo de la Interventoría | AA27: Ajuste a la decena | AB27: Conceptos especiales | AC27: Diferencial Balance S / C (Fac vs Rec) | AD27: Balance S / C Con Baase en (Recaudo) | AE27: REMUNERACION FINAL MAS CONCEPTOS ESPECIALES
B28: 1 | C28: PROMOAMBIENTAL DISTRITO S.A.S. ESP. | D28: ='RETRIBUCION NEGATIVA'!C10 -> 0 | E28: ='RETRIBUCION NEGATIVA'!D10 -> 0 | F28: ='RETRIBUCION NEGATIVA'!E10 -> 0 | G28: ='RETRIBUCION NEGATIVA'!F10 -> 0 | H28: ='RETRIBUCION NEGATIVA'!G10 -> 0 | I28: ='RETRIBUCION NEGATIVA'!H10 -> 0 | J28: 0 | K28: =D28-E28-F28-H28-I28-J28-G28 -> 0 | L28: 0 | M28: =K28-L28 -> 0 | N28: ='RETRIBUCION NEGATIVA'!I10 -> 0 | O28: =M28+N28 -> 0 | S28: 1 | T28: PROMOAMBIENTAL DISTRITO S.A.S. ESP. | U28: ='RETRIBUCION NEGATIVA'!J10 -> 0 | V28: ='RETRIBUCION NEGATIVA'!K10 -> 0 | W28: ='RETRIBUCION NEGATIVA'!L10 -> 0 | X28: ='RETRIBUCION NEGATIVA'!M10 -> 0 | Y28: ='RETRIBUCION NEGATIVA'!N10 -> 0 | Z28: =L28*-1 -> 0 | AA28: ='RETRIBUCION NEGATIVA'!O10 -> 0 | AB28: =N28 -> 0 | AC28: =-J28+AD28 -> 0 | AD28: ='RETRIBUCION NEGATIVA'!C11 -> 0 | AE28: =SUM(U28:AC28) -> 0 | AF28: =(AE28-O28) -> 0 | AG28: =AF28=0 -> TRUE
B29: 2 | C29: LIMPIEZA METROPOLITANA S.A. ESP. | D29: ='RETRIBUCION NEGATIVA'!C23 -> 0 | E29: ='RETRIBUCION NEGATIVA'!D23 -> 0 | F29: ='RETRIBUCION NEGATIVA'!E23 -> 0 | G29: ='RETRIBUCION NEGATIVA'!F23 -> 0 | H29: ='RETRIBUCION NEGATIVA'!G23 -> 0 | I29: ='RETRIBUCION NEGATIVA'!H23 -> 0 | J29: 0 | K29: =D29-E29-F29-H29-I29-J29-G29 -> 0 | L29: 0 | M29: =K29-L29 -> 0 | N29: ='RETRIBUCION NEGATIVA'!I23 -> 0 | O29: =M29+N29 -> 0 | S29: 2 | T29: LIMPIEZA METROPOLITANA S.A. ESP. | U29: ='RETRIBUCION NEGATIVA'!J23 -> 0 | V29: ='RETRIBUCION NEGATIVA'!K23 -> 0 | W29: ='RETRIBUCION NEGATIVA'!L23 -> 0 | X29: ='RETRIBUCION NEGATIVA'!M23 -> 0 | Y29: ='RETRIBUCION NEGATIVA'!N23 -> 0 | Z29: =L29*-1 -> 0 | AA29: ='RETRIBUCION NEGATIVA'!O23 -> 0 | AB29: =N29 -> 0 | AC29: =-J29+AD29 -> 0 | AD29: ='RETRIBUCION NEGATIVA'!C24 -> 0 | AE29: =SUM(U29:AC29) -> 0 | AF29: =(AE29-O29) -> 0 | AG29: =AF29=0 -> TRUE
B30: 3 | C30: CIUDAD LIMPIA BOGOTA S.A. ESP. | D30: ='RETRIBUCION NEGATIVA'!C36 -> 0 | E30: ='RETRIBUCION NEGATIVA'!D36 -> 0 | F30: ='RETRIBUCION NEGATIVA'!E36 -> 0 | G30: ='RETRIBUCION NEGATIVA'!F36 -> 0 | H30: ='RETRIBUCION NEGATIVA'!G36 -> 0 | I30: ='RETRIBUCION NEGATIVA'!H36 -> 0 | J30: 0 | K30: =D30-E30-F30-H30-I30-J30-G30 -> 0 | L30: 0 | M30: =K30-L30 -> 0 | N30: ='RETRIBUCION NEGATIVA'!I36 -> 0 | O30: =M30+N30 -> 0 | S30: 3 | T30: CIUDAD LIMPIA BOGOTA S.A. ESP. | U30: ='RETRIBUCION NEGATIVA'!J36 -> 0 | V30: ='RETRIBUCION NEGATIVA'!K36 -> 0 | W30: ='RETRIBUCION NEGATIVA'!L36 -> 0 | X30: ='RETRIBUCION NEGATIVA'!M36 -> 0 | Y30: ='RETRIBUCION NEGATIVA'!N36 -> 0 | Z30: =L30*-1 -> 0 | AA30: ='RETRIBUCION NEGATIVA'!O36 -> 0 | AB30: =N30 -> 0 | AC30: =-J30+AD30 -> 0 | AD30: ='RETRIBUCION NEGATIVA'!C37 -> 0 | AE30: =SUM(U30:AC30) -> 0 | AF30: =(AE30-O30) -> 0 | AG30: =AF30=0 -> TRUE
B31: 4 | C31: BOGOTA LIMPIA S.A.S. ESP. | D31: ='RETRIBUCION NEGATIVA'!C49 -> 0 | E31: ='RETRIBUCION NEGATIVA'!D49 -> 0 | F31: ='RETRIBUCION NEGATIVA'!E49 -> 0 | G31: ='RETRIBUCION NEGATIVA'!F49 -> 0 | H31: ='RETRIBUCION NEGATIVA'!G49 -> 0 | I31: ='RETRIBUCION NEGATIVA'!H49 -> 0 | J31: 0 | K31: =D31-E31-F31-H31-I31-J31-G31 -> 0 | L31: 0 | M31: =K31-L31 -> 0 | N31: ='RETRIBUCION NEGATIVA'!I49 -> 0 | O31: =M31+N31 -> 0 | S31: 4 | T31: BOGOTA LIMPIA S.A.S. ESP. | U31: ='RETRIBUCION NEGATIVA'!J49 -> 0 | V31: ='RETRIBUCION NEGATIVA'!K49 -> 0 | W31: ='RETRIBUCION NEGATIVA'!L49 -> 0 | X31: ='RETRIBUCION NEGATIVA'!M49 -> 0 | Y31: ='RETRIBUCION NEGATIVA'!N49 -> 0 | Z31: =L31*-1 -> 0 | AA31: ='RETRIBUCION NEGATIVA'!O49 -> 0 | AB31: =N31 -> 0 | AC31: =-J31+AD31 -> 0 | AD31: ='RETRIBUCION NEGATIVA'!C50 -> 0 | AE31: =SUM(U31:AC31) -> 0 | AF31: =(AE31-O31) -> 0 | AG31: =AF31=0 -> TRUE
B32: 5 | C32: AREA LIMPIA DISTRITO CAPITAL S.A.S. ESP. | D32: ='RETRIBUCION NEGATIVA'!C61 -> 0 | E32: ='RETRIBUCION NEGATIVA'!D61 -> 0 | F32: ='RETRIBUCION NEGATIVA'!E61 -> 0 | G32: ='RETRIBUCION NEGATIVA'!F61 -> 0 | H32: ='RETRIBUCION NEGATIVA'!G61 -> 0 | I32: ='RETRIBUCION NEGATIVA'!H61 -> 0 | J32: 0 | K32: =D32-E32-F32-H32-I32-J32-G32 -> 0 | L32: 0 | M32: =K32-L32 -> 0 | N32: ='RETRIBUCION NEGATIVA'!I61 -> 0 | O32: =M32+N32 -> 0 | S32: 5 | T32: AREA LIMPIA DISTRITO CAPITAL S.A.S. ESP. | U32: ='RETRIBUCION NEGATIVA'!J61 -> 0 | V32: ='RETRIBUCION NEGATIVA'!K61 -> 0 | W32: ='RETRIBUCION NEGATIVA'!L61 -> 0 | X32: ='RETRIBUCION NEGATIVA'!M61 -> 0 | Y32: ='RETRIBUCION NEGATIVA'!N61 -> 0 | Z32: =L32*-1 -> 0 | AA32: ='RETRIBUCION NEGATIVA'!O61 -> 0 | AB32: =N32 -> 0 | AC32: =-J32+AD32 -> 0 | AD32: ='RETRIBUCION NEGATIVA'!C62 -> 0 | AE32: =SUM(U32:AC32) -> 0 | AF32: =(AE32-O32) -> 0 | AG32: =AF32=0 -> TRUE
C33: TOTAL | D33: =SUM(D28:D32) -> 0 | E33: =SUM(E28:E32) -> 0 | F33: =SUM(F28:F32) -> 0 | G33: =SUM(G28:G32) -> 0 | H33: =SUM(H28:H32) -> 0 | I33: =SUM(I28:I32) -> 0 | J33: =SUM(J28:J32) -> 0 | K33: =SUM(K28:K32) -> 0 | ... O33: =SUM(O28:O32) -> 0 | T33: TOTAL | U33: =SUM(U28:U32) -> 0 | V33: =SUM(V28:V32) -> 0 | W33: =SUM(W28:W32) -> 0 | X33: =SUM(X28:X32) -> 0 | Y33: =SUM(Y28:Y32) -> 0 | Z33: =SUM(Z28:Z32) -> 0 | AA33: =SUM(AA28:AA32) -> 0 | AB33: =SUM(AB28:AB32) -> 0 | ... AF33: =SUM(AF28:AF32) -> 0 | AG33: =AF33=0 -> TRUE
J35: VALIDADOR DE POSTIVIOS EN REMUNERACION NEGATIVA | M35: =IF(MAX(D28:O32,U28:AE32)>0.9,"ERROR",TRUE) -> TRUE | Y35: =SUM(U33:Y33) -> 0
F37: Firma autorizada
F41: PROCERASEO S.A.S. | I41: NIT: 901 153 639 - 0 | M41: Codigo Remuneración: | N41: =N3 -> 2026101 | U41: PROCERASEO S.A.S. | W41: NIT: 901 153 639 - 0 | AA41: Codigo Remuneración: | AC41: =N41 -> 2026101
F42: 3. ESQUEMA FINANCIERO DEL SERVICIO PUBLICO DE ASEO | U42: 3. ESQUEMA FINANCIERO DEL SERVICIO PUBLICO DE ASEO
F43: Resoluciòn UAESP Número 27 de 2018 | U43: Resoluciòn UAESP Número 27 de 2018
C44: Fecha de Proceso: | D44: =D6 -> 46314 | F44: CONSOLIDADO SALDOS A FAVOR | U44: =+F44 -> CONSOLIDADO SALDOS A FAVOR
C45: Hora: | D45: =D7 -> 0.58333333 | F45: Fecha Desde: | H45: =H7 -> 46296 | J45: Feha Hasta: | K45: =K7 -> 46310 | U45: =F45 -> Fecha Desde: | V45: =H45 -> 46296 | X45: =J45 -> Feha Hasta: | Y45: =K45 -> 46310
B46: ASE | C46: Concesionarios | D46: Recaudo Total | E46: Recaudo por disposicion final | F46: Recaudo por tratamiento de lixiviados | G46: Recaudo por Componente VIAT ( Decreto 2412/2018) | H46: Recaudo por aprovechamiento | I46: Recaudo del componente de comercializacion para Aprovechamiento (11,4%) | J46: Balance de subsidio o contribuciones | K46: RECAUDO BASE DE REMUNERACION | L46: Costo de la Interventoría | M46: REMUNERACION FINAL | N46: Conceptos especiales | O46: REMUNERACION FINAL MAS CONCEPTOS ESPECIALES | S46: ASE | T46: Concesionarios | U46: Tarifa de Comercialización del Servicio. ( TCS) | V46: Tarifa de Limpieza Urbana del Servicio. ( TLU) | W46: Tarifa de Barrido y Limpieza del Servicio. ( TBL) | X46: Tarifa de Recolección y Transporte del Servicio. (TRT) | Y46: Recaudo del componente de comercializacion para Aprovechamiento (18,6%) | Z46: Costo de la Interventoría | AA46: Ajuste a la decena | AB46: Conceptos especiales | AC46: Diferencial Balance S / C (Fac vs Rec) | AD46: Balance S / C Con Baase en (Recaudo) | AE46: REMUNERACION FINAL MAS CONCEPTOS ESPECIALES
B47: 1 | C47: PROMOAMBIENTAL DISTRITO S.A.S. ESP. | D47: =D9+D28 -> 0 | E47: =E9+E28 -> 0 | F47: =F9+F28 -> 0 | G47: =G9+G28 -> 0 | H47: =H9+H28 -> 0 | I47: =I9+I28 -> 0 | J47: =J9+J28 -> 0 | K47: =D47-E47-F47-G47-H47-I47-J47 -> 0 | L47: 0 | M47: =K47-L47 -> 0 | N47: =N9+N28 -> 0 | O47: =M47+N47 -> 0 | S47: 1 | T47: PROMOAMBIENTAL DISTRITO S.A.S. ESP. | U47: =U9+U28 -> 0 | V47: =V9+V28 -> 0 | W47: =W9+W28 -> 0 | X47: =X9+X28 -> 0 | Y47: =Y9+Y28 -> 0 | Z47: =-L47 -> 0 | AA47: =AA9+AA28 -> 0 | AB47: =AB9+AB28 -> 0 | AC47: =AC9+AC28 -> 0 | AD47: =AD9+AD28 -> 0 | AE47: =SUM(U47:AC47) -> 0 | AF47: =(AE47-O47) -> 0 | AG47: =AF47=0 -> TRUE
B48: 2 | C48: LIMPIEZA METROPOLITANA S.A. ESP. | D48: =D10+D29 -> 0 | E48: =E10+E29 -> 0 | F48: =F10+F29 -> 0 | G48: =G10+G29 -> 0 | H48: =H10+H29 -> 0 | I48: =I10+I29 -> 0 | J48: =J10+J29 -> 0 | K48: =D48-E48-F48-G48-H48-I48-J48 -> 0 | L48: 0 | M48: =K48-L48 -> 0 | N48: =N10+N29 -> 0 | O48: =M48+N48 -> 0 | S48: 2 | T48: LIMPIEZA METROPOLITANA S.A. ESP. | U48: =U10+U29 -> 0 | V48: =V10+V29 -> 0 | W48: =W10+W29 -> 0 | X48: =X10+X29 -> 0 | Y48: =Y10+Y29 -> 0 | Z48: =-L48 -> 0 | AA48: =AA10+AA29 -> 0 | AB48: =AB10+AB29 -> 0 | AC48: =AC10+AC29 -> 0 | AD48: =AD10+AD29 -> 0 | AE48: =SUM(U48:AC48) -> 0 | AF48: =(AE48-O48) -> 0 | AG48: =AF48=0 -> TRUE
B49: 3 | C49: CIUDAD LIMPIA BOGOTA S.A. ESP. | D49: =D11+D30 -> 0 | E49: =E11+E30 -> 0 | F49: =F11+F30 -> 0 | G49: =G11+G30 -> 0 | H49: =H11+H30 -> 0 | I49: =I11+I30 -> 0 | J49: =J11+J30 -> 0 | K49: =D49-E49-F49-G49-H49-I49-J49 -> 0 | L49: 0 | M49: =K49-L49 -> 0 | N49: =N11+N30 -> 0 | O49: =M49+N49 -> 0 | S49: 3 | T49: CIUDAD LIMPIA BOGOTA S.A. ESP. | U49: =U11+U30 -> 0 | V49: =V11+V30 -> 0 | W49: =W11+W30 -> 0 | X49: =X11+X30 -> 0 | Y49: =Y11+Y30 -> 0 | Z49: =-L49 -> 0 | AA49: =AA11+AA30 -> 0 | AB49: =AB11+AB30 -> 0 | AC49: =AC11+AC30 -> 0 | AD49: =AD11+AD30 -> 0 | AE49: =SUM(U49:AC49) -> 0 | AF49: =(AE49-O49) -> 0 | AG49: =AF49=0 -> TRUE
B50: 4 | C50: BOGOTA LIMPIA S.A.S. ESP. | D50: =D12+D31 -> 0 | E50: =E12+E31 -> 0 | F50: =F12+F31 -> 0 | G50: =G12+G31 -> 0 | H50: =H12+H31 -> 0 | I50: =I12+I31 -> 0 | J50: =J12+J31 -> 0 | K50: =D50-E50-F50-G50-H50-I50-J50 -> 0 | L50: 0 | M50: =K50-L50 -> 0 | N50: =N12+N31 -> 0 | O50: =M50+N50 -> 0 | S50: 4 | T50: BOGOTA LIMPIA S.A.S. ESP. | U50: =U12+U31 -> 0 | V50: =V12+V31 -> 0 | W50: =W12+W31 -> 0 | X50: =X12+X31 -> 0 | Y50: =Y12+Y31 -> 0 | Z50: =-L50 -> 0 | AA50: =AA12+AA31 -> 0 | AB50: =AB12+AB31 -> 0 | AC50: =AC12+AC31 -> 0 | AD50: =AD12+AD31 -> 0 | AE50: =SUM(U50:AC50) -> 0 | AF50: =(AE50-O50) -> 0 | AG50: =AF50=0 -> TRUE
B51: 5 | C51: AREA LIMPIA DISTRITO CAPITAL S.A.S. ESP. | D51: =D13+D32 -> 0 | E51: =E13+E32 -> 0 | F51: =F13+F32 -> 0 | G51: =G13+G32 -> 0 | H51: =H13+H32 -> 0 | I51: =I13+I32 -> 0 | J51: =J13+J32 -> 0 | K51: =D51-E51-F51-G51-H51-I51-J51 -> 0 | L51: 0 | M51: =K51-L51 -> 0 | N51: =N13+N32 -> 0 | O51: =M51+N51 -> 0 | S51: 5 | T51: AREA LIMPIA DISTRITO CAPITAL S.A.S. ESP. | U51: =U13+U32 -> 0 | V51: =V13+V32 -> 0 | W51: =W13+W32 -> 0 | X51: =X13+X32 -> 0 | Y51: =Y13+Y32 -> 0 | Z51: =-L51 -> 0 | AA51: =AA13+AA32 -> 0 | AB51: =AB13+AB32 -> 0 | AC51: =AC13+AC32 -> 0 | AD51: =AD13+AD32 -> 0 | AE51: =SUM(U51:AC51) -> 0 | AF51: =(AE51-O51) -> 0 | AG51: =AF51=0 -> TRUE
C52: TOTAL | D52: =SUM(D47:D51) -> 0 | E52: =SUM(E47:E51) -> 0 | F52: =SUM(F47:F51) -> 0 | G52: =SUM(G47:G51) -> 0 | H52: =SUM(H47:H51) -> 0 | I52: =SUM(I47:I51) -> 0 | J52: =SUM(J47:J51) -> 0 | K52: =SUM(K47:K51) -> 0 | ... O52: =SUM(O47:O51) -> 0 | T52: TOTAL | U52: =SUM(U47:U51) -> 0 | V52: =SUM(V47:V51) -> 0 | W52: =SUM(W47:W51) -> 0 | X52: =SUM(X47:X51) -> 0 | Y52: =SUM(Y47:Y51) -> 0 | Z52: =SUM(Z47:Z51) -> 0 | AA52: =SUM(AA47:AA51) -> 0 | AB52: =SUM(AB47:AB51) -> 0 | ... AF52: =SUM(AF47:AF51) -> 0 | AG52: =AF52=0 -> TRUE
Y54: =SUM(U52:Y52) -> 0
F56: Firma autorizada

Sheet INTERVENTORIA
F2: 2026 01 2 | G2: 2026 02 1 | H2: 2026 02 2 | I2: 2026 03 1 | J2: 2026 03 2 | K2: 2026 04 1 | L2: 2026 04 2 | M2: 2026 05 1 | N2: 2026 05 2 | O2: 2026 06 1 | P2: 2026 06 2 | Q2: 2026 07 1
B3: VALOR MES | C3: ASE | D3: Concesionarios | E3: % | F3: MITAD 1 // ENERO -26 | G3: MITAD 2 // ENERO -26 | H3: MITAD 1 // FEBRERO -26 | I3: MITAD 2 // FEBRERO -26 | J3: MITAD 1 // MARZO -26 | K3: MITAD 2 // MARZO -26 | L3: MITAD 1 // ABRIL -26 | M3: MITAD 2 // ABRIL -26 | N3: MITAD 1 // MAYO -26 | O3: MITAD 2 // MAYO -26 | P3: MITAD 1 // JUNIO -26 | Q3: MITAD 2 // JUNIO -26
B4: 378371975 | C4: 1 | D4: PROMOAMBIENTAL DISTRITO S.A.S. ESP. | E4: 0.22 | F4: 189185988 | G4: 189185987 | H4: 189185988 | I4: 189185987 | J4: 189185988 | K4: 189185987 | L4: 189185988 | M4: 189185987 | N4: 189185988 | O4: 189185987 | P4: 189185988 | Q4: 189185987
B5: 533160511 | C5: 2 | D5: LIMPIEZA METROPOLITANA S.A. ESP. | E5: 0.31 | F5: 266580256 | G5: 266580255 | H5: 266580256 | I5: 266580255 | J5: 266580256 | K5: 266580255 | L5: 266580256 | M5: 266580255 | N5: 266580256 | O5: 266580255 | P5: 266580256 | Q5: 266580255
B6: 309577071 | C6: 3 | D6: CIUDAD LIMPIA BOGOTA S.A. ESP. | E6: 0.18 | F6: 154788536 | G6: 154788535 | H6: 154788536 | I6: 154788535 | J6: 154788536 | K6: 154788535 | L6: 154788536 | M6: 154788535 | N6: 154788536 | O6: 154788535 | P6: 154788536 | Q6: 154788535
B7: 240782166 | C7: 4 | D7: BOGOTA LIMPIA S.A.S. ESP. | E7: 0.14 | F7: 120391083 | G7: 120391083 | H7: 120391083 | I7: 120391083 | J7: 120391083 | K7: 120391083 | L7: 120391083 | M7: 120391083 | N7: 120391083 | O7: 120391083 | P7: 120391083 | Q7: 120391083
B8: 257980891 | C8: 5 | D8: AREA LIMPIA DISTRITO CAPITAL S.A.S. ESP. | E8: 0.15 | F8: 128990446 | G8: 128990445 | H8: 128990446 | I8: 128990445 | J8: 128990446 | K8: 128990445 | L8: 128990446 | M8: 128990445 | N8: 128990446 | O8: 128990445 | P8: 128990446 | Q8: 128990445
B9: 1719872614 | D9: TOTAL | E9: 1 | F9: 859936309 | G9: 859936305 | H9: 859936309 | I9: 859936305 | J9: 859936309 | K9: 859936305 | L9: 859936309 | M9: 859936305 | N9: 859936309 | O9: 859936305 | P9: 859936309 | Q9: 859936305
F10: =SUM(F9:G9) -> 1719872614 | H10: =SUM(H9:I9) -> 1719872614 | J10: =SUM(J9:K9) -> 1719872614 | L10: =SUM(L9:M9) -> 1719872614 | N10: =SUM(N9:O9) -> 1719872614 | P10: =SUM(P9:Q9) -> 1719872614
F13: 2026 07 2 | G13: 2026 08 1 | H13: 2026 08 2 | I13: 2026 09 1 | J13: 2026 09 2 | K13: 2026 10 1 | L13: 2026 10 2 | M13: 2026 11 1 | N13: 2026 11 2 | O13: 2026 12 1 | P13: 2026 12 2 | Q13: 2027 01 1
C14: ASE | D14: Concesionarios | E14: % | F14: MITAD 1 // JULIO -26 | G14: MITAD 2 // JULIO -26 | H14: MITAD 1 // AGOSTO -26 | I14: MITAD 2 // AGOSTO -26 | J14: MITAD 1 // SEPTIEMBRE -26 | K14: MITAD 2 // SEPTIEMBRE -26 | L14: MITAD 1 // OCTUBRE -26 | M14: MITAD 2 // OCTUBRE -26 | N14: MITAD 1 // NOVIEMBRE -26 | O14: MITAD 2 // NOVIEMBRE -26 | P14: MITAD 1 // DICIEMBRE -26 | Q14: MITAD 2 // DICIEMBRE -26
C15: 1 | D15: PROMOAMBIENTAL DISTRITO S.A.S. ESP. | E15: 0.22 | F15: 189185988 | G15: 189185987 | H15: 189185988 | I15: 189185987 | J15: 189185988 | K15: 189185987 | L15: 189185988 | M15: 189185987 | N15: 189185988 | O15: 189185987 | P15: 189185988 | Q15: 189185987
C16: 2 | D16: LIMPIEZA METROPOLITANA S.A. ESP. | E16: 0.31 | F16: 266580256 | G16: 266580255 | H16: 266580256 | I16: 266580255 | J16: 266580256 | K16: 266580255 | L16: 266580256 | M16: 266580255 | N16: 266580256 | O16: 266580255 | P16: 266580256 | Q16: 266580255
C17: 3 | D17: CIUDAD LIMPIA BOGOTA S.A. ESP. | E17: 0.18 | F17: 154788536 | G17: 154788535 | H17: 154788536 | I17: 154788535 | J17: 154788536 | K17: 154788535 | L17: 154788536 | M17: 154788535 | N17: 154788536 | O17: 154788535 | P17: 154788536 | Q17: 154788535
C18: 4 | D18: BOGOTA LIMPIA S.A.S. ESP. | E18: 0.14 | F18: 120391083 | G18: 120391083 | H18: 120391083 | I18: 120391083 | J18: 120391083 | K18: 120391083 | L18: 120391083 | M18: 120391083 | N18: 120391083 | O18: 120391083 | P18: 120391083 | Q18: 120391083
C19: 5 | D19: AREA LIMPIA DISTRITO CAPITAL S.A.S. ESP. | E19: 0.15 | F19: 128990446 | G19: 128990445 | H19: 128990446 | I19: 128990445 | J19: 128990446 | K19: 128990445 | L19: 128990446 | M19: 128990445 | N19: 128990446 | O19: 128990445 | P19: 128990446 | Q19: 128990445
D20: TOTAL | E20: 1 | F20: 859936309 | G20: 859936305 | H20: 859936309 | I20: 859936305 | J20: 859936309 | K20: 859936305 | L20: 859936309 | M20: 859936305 | N20: 859936309 | O20: 859936305 | P20: 859936309 | Q20: 859936305
F21: =SUM(F20:G20) -> 1719872614 | G21: 1191383498 | H21: =SUM(H20:I20) -> 1719872614 | I21: 1191383498 | J21: =SUM(J20:K20) -> 1719872614 | K21: 1191383498 | L21: =SUM(L20:M20) -> 1719872614 | M21: 1191383498 | N21: =SUM(N20:O20) -> 1719872614 | O21: 1191383498 | P21: =SUM(P20:Q20) -> 1719872614 | Q21: 1191383498
K25: VALOR OFICIAL MES | L25: ASE | M25: Segunda quincena | N25: Primera quincena | R25: VALIDACION
K26: 378371975 | L26: 1 | M26: 189185988 | N26: 189185987 | O26: =N26=R26 -> TRUE | Q26: ='CONSOLIDADO_TOTAL RECAUDO'!L104 -> 189185987 | R26: =K15 -> 189185987 | S26: =Q26=R26 -> TRUE
K27: 533160511 | L27: 2 | M27: 266580256 | N27: 266580255 | O27: =N27=R27 -> TRUE | Q27: ='CONSOLIDADO_TOTAL RECAUDO'!L105 -> 266580255 | R27: =K16 -> 266580255 | S27: =Q27=R27 -> TRUE
K28: 309577071 | L28: 3 | M28: 154788536 | N28: 154788535 | O28: =N28=R28 -> TRUE | Q28: ='CONSOLIDADO_TOTAL RECAUDO'!L106 -> 154788535 | R28: =K17 -> 154788535 | S28: =Q28=R28 -> TRUE
K29: 240782166 | L29: 4 | M29: 120391083 | N29: 120391083 | O29: =N29=R29 -> TRUE | Q29: ='CONSOLIDADO_TOTAL RECAUDO'!L107 -> 120391083 | R29: =K18 -> 120391083 | S29: =Q29=R29 -> TRUE
K30: 257980891 | L30: 5 | M30: 128990446 | N30: 128990445 | O30: =N30=R30 -> TRUE | Q30: ='CONSOLIDADO_TOTAL RECAUDO'!L108 -> 128990445 | R30: =K19 -> 128990445 | S30: =Q30=R30 -> TRUE
K31: =SUM(K26:K30) -> 1719872614 | M31: =SUM(M26:M30) -> 859936309 | N31: =SUM(N26:N30) -> 859936305 | O31: =N31=R31 -> TRUE | Q31: ='CONSOLIDADO_TOTAL RECAUDO'!L109 -> 859936305 | R31: =K20 -> 859936305 | S31: =Q31=R31 -> TRUE
K32: =SUM(M31:N31) -> 1719872614

Sheet Informe AFaseo Recaudo 202610-1
D5: PROCERASEO S.A.S. | I5: NIT: 901 153 639 - 0 | P5: PROCERASEO S.A.S. | T5: NIT: 901 153 639 - 0
D6: INFORME Afaseo // RECAUDO | P6: INFORME AFaseo
D7: BENEFICIO TRANSITORIO ALIVIO SOBRE EL VALOR DE LA FACTURA | P7: BENEFICIO TRANSITORIO ALIVIO SOBRE EL VALOR DE LA FACTURA
D8: Según Resoluciòn UAESP Número 273 de 2.020 | P8: Según Resoluciòn UAESP Número 273 de 2.020
E10: Fecha Desde: | F10: ='CONSOLIDADO_TOTAL RECAUDO'!G102 -> 46296 | H10: Feha Hasta: | I10: ='CONSOLIDADO_TOTAL RECAUDO'!K102 -> 46310
B11: ASE | C11: Concesionarios | D11: Valor Afaseo | E11: Afaseo por disposicion final | F11: Afaseo por tratamiento de lixiviados | G11: Afaseo por Componente VIAT ( Decreto 2412/2018) | H11: Afaseo por aprovechamiento | I11: Afaseo del componente de comercializacion para Aprovechamiento (11,4%) | J11: Afaseo RBL | N11: ASE | O11: Concesionarios | P11: Tarifa de Comercialización del Servicio. ( TCS) | Q11: Tarifa de Limpieza Urbana del Servicio. ( TLU) | R11: Tarifa de Barrido y Limpieza del Servicio. ( TBL) | S11: Tarifa de Recolección y Transporte del Servicio. (TRT) | T11: Componente de comercialización para Aprovechamiento (18,6%) | U11: Afaseo RBL
B12: 1 | C12: PROMOAMBIENTAL DISTRITO S.A.S. ESP. | D12: ='Reporte Componentes R1'!F88*$D$24 -> 2015.07 | E12: ='Reporte Componentes R1'!G88*$D$24 -> 122.1 | F12: ='Reporte Componentes R1'!H88*$D$24 -> 51.87 | G12: ='Reporte Componentes R1'!I88*$D$24 -> 22.65 | H12: ='Reporte Componentes R1'!J88*$D$24 -> 369.44 | I12: ='Reporte Componentes R1'!K88*$D$24 -> 23.88 | J12: =D12-E12-F12-G12-H12-I12 -> 1425.13 | N12: 1 | O12: PROMOAMBIENTAL DISTRITO S.A.S. ESP. | P12: ='Reporte Componentes R1'!M88*$P$24 -> 209.4 | Q12: ='Reporte Componentes R1'!N88*$P$24 -> 175.25 | R12: ='Reporte Componentes R1'!O88*$P$24 -> 699.55 | S12: ='Reporte Componentes R1'!P88*$P$24 -> 301.98 | T12: ='Reporte Componentes R1'!Q88*$P$24 -> 38.95 | U12: =SUM(P12:T12) -> 1425.13 | V12: =J12-U12 -> 0 | W12: =V12=0 -> TRUE
B13: 2 | C13: LIMPIEZA METROPOLITANA S.A. ESP. | D13: ='Reporte Componentes R1'!F221*$D$24 -> 243714.65 | E13: ='Reporte Componentes R1'!G221*$D$24 -> 20951.02 | F13: ='Reporte Componentes R1'!H221*$D$24 -> 8900.5 | G13: ='Reporte Componentes R1'!I221*$D$24 -> 3886.81 | H13: ='Reporte Componentes R1'!J221*$D$24 -> 48437.8 | I13: ='Reporte Componentes R1'!K221*$D$24 -> 2062.98 | J13: =D13-E13-F13-G13-H13-I13 -> 159475.54 | N13: 2 | O13: LIMPIEZA METROPOLITANA S.A. ESP. | P13: ='Reporte Componentes R1'!M221*$P$24 -> 18096.09 | Q13: ='Reporte Componentes R1'!N221*$P$24 -> 22688.82 | R13: ='Reporte Componentes R1'!O221*$P$24 -> 76193.1 | S13: ='Reporte Componentes R1'!P221*$P$24 -> 39131.24 | T13: ='Reporte Componentes R1'!Q221*$P$24 -> 3366.29 | U13: =SUM(P13:T13) -> 159475.54 | V13: =J13-U13 -> 0 | W13: =V13=0 -> TRUE
B14: 3 | C14: CIUDAD LIMPIA BOGOTA S.A. ESP. | D14: ='Reporte Componentes R1'!F349*$D$24 -> 558.05 | E14: ='Reporte Componentes R1'!G349*$D$24 -> 36.43 | F14: ='Reporte Componentes R1'!H349*$D$24 -> 15.48 | G14: ='Reporte Componentes R1'!I349*$D$24 -> 6.76 | H14: ='Reporte Componentes R1'!J349*$D$24 -> 123.14 | I14: ='Reporte Componentes R1'!K349*$D$24 -> 4.99 | J14: =D14-E14-F14-G14-H14-I14 -> 371.25 | N14: 3 | O14: CIUDAD LIMPIA BOGOTA S.A. ESP. | P14: ='Reporte Componentes R1'!M349*$P$24 -> 43.78 | Q14: ='Reporte Componentes R1'!N349*$P$24 -> 55.99 | R14: ='Reporte Componentes R1'!O349*$P$24 -> 184.32 | S14: ='Reporte Componentes R1'!P349*$P$24 -> 79.02 | T14: ='Reporte Componentes R1'!Q349*$P$24 -> 8.14 | U14: =SUM(P14:T14) -> 371.25 | V14: =J14-U14 -> 0 | W14: =V14=0 -> TRUE
B15: 4 | C15: BOGOTA LIMPIA S.A.S. ESP. | D15: ='Reporte Componentes R1'!F469*$D$24 -> 30180.94 | E15: ='Reporte Componentes R1'!G469*$D$24 -> 2445.45 | F15: ='Reporte Componentes R1'!H469*$D$24 -> 1038.91 | G15: ='Reporte Componentes R1'!I469*$D$24 -> 453.69 | H15: ='Reporte Componentes R1'!J469*$D$24 -> 5579.62 | I15: ='Reporte Componentes R1'!K469*$D$24 -> 227.22 | J15: =D15-E15-F15-G15-H15-I15 -> 20436.05 | N15: 4 | O15: BOGOTA LIMPIA S.A.S. ESP. | P15: ='Reporte Componentes R1'!M469*$P$24 -> 1993.18 | Q15: ='Reporte Componentes R1'!N469*$P$24 -> 2534.52 | R15: ='Reporte Componentes R1'!O469*$P$24 -> 9306.3 | S15: ='Reporte Componentes R1'!P469*$P$24 -> 6231.3 | T15: ='Reporte Componentes R1'!Q469*$P$24 -> 370.75 | U15: =SUM(P15:T15) -> 20436.05 | V15: =J15-U15 -> 0 | W15: =V15=0 -> TRUE
B16: 5 | C16: AREA LIMPIA DISTRITO CAPITAL S.A.S. ESP. | D16: ='Reporte Componentes R1'!F543*$D$24 -> 0 | E16: ='Reporte Componentes R1'!G543*$D$24 -> 0 | F16: ='Reporte Componentes R1'!H543*$D$24 -> 0 | G16: ='Reporte Componentes R1'!I543*$D$24 -> 0 | H16: ='Reporte Componentes R1'!J543*$D$24 -> 0 | I16: ='Reporte Componentes R1'!K543*$D$24 -> 0 | J16: =D16-E16-F16-G16-H16-I16 -> 0 | N16: 5 | O16: AREA LIMPIA DISTRITO CAPITAL S.A.S. ESP. | P16: ='Reporte Componentes R1'!M543*$P$24 -> 0 | Q16: ='Reporte Componentes R1'!N543*$P$24 -> 0 | R16: ='Reporte Componentes R1'!O543*$P$24 -> 0 | S16: ='Reporte Componentes R1'!P543*$P$24 -> 0 | T16: ='Reporte Componentes R1'!Q543*$P$24 -> 0 | U16: =SUM(P16:T16) -> 0 | V16: =J16-U16 -> 0 | W16: =V16=0 -> TRUE
C17: TOTAL | D17: =SUM(D12:D16) -> 276468.71 | E17: =SUM(E12:E16) -> 23555 | F17: =SUM(F12:F16) -> 10006.76 | G17: =SUM(G12:G16) -> 4369.91 | H17: =SUM(H12:H16) -> 54510 | I17: =SUM(I12:I16) -> 2319.07 | J17: =SUM(J12:J16) -> 181707.97 | O17: TOTAL | P17: =SUM(P12:P16) -> 20342.45 | Q17: =SUM(Q12:Q16) -> 25454.58 | R17: =SUM(R12:R16) -> 86383.27 | S17: =SUM(S12:S16) -> 45743.54 | T17: =SUM(T12:T16) -> 3784.13 | U17: =SUM(U12:U16) -> 181707.97 | V17: =SUM(V12:V16) -> 0 | W17: =V17=0 -> TRUE
T19: =SUM(P17:T17) -> 181707.97
J20: =+IF(MAX(J12:J17)>500000,"VALIDAR",TRUE) -> TRUE
F21: Firma autorizada
D24: -1 | P24: -1

Sheet CONSOLIDADO_TOTAL RECAUDO
F3: PROCERASEO S.A.S. | I3: NIT: 901 153 639 - 0 | M3: Codigo Remuneración: | N3: 2026101 | U3: PROCERASEO S.A.S. | W3: NIT: 901 153 639 - 0 | AA3: Codigo Remuneración: | AD3: =N3 -> 2026101
F4: 3. ESQUEMA FINANCIERO DEL SERVICIO PUBLICO DE ASEO | U4: 3. ESQUEMA FINANCIERO DEL SERVICIO PUBLICO DE ASEO
F5: Resoluciòn UAESP Número 27 de 2018 | U5: Resoluciòn UAESP Número 27 de 2018
C6: Fecha de Proceso: | D6: 46314 | F6: R1 - RECAUDO OPORTUNO | U6: R1 - RECAUDO OPORTUNO
C7: Hora: | D7: 0.58333333 | F7: Fecha Desde: | G7: 46296 | J7: Feha Hasta: | K7: 46310 | U7: =F7 -> Fecha Desde: | V7: =G7 -> 46296 | X7: =J7 -> Feha Hasta: | Y7: =K7 -> 46310
B8: ASE | C8: Concesionarios | D8: Recaudo Total | E8: Recaudo por disposicion final | F8: Recaudo por tratamiento de lixiviados | G8: Recaudo por Componente VIAT ( Decreto 2412/2018) | H8: Recaudo por aprovechamiento | I8: Recaudo del componente de comercializacion para Aprovechamiento (11,4%) | J8: Balance de subsidio o contribuciones | K8: RECAUDO BASE DE REMUNERACION | L8: Costo de la Interventoría | M8: REMUNERACION FINAL | N8: Conceptos especiales | O8: REMUNERACION FINAL MAS CONCEPTOS ESPECIALES | S8: ASE | T8: Concesionarios | U8: Tarifa de Comercialización del Servicio. ( TCS) | V8: Tarifa de Limpieza Urbana del Servicio. ( TLU) | W8: Tarifa de Barrido y Limpieza del Servicio. ( TBL) | X8: Tarifa de Recolección y Transporte del Servicio. (TRT) | Y8: Recaudo del componente de comercializacion para Aprovechamiento (18,6%) | Z8: Costo de la Interventoría | AA8: Ajuste a la decena | AB8: Conceptos especiales | AC8: Otros | AD8: Diferencial Balance S / C (Fac vs Rec) | AE8: Balance S / C Con Base en (Recaudo) | AF8: REMUNERACION FINAL MAS CONCEPTOS ESPECIALES
B9: 1 | C9: PROMOAMBIENTAL DISTRITO S.A.S. ESP. | D9: ='Reporte Componentes R1'!F58 -> 1.4815022e+10 | E9: ='Reporte Componentes R1'!G58 -> 8.4180604e+08 | F9: ='Reporte Componentes R1'!H58 -> 4.6891797e+08 | G9: ='Reporte Componentes R1'!I58 -> 2.4965692e+08 | H9: ='Reporte Componentes R1'!J58 -> 4.7568461e+09 | I9: ='Reporte Componentes R1'!K58 -> 1.5849797e+08 | J9: ='BCE SC POR FACT.'!F3 -> 2.1539508e+09 | K9: =D9-E9-F9-G9-H9-I9-J9 -> 6.1853461e+09 | L9: =INTERVENTORIA!K15 -> 189185987 | M9: =K9-L9 -> 5.9961602e+09 | N9: ='Reporte Componentes R1'!L58 -> 19931693 | O9: =M9+N9 -> 6.0160918e+09 | S9: 1 | T9: PROMOAMBIENTAL DISTRITO S.A.S. ESP. | U9: ='Reporte Componentes R1'!M58 -> 1.3917356e+09 | V9: ='Reporte Componentes R1'!N58 -> 1.3159586e+09 | W9: ='Reporte Componentes R1'!O58 -> 6.2722322e+09 | X9: ='Reporte Componentes R1'!P58 -> 2.2908891e+09 | Y9: ='Reporte Componentes R1'!Q58 -> 2.5874486e+08 | Z9: =L9*-1 -> -189185987 | AA9: ='Reporte Componentes R1'!R58+'Reporte Componentes R1'!U58+'Reporte Componentes R1'!V58 -> -27801.66 | AB9: =N9 -> 19931693 | AC9: ='Reporte Componentes R1'!T58+'Reporte Componentes R1'!W58+'Reporte Componentes R1'!X58+'Reporte Componentes R1'!Y58+'Reporte Componentes R1'!Z58+'Reporte Componentes R1'!S58 -> 149.13 | AD9: =-J9+AE9 -> -5.3441865e+09 | AE9: ='Reporte Componentes R1'!F59 -> -3.1902357e+09 | AF9: =SUM(U9:AD9) -> 6.0160918e+09 | AG9: =(AF9-O9) -> 4.7683716e-06 | AH9: =INT(AG9)=0 -> TRUE
B10: 2 | C10: LIMPIEZA METROPOLITANA S.A. ESP. | D10: ='Reporte Componentes R1'!F191 -> 1.1219101e+10 | E10: ='Reporte Componentes R1'!G191 -> 8.7325431e+08 | F10: ='Reporte Componentes R1'!H191 -> 4.8346293e+08 | G10: ='Reporte Componentes R1'!I191 -> 2.5630965e+08 | H10: ='Reporte Componentes R1'!J191 -> 3.5736206e+09 | I10: ='Reporte Componentes R1'!K191 -> 1.2662777e+08 | J10: ='BCE SC POR FACT.'!F4 -> -4.2171455e+09 | K10: =D10-E10-F10-G10-H10-I10-J10 -> 1.0122972e+10 | L10: =INTERVENTORIA!K16 -> 266580255 | M10: =K10-L10 -> 9.8563914e+09 | N10: ='Reporte Componentes R1'!L191 -> 9834335.8 | O10: =M10+N10 -> 9.8662257e+09 | S10: 2 | T10: LIMPIEZA METROPOLITANA S.A. ESP. | U10: ='Reporte Componentes R1'!M191 -> 1.1109993e+09 | V10: ='Reporte Componentes R1'!N191 -> 1.0681559e+09 | W10: ='Reporte Componentes R1'!O191 -> 5.074672e+09 | X10: ='Reporte Componentes R1'!P191 -> 1.712803e+09 | Y10: ='Reporte Componentes R1'!Q191 -> 2.0676196e+08 | Z10: =L10*-1 -> -266580255 | AA10: ='Reporte Componentes R1'!R191+'Reporte Componentes R1'!U191+'Reporte Componentes R1'!V191 -> -14204.66 | AB10: =N10 -> 9834335.8 | AC10: ='Reporte Componentes R1'!T191+'Reporte Componentes R1'!W191+'Reporte Componentes R1'!X191+'Reporte Componentes R1'!Y191+'Reporte Componentes R1'!Z191+'Reporte Componentes R1'!S191 -> -56307.81 | AD10: =-J10+AE10 -> 9.4964996e+08 | AE10: ='Reporte Componentes R1'!F192 -> -3.2674956e+09 | AF10: =SUM(U10:AD10) -> 9.8662257e+09 | AG10: =(AF10-O10) -> 1.9073486e-06 | AH10: =INT(AG10)=0 -> TRUE
B11: 3 | C11: CIUDAD LIMPIA BOGOTA S.A. ESP. | D11: ='Reporte Componentes R1'!F319 -> 8.8114722e+09 | E11: ='Reporte Componentes R1'!G319 -> 5.6904906e+08 | F11: ='Reporte Componentes R1'!H319 -> 3.1726749e+08 | G11: ='Reporte Componentes R1'!I319 -> 1.685178e+08 | H11: ='Reporte Componentes R1'!J319 -> 2.4290215e+09 | I11: ='Reporte Componentes R1'!K319 -> 86984011 | J11: ='BCE SC POR FACT.'!F5 -> -1.2888063e+09 | K11: =D11-E11-F11-G11-H11-I11-J11 -> 6.5294386e+09 | L11: =INTERVENTORIA!K17 -> 154788535 | M11: =K11-L11 -> 6.3746501e+09 | N11: ='Reporte Componentes R1'!L319 -> 19305718 | O11: =M11+N11 -> 6.3939558e+09 | S11: 3 | T11: CIUDAD LIMPIA BOGOTA S.A. ESP. | U11: ='Reporte Componentes R1'!M319 -> 7.636827e+08 | V11: ='Reporte Componentes R1'!N319 -> 7.2501882e+08 | W11: ='Reporte Componentes R1'!O319 -> 3.4442559e+09 | X11: ='Reporte Componentes R1'!P319 -> 1.3479162e+09 | Y11: ='Reporte Componentes R1'!Q319 -> 1.4202598e+08 | Z11: =L11*-1 -> -154788535 | AA11: ='Reporte Componentes R1'!R319+'Reporte Componentes R1'!U319+'Reporte Componentes R1'!V319 -> -81704.87 | AB11: =N11 -> 19305718 | AC11: ='Reporte Componentes R1'!T319+'Reporte Componentes R1'!W319+'Reporte Componentes R1'!X319+'Reporte Componentes R1'!Y319+'Reporte Componentes R1'!Z319+'Reporte Componentes R1'!S319 -> -41619.9 | AD11: =-J11+AE11 -> 1.0666238e+08 | AE11: ='Reporte Componentes R1'!F320 -> -1.182144e+09 | AF11: =SUM(U11:AD11) -> 6.3939558e+09 | AG11: =(AF11-O11) -> 0 | AH11: =INT(AG11)=0 -> TRUE
B12: 4 | C12: BOGOTA LIMPIA S.A.S. ESP. | D12: ='Reporte Componentes R1'!F439 -> 1.0473968e+10 | E12: ='Reporte Componentes R1'!G439 -> 6.0467e+08 | F12: ='Reporte Componentes R1'!H439 -> 3.3517547e+08 | G12: ='Reporte Componentes R1'!I439 -> 1.7872296e+08 | H12: ='Reporte Componentes R1'!J439 -> 2.3961854e+09 | I12: ='Reporte Componentes R1'!K439 -> 89652486 | J12: ='BCE SC POR FACT.'!F6 -> 61531954 | K12: =D12-E12-F12-G12-H12-I12-J12 -> 6.8080295e+09 | L12: =INTERVENTORIA!K18 -> 120391083 | M12: =K12-L12 -> 6.6876384e+09 | N12: ='Reporte Componentes R1'!L439 -> 8643135.6 | O12: =M12+N12 -> 6.6962816e+09 | S12: 4 | T12: BOGOTA LIMPIA S.A.S. ESP. | U12: ='Reporte Componentes R1'!M439 -> 7.8581447e+08 | V12: ='Reporte Componentes R1'!N439 -> 7.4992426e+08 | W12: ='Reporte Componentes R1'!O439 -> 3.8805462e+09 | X12: ='Reporte Componentes R1'!P439 -> 1.600708e+09 | Y12: ='Reporte Componentes R1'!Q439 -> 1.4652791e+08 | Z12: =L12*-1 -> -120391083 | AA12: ='Reporte Componentes R1'!R439+'Reporte Componentes R1'!U439+'Reporte Componentes R1'!V439 -> 31942.35 | AB12: =N12 -> 8643135.6 | AC12: ='Reporte Componentes R1'!T439+'Reporte Componentes R1'!W439+'Reporte Componentes R1'!X439+'Reporte Componentes R1'!Y439+'Reporte Componentes R1'!Z439+'Reporte Componentes R1'!S439 -> 189.43 | AD12: =-J12+AE12 -> -3.5552347e+08 | AE12: ='Reporte Componentes R1'!F440 -> -2.9399152e+08 | AF12: =SUM(U12:AD12) -> 6.6962816e+09 | AG12: =(AF12-O12) -> 1.9073486e-06 | AH12: =INT(AG12)=0 -> TRUE
B13: 5 | C13: AREA LIMPIA DISTRITO CAPITAL S.A.S. ESP. | D13: ='Reporte Componentes R1'!F513 -> 7.5442533e+09 | E13: ='Reporte Componentes R1'!G513 -> 4.0814547e+08 | F13: ='Reporte Componentes R1'!H513 -> 2.2711804e+08 | G13: ='Reporte Componentes R1'!I513 -> 1.2084103e+08 | H13: ='Reporte Componentes R1'!J513 -> 1.8642679e+09 | I13: ='Reporte Componentes R1'!K513 -> 62073127 | J13: ='BCE SC POR FACT.'!F7 -> -1.2464731e+09 | K13: =D13-E13-F13-G13-H13-I13-J13 -> 6.1082808e+09 | L13: =INTERVENTORIA!K19 -> 128990445 | M13: =K13-L13 -> 5.9792904e+09 | N13: ='Reporte Componentes R1'!L513 -> 12379938 | O13: =M13+N13 -> 5.9916703e+09 | S13: 5 | T13: AREA LIMPIA DISTRITO CAPITAL S.A.S. ESP. | U13: ='Reporte Componentes R1'!M513 -> 5.4468434e+08 | V13: ='Reporte Componentes R1'!N513 -> 5.1295881e+08 | W13: ='Reporte Componentes R1'!O513 -> 2.6405604e+09 | X13: ='Reporte Componentes R1'!P513 -> 1.2146777e+09 | Y13: ='Reporte Componentes R1'!Q513 -> 101292451 | Z13: =L13*-1 -> -128990445 | AA13: ='Reporte Componentes R1'!R513+'Reporte Componentes R1'!U513+'Reporte Componentes R1'!V513 -> 10679.52 | AB13: =N13 -> 12379938 | AC13: ='Reporte Componentes R1'!T513+'Reporte Componentes R1'!W513+'Reporte Componentes R1'!X513+'Reporte Componentes R1'!Y513+'Reporte Componentes R1'!Z513+'Reporte Componentes R1'!S513 -> 4.86 | AD13: =-J13+AE13 -> 1.0940964e+09 | AE13: ='Reporte Componentes R1'!F514 -> -152376731 | AF13: =SUM(U13:AD13) -> 5.9916703e+09 | AG13: =(AF13-O13) -> 0 | AH13: =INT(AG13)=0 -> TRUE
C14: TOTAL | D14: =SUM(D9:D13) -> 5.2863817e+10 | E14: =SUM(E9:E13) -> 3.2969249e+09 | F14: =SUM(F9:F13) -> 1.8319419e+09 | G14: =SUM(G9:G13) -> 9.7404836e+08 | H14: =SUM(H9:H13) -> 1.5019942e+10 | I14: =SUM(I9:I13) -> 5.2383536e+08 | J14: =SUM(J9:J13) -> -4.5369422e+09 | K14: =SUM(K9:K13) -> 3.5754067e+10 | ... O14: =SUM(O9:O13) -> 3.4964225e+10 | T14: TOTAL | U14: =SUM(U9:U13) -> 4.5969164e+09 | V14: =SUM(V9:V13) -> 4.3720164e+09 | W14: =SUM(W9:W13) -> 2.1312267e+10 | X14: =SUM(X9:X13) -> 8.1669939e+09 | Y14: =SUM(Y9:Y13) -> 8.5535316e+08 | Z14: =SUM(Z9:Z13) -> -859936305 | AA14: =SUM(AA9:AA13) -> -81089.32 | AB14: =SUM(AB9:AB13) -> 70094820 | ... AG14: =SUM(AG9:AG13) -> 8.5830688e-06 | AH14: =INT(AG14)=0 -> TRUE
Y16: =SUM(U14:Y14) -> 3.9303547e+10
F18: Firma autorizada
F22: PROCERASEO S.A.S. | I22: NIT: 901 153 639 - 0 | M22: Codigo Remuneración: | N22: =N3 -> 2026101 | U22: PROCERASEO S.A.S. | W22: NIT: 901 153 639 - 0 | AA22: Codigo Remuneración: | AD22: =N22 -> 2026101
F23: 3. ESQUEMA FINANCIERO DEL SERVICIO PUBLICO DE ASEO | U23: 3. ESQUEMA FINANCIERO DEL SERVICIO PUBLICO DE ASEO
F24: Resoluciòn UAESP Número 27 de 2018 | U24: Resoluciòn UAESP Número 27 de 2018
C25: Fecha de Proceso: | D25: =D6 -> 46314 | F25: R2 - ANTICIPOS A USUARIOS | U25: R2 - ANTICIPOS A USUARIOS
C26: Hora: | D26: =D7 -> 0.58333333 | F26: Fecha Desde: | G26: =G7 -> 46296 | J26: Feha Hasta: | K26: =K7 -> 46310 | U26: =F26 -> Fecha Desde: | V26: =G26 -> 46296 | X26: =J26 -> Feha Hasta: | Y26: =K26 -> 46310
B27: ASE | C27: Concesionarios | D27: Recaudo Total | E27: Recaudo por disposicion final | F27: Recaudo por tratamiento de lixiviados | G27: Recaudo por Componente VIAT ( Decreto 2412/2018) | H27: Recaudo por aprovechamiento | I27: Recaudo del componente de comercializacion para Aprovechamiento (11,4%) | J27: Balance de subsidio o contribuciones | K27: RECAUDO BASE DE REMUNERACION | L27: Costo de la Interventoría | M27: REMUNERACION FINAL | N27: Conceptos especiales | O27: REMUNERACION FINAL MAS CONCEPTOS ESPECIALES | S27: ASE | T27: Concesionarios | U27: Tarifa de Comercialización del Servicio. ( TCS) | V27: Tarifa de Limpieza Urbana del Servicio. ( TLU) | W27: Tarifa de Barrido y Limpieza del Servicio. ( TBL) | X27: Tarifa de Recolección y Transporte del Servicio. (TRT) | Y27: Recaudo del componente de comercializacion para Aprovechamiento (18,6%) | Z27: Costo de la Interventoría | AA27: Ajuste a la decena | AB27: Conceptos especiales | AC27: Otros | AD27: Diferencial Balance S / C (Fac vs Rec) | AE27: Balance S / C Con Base en (Recaudo) | AF27: REMUNERACION FINAL MAS CONCEPTOS ESPECIALES
B28: 1 | C28: PROMOAMBIENTAL DISTRITO S.A.S. ESP. | D28: ='Rem. Anticipos R2'!E43 -> 30588071 | E28: ='Rem. Anticipos R2'!F43 -> 2012917.5 | F28: ='Rem. Anticipos R2'!G43 -> 1105648.1 | G28: ='Rem. Anticipos R2'!H43 -> 439435.07 | H28: ='Rem. Anticipos R2'!I43 -> 7084790.8 | I28: ='Rem. Anticipos R2'!J43 -> 260451.93 | J28: 0 | K28: =D28-E28-F28-G28-H28-I28-J28 -> 19684828 | L28: 0 | M28: =K28-L28 -> 19684828 | N28: ='Rem. Anticipos R2'!K43 -> 0 | O28: =M28+N28 -> 19684828 | S28: 1 | T28: PROMOAMBIENTAL DISTRITO S.A.S. ESP. | U28: ='Rem. Anticipos R2'!L43 -> 3091186.5 | V28: ='Rem. Anticipos R2'!M43 -> 1972672.4 | W28: ='Rem. Anticipos R2'!N43 -> 9153752.9 | X28: ='Rem. Anticipos R2'!O43 -> 5752725.5 | Y28: ='Rem. Anticipos R2'!P43 -> 402882.84 | Z28: =L28*-1 -> 0 | AA28: ='Rem. Anticipos R2'!Q43 -> 278.97 | AB28: =N28 -> 0 | AC28: ='Rem. Anticipos R2'!R43 -> 0 | AD28: =-J28+AE28 -> -688671.4 | AE28: ='Rem. Anticipos R2'!E44 -> -688671.4 | AF28: =SUM(U28:AD28) -> 19684828 | AG28: =(AF28-O28) -> -3.7252903e-09 | AH28: =INT(AG28)=0 -> FALSE
B29: 2 | C29: LIMPIEZA METROPOLITANA S.A. ESP. | D29: ='Rem. Anticipos R2'!E146 -> 95634974 | E29: ='Rem. Anticipos R2'!F146 -> 7624401.8 | F29: ='Rem. Anticipos R2'!G146 -> 4364367 | G29: ='Rem. Anticipos R2'!H146 -> 1846002.7 | H29: ='Rem. Anticipos R2'!I146 -> 27039718 | I29: ='Rem. Anticipos R2'!J146 -> 956455.55 | J29: 0 | K29: =D29-E29-F29-G29-H29-I29-J29 -> 53804029 | L29: 0 | M29: =K29-L29 -> 53804029 | N29: ='Rem. Anticipos R2'!K146 -> 70736.95 | O29: =M29+N29 -> 53874766 | S29: 2 | T29: LIMPIEZA METROPOLITANA S.A. ESP. | U29: ='Rem. Anticipos R2'!L146 -> 9704863.7 | V29: ='Rem. Anticipos R2'!M146 -> 7563501.6 | W29: ='Rem. Anticipos R2'!N146 -> 32387932 | X29: ='Rem. Anticipos R2'!O146 -> 16697102 | Y29: ='Rem. Anticipos R2'!P146 -> 1395967 | Z29: =L29*-1 -> 0 | AA29: ='Rem. Anticipos R2'!Q146 -> 22.96 | AB29: =N29 -> 70736.95 | AC29: ='Rem. Anticipos R2'!R146 -> 6759348.8 | AD29: =-J29+AE29 -> -20704709 | AE29: ='Rem. Anticipos R2'!E147 -> -20704709 | AF29: =SUM(U29:AD29) -> 53874766 | AG29: =(AF29-O29) -> -7.4505806e-09 | AH29: =INT(AG29)=0 -> FALSE
B30: 3 | C30: CIUDAD LIMPIA BOGOTA S.A. ESP. | D30: ='Rem. Anticipos R2'!E259 -> 14574412 | E30: ='Rem. Anticipos R2'!F259 -> 1069009.9 | F30: ='Rem. Anticipos R2'!G259 -> 613827.68 | G30: ='Rem. Anticipos R2'!H259 -> 410378.89 | H30: ='Rem. Anticipos R2'!I259 -> 3149813.5 | I30: ='Rem. Anticipos R2'!J259 -> 100937.15 | J30: 0 | K30: =D30-E30-F30-G30-H30-I30-J30 -> 9230444.9 | L30: 0 | M30: =K30-L30 -> 9230444.9 | N30: ='Rem. Anticipos R2'!K259 -> 16082.29 | O30: =M30+N30 -> 9246527.2 | S30: 3 | T30: CIUDAD LIMPIA BOGOTA S.A. ESP. | U30: ='Rem. Anticipos R2'!L259 -> 1409323.4 | V30: ='Rem. Anticipos R2'!M259 -> 1076297 | W30: ='Rem. Anticipos R2'!N259 -> 7857677.6 | X30: ='Rem. Anticipos R2'!O259 -> 2601952.1 | Y30: ='Rem. Anticipos R2'!P259 -> 150307.89 | Z30: =L30*-1 -> 0 | AA30: ='Rem. Anticipos R2'!Q259 -> 2232.69 | AB30: =N30 -> 16082.29 | AC30: ='Rem. Anticipos R2'!R259 -> 0 | AD30: =-J30+AE30 -> -3867345.8 | AE30: ='Rem. Anticipos R2'!E260 -> -3867345.8 | AF30: =SUM(U30:AD30) -> 9246527.2 | AG30: =(AF30-O30) -> 0 | AH30: =INT(AG30)=0 -> TRUE
B31: 4 | C31: BOGOTA LIMPIA S.A.S. ESP. | D31: ='Rem. Anticipos R2'!E354 -> 29206357 | E31: ='Rem. Anticipos R2'!F354 -> 1731904.8 | F31: ='Rem. Anticipos R2'!G354 -> 1013035.8 | G31: ='Rem. Anticipos R2'!H354 -> 451249.43 | H31: ='Rem. Anticipos R2'!I354 -> 6174692.5 | I31: ='Rem. Anticipos R2'!J354 -> 229736.09 | J31: 0 | K31: =D31-E31-F31-G31-H31-I31-J31 -> 19605738 | L31: 0 | M31: =K31-L31 -> 19605738 | N31: ='Rem. Anticipos R2'!K354 -> 0 | O31: =M31+N31 -> 19605738 | S31: 4 | T31: BOGOTA LIMPIA S.A.S. ESP. | U31: ='Rem. Anticipos R2'!L354 -> 2253122.1 | V31: ='Rem. Anticipos R2'!M354 -> 2010598.6 | W31: ='Rem. Anticipos R2'!N354 -> 9848352.6 | X31: ='Rem. Anticipos R2'!O354 -> 4769719 | Y31: ='Rem. Anticipos R2'!P354 -> 341248.21 | Z31: =L31*-1 -> 0 | AA31: ='Rem. Anticipos R2'!Q354 -> 97.83 | AB31: =N31 -> 0 | AC31: ='Rem. Anticipos R2'!R354 -> 0 | AD31: =-J31+AE31 -> 382600.2 | AE31: ='Rem. Anticipos R2'!E355 -> 382600.2 | AF31: =SUM(U31:AD31) -> 19605738 | AG31: =(AF31-O31) -> -3.7252903e-09 | AH31: =INT(AG31)=0 -> FALSE
B32: 5 | C32: AREA LIMPIA DISTRITO CAPITAL S.A.S. ESP. | D32: ='Rem. Anticipos R2'!E426 -> 10379542 | E32: ='Rem. Anticipos R2'!F426 -> 630945.3 | F32: ='Rem. Anticipos R2'!G426 -> 361740.31 | G32: ='Rem. Anticipos R2'!H426 -> 165909.23 | H32: ='Rem. Anticipos R2'!I426 -> 2288749 | I32: ='Rem. Anticipos R2'!J426 -> 82728.38 | J32: 0 | K32: =D32-E32-F32-G32-H32-I32-J32 -> 6849469.8 | L32: 0 | M32: =K32-L32 -> 6849469.8 | N32: ='Rem. Anticipos R2'!K426 -> 0 | O32: =M32+N32 -> 6849469.8 | S32: 5 | T32: AREA LIMPIA DISTRITO CAPITAL S.A.S. ESP. | U32: ='Rem. Anticipos R2'!L426 -> 747261.86 | V32: ='Rem. Anticipos R2'!M426 -> 670768.89 | W32: ='Rem. Anticipos R2'!N426 -> 3419717.4 | X32: ='Rem. Anticipos R2'!O426 -> 1915217.5 | Y32: ='Rem. Anticipos R2'!P426 -> 129945.57 | Z32: =L32*-1 -> 0 | AA32: ='Rem. Anticipos R2'!Q426 -> -117.34 | AB32: =N32 -> 0 | AC32: ='Rem. Anticipos R2'!R426 -> 0 | AD32: =-J32+AE32 -> -33324.08 | AE32: ='Rem. Anticipos R2'!E427 -> -33324.08 | AF32: =SUM(U32:AD32) -> 6849469.8 | AG32: =(AF32-O32) -> 0 | AH32: =INT(AG32)=0 -> TRUE
C33: TOTAL | D33: =SUM(D28:D32) -> 1.8038336e+08 | E33: =SUM(E28:E32) -> 13069179 | F33: =SUM(F28:F32) -> 7458618.9 | G33: =SUM(G28:G32) -> 3312975.3 | H33: =SUM(H28:H32) -> 45737764 | I33: =SUM(I28:I32) -> 1630309.1 | J33: =SUM(J28:J32) -> 0 | K33: =SUM(K28:K32) -> 1.0917451e+08 | ... O33: =SUM(O28:O32) -> 1.0926133e+08 | T33: TOTAL | U33: =SUM(U28:U32) -> 17205758 | V33: =SUM(V28:V32) -> 13293838 | W33: =SUM(W28:W32) -> 62667433 | X33: =SUM(X28:X32) -> 31736716 | Y33: =SUM(Y28:Y32) -> 2420351.5 | Z33: =SUM(Z28:Z32) -> 0 | AA33: =SUM(AA28:AA32) -> 2515.11 | AB33: =SUM(AB28:AB32) -> 86819.24 | ... AG33: =SUM(AG28:AG32) -> -1.4901161e-08 | AH33: =INT(AG33)=0 -> FALSE
Y35: =SUM(U33:Y33) -> 1.273241e+08
F37: Firma autorizada
F41: PROCERASEO S.A.S. | I41: NIT: 901 153 639 - 0 | M41: Codigo Remuneración: | N41: =N3 -> 2026101 | U41: PROCERASEO S.A.S. | W41: NIT: 901 153 639 - 0 | AA41: Codigo Remuneración: | AD41: =N41 -> 2026101
F42: 3. ESQUEMA FINANCIERO DEL SERVICIO PUBLICO DE ASEO | U42: 3. ESQUEMA FINANCIERO DEL SERVICIO PUBLICO DE ASEO
F43: Resoluciòn UAESP Número 27 de 2018 | U43: Resoluciòn UAESP Número 27 de 2018
C44: Fecha de Proceso: | D44: =D6 -> 46314 | F44: R3 - RECAUDO EXTEMPORANEO | U44: R3 - RECAUDO EXTEMPORANEO
C45: Hora: | D45: =D7 -> 0.58333333 | F45: Fecha Desde: | G45: =G7 -> 46296 | J45: Feha Hasta: | K45: =K7 -> 46310 | U45: =F45 -> Fecha Desde: | V45: =G45 -> 46296 | X45: =J45 -> Feha Hasta: | Y45: =K45 -> 46310
B46: ASE | C46: Concesionarios | D46: Recaudo Total | E46: Recaudo por disposicion final | F46: Recaudo por tratamiento de lixiviados | G46: Recaudo por Componente VIAT ( Decreto 2412/2018) | H46: Recaudo por aprovechamiento | I46: Recaudo del componente de comercializacion para Aprovechamiento (11,4%) | J46: Balance de subsidio o contribuciones | K46: RECAUDO BASE DE REMUNERACION | L46: Costo de la Interventoría | M46: REMUNERACION FINAL | N46: Conceptos especiales | O46: REMUNERACION FINAL MAS CONCEPTOS ESPECIALES | S46: ASE | T46: Concesionarios | U46: Tarifa de Comercialización del Servicio. ( TCS) | V46: Tarifa de Limpieza Urbana del Servicio. ( TLU) | W46: Tarifa de Barrido y Limpieza del Servicio. ( TBL) | X46: Tarifa de Recolección y Transporte del Servicio. (TRT) | Y46: Recaudo del componente de comercializacion para Aprovechamiento (18,6%) | Z46: Costo de la Interventoría | AA46: Ajuste a la decena | AB46: Conceptos especiales | AC46: Otros | AD46: Diferencial Balance S / C (Fac vs Rec) | AE46: Balance S / C Con Base en (Recaudo) | AF46: REMUNERACION FINAL MAS CONCEPTOS ESPECIALES
B47: 1 | C47: PROMOAMBIENTAL DISTRITO S.A.S. ESP. | D47: ='Reporte Componentes R1'!F60 -> 648870 | E47: ='Reporte Componentes R1'!G60 -> 29223.59 | F47: ='Reporte Componentes R1'!H60 -> 16458.47 | G47: ='Reporte Componentes R1'!I60 -> 8660.22 | H47: ='Reporte Componentes R1'!J60 -> 141425.47 | I47: ='Reporte Componentes R1'!K60 -> 5825.54 | J47: 0 | K47: =D47-E47-F47-G47-H47-I47-J47 -> 447276.71 | L47: 0 | M47: =K47-L47 -> 447276.71 | N47: ='Reporte Componentes R1'!L60 -> 0 | O47: =M47+N47 -> 447276.71 | S47: 1 | T47: PROMOAMBIENTAL DISTRITO S.A.S. ESP. | U47: ='Reporte Componentes R1'!M60 -> 51101.37 | V47: ='Reporte Componentes R1'!N60 -> 51278.68 | W47: ='Reporte Componentes R1'!O60 -> 242748.43 | X47: ='Reporte Componentes R1'!P60 -> 79815.35 | Y47: ='Reporte Componentes R1'!Q60 -> 9504.83 | Z47: =-L47 -> 0 | AA47: ='Reporte Componentes R1'!R60+'Reporte Componentes R1'!V60+'Reporte Componentes R1'!U60 -> 5.12 | AB47: =N47 -> 0 | AC47: ='Reporte Componentes R1'!T60+'Reporte Componentes R1'!W60+'Reporte Componentes R1'!X60+'Reporte Componentes R1'!Y60+'Reporte Componentes R1'!Z60+'Reporte Componentes R1'!S60 -> 0 | AD47: =-J47+AE47 -> 12822.93 | AE47: ='Reporte Componentes R1'!F61 -> 12822.93 | AF47: =SUM(U47:AD47) -> 447276.71 | AG47: =(AF47-O47) -> -1.7462298e-10 | AH47: =INT(AG47)=0 -> FALSE
B48: 2 | C48: LIMPIEZA METROPOLITANA S.A. ESP. | D48: ='Reporte Componentes R1'!F193 -> 9704974 | E48: ='Reporte Componentes R1'!G193 -> 651837.25 | F48: ='Reporte Componentes R1'!H193 -> 367261.1 | G48: ='Reporte Componentes R1'!I193 -> 196265.14 | H48: ='Reporte Componentes R1'!J193 -> 2936066.5 | I48: ='Reporte Componentes R1'!K193 -> 79272.71 | J48: 0 | K48: =D48-E48-F48-G48-H48-I48-J48 -> 5474271.3 | L48: 0 | M48: =K48-L48 -> 5474271.3 | N48: ='Reporte Componentes R1'!L193 -> 0 | O48: =M48+N48 -> 5474271.3 | S48: 2 | T48: LIMPIEZA METROPOLITANA S.A. ESP. | U48: ='Reporte Componentes R1'!M193 -> 695375.41 | V48: ='Reporte Componentes R1'!N193 -> 925873.97 | W48: ='Reporte Componentes R1'!O193 -> 4476434.6 | X48: ='Reporte Componentes R1'!P193 -> 1295216.9 | Y48: ='Reporte Componentes R1'!Q193 -> 130580.61 | Z48: =-L48 -> 0 | AA48: ='Reporte Componentes R1'!R193+'Reporte Componentes R1'!V193+'Reporte Componentes R1'!U193 -> -101.63 | AB48: =N48 -> 0 | AC48: ='Reporte Componentes R1'!T193+'Reporte Componentes R1'!W193+'Reporte Componentes R1'!X193+'Reporte Componentes R1'!Y193+'Reporte Componentes R1'!Z193+'Reporte Componentes R1'!S193 -> 0.04 | AD48: =-J48+AE48 -> -2049108.6 | AE48: ='Reporte Componentes R1'!F194 -> -2049108.6 | AF48: =SUM(U48:AD48) -> 5474271.3 | AG48: =(AF48-O48) -> 0 | AH48: =INT(AG48)=0 -> TRUE
B49: 3 | C49: CIUDAD LIMPIA BOGOTA S.A. ESP. | D49: ='Reporte Componentes R1'!F321 -> 0 | E49: ='Reporte Componentes R1'!G321 -> 0 | F49: ='Reporte Componentes R1'!H321 -> 0 | G49: ='Reporte Componentes R1'!I321 -> 0 | H49: ='Reporte Componentes R1'!J321 -> 0 | I49: ='Reporte Componentes R1'!K321 -> 0 | J49: 0 | K49: =D49-E49-F49-G49-H49-I49-J49 -> 0 | L49: 0 | M49: =K49-L49 -> 0 | N49: ='Reporte Componentes R1'!L321 -> 0 | O49: =M49+N49 -> 0 | S49: 3 | T49: CIUDAD LIMPIA BOGOTA S.A. ESP. | U49: ='Reporte Componentes R1'!M321 -> 0 | V49: ='Reporte Componentes R1'!N321 -> 0 | W49: ='Reporte Componentes R1'!O321 -> 0 | X49: ='Reporte Componentes R1'!P321 -> 0 | Y49: ='Reporte Componentes R1'!Q321 -> 0 | Z49: =-L49 -> 0 | AA49: ='Reporte Componentes R1'!R321+'Reporte Componentes R1'!V321+'Reporte Componentes R1'!U321 -> 0 | AB49: =N49 -> 0 | AC49: ='Reporte Componentes R1'!T321+'Reporte Componentes R1'!W321+'Reporte Componentes R1'!X321+'Reporte Componentes R1'!Y321+'Reporte Componentes R1'!Z321+'Reporte Componentes R1'!S321 -> 0 | AD49: =-J49+AE49 -> 0 | AE49: ='Reporte Componentes R1'!F322 -> 0 | AF49: =SUM(U49:AD49) -> 0 | AG49: =(AF49-O49) -> 0 | AH49: =INT(AG49)=0 -> TRUE
B50: 4 | C50: BOGOTA LIMPIA S.A.S. ESP. | D50: ='Reporte Componentes R1'!F441 -> 21557177 | E50: ='Reporte Componentes R1'!G441 -> 1278757.6 | F50: ='Reporte Componentes R1'!H441 -> 719798.43 | G50: ='Reporte Componentes R1'!I441 -> 385650.58 | H50: ='Reporte Componentes R1'!J441 -> 5181365.2 | I50: ='Reporte Componentes R1'!K441 -> 155526.08 | J50: 0 | K50: =D50-E50-F50-G50-H50-I50-J50 -> 13836079 | L50: 0 | M50: =K50-L50 -> 13836079 | N50: ='Reporte Componentes R1'!L441 -> 0 | O50: =M50+N50 -> 13836079 | S50: 4 | T50: BOGOTA LIMPIA S.A.S. ESP. | U50: ='Reporte Componentes R1'!M441 -> 1351292.3 | V50: ='Reporte Componentes R1'!N441 -> 1669548.6 | W50: ='Reporte Componentes R1'!O441 -> 8617443.9 | X50: ='Reporte Componentes R1'!P441 -> 3417030.9 | Y50: ='Reporte Componentes R1'!Q441 -> 255177.82 | Z50: =-L50 -> 0 | AA50: ='Reporte Componentes R1'!R441+'Reporte Componentes R1'!V441+'Reporte Componentes R1'!U441 -> -9.05 | AB50: =N50 -> 0 | AC50: ='Reporte Componentes R1'!T441+'Reporte Componentes R1'!W441+'Reporte Componentes R1'!X441+'Reporte Componentes R1'!Y441+'Reporte Componentes R1'!Z441+'Reporte Componentes R1'!S441 -> 0 | AD50: =-J50+AE50 -> -1474405.3 | AE50: ='Reporte Componentes R1'!F442 -> -1474405.3 | AF50: =SUM(U50:AD50) -> 13836079 | AG50: =(AF50-O50) -> -1.8626451e-09 | AH50: =INT(AG50)=0 -> FALSE
B51: 5 | C51: AREA LIMPIA DISTRITO CAPITAL S.A.S. ESP. | D51: ='Reporte Componentes R1'!F515 -> 0 | E51: ='Reporte Componentes R1'!G515 -> 0 | F51: ='Reporte Componentes R1'!H515 -> 0 | G51: ='Reporte Componentes R1'!I515 -> 0 | H51: ='Reporte Componentes R1'!J515 -> 0 | I51: ='Reporte Componentes R1'!K515 -> 0 | J51: 0 | K51: =D51-E51-F51-G51-H51-I51-J51 -> 0 | L51: 0 | M51: =K51-L51 -> 0 | N51: ='Reporte Componentes R1'!L515 -> 0 | O51: =M51+N51 -> 0 | S51: 5 | T51: AREA LIMPIA DISTRITO CAPITAL S.A.S. ESP. | U51: ='Reporte Componentes R1'!M515 -> 0 | V51: ='Reporte Componentes R1'!N515 -> 0 | W51: ='Reporte Componentes R1'!O515 -> 0 | X51: ='Reporte Componentes R1'!P515 -> 0 | Y51: ='Reporte Componentes R1'!Q515 -> 0 | Z51: =-L51 -> 0 | AA51: ='Reporte Componentes R1'!R515+'Reporte Componentes R1'!V515+'Reporte Componentes R1'!U515 -> 0 | AB51: =N51 -> 0 | AC51: ='Reporte Componentes R1'!T515+'Reporte Componentes R1'!W515+'Reporte Componentes R1'!X515+'Reporte Componentes R1'!Y515+'Reporte Componentes R1'!Z515+'Reporte Componentes R1'!S515 -> 0 | AD51: =-J51+AE51 -> 0 | AE51: ='Reporte Componentes R1'!F516 -> 0 | AF51: =SUM(U51:AD51) -> 0 | AG51: =(AF51-O51) -> 0 | AH51: =INT(AG51)=0 -> TRUE
C52: TOTAL | D52: =SUM(D47:D51) -> 31911021 | E52: =SUM(E47:E51) -> 1959818.5 | F52: =SUM(F47:F51) -> 1103518 | G52: =SUM(G47:G51) -> 590575.94 | H52: =SUM(H47:H51) -> 8258857.1 | I52: =SUM(I47:I51) -> 240624.33 | J52: =SUM(J47:J51) -> 0 | K52: =SUM(K47:K51) -> 19757627 | ... O52: =SUM(O47:O51) -> 19757627 | T52: TOTAL | U52: =SUM(U47:U51) -> 2097769.1 | V52: =SUM(V47:V51) -> 2646701.2 | W52: =SUM(W47:W51) -> 13336627 | X52: =SUM(X47:X51) -> 4792063.2 | Y52: =SUM(Y47:Y51) -> 395263.26 | Z52: =SUM(Z47:Z51) -> 0 | AA52: =SUM(AA47:AA51) -> -105.56 | AB52: =SUM(AB47:AB51) -> 0 | ... AG52: =SUM(AG47:AG51) -> -2.0372681e-09 | AH52: =INT(AG52)=0 -> FALSE
Y54: =SUM(U52:Y52) -> 23268424
F56: Firma autorizada
F60: PROCERASEO S.A.S. | I60: NIT: 901 153 639 - 0 | M60: Codigo Remuneración: | N60: =N3 -> 2026101 | U60: PROCERASEO S.A.S. | W60: NIT: 901 153 639 - 0 | AA60: Codigo Remuneración: | AD60: =N60 -> 2026101
F61: 3. ESQUEMA FINANCIERO DEL SERVICIO PUBLICO DE ASEO | U61: 3. ESQUEMA FINANCIERO DEL SERVICIO PUBLICO DE ASEO
F62: Resoluciòn UAESP Número 27 de 2018 | U62: Resoluciòn UAESP Número 27 de 2018
C63: Fecha de Proceso: | D63: =D6 -> 46314 | F63: R4 - REVERSIÓN DE PAGOS | U63: R4 - REVERSIÓN DE PAGOS
C64: Hora: | D64: =D7 -> 0.58333333 | F64: Fecha Desde: | G64: =G7 -> 46296 | J64: Feha Hasta: | K64: =K7 -> 46310 | U64: =F64 -> Fecha Desde: | V64: =G64 -> 46296 | X64: =J64 -> Feha Hasta: | Y64: =K64 -> 46310
B65: ASE | C65: Concesionarios | D65: Recaudo Total | E65: Recaudo por disposicion final | F65: Recaudo por tratamiento de lixiviados | G65: Recaudo por Componente VIAT ( Decreto 2412/2018) | H65: Recaudo por aprovechamiento | I65: Recaudo del componente de comercializacion para Aprovechamiento (11,4%) | J65: Balance de subsidio o contribuciones | K65: RECAUDO BASE DE REMUNERACION | L65: Costo de la Interventoría | M65: REMUNERACION FINAL | N65: Conceptos especiales | O65: REMUNERACION FINAL MAS CONCEPTOS ESPECIALES | S65: ASE | T65: Concesionarios | U65: Tarifa de Comercialización del Servicio. ( TCS) | V65: Tarifa de Limpieza Urbana del Servicio. ( TLU) | W65: Tarifa de Barrido y Limpieza del Servicio. ( TBL) | X65: Tarifa de Recolección y Transporte del Servicio. (TRT) | Y65: Recaudo del componente de comercializacion para Aprovechamiento (18,6%) | Z65: Costo de la Interventoría | AA65: Ajuste a la decena | AB65: Conceptos especiales | AC65: Otros | AD65: Diferencial Balance S / C (Fac vs Rec) | AE65: Balance S / C Con Base en (Recaudo) | AF65: REMUNERACION FINAL MAS CONCEPTOS ESPECIALES
B66: 1 | C66: PROMOAMBIENTAL DISTRITO S.A.S. ESP. | D66: ='Reversion Pagos R4'!D73 -> -3833780 | E66: ='Reversion Pagos R4'!E73 -> -210057.54 | F66: ='Reversion Pagos R4'!F73 -> -118190.72 | G66: ='Reversion Pagos R4'!G73 -> -60636.25 | H66: ='Reversion Pagos R4'!H73 -> -1073708 | I66: ='Reversion Pagos R4'!I73 -> -39348.74 | J66: 0 | K66: =D66-E66-F66-G66-H66-I66-J66 -> -2331838.8 | L66: 0 | M66: =K66-L66 -> -2331838.8 | N66: ='Reversion Pagos R4'!P73 -> 0 | O66: =M66+N66 -> -2331838.8 | S66: 1 | T66: PROMOAMBIENTAL DISTRITO S.A.S. ESP. | U66: ='Reversion Pagos R4'!J73 -> -355242.07 | V66: ='Reversion Pagos R4'!K73 -> -332912.8 | W66: ='Reversion Pagos R4'!L73 -> -1571931.7 | X66: ='Reversion Pagos R4'!M73 -> -569354.35 | Y66: ='Reversion Pagos R4'!N73 -> -64199.78 | Z66: =-L66 -> 0 | AA66: ='Reversion Pagos R4'!O73 -> -33.24 | AB66: =N66 -> 0 | AC66: =+'Reversion Pagos R4'!Q73+'Reversion Pagos R4'!R73 -> 0 | AD66: =-J66+AE66 -> 561835.18 | AE66: ='Reversion Pagos R4'!D74 -> 561835.18 | AF66: =SUM(U66:AD66) -> -2331838.8 | AG66: =(AF66-O66) -> -4.6566129e-10 | AH66: =INT(AG66)=0 -> FALSE
B67: 2 | C67: LIMPIEZA METROPOLITANA S.A. ESP. | D67: ='Reversion Pagos R4'!D168 -> -21803648 | E67: ='Reversion Pagos R4'!E168 -> -2002860.9 | F67: ='Reversion Pagos R4'!F168 -> -1068771.3 | G67: ='Reversion Pagos R4'!G168 -> -535888.42 | H67: ='Reversion Pagos R4'!H168 -> -7566499.2 | I67: ='Reversion Pagos R4'!I168 -> -267247.27 | J67: 0 | K67: =D67-E67-F67-G67-H67-I67-J67 -> -10362381 | L67: 0 | M67: =K67-L67 -> -10362381 | N67: ='Reversion Pagos R4'!P168 -> 0 | O67: =M67+N67 -> -10362381 | S67: 2 | T67: LIMPIEZA METROPOLITANA S.A. ESP. | U67: ='Reversion Pagos R4'!J168 -> -2352070.3 | V67: ='Reversion Pagos R4'!K168 -> -2442005.8 | W67: ='Reversion Pagos R4'!L168 -> -10568392 | X67: ='Reversion Pagos R4'!M168 -> -4156097.5 | Y67: ='Reversion Pagos R4'!N168 -> -436032.87 | Z67: =-L67 -> 0 | AA67: ='Reversion Pagos R4'!O168 -> -18.47 | AB67: =N67 -> 0 | AC67: =+'Reversion Pagos R4'!Q168+'Reversion Pagos R4'!R168 -> 0.35 | AD67: =-J67+AE67 -> 9592235.1 | AE67: ='Reversion Pagos R4'!D169 -> 9592235.1 | AF67: =SUM(U67:AD67) -> -10362381 | AG67: =(AF67-O67) -> 1.8626451e-09 | AH67: =INT(AG67)=0 -> TRUE
B68: 3 | C68: CIUDAD LIMPIA BOGOTA S.A. ESP. | D68: ='Reversion Pagos R4'!D199 -> -2259272 | E68: ='Reversion Pagos R4'!E199 -> -142297.63 | F68: ='Reversion Pagos R4'!F199 -> -79543.95 | G68: ='Reversion Pagos R4'!G199 -> -41638.23 | H68: ='Reversion Pagos R4'!H199 -> -590000.48 | I68: ='Reversion Pagos R4'!I199 -> -19083.43 | J68: 0 | K68: =D68-E68-F68-G68-H68-I68-J68 -> -1386708.3 | L68: 0 | M68: =K68-L68 -> -1386708.3 | N68: ='Reversion Pagos R4'!P199 -> 0 | O68: =M68+N68 -> -1386708.3 | S68: 3 | T68: CIUDAD LIMPIA BOGOTA S.A. ESP. | U68: ='Reversion Pagos R4'!J199 -> -167398.71 | V68: ='Reversion Pagos R4'!K199 -> -161923.62 | W68: ='Reversion Pagos R4'!L199 -> -764905.41 | X68: ='Reversion Pagos R4'!M199 -> -336959.22 | Y68: ='Reversion Pagos R4'!N199 -> -31136.16 | Z68: =-L68 -> 0 | AA68: ='Reversion Pagos R4'!O199 -> -2.16 | AB68: =N68 -> 0 | AC68: =+'Reversion Pagos R4'!Q199+'Reversion Pagos R4'!R199 -> 0 | AD68: =-J68+AE68 -> 75617 | AE68: ='Reversion Pagos R4'!D200 -> 75617 | AF68: =SUM(U68:AD68) -> -1386708.3 | AG68: =(AF68-O68) -> 4.6566129e-10 | AH68: =INT(AG68)=0 -> TRUE
B69: 4 | C69: BOGOTA LIMPIA S.A.S. ESP. | D69: ='Reversion Pagos R4'!D313 -> -41558585 | E69: ='Reversion Pagos R4'!E313 -> -2496334.8 | F69: ='Reversion Pagos R4'!F313 -> -1365936.5 | G69: ='Reversion Pagos R4'!G313 -> -708861.09 | H69: ='Reversion Pagos R4'!H313 -> -10586463 | I69: ='Reversion Pagos R4'!I313 -> -381164.66 | J69: 0 | K69: =D69-E69-F69-G69-H69-I69-J69 -> -26019826 | L69: 0 | M69: =K69-L69 -> -26019826 | N69: ='Reversion Pagos R4'!P313 -> 0 | O69: =M69+N69 -> -26019826 | S69: 4 | T69: BOGOTA LIMPIA S.A.S. ESP. | U69: ='Reversion Pagos R4'!J313 -> -3340357.1 | V69: ='Reversion Pagos R4'!K313 -> -3316465.4 | W69: ='Reversion Pagos R4'!L313 -> -16693748 | X69: ='Reversion Pagos R4'!M313 -> -6675011.3 | Y69: ='Reversion Pagos R4'!N313 -> -623716.38 | Z69: =-L69 -> 0 | AA69: ='Reversion Pagos R4'!O313 -> -50.85 | AB69: =N69 -> 0 | AC69: =+'Reversion Pagos R4'!Q313+'Reversion Pagos R4'!R313 -> 0 | AD69: =-J69+AE69 -> 4629523.5 | AE69: ='Reversion Pagos R4'!D314 -> 4629523.5 | AF69: =SUM(U69:AD69) -> -26019826 | AG69: =(AF69-O69) -> -3.7252903e-09 | AH69: =INT(AG69)=0 -> FALSE
B70: 5 | C70: AREA LIMPIA DISTRITO CAPITAL S.A.S. ESP. | D70: ='Reversion Pagos R4'!D342 -> -3964157 | E70: ='Reversion Pagos R4'!E342 -> -249692.11 | F70: ='Reversion Pagos R4'!F342 -> -137439.75 | G70: ='Reversion Pagos R4'!G342 -> -74361.94 | H70: ='Reversion Pagos R4'!H342 -> -597920.8 | I70: ='Reversion Pagos R4'!I342 -> -20835.71 | J70: 0 | K70: =D70-E70-F70-G70-H70-I70-J70 -> -2883906.7 | L70: 0 | M70: =K70-L70 -> -2883906.7 | N70: ='Reversion Pagos R4'!P342 -> 0 | O70: =M70+N70 -> -2883906.7 | S70: 5 | T70: AREA LIMPIA DISTRITO CAPITAL S.A.S. ESP. | U70: ='Reversion Pagos R4'!J342 -> -182766.36 | V70: ='Reversion Pagos R4'!K342 -> -176896.84 | W70: ='Reversion Pagos R4'!L342 -> -902118.91 | X70: ='Reversion Pagos R4'!M342 -> -745598.4 | Y70: ='Reversion Pagos R4'!N342 -> -33994.58 | Z70: =-L70 -> 0 | AA70: ='Reversion Pagos R4'!O342 -> -43.08 | AB70: =N70 -> 0 | AC70: =+'Reversion Pagos R4'!Q342+'Reversion Pagos R4'!R342 -> 0 | AD70: =-J70+AE70 -> -842488.52 | AE70: ='Reversion Pagos R4'!D343 -> -842488.52 | AF70: =SUM(U70:AD70) -> -2883906.7 | AG70: =(AF70-O70) -> 4.6566129e-10 | AH70: =INT(AG70)=0 -> TRUE
C71: TOTAL | D71: =SUM(D66:D70) -> -73419443 | E71: =SUM(E66:E70) -> -5101243 | F71: =SUM(F66:F70) -> -2769882.3 | G71: =SUM(G66:G70) -> -1421385.9 | H71: =SUM(H66:H70) -> -20414591 | I71: =SUM(I66:I70) -> -727679.81 | J71: =SUM(J66:J70) -> 0 | K71: =SUM(K66:K70) -> -42984661 | ... O71: =SUM(O66:O70) -> -42984661 | T71: TOTAL | U71: =SUM(U66:U70) -> -6397834.5 | V71: =SUM(V66:V70) -> -6430204.5 | W71: =SUM(W66:W70) -> -30501096 | X71: =SUM(X66:X70) -> -12483021 | Y71: =SUM(Y66:Y70) -> -1189079.8 | Z71: =SUM(Z66:Z70) -> 0 | AA71: =SUM(AA66:AA70) -> -147.8 | AB71: =SUM(AB66:AB70) -> 0 | ... AG71: =SUM(AG66:AG70) -> -1.3969839e-09 | AH71: =INT(AG71)=0 -> FALSE
Y73: =SUM(U71:Y71) -> -57001235
F75: Firma autorizada
F79: PROCERASEO S.A.S. | I79: NIT: 901 153 639 - 0 | M79: Codigo Remuneración: | N79: =N3 -> 2026101 | U79: PROCERASEO S.A.S. | W79: NIT: 901 153 639 - 0 | AA79: Codigo Remuneración: | AD79: =N79 -> 2026101
F80: 3. ESQUEMA FINANCIERO DEL SERVICIO PUBLICO DE ASEO | U80: 3. ESQUEMA FINANCIERO DEL SERVICIO PUBLICO DE ASEO
F81: Resoluciòn UAESP Número 27 de 2018 | U81: Resoluciòn UAESP Número 27 de 2018
C82: Fecha de Proceso: | D82: =D6 -> 46314 | F82: R5 - REMUNERACIÓN SALDOS A FAVOR POR NOTA | U82: =F82 -> R5 - REMUNERACIÓN SALDOS A FAVOR POR NOTA
C83: Hora: | D83: =D7 -> 0.58333333 | F83: Fecha Desde: | G83: =G7 -> 46296 | J83: Feha Hasta: | K83: =K7 -> 46310 | U83: =F83 -> Fecha Desde: | V83: =G83 -> 46296 | X83: =J83 -> Feha Hasta: | Y83: =K83 -> 46310
B84: ASE | C84: Concesionarios | D84: Recaudo Total | E84: Recaudo por disposicion final | F84: Recaudo por tratamiento de lixiviados | G84: Recaudo por Componente VIAT ( Decreto 2412/2018) | H84: Recaudo por aprovechamiento | I84: Recaudo del componente de comercializacion para Aprovechamiento (11,4%) | J84: Balance de subsidio o contribuciones | K84: RECAUDO BASE DE REMUNERACION | L84: Costo de la Interventoría | M84: REMUNERACION FINAL | N84: Conceptos especiales | O84: REMUNERACION FINAL MAS CONCEPTOS ESPECIALES | S84: ASE | T84: Concesionarios | U84: Tarifa de Comercialización del Servicio. ( TCS) | V84: Tarifa de Limpieza Urbana del Servicio. ( TLU) | W84: Tarifa de Barrido y Limpieza del Servicio. ( TBL) | X84: Tarifa de Recolección y Transporte del Servicio. (TRT) | Y84: Recaudo del componente de comercializacion para Aprovechamiento (18,6%) | Z84: Costo de la Interventoría | AA84: Ajuste a la decena | AB84: Conceptos especiales | AC84: Otros | AD84: Diferencial Balance Subsidio y Contribución (Fac vs Rec) | AE84: Balance de subsidio o contribuciones (Recaudo) | AF84: REMUNERACION FINAL MAS CONCEPTOS ESPECIALES
B85: 1 | C85: PROMOAMBIENTAL DISTRITO S.A.S. ESP. | D85: ='AJUSTES - SF-T'!D47 -> 0 | E85: ='AJUSTES - SF-T'!E47 -> 0 | F85: ='AJUSTES - SF-T'!F47 -> 0 | G85: ='AJUSTES - SF-T'!G47 -> 0 | H85: ='AJUSTES - SF-T'!H47 -> 0 | I85: ='AJUSTES - SF-T'!I47 -> 0 | J85: ='AJUSTES - SF-T'!J47 -> 0 | K85: =D85-E85-F85-G85-H85-I85-J85 -> 0 | L85: 0 | M85: =K85-L85 -> 0 | N85: ='AJUSTES - SF-T'!N47 -> 0 | O85: =M85+N85 -> 0 | S85: 1 | T85: PROMOAMBIENTAL DISTRITO S.A.S. ESP. | U85: ='AJUSTES - SF-T'!U47 -> 0 | V85: ='AJUSTES - SF-T'!V47 -> 0 | W85: ='AJUSTES - SF-T'!W47 -> 0 | X85: ='AJUSTES - SF-T'!X47 -> 0 | Y85: ='AJUSTES - SF-T'!Y47 -> 0 | Z85: =-L85 -> 0 | AA85: 0 | AB85: =N85 -> 0 | AC85: ='AJUSTES - SF-T'!AA47 -> 0 | AD85: =-J85+AE85 -> 0 | AE85: ='AJUSTES - SF-T'!AD47 -> 0 | AF85: =SUM(U85:AD85) -> 0 | AG85: =AF85-O85 -> 0 | AH85: =INT(AG85)=0 -> TRUE
B86: 2 | C86: LIMPIEZA METROPOLITANA S.A. ESP. | D86: ='AJUSTES - SF-T'!D48 -> 0 | E86: ='AJUSTES - SF-T'!E48 -> 0 | F86: ='AJUSTES - SF-T'!F48 -> 0 | G86: ='AJUSTES - SF-T'!G48 -> 0 | H86: ='AJUSTES - SF-T'!H48 -> 0 | I86: ='AJUSTES - SF-T'!I48 -> 0 | J86: ='AJUSTES - SF-T'!J48 -> 0 | K86: =D86-E86-F86-G86-H86-I86-J86 -> 0 | L86: 0 | M86: =K86-L86 -> 0 | N86: ='AJUSTES - SF-T'!N48 -> 0 | O86: =M86+N86 -> 0 | S86: 2 | T86: LIMPIEZA METROPOLITANA S.A. ESP. | U86: ='AJUSTES - SF-T'!U48 -> 0 | V86: ='AJUSTES - SF-T'!V48 -> 0 | W86: ='AJUSTES - SF-T'!W48 -> 0 | X86: ='AJUSTES - SF-T'!X48 -> 0 | Y86: ='AJUSTES - SF-T'!Y48 -> 0 | Z86: =-L86 -> 0 | AA86: ='AJUSTES - SF-T'!AA48 -> 0 | AB86: =N86 -> 0 | AC86: 0 | AD86: =-J86+AE86 -> 0 | AE86: ='AJUSTES - SF-T'!AD48 -> 0 | AF86: =SUM(U86:AD86) -> 0 | AG86: =AF86-O86 -> 0 | AH86: =INT(AG86)=0 -> TRUE
B87: 3 | C87: CIUDAD LIMPIA BOGOTA S.A. ESP. | D87: ='AJUSTES - SF-T'!D49 -> 0 | E87: ='AJUSTES - SF-T'!E49 -> 0 | F87: ='AJUSTES - SF-T'!F49 -> 0 | G87: ='AJUSTES - SF-T'!G49 -> 0 | H87: ='AJUSTES - SF-T'!H49 -> 0 | I87: ='AJUSTES - SF-T'!I49 -> 0 | J87: ='AJUSTES - SF-T'!J49 -> 0 | K87: =D87-E87-F87-G87-H87-I87-J87 -> 0 | L87: 0 | M87: =K87-L87 -> 0 | N87: ='AJUSTES - SF-T'!N49 -> 0 | O87: =M87+N87 -> 0 | S87: 3 | T87: CIUDAD LIMPIA BOGOTA S.A. ESP. | U87: ='AJUSTES - SF-T'!U49 -> 0 | V87: ='AJUSTES - SF-T'!V49 -> 0 | W87: ='AJUSTES - SF-T'!W49 -> 0 | X87: ='AJUSTES - SF-T'!X49 -> 0 | Y87: ='AJUSTES - SF-T'!Y49 -> 0 | Z87: =-L87 -> 0 | AA87: ='AJUSTES - SF-T'!AA49 -> 0 | AB87: =N87 -> 0 | AC87: 0 | AD87: =-J87+AE87 -> 0 | AE87: ='AJUSTES - SF-T'!AD49 -> 0 | AF87: =SUM(U87:AD87) -> 0 | AG87: =AF87-O87 -> 0 | AH87: =INT(AG87)=0 -> TRUE
B88: 4 | C88: BOGOTA LIMPIA S.A.S. ESP. | D88: ='AJUSTES - SF-T'!D50 -> 0 | E88: ='AJUSTES - SF-T'!E50 -> 0 | F88: ='AJUSTES - SF-T'!F50 -> 0 | G88: ='AJUSTES - SF-T'!G50 -> 0 | H88: ='AJUSTES - SF-T'!H50 -> 0 | I88: ='AJUSTES - SF-T'!I50 -> 0 | J88: ='AJUSTES - SF-T'!J50 -> 0 | K88: =D88-E88-F88-G88-H88-I88-J88 -> 0 | L88: 0 | M88: =K88-L88 -> 0 | N88: ='AJUSTES - SF-T'!N50 -> 0 | O88: =M88+N88 -> 0 | S88: 4 | T88: BOGOTA LIMPIA S.A.S. ESP. | U88: ='AJUSTES - SF-T'!U50 -> 0 | V88: ='AJUSTES - SF-T'!V50 -> 0 | W88: ='AJUSTES - SF-T'!W50 -> 0 | X88: ='AJUSTES - SF-T'!X50 -> 0 | Y88: ='AJUSTES - SF-T'!Y50 -> 0 | Z88: =-L88 -> 0 | AA88: ='AJUSTES - SF-T'!AA50 -> 0 | AB88: =N88 -> 0 | AC88: 0 | AD88: =-J88+AE88 -> 0 | AE88: ='AJUSTES - SF-T'!AD50 -> 0 | AF88: =SUM(U88:AD88) -> 0 | AG88: =AF88-O88 -> 0 | AH88: =INT(AG88)=0 -> TRUE
B89: 5 | C89: AREA LIMPIA DISTRITO CAPITAL S.A.S. ESP. | D89: ='AJUSTES - SF-T'!D51 -> 0 | E89: ='AJUSTES - SF-T'!E51 -> 0 | F89: ='AJUSTES - SF-T'!F51 -> 0 | G89: ='AJUSTES - SF-T'!G51 -> 0 | H89: ='AJUSTES - SF-T'!H51 -> 0 | I89: ='AJUSTES - SF-T'!I51 -> 0 | J89: ='AJUSTES - SF-T'!J51 -> 0 | K89: =D89-E89-F89-G89-H89-I89-J89 -> 0 | L89: 0 | M89: =K89-L89 -> 0 | N89: ='AJUSTES - SF-T'!N51 -> 0 | O89: =M89+N89 -> 0 | S89: 5 | T89: AREA LIMPIA DISTRITO CAPITAL S.A.S. ESP. | U89: ='AJUSTES - SF-T'!U51 -> 0 | V89: ='AJUSTES - SF-T'!V51 -> 0 | W89: ='AJUSTES - SF-T'!W51 -> 0 | X89: ='AJUSTES - SF-T'!X51 -> 0 | Y89: ='AJUSTES - SF-T'!Y51 -> 0 | Z89: =-L89 -> 0 | AA89: ='AJUSTES - SF-T'!AA51 -> 0 | AB89: =N89 -> 0 | AC89: 0 | AD89: =-J89+AE89 -> 0 | AE89: ='AJUSTES - SF-T'!AD51 -> 0 | AF89: =SUM(U89:AD89) -> 0 | AG89: =AF89-O89 -> 0 | AH89: =INT(AG89)=0 -> TRUE
C90: TOTAL | D90: =SUM(D85:D89) -> 0 | E90: =SUM(E85:E89) -> 0 | F90: =SUM(F85:F89) -> 0 | G90: =SUM(G85:G89) -> 0 | H90: =SUM(H85:H89) -> 0 | I90: =SUM(I85:I89) -> 0 | J90: =SUM(J85:J89) -> 0 | K90: =SUM(K85:K89) -> 0 | ... O90: =SUM(O85:O89) -> 0 | T90: TOTAL | U90: =SUM(U85:U89) -> 0 | V90: =SUM(V85:V89) -> 0 | W90: =SUM(W85:W89) -> 0 | X90: =SUM(X85:X89) -> 0 | Y90: =SUM(Y85:Y89) -> 0 | Z90: =SUM(Z85:Z89) -> 0 | AA90: =SUM(AA85:AA89) -> 0 | AB90: =SUM(AB85:AB89) -> 0 | ... AG90: =SUM(AG85:AG89) -> 0 | AH90: =INT(AG90)=0 -> TRUE
Y92: =SUM(U90:Y90) -> 0
F94: Firma autorizada
F98: PROCERASEO S.A.S. | I98: NIT: 901 153 639 - 0 | M98: Codigo Remuneración: | N98: =N3 -> 2026101 | U98: PROCERASEO S.A.S. | W98: NIT: 901 153 639 - 0 | AA98: Codigo Remuneración: | AD98: =N98 -> 2026101
F99: 3. ESQUEMA FINANCIERO DEL SERVICIO PUBLICO DE ASEO | U99: 3. ESQUEMA FINANCIERO DEL SERVICIO PUBLICO DE ASEO
F100: Resoluciòn UAESP Número 27 de 2018 | U100: Resoluciòn UAESP Número 27 de 2018
C101: Fecha de Proceso: | D101: =D6 -> 46314 | F101: REPORTE CONSOLIDADO TOTAL DE RECAUDO | U101: REPORTE DETALLADO SUBBOLSA RBL DISCRIMINADO POR ACTIVIDADES
C102: Hora: | D102: =D7 -> 0.58333333 | F102: Fecha Desde: | G102: =G7 -> 46296 | J102: Feha Hasta: | K102: =K7 -> 46310 | U102: =F102 -> Fecha Desde: | V102: =G102 -> 46296 | X102: =J102 -> Feha Hasta: | Y102: =K102 -> 46310
B103: ASE | C103: Concesionarios | D103: Recaudo Total | E103: Recaudo por disposicion final | F103: Recaudo por tratamiento de lixiviados | G103: Recaudo por Componente VIAT ( Decreto 2412/2018) | H103: Recaudo por aprovechamiento | I103: Recaudo del componente de comercializacion para Aprovechamiento (11,4%) | J103: Balance de subsidio o contribuciones | K103: RECAUDO BASE DE REMUNERACION | L103: Costo de la Interventoría | M103: REMUNERACION FINAL | N103: Conceptos especiales | O103: REMUNERACION FINAL MAS CONCEPTOS ESPECIALES | S103: ASE | T103: Concesionarios | U103: Tarifa de Comercialización del Servicio. ( TCS) | V103: Tarifa de Limpieza Urbana del Servicio. ( TLU) | W103: Tarifa de Barrido y Limpieza del Servicio. ( TBL) | X103: Tarifa de Recolección y Transporte del Servicio. (TRT) | Y103: Recaudo del componente de comercializacion para Aprovechamiento (18,6%) | Z103: Costo de la Interventoría | AA103: Ajuste a la decena | AB103: Conceptos especiales | AC103: Otros | AD103: Diferencial Balance Subsidio y Contribución (Fac vs Rec) | AE103: Balance de subsidio o contribuciones (Recaudo) | AF103: REMUNERACION FINAL MAS CONCEPTOS ESPECIALES
B104: 1 | C104: PROMOAMBIENTAL DISTRITO S.A.S. ESP. | D104: =D9+D28+D47+D66+D85 -> 1.4842425e+10 | E104: =E9+E28+E47+E66+E85 -> 8.4363812e+08 | F104: =F9+F28+F47+F66+F85 -> 4.6992189e+08 | G104: =G9+G28+G47+G66+G85 -> 2.5004438e+08 | H104: =H9+H28+H47+H66+H85 -> 4.7629986e+09 | I104: =I9+I28+I47+I66+I85 -> 158724902 | J104: =J9+J28+J47+J66+J85 -> 2.1539508e+09 | K104: =D104-E104-F104-G104-H104-I104-J104 -> 6.2031464e+09 | L104: =L9+L28+L47+L66+L85 -> 189185987 | M104: =K104-L104 -> 6.0139604e+09 | N104: =N9+N28+N47+N66+N85 -> 19931693 | O104: =M104+N104 -> 6.0338921e+09 | S104: 1 | T104: PROMOAMBIENTAL DISTRITO S.A.S. ESP. | U104: =U9+U28+U47+U66+U85 -> 1.3945226e+09 | V104: =V9+V28+V47+V66+V85 -> 1.3176496e+09 | W104: =W9+W28+W47+W66+W85 -> 6.2800568e+09 | X104: =X9+X28+X47+X66+X85 -> 2.2961523e+09 | Y104: =Y9+Y28+Y47+Y66+Y85 -> 2.5909305e+08 | Z104: =Z9+Z28+Z47+Z66+Z85 -> -189185987 | AA104: =AA9+AA28+AA47+AA66+AA85 -> -27550.81 | AB104: =AB9+AB28+AB47+AB66+AB85 -> 19931693 | AC104: =AC9+AC28+AC47+AC66+AC85 -> 149.13 | AD104: =-J104+AE104 -> -5.3443005e+09 | AE104: =AE9+AE28+AE47+AE66+AE85 -> -3.1903497e+09 | AF104: =SUM(U104:AD104) -> 6.0338921e+09 | AG104: =AF104-O104 -> 0 | AH104: =INT(AG104)=0 -> TRUE
B105: 2 | C105: LIMPIEZA METROPOLITANA S.A. ESP. | D105: =D10+D29+D48+D67+D86 -> 1.1302638e+10 | E105: =E10+E29+E48+E67+E86 -> 8.7952768e+08 | F105: =F10+F29+F48+F67+F86 -> 4.8712579e+08 | G105: =G10+G29+G48+G67+G86 -> 2.5781603e+08 | H105: =H10+H29+H48+H67+H86 -> 3.5960298e+09 | I105: =I10+I29+I48+I67+I86 -> 1.2739625e+08 | J105: =J10+J29+J48+J67+J86 -> -4.2171455e+09 | K105: =D105-E105-F105-G105-H105-I105-J105 -> 1.0171888e+10 | L105: =L10+L29+L48+L67+L86 -> 266580255 | M105: =K105-L105 -> 9.9053073e+09 | N105: =N10+N29+N48+N67+N86 -> 9905072.8 | O105: =M105+N105 -> 9.9152123e+09 | S105: 2 | T105: LIMPIEZA METROPOLITANA S.A. ESP. | U105: =U10+U29+U48+U67+U86 -> 1.1190475e+09 | V105: =V10+V29+V48+V67+V86 -> 1.0742033e+09 | W105: =W10+W29+W48+W67+W86 -> 5.1009679e+09 | X105: =X10+X29+X48+X67+X86 -> 1.7266392e+09 | Y105: =Y10+Y29+Y48+Y67+Y86 -> 2.0785248e+08 | Z105: =Z10+Z29+Z48+Z67+Z86 -> -266580255 | AA105: =AA10+AA29+AA48+AA67+AA86 -> -14301.8 | AB105: =AB10+AB29+AB48+AB67+AB86 -> 9905072.8 | AC105: =AC10+AC29+AC48+AC67+AC86 -> 6703041.4 | AD105: =-J105+AE105 -> 9.3648838e+08 | AE105: =AE10+AE29+AE48+AE67+AE86 -> -3.2806571e+09 | AF105: =SUM(U105:AD105) -> 9.9152123e+09 | AG105: =AF105-O105 -> 0 | AH105: =INT(AG105)=0 -> TRUE
B106: 3 | C106: CIUDAD LIMPIA BOGOTA S.A. ESP. | D106: =D11+D30+D49+D68+D87 -> 8.8237873e+09 | E106: =E11+E30+E49+E68+E87 -> 5.6997577e+08 | F106: =F11+F30+F49+F68+F87 -> 3.1780177e+08 | G106: =G11+G30+G49+G68+G87 -> 1.6888654e+08 | H106: =H11+H30+H49+H68+H87 -> 2.4315814e+09 | I106: =I11+I30+I49+I68+I87 -> 87065864 | J106: =J11+J30+J49+J68+J87 -> -1.2888063e+09 | K106: =D106-E106-F106-G106-H106-I106-J106 -> 6.5372823e+09 | L106: =L11+L30+L49+L68+L87 -> 154788535 | M106: =K106-L106 -> 6.3824938e+09 | N106: =N11+N30+N49+N68+N87 -> 19321800 | O106: =M106+N106 -> 6.4018156e+09 | S106: 3 | T106: CIUDAD LIMPIA BOGOTA S.A. ESP. | U106: =U11+U30+U49+U68+U87 -> 7.6492463e+08 | V106: =V11+V30+V49+V68+V87 -> 7.259332e+08 | W106: =W11+W30+W49+W68+W87 -> 3.4513486e+09 | X106: =X11+X30+X49+X68+X87 -> 1.3501812e+09 | Y106: =Y11+Y30+Y49+Y68+Y87 -> 1.4214515e+08 | Z106: =Z11+Z30+Z49+Z68+Z87 -> -154788535 | AA106: =AA11+AA30+AA49+AA68+AA87 -> -79474.34 | AB106: =AB11+AB30+AB49+AB68+AB87 -> 19321800 | AC106: =AC11+AC30+AC49+AC68+AC87 -> -41619.9 | AD106: =-J106+AE106 -> 1.0287065e+08 | AE106: =AE11+AE30+AE49+AE68+AE87 -> -1.1859357e+09 | AF106: =SUM(U106:AD106) -> 6.4018156e+09 | AG106: =AF106-O106 -> 0 | AH106: =INT(AG106)=0 -> TRUE
B107: 4 | C107: BOGOTA LIMPIA S.A.S. ESP. | D107: =D12+D31+D50+D69+D88 -> 1.0483173e+10 | E107: =E12+E31+E50+E69+E88 -> 6.0518433e+08 | F107: =F12+F31+F50+F69+F88 -> 3.3554237e+08 | G107: =G12+G31+G50+G69+G88 -> 1.78851e+08 | H107: =H12+H31+H50+H69+H88 -> 2.396955e+09 | I107: =I12+I31+I50+I69+I88 -> 89656583 | J107: =J12+J31+J50+J69+J88 -> 61531954 | K107: =D107-E107-F107-G107-H107-I107-J107 -> 6.8154515e+09 | L107: =L12+L31+L50+L69+L88 -> 120391083 | M107: =K107-L107 -> 6.6950604e+09 | N107: =N12+N31+N50+N69+N88 -> 8643135.6 | O107: =M107+N107 -> 6.7037035e+09 | S107: 4 | T107: BOGOTA LIMPIA S.A.S. ESP. | U107: =U12+U31+U50+U69+U88 -> 7.8607852e+08 | V107: =V12+V31+V50+V69+V88 -> 7.5028795e+08 | W107: =W12+W31+W50+W69+W88 -> 3.8823183e+09 | X107: =X12+X31+X50+X69+X88 -> 1.6022197e+09 | Y107: =Y12+Y31+Y50+Y69+Y88 -> 1.4650061e+08 | Z107: =Z12+Z31+Z50+Z69+Z88 -> -120391083 | AA107: =AA12+AA31+AA50+AA69+AA88 -> 31980.28 | AB107: =AB12+AB31+AB50+AB69+AB88 -> 8643135.6 | AC107: =AC12+AC31+AC50+AC69+AC88 -> 189.43 | AD107: =-J107+AE107 -> -3.5198576e+08 | AE107: =AE12+AE31+AE50+AE69+AE88 -> -2.904538e+08 | AF107: =SUM(U107:AD107) -> 6.7037035e+09 | AG107: =AF107-O107 -> 0 | AH107: =INT(AG107)=0 -> TRUE
